Workbook

Sheet 0 - Indice
A1: Marco FIRE — Affitto vs Acquisto 2026
A2: Strumento informativo / divulgativo. NON è consulenza finanziaria. I valori sono indicativi al 2026 e vanno verificati col tuo consulente.
A4: Indice
A5: 1 - IL TUO CASO | B5: Rendimento da affitto, soglia, verdetto e cassa necessaria
A6: 2 - COSTI | B6: Tutti i costi una tantum, in entrata e in uscita
A7: 3 - CONFRONTO | B7: Patrimonio finale a 5, 10 e 20 anni
A8: 4 - SENSITIVITÀ | B8: La matrice che mostra quando il verdetto si ribalta
A10: Come usare
A11: 1. Le celle GIALLE sono input — modificale coi tuoi numeri.
A12: 2. Le celle VERDI sono output — si aggiornano automaticamente.
A13: 3. Tutti i numeri di default sono al 2026 da fonti pubbliche.
A14: 4. Niente codice nascosto: l'Excel è solo formule modificabili.
A16: Fonti dati
A17: • idealista — report prezzi di vendita e canoni di locazione, II trimestre 2026 (vendita 1.903 €/mq media naz.; affitti 15,4 €/mq/mese, massimo dal 2012)
A18: • Facile.it e MutuiOnline — media tassi mutui luglio 2026: TAN fisso prevalente 2,70-3,40%
A19: • BCE — decisione dell'11 giugno 2026: rialzo di 25 punti base, tasso sui depositi al 2,25% dal 17 giugno
A20: • Agenzia delle Entrate — «L'acquisto con i benefici prima casa»: registro 2% sul valore catastale (prezzo-valore), ipotecaria e catastale 50+50 €, sostitutiva mutuo 0,25%
A21: • D.P.R. 917/1986 (TUIR) art. 15 — detrazione 19% degli interessi passivi su max 4.000 € annui
A22: • ISTAT — indice dei prezzi delle abitazioni (IPAB): vs media 2010, nel 2021 -12,8% (esistenti -19,8%); I trimestre 2026 +5,2% su base annua
A24: Aggiornamenti: github.com/marcofire-it/marco-fire-simulatori

Sheet 1 - IL TUO CASO
A1: Affitto o acquisto: il tuo caso specifico
A2: Strumento informativo / divulgativo. NON è consulenza finanziaria. I valori sono indicativi al 2026 e vanno verificati col tuo consulente.
A4: INPUT — cambia solo le celle gialle
A5: Prezzo della casa che stai guardando (€) | B5: 415000
A6: Affitto mensile per una casa EQUIVALENTE (€) | B6: 1864
A7: Anticipo che puoi versare (%) | B7: 0.2
A8: Importo del mutuo | B8: =B5*(1-B7)
A9: TAN del mutuo (%) | B9: 0.032
A10: Durata del mutuo (anni) | B10: 25
A11: Manutenzione + assicurazione annua (% del valore) | B11: 0.0105
A12: Tasso mensile | B12: =B9/12
A13: Numero di rate | B13: =B10*12
A15: OUTPUT — la metrica che decide
A16: Canone annuo | B16: =B6*12
A17: RENDIMENTO LORDO DA AFFITTO | B17: =IFERROR(B16/B5,0)
A18: Costo del capitale (mutuo + opportunità anticipo) | B18: =B9*(1-B7)+0.04*B7
A19: SOGLIA DI INDIFFERENZA (costi non recuperabili) | B19: =B11+B18
A20: VERDETTO PRELIMINARE | B20: =IF(B17>B19,"COMPRARE parte avvantaggiato","AFFITTARE parte avvantaggiato")
A21: Margine sopra/sotto la soglia | B21: =B17-B19
A23: Il vero filtro: quanto ti serve in banca
A24: Anticipo | B24: =B5*B7
A25: Costi una tantum (foglio 2) | B25: ='2 - COSTI'!B16
A26: CASSA NECESSARIA AL ROGITO | B26: =B24+B25
A27: In percentuale sul prezzo | B27: =IFERROR(B26/B5,0)
A29: Confronto mensile (attenzione: è ingannevole)
A30: Rata del mutuo | B30: =B8*B12/(1-(1+B12)^-B13)
A31: Manutenzione + assicurazione mensile | B31: =B5*B11/12
A32: Quota capitale della prima rata (è risparmio) | B32: =B30-B8*B12
A33: Costo NETTO reale mensile del proprietario | B33: =B30+B31-B32
A34: Costo mensile dell'inquilino | B34: =B6
A36: Il rendimento lordo da affitto va calcolato su case EQUIVALENTI: stesso quartiere, stessa metratura, stesso stato. Confrontare il canone di un monolocale in centro col prezzo di un trilocale in periferia non ha senso. Per lo stesso motivo NON dividere mai il canone medio nazionale per il prezzo medio nazionale: i due indici hanno composizione territoriale diversa e il risultato è gonfiato.

Sheet 2 - COSTI
A1: I costi una tantum che quasi nessuno conta
A2: Strumento informativo / divulgativo. NON è consulenza finanziaria. I valori sono indicativi al 2026 e vanno verificati col tuo consulente.
A4: INPUT
A5: Prezzo della casa (dal foglio 1) | B5: ='1 - IL TUO CASO'!B5
A6: Rendita catastale dell'immobile (€) | B6: 1400
A7: Provvigione agenzia (%) — 0 se acquisti da privato | B7: 0.03
A8: Onorario notaio atto + mutuo (€) | B8: 4000
A9: Perizia e istruttoria (€) | B9: 300
A11: CALCOLO
A12: Valore catastale (rendita × 1,05 × 110) | B12: =B6*1.05*110
A13: Imposta di registro 2% (prima casa, prezzo-valore) | B13: =MAX(1000,B12*0.02)
A14: Imposte ipotecaria e catastale (50 + 50) | B14: =100
A15: Imposta sostitutiva sul mutuo (0,25%) | B15: ='1 - IL TUO CASO'!B8*0.0025
A16: TOTALE COSTI UNA TANTUM | B16: =B13+B14+B15+B8+B9+B5*B7*1.22
A17: In percentuale sul prezzo | B17: =IFERROR(B16/B5,0)
A18: Di cui provvigione agenzia (IVA inclusa) | B18: =B5*B7*1.22
A20: Costi anche in USCITA (quando rivenderai)
A21: Costi di vendita stimati (%) | B21: 0.03
A22: Su un valore di rivendita pari a | B22: =B5
A23: Costi di uscita | B23: =B22*B21
A24: COSTI TOTALI DI TRANSAZIONE (entrata + uscita) | B24: =B16+B23
A25: Anni di permanenza per ammortizzarli | B25: =IFERROR(B24/(B5*('1 - IL TUO CASO'!B17-'1 - IL TUO CASO'!B19)),NA())
A27: Detrazione interessi passivi: 19% su un massimo di 4.000 € di interessi annui, quindi al massimo 760 € l'anno. L'IMU sulla prima casa non di lusso non si paga. Se compri da impresa costruttrice si applica invece l'IVA al 4% sul PREZZO (non sul valore catastale) e le imposte fisse: in quel caso i costi salgono parecchio.

Sheet 3 - CONFRONTO
A1: Patrimonio finale: proprietario vs affittuario
A2: Strumento informativo / divulgativo. NON è consulenza finanziaria. I valori sono indicativi al 2026 e vanno verificati col tuo consulente.
A4: IPOTESI (le due che decidono tutto)
A5: Rivalutazione annua della casa (%) | B5: 0.02
A6: Rendimento annuo del portafoglio di chi affitta (%) | B6: 0.05
A7: Costi di vendita alla fine (%) | B7: ='2 - COSTI'!B21
A8: Cassa iniziale investita da chi affitta | B8: ='1 - IL TUO CASO'!B26
A9: Differenza mensile investibile da chi affitta | B9: =MAX(0,'1 - IL TUO CASO'!B30+'1 - IL TUO CASO'!B31-'1 - IL TUO CASO'!B6)
A11: RISULTATO per orizzonte temporale
A12: Voce | B12: 5 anni | C12: 10 anni | D12: 20 anni
A13: Valore della casa rivalutata | B13: ='1 - IL TUO CASO'!B5*(1+$B$5)^5 | C13: ='1 - IL TUO CASO'!B5*(1+$B$5)^10 | D13: ='1 - IL TUO CASO'!B5*(1+$B$5)^20
A14: Debito residuo | B14: ='1 - IL TUO CASO'!B8*(1+'1 - IL TUO CASO'!B12)^(5*12)-'1 - IL TUO CASO'!B30*(((1+'1 - IL TUO CASO'!B12)^(5*12)-1)/'1 - IL TUO CASO'!B12) | C14: ='1 - IL TUO CASO'!B8*(1+'1 - IL TUO CASO'!B12)^(10*12)-'1 - IL TUO CASO'!B30*(((1+'1 - IL TUO CASO'!B12)^(10*12)-1)/'1 - IL TUO CASO'!B12) | D14: ='1 - IL TUO CASO'!B8*(1+'1 - IL TUO CASO'!B12)^(20*12)-'1 - IL TUO CASO'!B30*(((1+'1 - IL TUO CASO'!B12)^(20*12)-1)/'1 - IL TUO CASO'!B12)
A15: PATRIMONIO del proprietario | B15: =B13*(1-$B$7)-MAX(0,B14) | C15: =C13*(1-$B$7)-MAX(0,C14) | D15: =D13*(1-$B$7)-MAX(0,D14)
A16: PATRIMONIO dell'affittuario | B16: =$B$8*(1+$B$6)^5+$B$9*12*(((1+$B$6)^5-1)/$B$6) | C16: =$B$8*(1+$B$6)^10+$B$9*12*(((1+$B$6)^10-1)/$B$6) | D16: =$B$8*(1+$B$6)^20+$B$9*12*(((1+$B$6)^20-1)/$B$6)
A17: Differenza (positivo = comprare vince) | B17: =B15-B16 | C17: =C15-C16 | D17: =D15-D16
A18: VERDETTO | B18: =IF(B17>0,"COMPRARE","AFFITTARE") | C18: =IF(C17>0,"COMPRARE","AFFITTARE") | D18: =IF(D17>0,"COMPRARE","AFFITTARE")
A20: Semplificazione dichiarata: la differenza mensile investibile è tenuta costante e l'affitto non viene indicizzato. Poiché di norma il canone cresce nel tempo, questa scelta è CONSERVATIVA verso l'acquisto solo se la differenza è positiva; in caso contrario è neutra. Il modello ignora inoltre la detrazione degli interessi (max 760 €/anno) e le tasse sul portafoglio al momento del disinvestimento.

Sheet 4 - SENSITIVITÀ
A1: Matrice di sensitività — la parte che conta davvero
A2: Strumento informativo / divulgativo. NON è consulenza finanziaria. I valori sono indicativi al 2026 e vanno verificati col tuo consulente.
A4: Orizzonte (anni) | B4: 10
A5: Righe = di quanto si rivaluta la casa ogni anno. Colonne = quanto rende il portafoglio di chi affitta. Ogni cella è la differenza fra il patrimonio del proprietario e quello dell'affittuario: positiva = comprare vince, negativa = affittare vince.
A7: Rivalutazione casa | B7: Portafoglio 3% | C7: Portafoglio 4% | D7: Portafoglio 5% | E7: Portafoglio 7%
A8: -1% all'anno | B8: ='1 - IL TUO CASO'!B5*(1+-0.01)^$B$4*(1-'2 - COSTI'!B21)-MAX(0,'1 - IL TUO CASO'!B8*(1+'1 - IL TUO CASO'!B12)^($B$4*12)-'1 - IL TUO CASO'!B30*(((1+'1 - IL TUO CASO'!B12)^($B$4*12)-1)/'1 - IL TUO CASO'!B12))-('1 - IL TUO CASO'!B26*(1+0.03)^$B$4+'3 - CONFRONTO'!$B$9*12*(((1+0.03)^$B$4-1)/0.03)) | C8: ='1 - IL TUO CASO'!B5*(1+-0.01)^$B$4*(1-'2 - COSTI'!B21)-MAX(0,'1 - IL TUO CASO'!B8*(1+'1 - IL TUO CASO'!B12)^($B$4*12)-'1 - IL TUO CASO'!B30*(((1+'1 - IL TUO CASO'!B12)^($B$4*12)-1)/'1 - IL TUO CASO'!B12))-('1 - IL TUO CASO'!B26*(1+0.04)^$B$4+'3 - CONFRONTO'!$B$9*12*(((1+0.04)^$B$4-1)/0.04)) | D8: ='1 - IL TUO CASO'!B5*(1+-0.01)^$B$4*(1-'2 - COSTI'!B21)-MAX(0,'1 - IL TUO CASO'!B8*(1+'1 - IL TUO CASO'!B12)^($B$4*12)-'1 - IL TUO CASO'!B30*(((1+'1 - IL TUO CASO'!B12)^($B$4*12)-1)/'1 - IL TUO CASO'!B12))-('1 - IL TUO CASO'!B26*(1+0.05)^$B$4+'3 - CONFRONTO'!$B$9*12*(((1+0.05)^$B$4-1)/0.05)) | E8: ='1 - IL TUO CASO'!B5*(1+-0.01)^$B$4*(1-'2 - COSTI'!B21)-MAX(0,'1 - IL TUO CASO'!B8*(1+'1 - IL TUO CASO'!B12)^($B$4*12)-'1 - IL TUO CASO'!B30*(((1+'1 - IL TUO CASO'!B12)^($B$4*12)-1)/'1 - IL TUO CASO'!B12))-('1 - IL TUO CASO'!B26*(1+0.07)^$B$4+'3 - CONFRONTO'!$B$9*12*(((1+0.07)^$B$4-1)/0.07))
A9: +0% all'anno | B9: ='1 - IL TUO CASO'!B5*(1+0.0)^$B$4*(1-'2 - COSTI'!B21)-MAX(0,'1 - IL TUO CASO'!B8*(1+'1 - IL TUO CASO'!B12)^($B$4*12)-'1 - IL TUO CASO'!B30*(((1+'1 - IL TUO CASO'!B12)^($B$4*12)-1)/'1 - IL TUO CASO'!B12))-('1 - IL TUO CASO'!B26*(1+0.03)^$B$4+'3 - CONFRONTO'!$B$9*12*(((1+0.03)^$B$4-1)/0.03)) | C9: ='1 - IL TUO CASO'!B5*(1+0.0)^$B$4*(1-'2 - COSTI'!B21)-MAX(0,'1 - IL TUO CASO'!B8*(1+'1 - IL TUO CASO'!B12)^($B$4*12)-'1 - IL TUO CASO'!B30*(((1+'1 - IL TUO CASO'!B12)^($B$4*12)-1)/'1 - IL TUO CASO'!B12))-('1 - IL TUO CASO'!B26*(1+0.04)^$B$4+'3 - CONFRONTO'!$B$9*12*(((1+0.04)^$B$4-1)/0.04)) | D9: ='1 - IL TUO CASO'!B5*(1+0.0)^$B$4*(1-'2 - COSTI'!B21)-MAX(0,'1 - IL TUO CASO'!B8*(1+'1 - IL TUO CASO'!B12)^($B$4*12)-'1 - IL TUO CASO'!B30*(((1+'1 - IL TUO CASO'!B12)^($B$4*12)-1)/'1 - IL TUO CASO'!B12))-('1 - IL TUO CASO'!B26*(1+0.05)^$B$4+'3 - CONFRONTO'!$B$9*12*(((1+0.05)^$B$4-1)/0.05)) | E9: ='1 - IL TUO CASO'!B5*(1+0.0)^$B$4*(1-'2 - COSTI'!B21)-MAX(0,'1 - IL TUO CASO'!B8*(1+'1 - IL TUO CASO'!B12)^($B$4*12)-'1 - IL TUO CASO'!B30*(((1+'1 - IL TUO CASO'!B12)^($B$4*12)-1)/'1 - IL TUO CASO'!B12))-('1 - IL TUO CASO'!B26*(1+0.07)^$B$4+'3 - CONFRONTO'!$B$9*12*(((1+0.07)^$B$4-1)/0.07))
A10: +1% all'anno | B10: ='1 - IL TUO CASO'!B5*(1+0.01)^$B$4*(1-'2 - COSTI'!B21)-MAX(0,'1 - IL TUO CASO'!B8*(1+'1 - IL TUO CASO'!B12)^($B$4*12)-'1 - IL TUO CASO'!B30*(((1+'1 - IL TUO CASO'!B12)^($B$4*12)-1)/'1 - IL TUO CASO'!B12))-('1 - IL TUO CASO'!B26*(1+0.03)^$B$4+'3 - CONFRONTO'!$B$9*12*(((1+0.03)^$B$4-1)/0.03)) | C10: ='1 - IL TUO CASO'!B5*(1+0.01)^$B$4*(1-'2 - COSTI'!B21)-MAX(0,'1 - IL TUO CASO'!B8*(1+'1 - IL TUO CASO'!B12)^($B$4*12)-'1 - IL TUO CASO'!B30*(((1+'1 - IL TUO CASO'!B12)^($B$4*12)-1)/'1 - IL TUO CASO'!B12))-('1 - IL TUO CASO'!B26*(1+0.04)^$B$4+'3 - CONFRONTO'!$B$9*12*(((1+0.04)^$B$4-1)/0.04)) | D10: ='1 - IL TUO CASO'!B5*(1+0.01)^$B$4*(1-'2 - COSTI'!B21)-MAX(0,'1 - IL TUO CASO'!B8*(1+'1 - IL TUO CASO'!B12)^($B$4*12)-'1 - IL TUO CASO'!B30*(((1+'1 - IL TUO CASO'!B12)^($B$4*12)-1)/'1 - IL TUO CASO'!B12))-('1 - IL TUO CASO'!B26*(1+0.05)^$B$4+'3 - CONFRONTO'!$B$9*12*(((1+0.05)^$B$4-1)/0.05)) | E10: ='1 - IL TUO CASO'!B5*(1+0.01)^$B$4*(1-'2 - COSTI'!B21)-MAX(0,'1 - IL TUO CASO'!B8*(1+'1 - IL TUO CASO'!B12)^($B$4*12)-'1 - IL TUO CASO'!B30*(((1+'1 - IL TUO CASO'!B12)^($B$4*12)-1)/'1 - IL TUO CASO'!B12))-('1 - IL TUO CASO'!B26*(1+0.07)^$B$4+'3 - CONFRONTO'!$B$9*12*(((1+0.07)^$B$4-1)/0.07))
A11: +2% all'anno | B11: ='1 - IL TUO CASO'!B5*(1+0.02)^$B$4*(1-'2 - COSTI'!B21)-MAX(0,'1 - IL TUO CASO'!B8*(1+'1 - IL TUO CASO'!B12)^($B$4*12)-'1 - IL TUO CASO'!B30*(((1+'1 - IL TUO CASO'!B12)^($B$4*12)-1)/'1 - IL TUO CASO'!B12))-('1 - IL TUO CASO'!B26*(1+0.03)^$B$4+'3 - CONFRONTO'!$B$9*12*(((1+0.03)^$B$4-1)/0.03)) | C11: ='1 - IL TUO CASO'!B5*(1+0.02)^$B$4*(1-'2 - COSTI'!B21)-MAX(0,'1 - IL TUO CASO'!B8*(1+'1 - IL TUO CASO'!B12)^($B$4*12)-'1 - IL TUO CASO'!B30*(((1+'1 - IL TUO CASO'!B12)^($B$4*12)-1)/'1 - IL TUO CASO'!B12))-('1 - IL TUO CASO'!B26*(1+0.04)^$B$4+'3 - CONFRONTO'!$B$9*12*(((1+0.04)^$B$4-1)/0.04)) | D11: ='1 - IL TUO CASO'!B5*(1+0.02)^$B$4*(1-'2 - COSTI'!B21)-MAX(0,'1 - IL TUO CASO'!B8*(1+'1 - IL TUO CASO'!B12)^($B$4*12)-'1 - IL TUO CASO'!B30*(((1+'1 - IL TUO CASO'!B12)^($B$4*12)-1)/'1 - IL TUO CASO'!B12))-('1 - IL TUO CASO'!B26*(1+0.05)^$B$4+'3 - CONFRONTO'!$B$9*12*(((1+0.05)^$B$4-1)/0.05)) | E11: ='1 - IL TUO CASO'!B5*(1+0.02)^$B$4*(1-'2 - COSTI'!B21)-MAX(0,'1 - IL TUO CASO'!B8*(1+'1 - IL TUO CASO'!B12)^($B$4*12)-'1 - IL TUO CASO'!B30*(((1+'1 - IL TUO CASO'!B12)^($B$4*12)-1)/'1 - IL TUO CASO'!B12))-('1 - IL TUO CASO'!B26*(1+0.07)^$B$4+'3 - CONFRONTO'!$B$9*12*(((1+0.07)^$B$4-1)/0.07))
A12: +3% all'anno | B12: ='1 - IL TUO CASO'!B5*(1+0.03)^$B$4*(1-'2 - COSTI'!B21)-MAX(0,'1 - IL TUO CASO'!B8*(1+'1 - IL TUO CASO'!B12)^($B$4*12)-'1 - IL TUO CASO'!B30*(((1+'1 - IL TUO CASO'!B12)^($B$4*12)-1)/'1 - IL TUO CASO'!B12))-('1 - IL TUO CASO'!B26*(1+0.03)^$B$4+'3 - CONFRONTO'!$B$9*12*(((1+0.03)^$B$4-1)/0.03)) | C12: ='1 - IL TUO CASO'!B5*(1+0.03)^$B$4*(1-'2 - COSTI'!B21)-MAX(0,'1 - IL TUO CASO'!B8*(1+'1 - IL TUO CASO'!B12)^($B$4*12)-'1 - IL TUO CASO'!B30*(((1+'1 - IL TUO CASO'!B12)^($B$4*12)-1)/'1 - IL TUO CASO'!B12))-('1 - IL TUO CASO'!B26*(1+0.04)^$B$4+'3 - CONFRONTO'!$B$9*12*(((1+0.04)^$B$4-1)/0.04)) | D12: ='1 - IL TUO CASO'!B5*(1+0.03)^$B$4*(1-'2 - COSTI'!B21)-MAX(0,'1 - IL TUO CASO'!B8*(1+'1 - IL TUO CASO'!B12)^($B$4*12)-'1 - IL TUO CASO'!B30*(((1+'1 - IL TUO CASO'!B12)^($B$4*12)-1)/'1 - IL TUO CASO'!B12))-('1 - IL TUO CASO'!B26*(1+0.05)^$B$4+'3 - CONFRONTO'!$B$9*12*(((1+0.05)^$B$4-1)/0.05)) | E12: ='1 - IL TUO CASO'!B5*(1+0.03)^$B$4*(1-'2 - COSTI'!B21)-MAX(0,'1 - IL TUO CASO'!B8*(1+'1 - IL TUO CASO'!B12)^($B$4*12)-'1 - IL TUO CASO'!B30*(((1+'1 - IL TUO CASO'!B12)^($B$4*12)-1)/'1 - IL TUO CASO'!B12))-('1 - IL TUO CASO'!B26*(1+0.07)^$B$4+'3 - CONFRONTO'!$B$9*12*(((1+0.07)^$B$4-1)/0.07))
A14: Il dato storico che serve per scegliere la riga
A15: Periodo / indice ISTAT | B15: Valore
A16: Media 2010 (base) | B16: 100
A17: 2021 — totale abitazioni | B17: 87,2 (-12,8%)
A18: 2021 — solo abitazioni esistenti | B18: 80,2 (-19,8%)
A19: 2021 — solo abitazioni nuove | B19: 107,6 (+7,6%)
A20: I trimestre 2026 — variazione annua | B20: +5,2%
A22: Negli undici anni fra il 2010 e il 2021 i prezzi delle case ESISTENTI in Italia sono scesi di quasi il 20% in termini nominali, quindi molto di più al netto dell'inflazione. Dal 2022 c'è stata una ripresa robusta. Prima di usare la riga «+2% o +3% all'anno» chiediti se stai facendo una previsione o un desiderio.
