Workbook

Sheet 0 - Indice
A1: Marco FIRE — Affitti brevi 2026: il conto vero
A2: Strumento informativo / divulgativo. NON è consulenza finanziaria. I valori sono indicativi al 2026 e vanno verificati col tuo consulente.
A4: Indice
A5: 1 - IL TUO CASO | B5: I sette numeri, i parametri operativi e la banda dei costi fissi
A6: 2 - CASCATA | B6: Dove finiscono i soldi dell'ospite, su quattro livelli misurati di notti
A7: 3 - PAREGGIO | B7: Le due soglie di pareggio, in notti e in fatturato, contro i dati veri
A8: 4 - BREVE VS LUNGO | B8: Lo stesso immobile affittato a lungo: canone libero e concordato
A9: 5 - DUE STAGIONI | B9: Che cosa cambia se il prezzo non è piatto tutto l'anno
A10: 6 - PARAMETRI 2026 | B10: Il caso di partenza, tutte le fonti e i limiti dichiarati del modello
A12: Come usare
A13: 1. Le celle GIALLE sono input — modificale coi tuoi numeri.
A14: 2. Le celle VERDI sono output — si aggiornano automaticamente.
A15: 3. Tutti i numeri di default sono al 2026 da fonti pubbliche.
A16: 4. Niente codice nascosto: l'Excel è solo formule modificabili.
A18: Fonti dati
A19: • Istruzioni al modello 730/2026, Quadro B (agg. 28/05/2026) e circolare AdE 24/E del 12/10/2017 p. 14 — la cedolare si applica al 100% del corrispettivo lordo, provvigione compresa quando la piattaforma la trattiene sul bonifico
A20: • L. 160/2019 art. 1 commi 745, 754 e 760 — base imponibile IMU, aliquota massima 1,06%, riduzione di un quarto per il canone concordato
A21: • AirROI — notti vendute per annuncio su 11 città medie; definizione di occupancy AirDNA (notti prenotate / notti in cui l'annuncio era attivo)
A22: • CleanBnB SpA, bilancio revisionato 2025 — 43,5 check-in per appartamento, margine netto 0,6%, costi per servizi all'81% dei ricavi
A23: • AdE, Rapporto Immobiliare 2026 — 6,79 €/mq/mese sui contratti 4+4 registrati; OMI 2° semestre 2025 e Nomisma per prezzi e sconto in trattativa
A24: • D.M. 31/12/1988 Gruppo XIX — coefficienti di ammortamento dell'ospitalità: mobili 10%, biancheria 40%, stoviglie 25%
... A27: Aggiornamenti: github.com/marcofire-it/marco-fire-simulatori

Sheet 1 - IL TUO CASO
A1: Il tuo caso — i sette numeri che decidono
A2: Strumento informativo / divulgativo. NON è consulenza finanziaria. I valori sono indicativi al 2026 e vanno verificati col tuo consulente.
A3: DEPERIBILITÀ — il quadro fiscale di questo foglio è quello del 2026: cedolare secca al 21% sul primo immobile, IMU sui fabbricati «a disposizione», detrazioni e adempimenti vigenti. Dal 2027 la materia si sposta nell'art. 207 del nuovo Testo unico: quando quel testo sarà consultabile, i numeri di questo foglio vanno rifatti.
A4: Il caso di partenza è un bilocale in una città turistica media — Verona, Bergamo, Trieste, Lucca — comprato con 250.000 € liquidi. Cambia le celle gialle e diventa il tuo. Un avvertimento sul quarto numero: NON scrivere una percentuale di occupazione presa dalle brochure. L'occupancy che leggi in giro è la quota di notti vendute su quelle in cui l'annuncio era APERTO, non sull'anno: il 64% di occupancy su 246 notti disponibili fa 157 notti, non 234. Qui si scrivono le notti vendute, e basta.
A6: I SETTE NUMERI — cambia solo le celle gialle
A7: 1. Prezzo di ROGITO dell'immobile (€) | B7: 174700 | E7: Non il prezzo richiesto: quello effettivamente pagato. Nel caso base sono 195.000 € richiesti meno il 10,4% di sconto medio in trattativa misurato da Nomisma.
A8: 2. Rendita catastale (€) | B8: 400 | E8: Da qui esce l'IMU. Se non la conosci, la trovi nella visura o nell'atto. Regola pratica: la base imponibile IMU è circa il 38,5% del valore di mercato nei comuni turistici, quindi la rendita è circa il valore diviso 437.
A9: 3. Prezzo medio a notte, PULIZIE ESCLUSE (€) | B9: 100 | E9: Attenzione: molti osservatori pubblicano l'ADR con la pulizia dentro. 100 € puliti qui equivalgono a circa 117 € nella metrica di AirDNA.
A10: 4. Notti vendute in un anno | B10: 87 | E10: Il numero che decide tutto. Nelle 11 città medie misurate la media per annuncio è 87; il quartile alto è 110, il decile alto 160. Se non hai un dato tuo, non inventarlo verso l'alto.
A11: 5. Soggiorno medio (notti) | B11: 3.7 | E11: Da un dato societario: CleanBnB 2025, 135.414 soggiorni su 3.115 appartamenti = 43,5 check-in l'anno. Usa 3,2 solo se sei in una città d'arte da city-break, 4,3-4,9 se sei al mare o al Sud. Meno turnover = meno pulizie e meno ore.
A12: 6. Commissione delle piattaforme (IVA inclusa) | B12: 0.185 | E12: Booking circa 18,3%, Airbnb circa 18,9% dopo il passaggio al modello host-only. La commissione si calcola su una base che include anche la fee di pulizia.
A13: 7. Compenso del property manager | B13: 0.2 | E13: Il costo di rendere l'operazione davvero passiva. Tipicamente 20-25%.
A14: su quale base si calcola il property manager | B14: lordo | E14: Scrivi «lordo» oppure «netto post-OTA». Non è un dettaglio: sullo scenario medio ballano quasi 400 € l'anno, ed è la prima cosa da chiedere in contratto.
A16: PARAMETRI OPERATIVI — cambiali se il tuo caso è diverso
A17: Fee di pulizia incassata dall'ospite (€) | B17: 62 | E17: Entra nel corrispettivo lordo, quindi ci paghi anche la cedolare.
A18: Fee di pulizia pagata all'impresa (€) | B18: 67 | E18: Costo reale di un turnover a tariffa oraria di contratto (DD Min. Lavoro n. 25 del 30/03/2026), biancheria inclusa. Si incassa meno di quanto si paga: la differenza è un sussidio implicito all'annuncio, perché una cleaning fee alta abbassa la conversione.
A19: Cedolare secca | B19: 0.21 | E19: 21% con un solo immobile destinato al breve; dal secondo al quarto sale al 26%. Si applica al 100% del corrispettivo LORDO, commissione compresa, quando la piattaforma la trattiene sul bonifico.
A20: Aliquota IMU | B20: 0.0106 | E20: 1,06% è il massimo di legge e si applica ai fabbricati «tenuti a disposizione»: poiché i contratti brevi non si registrano, l'immobile ci rientra.
A21: Ore di lavoro per ogni turnover | B21: 2.1 | E21: Annuncio, messaggi, check-in, coordinamento pulizie, imprevisti.
A22: Ore fisse all'anno | B22: 40 | E22: Adempimenti, comunicazioni, dichiarazioni, aggiornamenti dei prezzi.
A24: COSTI FISSI ANNUI — una banda, non un numero
A25: Voce | B25: Minimo | C25: Centro | D25: Massimo | E25: Fonte / nota
A26: IMU | B26: =$B$8*168*$B$20 | C26: =$B$8*168*$B$20 | D26: =$B$8*168*$B$20 | E26: Base imponibile = rendita rivalutata del 5% per il moltiplicatore 160 (L. 160/2019 art. 1 c. 745), in pratica rendita × 168. Non varia nella banda perché discende dalla rendita, che è un dato. Nessun Comune può creare un'aliquota dedicata agli affitti brevi: dal 2025 il Prospetto MEF ammette solo le fattispecie dell'Allegato A al D.M. 07/07/2023.
A27: TARI | B27: 125 | C27: 325 | D27: 700 | E27: forbice del dossier costi: 125-700 €, caso centrale 250-400 €
A28: Utenze e internet | B28: 1900 | C28: 2200 | D28: 2610 | E28: prezzi ARERA letti direttamente; un bilocale con ricambio continuo di ospiti consuma come una casa abitata
A29: Assicurazione | B29: 150 | C29: 375 | D29: 600 | E29: nessuna piattaforma copre fabbricato e contenuto: la polizza va comprata a parte
A30: Condominio | B30: 700 | C30: 900 | D30: 2000 | E30: spese ordinarie di un bilocale in condominio
A31: Manutenzione e rinnovo arredi | B31: 2000 | C31: 2500 | D31: 3000 | E31: ancorata al D.M. 31/12/1988 Gruppo XIX: mobili 10% l'anno, biancheria 40%, stoviglie 25%. L'ospitalità a rotazione consuma classi di beni che l'affitto lungo non tocca
A32: Manutenzione estintore | B32: 60 | C32: 105 | D32: 150 | E32: UNI 9994-1:2024, controllo semestrale
A33: Software e channel manager | B33: 380 | C33: 420 | D33: 465 | E33: listino ufficiale Smoobu Professional Flex
A34: TOTALE COSTI FISSI | B34: =SUM(B26:B33) | C34: =SUM(C26:C33) | D34: =SUM(D26:D33) | E34: Sono fissi: li paghi uguali a 60 notti e a 160. È il motivo per cui il risultato dipende quasi solo dalle notti vendute.
A35: Costo fisso per notte venduta | C35: =$C$34/$B$10 | E35: Ai default sono 87 € a notte di soli costi fissi, contro 100 € di prezzo.
A37: I TRE NUMERI DERIVATI CHE USANO TUTTI GLI ALTRI FOGLI
A38: Turnover (soggiorni) in un anno | B38: =$B$10/$B$11 | E38: Non arrotondato: è una media annua, non un conteggio.
A39: Fatturato lordo per notte venduta | B39: =$B$9+$B$17/$B$11 | E39: Il prezzo più la quota di pulizia che l'ospite paga.
A40: MARGINE NETTO per notte venduta | B40: =($B$9+$B$17/$B$11)*(1-$B$12-$B$19)-$B$18/$B$11 | E40: Quanto ti resta in tasca per ogni notte in più che vendi, dopo piattaforma, cedolare e pulizia. È costante, e da qui escono le due soglie di pareggio del foglio 3.

Sheet 2 - CASCATA
A1: La cascata — dove finiscono i soldi dell'ospite
A2: Strumento informativo / divulgativo. NON è consulenza finanziaria. I valori sono indicativi al 2026 e vanno verificati col tuo consulente.
A3: Le quattro colonne sono gradini misurati della stessa distribuzione, non scenari inventati: mediana, media, terzo quartile e decile alto delle notti vendute per annuncio nelle 11 città medie osservate. L'ultima colonna usa le TUE notti. Tutto è calcolato con l'ADR piatto, che è il ramo prudente: il foglio 5 mostra quanto ti penalizza.
A5: Voce | B5: Mediana di mercato | C5: Media misurata | D5: Quartile alto | E5: Decile alto | F5: Le TUE notti
B6: AirROI, mediana per annuncio delle 11 città medie | C6: AirROI, media per annuncio delle 11 città medie | D6: AirROI, terzo quartile per annuncio | E6: AirROI, decile alto per annuncio | F6: dalla cella B10 del foglio 1
A8: Notti vendute in un anno | B8: =60 | C8: =87 | D8: =110 | E8: =160 | F8: ='1 - IL TUO CASO'!$B$10
A9: Turnover (soggiorni) | B9: =B8/'1 - IL TUO CASO'!$B$11 | C9: =C8/'1 - IL TUO CASO'!$B$11 | D9: =D8/'1 - IL TUO CASO'!$B$11 | E9: =E8/'1 - IL TUO CASO'!$B$11 | F9: =F8/'1 - IL TUO CASO'!$B$11
A10: Corrispettivo lordo pagato dall'ospite | B10: ='1 - IL TUO CASO'!$B$9*B8+'1 - IL TUO CASO'!$B$17*B9 | C10: ='1 - IL TUO CASO'!$B$9*C8+'1 - IL TUO CASO'!$B$17*C9 | D10: ='1 - IL TUO CASO'!$B$9*D8+'1 - IL TUO CASO'!$B$17*D9 | E10: ='1 - IL TUO CASO'!$B$9*E8+'1 - IL TUO CASO'!$B$17*E9 | F10: ='1 - IL TUO CASO'!$B$9*F8+'1 - IL TUO CASO'!$B$17*F9 | G10: Prezzo delle notti più le fee di pulizia incassate. È la base su cui la piattaforma calcola la commissione E su cui lo Stato calcola la cedolare.
A11: − Commissioni delle piattaforme | B11: =-'1 - IL TUO CASO'!$B$12*B10 | C11: =-'1 - IL TUO CASO'!$B$12*C10 | D11: =-'1 - IL TUO CASO'!$B$12*D10 | E11: =-'1 - IL TUO CASO'!$B$12*E10 | F11: =-'1 - IL TUO CASO'!$B$12*F10
A12: − Pulizie pagate all'impresa | B12: =-'1 - IL TUO CASO'!$B$18*B9 | C12: =-'1 - IL TUO CASO'!$B$18*C9 | D12: =-'1 - IL TUO CASO'!$B$18*D9 | E12: =-'1 - IL TUO CASO'!$B$18*E9 | F12: =-'1 - IL TUO CASO'!$B$18*F9
A13: − Costi fissi (valore centrale) | B13: =-'1 - IL TUO CASO'!$C$34 | C13: =-'1 - IL TUO CASO'!$C$34 | D13: =-'1 - IL TUO CASO'!$C$34 | E13: =-'1 - IL TUO CASO'!$C$34 | F13: =-'1 - IL TUO CASO'!$C$34
A14: − Cedolare secca sul lordo | B14: =-'1 - IL TUO CASO'!$B$19*B10 | C14: =-'1 - IL TUO CASO'!$B$19*C10 | D14: =-'1 - IL TUO CASO'!$B$19*D10 | E14: =-'1 - IL TUO CASO'!$B$19*E10 | F14: =-'1 - IL TUO CASO'!$B$19*F10 | G14: Si paga sul corrispettivo lordo, commissione compresa, e si paga anche se il margine operativo è negativo: non è un'imposta sul profitto.
A15: NETTO-NETTO — quello che ti resta | B15: =SUM(B10:B14) | C15: =SUM(C10:C14) | D15: =SUM(D10:D14) | E15: =SUM(E10:E14) | F15: =SUM(F10:F14)
A16: in % sul prezzo di rogito | B16: =B15/'1 - IL TUO CASO'!$B$7 | C16: =C15/'1 - IL TUO CASO'!$B$7 | D16: =D15/'1 - IL TUO CASO'!$B$7 | E16: =E15/'1 - IL TUO CASO'!$B$7 | F16: =F15/'1 - IL TUO CASO'!$B$7
A17: Ore di lavoro all'anno | B17: =B9*'1 - IL TUO CASO'!$B$21+'1 - IL TUO CASO'!$B$22 | C17: =C9*'1 - IL TUO CASO'!$B$21+'1 - IL TUO CASO'!$B$22 | D17: =D9*'1 - IL TUO CASO'!$B$21+'1 - IL TUO CASO'!$B$22 | E17: =E9*'1 - IL TUO CASO'!$B$21+'1 - IL TUO CASO'!$B$22 | F17: =F9*'1 - IL TUO CASO'!$B$21+'1 - IL TUO CASO'!$B$22
A18: Guadagno per ora di lavoro | B18: =IFERROR(B15/B17,0) | C18: =IFERROR(C15/C17,0) | D18: =IFERROR(D15/D17,0) | E18: =IFERROR(E15/E17,0) | F18: =IFERROR(F15/F17,0)
A20: LA BANDA — lo stesso conto coi costi fissi ai due estremi
A21: NETTO coi costi fissi al MINIMO | B21: =B15+('1 - IL TUO CASO'!$C$34-'1 - IL TUO CASO'!$B$34) | C21: =C15+('1 - IL TUO CASO'!$C$34-'1 - IL TUO CASO'!$B$34) | D21: =D15+('1 - IL TUO CASO'!$C$34-'1 - IL TUO CASO'!$B$34) | E21: =E15+('1 - IL TUO CASO'!$C$34-'1 - IL TUO CASO'!$B$34) | F21: =F15+('1 - IL TUO CASO'!$C$34-'1 - IL TUO CASO'!$B$34)
A22: NETTO coi costi fissi al MASSIMO | B22: =B15-('1 - IL TUO CASO'!$D$34-'1 - IL TUO CASO'!$C$34) | C22: =C15-('1 - IL TUO CASO'!$D$34-'1 - IL TUO CASO'!$C$34) | D22: =D15-('1 - IL TUO CASO'!$D$34-'1 - IL TUO CASO'!$C$34) | E22: =E15-('1 - IL TUO CASO'!$D$34-'1 - IL TUO CASO'!$C$34) | F22: =F15-('1 - IL TUO CASO'!$D$34-'1 - IL TUO CASO'!$C$34)
A23: Allo scenario della media misurata la banda va da −1.457 € a −5.667 €. Non attraversa lo zero: è negativa da un capo all'altro. La banda è il modo corretto di mostrare l'incertezza, ma qui non cambia il segno della risposta.
A25: SE DELEGHI — il conto con il property manager
A26: Compenso del property manager | B26: =-IF('1 - IL TUO CASO'!$B$14="lordo",'1 - IL TUO CASO'!$B$13*B10,'1 - IL TUO CASO'!$B$13*(B10+B11)) | C26: =-IF('1 - IL TUO CASO'!$B$14="lordo",'1 - IL TUO CASO'!$B$13*C10,'1 - IL TUO CASO'!$B$13*(C10+C11)) | D26: =-IF('1 - IL TUO CASO'!$B$14="lordo",'1 - IL TUO CASO'!$B$13*D10,'1 - IL TUO CASO'!$B$13*(D10+D11)) | E26: =-IF('1 - IL TUO CASO'!$B$14="lordo",'1 - IL TUO CASO'!$B$13*E10,'1 - IL TUO CASO'!$B$13*(E10+E11)) | F26: =-IF('1 - IL TUO CASO'!$B$14="lordo",'1 - IL TUO CASO'!$B$13*F10,'1 - IL TUO CASO'!$B$13*(F10+F11))
A27: NETTO se deleghi la gestione | B27: =B15+B26 | C27: =C15+C26 | D27: =D15+D26 | E27: =E15+E26 | F27: =F15+F26
A28: Ore di lavoro che ti restano | B28: =10 | C28: =10 | D28: =10 | E28: =10 | F28: =10
A29: Una precisazione che il video fa e che vale la pena ripetere qui: il 20-25% del gestore non è rendita. CleanBnB, l'unico operatore quotato con bilancio revisionato, nel 2025 ha chiuso con un margine netto dello 0,6% e costi per servizi all'81% dei ricavi. Quella commissione è quasi tutta pulizie, lavanderia e personale: il settore ha margini sottili per tutti, proprietari e gestori.

Sheet 3 - PAREGGIO
A1: Il pareggio — quante notti ti servono, e quante ne vende chi ci riesce
A2: Strumento informativo / divulgativo. NON è consulenza finanziaria. I valori sono indicativi al 2026 e vanno verificati col tuo consulente.
A3: Se devi fare un conto solo prima di comprare, è questo. Prendi la soglia qui sotto e confrontala col massimo misurato nella tua città: se la soglia è più alta, hai finito e non serve altro.
A5: LE DUE SOGLIE
A6: Margine netto per notte venduta | B6: ='1 - IL TUO CASO'!$B$40
A7: Fatturato lordo per notte venduta | B7: ='1 - IL TUO CASO'!$B$39
A9: Soglia | B9: Notti da vendere | C9: Fatturato lordo | D9: Che cosa vuol dire
A10: PAREGGIO DI CASSA — non ci rimetti | B10: =ROUND('1 - IL TUO CASO'!$C$34/$B$6,0) | C10: ='1 - IL TUO CASO'!$C$34/$B$6*$B$7 | D10: La soglia da superare per non metterci soldi di tasca. Non remunera un euro del capitale investito e non paga un'ora del tuo tempo.
A11: PAREGGIO CON L'AFFITTO LUNGO — la soglia vera | B11: =ROUND(('1 - IL TUO CASO'!$C$34+'4 - BREVE VS LUNGO'!$B$23)/$B$6,0) | C11: =('1 - IL TUO CASO'!$C$34+'4 - BREVE VS LUNGO'!$B$23)/$B$6*$B$7 | D11: Sotto questa soglia lo stesso immobile ti rende di più affittato a lungo, con dieci ore di lavoro all'anno invece di novanta.
A12: in quota sul calendario dell'anno | B12: =$B$11/365
A13: Le tue notti, per confronto | B13: ='1 - IL TUO CASO'!$B$10 | C13: ='1 - IL TUO CASO'!$B$10*$B$7
A14: Ti mancano, per il pareggio di cassa | B14: =MAX(0,$B$10-$B$13)
A16: I FATTURATI MISURATI — la coppia che decide
A17: Tutti i valori sono fatturato lordo annuo pagato dall'ospite, pulizie comprese: la base è la stessa della soglia qui sopra, altrimenti il confronto non varrebbe niente. Le città medie vengono da un osservatorio che misura tutti gli annunci di undici città; le medie nazionali da bilanci di gestori professionali.
A18: Fonte | B18: Fatturato lordo annuo | C18: Notti implicite | D18: Rispetto al pareggio di cassa
A19: AirROI — media delle 11 città medie misurate | B19: 12315 | C19: =$B19/$B$7 | D19: =IF($B19>=$C$10,"sopra — ce la fa","SOTTO il pareggio") | E19: è la media della fascia in cui 250.000 € ti fanno comprare
A20: CleanBnB 2025 — media di portafoglio | B20: 20364 | C20: =$B20/$B$7 | D20: =IF($B20>=$C$10,"sopra — ce la fa","SOTTO il pareggio") | E20: gestore professionale quotato, bilancio revisionato
A21: AIGAB 2026 — media nazionale | B21: 20859 | C21: =$B21/$B$7 | D21: =IF($B21>=$C$10,"sopra — ce la fa","SOTTO il pareggio") | E21: associazione di categoria: la media è vera, ed è dominata da Roma e Milano
A22: CleanBnB — Milano | B22: 38037 | C22: =$B22/$B$7 | D22: =IF($B22>=$C$10,"sopra — ce la fa","SOTTO il pareggio") | E22: dove i numeri funzionano, il prezzo se li è già presi
A23: CleanBnB — Roma | B23: 47853 | C23: =$B23/$B$7 | D23: =IF($B23>=$C$10,"sopra — ce la fa","SOTTO il pareggio") | E23: idem
A24: CleanBnB — mare e montagna | B24: 7362 | C24: =$B24/$B$7 | D24: =IF($B24>=$C$10,"sopra — ce la fa","SOTTO il pareggio") | E24: stagionalità corta: la casa al mare è il caso peggiore, non il migliore
A26: Come si legge la colonna «notti implicite»: sono le notti che servirebbero per fare quel fatturato AL TUO PREZZO. Quando il numero supera le 365 non vuol dire che a Roma vendono più notti di quante ne abbia l'anno: vuol dire che là il prezzo a notte è molto più alto del tuo, ed è esattamente il punto — quei fatturati non si raggiungono lavorando di più, si raggiungono stando in un altro mercato.
A27: Questo è il verdetto del video, ed è strutturale, non morale: il breve funziona dove la domanda è alta, e non funziona dove non lo è. La media nazionale che il settore cita è vera, ed è dominata da Roma e Milano. Nelle città medie, misurate una per una, il fatturato medio sta SOTTO il pareggio di cassa. E si chiude il cerchio: i posti dove i numeri funzionano sono esattamente quelli dove 250.000 € non ti fanno entrare, perché il prezzo d'acquisto ha già incorporato la domanda turistica.
A28: Un controllo di robustezza che vale la pena rifare da soli: metti 194 notti nella cella B10 del foglio 1 — la cima del decile alto per annuncio — e guarda il netto. Viene circa +2.654 €, che è ancora sotto i 3.958 € dell'affitto lungo. Il verdetto regge su tutta l'estensione della distribuzione misurata, non solo al centro.

Sheet 4 - BREVE VS LUNGO
A1: Breve contro lungo — lo stesso immobile, due mestieri diversi
A2: Strumento informativo / divulgativo. NON è consulenza finanziaria. I valori sono indicativi al 2026 e vanno verificati col tuo consulente.
A3: Il confronto onesto non è «affitti brevi contro ETF»: è affitti brevi contro lo STESSO immobile affittato a lungo. Se il breve non batte il lungo, tutto il resto del ragionamento non serve.
A5: LE IPOTESI DELL'AFFITTO LUNGO
A6: Canone mensile richiesto (€) | B6: 750 | E6: Coerente col derivato di Verona nel dossier canoni. Sul rogito fa un rendimento lordo del 5,15%, che è all'estremo ALTO della forbice di zona centrale misurata (Verona 3,95%, Trieste 5,17%): il confronto è quindi tarato a favore del lungo, cioè in modo conservativo per la tesi del video.
A7: Sfitto e morosità (vacancy) | B7: 0.04 | E7: Circa quindici giorni l'anno fra un inquilino e l'altro.
A8: Provvigione di agenzia, spalmata sull'anno (€) | B8: 250
A9: Manutenzione ordinaria a carico del proprietario (€) | B9: 1425.6 | E9: 16,5% del canone al netto dello sfitto. Nel breve la stessa voce costa di più, perché il ricambio consuma di più.
A10: Quota condominiale a carico del proprietario (€) | B10: 480 | E10: Nel lungo le spese ordinarie sono in gran parte dell'inquilino; nel breve sono tutte tue.
A11: Sconto del canone concordato | B11: 0.2 | E11: Il concordato taglia il canone in cambio di cedolare al 10% e IMU ridotta.
A12: Cedolare del canone concordato | B12: 0.1
A13: Riduzione IMU col canone concordato | B13: 0.25 | E13: L. 160/2019 c. 760.
A15: Affitto lungo, voce per voce | B15: Canone libero | C15: Canone concordato
A16: Canone annuo | B16: =$B$6*12 | C16: =$B$6*12*(1-$B$11)
A17: − Sfitto e morosità | B17: =-$B$16*$B$7 | C17: =-$C$16*$B$7
A18: − Provvigione di agenzia | B18: =-$B$8 | C18: =-$B$8
A19: − IMU | B19: =-'1 - IL TUO CASO'!$C$26 | C19: =-'1 - IL TUO CASO'!$C$26*(1-$B$13)
A20: − Manutenzione ordinaria | B20: =-$B$9 | C20: =-$B$9
A21: − Quota condominiale | B21: =-$B$10 | C21: =-$B$10
A22: − Cedolare secca | B22: =-'1 - IL TUO CASO'!$B$19*($B$16+$B$17) | C22: =-$B$12*($C$16+$C$17)
A23: NETTO DELL'AFFITTO LUNGO | B23: =SUM($B$16:$B$22) | C23: =SUM($C$16:$C$22)
A24: in % sul prezzo di rogito | B24: =$B$23/'1 - IL TUO CASO'!$B$7 | C24: =$C$23/'1 - IL TUO CASO'!$B$7
A25: Ore di lavoro all'anno | B25: =10 | C25: =10
A26: Il canone concordato viene PEGGIO del libero, e non di poco: il vantaggio fiscale (cedolare al 10% invece che al 21%, IMU ridotta di un quarto) non compensa il 20% di canone in meno. È controintuitivo e va calcolato, non affermato. Attenzione però: dipende dallo sconto richiesto nel tuo accordo territoriale — prova a cambiare la cella B11.
A28: IL CONFRONTO
B29: Breve, alle tue notti | C29: Lungo, canone libero
A30: Netto in un anno | B30: ='2 - CASCATA'!$F$15 | C30: =$B$23
A31: Ore di lavoro | B31: ='2 - CASCATA'!$F$17 | C31: =10
A32: Differenza a favore del lungo | B32: =$B$23-$B$30
A33: Notti a cui il breve pareggia il lungo | B33: =ROUND(('1 - IL TUO CASO'!$C$34+$B$23)/'1 - IL TUO CASO'!$B$40,0)
A34: in quota sul calendario dell'anno | B34: =$B$33/365
A35: Ai default servono 219 notti, cioè il 60% del calendario, contro un massimo misurato di 107 notti per annuncio nelle città medie. Non è una questione di impegno: è che quelle notti, in quelle città, non ci sono da vendere.

Sheet 5 - DUE STAGIONI
A1: Due stagioni — perché il modello piatto ti penalizza
A2: Strumento informativo / divulgativo. NON è consulenza finanziaria. I valori sono indicativi al 2026 e vanno verificati col tuo consulente.
A3: Il modello principale usa un prezzo medio piatto tutto l'anno. Ma la stagionalità italiana è forte e misurata: luglio e agosto valgono circa il 35% delle presenze annue in poco più del 16% del calendario. Se vendi poche notti, quelle poche notti sono quelle di alta stagione — e valgono più della media. Cioè: il modello piatto SOTTOSTIMA i ricavi, e il conto del foglio 2 è il ramo prudente.
A4: Il limite di questo foglio, dichiarato: assume l'allocazione perfetta, cioè che ogni notte venduta sia una notte di alta stagione finché l'alta stagione non è satura. È l'estremo ottimistico, come il piatto è l'estremo prudente. Il valore vero sta in mezzo.
A6: LE IPOTESI DELLE DUE STAGIONI
A7: Giorni di alta stagione | B7: 153 | G7: Da maggio a settembre.
A8: Occupancy massima raggiungibile in alta | B8: 0.7 | G8: Anche in agosto non si riempie tutto: a Rimini l'occupancy di agosto misurata è il 59,5%.
A9: Prezzo a notte in alta stagione (€) | B9: 115
A10: Prezzo a notte in bassa stagione (€) | B10: 88
A11: Notti vendibili in alta stagione | B11: =$B$7*$B$8
A13: Voce | B13: Mediana di mercato | C13: Media misurata | D13: Quartile alto | E13: Decile alto | F13: Le TUE notti
A14: Notti vendute | B14: ='2 - CASCATA'!B8 | C14: ='2 - CASCATA'!C8 | D14: ='2 - CASCATA'!D8 | E14: ='2 - CASCATA'!E8 | F14: ='2 - CASCATA'!F8
A15: di cui in alta stagione | B15: =MIN(B14,$B$11) | C15: =MIN(C14,$B$11) | D15: =MIN(D14,$B$11) | E15: =MIN(E14,$B$11) | F15: =MIN(F14,$B$11)
A16: di cui in bassa stagione | B16: =B14-B15 | C16: =C14-C15 | D16: =D14-D15 | E16: =E14-E15 | F16: =F14-F15
A17: Turnover (soggiorni) | B17: =B14/'1 - IL TUO CASO'!$B$11 | C17: =C14/'1 - IL TUO CASO'!$B$11 | D17: =D14/'1 - IL TUO CASO'!$B$11 | E17: =E14/'1 - IL TUO CASO'!$B$11 | F17: =F14/'1 - IL TUO CASO'!$B$11
A18: Corrispettivo lordo | B18: =$B$9*B15+$B$10*B16+'1 - IL TUO CASO'!$B$17*B17 | C18: =$B$9*C15+$B$10*C16+'1 - IL TUO CASO'!$B$17*C17 | D18: =$B$9*D15+$B$10*D16+'1 - IL TUO CASO'!$B$17*D17 | E18: =$B$9*E15+$B$10*E16+'1 - IL TUO CASO'!$B$17*E17 | F18: =$B$9*F15+$B$10*F16+'1 - IL TUO CASO'!$B$17*F17
A19: − Commissioni piattaforme | B19: =-'1 - IL TUO CASO'!$B$12*B18 | C19: =-'1 - IL TUO CASO'!$B$12*C18 | D19: =-'1 - IL TUO CASO'!$B$12*D18 | E19: =-'1 - IL TUO CASO'!$B$12*E18 | F19: =-'1 - IL TUO CASO'!$B$12*F18
A20: − Pulizie pagate | B20: =-'1 - IL TUO CASO'!$B$18*B17 | C20: =-'1 - IL TUO CASO'!$B$18*C17 | D20: =-'1 - IL TUO CASO'!$B$18*D17 | E20: =-'1 - IL TUO CASO'!$B$18*E17 | F20: =-'1 - IL TUO CASO'!$B$18*F17
A21: − Costi fissi (centro) | B21: =-'1 - IL TUO CASO'!$C$34 | C21: =-'1 - IL TUO CASO'!$C$34 | D21: =-'1 - IL TUO CASO'!$C$34 | E21: =-'1 - IL TUO CASO'!$C$34 | F21: =-'1 - IL TUO CASO'!$C$34
A22: − Cedolare secca | B22: =-'1 - IL TUO CASO'!$B$19*B18 | C22: =-'1 - IL TUO CASO'!$B$19*C18 | D22: =-'1 - IL TUO CASO'!$B$19*D18 | E22: =-'1 - IL TUO CASO'!$B$19*E18 | F22: =-'1 - IL TUO CASO'!$B$19*F18
A23: NETTO con due stagioni | B23: =SUM(B18:B22) | C23: =SUM(C18:C22) | D23: =SUM(D18:D22) | E23: =SUM(E18:E22) | F23: =SUM(F18:F22)
A24: NETTO col prezzo piatto (foglio 2) | B24: ='2 - CASCATA'!B15 | C24: ='2 - CASCATA'!C15 | D24: ='2 - CASCATA'!D15 | E24: ='2 - CASCATA'!E15 | F24: ='2 - CASCATA'!F15
A25: DIFFERENZA — quanto ti costa il modello piatto | B25: =B23-B24 | C25: =C23-C24 | D25: =D23-D24 | E25: =E23-E24 | F25: =F23-F24
A27: Alla media misurata il modello piatto ti penalizza di circa 790 € l'anno, e il netto passa da −2.967 € a −2.178 €. La direzione conta più della misura: il conto del foglio 2 è quello prudente, non quello cattivo. E resta negativo in tutti e due i modelli, tranne che in cima alla distribuzione.
A28: C'è anche un uso pratico: «alzo il prezzo» e «riempio di più» sono strategie ALTERNATIVE, non sommabili. Se alzi il prezzo in agosto vendi meno notti, e l'angolo in alto a destra — prezzo alto E calendario pieno — semplicemente non esiste.

Sheet 6 - PARAMETRI 2026
A1: Parametri e fonti — da dove viene ogni numero
A2: Strumento informativo / divulgativo. NON è consulenza finanziaria. I valori sono indicativi al 2026 e vanno verificati col tuo consulente.
A3: DEPERIBILITÀ — quadro fiscale 2026. Dal 2027 la disciplina delle locazioni brevi si sposta nell'art. 207 del nuovo Testo unico delle imposte sui redditi: alla data di questo foglio il testo dell'articolo non è ancora consultabile sulla banca dati ufficiale, quindi non se ne afferma il contenuto. Da gennaio 2027 vanno riverificati cedolare, base imponibile e adempimenti.
A5: IL CASO DI PARTENZA — due varianti misurate
A6: Voce | B6: Città cara (default) | C6: Città media (variante)
A7: Città di riferimento | B7: Verona / Bergamo / Trieste / Lucca | C7: Parma / Ravenna / Siracusa
A8: Prezzo richiesto | B8: 195.000 € | C8: 150.000 €
A9: Prezzo di rogito (−10,4%, Nomisma) | B9: 174.700 € | C9: 134.400 €
A10: Rendita catastale | B10: 400 € | C10: 308 €
A11: IMU all'1,06% | B11: 712 € | C11: 548 €
A12: Prezzo medio a notte, pulizie escluse | B12: 100 € | C12: 90 €
A13: Costi fissi annui, valore centrale | B13: 7.537 € | C13: 7.373 €
A14: Canone lungo di confronto | B14: 750 €/mese | C14: 650 €/mese
A15: Capitale complessivamente impiegato | B15: 204.830 € | C15: 162.012 €
A17: Per passare alla variante «città media» basta cambiare quattro celle gialle del foglio 1: prezzo di rogito, rendita catastale, prezzo a notte e — nel foglio 4 — canone mensile. I costi fissi si adeguano quasi da soli, perché l'unica voce che dipende dall'immobile è l'IMU.
A18: Sulla rendita catastale, una nota di trasparenza. Il dossier costi dà due derivazioni: dalle statistiche catastali dell'Agenzia delle Entrate una rendita di 300-450 € per un bilocale di 50-55 mq, e dallo studio OMI sul rapporto fra valore di mercato e base catastale una stima centrale di 458 € su un immobile da 200.000 €. Il default di questo foglio è 400 €, che è la rendita coerente col rogito effettivo di 174.700 € una volta applicata la regola del 38,5%. Se il tuo immobile ha una rendita più alta, scrivila: ogni 50 € di rendita in più sono circa 89 € di IMU in più all'anno.
A20: FONTI — norme, prassi e dati
A21: Cedolare secca 21% e base imponibile | B21: Istruzioni al modello 730/2026, Quadro B (agg. 28/05/2026): nel corrispettivo lordo è inclusa «la provvigione dovuta all'intermediario SE è trattenuta dall'intermediario sul canone dovuto al locatore». Colonna 6: l'importo da indicare è pari al 100% del corrispettivo lordo. Esempio numerico in circolare 24/E del 12/10/2017, p. 14: provvigione 80 €, canone 1.000 € → base 1.080 €, ritenuta 227 €. La condizione conta: se l'intermediario addebita la provvigione all'ospite e tu non la ribalti, non entra nel lordo.
A22: Aliquota 21% e limite dei quattro immobili | B22: regime vigente 2026: 21% sul primo immobile destinato al breve, 26% dal secondo al quarto
A23: IMU — base imponibile | B23: L. 160/2019 art. 1 c. 745: rendita rivalutata del 5% per il moltiplicatore 160, in pratica rendita × 168. Aliquota massima 1,06% (c. 754), applicabile ai fabbricati «tenuti a disposizione»: poiché i contratti brevi non si registrano, l'immobile ci rientra. Dal 2025 i Comuni possono differenziare solo sulle fattispecie dell'Allegato A al D.M. 07/07/2023: nessuno può creare un'aliquota dedicata agli affitti brevi.
A24: Commissioni delle piattaforme | B24: 18,5% IVA inclusa, media fra Booking (~18,3%) e Airbnb (~18,9%) dopo il passaggio al modello host-only, completato nell'ultima ondata del 13/10/2026. Airbnb dichiara che «la maggior parte degli host paga il 15,5%, gli altri di solito versano tra il 14% e il 16%»; l'IVA italiana al 22% si applica a chi non fornisce partita IVA. La commissione si calcola su una base che include la fee di pulizia.
A25: Notti vendute e occupancy | B25: AirROI, misurazione per annuncio su 11 città medie. Definizione ufficiale di occupancy (AirDNA): notti prenotate su notti in cui l'annuncio era attivo, non sull'anno solare. Nel campione le notti disponibili sono in media 246, non 365. Fonte a metodo non pubblicato: è il fondamento più fragile del modello, e va detto. Contro-verifica indipendente: ART-ER per l'Emilia-Romagna, più solida ma regionale e prudente per costruzione.
A26: Soggiorno medio 3,7 notti | B26: CleanBnB 2025: 135.414 soggiorni su 3.115 appartamenti = 43,5 check-in l'anno. Coerente col paniere AirROI (Verona 3,2 · Bergamo 3,5 · Trieste 3,9 · Rimini 4,9)
A27: Costo delle pulizie | B27: 67 € pagati a turnover, biancheria inclusa, a tariffa oraria di contratto (Decreto direttoriale Min. Lavoro n. 25 del 30/03/2026); 62 € incassati dall'ospite. Il costo del dossier (52-83 €) include già la biancheria: contare a parte i consumabili sarebbe doppio conteggio.
A28: Manutenzione e rinnovo arredi | B28: D.M. 31/12/1988 Gruppo XIX (alberghi): mobili 10% l'anno, biancheria 40%, stoviglie 25%. Nelle categorie non ricettive biancheria e stoviglie non esistono nemmeno come voci: dal 1988 il fisco riconosce che l'ospitalità a rotazione consuma classi di beni che l'affitto lungo non tocca.
A29: Margini del settore | B29: CleanBnB SpA (EGM:CBB), bilancio revisionato: take rate implicito 38,4% del gross booking post-OTA, ma EBITDA margin 5,4% e margine netto 0,6% nel 2025, H1 in perdita, costi per servizi all'81% dei ricavi
A30: Canoni dell'affitto lungo | B30: OMI 2° semestre 2025, contratti registrati AdE 2025, Tecnocasa, Nomisma. Benchmark solido dei contratti 4+4 registrati in Italia: 6,79 €/mq/mese su 409.986 contratti (AdE, Rapporto Immobiliare 2026). Rendimenti lordi da affitto lungo della SOLA zona centrale: Verona 3,95% · Rimini 4,54% · Lucca 4,60% · Bergamo 5,03% · Trieste 5,17%, contro medie cittadine del 5,41-6,93%. Nei centri turistici il lungo rende poco perché il prezzo ha già incorporato l'aspettativa del breve.
A31: Sconto in trattativa | B31: Nomisma: divario medio del 10,4% fra prezzo richiesto e prezzo di rogito
A32: Identificazione degli ospiti e keybox | B32: art. 109 TULPS e art. 19-bis c. 1 D.L. 113/2018 conv. L. 132/2018; circolare Min. Interno prot. 0038138 del 18/11/2024, n. 557/ST/221.3.1.0. TAR Lazio Sez. I Ter n. 10210/2025 (dep. 27/05/2025) · Consiglio di Stato Sez. III 21/11/2025, che qualifica la circolare «di portata non innovativa» · TAR Toscana Sez. I n. 919/2026 (dep. 14/05/2026), che ammette l'identificazione con riscontro visivo in tempo reale e valida il divieto di keybox di Firenze. Milano: art. 90 del Regolamento di polizia urbana in vigore da gennaio 2026, sanzione 100-400 € e rimozione coattiva. La violazione dell'art. 109 è contravvenzione penale ex art. 17 TULPS, non depenalizzata.
... A34: Confronto finanziario (nel video, non in questo foglio) | B34: portafoglio 60/40 al 3% reale (DMS Yearbook 2023), inflazione 2%, imposta di bollo 0,2% (D.Lgs. 123/2025), 26% sulla plusvalenza finanziaria (D.L. 66/2014 art. 3), plusvalenza immobiliare esente oltre i 5 anni, arredo con valore di realizzo al 30% a dieci anni
A36: QUELLO CHE QUESTO FOGLIO NON SA
A37: 1. Le notti vendute vengono da un osservatorio a metodo non pubblicato. È il numero che decide tutto: se fossero sottostimate del 30%, il caso base passerebbe da −2.967 € a circa −700 €. Se hai un dato tuo, usa quello.
A38: 2. Il tasso del mutuo (3,70% sul seconda casa) e il costo dell'arredo (16.000 €, con una forbice reale di 4.250-26.000 €) sono ipotesi senza fonte primaria.
A39: 3. Il contenuto dell'art. 207 del nuovo Testo unico non è stato letto: alla data di questo foglio non è consultabile sulla banca dati ufficiale. Qui si dice solo che la norma trasloca, non che cosa dirà.
A40: 4. Il foglio calcola un anno di gestione a regime. Non contiene i costi d'acquisto (circa 13.830 € fra imposte e notaio), l'arredo iniziale, né il confronto a dieci anni con un portafoglio finanziario: quello sta nel video.
A41: 5. Se l'immobile ce l'hai già, questo foglio ti serve ancora — ma la domanda cambia: non è «comprare o no», è «breve, lungo o vendere». I costi d'acquisto sono sommersi e non tornano nel conto.
