Workbook

Sheet 0-Indice
A1: Marco FIRE — La strategia a secchi (caso Roberta, 2026)
A2: Strumento informativo / divulgativo. NON è consulenza finanziaria. I valori sono indicativi al 2026 e vanno verificati col tuo consulente.
A4: Indice
A5: 1-Input | B5: I 18 input del caso, stato abitativo compreso
A6: P-Parametri | B6: Parametri normativi e di fonte, referenziati da tutti i fogli
A7: 2-Caso | B7: Scheda-caso: accumulo, latente, ISTAT e affitti figurativi, tre scale
A8: 3-Liquidita | B8: I sei strumenti del secchio 1, la copertura vera, il bollo
A9: 4-Griglia | B9: Griglia madre: costo del secchio per orizzonte, taglia e strumento
A10: 5-Roberta | B10: Il motore del caso: spesa massima sostenibile, costo, autonomia
A11: 6-Banda | B11: Le dodici perturbazioni sul costo di due anni di secchio
A12: 7-Refill | B12: Il refill anno per anno e la quota azionaria (rossa sopra l'80%)
A13: 8-Kitces | B13: L'identita' di Kitces con la convenzione del prelievo come input
A14: 9-ETF-unico | B14: Tre sacche separate contro un ETF multi-asset, coi termini negativi
A15: 10-Benz | B15: La regola di Benz: secchio sulla spesa o sul fabbisogno netto
A16: 11-Verifica | B16: Cruscotto, controlli e lista degli anti-residui
A18: Come usare
A19: 1. Le celle GIALLE sono input — modificale coi tuoi numeri.
A20: 2. Le celle VERDI sono output — si aggiornano automaticamente.
A21: 3. Tutti i numeri di default sono al 2026 da fonti pubbliche.
A22: 4. Niente codice nascosto: l'Excel è solo formule modificabili.
A24: Fonti dati
A25: • Banca d'Italia, «Banche e moneta: serie nazionali», tav. 2.7 (MIR0700), giugno 2026 — depositi con durata prestabilita delle famiglie
A26: • MEF, Dipartimento del Tesoro — «Risultati Asta: BOT 12 MESI» del 09/09/2026, ISIN IT0005730681, durata 365 gg, emissione 14/9/2026, scadenza 14/9/2027 (prezzo medio ponderato e prezzo fiscale 97,080; rendimento medio ponderato 2,967%; rendimento lordo composto 2,966%; base annua 360 gg). Gate di produzione CHIUSO il 9 settembre 2026
A27: • Borsa Italiana — MOT, prezzi del 9/9/2026 dei quattro BTP del paniere di canale: IT0003535157 (5,00% 1/8/2034) 106,58; IT0003256820 (5,75% 1/2/2033) 110,69; IT0001444378 (6,00% 1/5/2031) 110,19; IT0005595803 (3,45% 15/7/2031) 99,16. YTM medio 3,81%. Gate di produzione CHIUSO il 9 settembre 2026
A28: • BCE — €STR del 7 settembre 2026, 2,188%
A29: • ISTAT, «Le spese per i consumi delle famiglie — Anno 2024», comunicato del 7/10/2025
A30: • Bollo: art. 9 commi 3 e 4 della Tariffa, Parte I, Allegato 3 al D.Lgs. 1/8/2025 n. 123 (GU n. 186 del 12/08/2025, S.O. 29/L), in applicazione dal 1° gennaio 2026
... A37: Aggiornamenti: github.com/marcofire-it/marco-fire-simulatori

Sheet 1-Input
A1: Gli input del caso — cambia una cella gialla e tutti i verdi si muovono
A2: Strumento informativo / divulgativo. NON è consulenza finanziaria. I valori sono indicativi al 2026 e vanno verificati col tuo consulente.
A4: INPUT DEL CASO
A5: (1) Anno di nascita di Roberta | B5: 1979
A6: (2) Eta' oggi (2026) | B6: 47
A7: (3) Accumulo — primo anno / ultimo anno | B7: 2011 | C7: 2026
A8: (4) Versamento annuo, euro reali costanti | B8: 6500
A9: (5) Vendita dell'appartamento — netto incassato / anno | B9: 240000 | C9: 2018
A10: (6) Spesa netta annua, DI CASSA | B10: 19800
A11: (7) Orizzonte — eta' finale | B11: 92
A12: (8) Pensione netta annua / dal quale anno del piano | B12: 11102 | C12: 23
A13: (9) Estremo alto della banda della pensione | B13: 12935
A14: (10) Rendimento reale del portafoglio — menu 2% / 3% / 4% | B14: 0.03
A15: (11) Anni di spesa nel secchio 1 (N) | B15: 2
A16: (12) Regola di dimensionamento: 1 = N x spesa · 0 = N x fabbisogno netto (Benz) | B16: 1
A17: (13) STATO ABITATIVO: 1 = casa senza costi · 0 = in affitto o con mutuo | B17: 1
A18: (14) Peso dell'affitto figurativo usato nel confronto ISTAT (0 = calcolato dal foglio 2) | B18: 0
A19: (15) Netto annuo da lavoro durante l'accumulo / lordo di carriera | B19: 22215.65 | C19: 28000
A20: (16) Identita' di Kitces — convenzione del prelievo: 1 = fine anno · 0 = inizio anno | B20: 1
A21: (17) Sovraccosto di TER dell'ETF multi-asset (punti percentuali) | B21: 0.001
A22: (18) Strumento del secchio 1: 1 = conto deposito · 2 = ETF monetario · 3 = BOT 12 mesi | B22: 1
A24: DERIVATI — non si toccano
A26: Orizzonte in anni | B26: ='1-Input'!$B$11-'1-Input'!$B$6 -> 45
A27: Rendimento reale della liquidita' scelta (al LORDO del bollo) | B27: =ROUND(IF('1-Input'!$B$22=3,'3-Liquidita'!$F$7,IF('1-Input'!$B$22=2,'3-Liquidita'!$F$11,'3-Liquidita'!$F$9)),4) -> -0.0036
A28: Anni di accumulo | B28: ='1-Input'!$C$7-'1-Input'!$B$7+1 -> 16
A29: Anni di capitalizzazione del netto della vendita | B29: ='1-Input'!$C$7-'1-Input'!$C$9 -> 8
A30: Anno di decorrenza della pensione (68 anni e 10 mesi — proiezione RGS) | B30: ='1-Input'!$B$5+'1-Input'!$B$6+'1-Input'!$C$12-1 -> 2048
A32: CONVENZIONE DICHIARATA — il prelievo e' a INIZIO anno, il secchio 1 si ricarica dal portafoglio PRIMA della crescita dell'anno, il bollo si paga a FINE anno sul patrimonio dopo la crescita e grava prima sul portafoglio e poi sul secchio. La base di costo si scorpora INSIEME al patrimonio quando si crea il secchio 1 (quinto errore di famiglia): base del portafoglio = base totale x portafoglio / patrimonio.
A33: UNA SOLA REGOLA DI REFILL in tutto il file: ogni anno il secchio 1 viene riportato al suo target vendendo dal portafoglio, per quanto il portafoglio consente. La regola riempie e non svuota mai: quando il target scende (perche' arriva la pensione), l'eccedenza resta nel secchio. Il foglio 10 misura quanto vale quella scelta.
A34: REFRESH GENNAIO 2027 — i tassi del foglio P sono una fotografia di settembre 2026. GATE CHIUSO IL 9 SETTEMBRE 2026: l'asta BOT 12 mesi del 09/09/2026 (ISIN IT0005730681, prezzo fiscale 97,080, rendimento medio ponderato 2,967%) e' stata pubblicata e sostituisce in P-Parametri quella del 12/08/2026. Il prossimo riallineamento e' il refresh di gennaio 2027.
A35: FISCALITA' — 26% sul capital gain, 12,5% sui titoli di Stato, 0,20% di bollo sono le aliquote in vigore nel 2026: una FOTOGRAFIA, non una regola eterna. Il D.Lgs. 117/2026 ricodifica il TUIR con effetti dal 1° gennaio 2027 (art. 377); e' una ricodificazione, non una soppressione, ma i rinvii per numero d'articolo cambiano.

Sheet P-Parametri
A1: Parametri normativi e di fonte
A2: Strumento informativo / divulgativo. NON è consulenza finanziaria. I valori sono indicativi al 2026 e vanno verificati col tuo consulente.
A3: Le uniche costanti del modello, oltre agli input, stanno qui. Tutti gli altri fogli le referenziano.
A5: Fiscalita' finanziaria 2026 — fotografia, non regime stabile
A6: Capital gain (redditi di capitale e diversi da ETF e azioni) | B6: 0.26
A7: Titoli di Stato ed equiparati | B7: 0.125
A8: Bollo su prodotti finanziari e depositi (art. 9 c. 4) | B8: 0.002
A9: Bollo fisso su conto corrente e libretto / soglia di esenzione (art. 9 c. 3) | B9: 34.2 | C9: 5000
A10: Inflazione attesa (canone del canale) | B10: 0.02
A12: Tassi della liquidita' — settembre 2026
A13: €STR (BCE, 7/9/2026) / TER dell'ETF monetario | B13: 0.02188 | C13: 0.001
A14: Conto deposito famiglie: fino a 1 anno / oltre 1 anno (Banca d'Italia tav. 2.7) | B14: 0.0222 | C14: 0.0269
A15: BOT 12 mesi — prezzo fiscale d'asta / rendimento medio ponderato / giorni | B15: 97.08 | C15: 0.02967 | D15: 365 | E15: MEF, «Risultati Asta: BOT 12 MESI» del 09/09/2026 — ISIN IT0005730681, durata 365 gg, emissione 14/9/2026, scadenza 14/9/2027, prezzo medio ponderato e prezzo fiscale 97,080, rendimento medio ponderato 2,967% (semplice lordo, base annua 360 gg), rendimento lordo composto 2,966%, copertura 1,39. Gate di produzione CHIUSO il 9 settembre 2026: sostituisce l'asta del 12/08/2026 (IT0005729220, 97,277 / 2,768%).
A16: Buono fruttifero postale — rendimento nei primi quattro anni | B16: 0.0075
A17: BTP a medio termine — rendimento a scadenza lordo (paniere MOT 9/9/2026) | B17: 0.0381 | E17: Media dei quattro BTP del paniere di canale, prezzi Borsa Italiana-MOT del 9/9/2026: IT0003535157 5,00% 1/8/2034 a 106,58 (YTM 4,056%); IT0003256820 5,75% 1/2/2033 a 110,69 (3,879%); IT0001444378 6,00% 1/5/2031 a 110,19 (3,629%); IT0005595803 3,45% 15/7/2031 a 99,16 (3,672%). Media 3,8088%, arrotondata a 3,81%. YTM ricalcolati con date di scadenza esatte, regolamento 9/9/2026, rateo ACT/ACT incluso e capitalizzazione annuale su base 365 (regola di canale). Gate di produzione CHIUSO il 9 settembre 2026: sostituisce il paniere del 14/8/2026 (media 3,49%).
A18: Conto corrente — rendimento reale netto dichiarato (bollo fisso su giacenza media) | B18: -0.0204
A20: ISTAT — spese per consumi delle famiglie, anno 2024 (7/10/2025)
A21: Spesa media mensile, totale Italia | B21: 2755.09
A22: Divisione «Abitazione, acqua, elettricita', gas» | B22: 984.42
A23: di cui affitti figurativi | B23: 617.39
A24: Quota della divisione abitazione per le famiglie monocomponente | B24: 0.439
A25: Persona sola fra 35 e 64 anni — spesa media mensile | B25: 2096.96
A26: Ipotesi alternativa: rapporto affitti figurativi / divisione per i single | B26: 0.55
A28: Mercati — ipotesi dichiarate degli scenari illustrativi
A29: Azionario negli anni normali / obbligazionario (reale) | B29: 0.068512 | C29: 0.005
A30: I due crolli — primo / secondo | B30: -0.35 | C30: -0.2
A31: Allocazione di Kitces — azioni / obbligazioni / liquidita' | B31: 0.6 | C31: 0.3 | D31: 0.1
A33: Pfeiffer-Salter-Evensky — le commissioni evitate
A34: Commissioni col secchio / senza secchio / orizzonte (dollari, 30 anni) | B34: 2580 | C34: 21600 | D34: 30
A35: Costo unitario dell'eseguito nello studio (dollari) | B35: 30
A36: Eseguiti evitati all'anno = (senza - col secchio) / anni / costo unitario | B36: =(C34-B34)/D34/B35 -> 21.133333
A38: Estrada 2019 — 21 paesi, 115 anni, 86 finestre trentennali
A39: Portafoglio 100% azionario — tasso di fallimento medio | B39: 0.278
A40: Regole a secchi BR-1 / BR-2 / BR-3 | B40: 0.316 | C40: 0.316 | D40: 0.301
A41: Titoli a breve italiani dal 1900 — reale geometrico / minimo annuo | B41: -0.035 | C41: -0.766
A43: Sweep delle 1.980 permutazioni — RISULTATI DICHIARATI, non ricalcolati qui
A44: Permutazioni dei due crolli (45 x 44 coppie ordinate) | B44: 1980
A45: Braccio A, total return — fallimenti / patrimonio medio | B45: 0.117 | C45: 249674
A46: Braccio B, secchio dentro — 1 anno / 5 anni | B46: 0.137 | C46: 0.191
A47: Braccio D, secchio aggiunto — 1 anno / 5 anni / patrimonio medio a 5 anni | B47: 0.197 | C47: 0.721 | D47: 24923
A49: Kitces — il pensionato del 1966 (dollari)
A50: Portafoglio a fine anno / prelievo / dopo il prelievo | B50: 958443.8 | C50: 40000 | D50: =B50-C50 -> 918443.8
A51: Ribilanciato a 60/30/10 — azioni / obbligazioni / liquidita' | B51: =D50*B31 -> 551066.28 | C51: =D50*C31 -> 275533.14 | D51: =D50*D31 -> 91844.38
A53: Altri riferimenti del video
A54: Nikkei — anni per rifare il massimo del 1989 | B54: 34.1667
A55: Divario di comportamento — chi non ribilancia (punti/anno) | B55: 0.012
A56: Divario di comportamento — prodotti che ribilanciano da soli (min / max) | B56: 0.001 | C56: 0.008
A57: Vendita di ETF in perdita — minusvalenza / credito d'imposta / riporto (anni) | B57: 14110 | C57: =B57*B6 -> 3668.6 | D57: 4
A59: I risultati dello sweep delle 1.980 permutazioni (righe 44-47) sono DICHIARATI: sono l'esito del motore della catena adversarial, riprodotto in modo indipendente dal Critico su tredici righe su tredici per i bracci A, B e D. Questo foglio di calcolo NON li ricalcola — 1.980 traiettorie da 45 anni non stanno in una cartella scaricabile. Quello che il foglio 7 ricalcola all'euro e' la TRACCIA DETERMINISTICA, cioe' la singola permutazione peggiore (i due crolli nei primi due anni).
A60: Il braccio E (secchio piu' regola tattica) e' RITIRATO COME PROVA: nel sweep e' irriproducibile. La traccia deterministica del foglio 7 e' invece riprodotta all'euro ed e' tenuta come illustrazione dichiarata, non come dimostrazione.
A61: Il rendimento reale del conto corrente (-2,04%) e' un valore dichiarato: il bollo del conto corrente e' un importo FISSO di 34,20 € e la sua incidenza percentuale dipende dalla giacenza media, che nel decumulo scende. Non e' derivabile da una singola aliquota, ed e' per questo che sta qui come parametro e non come formula.

Sheet 2-Caso
A1: La scheda-caso: da dove vengono i quattrocentotrentanovemila
A2: Strumento informativo / divulgativo. NON è consulenza finanziaria. I valori sono indicativi al 2026 e vanno verificati col tuo consulente.
A4: ACCUMULO E ORIGINE DEL CAPITALE — la latente e' DERIVATA, non postulata
A5: Versamento annuo, euro reali costanti | B5: ='1-Input'!$B$8 -> 6500
A6: Anni di accumulo (2011-2026) | B6: ='1-Input'!$B$28 -> 16
A7: Montante dei versamenti — rendita anticipata al rendimento reale | B7: =B5*(((1+'1-Input'!$B$14)^B6-1)/'1-Input'!$B$14)*(1+'1-Input'!$B$14) -> 134950.32
A8: Base di costo dei versamenti | B8: =B5*B6 -> 104000
A9: Vendita dell'appartamento nel 2018 — netto di mutuo residuo, imposte e spese | B9: ='1-Input'!$B$9 -> 240000
A10: Capitalizzato al rendimento reale fino a oggi | B10: =B9*(1+'1-Input'!$B$14)^'1-Input'!$B$29 -> 304024.82
A11: Base di costo del capitale immobiliare reinvestito | B11: =B9 -> 240000
A12: PATRIMONIO INVESTITO AL 2026 | B12: =B7+B10 -> 438975.14
A13: BASE DI COSTO FISCALE | B13: =B8+B11 -> 344000
A14: PLUSVALENZA LATENTE | B14: =MAX(0,(B12-B13)/B12) -> 0.21635653
A15: Fattore di lordizzazione G = 1 / (1 - capital gain x latente) | B15: =1/(1-'P-Parametri'!$B$6*B14) -> 1.0596057
A16: Aliquota effettiva sulla vendita (capital gain x latente) | B16: ='P-Parametri'!$B$6*B14 -> 0.056252699
A17: Tasso di risparmio implicito sul netto da lavoro | B17: =B5/'1-Input'!$B$19 -> 0.29258653
A18: Di che cosa viveva mentre risparmiava (netto meno versamento) | B18: ='1-Input'!$B$19-B5 -> 15715.65
A19: Salto fra il tenore di vita in accumulo e quello in decumulo | B19: ='1-Input'!$B$10-B18 -> 4084.35
A21: IL VINCOLO ARITMETICO. Tre parametri — quando comincia l'accumulo, quanto Roberta versa e a quanto ha venduto — sono scelti insieme per far tornare un numero solo, il patrimonio di oggi. E' una CALIBRAZIONE dichiarata, non una previsione. Quello che il conto deve dimostrare non e' che i numeri tornano, ma che il tasso di risparmio che ne esce e' possibile. Gli ingressi sono tondi e dichiarati (16 anni, 6.500 euro, 240.000 euro, 8 anni), le uscite sono frastagliate: non c'e' nessun sistema da risolvere.
A22: LA BIOGRAFIA CHE RENDE POSSIBILE IL CONTO. Appartamento comprato nel 2004 con un mutuo, estinto alla vendita del 2018; dal 2011 Roberta vive nella casa di famiglia e il vecchio appartamento e' affittato. Dal 2011 al 2018 il canone incassato e la rata ancora pagata sono trattati come PARTITA DI GIRO: si compensano, e il conto qui sopra non li porta. I 240.000 euro sono NETTI di mutuo residuo, imposte e spese. La plusvalenza immobiliare non e' tassata: l'immobile e' posseduto da piu' di cinque anni.
A24: STATO ABITATIVO E DENOMINATORE ISTAT — il quarto errore di famiglia
A25: Stato abitativo dichiarato | B25: =IF('1-Input'!$B$17=1,"casa senza costi abitativi","in affitto o con mutuo") -> casa senza costi abitativi
A26: Persona sola 35-64 anni — spesa media mensile ISTAT 2024 (affitto figurativo INCLUSO) | B26: ='P-Parametri'!$B$25 -> 2096.96
A27: Affitti figurativi in quota della spesa totale (media nazionale) | B27: ='P-Parametri'!$B$23/'P-Parametri'!$B$21 -> 0.22409068
A28: Affitti figurativi in quota della divisione abitazione | B28: ='P-Parametri'!$B$23/'P-Parametri'!$B$22 -> 0.62716117
A30: Ipotesi sul peso dell'affitto figurativo | B30: Peso | C30: Spesa di CASSA equivalente (mese)
A31: Quota nazionale su tutte le famiglie (limite alto della cassa) | B31: ='P-Parametri'!$B$23/'P-Parametri'!$B$21 -> 0.22409068 | C31: =B26*(1-B31) -> 1627.0508
A32: Quota CALCOLATA per la monocomponente (43,9% per 62,72%) | B32: ='P-Parametri'!$B$24*B28 -> 0.27532375 | C32: =B26*(1-B32) -> 1519.6171
A33: Se per i single il rapporto scendesse al 55% della divisione | B33: ='P-Parametri'!$B$24*'P-Parametri'!$B$26 -> 0.24145 | C33: =B26*(1-B33) -> 1590.649
A35: FORBICE DELLA SPESA DI CASSA — minimo / massimo (euro/mese) | B35: =MIN(C31:C33) -> 1519.6171 | C35: =MAX(C31:C33) -> 1627.0508
A36: Peso effettivamente usato nel confronto (0 nell'input = quello calcolato) | B36: =IF('1-Input'!$B$18=0,B32,'1-Input'!$B$18) -> 0.27532375
A37: DENOMINATORE OMOGENEO alla spesa di Roberta | B37: =IF('1-Input'!$B$17=1,B26*(1-B36),B26) -> 1519.6171
A38: Spesa di cassa di Roberta (euro/mese) | B38: ='1-Input'!$B$10/12 -> 1650
A39: Scarto contro il denominatore omogeneo | B39: =B38-B37 -> 130.3829 | C39: =B38/B37-1 -> 0.085799837
A40: VERDETTO | B40: =IF('1-Input'!$B$17<>1,IF(B38>B37,"SOPRA la media ISTAT piena","SOTTO la media ISTAT piena"),IF(B38>MAX(C31:C33),"SOPRA la forbice della media di cassa",IF(B38<MIN(C31:C33),"SOTTO la forbice della media di cassa","DENTRO la forbice della media di cassa"))) -> SOPRA la forbice della media di cassa
A42: PERCHE' LO STATO ABITATIVO E' UN INPUT E NON UN DETTAGLIO. L'aggregato ISTAT «spesa media mensile per consumi» include gli AFFITTI FIGURATIVI, che non sono un esborso di cassa: nel 2024 valgono 617,39 euro su 2.755,09, cioe' il 22,41% della spesa e il 62,72% della divisione abitazione. Confrontare quella media con un prelievo, con una pensione o con un fabbisogno e' omogeneo SOLO se si dichiara lo stato abitativo. Metti 0 nell'input (13) e il confronto passa sul dato pieno: e' quello giusto per chi un affitto lo paga davvero.
A43: Con lo stato abitativo dichiarato, Roberta a 1.650 euro al mese sta SOPRA la media di cassa di chi vive nella sua stessa condizione, non sotto. E' il numero scomodo, e si pubblica: il 29,3% di risparmio non viene dalla frugalita', viene dal fatto che dal 2011 non paga la casa.
A45: LE TRE SCALE DEL TASSO DI PRELIEVO — anno 1, senza secchio
A46: Scala | B46: Importo | C46: Sul patrimonio
A47: Cassa — quello che Roberta spende | B47: ='1-Input'!$B$10 -> 19800 | C47: =B47/B12 -> 0.04510506
A48: Omogeneo — vendita lorda, confrontabile col 4% di Trinity | B48: =B47*B15 -> 20980.192 | C48: =B48/B12 -> 0.047793578
A49: Col bollo — vendita lorda piu' il bollo dell'anno | B49: =B48+'P-Parametri'!$B$8*B12 -> 21858.143 | C49: =B49/B12 -> 0.049793578
A51: IL COSTO DELL'ORDINE SBAGLIATO — vendere ETF invece di liquidita'
A52: Imposta pagata sul prelievo se si liquida l'ETF (spesa per aliquota effettiva) | B52: =B47*B16 -> 1113.8034
A53: Capitalizzata sull'orizzonte al rendimento reale (rendita anticipata) | B53: =B52*(((1+'1-Input'!$B$14)^'1-Input'!$B$26-1)/'1-Input'!$B$14)*(1+'1-Input'!$B$14) -> 106369.85
A54: Il confronto e' fra PAGARE ADESSO e PAGARE DOPO, non fra pagare e non pagare: la liquidita' e' denaro gia' tassato, il titolo di Stato paga il 12,5%, l'ETF il 26% sulla plusvalenza. Chi porta a casa lo zero di Kitces e liquida la posizione piu' comoda liquida quasi sempre l'ETF ad accumulazione, che e' la sacca con l'aliquota piu' alta.

Sheet 3-Liquidita
A1: La liquidita' italiana: quanto rende davvero e quanto copre davvero
A2: Strumento informativo / divulgativo. NON è consulenza finanziaria. I valori sono indicativi al 2026 e vanno verificati col tuo consulente.
A4: I SEI STRUMENTI DEL SECCHIO 1 — netti d'imposta, di bollo e di inflazione
A6: Strumento | B6: Lordo | C6: Aliquota | D6: Netto d'imposta | E6: Bollo | F6: Reale al LORDO del bollo | G6: Reale netto di tutto | H6: Differenziale contro il portafoglio
A7: BOT 12 mesi (asta MEF 09/09/2026, ISIN IT0005730681) | B7: ='P-Parametri'!$C$15 -> 0.02967 | C7: ='P-Parametri'!$B$7 -> 0.125 | D7: =((100-'P-Parametri'!$B$7*(100-'P-Parametri'!$B$15))/'P-Parametri'!$B$15-1)*365/'P-Parametri'!$D$15 -> 0.0263185 | E7: ='P-Parametri'!$B$8 -> 0.002 | F7: =D7-'P-Parametri'!$B$10 -> 0.0063185002 | G7: =D7-E7-'P-Parametri'!$B$10 -> 0.0043185002 | H7: ='1-Input'!$B$14-F7 -> 0.0236815
A8: Conto deposito famiglie, oltre 1 anno | B8: ='P-Parametri'!$C$14 -> 0.0269 | C8: ='P-Parametri'!$B$6 -> 0.26 | D8: =B8*(1-C8) -> 0.019906 | E8: ='P-Parametri'!$B$8 -> 0.002 | F8: =D8-'P-Parametri'!$B$10 -> -9.4e-05 | G8: =D8-E8-'P-Parametri'!$B$10 -> -0.002094 | H8: ='1-Input'!$B$14-F8 -> 0.030094
A9: Conto deposito famiglie, fino a 1 anno | B9: ='P-Parametri'!$B$14 -> 0.0222 | C9: ='P-Parametri'!$B$6 -> 0.26 | D9: =B9*(1-C9) -> 0.016428 | E9: ='P-Parametri'!$B$8 -> 0.002 | F9: =D9-'P-Parametri'!$B$10 -> -0.003572 | G9: =D9-E9-'P-Parametri'!$B$10 -> -0.005572 | H9: ='1-Input'!$B$14-F9 -> 0.033572
A10: Buono fruttifero postale, primi quattro anni | B10: ='P-Parametri'!$B$16 -> 0.0075 | C10: ='P-Parametri'!$B$7 -> 0.125 | D10: =B10*(1-C10) -> 0.0065625 | E10: ='P-Parametri'!$B$8 -> 0.002 | F10: =D10-'P-Parametri'!$B$10 -> -0.0134375 | G10: =D10-E10-'P-Parametri'!$B$10 -> -0.0154375 | H10: ='1-Input'!$B$14-F10 -> 0.0434375
A11: ETF monetario (€STR meno TER) | B11: ='P-Parametri'!$B$13-'P-Parametri'!$C$13 -> 0.02088 | C11: ='P-Parametri'!$B$6 -> 0.26 | D11: =B11*(1-C11) -> 0.0154512 | E11: ='P-Parametri'!$B$8 -> 0.002 | F11: =D11-'P-Parametri'!$B$10 -> -0.0045488 | G11: =D11-E11-'P-Parametri'!$B$10 -> -0.0065488 | H11: ='1-Input'!$B$14-F11 -> 0.0345488
A12: Conto corrente (bollo fisso: valore reale dichiarato) | B12: =0 -> 0 | C12: ='P-Parametri'!$B$6 -> 0.26 | D12: =B12*(1-C12) -> 0 | E12: ='P-Parametri'!$B$9 -> 34.2 | F12: =-'P-Parametri'!$B$10 -> -0.02 | G12: ='P-Parametri'!$B$18 -> -0.0204 | H12: ='1-Input'!$B$14-F12 -> 0.05
A13: BTP a medio termine (paniere MOT 9/9/2026, media di quattro titoli) | B13: ='P-Parametri'!$B$17 -> 0.0381 | C13: ='P-Parametri'!$B$7 -> 0.125 | D13: =B13*(1-C13) -> 0.0333375 | E13: ='P-Parametri'!$B$8 -> 0.002 | F13: =D13-'P-Parametri'!$B$10 -> 0.0133375 | G13: =D13-E13-'P-Parametri'!$B$10 -> 0.0113375 | H13: ='1-Input'!$B$14-F13 -> 0.0166625
A15: IL BOLLO SI ELIDE. Nel differenziale (colonna H) i rendimenti sono al LORDO del bollo su ENTRAMBE le gambe, perche' lo 0,20% colpisce identico il portafoglio e la liquidita'. Nel motore del caso il bollo e' addebitato a parte, ogni anno, su tutto il patrimonio: usare li' il rendimento gia' netto di bollo sarebbe un DOPPIO CONTEGGIO (primo errore di famiglia) e gonfierebbe il costo del secchio di circa un decimo.
A16: Il netto del BOT non e' il rendimento moltiplicato per 0,875: e' la ritenuta del 12,5% sullo scarto d'emissione, cioe' su 100 meno il prezzo d'asta, riportata al prezzo pagato e annualizzata sui giorni effettivi. E' per questo che la colonna D e' una formula sul prezzo e non sul rendimento. FONTE AGGIORNATA: asta MEF del 09/09/2026, ISIN IT0005730681, prezzo fiscale 97,080 su 365 giorni, rendimento medio ponderato 2,967% (base annua 360 gg). Gate di produzione CHIUSO il 9 settembre 2026.
A18: LA COPERTURA VERA — otto anni di spesa, e dove li tieni conta
A19: Anni di spesa messi da parte (sulla carta) | B19: 8
A20: Montante corrispondente | B20: =B19*'1-Input'!$B$10 -> 158400
A21: Dove stanno gli otto anni | B21: Rendimento reale netto di tutto | C21: Anni di spesa effettivamente coperti
A22: Conto corrente | B22: =G12 -> -0.0204 | C22: =IF(ABS(B22)<0.0000001,$B$19,-LN(1-$B$19*B22/(1+B22))/LN(1+B22)) -> 7.4762355
A23: ETF monetario | B23: =G11 -> -0.0065488 | C23: =IF(ABS(B23)<0.0000001,$B$19,-LN(1-$B$19*B23/(1+B23))/LN(1+B23)) -> 7.8218597
A24: Conto deposito fino a 1 anno | B24: =G9 -> -0.005572 | C24: =IF(ABS(B24)<0.0000001,$B$19,-LN(1-$B$19*B24/(1+B24))/LN(1+B24)) -> 7.8477859
A25: BOT 12 mesi | B25: =G7 -> 0.0043185002 | C25: =IF(ABS(B25)<0.0000001,$B$19,-LN(1-$B$19*B25/(1+B25))/LN(1+B25)) -> 8.1233219
A26: BTP a medio termine | B26: =G13 -> 0.0113375 | C26: =IF(ABS(B26)<0.0000001,$B$19,-LN(1-$B$19*B26/(1+B26))/LN(1+B26)) -> 8.334666
A27: FORBICE — peggiore / migliore / differenza in anni | B27: =MIN(C22:C26) -> 7.4762355 | C27: =MAX(C22:C26) -> 8.334666 | D27: =C27-B27 -> 0.85843053
A28: FORBICE IN EURO — anni pieni per la spesa annua | B28: =D27*'1-Input'!$B$10 -> 16996.925
A29: FORBICE IN EURO — con gli anni arrotondati al centesimo, come vanno a schermo | B29: =(ROUND(C27,2)-ROUND(B27,2))*'1-Input'!$B$10 -> 16830
A30: Il numero della forbice in euro dipende da quanto si arrotondano gli anni PRIMA di moltiplicare: con gli anni pieni e' la riga 28, con gli anni arrotondati al centesimo (7,48 e 8,33 dopo la rilevazione MOT del 9/9/2026) e' la riga 29. La riga 28 e' il motore; la riga 29 e' il numero che si ottiene dai due valori pubblicati. Le due letture differiscono di alcune centinaia di euro e la differenza va dichiarata, non nascosta.
A32: IL BOLLO SULLA NORMA
A33: Conto corrente e libretto — imposta fissa / esenzione sotto la giacenza media | B33: ='P-Parametri'!$B$9 -> 34.2 | C33: ='P-Parametri'!$C$9 -> 5000
A34: Conto deposito e dossier titoli — aliquota annua | B34: ='P-Parametri'!$B$8 -> 0.002
A35: PAREGGIO fra il fisso e la percentuale | B35: ='P-Parametri'!$B$9/'P-Parametri'!$B$8 -> 17100
A36: Bollo annuo sul secchio 1 di Roberta | B36: ='P-Parametri'!$B$8*'1-Input'!$B$15*'1-Input'!$B$10 -> 79.2
A38: L'ATTRITO CHE NESSUNO CONTA — il 26% sugli interessi, ogni anno
A39: Interessi lordi annui del secchio 1 (conto deposito fino a 1 anno) | B39: ='1-Input'!$B$15*'1-Input'!$B$10*'P-Parametri'!$B$14 -> 879.12
A40: Imposta annua sugli interessi | B40: =B39*'P-Parametri'!$B$6 -> 228.5712
A41: Capitalizzata sull'orizzonte al rendimento reale (rendita anticipata) | B41: =B40*(((1+'1-Input'!$B$14)^'1-Input'!$B$26-1)/'1-Input'!$B$14)*(1+'1-Input'!$B$14) -> 21828.883
A43: LA SOGLIA DI EVENSKY — quanto dovrebbe costare un eseguito
A44: Commissioni nello studio: col secchio / senza / orizzonte (dollari) | B44: ='P-Parametri'!$B$34 -> 2580 | C44: ='P-Parametri'!$C$34 -> 21600 | D44: ='P-Parametri'!$D$34 -> 30
A45: Eseguiti evitati all'anno | B45: ='P-Parametri'!$B$36 -> 21.133333
A46: Costo annuo del secchio, PER ANNO di spesa messo in liquidita' | B46: =1*'1-Input'!$B$10*H9 -> 664.7256
A47: COMMISSIONE DI PAREGGIO PER ESEGUITO | B47: =B46/B45 -> 31.453893
A48: Trentuno euro a eseguito e' un ordine di grandezza sopra quello che costa vendere un ETF in Italia nel 2026, e su molte piattaforme e' infinite volte tanto. Il canale che rende positivo il risultato americano, in Italia, resta chiuso.

Sheet 4-Griglia
A1: La griglia madre: quanto costa il secchio, per orizzonte, taglia e strumento
A2: Strumento informativo / divulgativo. NON è consulenza finanziaria. I valori sono indicativi al 2026 e vanno verificati col tuo consulente.
A3: PARAMETRI IN TESTA: patrimonio di un milione, euro reali, portafoglio al rendimento reale dell'input (10), secchio 1 = N per la spesa annua, prelievo a inizio anno dal secchio, refill annuale dal portafoglio finche' il portafoglio lo consente. NESSUNA IMPOSTA E NESSUN BOLLO in questa griglia: e' fatta per essere ricostruibile da chi guarda con cinque colonne di foglio di calcolo. Il costo VERO del secchio e' piu' alto, perche' l'imposta sugli interessi si paga ogni anno mentre quella sulla plusvalenza si paga alla vendita: il conto completo e' nel foglio 5.
A5: Patrimonio della griglia | B5: 1000000
A6: Rendimento reale del portafoglio | B6: ='1-Input'!$B$14 -> 0.03
A7: Liquidita' — conto deposito fino a 1 anno / BOT 12 mesi (reale, lordo bollo) | B7: =ROUND('3-Liquidita'!$F$9,4) -> -0.0036 | C7: =ROUND('3-Liquidita'!$F$7,4) -> 0.0063
A9: IL COSTO IN PUNTI DI TASSO DI PRELIEVO
A10: Orizzonte e strumento | B10: N = 1 | C10: N = 2 | D10: N = 3 | E10: N = 5
A11: 20 anni — conto deposito | B11: =($B$165-$B$212)/$B$5*100 -> 0.19871671 | C11: =($B$165-$B$259)/$B$5*100 -> 0.37848237 | D11: =($B$165-$B$306)/$B$5*100 -> 0.5413069 | E11: =($B$165-$B$353)/$B$5*100 -> 0.8226666
A12: 20 anni — BOT 12 mesi | B12: =($B$400-$B$447)/$B$5*100 -> 0.14140074 | C12: =($B$400-$B$494)/$B$5*100 -> 0.27145238 | D12: =($B$400-$B$541)/$B$5*100 -> 0.390973 | E12: =($B$400-$B$588)/$B$5*100 -> 0.60116229
A13: 30 anni — conto deposito | B13: =($B$635-$B$682)/$B$5*100 -> 0.15329235 | C13: =($B$635-$B$729)/$B$5*100 -> 0.29429983 | D13: =($B$635-$B$776)/$B$5*100 -> 0.42427087 | E13: =($B$635-$B$823)/$B$5*100 -> 0.65526362
A14: 30 anni — BOT 12 mesi | B14: =($B$870-$B$917)/$B$5*100 -> 0.10910609 | C14: =($B$870-$B$964)/$B$5*100 -> 0.21121928 | D14: =($B$870-$B$1011)/$B$5*100 -> 0.30683681 | E14: =($B$870-$B$1058)/$B$5*100 -> 0.480306
A15: 40 anni — conto deposito | B15: =($B$1105-$B$1152)/$B$5*100 -> 0.13098386 | C15: =($B$1105-$B$1199)/$B$5*100 -> 0.2523985 | D15: =($B$1105-$B$1246)/$B$5*100 -> 0.36518301 | E15: =($B$1105-$B$1293)/$B$5*100 -> 0.56802685
A16: 40 anni — BOT 12 mesi | B16: =($B$1340-$B$1387)/$B$5*100 -> 0.093239294 | C16: =($B$1340-$B$1434)/$B$5*100 -> 0.18120477 | D16: =($B$1340-$B$1481)/$B$5*100 -> 0.26426375 | E16: =($B$1340-$B$1528)/$B$5*100 -> 0.41695144
A18: LO STESSO COSTO IN PERCENTUALE DELLA SPESA — la lettura che si applica a se'
A19: Orizzonte e strumento | B19: N = 1 | C19: N = 2 | D19: N = 3 | E19: N = 5
A20: 20 anni — conto deposito | B20: =($B$165-$B$212)/$B$165 -> 0.030450949 | C20: =($B$165-$B$259)/$B$165 -> 0.057997879 | D20: =($B$165-$B$306)/$B$165 -> 0.082948782 | E20: =($B$165-$B$353)/$B$165 -> 0.12606378
A21: 20 anni — BOT 12 mesi | B21: =($B$400-$B$447)/$B$400 -> 0.021667965 | C21: =($B$400-$B$494)/$B$400 -> 0.041596817 | D21: =($B$400-$B$541)/$B$400 -> 0.059911917 | E21: =($B$400-$B$588)/$B$400 -> 0.092120901
A22: 30 anni — conto deposito | B22: =($B$635-$B$682)/$B$635 -> 0.030947357 | C22: =($B$635-$B$729)/$B$635 -> 0.059414588 | D22: =($B$635-$B$776)/$B$635 -> 0.085653731 | E22: =($B$635-$B$823)/$B$635 -> 0.1322876
A23: 30 anni — BOT 12 mesi | B23: =($B$870-$B$917)/$B$870 -> 0.022026834 | C23: =($B$870-$B$964)/$B$870 -> 0.042641908 | D23: =($B$870-$B$1011)/$B$870 -> 0.06194561 | E23: =($B$870-$B$1058)/$B$870 -> 0.096966358
A24: 40 anni — conto deposito | B24: =($B$1105-$B$1152)/$B$1105 -> 0.03118492 | C24: =($B$1105-$B$1199)/$B$1105 -> 0.060091578 | D24: =($B$1105-$B$1246)/$B$1105 -> 0.086943556 | E24: =($B$1105-$B$1293)/$B$1105 -> 0.13523705
A25: 40 anni — BOT 12 mesi | B25: =($B$1340-$B$1387)/$B$1340 -> 0.022198612 | C25: =($B$1340-$B$1434)/$B$1340 -> 0.043141622 | D25: =($B$1340-$B$1481)/$B$1340 -> 0.062916483 | E25: =($B$1340-$B$1528)/$B$1340 -> 0.099268697
A26: IL QUARTO DI COSTO CHE DIPENDE SOLO DALLO STRUMENTO (30 anni, N = 2) | B26: =($B$635-$B$729)/$B$635 -> 0.059414588 | C26: =($B$870-$B$964)/$B$870 -> 0.042641908 | D26: =1-C26/B26 -> 0.28229902
A28: IL COSTO NON E' ADDITIVO — costo marginale del singolo anno (30 anni, conto deposito)
A29: Anno di liquidita' aggiunto | B29: 1° | C29: 2° | D29: 3° | E29: 4° | F29: 5°
A30: Costo cumulato in % della spesa | B30: =($B$635-$B$682)/$B$635 -> 0.030947357 | C30: =($B$635-$B$729)/$B$635 -> 0.059414588 | D30: =($B$635-$B$776)/$B$635 -> 0.085653731 | E30: =($B$635-$B$2945)/$B$635 -> 0.10988203 | F30: =($B$635-$B$823)/$B$635 -> 0.1322876
A31: Costo marginale in % della spesa | B31: =B30 -> 0.030947357 | C31: =C30-B30 -> 0.028467231 | D31: =D30-C30 -> 0.026239143 | E31: =E30-D30 -> 0.024228296 | F31: =F30-E30 -> 0.022405571
A32: Cinque anni non costano cinque volte il primo: il costo marginale decresce, perche' ogni anno aggiunto di liquidita' sostituisce una parte di portafoglio che avrebbe avuto meno tempo per lavorare.
A34: LO STESSO COSTO IN EURO CUMULATI — gap di patrimonio a spesa uguale
A35: Orizzonte | B35: N = 1 | C35: N = 2 | D35: N = 3 | E35: N = 5
A36: 30 anni | B36: =$B$1578 -> 74999.76 | C36: =$B$1624 -> 143539.79 | D36: =$B$1670 -> 205995.38 | E36: =$B$1716 -> 314079.38
A37: 40 anni | B37: =$B$1762 -> 101591.26 | C37: =$B$1808 -> 195249.37 | D37: =$B$1854 -> 281434.35 | E37: =$B$1900 -> 432952.21
A38: Il gap e' misurato a SPESA UGUALE: si tiene la spesa che il portafoglio senza secchio sostiene per l'intero orizzonte e si guarda quanto manca all'arrivo con il secchio. E' la stessa cosa del costo in punti, letta in euro invece che in tasso.
A40: GLI ANNI DI AUTONOMIA — a spesa fissa, quanto dura il capitale
A41: Orizzonte | B41: N = 0 | C41: N = 1 | D41: N = 2 | E41: N = 3 | F41: N = 5
A42: 20 anni | B42: =$B$1970 -> 20 | C42: =$B$2036 -> 19 | D42: =$B$2102 -> 18 | E42: =$B$2168 -> 17 | F42: =$B$2234 -> 16
A43: 30 anni | B43: =$B$2300 -> 30 | C43: =$B$2366 -> 28 | D43: =$B$2432 -> 27 | E43: =$B$2498 -> 26 | F43: =$B$2564 -> 24
A44: 40 anni | B44: =$B$2630 -> 40 | C44: =$B$2696 -> 37 | D44: =$B$2762 -> 35 | E44: =$B$2828 -> 33 | F44: =$B$2894 -> 31
A120: GRIGLIA — orizzonte 20 anni · conto deposito · N = 0
B121: =0.03*$B$5 -> 30000 | E121: =0.075*$B$5 -> 75000 | H121: =IFERROR(E121-E164*(E121-B121)/(E164-B164),E121) -> 65257.969 | K121: =IFERROR(H121-H164*(H121-E121)/(H164-E164),H121) -> 65257.969 | N121: =IFERROR(K121-K164*(K121-H121)/(K164-H164),K121) -> 65257.969 | Q121: =IFERROR(N121-N164*(N121-K121)/(N164-K164),N121) -> 65257.969
A122: anno | B122: lordo venduto | C122: secchio 1 | D122: portafoglio | E122: lordo venduto | F122: secchio 1 | G122: portafoglio | H122: lordo venduto | I122: secchio 1 | J122: portafoglio | K122: lordo venduto | L122: secchio 1 | M122: portafoglio | N122: lordo venduto | O122: secchio 1 | P122: portafoglio | Q122: lordo venduto | R122: secchio 1 | S122: portafoglio
A123: 0 | C123: =MIN(0*B121,$B$5) -> 0 | D123: =$B$5-C123 -> 1000000 | F123: =MIN(0*E121,$B$5) -> 0 | G123: =$B$5-F123 -> 1000000 | I123: =MIN(0*H121,$B$5) -> 0 | J123: =$B$5-I123 -> 1000000 | L123: =MIN(0*K121,$B$5) -> 0 | M123: =$B$5-L123 -> 1000000 | O123: =MIN(0*N121,$B$5) -> 0 | P123: =$B$5-O123 -> 1000000 | R123: =MIN(0*Q121,$B$5) -> 0 | S123: =$B$5-R123 -> 1000000
A124: =1 -> 1 | B124: =IF($A124>20,0,(B121-MIN(MAX(C123,0),B121))+MIN(MAX(0,D123-(B121-MIN(MAX(C123,0),B121))),MAX(0,0*B121-(C123-MIN(MAX(C123,0),B121))))) -> 30000 | C124: =IF($A124>20,C123,(C123-B121+B124)*(1+$B$7)) -> 0 | D124: =IF($A124>20,D123,(D123-B124)*(1+$B$6)) -> 999100 | E124: =IF($A124>20,0,(E121-MIN(MAX(F123,0),E121))+MIN(MAX(0,G123-(E121-MIN(MAX(F123,0),E121))),MAX(0,0*E121-(F123-MIN(MAX(F123,0),E121))))) -> 75000 | F124: =IF($A124>20,F123,(F123-E121+E124)*(1+$B$7)) -> 0 | G124: =IF($A124>20,G123,(G123-E124)*(1+$B$6)) -> 952750 | H124: =IF($A124>20,0,(H121-MIN(MAX(I123,0),H121))+MIN(MAX(0,J123-(H121-MIN(MAX(I123,0),H121))),MAX(0,0*H121-(I123-MIN(MAX(I123,0),H121))))) -> 65257.969 | I124: =IF($A124>20,I123,(I123-H121+H124)*(1+$B$7)) -> 0 | J124: =IF($A124>20,J123,(J123-H124)*(1+$B$6)) -> 962784.29 | K124: =IF($A124>20,0,(K121-MIN(MAX(L123,0),K121))+MIN(MAX(0,M123-(K121-MIN(MAX(L123,0),K121))),MAX(0,0*K121-(L123-MIN(MAX(L123,0),K121))))) -> 65257.969 | L124: =IF($A124>20,L123,(L123-K121+K124)*(1+$B$7)) -> 0 | M124: =IF($A124>20,M123,(M123-K124)*(1+$B$6)) -> 962784.29 | N124: =IF($A124>20,0,(N121-MIN(MAX(O123,0),N121))+MIN(MAX(0,P123-(N121-MIN(MAX(O123,0),N121))),MAX(0,0*N121-(O123-MIN(MAX(O123,0),N121))))) -> 65257.969 | O124: =IF($A124>20,O123,(O123-N121+N124)*(1+$B$7)) -> 0 | P124: =IF($A124>20,P123,(P123-N124)*(1+$B$6)) -> 962784.29 | Q124: =IF($A124>20,0,(Q121-MIN(MAX(R123,0),Q121))+MIN(MAX(0,S123-(Q121-MIN(MAX(R123,0),Q121))),MAX(0,0*Q121-(R123-MIN(MAX(R123,0),Q121))))) -> 65257.969 | R124: =IF($A124>20,R123,(R123-Q121+Q124)*(1+$B$7)) -> 0 | S124: =IF($A124>20,S123,(S123-Q124)*(1+$B$6)) -> 962784.29
A125: =2 -> 2 | B125: =IF($A125>20,0,(B121-MIN(MAX(C124,0),B121))+MIN(MAX(0,D124-(B121-MIN(MAX(C124,0),B121))),MAX(0,0*B121-(C124-MIN(MAX(C124,0),B121))))) -> 30000 | C125: =IF($A125>20,C124,(C124-B121+B125)*(1+$B$7)) -> 0 | D125: =IF($A125>20,D124,(D124-B125)*(1+$B$6)) -> 998173 | E125: =IF($A125>20,0,(E121-MIN(MAX(F124,0),E121))+MIN(MAX(0,G124-(E121-MIN(MAX(F124,0),E121))),MAX(0,0*E121-(F124-MIN(MAX(F124,0),E121))))) -> 75000 | F125: =IF($A125>20,F124,(F124-E121+E125)*(1+$B$7)) -> 0 | G125: =IF($A125>20,G124,(G124-E125)*(1+$B$6)) -> 904082.5 | H125: =IF($A125>20,0,(H121-MIN(MAX(I124,0),H121))+MIN(MAX(0,J124-(H121-MIN(MAX(I124,0),H121))),MAX(0,0*H121-(I124-MIN(MAX(I124,0),H121))))) -> 65257.969 | I125: =IF($A125>20,I124,(I124-H121+H125)*(1+$B$7)) -> 0 | J125: =IF($A125>20,J124,(J124-H125)*(1+$B$6)) -> 924452.11 | K125: =IF($A125>20,0,(K121-MIN(MAX(L124,0),K121))+MIN(MAX(0,M124-(K121-MIN(MAX(L124,0),K121))),MAX(0,0*K121-(L124-MIN(MAX(L124,0),K121))))) -> 65257.969 | L125: =IF($A125>20,L124,(L124-K121+K125)*(1+$B$7)) -> 0 | M125: =IF($A125>20,M124,(M124-K125)*(1+$B$6)) -> 924452.11 | N125: =IF($A125>20,0,(N121-MIN(MAX(O124,0),N121))+MIN(MAX(0,P124-(N121-MIN(MAX(O124,0),N121))),MAX(0,0*N121-(O124-MIN(MAX(O124,0),N121))))) -> 65257.969 | O125: =IF($A125>20,O124,(O124-N121+N125)*(1+$B$7)) -> 0 | P125: =IF($A125>20,P124,(P124-N125)*(1+$B$6)) -> 924452.11 | Q125: =IF($A125>20,0,(Q121-MIN(MAX(R124,0),Q121))+MIN(MAX(0,S124-(Q121-MIN(MAX(R124,0),Q121))),MAX(0,0*Q121-(R124-MIN(MAX(R124,0),Q121))))) -> 65257.969 | R125: =IF($A125>20,R124,(R124-Q121+Q125)*(1+$B$7)) -> 0 | S125: =IF($A125>20,S124,(S124-Q125)*(1+$B$6)) -> 924452.11
A126: =3 -> 3 | B126: =IF($A126>20,0,(B121-MIN(MAX(C125,0),B121))+MIN(MAX(0,D125-(B121-MIN(MAX(C125,0),B121))),MAX(0,0*B121-(C125-MIN(MAX(C125,0),B121))))) -> 30000 | C126: =IF($A126>20,C125,(C125-B121+B126)*(1+$B$7)) -> 0 | D126: =IF($A126>20,D125,(D125-B126)*(1+$B$6)) -> 997218.19 | E126: =IF($A126>20,0,(E121-MIN(MAX(F125,0),E121))+MIN(MAX(0,G125-(E121-MIN(MAX(F125,0),E121))),MAX(0,0*E121-(F125-MIN(MAX(F125,0),E121))))) -> 75000 | F126: =IF($A126>20,F125,(F125-E121+E126)*(1+$B$7)) -> 0 | G126: =IF($A126>20,G125,(G125-E126)*(1+$B$6)) -> 853954.97 | H126: =IF($A126>20,0,(H121-MIN(MAX(I125,0),H121))+MIN(MAX(0,J125-(H121-MIN(MAX(I125,0),H121))),MAX(0,0*H121-(I125-MIN(MAX(I125,0),H121))))) -> 65257.969 | I126: =IF($A126>20,I125,(I125-H121+H126)*(1+$B$7)) -> 0 | J126: =IF($A126>20,J125,(J125-H126)*(1+$B$6)) -> 884969.97 | K126: =IF($A126>20,0,(K121-MIN(MAX(L125,0),K121))+MIN(MAX(0,M125-(K121-MIN(MAX(L125,0),K121))),MAX(0,0*K121-(L125-MIN(MAX(L125,0),K121))))) -> 65257.969 | L126: =IF($A126>20,L125,(L125-K121+K126)*(1+$B$7)) -> 0 | M126: =IF($A126>20,M125,(M125-K126)*(1+$B$6)) -> 884969.97 | N126: =IF($A126>20,0,(N121-MIN(MAX(O125,0),N121))+MIN(MAX(0,P125-(N121-MIN(MAX(O125,0),N121))),MAX(0,0*N121-(O125-MIN(MAX(O125,0),N121))))) -> 65257.969 | O126: =IF($A126>20,O125,(O125-N121+N126)*(1+$B$7)) -> 0 | P126: =IF($A126>20,P125,(P125-N126)*(1+$B$6)) -> 884969.97 | Q126: =IF($A126>20,0,(Q121-MIN(MAX(R125,0),Q121))+MIN(MAX(0,S125-(Q121-MIN(MAX(R125,0),Q121))),MAX(0,0*Q121-(R125-MIN(MAX(R125,0),Q121))))) -> 65257.969 | R126: =IF($A126>20,R125,(R125-Q121+Q126)*(1+$B$7)) -> 0 | S126: =IF($A126>20,S125,(S125-Q126)*(1+$B$6)) -> 884969.97
A127: =4 -> 4 | B127: =IF($A127>20,0,(B121-MIN(MAX(C126,0),B121))+MIN(MAX(0,D126-(B121-MIN(MAX(C126,0),B121))),MAX(0,0*B121-(C126-MIN(MAX(C126,0),B121))))) -> 30000 | C127: =IF($A127>20,C126,(C126-B121+B127)*(1+$B$7)) -> 0 | D127: =IF($A127>20,D126,(D126-B127)*(1+$B$6)) -> 996234.74 | E127: =IF($A127>20,0,(E121-MIN(MAX(F126,0),E121))+MIN(MAX(0,G126-(E121-MIN(MAX(F126,0),E121))),MAX(0,0*E121-(F126-MIN(MAX(F126,0),E121))))) -> 75000 | F127: =IF($A127>20,F126,(F126-E121+E127)*(1+$B$7)) -> 0 | G127: =IF($A127>20,G126,(G126-E127)*(1+$B$6)) -> 802323.62 | H127: =IF($A127>20,0,(H121-MIN(MAX(I126,0),H121))+MIN(MAX(0,J126-(H121-MIN(MAX(I126,0),H121))),MAX(0,0*H121-(I126-MIN(MAX(I126,0),H121))))) -> 65257.969 | I127: =IF($A127>20,I126,(I126-H121+H127)*(1+$B$7)) -> 0 | J127: =IF($A127>20,J126,(J126-H127)*(1+$B$6)) -> 844303.36 | K127: =IF($A127>20,0,(K121-MIN(MAX(L126,0),K121))+MIN(MAX(0,M126-(K121-MIN(MAX(L126,0),K121))),MAX(0,0*K121-(L126-MIN(MAX(L126,0),K121))))) -> 65257.969 | L127: =IF($A127>20,L126,(L126-K121+K127)*(1+$B$7)) -> 0 | M127: =IF($A127>20,M126,(M126-K127)*(1+$B$6)) -> 844303.36 | N127: =IF($A127>20,0,(N121-MIN(MAX(O126,0),N121))+MIN(MAX(0,P126-(N121-MIN(MAX(O126,0),N121))),MAX(0,0*N121-(O126-MIN(MAX(O126,0),N121))))) -> 65257.969 | O127: =IF($A127>20,O126,(O126-N121+N127)*(1+$B$7)) -> 0 | P127: =IF($A127>20,P126,(P126-N127)*(1+$B$6)) -> 844303.36 | Q127: =IF($A127>20,0,(Q121-MIN(MAX(R126,0),Q121))+MIN(MAX(0,S126-(Q121-MIN(MAX(R126,0),Q121))),MAX(0,0*Q121-(R126-MIN(MAX(R126,0),Q121))))) -> 65257.969 | R127: =IF($A127>20,R126,(R126-Q121+Q127)*(1+$B$7)) -> 0 | S127: =IF($A127>20,S126,(S126-Q127)*(1+$B$6)) -> 844303.36
A128: =5 -> 5 | B128: =IF($A128>20,0,(B121-MIN(MAX(C127,0),B121))+MIN(MAX(0,D127-(B121-MIN(MAX(C127,0),B121))),MAX(0,0*B121-(C127-MIN(MAX(C127,0),B121))))) -> 30000 | C128: =IF($A128>20,C127,(C127-B121+B128)*(1+$B$7)) -> 0 | D128: =IF($A128>20,D127,(D127-B128)*(1+$B$6)) -> 995221.78 | E128: =IF($A128>20,0,(E121-MIN(MAX(F127,0),E121))+MIN(MAX(0,G127-(E121-MIN(MAX(F127,0),E121))),MAX(0,0*E121-(F127-MIN(MAX(F127,0),E121))))) -> 75000 | F128: =IF($A128>20,F127,(F127-E121+E128)*(1+$B$7)) -> 0 | G128: =IF($A128>20,G127,(G127-E128)*(1+$B$6)) -> 749143.33 | H128: =IF($A128>20,0,(H121-MIN(MAX(I127,0),H121))+MIN(MAX(0,J127-(H121-MIN(MAX(I127,0),H121))),MAX(0,0*H121-(I127-MIN(MAX(I127,0),H121))))) -> 65257.969 | I128: =IF($A128>20,I127,(I127-H121+H128)*(1+$B$7)) -> 0 | J128: =IF($A128>20,J127,(J127-H128)*(1+$B$6)) -> 802416.75 | K128: =IF($A128>20,0,(K121-MIN(MAX(L127,0),K121))+MIN(MAX(0,M127-(K121-MIN(MAX(L127,0),K121))),MAX(0,0*K121-(L127-MIN(MAX(L127,0),K121))))) -> 65257.969 | L128: =IF($A128>20,L127,(L127-K121+K128)*(1+$B$7)) -> 0 | M128: =IF($A128>20,M127,(M127-K128)*(1+$B$6)) -> 802416.75 | N128: =IF($A128>20,0,(N121-MIN(MAX(O127,0),N121))+MIN(MAX(0,P127-(N121-MIN(MAX(O127,0),N121))),MAX(0,0*N121-(O127-MIN(MAX(O127,0),N121))))) -> 65257.969 | O128: =IF($A128>20,O127,(O127-N121+N128)*(1+$B$7)) -> 0 | P128: =IF($A128>20,P127,(P127-N128)*(1+$B$6)) -> 802416.75 | Q128: =IF($A128>20,0,(Q121-MIN(MAX(R127,0),Q121))+MIN(MAX(0,S127-(Q121-MIN(MAX(R127,0),Q121))),MAX(0,0*Q121-(R127-MIN(MAX(R127,0),Q121))))) -> 65257.969 | R128: =IF($A128>20,R127,(R127-Q121+Q128)*(1+$B$7)) -> 0 | S128: =IF($A128>20,S127,(S127-Q128)*(1+$B$6)) -> 802416.75
A129: =6 -> 6 | B129: =IF($A129>20,0,(B121-MIN(MAX(C128,0),B121))+MIN(MAX(0,D128-(B121-MIN(MAX(C128,0),B121))),MAX(0,0*B121-(C128-MIN(MAX(C128,0),B121))))) -> 30000 | C129: =IF($A129>20,C128,(C128-B121+B129)*(1+$B$7)) -> 0 | D129: =IF($A129>20,D128,(D128-B129)*(1+$B$6)) -> 994178.43 | E129: =IF($A129>20,0,(E121-MIN(MAX(F128,0),E121))+MIN(MAX(0,G128-(E121-MIN(MAX(F128,0),E121))),MAX(0,0*E121-(F128-MIN(MAX(F128,0),E121))))) -> 75000 | F129: =IF($A129>20,F128,(F128-E121+E129)*(1+$B$7)) -> 0 | G129: =IF($A129>20,G128,(G128-E129)*(1+$B$6)) -> 694367.63 | H129: =IF($A129>20,0,(H121-MIN(MAX(I128,0),H121))+MIN(MAX(0,J128-(H121-MIN(MAX(I128,0),H121))),MAX(0,0*H121-(I128-MIN(MAX(I128,0),H121))))) -> 65257.969 | I129: =IF($A129>20,I128,(I128-H121+H129)*(1+$B$7)) -> 0 | J129: =IF($A129>20,J128,(J128-H129)*(1+$B$6)) -> 759273.55 | K129: =IF($A129>20,0,(K121-MIN(MAX(L128,0),K121))+MIN(MAX(0,M128-(K121-MIN(MAX(L128,0),K121))),MAX(0,0*K121-(L128-MIN(MAX(L128,0),K121))))) -> 65257.969 | L129: =IF($A129>20,L128,(L128-K121+K129)*(1+$B$7)) -> 0 | M129: =IF($A129>20,M128,(M128-K129)*(1+$B$6)) -> 759273.55 | N129: =IF($A129>20,0,(N121-MIN(MAX(O128,0),N121))+MIN(MAX(0,P128-(N121-MIN(MAX(O128,0),N121))),MAX(0,0*N121-(O128-MIN(MAX(O128,0),N121))))) -> 65257.969 | O129: =IF($A129>20,O128,(O128-N121+N129)*(1+$B$7)) -> 0 | P129: =IF($A129>20,P128,(P128-N129)*(1+$B$6)) -> 759273.55 | Q129: =IF($A129>20,0,(Q121-MIN(MAX(R128,0),Q121))+MIN(MAX(0,S128-(Q121-MIN(MAX(R128,0),Q121))),MAX(0,0*Q121-(R128-MIN(MAX(R128,0),Q121))))) -> 65257.969 | R129: =IF($A129>20,R128,(R128-Q121+Q129)*(1+$B$7)) -> 0 | S129: =IF($A129>20,S128,(S128-Q129)*(1+$B$6)) -> 759273.55
A130: =7 -> 7 | B130: =IF($A130>20,0,(B121-MIN(MAX(C129,0),B121))+MIN(MAX(0,D129-(B121-MIN(MAX(C129,0),B121))),MAX(0,0*B121-(C129-MIN(MAX(C129,0),B121))))) -> 30000 | C130: =IF($A130>20,C129,(C129-B121+B130)*(1+$B$7)) -> 0 | D130: =IF($A130>20,D129,(D129-B130)*(1+$B$6)) -> 993103.78 | E130: =IF($A130>20,0,(E121-MIN(MAX(F129,0),E121))+MIN(MAX(0,G129-(E121-MIN(MAX(F129,0),E121))),MAX(0,0*E121-(F129-MIN(MAX(F129,0),E121))))) -> 75000 | F130: =IF($A130>20,F129,(F129-E121+E130)*(1+$B$7)) -> 0 | G130: =IF($A130>20,G129,(G129-E130)*(1+$B$6)) -> 637948.66 | H130: =IF($A130>20,0,(H121-MIN(MAX(I129,0),H121))+MIN(MAX(0,J129-(H121-MIN(MAX(I129,0),H121))),MAX(0,0*H121-(I129-MIN(MAX(I129,0),H121))))) -> 65257.969 | I130: =IF($A130>20,I129,(I129-H121+H130)*(1+$B$7)) -> 0 | J130: =IF($A130>20,J129,(J129-H130)*(1+$B$6)) -> 714836.05 | K130: =IF($A130>20,0,(K121-MIN(MAX(L129,0),K121))+MIN(MAX(0,M129-(K121-MIN(MAX(L129,0),K121))),MAX(0,0*K121-(L129-MIN(MAX(L129,0),K121))))) -> 65257.969 | L130: =IF($A130>20,L129,(L129-K121+K130)*(1+$B$7)) -> 0 | M130: =IF($A130>20,M129,(M129-K130)*(1+$B$6)) -> 714836.05 | N130: =IF($A130>20,0,(N121-MIN(MAX(O129,0),N121))+MIN(MAX(0,P129-(N121-MIN(MAX(O129,0),N121))),MAX(0,0*N121-(O129-MIN(MAX(O129,0),N121))))) -> 65257.969 | O130: =IF($A130>20,O129,(O129-N121+N130)*(1+$B$7)) -> 0 | P130: =IF($A130>20,P129,(P129-N130)*(1+$B$6)) -> 714836.05 | Q130: =IF($A130>20,0,(Q121-MIN(MAX(R129,0),Q121))+MIN(MAX(0,S129-(Q121-MIN(MAX(R129,0),Q121))),MAX(0,0*Q121-(R129-MIN(MAX(R129,0),Q121))))) -> 65257.969 | R130: =IF($A130>20,R129,(R129-Q121+Q130)*(1+$B$7)) -> 0 | S130: =IF($A130>20,S129,(S129-Q130)*(1+$B$6)) -> 714836.05
A131: =8 -> 8 | B131: =IF($A131>20,0,(B121-MIN(MAX(C130,0),B121))+MIN(MAX(0,D130-(B121-MIN(MAX(C130,0),B121))),MAX(0,0*B121-(C130-MIN(MAX(C130,0),B121))))) -> 30000 | C131: =IF($A131>20,C130,(C130-B121+B131)*(1+$B$7)) -> 0 | D131: =IF($A131>20,D130,(D130-B131)*(1+$B$6)) -> 991996.9 | E131: =IF($A131>20,0,(E121-MIN(MAX(F130,0),E121))+MIN(MAX(0,G130-(E121-MIN(MAX(F130,0),E121))),MAX(0,0*E121-(F130-MIN(MAX(F130,0),E121))))) -> 75000 | F131: =IF($A131>20,F130,(F130-E121+E131)*(1+$B$7)) -> 0 | G131: =IF($A131>20,G130,(G130-E131)*(1+$B$6)) -> 579837.12 | H131: =IF($A131>20,0,(H121-MIN(MAX(I130,0),H121))+MIN(MAX(0,J130-(H121-MIN(MAX(I130,0),H121))),MAX(0,0*H121-(I130-MIN(MAX(I130,0),H121))))) -> 65257.969 | I131: =IF($A131>20,I130,(I130-H121+H131)*(1+$B$7)) -> 0 | J131: =IF($A131>20,J130,(J130-H131)*(1+$B$6)) -> 669065.42 | K131: =IF($A131>20,0,(K121-MIN(MAX(L130,0),K121))+MIN(MAX(0,M130-(K121-MIN(MAX(L130,0),K121))),MAX(0,0*K121-(L130-MIN(MAX(L130,0),K121))))) -> 65257.969 | L131: =IF($A131>20,L130,(L130-K121+K131)*(1+$B$7)) -> 0 | M131: =IF($A131>20,M130,(M130-K131)*(1+$B$6)) -> 669065.42 | N131: =IF($A131>20,0,(N121-MIN(MAX(O130,0),N121))+MIN(MAX(0,P130-(N121-MIN(MAX(O130,0),N121))),MAX(0,0*N121-(O130-MIN(MAX(O130,0),N121))))) -> 65257.969 | O131: =IF($A131>20,O130,(O130-N121+N131)*(1+$B$7)) -> 0 | P131: =IF($A131>20,P130,(P130-N131)*(1+$B$6)) -> 669065.42 | Q131: =IF($A131>20,0,(Q121-MIN(MAX(R130,0),Q121))+MIN(MAX(0,S130-(Q121-MIN(MAX(R130,0),Q121))),MAX(0,0*Q121-(R130-MIN(MAX(R130,0),Q121))))) -> 65257.969 | R131: =IF($A131>20,R130,(R130-Q121+Q131)*(1+$B$7)) -> 0 | S131: =IF($A131>20,S130,(S130-Q131)*(1+$B$6)) -> 669065.42
A132: =9 -> 9 | B132: =IF($A132>20,0,(B121-MIN(MAX(C131,0),B121))+MIN(MAX(0,D131-(B121-MIN(MAX(C131,0),B121))),MAX(0,0*B121-(C131-MIN(MAX(C131,0),B121))))) -> 30000 | C132: =IF($A132>20,C131,(C131-B121+B132)*(1+$B$7)) -> 0 | D132: =IF($A132>20,D131,(D131-B132)*(1+$B$6)) -> 990856.8 | E132: =IF($A132>20,0,(E121-MIN(MAX(F131,0),E121))+MIN(MAX(0,G131-(E121-MIN(MAX(F131,0),E121))),MAX(0,0*E121-(F131-MIN(MAX(F131,0),E121))))) -> 75000 | F132: =IF($A132>20,F131,(F131-E121+E132)*(1+$B$7)) -> 0 | G132: =IF($A132>20,G131,(G131-E132)*(1+$B$6)) -> 519982.24 | H132: =IF($A132>20,0,(H121-MIN(MAX(I131,0),H121))+MIN(MAX(0,J131-(H121-MIN(MAX(I131,0),H121))),MAX(0,0*H121-(I131-MIN(MAX(I131,0),H121))))) -> 65257.969 | I132: =IF($A132>20,I131,(I131-H121+H132)*(1+$B$7)) -> 0 | J132: =IF($A132>20,J131,(J131-H132)*(1+$B$6)) -> 621921.68 | K132: =IF($A132>20,0,(K121-MIN(MAX(L131,0),K121))+MIN(MAX(0,M131-(K121-MIN(MAX(L131,0),K121))),MAX(0,0*K121-(L131-MIN(MAX(L131,0),K121))))) -> 65257.969 | L132: =IF($A132>20,L131,(L131-K121+K132)*(1+$B$7)) -> 0 | M132: =IF($A132>20,M131,(M131-K132)*(1+$B$6)) -> 621921.68 | N132: =IF($A132>20,0,(N121-MIN(MAX(O131,0),N121))+MIN(MAX(0,P131-(N121-MIN(MAX(O131,0),N121))),MAX(0,0*N121-(O131-MIN(MAX(O131,0),N121))))) -> 65257.969 | O132: =IF($A132>20,O131,(O131-N121+N132)*(1+$B$7)) -> 0 | P132: =IF($A132>20,P131,(P131-N132)*(1+$B$6)) -> 621921.68 | Q132: =IF($A132>20,0,(Q121-MIN(MAX(R131,0),Q121))+MIN(MAX(0,S131-(Q121-MIN(MAX(R131,0),Q121))),MAX(0,0*Q121-(R131-MIN(MAX(R131,0),Q121))))) -> 65257.969 | R132: =IF($A132>20,R131,(R131-Q121+Q132)*(1+$B$7)) -> 0 | S132: =IF($A132>20,S131,(S131-Q132)*(1+$B$6)) -> 621921.68
A133: =10 -> 10 | B133: =IF($A133>20,0,(B121-MIN(MAX(C132,0),B121))+MIN(MAX(0,D132-(B121-MIN(MAX(C132,0),B121))),MAX(0,0*B121-(C132-MIN(MAX(C132,0),B121))))) -> 30000 | C133: =IF($A133>20,C132,(C132-B121+B133)*(1+$B$7)) -> 0 | D133: =IF($A133>20,D132,(D132-B133)*(1+$B$6)) -> 989682.51 | E133: =IF($A133>20,0,(E121-MIN(MAX(F132,0),E121))+MIN(MAX(0,G132-(E121-MIN(MAX(F132,0),E121))),MAX(0,0*E121-(F132-MIN(MAX(F132,0),E121))))) -> 75000 | F133: =IF($A133>20,F132,(F132-E121+E133)*(1+$B$7)) -> 0 | G133: =IF($A133>20,G132,(G132-E133)*(1+$B$6)) -> 458331.7 | H133: =IF($A133>20,0,(H121-MIN(MAX(I132,0),H121))+MIN(MAX(0,J132-(H121-MIN(MAX(I132,0),H121))),MAX(0,0*H121-(I132-MIN(MAX(I132,0),H121))))) -> 65257.969 | I133: =IF($A133>20,I132,(I132-H121+H133)*(1+$B$7)) -> 0 | J133: =IF($A133>20,J132,(J132-H133)*(1+$B$6)) -> 573363.62 | K133: =IF($A133>20,0,(K121-MIN(MAX(L132,0),K121))+MIN(MAX(0,M132-(K121-MIN(MAX(L132,0),K121))),MAX(0,0*K121-(L132-MIN(MAX(L132,0),K121))))) -> 65257.969 | L133: =IF($A133>20,L132,(L132-K121+K133)*(1+$B$7)) -> 0 | M133: =IF($A133>20,M132,(M132-K133)*(1+$B$6)) -> 573363.62 | N133: =IF($A133>20,0,(N121-MIN(MAX(O132,0),N121))+MIN(MAX(0,P132-(N121-MIN(MAX(O132,0),N121))),MAX(0,0*N121-(O132-MIN(MAX(O132,0),N121))))) -> 65257.969 | O133: =IF($A133>20,O132,(O132-N121+N133)*(1+$B$7)) -> 0 | P133: =IF($A133>20,P132,(P132-N133)*(1+$B$6)) -> 573363.62 | Q133: =IF($A133>20,0,(Q121-MIN(MAX(R132,0),Q121))+MIN(MAX(0,S132-(Q121-MIN(MAX(R132,0),Q121))),MAX(0,0*Q121-(R132-MIN(MAX(R132,0),Q121))))) -> 65257.969 | R133: =IF($A133>20,R132,(R132-Q121+Q133)*(1+$B$7)) -> 0 | S133: =IF($A133>20,S132,(S132-Q133)*(1+$B$6)) -> 573363.62
A134: =11 -> 11 | B134: =IF($A134>20,0,(B121-MIN(MAX(C133,0),B121))+MIN(MAX(0,D133-(B121-MIN(MAX(C133,0),B121))),MAX(0,0*B121-(C133-MIN(MAX(C133,0),B121))))) -> 30000 | C134: =IF($A134>20,C133,(C133-B121+B134)*(1+$B$7)) -> 0 | D134: =IF($A134>20,D133,(D133-B134)*(1+$B$6)) -> 988472.98 | E134: =IF($A134>20,0,(E121-MIN(MAX(F133,0),E121))+MIN(MAX(0,G133-(E121-MIN(MAX(F133,0),E121))),MAX(0,0*E121-(F133-MIN(MAX(F133,0),E121))))) -> 75000 | F134: =IF($A134>20,F133,(F133-E121+E134)*(1+$B$7)) -> 0 | G134: =IF($A134>20,G133,(G133-E134)*(1+$B$6)) -> 394831.65 | H134: =IF($A134>20,0,(H121-MIN(MAX(I133,0),H121))+MIN(MAX(0,J133-(H121-MIN(MAX(I133,0),H121))),MAX(0,0*H121-(I133-MIN(MAX(I133,0),H121))))) -> 65257.969 | I134: =IF($A134>20,I133,(I133-H121+H134)*(1+$B$7)) -> 0 | J134: =IF($A134>20,J133,(J133-H134)*(1+$B$6)) -> 523348.82 | K134: =IF($A134>20,0,(K121-MIN(MAX(L133,0),K121))+MIN(MAX(0,M133-(K121-MIN(MAX(L133,0),K121))),MAX(0,0*K121-(L133-MIN(MAX(L133,0),K121))))) -> 65257.969 | L134: =IF($A134>20,L133,(L133-K121+K134)*(1+$B$7)) -> 0 | M134: =IF($A134>20,M133,(M133-K134)*(1+$B$6)) -> 523348.82 | N134: =IF($A134>20,0,(N121-MIN(MAX(O133,0),N121))+MIN(MAX(0,P133-(N121-MIN(MAX(O133,0),N121))),MAX(0,0*N121-(O133-MIN(MAX(O133,0),N121))))) -> 65257.969 | O134: =IF($A134>20,O133,(O133-N121+N134)*(1+$B$7)) -> 0 | P134: =IF($A134>20,P133,(P133-N134)*(1+$B$6)) -> 523348.82 | Q134: =IF($A134>20,0,(Q121-MIN(MAX(R133,0),Q121))+MIN(MAX(0,S133-(Q121-MIN(MAX(R133,0),Q121))),MAX(0,0*Q121-(R133-MIN(MAX(R133,0),Q121))))) -> 65257.969 | R134: =IF($A134>20,R133,(R133-Q121+Q134)*(1+$B$7)) -> 0 | S134: =IF($A134>20,S133,(S133-Q134)*(1+$B$6)) -> 523348.82
A135: =12 -> 12 | B135: =IF($A135>20,0,(B121-MIN(MAX(C134,0),B121))+MIN(MAX(0,D134-(B121-MIN(MAX(C134,0),B121))),MAX(0,0*B121-(C134-MIN(MAX(C134,0),B121))))) -> 30000 | C135: =IF($A135>20,C134,(C134-B121+B135)*(1+$B$7)) -> 0 | D135: =IF($A135>20,D134,(D134-B135)*(1+$B$6)) -> 987227.17 | E135: =IF($A135>20,0,(E121-MIN(MAX(F134,0),E121))+MIN(MAX(0,G134-(E121-MIN(MAX(F134,0),E121))),MAX(0,0*E121-(F134-MIN(MAX(F134,0),E121))))) -> 75000 | F135: =IF($A135>20,F134,(F134-E121+E135)*(1+$B$7)) -> 0 | G135: =IF($A135>20,G134,(G134-E135)*(1+$B$6)) -> 329426.6 | H135: =IF($A135>20,0,(H121-MIN(MAX(I134,0),H121))+MIN(MAX(0,J134-(H121-MIN(MAX(I134,0),H121))),MAX(0,0*H121-(I134-MIN(MAX(I134,0),H121))))) -> 65257.969 | I135: =IF($A135>20,I134,(I134-H121+H135)*(1+$B$7)) -> 0 | J135: =IF($A135>20,J134,(J134-H135)*(1+$B$6)) -> 471833.58 | K135: =IF($A135>20,0,(K121-MIN(MAX(L134,0),K121))+MIN(MAX(0,M134-(K121-MIN(MAX(L134,0),K121))),MAX(0,0*K121-(L134-MIN(MAX(L134,0),K121))))) -> 65257.969 | L135: =IF($A135>20,L134,(L134-K121+K135)*(1+$B$7)) -> 0 | M135: =IF($A135>20,M134,(M134-K135)*(1+$B$6)) -> 471833.58 | N135: =IF($A135>20,0,(N121-MIN(MAX(O134,0),N121))+MIN(MAX(0,P134-(N121-MIN(MAX(O134,0),N121))),MAX(0,0*N121-(O134-MIN(MAX(O134,0),N121))))) -> 65257.969 | O135: =IF($A135>20,O134,(O134-N121+N135)*(1+$B$7)) -> 0 | P135: =IF($A135>20,P134,(P134-N135)*(1+$B$6)) -> 471833.58 | Q135: =IF($A135>20,0,(Q121-MIN(MAX(R134,0),Q121))+MIN(MAX(0,S134-(Q121-MIN(MAX(R134,0),Q121))),MAX(0,0*Q121-(R134-MIN(MAX(R134,0),Q121))))) -> 65257.969 | R135: =IF($A135>20,R134,(R134-Q121+Q135)*(1+$B$7)) -> 0 | S135: =IF($A135>20,S134,(S134-Q135)*(1+$B$6)) -> 471833.58
A136: =13 -> 13 | B136: =IF($A136>20,0,(B121-MIN(MAX(C135,0),B121))+MIN(MAX(0,D135-(B121-MIN(MAX(C135,0),B121))),MAX(0,0*B121-(C135-MIN(MAX(C135,0),B121))))) -> 30000 | C136: =IF($A136>20,C135,(C135-B121+B136)*(1+$B$7)) -> 0 | D136: =IF($A136>20,D135,(D135-B136)*(1+$B$6)) -> 985943.99 | E136: =IF($A136>20,0,(E121-MIN(MAX(F135,0),E121))+MIN(MAX(0,G135-(E121-MIN(MAX(F135,0),E121))),MAX(0,0*E121-(F135-MIN(MAX(F135,0),E121))))) -> 75000 | F136: =IF($A136>20,F135,(F135-E121+E136)*(1+$B$7)) -> 0 | G136: =IF($A136>20,G135,(G135-E136)*(1+$B$6)) -> 262059.4 | H136: =IF($A136>20,0,(H121-MIN(MAX(I135,0),H121))+MIN(MAX(0,J135-(H121-MIN(MAX(I135,0),H121))),MAX(0,0*H121-(I135-MIN(MAX(I135,0),H121))))) -> 65257.969 | I136: =IF($A136>20,I135,(I135-H121+H136)*(1+$B$7)) -> 0 | J136: =IF($A136>20,J135,(J135-H136)*(1+$B$6)) -> 418772.88 | K136: =IF($A136>20,0,(K121-MIN(MAX(L135,0),K121))+MIN(MAX(0,M135-(K121-MIN(MAX(L135,0),K121))),MAX(0,0*K121-(L135-MIN(MAX(L135,0),K121))))) -> 65257.969 | L136: =IF($A136>20,L135,(L135-K121+K136)*(1+$B$7)) -> 0 | M136: =IF($A136>20,M135,(M135-K136)*(1+$B$6)) -> 418772.88 | N136: =IF($A136>20,0,(N121-MIN(MAX(O135,0),N121))+MIN(MAX(0,P135-(N121-MIN(MAX(O135,0),N121))),MAX(0,0*N121-(O135-MIN(MAX(O135,0),N121))))) -> 65257.969 | O136: =IF($A136>20,O135,(O135-N121+N136)*(1+$B$7)) -> 0 | P136: =IF($A136>20,P135,(P135-N136)*(1+$B$6)) -> 418772.88 | Q136: =IF($A136>20,0,(Q121-MIN(MAX(R135,0),Q121))+MIN(MAX(0,S135-(Q121-MIN(MAX(R135,0),Q121))),MAX(0,0*Q121-(R135-MIN(MAX(R135,0),Q121))))) -> 65257.969 | R136: =IF($A136>20,R135,(R135-Q121+Q136)*(1+$B$7)) -> 0 | S136: =IF($A136>20,S135,(S135-Q136)*(1+$B$6)) -> 418772.88
A137: =14 -> 14 | B137: =IF($A137>20,0,(B121-MIN(MAX(C136,0),B121))+MIN(MAX(0,D136-(B121-MIN(MAX(C136,0),B121))),MAX(0,0*B121-(C136-MIN(MAX(C136,0),B121))))) -> 30000 | C137: =IF($A137>20,C136,(C136-B121+B137)*(1+$B$7)) -> 0 | D137: =IF($A137>20,D136,(D136-B137)*(1+$B$6)) -> 984622.31 | E137: =IF($A137>20,0,(E121-MIN(MAX(F136,0),E121))+MIN(MAX(0,G136-(E121-MIN(MAX(F136,0),E121))),MAX(0,0*E121-(F136-MIN(MAX(F136,0),E121))))) -> 75000 | F137: =IF($A137>20,F136,(F136-E121+E137)*(1+$B$7)) -> 0 | G137: =IF($A137>20,G136,(G136-E137)*(1+$B$6)) -> 192671.18 | H137: =IF($A137>20,0,(H121-MIN(MAX(I136,0),H121))+MIN(MAX(0,J136-(H121-MIN(MAX(I136,0),H121))),MAX(0,0*H121-(I136-MIN(MAX(I136,0),H121))))) -> 65257.969 | I137: =IF($A137>20,I136,(I136-H121+H137)*(1+$B$7)) -> 0 | J137: =IF($A137>20,J136,(J136-H137)*(1+$B$6)) -> 364120.36 | K137: =IF($A137>20,0,(K121-MIN(MAX(L136,0),K121))+MIN(MAX(0,M136-(K121-MIN(MAX(L136,0),K121))),MAX(0,0*K121-(L136-MIN(MAX(L136,0),K121))))) -> 65257.969 | L137: =IF($A137>20,L136,(L136-K121+K137)*(1+$B$7)) -> 0 | M137: =IF($A137>20,M136,(M136-K137)*(1+$B$6)) -> 364120.36 | N137: =IF($A137>20,0,(N121-MIN(MAX(O136,0),N121))+MIN(MAX(0,P136-(N121-MIN(MAX(O136,0),N121))),MAX(0,0*N121-(O136-MIN(MAX(O136,0),N121))))) -> 65257.969 | O137: =IF($A137>20,O136,(O136-N121+N137)*(1+$B$7)) -> 0 | P137: =IF($A137>20,P136,(P136-N137)*(1+$B$6)) -> 364120.36 | Q137: =IF($A137>20,0,(Q121-MIN(MAX(R136,0),Q121))+MIN(MAX(0,S136-(Q121-MIN(MAX(R136,0),Q121))),MAX(0,0*Q121-(R136-MIN(MAX(R136,0),Q121))))) -> 65257.969 | R137: =IF($A137>20,R136,(R136-Q121+Q137)*(1+$B$7)) -> 0 | S137: =IF($A137>20,S136,(S136-Q137)*(1+$B$6)) -> 364120.36
A138: =15 -> 15 | B138: =IF($A138>20,0,(B121-MIN(MAX(C137,0),B121))+MIN(MAX(0,D137-(B121-MIN(MAX(C137,0),B121))),MAX(0,0*B121-(C137-MIN(MAX(C137,0),B121))))) -> 30000 | C138: =IF($A138>20,C137,(C137-B121+B138)*(1+$B$7)) -> 0 | D138: =IF($A138>20,D137,(D137-B138)*(1+$B$6)) -> 983260.98 | E138: =IF($A138>20,0,(E121-MIN(MAX(F137,0),E121))+MIN(MAX(0,G137-(E121-MIN(MAX(F137,0),E121))),MAX(0,0*E121-(F137-MIN(MAX(F137,0),E121))))) -> 75000 | F138: =IF($A138>20,F137,(F137-E121+E138)*(1+$B$7)) -> 0 | G138: =IF($A138>20,G137,(G137-E138)*(1+$B$6)) -> 121201.32 | H138: =IF($A138>20,0,(H121-MIN(MAX(I137,0),H121))+MIN(MAX(0,J137-(H121-MIN(MAX(I137,0),H121))),MAX(0,0*H121-(I137-MIN(MAX(I137,0),H121))))) -> 65257.969 | I138: =IF($A138>20,I137,(I137-H121+H138)*(1+$B$7)) -> 0 | J138: =IF($A138>20,J137,(J137-H138)*(1+$B$6)) -> 307828.26 | K138: =IF($A138>20,0,(K121-MIN(MAX(L137,0),K121))+MIN(MAX(0,M137-(K121-MIN(MAX(L137,0),K121))),MAX(0,0*K121-(L137-MIN(MAX(L137,0),K121))))) -> 65257.969 | L138: =IF($A138>20,L137,(L137-K121+K138)*(1+$B$7)) -> 0 | M138: =IF($A138>20,M137,(M137-K138)*(1+$B$6)) -> 307828.26 | N138: =IF($A138>20,0,(N121-MIN(MAX(O137,0),N121))+MIN(MAX(0,P137-(N121-MIN(MAX(O137,0),N121))),MAX(0,0*N121-(O137-MIN(MAX(O137,0),N121))))) -> 65257.969 | O138: =IF($A138>20,O137,(O137-N121+N138)*(1+$B$7)) -> 0 | P138: =IF($A138>20,P137,(P137-N138)*(1+$B$6)) -> 307828.26 | Q138: =IF($A138>20,0,(Q121-MIN(MAX(R137,0),Q121))+MIN(MAX(0,S137-(Q121-MIN(MAX(R137,0),Q121))),MAX(0,0*Q121-(R137-MIN(MAX(R137,0),Q121))))) -> 65257.969 | R138: =IF($A138>20,R137,(R137-Q121+Q138)*(1+$B$7)) -> 0 | S138: =IF($A138>20,S137,(S137-Q138)*(1+$B$6)) -> 307828.26
A139: =16 -> 16 | B139: =IF($A139>20,0,(B121-MIN(MAX(C138,0),B121))+MIN(MAX(0,D138-(B121-MIN(MAX(C138,0),B121))),MAX(0,0*B121-(C138-MIN(MAX(C138,0),B121))))) -> 30000 | C139: =IF($A139>20,C138,(C138-B121+B139)*(1+$B$7)) -> 0 | D139: =IF($A139>20,D138,(D138-B139)*(1+$B$6)) -> 981858.81 | E139: =IF($A139>20,0,(E121-MIN(MAX(F138,0),E121))+MIN(MAX(0,G138-(E121-MIN(MAX(F138,0),E121))),MAX(0,0*E121-(F138-MIN(MAX(F138,0),E121))))) -> 75000 | F139: =IF($A139>20,F138,(F138-E121+E139)*(1+$B$7)) -> 0 | G139: =IF($A139>20,G138,(G138-E139)*(1+$B$6)) -> 47587.358 | H139: =IF($A139>20,0,(H121-MIN(MAX(I138,0),H121))+MIN(MAX(0,J138-(H121-MIN(MAX(I138,0),H121))),MAX(0,0*H121-(I138-MIN(MAX(I138,0),H121))))) -> 65257.969 | I139: =IF($A139>20,I138,(I138-H121+H139)*(1+$B$7)) -> 0 | J139: =IF($A139>20,J138,(J138-H139)*(1+$B$6)) -> 249847.4 | K139: =IF($A139>20,0,(K121-MIN(MAX(L138,0),K121))+MIN(MAX(0,M138-(K121-MIN(MAX(L138,0),K121))),MAX(0,0*K121-(L138-MIN(MAX(L138,0),K121))))) -> 65257.969 | L139: =IF($A139>20,L138,(L138-K121+K139)*(1+$B$7)) -> 0 | M139: =IF($A139>20,M138,(M138-K139)*(1+$B$6)) -> 249847.4 | N139: =IF($A139>20,0,(N121-MIN(MAX(O138,0),N121))+MIN(MAX(0,P138-(N121-MIN(MAX(O138,0),N121))),MAX(0,0*N121-(O138-MIN(MAX(O138,0),N121))))) -> 65257.969 | O139: =IF($A139>20,O138,(O138-N121+N139)*(1+$B$7)) -> 0 | P139: =IF($A139>20,P138,(P138-N139)*(1+$B$6)) -> 249847.4 | Q139: =IF($A139>20,0,(Q121-MIN(MAX(R138,0),Q121))+MIN(MAX(0,S138-(Q121-MIN(MAX(R138,0),Q121))),MAX(0,0*Q121-(R138-MIN(MAX(R138,0),Q121))))) -> 65257.969 | R139: =IF($A139>20,R138,(R138-Q121+Q139)*(1+$B$7)) -> 0 | S139: =IF($A139>20,S138,(S138-Q139)*(1+$B$6)) -> 249847.4
A140: =17 -> 17 | B140: =IF($A140>20,0,(B121-MIN(MAX(C139,0),B121))+MIN(MAX(0,D139-(B121-MIN(MAX(C139,0),B121))),MAX(0,0*B121-(C139-MIN(MAX(C139,0),B121))))) -> 30000 | C140: =IF($A140>20,C139,(C139-B121+B140)*(1+$B$7)) -> 0 | D140: =IF($A140>20,D139,(D139-B140)*(1+$B$6)) -> 980414.57 | E140: =IF($A140>20,0,(E121-MIN(MAX(F139,0),E121))+MIN(MAX(0,G139-(E121-MIN(MAX(F139,0),E121))),MAX(0,0*E121-(F139-MIN(MAX(F139,0),E121))))) -> 75000 | F140: =IF($A140>20,F139,(F139-E121+E140)*(1+$B$7)) -> 0 | G140: =IF($A140>20,G139,(G139-E140)*(1+$B$6)) -> -28235.021 | H140: =IF($A140>20,0,(H121-MIN(MAX(I139,0),H121))+MIN(MAX(0,J139-(H121-MIN(MAX(I139,0),H121))),MAX(0,0*H121-(I139-MIN(MAX(I139,0),H121))))) -> 65257.969 | I140: =IF($A140>20,I139,(I139-H121+H140)*(1+$B$7)) -> 0 | J140: =IF($A140>20,J139,(J139-H140)*(1+$B$6)) -> 190127.11 | K140: =IF($A140>20,0,(K121-MIN(MAX(L139,0),K121))+MIN(MAX(0,M139-(K121-MIN(MAX(L139,0),K121))),MAX(0,0*K121-(L139-MIN(MAX(L139,0),K121))))) -> 65257.969 | L140: =IF($A140>20,L139,(L139-K121+K140)*(1+$B$7)) -> 0 | M140: =IF($A140>20,M139,(M139-K140)*(1+$B$6)) -> 190127.11 | N140: =IF($A140>20,0,(N121-MIN(MAX(O139,0),N121))+MIN(MAX(0,P139-(N121-MIN(MAX(O139,0),N121))),MAX(0,0*N121-(O139-MIN(MAX(O139,0),N121))))) -> 65257.969 | O140: =IF($A140>20,O139,(O139-N121+N140)*(1+$B$7)) -> 0 | P140: =IF($A140>20,P139,(P139-N140)*(1+$B$6)) -> 190127.11 | Q140: =IF($A140>20,0,(Q121-MIN(MAX(R139,0),Q121))+MIN(MAX(0,S139-(Q121-MIN(MAX(R139,0),Q121))),MAX(0,0*Q121-(R139-MIN(MAX(R139,0),Q121))))) -> 65257.969 | R140: =IF($A140>20,R139,(R139-Q121+Q140)*(1+$B$7)) -> 0 | S140: =IF($A140>20,S139,(S139-Q140)*(1+$B$6)) -> 190127.11
A141: =18 -> 18 | B141: =IF($A141>20,0,(B121-MIN(MAX(C140,0),B121))+MIN(MAX(0,D140-(B121-MIN(MAX(C140,0),B121))),MAX(0,0*B121-(C140-MIN(MAX(C140,0),B121))))) -> 30000 | C141: =IF($A141>20,C140,(C140-B121+B141)*(1+$B$7)) -> 0 | D141: =IF($A141>20,D140,(D140-B141)*(1+$B$6)) -> 978927.01 | E141: =IF($A141>20,0,(E121-MIN(MAX(F140,0),E121))+MIN(MAX(0,G140-(E121-MIN(MAX(F140,0),E121))),MAX(0,0*E121-(F140-MIN(MAX(F140,0),E121))))) -> 75000 | F141: =IF($A141>20,F140,(F140-E121+E141)*(1+$B$7)) -> 0 | G141: =IF($A141>20,G140,(G140-E141)*(1+$B$6)) -> -106332.07 | H141: =IF($A141>20,0,(H121-MIN(MAX(I140,0),H121))+MIN(MAX(0,J140-(H121-MIN(MAX(I140,0),H121))),MAX(0,0*H121-(I140-MIN(MAX(I140,0),H121))))) -> 65257.969 | I141: =IF($A141>20,I140,(I140-H121+H141)*(1+$B$7)) -> 0 | J141: =IF($A141>20,J140,(J140-H141)*(1+$B$6)) -> 128615.22 | K141: =IF($A141>20,0,(K121-MIN(MAX(L140,0),K121))+MIN(MAX(0,M140-(K121-MIN(MAX(L140,0),K121))),MAX(0,0*K121-(L140-MIN(MAX(L140,0),K121))))) -> 65257.969 | L141: =IF($A141>20,L140,(L140-K121+K141)*(1+$B$7)) -> 0 | M141: =IF($A141>20,M140,(M140-K141)*(1+$B$6)) -> 128615.22 | N141: =IF($A141>20,0,(N121-MIN(MAX(O140,0),N121))+MIN(MAX(0,P140-(N121-MIN(MAX(O140,0),N121))),MAX(0,0*N121-(O140-MIN(MAX(O140,0),N121))))) -> 65257.969 | O141: =IF($A141>20,O140,(O140-N121+N141)*(1+$B$7)) -> 0 | P141: =IF($A141>20,P140,(P140-N141)*(1+$B$6)) -> 128615.22 | Q141: =IF($A141>20,0,(Q121-MIN(MAX(R140,0),Q121))+MIN(MAX(0,S140-(Q121-MIN(MAX(R140,0),Q121))),MAX(0,0*Q121-(R140-MIN(MAX(R140,0),Q121))))) -> 65257.969 | R141: =IF($A141>20,R140,(R140-Q121+Q141)*(1+$B$7)) -> 0 | S141: =IF($A141>20,S140,(S140-Q141)*(1+$B$6)) -> 128615.22
A142: =19 -> 19 | B142: =IF($A142>20,0,(B121-MIN(MAX(C141,0),B121))+MIN(MAX(0,D141-(B121-MIN(MAX(C141,0),B121))),MAX(0,0*B121-(C141-MIN(MAX(C141,0),B121))))) -> 30000 | C142: =IF($A142>20,C141,(C141-B121+B142)*(1+$B$7)) -> 0 | D142: =IF($A142>20,D141,(D141-B142)*(1+$B$6)) -> 977394.82 | E142: =IF($A142>20,0,(E121-MIN(MAX(F141,0),E121))+MIN(MAX(0,G141-(E121-MIN(MAX(F141,0),E121))),MAX(0,0*E121-(F141-MIN(MAX(F141,0),E121))))) -> 75000 | F142: =IF($A142>20,F141,(F141-E121+E142)*(1+$B$7)) -> 0 | G142: =IF($A142>20,G141,(G141-E142)*(1+$B$6)) -> -186772.03 | H142: =IF($A142>20,0,(H121-MIN(MAX(I141,0),H121))+MIN(MAX(0,J141-(H121-MIN(MAX(I141,0),H121))),MAX(0,0*H121-(I141-MIN(MAX(I141,0),H121))))) -> 65257.969 | I142: =IF($A142>20,I141,(I141-H121+H142)*(1+$B$7)) -> 0 | J142: =IF($A142>20,J141,(J141-H142)*(1+$B$6)) -> 65257.969 | K142: =IF($A142>20,0,(K121-MIN(MAX(L141,0),K121))+MIN(MAX(0,M141-(K121-MIN(MAX(L141,0),K121))),MAX(0,0*K121-(L141-MIN(MAX(L141,0),K121))))) -> 65257.969 | L142: =IF($A142>20,L141,(L141-K121+K142)*(1+$B$7)) -> 0 | M142: =IF($A142>20,M141,(M141-K142)*(1+$B$6)) -> 65257.969 | N142: =IF($A142>20,0,(N121-MIN(MAX(O141,0),N121))+MIN(MAX(0,P141-(N121-MIN(MAX(O141,0),N121))),MAX(0,0*N121-(O141-MIN(MAX(O141,0),N121))))) -> 65257.969 | O142: =IF($A142>20,O141,(O141-N121+N142)*(1+$B$7)) -> 0 | P142: =IF($A142>20,P141,(P141-N142)*(1+$B$6)) -> 65257.969 | Q142: =IF($A142>20,0,(Q121-MIN(MAX(R141,0),Q121))+MIN(MAX(0,S141-(Q121-MIN(MAX(R141,0),Q121))),MAX(0,0*Q121-(R141-MIN(MAX(R141,0),Q121))))) -> 65257.969 | R142: =IF($A142>20,R141,(R141-Q121+Q142)*(1+$B$7)) -> 0 | S142: =IF($A142>20,S141,(S141-Q142)*(1+$B$6)) -> 65257.969
A143: =20 -> 20 | B143: =IF($A143>20,0,(B121-MIN(MAX(C142,0),B121))+MIN(MAX(0,D142-(B121-MIN(MAX(C142,0),B121))),MAX(0,0*B121-(C142-MIN(MAX(C142,0),B121))))) -> 30000 | C143: =IF($A143>20,C142,(C142-B121+B143)*(1+$B$7)) -> 0 | D143: =IF($A143>20,D142,(D142-B143)*(1+$B$6)) -> 975816.66 | E143: =IF($A143>20,0,(E121-MIN(MAX(F142,0),E121))+MIN(MAX(0,G142-(E121-MIN(MAX(F142,0),E121))),MAX(0,0*E121-(F142-MIN(MAX(F142,0),E121))))) -> 75000 | F143: =IF($A143>20,F142,(F142-E121+E143)*(1+$B$7)) -> 0 | G143: =IF($A143>20,G142,(G142-E143)*(1+$B$6)) -> -269625.19 | H143: =IF($A143>20,0,(H121-MIN(MAX(I142,0),H121))+MIN(MAX(0,J142-(H121-MIN(MAX(I142,0),H121))),MAX(0,0*H121-(I142-MIN(MAX(I142,0),H121))))) -> 65257.969 | I143: =IF($A143>20,I142,(I142-H121+H143)*(1+$B$7)) -> 0 | J143: =IF($A143>20,J142,(J142-H143)*(1+$B$6)) -> -2.8478098e-10 | K143: =IF($A143>20,0,(K121-MIN(MAX(L142,0),K121))+MIN(MAX(0,M142-(K121-MIN(MAX(L142,0),K121))),MAX(0,0*K121-(L142-MIN(MAX(L142,0),K121))))) -> 65257.969 | L143: =IF($A143>20,L142,(L142-K121+K143)*(1+$B$7)) -> 0 | M143: =IF($A143>20,M142,(M142-K143)*(1+$B$6)) -> -8.24366e-11 | N143: =IF($A143>20,0,(N121-MIN(MAX(O142,0),N121))+MIN(MAX(0,P142-(N121-MIN(MAX(O142,0),N121))),MAX(0,0*N121-(O142-MIN(MAX(O142,0),N121))))) -> 65257.969 | O143: =IF($A143>20,O142,(O142-N121+N143)*(1+$B$7)) -> 0 | P143: =IF($A143>20,P142,(P142-N143)*(1+$B$6)) -> -8.24366e-11 | Q143: =IF($A143>20,0,(Q121-MIN(MAX(R142,0),Q121))+MIN(MAX(0,S142-(Q121-MIN(MAX(R142,0),Q121))),MAX(0,0*Q121-(R142-MIN(MAX(R142,0),Q121))))) -> 65257.969 | R143: =IF($A143>20,R142,(R142-Q121+Q143)*(1+$B$7)) -> 0 | S143: =IF($A143>20,S142,(S142-Q143)*(1+$B$6)) -> -8.24366e-11
A144: =21 -> 21 | B144: =IF($A144>20,0,(B121-MIN(MAX(C143,0),B121))+MIN(MAX(0,D143-(B121-MIN(MAX(C143,0),B121))),MAX(0,0*B121-(C143-MIN(MAX(C143,0),B121))))) -> 0 | C144: =IF($A144>20,C143,(C143-B121+B144)*(1+$B$7)) -> 0 | D144: =IF($A144>20,D143,(D143-B144)*(1+$B$6)) -> 975816.66 | E144: =IF($A144>20,0,(E121-MIN(MAX(F143,0),E121))+MIN(MAX(0,G143-(E121-MIN(MAX(F143,0),E121))),MAX(0,0*E121-(F143-MIN(MAX(F143,0),E121))))) -> 0 | F144: =IF($A144>20,F143,(F143-E121+E144)*(1+$B$7)) -> 0 | G144: =IF($A144>20,G143,(G143-E144)*(1+$B$6)) -> -269625.19 | H144: =IF($A144>20,0,(H121-MIN(MAX(I143,0),H121))+MIN(MAX(0,J143-(H121-MIN(MAX(I143,0),H121))),MAX(0,0*H121-(I143-MIN(MAX(I143,0),H121))))) -> 0 | I144: =IF($A144>20,I143,(I143-H121+H144)*(1+$B$7)) -> 0 | J144: =IF($A144>20,J143,(J143-H144)*(1+$B$6)) -> -2.8478098e-10 | K144: =IF($A144>20,0,(K121-MIN(MAX(L143,0),K121))+MIN(MAX(0,M143-(K121-MIN(MAX(L143,0),K121))),MAX(0,0*K121-(L143-MIN(MAX(L143,0),K121))))) -> 0 | L144: =IF($A144>20,L143,(L143-K121+K144)*(1+$B$7)) -> 0 | M144: =IF($A144>20,M143,(M143-K144)*(1+$B$6)) -> -8.24366e-11 | N144: =IF($A144>20,0,(N121-MIN(MAX(O143,0),N121))+MIN(MAX(0,P143-(N121-MIN(MAX(O143,0),N121))),MAX(0,0*N121-(O143-MIN(MAX(O143,0),N121))))) -> 0 | O144: =IF($A144>20,O143,(O143-N121+N144)*(1+$B$7)) -> 0 | P144: =IF($A144>20,P143,(P143-N144)*(1+$B$6)) -> -8.24366e-11 | Q144: =IF($A144>20,0,(Q121-MIN(MAX(R143,0),Q121))+MIN(MAX(0,S143-(Q121-MIN(MAX(R143,0),Q121))),MAX(0,0*Q121-(R143-MIN(MAX(R143,0),Q121))))) -> 0 | R144: =IF($A144>20,R143,(R143-Q121+Q144)*(1+$B$7)) -> 0 | S144: =IF($A144>20,S143,(S143-Q144)*(1+$B$6)) -> -8.24366e-11
A145: =22 -> 22 | B145: =IF($A145>20,0,(B121-MIN(MAX(C144,0),B121))+MIN(MAX(0,D144-(B121-MIN(MAX(C144,0),B121))),MAX(0,0*B121-(C144-MIN(MAX(C144,0),B121))))) -> 0 | C145: =IF($A145>20,C144,(C144-B121+B145)*(1+$B$7)) -> 0 | D145: =IF($A145>20,D144,(D144-B145)*(1+$B$6)) -> 975816.66 | E145: =IF($A145>20,0,(E121-MIN(MAX(F144,0),E121))+MIN(MAX(0,G144-(E121-MIN(MAX(F144,0),E121))),MAX(0,0*E121-(F144-MIN(MAX(F144,0),E121))))) -> 0 | F145: =IF($A145>20,F144,(F144-E121+E145)*(1+$B$7)) -> 0 | G145: =IF($A145>20,G144,(G144-E145)*(1+$B$6)) -> -269625.19 | H145: =IF($A145>20,0,(H121-MIN(MAX(I144,0),H121))+MIN(MAX(0,J144-(H121-MIN(MAX(I144,0),H121))),MAX(0,0*H121-(I144-MIN(MAX(I144,0),H121))))) -> 0 | I145: =IF($A145>20,I144,(I144-H121+H145)*(1+$B$7)) -> 0 | J145: =IF($A145>20,J144,(J144-H145)*(1+$B$6)) -> -2.8478098e-10 | K145: =IF($A145>20,0,(K121-MIN(MAX(L144,0),K121))+MIN(MAX(0,M144-(K121-MIN(MAX(L144,0),K121))),MAX(0,0*K121-(L144-MIN(MAX(L144,0),K121))))) -> 0 | L145: =IF($A145>20,L144,(L144-K121+K145)*(1+$B$7)) -> 0 | M145: =IF($A145>20,M144,(M144-K145)*(1+$B$6)) -> -8.24366e-11 | N145: =IF($A145>20,0,(N121-MIN(MAX(O144,0),N121))+MIN(MAX(0,P144-(N121-MIN(MAX(O144,0),N121))),MAX(0,0*N121-(O144-MIN(MAX(O144,0),N121))))) -> 0 | O145: =IF($A145>20,O144,(O144-N121+N145)*(1+$B$7)) -> 0 | P145: =IF($A145>20,P144,(P144-N145)*(1+$B$6)) -> -8.24366e-11 | Q145: =IF($A145>20,0,(Q121-MIN(MAX(R144,0),Q121))+MIN(MAX(0,S144-(Q121-MIN(MAX(R144,0),Q121))),MAX(0,0*Q121-(R144-MIN(MAX(R144,0),Q121))))) -> 0 | R145: =IF($A145>20,R144,(R144-Q121+Q145)*(1+$B$7)) -> 0 | S145: =IF($A145>20,S144,(S144-Q145)*(1+$B$6)) -> -8.24366e-11
A146: =23 -> 23 | B146: =IF($A146>20,0,(B121-MIN(MAX(C145,0),B121))+MIN(MAX(0,D145-(B121-MIN(MAX(C145,0),B121))),MAX(0,0*B121-(C145-MIN(MAX(C145,0),B121))))) -> 0 | C146: =IF($A146>20,C145,(C145-B121+B146)*(1+$B$7)) -> 0 | D146: =IF($A146>20,D145,(D145-B146)*(1+$B$6)) -> 975816.66 | E146: =IF($A146>20,0,(E121-MIN(MAX(F145,0),E121))+MIN(MAX(0,G145-(E121-MIN(MAX(F145,0),E121))),MAX(0,0*E121-(F145-MIN(MAX(F145,0),E121))))) -> 0 | F146: =IF($A146>20,F145,(F145-E121+E146)*(1+$B$7)) -> 0 | G146: =IF($A146>20,G145,(G145-E146)*(1+$B$6)) -> -269625.19 | H146: =IF($A146>20,0,(H121-MIN(MAX(I145,0),H121))+MIN(MAX(0,J145-(H121-MIN(MAX(I145,0),H121))),MAX(0,0*H121-(I145-MIN(MAX(I145,0),H121))))) -> 0 | I146: =IF($A146>20,I145,(I145-H121+H146)*(1+$B$7)) -> 0 | J146: =IF($A146>20,J145,(J145-H146)*(1+$B$6)) -> -2.8478098e-10 | K146: =IF($A146>20,0,(K121-MIN(MAX(L145,0),K121))+MIN(MAX(0,M145-(K121-MIN(MAX(L145,0),K121))),MAX(0,0*K121-(L145-MIN(MAX(L145,0),K121))))) -> 0 | L146: =IF($A146>20,L145,(L145-K121+K146)*(1+$B$7)) -> 0 | M146: =IF($A146>20,M145,(M145-K146)*(1+$B$6)) -> -8.24366e-11 | N146: =IF($A146>20,0,(N121-MIN(MAX(O145,0),N121))+MIN(MAX(0,P145-(N121-MIN(MAX(O145,0),N121))),MAX(0,0*N121-(O145-MIN(MAX(O145,0),N121))))) -> 0 | O146: =IF($A146>20,O145,(O145-N121+N146)*(1+$B$7)) -> 0 | P146: =IF($A146>20,P145,(P145-N146)*(1+$B$6)) -> -8.24366e-11 | Q146: =IF($A146>20,0,(Q121-MIN(MAX(R145,0),Q121))+MIN(MAX(0,S145-(Q121-MIN(MAX(R145,0),Q121))),MAX(0,0*Q121-(R145-MIN(MAX(R145,0),Q121))))) -> 0 | R146: =IF($A146>20,R145,(R145-Q121+Q146)*(1+$B$7)) -> 0 | S146: =IF($A146>20,S145,(S145-Q146)*(1+$B$6)) -> -8.24366e-11
A147: =24 -> 24 | B147: =IF($A147>20,0,(B121-MIN(MAX(C146,0),B121))+MIN(MAX(0,D146-(B121-MIN(MAX(C146,0),B121))),MAX(0,0*B121-(C146-MIN(MAX(C146,0),B121))))) -> 0 | C147: =IF($A147>20,C146,(C146-B121+B147)*(1+$B$7)) -> 0 | D147: =IF($A147>20,D146,(D146-B147)*(1+$B$6)) -> 975816.66 | E147: =IF($A147>20,0,(E121-MIN(MAX(F146,0),E121))+MIN(MAX(0,G146-(E121-MIN(MAX(F146,0),E121))),MAX(0,0*E121-(F146-MIN(MAX(F146,0),E121))))) -> 0 | F147: =IF($A147>20,F146,(F146-E121+E147)*(1+$B$7)) -> 0 | G147: =IF($A147>20,G146,(G146-E147)*(1+$B$6)) -> -269625.19 | H147: =IF($A147>20,0,(H121-MIN(MAX(I146,0),H121))+MIN(MAX(0,J146-(H121-MIN(MAX(I146,0),H121))),MAX(0,0*H121-(I146-MIN(MAX(I146,0),H121))))) -> 0 | I147: =IF($A147>20,I146,(I146-H121+H147)*(1+$B$7)) -> 0 | J147: =IF($A147>20,J146,(J146-H147)*(1+$B$6)) -> -2.8478098e-10 | K147: =IF($A147>20,0,(K121-MIN(MAX(L146,0),K121))+MIN(MAX(0,M146-(K121-MIN(MAX(L146,0),K121))),MAX(0,0*K121-(L146-MIN(MAX(L146,0),K121))))) -> 0 | L147: =IF($A147>20,L146,(L146-K121+K147)*(1+$B$7)) -> 0 | M147: =IF($A147>20,M146,(M146-K147)*(1+$B$6)) -> -8.24366e-11 | N147: =IF($A147>20,0,(N121-MIN(MAX(O146,0),N121))+MIN(MAX(0,P146-(N121-MIN(MAX(O146,0),N121))),MAX(0,0*N121-(O146-MIN(MAX(O146,0),N121))))) -> 0 | O147: =IF($A147>20,O146,(O146-N121+N147)*(1+$B$7)) -> 0 | P147: =IF($A147>20,P146,(P146-N147)*(1+$B$6)) -> -8.24366e-11 | Q147: =IF($A147>20,0,(Q121-MIN(MAX(R146,0),Q121))+MIN(MAX(0,S146-(Q121-MIN(MAX(R146,0),Q121))),MAX(0,0*Q121-(R146-MIN(MAX(R146,0),Q121))))) -> 0 | R147: =IF($A147>20,R146,(R146-Q121+Q147)*(1+$B$7)) -> 0 | S147: =IF($A147>20,S146,(S146-Q147)*(1+$B$6)) -> -8.24366e-11
A148: =25 -> 25 | B148: =IF($A148>20,0,(B121-MIN(MAX(C147,0),B121))+MIN(MAX(0,D147-(B121-MIN(MAX(C147,0),B121))),MAX(0,0*B121-(C147-MIN(MAX(C147,0),B121))))) -> 0 | C148: =IF($A148>20,C147,(C147-B121+B148)*(1+$B$7)) -> 0 | D148: =IF($A148>20,D147,(D147-B148)*(1+$B$6)) -> 975816.66 | E148: =IF($A148>20,0,(E121-MIN(MAX(F147,0),E121))+MIN(MAX(0,G147-(E121-MIN(MAX(F147,0),E121))),MAX(0,0*E121-(F147-MIN(MAX(F147,0),E121))))) -> 0 | F148: =IF($A148>20,F147,(F147-E121+E148)*(1+$B$7)) -> 0 | G148: =IF($A148>20,G147,(G147-E148)*(1+$B$6)) -> -269625.19 | H148: =IF($A148>20,0,(H121-MIN(MAX(I147,0),H121))+MIN(MAX(0,J147-(H121-MIN(MAX(I147,0),H121))),MAX(0,0*H121-(I147-MIN(MAX(I147,0),H121))))) -> 0 | I148: =IF($A148>20,I147,(I147-H121+H148)*(1+$B$7)) -> 0 | J148: =IF($A148>20,J147,(J147-H148)*(1+$B$6)) -> -2.8478098e-10 | K148: =IF($A148>20,0,(K121-MIN(MAX(L147,0),K121))+MIN(MAX(0,M147-(K121-MIN(MAX(L147,0),K121))),MAX(0,0*K121-(L147-MIN(MAX(L147,0),K121))))) -> 0 | L148: =IF($A148>20,L147,(L147-K121+K148)*(1+$B$7)) -> 0 | M148: =IF($A148>20,M147,(M147-K148)*(1+$B$6)) -> -8.24366e-11 | N148: =IF($A148>20,0,(N121-MIN(MAX(O147,0),N121))+MIN(MAX(0,P147-(N121-MIN(MAX(O147,0),N121))),MAX(0,0*N121-(O147-MIN(MAX(O147,0),N121))))) -> 0 | O148: =IF($A148>20,O147,(O147-N121+N148)*(1+$B$7)) -> 0 | P148: =IF($A148>20,P147,(P147-N148)*(1+$B$6)) -> -8.24366e-11 | Q148: =IF($A148>20,0,(Q121-MIN(MAX(R147,0),Q121))+MIN(MAX(0,S147-(Q121-MIN(MAX(R147,0),Q121))),MAX(0,0*Q121-(R147-MIN(MAX(R147,0),Q121))))) -> 0 | R148: =IF($A148>20,R147,(R147-Q121+Q148)*(1+$B$7)) -> 0 | S148: =IF($A148>20,S147,(S147-Q148)*(1+$B$6)) -> -8.24366e-11
A149: =26 -> 26 | B149: =IF($A149>20,0,(B121-MIN(MAX(C148,0),B121))+MIN(MAX(0,D148-(B121-MIN(MAX(C148,0),B121))),MAX(0,0*B121-(C148-MIN(MAX(C148,0),B121))))) -> 0 | C149: =IF($A149>20,C148,(C148-B121+B149)*(1+$B$7)) -> 0 | D149: =IF($A149>20,D148,(D148-B149)*(1+$B$6)) -> 975816.66 | E149: =IF($A149>20,0,(E121-MIN(MAX(F148,0),E121))+MIN(MAX(0,G148-(E121-MIN(MAX(F148,0),E121))),MAX(0,0*E121-(F148-MIN(MAX(F148,0),E121))))) -> 0 | F149: =IF($A149>20,F148,(F148-E121+E149)*(1+$B$7)) -> 0 | G149: =IF($A149>20,G148,(G148-E149)*(1+$B$6)) -> -269625.19 | H149: =IF($A149>20,0,(H121-MIN(MAX(I148,0),H121))+MIN(MAX(0,J148-(H121-MIN(MAX(I148,0),H121))),MAX(0,0*H121-(I148-MIN(MAX(I148,0),H121))))) -> 0 | I149: =IF($A149>20,I148,(I148-H121+H149)*(1+$B$7)) -> 0 | J149: =IF($A149>20,J148,(J148-H149)*(1+$B$6)) -> -2.8478098e-10 | K149: =IF($A149>20,0,(K121-MIN(MAX(L148,0),K121))+MIN(MAX(0,M148-(K121-MIN(MAX(L148,0),K121))),MAX(0,0*K121-(L148-MIN(MAX(L148,0),K121))))) -> 0 | L149: =IF($A149>20,L148,(L148-K121+K149)*(1+$B$7)) -> 0 | M149: =IF($A149>20,M148,(M148-K149)*(1+$B$6)) -> -8.24366e-11 | N149: =IF($A149>20,0,(N121-MIN(MAX(O148,0),N121))+MIN(MAX(0,P148-(N121-MIN(MAX(O148,0),N121))),MAX(0,0*N121-(O148-MIN(MAX(O148,0),N121))))) -> 0 | O149: =IF($A149>20,O148,(O148-N121+N149)*(1+$B$7)) -> 0 | P149: =IF($A149>20,P148,(P148-N149)*(1+$B$6)) -> -8.24366e-11 | Q149: =IF($A149>20,0,(Q121-MIN(MAX(R148,0),Q121))+MIN(MAX(0,S148-(Q121-MIN(MAX(R148,0),Q121))),MAX(0,0*Q121-(R148-MIN(MAX(R148,0),Q121))))) -> 0 | R149: =IF($A149>20,R148,(R148-Q121+Q149)*(1+$B$7)) -> 0 | S149: =IF($A149>20,S148,(S148-Q149)*(1+$B$6)) -> -8.24366e-11
A150: =27 -> 27 | B150: =IF($A150>20,0,(B121-MIN(MAX(C149,0),B121))+MIN(MAX(0,D149-(B121-MIN(MAX(C149,0),B121))),MAX(0,0*B121-(C149-MIN(MAX(C149,0),B121))))) -> 0 | C150: =IF($A150>20,C149,(C149-B121+B150)*(1+$B$7)) -> 0 | D150: =IF($A150>20,D149,(D149-B150)*(1+$B$6)) -> 975816.66 | E150: =IF($A150>20,0,(E121-MIN(MAX(F149,0),E121))+MIN(MAX(0,G149-(E121-MIN(MAX(F149,0),E121))),MAX(0,0*E121-(F149-MIN(MAX(F149,0),E121))))) -> 0 | F150: =IF($A150>20,F149,(F149-E121+E150)*(1+$B$7)) -> 0 | G150: =IF($A150>20,G149,(G149-E150)*(1+$B$6)) -> -269625.19 | H150: =IF($A150>20,0,(H121-MIN(MAX(I149,0),H121))+MIN(MAX(0,J149-(H121-MIN(MAX(I149,0),H121))),MAX(0,0*H121-(I149-MIN(MAX(I149,0),H121))))) -> 0 | I150: =IF($A150>20,I149,(I149-H121+H150)*(1+$B$7)) -> 0 | J150: =IF($A150>20,J149,(J149-H150)*(1+$B$6)) -> -2.8478098e-10 | K150: =IF($A150>20,0,(K121-MIN(MAX(L149,0),K121))+MIN(MAX(0,M149-(K121-MIN(MAX(L149,0),K121))),MAX(0,0*K121-(L149-MIN(MAX(L149,0),K121))))) -> 0 | L150: =IF($A150>20,L149,(L149-K121+K150)*(1+$B$7)) -> 0 | M150: =IF($A150>20,M149,(M149-K150)*(1+$B$6)) -> -8.24366e-11 | N150: =IF($A150>20,0,(N121-MIN(MAX(O149,0),N121))+MIN(MAX(0,P149-(N121-MIN(MAX(O149,0),N121))),MAX(0,0*N121-(O149-MIN(MAX(O149,0),N121))))) -> 0 | O150: =IF($A150>20,O149,(O149-N121+N150)*(1+$B$7)) -> 0 | P150: =IF($A150>20,P149,(P149-N150)*(1+$B$6)) -> -8.24366e-11 | Q150: =IF($A150>20,0,(Q121-MIN(MAX(R149,0),Q121))+MIN(MAX(0,S149-(Q121-MIN(MAX(R149,0),Q121))),MAX(0,0*Q121-(R149-MIN(MAX(R149,0),Q121))))) -> 0 | R150: =IF($A150>20,R149,(R149-Q121+Q150)*(1+$B$7)) -> 0 | S150: =IF($A150>20,S149,(S149-Q150)*(1+$B$6)) -> -8.24366e-11
A151: =28 -> 28 | B151: =IF($A151>20,0,(B121-MIN(MAX(C150,0),B121))+MIN(MAX(0,D150-(B121-MIN(MAX(C150,0),B121))),MAX(0,0*B121-(C150-MIN(MAX(C150,0),B121))))) -> 0 | C151: =IF($A151>20,C150,(C150-B121+B151)*(1+$B$7)) -> 0 | D151: =IF($A151>20,D150,(D150-B151)*(1+$B$6)) -> 975816.66 | E151: =IF($A151>20,0,(E121-MIN(MAX(F150,0),E121))+MIN(MAX(0,G150-(E121-MIN(MAX(F150,0),E121))),MAX(0,0*E121-(F150-MIN(MAX(F150,0),E121))))) -> 0 | F151: =IF($A151>20,F150,(F150-E121+E151)*(1+$B$7)) -> 0 | G151: =IF($A151>20,G150,(G150-E151)*(1+$B$6)) -> -269625.19 | H151: =IF($A151>20,0,(H121-MIN(MAX(I150,0),H121))+MIN(MAX(0,J150-(H121-MIN(MAX(I150,0),H121))),MAX(0,0*H121-(I150-MIN(MAX(I150,0),H121))))) -> 0 | I151: =IF($A151>20,I150,(I150-H121+H151)*(1+$B$7)) -> 0 | J151: =IF($A151>20,J150,(J150-H151)*(1+$B$6)) -> -2.8478098e-10 | K151: =IF($A151>20,0,(K121-MIN(MAX(L150,0),K121))+MIN(MAX(0,M150-(K121-MIN(MAX(L150,0),K121))),MAX(0,0*K121-(L150-MIN(MAX(L150,0),K121))))) -> 0 | L151: =IF($A151>20,L150,(L150-K121+K151)*(1+$B$7)) -> 0 | M151: =IF($A151>20,M150,(M150-K151)*(1+$B$6)) -> -8.24366e-11 | N151: =IF($A151>20,0,(N121-MIN(MAX(O150,0),N121))+MIN(MAX(0,P150-(N121-MIN(MAX(O150,0),N121))),MAX(0,0*N121-(O150-MIN(MAX(O150,0),N121))))) -> 0 | O151: =IF($A151>20,O150,(O150-N121+N151)*(1+$B$7)) -> 0 | P151: =IF($A151>20,P150,(P150-N151)*(1+$B$6)) -> -8.24366e-11 | Q151: =IF($A151>20,0,(Q121-MIN(MAX(R150,0),Q121))+MIN(MAX(0,S150-(Q121-MIN(MAX(R150,0),Q121))),MAX(0,0*Q121-(R150-MIN(MAX(R150,0),Q121))))) -> 0 | R151: =IF($A151>20,R150,(R150-Q121+Q151)*(1+$B$7)) -> 0 | S151: =IF($A151>20,S150,(S150-Q151)*(1+$B$6)) -> -8.24366e-11
A152: =29 -> 29 | B152: =IF($A152>20,0,(B121-MIN(MAX(C151,0),B121))+MIN(MAX(0,D151-(B121-MIN(MAX(C151,0),B121))),MAX(0,0*B121-(C151-MIN(MAX(C151,0),B121))))) -> 0 | C152: =IF($A152>20,C151,(C151-B121+B152)*(1+$B$7)) -> 0 | D152: =IF($A152>20,D151,(D151-B152)*(1+$B$6)) -> 975816.66 | E152: =IF($A152>20,0,(E121-MIN(MAX(F151,0),E121))+MIN(MAX(0,G151-(E121-MIN(MAX(F151,0),E121))),MAX(0,0*E121-(F151-MIN(MAX(F151,0),E121))))) -> 0 | F152: =IF($A152>20,F151,(F151-E121+E152)*(1+$B$7)) -> 0 | G152: =IF($A152>20,G151,(G151-E152)*(1+$B$6)) -> -269625.19 | H152: =IF($A152>20,0,(H121-MIN(MAX(I151,0),H121))+MIN(MAX(0,J151-(H121-MIN(MAX(I151,0),H121))),MAX(0,0*H121-(I151-MIN(MAX(I151,0),H121))))) -> 0 | I152: =IF($A152>20,I151,(I151-H121+H152)*(1+$B$7)) -> 0 | J152: =IF($A152>20,J151,(J151-H152)*(1+$B$6)) -> -2.8478098e-10 | K152: =IF($A152>20,0,(K121-MIN(MAX(L151,0),K121))+MIN(MAX(0,M151-(K121-MIN(MAX(L151,0),K121))),MAX(0,0*K121-(L151-MIN(MAX(L151,0),K121))))) -> 0 | L152: =IF($A152>20,L151,(L151-K121+K152)*(1+$B$7)) -> 0 | M152: =IF($A152>20,M151,(M151-K152)*(1+$B$6)) -> -8.24366e-11 | N152: =IF($A152>20,0,(N121-MIN(MAX(O151,0),N121))+MIN(MAX(0,P151-(N121-MIN(MAX(O151,0),N121))),MAX(0,0*N121-(O151-MIN(MAX(O151,0),N121))))) -> 0 | O152: =IF($A152>20,O151,(O151-N121+N152)*(1+$B$7)) -> 0 | P152: =IF($A152>20,P151,(P151-N152)*(1+$B$6)) -> -8.24366e-11 | Q152: =IF($A152>20,0,(Q121-MIN(MAX(R151,0),Q121))+MIN(MAX(0,S151-(Q121-MIN(MAX(R151,0),Q121))),MAX(0,0*Q121-(R151-MIN(MAX(R151,0),Q121))))) -> 0 | R152: =IF($A152>20,R151,(R151-Q121+Q152)*(1+$B$7)) -> 0 | S152: =IF($A152>20,S151,(S151-Q152)*(1+$B$6)) -> -8.24366e-11
A153: =30 -> 30 | B153: =IF($A153>20,0,(B121-MIN(MAX(C152,0),B121))+MIN(MAX(0,D152-(B121-MIN(MAX(C152,0),B121))),MAX(0,0*B121-(C152-MIN(MAX(C152,0),B121))))) -> 0 | C153: =IF($A153>20,C152,(C152-B121+B153)*(1+$B$7)) -> 0 | D153: =IF($A153>20,D152,(D152-B153)*(1+$B$6)) -> 975816.66 | E153: =IF($A153>20,0,(E121-MIN(MAX(F152,0),E121))+MIN(MAX(0,G152-(E121-MIN(MAX(F152,0),E121))),MAX(0,0*E121-(F152-MIN(MAX(F152,0),E121))))) -> 0 | F153: =IF($A153>20,F152,(F152-E121+E153)*(1+$B$7)) -> 0 | G153: =IF($A153>20,G152,(G152-E153)*(1+$B$6)) -> -269625.19 | H153: =IF($A153>20,0,(H121-MIN(MAX(I152,0),H121))+MIN(MAX(0,J152-(H121-MIN(MAX(I152,0),H121))),MAX(0,0*H121-(I152-MIN(MAX(I152,0),H121))))) -> 0 | I153: =IF($A153>20,I152,(I152-H121+H153)*(1+$B$7)) -> 0 | J153: =IF($A153>20,J152,(J152-H153)*(1+$B$6)) -> -2.8478098e-10 | K153: =IF($A153>20,0,(K121-MIN(MAX(L152,0),K121))+MIN(MAX(0,M152-(K121-MIN(MAX(L152,0),K121))),MAX(0,0*K121-(L152-MIN(MAX(L152,0),K121))))) -> 0 | L153: =IF($A153>20,L152,(L152-K121+K153)*(1+$B$7)) -> 0 | M153: =IF($A153>20,M152,(M152-K153)*(1+$B$6)) -> -8.24366e-11 | N153: =IF($A153>20,0,(N121-MIN(MAX(O152,0),N121))+MIN(MAX(0,P152-(N121-MIN(MAX(O152,0),N121))),MAX(0,0*N121-(O152-MIN(MAX(O152,0),N121))))) -> 0 | O153: =IF($A153>20,O152,(O152-N121+N153)*(1+$B$7)) -> 0 | P153: =IF($A153>20,P152,(P152-N153)*(1+$B$6)) -> -8.24366e-11 | Q153: =IF($A153>20,0,(Q121-MIN(MAX(R152,0),Q121))+MIN(MAX(0,S152-(Q121-MIN(MAX(R152,0),Q121))),MAX(0,0*Q121-(R152-MIN(MAX(R152,0),Q121))))) -> 0 | R153: =IF($A153>20,R152,(R152-Q121+Q153)*(1+$B$7)) -> 0 | S153: =IF($A153>20,S152,(S152-Q153)*(1+$B$6)) -> -8.24366e-11
A154: =31 -> 31 | B154: =IF($A154>20,0,(B121-MIN(MAX(C153,0),B121))+MIN(MAX(0,D153-(B121-MIN(MAX(C153,0),B121))),MAX(0,0*B121-(C153-MIN(MAX(C153,0),B121))))) -> 0 | C154: =IF($A154>20,C153,(C153-B121+B154)*(1+$B$7)) -> 0 | D154: =IF($A154>20,D153,(D153-B154)*(1+$B$6)) -> 975816.66 | E154: =IF($A154>20,0,(E121-MIN(MAX(F153,0),E121))+MIN(MAX(0,G153-(E121-MIN(MAX(F153,0),E121))),MAX(0,0*E121-(F153-MIN(MAX(F153,0),E121))))) -> 0 | F154: =IF($A154>20,F153,(F153-E121+E154)*(1+$B$7)) -> 0 | G154: =IF($A154>20,G153,(G153-E154)*(1+$B$6)) -> -269625.19 | H154: =IF($A154>20,0,(H121-MIN(MAX(I153,0),H121))+MIN(MAX(0,J153-(H121-MIN(MAX(I153,0),H121))),MAX(0,0*H121-(I153-MIN(MAX(I153,0),H121))))) -> 0 | I154: =IF($A154>20,I153,(I153-H121+H154)*(1+$B$7)) -> 0 | J154: =IF($A154>20,J153,(J153-H154)*(1+$B$6)) -> -2.8478098e-10 | K154: =IF($A154>20,0,(K121-MIN(MAX(L153,0),K121))+MIN(MAX(0,M153-(K121-MIN(MAX(L153,0),K121))),MAX(0,0*K121-(L153-MIN(MAX(L153,0),K121))))) -> 0 | L154: =IF($A154>20,L153,(L153-K121+K154)*(1+$B$7)) -> 0 | M154: =IF($A154>20,M153,(M153-K154)*(1+$B$6)) -> -8.24366e-11 | N154: =IF($A154>20,0,(N121-MIN(MAX(O153,0),N121))+MIN(MAX(0,P153-(N121-MIN(MAX(O153,0),N121))),MAX(0,0*N121-(O153-MIN(MAX(O153,0),N121))))) -> 0 | O154: =IF($A154>20,O153,(O153-N121+N154)*(1+$B$7)) -> 0 | P154: =IF($A154>20,P153,(P153-N154)*(1+$B$6)) -> -8.24366e-11 | Q154: =IF($A154>20,0,(Q121-MIN(MAX(R153,0),Q121))+MIN(MAX(0,S153-(Q121-MIN(MAX(R153,0),Q121))),MAX(0,0*Q121-(R153-MIN(MAX(R153,0),Q121))))) -> 0 | R154: =IF($A154>20,R153,(R153-Q121+Q154)*(1+$B$7)) -> 0 | S154: =IF($A154>20,S153,(S153-Q154)*(1+$B$6)) -> -8.24366e-11
A155: =32 -> 32 | B155: =IF($A155>20,0,(B121-MIN(MAX(C154,0),B121))+MIN(MAX(0,D154-(B121-MIN(MAX(C154,0),B121))),MAX(0,0*B121-(C154-MIN(MAX(C154,0),B121))))) -> 0 | C155: =IF($A155>20,C154,(C154-B121+B155)*(1+$B$7)) -> 0 | D155: =IF($A155>20,D154,(D154-B155)*(1+$B$6)) -> 975816.66 | E155: =IF($A155>20,0,(E121-MIN(MAX(F154,0),E121))+MIN(MAX(0,G154-(E121-MIN(MAX(F154,0),E121))),MAX(0,0*E121-(F154-MIN(MAX(F154,0),E121))))) -> 0 | F155: =IF($A155>20,F154,(F154-E121+E155)*(1+$B$7)) -> 0 | G155: =IF($A155>20,G154,(G154-E155)*(1+$B$6)) -> -269625.19 | H155: =IF($A155>20,0,(H121-MIN(MAX(I154,0),H121))+MIN(MAX(0,J154-(H121-MIN(MAX(I154,0),H121))),MAX(0,0*H121-(I154-MIN(MAX(I154,0),H121))))) -> 0 | I155: =IF($A155>20,I154,(I154-H121+H155)*(1+$B$7)) -> 0 | J155: =IF($A155>20,J154,(J154-H155)*(1+$B$6)) -> -2.8478098e-10 | K155: =IF($A155>20,0,(K121-MIN(MAX(L154,0),K121))+MIN(MAX(0,M154-(K121-MIN(MAX(L154,0),K121))),MAX(0,0*K121-(L154-MIN(MAX(L154,0),K121))))) -> 0 | L155: =IF($A155>20,L154,(L154-K121+K155)*(1+$B$7)) -> 0 | M155: =IF($A155>20,M154,(M154-K155)*(1+$B$6)) -> -8.24366e-11 | N155: =IF($A155>20,0,(N121-MIN(MAX(O154,0),N121))+MIN(MAX(0,P154-(N121-MIN(MAX(O154,0),N121))),MAX(0,0*N121-(O154-MIN(MAX(O154,0),N121))))) -> 0 | O155: =IF($A155>20,O154,(O154-N121+N155)*(1+$B$7)) -> 0 | P155: =IF($A155>20,P154,(P154-N155)*(1+$B$6)) -> -8.24366e-11 | Q155: =IF($A155>20,0,(Q121-MIN(MAX(R154,0),Q121))+MIN(MAX(0,S154-(Q121-MIN(MAX(R154,0),Q121))),MAX(0,0*Q121-(R154-MIN(MAX(R154,0),Q121))))) -> 0 | R155: =IF($A155>20,R154,(R154-Q121+Q155)*(1+$B$7)) -> 0 | S155: =IF($A155>20,S154,(S154-Q155)*(1+$B$6)) -> -8.24366e-11
A156: =33 -> 33 | B156: =IF($A156>20,0,(B121-MIN(MAX(C155,0),B121))+MIN(MAX(0,D155-(B121-MIN(MAX(C155,0),B121))),MAX(0,0*B121-(C155-MIN(MAX(C155,0),B121))))) -> 0 | C156: =IF($A156>20,C155,(C155-B121+B156)*(1+$B$7)) -> 0 | D156: =IF($A156>20,D155,(D155-B156)*(1+$B$6)) -> 975816.66 | E156: =IF($A156>20,0,(E121-MIN(MAX(F155,0),E121))+MIN(MAX(0,G155-(E121-MIN(MAX(F155,0),E121))),MAX(0,0*E121-(F155-MIN(MAX(F155,0),E121))))) -> 0 | F156: =IF($A156>20,F155,(F155-E121+E156)*(1+$B$7)) -> 0 | G156: =IF($A156>20,G155,(G155-E156)*(1+$B$6)) -> -269625.19 | H156: =IF($A156>20,0,(H121-MIN(MAX(I155,0),H121))+MIN(MAX(0,J155-(H121-MIN(MAX(I155,0),H121))),MAX(0,0*H121-(I155-MIN(MAX(I155,0),H121))))) -> 0 | I156: =IF($A156>20,I155,(I155-H121+H156)*(1+$B$7)) -> 0 | J156: =IF($A156>20,J155,(J155-H156)*(1+$B$6)) -> -2.8478098e-10 | K156: =IF($A156>20,0,(K121-MIN(MAX(L155,0),K121))+MIN(MAX(0,M155-(K121-MIN(MAX(L155,0),K121))),MAX(0,0*K121-(L155-MIN(MAX(L155,0),K121))))) -> 0 | L156: =IF($A156>20,L155,(L155-K121+K156)*(1+$B$7)) -> 0 | M156: =IF($A156>20,M155,(M155-K156)*(1+$B$6)) -> -8.24366e-11 | N156: =IF($A156>20,0,(N121-MIN(MAX(O155,0),N121))+MIN(MAX(0,P155-(N121-MIN(MAX(O155,0),N121))),MAX(0,0*N121-(O155-MIN(MAX(O155,0),N121))))) -> 0 | O156: =IF($A156>20,O155,(O155-N121+N156)*(1+$B$7)) -> 0 | P156: =IF($A156>20,P155,(P155-N156)*(1+$B$6)) -> -8.24366e-11 | Q156: =IF($A156>20,0,(Q121-MIN(MAX(R155,0),Q121))+MIN(MAX(0,S155-(Q121-MIN(MAX(R155,0),Q121))),MAX(0,0*Q121-(R155-MIN(MAX(R155,0),Q121))))) -> 0 | R156: =IF($A156>20,R155,(R155-Q121+Q156)*(1+$B$7)) -> 0 | S156: =IF($A156>20,S155,(S155-Q156)*(1+$B$6)) -> -8.24366e-11
A157: =34 -> 34 | B157: =IF($A157>20,0,(B121-MIN(MAX(C156,0),B121))+MIN(MAX(0,D156-(B121-MIN(MAX(C156,0),B121))),MAX(0,0*B121-(C156-MIN(MAX(C156,0),B121))))) -> 0 | C157: =IF($A157>20,C156,(C156-B121+B157)*(1+$B$7)) -> 0 | D157: =IF($A157>20,D156,(D156-B157)*(1+$B$6)) -> 975816.66 | E157: =IF($A157>20,0,(E121-MIN(MAX(F156,0),E121))+MIN(MAX(0,G156-(E121-MIN(MAX(F156,0),E121))),MAX(0,0*E121-(F156-MIN(MAX(F156,0),E121))))) -> 0 | F157: =IF($A157>20,F156,(F156-E121+E157)*(1+$B$7)) -> 0 | G157: =IF($A157>20,G156,(G156-E157)*(1+$B$6)) -> -269625.19 | H157: =IF($A157>20,0,(H121-MIN(MAX(I156,0),H121))+MIN(MAX(0,J156-(H121-MIN(MAX(I156,0),H121))),MAX(0,0*H121-(I156-MIN(MAX(I156,0),H121))))) -> 0 | I157: =IF($A157>20,I156,(I156-H121+H157)*(1+$B$7)) -> 0 | J157: =IF($A157>20,J156,(J156-H157)*(1+$B$6)) -> -2.8478098e-10 | K157: =IF($A157>20,0,(K121-MIN(MAX(L156,0),K121))+MIN(MAX(0,M156-(K121-MIN(MAX(L156,0),K121))),MAX(0,0*K121-(L156-MIN(MAX(L156,0),K121))))) -> 0 | L157: =IF($A157>20,L156,(L156-K121+K157)*(1+$B$7)) -> 0 | M157: =IF($A157>20,M156,(M156-K157)*(1+$B$6)) -> -8.24366e-11 | N157: =IF($A157>20,0,(N121-MIN(MAX(O156,0),N121))+MIN(MAX(0,P156-(N121-MIN(MAX(O156,0),N121))),MAX(0,0*N121-(O156-MIN(MAX(O156,0),N121))))) -> 0 | O157: =IF($A157>20,O156,(O156-N121+N157)*(1+$B$7)) -> 0 | P157: =IF($A157>20,P156,(P156-N157)*(1+$B$6)) -> -8.24366e-11 | Q157: =IF($A157>20,0,(Q121-MIN(MAX(R156,0),Q121))+MIN(MAX(0,S156-(Q121-MIN(MAX(R156,0),Q121))),MAX(0,0*Q121-(R156-MIN(MAX(R156,0),Q121))))) -> 0 | R157: =IF($A157>20,R156,(R156-Q121+Q157)*(1+$B$7)) -> 0 | S157: =IF($A157>20,S156,(S156-Q157)*(1+$B$6)) -> -8.24366e-11
A158: =35 -> 35 | B158: =IF($A158>20,0,(B121-MIN(MAX(C157,0),B121))+MIN(MAX(0,D157-(B121-MIN(MAX(C157,0),B121))),MAX(0,0*B121-(C157-MIN(MAX(C157,0),B121))))) -> 0 | C158: =IF($A158>20,C157,(C157-B121+B158)*(1+$B$7)) -> 0 | D158: =IF($A158>20,D157,(D157-B158)*(1+$B$6)) -> 975816.66 | E158: =IF($A158>20,0,(E121-MIN(MAX(F157,0),E121))+MIN(MAX(0,G157-(E121-MIN(MAX(F157,0),E121))),MAX(0,0*E121-(F157-MIN(MAX(F157,0),E121))))) -> 0 | F158: =IF($A158>20,F157,(F157-E121+E158)*(1+$B$7)) -> 0 | G158: =IF($A158>20,G157,(G157-E158)*(1+$B$6)) -> -269625.19 | H158: =IF($A158>20,0,(H121-MIN(MAX(I157,0),H121))+MIN(MAX(0,J157-(H121-MIN(MAX(I157,0),H121))),MAX(0,0*H121-(I157-MIN(MAX(I157,0),H121))))) -> 0 | I158: =IF($A158>20,I157,(I157-H121+H158)*(1+$B$7)) -> 0 | J158: =IF($A158>20,J157,(J157-H158)*(1+$B$6)) -> -2.8478098e-10 | K158: =IF($A158>20,0,(K121-MIN(MAX(L157,0),K121))+MIN(MAX(0,M157-(K121-MIN(MAX(L157,0),K121))),MAX(0,0*K121-(L157-MIN(MAX(L157,0),K121))))) -> 0 | L158: =IF($A158>20,L157,(L157-K121+K158)*(1+$B$7)) -> 0 | M158: =IF($A158>20,M157,(M157-K158)*(1+$B$6)) -> -8.24366e-11 | N158: =IF($A158>20,0,(N121-MIN(MAX(O157,0),N121))+MIN(MAX(0,P157-(N121-MIN(MAX(O157,0),N121))),MAX(0,0*N121-(O157-MIN(MAX(O157,0),N121))))) -> 0 | O158: =IF($A158>20,O157,(O157-N121+N158)*(1+$B$7)) -> 0 | P158: =IF($A158>20,P157,(P157-N158)*(1+$B$6)) -> -8.24366e-11 | Q158: =IF($A158>20,0,(Q121-MIN(MAX(R157,0),Q121))+MIN(MAX(0,S157-(Q121-MIN(MAX(R157,0),Q121))),MAX(0,0*Q121-(R157-MIN(MAX(R157,0),Q121))))) -> 0 | R158: =IF($A158>20,R157,(R157-Q121+Q158)*(1+$B$7)) -> 0 | S158: =IF($A158>20,S157,(S157-Q158)*(1+$B$6)) -> -8.24366e-11
A159: =36 -> 36 | B159: =IF($A159>20,0,(B121-MIN(MAX(C158,0),B121))+MIN(MAX(0,D158-(B121-MIN(MAX(C158,0),B121))),MAX(0,0*B121-(C158-MIN(MAX(C158,0),B121))))) -> 0 | C159: =IF($A159>20,C158,(C158-B121+B159)*(1+$B$7)) -> 0 | D159: =IF($A159>20,D158,(D158-B159)*(1+$B$6)) -> 975816.66 | E159: =IF($A159>20,0,(E121-MIN(MAX(F158,0),E121))+MIN(MAX(0,G158-(E121-MIN(MAX(F158,0),E121))),MAX(0,0*E121-(F158-MIN(MAX(F158,0),E121))))) -> 0 | F159: =IF($A159>20,F158,(F158-E121+E159)*(1+$B$7)) -> 0 | G159: =IF($A159>20,G158,(G158-E159)*(1+$B$6)) -> -269625.19 | H159: =IF($A159>20,0,(H121-MIN(MAX(I158,0),H121))+MIN(MAX(0,J158-(H121-MIN(MAX(I158,0),H121))),MAX(0,0*H121-(I158-MIN(MAX(I158,0),H121))))) -> 0 | I159: =IF($A159>20,I158,(I158-H121+H159)*(1+$B$7)) -> 0 | J159: =IF($A159>20,J158,(J158-H159)*(1+$B$6)) -> -2.8478098e-10 | K159: =IF($A159>20,0,(K121-MIN(MAX(L158,0),K121))+MIN(MAX(0,M158-(K121-MIN(MAX(L158,0),K121))),MAX(0,0*K121-(L158-MIN(MAX(L158,0),K121))))) -> 0 | L159: =IF($A159>20,L158,(L158-K121+K159)*(1+$B$7)) -> 0 | M159: =IF($A159>20,M158,(M158-K159)*(1+$B$6)) -> -8.24366e-11 | N159: =IF($A159>20,0,(N121-MIN(MAX(O158,0),N121))+MIN(MAX(0,P158-(N121-MIN(MAX(O158,0),N121))),MAX(0,0*N121-(O158-MIN(MAX(O158,0),N121))))) -> 0 | O159: =IF($A159>20,O158,(O158-N121+N159)*(1+$B$7)) -> 0 | P159: =IF($A159>20,P158,(P158-N159)*(1+$B$6)) -> -8.24366e-11 | Q159: =IF($A159>20,0,(Q121-MIN(MAX(R158,0),Q121))+MIN(MAX(0,S158-(Q121-MIN(MAX(R158,0),Q121))),MAX(0,0*Q121-(R158-MIN(MAX(R158,0),Q121))))) -> 0 | R159: =IF($A159>20,R158,(R158-Q121+Q159)*(1+$B$7)) -> 0 | S159: =IF($A159>20,S158,(S158-Q159)*(1+$B$6)) -> -8.24366e-11
A160: =37 -> 37 | B160: =IF($A160>20,0,(B121-MIN(MAX(C159,0),B121))+MIN(MAX(0,D159-(B121-MIN(MAX(C159,0),B121))),MAX(0,0*B121-(C159-MIN(MAX(C159,0),B121))))) -> 0 | C160: =IF($A160>20,C159,(C159-B121+B160)*(1+$B$7)) -> 0 | D160: =IF($A160>20,D159,(D159-B160)*(1+$B$6)) -> 975816.66 | E160: =IF($A160>20,0,(E121-MIN(MAX(F159,0),E121))+MIN(MAX(0,G159-(E121-MIN(MAX(F159,0),E121))),MAX(0,0*E121-(F159-MIN(MAX(F159,0),E121))))) -> 0 | F160: =IF($A160>20,F159,(F159-E121+E160)*(1+$B$7)) -> 0 | G160: =IF($A160>20,G159,(G159-E160)*(1+$B$6)) -> -269625.19 | H160: =IF($A160>20,0,(H121-MIN(MAX(I159,0),H121))+MIN(MAX(0,J159-(H121-MIN(MAX(I159,0),H121))),MAX(0,0*H121-(I159-MIN(MAX(I159,0),H121))))) -> 0 | I160: =IF($A160>20,I159,(I159-H121+H160)*(1+$B$7)) -> 0 | J160: =IF($A160>20,J159,(J159-H160)*(1+$B$6)) -> -2.8478098e-10 | K160: =IF($A160>20,0,(K121-MIN(MAX(L159,0),K121))+MIN(MAX(0,M159-(K121-MIN(MAX(L159,0),K121))),MAX(0,0*K121-(L159-MIN(MAX(L159,0),K121))))) -> 0 | L160: =IF($A160>20,L159,(L159-K121+K160)*(1+$B$7)) -> 0 | M160: =IF($A160>20,M159,(M159-K160)*(1+$B$6)) -> -8.24366e-11 | N160: =IF($A160>20,0,(N121-MIN(MAX(O159,0),N121))+MIN(MAX(0,P159-(N121-MIN(MAX(O159,0),N121))),MAX(0,0*N121-(O159-MIN(MAX(O159,0),N121))))) -> 0 | O160: =IF($A160>20,O159,(O159-N121+N160)*(1+$B$7)) -> 0 | P160: =IF($A160>20,P159,(P159-N160)*(1+$B$6)) -> -8.24366e-11 | Q160: =IF($A160>20,0,(Q121-MIN(MAX(R159,0),Q121))+MIN(MAX(0,S159-(Q121-MIN(MAX(R159,0),Q121))),MAX(0,0*Q121-(R159-MIN(MAX(R159,0),Q121))))) -> 0 | R160: =IF($A160>20,R159,(R159-Q121+Q160)*(1+$B$7)) -> 0 | S160: =IF($A160>20,S159,(S159-Q160)*(1+$B$6)) -> -8.24366e-11
A161: =38 -> 38 | B161: =IF($A161>20,0,(B121-MIN(MAX(C160,0),B121))+MIN(MAX(0,D160-(B121-MIN(MAX(C160,0),B121))),MAX(0,0*B121-(C160-MIN(MAX(C160,0),B121))))) -> 0 | C161: =IF($A161>20,C160,(C160-B121+B161)*(1+$B$7)) -> 0 | D161: =IF($A161>20,D160,(D160-B161)*(1+$B$6)) -> 975816.66 | E161: =IF($A161>20,0,(E121-MIN(MAX(F160,0),E121))+MIN(MAX(0,G160-(E121-MIN(MAX(F160,0),E121))),MAX(0,0*E121-(F160-MIN(MAX(F160,0),E121))))) -> 0 | F161: =IF($A161>20,F160,(F160-E121+E161)*(1+$B$7)) -> 0 | G161: =IF($A161>20,G160,(G160-E161)*(1+$B$6)) -> -269625.19 | H161: =IF($A161>20,0,(H121-MIN(MAX(I160,0),H121))+MIN(MAX(0,J160-(H121-MIN(MAX(I160,0),H121))),MAX(0,0*H121-(I160-MIN(MAX(I160,0),H121))))) -> 0 | I161: =IF($A161>20,I160,(I160-H121+H161)*(1+$B$7)) -> 0 | J161: =IF($A161>20,J160,(J160-H161)*(1+$B$6)) -> -2.8478098e-10 | K161: =IF($A161>20,0,(K121-MIN(MAX(L160,0),K121))+MIN(MAX(0,M160-(K121-MIN(MAX(L160,0),K121))),MAX(0,0*K121-(L160-MIN(MAX(L160,0),K121))))) -> 0 | L161: =IF($A161>20,L160,(L160-K121+K161)*(1+$B$7)) -> 0 | M161: =IF($A161>20,M160,(M160-K161)*(1+$B$6)) -> -8.24366e-11 | N161: =IF($A161>20,0,(N121-MIN(MAX(O160,0),N121))+MIN(MAX(0,P160-(N121-MIN(MAX(O160,0),N121))),MAX(0,0*N121-(O160-MIN(MAX(O160,0),N121))))) -> 0 | O161: =IF($A161>20,O160,(O160-N121+N161)*(1+$B$7)) -> 0 | P161: =IF($A161>20,P160,(P160-N161)*(1+$B$6)) -> -8.24366e-11 | Q161: =IF($A161>20,0,(Q121-MIN(MAX(R160,0),Q121))+MIN(MAX(0,S160-(Q121-MIN(MAX(R160,0),Q121))),MAX(0,0*Q121-(R160-MIN(MAX(R160,0),Q121))))) -> 0 | R161: =IF($A161>20,R160,(R160-Q121+Q161)*(1+$B$7)) -> 0 | S161: =IF($A161>20,S160,(S160-Q161)*(1+$B$6)) -> -8.24366e-11
A162: =39 -> 39 | B162: =IF($A162>20,0,(B121-MIN(MAX(C161,0),B121))+MIN(MAX(0,D161-(B121-MIN(MAX(C161,0),B121))),MAX(0,0*B121-(C161-MIN(MAX(C161,0),B121))))) -> 0 | C162: =IF($A162>20,C161,(C161-B121+B162)*(1+$B$7)) -> 0 | D162: =IF($A162>20,D161,(D161-B162)*(1+$B$6)) -> 975816.66 | E162: =IF($A162>20,0,(E121-MIN(MAX(F161,0),E121))+MIN(MAX(0,G161-(E121-MIN(MAX(F161,0),E121))),MAX(0,0*E121-(F161-MIN(MAX(F161,0),E121))))) -> 0 | F162: =IF($A162>20,F161,(F161-E121+E162)*(1+$B$7)) -> 0 | G162: =IF($A162>20,G161,(G161-E162)*(1+$B$6)) -> -269625.19 | H162: =IF($A162>20,0,(H121-MIN(MAX(I161,0),H121))+MIN(MAX(0,J161-(H121-MIN(MAX(I161,0),H121))),MAX(0,0*H121-(I161-MIN(MAX(I161,0),H121))))) -> 0 | I162: =IF($A162>20,I161,(I161-H121+H162)*(1+$B$7)) -> 0 | J162: =IF($A162>20,J161,(J161-H162)*(1+$B$6)) -> -2.8478098e-10 | K162: =IF($A162>20,0,(K121-MIN(MAX(L161,0),K121))+MIN(MAX(0,M161-(K121-MIN(MAX(L161,0),K121))),MAX(0,0*K121-(L161-MIN(MAX(L161,0),K121))))) -> 0 | L162: =IF($A162>20,L161,(L161-K121+K162)*(1+$B$7)) -> 0 | M162: =IF($A162>20,M161,(M161-K162)*(1+$B$6)) -> -8.24366e-11 | N162: =IF($A162>20,0,(N121-MIN(MAX(O161,0),N121))+MIN(MAX(0,P161-(N121-MIN(MAX(O161,0),N121))),MAX(0,0*N121-(O161-MIN(MAX(O161,0),N121))))) -> 0 | O162: =IF($A162>20,O161,(O161-N121+N162)*(1+$B$7)) -> 0 | P162: =IF($A162>20,P161,(P161-N162)*(1+$B$6)) -> -8.24366e-11 | Q162: =IF($A162>20,0,(Q121-MIN(MAX(R161,0),Q121))+MIN(MAX(0,S161-(Q121-MIN(MAX(R161,0),Q121))),MAX(0,0*Q121-(R161-MIN(MAX(R161,0),Q121))))) -> 0 | R162: =IF($A162>20,R161,(R161-Q121+Q162)*(1+$B$7)) -> 0 | S162: =IF($A162>20,S161,(S161-Q162)*(1+$B$6)) -> -8.24366e-11
A163: =40 -> 40 | B163: =IF($A163>20,0,(B121-MIN(MAX(C162,0),B121))+MIN(MAX(0,D162-(B121-MIN(MAX(C162,0),B121))),MAX(0,0*B121-(C162-MIN(MAX(C162,0),B121))))) -> 0 | C163: =IF($A163>20,C162,(C162-B121+B163)*(1+$B$7)) -> 0 | D163: =IF($A163>20,D162,(D162-B163)*(1+$B$6)) -> 975816.66 | E163: =IF($A163>20,0,(E121-MIN(MAX(F162,0),E121))+MIN(MAX(0,G162-(E121-MIN(MAX(F162,0),E121))),MAX(0,0*E121-(F162-MIN(MAX(F162,0),E121))))) -> 0 | F163: =IF($A163>20,F162,(F162-E121+E163)*(1+$B$7)) -> 0 | G163: =IF($A163>20,G162,(G162-E163)*(1+$B$6)) -> -269625.19 | H163: =IF($A163>20,0,(H121-MIN(MAX(I162,0),H121))+MIN(MAX(0,J162-(H121-MIN(MAX(I162,0),H121))),MAX(0,0*H121-(I162-MIN(MAX(I162,0),H121))))) -> 0 | I163: =IF($A163>20,I162,(I162-H121+H163)*(1+$B$7)) -> 0 | J163: =IF($A163>20,J162,(J162-H163)*(1+$B$6)) -> -2.8478098e-10 | K163: =IF($A163>20,0,(K121-MIN(MAX(L162,0),K121))+MIN(MAX(0,M162-(K121-MIN(MAX(L162,0),K121))),MAX(0,0*K121-(L162-MIN(MAX(L162,0),K121))))) -> 0 | L163: =IF($A163>20,L162,(L162-K121+K163)*(1+$B$7)) -> 0 | M163: =IF($A163>20,M162,(M162-K163)*(1+$B$6)) -> -8.24366e-11 | N163: =IF($A163>20,0,(N121-MIN(MAX(O162,0),N121))+MIN(MAX(0,P162-(N121-MIN(MAX(O162,0),N121))),MAX(0,0*N121-(O162-MIN(MAX(O162,0),N121))))) -> 0 | O163: =IF($A163>20,O162,(O162-N121+N163)*(1+$B$7)) -> 0 | P163: =IF($A163>20,P162,(P162-N163)*(1+$B$6)) -> -8.24366e-11 | Q163: =IF($A163>20,0,(Q121-MIN(MAX(R162,0),Q121))+MIN(MAX(0,S162-(Q121-MIN(MAX(R162,0),Q121))),MAX(0,0*Q121-(R162-MIN(MAX(R162,0),Q121))))) -> 0 | R163: =IF($A163>20,R162,(R162-Q121+Q163)*(1+$B$7)) -> 0 | S163: =IF($A163>20,S162,(S162-Q163)*(1+$B$6)) -> -8.24366e-11
B164: =C163+D163 -> 975816.66 | E164: =F163+G163 -> -269625.19 | H164: =I163+J163 -> -2.8478098e-10 | K164: =L163+M163 -> -8.24366e-11 | N164: =O163+P163 -> -8.24366e-11 | Q164: =R163+S163 -> -8.24366e-11
A165: SPESA MASSIMA SOSTENIBILE | B165: =IFERROR(Q121-Q164*(Q121-N121)/(Q164-N164),Q121) -> 65257.969
A167: GRIGLIA — orizzonte 20 anni · conto deposito · N = 1
B168: =0.03*$B$5 -> 30000 | E168: =0.075*$B$5 -> 75000 | H168: =IFERROR(E168-E211*(E168-B168)/(E211-B211),E168) -> 63545.786 | K168: =IFERROR(H168-H211*(H168-E168)/(H211-E211),H168) -> 63270.558 | N168: =IFERROR(K168-K211*(K168-H168)/(K211-H211),K168) -> 63270.801 | Q168: =IFERROR(N168-N211*(N168-K168)/(N211-K211),N168) -> 63270.801
A169: anno | B169: lordo venduto | C169: secchio 1 | D169: portafoglio | E169: lordo venduto | F169: secchio 1 | G169: portafoglio | H169: lordo venduto | I169: secchio 1 | J169: portafoglio | K169: lordo venduto | L169: secchio 1 | M169: portafoglio | N169: lordo venduto | O169: secchio 1 | P169: portafoglio | Q169: lordo venduto | R169: secchio 1 | S169: portafoglio
A170: 0 | C170: =MIN(1*B168,$B$5) -> 30000 | D170: =$B$5-C170 -> 970000 | F170: =MIN(1*E168,$B$5) -> 75000 | G170: =$B$5-F170 -> 925000 | I170: =MIN(1*H168,$B$5) -> 63545.786 | J170: =$B$5-I170 -> 936454.21 | L170: =MIN(1*K168,$B$5) -> 63270.558 | M170: =$B$5-L170 -> 936729.44 | O170: =MIN(1*N168,$B$5) -> 63270.801 | P170: =$B$5-O170 -> 936729.2 | R170: =MIN(1*Q168,$B$5) -> 63270.801 | S170: =$B$5-R170 -> 936729.2
A171: =1 -> 1 | B171: =IF($A171>20,0,(B168-MIN(MAX(C170,0),B168))+MIN(MAX(0,D170-(B168-MIN(MAX(C170,0),B168))),MAX(0,1*B168-(C170-MIN(MAX(C170,0),B168))))) -> 30000 | C171: =IF($A171>20,C170,(C170-B168+B171)*(1+$B$7)) -> 29892 | D171: =IF($A171>20,D170,(D170-B171)*(1+$B$6)) -> 968200 | E171: =IF($A171>20,0,(E168-MIN(MAX(F170,0),E168))+MIN(MAX(0,G170-(E168-MIN(MAX(F170,0),E168))),MAX(0,1*E168-(F170-MIN(MAX(F170,0),E168))))) -> 75000 | F171: =IF($A171>20,F170,(F170-E168+E171)*(1+$B$7)) -> 74730 | G171: =IF($A171>20,G170,(G170-E171)*(1+$B$6)) -> 875500 | H171: =IF($A171>20,0,(H168-MIN(MAX(I170,0),H168))+MIN(MAX(0,J170-(H168-MIN(MAX(I170,0),H168))),MAX(0,1*H168-(I170-MIN(MAX(I170,0),H168))))) -> 63545.786 | I171: =IF($A171>20,I170,(I170-H168+H171)*(1+$B$7)) -> 63317.021 | J171: =IF($A171>20,J170,(J170-H171)*(1+$B$6)) -> 899095.68 | K171: =IF($A171>20,0,(K168-MIN(MAX(L170,0),K168))+MIN(MAX(0,M170-(K168-MIN(MAX(L170,0),K168))),MAX(0,1*K168-(L170-MIN(MAX(L170,0),K168))))) -> 63270.558 | L171: =IF($A171>20,L170,(L170-K168+K171)*(1+$B$7)) -> 63042.784 | M171: =IF($A171>20,M170,(M170-K171)*(1+$B$6)) -> 899662.65 | N171: =IF($A171>20,0,(N168-MIN(MAX(O170,0),N168))+MIN(MAX(0,P170-(N168-MIN(MAX(O170,0),N168))),MAX(0,1*N168-(O170-MIN(MAX(O170,0),N168))))) -> 63270.801 | O171: =IF($A171>20,O170,(O170-N168+N171)*(1+$B$7)) -> 63043.026 | P171: =IF($A171>20,P170,(P170-N171)*(1+$B$6)) -> 899662.15 | Q171: =IF($A171>20,0,(Q168-MIN(MAX(R170,0),Q168))+MIN(MAX(0,S170-(Q168-MIN(MAX(R170,0),Q168))),MAX(0,1*Q168-(R170-MIN(MAX(R170,0),Q168))))) -> 63270.801 | R171: =IF($A171>20,R170,(R170-Q168+Q171)*(1+$B$7)) -> 63043.027 | S171: =IF($A171>20,S170,(S170-Q171)*(1+$B$6)) -> 899662.15
A172: =2 -> 2 | B172: =IF($A172>20,0,(B168-MIN(MAX(C171,0),B168))+MIN(MAX(0,D171-(B168-MIN(MAX(C171,0),B168))),MAX(0,1*B168-(C171-MIN(MAX(C171,0),B168))))) -> 30108 | C172: =IF($A172>20,C171,(C171-B168+B172)*(1+$B$7)) -> 29892 | D172: =IF($A172>20,D171,(D171-B172)*(1+$B$6)) -> 966234.76 | E172: =IF($A172>20,0,(E168-MIN(MAX(F171,0),E168))+MIN(MAX(0,G171-(E168-MIN(MAX(F171,0),E168))),MAX(0,1*E168-(F171-MIN(MAX(F171,0),E168))))) -> 75270 | F172: =IF($A172>20,F171,(F171-E168+E172)*(1+$B$7)) -> 74730 | G172: =IF($A172>20,G171,(G171-E172)*(1+$B$6)) -> 824236.9 | H172: =IF($A172>20,0,(H168-MIN(MAX(I171,0),H168))+MIN(MAX(0,J171-(H168-MIN(MAX(I171,0),H168))),MAX(0,1*H168-(I171-MIN(MAX(I171,0),H168))))) -> 63774.551 | I172: =IF($A172>20,I171,(I171-H168+H172)*(1+$B$7)) -> 63317.021 | J172: =IF($A172>20,J171,(J171-H172)*(1+$B$6)) -> 860380.76 | K172: =IF($A172>20,0,(K168-MIN(MAX(L171,0),K168))+MIN(MAX(0,M171-(K168-MIN(MAX(L171,0),K168))),MAX(0,1*K168-(L171-MIN(MAX(L171,0),K168))))) -> 63498.332 | L172: =IF($A172>20,L171,(L171-K168+K172)*(1+$B$7)) -> 63042.784 | M172: =IF($A172>20,M171,(M171-K172)*(1+$B$6)) -> 861249.25 | N172: =IF($A172>20,0,(N168-MIN(MAX(O171,0),N168))+MIN(MAX(0,P171-(N168-MIN(MAX(O171,0),N168))),MAX(0,1*N168-(O171-MIN(MAX(O171,0),N168))))) -> 63498.576 | O172: =IF($A172>20,O171,(O171-N168+N172)*(1+$B$7)) -> 63043.026 | P172: =IF($A172>20,P171,(P171-N172)*(1+$B$6)) -> 861248.48 | Q172: =IF($A172>20,0,(Q168-MIN(MAX(R171,0),Q168))+MIN(MAX(0,S171-(Q168-MIN(MAX(R171,0),Q168))),MAX(0,1*Q168-(R171-MIN(MAX(R171,0),Q168))))) -> 63498.576 | R172: =IF($A172>20,R171,(R171-Q168+Q172)*(1+$B$7)) -> 63043.027 | S172: =IF($A172>20,S171,(S171-Q172)*(1+$B$6)) -> 861248.48
A173: =3 -> 3 | B173: =IF($A173>20,0,(B168-MIN(MAX(C172,0),B168))+MIN(MAX(0,D172-(B168-MIN(MAX(C172,0),B168))),MAX(0,1*B168-(C172-MIN(MAX(C172,0),B168))))) -> 30108 | C173: =IF($A173>20,C172,(C172-B168+B173)*(1+$B$7)) -> 29892 | D173: =IF($A173>20,D172,(D172-B173)*(1+$B$6)) -> 964210.56 | E173: =IF($A173>20,0,(E168-MIN(MAX(F172,0),E168))+MIN(MAX(0,G172-(E168-MIN(MAX(F172,0),E168))),MAX(0,1*E168-(F172-MIN(MAX(F172,0),E168))))) -> 75270 | F173: =IF($A173>20,F172,(F172-E168+E173)*(1+$B$7)) -> 74730 | G173: =IF($A173>20,G172,(G172-E173)*(1+$B$6)) -> 771435.91 | H173: =IF($A173>20,0,(H168-MIN(MAX(I172,0),H168))+MIN(MAX(0,J172-(H168-MIN(MAX(I172,0),H168))),MAX(0,1*H168-(I172-MIN(MAX(I172,0),H168))))) -> 63774.551 | I173: =IF($A173>20,I172,(I172-H168+H173)*(1+$B$7)) -> 63317.021 | J173: =IF($A173>20,J172,(J172-H173)*(1+$B$6)) -> 820504.4 | K173: =IF($A173>20,0,(K168-MIN(MAX(L172,0),K168))+MIN(MAX(0,M172-(K168-MIN(MAX(L172,0),K168))),MAX(0,1*K168-(L172-MIN(MAX(L172,0),K168))))) -> 63498.332 | L173: =IF($A173>20,L172,(L172-K168+K173)*(1+$B$7)) -> 63042.784 | M173: =IF($A173>20,M172,(M172-K173)*(1+$B$6)) -> 821683.44 | N173: =IF($A173>20,0,(N168-MIN(MAX(O172,0),N168))+MIN(MAX(0,P172-(N168-MIN(MAX(O172,0),N168))),MAX(0,1*N168-(O172-MIN(MAX(O172,0),N168))))) -> 63498.576 | O173: =IF($A173>20,O172,(O172-N168+N173)*(1+$B$7)) -> 63043.026 | P173: =IF($A173>20,P172,(P172-N173)*(1+$B$6)) -> 821682.4 | Q173: =IF($A173>20,0,(Q168-MIN(MAX(R172,0),Q168))+MIN(MAX(0,S172-(Q168-MIN(MAX(R172,0),Q168))),MAX(0,1*Q168-(R172-MIN(MAX(R172,0),Q168))))) -> 63498.576 | R173: =IF($A173>20,R172,(R172-Q168+Q173)*(1+$B$7)) -> 63043.027 | S173: =IF($A173>20,S172,(S172-Q173)*(1+$B$6)) -> 821682.4
A174: =4 -> 4 | B174: =IF($A174>20,0,(B168-MIN(MAX(C173,0),B168))+MIN(MAX(0,D173-(B168-MIN(MAX(C173,0),B168))),MAX(0,1*B168-(C173-MIN(MAX(C173,0),B168))))) -> 30108 | C174: =IF($A174>20,C173,(C173-B168+B174)*(1+$B$7)) -> 29892 | D174: =IF($A174>20,D173,(D173-B174)*(1+$B$6)) -> 962125.64 | E174: =IF($A174>20,0,(E168-MIN(MAX(F173,0),E168))+MIN(MAX(0,G173-(E168-MIN(MAX(F173,0),E168))),MAX(0,1*E168-(F173-MIN(MAX(F173,0),E168))))) -> 75270 | F174: =IF($A174>20,F173,(F173-E168+E174)*(1+$B$7)) -> 74730 | G174: =IF($A174>20,G173,(G173-E174)*(1+$B$6)) -> 717050.88 | H174: =IF($A174>20,0,(H168-MIN(MAX(I173,0),H168))+MIN(MAX(0,J173-(H168-MIN(MAX(I173,0),H168))),MAX(0,1*H168-(I173-MIN(MAX(I173,0),H168))))) -> 63774.551 | I174: =IF($A174>20,I173,(I173-H168+H174)*(1+$B$7)) -> 63317.021 | J174: =IF($A174>20,J173,(J173-H174)*(1+$B$6)) -> 779431.74 | K174: =IF($A174>20,0,(K168-MIN(MAX(L173,0),K168))+MIN(MAX(0,M173-(K168-MIN(MAX(L173,0),K168))),MAX(0,1*K168-(L173-MIN(MAX(L173,0),K168))))) -> 63498.332 | L174: =IF($A174>20,L173,(L173-K168+K174)*(1+$B$7)) -> 63042.784 | M174: =IF($A174>20,M173,(M173-K174)*(1+$B$6)) -> 780930.66 | N174: =IF($A174>20,0,(N168-MIN(MAX(O173,0),N168))+MIN(MAX(0,P173-(N168-MIN(MAX(O173,0),N168))),MAX(0,1*N168-(O173-MIN(MAX(O173,0),N168))))) -> 63498.576 | O174: =IF($A174>20,O173,(O173-N168+N174)*(1+$B$7)) -> 63043.026 | P174: =IF($A174>20,P173,(P173-N174)*(1+$B$6)) -> 780929.34 | Q174: =IF($A174>20,0,(Q168-MIN(MAX(R173,0),Q168))+MIN(MAX(0,S173-(Q168-MIN(MAX(R173,0),Q168))),MAX(0,1*Q168-(R173-MIN(MAX(R173,0),Q168))))) -> 63498.576 | R174: =IF($A174>20,R173,(R173-Q168+Q174)*(1+$B$7)) -> 63043.027 | S174: =IF($A174>20,S173,(S173-Q174)*(1+$B$6)) -> 780929.34
A175: =5 -> 5 | B175: =IF($A175>20,0,(B168-MIN(MAX(C174,0),B168))+MIN(MAX(0,D174-(B168-MIN(MAX(C174,0),B168))),MAX(0,1*B168-(C174-MIN(MAX(C174,0),B168))))) -> 30108 | C175: =IF($A175>20,C174,(C174-B168+B175)*(1+$B$7)) -> 29892 | D175: =IF($A175>20,D174,(D174-B175)*(1+$B$6)) -> 959978.17 | E175: =IF($A175>20,0,(E168-MIN(MAX(F174,0),E168))+MIN(MAX(0,G174-(E168-MIN(MAX(F174,0),E168))),MAX(0,1*E168-(F174-MIN(MAX(F174,0),E168))))) -> 75270 | F175: =IF($A175>20,F174,(F174-E168+E175)*(1+$B$7)) -> 74730 | G175: =IF($A175>20,G174,(G174-E175)*(1+$B$6)) -> 661034.31 | H175: =IF($A175>20,0,(H168-MIN(MAX(I174,0),H168))+MIN(MAX(0,J174-(H168-MIN(MAX(I174,0),H168))),MAX(0,1*H168-(I174-MIN(MAX(I174,0),H168))))) -> 63774.551 | I175: =IF($A175>20,I174,(I174-H168+H175)*(1+$B$7)) -> 63317.021 | J175: =IF($A175>20,J174,(J174-H175)*(1+$B$6)) -> 737126.91 | K175: =IF($A175>20,0,(K168-MIN(MAX(L174,0),K168))+MIN(MAX(0,M174-(K168-MIN(MAX(L174,0),K168))),MAX(0,1*K168-(L174-MIN(MAX(L174,0),K168))))) -> 63498.332 | L175: =IF($A175>20,L174,(L174-K168+K175)*(1+$B$7)) -> 63042.784 | M175: =IF($A175>20,M174,(M174-K175)*(1+$B$6)) -> 738955.3 | N175: =IF($A175>20,0,(N168-MIN(MAX(O174,0),N168))+MIN(MAX(0,P174-(N168-MIN(MAX(O174,0),N168))),MAX(0,1*N168-(O174-MIN(MAX(O174,0),N168))))) -> 63498.576 | O175: =IF($A175>20,O174,(O174-N168+N175)*(1+$B$7)) -> 63043.026 | P175: =IF($A175>20,P174,(P174-N175)*(1+$B$6)) -> 738953.69 | Q175: =IF($A175>20,0,(Q168-MIN(MAX(R174,0),Q168))+MIN(MAX(0,S174-(Q168-MIN(MAX(R174,0),Q168))),MAX(0,1*Q168-(R174-MIN(MAX(R174,0),Q168))))) -> 63498.576 | R175: =IF($A175>20,R174,(R174-Q168+Q175)*(1+$B$7)) -> 63043.027 | S175: =IF($A175>20,S174,(S174-Q175)*(1+$B$6)) -> 738953.69
A176: =6 -> 6 | B176: =IF($A176>20,0,(B168-MIN(MAX(C175,0),B168))+MIN(MAX(0,D175-(B168-MIN(MAX(C175,0),B168))),MAX(0,1*B168-(C175-MIN(MAX(C175,0),B168))))) -> 30108 | C176: =IF($A176>20,C175,(C175-B168+B176)*(1+$B$7)) -> 29892 | D176: =IF($A176>20,D175,(D175-B176)*(1+$B$6)) -> 957766.27 | E176: =IF($A176>20,0,(E168-MIN(MAX(F175,0),E168))+MIN(MAX(0,G175-(E168-MIN(MAX(F175,0),E168))),MAX(0,1*E168-(F175-MIN(MAX(F175,0),E168))))) -> 75270 | F176: =IF($A176>20,F175,(F175-E168+E176)*(1+$B$7)) -> 74730 | G176: =IF($A176>20,G175,(G175-E176)*(1+$B$6)) -> 603337.24 | H176: =IF($A176>20,0,(H168-MIN(MAX(I175,0),H168))+MIN(MAX(0,J175-(H168-MIN(MAX(I175,0),H168))),MAX(0,1*H168-(I175-MIN(MAX(I175,0),H168))))) -> 63774.551 | I176: =IF($A176>20,I175,(I175-H168+H176)*(1+$B$7)) -> 63317.021 | J176: =IF($A176>20,J175,(J175-H176)*(1+$B$6)) -> 693552.93 | K176: =IF($A176>20,0,(K168-MIN(MAX(L175,0),K168))+MIN(MAX(0,M175-(K168-MIN(MAX(L175,0),K168))),MAX(0,1*K168-(L175-MIN(MAX(L175,0),K168))))) -> 63498.332 | L176: =IF($A176>20,L175,(L175-K168+K176)*(1+$B$7)) -> 63042.784 | M176: =IF($A176>20,M175,(M175-K176)*(1+$B$6)) -> 695720.68 | N176: =IF($A176>20,0,(N168-MIN(MAX(O175,0),N168))+MIN(MAX(0,P175-(N168-MIN(MAX(O175,0),N168))),MAX(0,1*N168-(O175-MIN(MAX(O175,0),N168))))) -> 63498.576 | O176: =IF($A176>20,O175,(O175-N168+N176)*(1+$B$7)) -> 63043.026 | P176: =IF($A176>20,P175,(P175-N176)*(1+$B$6)) -> 695718.76 | Q176: =IF($A176>20,0,(Q168-MIN(MAX(R175,0),Q168))+MIN(MAX(0,S175-(Q168-MIN(MAX(R175,0),Q168))),MAX(0,1*Q168-(R175-MIN(MAX(R175,0),Q168))))) -> 63498.576 | R176: =IF($A176>20,R175,(R175-Q168+Q176)*(1+$B$7)) -> 63043.027 | S176: =IF($A176>20,S175,(S175-Q176)*(1+$B$6)) -> 695718.76
A177: =7 -> 7 | B177: =IF($A177>20,0,(B168-MIN(MAX(C176,0),B168))+MIN(MAX(0,D176-(B168-MIN(MAX(C176,0),B168))),MAX(0,1*B168-(C176-MIN(MAX(C176,0),B168))))) -> 30108 | C177: =IF($A177>20,C176,(C176-B168+B177)*(1+$B$7)) -> 29892 | D177: =IF($A177>20,D176,(D176-B177)*(1+$B$6)) -> 955488.02 | E177: =IF($A177>20,0,(E168-MIN(MAX(F176,0),E168))+MIN(MAX(0,G176-(E168-MIN(MAX(F176,0),E168))),MAX(0,1*E168-(F176-MIN(MAX(F176,0),E168))))) -> 75270 | F177: =IF($A177>20,F176,(F176-E168+E177)*(1+$B$7)) -> 74730 | G177: =IF($A177>20,G176,(G176-E177)*(1+$B$6)) -> 543909.26 | H177: =IF($A177>20,0,(H168-MIN(MAX(I176,0),H168))+MIN(MAX(0,J176-(H168-MIN(MAX(I176,0),H168))),MAX(0,1*H168-(I176-MIN(MAX(I176,0),H168))))) -> 63774.551 | I177: =IF($A177>20,I176,(I176-H168+H177)*(1+$B$7)) -> 63317.021 | J177: =IF($A177>20,J176,(J176-H177)*(1+$B$6)) -> 648671.73 | K177: =IF($A177>20,0,(K168-MIN(MAX(L176,0),K168))+MIN(MAX(0,M176-(K168-MIN(MAX(L176,0),K168))),MAX(0,1*K168-(L176-MIN(MAX(L176,0),K168))))) -> 63498.332 | L177: =IF($A177>20,L176,(L176-K168+K177)*(1+$B$7)) -> 63042.784 | M177: =IF($A177>20,M176,(M176-K177)*(1+$B$6)) -> 651189.02 | N177: =IF($A177>20,0,(N168-MIN(MAX(O176,0),N168))+MIN(MAX(0,P176-(N168-MIN(MAX(O176,0),N168))),MAX(0,1*N168-(O176-MIN(MAX(O176,0),N168))))) -> 63498.576 | O177: =IF($A177>20,O176,(O176-N168+N177)*(1+$B$7)) -> 63043.026 | P177: =IF($A177>20,P176,(P176-N177)*(1+$B$6)) -> 651186.79 | Q177: =IF($A177>20,0,(Q168-MIN(MAX(R176,0),Q168))+MIN(MAX(0,S176-(Q168-MIN(MAX(R176,0),Q168))),MAX(0,1*Q168-(R176-MIN(MAX(R176,0),Q168))))) -> 63498.576 | R177: =IF($A177>20,R176,(R176-Q168+Q177)*(1+$B$7)) -> 63043.027 | S177: =IF($A177>20,S176,(S176-Q177)*(1+$B$6)) -> 651186.79
A178: =8 -> 8 | B178: =IF($A178>20,0,(B168-MIN(MAX(C177,0),B168))+MIN(MAX(0,D177-(B168-MIN(MAX(C177,0),B168))),MAX(0,1*B168-(C177-MIN(MAX(C177,0),B168))))) -> 30108 | C178: =IF($A178>20,C177,(C177-B168+B178)*(1+$B$7)) -> 29892 | D178: =IF($A178>20,D177,(D177-B178)*(1+$B$6)) -> 953141.42 | E178: =IF($A178>20,0,(E168-MIN(MAX(F177,0),E168))+MIN(MAX(0,G177-(E168-MIN(MAX(F177,0),E168))),MAX(0,1*E168-(F177-MIN(MAX(F177,0),E168))))) -> 75270 | F178: =IF($A178>20,F177,(F177-E168+E178)*(1+$B$7)) -> 74730 | G178: =IF($A178>20,G177,(G177-E178)*(1+$B$6)) -> 482698.43 | H178: =IF($A178>20,0,(H168-MIN(MAX(I177,0),H168))+MIN(MAX(0,J177-(H168-MIN(MAX(I177,0),H168))),MAX(0,1*H168-(I177-MIN(MAX(I177,0),H168))))) -> 63774.551 | I178: =IF($A178>20,I177,(I177-H168+H178)*(1+$B$7)) -> 63317.021 | J178: =IF($A178>20,J177,(J177-H178)*(1+$B$6)) -> 602444.1 | K178: =IF($A178>20,0,(K168-MIN(MAX(L177,0),K168))+MIN(MAX(0,M177-(K168-MIN(MAX(L177,0),K168))),MAX(0,1*K168-(L177-MIN(MAX(L177,0),K168))))) -> 63498.332 | L178: =IF($A178>20,L177,(L177-K168+K178)*(1+$B$7)) -> 63042.784 | M178: =IF($A178>20,M177,(M177-K178)*(1+$B$6)) -> 605321.4 | N178: =IF($A178>20,0,(N168-MIN(MAX(O177,0),N168))+MIN(MAX(0,P177-(N168-MIN(MAX(O177,0),N168))),MAX(0,1*N168-(O177-MIN(MAX(O177,0),N168))))) -> 63498.576 | O178: =IF($A178>20,O177,(O177-N168+N178)*(1+$B$7)) -> 63043.026 | P178: =IF($A178>20,P177,(P177-N178)*(1+$B$6)) -> 605318.86 | Q178: =IF($A178>20,0,(Q168-MIN(MAX(R177,0),Q168))+MIN(MAX(0,S177-(Q168-MIN(MAX(R177,0),Q168))),MAX(0,1*Q168-(R177-MIN(MAX(R177,0),Q168))))) -> 63498.576 | R178: =IF($A178>20,R177,(R177-Q168+Q178)*(1+$B$7)) -> 63043.027 | S178: =IF($A178>20,S177,(S177-Q178)*(1+$B$6)) -> 605318.86
A179: =9 -> 9 | B179: =IF($A179>20,0,(B168-MIN(MAX(C178,0),B168))+MIN(MAX(0,D178-(B168-MIN(MAX(C178,0),B168))),MAX(0,1*B168-(C178-MIN(MAX(C178,0),B168))))) -> 30108 | C179: =IF($A179>20,C178,(C178-B168+B179)*(1+$B$7)) -> 29892 | D179: =IF($A179>20,D178,(D178-B179)*(1+$B$6)) -> 950724.43 | E179: =IF($A179>20,0,(E168-MIN(MAX(F178,0),E168))+MIN(MAX(0,G178-(E168-MIN(MAX(F178,0),E168))),MAX(0,1*E168-(F178-MIN(MAX(F178,0),E168))))) -> 75270 | F179: =IF($A179>20,F178,(F178-E168+E179)*(1+$B$7)) -> 74730 | G179: =IF($A179>20,G178,(G178-E179)*(1+$B$6)) -> 419651.29 | H179: =IF($A179>20,0,(H168-MIN(MAX(I178,0),H168))+MIN(MAX(0,J178-(H168-MIN(MAX(I178,0),H168))),MAX(0,1*H168-(I178-MIN(MAX(I178,0),H168))))) -> 63774.551 | I179: =IF($A179>20,I178,(I178-H168+H179)*(1+$B$7)) -> 63317.021 | J179: =IF($A179>20,J178,(J178-H179)*(1+$B$6)) -> 554829.63 | K179: =IF($A179>20,0,(K168-MIN(MAX(L178,0),K168))+MIN(MAX(0,M178-(K168-MIN(MAX(L178,0),K168))),MAX(0,1*K168-(L178-MIN(MAX(L178,0),K168))))) -> 63498.332 | L179: =IF($A179>20,L178,(L178-K168+K179)*(1+$B$7)) -> 63042.784 | M179: =IF($A179>20,M178,(M178-K179)*(1+$B$6)) -> 558077.76 | N179: =IF($A179>20,0,(N168-MIN(MAX(O178,0),N168))+MIN(MAX(0,P178-(N168-MIN(MAX(O178,0),N168))),MAX(0,1*N168-(O178-MIN(MAX(O178,0),N168))))) -> 63498.576 | O179: =IF($A179>20,O178,(O178-N168+N179)*(1+$B$7)) -> 63043.026 | P179: =IF($A179>20,P178,(P178-N179)*(1+$B$6)) -> 558074.9 | Q179: =IF($A179>20,0,(Q168-MIN(MAX(R178,0),Q168))+MIN(MAX(0,S178-(Q168-MIN(MAX(R178,0),Q168))),MAX(0,1*Q168-(R178-MIN(MAX(R178,0),Q168))))) -> 63498.576 | R179: =IF($A179>20,R178,(R178-Q168+Q179)*(1+$B$7)) -> 63043.027 | S179: =IF($A179>20,S178,(S178-Q179)*(1+$B$6)) -> 558074.89
A180: =10 -> 10 | B180: =IF($A180>20,0,(B168-MIN(MAX(C179,0),B168))+MIN(MAX(0,D179-(B168-MIN(MAX(C179,0),B168))),MAX(0,1*B168-(C179-MIN(MAX(C179,0),B168))))) -> 30108 | C180: =IF($A180>20,C179,(C179-B168+B180)*(1+$B$7)) -> 29892 | D180: =IF($A180>20,D179,(D179-B180)*(1+$B$6)) -> 948234.92 | E180: =IF($A180>20,0,(E168-MIN(MAX(F179,0),E168))+MIN(MAX(0,G179-(E168-MIN(MAX(F179,0),E168))),MAX(0,1*E168-(F179-MIN(MAX(F179,0),E168))))) -> 75270 | F180: =IF($A180>20,F179,(F179-E168+E180)*(1+$B$7)) -> 74730 | G180: =IF($A180>20,G179,(G179-E180)*(1+$B$6)) -> 354712.73 | H180: =IF($A180>20,0,(H168-MIN(MAX(I179,0),H168))+MIN(MAX(0,J179-(H168-MIN(MAX(I179,0),H168))),MAX(0,1*H168-(I179-MIN(MAX(I179,0),H168))))) -> 63774.551 | I180: =IF($A180>20,I179,(I179-H168+H180)*(1+$B$7)) -> 63317.021 | J180: =IF($A180>20,J179,(J179-H180)*(1+$B$6)) -> 505786.73 | K180: =IF($A180>20,0,(K168-MIN(MAX(L179,0),K168))+MIN(MAX(0,M179-(K168-MIN(MAX(L179,0),K168))),MAX(0,1*K168-(L179-MIN(MAX(L179,0),K168))))) -> 63498.332 | L180: =IF($A180>20,L179,(L179-K168+K180)*(1+$B$7)) -> 63042.784 | M180: =IF($A180>20,M179,(M179-K180)*(1+$B$6)) -> 509416.81 | N180: =IF($A180>20,0,(N168-MIN(MAX(O179,0),N168))+MIN(MAX(0,P179-(N168-MIN(MAX(O179,0),N168))),MAX(0,1*N168-(O179-MIN(MAX(O179,0),N168))))) -> 63498.576 | O180: =IF($A180>20,O179,(O179-N168+N180)*(1+$B$7)) -> 63043.026 | P180: =IF($A180>20,P179,(P179-N180)*(1+$B$6)) -> 509413.61 | Q180: =IF($A180>20,0,(Q168-MIN(MAX(R179,0),Q168))+MIN(MAX(0,S179-(Q168-MIN(MAX(R179,0),Q168))),MAX(0,1*Q168-(R179-MIN(MAX(R179,0),Q168))))) -> 63498.576 | R180: =IF($A180>20,R179,(R179-Q168+Q180)*(1+$B$7)) -> 63043.027 | S180: =IF($A180>20,S179,(S179-Q180)*(1+$B$6)) -> 509413.61
A181: =11 -> 11 | B181: =IF($A181>20,0,(B168-MIN(MAX(C180,0),B168))+MIN(MAX(0,D180-(B168-MIN(MAX(C180,0),B168))),MAX(0,1*B168-(C180-MIN(MAX(C180,0),B168))))) -> 30108 | C181: =IF($A181>20,C180,(C180-B168+B181)*(1+$B$7)) -> 29892 | D181: =IF($A181>20,D180,(D180-B181)*(1+$B$6)) -> 945670.73 | E181: =IF($A181>20,0,(E168-MIN(MAX(F180,0),E168))+MIN(MAX(0,G180-(E168-MIN(MAX(F180,0),E168))),MAX(0,1*E168-(F180-MIN(MAX(F180,0),E168))))) -> 75270 | F181: =IF($A181>20,F180,(F180-E168+E181)*(1+$B$7)) -> 74730 | G181: =IF($A181>20,G180,(G180-E181)*(1+$B$6)) -> 287826.01 | H181: =IF($A181>20,0,(H168-MIN(MAX(I180,0),H168))+MIN(MAX(0,J180-(H168-MIN(MAX(I180,0),H168))),MAX(0,1*H168-(I180-MIN(MAX(I180,0),H168))))) -> 63774.551 | I181: =IF($A181>20,I180,(I180-H168+H181)*(1+$B$7)) -> 63317.021 | J181: =IF($A181>20,J180,(J180-H181)*(1+$B$6)) -> 455272.55 | K181: =IF($A181>20,0,(K168-MIN(MAX(L180,0),K168))+MIN(MAX(0,M180-(K168-MIN(MAX(L180,0),K168))),MAX(0,1*K168-(L180-MIN(MAX(L180,0),K168))))) -> 63498.332 | L181: =IF($A181>20,L180,(L180-K168+K181)*(1+$B$7)) -> 63042.784 | M181: =IF($A181>20,M180,(M180-K181)*(1+$B$6)) -> 459296.04 | N181: =IF($A181>20,0,(N168-MIN(MAX(O180,0),N168))+MIN(MAX(0,P180-(N168-MIN(MAX(O180,0),N168))),MAX(0,1*N168-(O180-MIN(MAX(O180,0),N168))))) -> 63498.576 | O181: =IF($A181>20,O180,(O180-N168+N181)*(1+$B$7)) -> 63043.026 | P181: =IF($A181>20,P180,(P180-N181)*(1+$B$6)) -> 459292.49 | Q181: =IF($A181>20,0,(Q168-MIN(MAX(R180,0),Q168))+MIN(MAX(0,S180-(Q168-MIN(MAX(R180,0),Q168))),MAX(0,1*Q168-(R180-MIN(MAX(R180,0),Q168))))) -> 63498.576 | R181: =IF($A181>20,R180,(R180-Q168+Q181)*(1+$B$7)) -> 63043.027 | S181: =IF($A181>20,S180,(S180-Q181)*(1+$B$6)) -> 459292.48
A182: =12 -> 12 | B182: =IF($A182>20,0,(B168-MIN(MAX(C181,0),B168))+MIN(MAX(0,D181-(B168-MIN(MAX(C181,0),B168))),MAX(0,1*B168-(C181-MIN(MAX(C181,0),B168))))) -> 30108 | C182: =IF($A182>20,C181,(C181-B168+B182)*(1+$B$7)) -> 29892 | D182: =IF($A182>20,D181,(D181-B182)*(1+$B$6)) -> 943029.61 | E182: =IF($A182>20,0,(E168-MIN(MAX(F181,0),E168))+MIN(MAX(0,G181-(E168-MIN(MAX(F181,0),E168))),MAX(0,1*E168-(F181-MIN(MAX(F181,0),E168))))) -> 75270 | F182: =IF($A182>20,F181,(F181-E168+E182)*(1+$B$7)) -> 74730 | G182: =IF($A182>20,G181,(G181-E182)*(1+$B$6)) -> 218932.69 | H182: =IF($A182>20,0,(H168-MIN(MAX(I181,0),H168))+MIN(MAX(0,J181-(H168-MIN(MAX(I181,0),H168))),MAX(0,1*H168-(I181-MIN(MAX(I181,0),H168))))) -> 63774.551 | I182: =IF($A182>20,I181,(I181-H168+H182)*(1+$B$7)) -> 63317.021 | J182: =IF($A182>20,J181,(J181-H182)*(1+$B$6)) -> 403242.94 | K182: =IF($A182>20,0,(K168-MIN(MAX(L181,0),K168))+MIN(MAX(0,M181-(K168-MIN(MAX(L181,0),K168))),MAX(0,1*K168-(L181-MIN(MAX(L181,0),K168))))) -> 63498.332 | L182: =IF($A182>20,L181,(L181-K168+K182)*(1+$B$7)) -> 63042.784 | M182: =IF($A182>20,M181,(M181-K182)*(1+$B$6)) -> 407671.63 | N182: =IF($A182>20,0,(N168-MIN(MAX(O181,0),N168))+MIN(MAX(0,P181-(N168-MIN(MAX(O181,0),N168))),MAX(0,1*N168-(O181-MIN(MAX(O181,0),N168))))) -> 63498.576 | O182: =IF($A182>20,O181,(O181-N168+N182)*(1+$B$7)) -> 63043.026 | P182: =IF($A182>20,P181,(P181-N182)*(1+$B$6)) -> 407667.73 | Q182: =IF($A182>20,0,(Q168-MIN(MAX(R181,0),Q168))+MIN(MAX(0,S181-(Q168-MIN(MAX(R181,0),Q168))),MAX(0,1*Q168-(R181-MIN(MAX(R181,0),Q168))))) -> 63498.576 | R182: =IF($A182>20,R181,(R181-Q168+Q182)*(1+$B$7)) -> 63043.027 | S182: =IF($A182>20,S181,(S181-Q182)*(1+$B$6)) -> 407667.72
...

Sheet 5-Roberta
A1: Il motore del caso: quanto puo' spendere Roberta, e quanto le costa il secchio
A2: Strumento informativo / divulgativo. NON è consulenza finanziaria. I valori sono indicativi al 2026 e vanno verificati col tuo consulente.
A4: Rendimento reale — basso / centrale / alto | B4: ='1-Input'!$B$14-0.01 -> 0.02 | C4: ='1-Input'!$B$14 -> 0.03 | D4: ='1-Input'!$B$14+0.01 -> 0.04
A6: SPESA MASSIMA SOSTENIBILE SU TUTTO L'ORIZZONTE
A7: Rendimento reale | B7: N = 0 | C7: N = 1 | D7: N = 2 | E7: N = 3 | F7: N = 5
A8: =$B$4 -> 0.02 | B8: ='5-Roberta'!$B$173 -> 17222.185 | C8: ='5-Roberta'!$B$228 -> 16926.34 | D8: ='5-Roberta'!$B$283 -> 16656.5 | E8: ='5-Roberta'!$B$338 -> 16412.124 | F8: ='5-Roberta'!$B$393 -> 16001.832
A9: =$C$4 -> 0.03 | B9: ='5-Roberta'!$B$448 -> 18844.494 | C9: ='5-Roberta'!$B$503 -> 18374.499 | D9: ='5-Roberta'!$B$558 -> 17944.672 | E9: ='5-Roberta'!$B$613 -> 17554.719 | F9: ='5-Roberta'!$B$668 -> 16889.427
A10: =$D$4 -> 0.04 | B10: ='5-Roberta'!$B$723 -> 20684.87 | C10: ='5-Roberta'!$B$778 -> 20010.465 | D10: ='5-Roberta'!$B$833 -> 19396.385 | E10: ='5-Roberta'!$B$888 -> 18838.514 | F10: ='5-Roberta'!$B$943 -> 17883.64
A12: IL COSTO DEL SECCHIO — al rendimento centrale
A13: Anni di spesa in liquidita' | B13: Spesa massima | C13: Costo | D13: In % del tenore di vita
A14: nessun secchio | B14: ='5-Roberta'!$B$448 -> 18844.494 | C14: =0 -> 0 | D14: =0 -> 0
A15: 1 anni | B15: ='5-Roberta'!$B$503 -> 18374.499 | C15: ='5-Roberta'!$B$448-'5-Roberta'!$B$503 -> 469.99447 | D15: =C15/'5-Roberta'!$B$448 -> 0.024940679
A16: 2 anni | B16: ='5-Roberta'!$B$558 -> 17944.672 | C16: ='5-Roberta'!$B$448-'5-Roberta'!$B$558 -> 899.82149 | D16: =C16/'5-Roberta'!$B$448 -> 0.047749836
A17: 3 anni | B17: ='5-Roberta'!$B$613 -> 17554.719 | C17: ='5-Roberta'!$B$448-'5-Roberta'!$B$613 -> 1289.7749 | D17: =C17/'5-Roberta'!$B$448 -> 0.068443065
A18: 5 anni | B18: ='5-Roberta'!$B$668 -> 16889.427 | C18: ='5-Roberta'!$B$448-'5-Roberta'!$B$668 -> 1955.0667 | D18: =C18/'5-Roberta'!$B$448 -> 0.10374737
A20: GLI ANNI DI AUTONOMIA, ALLA SPESA VERA DI ROBERTA
A21: Anni di spesa in liquidita' | B21: Il capitale dura | C21: Roberta arriva a | D21: Imposta cumulata | E21: Bollo cumulato | F21: Totale
A22: nessun secchio | B22: =$B$1003 -> 36 | C22: ='1-Input'!$B$6+B22 -> 83 | D22: =$C$1003 -> 75952.558 | E22: =$D$1003 -> 15039.866 | F22: =D22+E22 -> 90992.424
A23: 1 anni | B23: =$B$1059 -> 33 | C23: ='1-Input'!$B$6+B23 -> 80 | D23: =$C$1059 -> 67781.676 | E23: =$D$1059 -> 13895.81 | F23: =D23+E23 -> 81677.486
A24: 2 anni | B24: =$B$1115 -> 31 | C24: ='1-Input'!$B$6+B24 -> 78 | D24: =$C$1115 -> 59757.502 | E24: =$D$1115 -> 13004.248 | F24: =D24+E24 -> 72761.75
A25: 3 anni | B25: =$B$1171 -> 29 | C25: ='1-Input'!$B$6+B25 -> 76 | D25: =$C$1171 -> 53254.378 | E25: =$D$1171 -> 12299.503 | F25: =D25+E25 -> 65553.881
A26: 5 anni | B26: =$B$1227 -> 26 | C26: ='1-Input'!$B$6+B26 -> 73 | D26: =$C$1227 -> 42610.611 | E26: =$D$1227 -> 11235.217 | F26: =D26+E26 -> 53845.828
A27: RISPARMIO D'IMPOSTA COL SECCHIO DA DUE ANNI | B27: =D22-D24 -> 16195.056
A28: Non e' un risparmio: col secchio Roberta paga meno imposta perche' ha meno, e per cinque anni in meno. Il totale della colonna F scende insieme al patrimonio.
A30: IL CONTO CHE VA FATTO FINO IN FONDO — il piano non regge nemmeno senza secchio
A31: Spesa massima sostenibile senza secchio | B31: ='5-Roberta'!$B$448 -> 18844.494
A32: Spesa effettiva di Roberta | B32: ='1-Input'!$B$10 -> 19800
A33: DI QUANTO E' CORTA, ogni anno | B33: =B32-B31 -> 955.5063 | C33: =B33/B31 -> 0.050704801
A34: Costo del secchio da due anni | B34: ='5-Roberta'!$B$448-'5-Roberta'!$B$558 -> 899.82149
A35: Il costo del secchio in quota di quanto le manca | B35: =B34/B33 -> 0.9417222
A37: LE TRE LEVE VERE — e nessuna e' il secchio
A38: Leva | B38: Effetto | C38: Basta?
A39: Tagliare la spesa fino al sostenibile | B39: =-B33 -> -955.5063 | C39: ="si per costruzione" -> si per costruzione
A40: Accettare piu' rischio — rendimento reale alto, senza secchio | B40: ='5-Roberta'!$B$723-'1-Input'!$B$10 -> 884.86977 | C40: =IF('5-Roberta'!$B$723>='1-Input'!$B$10,"si","no") -> si
A41: Rendimento reale alto, con un anno di secchio | B41: ='5-Roberta'!$B$778-'1-Input'!$B$10 -> 210.46481 | C41: =IF('5-Roberta'!$B$778>='1-Input'!$B$10,"si","no") -> si
A42: Rendimento reale alto, con due anni di secchio | B42: ='5-Roberta'!$B$833-'1-Input'!$B$10 -> -403.61481 | C42: =IF('5-Roberta'!$B$833>='1-Input'!$B$10,"si","no") -> no
A43: Rendimento reale basso, senza secchio | B43: ='5-Roberta'!$B$173-'1-Input'!$B$10 -> -2577.8152 | C43: =IF('5-Roberta'!$B$173>='1-Input'!$B$10,"si","no") -> no
A44: Al rendimento basso Roberta non ce la fa in nessuna configurazione. Al rendimento alto ce la fa senza secchio — e la colonna «Basta?» dice da sola fino a quale taglia di secchio regge: e' un risultato del motore, non una frase.
A120: CASO ROBERTA — rendimento reale 2% · N = 0
A121: spesa provata → | B121: =0.038*'2-Caso'!$B$12 -> 16681.055 | I121: =0.05*'2-Caso'!$B$12 -> 21948.757 | P121: =IFERROR(I121-I172*(I121-B121)/(I172-B172),I121) -> 17301.136 | W121: =IFERROR(P121-P172*(P121-I121)/(P172-I172),P121) -> 17208.87 | AD121: =IFERROR(W121-W172*(W121-P121)/(W172-P172),W121) -> 17222.185 | AK121: =IFERROR(AD121-AD172*(AD121-W121)/(AD172-W172),AD121) -> 17222.185
A122: anno | B122: latente | C122: lordo venduto | D122: secchio ante bollo | E122: portaf. ante bollo | F122: secchio 1 | G122: portafoglio | H122: base di costo | I122: latente | J122: lordo venduto | K122: secchio ante bollo | L122: portaf. ante bollo | M122: secchio 1 | N122: portafoglio | O122: base di costo | P122: latente | Q122: lordo venduto | R122: secchio ante bollo | S122: portaf. ante bollo | T122: secchio 1 | U122: portafoglio | V122: base di costo | W122: latente | X122: lordo venduto | Y122: secchio ante bollo | Z122: portaf. ante bollo | AA122: secchio 1 | AB122: portafoglio | AC122: base di costo | AD122: latente | AE122: lordo venduto | AF122: secchio ante bollo | AG122: portaf. ante bollo | AH122: secchio 1 | AI122: portafoglio | AJ122: base di costo | AK122: latente | AL122: lordo venduto | AM122: secchio ante bollo | AN122: portaf. ante bollo | AO122: secchio 1 | AP122: portafoglio | AQ122: base di costo
A123: 0 | F123: =MIN(0*B121,'2-Caso'!$B$12) -> 0 | G123: ='2-Caso'!$B$12-F123 -> 438975.14 | H123: ='2-Caso'!$B$13*G123/'2-Caso'!$B$12 -> 344000 | M123: =MIN(0*I121,'2-Caso'!$B$12) -> 0 | N123: ='2-Caso'!$B$12-M123 -> 438975.14 | O123: ='2-Caso'!$B$13*N123/'2-Caso'!$B$12 -> 344000 | T123: =MIN(0*P121,'2-Caso'!$B$12) -> 0 | U123: ='2-Caso'!$B$12-T123 -> 438975.14 | V123: ='2-Caso'!$B$13*U123/'2-Caso'!$B$12 -> 344000 | AA123: =MIN(0*W121,'2-Caso'!$B$12) -> 0 | AB123: ='2-Caso'!$B$12-AA123 -> 438975.14 | AC123: ='2-Caso'!$B$13*AB123/'2-Caso'!$B$12 -> 344000 | AH123: =MIN(0*AD121,'2-Caso'!$B$12) -> 0 | AI123: ='2-Caso'!$B$12-AH123 -> 438975.14 | AJ123: ='2-Caso'!$B$13*AI123/'2-Caso'!$B$12 -> 344000 | AO123: =MIN(0*AK121,'2-Caso'!$B$12) -> 0 | AP123: ='2-Caso'!$B$12-AO123 -> 438975.14 | AQ123: ='2-Caso'!$B$13*AP123/'2-Caso'!$B$12 -> 344000
A124: =1 -> 1 | B124: =IF($A124>'1-Input'!$B$26,0,IF(G123<=0,0,MAX(0,(G123-H123)/G123))) -> 0.21635653 | C124: =IF($A124>'1-Input'!$B$26,0,(MAX(0,B121-IF($A124>='1-Input'!$C$12,'1-Input'!$B$12,0))-MIN(MAX(F123,0),MAX(0,B121-IF($A124>='1-Input'!$C$12,'1-Input'!$B$12,0))))*(1/(1-'P-Parametri'!$B$6*B124))+MIN(MAX(0,G123-(MAX(0,B121-IF($A124>='1-Input'!$C$12,'1-Input'!$B$12,0))-MIN(MAX(F123,0),MAX(0,B121-IF($A124>='1-Input'!$C$12,'1-Input'!$B$12,0))))*(1/(1-'P-Parametri'!$B$6*B124))),MAX(0,0*B121-(F123-MIN(MAX(F123,0),MAX(0,B121-IF($A124>='1-Input'!$C$12,'1-Input'!$B$12,0)))))*(1/(1-'P-Parametri'!$B$6*B124)))) -> 17675.341 | D124: =IF($A124>'1-Input'!$B$26,F123,(F123-MAX(0,B121-IF($A124>='1-Input'!$C$12,'1-Input'!$B$12,0))+C124*(1-'P-Parametri'!$B$6*B124))*(1+'1-Input'!$B$27)) -> -3.6248821e-12 | E124: =IF($A124>'1-Input'!$B$26,G123,(G123-C124)*(1+$B$4)) -> 429725.79 | F124: =IF($A124>'1-Input'!$B$26,D124,D124-'P-Parametri'!$B$8*(E124+D124)+MIN(MAX(E124,0),'P-Parametri'!$B$8*(E124+D124))) -> -3.6379788e-12 | G124: =IF($A124>'1-Input'!$B$26,E124,E124-MIN(MAX(E124,0),'P-Parametri'!$B$8*(E124+D124))) -> 428866.34 | H124: =IF($A124>'1-Input'!$B$26,H123,H123-C124*(1-B124)) -> 330148.83 | I124: =IF($A124>'1-Input'!$B$26,0,IF(N123<=0,0,MAX(0,(N123-O123)/N123))) -> 0.21635653 | J124: =IF($A124>'1-Input'!$B$26,0,(MAX(0,I121-IF($A124>='1-Input'!$C$12,'1-Input'!$B$12,0))-MIN(MAX(M123,0),MAX(0,I121-IF($A124>='1-Input'!$C$12,'1-Input'!$B$12,0))))*(1/(1-'P-Parametri'!$B$6*I124))+MIN(MAX(0,N123-(MAX(0,I121-IF($A124>='1-Input'!$C$12,'1-Input'!$B$12,0))-MIN(MAX(M123,0),MAX(0,I121-IF($A124>='1-Input'!$C$12,'1-Input'!$B$12,0))))*(1/(1-'P-Parametri'!$B$6*I124))),MAX(0,0*I121-(M123-MIN(MAX(M123,0),MAX(0,I121-IF($A124>='1-Input'!$C$12,'1-Input'!$B$12,0)))))*(1/(1-'P-Parametri'!$B$6*I124)))) -> 23257.028 | K124: =IF($A124>'1-Input'!$B$26,M123,(M123-MAX(0,I121-IF($A124>='1-Input'!$C$12,'1-Input'!$B$12,0))+J124*(1-'P-Parametri'!$B$6*I124))*(1+'1-Input'!$B$27)) -> 0 | L124: =IF($A124>'1-Input'!$B$26,N123,(N123-J124)*(1+$B$4)) -> 424032.47 | M124: =IF($A124>'1-Input'!$B$26,K124,K124-'P-Parametri'!$B$8*(L124+K124)+MIN(MAX(L124,0),'P-Parametri'!$B$8*(L124+K124))) -> 0 | N124: =IF($A124>'1-Input'!$B$26,L124,L124-MIN(MAX(L124,0),'P-Parametri'!$B$8*(L124+K124))) -> 423184.41 | O124: =IF($A124>'1-Input'!$B$26,O123,O123-J124*(1-I124)) -> 325774.78 | P124: =IF($A124>'1-Input'!$B$26,0,IF(U123<=0,0,MAX(0,(U123-V123)/U123))) -> 0.21635653 | Q124: =IF($A124>'1-Input'!$B$26,0,(MAX(0,P121-IF($A124>='1-Input'!$C$12,'1-Input'!$B$12,0))-MIN(MAX(T123,0),MAX(0,P121-IF($A124>='1-Input'!$C$12,'1-Input'!$B$12,0))))*(1/(1-'P-Parametri'!$B$6*P124))+MIN(MAX(0,U123-(MAX(0,P121-IF($A124>='1-Input'!$C$12,'1-Input'!$B$12,0))-MIN(MAX(T123,0),MAX(0,P121-IF($A124>='1-Input'!$C$12,'1-Input'!$B$12,0))))*(1/(1-'P-Parametri'!$B$6*P124))),MAX(0,0*P121-(T123-MIN(MAX(T123,0),MAX(0,P121-IF($A124>='1-Input'!$C$12,'1-Input'!$B$12,0)))))*(1/(1-'P-Parametri'!$B$6*P124)))) -> 18332.382 | R124: =IF($A124>'1-Input'!$B$26,T123,(T123-MAX(0,P121-IF($A124>='1-Input'!$C$12,'1-Input'!$B$12,0))+Q124*(1-'P-Parametri'!$B$6*P124))*(1+'1-Input'!$B$27)) -> -3.6248821e-12 | S124: =IF($A124>'1-Input'!$B$26,U123,(U123-Q124)*(1+$B$4)) -> 429055.61 | T124: =IF($A124>'1-Input'!$B$26,R124,R124-'P-Parametri'!$B$8*(S124+R124)+MIN(MAX(S124,0),'P-Parametri'!$B$8*(S124+R124))) -> -3.6379788e-12 | U124: =IF($A124>'1-Input'!$B$26,S124,S124-MIN(MAX(S124,0),'P-Parametri'!$B$8*(S124+R124))) -> 428197.5 | V124: =IF($A124>'1-Input'!$B$26,V123,V123-Q124*(1-P124)) -> 329633.95 | W124: =IF($A124>'1-Input'!$B$26,0,IF(AB123<=0,0,MAX(0,(AB123-AC123)/AB123))) -> 0.21635653 | X124: =IF($A124>'1-Input'!$B$26,0,(MAX(0,W121-IF($A124>='1-Input'!$C$12,'1-Input'!$B$12,0))-MIN(MAX(AA123,0),MAX(0,W121-IF($A124>='1-Input'!$C$12,'1-Input'!$B$12,0))))*(1/(1-'P-Parametri'!$B$6*W124))+MIN(MAX(0,AB123-(MAX(0,W121-IF($A124>='1-Input'!$C$12,'1-Input'!$B$12,0))-MIN(MAX(AA123,0),MAX(0,W121-IF($A124>='1-Input'!$C$12,'1-Input'!$B$12,0))))*(1/(1-'P-Parametri'!$B$6*W124))),MAX(0,0*W121-(AA123-MIN(MAX(AA123,0),MAX(0,W121-IF($A124>='1-Input'!$C$12,'1-Input'!$B$12,0)))))*(1/(1-'P-Parametri'!$B$6*W124)))) -> 18234.616 | Y124: =IF($A124>'1-Input'!$B$26,AA123,(AA123-MAX(0,W121-IF($A124>='1-Input'!$C$12,'1-Input'!$B$12,0))+X124*(1-'P-Parametri'!$B$6*W124))*(1+'1-Input'!$B$27)) -> 0 | Z124: =IF($A124>'1-Input'!$B$26,AB123,(AB123-X124)*(1+$B$4)) -> 429155.33 | AA124: =IF($A124>'1-Input'!$B$26,Y124,Y124-'P-Parametri'!$B$8*(Z124+Y124)+MIN(MAX(Z124,0),'P-Parametri'!$B$8*(Z124+Y124))) -> 0 | AB124: =IF($A124>'1-Input'!$B$26,Z124,Z124-MIN(MAX(Z124,0),'P-Parametri'!$B$8*(Z124+Y124))) -> 428297.02 | AC124: =IF($A124>'1-Input'!$B$26,AC123,AC123-X124*(1-W124)) -> 329710.56 | AD124: =IF($A124>'1-Input'!$B$26,0,IF(AI123<=0,0,MAX(0,(AI123-AJ123)/AI123))) -> 0.21635653 | AE124: =IF($A124>'1-Input'!$B$26,0,(MAX(0,AD121-IF($A124>='1-Input'!$C$12,'1-Input'!$B$12,0))-MIN(MAX(AH123,0),MAX(0,AD121-IF($A124>='1-Input'!$C$12,'1-Input'!$B$12,0))))*(1/(1-'P-Parametri'!$B$6*AD124))+MIN(MAX(0,AI123-(MAX(0,AD121-IF($A124>='1-Input'!$C$12,'1-Input'!$B$12,0))-MIN(MAX(AH123,0),MAX(0,AD121-IF($A124>='1-Input'!$C$12,'1-Input'!$B$12,0))))*(1/(1-'P-Parametri'!$B$6*AD124))),MAX(0,0*AD121-(AH123-MIN(MAX(AH123,0),MAX(0,AD121-IF($A124>='1-Input'!$C$12,'1-Input'!$B$12,0)))))*(1/(1-'P-Parametri'!$B$6*AD124)))) -> 18248.725 | AF124: =IF($A124>'1-Input'!$B$26,AH123,(AH123-MAX(0,AD121-IF($A124>='1-Input'!$C$12,'1-Input'!$B$12,0))+AE124*(1-'P-Parametri'!$B$6*AD124))*(1+'1-Input'!$B$27)) -> 0 | AG124: =IF($A124>'1-Input'!$B$26,AI123,(AI123-AE124)*(1+$B$4)) -> 429140.94 | AH124: =IF($A124>'1-Input'!$B$26,AF124,AF124-'P-Parametri'!$B$8*(AG124+AF124)+MIN(MAX(AG124,0),'P-Parametri'!$B$8*(AG124+AF124))) -> 0 | AI124: =IF($A124>'1-Input'!$B$26,AG124,AG124-MIN(MAX(AG124,0),'P-Parametri'!$B$8*(AG124+AF124))) -> 428282.66 | AJ124: =IF($A124>'1-Input'!$B$26,AJ123,AJ123-AE124*(1-AD124)) -> 329699.51 | AK124: =IF($A124>'1-Input'!$B$26,0,IF(AP123<=0,0,MAX(0,(AP123-AQ123)/AP123))) -> 0.21635653 | AL124: =IF($A124>'1-Input'!$B$26,0,(MAX(0,AK121-IF($A124>='1-Input'!$C$12,'1-Input'!$B$12,0))-MIN(MAX(AO123,0),MAX(0,AK121-IF($A124>='1-Input'!$C$12,'1-Input'!$B$12,0))))*(1/(1-'P-Parametri'!$B$6*AK124))+MIN(MAX(0,AP123-(MAX(0,AK121-IF($A124>='1-Input'!$C$12,'1-Input'!$B$12,0))-MIN(MAX(AO123,0),MAX(0,AK121-IF($A124>='1-Input'!$C$12,'1-Input'!$B$12,0))))*(1/(1-'P-Parametri'!$B$6*AK124))),MAX(0,0*AK121-(AO123-MIN(MAX(AO123,0),MAX(0,AK121-IF($A124>='1-Input'!$C$12,'1-Input'!$B$12,0)))))*(1/(1-'P-Parametri'!$B$6*AK124)))) -> 18248.725 | AM124: =IF($A124>'1-Input'!$B$26,AO123,(AO123-MAX(0,AK121-IF($A124>='1-Input'!$C$12,'1-Input'!$B$12,0))+AL124*(1-'P-Parametri'!$B$6*AK124))*(1+'1-Input'!$B$27)) -> 0 | AN124: =IF($A124>'1-Input'!$B$26,AP123,(AP123-AL124)*(1+$B$4)) -> 429140.94 | AO124: =IF($A124>'1-Input'!$B$26,AM124,AM124-'P-Parametri'!$B$8*(AN124+AM124)+MIN(MAX(AN124,0),'P-Parametri'!$B$8*(AN124+AM124))) -> 0 | AP124: =IF($A124>'1-Input'!$B$26,AN124,AN124-MIN(MAX(AN124,0),'P-Parametri'!$B$8*(AN124+AM124))) -> 428282.66 | AQ124: =IF($A124>'1-Input'!$B$26,AQ123,AQ123-AL124*(1-AK124)) -> 329699.51
A125: =2 -> 2 | B125: =IF($A125>'1-Input'!$B$26,0,IF(G124<=0,0,MAX(0,(G124-H124)/G124))) -> 0.23018246 | C125: =IF($A125>'1-Input'!$B$26,0,(MAX(0,B121-IF($A125>='1-Input'!$C$12,'1-Input'!$B$12,0))-MIN(MAX(F124,0),MAX(0,B121-IF($A125>='1-Input'!$C$12,'1-Input'!$B$12,0))))*(1/(1-'P-Parametri'!$B$6*B125))+MIN(MAX(0,G124-(MAX(0,B121-IF($A125>='1-Input'!$C$12,'1-Input'!$B$12,0))-MIN(MAX(F124,0),MAX(0,B121-IF($A125>='1-Input'!$C$12,'1-Input'!$B$12,0))))*(1/(1-'P-Parametri'!$B$6*B125))),MAX(0,0*B121-(F124-MIN(MAX(F124,0),MAX(0,B121-IF($A125>='1-Input'!$C$12,'1-Input'!$B$12,0)))))*(1/(1-'P-Parametri'!$B$6*B125)))) -> 17742.924 | D125: =IF($A125>'1-Input'!$B$26,F124,(F124-MAX(0,B121-IF($A125>='1-Input'!$C$12,'1-Input'!$B$12,0))+C125*(1-'P-Parametri'!$B$6*B125))*(1+'1-Input'!$B$27)) -> 0 | E125: =IF($A125>'1-Input'!$B$26,G124,(G124-C125)*(1+$B$4)) -> 419345.89 | F125: =IF($A125>'1-Input'!$B$26,D125,D125-'P-Parametri'!$B$8*(E125+D125)+MIN(MAX(E125,0),'P-Parametri'!$B$8*(E125+D125))) -> 0 | G125: =IF($A125>'1-Input'!$B$26,E125,E125-MIN(MAX(E125,0),'P-Parametri'!$B$8*(E125+D125))) -> 418507.2 | H125: =IF($A125>'1-Input'!$B$26,H124,H124-C125*(1-B125)) -> 316490.02 | I125: =IF($A125>'1-Input'!$B$26,0,IF(N124<=0,0,MAX(0,(N124-O124)/N124))) -> 0.23018246 | J125: =IF($A125>'1-Input'!$B$26,0,(MAX(0,I121-IF($A125>='1-Input'!$C$12,'1-Input'!$B$12,0))-MIN(MAX(M124,0),MAX(0,I121-IF($A125>='1-Input'!$C$12,'1-Input'!$B$12,0))))*(1/(1-'P-Parametri'!$B$6*I125))+MIN(MAX(0,N124-(MAX(0,I121-IF($A125>='1-Input'!$C$12,'1-Input'!$B$12,0))-MIN(MAX(M124,0),MAX(0,I121-IF($A125>='1-Input'!$C$12,'1-Input'!$B$12,0))))*(1/(1-'P-Parametri'!$B$6*I125))),MAX(0,0*I121-(M124-MIN(MAX(M124,0),MAX(0,I121-IF($A125>='1-Input'!$C$12,'1-Input'!$B$12,0)))))*(1/(1-'P-Parametri'!$B$6*I125)))) -> 23345.952 | K125: =IF($A125>'1-Input'!$B$26,M124,(M124-MAX(0,I121-IF($A125>='1-Input'!$C$12,'1-Input'!$B$12,0))+J125*(1-'P-Parametri'!$B$6*I125))*(1+'1-Input'!$B$27)) -> 0 | L125: =IF($A125>'1-Input'!$B$26,N124,(N124-J125)*(1+$B$4)) -> 407835.23 | M125: =IF($A125>'1-Input'!$B$26,K125,K125-'P-Parametri'!$B$8*(L125+K125)+MIN(MAX(L125,0),'P-Parametri'!$B$8*(L125+K125))) -> 0 | N125: =IF($A125>'1-Input'!$B$26,L125,L125-MIN(MAX(L125,0),'P-Parametri'!$B$8*(L125+K125))) -> 407019.56 | O125: =IF($A125>'1-Input'!$B$26,O124,O124-J125*(1-I125)) -> 307802.66 | P125: =IF($A125>'1-Input'!$B$26,0,IF(U124<=0,0,MAX(0,(U124-V124)/U124))) -> 0.23018246 | Q125: =IF($A125>'1-Input'!$B$26,0,(MAX(0,P121-IF($A125>='1-Input'!$C$12,'1-Input'!$B$12,0))-MIN(MAX(T124,0),MAX(0,P121-IF($A125>='1-Input'!$C$12,'1-Input'!$B$12,0))))*(1/(1-'P-Parametri'!$B$6*P125))+MIN(MAX(0,U124-(MAX(0,P121-IF($A125>='1-Input'!$C$12,'1-Input'!$B$12,0))-MIN(MAX(T124,0),MAX(0,P121-IF($A125>='1-Input'!$C$12,'1-Input'!$B$12,0))))*(1/(1-'P-Parametri'!$B$6*P125))),MAX(0,0*P121-(T124-MIN(MAX(T124,0),MAX(0,P121-IF($A125>='1-Input'!$C$12,'1-Input'!$B$12,0)))))*(1/(1-'P-Parametri'!$B$6*P125)))) -> 18402.477 | R125: =IF($A125>'1-Input'!$B$26,T124,(T124-MAX(0,P121-IF($A125>='1-Input'!$C$12,'1-Input'!$B$12,0))+Q125*(1-'P-Parametri'!$B$6*P125))*(1+'1-Input'!$B$27)) -> 0 | S125: =IF($A125>'1-Input'!$B$26,U124,(U124-Q125)*(1+$B$4)) -> 417990.93 | T125: =IF($A125>'1-Input'!$B$26,R125,R125-'P-Parametri'!$B$8*(S125+R125)+MIN(MAX(S125,0),'P-Parametri'!$B$8*(S125+R125))) -> 0 | U125: =IF($A125>'1-Input'!$B$26,S125,S125-MIN(MAX(S125,0),'P-Parametri'!$B$8*(S125+R125))) -> 417154.94 | V125: =IF($A125>'1-Input'!$B$26,V124,V124-Q125*(1-P125)) -> 315467.4 | W125: =IF($A125>'1-Input'!$B$26,0,IF(AB124<=0,0,MAX(0,(AB124-AC124)/AB124))) -> 0.23018246 | X125: =IF($A125>'1-Input'!$B$26,0,(MAX(0,W121-IF($A125>='1-Input'!$C$12,'1-Input'!$B$12,0))-MIN(MAX(AA124,0),MAX(0,W121-IF($A125>='1-Input'!$C$12,'1-Input'!$B$12,0))))*(1/(1-'P-Parametri'!$B$6*W125))+MIN(MAX(0,AB124-(MAX(0,W121-IF($A125>='1-Input'!$C$12,'1-Input'!$B$12,0))-MIN(MAX(AA124,0),MAX(0,W121-IF($A125>='1-Input'!$C$12,'1-Input'!$B$12,0))))*(1/(1-'P-Parametri'!$B$6*W125))),MAX(0,0*W121-(AA124-MIN(MAX(AA124,0),MAX(0,W121-IF($A125>='1-Input'!$C$12,'1-Input'!$B$12,0)))))*(1/(1-'P-Parametri'!$B$6*W125)))) -> 18304.337 | Y125: =IF($A125>'1-Input'!$B$26,AA124,(AA124-MAX(0,W121-IF($A125>='1-Input'!$C$12,'1-Input'!$B$12,0))+X125*(1-'P-Parametri'!$B$6*W125))*(1+'1-Input'!$B$27)) -> 0 | Z125: =IF($A125>'1-Input'!$B$26,AB124,(AB124-X125)*(1+$B$4)) -> 418192.54 | AA125: =IF($A125>'1-Input'!$B$26,Y125,Y125-'P-Parametri'!$B$8*(Z125+Y125)+MIN(MAX(Z125,0),'P-Parametri'!$B$8*(Z125+Y125))) -> 0 | AB125: =IF($A125>'1-Input'!$B$26,Z125,Z125-MIN(MAX(Z125,0),'P-Parametri'!$B$8*(Z125+Y125))) -> 417356.15 | AC125: =IF($A125>'1-Input'!$B$26,AC124,AC124-X125*(1-W125)) -> 315619.56 | AD125: =IF($A125>'1-Input'!$B$26,0,IF(AI124<=0,0,MAX(0,(AI124-AJ124)/AI124))) -> 0.23018246 | AE125: =IF($A125>'1-Input'!$B$26,0,(MAX(0,AD121-IF($A125>='1-Input'!$C$12,'1-Input'!$B$12,0))-MIN(MAX(AH124,0),MAX(0,AD121-IF($A125>='1-Input'!$C$12,'1-Input'!$B$12,0))))*(1/(1-'P-Parametri'!$B$6*AD125))+MIN(MAX(0,AI124-(MAX(0,AD121-IF($A125>='1-Input'!$C$12,'1-Input'!$B$12,0))-MIN(MAX(AH124,0),MAX(0,AD121-IF($A125>='1-Input'!$C$12,'1-Input'!$B$12,0))))*(1/(1-'P-Parametri'!$B$6*AD125))),MAX(0,0*AD121-(AH124-MIN(MAX(AH124,0),MAX(0,AD121-IF($A125>='1-Input'!$C$12,'1-Input'!$B$12,0)))))*(1/(1-'P-Parametri'!$B$6*AD125)))) -> 18318.5 | AF125: =IF($A125>'1-Input'!$B$26,AH124,(AH124-MAX(0,AD121-IF($A125>='1-Input'!$C$12,'1-Input'!$B$12,0))+AE125*(1-'P-Parametri'!$B$6*AD125))*(1+'1-Input'!$B$27)) -> -3.6248821e-12 | AG125: =IF($A125>'1-Input'!$B$26,AI124,(AI124-AE125)*(1+$B$4)) -> 418163.44 | AH125: =IF($A125>'1-Input'!$B$26,AF125,AF125-'P-Parametri'!$B$8*(AG125+AF125)+MIN(MAX(AG125,0),'P-Parametri'!$B$8*(AG125+AF125))) -> -3.6379788e-12 | AI125: =IF($A125>'1-Input'!$B$26,AG125,AG125-MIN(MAX(AG125,0),'P-Parametri'!$B$8*(AG125+AF125))) -> 417327.12 | AJ125: =IF($A125>'1-Input'!$B$26,AJ124,AJ124-AE125*(1-AD125)) -> 315597.6 | AK125: =IF($A125>'1-Input'!$B$26,0,IF(AP124<=0,0,MAX(0,(AP124-AQ124)/AP124))) -> 0.23018246 | AL125: =IF($A125>'1-Input'!$B$26,0,(MAX(0,AK121-IF($A125>='1-Input'!$C$12,'1-Input'!$B$12,0))-MIN(MAX(AO124,0),MAX(0,AK121-IF($A125>='1-Input'!$C$12,'1-Input'!$B$12,0))))*(1/(1-'P-Parametri'!$B$6*AK125))+MIN(MAX(0,AP124-(MAX(0,AK121-IF($A125>='1-Input'!$C$12,'1-Input'!$B$12,0))-MIN(MAX(AO124,0),MAX(0,AK121-IF($A125>='1-Input'!$C$12,'1-Input'!$B$12,0))))*(1/(1-'P-Parametri'!$B$6*AK125))),MAX(0,0*AK121-(AO124-MIN(MAX(AO124,0),MAX(0,AK121-IF($A125>='1-Input'!$C$12,'1-Input'!$B$12,0)))))*(1/(1-'P-Parametri'!$B$6*AK125)))) -> 18318.5 | AM125: =IF($A125>'1-Input'!$B$26,AO124,(AO124-MAX(0,AK121-IF($A125>='1-Input'!$C$12,'1-Input'!$B$12,0))+AL125*(1-'P-Parametri'!$B$6*AK125))*(1+'1-Input'!$B$27)) -> -3.6248821e-12 | AN125: =IF($A125>'1-Input'!$B$26,AP124,(AP124-AL125)*(1+$B$4)) -> 418163.44 | AO125: =IF($A125>'1-Input'!$B$26,AM125,AM125-'P-Parametri'!$B$8*(AN125+AM125)+MIN(MAX(AN125,0),'P-Parametri'!$B$8*(AN125+AM125))) -> -3.6379788e-12 | AP125: =IF($A125>'1-Input'!$B$26,AN125,AN125-MIN(MAX(AN125,0),'P-Parametri'!$B$8*(AN125+AM125))) -> 417327.12 | AQ125: =IF($A125>'1-Input'!$B$26,AQ124,AQ124-AL125*(1-AK125)) -> 315597.6
A126: =3 -> 3 | B126: =IF($A126>'1-Input'!$B$26,0,IF(G125<=0,0,MAX(0,(G125-H125)/G125))) -> 0.24376445 | C126: =IF($A126>'1-Input'!$B$26,0,(MAX(0,B121-IF($A126>='1-Input'!$C$12,'1-Input'!$B$12,0))-MIN(MAX(F125,0),MAX(0,B121-IF($A126>='1-Input'!$C$12,'1-Input'!$B$12,0))))*(1/(1-'P-Parametri'!$B$6*B126))+MIN(MAX(0,G125-(MAX(0,B121-IF($A126>='1-Input'!$C$12,'1-Input'!$B$12,0))-MIN(MAX(F125,0),MAX(0,B121-IF($A126>='1-Input'!$C$12,'1-Input'!$B$12,0))))*(1/(1-'P-Parametri'!$B$6*B126))),MAX(0,0*B121-(F125-MIN(MAX(F125,0),MAX(0,B121-IF($A126>='1-Input'!$C$12,'1-Input'!$B$12,0)))))*(1/(1-'P-Parametri'!$B$6*B126)))) -> 17809.82 | D126: =IF($A126>'1-Input'!$B$26,F125,(F125-MAX(0,B121-IF($A126>='1-Input'!$C$12,'1-Input'!$B$12,0))+C126*(1-'P-Parametri'!$B$6*B126))*(1+'1-Input'!$B$27)) -> 3.6248821e-12 | E126: =IF($A126>'1-Input'!$B$26,G125,(G125-C126)*(1+$B$4)) -> 408711.32 | F126: =IF($A126>'1-Input'!$B$26,D126,D126-'P-Parametri'!$B$8*(E126+D126)+MIN(MAX(E126,0),'P-Parametri'!$B$8*(E126+D126))) -> 3.6379788e-12 | G126: =IF($A126>'1-Input'!$B$26,E126,E126-MIN(MAX(E126,0),'P-Parametri'!$B$8*(E126+D126))) -> 407893.9 | H126: =IF($A126>'1-Input'!$B$26,H125,H125-C126*(1-B126)) -> 303021.6 | I126: =IF($A126>'1-Input'!$B$26,0,IF(N125<=0,0,MAX(0,(N125-O125)/N125))) -> 0.24376445 | J126: =IF($A126>'1-Input'!$B$26,0,(MAX(0,I121-IF($A126>='1-Input'!$C$12,'1-Input'!$B$12,0))-MIN(MAX(M125,0),MAX(0,I121-IF($A126>='1-Input'!$C$12,'1-Input'!$B$12,0))))*(1/(1-'P-Parametri'!$B$6*I126))+MIN(MAX(0,N125-(MAX(0,I121-IF($A126>='1-Input'!$C$12,'1-Input'!$B$12,0))-MIN(MAX(M125,0),MAX(0,I121-IF($A126>='1-Input'!$C$12,'1-Input'!$B$12,0))))*(1/(1-'P-Parametri'!$B$6*I126))),MAX(0,0*I121-(M125-MIN(MAX(M125,0),MAX(0,I121-IF($A126>='1-Input'!$C$12,'1-Input'!$B$12,0)))))*(1/(1-'P-Parametri'!$B$6*I126)))) -> 23433.973 | K126: =IF($A126>'1-Input'!$B$26,M125,(M125-MAX(0,I121-IF($A126>='1-Input'!$C$12,'1-Input'!$B$12,0))+J126*(1-'P-Parametri'!$B$6*I126))*(1+'1-Input'!$B$27)) -> -3.6248821e-12 | L126: =IF($A126>'1-Input'!$B$26,N125,(N125-J126)*(1+$B$4)) -> 391257.29 | M126: =IF($A126>'1-Input'!$B$26,K126,K126-'P-Parametri'!$B$8*(L126+K126)+MIN(MAX(L126,0),'P-Parametri'!$B$8*(L126+K126))) -> -3.6379788e-12 | N126: =IF($A126>'1-Input'!$B$26,L126,L126-MIN(MAX(L126,0),'P-Parametri'!$B$8*(L126+K126))) -> 390474.78 | O126: =IF($A126>'1-Input'!$B$26,O125,O125-J126*(1-I126)) -> 290081.06 | P126: =IF($A126>'1-Input'!$B$26,0,IF(U125<=0,0,MAX(0,(U125-V125)/U125))) -> 0.24376445 | Q126: =IF($A126>'1-Input'!$B$26,0,(MAX(0,P121-IF($A126>='1-Input'!$C$12,'1-Input'!$B$12,0))-MIN(MAX(T125,0),MAX(0,P121-IF($A126>='1-Input'!$C$12,'1-Input'!$B$12,0))))*(1/(1-'P-Parametri'!$B$6*P126))+MIN(MAX(0,U125-(MAX(0,P121-IF($A126>='1-Input'!$C$12,'1-Input'!$B$12,0))-MIN(MAX(T125,0),MAX(0,P121-IF($A126>='1-Input'!$C$12,'1-Input'!$B$12,0))))*(1/(1-'P-Parametri'!$B$6*P126))),MAX(0,0*P121-(T125-MIN(MAX(T125,0),MAX(0,P121-IF($A126>='1-Input'!$C$12,'1-Input'!$B$12,0)))))*(1/(1-'P-Parametri'!$B$6*P126)))) -> 18471.86 | R126: =IF($A126>'1-Input'!$B$26,T125,(T125-MAX(0,P121-IF($A126>='1-Input'!$C$12,'1-Input'!$B$12,0))+Q126*(1-'P-Parametri'!$B$6*P126))*(1+'1-Input'!$B$27)) -> 0 | S126: =IF($A126>'1-Input'!$B$26,U125,(U125-Q126)*(1+$B$4)) -> 406656.75 | T126: =IF($A126>'1-Input'!$B$26,R126,R126-'P-Parametri'!$B$8*(S126+R126)+MIN(MAX(S126,0),'P-Parametri'!$B$8*(S126+R126))) -> 0 | U126: =IF($A126>'1-Input'!$B$26,S126,S126-MIN(MAX(S126,0),'P-Parametri'!$B$8*(S126+R126))) -> 405843.43 | V126: =IF($A126>'1-Input'!$B$26,V125,V125-Q126*(1-P126)) -> 301498.32 | W126: =IF($A126>'1-Input'!$B$26,0,IF(AB125<=0,0,MAX(0,(AB125-AC125)/AB125))) -> 0.24376445 | X126: =IF($A126>'1-Input'!$B$26,0,(MAX(0,W121-IF($A126>='1-Input'!$C$12,'1-Input'!$B$12,0))-MIN(MAX(AA125,0),MAX(0,W121-IF($A126>='1-Input'!$C$12,'1-Input'!$B$12,0))))*(1/(1-'P-Parametri'!$B$6*W126))+MIN(MAX(0,AB125-(MAX(0,W121-IF($A126>='1-Input'!$C$12,'1-Input'!$B$12,0))-MIN(MAX(AA125,0),MAX(0,W121-IF($A126>='1-Input'!$C$12,'1-Input'!$B$12,0))))*(1/(1-'P-Parametri'!$B$6*W126))),MAX(0,0*W121-(AA125-MIN(MAX(AA125,0),MAX(0,W121-IF($A126>='1-Input'!$C$12,'1-Input'!$B$12,0)))))*(1/(1-'P-Parametri'!$B$6*W126)))) -> 18373.35 | Y126: =IF($A126>'1-Input'!$B$26,AA125,(AA125-MAX(0,W121-IF($A126>='1-Input'!$C$12,'1-Input'!$B$12,0))+X126*(1-'P-Parametri'!$B$6*W126))*(1+'1-Input'!$B$27)) -> -3.6248821e-12 | Z126: =IF($A126>'1-Input'!$B$26,AB125,(AB125-X126)*(1+$B$4)) -> 406962.46 | AA126: =IF($A126>'1-Input'!$B$26,Y126,Y126-'P-Parametri'!$B$8*(Z126+Y126)+MIN(MAX(Z126,0),'P-Parametri'!$B$8*(Z126+Y126))) -> -3.6379788e-12 | AB126: =IF($A126>'1-Input'!$B$26,Z126,Z126-MIN(MAX(Z126,0),'P-Parametri'!$B$8*(Z126+Y126))) -> 406148.54 | AC126: =IF($A126>'1-Input'!$B$26,AC125,AC125-X126*(1-W126)) -> 301724.98 | AD126: =IF($A126>'1-Input'!$B$26,0,IF(AI125<=0,0,MAX(0,(AI125-AJ125)/AI125))) -> 0.24376445 | AE126: =IF($A126>'1-Input'!$B$26,0,(MAX(0,AD121-IF($A126>='1-Input'!$C$12,'1-Input'!$B$12,0))-MIN(MAX(AH125,0),MAX(0,AD121-IF($A126>='1-Input'!$C$12,'1-Input'!$B$12,0))))*(1/(1-'P-Parametri'!$B$6*AD126))+MIN(MAX(0,AI125-(MAX(0,AD121-IF($A126>='1-Input'!$C$12,'1-Input'!$B$12,0))-MIN(MAX(AH125,0),MAX(0,AD121-IF($A126>='1-Input'!$C$12,'1-Input'!$B$12,0))))*(1/(1-'P-Parametri'!$B$6*AD126))),MAX(0,0*AD121-(AH125-MIN(MAX(AH125,0),MAX(0,AD121-IF($A126>='1-Input'!$C$12,'1-Input'!$B$12,0)))))*(1/(1-'P-Parametri'!$B$6*AD126)))) -> 18387.566 | AF126: =IF($A126>'1-Input'!$B$26,AH125,(AH125-MAX(0,AD121-IF($A126>='1-Input'!$C$12,'1-Input'!$B$12,0))+AE126*(1-'P-Parametri'!$B$6*AD126))*(1+'1-Input'!$B$27)) -> 0 | AG126: =IF($A126>'1-Input'!$B$26,AI125,(AI125-AE126)*(1+$B$4)) -> 406918.34 | AH126: =IF($A126>'1-Input'!$B$26,AF126,AF126-'P-Parametri'!$B$8*(AG126+AF126)+MIN(MAX(AG126,0),'P-Parametri'!$B$8*(AG126+AF126))) -> 0 | AI126: =IF($A126>'1-Input'!$B$26,AG126,AG126-MIN(MAX(AG126,0),'P-Parametri'!$B$8*(AG126+AF126))) -> 406104.51 | AJ126: =IF($A126>'1-Input'!$B$26,AJ125,AJ125-AE126*(1-AD126)) -> 301692.27 | AK126: =IF($A126>'1-Input'!$B$26,0,IF(AP125<=0,0,MAX(0,(AP125-AQ125)/AP125))) -> 0.24376445 | AL126: =IF($A126>'1-Input'!$B$26,0,(MAX(0,AK121-IF($A126>='1-Input'!$C$12,'1-Input'!$B$12,0))-MIN(MAX(AO125,0),MAX(0,AK121-IF($A126>='1-Input'!$C$12,'1-Input'!$B$12,0))))*(1/(1-'P-Parametri'!$B$6*AK126))+MIN(MAX(0,AP125-(MAX(0,AK121-IF($A126>='1-Input'!$C$12,'1-Input'!$B$12,0))-MIN(MAX(AO125,0),MAX(0,AK121-IF($A126>='1-Input'!$C$12,'1-Input'!$B$12,0))))*(1/(1-'P-Parametri'!$B$6*AK126))),MAX(0,0*AK121-(AO125-MIN(MAX(AO125,0),MAX(0,AK121-IF($A126>='1-Input'!$C$12,'1-Input'!$B$12,0)))))*(1/(1-'P-Parametri'!$B$6*AK126)))) -> 18387.566 | AM126: =IF($A126>'1-Input'!$B$26,AO125,(AO125-MAX(0,AK121-IF($A126>='1-Input'!$C$12,'1-Input'!$B$12,0))+AL126*(1-'P-Parametri'!$B$6*AK126))*(1+'1-Input'!$B$27)) -> 0 | AN126: =IF($A126>'1-Input'!$B$26,AP125,(AP125-AL126)*(1+$B$4)) -> 406918.34 | AO126: =IF($A126>'1-Input'!$B$26,AM126,AM126-'P-Parametri'!$B$8*(AN126+AM126)+MIN(MAX(AN126,0),'P-Parametri'!$B$8*(AN126+AM126))) -> 0 | AP126: =IF($A126>'1-Input'!$B$26,AN126,AN126-MIN(MAX(AN126,0),'P-Parametri'!$B$8*(AN126+AM126))) -> 406104.51 | AQ126: =IF($A126>'1-Input'!$B$26,AQ125,AQ125-AL126*(1-AK126)) -> 301692.27
A127: =4 -> 4 | B127: =IF($A127>'1-Input'!$B$26,0,IF(G126<=0,0,MAX(0,(G126-H126)/G126))) -> 0.25710681 | C127: =IF($A127>'1-Input'!$B$26,0,(MAX(0,B121-IF($A127>='1-Input'!$C$12,'1-Input'!$B$12,0))-MIN(MAX(F126,0),MAX(0,B121-IF($A127>='1-Input'!$C$12,'1-Input'!$B$12,0))))*(1/(1-'P-Parametri'!$B$6*B127))+MIN(MAX(0,G126-(MAX(0,B121-IF($A127>='1-Input'!$C$12,'1-Input'!$B$12,0))-MIN(MAX(F126,0),MAX(0,B121-IF($A127>='1-Input'!$C$12,'1-Input'!$B$12,0))))*(1/(1-'P-Parametri'!$B$6*B127))),MAX(0,0*B121-(F126-MIN(MAX(F126,0),MAX(0,B121-IF($A127>='1-Input'!$C$12,'1-Input'!$B$12,0)))))*(1/(1-'P-Parametri'!$B$6*B127)))) -> 17876.028 | D127: =IF($A127>'1-Input'!$B$26,F126,(F126-MAX(0,B121-IF($A127>='1-Input'!$C$12,'1-Input'!$B$12,0))+C127*(1-'P-Parametri'!$B$6*B127))*(1+'1-Input'!$B$27)) -> 0 | E127: =IF($A127>'1-Input'!$B$26,G126,(G126-C127)*(1+$B$4)) -> 397818.23 | F127: =IF($A127>'1-Input'!$B$26,D127,D127-'P-Parametri'!$B$8*(E127+D127)+MIN(MAX(E127,0),'P-Parametri'!$B$8*(E127+D127))) -> 0 | G127: =IF($A127>'1-Input'!$B$26,E127,E127-MIN(MAX(E127,0),'P-Parametri'!$B$8*(E127+D127))) -> 397022.59 | H127: =IF($A127>'1-Input'!$B$26,H126,H126-C127*(1-B127)) -> 289741.62 | I127: =IF($A127>'1-Input'!$B$26,0,IF(N126<=0,0,MAX(0,(N126-O126)/N126))) -> 0.25710681 | J127: =IF($A127>'1-Input'!$B$26,0,(MAX(0,I121-IF($A127>='1-Input'!$C$12,'1-Input'!$B$12,0))-MIN(MAX(M126,0),MAX(0,I121-IF($A127>='1-Input'!$C$12,'1-Input'!$B$12,0))))*(1/(1-'P-Parametri'!$B$6*I127))+MIN(MAX(0,N126-(MAX(0,I121-IF($A127>='1-Input'!$C$12,'1-Input'!$B$12,0))-MIN(MAX(M126,0),MAX(0,I121-IF($A127>='1-Input'!$C$12,'1-Input'!$B$12,0))))*(1/(1-'P-Parametri'!$B$6*I127))),MAX(0,0*I121-(M126-MIN(MAX(M126,0),MAX(0,I121-IF($A127>='1-Input'!$C$12,'1-Input'!$B$12,0)))))*(1/(1-'P-Parametri'!$B$6*I127)))) -> 23521.089 | K127: =IF($A127>'1-Input'!$B$26,M126,(M126-MAX(0,I121-IF($A127>='1-Input'!$C$12,'1-Input'!$B$12,0))+J127*(1-'P-Parametri'!$B$6*I127))*(1+'1-Input'!$B$27)) -> -3.6248821e-12 | L127: =IF($A127>'1-Input'!$B$26,N126,(N126-J127)*(1+$B$4)) -> 374292.76 | M127: =IF($A127>'1-Input'!$B$26,K127,K127-'P-Parametri'!$B$8*(L127+K127)+MIN(MAX(L127,0),'P-Parametri'!$B$8*(L127+K127))) -> -3.6379788e-12 | N127: =IF($A127>'1-Input'!$B$26,L127,L127-MIN(MAX(L127,0),'P-Parametri'!$B$8*(L127+K127))) -> 373544.18 | O127: =IF($A127>'1-Input'!$B$26,O126,O126-J127*(1-I127)) -> 272607.4 | P127: =IF($A127>'1-Input'!$B$26,0,IF(U126<=0,0,MAX(0,(U126-V126)/U126))) -> 0.25710681 | Q127: =IF($A127>'1-Input'!$B$26,0,(MAX(0,P121-IF($A127>='1-Input'!$C$12,'1-Input'!$B$12,0))-MIN(MAX(T126,0),MAX(0,P121-IF($A127>='1-Input'!$C$12,'1-Input'!$B$12,0))))*(1/(1-'P-Parametri'!$B$6*P127))+MIN(MAX(0,U126-(MAX(0,P121-IF($A127>='1-Input'!$C$12,'1-Input'!$B$12,0))-MIN(MAX(T126,0),MAX(0,P121-IF($A127>='1-Input'!$C$12,'1-Input'!$B$12,0))))*(1/(1-'P-Parametri'!$B$6*P127))),MAX(0,0*P121-(T126-MIN(MAX(T126,0),MAX(0,P121-IF($A127>='1-Input'!$C$12,'1-Input'!$B$12,0)))))*(1/(1-'P-Parametri'!$B$6*P127)))) -> 18540.529 | R127: =IF($A127>'1-Input'!$B$26,T126,(T126-MAX(0,P121-IF($A127>='1-Input'!$C$12,'1-Input'!$B$12,0))+Q127*(1-'P-Parametri'!$B$6*P127))*(1+'1-Input'!$B$27)) -> 0 | S127: =IF($A127>'1-Input'!$B$26,U126,(U126-Q127)*(1+$B$4)) -> 395048.96 | T127: =IF($A127>'1-Input'!$B$26,R127,R127-'P-Parametri'!$B$8*(S127+R127)+MIN(MAX(S127,0),'P-Parametri'!$B$8*(S127+R127))) -> 0 | U127: =IF($A127>'1-Input'!$B$26,S127,S127-MIN(MAX(S127,0),'P-Parametri'!$B$8*(S127+R127))) -> 394258.86 | V127: =IF($A127>'1-Input'!$B$26,V126,V126-Q127*(1-P127)) -> 287724.69 | W127: =IF($A127>'1-Input'!$B$26,0,IF(AB126<=0,0,MAX(0,(AB126-AC126)/AB126))) -> 0.25710681 | X127: =IF($A127>'1-Input'!$B$26,0,(MAX(0,W121-IF($A127>='1-Input'!$C$12,'1-Input'!$B$12,0))-MIN(MAX(AA126,0),MAX(0,W121-IF($A127>='1-Input'!$C$12,'1-Input'!$B$12,0))))*(1/(1-'P-Parametri'!$B$6*W127))+MIN(MAX(0,AB126-(MAX(0,W121-IF($A127>='1-Input'!$C$12,'1-Input'!$B$12,0))-MIN(MAX(AA126,0),MAX(0,W121-IF($A127>='1-Input'!$C$12,'1-Input'!$B$12,0))))*(1/(1-'P-Parametri'!$B$6*W127))),MAX(0,0*W121-(AA126-MIN(MAX(AA126,0),MAX(0,W121-IF($A127>='1-Input'!$C$12,'1-Input'!$B$12,0)))))*(1/(1-'P-Parametri'!$B$6*W127)))) -> 18441.653 | Y127: =IF($A127>'1-Input'!$B$26,AA126,(AA126-MAX(0,W121-IF($A127>='1-Input'!$C$12,'1-Input'!$B$12,0))+X127*(1-'P-Parametri'!$B$6*W127))*(1+'1-Input'!$B$27)) -> -3.6248821e-12 | Z127: =IF($A127>'1-Input'!$B$26,AB126,(AB126-X127)*(1+$B$4)) -> 395461.02 | AA127: =IF($A127>'1-Input'!$B$26,Y127,Y127-'P-Parametri'!$B$8*(Z127+Y127)+MIN(MAX(Z127,0),'P-Parametri'!$B$8*(Z127+Y127))) -> -3.6379788e-12 | AB127: =IF($A127>'1-Input'!$B$26,Z127,Z127-MIN(MAX(Z127,0),'P-Parametri'!$B$8*(Z127+Y127))) -> 394670.1 | AC127: =IF($A127>'1-Input'!$B$26,AC126,AC126-X127*(1-W127)) -> 288024.8 | AD127: =IF($A127>'1-Input'!$B$26,0,IF(AI126<=0,0,MAX(0,(AI126-AJ126)/AI126))) -> 0.25710681 | AE127: =IF($A127>'1-Input'!$B$26,0,(MAX(0,AD121-IF($A127>='1-Input'!$C$12,'1-Input'!$B$12,0))-MIN(MAX(AH126,0),MAX(0,AD121-IF($A127>='1-Input'!$C$12,'1-Input'!$B$12,0))))*(1/(1-'P-Parametri'!$B$6*AD127))+MIN(MAX(0,AI126-(MAX(0,AD121-IF($A127>='1-Input'!$C$12,'1-Input'!$B$12,0))-MIN(MAX(AH126,0),MAX(0,AD121-IF($A127>='1-Input'!$C$12,'1-Input'!$B$12,0))))*(1/(1-'P-Parametri'!$B$6*AD127))),MAX(0,0*AD121-(AH126-MIN(MAX(AH126,0),MAX(0,AD121-IF($A127>='1-Input'!$C$12,'1-Input'!$B$12,0)))))*(1/(1-'P-Parametri'!$B$6*AD127)))) -> 18455.922 | AF127: =IF($A127>'1-Input'!$B$26,AH126,(AH126-MAX(0,AD121-IF($A127>='1-Input'!$C$12,'1-Input'!$B$12,0))+AE127*(1-'P-Parametri'!$B$6*AD127))*(1+'1-Input'!$B$27)) -> -3.6248821e-12 | AG127: =IF($A127>'1-Input'!$B$26,AI126,(AI126-AE127)*(1+$B$4)) -> 395401.56 | AH127: =IF($A127>'1-Input'!$B$26,AF127,AF127-'P-Parametri'!$B$8*(AG127+AF127)+MIN(MAX(AG127,0),'P-Parametri'!$B$8*(AG127+AF127))) -> -3.6379788e-12 | AI127: =IF($A127>'1-Input'!$B$26,AG127,AG127-MIN(MAX(AG127,0),'P-Parametri'!$B$8*(AG127+AF127))) -> 394610.75 | AJ127: =IF($A127>'1-Input'!$B$26,AJ126,AJ126-AE127*(1-AD127)) -> 287981.49 | AK127: =IF($A127>'1-Input'!$B$26,0,IF(AP126<=0,0,MAX(0,(AP126-AQ126)/AP126))) -> 0.25710681 | AL127: =IF($A127>'1-Input'!$B$26,0,(MAX(0,AK121-IF($A127>='1-Input'!$C$12,'1-Input'!$B$12,0))-MIN(MAX(AO126,0),MAX(0,AK121-IF($A127>='1-Input'!$C$12,'1-Input'!$B$12,0))))*(1/(1-'P-Parametri'!$B$6*AK127))+MIN(MAX(0,AP126-(MAX(0,AK121-IF($A127>='1-Input'!$C$12,'1-Input'!$B$12,0))-MIN(MAX(AO126,0),MAX(0,AK121-IF($A127>='1-Input'!$C$12,'1-Input'!$B$12,0))))*(1/(1-'P-Parametri'!$B$6*AK127))),MAX(0,0*AK121-(AO126-MIN(MAX(AO126,0),MAX(0,AK121-IF($A127>='1-Input'!$C$12,'1-Input'!$B$12,0)))))*(1/(1-'P-Parametri'!$B$6*AK127)))) -> 18455.922 | AM127: =IF($A127>'1-Input'!$B$26,AO126,(AO126-MAX(0,AK121-IF($A127>='1-Input'!$C$12,'1-Input'!$B$12,0))+AL127*(1-'P-Parametri'!$B$6*AK127))*(1+'1-Input'!$B$27)) -> -3.6248821e-12 | AN127: =IF($A127>'1-Input'!$B$26,AP126,(AP126-AL127)*(1+$B$4)) -> 395401.56 | AO127: =IF($A127>'1-Input'!$B$26,AM127,AM127-'P-Parametri'!$B$8*(AN127+AM127)+MIN(MAX(AN127,0),'P-Parametri'!$B$8*(AN127+AM127))) -> -3.6379788e-12 | AP127: =IF($A127>'1-Input'!$B$26,AN127,AN127-MIN(MAX(AN127,0),'P-Parametri'!$B$8*(AN127+AM127))) -> 394610.75 | AQ127: =IF($A127>'1-Input'!$B$26,AQ126,AQ126-AL127*(1-AK127)) -> 287981.49
A128: =5 -> 5 | B128: =IF($A128>'1-Input'!$B$26,0,IF(G127<=0,0,MAX(0,(G127-H127)/G127))) -> 0.27021377 | C128: =IF($A128>'1-Input'!$B$26,0,(MAX(0,B121-IF($A128>='1-Input'!$C$12,'1-Input'!$B$12,0))-MIN(MAX(F127,0),MAX(0,B121-IF($A128>='1-Input'!$C$12,'1-Input'!$B$12,0))))*(1/(1-'P-Parametri'!$B$6*B128))+MIN(MAX(0,G127-(MAX(0,B121-IF($A128>='1-Input'!$C$12,'1-Input'!$B$12,0))-MIN(MAX(F127,0),MAX(0,B121-IF($A128>='1-Input'!$C$12,'1-Input'!$B$12,0))))*(1/(1-'P-Parametri'!$B$6*B128))),MAX(0,0*B121-(F127-MIN(MAX(F127,0),MAX(0,B121-IF($A128>='1-Input'!$C$12,'1-Input'!$B$12,0)))))*(1/(1-'P-Parametri'!$B$6*B128)))) -> 17941.549 | D128: =IF($A128>'1-Input'!$B$26,F127,(F127-MAX(0,B121-IF($A128>='1-Input'!$C$12,'1-Input'!$B$12,0))+C128*(1-'P-Parametri'!$B$6*B128))*(1+'1-Input'!$B$27)) -> 0 | E128: =IF($A128>'1-Input'!$B$26,G127,(G127-C128)*(1+$B$4)) -> 386662.67 | F128: =IF($A128>'1-Input'!$B$26,D128,D128-'P-Parametri'!$B$8*(E128+D128)+MIN(MAX(E128,0),'P-Parametri'!$B$8*(E128+D128))) -> 0 | G128: =IF($A128>'1-Input'!$B$26,E128,E128-MIN(MAX(E128,0),'P-Parametri'!$B$8*(E128+D128))) -> 385889.34 | H128: =IF($A128>'1-Input'!$B$26,H127,H127-C128*(1-B128)) -> 276648.13 | I128: =IF($A128>'1-Input'!$B$26,0,IF(N127<=0,0,MAX(0,(N127-O127)/N127))) -> 0.27021377 | J128: =IF($A128>'1-Input'!$B$26,0,(MAX(0,I121-IF($A128>='1-Input'!$C$12,'1-Input'!$B$12,0))-MIN(MAX(M127,0),MAX(0,I121-IF($A128>='1-Input'!$C$12,'1-Input'!$B$12,0))))*(1/(1-'P-Parametri'!$B$6*I128))+MIN(MAX(0,N127-(MAX(0,I121-IF($A128>='1-Input'!$C$12,'1-Input'!$B$12,0))-MIN(MAX(M127,0),MAX(0,I121-IF($A128>='1-Input'!$C$12,'1-Input'!$B$12,0))))*(1/(1-'P-Parametri'!$B$6*I128))),MAX(0,0*I121-(M127-MIN(MAX(M127,0),MAX(0,I121-IF($A128>='1-Input'!$C$12,'1-Input'!$B$12,0)))))*(1/(1-'P-Parametri'!$B$6*I128)))) -> 23607.302 | K128: =IF($A128>'1-Input'!$B$26,M127,(M127-MAX(0,I121-IF($A128>='1-Input'!$C$12,'1-Input'!$B$12,0))+J128*(1-'P-Parametri'!$B$6*I128))*(1+'1-Input'!$B$27)) -> -3.6248821e-12 | L128: =IF($A128>'1-Input'!$B$26,N127,(N127-J128)*(1+$B$4)) -> 356935.61 | M128: =IF($A128>'1-Input'!$B$26,K128,K128-'P-Parametri'!$B$8*(L128+K128)+MIN(MAX(L128,0),'P-Parametri'!$B$8*(L128+K128))) -> -3.6379788e-12 | N128: =IF($A128>'1-Input'!$B$26,L128,L128-MIN(MAX(L128,0),'P-Parametri'!$B$8*(L128+K128))) -> 356221.74 | O128: =IF($A128>'1-Input'!$B$26,O127,O127-J128*(1-I128)) -> 255379.11 | P128: =IF($A128>'1-Input'!$B$26,0,IF(U127<=0,0,MAX(0,(U127-V127)/U127))) -> 0.27021377 | Q128: =IF($A128>'1-Input'!$B$26,0,(MAX(0,P121-IF($A128>='1-Input'!$C$12,'1-Input'!$B$12,0))-MIN(MAX(T127,0),MAX(0,P121-IF($A128>='1-Input'!$C$12,'1-Input'!$B$12,0))))*(1/(1-'P-Parametri'!$B$6*P128))+MIN(MAX(0,U127-(MAX(0,P121-IF($A128>='1-Input'!$C$12,'1-Input'!$B$12,0))-MIN(MAX(T127,0),MAX(0,P121-IF($A128>='1-Input'!$C$12,'1-Input'!$B$12,0))))*(1/(1-'P-Parametri'!$B$6*P128))),MAX(0,0*P121-(T127-MIN(MAX(T127,0),MAX(0,P121-IF($A128>='1-Input'!$C$12,'1-Input'!$B$12,0)))))*(1/(1-'P-Parametri'!$B$6*P128)))) -> 18608.486 | R128: =IF($A128>'1-Input'!$B$26,T127,(T127-MAX(0,P121-IF($A128>='1-Input'!$C$12,'1-Input'!$B$12,0))+Q128*(1-'P-Parametri'!$B$6*P128))*(1+'1-Input'!$B$27)) -> 0 | S128: =IF($A128>'1-Input'!$B$26,U127,(U127-Q128)*(1+$B$4)) -> 383163.38 | T128: =IF($A128>'1-Input'!$B$26,R128,R128-'P-Parametri'!$B$8*(S128+R128)+MIN(MAX(S128,0),'P-Parametri'!$B$8*(S128+R128))) -> 0 | U128: =IF($A128>'1-Input'!$B$26,S128,S128-MIN(MAX(S128,0),'P-Parametri'!$B$8*(S128+R128))) -> 382397.06 | V128: =IF($A128>'1-Input'!$B$26,V127,V127-Q128*(1-P128)) -> 274144.47 | W128: =IF($A128>'1-Input'!$B$26,0,IF(AB127<=0,0,MAX(0,(AB127-AC127)/AB127))) -> 0.27021377 | X128: =IF($A128>'1-Input'!$B$26,0,(MAX(0,W121-IF($A128>='1-Input'!$C$12,'1-Input'!$B$12,0))-MIN(MAX(AA127,0),MAX(0,W121-IF($A128>='1-Input'!$C$12,'1-Input'!$B$12,0))))*(1/(1-'P-Parametri'!$B$6*W128))+MIN(MAX(0,AB127-(MAX(0,W121-IF($A128>='1-Input'!$C$12,'1-Input'!$B$12,0))-MIN(MAX(AA127,0),MAX(0,W121-IF($A128>='1-Input'!$C$12,'1-Input'!$B$12,0))))*(1/(1-'P-Parametri'!$B$6*W128))),MAX(0,0*W121-(AA127-MIN(MAX(AA127,0),MAX(0,W121-IF($A128>='1-Input'!$C$12,'1-Input'!$B$12,0)))))*(1/(1-'P-Parametri'!$B$6*W128)))) -> 18509.248 | Y128: =IF($A128>'1-Input'!$B$26,AA127,(AA127-MAX(0,W121-IF($A128>='1-Input'!$C$12,'1-Input'!$B$12,0))+X128*(1-'P-Parametri'!$B$6*W128))*(1+'1-Input'!$B$27)) -> -3.6248821e-12 | Z128: =IF($A128>'1-Input'!$B$26,AB127,(AB127-X128)*(1+$B$4)) -> 383684.07 | AA128: =IF($A128>'1-Input'!$B$26,Y128,Y128-'P-Parametri'!$B$8*(Z128+Y128)+MIN(MAX(Z128,0),'P-Parametri'!$B$8*(Z128+Y128))) -> -3.6379788e-12 | AB128: =IF($A128>'1-Input'!$B$26,Z128,Z128-MIN(MAX(Z128,0),'P-Parametri'!$B$8*(Z128+Y128))) -> 382916.7 | AC128: =IF($A128>'1-Input'!$B$26,AC127,AC127-X128*(1-W128)) -> 274517.01 | AD128: =IF($A128>'1-Input'!$B$26,0,IF(AI127<=0,0,MAX(0,(AI127-AJ127)/AI127))) -> 0.27021377 | AE128: =IF($A128>'1-Input'!$B$26,0,(MAX(0,AD121-IF($A128>='1-Input'!$C$12,'1-Input'!$B$12,0))-MIN(MAX(AH127,0),MAX(0,AD121-IF($A128>='1-Input'!$C$12,'1-Input'!$B$12,0))))*(1/(1-'P-Parametri'!$B$6*AD128))+MIN(MAX(0,AI127-(MAX(0,AD121-IF($A128>='1-Input'!$C$12,'1-Input'!$B$12,0))-MIN(MAX(AH127,0),MAX(0,AD121-IF($A128>='1-Input'!$C$12,'1-Input'!$B$12,0))))*(1/(1-'P-Parametri'!$B$6*AD128))),MAX(0,0*AD121-(AH127-MIN(MAX(AH127,0),MAX(0,AD121-IF($A128>='1-Input'!$C$12,'1-Input'!$B$12,0)))))*(1/(1-'P-Parametri'!$B$6*AD128)))) -> 18523.569 | AF128: =IF($A128>'1-Input'!$B$26,AH127,(AH127-MAX(0,AD121-IF($A128>='1-Input'!$C$12,'1-Input'!$B$12,0))+AE128*(1-'P-Parametri'!$B$6*AD128))*(1+'1-Input'!$B$27)) -> -3.6248821e-12 | AG128: =IF($A128>'1-Input'!$B$26,AI127,(AI127-AE128)*(1+$B$4)) -> 383608.93 | AH128: =IF($A128>'1-Input'!$B$26,AF128,AF128-'P-Parametri'!$B$8*(AG128+AF128)+MIN(MAX(AG128,0),'P-Parametri'!$B$8*(AG128+AF128))) -> -3.6379788e-12 | AI128: =IF($A128>'1-Input'!$B$26,AG128,AG128-MIN(MAX(AG128,0),'P-Parametri'!$B$8*(AG128+AF128))) -> 382841.71 | AJ128: =IF($A128>'1-Input'!$B$26,AJ127,AJ127-AE128*(1-AD128)) -> 274463.25 | AK128: =IF($A128>'1-Input'!$B$26,0,IF(AP127<=0,0,MAX(0,(AP127-AQ127)/AP127))) -> 0.27021377 | AL128: =IF($A128>'1-Input'!$B$26,0,(MAX(0,AK121-IF($A128>='1-Input'!$C$12,'1-Input'!$B$12,0))-MIN(MAX(AO127,0),MAX(0,AK121-IF($A128>='1-Input'!$C$12,'1-Input'!$B$12,0))))*(1/(1-'P-Parametri'!$B$6*AK128))+MIN(MAX(0,AP127-(MAX(0,AK121-IF($A128>='1-Input'!$C$12,'1-Input'!$B$12,0))-MIN(MAX(AO127,0),MAX(0,AK121-IF($A128>='1-Input'!$C$12,'1-Input'!$B$12,0))))*(1/(1-'P-Parametri'!$B$6*AK128))),MAX(0,0*AK121-(AO127-MIN(MAX(AO127,0),MAX(0,AK121-IF($A128>='1-Input'!$C$12,'1-Input'!$B$12,0)))))*(1/(1-'P-Parametri'!$B$6*AK128)))) -> 18523.569 | AM128: =IF($A128>'1-Input'!$B$26,AO127,(AO127-MAX(0,AK121-IF($A128>='1-Input'!$C$12,'1-Input'!$B$12,0))+AL128*(1-'P-Parametri'!$B$6*AK128))*(1+'1-Input'!$B$27)) -> -3.6248821e-12 | AN128: =IF($A128>'1-Input'!$B$26,AP127,(AP127-AL128)*(1+$B$4)) -> 383608.93 | AO128: =IF($A128>'1-Input'!$B$26,AM128,AM128-'P-Parametri'!$B$8*(AN128+AM128)+MIN(MAX(AN128,0),'P-Parametri'!$B$8*(AN128+AM128))) -> -3.6379788e-12 | AP128: =IF($A128>'1-Input'!$B$26,AN128,AN128-MIN(MAX(AN128,0),'P-Parametri'!$B$8*(AN128+AM128))) -> 382841.71 | AQ128: =IF($A128>'1-Input'!$B$26,AQ127,AQ127-AL128*(1-AK128)) -> 274463.25
A129: =6 -> 6 | B129: =IF($A129>'1-Input'!$B$26,0,IF(G128<=0,0,MAX(0,(G128-H128)/G128))) -> 0.28308948 | C129: =IF($A129>'1-Input'!$B$26,0,(MAX(0,B121-IF($A129>='1-Input'!$C$12,'1-Input'!$B$12,0))-MIN(MAX(F128,0),MAX(0,B121-IF($A129>='1-Input'!$C$12,'1-Input'!$B$12,0))))*(1/(1-'P-Parametri'!$B$6*B129))+MIN(MAX(0,G128-(MAX(0,B121-IF($A129>='1-Input'!$C$12,'1-Input'!$B$12,0))-MIN(MAX(F128,0),MAX(0,B121-IF($A129>='1-Input'!$C$12,'1-Input'!$B$12,0))))*(1/(1-'P-Parametri'!$B$6*B129))),MAX(0,0*B121-(F128-MIN(MAX(F128,0),MAX(0,B121-IF($A129>='1-Input'!$C$12,'1-Input'!$B$12,0)))))*(1/(1-'P-Parametri'!$B$6*B129)))) -> 18006.384 | D129: =IF($A129>'1-Input'!$B$26,F128,(F128-MAX(0,B121-IF($A129>='1-Input'!$C$12,'1-Input'!$B$12,0))+C129*(1-'P-Parametri'!$B$6*B129))*(1+'1-Input'!$B$27)) -> -3.6248821e-12 | E129: =IF($A129>'1-Input'!$B$26,G128,(G128-C129)*(1+$B$4)) -> 375240.62 | F129: =IF($A129>'1-Input'!$B$26,D129,D129-'P-Parametri'!$B$8*(E129+D129)+MIN(MAX(E129,0),'P-Parametri'!$B$8*(E129+D129))) -> -3.6379788e-12 | G129: =IF($A129>'1-Input'!$B$26,E129,E129-MIN(MAX(E129,0),'P-Parametri'!$B$8*(E129+D129))) -> 374490.13 | H129: =IF($A129>'1-Input'!$B$26,H128,H128-C129*(1-B129)) -> 263739.16 | I129: =IF($A129>'1-Input'!$B$26,0,IF(N128<=0,0,MAX(0,(N128-O128)/N128))) -> 0.28308948 | J129: =IF($A129>'1-Input'!$B$26,0,(MAX(0,I121-IF($A129>='1-Input'!$C$12,'1-Input'!$B$12,0))-MIN(MAX(M128,0),MAX(0,I121-IF($A129>='1-Input'!$C$12,'1-Input'!$B$12,0))))*(1/(1-'P-Parametri'!$B$6*I129))+MIN(MAX(0,N128-(MAX(0,I121-IF($A129>='1-Input'!$C$12,'1-Input'!$B$12,0))-MIN(MAX(M128,0),MAX(0,I121-IF($A129>='1-Input'!$C$12,'1-Input'!$B$12,0))))*(1/(1-'P-Parametri'!$B$6*I129))),MAX(0,0*I121-(M128-MIN(MAX(M128,0),MAX(0,I121-IF($A129>='1-Input'!$C$12,'1-Input'!$B$12,0)))))*(1/(1-'P-Parametri'!$B$6*I129)))) -> 23692.61 | K129: =IF($A129>'1-Input'!$B$26,M128,(M128-MAX(0,I121-IF($A129>='1-Input'!$C$12,'1-Input'!$B$12,0))+J129*(1-'P-Parametri'!$B$6*I129))*(1+'1-Input'!$B$27)) -> 0 | L129: =IF($A129>'1-Input'!$B$26,N128,(N128-J129)*(1+$B$4)) -> 339179.72 | M129: =IF($A129>'1-Input'!$B$26,K129,K129-'P-Parametri'!$B$8*(L129+K129)+MIN(MAX(L129,0),'P-Parametri'!$B$8*(L129+K129))) -> 0 | N129: =IF($A129>'1-Input'!$B$26,L129,L129-MIN(MAX(L129,0),'P-Parametri'!$B$8*(L129+K129))) -> 338501.36 | O129: =IF($A129>'1-Input'!$B$26,O128,O128-J129*(1-I129)) -> 238393.63 | P129: =IF($A129>'1-Input'!$B$26,0,IF(U128<=0,0,MAX(0,(U128-V128)/U128))) -> 0.28308948 | Q129: =IF($A129>'1-Input'!$B$26,0,(MAX(0,P121-IF($A129>='1-Input'!$C$12,'1-Input'!$B$12,0))-MIN(MAX(T128,0),MAX(0,P121-IF($A129>='1-Input'!$C$12,'1-Input'!$B$12,0))))*(1/(1-'P-Parametri'!$B$6*P129))+MIN(MAX(0,U128-(MAX(0,P121-IF($A129>='1-Input'!$C$12,'1-Input'!$B$12,0))-MIN(MAX(T128,0),MAX(0,P121-IF($A129>='1-Input'!$C$12,'1-Input'!$B$12,0))))*(1/(1-'P-Parametri'!$B$6*P129))),MAX(0,0*P121-(T128-MIN(MAX(T128,0),MAX(0,P121-IF($A129>='1-Input'!$C$12,'1-Input'!$B$12,0)))))*(1/(1-'P-Parametri'!$B$6*P129)))) -> 18675.731 | R129: =IF($A129>'1-Input'!$B$26,T128,(T128-MAX(0,P121-IF($A129>='1-Input'!$C$12,'1-Input'!$B$12,0))+Q129*(1-'P-Parametri'!$B$6*P129))*(1+'1-Input'!$B$27)) -> 0 | S129: =IF($A129>'1-Input'!$B$26,U128,(U128-Q129)*(1+$B$4)) -> 370995.75 | T129: =IF($A129>'1-Input'!$B$26,R129,R129-'P-Parametri'!$B$8*(S129+R129)+MIN(MAX(S129,0),'P-Parametri'!$B$8*(S129+R129))) -> 0 | U129: =IF($A129>'1-Input'!$B$26,S129,S129-MIN(MAX(S129,0),'P-Parametri'!$B$8*(S129+R129))) -> 370253.76 | V129: =IF($A129>'1-Input'!$B$26,V128,V128-Q129*(1-P129)) -> 260755.64 | W129: =IF($A129>'1-Input'!$B$26,0,IF(AB128<=0,0,MAX(0,(AB128-AC128)/AB128))) -> 0.28308948 | X129: =IF($A129>'1-Input'!$B$26,0,(MAX(0,W121-IF($A129>='1-Input'!$C$12,'1-Input'!$B$12,0))-MIN(MAX(AA128,0),MAX(0,W121-IF($A129>='1-Input'!$C$12,'1-Input'!$B$12,0))))*(1/(1-'P-Parametri'!$B$6*W129))+MIN(MAX(0,AB128-(MAX(0,W121-IF($A129>='1-Input'!$C$12,'1-Input'!$B$12,0))-MIN(MAX(AA128,0),MAX(0,W121-IF($A129>='1-Input'!$C$12,'1-Input'!$B$12,0))))*(1/(1-'P-Parametri'!$B$6*W129))),MAX(0,0*W121-(AA128-MIN(MAX(AA128,0),MAX(0,W121-IF($A129>='1-Input'!$C$12,'1-Input'!$B$12,0)))))*(1/(1-'P-Parametri'!$B$6*W129)))) -> 18576.134 | Y129: =IF($A129>'1-Input'!$B$26,AA128,(AA128-MAX(0,W121-IF($A129>='1-Input'!$C$12,'1-Input'!$B$12,0))+X129*(1-'P-Parametri'!$B$6*W129))*(1+'1-Input'!$B$27)) -> 0 | Z129: =IF($A129>'1-Input'!$B$26,AB128,(AB128-X129)*(1+$B$4)) -> 371627.38 | AA129: =IF($A129>'1-Input'!$B$26,Y129,Y129-'P-Parametri'!$B$8*(Z129+Y129)+MIN(MAX(Z129,0),'P-Parametri'!$B$8*(Z129+Y129))) -> 0 | AB129: =IF($A129>'1-Input'!$B$26,Z129,Z129-MIN(MAX(Z129,0),'P-Parametri'!$B$8*(Z129+Y129))) -> 370884.12 | AC129: =IF($A129>'1-Input'!$B$26,AC128,AC128-X129*(1-W129)) -> 261199.58 | AD129: =IF($A129>'1-Input'!$B$26,0,IF(AI128<=0,0,MAX(0,(AI128-AJ128)/AI128))) -> 0.28308948 | AE129: =IF($A129>'1-Input'!$B$26,0,(MAX(0,AD121-IF($A129>='1-Input'!$C$12,'1-Input'!$B$12,0))-MIN(MAX(AH128,0),MAX(0,AD121-IF($A129>='1-Input'!$C$12,'1-Input'!$B$12,0))))*(1/(1-'P-Parametri'!$B$6*AD129))+MIN(MAX(0,AI128-(MAX(0,AD121-IF($A129>='1-Input'!$C$12,'1-Input'!$B$12,0))-MIN(MAX(AH128,0),MAX(0,AD121-IF($A129>='1-Input'!$C$12,'1-Input'!$B$12,0))))*(1/(1-'P-Parametri'!$B$6*AD129))),MAX(0,0*AD121-(AH128-MIN(MAX(AH128,0),MAX(0,AD121-IF($A129>='1-Input'!$C$12,'1-Input'!$B$12,0)))))*(1/(1-'P-Parametri'!$B$6*AD129)))) -> 18590.507 | AF129: =IF($A129>'1-Input'!$B$26,AH128,(AH128-MAX(0,AD121-IF($A129>='1-Input'!$C$12,'1-Input'!$B$12,0))+AE129*(1-'P-Parametri'!$B$6*AD129))*(1+'1-Input'!$B$27)) -> 0 | AG129: =IF($A129>'1-Input'!$B$26,AI128,(AI128-AE129)*(1+$B$4)) -> 371536.23 | AH129: =IF($A129>'1-Input'!$B$26,AF129,AF129-'P-Parametri'!$B$8*(AG129+AF129)+MIN(MAX(AG129,0),'P-Parametri'!$B$8*(AG129+AF129))) -> 0 | AI129: =IF($A129>'1-Input'!$B$26,AG129,AG129-MIN(MAX(AG129,0),'P-Parametri'!$B$8*(AG129+AF129))) -> 370793.15 | AJ129: =IF($A129>'1-Input'!$B$26,AJ128,AJ128-AE129*(1-AD129)) -> 261135.52 | AK129: =IF($A129>'1-Input'!$B$26,0,IF(AP128<=0,0,MAX(0,(AP128-AQ128)/AP128))) -> 0.28308948 | AL129: =IF($A129>'1-Input'!$B$26,0,(MAX(0,AK121-IF($A129>='1-Input'!$C$12,'1-Input'!$B$12,0))-MIN(MAX(AO128,0),MAX(0,AK121-IF($A129>='1-Input'!$C$12,'1-Input'!$B$12,0))))*(1/(1-'P-Parametri'!$B$6*AK129))+MIN(MAX(0,AP128-(MAX(0,AK121-IF($A129>='1-Input'!$C$12,'1-Input'!$B$12,0))-MIN(MAX(AO128,0),MAX(0,AK121-IF($A129>='1-Input'!$C$12,'1-Input'!$B$12,0))))*(1/(1-'P-Parametri'!$B$6*AK129))),MAX(0,0*AK121-(AO128-MIN(MAX(AO128,0),MAX(0,AK121-IF($A129>='1-Input'!$C$12,'1-Input'!$B$12,0)))))*(1/(1-'P-Parametri'!$B$6*AK129)))) -> 18590.507 | AM129: =IF($A129>'1-Input'!$B$26,AO128,(AO128-MAX(0,AK121-IF($A129>='1-Input'!$C$12,'1-Input'!$B$12,0))+AL129*(1-'P-Parametri'!$B$6*AK129))*(1+'1-Input'!$B$27)) -> 0 | AN129: =IF($A129>'1-Input'!$B$26,AP128,(AP128-AL129)*(1+$B$4)) -> 371536.23 | AO129: =IF($A129>'1-Input'!$B$26,AM129,AM129-'P-Parametri'!$B$8*(AN129+AM129)+MIN(MAX(AN129,0),'P-Parametri'!$B$8*(AN129+AM129))) -> 0 | AP129: =IF($A129>'1-Input'!$B$26,AN129,AN129-MIN(MAX(AN129,0),'P-Parametri'!$B$8*(AN129+AM129))) -> 370793.15 | AQ129: =IF($A129>'1-Input'!$B$26,AQ128,AQ128-AL129*(1-AK129)) -> 261135.52
A130: =7 -> 7 | B130: =IF($A130>'1-Input'!$B$26,0,IF(G129<=0,0,MAX(0,(G129-H129)/G129))) -> 0.29573803 | C130: =IF($A130>'1-Input'!$B$26,0,(MAX(0,B121-IF($A130>='1-Input'!$C$12,'1-Input'!$B$12,0))-MIN(MAX(F129,0),MAX(0,B121-IF($A130>='1-Input'!$C$12,'1-Input'!$B$12,0))))*(1/(1-'P-Parametri'!$B$6*B130))+MIN(MAX(0,G129-(MAX(0,B121-IF($A130>='1-Input'!$C$12,'1-Input'!$B$12,0))-MIN(MAX(F129,0),MAX(0,B121-IF($A130>='1-Input'!$C$12,'1-Input'!$B$12,0))))*(1/(1-'P-Parametri'!$B$6*B130))),MAX(0,0*B121-(F129-MIN(MAX(F129,0),MAX(0,B121-IF($A130>='1-Input'!$C$12,'1-Input'!$B$12,0)))))*(1/(1-'P-Parametri'!$B$6*B130)))) -> 18070.533 | D130: =IF($A130>'1-Input'!$B$26,F129,(F129-MAX(0,B121-IF($A130>='1-Input'!$C$12,'1-Input'!$B$12,0))+C130*(1-'P-Parametri'!$B$6*B130))*(1+'1-Input'!$B$27)) -> 3.6248821e-12 | E130: =IF($A130>'1-Input'!$B$26,G129,(G129-C130)*(1+$B$4)) -> 363547.99 | F130: =IF($A130>'1-Input'!$B$26,D130,D130-'P-Parametri'!$B$8*(E130+D130)+MIN(MAX(E130,0),'P-Parametri'!$B$8*(E130+D130))) -> 3.6379788e-12 | G130: =IF($A130>'1-Input'!$B$26,E130,E130-MIN(MAX(E130,0),'P-Parametri'!$B$8*(E130+D130))) -> 362820.9 | H130: =IF($A130>'1-Input'!$B$26,H129,H129-C130*(1-B130)) -> 251012.77 | I130: =IF($A130>'1-Input'!$B$26,0,IF(N129<=0,0,MAX(0,(N129-O129)/N129))) -> 0.29573803 | J130: =IF($A130>'1-Input'!$B$26,0,(MAX(0,I121-IF($A130>='1-Input'!$C$12,'1-Input'!$B$12,0))-MIN(MAX(M129,0),MAX(0,I121-IF($A130>='1-Input'!$C$12,'1-Input'!$B$12,0))))*(1/(1-'P-Parametri'!$B$6*I130))+MIN(MAX(0,N129-(MAX(0,I121-IF($A130>='1-Input'!$C$12,'1-Input'!$B$12,0))-MIN(MAX(M129,0),MAX(0,I121-IF($A130>='1-Input'!$C$12,'1-Input'!$B$12,0))))*(1/(1-'P-Parametri'!$B$6*I130))),MAX(0,0*I121-(M129-MIN(MAX(M129,0),MAX(0,I121-IF($A130>='1-Input'!$C$12,'1-Input'!$B$12,0)))))*(1/(1-'P-Parametri'!$B$6*I130)))) -> 23777.017 | K130: =IF($A130>'1-Input'!$B$26,M129,(M129-MAX(0,I121-IF($A130>='1-Input'!$C$12,'1-Input'!$B$12,0))+J130*(1-'P-Parametri'!$B$6*I130))*(1+'1-Input'!$B$27)) -> 0 | L130: =IF($A130>'1-Input'!$B$26,N129,(N129-J130)*(1+$B$4)) -> 321018.83 | M130: =IF($A130>'1-Input'!$B$26,K130,K130-'P-Parametri'!$B$8*(L130+K130)+MIN(MAX(L130,0),'P-Parametri'!$B$8*(L130+K130))) -> 0 | N130: =IF($A130>'1-Input'!$B$26,L130,L130-MIN(MAX(L130,0),'P-Parametri'!$B$8*(L130+K130))) -> 320376.79 | O130: =IF($A130>'1-Input'!$B$26,O129,O129-J130*(1-I130)) -> 221648.38 | P130: =IF($A130>'1-Input'!$B$26,0,IF(U129<=0,0,MAX(0,(U129-V129)/U129))) -> 0.29573803 | Q130: =IF($A130>'1-Input'!$B$26,0,(MAX(0,P121-IF($A130>='1-Input'!$C$12,'1-Input'!$B$12,0))-MIN(MAX(T129,0),MAX(0,P121-IF($A130>='1-Input'!$C$12,'1-Input'!$B$12,0))))*(1/(1-'P-Parametri'!$B$6*P130))+MIN(MAX(0,U129-(MAX(0,P121-IF($A130>='1-Input'!$C$12,'1-Input'!$B$12,0))-MIN(MAX(T129,0),MAX(0,P121-IF($A130>='1-Input'!$C$12,'1-Input'!$B$12,0))))*(1/(1-'P-Parametri'!$B$6*P130))),MAX(0,0*P121-(T129-MIN(MAX(T129,0),MAX(0,P121-IF($A130>='1-Input'!$C$12,'1-Input'!$B$12,0)))))*(1/(1-'P-Parametri'!$B$6*P130)))) -> 18742.264 | R130: =IF($A130>'1-Input'!$B$26,T129,(T129-MAX(0,P121-IF($A130>='1-Input'!$C$12,'1-Input'!$B$12,0))+Q130*(1-'P-Parametri'!$B$6*P130))*(1+'1-Input'!$B$27)) -> 0 | S130: =IF($A130>'1-Input'!$B$26,U129,(U129-Q130)*(1+$B$4)) -> 358541.73 | T130: =IF($A130>'1-Input'!$B$26,R130,R130-'P-Parametri'!$B$8*(S130+R130)+MIN(MAX(S130,0),'P-Parametri'!$B$8*(S130+R130))) -> 0 | U130: =IF($A130>'1-Input'!$B$26,S130,S130-MIN(MAX(S130,0),'P-Parametri'!$B$8*(S130+R130))) -> 357824.64 | V130: =IF($A130>'1-Input'!$B$26,V129,V129-Q130*(1-P130)) -> 247556.18 | W130: =IF($A130>'1-Input'!$B$26,0,IF(AB129<=0,0,MAX(0,(AB129-AC129)/AB129))) -> 0.29573803 | X130: =IF($A130>'1-Input'!$B$26,0,(MAX(0,W121-IF($A130>='1-Input'!$C$12,'1-Input'!$B$12,0))-MIN(MAX(AA129,0),MAX(0,W121-IF($A130>='1-Input'!$C$12,'1-Input'!$B$12,0))))*(1/(1-'P-Parametri'!$B$6*W130))+MIN(MAX(0,AB129-(MAX(0,W121-IF($A130>='1-Input'!$C$12,'1-Input'!$B$12,0))-MIN(MAX(AA129,0),MAX(0,W121-IF($A130>='1-Input'!$C$12,'1-Input'!$B$12,0))))*(1/(1-'P-Parametri'!$B$6*W130))),MAX(0,0*W121-(AA129-MIN(MAX(AA129,0),MAX(0,W121-IF($A130>='1-Input'!$C$12,'1-Input'!$B$12,0)))))*(1/(1-'P-Parametri'!$B$6*W130)))) -> 18642.312 | Y130: =IF($A130>'1-Input'!$B$26,AA129,(AA129-MAX(0,W121-IF($A130>='1-Input'!$C$12,'1-Input'!$B$12,0))+X130*(1-'P-Parametri'!$B$6*W130))*(1+'1-Input'!$B$27)) -> 0 | Z130: =IF($A130>'1-Input'!$B$26,AB129,(AB129-X130)*(1+$B$4)) -> 359286.65 | AA130: =IF($A130>'1-Input'!$B$26,Y130,Y130-'P-Parametri'!$B$8*(Z130+Y130)+MIN(MAX(Z130,0),'P-Parametri'!$B$8*(Z130+Y130))) -> 0 | AB130: =IF($A130>'1-Input'!$B$26,Z130,Z130-MIN(MAX(Z130,0),'P-Parametri'!$B$8*(Z130+Y130))) -> 358568.07 | AC130: =IF($A130>'1-Input'!$B$26,AC129,AC129-X130*(1-W130)) -> 248070.51 | AD130: =IF($A130>'1-Input'!$B$26,0,IF(AI129<=0,0,MAX(0,(AI129-AJ129)/AI129))) -> 0.29573803 | AE130: =IF($A130>'1-Input'!$B$26,0,(MAX(0,AD121-IF($A130>='1-Input'!$C$12,'1-Input'!$B$12,0))-MIN(MAX(AH129,0),MAX(0,AD121-IF($A130>='1-Input'!$C$12,'1-Input'!$B$12,0))))*(1/(1-'P-Parametri'!$B$6*AD130))+MIN(MAX(0,AI129-(MAX(0,AD121-IF($A130>='1-Input'!$C$12,'1-Input'!$B$12,0))-MIN(MAX(AH129,0),MAX(0,AD121-IF($A130>='1-Input'!$C$12,'1-Input'!$B$12,0))))*(1/(1-'P-Parametri'!$B$6*AD130))),MAX(0,0*AD121-(AH129-MIN(MAX(AH129,0),MAX(0,AD121-IF($A130>='1-Input'!$C$12,'1-Input'!$B$12,0)))))*(1/(1-'P-Parametri'!$B$6*AD130)))) -> 18656.736 | AF130: =IF($A130>'1-Input'!$B$26,AH129,(AH129-MAX(0,AD121-IF($A130>='1-Input'!$C$12,'1-Input'!$B$12,0))+AE130*(1-'P-Parametri'!$B$6*AD130))*(1+'1-Input'!$B$27)) -> 3.6248821e-12 | AG130: =IF($A130>'1-Input'!$B$26,AI129,(AI129-AE130)*(1+$B$4)) -> 359179.15 | AH130: =IF($A130>'1-Input'!$B$26,AF130,AF130-'P-Parametri'!$B$8*(AG130+AF130)+MIN(MAX(AG130,0),'P-Parametri'!$B$8*(AG130+AF130))) -> 3.6379788e-12 | AI130: =IF($A130>'1-Input'!$B$26,AG130,AG130-MIN(MAX(AG130,0),'P-Parametri'!$B$8*(AG130+AF130))) -> 358460.79 | AJ130: =IF($A130>'1-Input'!$B$26,AJ129,AJ129-AE130*(1-AD130)) -> 247996.29 | AK130: =IF($A130>'1-Input'!$B$26,0,IF(AP129<=0,0,MAX(0,(AP129-AQ129)/AP129))) -> 0.29573803 | AL130: =IF($A130>'1-Input'!$B$26,0,(MAX(0,AK121-IF($A130>='1-Input'!$C$12,'1-Input'!$B$12,0))-MIN(MAX(AO129,0),MAX(0,AK121-IF($A130>='1-Input'!$C$12,'1-Input'!$B$12,0))))*(1/(1-'P-Parametri'!$B$6*AK130))+MIN(MAX(0,AP129-(MAX(0,AK121-IF($A130>='1-Input'!$C$12,'1-Input'!$B$12,0))-MIN(MAX(AO129,0),MAX(0,AK121-IF($A130>='1-Input'!$C$12,'1-Input'!$B$12,0))))*(1/(1-'P-Parametri'!$B$6*AK130))),MAX(0,0*AK121-(AO129-MIN(MAX(AO129,0),MAX(0,AK121-IF($A130>='1-Input'!$C$12,'1-Input'!$B$12,0)))))*(1/(1-'P-Parametri'!$B$6*AK130)))) -> 18656.736 | AM130: =IF($A130>'1-Input'!$B$26,AO129,(AO129-MAX(0,AK121-IF($A130>='1-Input'!$C$12,'1-Input'!$B$12,0))+AL130*(1-'P-Parametri'!$B$6*AK130))*(1+'1-Input'!$B$27)) -> 3.6248821e-12 | AN130: =IF($A130>'1-Input'!$B$26,AP129,(AP129-AL130)*(1+$B$4)) -> 359179.15 | AO130: =IF($A130>'1-Input'!$B$26,AM130,AM130-'P-Parametri'!$B$8*(AN130+AM130)+MIN(MAX(AN130,0),'P-Parametri'!$B$8*(AN130+AM130))) -> 3.6379788e-12 | AP130: =IF($A130>'1-Input'!$B$26,AN130,AN130-MIN(MAX(AN130,0),'P-Parametri'!$B$8*(AN130+AM130))) -> 358460.79 | AQ130: =IF($A130>'1-Input'!$B$26,AQ129,AQ129-AL130*(1-AK130)) -> 247996.29
A131: =8 -> 8 | B131: =IF($A131>'1-Input'!$B$26,0,IF(G130<=0,0,MAX(0,(G130-H130)/G130))) -> 0.30816341 | C131: =IF($A131>'1-Input'!$B$26,0,(MAX(0,B121-IF($A131>='1-Input'!$C$12,'1-Input'!$B$12,0))-MIN(MAX(F130,0),MAX(0,B121-IF($A131>='1-Input'!$C$12,'1-Input'!$B$12,0))))*(1/(1-'P-Parametri'!$B$6*B131))+MIN(MAX(0,G130-(MAX(0,B121-IF($A131>='1-Input'!$C$12,'1-Input'!$B$12,0))-MIN(MAX(F130,0),MAX(0,B121-IF($A131>='1-Input'!$C$12,'1-Input'!$B$12,0))))*(1/(1-'P-Parametri'!$B$6*B131))),MAX(0,0*B121-(F130-MIN(MAX(F130,0),MAX(0,B121-IF($A131>='1-Input'!$C$12,'1-Input'!$B$12,0)))))*(1/(1-'P-Parametri'!$B$6*B131)))) -> 18133.996 | D131: =IF($A131>'1-Input'!$B$26,F130,(F130-MAX(0,B121-IF($A131>='1-Input'!$C$12,'1-Input'!$B$12,0))+C131*(1-'P-Parametri'!$B$6*B131))*(1+'1-Input'!$B$27)) -> 0 | E131: =IF($A131>'1-Input'!$B$26,G130,(G130-C131)*(1+$B$4)) -> 351580.64 | F131: =IF($A131>'1-Input'!$B$26,D131,D131-'P-Parametri'!$B$8*(E131+D131)+MIN(MAX(E131,0),'P-Parametri'!$B$8*(E131+D131))) -> 0 | G131: =IF($A131>'1-Input'!$B$26,E131,E131-MIN(MAX(E131,0),'P-Parametri'!$B$8*(E131+D131))) -> 350877.48 | H131: =IF($A131>'1-Input'!$B$26,H130,H130-C131*(1-B131)) -> 238467.01 | I131: =IF($A131>'1-Input'!$B$26,0,IF(N130<=0,0,MAX(0,(N130-O130)/N130))) -> 0.30816341 | J131: =IF($A131>'1-Input'!$B$26,0,(MAX(0,I121-IF($A131>='1-Input'!$C$12,'1-Input'!$B$12,0))-MIN(MAX(M130,0),MAX(0,I121-IF($A131>='1-Input'!$C$12,'1-Input'!$B$12,0))))*(1/(1-'P-Parametri'!$B$6*I131))+MIN(MAX(0,N130-(MAX(0,I121-IF($A131>='1-Input'!$C$12,'1-Input'!$B$12,0))-MIN(MAX(M130,0),MAX(0,I121-IF($A131>='1-Input'!$C$12,'1-Input'!$B$12,0))))*(1/(1-'P-Parametri'!$B$6*I131))),MAX(0,0*I121-(M130-MIN(MAX(M130,0),MAX(0,I121-IF($A131>='1-Input'!$C$12,'1-Input'!$B$12,0)))))*(1/(1-'P-Parametri'!$B$6*I131)))) -> 23860.521 | K131: =IF($A131>'1-Input'!$B$26,M130,(M130-MAX(0,I121-IF($A131>='1-Input'!$C$12,'1-Input'!$B$12,0))+J131*(1-'P-Parametri'!$B$6*I131))*(1+'1-Input'!$B$27)) -> 0 | L131: =IF($A131>'1-Input'!$B$26,N130,(N130-J131)*(1+$B$4)) -> 302446.59 | M131: =IF($A131>'1-Input'!$B$26,K131,K131-'P-Parametri'!$B$8*(L131+K131)+MIN(MAX(L131,0),'P-Parametri'!$B$8*(L131+K131))) -> 0 | N131: =IF($A131>'1-Input'!$B$26,L131,L131-MIN(MAX(L131,0),'P-Parametri'!$B$8*(L131+K131))) -> 301841.7 | O131: =IF($A131>'1-Input'!$B$26,O130,O130-J131*(1-I131)) -> 205140.8 | P131: =IF($A131>'1-Input'!$B$26,0,IF(U130<=0,0,MAX(0,(U130-V130)/U130))) -> 0.30816341 | Q131: =IF($A131>'1-Input'!$B$26,0,(MAX(0,P121-IF($A131>='1-Input'!$C$12,'1-Input'!$B$12,0))-MIN(MAX(T130,0),MAX(0,P121-IF($A131>='1-Input'!$C$12,'1-Input'!$B$12,0))))*(1/(1-'P-Parametri'!$B$6*P131))+MIN(MAX(0,U130-(MAX(0,P121-IF($A131>='1-Input'!$C$12,'1-Input'!$B$12,0))-MIN(MAX(T130,0),MAX(0,P121-IF($A131>='1-Input'!$C$12,'1-Input'!$B$12,0))))*(1/(1-'P-Parametri'!$B$6*P131))),MAX(0,0*P121-(T130-MIN(MAX(T130,0),MAX(0,P121-IF($A131>='1-Input'!$C$12,'1-Input'!$B$12,0)))))*(1/(1-'P-Parametri'!$B$6*P131)))) -> 18808.087 | R131: =IF($A131>'1-Input'!$B$26,T130,(T130-MAX(0,P121-IF($A131>='1-Input'!$C$12,'1-Input'!$B$12,0))+Q131*(1-'P-Parametri'!$B$6*P131))*(1+'1-Input'!$B$27)) -> 3.6248821e-12 | S131: =IF($A131>'1-Input'!$B$26,U130,(U130-Q131)*(1+$B$4)) -> 345796.89 | T131: =IF($A131>'1-Input'!$B$26,R131,R131-'P-Parametri'!$B$8*(S131+R131)+MIN(MAX(S131,0),'P-Parametri'!$B$8*(S131+R131))) -> 3.6379788e-12 | U131: =IF($A131>'1-Input'!$B$26,S131,S131-MIN(MAX(S131,0),'P-Parametri'!$B$8*(S131+R131))) -> 345105.3 | V131: =IF($A131>'1-Input'!$B$26,V130,V130-Q131*(1-P131)) -> 234544.06 | W131: =IF($A131>'1-Input'!$B$26,0,IF(AB130<=0,0,MAX(0,(AB130-AC130)/AB130))) -> 0.30816341 | X131: =IF($A131>'1-Input'!$B$26,0,(MAX(0,W121-IF($A131>='1-Input'!$C$12,'1-Input'!$B$12,0))-MIN(MAX(AA130,0),MAX(0,W121-IF($A131>='1-Input'!$C$12,'1-Input'!$B$12,0))))*(1/(1-'P-Parametri'!$B$6*W131))+MIN(MAX(0,AB130-(MAX(0,W121-IF($A131>='1-Input'!$C$12,'1-Input'!$B$12,0))-MIN(MAX(AA130,0),MAX(0,W121-IF($A131>='1-Input'!$C$12,'1-Input'!$B$12,0))))*(1/(1-'P-Parametri'!$B$6*W131))),MAX(0,0*W121-(AA130-MIN(MAX(AA130,0),MAX(0,W121-IF($A131>='1-Input'!$C$12,'1-Input'!$B$12,0)))))*(1/(1-'P-Parametri'!$B$6*W131)))) -> 18707.784 | Y131: =IF($A131>'1-Input'!$B$26,AA130,(AA130-MAX(0,W121-IF($A131>='1-Input'!$C$12,'1-Input'!$B$12,0))+X131*(1-'P-Parametri'!$B$6*W131))*(1+'1-Input'!$B$27)) -> 3.6248821e-12 | Z131: =IF($A131>'1-Input'!$B$26,AB130,(AB130-X131)*(1+$B$4)) -> 346657.5 | AA131: =IF($A131>'1-Input'!$B$26,Y131,Y131-'P-Parametri'!$B$8*(Z131+Y131)+MIN(MAX(Z131,0),'P-Parametri'!$B$8*(Z131+Y131))) -> 3.6379788e-12 | AB131: =IF($A131>'1-Input'!$B$26,Z131,Z131-MIN(MAX(Z131,0),'P-Parametri'!$B$8*(Z131+Y131))) -> 345964.18 | AC131: =IF($A131>'1-Input'!$B$26,AC130,AC130-X131*(1-W131)) -> 235127.78 | AD131: =IF($A131>'1-Input'!$B$26,0,IF(AI130<=0,0,MAX(0,(AI130-AJ130)/AI130))) -> 0.30816341 | AE131: =IF($A131>'1-Input'!$B$26,0,(MAX(0,AD121-IF($A131>='1-Input'!$C$12,'1-Input'!$B$12,0))-MIN(MAX(AH130,0),MAX(0,AD121-IF($A131>='1-Input'!$C$12,'1-Input'!$B$12,0))))*(1/(1-'P-Parametri'!$B$6*AD131))+MIN(MAX(0,AI130-(MAX(0,AD121-IF($A131>='1-Input'!$C$12,'1-Input'!$B$12,0))-MIN(MAX(AH130,0),MAX(0,AD121-IF($A131>='1-Input'!$C$12,'1-Input'!$B$12,0))))*(1/(1-'P-Parametri'!$B$6*AD131))),MAX(0,0*AD121-(AH130-MIN(MAX(AH130,0),MAX(0,AD121-IF($A131>='1-Input'!$C$12,'1-Input'!$B$12,0)))))*(1/(1-'P-Parametri'!$B$6*AD131)))) -> 18722.259 | AF131: =IF($A131>'1-Input'!$B$26,AH130,(AH130-MAX(0,AD121-IF($A131>='1-Input'!$C$12,'1-Input'!$B$12,0))+AE131*(1-'P-Parametri'!$B$6*AD131))*(1+'1-Input'!$B$27)) -> 0 | AG131: =IF($A131>'1-Input'!$B$26,AI130,(AI130-AE131)*(1+$B$4)) -> 346533.3 | AH131: =IF($A131>'1-Input'!$B$26,AF131,AF131-'P-Parametri'!$B$8*(AG131+AF131)+MIN(MAX(AG131,0),'P-Parametri'!$B$8*(AG131+AF131))) -> 0 | AI131: =IF($A131>'1-Input'!$B$26,AG131,AG131-MIN(MAX(AG131,0),'P-Parametri'!$B$8*(AG131+AF131))) -> 345840.23 | AJ131: =IF($A131>'1-Input'!$B$26,AJ130,AJ130-AE131*(1-AD131)) -> 235043.54 | AK131: =IF($A131>'1-Input'!$B$26,0,IF(AP130<=0,0,MAX(0,(AP130-AQ130)/AP130))) -> 0.30816341 | AL131: =IF($A131>'1-Input'!$B$26,0,(MAX(0,AK121-IF($A131>='1-Input'!$C$12,'1-Input'!$B$12,0))-MIN(MAX(AO130,0),MAX(0,AK121-IF($A131>='1-Input'!$C$12,'1-Input'!$B$12,0))))*(1/(1-'P-Parametri'!$B$6*AK131))+MIN(MAX(0,AP130-(MAX(0,AK121-IF($A131>='1-Input'!$C$12,'1-Input'!$B$12,0))-MIN(MAX(AO130,0),MAX(0,AK121-IF($A131>='1-Input'!$C$12,'1-Input'!$B$12,0))))*(1/(1-'P-Parametri'!$B$6*AK131))),MAX(0,0*AK121-(AO130-MIN(MAX(AO130,0),MAX(0,AK121-IF($A131>='1-Input'!$C$12,'1-Input'!$B$12,0)))))*(1/(1-'P-Parametri'!$B$6*AK131)))) -> 18722.259 | AM131: =IF($A131>'1-Input'!$B$26,AO130,(AO130-MAX(0,AK121-IF($A131>='1-Input'!$C$12,'1-Input'!$B$12,0))+AL131*(1-'P-Parametri'!$B$6*AK131))*(1+'1-Input'!$B$27)) -> 0 | AN131: =IF($A131>'1-Input'!$B$26,AP130,(AP130-AL131)*(1+$B$4)) -> 346533.3 | AO131: =IF($A131>'1-Input'!$B$26,AM131,AM131-'P-Parametri'!$B$8*(AN131+AM131)+MIN(MAX(AN131,0),'P-Parametri'!$B$8*(AN131+AM131))) -> 0 | AP131: =IF($A131>'1-Input'!$B$26,AN131,AN131-MIN(MAX(AN131,0),'P-Parametri'!$B$8*(AN131+AM131))) -> 345840.23 | AQ131: =IF($A131>'1-Input'!$B$26,AQ130,AQ130-AL131*(1-AK131)) -> 235043.54
A132: =9 -> 9 | B132: =IF($A132>'1-Input'!$B$26,0,IF(G131<=0,0,MAX(0,(G131-H131)/G131))) -> 0.32036958 | C132: =IF($A132>'1-Input'!$B$26,0,(MAX(0,B121-IF($A132>='1-Input'!$C$12,'1-Input'!$B$12,0))-MIN(MAX(F131,0),MAX(0,B121-IF($A132>='1-Input'!$C$12,'1-Input'!$B$12,0))))*(1/(1-'P-Parametri'!$B$6*B132))+MIN(MAX(0,G131-(MAX(0,B121-IF($A132>='1-Input'!$C$12,'1-Input'!$B$12,0))-MIN(MAX(F131,0),MAX(0,B121-IF($A132>='1-Input'!$C$12,'1-Input'!$B$12,0))))*(1/(1-'P-Parametri'!$B$6*B132))),MAX(0,0*B121-(F131-MIN(MAX(F131,0),MAX(0,B121-IF($A132>='1-Input'!$C$12,'1-Input'!$B$12,0)))))*(1/(1-'P-Parametri'!$B$6*B132)))) -> 18196.776 | D132: =IF($A132>'1-Input'!$B$26,F131,(F131-MAX(0,B121-IF($A132>='1-Input'!$C$12,'1-Input'!$B$12,0))+C132*(1-'P-Parametri'!$B$6*B132))*(1+'1-Input'!$B$27)) -> 0 | E132: =IF($A132>'1-Input'!$B$26,G131,(G131-C132)*(1+$B$4)) -> 339334.32 | F132: =IF($A132>'1-Input'!$B$26,D132,D132-'P-Parametri'!$B$8*(E132+D132)+MIN(MAX(E132,0),'P-Parametri'!$B$8*(E132+D132))) -> 0 | G132: =IF($A132>'1-Input'!$B$26,E132,E132-MIN(MAX(E132,0),'P-Parametri'!$B$8*(E132+D132))) -> 338655.65 | H132: =IF($A132>'1-Input'!$B$26,H131,H131-C132*(1-B132)) -> 226099.93 | I132: =IF($A132>'1-Input'!$B$26,0,IF(N131<=0,0,MAX(0,(N131-O131)/N131))) -> 0.32036958 | J132: =IF($A132>'1-Input'!$B$26,0,(MAX(0,I121-IF($A132>='1-Input'!$C$12,'1-Input'!$B$12,0))-MIN(MAX(M131,0),MAX(0,I121-IF($A132>='1-Input'!$C$12,'1-Input'!$B$12,0))))*(1/(1-'P-Parametri'!$B$6*I132))+MIN(MAX(0,N131-(MAX(0,I121-IF($A132>='1-Input'!$C$12,'1-Input'!$B$12,0))-MIN(MAX(M131,0),MAX(0,I121-IF($A132>='1-Input'!$C$12,'1-Input'!$B$12,0))))*(1/(1-'P-Parametri'!$B$6*I132))),MAX(0,0*I121-(M131-MIN(MAX(M131,0),MAX(0,I121-IF($A132>='1-Input'!$C$12,'1-Input'!$B$12,0)))))*(1/(1-'P-Parametri'!$B$6*I132)))) -> 23943.126 | K132: =IF($A132>'1-Input'!$B$26,M131,(M131-MAX(0,I121-IF($A132>='1-Input'!$C$12,'1-Input'!$B$12,0))+J132*(1-'P-Parametri'!$B$6*I132))*(1+'1-Input'!$B$27)) -> 0 | L132: =IF($A132>'1-Input'!$B$26,N131,(N131-J132)*(1+$B$4)) -> 283456.55 | M132: =IF($A132>'1-Input'!$B$26,K132,K132-'P-Parametri'!$B$8*(L132+K132)+MIN(MAX(L132,0),'P-Parametri'!$B$8*(L132+K132))) -> 0 | N132: =IF($A132>'1-Input'!$B$26,L132,L132-MIN(MAX(L132,0),'P-Parametri'!$B$8*(L132+K132))) -> 282889.63 | O132: =IF($A132>'1-Input'!$B$26,O131,O131-J132*(1-I132)) -> 188868.33 | P132: =IF($A132>'1-Input'!$B$26,0,IF(U131<=0,0,MAX(0,(U131-V131)/U131))) -> 0.32036958 | Q132: =IF($A132>'1-Input'!$B$26,0,(MAX(0,P121-IF($A132>='1-Input'!$C$12,'1-Input'!$B$12,0))-MIN(MAX(T131,0),MAX(0,P121-IF($A132>='1-Input'!$C$12,'1-Input'!$B$12,0))))*(1/(1-'P-Parametri'!$B$6*P132))+MIN(MAX(0,U131-(MAX(0,P121-IF($A132>='1-Input'!$C$12,'1-Input'!$B$12,0))-MIN(MAX(T131,0),MAX(0,P121-IF($A132>='1-Input'!$C$12,'1-Input'!$B$12,0))))*(1/(1-'P-Parametri'!$B$6*P132))),MAX(0,0*P121-(T131-MIN(MAX(T131,0),MAX(0,P121-IF($A132>='1-Input'!$C$12,'1-Input'!$B$12,0)))))*(1/(1-'P-Parametri'!$B$6*P132)))) -> 18873.2 | R132: =IF($A132>'1-Input'!$B$26,T131,(T131-MAX(0,P121-IF($A132>='1-Input'!$C$12,'1-Input'!$B$12,0))+Q132*(1-'P-Parametri'!$B$6*P132))*(1+'1-Input'!$B$27)) -> 3.6248821e-12 | S132: =IF($A132>'1-Input'!$B$26,U131,(U131-Q132)*(1+$B$4)) -> 332756.74 | T132: =IF($A132>'1-Input'!$B$26,R132,R132-'P-Parametri'!$B$8*(S132+R132)+MIN(MAX(S132,0),'P-Parametri'!$B$8*(S132+R132))) -> 3.6379788e-12 | U132: =IF($A132>'1-Input'!$B$26,S132,S132-MIN(MAX(S132,0),'P-Parametri'!$B$8*(S132+R132))) -> 332091.22 | V132: =IF($A132>'1-Input'!$B$26,V131,V131-Q132*(1-P132)) -> 221717.26 | W132: =IF($A132>'1-Input'!$B$26,0,IF(AB131<=0,0,MAX(0,(AB131-AC131)/AB131))) -> 0.32036958 | X132: =IF($A132>'1-Input'!$B$26,0,(MAX(0,W121-IF($A132>='1-Input'!$C$12,'1-Input'!$B$12,0))-MIN(MAX(AA131,0),MAX(0,W121-IF($A132>='1-Input'!$C$12,'1-Input'!$B$12,0))))*(1/(1-'P-Parametri'!$B$6*W132))+MIN(MAX(0,AB131-(MAX(0,W121-IF($A132>='1-Input'!$C$12,'1-Input'!$B$12,0))-MIN(MAX(AA131,0),MAX(0,W121-IF($A132>='1-Input'!$C$12,'1-Input'!$B$12,0))))*(1/(1-'P-Parametri'!$B$6*W132))),MAX(0,0*W121-(AA131-MIN(MAX(AA131,0),MAX(0,W121-IF($A132>='1-Input'!$C$12,'1-Input'!$B$12,0)))))*(1/(1-'P-Parametri'!$B$6*W132)))) -> 18772.55 | Y132: =IF($A132>'1-Input'!$B$26,AA131,(AA131-MAX(0,W121-IF($A132>='1-Input'!$C$12,'1-Input'!$B$12,0))+X132*(1-'P-Parametri'!$B$6*W132))*(1+'1-Input'!$B$27)) -> 3.6248821e-12 | Z132: =IF($A132>'1-Input'!$B$26,AB131,(AB131-X132)*(1+$B$4)) -> 333735.46 | AA132: =IF($A132>'1-Input'!$B$26,Y132,Y132-'P-Parametri'!$B$8*(Z132+Y132)+MIN(MAX(Z132,0),'P-Parametri'!$B$8*(Z132+Y132))) -> 3.6379788e-12 | AB132: =IF($A132>'1-Input'!$B$26,Z132,Z132-MIN(MAX(Z132,0),'P-Parametri'!$B$8*(Z132+Y132))) -> 333067.99 | AC132: =IF($A132>'1-Input'!$B$26,AC131,AC131-X132*(1-W132)) -> 222369.39 | AD132: =IF($A132>'1-Input'!$B$26,0,IF(AI131<=0,0,MAX(0,(AI131-AJ131)/AI131))) -> 0.32036958 | AE132: =IF($A132>'1-Input'!$B$26,0,(MAX(0,AD121-IF($A132>='1-Input'!$C$12,'1-Input'!$B$12,0))-MIN(MAX(AH131,0),MAX(0,AD121-IF($A132>='1-Input'!$C$12,'1-Input'!$B$12,0))))*(1/(1-'P-Parametri'!$B$6*AD132))+MIN(MAX(0,AI131-(MAX(0,AD121-IF($A132>='1-Input'!$C$12,'1-Input'!$B$12,0))-MIN(MAX(AH131,0),MAX(0,AD121-IF($A132>='1-Input'!$C$12,'1-Input'!$B$12,0))))*(1/(1-'P-Parametri'!$B$6*AD132))),MAX(0,0*AD121-(AH131-MIN(MAX(AH131,0),MAX(0,AD121-IF($A132>='1-Input'!$C$12,'1-Input'!$B$12,0)))))*(1/(1-'P-Parametri'!$B$6*AD132)))) -> 18787.075 | AF132: =IF($A132>'1-Input'!$B$26,AH131,(AH131-MAX(0,AD121-IF($A132>='1-Input'!$C$12,'1-Input'!$B$12,0))+AE132*(1-'P-Parametri'!$B$6*AD132))*(1+'1-Input'!$B$27)) -> 0 | AG132: =IF($A132>'1-Input'!$B$26,AI131,(AI131-AE132)*(1+$B$4)) -> 333594.22 | AH132: =IF($A132>'1-Input'!$B$26,AF132,AF132-'P-Parametri'!$B$8*(AG132+AF132)+MIN(MAX(AG132,0),'P-Parametri'!$B$8*(AG132+AF132))) -> 0 | AI132: =IF($A132>'1-Input'!$B$26,AG132,AG132-MIN(MAX(AG132,0),'P-Parametri'!$B$8*(AG132+AF132))) -> 332927.03 | AJ132: =IF($A132>'1-Input'!$B$26,AJ131,AJ131-AE132*(1-AD132)) -> 222275.28 | AK132: =IF($A132>'1-Input'!$B$26,0,IF(AP131<=0,0,MAX(0,(AP131-AQ131)/AP131))) -> 0.32036958 | AL132: =IF($A132>'1-Input'!$B$26,0,(MAX(0,AK121-IF($A132>='1-Input'!$C$12,'1-Input'!$B$12,0))-MIN(MAX(AO131,0),MAX(0,AK121-IF($A132>='1-Input'!$C$12,'1-Input'!$B$12,0))))*(1/(1-'P-Parametri'!$B$6*AK132))+MIN(MAX(0,AP131-(MAX(0,AK121-IF($A132>='1-Input'!$C$12,'1-Input'!$B$12,0))-MIN(MAX(AO131,0),MAX(0,AK121-IF($A132>='1-Input'!$C$12,'1-Input'!$B$12,0))))*(1/(1-'P-Parametri'!$B$6*AK132))),MAX(0,0*AK121-(AO131-MIN(MAX(AO131,0),MAX(0,AK121-IF($A132>='1-Input'!$C$12,'1-Input'!$B$12,0)))))*(1/(1-'P-Parametri'!$B$6*AK132)))) -> 18787.075 | AM132: =IF($A132>'1-Input'!$B$26,AO131,(AO131-MAX(0,AK121-IF($A132>='1-Input'!$C$12,'1-Input'!$B$12,0))+AL132*(1-'P-Parametri'!$B$6*AK132))*(1+'1-Input'!$B$27)) -> 0 | AN132: =IF($A132>'1-Input'!$B$26,AP131,(AP131-AL132)*(1+$B$4)) -> 333594.22 | AO132: =IF($A132>'1-Input'!$B$26,AM132,AM132-'P-Parametri'!$B$8*(AN132+AM132)+MIN(MAX(AN132,0),'P-Parametri'!$B$8*(AN132+AM132))) -> 0 | AP132: =IF($A132>'1-Input'!$B$26,AN132,AN132-MIN(MAX(AN132,0),'P-Parametri'!$B$8*(AN132+AM132))) -> 332927.03 | AQ132: =IF($A132>'1-Input'!$B$26,AQ131,AQ131-AL132*(1-AK132)) -> 222275.28
A133: =10 -> 10 | B133: =IF($A133>'1-Input'!$B$26,0,IF(G132<=0,0,MAX(0,(G132-H132)/G132))) -> 0.33236038 | C133: =IF($A133>'1-Input'!$B$26,0,(MAX(0,B121-IF($A133>='1-Input'!$C$12,'1-Input'!$B$12,0))-MIN(MAX(F132,0),MAX(0,B121-IF($A133>='1-Input'!$C$12,'1-Input'!$B$12,0))))*(1/(1-'P-Parametri'!$B$6*B133))+MIN(MAX(0,G132-(MAX(0,B121-IF($A133>='1-Input'!$C$12,'1-Input'!$B$12,0))-MIN(MAX(F132,0),MAX(0,B121-IF($A133>='1-Input'!$C$12,'1-Input'!$B$12,0))))*(1/(1-'P-Parametri'!$B$6*B133))),MAX(0,0*B121-(F132-MIN(MAX(F132,0),MAX(0,B121-IF($A133>='1-Input'!$C$12,'1-Input'!$B$12,0)))))*(1/(1-'P-Parametri'!$B$6*B133)))) -> 18258.872 | D133: =IF($A133>'1-Input'!$B$26,F132,(F132-MAX(0,B121-IF($A133>='1-Input'!$C$12,'1-Input'!$B$12,0))+C133*(1-'P-Parametri'!$B$6*B133))*(1+'1-Input'!$B$27)) -> 0 | E133: =IF($A133>'1-Input'!$B$26,G132,(G132-C133)*(1+$B$4)) -> 326804.71 | F133: =IF($A133>'1-Input'!$B$26,D133,D133-'P-Parametri'!$B$8*(E133+D133)+MIN(MAX(E133,0),'P-Parametri'!$B$8*(E133+D133))) -> 0 | G133: =IF($A133>'1-Input'!$B$26,E133,E133-MIN(MAX(E133,0),'P-Parametri'!$B$8*(E133+D133))) -> 326151.1 | H133: =IF($A133>'1-Input'!$B$26,H132,H132-C133*(1-B133)) -> 213909.58 | I133: =IF($A133>'1-Input'!$B$26,0,IF(N132<=0,0,MAX(0,(N132-O132)/N132))) -> 0.33236038 | J133: =IF($A133>'1-Input'!$B$26,0,(MAX(0,I121-IF($A133>='1-Input'!$C$12,'1-Input'!$B$12,0))-MIN(MAX(M132,0),MAX(0,I121-IF($A133>='1-Input'!$C$12,'1-Input'!$B$12,0))))*(1/(1-'P-Parametri'!$B$6*I133))+MIN(MAX(0,N132-(MAX(0,I121-IF($A133>='1-Input'!$C$12,'1-Input'!$B$12,0))-MIN(MAX(M132,0),MAX(0,I121-IF($A133>='1-Input'!$C$12,'1-Input'!$B$12,0))))*(1/(1-'P-Parametri'!$B$6*I133))),MAX(0,0*I121-(M132-MIN(MAX(M132,0),MAX(0,I121-IF($A133>='1-Input'!$C$12,'1-Input'!$B$12,0)))))*(1/(1-'P-Parametri'!$B$6*I133)))) -> 24024.832 | K133: =IF($A133>'1-Input'!$B$26,M132,(M132-MAX(0,I121-IF($A133>='1-Input'!$C$12,'1-Input'!$B$12,0))+J133*(1-'P-Parametri'!$B$6*I133))*(1+'1-Input'!$B$27)) -> 3.6248821e-12 | L133: =IF($A133>'1-Input'!$B$26,N132,(N132-J133)*(1+$B$4)) -> 264042.1 | M133: =IF($A133>'1-Input'!$B$26,K133,K133-'P-Parametri'!$B$8*(L133+K133)+MIN(MAX(L133,0),'P-Parametri'!$B$8*(L133+K133))) -> 3.6379788e-12 | N133: =IF($A133>'1-Input'!$B$26,L133,L133-MIN(MAX(L133,0),'P-Parametri'!$B$8*(L133+K133))) -> 263514.01 | O133: =IF($A133>'1-Input'!$B$26,O132,O132-J133*(1-I133)) -> 172828.4 | P133: =IF($A133>'1-Input'!$B$26,0,IF(U132<=0,0,MAX(0,(U132-V132)/U132))) -> 0.33236038 | Q133: =IF($A133>'1-Input'!$B$26,0,(MAX(0,P121-IF($A133>='1-Input'!$C$12,'1-Input'!$B$12,0))-MIN(MAX(T132,0),MAX(0,P121-IF($A133>='1-Input'!$C$12,'1-Input'!$B$12,0))))*(1/(1-'P-Parametri'!$B$6*P133))+MIN(MAX(0,U132-(MAX(0,P121-IF($A133>='1-Input'!$C$12,'1-Input'!$B$12,0))-MIN(MAX(T132,0),MAX(0,P121-IF($A133>='1-Input'!$C$12,'1-Input'!$B$12,0))))*(1/(1-'P-Parametri'!$B$6*P133))),MAX(0,0*P121-(T132-MIN(MAX(T132,0),MAX(0,P121-IF($A133>='1-Input'!$C$12,'1-Input'!$B$12,0)))))*(1/(1-'P-Parametri'!$B$6*P133)))) -> 18937.604 | R133: =IF($A133>'1-Input'!$B$26,T132,(T132-MAX(0,P121-IF($A133>='1-Input'!$C$12,'1-Input'!$B$12,0))+Q133*(1-'P-Parametri'!$B$6*P133))*(1+'1-Input'!$B$27)) -> 3.6248821e-12 | S133: =IF($A133>'1-Input'!$B$26,U132,(U132-Q133)*(1+$B$4)) -> 319416.69 | T133: =IF($A133>'1-Input'!$B$26,R133,R133-'P-Parametri'!$B$8*(S133+R133)+MIN(MAX(S133,0),'P-Parametri'!$B$8*(S133+R133))) -> 3.6379788e-12 | U133: =IF($A133>'1-Input'!$B$26,S133,S133-MIN(MAX(S133,0),'P-Parametri'!$B$8*(S133+R133))) -> 318777.86 | V133: =IF($A133>'1-Input'!$B$26,V132,V132-Q133*(1-P133)) -> 209073.76 | W133: =IF($A133>'1-Input'!$B$26,0,IF(AB132<=0,0,MAX(0,(AB132-AC132)/AB132))) -> 0.33236038 | X133: =IF($A133>'1-Input'!$B$26,0,(MAX(0,W121-IF($A133>='1-Input'!$C$12,'1-Input'!$B$12,0))-MIN(MAX(AA132,0),MAX(0,W121-IF($A133>='1-Input'!$C$12,'1-Input'!$B$12,0))))*(1/(1-'P-Parametri'!$B$6*W133))+MIN(MAX(0,AB132-(MAX(0,W121-IF($A133>='1-Input'!$C$12,'1-Input'!$B$12,0))-MIN(MAX(AA132,0),MAX(0,W121-IF($A133>='1-Input'!$C$12,'1-Input'!$B$12,0))))*(1/(1-'P-Parametri'!$B$6*W133))),MAX(0,0*W121-(AA132-MIN(MAX(AA132,0),MAX(0,W121-IF($A133>='1-Input'!$C$12,'1-Input'!$B$12,0)))))*(1/(1-'P-Parametri'!$B$6*W133)))) -> 18836.611 | Y133: =IF($A133>'1-Input'!$B$26,AA132,(AA132-MAX(0,W121-IF($A133>='1-Input'!$C$12,'1-Input'!$B$12,0))+X133*(1-'P-Parametri'!$B$6*W133))*(1+'1-Input'!$B$27)) -> 0 | Z133: =IF($A133>'1-Input'!$B$26,AB132,(AB132-X133)*(1+$B$4)) -> 320516.01 | AA133: =IF($A133>'1-Input'!$B$26,Y133,Y133-'P-Parametri'!$B$8*(Z133+Y133)+MIN(MAX(Z133,0),'P-Parametri'!$B$8*(Z133+Y133))) -> 0 | AB133: =IF($A133>'1-Input'!$B$26,Z133,Z133-MIN(MAX(Z133,0),'P-Parametri'!$B$8*(Z133+Y133))) -> 319874.98 | AC133: =IF($A133>'1-Input'!$B$26,AC132,AC132-X133*(1-W133)) -> 209793.32 | AD133: =IF($A133>'1-Input'!$B$26,0,IF(AI132<=0,0,MAX(0,(AI132-AJ132)/AI132))) -> 0.33236038 | AE133: =IF($A133>'1-Input'!$B$26,0,(MAX(0,AD121-IF($A133>='1-Input'!$C$12,'1-Input'!$B$12,0))-MIN(MAX(AH132,0),MAX(0,AD121-IF($A133>='1-Input'!$C$12,'1-Input'!$B$12,0))))*(1/(1-'P-Parametri'!$B$6*AD133))+MIN(MAX(0,AI132-(MAX(0,AD121-IF($A133>='1-Input'!$C$12,'1-Input'!$B$12,0))-MIN(MAX(AH132,0),MAX(0,AD121-IF($A133>='1-Input'!$C$12,'1-Input'!$B$12,0))))*(1/(1-'P-Parametri'!$B$6*AD133))),MAX(0,0*AD121-(AH132-MIN(MAX(AH132,0),MAX(0,AD121-IF($A133>='1-Input'!$C$12,'1-Input'!$B$12,0)))))*(1/(1-'P-Parametri'!$B$6*AD133)))) -> 18851.185 | AF133: =IF($A133>'1-Input'!$B$26,AH132,(AH132-MAX(0,AD121-IF($A133>='1-Input'!$C$12,'1-Input'!$B$12,0))+AE133*(1-'P-Parametri'!$B$6*AD133))*(1+'1-Input'!$B$27)) -> 0 | AG133: =IF($A133>'1-Input'!$B$26,AI132,(AI132-AE133)*(1+$B$4)) -> 320357.37 | AH133: =IF($A133>'1-Input'!$B$26,AF133,AF133-'P-Parametri'!$B$8*(AG133+AF133)+MIN(MAX(AG133,0),'P-Parametri'!$B$8*(AG133+AF133))) -> 0 | AI133: =IF($A133>'1-Input'!$B$26,AG133,AG133-MIN(MAX(AG133,0),'P-Parametri'!$B$8*(AG133+AF133))) -> 319716.65 | AJ133: =IF($A133>'1-Input'!$B$26,AJ132,AJ132-AE133*(1-AD133)) -> 209689.48 | AK133: =IF($A133>'1-Input'!$B$26,0,IF(AP132<=0,0,MAX(0,(AP132-AQ132)/AP132))) -> 0.33236038 | AL133: =IF($A133>'1-Input'!$B$26,0,(MAX(0,AK121-IF($A133>='1-Input'!$C$12,'1-Input'!$B$12,0))-MIN(MAX(AO132,0),MAX(0,AK121-IF($A133>='1-Input'!$C$12,'1-Input'!$B$12,0))))*(1/(1-'P-Parametri'!$B$6*AK133))+MIN(MAX(0,AP132-(MAX(0,AK121-IF($A133>='1-Input'!$C$12,'1-Input'!$B$12,0))-MIN(MAX(AO132,0),MAX(0,AK121-IF($A133>='1-Input'!$C$12,'1-Input'!$B$12,0))))*(1/(1-'P-Parametri'!$B$6*AK133))),MAX(0,0*AK121-(AO132-MIN(MAX(AO132,0),MAX(0,AK121-IF($A133>='1-Input'!$C$12,'1-Input'!$B$12,0)))))*(1/(1-'P-Parametri'!$B$6*AK133)))) -> 18851.185 | AM133: =IF($A133>'1-Input'!$B$26,AO132,(AO132-MAX(0,AK121-IF($A133>='1-Input'!$C$12,'1-Input'!$B$12,0))+AL133*(1-'P-Parametri'!$B$6*AK133))*(1+'1-Input'!$B$27)) -> 0 | AN133: =IF($A133>'1-Input'!$B$26,AP132,(AP132-AL133)*(1+$B$4)) -> 320357.37 | AO133: =IF($A133>'1-Input'!$B$26,AM133,AM133-'P-Parametri'!$B$8*(AN133+AM133)+MIN(MAX(AN133,0),'P-Parametri'!$B$8*(AN133+AM133))) -> 0 | AP133: =IF($A133>'1-Input'!$B$26,AN133,AN133-MIN(MAX(AN133,0),'P-Parametri'!$B$8*(AN133+AM133))) -> 319716.65 | AQ133: =IF($A133>'1-Input'!$B$26,AQ132,AQ132-AL133*(1-AK133)) -> 209689.48
