Workbook

Sheet 0 - Indice
A1: Quanto ti costa l'auto in libertà — il simulatore (ottobre 2026)
A2: Strumento informativo / divulgativo. NON è consulenza finanziaria. I valori sono indicativi al 2026 e vanno verificati col tuo consulente.
A4: Indice
A5: 1 - Il tuo profilo | B5: Chi sei: età, km, stipendio, spese, capitale, prezzi dell'energia; spesa totale, tasso di risparmio, capitale netto
A6: 2 - Le opzioni | B6: Le opzioni: rate, maxirata, contanti, usata, noleggio, tenere l'auto di oggi, senza auto; €/mese per sempre
A7: 3 - Il costo opportunità | B7: Il costo opportunità: la differenza di spesa diventa capitale ed entrata al mese, al netto di bollo e imposte
A8: 4 - Abitudine o contratto | B8: Abitudine o contratto: cambiarla spesso, il credito, l'eccedenza; il contratto «da 199 €»; la soglia dell'officina
A9: 5 - Senza auto | B9: Senza auto: abbonamento, noleggi e taxi in tre profili; quante giornate di noleggio paga il margine
A10: 6 - Elettrico o termico | B10: Elettrico o termico: differenza di valore attuale e km all'anno di pareggio
A12: Come usare
A13: 1. Le celle GIALLE sono input — modificale coi tuoi numeri.
A14: 2. Le celle VERDI sono output — si aggiornano automaticamente.
A15: 3. Tutti i numeri di default sono al 2026 da fonti pubbliche.
A16: 4. Niente codice nascosto: l'Excel è solo formule modificabili.
A18: Fonti dati
A19: • F-01 — Agenzia delle Entrate, tabelle nazionali dei costi chilometrici 2026 (GU n. 297 del 23/12/2025, S.O. n. 40) — https://www.gazzettaufficiale.it/eli/gu/2025/12/23/297/so/40/sg/pdf — accesso 08/10/2026
A20: • F-03 — MASE-DGSAIE, prezzi medi settimanali dei carburanti (benzina, media 2026 al 05/10/2026) — https://sisen.mase.gov.it/dgsaie/api/v1/weekly-prices/report/export?format=CSV&lang=it — accesso 08/10/2026
A21: • F-04 — IVASS, IPER II trimestre 2026, comunicazione statistica n. 7/2026 del 24/09/2026 (RC auto, donne 35-44 anni) — https://www.ivass.it/pubblicazioni-e-statistiche/statistiche/comunicazioni-statistiche/2026/cs-n-7-2026/ — accesso 08/10/2026
A22: • F-05 — MEF, decreto tassi effettivi globali medi ottobre-dicembre 2026 (soglie di usura) — https://www.dt.mef.gov.it/export/sites/sitodt/modules/documenti_it/prevenzione_reati_finanziari/antiusura/decreto-tassi-usura-ottobre-dicembre-2026.pdf — accesso 08/10/2026
A23: • F-06 — BCE, statistiche sui tassi bancari, Italia, credito al consumo, nuove operazioni (agosto 2026: tasso 9,12%) — https://data.ecb.europa.eu (serie M.IT.B.A2B.A.R.A.2250.EUR.N) — accesso 08/10/2026
A24: • F-08 — Eurostat nrg_pc_204, elettricità per le famiglie, Italia, 2.500-4.999 kWh, tutte le imposte, 2025-S2 — https://ec.europa.eu/eurostat/databrowser/view/nrg_pc_204/default/table — accesso 08/10/2026
... A46: Sono ipotesi, non consulenza: i prezzi delle auto, i residui e i canoni sono stime. Cambiali con i preventivi veri.

Sheet 1 - Il tuo profilo
A1: Il tuo profilo: chi sei, quanto guadagni, quanto spendi
A2: Strumento informativo / divulgativo. NON è consulenza finanziaria. I valori sono indicativi al 2026 e vanno verificati col tuo consulente.
A3: Valori di partenza: Valentina, 36 anni, single, dipendente, in affitto in un comune medio del Nord Est. Valentina non esiste: è un caso costruito con dati veri. Sostituisci i gialli con i tuoi numeri.
A5: Chi sei e quanto guidi
A6: Età oggi | B6: 36
A7: Età a cui misuri il capitale | B7: 66 | C7: Fra 30 anni, prima dell'età di pensione: il capitale si aggiunge alla pensione, non la sostituisce
A8: Anni di confronto | B8: ='1 - Il tuo profilo'!$B$7-'1 - Il tuo profilo'!$B$6 -> 30
A9: Km all'anno | B9: 12000 | C9: Valentina: 12.000 km, casa-lavoro 18 km a tratta
A10: Orizzonte del confronto fra le opzioni | B10: 10 anni | C10: Fisso: è la struttura del motore (flussi anno per anno, opzioni a ciclo ripetute fino a 10 anni)
A12: Mercati e regole del canale
A13: Rendimento reale del capitale (60/40) | B13: 0.03 | C13: Canone del canale: 3% oltre l'inflazione. È anche il tasso di sconto dei flussi
A14: Inflazione | B14: 0.02 | C14: Serve solo a deflazionare rate e canoni fissi in euro nominali
A15: Prelievo annuo dal capitale | B15: 0.03 | C15: Valori del canale: 4% (25 volte la spesa), 3% (33,3 volte, principale), 2,31% (43,3 volte)
A17: Entrate e spese (euro all'anno)
A18: Stipendio netto annuo | B18: 27326.6 | C18: Valentina: RAL 38.000 → netto 27.326,60 (controllo in fondo al foglio)
A19: Affitto annuo | B19: 6000 | C19: 500 €/mese: canone medio dei nuovi contratti nei comuni non ad alta tensione abitativa del Nord Est (F-13: 504 €/mese)
A20: Utenze, condominio e piccola manutenzione di casa | B20: 1800 | C20: 150 €/mese (ipotesi). Tetto ISTAT: non più di 339,17 €/mese = 4.070 €/anno (F-12, calcolo in fondo al foglio)
A21: Tutte le altre spese (cibo, vestiti, salute, svago…) | B21: 11948.87 | C21: ISTAT 2025, persona sola 35-64 anni, mediana riscalata, senza casa e trasporti (F-12, calcolo in fondo al foglio)
A22: Capitale già investito oggi | B22: 60000
A24: Energia e costi fissi dell'auto
A25: Benzina, €/litro | B25: 1.84995 | C25: Media 2026 al 05/10/2026 (F-03). Banda dell'anno 1,626-2,156
A26: Elettricità a casa, €/kWh | B26: 0.2966 | C26: Famiglie 2.500-4.999 kWh, tutte le imposte, 2025-S2 (F-08)
A27: Ricarica alla colonnina, €/kWh | B27: 0.6 | C27: Ipotesi: nessuna fonte primaria, banda 0,45-0,80
A28: Quota di ricarica alla colonnina (elettrica, caso base) | B28: 0.1 | C28: 90% a casa, 10% alla colonnina
A29: Assicurazione obbligatoria (RC), €/anno | B29: 409.2 | C29: Premio medio donne 35-44 anni, II trimestre 2026 (F-04)
A30: Bollo, € per kW | B30: 2.58 | C30: Euro 4 e oltre, fino a 100 kW (F-14)
A31: Revisione, € (4° anno, poi ogni 2) | B31: 79.02 | C31: Tariffa dei centri privati (ipotesi; in Motorizzazione 45 €, F-18)
A32: Furto-incendio dell'auto nuova, €/anno | B32: 250 | C32: Ipotesi, solo nei primi anni dell'auto nuova (anni nel foglio 2)
A33: Valore dell'auto di oggi, se la vendi | B33: 3000 | C33: Benzina di 13 anni: «qualche migliaio di euro»
A35: Risultati
A36: L'auto di oggi, primo anno (€/anno) | B36: ='2 - Le opzioni'!$L$364 -> 3462.761 | C36: Benzina, assicurazione, bollo, revisione e manutenzione del prossimo anno (foglio 2, opzione F10)
A37: L'auto di oggi, al mese | B37: ='1 - Il tuo profilo'!$B$36/12 -> 288.56342
A38: Spesa totale annua | B38: ='1 - Il tuo profilo'!$B$19+'1 - Il tuo profilo'!$B$20+'1 - Il tuo profilo'!$B$21+'1 - Il tuo profilo'!$B$36 -> 23211.631
A39: Risparmio annuo | B39: ='1 - Il tuo profilo'!$B$18-'1 - Il tuo profilo'!$B$38 -> 4114.969
A40: Tasso di risparmio | B40: ='1 - Il tuo profilo'!$B$39/'1 - Il tuo profilo'!$B$18 -> 0.15058474
A41: Anni di risparmio che spiegano il capitale di oggi | B41: =IF('1 - Il tuo profilo'!$B$39<=0,"risparmio nullo",NPER('1 - Il tuo profilo'!$B$13,-'1 - Il tuo profilo'!$B$39,0,'1 - Il tuo profilo'!$B$22)) -> 12.275699 | C41: Quanti anni di questo risparmio, investito al rendimento reale, servono per arrivare al capitale di oggi
A42: Capitale netto all'età scelta | B42: =(((('1 - Il tuo profilo'!$B$22)*INDEX('3 - Il costo opportunità'!$B$74:$B$134,('1 - Il tuo profilo'!$B$8)+1)+('1 - Il tuo profilo'!$B$39)*INDEX('3 - Il costo opportunità'!$C$74:$C$134,('1 - Il tuo profilo'!$B$8)+1))-'3 - Il costo opportunità'!$B$8*MAX(0,(('1 - Il tuo profilo'!$B$22)*INDEX('3 - Il costo opportunità'!$B$74:$B$134,('1 - Il tuo profilo'!$B$8)+1)+('1 - Il tuo profilo'!$B$39)*INDEX('3 - Il costo opportunità'!$C$74:$C$134,('1 - Il tuo profilo'!$B$8)+1))-(('1 - Il tuo profilo'!$B$22)+('1 - Il tuo profilo'!$B$39)*INDEX('3 - Il costo opportunità'!$D$74:$D$134,('1 - Il tuo profilo'!$B$8)+1))))/(1+'1 - Il tuo profilo'!$B$14)^('1 - Il tuo profilo'!$B$8)) -> 287016.89 | C42: Capitale di oggi + risparmio di oggi, al netto di bollo e imposta (foglio 3) | H42: =FV('1 - Il tuo profilo'!$B$13,'1 - Il tuo profilo'!$B$8,-('1 - Il tuo profilo'!$B$39),-('1 - Il tuo profilo'!$B$22)) -> 341407.11
A43: Entrata netta al mese, al prelievo scelto | B43: ='1 - Il tuo profilo'!$B$42*'1 - Il tuo profilo'!$B$15/12 -> 717.54222
A48: Controllo: il netto dalla RAL (dipendente, 2026)
A49: Retribuzione annua lorda (RAL) | B49: 38000
A50: Contributi a carico del dipendente | B50: 0.0919
A51: Addizionali regionale e comunale | B51: 0.02 | C51: Ipotesi media
A52: Contributi | B52: ='1 - Il tuo profilo'!$B$49*'1 - Il tuo profilo'!$B$50 -> 3492.2
A53: Reddito imponibile | B53: ='1 - Il tuo profilo'!$B$49-'1 - Il tuo profilo'!$B$52 -> 34507.8
A54: IRPEF lorda (23% / 33% / 43%) | B54: =0.23*MIN('1 - Il tuo profilo'!$B$53,28000)+0.33*MAX(0,MIN('1 - Il tuo profilo'!$B$53,50000)-28000)+0.43*MAX(0,'1 - Il tuo profilo'!$B$53-50000) -> 8587.574 | C54: TUIR art. 11, vigente nel 2026 (F-22)
A55: Detrazione per lavoro dipendente | B55: =IF('1 - Il tuo profilo'!$B$53<=15000,1955,IF('1 - Il tuo profilo'!$B$53<=28000,1910+1190*(28000-'1 - Il tuo profilo'!$B$53)/13000,IF('1 - Il tuo profilo'!$B$53<=50000,1910*(50000-'1 - Il tuo profilo'!$B$53)/22000,0)))+IF(AND('1 - Il tuo profilo'!$B$53>25000,'1 - Il tuo profilo'!$B$53<=35000),65,0) -> 1410.0046 | C55: TUIR art. 13, compresi i 65 € del c. 1.1 fra 25.000 e 35.000 (F-22)
A56: Ulteriore detrazione | B56: =IF('1 - Il tuo profilo'!$B$53<=20000,0,IF('1 - Il tuo profilo'!$B$53<=32000,1000,IF('1 - Il tuo profilo'!$B$53<=40000,1000*(40000-'1 - Il tuo profilo'!$B$53)/8000,0))) -> 686.525
A57: IRPEF netta | B57: =MAX(0,'1 - Il tuo profilo'!$B$54-'1 - Il tuo profilo'!$B$55-'1 - Il tuo profilo'!$B$56) -> 6491.0444
A58: Addizionali | B58: ='1 - Il tuo profilo'!$B$51*'1 - Il tuo profilo'!$B$53 -> 690.156
A59: Netto stimato dalla RAL | B59: ='1 - Il tuo profilo'!$B$49-'1 - Il tuo profilo'!$B$52-'1 - Il tuo profilo'!$B$57-'1 - Il tuo profilo'!$B$58 -> 27326.6 | C59: Se cambi la RAL, copia questo valore nella cella gialla dello stipendio netto
A61: Controllo: le altre spese e il tetto delle utenze (ISTAT 2025, F-12, prospetto 5)
A62: Persona sola 35-64 anni: spesa media mensile | B62: 2223.39
A63: Spesa mediana mensile | B63: 1996.39
A64: Divisione abitazione (media mensile) | B64: 864.56
A65: di cui affitti figurativi | B65: 507.44
A66: di cui ristrutturazioni | B66: 17.95
A67: Divisione trasporti (media mensile) | B67: 249.87
A68: Tutto il resto, media mensile (senza casa e trasporti) | B68: ='1 - Il tuo profilo'!$B$62-'1 - Il tuo profilo'!$B$64-'1 - Il tuo profilo'!$B$67 -> 1108.96
A69: Tutto il resto riscalato alla mediana, €/anno | B69: ='1 - Il tuo profilo'!$B$68*'1 - Il tuo profilo'!$B$63/'1 - Il tuo profilo'!$B$62*12 -> 11948.871 | C69: È il valore di partenza delle «altre spese»
A70: Tetto delle utenze, €/mese | B70: ='1 - Il tuo profilo'!$B$64-'1 - Il tuo profilo'!$B$65-'1 - Il tuo profilo'!$B$66 -> 339.17 | C70: Abitazione meno affitti figurativi e ristrutturazioni: contiene anche gli affitti veri, quindi è un tetto, non una stima
A71: Le tue utenze rispetto al tetto | B71: =IF('1 - Il tuo profilo'!$B$20<='1 - Il tuo profilo'!$B$70*12,"sotto il tetto ISTAT","sopra il tetto ISTAT: controlla") -> sotto il tetto ISTAT
A72: La divisione assicurativa ISTAT (55,34 €/mese) contiene anche la RC auto, che qui è già nei costi dell'auto: la spesa è sovrastimata al massimo di 34 €/mese.

Sheet 2 - Le opzioni
A1: Le opzioni: quanto costa davvero ogni modo di avere (o non avere) l'auto
A2: Strumento informativo / divulgativo. NON è consulenza finanziaria. I valori sono indicativi al 2026 e vanno verificati col tuo consulente.
A3: Euro di oggi (2026), valore residuo sottratto, flussi scontati al rendimento reale del foglio 1. €/mese = rata annua equivalente / 12: è quanto l'auto ti costa ogni mese, per sempre.
A5: L'auto nuova a benzina (opzioni A, B, C)
A6: Prezzo di strada, IVA inclusa | B6: 19000 | C6: Ipotesi: segmento B. Prezzo medio 2025 delle berline B immatricolate: 20.657 € (F-20)
A7: Potenza, kW | B7: 70
A8: Consumo reale, litri per 100 km | B8: 5.6
A10: L'usata (opzione D): la stessa auto, qualche anno dopo
A11: Età dell'usata quando la compri | B11: 4
A12: Ricarico del rivenditore sul valore di mercato | B12: 0.2 | C12: Ipotesi, banda 0-30%
A13: Prezzo dell'usata (calcolato) | B13: ='2 - Le opzioni'!$B$6*IF('2 - Le opzioni'!$B$11>=MAX('2 - Le opzioni'!$B$67:$K$67),0,INDEX('2 - Le opzioni'!$B$68:$K$68,MATCH('2 - Le opzioni'!$B$11,'2 - Le opzioni'!$B$67:$K$67,1))+(INDEX('2 - Le opzioni'!$B$68:$K$68,MATCH('2 - Le opzioni'!$B$11,'2 - Le opzioni'!$B$67:$K$67,1)+1)-INDEX('2 - Le opzioni'!$B$68:$K$68,MATCH('2 - Le opzioni'!$B$11,'2 - Le opzioni'!$B$67:$K$67,1)))*('2 - Le opzioni'!$B$11-INDEX('2 - Le opzioni'!$B$67:$K$67,MATCH('2 - Le opzioni'!$B$11,'2 - Le opzioni'!$B$67:$K$67,1)))/(INDEX('2 - Le opzioni'!$B$67:$K$67,MATCH('2 - Le opzioni'!$B$11,'2 - Le opzioni'!$B$67:$K$67,1)+1)-INDEX('2 - Le opzioni'!$B$67:$K$67,MATCH('2 - Le opzioni'!$B$11,'2 - Le opzioni'!$B$67:$K$67,1))))*(1+'2 - Le opzioni'!$B$12) -> 12540
A14: Stessa potenza e stesso consumo della nuova. Prezzo = prezzo della nuova × valore residuo all'età scelta × (1 + ricarico).
A16: L'auto di oggi (opzione F)
A17: Età dell'auto di oggi | B17: 13
A18: Potenza, kW | B18: 51
A19: Consumo reale, litri per 100 km | B19: 6.5
A20: Valore di rivendita (ipotesi): quello del foglio 1 oggi, poi giù in linea retta fino a 500 € a 18 anni e a zero a 23.
A22: Ibrida ed elettrica
A23: Ibrida: prezzo di strada | B23: 23000
A24: Ibrida: potenza, kW | B24: 70
A25: Ibrida: consumo, litri per 100 km | B25: 4.6
A26: Ibrida nuova: quota di bollo nei primi anni | B26: 0.5 | C26: Esempio regionale: metà bollo (F-14). Le regole cambiano da Regione a Regione
A27: Ibrida nuova: anni di bollo ridotto | B27: 5
A28: Elettrica: prezzo di strada | B28: 26000
A29: Elettrica: potenza, kW | B29: 85
A30: Elettrica: consumo alla presa, kWh per 100 km | B30: 17
A31: Elettrica: anni senza bollo | B31: 5 | C31: Regola nazionale (ipotesi); alcune Regioni esentano più a lungo
A32: Elettrica: quota di bollo dopo | B32: 0.25
A33: Elettrica «colonnina»: quota di ricarica pubblica | B33: 0.8 | C33: Scenario dell'opzione C-el-pub: 20% a casa, 80% alla colonnina
A35: Credito: rate e maxirata
A36: Tasso del finanziamento (TAN) | B36: 0.0912 | C36: Credito al consumo, nuove operazioni, agosto 2026 (F-06)
A37: Spese di istruttoria | B37: 300 | C37: Ipotesi
A38: Finanziamento classico: mesi | B38: 60
A39: Maxirata: mesi | B39: 36 | C39: Scegli 36, 48 o 60: la maxirata rinnovata si ripete a ogni scadenza
A40: Maxirata: rata finale, % del prezzo | B40: 0.55 | C40: Ipotesi, uguale al contratto-tipo «da 199 €» del foglio 4
A41: Maxirata: rata finale in euro | B41: ='2 - Le opzioni'!$B$40*'2 - Le opzioni'!$B$6 -> 10450
A42: Maxirata: anni del ciclo | B42: ='2 - Le opzioni'!$B$39/12 -> 3
A43: Rifinanziamento della rata finale: mesi | B43: 48 | C43: Opzione B2, allo stesso tasso
A44: Riparazioni addebitate alla riconsegna | B44: 400 | C44: Ipotesi, maxirata con restituzione e noleggio
A46: Noleggio a lungo termine (opzione E)
A47: Canone mensile, benzina (IVA inclusa) | B47: 300 | C47: Ipotesi: nessuna fonte pubblica dei canoni (F-21 dà solo le quote di mercato)
A48: Canone mensile, elettrica | B48: 340
A49: Durata, mesi | B49: 48
A50: Noleggio: anni del ciclo | B50: ='2 - Le opzioni'!$B$49/12 -> 4
A51: Km inclusi all'anno | B51: 15000
A52: € per km oltre i km inclusi | B52: 0.1
A53: Il canone comprende assicurazione, furto-incendio, bollo, manutenzione e gomme; l'energia resta a carico. Anticipo = valore dell'auto di oggi.
A55: Manutenzione, gomme e guasti, €/anno a 12.000 km (ipotesi)
A56: Auto di 1-3 anni | B56: 350
A57: Auto di 4-7 anni | B57: 600
A58: Auto di 8-12 anni | B58: 900
A59: Auto di 13 anni | B59: 1300
A60: In più per ogni anno oltre i 13 | B60: 100
A61: Ibrida: frazione della benzina | B61: 0.9
A62: Elettrica: frazione della benzina | B62: 0.7
A63: Km di riferimento della manutenzione | B63: 12000 | C63: Metà della manutenzione cresce con i km, metà no
A64: Anni di furto-incendio dell'auto nuova | B64: 5
A66: Curva dei valori residui (frazione del prezzo a nuovo, ipotesi; in mezzo si interpola)
A67: Età (anni) | B67: 0 | C67: 1 | D67: 3 | E67: 4 | F67: 5 | G67: 8 | H67: 10 | I67: 14 | J67: 18 | K67: 23
A68: Benzina e ibrida | B68: 1 | C68: 0.8 | D68: 0.62 | E68: 0.55 | F68: 0.49 | G68: 0.33 | H68: 0.24 | I68: 0.12 | J68: 0.05 | K68: 0
A69: Elettrica | B69: 1 | C69: 0.72 | D69: 0.52 | E69: 0.45 | F69: 0.39 | G69: 0.25 | H69: 0.17 | I69: 0.08 | J69: 0.03 | K69: 0
A70: Valori di mercato stimati (nessuna fonte pubblica primaria): −20% il primo anno, −38% in 3, −45% in 4. Le età devono restare in ordine crescente; oltre l'ultima il valore è zero.
A72: Affitti di confronto
A73: Affitto di Valentina, €/mese (dal foglio 1) | B73: ='1 - Il tuo profilo'!$B$19/12 -> 500
A74: Affitto medio dei comuni ad alta tensione abitativa del Nord Est, €/mese | B74: 703.34537 | C74: Nuovi contratti 2025: 306,2 milioni / 36.279 abitazioni / 12 (F-13)
A76: Rate e TAEG (spese di istruttoria comprese)
A77: Finanziamento classico: rata mensile | B77: ='2 - Le opzioni'!$B$222 -> 333.0663
A78: Finanziamento classico: TAEG | B78: =(1+RATE('2 - Le opzioni'!$B$38,-'2 - Le opzioni'!$B$77,'2 - Le opzioni'!$B$6-'1 - Il tuo profilo'!$B$33-'2 - Le opzioni'!$B$37,0))^12-1 -> 0.10398639
A79: Maxirata: rata mensile | B79: ='2 - Le opzioni'!$B$260 -> 256.21864
A80: Maxirata: TAEG | B80: =(1+RATE('2 - Le opzioni'!$B$39,-'2 - Le opzioni'!$B$79,'2 - Le opzioni'!$B$6-'1 - Il tuo profilo'!$B$33-'2 - Le opzioni'!$B$37,-'2 - Le opzioni'!$B$41))^12-1 -> 0.10445087
A81: Maxirata rinnovata: eccedenza riconosciuta alla riconsegna? | B81: no | C81: «no» = il valore di mercato sopra la rata finale resta a chi riprende l'auto (caso alto); «sì» = torna come permuta (caso basso)
A83: Cod | B83: Opzione | C83: Rata mensile | D83: Totale 10 anni (somma semplice) | E83: Valore attuale 10 anni | F83: €/mese equivalenti | G83: €/km | H83: Ciclo (anni)
A84: A | B84: Nuova benzina, finanziamento classico | C84: ='2 - Le opzioni'!$B$222 -> 333.0663 | D84: ='2 - Le opzioni'!$J$224 -> 40796.549 | E84: ='2 - Le opzioni'!$I$224 -> 36718.387 | F84: ='2 - Le opzioni'!$L$224 -> 358.70959 | G84: ='2 - Le opzioni'!$M$224 -> 0.35870959 | H84: ='2 - Le opzioni'!$C$224 -> 10
A85: B1 | B85: Maxirata, poi riscatto pagando la rata finale | C85: ='2 - Le opzioni'!$B$260 -> 256.21864 | D85: ='2 - Le opzioni'!$J$262 -> 40580.857 | E85: ='2 - Le opzioni'!$I$262 -> 36613.382 | F85: ='2 - Le opzioni'!$L$262 -> 357.68378 | G85: ='2 - Le opzioni'!$M$262 -> 0.35768378 | H85: ='2 - Le opzioni'!$C$262 -> 10
A86: B2 | B86: Maxirata, poi rata finale rifinanziata | C86: ='2 - Le opzioni'!$B$279 -> 256.21864 | D86: ='2 - Le opzioni'!$J$281 -> 42358.744 | E86: ='2 - Le opzioni'!$I$281 -> 37646.73 | F86: ='2 - Le opzioni'!$L$281 -> 367.77877 | G86: ='2 - Le opzioni'!$M$281 -> 0.36777877 | H86: ='2 - Le opzioni'!$C$281 -> 10
A87: B3 | B87: Maxirata rinnovata ogni scadenza (eccedenza secondo la scelta qui sopra) | C87: ='2 - Le opzioni'!$B$298 -> 256.21864 | D87: =IF('2 - Le opzioni'!$B$81="sì",'2 - Le opzioni'!$J$319,'2 - Le opzioni'!$J$300) -> 63489.147 | E87: =IF('2 - Le opzioni'!$B$81="sì",'2 - Le opzioni'!$I$319,'2 - Le opzioni'!$I$300) -> 54610.959 | F87: =IF('2 - Le opzioni'!$B$81="sì",'2 - Le opzioni'!$L$319,'2 - Le opzioni'!$L$300) -> 533.50587 | G87: =IF('2 - Le opzioni'!$B$81="sì",'2 - Le opzioni'!$M$319,'2 - Le opzioni'!$M$300) -> 0.53350587 | H87: =IF('2 - Le opzioni'!$B$81="sì",'2 - Le opzioni'!$C$319,'2 - Le opzioni'!$C$300) -> 3
A88: C | B88: Nuova benzina in contanti | C88: — | D88: ='2 - Le opzioni'!$J$129 -> 37485.744 | E88: ='2 - Le opzioni'!$I$129 -> 34745.942 | F88: ='2 - Le opzioni'!$L$129 -> 339.44037 | G88: ='2 - Le opzioni'!$M$129 -> 0.33944037 | H88: ='2 - Le opzioni'!$C$129 -> 10
A89: D | B89: Usata in contanti (la stessa auto, qualche anno dopo) | C89: — | D89: ='2 - Le opzioni'!$J$148 -> 34984.764 | E89: ='2 - Le opzioni'!$I$148 -> 31318.301 | F89: ='2 - Le opzioni'!$L$148 -> 305.95503 | G89: ='2 - Le opzioni'!$M$148 -> 0.30595503 | H89: ='2 - Le opzioni'!$C$148 -> 10
A90: E | B90: Noleggio a lungo termine, benzina | C90: ='2 - Le opzioni'!$H$336 -> 300 | D90: ='2 - Le opzioni'!$J$338 -> 52571.353 | E90: ='2 - Le opzioni'!$I$338 -> 45354.376 | F90: ='2 - Le opzioni'!$L$338 -> 443.07638 | G90: ='2 - Le opzioni'!$M$338 -> 0.44307638 | H90: ='2 - Le opzioni'!$C$338 -> 4
A91: F5 | B91: Tenere l'auto di oggi 5 anni, poi l'usata | C91: — | D91: ='2 - Le opzioni'!$J$395 -> 37703.637 | E91: ='2 - Le opzioni'!$I$395 -> 33148.547 | F91: ='2 - Le opzioni'!$L$395 -> 323.83508 | G91: ='2 - Le opzioni'!$M$395 -> 0.32383508 | H91: ='2 - Le opzioni'!$C$395 -> 10
A92: F10 | B92: Tenere l'auto di oggi 10 anni | C92: — | D92: ='2 - Le opzioni'!$J$376 -> 38732.51 | E92: ='2 - Le opzioni'!$I$376 -> 32836.885 | F92: ='2 - Le opzioni'!$L$376 -> 320.79039 | G92: ='2 - Le opzioni'!$M$376 -> 0.32079039 | H92: ='2 - Le opzioni'!$C$376 -> 10
A93: G | B93: Senza auto, città media | C93: — | D93: ='2 - Le opzioni'!$J$414 -> 21060 | E93: ='2 - Le opzioni'!$I$414 -> 17523.668 | F93: ='2 - Le opzioni'!$L$414 -> 171.19237 | G93: ='2 - Le opzioni'!$M$414 -> 0.17119237 | H93: ='2 - Le opzioni'!$C$414 -> 10
A94: C-ibr | B94: Nuova ibrida in contanti | C94: — | D94: ='2 - Le opzioni'!$J$167 -> 37239.304 | E94: ='2 - Le opzioni'!$I$167 -> 35214.316 | F94: ='2 - Le opzioni'!$L$167 -> 344.01601 | G94: ='2 - Le opzioni'!$M$167 -> 0.34401601 | H94: ='2 - Le opzioni'!$C$167 -> 10
A95: C-el | B95: Nuova elettrica in contanti, ricarica a casa | C95: — | D95: ='2 - Le opzioni'!$J$186 -> 35486.781 | E95: ='2 - Le opzioni'!$I$186 -> 34080.685 | F95: ='2 - Le opzioni'!$L$186 -> 332.94133 | G95: ='2 - Le opzioni'!$M$186 -> 0.33294133 | H95: ='2 - Le opzioni'!$C$186 -> 10
A96: C-el-pub | B96: Nuova elettrica in contanti, ricarica soprattutto alla colonnina | C96: — | D96: ='2 - Le opzioni'!$J$205 -> 39819.333 | E96: ='2 - Le opzioni'!$I$205 -> 37776.44 | F96: ='2 - Le opzioni'!$L$205 -> 369.04593 | G96: ='2 - Le opzioni'!$M$205 -> 0.36904593 | H96: ='2 - Le opzioni'!$C$205 -> 10
A97: A-el | B97: Nuova elettrica a rate, ricarica a casa | C97: ='2 - Le opzioni'!$B$241 -> 478.7828 | D97: ='2 - Le opzioni'!$J$243 -> 40114.813 | E97: ='2 - Le opzioni'!$I$243 -> 36784.824 | F97: ='2 - Le opzioni'!$L$243 -> 359.35863 | G97: ='2 - Le opzioni'!$M$243 -> 0.35935863 | H97: ='2 - Le opzioni'!$C$243 -> 10
A98: E-el | B98: Noleggio a lungo termine, elettrica | C98: ='2 - Le opzioni'!$H$355 -> 340 | D98: ='2 - Le opzioni'!$J$357 -> 51427.89 | E98: ='2 - Le opzioni'!$I$357 -> 44445.834 | F98: ='2 - Le opzioni'!$L$357 -> 434.20064 | G98: ='2 - Le opzioni'!$M$357 -> 0.43420064 | H98: ='2 - Le opzioni'!$C$357 -> 4
A99: G-gc | B99: Senza auto, grande città | C99: — | D99: ='2 - Le opzioni'!$J$433 -> 14330 | E99: ='2 - Le opzioni'!$I$433 -> 11782.842 | F99: ='2 - Le opzioni'!$L$433 -> 115.10904 | G99: ='2 - Le opzioni'!$M$433 -> 0.11510904 | H99: ='2 - Le opzioni'!$C$433 -> 10
A100: G-pr | B100: Senza auto, provincia | C100: — | D100: ='2 - Le opzioni'!$J$452 -> 39000 | E100: ='2 - Le opzioni'!$I$452 -> 32826.852 | F100: ='2 - Le opzioni'!$L$452 -> 320.69237 | G100: ='2 - Le opzioni'!$M$452 -> 0.32069237 | H100: ='2 - Le opzioni'!$C$452 -> 10
A101: Codici: A rate, B1-B3 maxirata (riscatto, rifinanziamento, rinnovo), C contanti, D usata, E noleggio, F tenere l'auto di oggi, G senza auto. Il «noleggio» mostra il canone al posto della rata.
A102: Opzioni a ciclo (maxirata rinnovata, noleggio): il costo di un ciclo si ripete per sempre; l'incasso dell'auto di oggi si conta una volta sola.
A108: Motore del calcolo — non modificare
A109: Calcoli intermedi usati dalle celle verdi qui sopra: si possono leggere, non vanno modificati.
A110: Tasso mensile per scontare i flussi deflazionati | B110: =((1+'1 - Il tuo profilo'!$B$14)*(1+'1 - Il tuo profilo'!$B$13))^(1/12)-1 -> 0.0041219243
A111: Tasso mensile di inflazione | B111: =(1+'1 - Il tuo profilo'!$B$14)^(1/12)-1 -> 0.0016515813
A112: Fattore di rendita a 10 anni | B112: =PV('1 - Il tuo profilo'!$B$13,10,-1) -> 8.5302028
A114: C — Nuova benzina in contanti
A115: t (anni) | B115: Età dell'auto | C115: Energia | D115: Assicurazione | E115: Bollo e revisione | F115: Manutenzione | G115: Acquisto e rivendita | H115: Credito | I115: Uso senza proprietà | J115: Riconsegna e km extra | K115: Mobilità alternativa | L115: Totale dell'anno | M115: Fattore di sconto
A116: 0 | G116: =-'1 - Il tuo profilo'!$B$33+'2 - Le opzioni'!$B$6 -> 16000 | L116: =SUM(C116:K116) -> 16000 | M116: =1/(1+'1 - Il tuo profilo'!$B$13)^A116 -> 1
A117: 1 | B117: =1 -> 1 | C117: ='1 - Il tuo profilo'!$B$9/100*'2 - Le opzioni'!$B$8*'1 - Il tuo profilo'!$B$25 -> 1243.1664 | D117: ='1 - Il tuo profilo'!$B$29+IF($B117<='2 - Le opzioni'!$B$64,'1 - Il tuo profilo'!$B$32,0) -> 659.2 | E117: ='2 - Le opzioni'!$B$7*'1 - Il tuo profilo'!$B$30+IF(AND($B117>=4,MOD($B117,2)=0),'1 - Il tuo profilo'!$B$31,0) -> 180.6 | F117: =IF($B117<=3,'2 - Le opzioni'!$B$56,IF($B117<=7,'2 - Le opzioni'!$B$57,IF($B117<=12,'2 - Le opzioni'!$B$58,'2 - Le opzioni'!$B$59+'2 - Le opzioni'!$B$60*($B117-13))))*1*(0.5+0.5*'1 - Il tuo profilo'!$B$9/'2 - Le opzioni'!$B$63) -> 350 | L117: =SUM(C117:K117) -> 2432.9664 | M117: =1/(1+'1 - Il tuo profilo'!$B$13)^A117 -> 0.97087379
...

Sheet 3 - Il costo opportunità
A1: Il costo opportunità: la differenza di spesa, investita, quanto diventa
A2: Strumento informativo / divulgativo. NON è consulenza finanziaria. I valori sono indicativi al 2026 e vanno verificati col tuo consulente.
A3: Capitali ed entrate AL NETTO del bollo titoli e dell'imposta sui guadagni, in euro di oggi. Ogni differenza di spesa si immagina versata ogni mese in un portafoglio 60/40, per gli anni scelti nel foglio 1.
A5: Le tue scelte
A6: Opzione di riferimento (la più economica che useresti davvero) | B6: D | C6: Codici nella tabella qui sotto (D = usata in contanti)
A7: Bollo titoli, % del valore ogni anno | B7: 0.002 | C7: Imposta di bollo sul deposito titoli
A8: Imposta media sui guadagni | B8: 0.206 | C8: Portafoglio 60/40: 60% × 26% (azioni) + 40% × 12,5% (titoli di Stato) = 20,6%
A9: Anni di accumulo (dal foglio 1) | B9: ='1 - Il tuo profilo'!$B$8 -> 30
A10: Prelievo annuo (dal foglio 1) | B10: ='1 - Il tuo profilo'!$B$15 -> 0.03
A12: Traduttore: 1 € al mese in più di spesa, per sempre
A13: Prelievo | B13: 0.04 | C13: capitale in più che serve | D13: =12/'3 - Il costo opportunità'!$B$13 -> 300
A14: Prelievo | B14: 0.03 | C14: capitale in più che serve | D14: =12/'3 - Il costo opportunità'!$B$14 -> 400
A15: Prelievo | B15: 0.0231 | C15: capitale in più che serve | D15: =12/'3 - Il costo opportunità'!$B$15 -> 519.48052
A16: Ogni euro al mese di spesa fissa chiede 300 € di capitale al 4%, 400 € al 3% (canone del canale), 519,48 € al 2,31%.
A18: Prova con una cifra
A19: Spesa in più, € al mese | B19: 100
A20: Capitale netto che avresti alla fine | B20: =SIGN('3 - Il costo opportunità'!$B$19*12)*((((0)*INDEX('3 - Il costo opportunità'!$B$74:$B$134,('3 - Il costo opportunità'!$B$9)+1)+(ABS('3 - Il costo opportunità'!$B$19*12))*INDEX('3 - Il costo opportunità'!$C$74:$C$134,('3 - Il costo opportunità'!$B$9)+1))-'3 - Il costo opportunità'!$B$8*MAX(0,((0)*INDEX('3 - Il costo opportunità'!$B$74:$B$134,('3 - Il costo opportunità'!$B$9)+1)+(ABS('3 - Il costo opportunità'!$B$19*12))*INDEX('3 - Il costo opportunità'!$C$74:$C$134,('3 - Il costo opportunità'!$B$9)+1))-((0)+(ABS('3 - Il costo opportunità'!$B$19*12))*INDEX('3 - Il costo opportunità'!$D$74:$D$134,('3 - Il costo opportunità'!$B$9)+1))))/(1+'1 - Il tuo profilo'!$B$14)^('3 - Il costo opportunità'!$B$9)) -> 49953.94 | N20: =FV('1 - Il tuo profilo'!$B$13,'3 - Il costo opportunità'!$B$9,-('3 - Il costo opportunità'!$B$19*12),-(0)) -> 57090.499
A21: Entrata in più al mese, netta, al prelievo scelto | B21: ='3 - Il costo opportunità'!$B$20*'3 - Il costo opportunità'!$B$10/12 -> 124.88485
A22: Capitale in più che serve per sempre, al prelievo scelto | B22: ='3 - Il costo opportunità'!$B$19*12/'3 - Il costo opportunità'!$B$10 -> 40000
A24: Tutte le opzioni a confronto (12 colonne verdi; i valori lordi di controllo sono nelle colonne nascoste)
A25: Cod | B25: Opzione | C25: €/mese equivalenti | D25: Differenza dal riferimento, €/mese | E25: Capitale netto perso in 10 anni | F25: Capitale netto perso a fine accumulo | G25: Entrata netta persa, €/mese | H25: Spesa annua totale | I25: Risparmio annuo | J25: Tasso di risparmio | K25: Capitale netto a fine accumulo | L25: Entrata netta al mese | N25: Controllo: Δ capitale lordo 10 anni | O25: Controllo: Δ capitale lordo fine accumulo | P25: Controllo: Δ entrata lorda | Q25: Controllo: Capitale lordo fine accumulo | R25: Controllo: Entrata lorda
A26: A | B26: Nuova benzina, finanziamento classico | C26: ='2 - Le opzioni'!$L$224 -> 358.70959 | D26: =C26-INDEX('3 - Il costo opportunità'!$C$26:$C$44,MATCH('3 - Il costo opportunità'!$B$6,'3 - Il costo opportunità'!$A$26:$A$44,0)) -> 52.754561 | E26: =SIGN(D26*12)*((((0)*INDEX('3 - Il costo opportunità'!$B$74:$B$134,(10)+1)+(ABS(D26*12))*INDEX('3 - Il costo opportunità'!$C$74:$C$134,(10)+1))-'3 - Il costo opportunità'!$B$8*MAX(0,((0)*INDEX('3 - Il costo opportunità'!$B$74:$B$134,(10)+1)+(ABS(D26*12))*INDEX('3 - Il costo opportunità'!$C$74:$C$134,(10)+1))-((0)+(ABS(D26*12))*INDEX('3 - Il costo opportunità'!$D$74:$D$134,(10)+1))))/(1+'1 - Il tuo profilo'!$B$14)^(10)) -> 6958.4556 | F26: =SIGN(D26*12)*((((0)*INDEX('3 - Il costo opportunità'!$B$74:$B$134,('3 - Il costo opportunità'!$B$9)+1)+(ABS(D26*12))*INDEX('3 - Il costo opportunità'!$C$74:$C$134,('3 - Il costo opportunità'!$B$9)+1))-'3 - Il costo opportunità'!$B$8*MAX(0,((0)*INDEX('3 - Il costo opportunità'!$B$74:$B$134,('3 - Il costo opportunità'!$B$9)+1)+(ABS(D26*12))*INDEX('3 - Il costo opportunità'!$C$74:$C$134,('3 - Il costo opportunità'!$B$9)+1))-((0)+(ABS(D26*12))*INDEX('3 - Il costo opportunità'!$D$74:$D$134,('3 - Il costo opportunità'!$B$9)+1))))/(1+'1 - Il tuo profilo'!$B$14)^('3 - Il costo opportunità'!$B$9)) -> 26352.982 | G26: =F26*'3 - Il costo opportunità'!$B$10/12 -> 65.882454 | H26: =('1 - Il tuo profilo'!$B$19+'1 - Il tuo profilo'!$B$20+'1 - Il tuo profilo'!$B$21)+C26*12 -> 24053.385 | I26: ='1 - Il tuo profilo'!$B$18-H26 -> 3273.2149 | J26: =I26/'1 - Il tuo profilo'!$B$18 -> 0.11978127 | K26: =(((('1 - Il tuo profilo'!$B$22)*INDEX('3 - Il costo opportunità'!$B$74:$B$134,('3 - Il costo opportunità'!$B$9)+1)+(I26)*INDEX('3 - Il costo opportunità'!$C$74:$C$134,('3 - Il costo opportunità'!$B$9)+1))-'3 - Il costo opportunità'!$B$8*MAX(0,(('1 - Il tuo profilo'!$B$22)*INDEX('3 - Il costo opportunità'!$B$74:$B$134,('3 - Il costo opportunità'!$B$9)+1)+(I26)*INDEX('3 - Il costo opportunità'!$C$74:$C$134,('3 - Il costo opportunità'!$B$9)+1))-(('1 - Il tuo profilo'!$B$22)+(I26)*INDEX('3 - Il costo opportunità'!$D$74:$D$134,('3 - Il costo opportunità'!$B$9)+1))))/(1+'1 - Il tuo profilo'!$B$14)^('3 - Il costo opportunità'!$B$9)) -> 251976.11 | L26: =K26*'3 - Il costo opportunità'!$B$10/12 -> 629.94027 | N26: =FV('1 - Il tuo profilo'!$B$13,10,-D26*12) -> 7257.2631 | O26: =FV('1 - Il tuo profilo'!$B$13,'3 - Il costo opportunità'!$B$9,-D26*12) -> 30117.842 | P26: =O26*'3 - Il costo opportunità'!$B$10/12 -> 75.294605 | Q26: =FV('1 - Il tuo profilo'!$B$13,'3 - Il costo opportunità'!$B$9,-(I26),-('1 - Il tuo profilo'!$B$22)) -> 301360.31 | R26: =Q26*'3 - Il costo opportunità'!$B$10/12 -> 753.40077
A27: B1 | B27: Maxirata, poi riscatto pagando la rata finale | C27: ='2 - Le opzioni'!$L$262 -> 357.68378 | D27: =C27-INDEX('3 - Il costo opportunità'!$C$26:$C$44,MATCH('3 - Il costo opportunità'!$B$6,'3 - Il costo opportunità'!$A$26:$A$44,0)) -> 51.728751 | E27: =SIGN(D27*12)*((((0)*INDEX('3 - Il costo opportunità'!$B$74:$B$134,(10)+1)+(ABS(D27*12))*INDEX('3 - Il costo opportunità'!$C$74:$C$134,(10)+1))-'3 - Il costo opportunità'!$B$8*MAX(0,((0)*INDEX('3 - Il costo opportunità'!$B$74:$B$134,(10)+1)+(ABS(D27*12))*INDEX('3 - Il costo opportunità'!$C$74:$C$134,(10)+1))-((0)+(ABS(D27*12))*INDEX('3 - Il costo opportunità'!$D$74:$D$134,(10)+1))))/(1+'1 - Il tuo profilo'!$B$14)^(10)) -> 6823.1488 | F27: =SIGN(D27*12)*((((0)*INDEX('3 - Il costo opportunità'!$B$74:$B$134,('3 - Il costo opportunità'!$B$9)+1)+(ABS(D27*12))*INDEX('3 - Il costo opportunità'!$C$74:$C$134,('3 - Il costo opportunità'!$B$9)+1))-'3 - Il costo opportunità'!$B$8*MAX(0,((0)*INDEX('3 - Il costo opportunità'!$B$74:$B$134,('3 - Il costo opportunità'!$B$9)+1)+(ABS(D27*12))*INDEX('3 - Il costo opportunità'!$C$74:$C$134,('3 - Il costo opportunità'!$B$9)+1))-((0)+(ABS(D27*12))*INDEX('3 - Il costo opportunità'!$D$74:$D$134,('3 - Il costo opportunità'!$B$9)+1))))/(1+'1 - Il tuo profilo'!$B$14)^('3 - Il costo opportunità'!$B$9)) -> 25840.549 | G27: =F27*'3 - Il costo opportunità'!$B$10/12 -> 64.601373 | H27: =('1 - Il tuo profilo'!$B$19+'1 - Il tuo profilo'!$B$20+'1 - Il tuo profilo'!$B$21)+C27*12 -> 24041.075 | I27: ='1 - Il tuo profilo'!$B$18-H27 -> 3285.5246 | J27: =I27/'1 - Il tuo profilo'!$B$18 -> 0.12023174 | K27: =(((('1 - Il tuo profilo'!$B$22)*INDEX('3 - Il costo opportunità'!$B$74:$B$134,('3 - Il costo opportunità'!$B$9)+1)+(I27)*INDEX('3 - Il costo opportunità'!$C$74:$C$134,('3 - Il costo opportunità'!$B$9)+1))-'3 - Il costo opportunità'!$B$8*MAX(0,(('1 - Il tuo profilo'!$B$22)*INDEX('3 - Il costo opportunità'!$B$74:$B$134,('3 - Il costo opportunità'!$B$9)+1)+(I27)*INDEX('3 - Il costo opportunità'!$C$74:$C$134,('3 - Il costo opportunità'!$B$9)+1))-(('1 - Il tuo profilo'!$B$22)+(I27)*INDEX('3 - Il costo opportunità'!$D$74:$D$134,('3 - Il costo opportunità'!$B$9)+1))))/(1+'1 - Il tuo profilo'!$B$14)^('3 - Il costo opportunità'!$B$9)) -> 252488.54 | L27: =K27*'3 - Il costo opportunità'!$B$10/12 -> 631.22135 | N27: =FV('1 - Il tuo profilo'!$B$13,10,-D27*12) -> 7116.146 | O27: =FV('1 - Il tuo profilo'!$B$13,'3 - Il costo opportunità'!$B$9,-D27*12) -> 29532.202 | P27: =O27*'3 - Il costo opportunità'!$B$10/12 -> 73.830506 | Q27: =FV('1 - Il tuo profilo'!$B$13,'3 - Il costo opportunità'!$B$9,-(I27),-('1 - Il tuo profilo'!$B$22)) -> 301945.95 | R27: =Q27*'3 - Il costo opportunità'!$B$10/12 -> 754.86487
A28: B2 | B28: Maxirata, poi rata finale rifinanziata | C28: ='2 - Le opzioni'!$L$281 -> 367.77877 | D28: =C28-INDEX('3 - Il costo opportunità'!$C$26:$C$44,MATCH('3 - Il costo opportunità'!$B$6,'3 - Il costo opportunità'!$A$26:$A$44,0)) -> 61.823738 | E28: =SIGN(D28*12)*((((0)*INDEX('3 - Il costo opportunità'!$B$74:$B$134,(10)+1)+(ABS(D28*12))*INDEX('3 - Il costo opportunità'!$C$74:$C$134,(10)+1))-'3 - Il costo opportunità'!$B$8*MAX(0,((0)*INDEX('3 - Il costo opportunità'!$B$74:$B$134,(10)+1)+(ABS(D28*12))*INDEX('3 - Il costo opportunità'!$C$74:$C$134,(10)+1))-((0)+(ABS(D28*12))*INDEX('3 - Il costo opportunità'!$D$74:$D$134,(10)+1))))/(1+'1 - Il tuo profilo'!$B$14)^(10)) -> 8154.7022 | F28: =SIGN(D28*12)*((((0)*INDEX('3 - Il costo opportunità'!$B$74:$B$134,('3 - Il costo opportunità'!$B$9)+1)+(ABS(D28*12))*INDEX('3 - Il costo opportunità'!$C$74:$C$134,('3 - Il costo opportunità'!$B$9)+1))-'3 - Il costo opportunità'!$B$8*MAX(0,((0)*INDEX('3 - Il costo opportunità'!$B$74:$B$134,('3 - Il costo opportunità'!$B$9)+1)+(ABS(D28*12))*INDEX('3 - Il costo opportunità'!$C$74:$C$134,('3 - Il costo opportunità'!$B$9)+1))-((0)+(ABS(D28*12))*INDEX('3 - Il costo opportunità'!$D$74:$D$134,('3 - Il costo opportunità'!$B$9)+1))))/(1+'1 - Il tuo profilo'!$B$14)^('3 - Il costo opportunità'!$B$9)) -> 30883.393 | G28: =F28*'3 - Il costo opportunità'!$B$10/12 -> 77.208482 | H28: =('1 - Il tuo profilo'!$B$19+'1 - Il tuo profilo'!$B$20+'1 - Il tuo profilo'!$B$21)+C28*12 -> 24162.215 | I28: ='1 - Il tuo profilo'!$B$18-H28 -> 3164.3848 | J28: =I28/'1 - Il tuo profilo'!$B$18 -> 0.1157987 | K28: =(((('1 - Il tuo profilo'!$B$22)*INDEX('3 - Il costo opportunità'!$B$74:$B$134,('3 - Il costo opportunità'!$B$9)+1)+(I28)*INDEX('3 - Il costo opportunità'!$C$74:$C$134,('3 - Il costo opportunità'!$B$9)+1))-'3 - Il costo opportunità'!$B$8*MAX(0,(('1 - Il tuo profilo'!$B$22)*INDEX('3 - Il costo opportunità'!$B$74:$B$134,('3 - Il costo opportunità'!$B$9)+1)+(I28)*INDEX('3 - Il costo opportunità'!$C$74:$C$134,('3 - Il costo opportunità'!$B$9)+1))-(('1 - Il tuo profilo'!$B$22)+(I28)*INDEX('3 - Il costo opportunità'!$D$74:$D$134,('3 - Il costo opportunità'!$B$9)+1))))/(1+'1 - Il tuo profilo'!$B$14)^('3 - Il costo opportunità'!$B$9)) -> 247445.7 | L28: =K28*'3 - Il costo opportunità'!$B$10/12 -> 618.61425 | N28: =FV('1 - Il tuo profilo'!$B$13,10,-D28*12) -> 8504.8784 | O28: =FV('1 - Il tuo profilo'!$B$13,'3 - Il costo opportunità'!$B$9,-D28*12) -> 35295.48 | P28: =O28*'3 - Il costo opportunità'!$B$10/12 -> 88.238701 | Q28: =FV('1 - Il tuo profilo'!$B$13,'3 - Il costo opportunità'!$B$9,-(I28),-('1 - Il tuo profilo'!$B$22)) -> 296182.67 | R28: =Q28*'3 - Il costo opportunità'!$B$10/12 -> 740.45668
A29: B3 alto | B29: Maxirata rinnovata, eccedenza persa (alto) | C29: ='2 - Le opzioni'!$L$300 -> 533.50587 | D29: =C29-INDEX('3 - Il costo opportunità'!$C$26:$C$44,MATCH('3 - Il costo opportunità'!$B$6,'3 - Il costo opportunità'!$A$26:$A$44,0)) -> 227.55084 | E29: =SIGN(D29*12)*((((0)*INDEX('3 - Il costo opportunità'!$B$74:$B$134,(10)+1)+(ABS(D29*12))*INDEX('3 - Il costo opportunità'!$C$74:$C$134,(10)+1))-'3 - Il costo opportunità'!$B$8*MAX(0,((0)*INDEX('3 - Il costo opportunità'!$B$74:$B$134,(10)+1)+(ABS(D29*12))*INDEX('3 - Il costo opportunità'!$C$74:$C$134,(10)+1))-((0)+(ABS(D29*12))*INDEX('3 - Il costo opportunità'!$D$74:$D$134,(10)+1))))/(1+'1 - Il tuo profilo'!$B$14)^(10)) -> 30014.512 | F29: =SIGN(D29*12)*((((0)*INDEX('3 - Il costo opportunità'!$B$74:$B$134,('3 - Il costo opportunità'!$B$9)+1)+(ABS(D29*12))*INDEX('3 - Il costo opportunità'!$C$74:$C$134,('3 - Il costo opportunità'!$B$9)+1))-'3 - Il costo opportunità'!$B$8*MAX(0,((0)*INDEX('3 - Il costo opportunità'!$B$74:$B$134,('3 - Il costo opportunità'!$B$9)+1)+(ABS(D29*12))*INDEX('3 - Il costo opportunità'!$C$74:$C$134,('3 - Il costo opportunità'!$B$9)+1))-((0)+(ABS(D29*12))*INDEX('3 - Il costo opportunità'!$D$74:$D$134,('3 - Il costo opportunità'!$B$9)+1))))/(1+'1 - Il tuo profilo'!$B$14)^('3 - Il costo opportunità'!$B$9)) -> 113670.61 | G29: =F29*'3 - Il costo opportunità'!$B$10/12 -> 284.17652 | H29: =('1 - Il tuo profilo'!$B$19+'1 - Il tuo profilo'!$B$20+'1 - Il tuo profilo'!$B$21)+C29*12 -> 26150.94 | I29: ='1 - Il tuo profilo'!$B$18-H29 -> 1175.6596 | J29: =I29/'1 - Il tuo profilo'!$B$18 -> 0.043022535 | K29: =(((('1 - Il tuo profilo'!$B$22)*INDEX('3 - Il costo opportunità'!$B$74:$B$134,('3 - Il costo opportunità'!$B$9)+1)+(I29)*INDEX('3 - Il costo opportunità'!$C$74:$C$134,('3 - Il costo opportunità'!$B$9)+1))-'3 - Il costo opportunità'!$B$8*MAX(0,(('1 - Il tuo profilo'!$B$22)*INDEX('3 - Il costo opportunità'!$B$74:$B$134,('3 - Il costo opportunità'!$B$9)+1)+(I29)*INDEX('3 - Il costo opportunità'!$C$74:$C$134,('3 - Il costo opportunità'!$B$9)+1))-(('1 - Il tuo profilo'!$B$22)+(I29)*INDEX('3 - Il costo opportunità'!$D$74:$D$134,('3 - Il costo opportunità'!$B$9)+1))))/(1+'1 - Il tuo profilo'!$B$14)^('3 - Il costo opportunità'!$B$9)) -> 164658.48 | L29: =K29*'3 - Il costo opportunità'!$B$10/12 -> 411.64621 | N29: =FV('1 - Il tuo profilo'!$B$13,10,-D29*12) -> 31303.384 | O29: =FV('1 - Il tuo profilo'!$B$13,'3 - Il costo opportunità'!$B$9,-D29*12) -> 129909.91 | P29: =O29*'3 - Il costo opportunità'!$B$10/12 -> 324.77477 | Q29: =FV('1 - Il tuo profilo'!$B$13,'3 - Il costo opportunità'!$B$9,-(I29),-('1 - Il tuo profilo'!$B$22)) -> 201568.24 | R29: =Q29*'3 - Il costo opportunità'!$B$10/12 -> 503.92061
A30: B3 basso | B30: Maxirata rinnovata, eccedenza riconosciuta (basso) | C30: ='2 - Le opzioni'!$L$319 -> 481.39775 | D30: =C30-INDEX('3 - Il costo opportunità'!$C$26:$C$44,MATCH('3 - Il costo opportunità'!$B$6,'3 - Il costo opportunità'!$A$26:$A$44,0)) -> 175.44272 | E30: =SIGN(D30*12)*((((0)*INDEX('3 - Il costo opportunità'!$B$74:$B$134,(10)+1)+(ABS(D30*12))*INDEX('3 - Il costo opportunità'!$C$74:$C$134,(10)+1))-'3 - Il costo opportunità'!$B$8*MAX(0,((0)*INDEX('3 - Il costo opportunità'!$B$74:$B$134,(10)+1)+(ABS(D30*12))*INDEX('3 - Il costo opportunità'!$C$74:$C$134,(10)+1))-((0)+(ABS(D30*12))*INDEX('3 - Il costo opportunità'!$D$74:$D$134,(10)+1))))/(1+'1 - Il tuo profilo'!$B$14)^(10)) -> 23141.324 | F30: =SIGN(D30*12)*((((0)*INDEX('3 - Il costo opportunità'!$B$74:$B$134,('3 - Il costo opportunità'!$B$9)+1)+(ABS(D30*12))*INDEX('3 - Il costo opportunità'!$C$74:$C$134,('3 - Il costo opportunità'!$B$9)+1))-'3 - Il costo opportunità'!$B$8*MAX(0,((0)*INDEX('3 - Il costo opportunità'!$B$74:$B$134,('3 - Il costo opportunità'!$B$9)+1)+(ABS(D30*12))*INDEX('3 - Il costo opportunità'!$C$74:$C$134,('3 - Il costo opportunità'!$B$9)+1))-((0)+(ABS(D30*12))*INDEX('3 - Il costo opportunità'!$D$74:$D$134,('3 - Il costo opportunità'!$B$9)+1))))/(1+'1 - Il tuo profilo'!$B$14)^('3 - Il costo opportunità'!$B$9)) -> 87640.553 | G30: =F30*'3 - Il costo opportunità'!$B$10/12 -> 219.10138 | H30: =('1 - Il tuo profilo'!$B$19+'1 - Il tuo profilo'!$B$20+'1 - Il tuo profilo'!$B$21)+C30*12 -> 25525.643 | I30: ='1 - Il tuo profilo'!$B$18-H30 -> 1800.957 | J30: =I30/'1 - Il tuo profilo'!$B$18 -> 0.065904904 | K30: =(((('1 - Il tuo profilo'!$B$22)*INDEX('3 - Il costo opportunità'!$B$74:$B$134,('3 - Il costo opportunità'!$B$9)+1)+(I30)*INDEX('3 - Il costo opportunità'!$C$74:$C$134,('3 - Il costo opportunità'!$B$9)+1))-'3 - Il costo opportunità'!$B$8*MAX(0,(('1 - Il tuo profilo'!$B$22)*INDEX('3 - Il costo opportunità'!$B$74:$B$134,('3 - Il costo opportunità'!$B$9)+1)+(I30)*INDEX('3 - Il costo opportunità'!$C$74:$C$134,('3 - Il costo opportunità'!$B$9)+1))-(('1 - Il tuo profilo'!$B$22)+(I30)*INDEX('3 - Il costo opportunità'!$D$74:$D$134,('3 - Il costo opportunità'!$B$9)+1))))/(1+'1 - Il tuo profilo'!$B$14)^('3 - Il costo opportunità'!$B$9)) -> 190688.54 | L30: =K30*'3 - Il costo opportunità'!$B$10/12 -> 476.72135 | N30: =FV('1 - Il tuo profilo'!$B$13,10,-D30*12) -> 24135.051 | O30: =FV('1 - Il tuo profilo'!$B$13,'3 - Il costo opportunità'!$B$9,-D30*12) -> 100161.13 | P30: =O30*'3 - Il costo opportunità'!$B$10/12 -> 250.40282 | Q30: =FV('1 - Il tuo profilo'!$B$13,'3 - Il costo opportunità'!$B$9,-(I30),-('1 - Il tuo profilo'!$B$22)) -> 231317.02 | R30: =Q30*'3 - Il costo opportunità'!$B$10/12 -> 578.29256
A31: C | B31: Nuova benzina in contanti | C31: ='2 - Le opzioni'!$L$129 -> 339.44037 | D31: =C31-INDEX('3 - Il costo opportunità'!$C$26:$C$44,MATCH('3 - Il costo opportunità'!$B$6,'3 - Il costo opportunità'!$A$26:$A$44,0)) -> 33.485339 | E31: =SIGN(D31*12)*((((0)*INDEX('3 - Il costo opportunità'!$B$74:$B$134,(10)+1)+(ABS(D31*12))*INDEX('3 - Il costo opportunità'!$C$74:$C$134,(10)+1))-'3 - Il costo opportunità'!$B$8*MAX(0,((0)*INDEX('3 - Il costo opportunità'!$B$74:$B$134,(10)+1)+(ABS(D31*12))*INDEX('3 - Il costo opportunità'!$C$74:$C$134,(10)+1))-((0)+(ABS(D31*12))*INDEX('3 - Il costo opportunità'!$D$74:$D$134,(10)+1))))/(1+'1 - Il tuo profilo'!$B$14)^(10)) -> 4416.798 | F31: =SIGN(D31*12)*((((0)*INDEX('3 - Il costo opportunità'!$B$74:$B$134,('3 - Il costo opportunità'!$B$9)+1)+(ABS(D31*12))*INDEX('3 - Il costo opportunità'!$C$74:$C$134,('3 - Il costo opportunità'!$B$9)+1))-'3 - Il costo opportunità'!$B$8*MAX(0,((0)*INDEX('3 - Il costo opportunità'!$B$74:$B$134,('3 - Il costo opportunità'!$B$9)+1)+(ABS(D31*12))*INDEX('3 - Il costo opportunità'!$C$74:$C$134,('3 - Il costo opportunità'!$B$9)+1))-((0)+(ABS(D31*12))*INDEX('3 - Il costo opportunità'!$D$74:$D$134,('3 - Il costo opportunità'!$B$9)+1))))/(1+'1 - Il tuo profilo'!$B$14)^('3 - Il costo opportunità'!$B$9)) -> 16727.246 | G31: =F31*'3 - Il costo opportunità'!$B$10/12 -> 41.818115 | H31: =('1 - Il tuo profilo'!$B$19+'1 - Il tuo profilo'!$B$20+'1 - Il tuo profilo'!$B$21)+C31*12 -> 23822.154 | I31: ='1 - Il tuo profilo'!$B$18-H31 -> 3504.4456 | J31: =I31/'1 - Il tuo profilo'!$B$18 -> 0.12824302 | K31: =(((('1 - Il tuo profilo'!$B$22)*INDEX('3 - Il costo opportunità'!$B$74:$B$134,('3 - Il costo opportunità'!$B$9)+1)+(I31)*INDEX('3 - Il costo opportunità'!$C$74:$C$134,('3 - Il costo opportunità'!$B$9)+1))-'3 - Il costo opportunità'!$B$8*MAX(0,(('1 - Il tuo profilo'!$B$22)*INDEX('3 - Il costo opportunità'!$B$74:$B$134,('3 - Il costo opportunità'!$B$9)+1)+(I31)*INDEX('3 - Il costo opportunità'!$C$74:$C$134,('3 - Il costo opportunità'!$B$9)+1))-(('1 - Il tuo profilo'!$B$22)+(I31)*INDEX('3 - Il costo opportunità'!$D$74:$D$134,('3 - Il costo opportunità'!$B$9)+1))))/(1+'1 - Il tuo profilo'!$B$14)^('3 - Il costo opportunità'!$B$9)) -> 261601.85 | L31: =K31*'3 - Il costo opportunità'!$B$10/12 -> 654.00461 | N31: =FV('1 - Il tuo profilo'!$B$13,10,-D31*12) -> 4606.4626 | O31: =FV('1 - Il tuo profilo'!$B$13,'3 - Il costo opportunità'!$B$9,-D31*12) -> 19116.947 | P31: =O31*'3 - Il costo opportunità'!$B$10/12 -> 47.792367 | Q31: =FV('1 - Il tuo profilo'!$B$13,'3 - Il costo opportunità'!$B$9,-(I31),-('1 - Il tuo profilo'!$B$22)) -> 312361.2 | R31: =Q31*'3 - Il costo opportunità'!$B$10/12 -> 780.90301
A32: D | B32: Usata in contanti (la stessa auto, qualche anno dopo) | C32: ='2 - Le opzioni'!$L$148 -> 305.95503 | D32: =C32-INDEX('3 - Il costo opportunità'!$C$26:$C$44,MATCH('3 - Il costo opportunità'!$B$6,'3 - Il costo opportunità'!$A$26:$A$44,0)) -> 0 | E32: =SIGN(D32*12)*((((0)*INDEX('3 - Il costo opportunità'!$B$74:$B$134,(10)+1)+(ABS(D32*12))*INDEX('3 - Il costo opportunità'!$C$74:$C$134,(10)+1))-'3 - Il costo opportunità'!$B$8*MAX(0,((0)*INDEX('3 - Il costo opportunità'!$B$74:$B$134,(10)+1)+(ABS(D32*12))*INDEX('3 - Il costo opportunità'!$C$74:$C$134,(10)+1))-((0)+(ABS(D32*12))*INDEX('3 - Il costo opportunità'!$D$74:$D$134,(10)+1))))/(1+'1 - Il tuo profilo'!$B$14)^(10)) -> 0 | F32: =SIGN(D32*12)*((((0)*INDEX('3 - Il costo opportunità'!$B$74:$B$134,('3 - Il costo opportunità'!$B$9)+1)+(ABS(D32*12))*INDEX('3 - Il costo opportunità'!$C$74:$C$134,('3 - Il costo opportunità'!$B$9)+1))-'3 - Il costo opportunità'!$B$8*MAX(0,((0)*INDEX('3 - Il costo opportunità'!$B$74:$B$134,('3 - Il costo opportunità'!$B$9)+1)+(ABS(D32*12))*INDEX('3 - Il costo opportunità'!$C$74:$C$134,('3 - Il costo opportunità'!$B$9)+1))-((0)+(ABS(D32*12))*INDEX('3 - Il costo opportunità'!$D$74:$D$134,('3 - Il costo opportunità'!$B$9)+1))))/(1+'1 - Il tuo profilo'!$B$14)^('3 - Il costo opportunità'!$B$9)) -> 0 | G32: =F32*'3 - Il costo opportunità'!$B$10/12 -> 0 | H32: =('1 - Il tuo profilo'!$B$19+'1 - Il tuo profilo'!$B$20+'1 - Il tuo profilo'!$B$21)+C32*12 -> 23420.33 | I32: ='1 - Il tuo profilo'!$B$18-H32 -> 3906.2697 | J32: =I32/'1 - Il tuo profilo'!$B$18 -> 0.14294752 | K32: =(((('1 - Il tuo profilo'!$B$22)*INDEX('3 - Il costo opportunità'!$B$74:$B$134,('3 - Il costo opportunità'!$B$9)+1)+(I32)*INDEX('3 - Il costo opportunità'!$C$74:$C$134,('3 - Il costo opportunità'!$B$9)+1))-'3 - Il costo opportunità'!$B$8*MAX(0,(('1 - Il tuo profilo'!$B$22)*INDEX('3 - Il costo opportunità'!$B$74:$B$134,('3 - Il costo opportunità'!$B$9)+1)+(I32)*INDEX('3 - Il costo opportunità'!$C$74:$C$134,('3 - Il costo opportunità'!$B$9)+1))-(('1 - Il tuo profilo'!$B$22)+(I32)*INDEX('3 - Il costo opportunità'!$D$74:$D$134,('3 - Il costo opportunità'!$B$9)+1))))/(1+'1 - Il tuo profilo'!$B$14)^('3 - Il costo opportunità'!$B$9)) -> 278329.09 | L32: =K32*'3 - Il costo opportunità'!$B$10/12 -> 695.82273 | N32: =FV('1 - Il tuo profilo'!$B$13,10,-D32*12) -> 0 | O32: =FV('1 - Il tuo profilo'!$B$13,'3 - Il costo opportunità'!$B$9,-D32*12) -> 0 | P32: =O32*'3 - Il costo opportunità'!$B$10/12 -> 0 | Q32: =FV('1 - Il tuo profilo'!$B$13,'3 - Il costo opportunità'!$B$9,-(I32),-('1 - Il tuo profilo'!$B$22)) -> 331478.15 | R32: =Q32*'3 - Il costo opportunità'!$B$10/12 -> 828.69538
A33: E | B33: Noleggio a lungo termine, benzina | C33: ='2 - Le opzioni'!$L$338 -> 443.07638 | D33: =C33-INDEX('3 - Il costo opportunità'!$C$26:$C$44,MATCH('3 - Il costo opportunità'!$B$6,'3 - Il costo opportunità'!$A$26:$A$44,0)) -> 137.12135 | E33: =SIGN(D33*12)*((((0)*INDEX('3 - Il costo opportunità'!$B$74:$B$134,(10)+1)+(ABS(D33*12))*INDEX('3 - Il costo opportunità'!$C$74:$C$134,(10)+1))-'3 - Il costo opportunità'!$B$8*MAX(0,((0)*INDEX('3 - Il costo opportunità'!$B$74:$B$134,(10)+1)+(ABS(D33*12))*INDEX('3 - Il costo opportunità'!$C$74:$C$134,(10)+1))-((0)+(ABS(D33*12))*INDEX('3 - Il costo opportunità'!$D$74:$D$134,(10)+1))))/(1+'1 - Il tuo profilo'!$B$14)^(10)) -> 18086.641 | F33: =SIGN(D33*12)*((((0)*INDEX('3 - Il costo opportunità'!$B$74:$B$134,('3 - Il costo opportunità'!$B$9)+1)+(ABS(D33*12))*INDEX('3 - Il costo opportunità'!$C$74:$C$134,('3 - Il costo opportunità'!$B$9)+1))-'3 - Il costo opportunità'!$B$8*MAX(0,((0)*INDEX('3 - Il costo opportunità'!$B$74:$B$134,('3 - Il costo opportunità'!$B$9)+1)+(ABS(D33*12))*INDEX('3 - Il costo opportunità'!$C$74:$C$134,('3 - Il costo opportunità'!$B$9)+1))-((0)+(ABS(D33*12))*INDEX('3 - Il costo opportunità'!$D$74:$D$134,('3 - Il costo opportunità'!$B$9)+1))))/(1+'1 - Il tuo profilo'!$B$14)^('3 - Il costo opportunità'!$B$9)) -> 68497.515 | G33: =F33*'3 - Il costo opportunità'!$B$10/12 -> 171.24379 | H33: =('1 - Il tuo profilo'!$B$19+'1 - Il tuo profilo'!$B$20+'1 - Il tuo profilo'!$B$21)+C33*12 -> 25065.787 | I33: ='1 - Il tuo profilo'!$B$18-H33 -> 2260.8135 | J33: =I33/'1 - Il tuo profilo'!$B$18 -> 0.082733069 | K33: =(((('1 - Il tuo profilo'!$B$22)*INDEX('3 - Il costo opportunità'!$B$74:$B$134,('3 - Il costo opportunità'!$B$9)+1)+(I33)*INDEX('3 - Il costo opportunità'!$C$74:$C$134,('3 - Il costo opportunità'!$B$9)+1))-'3 - Il costo opportunità'!$B$8*MAX(0,(('1 - Il tuo profilo'!$B$22)*INDEX('3 - Il costo opportunità'!$B$74:$B$134,('3 - Il costo opportunità'!$B$9)+1)+(I33)*INDEX('3 - Il costo opportunità'!$C$74:$C$134,('3 - Il costo opportunità'!$B$9)+1))-(('1 - Il tuo profilo'!$B$22)+(I33)*INDEX('3 - Il costo opportunità'!$D$74:$D$134,('3 - Il costo opportunità'!$B$9)+1))))/(1+'1 - Il tuo profilo'!$B$14)^('3 - Il costo opportunità'!$B$9)) -> 209831.58 | L33: =K33*'3 - Il costo opportunità'!$B$10/12 -> 524.57894 | N33: =FV('1 - Il tuo profilo'!$B$13,10,-D33*12) -> 18863.311 | O33: =FV('1 - Il tuo profilo'!$B$13,'3 - Il costo opportunità'!$B$9,-D33*12) -> 78283.261 | P33: =O33*'3 - Il costo opportunità'!$B$10/12 -> 195.70815 | Q33: =FV('1 - Il tuo profilo'!$B$13,'3 - Il costo opportunità'!$B$9,-(I33),-('1 - Il tuo profilo'!$B$22)) -> 253194.89 | R33: =Q33*'3 - Il costo opportunità'!$B$10/12 -> 632.98722
A34: F5 | B34: Tenere l'auto di oggi 5 anni, poi l'usata | C34: ='2 - Le opzioni'!$L$395 -> 323.83508 | D34: =C34-INDEX('3 - Il costo opportunità'!$C$26:$C$44,MATCH('3 - Il costo opportunità'!$B$6,'3 - Il costo opportunità'!$A$26:$A$44,0)) -> 17.880052 | E34: =SIGN(D34*12)*((((0)*INDEX('3 - Il costo opportunità'!$B$74:$B$134,(10)+1)+(ABS(D34*12))*INDEX('3 - Il costo opportunità'!$C$74:$C$134,(10)+1))-'3 - Il costo opportunità'!$B$8*MAX(0,((0)*INDEX('3 - Il costo opportunità'!$B$74:$B$134,(10)+1)+(ABS(D34*12))*INDEX('3 - Il costo opportunità'!$C$74:$C$134,(10)+1))-((0)+(ABS(D34*12))*INDEX('3 - Il costo opportunità'!$D$74:$D$134,(10)+1))))/(1+'1 - Il tuo profilo'!$B$14)^(10)) -> 2358.4226 | F34: =SIGN(D34*12)*((((0)*INDEX('3 - Il costo opportunità'!$B$74:$B$134,('3 - Il costo opportunità'!$B$9)+1)+(ABS(D34*12))*INDEX('3 - Il costo opportunità'!$C$74:$C$134,('3 - Il costo opportunità'!$B$9)+1))-'3 - Il costo opportunità'!$B$8*MAX(0,((0)*INDEX('3 - Il costo opportunità'!$B$74:$B$134,('3 - Il costo opportunità'!$B$9)+1)+(ABS(D34*12))*INDEX('3 - Il costo opportunità'!$C$74:$C$134,('3 - Il costo opportunità'!$B$9)+1))-((0)+(ABS(D34*12))*INDEX('3 - Il costo opportunità'!$D$74:$D$134,('3 - Il costo opportunità'!$B$9)+1))))/(1+'1 - Il tuo profilo'!$B$14)^('3 - Il costo opportunità'!$B$9)) -> 8931.7906 | G34: =F34*'3 - Il costo opportunità'!$B$10/12 -> 22.329477 | H34: =('1 - Il tuo profilo'!$B$19+'1 - Il tuo profilo'!$B$20+'1 - Il tuo profilo'!$B$21)+C34*12 -> 23634.891 | I34: ='1 - Il tuo profilo'!$B$18-H34 -> 3691.709 | J34: =I34/'1 - Il tuo profilo'!$B$18 -> 0.13509581 | K34: =(((('1 - Il tuo profilo'!$B$22)*INDEX('3 - Il costo opportunità'!$B$74:$B$134,('3 - Il costo opportunità'!$B$9)+1)+(I34)*INDEX('3 - Il costo opportunità'!$C$74:$C$134,('3 - Il costo opportunità'!$B$9)+1))-'3 - Il costo opportunità'!$B$8*MAX(0,(('1 - Il tuo profilo'!$B$22)*INDEX('3 - Il costo opportunità'!$B$74:$B$134,('3 - Il costo opportunità'!$B$9)+1)+(I34)*INDEX('3 - Il costo opportunità'!$C$74:$C$134,('3 - Il costo opportunità'!$B$9)+1))-(('1 - Il tuo profilo'!$B$22)+(I34)*INDEX('3 - Il costo opportunità'!$D$74:$D$134,('3 - Il costo opportunità'!$B$9)+1))))/(1+'1 - Il tuo profilo'!$B$14)^('3 - Il costo opportunità'!$B$9)) -> 269397.3 | L34: =K34*'3 - Il costo opportunità'!$B$10/12 -> 673.49325 | N34: =FV('1 - Il tuo profilo'!$B$13,10,-D34*12) -> 2459.6972 | O34: =FV('1 - Il tuo profilo'!$B$13,'3 - Il costo opportunità'!$B$9,-D34*12) -> 10207.811 | P34: =O34*'3 - Il costo opportunità'!$B$10/12 -> 25.519528 | Q34: =FV('1 - Il tuo profilo'!$B$13,'3 - Il costo opportunità'!$B$9,-(I34),-('1 - Il tuo profilo'!$B$22)) -> 321270.34 | R34: =Q34*'3 - Il costo opportunità'!$B$10/12 -> 803.17585
A35: F10 | B35: Tenere l'auto di oggi 10 anni | C35: ='2 - Le opzioni'!$L$376 -> 320.79039 | D35: =C35-INDEX('3 - Il costo opportunità'!$C$26:$C$44,MATCH('3 - Il costo opportunità'!$B$6,'3 - Il costo opportunità'!$A$26:$A$44,0)) -> 14.83536 | E35: =SIGN(D35*12)*((((0)*INDEX('3 - Il costo opportunità'!$B$74:$B$134,(10)+1)+(ABS(D35*12))*INDEX('3 - Il costo opportunità'!$C$74:$C$134,(10)+1))-'3 - Il costo opportunità'!$B$8*MAX(0,((0)*INDEX('3 - Il costo opportunità'!$B$74:$B$134,(10)+1)+(ABS(D35*12))*INDEX('3 - Il costo opportunità'!$C$74:$C$134,(10)+1))-((0)+(ABS(D35*12))*INDEX('3 - Il costo opportunità'!$D$74:$D$134,(10)+1))))/(1+'1 - Il tuo profilo'!$B$14)^(10)) -> 1956.8203 | F35: =SIGN(D35*12)*((((0)*INDEX('3 - Il costo opportunità'!$B$74:$B$134,('3 - Il costo opportunità'!$B$9)+1)+(ABS(D35*12))*INDEX('3 - Il costo opportunità'!$C$74:$C$134,('3 - Il costo opportunità'!$B$9)+1))-'3 - Il costo opportunità'!$B$8*MAX(0,((0)*INDEX('3 - Il costo opportunità'!$B$74:$B$134,('3 - Il costo opportunità'!$B$9)+1)+(ABS(D35*12))*INDEX('3 - Il costo opportunità'!$C$74:$C$134,('3 - Il costo opportunità'!$B$9)+1))-((0)+(ABS(D35*12))*INDEX('3 - Il costo opportunità'!$D$74:$D$134,('3 - Il costo opportunità'!$B$9)+1))))/(1+'1 - Il tuo profilo'!$B$14)^('3 - Il costo opportunità'!$B$9)) -> 7410.847 | G35: =F35*'3 - Il costo opportunità'!$B$10/12 -> 18.527118 | H35: =('1 - Il tuo profilo'!$B$19+'1 - Il tuo profilo'!$B$20+'1 - Il tuo profilo'!$B$21)+C35*12 -> 23598.355 | I35: ='1 - Il tuo profilo'!$B$18-H35 -> 3728.2453 | J35: =I35/'1 - Il tuo profilo'!$B$18 -> 0.13643283 | K35: =(((('1 - Il tuo profilo'!$B$22)*INDEX('3 - Il costo opportunità'!$B$74:$B$134,('3 - Il costo opportunità'!$B$9)+1)+(I35)*INDEX('3 - Il costo opportunità'!$C$74:$C$134,('3 - Il costo opportunità'!$B$9)+1))-'3 - Il costo opportunità'!$B$8*MAX(0,(('1 - Il tuo profilo'!$B$22)*INDEX('3 - Il costo opportunità'!$B$74:$B$134,('3 - Il costo opportunità'!$B$9)+1)+(I35)*INDEX('3 - Il costo opportunità'!$C$74:$C$134,('3 - Il costo opportunità'!$B$9)+1))-(('1 - Il tuo profilo'!$B$22)+(I35)*INDEX('3 - Il costo opportunità'!$D$74:$D$134,('3 - Il costo opportunità'!$B$9)+1))))/(1+'1 - Il tuo profilo'!$B$14)^('3 - Il costo opportunità'!$B$9)) -> 270918.24 | L35: =K35*'3 - Il costo opportunità'!$B$10/12 -> 677.29561 | N35: =FV('1 - Il tuo profilo'!$B$13,10,-D35*12) -> 2040.8494 | O35: =FV('1 - Il tuo profilo'!$B$13,'3 - Il costo opportunità'!$B$9,-D35*12) -> 8469.5813 | P35: =O35*'3 - Il costo opportunità'!$B$10/12 -> 21.173953 | Q35: =FV('1 - Il tuo profilo'!$B$13,'3 - Il costo opportunità'!$B$9,-(I35),-('1 - Il tuo profilo'!$B$22)) -> 323008.57 | R35: =Q35*'3 - Il costo opportunità'!$B$10/12 -> 807.52142
A36: G | B36: Senza auto, città media | C36: ='2 - Le opzioni'!$L$414 -> 171.19237 | D36: =C36-INDEX('3 - Il costo opportunità'!$C$26:$C$44,MATCH('3 - Il costo opportunità'!$B$6,'3 - Il costo opportunità'!$A$26:$A$44,0)) -> -134.76266 | E36: =SIGN(D36*12)*((((0)*INDEX('3 - Il costo opportunità'!$B$74:$B$134,(10)+1)+(ABS(D36*12))*INDEX('3 - Il costo opportunità'!$C$74:$C$134,(10)+1))-'3 - Il costo opportunità'!$B$8*MAX(0,((0)*INDEX('3 - Il costo opportunità'!$B$74:$B$134,(10)+1)+(ABS(D36*12))*INDEX('3 - Il costo opportunità'!$C$74:$C$134,(10)+1))-((0)+(ABS(D36*12))*INDEX('3 - Il costo opportunità'!$D$74:$D$134,(10)+1))))/(1+'1 - Il tuo profilo'!$B$14)^(10)) -> -17775.524 | F36: =SIGN(D36*12)*((((0)*INDEX('3 - Il costo opportunità'!$B$74:$B$134,('3 - Il costo opportunità'!$B$9)+1)+(ABS(D36*12))*INDEX('3 - Il costo opportunità'!$C$74:$C$134,('3 - Il costo opportunità'!$B$9)+1))-'3 - Il costo opportunità'!$B$8*MAX(0,((0)*INDEX('3 - Il costo opportunità'!$B$74:$B$134,('3 - Il costo opportunità'!$B$9)+1)+(ABS(D36*12))*INDEX('3 - Il costo opportunità'!$C$74:$C$134,('3 - Il costo opportunità'!$B$9)+1))-((0)+(ABS(D36*12))*INDEX('3 - Il costo opportunità'!$D$74:$D$134,('3 - Il costo opportunità'!$B$9)+1))))/(1+'1 - Il tuo profilo'!$B$14)^('3 - Il costo opportunità'!$B$9)) -> -67319.256 | G36: =F36*'3 - Il costo opportunità'!$B$10/12 -> -168.29814 | H36: =('1 - Il tuo profilo'!$B$19+'1 - Il tuo profilo'!$B$20+'1 - Il tuo profilo'!$B$21)+C36*12 -> 21803.178 | I36: ='1 - Il tuo profilo'!$B$18-H36 -> 5523.4215 | J36: =I36/'1 - Il tuo profilo'!$B$18 -> 0.20212619 | K36: =(((('1 - Il tuo profilo'!$B$22)*INDEX('3 - Il costo opportunità'!$B$74:$B$134,('3 - Il costo opportunità'!$B$9)+1)+(I36)*INDEX('3 - Il costo opportunità'!$C$74:$C$134,('3 - Il costo opportunità'!$B$9)+1))-'3 - Il costo opportunità'!$B$8*MAX(0,(('1 - Il tuo profilo'!$B$22)*INDEX('3 - Il costo opportunità'!$B$74:$B$134,('3 - Il costo opportunità'!$B$9)+1)+(I36)*INDEX('3 - Il costo opportunità'!$C$74:$C$134,('3 - Il costo opportunità'!$B$9)+1))-(('1 - Il tuo profilo'!$B$22)+(I36)*INDEX('3 - Il costo opportunità'!$D$74:$D$134,('3 - Il costo opportunità'!$B$9)+1))))/(1+'1 - Il tuo profilo'!$B$14)^('3 - Il costo opportunità'!$B$9)) -> 345648.35 | L36: =K36*'3 - Il costo opportunità'!$B$10/12 -> 864.12087 | N36: =FV('1 - Il tuo profilo'!$B$13,10,-D36*12) -> -18538.834 | O36: =FV('1 - Il tuo profilo'!$B$13,'3 - Il costo opportunità'!$B$9,-D36*12) -> -76936.672 | P36: =O36*'3 - Il costo opportunità'!$B$10/12 -> -192.34168 | Q36: =FV('1 - Il tuo profilo'!$B$13,'3 - Il costo opportunità'!$B$9,-(I36),-('1 - Il tuo profilo'!$B$22)) -> 408414.82 | R36: =Q36*'3 - Il costo opportunità'!$B$10/12 -> 1021.0371
A37: C-ibr | B37: Nuova ibrida in contanti | C37: ='2 - Le opzioni'!$L$167 -> 344.01601 | D37: =C37-INDEX('3 - Il costo opportunità'!$C$26:$C$44,MATCH('3 - Il costo opportunità'!$B$6,'3 - Il costo opportunità'!$A$26:$A$44,0)) -> 38.060982 | E37: =SIGN(D37*12)*((((0)*INDEX('3 - Il costo opportunità'!$B$74:$B$134,(10)+1)+(ABS(D37*12))*INDEX('3 - Il costo opportunità'!$C$74:$C$134,(10)+1))-'3 - Il costo opportunità'!$B$8*MAX(0,((0)*INDEX('3 - Il costo opportunità'!$B$74:$B$134,(10)+1)+(ABS(D37*12))*INDEX('3 - Il costo opportunità'!$C$74:$C$134,(10)+1))-((0)+(ABS(D37*12))*INDEX('3 - Il costo opportunità'!$D$74:$D$134,(10)+1))))/(1+'1 - Il tuo profilo'!$B$14)^(10)) -> 5020.3365 | F37: =SIGN(D37*12)*((((0)*INDEX('3 - Il costo opportunità'!$B$74:$B$134,('3 - Il costo opportunità'!$B$9)+1)+(ABS(D37*12))*INDEX('3 - Il costo opportunità'!$C$74:$C$134,('3 - Il costo opportunità'!$B$9)+1))-'3 - Il costo opportunità'!$B$8*MAX(0,((0)*INDEX('3 - Il costo opportunità'!$B$74:$B$134,('3 - Il costo opportunità'!$B$9)+1)+(ABS(D37*12))*INDEX('3 - Il costo opportunità'!$C$74:$C$134,('3 - Il costo opportunità'!$B$9)+1))-((0)+(ABS(D37*12))*INDEX('3 - Il costo opportunità'!$D$74:$D$134,('3 - Il costo opportunità'!$B$9)+1))))/(1+'1 - Il tuo profilo'!$B$14)^('3 - Il costo opportunità'!$B$9)) -> 19012.96 | G37: =F37*'3 - Il costo opportunità'!$B$10/12 -> 47.5324 | H37: =('1 - Il tuo profilo'!$B$19+'1 - Il tuo profilo'!$B$20+'1 - Il tuo profilo'!$B$21)+C37*12 -> 23877.062 | I37: ='1 - Il tuo profilo'!$B$18-H37 -> 3449.5379 | J37: =I37/'1 - Il tuo profilo'!$B$18 -> 0.1262337 | K37: =(((('1 - Il tuo profilo'!$B$22)*INDEX('3 - Il costo opportunità'!$B$74:$B$134,('3 - Il costo opportunità'!$B$9)+1)+(I37)*INDEX('3 - Il costo opportunità'!$C$74:$C$134,('3 - Il costo opportunità'!$B$9)+1))-'3 - Il costo opportunità'!$B$8*MAX(0,(('1 - Il tuo profilo'!$B$22)*INDEX('3 - Il costo opportunità'!$B$74:$B$134,('3 - Il costo opportunità'!$B$9)+1)+(I37)*INDEX('3 - Il costo opportunità'!$C$74:$C$134,('3 - Il costo opportunità'!$B$9)+1))-(('1 - Il tuo profilo'!$B$22)+(I37)*INDEX('3 - Il costo opportunità'!$D$74:$D$134,('3 - Il costo opportunità'!$B$9)+1))))/(1+'1 - Il tuo profilo'!$B$14)^('3 - Il costo opportunità'!$B$9)) -> 259316.13 | L37: =K37*'3 - Il costo opportunità'!$B$10/12 -> 648.29033 | N37: =FV('1 - Il tuo profilo'!$B$13,10,-D37*12) -> 5235.918 | O37: =FV('1 - Il tuo profilo'!$B$13,'3 - Il costo opportunità'!$B$9,-D37*12) -> 21729.204 | P37: =O37*'3 - Il costo opportunità'!$B$10/12 -> 54.323011 | Q37: =FV('1 - Il tuo profilo'!$B$13,'3 - Il costo opportunità'!$B$9,-(I37),-('1 - Il tuo profilo'!$B$22)) -> 309748.95 | R37: =Q37*'3 - Il costo opportunità'!$B$10/12 -> 774.37237
A38: C-el | B38: Nuova elettrica in contanti, ricarica a casa | C38: ='2 - Le opzioni'!$L$186 -> 332.94133 | D38: =C38-INDEX('3 - Il costo opportunità'!$C$26:$C$44,MATCH('3 - Il costo opportunità'!$B$6,'3 - Il costo opportunità'!$A$26:$A$44,0)) -> 26.986305 | E38: =SIGN(D38*12)*((((0)*INDEX('3 - Il costo opportunità'!$B$74:$B$134,(10)+1)+(ABS(D38*12))*INDEX('3 - Il costo opportunità'!$C$74:$C$134,(10)+1))-'3 - Il costo opportunità'!$B$8*MAX(0,((0)*INDEX('3 - Il costo opportunità'!$B$74:$B$134,(10)+1)+(ABS(D38*12))*INDEX('3 - Il costo opportunità'!$C$74:$C$134,(10)+1))-((0)+(ABS(D38*12))*INDEX('3 - Il costo opportunità'!$D$74:$D$134,(10)+1))))/(1+'1 - Il tuo profilo'!$B$14)^(10)) -> 3559.5596 | F38: =SIGN(D38*12)*((((0)*INDEX('3 - Il costo opportunità'!$B$74:$B$134,('3 - Il costo opportunità'!$B$9)+1)+(ABS(D38*12))*INDEX('3 - Il costo opportunità'!$C$74:$C$134,('3 - Il costo opportunità'!$B$9)+1))-'3 - Il costo opportunità'!$B$8*MAX(0,((0)*INDEX('3 - Il costo opportunità'!$B$74:$B$134,('3 - Il costo opportunità'!$B$9)+1)+(ABS(D38*12))*INDEX('3 - Il costo opportunità'!$C$74:$C$134,('3 - Il costo opportunità'!$B$9)+1))-((0)+(ABS(D38*12))*INDEX('3 - Il costo opportunità'!$D$74:$D$134,('3 - Il costo opportunità'!$B$9)+1))))/(1+'1 - Il tuo profilo'!$B$14)^('3 - Il costo opportunità'!$B$9)) -> 13480.722 | G38: =F38*'3 - Il costo opportunità'!$B$10/12 -> 33.701806 | H38: =('1 - Il tuo profilo'!$B$19+'1 - Il tuo profilo'!$B$20+'1 - Il tuo profilo'!$B$21)+C38*12 -> 23744.166 | I38: ='1 - Il tuo profilo'!$B$18-H38 -> 3582.434 | J38: =I38/'1 - Il tuo profilo'!$B$18 -> 0.13109695 | K38: =(((('1 - Il tuo profilo'!$B$22)*INDEX('3 - Il costo opportunità'!$B$74:$B$134,('3 - Il costo opportunità'!$B$9)+1)+(I38)*INDEX('3 - Il costo opportunità'!$C$74:$C$134,('3 - Il costo opportunità'!$B$9)+1))-'3 - Il costo opportunità'!$B$8*MAX(0,(('1 - Il tuo profilo'!$B$22)*INDEX('3 - Il costo opportunità'!$B$74:$B$134,('3 - Il costo opportunità'!$B$9)+1)+(I38)*INDEX('3 - Il costo opportunità'!$C$74:$C$134,('3 - Il costo opportunità'!$B$9)+1))-(('1 - Il tuo profilo'!$B$22)+(I38)*INDEX('3 - Il costo opportunità'!$D$74:$D$134,('3 - Il costo opportunità'!$B$9)+1))))/(1+'1 - Il tuo profilo'!$B$14)^('3 - Il costo opportunità'!$B$9)) -> 264848.37 | L38: =K38*'3 - Il costo opportunità'!$B$10/12 -> 662.12092 | N38: =FV('1 - Il tuo profilo'!$B$13,10,-D38*12) -> 3712.4129 | O38: =FV('1 - Il tuo profilo'!$B$13,'3 - Il costo opportunità'!$B$9,-D38*12) -> 15406.616 | P38: =O38*'3 - Il costo opportunità'!$B$10/12 -> 38.51654 | Q38: =FV('1 - Il tuo profilo'!$B$13,'3 - Il costo opportunità'!$B$9,-(I38),-('1 - Il tuo profilo'!$B$22)) -> 316071.54 | R38: =Q38*'3 - Il costo opportunità'!$B$10/12 -> 790.17884
A39: C-el-pub | B39: Nuova elettrica in contanti, ricarica soprattutto alla colonnina | C39: ='2 - Le opzioni'!$L$205 -> 369.04593 | D39: =C39-INDEX('3 - Il costo opportunità'!$C$26:$C$44,MATCH('3 - Il costo opportunità'!$B$6,'3 - Il costo opportunità'!$A$26:$A$44,0)) -> 63.090905 | E39: =SIGN(D39*12)*((((0)*INDEX('3 - Il costo opportunità'!$B$74:$B$134,(10)+1)+(ABS(D39*12))*INDEX('3 - Il costo opportunità'!$C$74:$C$134,(10)+1))-'3 - Il costo opportunità'!$B$8*MAX(0,((0)*INDEX('3 - Il costo opportunità'!$B$74:$B$134,(10)+1)+(ABS(D39*12))*INDEX('3 - Il costo opportunità'!$C$74:$C$134,(10)+1))-((0)+(ABS(D39*12))*INDEX('3 - Il costo opportunità'!$D$74:$D$134,(10)+1))))/(1+'1 - Il tuo profilo'!$B$14)^(10)) -> 8321.8446 | F39: =SIGN(D39*12)*((((0)*INDEX('3 - Il costo opportunità'!$B$74:$B$134,('3 - Il costo opportunità'!$B$9)+1)+(ABS(D39*12))*INDEX('3 - Il costo opportunità'!$C$74:$C$134,('3 - Il costo opportunità'!$B$9)+1))-'3 - Il costo opportunità'!$B$8*MAX(0,((0)*INDEX('3 - Il costo opportunità'!$B$74:$B$134,('3 - Il costo opportunità'!$B$9)+1)+(ABS(D39*12))*INDEX('3 - Il costo opportunità'!$C$74:$C$134,('3 - Il costo opportunità'!$B$9)+1))-((0)+(ABS(D39*12))*INDEX('3 - Il costo opportunità'!$D$74:$D$134,('3 - Il costo opportunità'!$B$9)+1))))/(1+'1 - Il tuo profilo'!$B$14)^('3 - Il costo opportunità'!$B$9)) -> 31516.392 | G39: =F39*'3 - Il costo opportunità'!$B$10/12 -> 78.790981 | H39: =('1 - Il tuo profilo'!$B$19+'1 - Il tuo profilo'!$B$20+'1 - Il tuo profilo'!$B$21)+C39*12 -> 24177.421 | I39: ='1 - Il tuo profilo'!$B$18-H39 -> 3149.1788 | J39: =I39/'1 - Il tuo profilo'!$B$18 -> 0.11524225 | K39: =(((('1 - Il tuo profilo'!$B$22)*INDEX('3 - Il costo opportunità'!$B$74:$B$134,('3 - Il costo opportunità'!$B$9)+1)+(I39)*INDEX('3 - Il costo opportunità'!$C$74:$C$134,('3 - Il costo opportunità'!$B$9)+1))-'3 - Il costo opportunità'!$B$8*MAX(0,(('1 - Il tuo profilo'!$B$22)*INDEX('3 - Il costo opportunità'!$B$74:$B$134,('3 - Il costo opportunità'!$B$9)+1)+(I39)*INDEX('3 - Il costo opportunità'!$C$74:$C$134,('3 - Il costo opportunità'!$B$9)+1))-(('1 - Il tuo profilo'!$B$22)+(I39)*INDEX('3 - Il costo opportunità'!$D$74:$D$134,('3 - Il costo opportunità'!$B$9)+1))))/(1+'1 - Il tuo profilo'!$B$14)^('3 - Il costo opportunità'!$B$9)) -> 246812.7 | L39: =K39*'3 - Il costo opportunità'!$B$10/12 -> 617.03175 | N39: =FV('1 - Il tuo profilo'!$B$13,10,-D39*12) -> 8679.1982 | O39: =FV('1 - Il tuo profilo'!$B$13,'3 - Il costo opportunità'!$B$9,-D39*12) -> 36018.912 | P39: =O39*'3 - Il costo opportunità'!$B$10/12 -> 90.04728 | Q39: =FV('1 - Il tuo profilo'!$B$13,'3 - Il costo opportunità'!$B$9,-(I39),-('1 - Il tuo profilo'!$B$22)) -> 295459.24 | R39: =Q39*'3 - Il costo opportunità'!$B$10/12 -> 738.6481
A40: A-el | B40: Nuova elettrica a rate, ricarica a casa | C40: ='2 - Le opzioni'!$L$243 -> 359.35863 | D40: =C40-INDEX('3 - Il costo opportunità'!$C$26:$C$44,MATCH('3 - Il costo opportunità'!$B$6,'3 - Il costo opportunità'!$A$26:$A$44,0)) -> 53.403603 | E40: =SIGN(D40*12)*((((0)*INDEX('3 - Il costo opportunità'!$B$74:$B$134,(10)+1)+(ABS(D40*12))*INDEX('3 - Il costo opportunità'!$C$74:$C$134,(10)+1))-'3 - Il costo opportunità'!$B$8*MAX(0,((0)*INDEX('3 - Il costo opportunità'!$B$74:$B$134,(10)+1)+(ABS(D40*12))*INDEX('3 - Il costo opportunità'!$C$74:$C$134,(10)+1))-((0)+(ABS(D40*12))*INDEX('3 - Il costo opportunità'!$D$74:$D$134,(10)+1))))/(1+'1 - Il tuo profilo'!$B$14)^(10)) -> 7044.0658 | F40: =SIGN(D40*12)*((((0)*INDEX('3 - Il costo opportunità'!$B$74:$B$134,('3 - Il costo opportunità'!$B$9)+1)+(ABS(D40*12))*INDEX('3 - Il costo opportunità'!$C$74:$C$134,('3 - Il costo opportunità'!$B$9)+1))-'3 - Il costo opportunità'!$B$8*MAX(0,((0)*INDEX('3 - Il costo opportunità'!$B$74:$B$134,('3 - Il costo opportunità'!$B$9)+1)+(ABS(D40*12))*INDEX('3 - Il costo opportunità'!$C$74:$C$134,('3 - Il costo opportunità'!$B$9)+1))-((0)+(ABS(D40*12))*INDEX('3 - Il costo opportunità'!$D$74:$D$134,('3 - Il costo opportunità'!$B$9)+1))))/(1+'1 - Il tuo profilo'!$B$14)^('3 - Il costo opportunità'!$B$9)) -> 26677.204 | G40: =F40*'3 - Il costo opportunità'!$B$10/12 -> 66.693009 | H40: =('1 - Il tuo profilo'!$B$19+'1 - Il tuo profilo'!$B$20+'1 - Il tuo profilo'!$B$21)+C40*12 -> 24061.174 | I40: ='1 - Il tuo profilo'!$B$18-H40 -> 3265.4264 | J40: =I40/'1 - Il tuo profilo'!$B$18 -> 0.11949626 | K40: =(((('1 - Il tuo profilo'!$B$22)*INDEX('3 - Il costo opportunità'!$B$74:$B$134,('3 - Il costo opportunità'!$B$9)+1)+(I40)*INDEX('3 - Il costo opportunità'!$C$74:$C$134,('3 - Il costo opportunità'!$B$9)+1))-'3 - Il costo opportunità'!$B$8*MAX(0,(('1 - Il tuo profilo'!$B$22)*INDEX('3 - Il costo opportunità'!$B$74:$B$134,('3 - Il costo opportunità'!$B$9)+1)+(I40)*INDEX('3 - Il costo opportunità'!$C$74:$C$134,('3 - Il costo opportunità'!$B$9)+1))-(('1 - Il tuo profilo'!$B$22)+(I40)*INDEX('3 - Il costo opportunità'!$D$74:$D$134,('3 - Il costo opportunità'!$B$9)+1))))/(1+'1 - Il tuo profilo'!$B$14)^('3 - Il costo opportunità'!$B$9)) -> 251651.89 | L40: =K40*'3 - Il costo opportunità'!$B$10/12 -> 629.12972 | N40: =FV('1 - Il tuo profilo'!$B$13,10,-D40*12) -> 7346.5496 | O40: =FV('1 - Il tuo profilo'!$B$13,'3 - Il costo opportunità'!$B$9,-D40*12) -> 30488.384 | P40: =O40*'3 - Il costo opportunità'!$B$10/12 -> 76.220959 | Q40: =FV('1 - Il tuo profilo'!$B$13,'3 - Il costo opportunità'!$B$9,-(I40),-('1 - Il tuo profilo'!$B$22)) -> 300989.77 | R40: =Q40*'3 - Il costo opportunità'!$B$10/12 -> 752.47442
A41: E-el | B41: Noleggio a lungo termine, elettrica | C41: ='2 - Le opzioni'!$L$357 -> 434.20064 | D41: =C41-INDEX('3 - Il costo opportunità'!$C$26:$C$44,MATCH('3 - Il costo opportunità'!$B$6,'3 - Il costo opportunità'!$A$26:$A$44,0)) -> 128.24561 | E41: =SIGN(D41*12)*((((0)*INDEX('3 - Il costo opportunità'!$B$74:$B$134,(10)+1)+(ABS(D41*12))*INDEX('3 - Il costo opportunità'!$C$74:$C$134,(10)+1))-'3 - Il costo opportunità'!$B$8*MAX(0,((0)*INDEX('3 - Il costo opportunità'!$B$74:$B$134,(10)+1)+(ABS(D41*12))*INDEX('3 - Il costo opportunità'!$C$74:$C$134,(10)+1))-((0)+(ABS(D41*12))*INDEX('3 - Il costo opportunità'!$D$74:$D$134,(10)+1))))/(1+'1 - Il tuo profilo'!$B$14)^(10)) -> 16915.91 | F41: =SIGN(D41*12)*((((0)*INDEX('3 - Il costo opportunità'!$B$74:$B$134,('3 - Il costo opportunità'!$B$9)+1)+(ABS(D41*12))*INDEX('3 - Il costo opportunità'!$C$74:$C$134,('3 - Il costo opportunità'!$B$9)+1))-'3 - Il costo opportunità'!$B$8*MAX(0,((0)*INDEX('3 - Il costo opportunità'!$B$74:$B$134,('3 - Il costo opportunità'!$B$9)+1)+(ABS(D41*12))*INDEX('3 - Il costo opportunità'!$C$74:$C$134,('3 - Il costo opportunità'!$B$9)+1))-((0)+(ABS(D41*12))*INDEX('3 - Il costo opportunità'!$D$74:$D$134,('3 - Il costo opportunità'!$B$9)+1))))/(1+'1 - Il tuo profilo'!$B$14)^('3 - Il costo opportunità'!$B$9)) -> 64063.735 | G41: =F41*'3 - Il costo opportunità'!$B$10/12 -> 160.15934 | H41: =('1 - Il tuo profilo'!$B$19+'1 - Il tuo profilo'!$B$20+'1 - Il tuo profilo'!$B$21)+C41*12 -> 24959.278 | I41: ='1 - Il tuo profilo'!$B$18-H41 -> 2367.3223 | J41: =I41/'1 - Il tuo profilo'!$B$18 -> 0.086630694 | K41: =(((('1 - Il tuo profilo'!$B$22)*INDEX('3 - Il costo opportunità'!$B$74:$B$134,('3 - Il costo opportunità'!$B$9)+1)+(I41)*INDEX('3 - Il costo opportunità'!$C$74:$C$134,('3 - Il costo opportunità'!$B$9)+1))-'3 - Il costo opportunità'!$B$8*MAX(0,(('1 - Il tuo profilo'!$B$22)*INDEX('3 - Il costo opportunità'!$B$74:$B$134,('3 - Il costo opportunità'!$B$9)+1)+(I41)*INDEX('3 - Il costo opportunità'!$C$74:$C$134,('3 - Il costo opportunità'!$B$9)+1))-(('1 - Il tuo profilo'!$B$22)+(I41)*INDEX('3 - Il costo opportunità'!$D$74:$D$134,('3 - Il costo opportunità'!$B$9)+1))))/(1+'1 - Il tuo profilo'!$B$14)^('3 - Il costo opportunità'!$B$9)) -> 214265.36 | L41: =K41*'3 - Il costo opportunità'!$B$10/12 -> 535.66339 | N41: =FV('1 - Il tuo profilo'!$B$13,10,-D41*12) -> 17642.306 | O41: =FV('1 - Il tuo profilo'!$B$13,'3 - Il costo opportunità'!$B$9,-D41*12) -> 73216.059 | P41: =O41*'3 - Il costo opportunità'!$B$10/12 -> 183.04015 | Q41: =FV('1 - Il tuo profilo'!$B$13,'3 - Il costo opportunità'!$B$9,-(I41),-('1 - Il tuo profilo'!$B$22)) -> 258262.09 | R41: =Q41*'3 - Il costo opportunità'!$B$10/12 -> 645.65523
A42: G-gc | B42: Senza auto, grande città | C42: ='2 - Le opzioni'!$L$433 -> 115.10904 | D42: =C42-INDEX('3 - Il costo opportunità'!$C$26:$C$44,MATCH('3 - Il costo opportunità'!$B$6,'3 - Il costo opportunità'!$A$26:$A$44,0)) -> -190.84599 | E42: =SIGN(D42*12)*((((0)*INDEX('3 - Il costo opportunità'!$B$74:$B$134,(10)+1)+(ABS(D42*12))*INDEX('3 - Il costo opportunità'!$C$74:$C$134,(10)+1))-'3 - Il costo opportunità'!$B$8*MAX(0,((0)*INDEX('3 - Il costo opportunità'!$B$74:$B$134,(10)+1)+(ABS(D42*12))*INDEX('3 - Il costo opportunità'!$C$74:$C$134,(10)+1))-((0)+(ABS(D42*12))*INDEX('3 - Il costo opportunità'!$D$74:$D$134,(10)+1))))/(1+'1 - Il tuo profilo'!$B$14)^(10)) -> -25173.052 | F42: =SIGN(D42*12)*((((0)*INDEX('3 - Il costo opportunità'!$B$74:$B$134,('3 - Il costo opportunità'!$B$9)+1)+(ABS(D42*12))*INDEX('3 - Il costo opportunità'!$C$74:$C$134,('3 - Il costo opportunità'!$B$9)+1))-'3 - Il costo opportunità'!$B$8*MAX(0,((0)*INDEX('3 - Il costo opportunità'!$B$74:$B$134,('3 - Il costo opportunità'!$B$9)+1)+(ABS(D42*12))*INDEX('3 - Il costo opportunità'!$C$74:$C$134,('3 - Il costo opportunità'!$B$9)+1))-((0)+(ABS(D42*12))*INDEX('3 - Il costo opportunità'!$D$74:$D$134,('3 - Il costo opportunità'!$B$9)+1))))/(1+'1 - Il tuo profilo'!$B$14)^('3 - Il costo opportunità'!$B$9)) -> -95335.09 | G42: =F42*'3 - Il costo opportunità'!$B$10/12 -> -238.33773 | H42: =('1 - Il tuo profilo'!$B$19+'1 - Il tuo profilo'!$B$20+'1 - Il tuo profilo'!$B$21)+C42*12 -> 21130.178 | I42: ='1 - Il tuo profilo'!$B$18-H42 -> 6196.4215 | J42: =I42/'1 - Il tuo profilo'!$B$18 -> 0.22675421 | K42: =(((('1 - Il tuo profilo'!$B$22)*INDEX('3 - Il costo opportunità'!$B$74:$B$134,('3 - Il costo opportunità'!$B$9)+1)+(I42)*INDEX('3 - Il costo opportunità'!$C$74:$C$134,('3 - Il costo opportunità'!$B$9)+1))-'3 - Il costo opportunità'!$B$8*MAX(0,(('1 - Il tuo profilo'!$B$22)*INDEX('3 - Il costo opportunità'!$B$74:$B$134,('3 - Il costo opportunità'!$B$9)+1)+(I42)*INDEX('3 - Il costo opportunità'!$C$74:$C$134,('3 - Il costo opportunità'!$B$9)+1))-(('1 - Il tuo profilo'!$B$22)+(I42)*INDEX('3 - Il costo opportunità'!$D$74:$D$134,('3 - Il costo opportunità'!$B$9)+1))))/(1+'1 - Il tuo profilo'!$B$14)^('3 - Il costo opportunità'!$B$9)) -> 373664.18 | L42: =K42*'3 - Il costo opportunità'!$B$10/12 -> 934.16045 | N42: =FV('1 - Il tuo profilo'!$B$13,10,-D42*12) -> -26254.025 | O42: =FV('1 - Il tuo profilo'!$B$13,'3 - Il costo opportunità'!$B$9,-D42*12) -> -108954.93 | P42: =O42*'3 - Il costo opportunità'!$B$10/12 -> -272.38732 | Q42: =FV('1 - Il tuo profilo'!$B$13,'3 - Il costo opportunità'!$B$9,-(I42),-('1 - Il tuo profilo'!$B$22)) -> 440433.08 | R42: =Q42*'3 - Il costo opportunità'!$B$10/12 -> 1101.0827
A43: G-pr | B43: Senza auto, provincia | C43: ='2 - Le opzioni'!$L$452 -> 320.69237 | D43: =C43-INDEX('3 - Il costo opportunità'!$C$26:$C$44,MATCH('3 - Il costo opportunità'!$B$6,'3 - Il costo opportunità'!$A$26:$A$44,0)) -> 14.737345 | E43: =SIGN(D43*12)*((((0)*INDEX('3 - Il costo opportunità'!$B$74:$B$134,(10)+1)+(ABS(D43*12))*INDEX('3 - Il costo opportunità'!$C$74:$C$134,(10)+1))-'3 - Il costo opportunità'!$B$8*MAX(0,((0)*INDEX('3 - Il costo opportunità'!$B$74:$B$134,(10)+1)+(ABS(D43*12))*INDEX('3 - Il costo opportunità'!$C$74:$C$134,(10)+1))-((0)+(ABS(D43*12))*INDEX('3 - Il costo opportunità'!$D$74:$D$134,(10)+1))))/(1+'1 - Il tuo profilo'!$B$14)^(10)) -> 1943.8918 | F43: =SIGN(D43*12)*((((0)*INDEX('3 - Il costo opportunità'!$B$74:$B$134,('3 - Il costo opportunità'!$B$9)+1)+(ABS(D43*12))*INDEX('3 - Il costo opportunità'!$C$74:$C$134,('3 - Il costo opportunità'!$B$9)+1))-'3 - Il costo opportunità'!$B$8*MAX(0,((0)*INDEX('3 - Il costo opportunità'!$B$74:$B$134,('3 - Il costo opportunità'!$B$9)+1)+(ABS(D43*12))*INDEX('3 - Il costo opportunità'!$C$74:$C$134,('3 - Il costo opportunità'!$B$9)+1))-((0)+(ABS(D43*12))*INDEX('3 - Il costo opportunità'!$D$74:$D$134,('3 - Il costo opportunità'!$B$9)+1))))/(1+'1 - Il tuo profilo'!$B$14)^('3 - Il costo opportunità'!$B$9)) -> 7361.8842 | G43: =F43*'3 - Il costo opportunità'!$B$10/12 -> 18.404711 | H43: =('1 - Il tuo profilo'!$B$19+'1 - Il tuo profilo'!$B$20+'1 - Il tuo profilo'!$B$21)+C43*12 -> 23597.178 | I43: ='1 - Il tuo profilo'!$B$18-H43 -> 3729.4215 | J43: =I43/'1 - Il tuo profilo'!$B$18 -> 0.13647587 | K43: =(((('1 - Il tuo profilo'!$B$22)*INDEX('3 - Il costo opportunità'!$B$74:$B$134,('3 - Il costo opportunità'!$B$9)+1)+(I43)*INDEX('3 - Il costo opportunità'!$C$74:$C$134,('3 - Il costo opportunità'!$B$9)+1))-'3 - Il costo opportunità'!$B$8*MAX(0,(('1 - Il tuo profilo'!$B$22)*INDEX('3 - Il costo opportunità'!$B$74:$B$134,('3 - Il costo opportunità'!$B$9)+1)+(I43)*INDEX('3 - Il costo opportunità'!$C$74:$C$134,('3 - Il costo opportunità'!$B$9)+1))-(('1 - Il tuo profilo'!$B$22)+(I43)*INDEX('3 - Il costo opportunità'!$D$74:$D$134,('3 - Il costo opportunità'!$B$9)+1))))/(1+'1 - Il tuo profilo'!$B$14)^('3 - Il costo opportunità'!$B$9)) -> 270967.21 | L43: =K43*'3 - Il costo opportunità'!$B$10/12 -> 677.41802 | N43: =FV('1 - Il tuo profilo'!$B$13,10,-D43*12) -> 2027.3657 | O43: =FV('1 - Il tuo profilo'!$B$13,'3 - Il costo opportunità'!$B$9,-D43*12) -> 8413.6235 | P43: =O43*'3 - Il costo opportunità'!$B$10/12 -> 21.034059 | Q43: =FV('1 - Il tuo profilo'!$B$13,'3 - Il costo opportunità'!$B$9,-(I43),-('1 - Il tuo profilo'!$B$22)) -> 323064.53 | R43: =Q43*'3 - Il costo opportunità'!$B$10/12 -> 807.66132
A44: C3 | B44: Nuova in contanti cambiata ogni 3 anni | C44: ='2 - Le opzioni'!$L$471 -> 415.59701 | D44: =C44-INDEX('3 - Il costo opportunità'!$C$26:$C$44,MATCH('3 - Il costo opportunità'!$B$6,'3 - Il costo opportunità'!$A$26:$A$44,0)) -> 109.64198 | E44: =SIGN(D44*12)*((((0)*INDEX('3 - Il costo opportunità'!$B$74:$B$134,(10)+1)+(ABS(D44*12))*INDEX('3 - Il costo opportunità'!$C$74:$C$134,(10)+1))-'3 - Il costo opportunità'!$B$8*MAX(0,((0)*INDEX('3 - Il costo opportunità'!$B$74:$B$134,(10)+1)+(ABS(D44*12))*INDEX('3 - Il costo opportunità'!$C$74:$C$134,(10)+1))-((0)+(ABS(D44*12))*INDEX('3 - Il costo opportunità'!$D$74:$D$134,(10)+1))))/(1+'1 - Il tuo profilo'!$B$14)^(10)) -> 14462.045 | F44: =SIGN(D44*12)*((((0)*INDEX('3 - Il costo opportunità'!$B$74:$B$134,('3 - Il costo opportunità'!$B$9)+1)+(ABS(D44*12))*INDEX('3 - Il costo opportunità'!$C$74:$C$134,('3 - Il costo opportunità'!$B$9)+1))-'3 - Il costo opportunità'!$B$8*MAX(0,((0)*INDEX('3 - Il costo opportunità'!$B$74:$B$134,('3 - Il costo opportunità'!$B$9)+1)+(ABS(D44*12))*INDEX('3 - Il costo opportunità'!$C$74:$C$134,('3 - Il costo opportunità'!$B$9)+1))-((0)+(ABS(D44*12))*INDEX('3 - Il costo opportunità'!$D$74:$D$134,('3 - Il costo opportunità'!$B$9)+1))))/(1+'1 - Il tuo profilo'!$B$14)^('3 - Il costo opportunità'!$B$9)) -> 54770.488 | G44: =F44*'3 - Il costo opportunità'!$B$10/12 -> 136.92622 | H44: =('1 - Il tuo profilo'!$B$19+'1 - Il tuo profilo'!$B$20+'1 - Il tuo profilo'!$B$21)+C44*12 -> 24736.034 | I44: ='1 - Il tuo profilo'!$B$18-H44 -> 2590.5659 | J44: =I44/'1 - Il tuo profilo'!$B$18 -> 0.094800154 | K44: =(((('1 - Il tuo profilo'!$B$22)*INDEX('3 - Il costo opportunità'!$B$74:$B$134,('3 - Il costo opportunità'!$B$9)+1)+(I44)*INDEX('3 - Il costo opportunità'!$C$74:$C$134,('3 - Il costo opportunità'!$B$9)+1))-'3 - Il costo opportunità'!$B$8*MAX(0,(('1 - Il tuo profilo'!$B$22)*INDEX('3 - Il costo opportunità'!$B$74:$B$134,('3 - Il costo opportunità'!$B$9)+1)+(I44)*INDEX('3 - Il costo opportunità'!$C$74:$C$134,('3 - Il costo opportunità'!$B$9)+1))-(('1 - Il tuo profilo'!$B$22)+(I44)*INDEX('3 - Il costo opportunità'!$D$74:$D$134,('3 - Il costo opportunità'!$B$9)+1))))/(1+'1 - Il tuo profilo'!$B$14)^('3 - Il costo opportunità'!$B$9)) -> 223558.6 | L44: =K44*'3 - Il costo opportunità'!$B$10/12 -> 558.89651 | N44: =FV('1 - Il tuo profilo'!$B$13,10,-D44*12) -> 15083.069 | O44: =FV('1 - Il tuo profilo'!$B$13,'3 - Il costo opportunità'!$B$9,-D44*12) -> 62595.153 | P44: =O44*'3 - Il costo opportunità'!$B$10/12 -> 156.48788 | Q44: =FV('1 - Il tuo profilo'!$B$13,'3 - Il costo opportunità'!$B$9,-(I44),-('1 - Il tuo profilo'!$B$22)) -> 268883 | R44: =Q44*'3 - Il costo opportunità'!$B$10/12 -> 672.20749
A45: B3 alto = maxirata rinnovata con l'eccedenza persa; B3 basso = con l'eccedenza riconosciuta; C3 = nuova in contanti cambiata ogni 3 anni. Differenze negative = spendi meno del riferimento: capitale in più.
A47: Il confronto del video: usata in contanti contro maxirata rinnovata
A48: Differenza di spesa, €/mese (basso - alto) | B48: =TEXT(D30,"0")&" - "&TEXT(D29,"0")&" €/mese" -> 175 - 228 €/mese
A49: Capitale netto perso a fine accumulo (basso) | B49: =F30-F32 -> 87640.553
A50: Capitale netto perso a fine accumulo (alto) | B50: =F29-F32 -> 113670.61
A51: Entrata netta persa al mese (basso) | B51: ='3 - Il costo opportunità'!$B$49*'3 - Il costo opportunità'!$B$10/12 -> 219.10138
A52: Entrata netta persa al mese (alto) | B52: ='3 - Il costo opportunità'!$B$50*'3 - Il costo opportunità'!$B$10/12 -> 284.17652
A62: Motore del calcolo — non modificare
A63: Calcoli intermedi usati dalle celle verdi qui sopra: si possono leggere, non vanno modificati.
A64: Rendimento nominale annuo | B64: =(1+'1 - Il tuo profilo'!$B$13)*(1+'1 - Il tuo profilo'!$B$14)-1 -> 0.0506
A65: Fattore mensile del rendimento (q) | B65: =(1+'3 - Il costo opportunità'!$B$64)^(1/12) -> 1.0041219
A66: Fattore mensile dell'inflazione (g) | B66: =(1+'1 - Il tuo profilo'!$B$14)^(1/12) -> 1.0016516
A67: Valore a fine anno di 12 versamenti mensili indicizzati da 1/12 | B67: ='3 - Il costo opportunità'!$B$65^12*('3 - Il costo opportunità'!$B$66/'3 - Il costo opportunità'!$B$65)*(1-('3 - Il costo opportunità'!$B$66/'3 - Il costo opportunità'!$B$65)^12)/(1-'3 - Il costo opportunità'!$B$66/'3 - Il costo opportunità'!$B$65)/12 -> 1.0339501
A68: Somma dei 12 versamenti mensili indicizzati da 1/12 | B68: ='3 - Il costo opportunità'!$B$66*('3 - Il costo opportunità'!$B$66^12-1)/('3 - Il costo opportunità'!$B$66-1)/12 -> 1.0108006
A69: Versamento mensile indicizzato all'inflazione, rendimento nominale, bollo pagato a fine anno sul valore, imposta sui guadagni latenti alla fine, tutto riportato in euro di oggi.
A73: Anno | B73: Valore di 1 € iniziale | C73: Valore di 1 €/anno versato | D73: Versato (base fiscale) di 1 €/anno
A74: 0 | B74: 1 | C74: 0 | D74: 0
A75: 1 | B75: =B74*'3 - Il costo opportunità'!$B$65^12*(1-'3 - Il costo opportunità'!$B$7) -> 1.0484988 | C75: =(C74*'3 - Il costo opportunità'!$B$65^12+(1+'1 - Il tuo profilo'!$B$14)^(A75-1)*'3 - Il costo opportunità'!$B$67)*(1-'3 - Il costo opportunità'!$B$7) -> 1.0318822 | D75: =D74+(1+'1 - Il tuo profilo'!$B$14)^(A75-1)*'3 - Il costo opportunità'!$B$68 -> 1.0108006
A76: 2 | B76: =B75*'3 - Il costo opportunità'!$B$65^12*(1-'3 - Il costo opportunità'!$B$7) -> 1.0993497 | C76: =(C75*'3 - Il costo opportunità'!$B$65^12+(1+'1 - Il tuo profilo'!$B$14)^(A76-1)*'3 - Il costo opportunità'!$B$67)*(1-'3 - Il costo opportunità'!$B$7) -> 2.1344472 | D76: =D75+(1+'1 - Il tuo profilo'!$B$14)^(A76-1)*'3 - Il costo opportunità'!$B$68 -> 2.0418171
A77: 3 | B77: =B76*'3 - Il costo opportunità'!$B$65^12*(1-'3 - Il costo opportunità'!$B$7) -> 1.1526669 | C77: =(C76*'3 - Il costo opportunità'!$B$65^12+(1+'1 - Il tuo profilo'!$B$14)^(A77-1)*'3 - Il costo opportunità'!$B$67)*(1-'3 - Il costo opportunità'!$B$7) -> 3.3115356 | D77: =D76+(1+'1 - Il tuo profilo'!$B$14)^(A77-1)*'3 - Il costo opportunità'!$B$68 -> 3.093454
A78: 4 | B78: =B77*'3 - Il costo opportunità'!$B$65^12*(1-'3 - Il costo opportunità'!$B$7) -> 1.2085698 | C78: =(C77*'3 - Il costo opportunità'!$B$65^12+(1+'1 - Il tuo profilo'!$B$14)^(A78-1)*'3 - Il costo opportunità'!$B$67)*(1-'3 - Il costo opportunità'!$B$7) -> 4.5671828 | D78: =D77+(1+'1 - Il tuo profilo'!$B$14)^(A78-1)*'3 - Il costo opportunità'!$B$68 -> 4.1661237
A79: 5 | B79: =B78*'3 - Il costo opportunità'!$B$65^12*(1-'3 - Il costo opportunità'!$B$7) -> 1.267184 | C79: =(C78*'3 - Il costo opportunità'!$B$65^12+(1+'1 - Il tuo profilo'!$B$14)^(A79-1)*'3 - Il costo opportunità'!$B$67)*(1-'3 - Il costo opportunità'!$B$7) -> 5.9056282 | D79: =D78+(1+'1 - Il tuo profilo'!$B$14)^(A79-1)*'3 - Il costo opportunità'!$B$68 -> 5.2602467
A80: 6 | B80: =B79*'3 - Il costo opportunità'!$B$65^12*(1-'3 - Il costo opportunità'!$B$7) -> 1.3286409 | C80: =(C79*'3 - Il costo opportunità'!$B$65^12+(1+'1 - Il tuo profilo'!$B$14)^(A80-1)*'3 - Il costo opportunità'!$B$67)*(1-'3 - Il costo opportunità'!$B$7) -> 7.3313255 | D80: =D79+(1+'1 - Il tuo profilo'!$B$14)^(A80-1)*'3 - Il costo opportunità'!$B$68 -> 6.3762522
A81: 7 | B81: =B80*'3 - Il costo opportunità'!$B$65^12*(1-'3 - Il costo opportunità'!$B$7) -> 1.3930784 | C81: =(C80*'3 - Il costo opportunità'!$B$65^12+(1+'1 - Il tuo profilo'!$B$14)^(A81-1)*'3 - Il costo opportunità'!$B$67)*(1-'3 - Il costo opportunità'!$B$7) -> 8.848953 | D81: =D80+(1+'1 - Il tuo profilo'!$B$14)^(A81-1)*'3 - Il costo opportunità'!$B$68 -> 7.5145778
A82: 8 | B82: =B81*'3 - Il costo opportunità'!$B$65^12*(1-'3 - Il costo opportunità'!$B$7) -> 1.4606411 | C82: =(C81*'3 - Il costo opportunità'!$B$65^12+(1+'1 - Il tuo profilo'!$B$14)^(A82-1)*'3 - Il costo opportunità'!$B$67)*(1-'3 - Il costo opportunità'!$B$7) -> 10.463425 | D82: =D81+(1+'1 - Il tuo profilo'!$B$14)^(A82-1)*'3 - Il costo opportunità'!$B$68 -> 8.6756699
A83: 9 | B83: =B82*'3 - Il costo opportunità'!$B$65^12*(1-'3 - Il costo opportunità'!$B$7) -> 1.5314804 | C83: =(C82*'3 - Il costo opportunità'!$B$65^12+(1+'1 - Il tuo profilo'!$B$14)^(A83-1)*'3 - Il costo opportunità'!$B$67)*(1-'3 - Il costo opportunità'!$B$7) -> 12.179903 | D83: =D82+(1+'1 - Il tuo profilo'!$B$14)^(A83-1)*'3 - Il costo opportunità'!$B$68 -> 9.8599839
A84: 10 | B84: =B83*'3 - Il costo opportunità'!$B$65^12*(1-'3 - Il costo opportunità'!$B$7) -> 1.6057553 | C84: =(C83*'3 - Il costo opportunità'!$B$65^12+(1+'1 - Il tuo profilo'!$B$14)^(A84-1)*'3 - Il costo opportunità'!$B$67)*(1-'3 - Il costo opportunità'!$B$7) -> 14.003809 | D84: =D83+(1+'1 - Il tuo profilo'!$B$14)^(A84-1)*'3 - Il costo opportunità'!$B$68 -> 11.067984
A85: 11 | B85: =B84*'3 - Il costo opportunità'!$B$65^12*(1-'3 - Il costo opportunità'!$B$7) -> 1.6836326 | C85: =(C84*'3 - Il costo opportunità'!$B$65^12+(1+'1 - Il tuo profilo'!$B$14)^(A85-1)*'3 - Il costo opportunità'!$B$67)*(1-'3 - Il costo opportunità'!$B$7) -> 15.940835 | D85: =D84+(1+'1 - Il tuo profilo'!$B$14)^(A85-1)*'3 - Il costo opportunità'!$B$68 -> 12.300144
A86: 12 | B86: =B85*'3 - Il costo opportunità'!$B$65^12*(1-'3 - Il costo opportunità'!$B$7) -> 1.7652867 | C86: =(C85*'3 - Il costo opportunità'!$B$65^12+(1+'1 - Il tuo profilo'!$B$14)^(A86-1)*'3 - Il costo opportunità'!$B$67)*(1-'3 - Il costo opportunità'!$B$7) -> 17.996962 | D86: =D85+(1+'1 - Il tuo profilo'!$B$14)^(A86-1)*'3 - Il costo opportunità'!$B$68 -> 13.556948
... A134: 60 | B134: =B133*'3 - Il costo opportunità'!$B$65^12*(1-'3 - Il costo opportunità'!$B$7) -> 17.142583 | C134: =(C133*'3 - Il costo opportunità'!$B$65^12+(1+'1 - Il tuo profilo'!$B$14)^(A134-1)*'3 - Il costo opportunità'!$B$67)*(1-'3 - Il costo opportunità'!$B$7) -> 501.89797 | D134: =D133+(1+'1 - Il tuo profilo'!$B$14)^(A134-1)*'3 - Il costo opportunità'!$B$68 -> 115.28336

Sheet 4 - Abitudine o contratto
A1: Abitudine o contratto: quanto costa avere sempre l'auto giovane, e quanto il credito
A2: Strumento informativo / divulgativo. NON è consulenza finanziaria. I valori sono indicativi al 2026 e vanno verificati col tuo consulente.
A3: La maxirata rinnovata costa di più dell'usata per tre motivi diversi: cambiare spesso, pagare il credito, lasciare l'eccedenza a chi riprende l'auto. Qui si separano.
A5: Nuova in contanti, cambiata ogni N anni
A6: Ogni quanti anni la cambi | B6: 3
A7: €/mese equivalenti, cambiata ogni N anni | B7: ='2 - Le opzioni'!$L$528 -> 415.59701
A8: Cambiata ogni 3 anni | B8: ='2 - Le opzioni'!$L$471 -> 415.59701
A9: Cambiata ogni 4 anni | B9: ='2 - Le opzioni'!$L$490 -> 397.80007
A10: Cambiata ogni 5 anni | B10: ='2 - Le opzioni'!$L$509 -> 382.27924
A11: Tenuta 10 anni (opzione C) | B11: ='2 - Le opzioni'!$L$129 -> 339.44037
A12: Usata in contanti (opzione D) | B12: ='2 - Le opzioni'!$L$148 -> 305.95503
A14: Maxirata rinnovata contro usata: la scomposizione
A15: Maxirata rinnovata, eccedenza persa (alto) | B15: ='2 - Le opzioni'!$L$300 -> 533.50587
A16: Maxirata rinnovata, eccedenza riconosciuta (basso) | B16: ='2 - Le opzioni'!$L$319 -> 481.39775
A17: Nuova in contanti cambiata a ogni scadenza della maxirata | B17: ='2 - Le opzioni'!$L$547 -> 415.59701
A18: Differenza alto - usata, €/mese | B18: ='4 - Abitudine o contratto'!$B$15-'4 - Abitudine o contratto'!$B$12 -> 227.55084
A19: di cui abitudine (cambiare spesso) | B19: ='4 - Abitudine o contratto'!$B$17-'4 - Abitudine o contratto'!$B$12 -> 109.64198
A20: di cui credito (il contratto) | B20: ='4 - Abitudine o contratto'!$B$16-'4 - Abitudine o contratto'!$B$17 -> 65.800745
A21: di cui eccedenza lasciata | B21: ='4 - Abitudine o contratto'!$B$15-'4 - Abitudine o contratto'!$B$16 -> 52.108113
A22: Differenza basso - usata, €/mese | B22: ='4 - Abitudine o contratto'!$B$16-'4 - Abitudine o contratto'!$B$12 -> 175.44272
A23: Valore di mercato a fine contratto, euro di oggi | B23: ='2 - Le opzioni'!$B$6*IF('2 - Le opzioni'!$B$42>=MAX('2 - Le opzioni'!$B$67:$K$67),0,INDEX('2 - Le opzioni'!$B$68:$K$68,MATCH('2 - Le opzioni'!$B$42,'2 - Le opzioni'!$B$67:$K$67,1))+(INDEX('2 - Le opzioni'!$B$68:$K$68,MATCH('2 - Le opzioni'!$B$42,'2 - Le opzioni'!$B$67:$K$67,1)+1)-INDEX('2 - Le opzioni'!$B$68:$K$68,MATCH('2 - Le opzioni'!$B$42,'2 - Le opzioni'!$B$67:$K$67,1)))*('2 - Le opzioni'!$B$42-INDEX('2 - Le opzioni'!$B$67:$K$67,MATCH('2 - Le opzioni'!$B$42,'2 - Le opzioni'!$B$67:$K$67,1)))/(INDEX('2 - Le opzioni'!$B$67:$K$67,MATCH('2 - Le opzioni'!$B$42,'2 - Le opzioni'!$B$67:$K$67,1)+1)-INDEX('2 - Le opzioni'!$B$67:$K$67,MATCH('2 - Le opzioni'!$B$42,'2 - Le opzioni'!$B$67:$K$67,1)))) -> 11780
A24: Eccedenza lasciata per ciclo, euro di oggi | B24: ='4 - Abitudine o contratto'!$B$23-'2 - Le opzioni'!$B$41/(1+'1 - Il tuo profilo'!$B$14)^'2 - Le opzioni'!$B$42 -> 1932.7316
A26: Il contratto «da 199 € al mese» (esempio anonimo)
A27: Prezzo dell'auto | B27: 19000
A28: Anticipo | B28: 4000
A29: Mesi | B29: 36
A30: Rata finale, % del prezzo | B30: 0.55
A31: TAN | B31: 0.0599
A32: Spese di istruttoria | B32: 300
A33: Servizi accessori, € al mese | B33: 9
A34: Rata finale | B34: ='4 - Abitudine o contratto'!$B$27*'4 - Abitudine o contratto'!$B$30 -> 10450
A35: Rata finanziaria | B35: =-PMT('4 - Abitudine o contratto'!$B$31/12,'4 - Abitudine o contratto'!$B$29,'4 - Abitudine o contratto'!$B$27-'4 - Abitudine o contratto'!$B$28,-'4 - Abitudine o contratto'!$B$34) -> 190.56212
A36: Rata pubblicizzata (con i servizi) | B36: ='4 - Abitudine o contratto'!$B$35+'4 - Abitudine o contratto'!$B$33 -> 199.56212
A37: TAEG senza servizi | B37: =(1+RATE('4 - Abitudine o contratto'!$B$29,-'4 - Abitudine o contratto'!$B$35,'4 - Abitudine o contratto'!$B$27-'4 - Abitudine o contratto'!$B$28-'4 - Abitudine o contratto'!$B$32,-'4 - Abitudine o contratto'!$B$34))^12-1 -> 0.070665724
A38: TAEG con i servizi | B38: =(1+RATE('4 - Abitudine o contratto'!$B$29,-'4 - Abitudine o contratto'!$B$36,'4 - Abitudine o contratto'!$B$27-'4 - Abitudine o contratto'!$B$28-'4 - Abitudine o contratto'!$B$32,-'4 - Abitudine o contratto'!$B$34))^12-1 -> 0.079691713
A39: Quanto esce prima della rata finale | B39: ='4 - Abitudine o contratto'!$B$28+'4 - Abitudine o contratto'!$B$32+'4 - Abitudine o contratto'!$B$29*'4 - Abitudine o contratto'!$B$36 -> 11484.236
A40: Media al mese prima della rata finale | B40: ='4 - Abitudine o contratto'!$B$39/'4 - Abitudine o contratto'!$B$29 -> 319.00656
A41: Interessi, spese e servizi | B41: ='4 - Abitudine o contratto'!$B$39+'4 - Abitudine o contratto'!$B$34-'4 - Abitudine o contratto'!$B$27 -> 2934.2362
A42: di cui interessi | B42: ='4 - Abitudine o contratto'!$B$29*'4 - Abitudine o contratto'!$B$35+'4 - Abitudine o contratto'!$B$34-('4 - Abitudine o contratto'!$B$27-'4 - Abitudine o contratto'!$B$28) -> 2310.2362
A44: Finanziamento classico: la rata non è il costo
A45: Rata mensile | B45: ='2 - Le opzioni'!$B$77 -> 333.0663
A46: Interessi nominali | B46: ='2 - Le opzioni'!$B$77*'2 - Le opzioni'!$B$38-('2 - Le opzioni'!$B$6-'1 - Il tuo profilo'!$B$33) -> 3983.9777
A47: Primo anno di cassa (rate in euro di oggi + gestione) | B47: ='2 - Le opzioni'!$B$77*PV('2 - Le opzioni'!$B$111,12,-1)+'2 - Le opzioni'!$L$212 -> 6387.1839
A48: Primo anno di cassa, al mese | B48: ='4 - Abitudine o contratto'!$B$47/12 -> 532.26532
A49: Costo vero, €/mese equivalenti | B49: ='2 - Le opzioni'!$L$224 -> 358.70959
A51: Tenerla o cambiarla: la soglia dell'officina
A52: Manutenzione e guasti dell'auto di oggi che pareggiano l'usata, €/anno | B52: ='2 - Le opzioni'!$K$148-('2 - Le opzioni'!$I$376-'2 - Le opzioni'!$G$378)/'2 - Le opzioni'!$B$112 -> 1647.6255 | C52: Se nei prossimi 10 anni l'auto di oggi ti costa in media meno di così, tenerla costa meno dell'usata
A53: Media ipotizzata nel foglio 2 | B53: =SUM('2 - Le opzioni'!F364:F373)/10 -> 1850
A54: Un guasto da 2.000 €, spalmato su 10 anni, €/mese | B54: =2000/(1+'1 - Il tuo profilo'!$B$13)^5/'2 - Le opzioni'!$B$112/12 -> 16.854011 | C54: Guasto a metà strada (anno 5)

Sheet 5 - Senza auto
A1: Senza auto: quanto costa muoversi con abbonamento, noleggi e qualche taxi
A2: Strumento informativo / divulgativo. NON è consulenza finanziaria. I valori sono indicativi al 2026 e vanno verificati col tuo consulente.
A3: Tariffe unitarie da pagine ufficiali di operatori di trasporto e di car sharing (F-15, F-16, F-19, mai nominati); le quantità sono ipotesi. Il tempo in più non è prezzato.
A5: Tariffe di noleggio a ore e a giornata
A6: Noleggio a giornata, € | B6: 45 | C6: Tariffa giornaliera con 30 km inclusi (F-19)
A7: Km inclusi nella giornata | B7: 30
A8: € per km oltre quelli inclusi (e nel noleggio a ore) | B8: 0.25
A9: Km di una gita in giornata | B9: 150
A10: Noleggio a ore, € all'ora | B10: 9 | C10: F-19
A11: Km di un'uscita da un'ora | B11: 15
A12: Costo di una giornata di noleggio | B12: ='5 - Senza auto'!$B$6+'5 - Senza auto'!$B$8*MAX(0,'5 - Senza auto'!$B$9-'5 - Senza auto'!$B$7) -> 75
A13: Costo di un'uscita da un'ora | B13: ='5 - Senza auto'!$B$10+'5 - Senza auto'!$B$8*'5 - Senza auto'!$B$11 -> 12.75
A15: Tre profili (quantità all'anno, ipotesi)
A16: Voce | B16: Grande città | C16: Città media | D16: Provincia
A17: Abbonamento ai mezzi pubblici, €/anno | B17: 330 | C17: 600 | D17: 900
A18: Giornate di noleggio all'anno | B18: 10 | C18: 12 | D18: 24
A19: Ore di noleggio all'anno | B19: 12 | C19: 24 | D19: 0
A20: Treni, taxi, passaggi e consegne, €/anno | B20: 500 | C20: 600 | D20: 1500
A21: Grande città: abbonamento urbano annuale di circa 310-330 € (F-15, F-16). Città media: extraurbano per 18 km (ipotesi). Provincia: corse rare, più taxi e passaggi.
A23: Quanto costa senza auto
A24: Confronta con l'opzione | B24: D
A25: Risultato | B25: Grande città | C25: Città media | D25: Provincia
A26: Costo annuo | B26: ='5 - Senza auto'!$B$17+'5 - Senza auto'!$B$18*'5 - Senza auto'!$B$12+'5 - Senza auto'!$B$19*'5 - Senza auto'!$B$13+'5 - Senza auto'!$B$20 -> 1733 | C26: ='5 - Senza auto'!$C$17+'5 - Senza auto'!$C$18*'5 - Senza auto'!$B$12+'5 - Senza auto'!$C$19*'5 - Senza auto'!$B$13+'5 - Senza auto'!$C$20 -> 2406 | D26: ='5 - Senza auto'!$D$17+'5 - Senza auto'!$D$18*'5 - Senza auto'!$B$12+'5 - Senza auto'!$D$19*'5 - Senza auto'!$B$13+'5 - Senza auto'!$D$20 -> 4200
A27: Costo al mese | B27: =B26/12 -> 144.41667 | C27: =C26/12 -> 200.5 | D27: =D26/12 -> 350
A28: €/mese equivalenti (con l'incasso dell'auto di oggi) | B28: ='2 - Le opzioni'!$L$433 -> 115.10904 | C28: ='2 - Le opzioni'!$L$414 -> 171.19237 | D28: ='2 - Le opzioni'!$L$452 -> 320.69237
A29: Margine sull'opzione scelta, €/mese | B29: =INDEX('2 - Le opzioni'!$F$84:$F$100,MATCH('5 - Senza auto'!$B$24,'2 - Le opzioni'!$A$84:$A$100,0))-B28 -> 190.84599 | C29: =INDEX('2 - Le opzioni'!$F$84:$F$100,MATCH('5 - Senza auto'!$B$24,'2 - Le opzioni'!$A$84:$A$100,0))-C28 -> 134.76266 | D29: =INDEX('2 - Le opzioni'!$F$84:$F$100,MATCH('5 - Senza auto'!$B$24,'2 - Le opzioni'!$A$84:$A$100,0))-D28 -> -14.737345
A30: Giornate di noleggio in più che il margine paga, all'anno | B30: =B29*12/'5 - Senza auto'!$B$12 -> 30.535358 | C30: =C29*12/'5 - Senza auto'!$B$12 -> 21.562025 | D30: =D29*12/'5 - Senza auto'!$B$12 -> -2.3579751
A31: Il costo equivalente è più basso del costo annuo perché vendere l'auto di oggi porta un incasso una tantum. Il tempo in più sui mezzi non è contato.

Sheet 6 - Elettrico o termico
A1: Elettrico o termico: da quanti chilometri l'anno l'elettrica costa meno
A2: Strumento informativo / divulgativo. NON è consulenza finanziaria. I valori sono indicativi al 2026 e vanno verificati col tuo consulente.
A3: Nuova benzina contro nuova elettrica, comprate in contanti e tenute 10 anni. Assicurazione e revisione sono uguali e si annullano. Manutenzione, curve dei residui e regole del bollo vengono dal foglio 2.
A5: Le due auto
A6: Benzina: prezzo | B6: 19000
A7: Benzina: consumo, litri per 100 km | B7: 5.6
A8: Benzina: potenza, kW | B8: 70
A9: Elettrica: prezzo | B9: 26000
A10: Incentivo all'acquisto dell'elettrica | B10: 0 | C10: Nazionale: nessuno a ottobre 2026 (F-10, F-11). Regionale: da verificare sul sito della tua Regione
A11: Elettrica: consumo alla presa, kWh per 100 km | B11: 17
A12: Elettrica: potenza, kW | B12: 85
A14: Energia
A15: Benzina, €/litro | B15: 1.84995 | C15: Media 2026 al 05/10/2026 (F-03)
A16: Elettricità a casa, €/kWh | B16: 0.2966 | C16: F-08
A17: Ricarica alla colonnina, €/kWh | B17: 0.6 | C17: Ipotesi, banda 0,45-0,80
A18: Quota di ricarica alla colonnina | B18: 0.1
A20: Risultato
A21: Differenza di valore attuale in 10 anni (elettrica − benzina) ai tuoi km | B21: ='6 - Elettrico o termico'!$B$74+('2 - Le opzioni'!$B$112*('6 - Elettrico o termico'!$B$11/100*((1-('6 - Elettrico o termico'!$B$18))*'6 - Elettrico o termico'!$B$16+('6 - Elettrico o termico'!$B$18)*('6 - Elettrico o termico'!$B$17))-'6 - Elettrico o termico'!$B$7/100*'6 - Elettrico o termico'!$B$15)+'6 - Elettrico o termico'!$B$75)*'1 - Il tuo profilo'!$B$9 -> -665.25695 | C21: Negativa = l'elettrica costa meno
A22: Km all'anno di pareggio | B22: =IF(AND('6 - Elettrico o termico'!$B$74>0,('2 - Le opzioni'!$B$112*('6 - Elettrico o termico'!$B$11/100*((1-('6 - Elettrico o termico'!$B$18))*'6 - Elettrico o termico'!$B$16+('6 - Elettrico o termico'!$B$18)*('6 - Elettrico o termico'!$B$17))-'6 - Elettrico o termico'!$B$7/100*'6 - Elettrico o termico'!$B$15)+'6 - Elettrico o termico'!$B$75)<0),-'6 - Elettrico o termico'!$B$74/('2 - Le opzioni'!$B$112*('6 - Elettrico o termico'!$B$11/100*((1-('6 - Elettrico o termico'!$B$18))*'6 - Elettrico o termico'!$B$16+('6 - Elettrico o termico'!$B$18)*('6 - Elettrico o termico'!$B$17))-'6 - Elettrico o termico'!$B$7/100*'6 - Elettrico o termico'!$B$15)+'6 - Elettrico o termico'!$B$75),IF(AND('6 - Elettrico o termico'!$B$74<=0,('2 - Le opzioni'!$B$112*('6 - Elettrico o termico'!$B$11/100*((1-('6 - Elettrico o termico'!$B$18))*'6 - Elettrico o termico'!$B$16+('6 - Elettrico o termico'!$B$18)*('6 - Elettrico o termico'!$B$17))-'6 - Elettrico o termico'!$B$7/100*'6 - Elettrico o termico'!$B$15)+'6 - Elettrico o termico'!$B$75)<=0),"sempre",IF(AND('6 - Elettrico o termico'!$B$74>0,('2 - Le opzioni'!$B$112*('6 - Elettrico o termico'!$B$11/100*((1-('6 - Elettrico o termico'!$B$18))*'6 - Elettrico o termico'!$B$16+('6 - Elettrico o termico'!$B$18)*('6 - Elettrico o termico'!$B$17))-'6 - Elettrico o termico'!$B$7/100*'6 - Elettrico o termico'!$B$15)+'6 - Elettrico o termico'!$B$75)>=0),"mai","sotto "&ROUND(-'6 - Elettrico o termico'!$B$74/('2 - Le opzioni'!$B$112*('6 - Elettrico o termico'!$B$11/100*((1-('6 - Elettrico o termico'!$B$18))*'6 - Elettrico o termico'!$B$16+('6 - Elettrico o termico'!$B$18)*('6 - Elettrico o termico'!$B$17))-'6 - Elettrico o termico'!$B$7/100*'6 - Elettrico o termico'!$B$15)+'6 - Elettrico o termico'!$B$75),0)&" km"))) -> 10594.607 | C22: Sopra questi km l'elettrica costa meno
A24: Km di pareggio per quota di ricarica alla colonnina e prezzo della colonnina
A25: Quota alla colonnina | B25: 0.45 | C25: 0.6 | D25: 0.8
A26: 0.1 | B26: =IF(AND('6 - Elettrico o termico'!$B$74>0,('2 - Le opzioni'!$B$112*('6 - Elettrico o termico'!$B$11/100*((1-($A26))*'6 - Elettrico o termico'!$B$16+($A26)*(B$25))-'6 - Elettrico o termico'!$B$7/100*'6 - Elettrico o termico'!$B$15)+'6 - Elettrico o termico'!$B$75)<0),-'6 - Elettrico o termico'!$B$74/('2 - Le opzioni'!$B$112*('6 - Elettrico o termico'!$B$11/100*((1-($A26))*'6 - Elettrico o termico'!$B$16+($A26)*(B$25))-'6 - Elettrico o termico'!$B$7/100*'6 - Elettrico o termico'!$B$15)+'6 - Elettrico o termico'!$B$75),IF(AND('6 - Elettrico o termico'!$B$74<=0,('2 - Le opzioni'!$B$112*('6 - Elettrico o termico'!$B$11/100*((1-($A26))*'6 - Elettrico o termico'!$B$16+($A26)*(B$25))-'6 - Elettrico o termico'!$B$7/100*'6 - Elettrico o termico'!$B$15)+'6 - Elettrico o termico'!$B$75)<=0),"sempre",IF(AND('6 - Elettrico o termico'!$B$74>0,('2 - Le opzioni'!$B$112*('6 - Elettrico o termico'!$B$11/100*((1-($A26))*'6 - Elettrico o termico'!$B$16+($A26)*(B$25))-'6 - Elettrico o termico'!$B$7/100*'6 - Elettrico o termico'!$B$15)+'6 - Elettrico o termico'!$B$75)>=0),"mai","sotto "&ROUND(-'6 - Elettrico o termico'!$B$74/('2 - Le opzioni'!$B$112*('6 - Elettrico o termico'!$B$11/100*((1-($A26))*'6 - Elettrico o termico'!$B$16+($A26)*(B$25))-'6 - Elettrico o termico'!$B$7/100*'6 - Elettrico o termico'!$B$15)+'6 - Elettrico o termico'!$B$75),0)&" km"))) -> 10129.148 | C26: =IF(AND('6 - Elettrico o termico'!$B$74>0,('2 - Le opzioni'!$B$112*('6 - Elettrico o termico'!$B$11/100*((1-($A26))*'6 - Elettrico o termico'!$B$16+($A26)*(C$25))-'6 - Elettrico o termico'!$B$7/100*'6 - Elettrico o termico'!$B$15)+'6 - Elettrico o termico'!$B$75)<0),-'6 - Elettrico o termico'!$B$74/('2 - Le opzioni'!$B$112*('6 - Elettrico o termico'!$B$11/100*((1-($A26))*'6 - Elettrico o termico'!$B$16+($A26)*(C$25))-'6 - Elettrico o termico'!$B$7/100*'6 - Elettrico o termico'!$B$15)+'6 - Elettrico o termico'!$B$75),IF(AND('6 - Elettrico o termico'!$B$74<=0,('2 - Le opzioni'!$B$112*('6 - Elettrico o termico'!$B$11/100*((1-($A26))*'6 - Elettrico o termico'!$B$16+($A26)*(C$25))-'6 - Elettrico o termico'!$B$7/100*'6 - Elettrico o termico'!$B$15)+'6 - Elettrico o termico'!$B$75)<=0),"sempre",IF(AND('6 - Elettrico o termico'!$B$74>0,('2 - Le opzioni'!$B$112*('6 - Elettrico o termico'!$B$11/100*((1-($A26))*'6 - Elettrico o termico'!$B$16+($A26)*(C$25))-'6 - Elettrico o termico'!$B$7/100*'6 - Elettrico o termico'!$B$15)+'6 - Elettrico o termico'!$B$75)>=0),"mai","sotto "&ROUND(-'6 - Elettrico o termico'!$B$74/('2 - Le opzioni'!$B$112*('6 - Elettrico o termico'!$B$11/100*((1-($A26))*'6 - Elettrico o termico'!$B$16+($A26)*(C$25))-'6 - Elettrico o termico'!$B$7/100*'6 - Elettrico o termico'!$B$15)+'6 - Elettrico o termico'!$B$75),0)&" km"))) -> 10594.607 | D26: =IF(AND('6 - Elettrico o termico'!$B$74>0,('2 - Le opzioni'!$B$112*('6 - Elettrico o termico'!$B$11/100*((1-($A26))*'6 - Elettrico o termico'!$B$16+($A26)*(D$25))-'6 - Elettrico o termico'!$B$7/100*'6 - Elettrico o termico'!$B$15)+'6 - Elettrico o termico'!$B$75)<0),-'6 - Elettrico o termico'!$B$74/('2 - Le opzioni'!$B$112*('6 - Elettrico o termico'!$B$11/100*((1-($A26))*'6 - Elettrico o termico'!$B$16+($A26)*(D$25))-'6 - Elettrico o termico'!$B$7/100*'6 - Elettrico o termico'!$B$15)+'6 - Elettrico o termico'!$B$75),IF(AND('6 - Elettrico o termico'!$B$74<=0,('2 - Le opzioni'!$B$112*('6 - Elettrico o termico'!$B$11/100*((1-($A26))*'6 - Elettrico o termico'!$B$16+($A26)*(D$25))-'6 - Elettrico o termico'!$B$7/100*'6 - Elettrico o termico'!$B$15)+'6 - Elettrico o termico'!$B$75)<=0),"sempre",IF(AND('6 - Elettrico o termico'!$B$74>0,('2 - Le opzioni'!$B$112*('6 - Elettrico o termico'!$B$11/100*((1-($A26))*'6 - Elettrico o termico'!$B$16+($A26)*(D$25))-'6 - Elettrico o termico'!$B$7/100*'6 - Elettrico o termico'!$B$15)+'6 - Elettrico o termico'!$B$75)>=0),"mai","sotto "&ROUND(-'6 - Elettrico o termico'!$B$74/('2 - Le opzioni'!$B$112*('6 - Elettrico o termico'!$B$11/100*((1-($A26))*'6 - Elettrico o termico'!$B$16+($A26)*(D$25))-'6 - Elettrico o termico'!$B$7/100*'6 - Elettrico o termico'!$B$15)+'6 - Elettrico o termico'!$B$75),0)&" km"))) -> 11286.104
A27: 0.5 | B27: =IF(AND('6 - Elettrico o termico'!$B$74>0,('2 - Le opzioni'!$B$112*('6 - Elettrico o termico'!$B$11/100*((1-($A27))*'6 - Elettrico o termico'!$B$16+($A27)*(B$25))-'6 - Elettrico o termico'!$B$7/100*'6 - Elettrico o termico'!$B$15)+'6 - Elettrico o termico'!$B$75)<0),-'6 - Elettrico o termico'!$B$74/('2 - Le opzioni'!$B$112*('6 - Elettrico o termico'!$B$11/100*((1-($A27))*'6 - Elettrico o termico'!$B$16+($A27)*(B$25))-'6 - Elettrico o termico'!$B$7/100*'6 - Elettrico o termico'!$B$15)+'6 - Elettrico o termico'!$B$75),IF(AND('6 - Elettrico o termico'!$B$74<=0,('2 - Le opzioni'!$B$112*('6 - Elettrico o termico'!$B$11/100*((1-($A27))*'6 - Elettrico o termico'!$B$16+($A27)*(B$25))-'6 - Elettrico o termico'!$B$7/100*'6 - Elettrico o termico'!$B$15)+'6 - Elettrico o termico'!$B$75)<=0),"sempre",IF(AND('6 - Elettrico o termico'!$B$74>0,('2 - Le opzioni'!$B$112*('6 - Elettrico o termico'!$B$11/100*((1-($A27))*'6 - Elettrico o termico'!$B$16+($A27)*(B$25))-'6 - Elettrico o termico'!$B$7/100*'6 - Elettrico o termico'!$B$15)+'6 - Elettrico o termico'!$B$75)>=0),"mai","sotto "&ROUND(-'6 - Elettrico o termico'!$B$74/('2 - Le opzioni'!$B$112*('6 - Elettrico o termico'!$B$11/100*((1-($A27))*'6 - Elettrico o termico'!$B$16+($A27)*(B$25))-'6 - Elettrico o termico'!$B$7/100*'6 - Elettrico o termico'!$B$15)+'6 - Elettrico o termico'!$B$75),0)&" km"))) -> 12348.364 | C27: =IF(AND('6 - Elettrico o termico'!$B$74>0,('2 - Le opzioni'!$B$112*('6 - Elettrico o termico'!$B$11/100*((1-($A27))*'6 - Elettrico o termico'!$B$16+($A27)*(C$25))-'6 - Elettrico o termico'!$B$7/100*'6 - Elettrico o termico'!$B$15)+'6 - Elettrico o termico'!$B$75)<0),-'6 - Elettrico o termico'!$B$74/('2 - Le opzioni'!$B$112*('6 - Elettrico o termico'!$B$11/100*((1-($A27))*'6 - Elettrico o termico'!$B$16+($A27)*(C$25))-'6 - Elettrico o termico'!$B$7/100*'6 - Elettrico o termico'!$B$15)+'6 - Elettrico o termico'!$B$75),IF(AND('6 - Elettrico o termico'!$B$74<=0,('2 - Le opzioni'!$B$112*('6 - Elettrico o termico'!$B$11/100*((1-($A27))*'6 - Elettrico o termico'!$B$16+($A27)*(C$25))-'6 - Elettrico o termico'!$B$7/100*'6 - Elettrico o termico'!$B$15)+'6 - Elettrico o termico'!$B$75)<=0),"sempre",IF(AND('6 - Elettrico o termico'!$B$74>0,('2 - Le opzioni'!$B$112*('6 - Elettrico o termico'!$B$11/100*((1-($A27))*'6 - Elettrico o termico'!$B$16+($A27)*(C$25))-'6 - Elettrico o termico'!$B$7/100*'6 - Elettrico o termico'!$B$15)+'6 - Elettrico o termico'!$B$75)>=0),"mai","sotto "&ROUND(-'6 - Elettrico o termico'!$B$74/('2 - Le opzioni'!$B$112*('6 - Elettrico o termico'!$B$11/100*((1-($A27))*'6 - Elettrico o termico'!$B$16+($A27)*(C$25))-'6 - Elettrico o termico'!$B$7/100*'6 - Elettrico o termico'!$B$15)+'6 - Elettrico o termico'!$B$75),0)&" km"))) -> 16864.629 | D27: =IF(AND('6 - Elettrico o termico'!$B$74>0,('2 - Le opzioni'!$B$112*('6 - Elettrico o termico'!$B$11/100*((1-($A27))*'6 - Elettrico o termico'!$B$16+($A27)*(D$25))-'6 - Elettrico o termico'!$B$7/100*'6 - Elettrico o termico'!$B$15)+'6 - Elettrico o termico'!$B$75)<0),-'6 - Elettrico o termico'!$B$74/('2 - Le opzioni'!$B$112*('6 - Elettrico o termico'!$B$11/100*((1-($A27))*'6 - Elettrico o termico'!$B$16+($A27)*(D$25))-'6 - Elettrico o termico'!$B$7/100*'6 - Elettrico o termico'!$B$15)+'6 - Elettrico o termico'!$B$75),IF(AND('6 - Elettrico o termico'!$B$74<=0,('2 - Le opzioni'!$B$112*('6 - Elettrico o termico'!$B$11/100*((1-($A27))*'6 - Elettrico o termico'!$B$16+($A27)*(D$25))-'6 - Elettrico o termico'!$B$7/100*'6 - Elettrico o termico'!$B$15)+'6 - Elettrico o termico'!$B$75)<=0),"sempre",IF(AND('6 - Elettrico o termico'!$B$74>0,('2 - Le opzioni'!$B$112*('6 - Elettrico o termico'!$B$11/100*((1-($A27))*'6 - Elettrico o termico'!$B$16+($A27)*(D$25))-'6 - Elettrico o termico'!$B$7/100*'6 - Elettrico o termico'!$B$15)+'6 - Elettrico o termico'!$B$75)>=0),"mai","sotto "&ROUND(-'6 - Elettrico o termico'!$B$74/('2 - Le opzioni'!$B$112*('6 - Elettrico o termico'!$B$11/100*((1-($A27))*'6 - Elettrico o termico'!$B$16+($A27)*(D$25))-'6 - Elettrico o termico'!$B$7/100*'6 - Elettrico o termico'!$B$15)+'6 - Elettrico o termico'!$B$75),0)&" km"))) -> 32916.263
A28: 0.8 | B28: =IF(AND('6 - Elettrico o termico'!$B$74>0,('2 - Le opzioni'!$B$112*('6 - Elettrico o termico'!$B$11/100*((1-($A28))*'6 - Elettrico o termico'!$B$16+($A28)*(B$25))-'6 - Elettrico o termico'!$B$7/100*'6 - Elettrico o termico'!$B$15)+'6 - Elettrico o termico'!$B$75)<0),-'6 - Elettrico o termico'!$B$74/('2 - Le opzioni'!$B$112*('6 - Elettrico o termico'!$B$11/100*((1-($A28))*'6 - Elettrico o termico'!$B$16+($A28)*(B$25))-'6 - Elettrico o termico'!$B$7/100*'6 - Elettrico o termico'!$B$15)+'6 - Elettrico o termico'!$B$75),IF(AND('6 - Elettrico o termico'!$B$74<=0,('2 - Le opzioni'!$B$112*('6 - Elettrico o termico'!$B$11/100*((1-($A28))*'6 - Elettrico o termico'!$B$16+($A28)*(B$25))-'6 - Elettrico o termico'!$B$7/100*'6 - Elettrico o termico'!$B$15)+'6 - Elettrico o termico'!$B$75)<=0),"sempre",IF(AND('6 - Elettrico o termico'!$B$74>0,('2 - Le opzioni'!$B$112*('6 - Elettrico o termico'!$B$11/100*((1-($A28))*'6 - Elettrico o termico'!$B$16+($A28)*(B$25))-'6 - Elettrico o termico'!$B$7/100*'6 - Elettrico o termico'!$B$15)+'6 - Elettrico o termico'!$B$75)>=0),"mai","sotto "&ROUND(-'6 - Elettrico o termico'!$B$74/('2 - Le opzioni'!$B$112*('6 - Elettrico o termico'!$B$11/100*((1-($A28))*'6 - Elettrico o termico'!$B$16+($A28)*(B$25))-'6 - Elettrico o termico'!$B$7/100*'6 - Elettrico o termico'!$B$15)+'6 - Elettrico o termico'!$B$75),0)&" km"))) -> 14776.41 | C28: =IF(AND('6 - Elettrico o termico'!$B$74>0,('2 - Le opzioni'!$B$112*('6 - Elettrico o termico'!$B$11/100*((1-($A28))*'6 - Elettrico o termico'!$B$16+($A28)*(C$25))-'6 - Elettrico o termico'!$B$7/100*'6 - Elettrico o termico'!$B$15)+'6 - Elettrico o termico'!$B$75)<0),-'6 - Elettrico o termico'!$B$74/('2 - Le opzioni'!$B$112*('6 - Elettrico o termico'!$B$11/100*((1-($A28))*'6 - Elettrico o termico'!$B$16+($A28)*(C$25))-'6 - Elettrico o termico'!$B$7/100*'6 - Elettrico o termico'!$B$15)+'6 - Elettrico o termico'!$B$75),IF(AND('6 - Elettrico o termico'!$B$74<=0,('2 - Le opzioni'!$B$112*('6 - Elettrico o termico'!$B$11/100*((1-($A28))*'6 - Elettrico o termico'!$B$16+($A28)*(C$25))-'6 - Elettrico o termico'!$B$7/100*'6 - Elettrico o termico'!$B$15)+'6 - Elettrico o termico'!$B$75)<=0),"sempre",IF(AND('6 - Elettrico o termico'!$B$74>0,('2 - Le opzioni'!$B$112*('6 - Elettrico o termico'!$B$11/100*((1-($A28))*'6 - Elettrico o termico'!$B$16+($A28)*(C$25))-'6 - Elettrico o termico'!$B$7/100*'6 - Elettrico o termico'!$B$15)+'6 - Elettrico o termico'!$B$75)>=0),"mai","sotto "&ROUND(-'6 - Elettrico o termico'!$B$74/('2 - Le opzioni'!$B$112*('6 - Elettrico o termico'!$B$11/100*((1-($A28))*'6 - Elettrico o termico'!$B$16+($A28)*(C$25))-'6 - Elettrico o termico'!$B$7/100*'6 - Elettrico o termico'!$B$15)+'6 - Elettrico o termico'!$B$75),0)&" km"))) -> 30324.406 | D28: =IF(AND('6 - Elettrico o termico'!$B$74>0,('2 - Le opzioni'!$B$112*('6 - Elettrico o termico'!$B$11/100*((1-($A28))*'6 - Elettrico o termico'!$B$16+($A28)*(D$25))-'6 - Elettrico o termico'!$B$7/100*'6 - Elettrico o termico'!$B$15)+'6 - Elettrico o termico'!$B$75)<0),-'6 - Elettrico o termico'!$B$74/('2 - Le opzioni'!$B$112*('6 - Elettrico o termico'!$B$11/100*((1-($A28))*'6 - Elettrico o termico'!$B$16+($A28)*(D$25))-'6 - Elettrico o termico'!$B$7/100*'6 - Elettrico o termico'!$B$15)+'6 - Elettrico o termico'!$B$75),IF(AND('6 - Elettrico o termico'!$B$74<=0,('2 - Le opzioni'!$B$112*('6 - Elettrico o termico'!$B$11/100*((1-($A28))*'6 - Elettrico o termico'!$B$16+($A28)*(D$25))-'6 - Elettrico o termico'!$B$7/100*'6 - Elettrico o termico'!$B$15)+'6 - Elettrico o termico'!$B$75)<=0),"sempre",IF(AND('6 - Elettrico o termico'!$B$74>0,('2 - Le opzioni'!$B$112*('6 - Elettrico o termico'!$B$11/100*((1-($A28))*'6 - Elettrico o termico'!$B$16+($A28)*(D$25))-'6 - Elettrico o termico'!$B$7/100*'6 - Elettrico o termico'!$B$15)+'6 - Elettrico o termico'!$B$75)>=0),"mai","sotto "&ROUND(-'6 - Elettrico o termico'!$B$74/('2 - Le opzioni'!$B$112*('6 - Elettrico o termico'!$B$11/100*((1-($A28))*'6 - Elettrico o termico'!$B$16+($A28)*(D$25))-'6 - Elettrico o termico'!$B$7/100*'6 - Elettrico o termico'!$B$15)+'6 - Elettrico o termico'!$B$75),0)&" km"))) -> mai
A29: Il prezzo della colonnina non ha una fonte primaria: per questo la tabella mostra tre prezzi.
A31: Differenza di valore attuale per km all'anno (elettrica − benzina, quota e prezzi qui sopra)
A32: Km all'anno | B32: Differenza | C32: Costa meno | E32: Km all'anno | F32: Differenza | G32: Costa meno | I32: Km all'anno | J32: Differenza | K32: Costa meno
A33: 1000 | B33: ='6 - Elettrico o termico'!$B$74+('2 - Le opzioni'!$B$112*('6 - Elettrico o termico'!$B$11/100*((1-('6 - Elettrico o termico'!$B$18))*'6 - Elettrico o termico'!$B$16+('6 - Elettrico o termico'!$B$18)*('6 - Elettrico o termico'!$B$17))-'6 - Elettrico o termico'!$B$7/100*'6 - Elettrico o termico'!$B$15)+'6 - Elettrico o termico'!$B$75)*A33 -> 4541.7027 | C33: =IF(B33<0,"elettrica","benzina") -> benzina | E33: 21000 | F33: ='6 - Elettrico o termico'!$B$74+('2 - Le opzioni'!$B$112*('6 - Elettrico o termico'!$B$11/100*((1-('6 - Elettrico o termico'!$B$18))*'6 - Elettrico o termico'!$B$16+('6 - Elettrico o termico'!$B$18)*('6 - Elettrico o termico'!$B$17))-'6 - Elettrico o termico'!$B$7/100*'6 - Elettrico o termico'!$B$15)+'6 - Elettrico o termico'!$B$75)*E33 -> -4925.4967 | G33: =IF(F33<0,"elettrica","benzina") -> elettrica | I33: 41000 | J33: ='6 - Elettrico o termico'!$B$74+('2 - Le opzioni'!$B$112*('6 - Elettrico o termico'!$B$11/100*((1-('6 - Elettrico o termico'!$B$18))*'6 - Elettrico o termico'!$B$16+('6 - Elettrico o termico'!$B$18)*('6 - Elettrico o termico'!$B$17))-'6 - Elettrico o termico'!$B$7/100*'6 - Elettrico o termico'!$B$15)+'6 - Elettrico o termico'!$B$75)*I33 -> -14392.696 | K33: =IF(J33<0,"elettrica","benzina") -> elettrica
A34: 2000 | B34: ='6 - Elettrico o termico'!$B$74+('2 - Le opzioni'!$B$112*('6 - Elettrico o termico'!$B$11/100*((1-('6 - Elettrico o termico'!$B$18))*'6 - Elettrico o termico'!$B$16+('6 - Elettrico o termico'!$B$18)*('6 - Elettrico o termico'!$B$17))-'6 - Elettrico o termico'!$B$7/100*'6 - Elettrico o termico'!$B$15)+'6 - Elettrico o termico'!$B$75)*A34 -> 4068.3428 | C34: =IF(B34<0,"elettrica","benzina") -> benzina | E34: 22000 | F34: ='6 - Elettrico o termico'!$B$74+('2 - Le opzioni'!$B$112*('6 - Elettrico o termico'!$B$11/100*((1-('6 - Elettrico o termico'!$B$18))*'6 - Elettrico o termico'!$B$16+('6 - Elettrico o termico'!$B$18)*('6 - Elettrico o termico'!$B$17))-'6 - Elettrico o termico'!$B$7/100*'6 - Elettrico o termico'!$B$15)+'6 - Elettrico o termico'!$B$75)*E34 -> -5398.8567 | G34: =IF(F34<0,"elettrica","benzina") -> elettrica | I34: 42000 | J34: ='6 - Elettrico o termico'!$B$74+('2 - Le opzioni'!$B$112*('6 - Elettrico o termico'!$B$11/100*((1-('6 - Elettrico o termico'!$B$18))*'6 - Elettrico o termico'!$B$16+('6 - Elettrico o termico'!$B$18)*('6 - Elettrico o termico'!$B$17))-'6 - Elettrico o termico'!$B$7/100*'6 - Elettrico o termico'!$B$15)+'6 - Elettrico o termico'!$B$75)*I34 -> -14866.056 | K34: =IF(J34<0,"elettrica","benzina") -> elettrica
A35: 3000 | B35: ='6 - Elettrico o termico'!$B$74+('2 - Le opzioni'!$B$112*('6 - Elettrico o termico'!$B$11/100*((1-('6 - Elettrico o termico'!$B$18))*'6 - Elettrico o termico'!$B$16+('6 - Elettrico o termico'!$B$18)*('6 - Elettrico o termico'!$B$17))-'6 - Elettrico o termico'!$B$7/100*'6 - Elettrico o termico'!$B$15)+'6 - Elettrico o termico'!$B$75)*A35 -> 3594.9828 | C35: =IF(B35<0,"elettrica","benzina") -> benzina | E35: 23000 | F35: ='6 - Elettrico o termico'!$B$74+('2 - Le opzioni'!$B$112*('6 - Elettrico o termico'!$B$11/100*((1-('6 - Elettrico o termico'!$B$18))*'6 - Elettrico o termico'!$B$16+('6 - Elettrico o termico'!$B$18)*('6 - Elettrico o termico'!$B$17))-'6 - Elettrico o termico'!$B$7/100*'6 - Elettrico o termico'!$B$15)+'6 - Elettrico o termico'!$B$75)*E35 -> -5872.2166 | G35: =IF(F35<0,"elettrica","benzina") -> elettrica | I35: 43000 | J35: ='6 - Elettrico o termico'!$B$74+('2 - Le opzioni'!$B$112*('6 - Elettrico o termico'!$B$11/100*((1-('6 - Elettrico o termico'!$B$18))*'6 - Elettrico o termico'!$B$16+('6 - Elettrico o termico'!$B$18)*('6 - Elettrico o termico'!$B$17))-'6 - Elettrico o termico'!$B$7/100*'6 - Elettrico o termico'!$B$15)+'6 - Elettrico o termico'!$B$75)*I35 -> -15339.416 | K35: =IF(J35<0,"elettrica","benzina") -> elettrica
A36: 4000 | B36: ='6 - Elettrico o termico'!$B$74+('2 - Le opzioni'!$B$112*('6 - Elettrico o termico'!$B$11/100*((1-('6 - Elettrico o termico'!$B$18))*'6 - Elettrico o termico'!$B$16+('6 - Elettrico o termico'!$B$18)*('6 - Elettrico o termico'!$B$17))-'6 - Elettrico o termico'!$B$7/100*'6 - Elettrico o termico'!$B$15)+'6 - Elettrico o termico'!$B$75)*A36 -> 3121.6228 | C36: =IF(B36<0,"elettrica","benzina") -> benzina | E36: 24000 | F36: ='6 - Elettrico o termico'!$B$74+('2 - Le opzioni'!$B$112*('6 - Elettrico o termico'!$B$11/100*((1-('6 - Elettrico o termico'!$B$18))*'6 - Elettrico o termico'!$B$16+('6 - Elettrico o termico'!$B$18)*('6 - Elettrico o termico'!$B$17))-'6 - Elettrico o termico'!$B$7/100*'6 - Elettrico o termico'!$B$15)+'6 - Elettrico o termico'!$B$75)*E36 -> -6345.5766 | G36: =IF(F36<0,"elettrica","benzina") -> elettrica | I36: 44000 | J36: ='6 - Elettrico o termico'!$B$74+('2 - Le opzioni'!$B$112*('6 - Elettrico o termico'!$B$11/100*((1-('6 - Elettrico o termico'!$B$18))*'6 - Elettrico o termico'!$B$16+('6 - Elettrico o termico'!$B$18)*('6 - Elettrico o termico'!$B$17))-'6 - Elettrico o termico'!$B$7/100*'6 - Elettrico o termico'!$B$15)+'6 - Elettrico o termico'!$B$75)*I36 -> -15812.776 | K36: =IF(J36<0,"elettrica","benzina") -> elettrica
A37: 5000 | B37: ='6 - Elettrico o termico'!$B$74+('2 - Le opzioni'!$B$112*('6 - Elettrico o termico'!$B$11/100*((1-('6 - Elettrico o termico'!$B$18))*'6 - Elettrico o termico'!$B$16+('6 - Elettrico o termico'!$B$18)*('6 - Elettrico o termico'!$B$17))-'6 - Elettrico o termico'!$B$7/100*'6 - Elettrico o termico'!$B$15)+'6 - Elettrico o termico'!$B$75)*A37 -> 2648.2629 | C37: =IF(B37<0,"elettrica","benzina") -> benzina | E37: 25000 | F37: ='6 - Elettrico o termico'!$B$74+('2 - Le opzioni'!$B$112*('6 - Elettrico o termico'!$B$11/100*((1-('6 - Elettrico o termico'!$B$18))*'6 - Elettrico o termico'!$B$16+('6 - Elettrico o termico'!$B$18)*('6 - Elettrico o termico'!$B$17))-'6 - Elettrico o termico'!$B$7/100*'6 - Elettrico o termico'!$B$15)+'6 - Elettrico o termico'!$B$75)*E37 -> -6818.9366 | G37: =IF(F37<0,"elettrica","benzina") -> elettrica | I37: 45000 | J37: ='6 - Elettrico o termico'!$B$74+('2 - Le opzioni'!$B$112*('6 - Elettrico o termico'!$B$11/100*((1-('6 - Elettrico o termico'!$B$18))*'6 - Elettrico o termico'!$B$16+('6 - Elettrico o termico'!$B$18)*('6 - Elettrico o termico'!$B$17))-'6 - Elettrico o termico'!$B$7/100*'6 - Elettrico o termico'!$B$15)+'6 - Elettrico o termico'!$B$75)*I37 -> -16286.136 | K37: =IF(J37<0,"elettrica","benzina") -> elettrica
A38: 6000 | B38: ='6 - Elettrico o termico'!$B$74+('2 - Le opzioni'!$B$112*('6 - Elettrico o termico'!$B$11/100*((1-('6 - Elettrico o termico'!$B$18))*'6 - Elettrico o termico'!$B$16+('6 - Elettrico o termico'!$B$18)*('6 - Elettrico o termico'!$B$17))-'6 - Elettrico o termico'!$B$7/100*'6 - Elettrico o termico'!$B$15)+'6 - Elettrico o termico'!$B$75)*A38 -> 2174.9029 | C38: =IF(B38<0,"elettrica","benzina") -> benzina | E38: 26000 | F38: ='6 - Elettrico o termico'!$B$74+('2 - Le opzioni'!$B$112*('6 - Elettrico o termico'!$B$11/100*((1-('6 - Elettrico o termico'!$B$18))*'6 - Elettrico o termico'!$B$16+('6 - Elettrico o termico'!$B$18)*('6 - Elettrico o termico'!$B$17))-'6 - Elettrico o termico'!$B$7/100*'6 - Elettrico o termico'!$B$15)+'6 - Elettrico o termico'!$B$75)*E38 -> -7292.2966 | G38: =IF(F38<0,"elettrica","benzina") -> elettrica | I38: 46000 | J38: ='6 - Elettrico o termico'!$B$74+('2 - Le opzioni'!$B$112*('6 - Elettrico o termico'!$B$11/100*((1-('6 - Elettrico o termico'!$B$18))*'6 - Elettrico o termico'!$B$16+('6 - Elettrico o termico'!$B$18)*('6 - Elettrico o termico'!$B$17))-'6 - Elettrico o termico'!$B$7/100*'6 - Elettrico o termico'!$B$15)+'6 - Elettrico o termico'!$B$75)*I38 -> -16759.496 | K38: =IF(J38<0,"elettrica","benzina") -> elettrica
A39: 7000 | B39: ='6 - Elettrico o termico'!$B$74+('2 - Le opzioni'!$B$112*('6 - Elettrico o termico'!$B$11/100*((1-('6 - Elettrico o termico'!$B$18))*'6 - Elettrico o termico'!$B$16+('6 - Elettrico o termico'!$B$18)*('6 - Elettrico o termico'!$B$17))-'6 - Elettrico o termico'!$B$7/100*'6 - Elettrico o termico'!$B$15)+'6 - Elettrico o termico'!$B$75)*A39 -> 1701.5429 | C39: =IF(B39<0,"elettrica","benzina") -> benzina | E39: 27000 | F39: ='6 - Elettrico o termico'!$B$74+('2 - Le opzioni'!$B$112*('6 - Elettrico o termico'!$B$11/100*((1-('6 - Elettrico o termico'!$B$18))*'6 - Elettrico o termico'!$B$16+('6 - Elettrico o termico'!$B$18)*('6 - Elettrico o termico'!$B$17))-'6 - Elettrico o termico'!$B$7/100*'6 - Elettrico o termico'!$B$15)+'6 - Elettrico o termico'!$B$75)*E39 -> -7765.6565 | G39: =IF(F39<0,"elettrica","benzina") -> elettrica | I39: 47000 | J39: ='6 - Elettrico o termico'!$B$74+('2 - Le opzioni'!$B$112*('6 - Elettrico o termico'!$B$11/100*((1-('6 - Elettrico o termico'!$B$18))*'6 - Elettrico o termico'!$B$16+('6 - Elettrico o termico'!$B$18)*('6 - Elettrico o termico'!$B$17))-'6 - Elettrico o termico'!$B$7/100*'6 - Elettrico o termico'!$B$15)+'6 - Elettrico o termico'!$B$75)*I39 -> -17232.856 | K39: =IF(J39<0,"elettrica","benzina") -> elettrica
A40: 8000 | B40: ='6 - Elettrico o termico'!$B$74+('2 - Le opzioni'!$B$112*('6 - Elettrico o termico'!$B$11/100*((1-('6 - Elettrico o termico'!$B$18))*'6 - Elettrico o termico'!$B$16+('6 - Elettrico o termico'!$B$18)*('6 - Elettrico o termico'!$B$17))-'6 - Elettrico o termico'!$B$7/100*'6 - Elettrico o termico'!$B$15)+'6 - Elettrico o termico'!$B$75)*A40 -> 1228.1829 | C40: =IF(B40<0,"elettrica","benzina") -> benzina | E40: 28000 | F40: ='6 - Elettrico o termico'!$B$74+('2 - Le opzioni'!$B$112*('6 - Elettrico o termico'!$B$11/100*((1-('6 - Elettrico o termico'!$B$18))*'6 - Elettrico o termico'!$B$16+('6 - Elettrico o termico'!$B$18)*('6 - Elettrico o termico'!$B$17))-'6 - Elettrico o termico'!$B$7/100*'6 - Elettrico o termico'!$B$15)+'6 - Elettrico o termico'!$B$75)*E40 -> -8239.0165 | G40: =IF(F40<0,"elettrica","benzina") -> elettrica | I40: 48000 | J40: ='6 - Elettrico o termico'!$B$74+('2 - Le opzioni'!$B$112*('6 - Elettrico o termico'!$B$11/100*((1-('6 - Elettrico o termico'!$B$18))*'6 - Elettrico o termico'!$B$16+('6 - Elettrico o termico'!$B$18)*('6 - Elettrico o termico'!$B$17))-'6 - Elettrico o termico'!$B$7/100*'6 - Elettrico o termico'!$B$15)+'6 - Elettrico o termico'!$B$75)*I40 -> -17706.216 | K40: =IF(J40<0,"elettrica","benzina") -> elettrica
A41: 9000 | B41: ='6 - Elettrico o termico'!$B$74+('2 - Le opzioni'!$B$112*('6 - Elettrico o termico'!$B$11/100*((1-('6 - Elettrico o termico'!$B$18))*'6 - Elettrico o termico'!$B$16+('6 - Elettrico o termico'!$B$18)*('6 - Elettrico o termico'!$B$17))-'6 - Elettrico o termico'!$B$7/100*'6 - Elettrico o termico'!$B$15)+'6 - Elettrico o termico'!$B$75)*A41 -> 754.82297 | C41: =IF(B41<0,"elettrica","benzina") -> benzina | E41: 29000 | F41: ='6 - Elettrico o termico'!$B$74+('2 - Le opzioni'!$B$112*('6 - Elettrico o termico'!$B$11/100*((1-('6 - Elettrico o termico'!$B$18))*'6 - Elettrico o termico'!$B$16+('6 - Elettrico o termico'!$B$18)*('6 - Elettrico o termico'!$B$17))-'6 - Elettrico o termico'!$B$7/100*'6 - Elettrico o termico'!$B$15)+'6 - Elettrico o termico'!$B$75)*E41 -> -8712.3765 | G41: =IF(F41<0,"elettrica","benzina") -> elettrica | I41: 49000 | J41: ='6 - Elettrico o termico'!$B$74+('2 - Le opzioni'!$B$112*('6 - Elettrico o termico'!$B$11/100*((1-('6 - Elettrico o termico'!$B$18))*'6 - Elettrico o termico'!$B$16+('6 - Elettrico o termico'!$B$18)*('6 - Elettrico o termico'!$B$17))-'6 - Elettrico o termico'!$B$7/100*'6 - Elettrico o termico'!$B$15)+'6 - Elettrico o termico'!$B$75)*I41 -> -18179.576 | K41: =IF(J41<0,"elettrica","benzina") -> elettrica
A42: 10000 | B42: ='6 - Elettrico o termico'!$B$74+('2 - Le opzioni'!$B$112*('6 - Elettrico o termico'!$B$11/100*((1-('6 - Elettrico o termico'!$B$18))*'6 - Elettrico o termico'!$B$16+('6 - Elettrico o termico'!$B$18)*('6 - Elettrico o termico'!$B$17))-'6 - Elettrico o termico'!$B$7/100*'6 - Elettrico o termico'!$B$15)+'6 - Elettrico o termico'!$B$75)*A42 -> 281.463 | C42: =IF(B42<0,"elettrica","benzina") -> benzina | E42: 30000 | F42: ='6 - Elettrico o termico'!$B$74+('2 - Le opzioni'!$B$112*('6 - Elettrico o termico'!$B$11/100*((1-('6 - Elettrico o termico'!$B$18))*'6 - Elettrico o termico'!$B$16+('6 - Elettrico o termico'!$B$18)*('6 - Elettrico o termico'!$B$17))-'6 - Elettrico o termico'!$B$7/100*'6 - Elettrico o termico'!$B$15)+'6 - Elettrico o termico'!$B$75)*E42 -> -9185.7364 | G42: =IF(F42<0,"elettrica","benzina") -> elettrica | I42: 50000 | J42: ='6 - Elettrico o termico'!$B$74+('2 - Le opzioni'!$B$112*('6 - Elettrico o termico'!$B$11/100*((1-('6 - Elettrico o termico'!$B$18))*'6 - Elettrico o termico'!$B$16+('6 - Elettrico o termico'!$B$18)*('6 - Elettrico o termico'!$B$17))-'6 - Elettrico o termico'!$B$7/100*'6 - Elettrico o termico'!$B$15)+'6 - Elettrico o termico'!$B$75)*I42 -> -18652.936 | K42: =IF(J42<0,"elettrica","benzina") -> elettrica
A43: 11000 | B43: ='6 - Elettrico o termico'!$B$74+('2 - Le opzioni'!$B$112*('6 - Elettrico o termico'!$B$11/100*((1-('6 - Elettrico o termico'!$B$18))*'6 - Elettrico o termico'!$B$16+('6 - Elettrico o termico'!$B$18)*('6 - Elettrico o termico'!$B$17))-'6 - Elettrico o termico'!$B$7/100*'6 - Elettrico o termico'!$B$15)+'6 - Elettrico o termico'!$B$75)*A43 -> -191.89698 | C43: =IF(B43<0,"elettrica","benzina") -> elettrica | E43: 31000 | F43: ='6 - Elettrico o termico'!$B$74+('2 - Le opzioni'!$B$112*('6 - Elettrico o termico'!$B$11/100*((1-('6 - Elettrico o termico'!$B$18))*'6 - Elettrico o termico'!$B$16+('6 - Elettrico o termico'!$B$18)*('6 - Elettrico o termico'!$B$17))-'6 - Elettrico o termico'!$B$7/100*'6 - Elettrico o termico'!$B$15)+'6 - Elettrico o termico'!$B$75)*E43 -> -9659.0964 | G43: =IF(F43<0,"elettrica","benzina") -> elettrica | I43: 51000 | J43: ='6 - Elettrico o termico'!$B$74+('2 - Le opzioni'!$B$112*('6 - Elettrico o termico'!$B$11/100*((1-('6 - Elettrico o termico'!$B$18))*'6 - Elettrico o termico'!$B$16+('6 - Elettrico o termico'!$B$18)*('6 - Elettrico o termico'!$B$17))-'6 - Elettrico o termico'!$B$7/100*'6 - Elettrico o termico'!$B$15)+'6 - Elettrico o termico'!$B$75)*I43 -> -19126.296 | K43: =IF(J43<0,"elettrica","benzina") -> elettrica
A44: 12000 | B44: ='6 - Elettrico o termico'!$B$74+('2 - Le opzioni'!$B$112*('6 - Elettrico o termico'!$B$11/100*((1-('6 - Elettrico o termico'!$B$18))*'6 - Elettrico o termico'!$B$16+('6 - Elettrico o termico'!$B$18)*('6 - Elettrico o termico'!$B$17))-'6 - Elettrico o termico'!$B$7/100*'6 - Elettrico o termico'!$B$15)+'6 - Elettrico o termico'!$B$75)*A44 -> -665.25695 | C44: =IF(B44<0,"elettrica","benzina") -> elettrica | E44: 32000 | F44: ='6 - Elettrico o termico'!$B$74+('2 - Le opzioni'!$B$112*('6 - Elettrico o termico'!$B$11/100*((1-('6 - Elettrico o termico'!$B$18))*'6 - Elettrico o termico'!$B$16+('6 - Elettrico o termico'!$B$18)*('6 - Elettrico o termico'!$B$17))-'6 - Elettrico o termico'!$B$7/100*'6 - Elettrico o termico'!$B$15)+'6 - Elettrico o termico'!$B$75)*E44 -> -10132.456 | G44: =IF(F44<0,"elettrica","benzina") -> elettrica | I44: 52000 | J44: ='6 - Elettrico o termico'!$B$74+('2 - Le opzioni'!$B$112*('6 - Elettrico o termico'!$B$11/100*((1-('6 - Elettrico o termico'!$B$18))*'6 - Elettrico o termico'!$B$16+('6 - Elettrico o termico'!$B$18)*('6 - Elettrico o termico'!$B$17))-'6 - Elettrico o termico'!$B$7/100*'6 - Elettrico o termico'!$B$15)+'6 - Elettrico o termico'!$B$75)*I44 -> -19599.656 | K44: =IF(J44<0,"elettrica","benzina") -> elettrica
... A52: 20000 | B52: ='6 - Elettrico o termico'!$B$74+('2 - Le opzioni'!$B$112*('6 - Elettrico o termico'!$B$11/100*((1-('6 - Elettrico o termico'!$B$18))*'6 - Elettrico o termico'!$B$16+('6 - Elettrico o termico'!$B$18)*('6 - Elettrico o termico'!$B$17))-'6 - Elettrico o termico'!$B$7/100*'6 - Elettrico o termico'!$B$15)+'6 - Elettrico o termico'!$B$75)*A52 -> -4452.1367 | C52: =IF(B52<0,"elettrica","benzina") -> elettrica | E52: 40000 | F52: ='6 - Elettrico o termico'!$B$74+('2 - Le opzioni'!$B$112*('6 - Elettrico o termico'!$B$11/100*((1-('6 - Elettrico o termico'!$B$18))*'6 - Elettrico o termico'!$B$16+('6 - Elettrico o termico'!$B$18)*('6 - Elettrico o termico'!$B$17))-'6 - Elettrico o termico'!$B$7/100*'6 - Elettrico o termico'!$B$15)+'6 - Elettrico o termico'!$B$75)*E52 -> -13919.336 | G52: =IF(F52<0,"elettrica","benzina") -> elettrica | I52: 60000 | J52: ='6 - Elettrico o termico'!$B$74+('2 - Le opzioni'!$B$112*('6 - Elettrico o termico'!$B$11/100*((1-('6 - Elettrico o termico'!$B$18))*'6 - Elettrico o termico'!$B$16+('6 - Elettrico o termico'!$B$18)*('6 - Elettrico o termico'!$B$17))-'6 - Elettrico o termico'!$B$7/100*'6 - Elettrico o termico'!$B$15)+'6 - Elettrico o termico'!$B$75)*I52 -> -23386.536 | K52: =IF(J52<0,"elettrica","benzina") -> elettrica
A60: Motore del calcolo — non modificare
A61: Calcoli intermedi usati dalle celle verdi qui sopra: si possono leggere, non vanno modificati.
A62: Anno | B62: Fattore di sconto | C62: Manutenzione base | D62: Bollo benzina | E62: Bollo elettrica
A63: 1 | B63: =1/(1+'1 - Il tuo profilo'!$B$13)^A63 -> 0.97087379 | C63: =IF(A63<=3,'2 - Le opzioni'!$B$56,IF(A63<=7,'2 - Le opzioni'!$B$57,IF(A63<=12,'2 - Le opzioni'!$B$58,'2 - Le opzioni'!$B$59+'2 - Le opzioni'!$B$60*(A63-13)))) -> 350 | D63: ='6 - Elettrico o termico'!$B$8*'1 - Il tuo profilo'!$B$30 -> 180.6 | E63: =IF(A63<='2 - Le opzioni'!$B$31,0,'2 - Le opzioni'!$B$32)*'6 - Elettrico o termico'!$B$12*'1 - Il tuo profilo'!$B$30 -> 0
A64: 2 | B64: =1/(1+'1 - Il tuo profilo'!$B$13)^A64 -> 0.94259591 | C64: =IF(A64<=3,'2 - Le opzioni'!$B$56,IF(A64<=7,'2 - Le opzioni'!$B$57,IF(A64<=12,'2 - Le opzioni'!$B$58,'2 - Le opzioni'!$B$59+'2 - Le opzioni'!$B$60*(A64-13)))) -> 350 | D64: ='6 - Elettrico o termico'!$B$8*'1 - Il tuo profilo'!$B$30 -> 180.6 | E64: =IF(A64<='2 - Le opzioni'!$B$31,0,'2 - Le opzioni'!$B$32)*'6 - Elettrico o termico'!$B$12*'1 - Il tuo profilo'!$B$30 -> 0
A65: 3 | B65: =1/(1+'1 - Il tuo profilo'!$B$13)^A65 -> 0.91514166 | C65: =IF(A65<=3,'2 - Le opzioni'!$B$56,IF(A65<=7,'2 - Le opzioni'!$B$57,IF(A65<=12,'2 - Le opzioni'!$B$58,'2 - Le opzioni'!$B$59+'2 - Le opzioni'!$B$60*(A65-13)))) -> 350 | D65: ='6 - Elettrico o termico'!$B$8*'1 - Il tuo profilo'!$B$30 -> 180.6 | E65: =IF(A65<='2 - Le opzioni'!$B$31,0,'2 - Le opzioni'!$B$32)*'6 - Elettrico o termico'!$B$12*'1 - Il tuo profilo'!$B$30 -> 0
A66: 4 | B66: =1/(1+'1 - Il tuo profilo'!$B$13)^A66 -> 0.88848705 | C66: =IF(A66<=3,'2 - Le opzioni'!$B$56,IF(A66<=7,'2 - Le opzioni'!$B$57,IF(A66<=12,'2 - Le opzioni'!$B$58,'2 - Le opzioni'!$B$59+'2 - Le opzioni'!$B$60*(A66-13)))) -> 600 | D66: ='6 - Elettrico o termico'!$B$8*'1 - Il tuo profilo'!$B$30 -> 180.6 | E66: =IF(A66<='2 - Le opzioni'!$B$31,0,'2 - Le opzioni'!$B$32)*'6 - Elettrico o termico'!$B$12*'1 - Il tuo profilo'!$B$30 -> 0
A67: 5 | B67: =1/(1+'1 - Il tuo profilo'!$B$13)^A67 -> 0.86260878 | C67: =IF(A67<=3,'2 - Le opzioni'!$B$56,IF(A67<=7,'2 - Le opzioni'!$B$57,IF(A67<=12,'2 - Le opzioni'!$B$58,'2 - Le opzioni'!$B$59+'2 - Le opzioni'!$B$60*(A67-13)))) -> 600 | D67: ='6 - Elettrico o termico'!$B$8*'1 - Il tuo profilo'!$B$30 -> 180.6 | E67: =IF(A67<='2 - Le opzioni'!$B$31,0,'2 - Le opzioni'!$B$32)*'6 - Elettrico o termico'!$B$12*'1 - Il tuo profilo'!$B$30 -> 0
A68: 6 | B68: =1/(1+'1 - Il tuo profilo'!$B$13)^A68 -> 0.83748426 | C68: =IF(A68<=3,'2 - Le opzioni'!$B$56,IF(A68<=7,'2 - Le opzioni'!$B$57,IF(A68<=12,'2 - Le opzioni'!$B$58,'2 - Le opzioni'!$B$59+'2 - Le opzioni'!$B$60*(A68-13)))) -> 600 | D68: ='6 - Elettrico o termico'!$B$8*'1 - Il tuo profilo'!$B$30 -> 180.6 | E68: =IF(A68<='2 - Le opzioni'!$B$31,0,'2 - Le opzioni'!$B$32)*'6 - Elettrico o termico'!$B$12*'1 - Il tuo profilo'!$B$30 -> 54.825
A69: 7 | B69: =1/(1+'1 - Il tuo profilo'!$B$13)^A69 -> 0.81309151 | C69: =IF(A69<=3,'2 - Le opzioni'!$B$56,IF(A69<=7,'2 - Le opzioni'!$B$57,IF(A69<=12,'2 - Le opzioni'!$B$58,'2 - Le opzioni'!$B$59+'2 - Le opzioni'!$B$60*(A69-13)))) -> 600 | D69: ='6 - Elettrico o termico'!$B$8*'1 - Il tuo profilo'!$B$30 -> 180.6 | E69: =IF(A69<='2 - Le opzioni'!$B$31,0,'2 - Le opzioni'!$B$32)*'6 - Elettrico o termico'!$B$12*'1 - Il tuo profilo'!$B$30 -> 54.825
A70: 8 | B70: =1/(1+'1 - Il tuo profilo'!$B$13)^A70 -> 0.78940923 | C70: =IF(A70<=3,'2 - Le opzioni'!$B$56,IF(A70<=7,'2 - Le opzioni'!$B$57,IF(A70<=12,'2 - Le opzioni'!$B$58,'2 - Le opzioni'!$B$59+'2 - Le opzioni'!$B$60*(A70-13)))) -> 900 | D70: ='6 - Elettrico o termico'!$B$8*'1 - Il tuo profilo'!$B$30 -> 180.6 | E70: =IF(A70<='2 - Le opzioni'!$B$31,0,'2 - Le opzioni'!$B$32)*'6 - Elettrico o termico'!$B$12*'1 - Il tuo profilo'!$B$30 -> 54.825
A71: 9 | B71: =1/(1+'1 - Il tuo profilo'!$B$13)^A71 -> 0.76641673 | C71: =IF(A71<=3,'2 - Le opzioni'!$B$56,IF(A71<=7,'2 - Le opzioni'!$B$57,IF(A71<=12,'2 - Le opzioni'!$B$58,'2 - Le opzioni'!$B$59+'2 - Le opzioni'!$B$60*(A71-13)))) -> 900 | D71: ='6 - Elettrico o termico'!$B$8*'1 - Il tuo profilo'!$B$30 -> 180.6 | E71: =IF(A71<='2 - Le opzioni'!$B$31,0,'2 - Le opzioni'!$B$32)*'6 - Elettrico o termico'!$B$12*'1 - Il tuo profilo'!$B$30 -> 54.825
A72: 10 | B72: =1/(1+'1 - Il tuo profilo'!$B$13)^A72 -> 0.74409391 | C72: =IF(A72<=3,'2 - Le opzioni'!$B$56,IF(A72<=7,'2 - Le opzioni'!$B$57,IF(A72<=12,'2 - Le opzioni'!$B$58,'2 - Le opzioni'!$B$59+'2 - Le opzioni'!$B$60*(A72-13)))) -> 900 | D72: ='6 - Elettrico o termico'!$B$8*'1 - Il tuo profilo'!$B$30 -> 180.6 | E72: =IF(A72<='2 - Le opzioni'!$B$31,0,'2 - Le opzioni'!$B$32)*'6 - Elettrico o termico'!$B$12*'1 - Il tuo profilo'!$B$30 -> 54.825
A74: Parte fissa della differenza (prezzi, residui, bollo, metà manutenzione) | B74: =('6 - Elettrico o termico'!$B$9-'6 - Elettrico o termico'!$B$10-'6 - Elettrico o termico'!$B$6)-('6 - Elettrico o termico'!$B$9*IF(10>=MAX('2 - Le opzioni'!$B$67:$K$67),0,INDEX('2 - Le opzioni'!$B$69:$K$69,MATCH(10,'2 - Le opzioni'!$B$67:$K$67,1))+(INDEX('2 - Le opzioni'!$B$69:$K$69,MATCH(10,'2 - Le opzioni'!$B$67:$K$67,1)+1)-INDEX('2 - Le opzioni'!$B$69:$K$69,MATCH(10,'2 - Le opzioni'!$B$67:$K$67,1)))*(10-INDEX('2 - Le opzioni'!$B$67:$K$67,MATCH(10,'2 - Le opzioni'!$B$67:$K$67,1)))/(INDEX('2 - Le opzioni'!$B$67:$K$67,MATCH(10,'2 - Le opzioni'!$B$67:$K$67,1)+1)-INDEX('2 - Le opzioni'!$B$67:$K$67,MATCH(10,'2 - Le opzioni'!$B$67:$K$67,1))))-'6 - Elettrico o termico'!$B$6*IF(10>=MAX('2 - Le opzioni'!$B$67:$K$67),0,INDEX('2 - Le opzioni'!$B$68:$K$68,MATCH(10,'2 - Le opzioni'!$B$67:$K$67,1))+(INDEX('2 - Le opzioni'!$B$68:$K$68,MATCH(10,'2 - Le opzioni'!$B$67:$K$67,1)+1)-INDEX('2 - Le opzioni'!$B$68:$K$68,MATCH(10,'2 - Le opzioni'!$B$67:$K$67,1)))*(10-INDEX('2 - Le opzioni'!$B$67:$K$67,MATCH(10,'2 - Le opzioni'!$B$67:$K$67,1)))/(INDEX('2 - Le opzioni'!$B$67:$K$67,MATCH(10,'2 - Le opzioni'!$B$67:$K$67,1)+1)-INDEX('2 - Le opzioni'!$B$67:$K$67,MATCH(10,'2 - Le opzioni'!$B$67:$K$67,1)))))/(1+'1 - Il tuo profilo'!$B$13)^10+SUMPRODUCT('6 - Elettrico o termico'!$B$63:$B$72,'6 - Elettrico o termico'!$E$63:$E$72)-SUMPRODUCT('6 - Elettrico o termico'!$B$63:$B$72,'6 - Elettrico o termico'!$D$63:$D$72)+SUMPRODUCT('6 - Elettrico o termico'!$B$63:$B$72,'6 - Elettrico o termico'!$C$63:$C$72)*0.5*('2 - Le opzioni'!$B$62-1) -> 5015.0627
A75: Parte della manutenzione che cresce con i km, per km | B75: =SUMPRODUCT('6 - Elettrico o termico'!$B$63:$B$72,'6 - Elettrico o termico'!$C$63:$C$72)*0.5*('2 - Le opzioni'!$B$62-1)/'2 - Le opzioni'!$B$63 -> -0.06376181
