Workbook

Sheet 0 - Indice
A1: Dividendo mensile: rendita o capitale che torna indietro? Il caso di Renata (caso inventato e illustrativo)
A2: Caso inventato e illustrativo, non è consulenza e non è una previsione. Fotografia di ottobre 2026, regole fiscali di oggi. Prima di decidere fai i conti sul tuo caso e parlane con professionisti abilitati.
A4: Indice
A5: 0 - Indice | B5: Questo indice
A6: 1 - Input | B6: Il caso di Renata e le ipotesi (celle gialle): capitale, spesa, distribuzione, quota Q, fisco, scenario
A7: 2 - Distribuzione | B7: Tre percorsi con distribuzione: caso atteso (Q = 0%), Q scelta, limite teorico (Q = 100%)
A8: 3 - Accumulo | B8: La stessa strategia ad accumulo, con sole vendite
A9: 4 - Confronto | B9: Confronto: durate, imposte, minusvalenze, capitale a 10 e 15 anni
A10: 5 - Annualizzatore | B10: Annualizzatore di uno stacco e quota che è capitale che torna indietro
A12: Come usare
A13: 1. Le celle GIALLE sono input — modificale coi tuoi numeri.
A14: 2. Le celle VERDI sono output — si aggiornano automaticamente.
A15: 3. Tutti i numeri di default sono al 2026 da fonti pubbliche.
A16: 4. Niente codice nascosto: l'Excel è solo formule modificabili.
A18: Fonti dati
A19: • Regole fiscali di ottobre 2026: D.L. 66/2014 (26%), D.P.R. 642/1972 (bollo), art. 10-ter L. 77/1983 (proventi dei fondi) (P)
A20: • Rimborso di capitale: Agenzia delle Entrate, risposta 161/2022 e circolare 33/E del 2011, per analogia su un fondo chiuso italiano (P)
A21: • Serie storica dell'indice a opzioni di acquisto coperte, 2002-2026, per gli scenari piatto, crollo e rialzo (P)
A22: • CALCOLI MIEI (E): il caso di Renata, il motore mensile, gli scenari. Gradi: P = fonte primaria, E = stima o calcolo mio
A24: Aggiornamenti: github.com/marcofire-it/marco-fire-simulatori
A25: Note e limiti
... A30: Il motore del calcolo è in fondo ai fogli 2 e 3: non modificare. Nessuna macro, solo formule.

Sheet 1 - Input
A1: Dividendo mensile: rendita o capitale che torna indietro? Il caso di Renata (caso inventato e illustrativo)
A2: Caso inventato e illustrativo, non è consulenza e non è una previsione. Fotografia di ottobre 2026, regole fiscali di oggi. Prima di decidere fai i conti sul tuo caso e parlane con professionisti abilitati.
A4: Input (celle gialle)
A5: Voce | B5: Valore | C5: Nota
A6: Capitale iniziale | B6: 486500 | C6: Capitale investito nel fondo al via.
A7: Spesa netta mensile | B7: 2700 | C7: Netta di imposta, in cassa, indicizzata all'inflazione. Il bollo è a parte.
A8: Distribuzione annua (% del valore) | B8: 0.09 | C8: Versata in dodici rate uguali a distribuzione/12, sul valore di fine mese.
A9: Quota Q: parte della distribuzione qualificata come rimborso di capitale | B9: 0 | C9: Dipende dalla delibera e dal rendiconto del fondo. 0% = tutto provento, tassato per intero. 100% = tutto rimborso: limite teorico, senza fonte per gli ETF esteri. Leggi il rendiconto.
A10: Aliquota sui proventi e sulle plusvalenze | B10: 0.26 | C10: Fotografia di ottobre 2026.
A11: Bollo annuo sul valore | B11: 0.002 | C11: Pagato a dicembre dal portafoglio, non sulla spesa.
A12: Inflazione (indicizzazione della spesa) | B12: 0.02 | C12: Ipotesi di base.
A13: Rendimento reale dell'ipotesi di base | B13: 0.03 | C13: Serve a generare il vettore dei rendimenti base e piatto.
A14: Orizzonte in anni (1-30) | B14: 30 | C14: Per i risultati a fine orizzonte del foglio 4.
A15: Costo fiscale diviso valore al via | B15: 1 | C15: Con una plusvalenza latente (meno di 100%) il percorso ad accumulo perde parte del vantaggio.
A16: Scenario (1-4) | B16: 1 | C16: 1 base, 2 piatto, 3 crollo al primo anno, 4 rialzo forte per tre anni.
A17: Integra con vendite (1 = sì, 0 = solo distribuzioni) | B17: 1 | C17: Con 0 si vede quanto vale la sola distribuzione.
... A20: Interruttore: senza imposte e senza bollo (1 = sì) | B20: 0 | C20: Con 1 aliquota e bollo valgono zero: serve a separare l'effetto del fisco.
A21: Parametri effettivi (formule)
A22: Aliquota effettiva | B22: =IF('1 - Input'!$B$20=1,0,'1 - Input'!$B$10) -> 0.26
A23: Bollo effettivo | B23: =IF('1 - Input'!$B$20=1,0,'1 - Input'!$B$11) -> 0.002
A25: Il vincolo aritmetico del caso
A26: Spesa netta annua | B26: =12*'1 - Input'!$B$7 -> 32400
A27: Prelievo lordo necessario (spesa annua diviso uno meno l'aliquota) | B27: =B26/(1-'1 - Input'!$B$10) -> 43783.784
A28: Il lordo necessario come distribuzione sul capitale | B28: =B27/'1 - Input'!$B$6 -> 0.0899975
A29: Spesa annua diviso capitale | B29: =B26/'1 - Input'!$B$6 -> 0.06659815
A30: Rendimento nominale dell'ipotesi di base | B30: =(1+'1 - Input'!$B$13)*(1+'1 - Input'!$B$12)-1 -> 0.0506
A31: Capitale con un prelievo del 3% (confronto indicativo: il tasso è lordo, la spesa è netta) | B31: =B26/0.03 -> 1080000
A32: Vettore dei rendimenti annui nominali (formule)
A33: Anno | B33: 1 - Base | C33: 2 - Piatto | D33: 3 - Crollo al via | E33: 4 - Rialzo forte
A34: 1 | B34: =(1+'1 - Input'!$B$13)*(1+'1 - Input'!$B$12)-1 -> 0.0506 | C34: ='1 - Input'!$B$12 -> 0.02 | D34: ='1 - Input'!$B$18 -> -0.28654676 | E34: ='1 - Input'!$B$19 -> 0.17386739
A35: 2 | B35: =(1+'1 - Input'!$B$13)*(1+'1 - Input'!$B$12)-1 -> 0.0506 | C35: ='1 - Input'!$B$12 -> 0.02 | D35: =$B$30 -> 0.0506 | E35: ='1 - Input'!$B$19 -> 0.17386739
A36: 3 | B36: =(1+'1 - Input'!$B$13)*(1+'1 - Input'!$B$12)-1 -> 0.0506 | C36: ='1 - Input'!$B$12 -> 0.02 | D36: =$B$30 -> 0.0506 | E36: ='1 - Input'!$B$19 -> 0.17386739
A37: 4 | B37: =(1+'1 - Input'!$B$13)*(1+'1 - Input'!$B$12)-1 -> 0.0506 | C37: ='1 - Input'!$B$12 -> 0.02 | D37: =$B$30 -> 0.0506 | E37: =$B$30 -> 0.0506
A38: 5 | B38: =(1+'1 - Input'!$B$13)*(1+'1 - Input'!$B$12)-1 -> 0.0506 | C38: ='1 - Input'!$B$12 -> 0.02 | D38: =$B$30 -> 0.0506 | E38: =$B$30 -> 0.0506
A39: 6 | B39: =(1+'1 - Input'!$B$13)*(1+'1 - Input'!$B$12)-1 -> 0.0506 | C39: ='1 - Input'!$B$12 -> 0.02 | D39: =$B$30 -> 0.0506 | E39: =$B$30 -> 0.0506
A40: 7 | B40: =(1+'1 - Input'!$B$13)*(1+'1 - Input'!$B$12)-1 -> 0.0506 | C40: ='1 - Input'!$B$12 -> 0.02 | D40: =$B$30 -> 0.0506 | E40: =$B$30 -> 0.0506
A41: 8 | B41: =(1+'1 - Input'!$B$13)*(1+'1 - Input'!$B$12)-1 -> 0.0506 | C41: ='1 - Input'!$B$12 -> 0.02 | D41: =$B$30 -> 0.0506 | E41: =$B$30 -> 0.0506
A42: 9 | B42: =(1+'1 - Input'!$B$13)*(1+'1 - Input'!$B$12)-1 -> 0.0506 | C42: ='1 - Input'!$B$12 -> 0.02 | D42: =$B$30 -> 0.0506 | E42: =$B$30 -> 0.0506
A43: 10 | B43: =(1+'1 - Input'!$B$13)*(1+'1 - Input'!$B$12)-1 -> 0.0506 | C43: ='1 - Input'!$B$12 -> 0.02 | D43: =$B$30 -> 0.0506 | E43: =$B$30 -> 0.0506
A44: 11 | B44: =(1+'1 - Input'!$B$13)*(1+'1 - Input'!$B$12)-1 -> 0.0506 | C44: ='1 - Input'!$B$12 -> 0.02 | D44: =$B$30 -> 0.0506 | E44: =$B$30 -> 0.0506
A45: 12 | B45: =(1+'1 - Input'!$B$13)*(1+'1 - Input'!$B$12)-1 -> 0.0506 | C45: ='1 - Input'!$B$12 -> 0.02 | D45: =$B$30 -> 0.0506 | E45: =$B$30 -> 0.0506
A46: 13 | B46: =(1+'1 - Input'!$B$13)*(1+'1 - Input'!$B$12)-1 -> 0.0506 | C46: ='1 - Input'!$B$12 -> 0.02 | D46: =$B$30 -> 0.0506 | E46: =$B$30 -> 0.0506
A47: 14 | B47: =(1+'1 - Input'!$B$13)*(1+'1 - Input'!$B$12)-1 -> 0.0506 | C47: ='1 - Input'!$B$12 -> 0.02 | D47: =$B$30 -> 0.0506 | E47: =$B$30 -> 0.0506
A48: 15 | B48: =(1+'1 - Input'!$B$13)*(1+'1 - Input'!$B$12)-1 -> 0.0506 | C48: ='1 - Input'!$B$12 -> 0.02 | D48: =$B$30 -> 0.0506 | E48: =$B$30 -> 0.0506
... A63: 30 | B63: =(1+'1 - Input'!$B$13)*(1+'1 - Input'!$B$12)-1 -> 0.0506 | C63: ='1 - Input'!$B$12 -> 0.02 | D63: =$B$30 -> 0.0506 | E63: =$B$30 -> 0.0506

Sheet 2 - Distribuzione
A1: Dividendo mensile: rendita o capitale che torna indietro? Il caso di Renata (caso inventato e illustrativo)
A2: Caso inventato e illustrativo, non è consulenza e non è una previsione. Fotografia di ottobre 2026, regole fiscali di oggi. Prima di decidere fai i conti sul tuo caso e parlane con professionisti abilitati.
A3: Tre percorsi dello stesso motore mensile. La tabella annua è in alto, il motore del calcolo è in fondo (non modificare). Il blocco B è un limite teorico, senza fonte per gli ETF esteri.
A4: A: caso atteso, Q = 0% (tutto provento) | N4: U: Q scelta nel foglio 1 | AA4: B: limite teorico, senza fonte per gli ETF esteri, Q = 100%
A5: Anno | B5: Valore a fine anno (dopo bollo) | C5: Costo fiscale a fine anno | D5: Valore in euro di oggi | E5: Distribuzioni lorde | F5: Distribuzioni nette | G5: Imposte sulle distribuzioni | H5: Imposte sulle vendite | I5: Bollo | J5: Minusvalenze cumulate | K5: Spesa netta media al mese, euro correnti | L5: Spesa netta media al mese, euro di oggi | N5: Anno | O5: Valore a fine anno (dopo bollo) | P5: Costo fiscale a fine anno | Q5: Valore in euro di oggi | R5: Distribuzioni lorde | S5: Distribuzioni nette | T5: Imposte sulle distribuzioni | U5: Imposte sulle vendite | V5: Bollo | W5: Minusvalenze cumulate | X5: Spesa netta media al mese, euro correnti | Y5: Spesa netta media al mese, euro di oggi | AA5: Anno | AB5: Valore a fine anno (dopo bollo) | AC5: Costo fiscale a fine anno | AD5: Valore in euro di oggi | AE5: Distribuzioni lorde | AF5: Distribuzioni nette | AG5: Imposte sulle distribuzioni | AH5: Imposte sulle vendite | AI5: Bollo | AJ5: Minusvalenze cumulate | AK5: Spesa netta media al mese, euro correnti | AL5: Spesa netta media al mese, euro di oggi
A6: 1 | B6: =INDEX('2 - Distribuzione'!$Z$44:$Z$403,12*$A6) -> 465562.82 | C6: =INDEX('2 - Distribuzione'!$AA$44:$AA$403,12*$A6) -> 485036.76 | D6: =B6/(1+'1 - Input'!$B$12)^$A6 -> 456434.13 | E6: =SUMIFS('2 - Distribuzione'!$H$44:$H$403,'2 - Distribuzione'!$B$44:$B$403,$A6) -> 43140.785 | F6: =SUMIFS('2 - Distribuzione'!$L$44:$L$403,'2 - Distribuzione'!$B$44:$B$403,$A6) -> 31924.181 | G6: =SUMIFS('2 - Distribuzione'!$K$44:$K$403,'2 - Distribuzione'!$B$44:$B$403,$A6) -> 11216.604 | H6: =SUMIFS('2 - Distribuzione'!$S$44:$S$403,'2 - Distribuzione'!$B$44:$B$403,$A6) -> 0 | I6: =SUMIFS('2 - Distribuzione'!$Y$44:$Y$403,'2 - Distribuzione'!$B$44:$B$403,$A6) -> 932.99161 | J6: =INDEX('2 - Distribuzione'!$AF$44:$AF$403,12*$A6) -> 15.398999 | K6: =SUMIFS('2 - Distribuzione'!$AB$44:$AB$403,'2 - Distribuzione'!$B$44:$B$403,$A6)/12 -> 2700 | L6: =K6/(1+'1 - Input'!$B$12)^($A6-0.5) -> 2673.3984 | N6: 1 | O6: =INDEX('2 - Distribuzione'!$BJ$44:$BJ$403,12*$N6) -> 465562.82 | P6: =INDEX('2 - Distribuzione'!$BK$44:$BK$403,12*$N6) -> 485036.76 | Q6: =O6/(1+'1 - Input'!$B$12)^$N6 -> 456434.13 | R6: =SUMIFS('2 - Distribuzione'!$AR$44:$AR$403,'2 - Distribuzione'!$AL$44:$AL$403,$N6) -> 43140.785 | S6: =SUMIFS('2 - Distribuzione'!$AV$44:$AV$403,'2 - Distribuzione'!$AL$44:$AL$403,$N6) -> 31924.181 | T6: =SUMIFS('2 - Distribuzione'!$AU$44:$AU$403,'2 - Distribuzione'!$AL$44:$AL$403,$N6) -> 11216.604 | U6: =SUMIFS('2 - Distribuzione'!$BC$44:$BC$403,'2 - Distribuzione'!$AL$44:$AL$403,$N6) -> 0 | V6: =SUMIFS('2 - Distribuzione'!$BI$44:$BI$403,'2 - Distribuzione'!$AL$44:$AL$403,$N6) -> 932.99161 | W6: =INDEX('2 - Distribuzione'!$BP$44:$BP$403,12*$N6) -> 15.398999 | X6: =SUMIFS('2 - Distribuzione'!$BL$44:$BL$403,'2 - Distribuzione'!$AL$44:$AL$403,$N6)/12 -> 2700 | Y6: =X6/(1+'1 - Input'!$B$12)^($N6-0.5) -> 2673.3984 | AA6: 1 | AB6: =INDEX('2 - Distribuzione'!$CT$44:$CT$403,12*$AA6) -> 477016.24 | AC6: =INDEX('2 - Distribuzione'!$CU$44:$CU$403,12*$AA6) -> 453191.8 | AD6: =AB6/(1+'1 - Input'!$B$12)^$AA6 -> 467662.98 | AE6: =SUMIFS('2 - Distribuzione'!$CB$44:$CB$403,'2 - Distribuzione'!$BV$44:$BV$403,$AA6) -> 43615.404 | AF6: =SUMIFS('2 - Distribuzione'!$CF$44:$CF$403,'2 - Distribuzione'!$BV$44:$BV$403,$AA6) -> 43615.404 | AG6: =SUMIFS('2 - Distribuzione'!$CE$44:$CE$403,'2 - Distribuzione'!$BV$44:$BV$403,$AA6) -> 0 | AH6: =SUMIFS('2 - Distribuzione'!$CM$44:$CM$403,'2 - Distribuzione'!$BV$44:$BV$403,$AA6) -> 0 | AI6: =SUMIFS('2 - Distribuzione'!$CS$44:$CS$403,'2 - Distribuzione'!$BV$44:$BV$403,$AA6) -> 955.94437 | AJ6: =INDEX('2 - Distribuzione'!$CZ$44:$CZ$403,12*$AA6) -> 0 | AK6: =SUMIFS('2 - Distribuzione'!$CV$44:$CV$403,'2 - Distribuzione'!$BV$44:$BV$403,$AA6)/12 -> 2700 | AL6: =AK6/(1+'1 - Input'!$B$12)^($AA6-0.5) -> 2673.3984
A7: 2 | B7: =INDEX('2 - Distribuzione'!$Z$44:$Z$403,12*$A7) -> 443463.96 | C7: =INDEX('2 - Distribuzione'!$AA$44:$AA$403,12*$A7) -> 481339.08 | D7: =B7/(1+'1 - Input'!$B$12)^$A7 -> 426243.72 | E7: =SUMIFS('2 - Distribuzione'!$H$44:$H$403,'2 - Distribuzione'!$B$44:$B$403,$A7) -> 41198.954 | F7: =SUMIFS('2 - Distribuzione'!$L$44:$L$403,'2 - Distribuzione'!$B$44:$B$403,$A7) -> 30487.226 | G7: =SUMIFS('2 - Distribuzione'!$K$44:$K$403,'2 - Distribuzione'!$B$44:$B$403,$A7) -> 10711.728 | H7: =SUMIFS('2 - Distribuzione'!$S$44:$S$403,'2 - Distribuzione'!$B$44:$B$403,$A7) -> 0 | I7: =SUMIFS('2 - Distribuzione'!$Y$44:$Y$403,'2 - Distribuzione'!$B$44:$B$403,$A7) -> 888.70534 | J7: =INDEX('2 - Distribuzione'!$AF$44:$AF$403,12*$A7) -> 187.70039 | K7: =SUMIFS('2 - Distribuzione'!$AB$44:$AB$403,'2 - Distribuzione'!$B$44:$B$403,$A7)/12 -> 2754 | L7: =K7/(1+'1 - Input'!$B$12)^($A7-0.5) -> 2673.3984 | N7: 2 | O7: =INDEX('2 - Distribuzione'!$BJ$44:$BJ$403,12*$N7) -> 443463.96 | P7: =INDEX('2 - Distribuzione'!$BK$44:$BK$403,12*$N7) -> 481339.08 | Q7: =O7/(1+'1 - Input'!$B$12)^$N7 -> 426243.72 | R7: =SUMIFS('2 - Distribuzione'!$AR$44:$AR$403,'2 - Distribuzione'!$AL$44:$AL$403,$N7) -> 41198.954 | S7: =SUMIFS('2 - Distribuzione'!$AV$44:$AV$403,'2 - Distribuzione'!$AL$44:$AL$403,$N7) -> 30487.226 | T7: =SUMIFS('2 - Distribuzione'!$AU$44:$AU$403,'2 - Distribuzione'!$AL$44:$AL$403,$N7) -> 10711.728 | U7: =SUMIFS('2 - Distribuzione'!$BC$44:$BC$403,'2 - Distribuzione'!$AL$44:$AL$403,$N7) -> 0 | V7: =SUMIFS('2 - Distribuzione'!$BI$44:$BI$403,'2 - Distribuzione'!$AL$44:$AL$403,$N7) -> 888.70534 | W7: =INDEX('2 - Distribuzione'!$BP$44:$BP$403,12*$N7) -> 187.70039 | X7: =SUMIFS('2 - Distribuzione'!$BL$44:$BL$403,'2 - Distribuzione'!$AL$44:$AL$403,$N7)/12 -> 2754 | Y7: =X7/(1+'1 - Input'!$B$12)^($N7-0.5) -> 2673.3984 | AA7: 2 | AB7: =INDEX('2 - Distribuzione'!$CT$44:$CT$403,12*$AA7) -> 466410.97 | AC7: =INDEX('2 - Distribuzione'!$CU$44:$CU$403,12*$AA7) -> 419303.51 | AD7: =AB7/(1+'1 - Input'!$B$12)^$AA7 -> 448299.66 | AE7: =SUMIFS('2 - Distribuzione'!$CB$44:$CB$403,'2 - Distribuzione'!$BV$44:$BV$403,$AA7) -> 42711.436 | AF7: =SUMIFS('2 - Distribuzione'!$CF$44:$CF$403,'2 - Distribuzione'!$BV$44:$BV$403,$AA7) -> 42711.436 | AG7: =SUMIFS('2 - Distribuzione'!$CE$44:$CE$403,'2 - Distribuzione'!$BV$44:$BV$403,$AA7) -> 0 | AH7: =SUMIFS('2 - Distribuzione'!$CM$44:$CM$403,'2 - Distribuzione'!$BV$44:$BV$403,$AA7) -> 0 | AI7: =SUMIFS('2 - Distribuzione'!$CS$44:$CS$403,'2 - Distribuzione'!$BV$44:$BV$403,$AA7) -> 934.69131 | AJ7: =INDEX('2 - Distribuzione'!$CZ$44:$CZ$403,12*$AA7) -> 0 | AK7: =SUMIFS('2 - Distribuzione'!$CV$44:$CV$403,'2 - Distribuzione'!$BV$44:$BV$403,$AA7)/12 -> 2754 | AL7: =AK7/(1+'1 - Input'!$B$12)^($AA7-0.5) -> 2673.3984
A8: 3 | B8: =INDEX('2 - Distribuzione'!$Z$44:$Z$403,12*$A8) -> 420162.21 | C8: =INDEX('2 - Distribuzione'!$AA$44:$AA$403,12*$A8) -> 475123.16 | D8: =B8/(1+'1 - Input'!$B$12)^$A8 -> 395928.24 | E8: =SUMIFS('2 - Distribuzione'!$H$44:$H$403,'2 - Distribuzione'!$B$44:$B$403,$A8) -> 39150.344 | F8: =SUMIFS('2 - Distribuzione'!$L$44:$L$403,'2 - Distribuzione'!$B$44:$B$403,$A8) -> 28971.254 | G8: =SUMIFS('2 - Distribuzione'!$K$44:$K$403,'2 - Distribuzione'!$B$44:$B$403,$A8) -> 10179.089 | H8: =SUMIFS('2 - Distribuzione'!$S$44:$S$403,'2 - Distribuzione'!$B$44:$B$403,$A8) -> 0 | I8: =SUMIFS('2 - Distribuzione'!$Y$44:$Y$403,'2 - Distribuzione'!$B$44:$B$403,$A8) -> 842.00845 | J8: =INDEX('2 - Distribuzione'!$AF$44:$AF$403,12*$A8) -> 713.76468 | K8: =SUMIFS('2 - Distribuzione'!$AB$44:$AB$403,'2 - Distribuzione'!$B$44:$B$403,$A8)/12 -> 2809.08 | L8: =K8/(1+'1 - Input'!$B$12)^($A8-0.5) -> 2673.3984 | N8: 3 | O8: =INDEX('2 - Distribuzione'!$BJ$44:$BJ$403,12*$N8) -> 420162.21 | P8: =INDEX('2 - Distribuzione'!$BK$44:$BK$403,12*$N8) -> 475123.16 | Q8: =O8/(1+'1 - Input'!$B$12)^$N8 -> 395928.24 | R8: =SUMIFS('2 - Distribuzione'!$AR$44:$AR$403,'2 - Distribuzione'!$AL$44:$AL$403,$N8) -> 39150.344 | S8: =SUMIFS('2 - Distribuzione'!$AV$44:$AV$403,'2 - Distribuzione'!$AL$44:$AL$403,$N8) -> 28971.254 | T8: =SUMIFS('2 - Distribuzione'!$AU$44:$AU$403,'2 - Distribuzione'!$AL$44:$AL$403,$N8) -> 10179.089 | U8: =SUMIFS('2 - Distribuzione'!$BC$44:$BC$403,'2 - Distribuzione'!$AL$44:$AL$403,$N8) -> 0 | V8: =SUMIFS('2 - Distribuzione'!$BI$44:$BI$403,'2 - Distribuzione'!$AL$44:$AL$403,$N8) -> 842.00845 | W8: =INDEX('2 - Distribuzione'!$BP$44:$BP$403,12*$N8) -> 713.76468 | X8: =SUMIFS('2 - Distribuzione'!$BL$44:$BL$403,'2 - Distribuzione'!$AL$44:$AL$403,$N8)/12 -> 2809.08 | Y8: =X8/(1+'1 - Input'!$B$12)^($N8-0.5) -> 2673.3984 | AA8: 3 | AB8: =INDEX('2 - Distribuzione'!$CT$44:$CT$403,12*$AA8) -> 454616.55 | AC8: =INDEX('2 - Distribuzione'!$CU$44:$CU$403,12*$AA8) -> 384823.36 | AD8: =AB8/(1+'1 - Input'!$B$12)^$AA8 -> 428395.32 | AE8: =SUMIFS('2 - Distribuzione'!$CB$44:$CB$403,'2 - Distribuzione'!$BV$44:$BV$403,$AA8) -> 41703.241 | AF8: =SUMIFS('2 - Distribuzione'!$CF$44:$CF$403,'2 - Distribuzione'!$BV$44:$BV$403,$AA8) -> 41703.241 | AG8: =SUMIFS('2 - Distribuzione'!$CE$44:$CE$403,'2 - Distribuzione'!$BV$44:$BV$403,$AA8) -> 0 | AH8: =SUMIFS('2 - Distribuzione'!$CM$44:$CM$403,'2 - Distribuzione'!$BV$44:$BV$403,$AA8) -> 0 | AI8: =SUMIFS('2 - Distribuzione'!$CS$44:$CS$403,'2 - Distribuzione'!$BV$44:$BV$403,$AA8) -> 911.0552 | AJ8: =INDEX('2 - Distribuzione'!$CZ$44:$CZ$403,12*$AA8) -> 0 | AK8: =SUMIFS('2 - Distribuzione'!$CV$44:$CV$403,'2 - Distribuzione'!$BV$44:$BV$403,$AA8)/12 -> 2809.08 | AL8: =AK8/(1+'1 - Input'!$B$12)^($AA8-0.5) -> 2673.3984
A9: 4 | B9: =INDEX('2 - Distribuzione'!$Z$44:$Z$403,12*$A9) -> 395615.07 | C9: =INDEX('2 - Distribuzione'!$AA$44:$AA$403,12*$A9) -> 466077.84 | D9: =B9/(1+'1 - Input'!$B$12)^$A9 -> 365487.18 | E9: =SUMIFS('2 - Distribuzione'!$H$44:$H$403,'2 - Distribuzione'!$B$44:$B$403,$A9) -> 36991.171 | F9: =SUMIFS('2 - Distribuzione'!$L$44:$L$403,'2 - Distribuzione'!$B$44:$B$403,$A9) -> 27373.467 | G9: =SUMIFS('2 - Distribuzione'!$K$44:$K$403,'2 - Distribuzione'!$B$44:$B$403,$A9) -> 9617.7045 | H9: =SUMIFS('2 - Distribuzione'!$S$44:$S$403,'2 - Distribuzione'!$B$44:$B$403,$A9) -> 0 | I9: =SUMIFS('2 - Distribuzione'!$Y$44:$Y$403,'2 - Distribuzione'!$B$44:$B$403,$A9) -> 792.81578 | J9: =INDEX('2 - Distribuzione'!$AF$44:$AF$403,12*$A9) -> 1815.3853 | K9: =SUMIFS('2 - Distribuzione'!$AB$44:$AB$403,'2 - Distribuzione'!$B$44:$B$403,$A9)/12 -> 2865.2616 | L9: =K9/(1+'1 - Input'!$B$12)^($A9-0.5) -> 2673.3984 | N9: 4 | O9: =INDEX('2 - Distribuzione'!$BJ$44:$BJ$403,12*$N9) -> 395615.07 | P9: =INDEX('2 - Distribuzione'!$BK$44:$BK$403,12*$N9) -> 466077.84 | Q9: =O9/(1+'1 - Input'!$B$12)^$N9 -> 365487.18 | R9: =SUMIFS('2 - Distribuzione'!$AR$44:$AR$403,'2 - Distribuzione'!$AL$44:$AL$403,$N9) -> 36991.171 | S9: =SUMIFS('2 - Distribuzione'!$AV$44:$AV$403,'2 - Distribuzione'!$AL$44:$AL$403,$N9) -> 27373.467 | T9: =SUMIFS('2 - Distribuzione'!$AU$44:$AU$403,'2 - Distribuzione'!$AL$44:$AL$403,$N9) -> 9617.7045 | U9: =SUMIFS('2 - Distribuzione'!$BC$44:$BC$403,'2 - Distribuzione'!$AL$44:$AL$403,$N9) -> 0 | V9: =SUMIFS('2 - Distribuzione'!$BI$44:$BI$403,'2 - Distribuzione'!$AL$44:$AL$403,$N9) -> 792.81578 | W9: =INDEX('2 - Distribuzione'!$BP$44:$BP$403,12*$N9) -> 1815.3853 | X9: =SUMIFS('2 - Distribuzione'!$BL$44:$BL$403,'2 - Distribuzione'!$AL$44:$AL$403,$N9)/12 -> 2865.2616 | Y9: =X9/(1+'1 - Input'!$B$12)^($N9-0.5) -> 2673.3984 | AA9: 4 | AB9: =INDEX('2 - Distribuzione'!$CT$44:$CT$403,12*$AA9) -> 441561.81 | AC9: =INDEX('2 - Distribuzione'!$CU$44:$CU$403,12*$AA9) -> 349739.34 | AD9: =AB9/(1+'1 - Input'!$B$12)^$AA9 -> 407934.86 | AE9: =SUMIFS('2 - Distribuzione'!$CB$44:$CB$403,'2 - Distribuzione'!$BV$44:$BV$403,$AA9) -> 40584.557 | AF9: =SUMIFS('2 - Distribuzione'!$CF$44:$CF$403,'2 - Distribuzione'!$BV$44:$BV$403,$AA9) -> 40584.557 | AG9: =SUMIFS('2 - Distribuzione'!$CE$44:$CE$403,'2 - Distribuzione'!$BV$44:$BV$403,$AA9) -> 0 | AH9: =SUMIFS('2 - Distribuzione'!$CM$44:$CM$403,'2 - Distribuzione'!$BV$44:$BV$403,$AA9) -> 0 | AI9: =SUMIFS('2 - Distribuzione'!$CS$44:$CS$403,'2 - Distribuzione'!$BV$44:$BV$403,$AA9) -> 884.89341 | AJ9: =INDEX('2 - Distribuzione'!$CZ$44:$CZ$403,12*$AA9) -> 0 | AK9: =SUMIFS('2 - Distribuzione'!$CV$44:$CV$403,'2 - Distribuzione'!$BV$44:$BV$403,$AA9)/12 -> 2865.2616 | AL9: =AK9/(1+'1 - Input'!$B$12)^($AA9-0.5) -> 2673.3984
A10: 5 | B10: =INDEX('2 - Distribuzione'!$Z$44:$Z$403,12*$A10) -> 369778.76 | C10: =INDEX('2 - Distribuzione'!$AA$44:$AA$403,12*$A10) -> 453862.19 | D10: =B10/(1+'1 - Input'!$B$12)^$A10 -> 334920.01 | E10: =SUMIFS('2 - Distribuzione'!$H$44:$H$403,'2 - Distribuzione'!$B$44:$B$403,$A10) -> 34717.54 | F10: =SUMIFS('2 - Distribuzione'!$L$44:$L$403,'2 - Distribuzione'!$B$44:$B$403,$A10) -> 25690.98 | G10: =SUMIFS('2 - Distribuzione'!$K$44:$K$403,'2 - Distribuzione'!$B$44:$B$403,$A10) -> 9026.5605 | H10: =SUMIFS('2 - Distribuzione'!$S$44:$S$403,'2 - Distribuzione'!$B$44:$B$403,$A10) -> 0 | I10: =SUMIFS('2 - Distribuzione'!$Y$44:$Y$403,'2 - Distribuzione'!$B$44:$B$403,$A10) -> 741.03959 | J10: =INDEX('2 - Distribuzione'!$AF$44:$AF$403,12*$A10) -> 3741.6746 | K10: =SUMIFS('2 - Distribuzione'!$AB$44:$AB$403,'2 - Distribuzione'!$B$44:$B$403,$A10)/12 -> 2922.5668 | L10: =K10/(1+'1 - Input'!$B$12)^($A10-0.5) -> 2673.3984 | N10: 5 | O10: =INDEX('2 - Distribuzione'!$BJ$44:$BJ$403,12*$N10) -> 369778.76 | P10: =INDEX('2 - Distribuzione'!$BK$44:$BK$403,12*$N10) -> 453862.19 | Q10: =O10/(1+'1 - Input'!$B$12)^$N10 -> 334920.01 | R10: =SUMIFS('2 - Distribuzione'!$AR$44:$AR$403,'2 - Distribuzione'!$AL$44:$AL$403,$N10) -> 34717.54 | S10: =SUMIFS('2 - Distribuzione'!$AV$44:$AV$403,'2 - Distribuzione'!$AL$44:$AL$403,$N10) -> 25690.98 | T10: =SUMIFS('2 - Distribuzione'!$AU$44:$AU$403,'2 - Distribuzione'!$AL$44:$AL$403,$N10) -> 9026.5605 | U10: =SUMIFS('2 - Distribuzione'!$BC$44:$BC$403,'2 - Distribuzione'!$AL$44:$AL$403,$N10) -> 0 | V10: =SUMIFS('2 - Distribuzione'!$BI$44:$BI$403,'2 - Distribuzione'!$AL$44:$AL$403,$N10) -> 741.03959 | W10: =INDEX('2 - Distribuzione'!$BP$44:$BP$403,12*$N10) -> 3741.6746 | X10: =SUMIFS('2 - Distribuzione'!$BL$44:$BL$403,'2 - Distribuzione'!$AL$44:$AL$403,$N10)/12 -> 2922.5668 | Y10: =X10/(1+'1 - Input'!$B$12)^($N10-0.5) -> 2673.3984 | AA10: 5 | AB10: =INDEX('2 - Distribuzione'!$CT$44:$CT$403,12*$AA10) -> 427171.88 | AC10: =INDEX('2 - Distribuzione'!$CU$44:$CU$403,12*$AA10) -> 314039.2 | AD10: =AB10/(1+'1 - Input'!$B$12)^$AA10 -> 386902.73 | AE10: =SUMIFS('2 - Distribuzione'!$CB$44:$CB$403,'2 - Distribuzione'!$BV$44:$BV$403,$AA10) -> 39348.793 | AF10: =SUMIFS('2 - Distribuzione'!$CF$44:$CF$403,'2 - Distribuzione'!$BV$44:$BV$403,$AA10) -> 39348.793 | AG10: =SUMIFS('2 - Distribuzione'!$CE$44:$CE$403,'2 - Distribuzione'!$BV$44:$BV$403,$AA10) -> 0 | AH10: =SUMIFS('2 - Distribuzione'!$CM$44:$CM$403,'2 - Distribuzione'!$BV$44:$BV$403,$AA10) -> 0 | AI10: =SUMIFS('2 - Distribuzione'!$CS$44:$CS$403,'2 - Distribuzione'!$BV$44:$BV$403,$AA10) -> 856.05588 | AJ10: =INDEX('2 - Distribuzione'!$CZ$44:$CZ$403,12*$AA10) -> 0 | AK10: =SUMIFS('2 - Distribuzione'!$CV$44:$CV$403,'2 - Distribuzione'!$BV$44:$BV$403,$AA10)/12 -> 2922.5668 | AL10: =AK10/(1+'1 - Input'!$B$12)^($AA10-0.5) -> 2673.3984
A11: 6 | B11: =INDEX('2 - Distribuzione'!$Z$44:$Z$403,12*$A11) -> 342608.14 | C11: =INDEX('2 - Distribuzione'!$AA$44:$AA$403,12*$A11) -> 438102.91 | D11: =B11/(1+'1 - Input'!$B$12)^$A11 -> 304226.22 | E11: =SUMIFS('2 - Distribuzione'!$H$44:$H$403,'2 - Distribuzione'!$B$44:$B$403,$A11) -> 32325.434 | F11: =SUMIFS('2 - Distribuzione'!$L$44:$L$403,'2 - Distribuzione'!$B$44:$B$403,$A11) -> 23920.821 | G11: =SUMIFS('2 - Distribuzione'!$K$44:$K$403,'2 - Distribuzione'!$B$44:$B$403,$A11) -> 8404.613 | H11: =SUMIFS('2 - Distribuzione'!$S$44:$S$403,'2 - Distribuzione'!$B$44:$B$403,$A11) -> 0 | I11: =SUMIFS('2 - Distribuzione'!$Y$44:$Y$403,'2 - Distribuzione'!$B$44:$B$403,$A11) -> 686.58946 | J11: =INDEX('2 - Distribuzione'!$AF$44:$AF$403,12*$A11) -> 6771.5916 | K11: =SUMIFS('2 - Distribuzione'!$AB$44:$AB$403,'2 - Distribuzione'!$B$44:$B$403,$A11)/12 -> 2981.0182 | L11: =K11/(1+'1 - Input'!$B$12)^($A11-0.5) -> 2673.3984 | N11: 6 | O11: =INDEX('2 - Distribuzione'!$BJ$44:$BJ$403,12*$N11) -> 342608.14 | P11: =INDEX('2 - Distribuzione'!$BK$44:$BK$403,12*$N11) -> 438102.91 | Q11: =O11/(1+'1 - Input'!$B$12)^$N11 -> 304226.22 | R11: =SUMIFS('2 - Distribuzione'!$AR$44:$AR$403,'2 - Distribuzione'!$AL$44:$AL$403,$N11) -> 32325.434 | S11: =SUMIFS('2 - Distribuzione'!$AV$44:$AV$403,'2 - Distribuzione'!$AL$44:$AL$403,$N11) -> 23920.821 | T11: =SUMIFS('2 - Distribuzione'!$AU$44:$AU$403,'2 - Distribuzione'!$AL$44:$AL$403,$N11) -> 8404.613 | U11: =SUMIFS('2 - Distribuzione'!$BC$44:$BC$403,'2 - Distribuzione'!$AL$44:$AL$403,$N11) -> 0 | V11: =SUMIFS('2 - Distribuzione'!$BI$44:$BI$403,'2 - Distribuzione'!$AL$44:$AL$403,$N11) -> 686.58946 | W11: =INDEX('2 - Distribuzione'!$BP$44:$BP$403,12*$N11) -> 6771.5916 | X11: =SUMIFS('2 - Distribuzione'!$BL$44:$BL$403,'2 - Distribuzione'!$AL$44:$AL$403,$N11)/12 -> 2981.0182 | Y11: =X11/(1+'1 - Input'!$B$12)^($N11-0.5) -> 2673.3984 | AA11: 6 | AB11: =INDEX('2 - Distribuzione'!$CT$44:$CT$403,12*$AA11) -> 411367.95 | AC11: =INDEX('2 - Distribuzione'!$CU$44:$CU$403,12*$AA11) -> 277710.45 | AD11: =AB11/(1+'1 - Input'!$B$12)^$AA11 -> 365282.97 | AE11: =SUMIFS('2 - Distribuzione'!$CB$44:$CB$403,'2 - Distribuzione'!$BV$44:$BV$403,$AA11) -> 37989.015 | AF11: =SUMIFS('2 - Distribuzione'!$CF$44:$CF$403,'2 - Distribuzione'!$BV$44:$BV$403,$AA11) -> 37989.015 | AG11: =SUMIFS('2 - Distribuzione'!$CE$44:$CE$403,'2 - Distribuzione'!$BV$44:$BV$403,$AA11) -> 0 | AH11: =SUMIFS('2 - Distribuzione'!$CM$44:$CM$403,'2 - Distribuzione'!$BV$44:$BV$403,$AA11) -> 0 | AI11: =SUMIFS('2 - Distribuzione'!$CS$44:$CS$403,'2 - Distribuzione'!$BV$44:$BV$403,$AA11) -> 824.38468 | AJ11: =INDEX('2 - Distribuzione'!$CZ$44:$CZ$403,12*$AA11) -> 0 | AK11: =SUMIFS('2 - Distribuzione'!$CV$44:$CV$403,'2 - Distribuzione'!$BV$44:$BV$403,$AA11)/12 -> 2981.0182 | AL11: =AK11/(1+'1 - Input'!$B$12)^($AA11-0.5) -> 2673.3984
A12: 7 | B12: =INDEX('2 - Distribuzione'!$Z$44:$Z$403,12*$A12) -> 314056.73 | C12: =INDEX('2 - Distribuzione'!$AA$44:$AA$403,12*$A12) -> 418391.63 | D12: =B12/(1+'1 - Input'!$B$12)^$A12 -> 273405.29 | E12: =SUMIFS('2 - Distribuzione'!$H$44:$H$403,'2 - Distribuzione'!$B$44:$B$403,$A12) -> 29810.716 | F12: =SUMIFS('2 - Distribuzione'!$L$44:$L$403,'2 - Distribuzione'!$B$44:$B$403,$A12) -> 22059.93 | G12: =SUMIFS('2 - Distribuzione'!$K$44:$K$403,'2 - Distribuzione'!$B$44:$B$403,$A12) -> 7750.7862 | H12: =SUMIFS('2 - Distribuzione'!$S$44:$S$403,'2 - Distribuzione'!$B$44:$B$403,$A12) -> 0 | I12: =SUMIFS('2 - Distribuzione'!$Y$44:$Y$403,'2 - Distribuzione'!$B$44:$B$403,$A12) -> 629.37221 | J12: =INDEX('2 - Distribuzione'!$AF$44:$AF$403,12*$A12) -> 11216.679 | K12: =SUMIFS('2 - Distribuzione'!$AB$44:$AB$403,'2 - Distribuzione'!$B$44:$B$403,$A12)/12 -> 3040.6385 | L12: =K12/(1+'1 - Input'!$B$12)^($A12-0.5) -> 2673.3984 | N12: 7 | O12: =INDEX('2 - Distribuzione'!$BJ$44:$BJ$403,12*$N12) -> 314056.73 | P12: =INDEX('2 - Distribuzione'!$BK$44:$BK$403,12*$N12) -> 418391.63 | Q12: =O12/(1+'1 - Input'!$B$12)^$N12 -> 273405.29 | R12: =SUMIFS('2 - Distribuzione'!$AR$44:$AR$403,'2 - Distribuzione'!$AL$44:$AL$403,$N12) -> 29810.716 | S12: =SUMIFS('2 - Distribuzione'!$AV$44:$AV$403,'2 - Distribuzione'!$AL$44:$AL$403,$N12) -> 22059.93 | T12: =SUMIFS('2 - Distribuzione'!$AU$44:$AU$403,'2 - Distribuzione'!$AL$44:$AL$403,$N12) -> 7750.7862 | U12: =SUMIFS('2 - Distribuzione'!$BC$44:$BC$403,'2 - Distribuzione'!$AL$44:$AL$403,$N12) -> 0 | V12: =SUMIFS('2 - Distribuzione'!$BI$44:$BI$403,'2 - Distribuzione'!$AL$44:$AL$403,$N12) -> 629.37221 | W12: =INDEX('2 - Distribuzione'!$BP$44:$BP$403,12*$N12) -> 11216.679 | X12: =SUMIFS('2 - Distribuzione'!$BL$44:$BL$403,'2 - Distribuzione'!$AL$44:$AL$403,$N12)/12 -> 3040.6385 | Y12: =X12/(1+'1 - Input'!$B$12)^($N12-0.5) -> 2673.3984 | AA12: 7 | AB12: =INDEX('2 - Distribuzione'!$CT$44:$CT$403,12*$AA12) -> 394047.13 | AC12: =INDEX('2 - Distribuzione'!$CU$44:$CU$403,12*$AA12) -> 240796.91 | AD12: =AB12/(1+'1 - Input'!$B$12)^$AA12 -> 343041.74 | AE12: =SUMIFS('2 - Distribuzione'!$CB$44:$CB$403,'2 - Distribuzione'!$BV$44:$BV$403,$AA12) -> 36497.707 | AF12: =SUMIFS('2 - Distribuzione'!$CF$44:$CF$403,'2 - Distribuzione'!$BV$44:$BV$403,$AA12) -> 36497.707 | AG12: =SUMIFS('2 - Distribuzione'!$CE$44:$CE$403,'2 - Distribuzione'!$BV$44:$BV$403,$AA12) -> 0 | AH12: =SUMIFS('2 - Distribuzione'!$CM$44:$CM$403,'2 - Distribuzione'!$BV$44:$BV$403,$AA12) -> 19.915833 | AI12: =SUMIFS('2 - Distribuzione'!$CS$44:$CS$403,'2 - Distribuzione'!$BV$44:$BV$403,$AA12) -> 789.67361 | AJ12: =INDEX('2 - Distribuzione'!$CZ$44:$CZ$403,12*$AA12) -> 0 | AK12: =SUMIFS('2 - Distribuzione'!$CV$44:$CV$403,'2 - Distribuzione'!$BV$44:$BV$403,$AA12)/12 -> 3040.6385 | AL12: =AK12/(1+'1 - Input'!$B$12)^($AA12-0.5) -> 2673.3984
A13: 8 | B13: =INDEX('2 - Distribuzione'!$Z$44:$Z$403,12*$A13) -> 284076.63 | C13: =INDEX('2 - Distribuzione'!$AA$44:$AA$403,12*$A13) -> 394281.88 | D13: =B13/(1+'1 - Input'!$B$12)^$A13 -> 242456.67 | E13: =SUMIFS('2 - Distribuzione'!$H$44:$H$403,'2 - Distribuzione'!$B$44:$B$403,$A13) -> 27169.121 | F13: =SUMIFS('2 - Distribuzione'!$L$44:$L$403,'2 - Distribuzione'!$B$44:$B$403,$A13) -> 20105.15 | G13: =SUMIFS('2 - Distribuzione'!$K$44:$K$403,'2 - Distribuzione'!$B$44:$B$403,$A13) -> 7063.9715 | H13: =SUMIFS('2 - Distribuzione'!$S$44:$S$403,'2 - Distribuzione'!$B$44:$B$403,$A13) -> 0 | I13: =SUMIFS('2 - Distribuzione'!$Y$44:$Y$403,'2 - Distribuzione'!$B$44:$B$403,$A13) -> 569.29185 | J13: =INDEX('2 - Distribuzione'!$AF$44:$AF$403,12*$A13) -> 17424.027 | K13: =SUMIFS('2 - Distribuzione'!$AB$44:$AB$403,'2 - Distribuzione'!$B$44:$B$403,$A13)/12 -> 3101.4513 | L13: =K13/(1+'1 - Input'!$B$12)^($A13-0.5) -> 2673.3984 | N13: 8 | O13: =INDEX('2 - Distribuzione'!$BJ$44:$BJ$403,12*$N13) -> 284076.63 | P13: =INDEX('2 - Distribuzione'!$BK$44:$BK$403,12*$N13) -> 394281.88 | Q13: =O13/(1+'1 - Input'!$B$12)^$N13 -> 242456.67 | R13: =SUMIFS('2 - Distribuzione'!$AR$44:$AR$403,'2 - Distribuzione'!$AL$44:$AL$403,$N13) -> 27169.121 | S13: =SUMIFS('2 - Distribuzione'!$AV$44:$AV$403,'2 - Distribuzione'!$AL$44:$AL$403,$N13) -> 20105.15 | T13: =SUMIFS('2 - Distribuzione'!$AU$44:$AU$403,'2 - Distribuzione'!$AL$44:$AL$403,$N13) -> 7063.9715 | U13: =SUMIFS('2 - Distribuzione'!$BC$44:$BC$403,'2 - Distribuzione'!$AL$44:$AL$403,$N13) -> 0 | V13: =SUMIFS('2 - Distribuzione'!$BI$44:$BI$403,'2 - Distribuzione'!$AL$44:$AL$403,$N13) -> 569.29185 | W13: =INDEX('2 - Distribuzione'!$BP$44:$BP$403,12*$N13) -> 17424.027 | X13: =SUMIFS('2 - Distribuzione'!$BL$44:$BL$403,'2 - Distribuzione'!$AL$44:$AL$403,$N13)/12 -> 3101.4513 | Y13: =X13/(1+'1 - Input'!$B$12)^($N13-0.5) -> 2673.3984 | AA13: 8 | AB13: =INDEX('2 - Distribuzione'!$CT$44:$CT$403,12*$AA13) -> 374859.67 | AC13: =INDEX('2 - Distribuzione'!$CU$44:$CU$403,12*$AA13) -> 204014.36 | AD13: =AB13/(1+'1 - Input'!$B$12)^$AA13 -> 319939.11 | AE13: =SUMIFS('2 - Distribuzione'!$CB$44:$CB$403,'2 - Distribuzione'!$BV$44:$BV$403,$AA13) -> 34855.527 | AF13: =SUMIFS('2 - Distribuzione'!$CF$44:$CF$403,'2 - Distribuzione'!$BV$44:$BV$403,$AA13) -> 34855.527 | AG13: =SUMIFS('2 - Distribuzione'!$CE$44:$CE$403,'2 - Distribuzione'!$BV$44:$BV$403,$AA13) -> 0 | AH13: =SUMIFS('2 - Distribuzione'!$CM$44:$CM$403,'2 - Distribuzione'!$BV$44:$BV$403,$AA13) -> 296.43827 | AI13: =SUMIFS('2 - Distribuzione'!$CS$44:$CS$403,'2 - Distribuzione'!$BV$44:$BV$403,$AA13) -> 751.22177 | AJ13: =INDEX('2 - Distribuzione'!$CZ$44:$CZ$403,12*$AA13) -> 0 | AK13: =SUMIFS('2 - Distribuzione'!$CV$44:$CV$403,'2 - Distribuzione'!$BV$44:$BV$403,$AA13)/12 -> 3101.4513 | AL13: =AK13/(1+'1 - Input'!$B$12)^($AA13-0.5) -> 2673.3984
A14: 9 | B14: =INDEX('2 - Distribuzione'!$Z$44:$Z$403,12*$A14) -> 252618.49 | C14: =INDEX('2 - Distribuzione'!$AA$44:$AA$403,12*$A14) -> 365285.86 | D14: =B14/(1+'1 - Input'!$B$12)^$A14 -> 211379.85 | E14: =SUMIFS('2 - Distribuzione'!$H$44:$H$403,'2 - Distribuzione'!$B$44:$B$403,$A14) -> 24396.258 | F14: =SUMIFS('2 - Distribuzione'!$L$44:$L$403,'2 - Distribuzione'!$B$44:$B$403,$A14) -> 18053.231 | G14: =SUMIFS('2 - Distribuzione'!$K$44:$K$403,'2 - Distribuzione'!$B$44:$B$403,$A14) -> 6343.027 | H14: =SUMIFS('2 - Distribuzione'!$S$44:$S$403,'2 - Distribuzione'!$B$44:$B$403,$A14) -> 0 | I14: =SUMIFS('2 - Distribuzione'!$Y$44:$Y$403,'2 - Distribuzione'!$B$44:$B$403,$A14) -> 506.24948 | J14: =INDEX('2 - Distribuzione'!$AF$44:$AF$403,12*$A14) -> 25779.479 | K14: =SUMIFS('2 - Distribuzione'!$AB$44:$AB$403,'2 - Distribuzione'!$B$44:$B$403,$A14)/12 -> 3163.4803 | L14: =K14/(1+'1 - Input'!$B$12)^($A14-0.5) -> 2673.3984 | N14: 9 | O14: =INDEX('2 - Distribuzione'!$BJ$44:$BJ$403,12*$N14) -> 252618.49 | P14: =INDEX('2 - Distribuzione'!$BK$44:$BK$403,12*$N14) -> 365285.86 | Q14: =O14/(1+'1 - Input'!$B$12)^$N14 -> 211379.85 | R14: =SUMIFS('2 - Distribuzione'!$AR$44:$AR$403,'2 - Distribuzione'!$AL$44:$AL$403,$N14) -> 24396.258 | S14: =SUMIFS('2 - Distribuzione'!$AV$44:$AV$403,'2 - Distribuzione'!$AL$44:$AL$403,$N14) -> 18053.231 | T14: =SUMIFS('2 - Distribuzione'!$AU$44:$AU$403,'2 - Distribuzione'!$AL$44:$AL$403,$N14) -> 6343.027 | U14: =SUMIFS('2 - Distribuzione'!$BC$44:$BC$403,'2 - Distribuzione'!$AL$44:$AL$403,$N14) -> 0 | V14: =SUMIFS('2 - Distribuzione'!$BI$44:$BI$403,'2 - Distribuzione'!$AL$44:$AL$403,$N14) -> 506.24948 | W14: =INDEX('2 - Distribuzione'!$BP$44:$BP$403,12*$N14) -> 25779.479 | X14: =SUMIFS('2 - Distribuzione'!$BL$44:$BL$403,'2 - Distribuzione'!$AL$44:$AL$403,$N14)/12 -> 3163.4803 | Y14: =X14/(1+'1 - Input'!$B$12)^($N14-0.5) -> 2673.3984 | AA14: 9 | AB14: =INDEX('2 - Distribuzione'!$CT$44:$CT$403,12*$AA14) -> 353540.73 | AC14: =INDEX('2 - Distribuzione'!$CU$44:$CU$403,12*$AA14) -> 167790.9 | AD14: =AB14/(1+'1 - Input'!$B$12)^$AA14 -> 295827.07 | AE14: =SUMIFS('2 - Distribuzione'!$CB$44:$CB$403,'2 - Distribuzione'!$BV$44:$BV$403,$AA14) -> 33033.274 | AF14: =SUMIFS('2 - Distribuzione'!$CF$44:$CF$403,'2 - Distribuzione'!$BV$44:$BV$403,$AA14) -> 33033.274 | AG14: =SUMIFS('2 - Distribuzione'!$CE$44:$CE$403,'2 - Distribuzione'!$BV$44:$BV$403,$AA14) -> 0 | AH14: =SUMIFS('2 - Distribuzione'!$CM$44:$CM$403,'2 - Distribuzione'!$BV$44:$BV$403,$AA14) -> 728.89708 | AI14: =SUMIFS('2 - Distribuzione'!$CS$44:$CS$403,'2 - Distribuzione'!$BV$44:$BV$403,$AA14) -> 708.49847 | AJ14: =INDEX('2 - Distribuzione'!$CZ$44:$CZ$403,12*$AA14) -> 0 | AK14: =SUMIFS('2 - Distribuzione'!$CV$44:$CV$403,'2 - Distribuzione'!$BV$44:$BV$403,$AA14)/12 -> 3163.4803 | AL14: =AK14/(1+'1 - Input'!$B$12)^($AA14-0.5) -> 2673.3984
A15: 10 | B15: =INDEX('2 - Distribuzione'!$Z$44:$Z$403,12*$A15) -> 219631.46 | C15: =INDEX('2 - Distribuzione'!$AA$44:$AA$403,12*$A15) -> 330870.99 | D15: =B15/(1+'1 - Input'!$B$12)^$A15 -> 180174.3 | E15: =SUMIFS('2 - Distribuzione'!$H$44:$H$403,'2 - Distribuzione'!$B$44:$B$403,$A15) -> 21487.6 | F15: =SUMIFS('2 - Distribuzione'!$L$44:$L$403,'2 - Distribuzione'!$B$44:$B$403,$A15) -> 15900.824 | G15: =SUMIFS('2 - Distribuzione'!$K$44:$K$403,'2 - Distribuzione'!$B$44:$B$403,$A15) -> 5586.7759 | H15: =SUMIFS('2 - Distribuzione'!$S$44:$S$403,'2 - Distribuzione'!$B$44:$B$403,$A15) -> 0 | I15: =SUMIFS('2 - Distribuzione'!$Y$44:$Y$403,'2 - Distribuzione'!$B$44:$B$403,$A15) -> 440.14321 | J15: =INDEX('2 - Distribuzione'!$AF$44:$AF$403,12*$A15) -> 36711.099 | K15: =SUMIFS('2 - Distribuzione'!$AB$44:$AB$403,'2 - Distribuzione'!$B$44:$B$403,$A15)/12 -> 3226.7499 | L15: =K15/(1+'1 - Input'!$B$12)^($A15-0.5) -> 2673.3984 | N15: 10 | O15: =INDEX('2 - Distribuzione'!$BJ$44:$BJ$403,12*$N15) -> 219631.46 | P15: =INDEX('2 - Distribuzione'!$BK$44:$BK$403,12*$N15) -> 330870.99 | Q15: =O15/(1+'1 - Input'!$B$12)^$N15 -> 180174.3 | R15: =SUMIFS('2 - Distribuzione'!$AR$44:$AR$403,'2 - Distribuzione'!$AL$44:$AL$403,$N15) -> 21487.6 | S15: =SUMIFS('2 - Distribuzione'!$AV$44:$AV$403,'2 - Distribuzione'!$AL$44:$AL$403,$N15) -> 15900.824 | T15: =SUMIFS('2 - Distribuzione'!$AU$44:$AU$403,'2 - Distribuzione'!$AL$44:$AL$403,$N15) -> 5586.7759 | U15: =SUMIFS('2 - Distribuzione'!$BC$44:$BC$403,'2 - Distribuzione'!$AL$44:$AL$403,$N15) -> 0 | V15: =SUMIFS('2 - Distribuzione'!$BI$44:$BI$403,'2 - Distribuzione'!$AL$44:$AL$403,$N15) -> 440.14321 | W15: =INDEX('2 - Distribuzione'!$BP$44:$BP$403,12*$N15) -> 36711.099 | X15: =SUMIFS('2 - Distribuzione'!$BL$44:$BL$403,'2 - Distribuzione'!$AL$44:$AL$403,$N15)/12 -> 3226.7499 | Y15: =X15/(1+'1 - Input'!$B$12)^($N15-0.5) -> 2673.3984 | AA15: 10 | AB15: =INDEX('2 - Distribuzione'!$CT$44:$CT$403,12*$AA15) -> 329797.96 | AC15: =INDEX('2 - Distribuzione'!$CU$44:$CU$403,12*$AA15) -> 132594.5 | AD15: =AB15/(1+'1 - Input'!$B$12)^$AA15 -> 270549.2 | AE15: =SUMIFS('2 - Distribuzione'!$CB$44:$CB$403,'2 - Distribuzione'!$BV$44:$BV$403,$AA15) -> 31006.455 | AF15: =SUMIFS('2 - Distribuzione'!$CF$44:$CF$403,'2 - Distribuzione'!$BV$44:$BV$403,$AA15) -> 31006.455 | AG15: =SUMIFS('2 - Distribuzione'!$CE$44:$CE$403,'2 - Distribuzione'!$BV$44:$BV$403,$AA15) -> 0 | AH15: =SUMIFS('2 - Distribuzione'!$CM$44:$CM$403,'2 - Distribuzione'!$BV$44:$BV$403,$AA15) -> 1331.7354 | AI15: =SUMIFS('2 - Distribuzione'!$CS$44:$CS$403,'2 - Distribuzione'!$BV$44:$BV$403,$AA15) -> 660.91776 | AJ15: =INDEX('2 - Distribuzione'!$CZ$44:$CZ$403,12*$AA15) -> 0 | AK15: =SUMIFS('2 - Distribuzione'!$CV$44:$CV$403,'2 - Distribuzione'!$BV$44:$BV$403,$AA15)/12 -> 3226.7499 | AL15: =AK15/(1+'1 - Input'!$B$12)^($AA15-0.5) -> 2673.3984
A16: 11 | B16: =INDEX('2 - Distribuzione'!$Z$44:$Z$403,12*$A16) -> 185063.18 | C16: =INDEX('2 - Distribuzione'!$AA$44:$AA$403,12*$A16) -> 290456.14 | D16: =B16/(1+'1 - Input'!$B$12)^$A16 -> 148839.47 | E16: =SUMIFS('2 - Distribuzione'!$H$44:$H$403,'2 - Distribuzione'!$B$44:$B$403,$A16) -> 18438.485 | F16: =SUMIFS('2 - Distribuzione'!$L$44:$L$403,'2 - Distribuzione'!$B$44:$B$403,$A16) -> 13644.479 | G16: =SUMIFS('2 - Distribuzione'!$K$44:$K$403,'2 - Distribuzione'!$B$44:$B$403,$A16) -> 4794.006 | H16: =SUMIFS('2 - Distribuzione'!$S$44:$S$403,'2 - Distribuzione'!$B$44:$B$403,$A16) -> 0 | I16: =SUMIFS('2 - Distribuzione'!$Y$44:$Y$403,'2 - Distribuzione'!$B$44:$B$403,$A16) -> 370.86809 | J16: =INDEX('2 - Distribuzione'!$AF$44:$AF$403,12*$A16) -> 50692.929 | K16: =SUMIFS('2 - Distribuzione'!$AB$44:$AB$403,'2 - Distribuzione'!$B$44:$B$403,$A16)/12 -> 3291.2849 | L16: =K16/(1+'1 - Input'!$B$12)^($A16-0.5) -> 2673.3984 | N16: 11 | O16: =INDEX('2 - Distribuzione'!$BJ$44:$BJ$403,12*$N16) -> 185063.18 | P16: =INDEX('2 - Distribuzione'!$BK$44:$BK$403,12*$N16) -> 290456.14 | Q16: =O16/(1+'1 - Input'!$B$12)^$N16 -> 148839.47 | R16: =SUMIFS('2 - Distribuzione'!$AR$44:$AR$403,'2 - Distribuzione'!$AL$44:$AL$403,$N16) -> 18438.485 | S16: =SUMIFS('2 - Distribuzione'!$AV$44:$AV$403,'2 - Distribuzione'!$AL$44:$AL$403,$N16) -> 13644.479 | T16: =SUMIFS('2 - Distribuzione'!$AU$44:$AU$403,'2 - Distribuzione'!$AL$44:$AL$403,$N16) -> 4794.006 | U16: =SUMIFS('2 - Distribuzione'!$BC$44:$BC$403,'2 - Distribuzione'!$AL$44:$AL$403,$N16) -> 0 | V16: =SUMIFS('2 - Distribuzione'!$BI$44:$BI$403,'2 - Distribuzione'!$AL$44:$AL$403,$N16) -> 370.86809 | W16: =INDEX('2 - Distribuzione'!$BP$44:$BP$403,12*$N16) -> 50692.929 | X16: =SUMIFS('2 - Distribuzione'!$BL$44:$BL$403,'2 - Distribuzione'!$AL$44:$AL$403,$N16)/12 -> 3291.2849 | Y16: =X16/(1+'1 - Input'!$B$12)^($N16-0.5) -> 2673.3984 | AA16: 11 | AB16: =INDEX('2 - Distribuzione'!$CT$44:$CT$403,12*$AA16) -> 303282.34 | AC16: =INDEX('2 - Distribuzione'!$CU$44:$CU$403,12*$AA16) -> 99009.303 | AD16: =AB16/(1+'1 - Input'!$B$12)^$AA16 -> 243918.78 | AE16: =SUMIFS('2 - Distribuzione'!$CB$44:$CB$403,'2 - Distribuzione'!$BV$44:$BV$403,$AA16) -> 28746.364 | AF16: =SUMIFS('2 - Distribuzione'!$CF$44:$CF$403,'2 - Distribuzione'!$BV$44:$BV$403,$AA16) -> 28746.364 | AG16: =SUMIFS('2 - Distribuzione'!$CE$44:$CE$403,'2 - Distribuzione'!$BV$44:$BV$403,$AA16) -> 0 | AH16: =SUMIFS('2 - Distribuzione'!$CM$44:$CM$403,'2 - Distribuzione'!$BV$44:$BV$403,$AA16) -> 2146.2777 | AI16: =SUMIFS('2 - Distribuzione'!$CS$44:$CS$403,'2 - Distribuzione'!$BV$44:$BV$403,$AA16) -> 607.78025 | AJ16: =INDEX('2 - Distribuzione'!$CZ$44:$CZ$403,12*$AA16) -> 0 | AK16: =SUMIFS('2 - Distribuzione'!$CV$44:$CV$403,'2 - Distribuzione'!$BV$44:$BV$403,$AA16)/12 -> 3291.2849 | AL16: =AK16/(1+'1 - Input'!$B$12)^($AA16-0.5) -> 2673.3984
A17: 12 | B17: =INDEX('2 - Distribuzione'!$Z$44:$Z$403,12*$A17) -> 148859.68 | C17: =INDEX('2 - Distribuzione'!$AA$44:$AA$403,12*$A17) -> 243407.56 | D17: =B17/(1+'1 - Input'!$B$12)^$A17 -> 117374.84 | E17: =SUMIFS('2 - Distribuzione'!$H$44:$H$403,'2 - Distribuzione'!$B$44:$B$403,$A17) -> 15244.111 | F17: =SUMIFS('2 - Distribuzione'!$L$44:$L$403,'2 - Distribuzione'!$B$44:$B$403,$A17) -> 11280.642 | G17: =SUMIFS('2 - Distribuzione'!$K$44:$K$403,'2 - Distribuzione'!$B$44:$B$403,$A17) -> 3963.4688 | H17: =SUMIFS('2 - Distribuzione'!$S$44:$S$403,'2 - Distribuzione'!$B$44:$B$403,$A17) -> 0 | I17: =SUMIFS('2 - Distribuzione'!$Y$44:$Y$403,'2 - Distribuzione'!$B$44:$B$403,$A17) -> 298.316 | J17: =INDEX('2 - Distribuzione'!$AF$44:$AF$403,12*$A17) -> 68249.038 | K17: =SUMIFS('2 - Distribuzione'!$AB$44:$AB$403,'2 - Distribuzione'!$B$44:$B$403,$A17)/12 -> 3357.1106 | L17: =K17/(1+'1 - Input'!$B$12)^($A17-0.5) -> 2673.3984 | N17: 12 | O17: =INDEX('2 - Distribuzione'!$BJ$44:$BJ$403,12*$N17) -> 148859.68 | P17: =INDEX('2 - Distribuzione'!$BK$44:$BK$403,12*$N17) -> 243407.56 | Q17: =O17/(1+'1 - Input'!$B$12)^$N17 -> 117374.84 | R17: =SUMIFS('2 - Distribuzione'!$AR$44:$AR$403,'2 - Distribuzione'!$AL$44:$AL$403,$N17) -> 15244.111 | S17: =SUMIFS('2 - Distribuzione'!$AV$44:$AV$403,'2 - Distribuzione'!$AL$44:$AL$403,$N17) -> 11280.642 | T17: =SUMIFS('2 - Distribuzione'!$AU$44:$AU$403,'2 - Distribuzione'!$AL$44:$AL$403,$N17) -> 3963.4688 | U17: =SUMIFS('2 - Distribuzione'!$BC$44:$BC$403,'2 - Distribuzione'!$AL$44:$AL$403,$N17) -> 0 | V17: =SUMIFS('2 - Distribuzione'!$BI$44:$BI$403,'2 - Distribuzione'!$AL$44:$AL$403,$N17) -> 298.316 | W17: =INDEX('2 - Distribuzione'!$BP$44:$BP$403,12*$N17) -> 68249.038 | X17: =SUMIFS('2 - Distribuzione'!$BL$44:$BL$403,'2 - Distribuzione'!$AL$44:$AL$403,$N17)/12 -> 3357.1106 | Y17: =X17/(1+'1 - Input'!$B$12)^($N17-0.5) -> 2673.3984 | AA17: 12 | AB17: =INDEX('2 - Distribuzione'!$CT$44:$CT$403,12*$AA17) -> 273574.2 | AC17: =INDEX('2 - Distribuzione'!$CU$44:$CU$403,12*$AA17) -> 67766.761 | AD17: =AB17/(1+'1 - Input'!$B$12)^$AA17 -> 215711.39 | AE17: =SUMIFS('2 - Distribuzione'!$CB$44:$CB$403,'2 - Distribuzione'!$BV$44:$BV$403,$AA17) -> 26218.616 | AF17: =SUMIFS('2 - Distribuzione'!$CF$44:$CF$403,'2 - Distribuzione'!$BV$44:$BV$403,$AA17) -> 26218.616 | AG17: =SUMIFS('2 - Distribuzione'!$CE$44:$CE$403,'2 - Distribuzione'!$BV$44:$BV$403,$AA17) -> 0 | AH17: =SUMIFS('2 - Distribuzione'!$CM$44:$CM$403,'2 - Distribuzione'!$BV$44:$BV$403,$AA17) -> 3224.9105 | AI17: =SUMIFS('2 - Distribuzione'!$CS$44:$CS$403,'2 - Distribuzione'!$BV$44:$BV$403,$AA17) -> 548.24489 | AJ17: =INDEX('2 - Distribuzione'!$CZ$44:$CZ$403,12*$AA17) -> 0 | AK17: =SUMIFS('2 - Distribuzione'!$CV$44:$CV$403,'2 - Distribuzione'!$BV$44:$BV$403,$AA17)/12 -> 3357.1106 | AL17: =AK17/(1+'1 - Input'!$B$12)^($AA17-0.5) -> 2673.3984
... A35: 30 | B35: =INDEX('2 - Distribuzione'!$Z$44:$Z$403,12*$A35) -> 0 | C35: =INDEX('2 - Distribuzione'!$AA$44:$AA$403,12*$A35) -> 0 | D35: =B35/(1+'1 - Input'!$B$12)^$A35 -> 0 | E35: =SUMIFS('2 - Distribuzione'!$H$44:$H$403,'2 - Distribuzione'!$B$44:$B$403,$A35) -> 0 | F35: =SUMIFS('2 - Distribuzione'!$L$44:$L$403,'2 - Distribuzione'!$B$44:$B$403,$A35) -> 0 | G35: =SUMIFS('2 - Distribuzione'!$K$44:$K$403,'2 - Distribuzione'!$B$44:$B$403,$A35) -> 0 | H35: =SUMIFS('2 - Distribuzione'!$S$44:$S$403,'2 - Distribuzione'!$B$44:$B$403,$A35) -> 0 | I35: =SUMIFS('2 - Distribuzione'!$Y$44:$Y$403,'2 - Distribuzione'!$B$44:$B$403,$A35) -> 0 | J35: =INDEX('2 - Distribuzione'!$AF$44:$AF$403,12*$A35) -> 174289.24 | K35: =SUMIFS('2 - Distribuzione'!$AB$44:$AB$403,'2 - Distribuzione'!$B$44:$B$403,$A35)/12 -> 0 | L35: =K35/(1+'1 - Input'!$B$12)^($A35-0.5) -> 0 | N35: 30 | O35: =INDEX('2 - Distribuzione'!$BJ$44:$BJ$403,12*$N35) -> 0 | P35: =INDEX('2 - Distribuzione'!$BK$44:$BK$403,12*$N35) -> 0 | Q35: =O35/(1+'1 - Input'!$B$12)^$N35 -> 0 | R35: =SUMIFS('2 - Distribuzione'!$AR$44:$AR$403,'2 - Distribuzione'!$AL$44:$AL$403,$N35) -> 0 | S35: =SUMIFS('2 - Distribuzione'!$AV$44:$AV$403,'2 - Distribuzione'!$AL$44:$AL$403,$N35) -> 0 | T35: =SUMIFS('2 - Distribuzione'!$AU$44:$AU$403,'2 - Distribuzione'!$AL$44:$AL$403,$N35) -> 0 | U35: =SUMIFS('2 - Distribuzione'!$BC$44:$BC$403,'2 - Distribuzione'!$AL$44:$AL$403,$N35) -> 0 | V35: =SUMIFS('2 - Distribuzione'!$BI$44:$BI$403,'2 - Distribuzione'!$AL$44:$AL$403,$N35) -> 0 | W35: =INDEX('2 - Distribuzione'!$BP$44:$BP$403,12*$N35) -> 174289.24 | X35: =SUMIFS('2 - Distribuzione'!$BL$44:$BL$403,'2 - Distribuzione'!$AL$44:$AL$403,$N35)/12 -> 0 | Y35: =X35/(1+'1 - Input'!$B$12)^($N35-0.5) -> 0 | AA35: 30 | AB35: =INDEX('2 - Distribuzione'!$CT$44:$CT$403,12*$AA35) -> 0 | AC35: =INDEX('2 - Distribuzione'!$CU$44:$CU$403,12*$AA35) -> 0 | AD35: =AB35/(1+'1 - Input'!$B$12)^$AA35 -> 0 | AE35: =SUMIFS('2 - Distribuzione'!$CB$44:$CB$403,'2 - Distribuzione'!$BV$44:$BV$403,$AA35) -> 0 | AF35: =SUMIFS('2 - Distribuzione'!$CF$44:$CF$403,'2 - Distribuzione'!$BV$44:$BV$403,$AA35) -> 0 | AG35: =SUMIFS('2 - Distribuzione'!$CE$44:$CE$403,'2 - Distribuzione'!$BV$44:$BV$403,$AA35) -> 0 | AH35: =SUMIFS('2 - Distribuzione'!$CM$44:$CM$403,'2 - Distribuzione'!$BV$44:$BV$403,$AA35) -> 0 | AI35: =SUMIFS('2 - Distribuzione'!$CS$44:$CS$403,'2 - Distribuzione'!$BV$44:$BV$403,$AA35) -> 0 | AJ35: =INDEX('2 - Distribuzione'!$CZ$44:$CZ$403,12*$AA35) -> 0 | AK35: =SUMIFS('2 - Distribuzione'!$CV$44:$CV$403,'2 - Distribuzione'!$BV$44:$BV$403,$AA35)/12 -> 0 | AL35: =AK35/(1+'1 - Input'!$B$12)^($AA35-0.5) -> 0
A40: Motore del calcolo, non modificare. A: caso atteso, Q = 0% (tutto provento) | AK40: Motore del calcolo, non modificare. U: Q scelta nel foglio 1 | BU40: Motore del calcolo, non modificare. B: limite teorico, senza fonte per gli ETF esteri, Q = 100%
A41: Quota Q del blocco | B41: =0 -> 0 | AK41: Quota Q del blocco | AL41: ='1 - Input'!$B$9 -> 0 | BU41: Quota Q del blocco | BV41: =1 -> 1
A43: Mese k | B43: Anno | C43: Rendimento mensile | D43: Spesa del mese | E43: Valore prima | F43: Costo prima | G43: Valore con rendimento | H43: Distribuzione lorda | I43: Valore dopo lo stacco | J43: Rimborso di capitale | K43: Imposta sulla distribuzione | L43: Distribuzione netta | M43: Costo dopo rimborso | N43: Avanzo reinvestito | O43: Fabbisogno | P43: Quota di guadagno nel valore | Q43: Vendita necessaria lorda | R43: Vendita effettiva | S43: Imposta sulla vendita | T43: Vendita netta | U43: Spesa non coperta | V43: Minusvalenza realizzata | W43: Valore a fine mese | X43: Costo a fine mese | Y43: Bollo | Z43: Valore dopo bollo | AA43: Costo dopo bollo | AB43: Speso nel mese | AC43: Speso cumulato | AD43: Imposte distribuzione cumulate | AE43: Imposte vendita cumulate | AF43: Minusvalenze cumulate | AG43: Bollo cumulato | AH43: Non coperto cumulato | AI43: Esaurito (1 = sì) | AK43: Mese k | AL43: Anno | AM43: Rendimento mensile | AN43: Spesa del mese | AO43: Valore prima | AP43: Costo prima | AQ43: Valore con rendimento | AR43: Distribuzione lorda | AS43: Valore dopo lo stacco | AT43: Rimborso di capitale | AU43: Imposta sulla distribuzione | AV43: Distribuzione netta | AW43: Costo dopo rimborso | AX43: Avanzo reinvestito | AY43: Fabbisogno | AZ43: Quota di guadagno nel valore | BA43: Vendita necessaria lorda | BB43: Vendita effettiva | BC43: Imposta sulla vendita | BD43: Vendita netta | BE43: Spesa non coperta | BF43: Minusvalenza realizzata | BG43: Valore a fine mese | BH43: Costo a fine mese | BI43: Bollo | BJ43: Valore dopo bollo | BK43: Costo dopo bollo | BL43: Speso nel mese | BM43: Speso cumulato | BN43: Imposte distribuzione cumulate | BO43: Imposte vendita cumulate | BP43: Minusvalenze cumulate | BQ43: Bollo cumulato | BR43: Non coperto cumulato | BS43: Esaurito (1 = sì) | BU43: Mese k | BV43: Anno | BW43: Rendimento mensile | BX43: Spesa del mese | BY43: Valore prima | BZ43: Costo prima | CA43: Valore con rendimento | CB43: Distribuzione lorda | CC43: Valore dopo lo stacco | CD43: Rimborso di capitale | CE43: Imposta sulla distribuzione | CF43: Distribuzione netta | CG43: Costo dopo rimborso | CH43: Avanzo reinvestito | CI43: Fabbisogno | CJ43: Quota di guadagno nel valore | CK43: Vendita necessaria lorda | CL43: Vendita effettiva | CM43: Imposta sulla vendita | CN43: Vendita netta | CO43: Spesa non coperta | CP43: Minusvalenza realizzata | CQ43: Valore a fine mese | CR43: Costo a fine mese | CS43: Bollo | CT43: Valore dopo bollo | CU43: Costo dopo bollo | CV43: Speso nel mese | CW43: Speso cumulato | CX43: Imposte distribuzione cumulate | CY43: Imposte vendita cumulate | CZ43: Minusvalenze cumulate | DA43: Bollo cumulato | DB43: Non coperto cumulato | DC43: Esaurito (1 = sì)
A44: 1 | B44: =ROUNDUP(A44/12,0) -> 1 | C44: =(1+INDEX('1 - Input'!$B$34:$E$63,B44,'1 - Input'!$B$16))^(1/12)-1 -> 0.0041219243 | D44: ='1 - Input'!$B$7*(1+'1 - Input'!$B$12)^(B44-1) -> 2700 | E44: ='1 - Input'!$B$6 -> 486500 | F44: ='1 - Input'!$B$6*'1 - Input'!$B$15 -> 486500 | G44: =E44*(1+C44) -> 488505.32 | H44: =IF(G44>0,'1 - Input'!$B$8/12*G44,0) -> 3663.7899 | I44: =G44-H44 -> 484841.53 | J44: =MIN($B$41*H44,F44) -> 0 | K44: ='1 - Input'!$B$22*(H44-J44) -> 952.58537 | L44: =H44-K44 -> 2711.2045 | M44: =F44-J44 -> 486500 | N44: =IF('1 - Input'!$B$17=1,MAX(0,L44-D44),0) -> 11.204505 | O44: =IF('1 - Input'!$B$17=1,MAX(0,D44-L44),0) -> 0 | P44: =IF(I44>0,MAX(0,1-M44/I44),0) -> 0 | Q44: =IF(AND(O44>0,I44>0),O44/(1-'1 - Input'!$B$22*P44),0) -> 0 | R44: =MIN(Q44,I44) -> 0 | S44: ='1 - Input'!$B$22*P44*R44 -> 0 | T44: =R44-S44 -> 0 | U44: =O44-T44 -> 0 | V44: =IF(I44>0,R44*MAX(0,M44/I44-1),0) -> 0 | W44: =I44-R44+N44 -> 484852.73 | X44: =IF(R44>0,M44*(1-R44/I44),M44)+N44 -> 486511.2 | Y44: =IF(MOD(A44,12)=0,W44*'1 - Input'!$B$23,0) -> 0 | Z44: =W44-Y44 -> 484852.73 | AA44: =IF(MOD(A44,12)=0,X44*(1-'1 - Input'!$B$23),X44) -> 486511.2 | AB44: =IF('1 - Input'!$B$17=1,MIN(L44,D44)+T44,L44) -> 2700 | AC44: =AB44 -> 2700 | AD44: =K44 -> 952.58537 | AE44: =S44 -> 0 | AF44: =V44 -> 0 | AG44: =Y44 -> 0 | AH44: =U44 -> 0 | AI44: =IF(W44<=0.000001,1,0) -> 0 | AK44: 1 | AL44: =ROUNDUP(AK44/12,0) -> 1 | AM44: =(1+INDEX('1 - Input'!$B$34:$E$63,AL44,'1 - Input'!$B$16))^(1/12)-1 -> 0.0041219243 | AN44: ='1 - Input'!$B$7*(1+'1 - Input'!$B$12)^(AL44-1) -> 2700 | AO44: ='1 - Input'!$B$6 -> 486500 | AP44: ='1 - Input'!$B$6*'1 - Input'!$B$15 -> 486500 | AQ44: =AO44*(1+AM44) -> 488505.32 | AR44: =IF(AQ44>0,'1 - Input'!$B$8/12*AQ44,0) -> 3663.7899 | AS44: =AQ44-AR44 -> 484841.53 | AT44: =MIN($AL$41*AR44,AP44) -> 0 | AU44: ='1 - Input'!$B$22*(AR44-AT44) -> 952.58537 | AV44: =AR44-AU44 -> 2711.2045 | AW44: =AP44-AT44 -> 486500 | AX44: =IF('1 - Input'!$B$17=1,MAX(0,AV44-AN44),0) -> 11.204505 | AY44: =IF('1 - Input'!$B$17=1,MAX(0,AN44-AV44),0) -> 0 | AZ44: =IF(AS44>0,MAX(0,1-AW44/AS44),0) -> 0 | BA44: =IF(AND(AY44>0,AS44>0),AY44/(1-'1 - Input'!$B$22*AZ44),0) -> 0 | BB44: =MIN(BA44,AS44) -> 0 | BC44: ='1 - Input'!$B$22*AZ44*BB44 -> 0 | BD44: =BB44-BC44 -> 0 | BE44: =AY44-BD44 -> 0 | BF44: =IF(AS44>0,BB44*MAX(0,AW44/AS44-1),0) -> 0 | BG44: =AS44-BB44+AX44 -> 484852.73 | BH44: =IF(BB44>0,AW44*(1-BB44/AS44),AW44)+AX44 -> 486511.2 | BI44: =IF(MOD(AK44,12)=0,BG44*'1 - Input'!$B$23,0) -> 0 | BJ44: =BG44-BI44 -> 484852.73 | BK44: =IF(MOD(AK44,12)=0,BH44*(1-'1 - Input'!$B$23),BH44) -> 486511.2 | BL44: =IF('1 - Input'!$B$17=1,MIN(AV44,AN44)+BD44,AV44) -> 2700 | BM44: =BL44 -> 2700 | BN44: =AU44 -> 952.58537 | BO44: =BC44 -> 0 | BP44: =BF44 -> 0 | BQ44: =BI44 -> 0 | BR44: =BE44 -> 0 | BS44: =IF(BG44<=0.000001,1,0) -> 0 | BU44: 1 | BV44: =ROUNDUP(BU44/12,0) -> 1 | BW44: =(1+INDEX('1 - Input'!$B$34:$E$63,BV44,'1 - Input'!$B$16))^(1/12)-1 -> 0.0041219243 | BX44: ='1 - Input'!$B$7*(1+'1 - Input'!$B$12)^(BV44-1) -> 2700 | BY44: ='1 - Input'!$B$6 -> 486500 | BZ44: ='1 - Input'!$B$6*'1 - Input'!$B$15 -> 486500 | CA44: =BY44*(1+BW44) -> 488505.32 | CB44: =IF(CA44>0,'1 - Input'!$B$8/12*CA44,0) -> 3663.7899 | CC44: =CA44-CB44 -> 484841.53 | CD44: =MIN($BV$41*CB44,BZ44) -> 3663.7899 | CE44: ='1 - Input'!$B$22*(CB44-CD44) -> 0 | CF44: =CB44-CE44 -> 3663.7899 | CG44: =BZ44-CD44 -> 482836.21 | CH44: =IF('1 - Input'!$B$17=1,MAX(0,CF44-BX44),0) -> 963.78987 | CI44: =IF('1 - Input'!$B$17=1,MAX(0,BX44-CF44),0) -> 0 | CJ44: =IF(CC44>0,MAX(0,1-CG44/CC44),0) -> 0.004136024 | CK44: =IF(AND(CI44>0,CC44>0),CI44/(1-'1 - Input'!$B$22*CJ44),0) -> 0 | CL44: =MIN(CK44,CC44) -> 0 | CM44: ='1 - Input'!$B$22*CJ44*CL44 -> 0 | CN44: =CL44-CM44 -> 0 | CO44: =CI44-CN44 -> 0 | CP44: =IF(CC44>0,CL44*MAX(0,CG44/CC44-1),0) -> 0 | CQ44: =CC44-CL44+CH44 -> 485805.32 | CR44: =IF(CL44>0,CG44*(1-CL44/CC44),CG44)+CH44 -> 483800 | CS44: =IF(MOD(BU44,12)=0,CQ44*'1 - Input'!$B$23,0) -> 0 | CT44: =CQ44-CS44 -> 485805.32 | CU44: =IF(MOD(BU44,12)=0,CR44*(1-'1 - Input'!$B$23),CR44) -> 483800 | CV44: =IF('1 - Input'!$B$17=1,MIN(CF44,BX44)+CN44,CF44) -> 2700 | CW44: =CV44 -> 2700 | CX44: =CE44 -> 0 | CY44: =CM44 -> 0 | CZ44: =CP44 -> 0 | DA44: =CS44 -> 0 | DB44: =CO44 -> 0 | DC44: =IF(CQ44<=0.000001,1,0) -> 0
A45: 2 | B45: =ROUNDUP(A45/12,0) -> 1 | C45: =(1+INDEX('1 - Input'!$B$34:$E$63,B45,'1 - Input'!$B$16))^(1/12)-1 -> 0.0041219243 | D45: ='1 - Input'!$B$7*(1+'1 - Input'!$B$12)^(B45-1) -> 2700 | E45: =Z44 -> 484852.73 | F45: =AA44 -> 486511.2 | G45: =E45*(1+C45) -> 486851.26 | H45: =IF(G45>0,'1 - Input'!$B$8/12*G45,0) -> 3651.3844 | I45: =G45-H45 -> 483199.87 | J45: =MIN($B$41*H45,F45) -> 0 | K45: ='1 - Input'!$B$22*(H45-J45) -> 949.35995 | L45: =H45-K45 -> 2702.0245 | M45: =F45-J45 -> 486511.2 | N45: =IF('1 - Input'!$B$17=1,MAX(0,L45-D45),0) -> 2.0244768 | O45: =IF('1 - Input'!$B$17=1,MAX(0,D45-L45),0) -> 0 | P45: =IF(I45>0,MAX(0,1-M45/I45),0) -> 0 | Q45: =IF(AND(O45>0,I45>0),O45/(1-'1 - Input'!$B$22*P45),0) -> 0 | R45: =MIN(Q45,I45) -> 0 | S45: ='1 - Input'!$B$22*P45*R45 -> 0 | T45: =R45-S45 -> 0 | U45: =O45-T45 -> 0 | V45: =IF(I45>0,R45*MAX(0,M45/I45-1),0) -> 0 | W45: =I45-R45+N45 -> 483201.9 | X45: =IF(R45>0,M45*(1-R45/I45),M45)+N45 -> 486513.23 | Y45: =IF(MOD(A45,12)=0,W45*'1 - Input'!$B$23,0) -> 0 | Z45: =W45-Y45 -> 483201.9 | AA45: =IF(MOD(A45,12)=0,X45*(1-'1 - Input'!$B$23),X45) -> 486513.23 | AB45: =IF('1 - Input'!$B$17=1,MIN(L45,D45)+T45,L45) -> 2700 | AC45: =AC44+AB45 -> 5400 | AD45: =AD44+K45 -> 1901.9453 | AE45: =AE44+S45 -> 0 | AF45: =AF44+V45 -> 0 | AG45: =AG44+Y45 -> 0 | AH45: =AH44+U45 -> 0 | AI45: =IF(W45<=0.000001,1,0) -> 0 | AK45: 2 | AL45: =ROUNDUP(AK45/12,0) -> 1 | AM45: =(1+INDEX('1 - Input'!$B$34:$E$63,AL45,'1 - Input'!$B$16))^(1/12)-1 -> 0.0041219243 | AN45: ='1 - Input'!$B$7*(1+'1 - Input'!$B$12)^(AL45-1) -> 2700 | AO45: =BJ44 -> 484852.73 | AP45: =BK44 -> 486511.2 | AQ45: =AO45*(1+AM45) -> 486851.26 | AR45: =IF(AQ45>0,'1 - Input'!$B$8/12*AQ45,0) -> 3651.3844 | AS45: =AQ45-AR45 -> 483199.87 | AT45: =MIN($AL$41*AR45,AP45) -> 0 | AU45: ='1 - Input'!$B$22*(AR45-AT45) -> 949.35995 | AV45: =AR45-AU45 -> 2702.0245 | AW45: =AP45-AT45 -> 486511.2 | AX45: =IF('1 - Input'!$B$17=1,MAX(0,AV45-AN45),0) -> 2.0244768 | AY45: =IF('1 - Input'!$B$17=1,MAX(0,AN45-AV45),0) -> 0 | AZ45: =IF(AS45>0,MAX(0,1-AW45/AS45),0) -> 0 | BA45: =IF(AND(AY45>0,AS45>0),AY45/(1-'1 - Input'!$B$22*AZ45),0) -> 0 | BB45: =MIN(BA45,AS45) -> 0 | BC45: ='1 - Input'!$B$22*AZ45*BB45 -> 0 | BD45: =BB45-BC45 -> 0 | BE45: =AY45-BD45 -> 0 | BF45: =IF(AS45>0,BB45*MAX(0,AW45/AS45-1),0) -> 0 | BG45: =AS45-BB45+AX45 -> 483201.9 | BH45: =IF(BB45>0,AW45*(1-BB45/AS45),AW45)+AX45 -> 486513.23 | BI45: =IF(MOD(AK45,12)=0,BG45*'1 - Input'!$B$23,0) -> 0 | BJ45: =BG45-BI45 -> 483201.9 | BK45: =IF(MOD(AK45,12)=0,BH45*(1-'1 - Input'!$B$23),BH45) -> 486513.23 | BL45: =IF('1 - Input'!$B$17=1,MIN(AV45,AN45)+BD45,AV45) -> 2700 | BM45: =BM44+BL45 -> 5400 | BN45: =BN44+AU45 -> 1901.9453 | BO45: =BO44+BC45 -> 0 | BP45: =BP44+BF45 -> 0 | BQ45: =BQ44+BI45 -> 0 | BR45: =BR44+BE45 -> 0 | BS45: =IF(BG45<=0.000001,1,0) -> 0 | BU45: 2 | BV45: =ROUNDUP(BU45/12,0) -> 1 | BW45: =(1+INDEX('1 - Input'!$B$34:$E$63,BV45,'1 - Input'!$B$16))^(1/12)-1 -> 0.0041219243 | BX45: ='1 - Input'!$B$7*(1+'1 - Input'!$B$12)^(BV45-1) -> 2700 | BY45: =CT44 -> 485805.32 | BZ45: =CU44 -> 483800 | CA45: =BY45*(1+BW45) -> 487807.77 | CB45: =IF(CA45>0,'1 - Input'!$B$8/12*CA45,0) -> 3658.5583 | CC45: =CA45-CB45 -> 484149.21 | CD45: =MIN($BV$41*CB45,BZ45) -> 3658.5583 | CE45: ='1 - Input'!$B$22*(CB45-CD45) -> 0 | CF45: =CB45-CE45 -> 3658.5583 | CG45: =BZ45-CD45 -> 480141.44 | CH45: =IF('1 - Input'!$B$17=1,MAX(0,CF45-BX45),0) -> 958.55827 | CI45: =IF('1 - Input'!$B$17=1,MAX(0,BX45-CF45),0) -> 0 | CJ45: =IF(CC45>0,MAX(0,1-CG45/CC45),0) -> 0.0082779623 | CK45: =IF(AND(CI45>0,CC45>0),CI45/(1-'1 - Input'!$B$22*CJ45),0) -> 0 | CL45: =MIN(CK45,CC45) -> 0 | CM45: ='1 - Input'!$B$22*CJ45*CL45 -> 0 | CN45: =CL45-CM45 -> 0 | CO45: =CI45-CN45 -> 0 | CP45: =IF(CC45>0,CL45*MAX(0,CG45/CC45-1),0) -> 0 | CQ45: =CC45-CL45+CH45 -> 485107.77 | CR45: =IF(CL45>0,CG45*(1-CL45/CC45),CG45)+CH45 -> 481100 | CS45: =IF(MOD(BU45,12)=0,CQ45*'1 - Input'!$B$23,0) -> 0 | CT45: =CQ45-CS45 -> 485107.77 | CU45: =IF(MOD(BU45,12)=0,CR45*(1-'1 - Input'!$B$23),CR45) -> 481100 | CV45: =IF('1 - Input'!$B$17=1,MIN(CF45,BX45)+CN45,CF45) -> 2700 | CW45: =CW44+CV45 -> 5400 | CX45: =CX44+CE45 -> 0 | CY45: =CY44+CM45 -> 0 | CZ45: =CZ44+CP45 -> 0 | DA45: =DA44+CS45 -> 0 | DB45: =DB44+CO45 -> 0 | DC45: =IF(CQ45<=0.000001,1,0) -> 0
A46: 3 | B46: =ROUNDUP(A46/12,0) -> 1 | C46: =(1+INDEX('1 - Input'!$B$34:$E$63,B46,'1 - Input'!$B$16))^(1/12)-1 -> 0.0041219243 | D46: ='1 - Input'!$B$7*(1+'1 - Input'!$B$12)^(B46-1) -> 2700 | E46: =Z45 -> 483201.9 | F46: =AA45 -> 486513.23 | G46: =E46*(1+C46) -> 485193.62 | H46: =IF(G46>0,'1 - Input'!$B$8/12*G46,0) -> 3638.9521 | I46: =G46-H46 -> 481554.67 | J46: =MIN($B$41*H46,F46) -> 0 | K46: ='1 - Input'!$B$22*(H46-J46) -> 946.12756 | L46: =H46-K46 -> 2692.8246 | M46: =F46-J46 -> 486513.23 | N46: =IF('1 - Input'!$B$17=1,MAX(0,L46-D46),0) -> 0 | O46: =IF('1 - Input'!$B$17=1,MAX(0,D46-L46),0) -> 7.1754158 | P46: =IF(I46>0,MAX(0,1-M46/I46),0) -> 0 | Q46: =IF(AND(O46>0,I46>0),O46/(1-'1 - Input'!$B$22*P46),0) -> 7.1754158 | R46: =MIN(Q46,I46) -> 7.1754158 | S46: ='1 - Input'!$B$22*P46*R46 -> 0 | T46: =R46-S46 -> 7.1754158 | U46: =O46-T46 -> 0 | V46: =IF(I46>0,R46*MAX(0,M46/I46-1),0) -> 0.073885166 | W46: =I46-R46+N46 -> 481547.49 | X46: =IF(R46>0,M46*(1-R46/I46),M46)+N46 -> 486505.98 | Y46: =IF(MOD(A46,12)=0,W46*'1 - Input'!$B$23,0) -> 0 | Z46: =W46-Y46 -> 481547.49 | AA46: =IF(MOD(A46,12)=0,X46*(1-'1 - Input'!$B$23),X46) -> 486505.98 | AB46: =IF('1 - Input'!$B$17=1,MIN(L46,D46)+T46,L46) -> 2700 | AC46: =AC45+AB46 -> 8100 | AD46: =AD45+K46 -> 2848.0729 | AE46: =AE45+S46 -> 0 | AF46: =AF45+V46 -> 0.073885166 | AG46: =AG45+Y46 -> 0 | AH46: =AH45+U46 -> 0 | AI46: =IF(W46<=0.000001,1,0) -> 0 | AK46: 3 | AL46: =ROUNDUP(AK46/12,0) -> 1 | AM46: =(1+INDEX('1 - Input'!$B$34:$E$63,AL46,'1 - Input'!$B$16))^(1/12)-1 -> 0.0041219243 | AN46: ='1 - Input'!$B$7*(1+'1 - Input'!$B$12)^(AL46-1) -> 2700 | AO46: =BJ45 -> 483201.9 | AP46: =BK45 -> 486513.23 | AQ46: =AO46*(1+AM46) -> 485193.62 | AR46: =IF(AQ46>0,'1 - Input'!$B$8/12*AQ46,0) -> 3638.9521 | AS46: =AQ46-AR46 -> 481554.67 | AT46: =MIN($AL$41*AR46,AP46) -> 0 | AU46: ='1 - Input'!$B$22*(AR46-AT46) -> 946.12756 | AV46: =AR46-AU46 -> 2692.8246 | AW46: =AP46-AT46 -> 486513.23 | AX46: =IF('1 - Input'!$B$17=1,MAX(0,AV46-AN46),0) -> 0 | AY46: =IF('1 - Input'!$B$17=1,MAX(0,AN46-AV46),0) -> 7.1754158 | AZ46: =IF(AS46>0,MAX(0,1-AW46/AS46),0) -> 0 | BA46: =IF(AND(AY46>0,AS46>0),AY46/(1-'1 - Input'!$B$22*AZ46),0) -> 7.1754158 | BB46: =MIN(BA46,AS46) -> 7.1754158 | BC46: ='1 - Input'!$B$22*AZ46*BB46 -> 0 | BD46: =BB46-BC46 -> 7.1754158 | BE46: =AY46-BD46 -> 0 | BF46: =IF(AS46>0,BB46*MAX(0,AW46/AS46-1),0) -> 0.073885166 | BG46: =AS46-BB46+AX46 -> 481547.49 | BH46: =IF(BB46>0,AW46*(1-BB46/AS46),AW46)+AX46 -> 486505.98 | BI46: =IF(MOD(AK46,12)=0,BG46*'1 - Input'!$B$23,0) -> 0 | BJ46: =BG46-BI46 -> 481547.49 | BK46: =IF(MOD(AK46,12)=0,BH46*(1-'1 - Input'!$B$23),BH46) -> 486505.98 | BL46: =IF('1 - Input'!$B$17=1,MIN(AV46,AN46)+BD46,AV46) -> 2700 | BM46: =BM45+BL46 -> 8100 | BN46: =BN45+AU46 -> 2848.0729 | BO46: =BO45+BC46 -> 0 | BP46: =BP45+BF46 -> 0.073885166 | BQ46: =BQ45+BI46 -> 0 | BR46: =BR45+BE46 -> 0 | BS46: =IF(BG46<=0.000001,1,0) -> 0 | BU46: 3 | BV46: =ROUNDUP(BU46/12,0) -> 1 | BW46: =(1+INDEX('1 - Input'!$B$34:$E$63,BV46,'1 - Input'!$B$16))^(1/12)-1 -> 0.0041219243 | BX46: ='1 - Input'!$B$7*(1+'1 - Input'!$B$12)^(BV46-1) -> 2700 | BY46: =CT45 -> 485107.77 | BZ46: =CU45 -> 481100 | CA46: =BY46*(1+BW46) -> 487107.35 | CB46: =IF(CA46>0,'1 - Input'!$B$8/12*CA46,0) -> 3653.3051 | CC46: =CA46-CB46 -> 483454.04 | CD46: =MIN($BV$41*CB46,BZ46) -> 3653.3051 | CE46: ='1 - Input'!$B$22*(CB46-CD46) -> 0 | CF46: =CB46-CE46 -> 3653.3051 | CG46: =BZ46-CD46 -> 477446.69 | CH46: =IF('1 - Input'!$B$17=1,MAX(0,CF46-BX46),0) -> 953.3051 | CI46: =IF('1 - Input'!$B$17=1,MAX(0,BX46-CF46),0) -> 0 | CJ46: =IF(CC46>0,MAX(0,1-CG46/CC46),0) -> 0.012425889 | CK46: =IF(AND(CI46>0,CC46>0),CI46/(1-'1 - Input'!$B$22*CJ46),0) -> 0 | CL46: =MIN(CK46,CC46) -> 0 | CM46: ='1 - Input'!$B$22*CJ46*CL46 -> 0 | CN46: =CL46-CM46 -> 0 | CO46: =CI46-CN46 -> 0 | CP46: =IF(CC46>0,CL46*MAX(0,CG46/CC46-1),0) -> 0 | CQ46: =CC46-CL46+CH46 -> 484407.35 | CR46: =IF(CL46>0,CG46*(1-CL46/CC46),CG46)+CH46 -> 478400 | CS46: =IF(MOD(BU46,12)=0,CQ46*'1 - Input'!$B$23,0) -> 0 | CT46: =CQ46-CS46 -> 484407.35 | CU46: =IF(MOD(BU46,12)=0,CR46*(1-'1 - Input'!$B$23),CR46) -> 478400 | CV46: =IF('1 - Input'!$B$17=1,MIN(CF46,BX46)+CN46,CF46) -> 2700 | CW46: =CW45+CV46 -> 8100 | CX46: =CX45+CE46 -> 0 | CY46: =CY45+CM46 -> 0 | CZ46: =CZ45+CP46 -> 0 | DA46: =DA45+CS46 -> 0 | DB46: =DB45+CO46 -> 0 | DC46: =IF(CQ46<=0.000001,1,0) -> 0
A47: 4 | B47: =ROUNDUP(A47/12,0) -> 1 | C47: =(1+INDEX('1 - Input'!$B$34:$E$63,B47,'1 - Input'!$B$16))^(1/12)-1 -> 0.0041219243 | D47: ='1 - Input'!$B$7*(1+'1 - Input'!$B$12)^(B47-1) -> 2700 | E47: =Z46 -> 481547.49 | F47: =AA46 -> 486505.98 | G47: =E47*(1+C47) -> 483532.39 | H47: =IF(G47>0,'1 - Input'!$B$8/12*G47,0) -> 3626.493 | I47: =G47-H47 -> 479905.9 | J47: =MIN($B$41*H47,F47) -> 0 | K47: ='1 - Input'!$B$22*(H47-J47) -> 942.88817 | L47: =H47-K47 -> 2683.6048 | M47: =F47-J47 -> 486505.98 | N47: =IF('1 - Input'!$B$17=1,MAX(0,L47-D47),0) -> 0 | O47: =IF('1 - Input'!$B$17=1,MAX(0,D47-L47),0) -> 16.395216 | P47: =IF(I47>0,MAX(0,1-M47/I47),0) -> 0 | Q47: =IF(AND(O47>0,I47>0),O47/(1-'1 - Input'!$B$22*P47),0) -> 16.395216 | R47: =MIN(Q47,I47) -> 16.395216 | S47: ='1 - Input'!$B$22*P47*R47 -> 0 | T47: =R47-S47 -> 16.395216 | U47: =O47-T47 -> 0 | V47: =IF(I47>0,R47*MAX(0,M47/I47-1),0) -> 0.22548112 | W47: =I47-R47+N47 -> 479889.51 | X47: =IF(R47>0,M47*(1-R47/I47),M47)+N47 -> 486489.36 | Y47: =IF(MOD(A47,12)=0,W47*'1 - Input'!$B$23,0) -> 0 | Z47: =W47-Y47 -> 479889.51 | AA47: =IF(MOD(A47,12)=0,X47*(1-'1 - Input'!$B$23),X47) -> 486489.36 | AB47: =IF('1 - Input'!$B$17=1,MIN(L47,D47)+T47,L47) -> 2700 | AC47: =AC46+AB47 -> 10800 | AD47: =AD46+K47 -> 3790.961 | AE47: =AE46+S47 -> 0 | AF47: =AF46+V47 -> 0.29936629 | AG47: =AG46+Y47 -> 0 | AH47: =AH46+U47 -> 0 | AI47: =IF(W47<=0.000001,1,0) -> 0 | AK47: 4 | AL47: =ROUNDUP(AK47/12,0) -> 1 | AM47: =(1+INDEX('1 - Input'!$B$34:$E$63,AL47,'1 - Input'!$B$16))^(1/12)-1 -> 0.0041219243 | AN47: ='1 - Input'!$B$7*(1+'1 - Input'!$B$12)^(AL47-1) -> 2700 | AO47: =BJ46 -> 481547.49 | AP47: =BK46 -> 486505.98 | AQ47: =AO47*(1+AM47) -> 483532.39 | AR47: =IF(AQ47>0,'1 - Input'!$B$8/12*AQ47,0) -> 3626.493 | AS47: =AQ47-AR47 -> 479905.9 | AT47: =MIN($AL$41*AR47,AP47) -> 0 | AU47: ='1 - Input'!$B$22*(AR47-AT47) -> 942.88817 | AV47: =AR47-AU47 -> 2683.6048 | AW47: =AP47-AT47 -> 486505.98 | AX47: =IF('1 - Input'!$B$17=1,MAX(0,AV47-AN47),0) -> 0 | AY47: =IF('1 - Input'!$B$17=1,MAX(0,AN47-AV47),0) -> 16.395216 | AZ47: =IF(AS47>0,MAX(0,1-AW47/AS47),0) -> 0 | BA47: =IF(AND(AY47>0,AS47>0),AY47/(1-'1 - Input'!$B$22*AZ47),0) -> 16.395216 | BB47: =MIN(BA47,AS47) -> 16.395216 | BC47: ='1 - Input'!$B$22*AZ47*BB47 -> 0 | BD47: =BB47-BC47 -> 16.395216 | BE47: =AY47-BD47 -> 0 | BF47: =IF(AS47>0,BB47*MAX(0,AW47/AS47-1),0) -> 0.22548112 | BG47: =AS47-BB47+AX47 -> 479889.51 | BH47: =IF(BB47>0,AW47*(1-BB47/AS47),AW47)+AX47 -> 486489.36 | BI47: =IF(MOD(AK47,12)=0,BG47*'1 - Input'!$B$23,0) -> 0 | BJ47: =BG47-BI47 -> 479889.51 | BK47: =IF(MOD(AK47,12)=0,BH47*(1-'1 - Input'!$B$23),BH47) -> 486489.36 | BL47: =IF('1 - Input'!$B$17=1,MIN(AV47,AN47)+BD47,AV47) -> 2700 | BM47: =BM46+BL47 -> 10800 | BN47: =BN46+AU47 -> 3790.961 | BO47: =BO46+BC47 -> 0 | BP47: =BP46+BF47 -> 0.29936629 | BQ47: =BQ46+BI47 -> 0 | BR47: =BR46+BE47 -> 0 | BS47: =IF(BG47<=0.000001,1,0) -> 0 | BU47: 4 | BV47: =ROUNDUP(BU47/12,0) -> 1 | BW47: =(1+INDEX('1 - Input'!$B$34:$E$63,BV47,'1 - Input'!$B$16))^(1/12)-1 -> 0.0041219243 | BX47: ='1 - Input'!$B$7*(1+'1 - Input'!$B$12)^(BV47-1) -> 2700 | BY47: =CT46 -> 484407.35 | BZ47: =CU46 -> 478400 | CA47: =BY47*(1+BW47) -> 486404.04 | CB47: =IF(CA47>0,'1 - Input'!$B$8/12*CA47,0) -> 3648.0303 | CC47: =CA47-CB47 -> 482756.01 | CD47: =MIN($BV$41*CB47,BZ47) -> 3648.0303 | CE47: ='1 - Input'!$B$22*(CB47-CD47) -> 0 | CF47: =CB47-CE47 -> 3648.0303 | CG47: =BZ47-CD47 -> 474751.97 | CH47: =IF('1 - Input'!$B$17=1,MAX(0,CF47-BX47),0) -> 948.03028 | CI47: =IF('1 - Input'!$B$17=1,MAX(0,BX47-CF47),0) -> 0 | CJ47: =IF(CC47>0,MAX(0,1-CG47/CC47),0) -> 0.01657988 | CK47: =IF(AND(CI47>0,CC47>0),CI47/(1-'1 - Input'!$B$22*CJ47),0) -> 0 | CL47: =MIN(CK47,CC47) -> 0 | CM47: ='1 - Input'!$B$22*CJ47*CL47 -> 0 | CN47: =CL47-CM47 -> 0 | CO47: =CI47-CN47 -> 0 | CP47: =IF(CC47>0,CL47*MAX(0,CG47/CC47-1),0) -> 0 | CQ47: =CC47-CL47+CH47 -> 483704.04 | CR47: =IF(CL47>0,CG47*(1-CL47/CC47),CG47)+CH47 -> 475700 | CS47: =IF(MOD(BU47,12)=0,CQ47*'1 - Input'!$B$23,0) -> 0 | CT47: =CQ47-CS47 -> 483704.04 | CU47: =IF(MOD(BU47,12)=0,CR47*(1-'1 - Input'!$B$23),CR47) -> 475700 | CV47: =IF('1 - Input'!$B$17=1,MIN(CF47,BX47)+CN47,CF47) -> 2700 | CW47: =CW46+CV47 -> 10800 | CX47: =CX46+CE47 -> 0 | CY47: =CY46+CM47 -> 0 | CZ47: =CZ46+CP47 -> 0 | DA47: =DA46+CS47 -> 0 | DB47: =DB46+CO47 -> 0 | DC47: =IF(CQ47<=0.000001,1,0) -> 0
A48: 5 | B48: =ROUNDUP(A48/12,0) -> 1 | C48: =(1+INDEX('1 - Input'!$B$34:$E$63,B48,'1 - Input'!$B$16))^(1/12)-1 -> 0.0041219243 | D48: ='1 - Input'!$B$7*(1+'1 - Input'!$B$12)^(B48-1) -> 2700 | E48: =Z47 -> 479889.51 | F48: =AA47 -> 486489.36 | G48: =E48*(1+C48) -> 481867.57 | H48: =IF(G48>0,'1 - Input'!$B$8/12*G48,0) -> 3614.0068 | I48: =G48-H48 -> 478253.57 | J48: =MIN($B$41*H48,F48) -> 0 | K48: ='1 - Input'!$B$22*(H48-J48) -> 939.64177 | L48: =H48-K48 -> 2674.365 | M48: =F48-J48 -> 486489.36 | N48: =IF('1 - Input'!$B$17=1,MAX(0,L48-D48),0) -> 0 | O48: =IF('1 - Input'!$B$17=1,MAX(0,D48-L48),0) -> 25.634967 | P48: =IF(I48>0,MAX(0,1-M48/I48),0) -> 0 | Q48: =IF(AND(O48>0,I48>0),O48/(1-'1 - Input'!$B$22*P48),0) -> 25.634967 | R48: =MIN(Q48,I48) -> 25.634967 | S48: ='1 - Input'!$B$22*P48*R48 -> 0 | T48: =R48-S48 -> 25.634967 | U48: =O48-T48 -> 0 | V48: =IF(I48>0,R48*MAX(0,M48/I48-1),0) -> 0.44144837 | W48: =I48-R48+N48 -> 478227.93 | X48: =IF(R48>0,M48*(1-R48/I48),M48)+N48 -> 486463.28 | Y48: =IF(MOD(A48,12)=0,W48*'1 - Input'!$B$23,0) -> 0 | Z48: =W48-Y48 -> 478227.93 | AA48: =IF(MOD(A48,12)=0,X48*(1-'1 - Input'!$B$23),X48) -> 486463.28 | AB48: =IF('1 - Input'!$B$17=1,MIN(L48,D48)+T48,L48) -> 2700 | AC48: =AC47+AB48 -> 13500 | AD48: =AD47+K48 -> 4730.6028 | AE48: =AE47+S48 -> 0 | AF48: =AF47+V48 -> 0.74081466 | AG48: =AG47+Y48 -> 0 | AH48: =AH47+U48 -> 0 | AI48: =IF(W48<=0.000001,1,0) -> 0 | AK48: 5 | AL48: =ROUNDUP(AK48/12,0) -> 1 | AM48: =(1+INDEX('1 - Input'!$B$34:$E$63,AL48,'1 - Input'!$B$16))^(1/12)-1 -> 0.0041219243 | AN48: ='1 - Input'!$B$7*(1+'1 - Input'!$B$12)^(AL48-1) -> 2700 | AO48: =BJ47 -> 479889.51 | AP48: =BK47 -> 486489.36 | AQ48: =AO48*(1+AM48) -> 481867.57 | AR48: =IF(AQ48>0,'1 - Input'!$B$8/12*AQ48,0) -> 3614.0068 | AS48: =AQ48-AR48 -> 478253.57 | AT48: =MIN($AL$41*AR48,AP48) -> 0 | AU48: ='1 - Input'!$B$22*(AR48-AT48) -> 939.64177 | AV48: =AR48-AU48 -> 2674.365 | AW48: =AP48-AT48 -> 486489.36 | AX48: =IF('1 - Input'!$B$17=1,MAX(0,AV48-AN48),0) -> 0 | AY48: =IF('1 - Input'!$B$17=1,MAX(0,AN48-AV48),0) -> 25.634967 | AZ48: =IF(AS48>0,MAX(0,1-AW48/AS48),0) -> 0 | BA48: =IF(AND(AY48>0,AS48>0),AY48/(1-'1 - Input'!$B$22*AZ48),0) -> 25.634967 | BB48: =MIN(BA48,AS48) -> 25.634967 | BC48: ='1 - Input'!$B$22*AZ48*BB48 -> 0 | BD48: =BB48-BC48 -> 25.634967 | BE48: =AY48-BD48 -> 0 | BF48: =IF(AS48>0,BB48*MAX(0,AW48/AS48-1),0) -> 0.44144837 | BG48: =AS48-BB48+AX48 -> 478227.93 | BH48: =IF(BB48>0,AW48*(1-BB48/AS48),AW48)+AX48 -> 486463.28 | BI48: =IF(MOD(AK48,12)=0,BG48*'1 - Input'!$B$23,0) -> 0 | BJ48: =BG48-BI48 -> 478227.93 | BK48: =IF(MOD(AK48,12)=0,BH48*(1-'1 - Input'!$B$23),BH48) -> 486463.28 | BL48: =IF('1 - Input'!$B$17=1,MIN(AV48,AN48)+BD48,AV48) -> 2700 | BM48: =BM47+BL48 -> 13500 | BN48: =BN47+AU48 -> 4730.6028 | BO48: =BO47+BC48 -> 0 | BP48: =BP47+BF48 -> 0.74081466 | BQ48: =BQ47+BI48 -> 0 | BR48: =BR47+BE48 -> 0 | BS48: =IF(BG48<=0.000001,1,0) -> 0 | BU48: 5 | BV48: =ROUNDUP(BU48/12,0) -> 1 | BW48: =(1+INDEX('1 - Input'!$B$34:$E$63,BV48,'1 - Input'!$B$16))^(1/12)-1 -> 0.0041219243 | BX48: ='1 - Input'!$B$7*(1+'1 - Input'!$B$12)^(BV48-1) -> 2700 | BY48: =CT47 -> 483704.04 | BZ48: =CU47 -> 475700 | CA48: =BY48*(1+BW48) -> 485697.83 | CB48: =IF(CA48>0,'1 - Input'!$B$8/12*CA48,0) -> 3642.7337 | CC48: =CA48-CB48 -> 482055.09 | CD48: =MIN($BV$41*CB48,BZ48) -> 3642.7337 | CE48: ='1 - Input'!$B$22*(CB48-CD48) -> 0 | CF48: =CB48-CE48 -> 3642.7337 | CG48: =BZ48-CD48 -> 472057.27 | CH48: =IF('1 - Input'!$B$17=1,MAX(0,CF48-BX48),0) -> 942.73371 | CI48: =IF('1 - Input'!$B$17=1,MAX(0,BX48-CF48),0) -> 0 | CJ48: =IF(CC48>0,MAX(0,1-CG48/CC48),0) -> 0.020740012 | CK48: =IF(AND(CI48>0,CC48>0),CI48/(1-'1 - Input'!$B$22*CJ48),0) -> 0 | CL48: =MIN(CK48,CC48) -> 0 | CM48: ='1 - Input'!$B$22*CJ48*CL48 -> 0 | CN48: =CL48-CM48 -> 0 | CO48: =CI48-CN48 -> 0 | CP48: =IF(CC48>0,CL48*MAX(0,CG48/CC48-1),0) -> 0 | CQ48: =CC48-CL48+CH48 -> 482997.83 | CR48: =IF(CL48>0,CG48*(1-CL48/CC48),CG48)+CH48 -> 473000 | CS48: =IF(MOD(BU48,12)=0,CQ48*'1 - Input'!$B$23,0) -> 0 | CT48: =CQ48-CS48 -> 482997.83 | CU48: =IF(MOD(BU48,12)=0,CR48*(1-'1 - Input'!$B$23),CR48) -> 473000 | CV48: =IF('1 - Input'!$B$17=1,MIN(CF48,BX48)+CN48,CF48) -> 2700 | CW48: =CW47+CV48 -> 13500 | CX48: =CX47+CE48 -> 0 | CY48: =CY47+CM48 -> 0 | CZ48: =CZ47+CP48 -> 0 | DA48: =DA47+CS48 -> 0 | DB48: =DB47+CO48 -> 0 | DC48: =IF(CQ48<=0.000001,1,0) -> 0
A49: 6 | B49: =ROUNDUP(A49/12,0) -> 1 | C49: =(1+INDEX('1 - Input'!$B$34:$E$63,B49,'1 - Input'!$B$16))^(1/12)-1 -> 0.0041219243 | D49: ='1 - Input'!$B$7*(1+'1 - Input'!$B$12)^(B49-1) -> 2700 | E49: =Z48 -> 478227.93 | F49: =AA48 -> 486463.28 | G49: =E49*(1+C49) -> 480199.15 | H49: =IF(G49>0,'1 - Input'!$B$8/12*G49,0) -> 3601.4936 | I49: =G49-H49 -> 476597.66 | J49: =MIN($B$41*H49,F49) -> 0 | K49: ='1 - Input'!$B$22*(H49-J49) -> 936.38834 | L49: =H49-K49 -> 2665.1053 | M49: =F49-J49 -> 486463.28 | N49: =IF('1 - Input'!$B$17=1,MAX(0,L49-D49),0) -> 0 | O49: =IF('1 - Input'!$B$17=1,MAX(0,D49-L49),0) -> 34.894711 | P49: =IF(I49>0,MAX(0,1-M49/I49),0) -> 0 | Q49: =IF(AND(O49>0,I49>0),O49/(1-'1 - Input'!$B$22*P49),0) -> 34.894711 | R49: =MIN(Q49,I49) -> 34.894711 | S49: ='1 - Input'!$B$22*P49*R49 -> 0 | T49: =R49-S49 -> 34.894711 | U49: =O49-T49 -> 0 | V49: =IF(I49>0,R49*MAX(0,M49/I49-1),0) -> 0.72232444 | W49: =I49-R49+N49 -> 476562.76 | X49: =IF(R49>0,M49*(1-R49/I49),M49)+N49 -> 486427.67 | Y49: =IF(MOD(A49,12)=0,W49*'1 - Input'!$B$23,0) -> 0 | Z49: =W49-Y49 -> 476562.76 | AA49: =IF(MOD(A49,12)=0,X49*(1-'1 - Input'!$B$23),X49) -> 486427.67 | AB49: =IF('1 - Input'!$B$17=1,MIN(L49,D49)+T49,L49) -> 2700 | AC49: =AC48+AB49 -> 16200 | AD49: =AD48+K49 -> 5666.9912 | AE49: =AE48+S49 -> 0 | AF49: =AF48+V49 -> 1.4631391 | AG49: =AG48+Y49 -> 0 | AH49: =AH48+U49 -> 0 | AI49: =IF(W49<=0.000001,1,0) -> 0 | AK49: 6 | AL49: =ROUNDUP(AK49/12,0) -> 1 | AM49: =(1+INDEX('1 - Input'!$B$34:$E$63,AL49,'1 - Input'!$B$16))^(1/12)-1 -> 0.0041219243 | AN49: ='1 - Input'!$B$7*(1+'1 - Input'!$B$12)^(AL49-1) -> 2700 | AO49: =BJ48 -> 478227.93 | AP49: =BK48 -> 486463.28 | AQ49: =AO49*(1+AM49) -> 480199.15 | AR49: =IF(AQ49>0,'1 - Input'!$B$8/12*AQ49,0) -> 3601.4936 | AS49: =AQ49-AR49 -> 476597.66 | AT49: =MIN($AL$41*AR49,AP49) -> 0 | AU49: ='1 - Input'!$B$22*(AR49-AT49) -> 936.38834 | AV49: =AR49-AU49 -> 2665.1053 | AW49: =AP49-AT49 -> 486463.28 | AX49: =IF('1 - Input'!$B$17=1,MAX(0,AV49-AN49),0) -> 0 | AY49: =IF('1 - Input'!$B$17=1,MAX(0,AN49-AV49),0) -> 34.894711 | AZ49: =IF(AS49>0,MAX(0,1-AW49/AS49),0) -> 0 | BA49: =IF(AND(AY49>0,AS49>0),AY49/(1-'1 - Input'!$B$22*AZ49),0) -> 34.894711 | BB49: =MIN(BA49,AS49) -> 34.894711 | BC49: ='1 - Input'!$B$22*AZ49*BB49 -> 0 | BD49: =BB49-BC49 -> 34.894711 | BE49: =AY49-BD49 -> 0 | BF49: =IF(AS49>0,BB49*MAX(0,AW49/AS49-1),0) -> 0.72232444 | BG49: =AS49-BB49+AX49 -> 476562.76 | BH49: =IF(BB49>0,AW49*(1-BB49/AS49),AW49)+AX49 -> 486427.67 | BI49: =IF(MOD(AK49,12)=0,BG49*'1 - Input'!$B$23,0) -> 0 | BJ49: =BG49-BI49 -> 476562.76 | BK49: =IF(MOD(AK49,12)=0,BH49*(1-'1 - Input'!$B$23),BH49) -> 486427.67 | BL49: =IF('1 - Input'!$B$17=1,MIN(AV49,AN49)+BD49,AV49) -> 2700 | BM49: =BM48+BL49 -> 16200 | BN49: =BN48+AU49 -> 5666.9912 | BO49: =BO48+BC49 -> 0 | BP49: =BP48+BF49 -> 1.4631391 | BQ49: =BQ48+BI49 -> 0 | BR49: =BR48+BE49 -> 0 | BS49: =IF(BG49<=0.000001,1,0) -> 0 | BU49: 6 | BV49: =ROUNDUP(BU49/12,0) -> 1 | BW49: =(1+INDEX('1 - Input'!$B$34:$E$63,BV49,'1 - Input'!$B$16))^(1/12)-1 -> 0.0041219243 | BX49: ='1 - Input'!$B$7*(1+'1 - Input'!$B$12)^(BV49-1) -> 2700 | BY49: =CT48 -> 482997.83 | BZ49: =CU48 -> 473000 | CA49: =BY49*(1+BW49) -> 484988.71 | CB49: =IF(CA49>0,'1 - Input'!$B$8/12*CA49,0) -> 3637.4153 | CC49: =CA49-CB49 -> 481351.29 | CD49: =MIN($BV$41*CB49,BZ49) -> 3637.4153 | CE49: ='1 - Input'!$B$22*(CB49-CD49) -> 0 | CF49: =CB49-CE49 -> 3637.4153 | CG49: =BZ49-CD49 -> 469362.58 | CH49: =IF('1 - Input'!$B$17=1,MAX(0,CF49-BX49),0) -> 937.41532 | CI49: =IF('1 - Input'!$B$17=1,MAX(0,BX49-CF49),0) -> 0 | CJ49: =IF(CC49>0,MAX(0,1-CG49/CC49),0) -> 0.02490636 | CK49: =IF(AND(CI49>0,CC49>0),CI49/(1-'1 - Input'!$B$22*CJ49),0) -> 0 | CL49: =MIN(CK49,CC49) -> 0 | CM49: ='1 - Input'!$B$22*CJ49*CL49 -> 0 | CN49: =CL49-CM49 -> 0 | CO49: =CI49-CN49 -> 0 | CP49: =IF(CC49>0,CL49*MAX(0,CG49/CC49-1),0) -> 0 | CQ49: =CC49-CL49+CH49 -> 482288.71 | CR49: =IF(CL49>0,CG49*(1-CL49/CC49),CG49)+CH49 -> 470300 | CS49: =IF(MOD(BU49,12)=0,CQ49*'1 - Input'!$B$23,0) -> 0 | CT49: =CQ49-CS49 -> 482288.71 | CU49: =IF(MOD(BU49,12)=0,CR49*(1-'1 - Input'!$B$23),CR49) -> 470300 | CV49: =IF('1 - Input'!$B$17=1,MIN(CF49,BX49)+CN49,CF49) -> 2700 | CW49: =CW48+CV49 -> 16200 | CX49: =CX48+CE49 -> 0 | CY49: =CY48+CM49 -> 0 | CZ49: =CZ48+CP49 -> 0 | DA49: =DA48+CS49 -> 0 | DB49: =DB48+CO49 -> 0 | DC49: =IF(CQ49<=0.000001,1,0) -> 0
A50: 7 | B50: =ROUNDUP(A50/12,0) -> 1 | C50: =(1+INDEX('1 - Input'!$B$34:$E$63,B50,'1 - Input'!$B$16))^(1/12)-1 -> 0.0041219243 | D50: ='1 - Input'!$B$7*(1+'1 - Input'!$B$12)^(B50-1) -> 2700 | E50: =Z49 -> 476562.76 | F50: =AA49 -> 486427.67 | G50: =E50*(1+C50) -> 478527.12 | H50: =IF(G50>0,'1 - Input'!$B$8/12*G50,0) -> 3588.9534 | I50: =G50-H50 -> 474938.17 | J50: =MIN($B$41*H50,F50) -> 0 | K50: ='1 - Input'!$B$22*(H50-J50) -> 933.12788 | L50: =H50-K50 -> 2655.8255 | M50: =F50-J50 -> 486427.67 | N50: =IF('1 - Input'!$B$17=1,MAX(0,L50-D50),0) -> 0 | O50: =IF('1 - Input'!$B$17=1,MAX(0,D50-L50),0) -> 44.174493 | P50: =IF(I50>0,MAX(0,1-M50/I50),0) -> 0 | Q50: =IF(AND(O50>0,I50>0),O50/(1-'1 - Input'!$B$22*P50),0) -> 44.174493 | R50: =MIN(Q50,I50) -> 44.174493 | S50: ='1 - Input'!$B$22*P50*R50 -> 0 | T50: =R50-S50 -> 44.174493 | U50: =O50-T50 -> 0 | V50: =IF(I50>0,R50*MAX(0,M50/I50-1),0) -> 1.0686504 | W50: =I50-R50+N50 -> 474893.99 | X50: =IF(R50>0,M50*(1-R50/I50),M50)+N50 -> 486382.42 | Y50: =IF(MOD(A50,12)=0,W50*'1 - Input'!$B$23,0) -> 0 | Z50: =W50-Y50 -> 474893.99 | AA50: =IF(MOD(A50,12)=0,X50*(1-'1 - Input'!$B$23),X50) -> 486382.42 | AB50: =IF('1 - Input'!$B$17=1,MIN(L50,D50)+T50,L50) -> 2700 | AC50: =AC49+AB50 -> 18900 | AD50: =AD49+K50 -> 6600.119 | AE50: =AE49+S50 -> 0 | AF50: =AF49+V50 -> 2.5317895 | AG50: =AG49+Y50 -> 0 | AH50: =AH49+U50 -> 0 | AI50: =IF(W50<=0.000001,1,0) -> 0 | AK50: 7 | AL50: =ROUNDUP(AK50/12,0) -> 1 | AM50: =(1+INDEX('1 - Input'!$B$34:$E$63,AL50,'1 - Input'!$B$16))^(1/12)-1 -> 0.0041219243 | AN50: ='1 - Input'!$B$7*(1+'1 - Input'!$B$12)^(AL50-1) -> 2700 | AO50: =BJ49 -> 476562.76 | AP50: =BK49 -> 486427.67 | AQ50: =AO50*(1+AM50) -> 478527.12 | AR50: =IF(AQ50>0,'1 - Input'!$B$8/12*AQ50,0) -> 3588.9534 | AS50: =AQ50-AR50 -> 474938.17 | AT50: =MIN($AL$41*AR50,AP50) -> 0 | AU50: ='1 - Input'!$B$22*(AR50-AT50) -> 933.12788 | AV50: =AR50-AU50 -> 2655.8255 | AW50: =AP50-AT50 -> 486427.67 | AX50: =IF('1 - Input'!$B$17=1,MAX(0,AV50-AN50),0) -> 0 | AY50: =IF('1 - Input'!$B$17=1,MAX(0,AN50-AV50),0) -> 44.174493 | AZ50: =IF(AS50>0,MAX(0,1-AW50/AS50),0) -> 0 | BA50: =IF(AND(AY50>0,AS50>0),AY50/(1-'1 - Input'!$B$22*AZ50),0) -> 44.174493 | BB50: =MIN(BA50,AS50) -> 44.174493 | BC50: ='1 - Input'!$B$22*AZ50*BB50 -> 0 | BD50: =BB50-BC50 -> 44.174493 | BE50: =AY50-BD50 -> 0 | BF50: =IF(AS50>0,BB50*MAX(0,AW50/AS50-1),0) -> 1.0686504 | BG50: =AS50-BB50+AX50 -> 474893.99 | BH50: =IF(BB50>0,AW50*(1-BB50/AS50),AW50)+AX50 -> 486382.42 | BI50: =IF(MOD(AK50,12)=0,BG50*'1 - Input'!$B$23,0) -> 0 | BJ50: =BG50-BI50 -> 474893.99 | BK50: =IF(MOD(AK50,12)=0,BH50*(1-'1 - Input'!$B$23),BH50) -> 486382.42 | BL50: =IF('1 - Input'!$B$17=1,MIN(AV50,AN50)+BD50,AV50) -> 2700 | BM50: =BM49+BL50 -> 18900 | BN50: =BN49+AU50 -> 6600.119 | BO50: =BO49+BC50 -> 0 | BP50: =BP49+BF50 -> 2.5317895 | BQ50: =BQ49+BI50 -> 0 | BR50: =BR49+BE50 -> 0 | BS50: =IF(BG50<=0.000001,1,0) -> 0 | BU50: 7 | BV50: =ROUNDUP(BU50/12,0) -> 1 | BW50: =(1+INDEX('1 - Input'!$B$34:$E$63,BV50,'1 - Input'!$B$16))^(1/12)-1 -> 0.0041219243 | BX50: ='1 - Input'!$B$7*(1+'1 - Input'!$B$12)^(BV50-1) -> 2700 | BY50: =CT49 -> 482288.71 | BZ50: =CU49 -> 470300 | CA50: =BY50*(1+BW50) -> 484276.67 | CB50: =IF(CA50>0,'1 - Input'!$B$8/12*CA50,0) -> 3632.075 | CC50: =CA50-CB50 -> 480644.59 | CD50: =MIN($BV$41*CB50,BZ50) -> 3632.075 | CE50: ='1 - Input'!$B$22*(CB50-CD50) -> 0 | CF50: =CB50-CE50 -> 3632.075 | CG50: =BZ50-CD50 -> 466667.93 | CH50: =IF('1 - Input'!$B$17=1,MAX(0,CF50-BX50),0) -> 932.075 | CI50: =IF('1 - Input'!$B$17=1,MAX(0,BX50-CF50),0) -> 0 | CJ50: =IF(CC50>0,MAX(0,1-CG50/CC50),0) -> 0.029079005 | CK50: =IF(AND(CI50>0,CC50>0),CI50/(1-'1 - Input'!$B$22*CJ50),0) -> 0 | CL50: =MIN(CK50,CC50) -> 0 | CM50: ='1 - Input'!$B$22*CJ50*CL50 -> 0 | CN50: =CL50-CM50 -> 0 | CO50: =CI50-CN50 -> 0 | CP50: =IF(CC50>0,CL50*MAX(0,CG50/CC50-1),0) -> 0 | CQ50: =CC50-CL50+CH50 -> 481576.67 | CR50: =IF(CL50>0,CG50*(1-CL50/CC50),CG50)+CH50 -> 467600 | CS50: =IF(MOD(BU50,12)=0,CQ50*'1 - Input'!$B$23,0) -> 0 | CT50: =CQ50-CS50 -> 481576.67 | CU50: =IF(MOD(BU50,12)=0,CR50*(1-'1 - Input'!$B$23),CR50) -> 467600 | CV50: =IF('1 - Input'!$B$17=1,MIN(CF50,BX50)+CN50,CF50) -> 2700 | CW50: =CW49+CV50 -> 18900 | CX50: =CX49+CE50 -> 0 | CY50: =CY49+CM50 -> 0 | CZ50: =CZ49+CP50 -> 0 | DA50: =DA49+CS50 -> 0 | DB50: =DB49+CO50 -> 0 | DC50: =IF(CQ50<=0.000001,1,0) -> 0
A51: 8 | B51: =ROUNDUP(A51/12,0) -> 1 | C51: =(1+INDEX('1 - Input'!$B$34:$E$63,B51,'1 - Input'!$B$16))^(1/12)-1 -> 0.0041219243 | D51: ='1 - Input'!$B$7*(1+'1 - Input'!$B$12)^(B51-1) -> 2700 | E51: =Z50 -> 474893.99 | F51: =AA50 -> 486382.42 | G51: =E51*(1+C51) -> 476851.47 | H51: =IF(G51>0,'1 - Input'!$B$8/12*G51,0) -> 3576.386 | I51: =G51-H51 -> 473275.08 | J51: =MIN($B$41*H51,F51) -> 0 | K51: ='1 - Input'!$B$22*(H51-J51) -> 929.86036 | L51: =H51-K51 -> 2646.5256 | M51: =F51-J51 -> 486382.42 | N51: =IF('1 - Input'!$B$17=1,MAX(0,L51-D51),0) -> 0 | O51: =IF('1 - Input'!$B$17=1,MAX(0,D51-L51),0) -> 53.474354 | P51: =IF(I51>0,MAX(0,1-M51/I51),0) -> 0 | Q51: =IF(AND(O51>0,I51>0),O51/(1-'1 - Input'!$B$22*P51),0) -> 53.474354 | R51: =MIN(Q51,I51) -> 53.474354 | S51: ='1 - Input'!$B$22*P51*R51 -> 0 | T51: =R51-S51 -> 53.474354 | U51: =O51-T51 -> 0 | V51: =IF(I51>0,R51*MAX(0,M51/I51-1),0) -> 1.4809708 | W51: =I51-R51+N51 -> 473221.61 | X51: =IF(R51>0,M51*(1-R51/I51),M51)+N51 -> 486327.47 | Y51: =IF(MOD(A51,12)=0,W51*'1 - Input'!$B$23,0) -> 0 | Z51: =W51-Y51 -> 473221.61 | AA51: =IF(MOD(A51,12)=0,X51*(1-'1 - Input'!$B$23),X51) -> 486327.47 | AB51: =IF('1 - Input'!$B$17=1,MIN(L51,D51)+T51,L51) -> 2700 | AC51: =AC50+AB51 -> 21600 | AD51: =AD50+K51 -> 7529.9794 | AE51: =AE50+S51 -> 0 | AF51: =AF50+V51 -> 4.0127603 | AG51: =AG50+Y51 -> 0 | AH51: =AH50+U51 -> 0 | AI51: =IF(W51<=0.000001,1,0) -> 0 | AK51: 8 | AL51: =ROUNDUP(AK51/12,0) -> 1 | AM51: =(1+INDEX('1 - Input'!$B$34:$E$63,AL51,'1 - Input'!$B$16))^(1/12)-1 -> 0.0041219243 | AN51: ='1 - Input'!$B$7*(1+'1 - Input'!$B$12)^(AL51-1) -> 2700 | AO51: =BJ50 -> 474893.99 | AP51: =BK50 -> 486382.42 | AQ51: =AO51*(1+AM51) -> 476851.47 | AR51: =IF(AQ51>0,'1 - Input'!$B$8/12*AQ51,0) -> 3576.386 | AS51: =AQ51-AR51 -> 473275.08 | AT51: =MIN($AL$41*AR51,AP51) -> 0 | AU51: ='1 - Input'!$B$22*(AR51-AT51) -> 929.86036 | AV51: =AR51-AU51 -> 2646.5256 | AW51: =AP51-AT51 -> 486382.42 | AX51: =IF('1 - Input'!$B$17=1,MAX(0,AV51-AN51),0) -> 0 | AY51: =IF('1 - Input'!$B$17=1,MAX(0,AN51-AV51),0) -> 53.474354 | AZ51: =IF(AS51>0,MAX(0,1-AW51/AS51),0) -> 0 | BA51: =IF(AND(AY51>0,AS51>0),AY51/(1-'1 - Input'!$B$22*AZ51),0) -> 53.474354 | BB51: =MIN(BA51,AS51) -> 53.474354 | BC51: ='1 - Input'!$B$22*AZ51*BB51 -> 0 | BD51: =BB51-BC51 -> 53.474354 | BE51: =AY51-BD51 -> 0 | BF51: =IF(AS51>0,BB51*MAX(0,AW51/AS51-1),0) -> 1.4809708 | BG51: =AS51-BB51+AX51 -> 473221.61 | BH51: =IF(BB51>0,AW51*(1-BB51/AS51),AW51)+AX51 -> 486327.47 | BI51: =IF(MOD(AK51,12)=0,BG51*'1 - Input'!$B$23,0) -> 0 | BJ51: =BG51-BI51 -> 473221.61 | BK51: =IF(MOD(AK51,12)=0,BH51*(1-'1 - Input'!$B$23),BH51) -> 486327.47 | BL51: =IF('1 - Input'!$B$17=1,MIN(AV51,AN51)+BD51,AV51) -> 2700 | BM51: =BM50+BL51 -> 21600 | BN51: =BN50+AU51 -> 7529.9794 | BO51: =BO50+BC51 -> 0 | BP51: =BP50+BF51 -> 4.0127603 | BQ51: =BQ50+BI51 -> 0 | BR51: =BR50+BE51 -> 0 | BS51: =IF(BG51<=0.000001,1,0) -> 0 | BU51: 8 | BV51: =ROUNDUP(BU51/12,0) -> 1 | BW51: =(1+INDEX('1 - Input'!$B$34:$E$63,BV51,'1 - Input'!$B$16))^(1/12)-1 -> 0.0041219243 | BX51: ='1 - Input'!$B$7*(1+'1 - Input'!$B$12)^(BV51-1) -> 2700 | BY51: =CT50 -> 481576.67 | BZ51: =CU50 -> 467600 | CA51: =BY51*(1+BW51) -> 483561.69 | CB51: =IF(CA51>0,'1 - Input'!$B$8/12*CA51,0) -> 3626.7127 | CC51: =CA51-CB51 -> 479934.98 | CD51: =MIN($BV$41*CB51,BZ51) -> 3626.7127 | CE51: ='1 - Input'!$B$22*(CB51-CD51) -> 0 | CF51: =CB51-CE51 -> 3626.7127 | CG51: =BZ51-CD51 -> 463973.29 | CH51: =IF('1 - Input'!$B$17=1,MAX(0,CF51-BX51),0) -> 926.71267 | CI51: =IF('1 - Input'!$B$17=1,MAX(0,BX51-CF51),0) -> 0 | CJ51: =IF(CC51>0,MAX(0,1-CG51/CC51),0) -> 0.033258024 | CK51: =IF(AND(CI51>0,CC51>0),CI51/(1-'1 - Input'!$B$22*CJ51),0) -> 0 | CL51: =MIN(CK51,CC51) -> 0 | CM51: ='1 - Input'!$B$22*CJ51*CL51 -> 0 | CN51: =CL51-CM51 -> 0 | CO51: =CI51-CN51 -> 0 | CP51: =IF(CC51>0,CL51*MAX(0,CG51/CC51-1),0) -> 0 | CQ51: =CC51-CL51+CH51 -> 480861.69 | CR51: =IF(CL51>0,CG51*(1-CL51/CC51),CG51)+CH51 -> 464900 | CS51: =IF(MOD(BU51,12)=0,CQ51*'1 - Input'!$B$23,0) -> 0 | CT51: =CQ51-CS51 -> 480861.69 | CU51: =IF(MOD(BU51,12)=0,CR51*(1-'1 - Input'!$B$23),CR51) -> 464900 | CV51: =IF('1 - Input'!$B$17=1,MIN(CF51,BX51)+CN51,CF51) -> 2700 | CW51: =CW50+CV51 -> 21600 | CX51: =CX50+CE51 -> 0 | CY51: =CY50+CM51 -> 0 | CZ51: =CZ50+CP51 -> 0 | DA51: =DA50+CS51 -> 0 | DB51: =DB50+CO51 -> 0 | DC51: =IF(CQ51<=0.000001,1,0) -> 0
A52: 9 | B52: =ROUNDUP(A52/12,0) -> 1 | C52: =(1+INDEX('1 - Input'!$B$34:$E$63,B52,'1 - Input'!$B$16))^(1/12)-1 -> 0.0041219243 | D52: ='1 - Input'!$B$7*(1+'1 - Input'!$B$12)^(B52-1) -> 2700 | E52: =Z51 -> 473221.61 | F52: =AA51 -> 486327.47 | G52: =E52*(1+C52) -> 475172.19 | H52: =IF(G52>0,'1 - Input'!$B$8/12*G52,0) -> 3563.7914 | I52: =G52-H52 -> 471608.4 | J52: =MIN($B$41*H52,F52) -> 0 | K52: ='1 - Input'!$B$22*(H52-J52) -> 926.58577 | L52: =H52-K52 -> 2637.2057 | M52: =F52-J52 -> 486327.47 | N52: =IF('1 - Input'!$B$17=1,MAX(0,L52-D52),0) -> 0 | O52: =IF('1 - Input'!$B$17=1,MAX(0,D52-L52),0) -> 62.79434 | P52: =IF(I52>0,MAX(0,1-M52/I52),0) -> 0 | Q52: =IF(AND(O52>0,I52>0),O52/(1-'1 - Input'!$B$22*P52),0) -> 62.79434 | R52: =MIN(Q52,I52) -> 62.79434 | S52: ='1 - Input'!$B$22*P52*R52 -> 0 | T52: =R52-S52 -> 62.79434 | U52: =O52-T52 -> 0 | V52: =IF(I52>0,R52*MAX(0,M52/I52-1),0) -> 1.9598339 | W52: =I52-R52+N52 -> 471545.61 | X52: =IF(R52>0,M52*(1-R52/I52),M52)+N52 -> 486262.71 | Y52: =IF(MOD(A52,12)=0,W52*'1 - Input'!$B$23,0) -> 0 | Z52: =W52-Y52 -> 471545.61 | AA52: =IF(MOD(A52,12)=0,X52*(1-'1 - Input'!$B$23),X52) -> 486262.71 | AB52: =IF('1 - Input'!$B$17=1,MIN(L52,D52)+T52,L52) -> 2700 | AC52: =AC51+AB52 -> 24300 | AD52: =AD51+K52 -> 8456.5652 | AE52: =AE51+S52 -> 0 | AF52: =AF51+V52 -> 5.9725942 | AG52: =AG51+Y52 -> 0 | AH52: =AH51+U52 -> 0 | AI52: =IF(W52<=0.000001,1,0) -> 0 | AK52: 9 | AL52: =ROUNDUP(AK52/12,0) -> 1 | AM52: =(1+INDEX('1 - Input'!$B$34:$E$63,AL52,'1 - Input'!$B$16))^(1/12)-1 -> 0.0041219243 | AN52: ='1 - Input'!$B$7*(1+'1 - Input'!$B$12)^(AL52-1) -> 2700 | AO52: =BJ51 -> 473221.61 | AP52: =BK51 -> 486327.47 | AQ52: =AO52*(1+AM52) -> 475172.19 | AR52: =IF(AQ52>0,'1 - Input'!$B$8/12*AQ52,0) -> 3563.7914 | AS52: =AQ52-AR52 -> 471608.4 | AT52: =MIN($AL$41*AR52,AP52) -> 0 | AU52: ='1 - Input'!$B$22*(AR52-AT52) -> 926.58577 | AV52: =AR52-AU52 -> 2637.2057 | AW52: =AP52-AT52 -> 486327.47 | AX52: =IF('1 - Input'!$B$17=1,MAX(0,AV52-AN52),0) -> 0 | AY52: =IF('1 - Input'!$B$17=1,MAX(0,AN52-AV52),0) -> 62.79434 | AZ52: =IF(AS52>0,MAX(0,1-AW52/AS52),0) -> 0 | BA52: =IF(AND(AY52>0,AS52>0),AY52/(1-'1 - Input'!$B$22*AZ52),0) -> 62.79434 | BB52: =MIN(BA52,AS52) -> 62.79434 | BC52: ='1 - Input'!$B$22*AZ52*BB52 -> 0 | BD52: =BB52-BC52 -> 62.79434 | BE52: =AY52-BD52 -> 0 | BF52: =IF(AS52>0,BB52*MAX(0,AW52/AS52-1),0) -> 1.9598339 | BG52: =AS52-BB52+AX52 -> 471545.61 | BH52: =IF(BB52>0,AW52*(1-BB52/AS52),AW52)+AX52 -> 486262.71 | BI52: =IF(MOD(AK52,12)=0,BG52*'1 - Input'!$B$23,0) -> 0 | BJ52: =BG52-BI52 -> 471545.61 | BK52: =IF(MOD(AK52,12)=0,BH52*(1-'1 - Input'!$B$23),BH52) -> 486262.71 | BL52: =IF('1 - Input'!$B$17=1,MIN(AV52,AN52)+BD52,AV52) -> 2700 | BM52: =BM51+BL52 -> 24300 | BN52: =BN51+AU52 -> 8456.5652 | BO52: =BO51+BC52 -> 0 | BP52: =BP51+BF52 -> 5.9725942 | BQ52: =BQ51+BI52 -> 0 | BR52: =BR51+BE52 -> 0 | BS52: =IF(BG52<=0.000001,1,0) -> 0 | BU52: 9 | BV52: =ROUNDUP(BU52/12,0) -> 1 | BW52: =(1+INDEX('1 - Input'!$B$34:$E$63,BV52,'1 - Input'!$B$16))^(1/12)-1 -> 0.0041219243 | BX52: ='1 - Input'!$B$7*(1+'1 - Input'!$B$12)^(BV52-1) -> 2700 | BY52: =CT51 -> 480861.69 | BZ52: =CU51 -> 464900 | CA52: =BY52*(1+BW52) -> 482843.76 | CB52: =IF(CA52>0,'1 - Input'!$B$8/12*CA52,0) -> 3621.3282 | CC52: =CA52-CB52 -> 479222.44 | CD52: =MIN($BV$41*CB52,BZ52) -> 3621.3282 | CE52: ='1 - Input'!$B$22*(CB52-CD52) -> 0 | CF52: =CB52-CE52 -> 3621.3282 | CG52: =BZ52-CD52 -> 461278.67 | CH52: =IF('1 - Input'!$B$17=1,MAX(0,CF52-BX52),0) -> 921.32823 | CI52: =IF('1 - Input'!$B$17=1,MAX(0,BX52-CF52),0) -> 0 | CJ52: =IF(CC52>0,MAX(0,1-CG52/CC52),0) -> 0.037443498 | CK52: =IF(AND(CI52>0,CC52>0),CI52/(1-'1 - Input'!$B$22*CJ52),0) -> 0 | CL52: =MIN(CK52,CC52) -> 0 | CM52: ='1 - Input'!$B$22*CJ52*CL52 -> 0 | CN52: =CL52-CM52 -> 0 | CO52: =CI52-CN52 -> 0 | CP52: =IF(CC52>0,CL52*MAX(0,CG52/CC52-1),0) -> 0 | CQ52: =CC52-CL52+CH52 -> 480143.76 | CR52: =IF(CL52>0,CG52*(1-CL52/CC52),CG52)+CH52 -> 462200 | CS52: =IF(MOD(BU52,12)=0,CQ52*'1 - Input'!$B$23,0) -> 0 | CT52: =CQ52-CS52 -> 480143.76 | CU52: =IF(MOD(BU52,12)=0,CR52*(1-'1 - Input'!$B$23),CR52) -> 462200 | CV52: =IF('1 - Input'!$B$17=1,MIN(CF52,BX52)+CN52,CF52) -> 2700 | CW52: =CW51+CV52 -> 24300 | CX52: =CX51+CE52 -> 0 | CY52: =CY51+CM52 -> 0 | CZ52: =CZ51+CP52 -> 0 | DA52: =DA51+CS52 -> 0 | DB52: =DB51+CO52 -> 0 | DC52: =IF(CQ52<=0.000001,1,0) -> 0
A53: 10 | B53: =ROUNDUP(A53/12,0) -> 1 | C53: =(1+INDEX('1 - Input'!$B$34:$E$63,B53,'1 - Input'!$B$16))^(1/12)-1 -> 0.0041219243 | D53: ='1 - Input'!$B$7*(1+'1 - Input'!$B$12)^(B53-1) -> 2700 | E53: =Z52 -> 471545.61 | F53: =AA52 -> 486262.71 | G53: =E53*(1+C53) -> 473489.28 | H53: =IF(G53>0,'1 - Input'!$B$8/12*G53,0) -> 3551.1696 | I53: =G53-H53 -> 469938.11 | J53: =MIN($B$41*H53,F53) -> 0 | K53: ='1 - Input'!$B$22*(H53-J53) -> 923.3041 | L53: =H53-K53 -> 2627.8655 | M53: =F53-J53 -> 486262.71 | N53: =IF('1 - Input'!$B$17=1,MAX(0,L53-D53),0) -> 0 | O53: =IF('1 - Input'!$B$17=1,MAX(0,D53-L53),0) -> 72.134493 | P53: =IF(I53>0,MAX(0,1-M53/I53),0) -> 0 | Q53: =IF(AND(O53>0,I53>0),O53/(1-'1 - Input'!$B$22*P53),0) -> 72.134493 | R53: =MIN(Q53,I53) -> 72.134493 | S53: ='1 - Input'!$B$22*P53*R53 -> 0 | T53: =R53-S53 -> 72.134493 | U53: =O53-T53 -> 0 | V53: =IF(I53>0,R53*MAX(0,M53/I53-1),0) -> 2.5057914 | W53: =I53-R53+N53 -> 469865.98 | X53: =IF(R53>0,M53*(1-R53/I53),M53)+N53 -> 486188.07 | Y53: =IF(MOD(A53,12)=0,W53*'1 - Input'!$B$23,0) -> 0 | Z53: =W53-Y53 -> 469865.98 | AA53: =IF(MOD(A53,12)=0,X53*(1-'1 - Input'!$B$23),X53) -> 486188.07 | AB53: =IF('1 - Input'!$B$17=1,MIN(L53,D53)+T53,L53) -> 2700 | AC53: =AC52+AB53 -> 27000 | AD53: =AD52+K53 -> 9379.8693 | AE53: =AE52+S53 -> 0 | AF53: =AF52+V53 -> 8.4783856 | AG53: =AG52+Y53 -> 0 | AH53: =AH52+U53 -> 0 | AI53: =IF(W53<=0.000001,1,0) -> 0 | AK53: 10 | AL53: =ROUNDUP(AK53/12,0) -> 1 | AM53: =(1+INDEX('1 - Input'!$B$34:$E$63,AL53,'1 - Input'!$B$16))^(1/12)-1 -> 0.0041219243 | AN53: ='1 - Input'!$B$7*(1+'1 - Input'!$B$12)^(AL53-1) -> 2700 | AO53: =BJ52 -> 471545.61 | AP53: =BK52 -> 486262.71 | AQ53: =AO53*(1+AM53) -> 473489.28 | AR53: =IF(AQ53>0,'1 - Input'!$B$8/12*AQ53,0) -> 3551.1696 | AS53: =AQ53-AR53 -> 469938.11 | AT53: =MIN($AL$41*AR53,AP53) -> 0 | AU53: ='1 - Input'!$B$22*(AR53-AT53) -> 923.3041 | AV53: =AR53-AU53 -> 2627.8655 | AW53: =AP53-AT53 -> 486262.71 | AX53: =IF('1 - Input'!$B$17=1,MAX(0,AV53-AN53),0) -> 0 | AY53: =IF('1 - Input'!$B$17=1,MAX(0,AN53-AV53),0) -> 72.134493 | AZ53: =IF(AS53>0,MAX(0,1-AW53/AS53),0) -> 0 | BA53: =IF(AND(AY53>0,AS53>0),AY53/(1-'1 - Input'!$B$22*AZ53),0) -> 72.134493 | BB53: =MIN(BA53,AS53) -> 72.134493 | BC53: ='1 - Input'!$B$22*AZ53*BB53 -> 0 | BD53: =BB53-BC53 -> 72.134493 | BE53: =AY53-BD53 -> 0 | BF53: =IF(AS53>0,BB53*MAX(0,AW53/AS53-1),0) -> 2.5057914 | BG53: =AS53-BB53+AX53 -> 469865.98 | BH53: =IF(BB53>0,AW53*(1-BB53/AS53),AW53)+AX53 -> 486188.07 | BI53: =IF(MOD(AK53,12)=0,BG53*'1 - Input'!$B$23,0) -> 0 | BJ53: =BG53-BI53 -> 469865.98 | BK53: =IF(MOD(AK53,12)=0,BH53*(1-'1 - Input'!$B$23),BH53) -> 486188.07 | BL53: =IF('1 - Input'!$B$17=1,MIN(AV53,AN53)+BD53,AV53) -> 2700 | BM53: =BM52+BL53 -> 27000 | BN53: =BN52+AU53 -> 9379.8693 | BO53: =BO52+BC53 -> 0 | BP53: =BP52+BF53 -> 8.4783856 | BQ53: =BQ52+BI53 -> 0 | BR53: =BR52+BE53 -> 0 | BS53: =IF(BG53<=0.000001,1,0) -> 0 | BU53: 10 | BV53: =ROUNDUP(BU53/12,0) -> 1 | BW53: =(1+INDEX('1 - Input'!$B$34:$E$63,BV53,'1 - Input'!$B$16))^(1/12)-1 -> 0.0041219243 | BX53: ='1 - Input'!$B$7*(1+'1 - Input'!$B$12)^(BV53-1) -> 2700 | BY53: =CT52 -> 480143.76 | BZ53: =CU52 -> 462200 | CA53: =BY53*(1+BW53) -> 482122.88 | CB53: =IF(CA53>0,'1 - Input'!$B$8/12*CA53,0) -> 3615.9216 | CC53: =CA53-CB53 -> 478506.96 | CD53: =MIN($BV$41*CB53,BZ53) -> 3615.9216 | CE53: ='1 - Input'!$B$22*(CB53-CD53) -> 0 | CF53: =CB53-CE53 -> 3615.9216 | CG53: =BZ53-CD53 -> 458584.08 | CH53: =IF('1 - Input'!$B$17=1,MAX(0,CF53-BX53),0) -> 915.92161 | CI53: =IF('1 - Input'!$B$17=1,MAX(0,BX53-CF53),0) -> 0 | CJ53: =IF(CC53>0,MAX(0,1-CG53/CC53),0) -> 0.041635509 | CK53: =IF(AND(CI53>0,CC53>0),CI53/(1-'1 - Input'!$B$22*CJ53),0) -> 0 | CL53: =MIN(CK53,CC53) -> 0 | CM53: ='1 - Input'!$B$22*CJ53*CL53 -> 0 | CN53: =CL53-CM53 -> 0 | CO53: =CI53-CN53 -> 0 | CP53: =IF(CC53>0,CL53*MAX(0,CG53/CC53-1),0) -> 0 | CQ53: =CC53-CL53+CH53 -> 479422.88 | CR53: =IF(CL53>0,CG53*(1-CL53/CC53),CG53)+CH53 -> 459500 | CS53: =IF(MOD(BU53,12)=0,CQ53*'1 - Input'!$B$23,0) -> 0 | CT53: =CQ53-CS53 -> 479422.88 | CU53: =IF(MOD(BU53,12)=0,CR53*(1-'1 - Input'!$B$23),CR53) -> 459500 | CV53: =IF('1 - Input'!$B$17=1,MIN(CF53,BX53)+CN53,CF53) -> 2700 | CW53: =CW52+CV53 -> 27000 | CX53: =CX52+CE53 -> 0 | CY53: =CY52+CM53 -> 0 | CZ53: =CZ52+CP53 -> 0 | DA53: =DA52+CS53 -> 0 | DB53: =DB52+CO53 -> 0 | DC53: =IF(CQ53<=0.000001,1,0) -> 0
A54: 11 | B54: =ROUNDUP(A54/12,0) -> 1 | C54: =(1+INDEX('1 - Input'!$B$34:$E$63,B54,'1 - Input'!$B$16))^(1/12)-1 -> 0.0041219243 | D54: ='1 - Input'!$B$7*(1+'1 - Input'!$B$12)^(B54-1) -> 2700 | E54: =Z53 -> 469865.98 | F54: =AA53 -> 486188.07 | G54: =E54*(1+C54) -> 471802.73 | H54: =IF(G54>0,'1 - Input'!$B$8/12*G54,0) -> 3538.5205 | I54: =G54-H54 -> 468264.21 | J54: =MIN($B$41*H54,F54) -> 0 | K54: ='1 - Input'!$B$22*(H54-J54) -> 920.01532 | L54: =H54-K54 -> 2618.5051 | M54: =F54-J54 -> 486188.07 | N54: =IF('1 - Input'!$B$17=1,MAX(0,L54-D54),0) -> 0 | O54: =IF('1 - Input'!$B$17=1,MAX(0,D54-L54),0) -> 81.494857 | P54: =IF(I54>0,MAX(0,1-M54/I54),0) -> 0 | Q54: =IF(AND(O54>0,I54>0),O54/(1-'1 - Input'!$B$22*P54),0) -> 81.494857 | R54: =MIN(Q54,I54) -> 81.494857 | S54: ='1 - Input'!$B$22*P54*R54 -> 0 | T54: =R54-S54 -> 81.494857 | U54: =O54-T54 -> 0 | V54: =IF(I54>0,R54*MAX(0,M54/I54-1),0) -> 3.1193988 | W54: =I54-R54+N54 -> 468182.71 | X54: =IF(R54>0,M54*(1-R54/I54),M54)+N54 -> 486103.46 | Y54: =IF(MOD(A54,12)=0,W54*'1 - Input'!$B$23,0) -> 0 | Z54: =W54-Y54 -> 468182.71 | AA54: =IF(MOD(A54,12)=0,X54*(1-'1 - Input'!$B$23),X54) -> 486103.46 | AB54: =IF('1 - Input'!$B$17=1,MIN(L54,D54)+T54,L54) -> 2700 | AC54: =AC53+AB54 -> 29700 | AD54: =AD53+K54 -> 10299.885 | AE54: =AE53+S54 -> 0 | AF54: =AF53+V54 -> 11.597784 | AG54: =AG53+Y54 -> 0 | AH54: =AH53+U54 -> 0 | AI54: =IF(W54<=0.000001,1,0) -> 0 | AK54: 11 | AL54: =ROUNDUP(AK54/12,0) -> 1 | AM54: =(1+INDEX('1 - Input'!$B$34:$E$63,AL54,'1 - Input'!$B$16))^(1/12)-1 -> 0.0041219243 | AN54: ='1 - Input'!$B$7*(1+'1 - Input'!$B$12)^(AL54-1) -> 2700 | AO54: =BJ53 -> 469865.98 | AP54: =BK53 -> 486188.07 | AQ54: =AO54*(1+AM54) -> 471802.73 | AR54: =IF(AQ54>0,'1 - Input'!$B$8/12*AQ54,0) -> 3538.5205 | AS54: =AQ54-AR54 -> 468264.21 | AT54: =MIN($AL$41*AR54,AP54) -> 0 | AU54: ='1 - Input'!$B$22*(AR54-AT54) -> 920.01532 | AV54: =AR54-AU54 -> 2618.5051 | AW54: =AP54-AT54 -> 486188.07 | AX54: =IF('1 - Input'!$B$17=1,MAX(0,AV54-AN54),0) -> 0 | AY54: =IF('1 - Input'!$B$17=1,MAX(0,AN54-AV54),0) -> 81.494857 | AZ54: =IF(AS54>0,MAX(0,1-AW54/AS54),0) -> 0 | BA54: =IF(AND(AY54>0,AS54>0),AY54/(1-'1 - Input'!$B$22*AZ54),0) -> 81.494857 | BB54: =MIN(BA54,AS54) -> 81.494857 | BC54: ='1 - Input'!$B$22*AZ54*BB54 -> 0 | BD54: =BB54-BC54 -> 81.494857 | BE54: =AY54-BD54 -> 0 | BF54: =IF(AS54>0,BB54*MAX(0,AW54/AS54-1),0) -> 3.1193988 | BG54: =AS54-BB54+AX54 -> 468182.71 | BH54: =IF(BB54>0,AW54*(1-BB54/AS54),AW54)+AX54 -> 486103.46 | BI54: =IF(MOD(AK54,12)=0,BG54*'1 - Input'!$B$23,0) -> 0 | BJ54: =BG54-BI54 -> 468182.71 | BK54: =IF(MOD(AK54,12)=0,BH54*(1-'1 - Input'!$B$23),BH54) -> 486103.46 | BL54: =IF('1 - Input'!$B$17=1,MIN(AV54,AN54)+BD54,AV54) -> 2700 | BM54: =BM53+BL54 -> 29700 | BN54: =BN53+AU54 -> 10299.885 | BO54: =BO53+BC54 -> 0 | BP54: =BP53+BF54 -> 11.597784 | BQ54: =BQ53+BI54 -> 0 | BR54: =BR53+BE54 -> 0 | BS54: =IF(BG54<=0.000001,1,0) -> 0 | BU54: 11 | BV54: =ROUNDUP(BU54/12,0) -> 1 | BW54: =(1+INDEX('1 - Input'!$B$34:$E$63,BV54,'1 - Input'!$B$16))^(1/12)-1 -> 0.0041219243 | BX54: ='1 - Input'!$B$7*(1+'1 - Input'!$B$12)^(BV54-1) -> 2700 | BY54: =CT53 -> 479422.88 | BZ54: =CU53 -> 459500 | CA54: =BY54*(1+BW54) -> 481399.03 | CB54: =IF(CA54>0,'1 - Input'!$B$8/12*CA54,0) -> 3610.4927 | CC54: =CA54-CB54 -> 477788.53 | CD54: =MIN($BV$41*CB54,BZ54) -> 3610.4927 | CE54: ='1 - Input'!$B$22*(CB54-CD54) -> 0 | CF54: =CB54-CE54 -> 3610.4927 | CG54: =BZ54-CD54 -> 455889.51 | CH54: =IF('1 - Input'!$B$17=1,MAX(0,CF54-BX54),0) -> 910.49269 | CI54: =IF('1 - Input'!$B$17=1,MAX(0,BX54-CF54),0) -> 0 | CJ54: =IF(CC54>0,MAX(0,1-CG54/CC54),0) -> 0.045834138 | CK54: =IF(AND(CI54>0,CC54>0),CI54/(1-'1 - Input'!$B$22*CJ54),0) -> 0 | CL54: =MIN(CK54,CC54) -> 0 | CM54: ='1 - Input'!$B$22*CJ54*CL54 -> 0 | CN54: =CL54-CM54 -> 0 | CO54: =CI54-CN54 -> 0 | CP54: =IF(CC54>0,CL54*MAX(0,CG54/CC54-1),0) -> 0 | CQ54: =CC54-CL54+CH54 -> 478699.03 | CR54: =IF(CL54>0,CG54*(1-CL54/CC54),CG54)+CH54 -> 456800 | CS54: =IF(MOD(BU54,12)=0,CQ54*'1 - Input'!$B$23,0) -> 0 | CT54: =CQ54-CS54 -> 478699.03 | CU54: =IF(MOD(BU54,12)=0,CR54*(1-'1 - Input'!$B$23),CR54) -> 456800 | CV54: =IF('1 - Input'!$B$17=1,MIN(CF54,BX54)+CN54,CF54) -> 2700 | CW54: =CW53+CV54 -> 29700 | CX54: =CX53+CE54 -> 0 | CY54: =CY53+CM54 -> 0 | CZ54: =CZ53+CP54 -> 0 | DA54: =DA53+CS54 -> 0 | DB54: =DB53+CO54 -> 0 | DC54: =IF(CQ54<=0.000001,1,0) -> 0
A55: 12 | B55: =ROUNDUP(A55/12,0) -> 1 | C55: =(1+INDEX('1 - Input'!$B$34:$E$63,B55,'1 - Input'!$B$16))^(1/12)-1 -> 0.0041219243 | D55: ='1 - Input'!$B$7*(1+'1 - Input'!$B$12)^(B55-1) -> 2700 | E55: =Z54 -> 468182.71 | F55: =AA54 -> 486103.46 | G55: =E55*(1+C55) -> 470112.53 | H55: =IF(G55>0,'1 - Input'!$B$8/12*G55,0) -> 3525.844 | I55: =G55-H55 -> 466586.68 | J55: =MIN($B$41*H55,F55) -> 0 | K55: ='1 - Input'!$B$22*(H55-J55) -> 916.71943 | L55: =H55-K55 -> 2609.1245 | M55: =F55-J55 -> 486103.46 | N55: =IF('1 - Input'!$B$17=1,MAX(0,L55-D55),0) -> 0 | O55: =IF('1 - Input'!$B$17=1,MAX(0,D55-L55),0) -> 90.875476 | P55: =IF(I55>0,MAX(0,1-M55/I55),0) -> 0 | Q55: =IF(AND(O55>0,I55>0),O55/(1-'1 - Input'!$B$22*P55),0) -> 90.875476 | R55: =MIN(Q55,I55) -> 90.875476 | S55: ='1 - Input'!$B$22*P55*R55 -> 0 | T55: =R55-S55 -> 90.875476 | U55: =O55-T55 -> 0 | V55: =IF(I55>0,R55*MAX(0,M55/I55-1),0) -> 3.8012149 | W55: =I55-R55+N55 -> 466495.81 | X55: =IF(R55>0,M55*(1-R55/I55),M55)+N55 -> 486008.78 | Y55: =IF(MOD(A55,12)=0,W55*'1 - Input'!$B$23,0) -> 932.99161 | Z55: =W55-Y55 -> 465562.82 | AA55: =IF(MOD(A55,12)=0,X55*(1-'1 - Input'!$B$23),X55) -> 485036.76 | AB55: =IF('1 - Input'!$B$17=1,MIN(L55,D55)+T55,L55) -> 2700 | AC55: =AC54+AB55 -> 32400 | AD55: =AD54+K55 -> 11216.604 | AE55: =AE54+S55 -> 0 | AF55: =AF54+V55 -> 15.398999 | AG55: =AG54+Y55 -> 932.99161 | AH55: =AH54+U55 -> 0 | AI55: =IF(W55<=0.000001,1,0) -> 0 | AK55: 12 | AL55: =ROUNDUP(AK55/12,0) -> 1 | AM55: =(1+INDEX('1 - Input'!$B$34:$E$63,AL55,'1 - Input'!$B$16))^(1/12)-1 -> 0.0041219243 | AN55: ='1 - Input'!$B$7*(1+'1 - Input'!$B$12)^(AL55-1) -> 2700 | AO55: =BJ54 -> 468182.71 | AP55: =BK54 -> 486103.46 | AQ55: =AO55*(1+AM55) -> 470112.53 | AR55: =IF(AQ55>0,'1 - Input'!$B$8/12*AQ55,0) -> 3525.844 | AS55: =AQ55-AR55 -> 466586.68 | AT55: =MIN($AL$41*AR55,AP55) -> 0 | AU55: ='1 - Input'!$B$22*(AR55-AT55) -> 916.71943 | AV55: =AR55-AU55 -> 2609.1245 | AW55: =AP55-AT55 -> 486103.46 | AX55: =IF('1 - Input'!$B$17=1,MAX(0,AV55-AN55),0) -> 0 | AY55: =IF('1 - Input'!$B$17=1,MAX(0,AN55-AV55),0) -> 90.875476 | AZ55: =IF(AS55>0,MAX(0,1-AW55/AS55),0) -> 0 | BA55: =IF(AND(AY55>0,AS55>0),AY55/(1-'1 - Input'!$B$22*AZ55),0) -> 90.875476 | BB55: =MIN(BA55,AS55) -> 90.875476 | BC55: ='1 - Input'!$B$22*AZ55*BB55 -> 0 | BD55: =BB55-BC55 -> 90.875476 | BE55: =AY55-BD55 -> 0 | BF55: =IF(AS55>0,BB55*MAX(0,AW55/AS55-1),0) -> 3.8012149 | BG55: =AS55-BB55+AX55 -> 466495.81 | BH55: =IF(BB55>0,AW55*(1-BB55/AS55),AW55)+AX55 -> 486008.78 | BI55: =IF(MOD(AK55,12)=0,BG55*'1 - Input'!$B$23,0) -> 932.99161 | BJ55: =BG55-BI55 -> 465562.82 | BK55: =IF(MOD(AK55,12)=0,BH55*(1-'1 - Input'!$B$23),BH55) -> 485036.76 | BL55: =IF('1 - Input'!$B$17=1,MIN(AV55,AN55)+BD55,AV55) -> 2700 | BM55: =BM54+BL55 -> 32400 | BN55: =BN54+AU55 -> 11216.604 | BO55: =BO54+BC55 -> 0 | BP55: =BP54+BF55 -> 15.398999 | BQ55: =BQ54+BI55 -> 932.99161 | BR55: =BR54+BE55 -> 0 | BS55: =IF(BG55<=0.000001,1,0) -> 0 | BU55: 12 | BV55: =ROUNDUP(BU55/12,0) -> 1 | BW55: =(1+INDEX('1 - Input'!$B$34:$E$63,BV55,'1 - Input'!$B$16))^(1/12)-1 -> 0.0041219243 | BX55: ='1 - Input'!$B$7*(1+'1 - Input'!$B$12)^(BV55-1) -> 2700 | BY55: =CT54 -> 478699.03 | BZ55: =CU54 -> 456800 | CA55: =BY55*(1+BW55) -> 480672.19 | CB55: =IF(CA55>0,'1 - Input'!$B$8/12*CA55,0) -> 3605.0414 | CC55: =CA55-CB55 -> 477067.15 | CD55: =MIN($BV$41*CB55,BZ55) -> 3605.0414 | CE55: ='1 - Input'!$B$22*(CB55-CD55) -> 0 | CF55: =CB55-CE55 -> 3605.0414 | CG55: =BZ55-CD55 -> 453194.96 | CH55: =IF('1 - Input'!$B$17=1,MAX(0,CF55-BX55),0) -> 905.0414 | CI55: =IF('1 - Input'!$B$17=1,MAX(0,BX55-CF55),0) -> 0 | CJ55: =IF(CC55>0,MAX(0,1-CG55/CC55),0) -> 0.050039469 | CK55: =IF(AND(CI55>0,CC55>0),CI55/(1-'1 - Input'!$B$22*CJ55),0) -> 0 | CL55: =MIN(CK55,CC55) -> 0 | CM55: ='1 - Input'!$B$22*CJ55*CL55 -> 0 | CN55: =CL55-CM55 -> 0 | CO55: =CI55-CN55 -> 0 | CP55: =IF(CC55>0,CL55*MAX(0,CG55/CC55-1),0) -> 0 | CQ55: =CC55-CL55+CH55 -> 477972.19 | CR55: =IF(CL55>0,CG55*(1-CL55/CC55),CG55)+CH55 -> 454100 | CS55: =IF(MOD(BU55,12)=0,CQ55*'1 - Input'!$B$23,0) -> 955.94437 | CT55: =CQ55-CS55 -> 477016.24 | CU55: =IF(MOD(BU55,12)=0,CR55*(1-'1 - Input'!$B$23),CR55) -> 453191.8 | CV55: =IF('1 - Input'!$B$17=1,MIN(CF55,BX55)+CN55,CF55) -> 2700 | CW55: =CW54+CV55 -> 32400 | CX55: =CX54+CE55 -> 0 | CY55: =CY54+CM55 -> 0 | CZ55: =CZ54+CP55 -> 0 | DA55: =DA54+CS55 -> 955.94437 | DB55: =DB54+CO55 -> 0 | DC55: =IF(CQ55<=0.000001,1,0) -> 0
A56: 13 | B56: =ROUNDUP(A56/12,0) -> 2 | C56: =(1+INDEX('1 - Input'!$B$34:$E$63,B56,'1 - Input'!$B$16))^(1/12)-1 -> 0.0041219243 | D56: ='1 - Input'!$B$7*(1+'1 - Input'!$B$12)^(B56-1) -> 2754 | E56: =Z55 -> 465562.82 | F56: =AA55 -> 485036.76 | G56: =E56*(1+C56) -> 467481.83 | H56: =IF(G56>0,'1 - Input'!$B$8/12*G56,0) -> 3506.1137 | I56: =G56-H56 -> 463975.72 | J56: =MIN($B$41*H56,F56) -> 0 | K56: ='1 - Input'!$B$22*(H56-J56) -> 911.58957 | L56: =H56-K56 -> 2594.5242 | M56: =F56-J56 -> 485036.76 | N56: =IF('1 - Input'!$B$17=1,MAX(0,L56-D56),0) -> 0 | O56: =IF('1 - Input'!$B$17=1,MAX(0,D56-L56),0) -> 159.47584 | P56: =IF(I56>0,MAX(0,1-M56/I56),0) -> 0 | Q56: =IF(AND(O56>0,I56>0),O56/(1-'1 - Input'!$B$22*P56),0) -> 159.47584 | R56: =MIN(Q56,I56) -> 159.47584 | S56: ='1 - Input'!$B$22*P56*R56 -> 0 | T56: =R56-S56 -> 159.47584 | U56: =O56-T56 -> 0 | V56: =IF(I56>0,R56*MAX(0,M56/I56-1),0) -> 7.2390173 | W56: =I56-R56+N56 -> 463816.24 | X56: =IF(R56>0,M56*(1-R56/I56),M56)+N56 -> 484870.05 | Y56: =IF(MOD(A56,12)=0,W56*'1 - Input'!$B$23,0) -> 0 | Z56: =W56-Y56 -> 463816.24 | AA56: =IF(MOD(A56,12)=0,X56*(1-'1 - Input'!$B$23),X56) -> 484870.05 | AB56: =IF('1 - Input'!$B$17=1,MIN(L56,D56)+T56,L56) -> 2754 | AC56: =AC55+AB56 -> 35154 | AD56: =AD55+K56 -> 12128.194 | AE56: =AE55+S56 -> 0 | AF56: =AF55+V56 -> 22.638017 | AG56: =AG55+Y56 -> 932.99161 | AH56: =AH55+U56 -> 0 | AI56: =IF(W56<=0.000001,1,0) -> 0 | AK56: 13 | AL56: =ROUNDUP(AK56/12,0) -> 2 | AM56: =(1+INDEX('1 - Input'!$B$34:$E$63,AL56,'1 - Input'!$B$16))^(1/12)-1 -> 0.0041219243 | AN56: ='1 - Input'!$B$7*(1+'1 - Input'!$B$12)^(AL56-1) -> 2754 | AO56: =BJ55 -> 465562.82 | AP56: =BK55 -> 485036.76 | AQ56: =AO56*(1+AM56) -> 467481.83 | AR56: =IF(AQ56>0,'1 - Input'!$B$8/12*AQ56,0) -> 3506.1137 | AS56: =AQ56-AR56 -> 463975.72 | AT56: =MIN($AL$41*AR56,AP56) -> 0 | AU56: ='1 - Input'!$B$22*(AR56-AT56) -> 911.58957 | AV56: =AR56-AU56 -> 2594.5242 | AW56: =AP56-AT56 -> 485036.76 | AX56: =IF('1 - Input'!$B$17=1,MAX(0,AV56-AN56),0) -> 0 | AY56: =IF('1 - Input'!$B$17=1,MAX(0,AN56-AV56),0) -> 159.47584 | AZ56: =IF(AS56>0,MAX(0,1-AW56/AS56),0) -> 0 | BA56: =IF(AND(AY56>0,AS56>0),AY56/(1-'1 - Input'!$B$22*AZ56),0) -> 159.47584 | BB56: =MIN(BA56,AS56) -> 159.47584 | BC56: ='1 - Input'!$B$22*AZ56*BB56 -> 0 | BD56: =BB56-BC56 -> 159.47584 | BE56: =AY56-BD56 -> 0 | BF56: =IF(AS56>0,BB56*MAX(0,AW56/AS56-1),0) -> 7.2390173 | BG56: =AS56-BB56+AX56 -> 463816.24 | BH56: =IF(BB56>0,AW56*(1-BB56/AS56),AW56)+AX56 -> 484870.05 | BI56: =IF(MOD(AK56,12)=0,BG56*'1 - Input'!$B$23,0) -> 0 | BJ56: =BG56-BI56 -> 463816.24 | BK56: =IF(MOD(AK56,12)=0,BH56*(1-'1 - Input'!$B$23),BH56) -> 484870.05 | BL56: =IF('1 - Input'!$B$17=1,MIN(AV56,AN56)+BD56,AV56) -> 2754 | BM56: =BM55+BL56 -> 35154 | BN56: =BN55+AU56 -> 12128.194 | BO56: =BO55+BC56 -> 0 | BP56: =BP55+BF56 -> 22.638017 | BQ56: =BQ55+BI56 -> 932.99161 | BR56: =BR55+BE56 -> 0 | BS56: =IF(BG56<=0.000001,1,0) -> 0 | BU56: 13 | BV56: =ROUNDUP(BU56/12,0) -> 2 | BW56: =(1+INDEX('1 - Input'!$B$34:$E$63,BV56,'1 - Input'!$B$16))^(1/12)-1 -> 0.0041219243 | BX56: ='1 - Input'!$B$7*(1+'1 - Input'!$B$12)^(BV56-1) -> 2754 | BY56: =CT55 -> 477016.24 | BZ56: =CU55 -> 453191.8 | CA56: =BY56*(1+BW56) -> 478982.47 | CB56: =IF(CA56>0,'1 - Input'!$B$8/12*CA56,0) -> 3592.3685 | CC56: =CA56-CB56 -> 475390.1 | CD56: =MIN($BV$41*CB56,BZ56) -> 3592.3685 | CE56: ='1 - Input'!$B$22*(CB56-CD56) -> 0 | CF56: =CB56-CE56 -> 3592.3685 | CG56: =BZ56-CD56 -> 449599.43 | CH56: =IF('1 - Input'!$B$17=1,MAX(0,CF56-BX56),0) -> 838.3685 | CI56: =IF('1 - Input'!$B$17=1,MAX(0,BX56-CF56),0) -> 0 | CJ56: =IF(CC56>0,MAX(0,1-CG56/CC56),0) -> 0.054251587 | CK56: =IF(AND(CI56>0,CC56>0),CI56/(1-'1 - Input'!$B$22*CJ56),0) -> 0 | CL56: =MIN(CK56,CC56) -> 0 | CM56: ='1 - Input'!$B$22*CJ56*CL56 -> 0 | CN56: =CL56-CM56 -> 0 | CO56: =CI56-CN56 -> 0 | CP56: =IF(CC56>0,CL56*MAX(0,CG56/CC56-1),0) -> 0 | CQ56: =CC56-CL56+CH56 -> 476228.47 | CR56: =IF(CL56>0,CG56*(1-CL56/CC56),CG56)+CH56 -> 450437.8 | CS56: =IF(MOD(BU56,12)=0,CQ56*'1 - Input'!$B$23,0) -> 0 | CT56: =CQ56-CS56 -> 476228.47 | CU56: =IF(MOD(BU56,12)=0,CR56*(1-'1 - Input'!$B$23),CR56) -> 450437.8 | CV56: =IF('1 - Input'!$B$17=1,MIN(CF56,BX56)+CN56,CF56) -> 2754 | CW56: =CW55+CV56 -> 35154 | CX56: =CX55+CE56 -> 0 | CY56: =CY55+CM56 -> 0 | CZ56: =CZ55+CP56 -> 0 | DA56: =DA55+CS56 -> 955.94437 | DB56: =DB55+CO56 -> 0 | DC56: =IF(CQ56<=0.000001,1,0) -> 0
... A403: 360 | B403: =ROUNDUP(A403/12,0) -> 30 | C403: =(1+INDEX('1 - Input'!$B$34:$E$63,B403,'1 - Input'!$B$16))^(1/12)-1 -> 0.0041219243 | D403: ='1 - Input'!$B$7*(1+'1 - Input'!$B$12)^(B403-1) -> 4794.7807 | E403: =Z402 -> 0 | F403: =AA402 -> 0 | G403: =E403*(1+C403) -> 0 | H403: =IF(G403>0,'1 - Input'!$B$8/12*G403,0) -> 0 | I403: =G403-H403 -> 0 | J403: =MIN($B$41*H403,F403) -> 0 | K403: ='1 - Input'!$B$22*(H403-J403) -> 0 | L403: =H403-K403 -> 0 | M403: =F403-J403 -> 0 | N403: =IF('1 - Input'!$B$17=1,MAX(0,L403-D403),0) -> 0 | O403: =IF('1 - Input'!$B$17=1,MAX(0,D403-L403),0) -> 4794.7807 | P403: =IF(I403>0,MAX(0,1-M403/I403),0) -> 0 | Q403: =IF(AND(O403>0,I403>0),O403/(1-'1 - Input'!$B$22*P403),0) -> 0 | R403: =MIN(Q403,I403) -> 0 | S403: ='1 - Input'!$B$22*P403*R403 -> 0 | T403: =R403-S403 -> 0 | U403: =O403-T403 -> 4794.7807 | V403: =IF(I403>0,R403*MAX(0,M403/I403-1),0) -> 0 | W403: =I403-R403+N403 -> 0 | X403: =IF(R403>0,M403*(1-R403/I403),M403)+N403 -> 0 | Y403: =IF(MOD(A403,12)=0,W403*'1 - Input'!$B$23,0) -> 0 | Z403: =W403-Y403 -> 0 | AA403: =IF(MOD(A403,12)=0,X403*(1-'1 - Input'!$B$23),X403) -> 0 | AB403: =IF('1 - Input'!$B$17=1,MIN(L403,D403)+T403,L403) -> 0 | AC403: =AC402+AB403 -> 590482.94 | AD403: =AD402+K403 -> 101441.9 | AE403: =AE402+S403 -> 0 | AF403: =AF402+V403 -> 174289.24 | AG403: =AG402+Y403 -> 8123.5663 | AH403: =AH402+U403 -> 723922.83 | AI403: =IF(W403<=0.000001,1,0) -> 1 | AK403: 360 | AL403: =ROUNDUP(AK403/12,0) -> 30 | AM403: =(1+INDEX('1 - Input'!$B$34:$E$63,AL403,'1 - Input'!$B$16))^(1/12)-1 -> 0.0041219243 | AN403: ='1 - Input'!$B$7*(1+'1 - Input'!$B$12)^(AL403-1) -> 4794.7807 | AO403: =BJ402 -> 0 | AP403: =BK402 -> 0 | AQ403: =AO403*(1+AM403) -> 0 | AR403: =IF(AQ403>0,'1 - Input'!$B$8/12*AQ403,0) -> 0 | AS403: =AQ403-AR403 -> 0 | AT403: =MIN($AL$41*AR403,AP403) -> 0 | AU403: ='1 - Input'!$B$22*(AR403-AT403) -> 0 | AV403: =AR403-AU403 -> 0 | AW403: =AP403-AT403 -> 0 | AX403: =IF('1 - Input'!$B$17=1,MAX(0,AV403-AN403),0) -> 0 | AY403: =IF('1 - Input'!$B$17=1,MAX(0,AN403-AV403),0) -> 4794.7807 | AZ403: =IF(AS403>0,MAX(0,1-AW403/AS403),0) -> 0 | BA403: =IF(AND(AY403>0,AS403>0),AY403/(1-'1 - Input'!$B$22*AZ403),0) -> 0 | BB403: =MIN(BA403,AS403) -> 0 | BC403: ='1 - Input'!$B$22*AZ403*BB403 -> 0 | BD403: =BB403-BC403 -> 0 | BE403: =AY403-BD403 -> 4794.7807 | BF403: =IF(AS403>0,BB403*MAX(0,AW403/AS403-1),0) -> 0 | BG403: =AS403-BB403+AX403 -> 0 | BH403: =IF(BB403>0,AW403*(1-BB403/AS403),AW403)+AX403 -> 0 | BI403: =IF(MOD(AK403,12)=0,BG403*'1 - Input'!$B$23,0) -> 0 | BJ403: =BG403-BI403 -> 0 | BK403: =IF(MOD(AK403,12)=0,BH403*(1-'1 - Input'!$B$23),BH403) -> 0 | BL403: =IF('1 - Input'!$B$17=1,MIN(AV403,AN403)+BD403,AV403) -> 0 | BM403: =BM402+BL403 -> 590482.94 | BN403: =BN402+AU403 -> 101441.9 | BO403: =BO402+BC403 -> 0 | BP403: =BP402+BF403 -> 174289.24 | BQ403: =BQ402+BI403 -> 8123.5663 | BR403: =BR402+BE403 -> 723922.83 | BS403: =IF(BG403<=0.000001,1,0) -> 1 | BU403: 360 | BV403: =ROUNDUP(BU403/12,0) -> 30 | BW403: =(1+INDEX('1 - Input'!$B$34:$E$63,BV403,'1 - Input'!$B$16))^(1/12)-1 -> 0.0041219243 | BX403: ='1 - Input'!$B$7*(1+'1 - Input'!$B$12)^(BV403-1) -> 4794.7807 | BY403: =CT402 -> 0 | BZ403: =CU402 -> 0 | CA403: =BY403*(1+BW403) -> 0 | CB403: =IF(CA403>0,'1 - Input'!$B$8/12*CA403,0) -> 0 | CC403: =CA403-CB403 -> 0 | CD403: =MIN($BV$41*CB403,BZ403) -> 0 | CE403: ='1 - Input'!$B$22*(CB403-CD403) -> 0 | CF403: =CB403-CE403 -> 0 | CG403: =BZ403-CD403 -> 0 | CH403: =IF('1 - Input'!$B$17=1,MAX(0,CF403-BX403),0) -> 0 | CI403: =IF('1 - Input'!$B$17=1,MAX(0,BX403-CF403),0) -> 4794.7807 | CJ403: =IF(CC403>0,MAX(0,1-CG403/CC403),0) -> 0 | CK403: =IF(AND(CI403>0,CC403>0),CI403/(1-'1 - Input'!$B$22*CJ403),0) -> 0 | CL403: =MIN(CK403,CC403) -> 0 | CM403: ='1 - Input'!$B$22*CJ403*CL403 -> 0 | CN403: =CL403-CM403 -> 0 | CO403: =CI403-CN403 -> 4794.7807 | CP403: =IF(CC403>0,CL403*MAX(0,CG403/CC403-1),0) -> 0 | CQ403: =CC403-CL403+CH403 -> 0 | CR403: =IF(CL403>0,CG403*(1-CL403/CC403),CG403)+CH403 -> 0 | CS403: =IF(MOD(BU403,12)=0,CQ403*'1 - Input'!$B$23,0) -> 0 | CT403: =CQ403-CS403 -> 0 | CU403: =IF(MOD(BU403,12)=0,CR403*(1-'1 - Input'!$B$23),CR403) -> 0 | CV403: =IF('1 - Input'!$B$17=1,MIN(CF403,BX403)+CN403,CF403) -> 0 | CW403: =CW402+CV403 -> 686605.5 | CX403: =CX402+CE403 -> 6018.3403 | CY403: =CY402+CM403 -> 66518.776 | CZ403: =CZ402+CP403 -> 0 | DA403: =DA402+CS403 -> 10954.114 | DB403: =DB402+CO403 -> 627800.27 | DC403: =IF(CQ403<=0.000001,1,0) -> 1

Sheet 3 - Accumulo
A1: Dividendo mensile: rendita o capitale che torna indietro? Il caso di Renata (caso inventato e illustrativo)
A2: Caso inventato e illustrativo, non è consulenza e non è una previsione. Fotografia di ottobre 2026, regole fiscali di oggi. Prima di decidere fai i conti sul tuo caso e parlane con professionisti abilitati.
A3: Stessa strategia in versione ad accumulo: nessuna distribuzione, solo vendite di quote per pagare la spesa. La tabella annua è in alto, il motore del calcolo è in fondo (non modificare).
A4: Accumulo con vendite
A5: Anno | B5: Valore a fine anno (dopo bollo) | C5: Costo fiscale a fine anno | D5: Valore in euro di oggi | E5: Distribuzioni lorde | F5: Distribuzioni nette | G5: Imposte sulle distribuzioni | H5: Imposte sulle vendite | I5: Bollo | J5: Minusvalenze cumulate | K5: Spesa netta media al mese, euro correnti | L5: Spesa netta media al mese, euro di oggi
A6: 1 | B6: =INDEX('3 - Accumulo'!$Z$44:$Z$403,12*$A6) -> 476789.9 | C6: =INDEX('3 - Accumulo'!$AA$44:$AA$403,12*$A6) -> 453826.29 | D6: =B6/(1+'1 - Input'!$B$12)^$A6 -> 467441.08 | E6: =SUMIFS('3 - Accumulo'!$H$44:$H$403,'3 - Accumulo'!$B$44:$B$403,$A6) -> 0 | F6: =SUMIFS('3 - Accumulo'!$L$44:$L$403,'3 - Accumulo'!$B$44:$B$403,$A6) -> 0 | G6: =SUMIFS('3 - Accumulo'!$K$44:$K$403,'3 - Accumulo'!$B$44:$B$403,$A6) -> 0 | H6: =SUMIFS('3 - Accumulo'!$S$44:$S$403,'3 - Accumulo'!$B$44:$B$403,$A6) -> 223.37587 | I6: =SUMIFS('3 - Accumulo'!$Y$44:$Y$403,'3 - Accumulo'!$B$44:$B$403,$A6) -> 955.49078 | J6: =INDEX('3 - Accumulo'!$AF$44:$AF$403,12*$A6) -> 0 | K6: =SUMIFS('3 - Accumulo'!$AB$44:$AB$403,'3 - Accumulo'!$B$44:$B$403,$A6)/12 -> 2700 | L6: =K6/(1+'1 - Input'!$B$12)^($A6-0.5) -> 2673.3984
A7: 2 | B7: =INDEX('3 - Accumulo'!$Z$44:$Z$403,12*$A7) -> 465520.5 | C7: =INDEX('3 - Accumulo'!$AA$44:$AA$403,12*$A7) -> 421758.67 | D7: =B7/(1+'1 - Input'!$B$12)^$A7 -> 447443.77 | E7: =SUMIFS('3 - Accumulo'!$H$44:$H$403,'3 - Accumulo'!$B$44:$B$403,$A7) -> 0 | F7: =SUMIFS('3 - Accumulo'!$L$44:$L$403,'3 - Accumulo'!$B$44:$B$403,$A7) -> 0 | G7: =SUMIFS('3 - Accumulo'!$K$44:$K$403,'3 - Accumulo'!$B$44:$B$403,$A7) -> 0 | H7: =SUMIFS('3 - Accumulo'!$S$44:$S$403,'3 - Accumulo'!$B$44:$B$403,$A7) -> 641.42139 | I7: =SUMIFS('3 - Accumulo'!$Y$44:$Y$403,'3 - Accumulo'!$B$44:$B$403,$A7) -> 932.90681 | J7: =INDEX('3 - Accumulo'!$AF$44:$AF$403,12*$A7) -> 0 | K7: =SUMIFS('3 - Accumulo'!$AB$44:$AB$403,'3 - Accumulo'!$B$44:$B$403,$A7)/12 -> 2754 | L7: =K7/(1+'1 - Input'!$B$12)^($A7-0.5) -> 2673.3984
A8: 3 | B8: =INDEX('3 - Accumulo'!$Z$44:$Z$403,12*$A8) -> 452596.63 | C8: =INDEX('3 - Accumulo'!$AA$44:$AA$403,12*$A8) -> 390300.52 | D8: =B8/(1+'1 - Input'!$B$12)^$A8 -> 426491.91 | E8: =SUMIFS('3 - Accumulo'!$H$44:$H$403,'3 - Accumulo'!$B$44:$B$403,$A8) -> 0 | F8: =SUMIFS('3 - Accumulo'!$L$44:$L$403,'3 - Accumulo'!$B$44:$B$403,$A8) -> 0 | G8: =SUMIFS('3 - Accumulo'!$K$44:$K$403,'3 - Accumulo'!$B$44:$B$403,$A8) -> 0 | H8: =SUMIFS('3 - Accumulo'!$S$44:$S$403,'3 - Accumulo'!$B$44:$B$403,$A8) -> 1065.6404 | I8: =SUMIFS('3 - Accumulo'!$Y$44:$Y$403,'3 - Accumulo'!$B$44:$B$403,$A8) -> 907.00728 | J8: =INDEX('3 - Accumulo'!$AF$44:$AF$403,12*$A8) -> 0 | K8: =SUMIFS('3 - Accumulo'!$AB$44:$AB$403,'3 - Accumulo'!$B$44:$B$403,$A8)/12 -> 2809.08 | L8: =K8/(1+'1 - Input'!$B$12)^($A8-0.5) -> 2673.3984
A9: 4 | B9: =INDEX('3 - Accumulo'!$Z$44:$Z$403,12*$A9) -> 437918.5 | C9: =INDEX('3 - Accumulo'!$AA$44:$AA$403,12*$A9) -> 359454.32 | D9: =B9/(1+'1 - Input'!$B$12)^$A9 -> 404569 | E9: =SUMIFS('3 - Accumulo'!$H$44:$H$403,'3 - Accumulo'!$B$44:$B$403,$A9) -> 0 | F9: =SUMIFS('3 - Accumulo'!$L$44:$L$403,'3 - Accumulo'!$B$44:$B$403,$A9) -> 0 | G9: =SUMIFS('3 - Accumulo'!$K$44:$K$403,'3 - Accumulo'!$B$44:$B$403,$A9) -> 0 | H9: =SUMIFS('3 - Accumulo'!$S$44:$S$403,'3 - Accumulo'!$B$44:$B$403,$A9) -> 1495.8032 | I9: =SUMIFS('3 - Accumulo'!$Y$44:$Y$403,'3 - Accumulo'!$B$44:$B$403,$A9) -> 877.59217 | J9: =INDEX('3 - Accumulo'!$AF$44:$AF$403,12*$A9) -> 0 | K9: =SUMIFS('3 - Accumulo'!$AB$44:$AB$403,'3 - Accumulo'!$B$44:$B$403,$A9)/12 -> 2865.2616 | L9: =K9/(1+'1 - Input'!$B$12)^($A9-0.5) -> 2673.3984
A10: 5 | B10: =INDEX('3 - Accumulo'!$Z$44:$Z$403,12*$A10) -> 421381.4 | C10: =INDEX('3 - Accumulo'!$AA$44:$AA$403,12*$A10) -> 329221.64 | D10: =B10/(1+'1 - Input'!$B$12)^$A10 -> 381658.11 | E10: =SUMIFS('3 - Accumulo'!$H$44:$H$403,'3 - Accumulo'!$B$44:$B$403,$A10) -> 0 | F10: =SUMIFS('3 - Accumulo'!$L$44:$L$403,'3 - Accumulo'!$B$44:$B$403,$A10) -> 0 | G10: =SUMIFS('3 - Accumulo'!$K$44:$K$403,'3 - Accumulo'!$B$44:$B$403,$A10) -> 0 | H10: =SUMIFS('3 - Accumulo'!$S$44:$S$403,'3 - Accumulo'!$B$44:$B$403,$A10) -> 1931.6916 | I10: =SUMIFS('3 - Accumulo'!$Y$44:$Y$403,'3 - Accumulo'!$B$44:$B$403,$A10) -> 844.4517 | J10: =INDEX('3 - Accumulo'!$AF$44:$AF$403,12*$A10) -> 0 | K10: =SUMIFS('3 - Accumulo'!$AB$44:$AB$403,'3 - Accumulo'!$B$44:$B$403,$A10)/12 -> 2922.5668 | L10: =K10/(1+'1 - Input'!$B$12)^($A10-0.5) -> 2673.3984
A11: 6 | B11: =INDEX('3 - Accumulo'!$Z$44:$Z$403,12*$A11) -> 402875.5 | C11: =INDEX('3 - Accumulo'!$AA$44:$AA$403,12*$A11) -> 299603.22 | D11: =B11/(1+'1 - Input'!$B$12)^$A11 -> 357741.92 | E11: =SUMIFS('3 - Accumulo'!$H$44:$H$403,'3 - Accumulo'!$B$44:$B$403,$A11) -> 0 | F11: =SUMIFS('3 - Accumulo'!$L$44:$L$403,'3 - Accumulo'!$B$44:$B$403,$A11) -> 0 | G11: =SUMIFS('3 - Accumulo'!$K$44:$K$403,'3 - Accumulo'!$B$44:$B$403,$A11) -> 0 | H11: =SUMIFS('3 - Accumulo'!$S$44:$S$403,'3 - Accumulo'!$B$44:$B$403,$A11) -> 2373.0997 | I11: =SUMIFS('3 - Accumulo'!$Y$44:$Y$403,'3 - Accumulo'!$B$44:$B$403,$A11) -> 807.36574 | J11: =INDEX('3 - Accumulo'!$AF$44:$AF$403,12*$A11) -> 0 | K11: =SUMIFS('3 - Accumulo'!$AB$44:$AB$403,'3 - Accumulo'!$B$44:$B$403,$A11)/12 -> 2981.0182 | L11: =K11/(1+'1 - Input'!$B$12)^($A11-0.5) -> 2673.3984
A12: 7 | B12: =INDEX('3 - Accumulo'!$Z$44:$Z$403,12*$A12) -> 382285.57 | C12: =INDEX('3 - Accumulo'!$AA$44:$AA$403,12*$A12) -> 270598.96 | D12: =B12/(1+'1 - Input'!$B$12)^$A12 -> 332802.59 | E12: =SUMIFS('3 - Accumulo'!$H$44:$H$403,'3 - Accumulo'!$B$44:$B$403,$A12) -> 0 | F12: =SUMIFS('3 - Accumulo'!$L$44:$L$403,'3 - Accumulo'!$B$44:$B$403,$A12) -> 0 | G12: =SUMIFS('3 - Accumulo'!$K$44:$K$403,'3 - Accumulo'!$B$44:$B$403,$A12) -> 0 | H12: =SUMIFS('3 - Accumulo'!$S$44:$S$403,'3 - Accumulo'!$B$44:$B$403,$A12) -> 2819.8343 | I12: =SUMIFS('3 - Accumulo'!$Y$44:$Y$403,'3 - Accumulo'!$B$44:$B$403,$A12) -> 766.10334 | J12: =INDEX('3 - Accumulo'!$AF$44:$AF$403,12*$A12) -> 0 | K12: =SUMIFS('3 - Accumulo'!$AB$44:$AB$403,'3 - Accumulo'!$B$44:$B$403,$A12)/12 -> 3040.6385 | L12: =K12/(1+'1 - Input'!$B$12)^($A12-0.5) -> 2673.3984
A13: 8 | B13: =INDEX('3 - Accumulo'!$Z$44:$Z$403,12*$A13) -> 359490.65 | C13: =INDEX('3 - Accumulo'!$AA$44:$AA$403,12*$A13) -> 242207.97 | D13: =B13/(1+'1 - Input'!$B$12)^$A13 -> 306821.81 | E13: =SUMIFS('3 - Accumulo'!$H$44:$H$403,'3 - Accumulo'!$B$44:$B$403,$A13) -> 0 | F13: =SUMIFS('3 - Accumulo'!$L$44:$L$403,'3 - Accumulo'!$B$44:$B$403,$A13) -> 0 | G13: =SUMIFS('3 - Accumulo'!$K$44:$K$403,'3 - Accumulo'!$B$44:$B$403,$A13) -> 0 | H13: =SUMIFS('3 - Accumulo'!$S$44:$S$403,'3 - Accumulo'!$B$44:$B$403,$A13) -> 3271.7164 | I13: =SUMIFS('3 - Accumulo'!$Y$44:$Y$403,'3 - Accumulo'!$B$44:$B$403,$A13) -> 720.42214 | J13: =INDEX('3 - Accumulo'!$AF$44:$AF$403,12*$A13) -> 0 | K13: =SUMIFS('3 - Accumulo'!$AB$44:$AB$403,'3 - Accumulo'!$B$44:$B$403,$A13)/12 -> 3101.4513 | L13: =K13/(1+'1 - Input'!$B$12)^($A13-0.5) -> 2673.3984
A14: 9 | B14: =INDEX('3 - Accumulo'!$Z$44:$Z$403,12*$A14) -> 334363.82 | C14: =INDEX('3 - Accumulo'!$AA$44:$AA$403,12*$A14) -> 214428.6 | D14: =B14/(1+'1 - Input'!$B$12)^$A14 -> 279780.69 | E14: =SUMIFS('3 - Accumulo'!$H$44:$H$403,'3 - Accumulo'!$B$44:$B$403,$A14) -> 0 | F14: =SUMIFS('3 - Accumulo'!$L$44:$L$403,'3 - Accumulo'!$B$44:$B$403,$A14) -> 0 | G14: =SUMIFS('3 - Accumulo'!$K$44:$K$403,'3 - Accumulo'!$B$44:$B$403,$A14) -> 0 | H14: =SUMIFS('3 - Accumulo'!$S$44:$S$403,'3 - Accumulo'!$B$44:$B$403,$A14) -> 3728.5806 | I14: =SUMIFS('3 - Accumulo'!$Y$44:$Y$403,'3 - Accumulo'!$B$44:$B$403,$A14) -> 670.06778 | J14: =INDEX('3 - Accumulo'!$AF$44:$AF$403,12*$A14) -> 0 | K14: =SUMIFS('3 - Accumulo'!$AB$44:$AB$403,'3 - Accumulo'!$B$44:$B$403,$A14)/12 -> 3163.4803 | L14: =K14/(1+'1 - Input'!$B$12)^($A14-0.5) -> 2673.3984
A15: 10 | B15: =INDEX('3 - Accumulo'!$Z$44:$Z$403,12*$A15) -> 306771.86 | C15: =INDEX('3 - Accumulo'!$AA$44:$AA$403,12*$A15) -> 187258.51 | D15: =B15/(1+'1 - Input'!$B$12)^$A15 -> 251659.77 | E15: =SUMIFS('3 - Accumulo'!$H$44:$H$403,'3 - Accumulo'!$B$44:$B$403,$A15) -> 0 | F15: =SUMIFS('3 - Accumulo'!$L$44:$L$403,'3 - Accumulo'!$B$44:$B$403,$A15) -> 0 | G15: =SUMIFS('3 - Accumulo'!$K$44:$K$403,'3 - Accumulo'!$B$44:$B$403,$A15) -> 0 | H15: =SUMIFS('3 - Accumulo'!$S$44:$S$403,'3 - Accumulo'!$B$44:$B$403,$A15) -> 4190.2766 | I15: =SUMIFS('3 - Accumulo'!$Y$44:$Y$403,'3 - Accumulo'!$B$44:$B$403,$A15) -> 614.77326 | J15: =INDEX('3 - Accumulo'!$AF$44:$AF$403,12*$A15) -> 0 | K15: =SUMIFS('3 - Accumulo'!$AB$44:$AB$403,'3 - Accumulo'!$B$44:$B$403,$A15)/12 -> 3226.7499 | L15: =K15/(1+'1 - Input'!$B$12)^($A15-0.5) -> 2673.3984
A16: 11 | B16: =INDEX('3 - Accumulo'!$Z$44:$Z$403,12*$A16) -> 276574.91 | C16: =INDEX('3 - Accumulo'!$AA$44:$AA$403,12*$A16) -> 160694.65 | D16: =B16/(1+'1 - Input'!$B$12)^$A16 -> 222438.97 | E16: =SUMIFS('3 - Accumulo'!$H$44:$H$403,'3 - Accumulo'!$B$44:$B$403,$A16) -> 0 | F16: =SUMIFS('3 - Accumulo'!$L$44:$L$403,'3 - Accumulo'!$B$44:$B$403,$A16) -> 0 | G16: =SUMIFS('3 - Accumulo'!$K$44:$K$403,'3 - Accumulo'!$B$44:$B$403,$A16) -> 0 | H16: =SUMIFS('3 - Accumulo'!$S$44:$S$403,'3 - Accumulo'!$B$44:$B$403,$A16) -> 4656.6687 | I16: =SUMIFS('3 - Accumulo'!$Y$44:$Y$403,'3 - Accumulo'!$B$44:$B$403,$A16) -> 554.25833 | J16: =INDEX('3 - Accumulo'!$AF$44:$AF$403,12*$A16) -> 0 | K16: =SUMIFS('3 - Accumulo'!$AB$44:$AB$403,'3 - Accumulo'!$B$44:$B$403,$A16)/12 -> 3291.2849 | L16: =K16/(1+'1 - Input'!$B$12)^($A16-0.5) -> 2673.3984
A17: 12 | B17: =INDEX('3 - Accumulo'!$Z$44:$Z$403,12*$A17) -> 243626.14 | C17: =INDEX('3 - Accumulo'!$AA$44:$AA$403,12*$A17) -> 134733.36 | D17: =B17/(1+'1 - Input'!$B$12)^$A17 -> 192097.55 | E17: =SUMIFS('3 - Accumulo'!$H$44:$H$403,'3 - Accumulo'!$B$44:$B$403,$A17) -> 0 | F17: =SUMIFS('3 - Accumulo'!$L$44:$L$403,'3 - Accumulo'!$B$44:$B$403,$A17) -> 0 | G17: =SUMIFS('3 - Accumulo'!$K$44:$K$403,'3 - Accumulo'!$B$44:$B$403,$A17) -> 0 | H17: =SUMIFS('3 - Accumulo'!$S$44:$S$403,'3 - Accumulo'!$B$44:$B$403,$A17) -> 5127.6365 | I17: =SUMIFS('3 - Accumulo'!$Y$44:$Y$403,'3 - Accumulo'!$B$44:$B$403,$A17) -> 488.22874 | J17: =INDEX('3 - Accumulo'!$AF$44:$AF$403,12*$A17) -> 0 | K17: =SUMIFS('3 - Accumulo'!$AB$44:$AB$403,'3 - Accumulo'!$B$44:$B$403,$A17)/12 -> 3357.1106 | L17: =K17/(1+'1 - Input'!$B$12)^($A17-0.5) -> 2673.3984
... A35: 30 | B35: =INDEX('3 - Accumulo'!$Z$44:$Z$403,12*$A35) -> 0 | C35: =INDEX('3 - Accumulo'!$AA$44:$AA$403,12*$A35) -> 0 | D35: =B35/(1+'1 - Input'!$B$12)^$A35 -> 0 | E35: =SUMIFS('3 - Accumulo'!$H$44:$H$403,'3 - Accumulo'!$B$44:$B$403,$A35) -> 0 | F35: =SUMIFS('3 - Accumulo'!$L$44:$L$403,'3 - Accumulo'!$B$44:$B$403,$A35) -> 0 | G35: =SUMIFS('3 - Accumulo'!$K$44:$K$403,'3 - Accumulo'!$B$44:$B$403,$A35) -> 0 | H35: =SUMIFS('3 - Accumulo'!$S$44:$S$403,'3 - Accumulo'!$B$44:$B$403,$A35) -> 0 | I35: =SUMIFS('3 - Accumulo'!$Y$44:$Y$403,'3 - Accumulo'!$B$44:$B$403,$A35) -> 0 | J35: =INDEX('3 - Accumulo'!$AF$44:$AF$403,12*$A35) -> 0 | K35: =SUMIFS('3 - Accumulo'!$AB$44:$AB$403,'3 - Accumulo'!$B$44:$B$403,$A35)/12 -> 0 | L35: =K35/(1+'1 - Input'!$B$12)^($A35-0.5) -> 0
A40: Motore del calcolo, non modificare. Accumulo con vendite
A41: Quota Q del blocco | B41: =0 -> 0
A43: Mese k | B43: Anno | C43: Rendimento mensile | D43: Spesa del mese | E43: Valore prima | F43: Costo prima | G43: Valore con rendimento | H43: Distribuzione lorda | I43: Valore dopo lo stacco | J43: Rimborso di capitale | K43: Imposta sulla distribuzione | L43: Distribuzione netta | M43: Costo dopo rimborso | N43: Avanzo reinvestito | O43: Fabbisogno | P43: Quota di guadagno nel valore | Q43: Vendita necessaria lorda | R43: Vendita effettiva | S43: Imposta sulla vendita | T43: Vendita netta | U43: Spesa non coperta | V43: Minusvalenza realizzata | W43: Valore a fine mese | X43: Costo a fine mese | Y43: Bollo | Z43: Valore dopo bollo | AA43: Costo dopo bollo | AB43: Speso nel mese | AC43: Speso cumulato | AD43: Imposte distribuzione cumulate | AE43: Imposte vendita cumulate | AF43: Minusvalenze cumulate | AG43: Bollo cumulato | AH43: Non coperto cumulato | AI43: Esaurito (1 = sì)
A44: 1 | B44: =ROUNDUP(A44/12,0) -> 1 | C44: =(1+INDEX('1 - Input'!$B$34:$E$63,B44,'1 - Input'!$B$16))^(1/12)-1 -> 0.0041219243 | D44: ='1 - Input'!$B$7*(1+'1 - Input'!$B$12)^(B44-1) -> 2700 | E44: ='1 - Input'!$B$6 -> 486500 | F44: ='1 - Input'!$B$6*'1 - Input'!$B$15 -> 486500 | G44: =E44*(1+C44) -> 488505.32 | H44: =0 -> 0 | I44: =G44-H44 -> 488505.32 | J44: =MIN($B$41*H44,F44) -> 0 | K44: ='1 - Input'!$B$22*(H44-J44) -> 0 | L44: =H44-K44 -> 0 | M44: =F44-J44 -> 486500 | N44: =0 -> 0 | O44: =D44 -> 2700 | P44: =IF(I44>0,MAX(0,1-M44/I44),0) -> 0.0041050038 | Q44: =IF(AND(O44>0,I44>0),O44/(1-'1 - Input'!$B$22*P44),0) -> 2702.8848 | R44: =MIN(Q44,I44) -> 2702.8848 | S44: ='1 - Input'!$B$22*P44*R44 -> 2.8847916 | T44: =R44-S44 -> 2700 | U44: =O44-T44 -> 0 | V44: =IF(I44>0,R44*MAX(0,M44/I44-1),0) -> 0 | W44: =I44-R44+N44 -> 485802.43 | X44: =IF(R44>0,M44*(1-R44/I44),M44)+N44 -> 483808.21 | Y44: =IF(MOD(A44,12)=0,W44*'1 - Input'!$B$23,0) -> 0 | Z44: =W44-Y44 -> 485802.43 | AA44: =IF(MOD(A44,12)=0,X44*(1-'1 - Input'!$B$23),X44) -> 483808.21 | AB44: =T44 -> 2700 | AC44: =AB44 -> 2700 | AD44: =K44 -> 0 | AE44: =S44 -> 2.8847916 | AF44: =V44 -> 0 | AG44: =Y44 -> 0 | AH44: =U44 -> 0 | AI44: =IF(W44<=0.000001,1,0) -> 0
A45: 2 | B45: =ROUNDUP(A45/12,0) -> 1 | C45: =(1+INDEX('1 - Input'!$B$34:$E$63,B45,'1 - Input'!$B$16))^(1/12)-1 -> 0.0041219243 | D45: ='1 - Input'!$B$7*(1+'1 - Input'!$B$12)^(B45-1) -> 2700 | E45: =Z44 -> 485802.43 | F45: =AA44 -> 483808.21 | G45: =E45*(1+C45) -> 487804.87 | H45: =0 -> 0 | I45: =G45-H45 -> 487804.87 | J45: =MIN($B$41*H45,F45) -> 0 | K45: ='1 - Input'!$B$22*(H45-J45) -> 0 | L45: =H45-K45 -> 0 | M45: =F45-J45 -> 483808.21 | N45: =0 -> 0 | O45: =D45 -> 2700 | P45: =IF(I45>0,MAX(0,1-M45/I45),0) -> 0.0081931566 | Q45: =IF(AND(O45>0,I45>0),O45/(1-'1 - Input'!$B$22*P45),0) -> 2705.7639 | R45: =MIN(Q45,I45) -> 2705.7639 | S45: ='1 - Input'!$B$22*P45*R45 -> 5.7638742 | T45: =R45-S45 -> 2700 | U45: =O45-T45 -> 0 | V45: =IF(I45>0,R45*MAX(0,M45/I45-1),0) -> 0 | W45: =I45-R45+N45 -> 485099.11 | X45: =IF(R45>0,M45*(1-R45/I45),M45)+N45 -> 481124.62 | Y45: =IF(MOD(A45,12)=0,W45*'1 - Input'!$B$23,0) -> 0 | Z45: =W45-Y45 -> 485099.11 | AA45: =IF(MOD(A45,12)=0,X45*(1-'1 - Input'!$B$23),X45) -> 481124.62 | AB45: =T45 -> 2700 | AC45: =AC44+AB45 -> 5400 | AD45: =AD44+K45 -> 0 | AE45: =AE44+S45 -> 8.6486658 | AF45: =AF44+V45 -> 0 | AG45: =AG44+Y45 -> 0 | AH45: =AH44+U45 -> 0 | AI45: =IF(W45<=0.000001,1,0) -> 0
A46: 3 | B46: =ROUNDUP(A46/12,0) -> 1 | C46: =(1+INDEX('1 - Input'!$B$34:$E$63,B46,'1 - Input'!$B$16))^(1/12)-1 -> 0.0041219243 | D46: ='1 - Input'!$B$7*(1+'1 - Input'!$B$12)^(B46-1) -> 2700 | E46: =Z45 -> 485099.11 | F46: =AA45 -> 481124.62 | G46: =E46*(1+C46) -> 487098.65 | H46: =0 -> 0 | I46: =G46-H46 -> 487098.65 | J46: =MIN($B$41*H46,F46) -> 0 | K46: ='1 - Input'!$B$22*(H46-J46) -> 0 | L46: =H46-K46 -> 0 | M46: =F46-J46 -> 481124.62 | N46: =0 -> 0 | O46: =D46 -> 2700 | P46: =IF(I46>0,MAX(0,1-M46/I46),0) -> 0.012264527 | Q46: =IF(AND(O46>0,I46>0),O46/(1-'1 - Input'!$B$22*P46),0) -> 2708.6372 | R46: =MIN(Q46,I46) -> 2708.6372 | S46: ='1 - Input'!$B$22*P46*R46 -> 8.6372405 | T46: =R46-S46 -> 2700 | U46: =O46-T46 -> 0 | V46: =IF(I46>0,R46*MAX(0,M46/I46-1),0) -> 0 | W46: =I46-R46+N46 -> 484390.01 | X46: =IF(R46>0,M46*(1-R46/I46),M46)+N46 -> 478449.2 | Y46: =IF(MOD(A46,12)=0,W46*'1 - Input'!$B$23,0) -> 0 | Z46: =W46-Y46 -> 484390.01 | AA46: =IF(MOD(A46,12)=0,X46*(1-'1 - Input'!$B$23),X46) -> 478449.2 | AB46: =T46 -> 2700 | AC46: =AC45+AB46 -> 8100 | AD46: =AD45+K46 -> 0 | AE46: =AE45+S46 -> 17.285906 | AF46: =AF45+V46 -> 0 | AG46: =AG45+Y46 -> 0 | AH46: =AH45+U46 -> 0 | AI46: =IF(W46<=0.000001,1,0) -> 0
A47: 4 | B47: =ROUNDUP(A47/12,0) -> 1 | C47: =(1+INDEX('1 - Input'!$B$34:$E$63,B47,'1 - Input'!$B$16))^(1/12)-1 -> 0.0041219243 | D47: ='1 - Input'!$B$7*(1+'1 - Input'!$B$12)^(B47-1) -> 2700 | E47: =Z46 -> 484390.01 | F47: =AA46 -> 478449.2 | G47: =E47*(1+C47) -> 486386.63 | H47: =0 -> 0 | I47: =G47-H47 -> 486386.63 | J47: =MIN($B$41*H47,F47) -> 0 | K47: ='1 - Input'!$B$22*(H47-J47) -> 0 | L47: =H47-K47 -> 0 | M47: =F47-J47 -> 478449.2 | N47: =0 -> 0 | O47: =D47 -> 2700 | P47: =IF(I47>0,MAX(0,1-M47/I47),0) -> 0.016319185 | Q47: =IF(AND(O47>0,I47>0),O47/(1-'1 - Input'!$B$22*P47),0) -> 2711.5049 | R47: =MIN(Q47,I47) -> 2711.5049 | S47: ='1 - Input'!$B$22*P47*R47 -> 11.504883 | T47: =R47-S47 -> 2700 | U47: =O47-T47 -> 0 | V47: =IF(I47>0,R47*MAX(0,M47/I47-1),0) -> 0 | W47: =I47-R47+N47 -> 483675.13 | X47: =IF(R47>0,M47*(1-R47/I47),M47)+N47 -> 475781.94 | Y47: =IF(MOD(A47,12)=0,W47*'1 - Input'!$B$23,0) -> 0 | Z47: =W47-Y47 -> 483675.13 | AA47: =IF(MOD(A47,12)=0,X47*(1-'1 - Input'!$B$23),X47) -> 475781.94 | AB47: =T47 -> 2700 | AC47: =AC46+AB47 -> 10800 | AD47: =AD46+K47 -> 0 | AE47: =AE46+S47 -> 28.790789 | AF47: =AF46+V47 -> 0 | AG47: =AG46+Y47 -> 0 | AH47: =AH46+U47 -> 0 | AI47: =IF(W47<=0.000001,1,0) -> 0
A48: 5 | B48: =ROUNDUP(A48/12,0) -> 1 | C48: =(1+INDEX('1 - Input'!$B$34:$E$63,B48,'1 - Input'!$B$16))^(1/12)-1 -> 0.0041219243 | D48: ='1 - Input'!$B$7*(1+'1 - Input'!$B$12)^(B48-1) -> 2700 | E48: =Z47 -> 483675.13 | F48: =AA47 -> 475781.94 | G48: =E48*(1+C48) -> 485668.8 | H48: =0 -> 0 | I48: =G48-H48 -> 485668.8 | J48: =MIN($B$41*H48,F48) -> 0 | K48: ='1 - Input'!$B$22*(H48-J48) -> 0 | L48: =H48-K48 -> 0 | M48: =F48-J48 -> 475781.94 | N48: =0 -> 0 | O48: =D48 -> 2700 | P48: =IF(I48>0,MAX(0,1-M48/I48),0) -> 0.020357199 | Q48: =IF(AND(O48>0,I48>0),O48/(1-'1 - Input'!$B$22*P48),0) -> 2714.3668 | R48: =MIN(Q48,I48) -> 2714.3668 | S48: ='1 - Input'!$B$22*P48*R48 -> 14.366795 | T48: =R48-S48 -> 2700 | U48: =O48-T48 -> 0 | V48: =IF(I48>0,R48*MAX(0,M48/I48-1),0) -> 0 | W48: =I48-R48+N48 -> 482954.43 | X48: =IF(R48>0,M48*(1-R48/I48),M48)+N48 -> 473122.83 | Y48: =IF(MOD(A48,12)=0,W48*'1 - Input'!$B$23,0) -> 0 | Z48: =W48-Y48 -> 482954.43 | AA48: =IF(MOD(A48,12)=0,X48*(1-'1 - Input'!$B$23),X48) -> 473122.83 | AB48: =T48 -> 2700 | AC48: =AC47+AB48 -> 13500 | AD48: =AD47+K48 -> 0 | AE48: =AE47+S48 -> 43.157585 | AF48: =AF47+V48 -> 0 | AG48: =AG47+Y48 -> 0 | AH48: =AH47+U48 -> 0 | AI48: =IF(W48<=0.000001,1,0) -> 0
A49: 6 | B49: =ROUNDUP(A49/12,0) -> 1 | C49: =(1+INDEX('1 - Input'!$B$34:$E$63,B49,'1 - Input'!$B$16))^(1/12)-1 -> 0.0041219243 | D49: ='1 - Input'!$B$7*(1+'1 - Input'!$B$12)^(B49-1) -> 2700 | E49: =Z48 -> 482954.43 | F49: =AA48 -> 473122.83 | G49: =E49*(1+C49) -> 484945.13 | H49: =0 -> 0 | I49: =G49-H49 -> 484945.13 | J49: =MIN($B$41*H49,F49) -> 0 | K49: ='1 - Input'!$B$22*(H49-J49) -> 0 | L49: =H49-K49 -> 0 | M49: =F49-J49 -> 473122.83 | N49: =0 -> 0 | O49: =D49 -> 2700 | P49: =IF(I49>0,MAX(0,1-M49/I49),0) -> 0.024378636 | Q49: =IF(AND(O49>0,I49>0),O49/(1-'1 - Input'!$B$22*P49),0) -> 2717.223 | R49: =MIN(Q49,I49) -> 2717.223 | S49: ='1 - Input'!$B$22*P49*R49 -> 17.222969 | T49: =R49-S49 -> 2700 | U49: =O49-T49 -> 0 | V49: =IF(I49>0,R49*MAX(0,M49/I49-1),0) -> 0 | W49: =I49-R49+N49 -> 482227.91 | X49: =IF(R49>0,M49*(1-R49/I49),M49)+N49 -> 470471.85 | Y49: =IF(MOD(A49,12)=0,W49*'1 - Input'!$B$23,0) -> 0 | Z49: =W49-Y49 -> 482227.91 | AA49: =IF(MOD(A49,12)=0,X49*(1-'1 - Input'!$B$23),X49) -> 470471.85 | AB49: =T49 -> 2700 | AC49: =AC48+AB49 -> 16200 | AD49: =AD48+K49 -> 0 | AE49: =AE48+S49 -> 60.380554 | AF49: =AF48+V49 -> 0 | AG49: =AG48+Y49 -> 0 | AH49: =AH48+U49 -> 0 | AI49: =IF(W49<=0.000001,1,0) -> 0
A50: 7 | B50: =ROUNDUP(A50/12,0) -> 1 | C50: =(1+INDEX('1 - Input'!$B$34:$E$63,B50,'1 - Input'!$B$16))^(1/12)-1 -> 0.0041219243 | D50: ='1 - Input'!$B$7*(1+'1 - Input'!$B$12)^(B50-1) -> 2700 | E50: =Z49 -> 482227.91 | F50: =AA49 -> 470471.85 | G50: =E50*(1+C50) -> 484215.62 | H50: =0 -> 0 | I50: =G50-H50 -> 484215.62 | J50: =MIN($B$41*H50,F50) -> 0 | K50: ='1 - Input'!$B$22*(H50-J50) -> 0 | L50: =H50-K50 -> 0 | M50: =F50-J50 -> 470471.85 | N50: =0 -> 0 | O50: =D50 -> 2700 | P50: =IF(I50>0,MAX(0,1-M50/I50),0) -> 0.028383566 | Q50: =IF(AND(O50>0,I50>0),O50/(1-'1 - Input'!$B$22*P50),0) -> 2720.0734 | R50: =MIN(Q50,I50) -> 2720.0734 | S50: ='1 - Input'!$B$22*P50*R50 -> 20.073399 | T50: =R50-S50 -> 2700 | U50: =O50-T50 -> 0 | V50: =IF(I50>0,R50*MAX(0,M50/I50-1),0) -> 0 | W50: =I50-R50+N50 -> 481495.54 | X50: =IF(R50>0,M50*(1-R50/I50),M50)+N50 -> 467828.98 | Y50: =IF(MOD(A50,12)=0,W50*'1 - Input'!$B$23,0) -> 0 | Z50: =W50-Y50 -> 481495.54 | AA50: =IF(MOD(A50,12)=0,X50*(1-'1 - Input'!$B$23),X50) -> 467828.98 | AB50: =T50 -> 2700 | AC50: =AC49+AB50 -> 18900 | AD50: =AD49+K50 -> 0 | AE50: =AE49+S50 -> 80.453953 | AF50: =AF49+V50 -> 0 | AG50: =AG49+Y50 -> 0 | AH50: =AH49+U50 -> 0 | AI50: =IF(W50<=0.000001,1,0) -> 0
A51: 8 | B51: =ROUNDUP(A51/12,0) -> 1 | C51: =(1+INDEX('1 - Input'!$B$34:$E$63,B51,'1 - Input'!$B$16))^(1/12)-1 -> 0.0041219243 | D51: ='1 - Input'!$B$7*(1+'1 - Input'!$B$12)^(B51-1) -> 2700 | E51: =Z50 -> 481495.54 | F51: =AA50 -> 467828.98 | G51: =E51*(1+C51) -> 483480.23 | H51: =0 -> 0 | I51: =G51-H51 -> 483480.23 | J51: =MIN($B$41*H51,F51) -> 0 | K51: ='1 - Input'!$B$22*(H51-J51) -> 0 | L51: =H51-K51 -> 0 | M51: =F51-J51 -> 467828.98 | N51: =0 -> 0 | O51: =D51 -> 2700 | P51: =IF(I51>0,MAX(0,1-M51/I51),0) -> 0.032372055 | Q51: =IF(AND(O51>0,I51>0),O51/(1-'1 - Input'!$B$22*P51),0) -> 2722.9181 | R51: =MIN(Q51,I51) -> 2722.9181 | S51: ='1 - Input'!$B$22*P51*R51 -> 22.918078 | T51: =R51-S51 -> 2700 | U51: =O51-T51 -> 0 | V51: =IF(I51>0,R51*MAX(0,M51/I51-1),0) -> 0 | W51: =I51-R51+N51 -> 480757.31 | X51: =IF(R51>0,M51*(1-R51/I51),M51)+N51 -> 465194.21 | Y51: =IF(MOD(A51,12)=0,W51*'1 - Input'!$B$23,0) -> 0 | Z51: =W51-Y51 -> 480757.31 | AA51: =IF(MOD(A51,12)=0,X51*(1-'1 - Input'!$B$23),X51) -> 465194.21 | AB51: =T51 -> 2700 | AC51: =AC50+AB51 -> 21600 | AD51: =AD50+K51 -> 0 | AE51: =AE50+S51 -> 103.37203 | AF51: =AF50+V51 -> 0 | AG51: =AG50+Y51 -> 0 | AH51: =AH50+U51 -> 0 | AI51: =IF(W51<=0.000001,1,0) -> 0
A52: 9 | B52: =ROUNDUP(A52/12,0) -> 1 | C52: =(1+INDEX('1 - Input'!$B$34:$E$63,B52,'1 - Input'!$B$16))^(1/12)-1 -> 0.0041219243 | D52: ='1 - Input'!$B$7*(1+'1 - Input'!$B$12)^(B52-1) -> 2700 | E52: =Z51 -> 480757.31 | F52: =AA51 -> 465194.21 | G52: =E52*(1+C52) -> 482738.96 | H52: =0 -> 0 | I52: =G52-H52 -> 482738.96 | J52: =MIN($B$41*H52,F52) -> 0 | K52: ='1 - Input'!$B$22*(H52-J52) -> 0 | L52: =H52-K52 -> 0 | M52: =F52-J52 -> 465194.21 | N52: =0 -> 0 | O52: =D52 -> 2700 | P52: =IF(I52>0,MAX(0,1-M52/I52),0) -> 0.036344171 | Q52: =IF(AND(O52>0,I52>0),O52/(1-'1 - Input'!$B$22*P52),0) -> 2725.757 | R52: =MIN(Q52,I52) -> 2725.757 | S52: ='1 - Input'!$B$22*P52*R52 -> 25.756999 | T52: =R52-S52 -> 2700 | U52: =O52-T52 -> 0 | V52: =IF(I52>0,R52*MAX(0,M52/I52-1),0) -> 0 | W52: =I52-R52+N52 -> 480013.2 | X52: =IF(R52>0,M52*(1-R52/I52),M52)+N52 -> 462567.52 | Y52: =IF(MOD(A52,12)=0,W52*'1 - Input'!$B$23,0) -> 0 | Z52: =W52-Y52 -> 480013.2 | AA52: =IF(MOD(A52,12)=0,X52*(1-'1 - Input'!$B$23),X52) -> 462567.52 | AB52: =T52 -> 2700 | AC52: =AC51+AB52 -> 24300 | AD52: =AD51+K52 -> 0 | AE52: =AE51+S52 -> 129.12903 | AF52: =AF51+V52 -> 0 | AG52: =AG51+Y52 -> 0 | AH52: =AH51+U52 -> 0 | AI52: =IF(W52<=0.000001,1,0) -> 0
A53: 10 | B53: =ROUNDUP(A53/12,0) -> 1 | C53: =(1+INDEX('1 - Input'!$B$34:$E$63,B53,'1 - Input'!$B$16))^(1/12)-1 -> 0.0041219243 | D53: ='1 - Input'!$B$7*(1+'1 - Input'!$B$12)^(B53-1) -> 2700 | E53: =Z52 -> 480013.2 | F53: =AA52 -> 462567.52 | G53: =E53*(1+C53) -> 481991.78 | H53: =0 -> 0 | I53: =G53-H53 -> 481991.78 | J53: =MIN($B$41*H53,F53) -> 0 | K53: ='1 - Input'!$B$22*(H53-J53) -> 0 | L53: =H53-K53 -> 0 | M53: =F53-J53 -> 462567.52 | N53: =0 -> 0 | O53: =D53 -> 2700 | P53: =IF(I53>0,MAX(0,1-M53/I53),0) -> 0.040299982 | Q53: =IF(AND(O53>0,I53>0),O53/(1-'1 - Input'!$B$22*P53),0) -> 2728.5902 | R53: =MIN(Q53,I53) -> 2728.5902 | S53: ='1 - Input'!$B$22*P53*R53 -> 28.590155 | T53: =R53-S53 -> 2700 | U53: =O53-T53 -> 0 | V53: =IF(I53>0,R53*MAX(0,M53/I53-1),0) -> 0 | W53: =I53-R53+N53 -> 479263.19 | X53: =IF(R53>0,M53*(1-R53/I53),M53)+N53 -> 459948.89 | Y53: =IF(MOD(A53,12)=0,W53*'1 - Input'!$B$23,0) -> 0 | Z53: =W53-Y53 -> 479263.19 | AA53: =IF(MOD(A53,12)=0,X53*(1-'1 - Input'!$B$23),X53) -> 459948.89 | AB53: =T53 -> 2700 | AC53: =AC52+AB53 -> 27000 | AD53: =AD52+K53 -> 0 | AE53: =AE52+S53 -> 157.71918 | AF53: =AF52+V53 -> 0 | AG53: =AG52+Y53 -> 0 | AH53: =AH52+U53 -> 0 | AI53: =IF(W53<=0.000001,1,0) -> 0
A54: 11 | B54: =ROUNDUP(A54/12,0) -> 1 | C54: =(1+INDEX('1 - Input'!$B$34:$E$63,B54,'1 - Input'!$B$16))^(1/12)-1 -> 0.0041219243 | D54: ='1 - Input'!$B$7*(1+'1 - Input'!$B$12)^(B54-1) -> 2700 | E54: =Z53 -> 479263.19 | F54: =AA53 -> 459948.89 | G54: =E54*(1+C54) -> 481238.68 | H54: =0 -> 0 | I54: =G54-H54 -> 481238.68 | J54: =MIN($B$41*H54,F54) -> 0 | K54: ='1 - Input'!$B$22*(H54-J54) -> 0 | L54: =H54-K54 -> 0 | M54: =F54-J54 -> 459948.89 | N54: =0 -> 0 | O54: =D54 -> 2700 | P54: =IF(I54>0,MAX(0,1-M54/I54),0) -> 0.044239554 | Q54: =IF(AND(O54>0,I54>0),O54/(1-'1 - Input'!$B$22*P54),0) -> 2731.4175 | R54: =MIN(Q54,I54) -> 2731.4175 | S54: ='1 - Input'!$B$22*P54*R54 -> 31.417541 | T54: =R54-S54 -> 2700 | U54: =O54-T54 -> 0 | V54: =IF(I54>0,R54*MAX(0,M54/I54-1),0) -> 0 | W54: =I54-R54+N54 -> 478507.26 | X54: =IF(R54>0,M54*(1-R54/I54),M54)+N54 -> 457338.31 | Y54: =IF(MOD(A54,12)=0,W54*'1 - Input'!$B$23,0) -> 0 | Z54: =W54-Y54 -> 478507.26 | AA54: =IF(MOD(A54,12)=0,X54*(1-'1 - Input'!$B$23),X54) -> 457338.31 | AB54: =T54 -> 2700 | AC54: =AC53+AB54 -> 29700 | AD54: =AD53+K54 -> 0 | AE54: =AE53+S54 -> 189.13673 | AF54: =AF53+V54 -> 0 | AG54: =AG53+Y54 -> 0 | AH54: =AH53+U54 -> 0 | AI54: =IF(W54<=0.000001,1,0) -> 0
A55: 12 | B55: =ROUNDUP(A55/12,0) -> 1 | C55: =(1+INDEX('1 - Input'!$B$34:$E$63,B55,'1 - Input'!$B$16))^(1/12)-1 -> 0.0041219243 | D55: ='1 - Input'!$B$7*(1+'1 - Input'!$B$12)^(B55-1) -> 2700 | E55: =Z54 -> 478507.26 | F55: =AA54 -> 457338.31 | G55: =E55*(1+C55) -> 480479.63 | H55: =0 -> 0 | I55: =G55-H55 -> 480479.63 | J55: =MIN($B$41*H55,F55) -> 0 | K55: ='1 - Input'!$B$22*(H55-J55) -> 0 | L55: =H55-K55 -> 0 | M55: =F55-J55 -> 457338.31 | N55: =0 -> 0 | O55: =D55 -> 2700 | P55: =IF(I55>0,MAX(0,1-M55/I55),0) -> 0.048162955 | Q55: =IF(AND(O55>0,I55>0),O55/(1-'1 - Input'!$B$22*P55),0) -> 2734.2391 | R55: =MIN(Q55,I55) -> 2734.2391 | S55: ='1 - Input'!$B$22*P55*R55 -> 34.239149 | T55: =R55-S55 -> 2700 | U55: =O55-T55 -> 0 | V55: =IF(I55>0,R55*MAX(0,M55/I55-1),0) -> 0 | W55: =I55-R55+N55 -> 477745.39 | X55: =IF(R55>0,M55*(1-R55/I55),M55)+N55 -> 454735.76 | Y55: =IF(MOD(A55,12)=0,W55*'1 - Input'!$B$23,0) -> 955.49078 | Z55: =W55-Y55 -> 476789.9 | AA55: =IF(MOD(A55,12)=0,X55*(1-'1 - Input'!$B$23),X55) -> 453826.29 | AB55: =T55 -> 2700 | AC55: =AC54+AB55 -> 32400 | AD55: =AD54+K55 -> 0 | AE55: =AE54+S55 -> 223.37587 | AF55: =AF54+V55 -> 0 | AG55: =AG54+Y55 -> 955.49078 | AH55: =AH54+U55 -> 0 | AI55: =IF(W55<=0.000001,1,0) -> 0
A56: 13 | B56: =ROUNDUP(A56/12,0) -> 2 | C56: =(1+INDEX('1 - Input'!$B$34:$E$63,B56,'1 - Input'!$B$16))^(1/12)-1 -> 0.0041219243 | D56: ='1 - Input'!$B$7*(1+'1 - Input'!$B$12)^(B56-1) -> 2754 | E56: =Z55 -> 476789.9 | F56: =AA55 -> 453826.29 | G56: =E56*(1+C56) -> 478755.19 | H56: =0 -> 0 | I56: =G56-H56 -> 478755.19 | J56: =MIN($B$41*H56,F56) -> 0 | K56: ='1 - Input'!$B$22*(H56-J56) -> 0 | L56: =H56-K56 -> 0 | M56: =F56-J56 -> 453826.29 | N56: =0 -> 0 | O56: =D56 -> 2754 | P56: =IF(I56>0,MAX(0,1-M56/I56),0) -> 0.052070249 | Q56: =IF(AND(O56>0,I56>0),O56/(1-'1 - Input'!$B$22*P56),0) -> 2791.7961 | R56: =MIN(Q56,I56) -> 2791.7961 | S56: ='1 - Input'!$B$22*P56*R56 -> 37.796074 | T56: =R56-S56 -> 2754 | U56: =O56-T56 -> 0 | V56: =IF(I56>0,R56*MAX(0,M56/I56-1),0) -> 0 | W56: =I56-R56+N56 -> 475963.4 | X56: =IF(R56>0,M56*(1-R56/I56),M56)+N56 -> 451179.86 | Y56: =IF(MOD(A56,12)=0,W56*'1 - Input'!$B$23,0) -> 0 | Z56: =W56-Y56 -> 475963.4 | AA56: =IF(MOD(A56,12)=0,X56*(1-'1 - Input'!$B$23),X56) -> 451179.86 | AB56: =T56 -> 2754 | AC56: =AC55+AB56 -> 35154 | AD56: =AD55+K56 -> 0 | AE56: =AE55+S56 -> 261.17195 | AF56: =AF55+V56 -> 0 | AG56: =AG55+Y56 -> 955.49078 | AH56: =AH55+U56 -> 0 | AI56: =IF(W56<=0.000001,1,0) -> 0
... A403: 360 | B403: =ROUNDUP(A403/12,0) -> 30 | C403: =(1+INDEX('1 - Input'!$B$34:$E$63,B403,'1 - Input'!$B$16))^(1/12)-1 -> 0.0041219243 | D403: ='1 - Input'!$B$7*(1+'1 - Input'!$B$12)^(B403-1) -> 4794.7807 | E403: =Z402 -> 0 | F403: =AA402 -> 0 | G403: =E403*(1+C403) -> 0 | H403: =0 -> 0 | I403: =G403-H403 -> 0 | J403: =MIN($B$41*H403,F403) -> 0 | K403: ='1 - Input'!$B$22*(H403-J403) -> 0 | L403: =H403-K403 -> 0 | M403: =F403-J403 -> 0 | N403: =0 -> 0 | O403: =D403 -> 4794.7807 | P403: =IF(I403>0,MAX(0,1-M403/I403),0) -> 0 | Q403: =IF(AND(O403>0,I403>0),O403/(1-'1 - Input'!$B$22*P403),0) -> 0 | R403: =MIN(Q403,I403) -> 0 | S403: ='1 - Input'!$B$22*P403*R403 -> 0 | T403: =R403-S403 -> 0 | U403: =O403-T403 -> 4794.7807 | V403: =IF(I403>0,R403*MAX(0,M403/I403-1),0) -> 0 | W403: =I403-R403+N403 -> 0 | X403: =IF(R403>0,M403*(1-R403/I403),M403)+N403 -> 0 | Y403: =IF(MOD(A403,12)=0,W403*'1 - Input'!$B$23,0) -> 0 | Z403: =W403-Y403 -> 0 | AA403: =IF(MOD(A403,12)=0,X403*(1-'1 - Input'!$B$23),X403) -> 0 | AB403: =T403 -> 0 | AC403: =AC402+AB403 -> 676015.58 | AD403: =AD402+K403 -> 0 | AE403: =AE402+S403 -> 69240.415 | AF403: =AF402+V403 -> 0 | AG403: =AG402+Y403 -> 10373.843 | AH403: =AH402+U403 -> 638390.19 | AI403: =IF(W403<=0.000001,1,0) -> 1

Sheet 4 - Confronto
A1: Dividendo mensile: rendita o capitale che torna indietro? Il caso di Renata (caso inventato e illustrativo)
A2: Caso inventato e illustrativo, non è consulenza e non è una previsione. Fotografia di ottobre 2026, regole fiscali di oggi. Prima di decidere fai i conti sul tuo caso e parlane con professionisti abilitati.
A4: Quota Q usata nel percorso U (foglio 1) | B4: ='1 - Input'!$B$9 -> 0 | C4: Dipende dalla delibera e dal rendiconto del fondo. Per i fondi esteri nessuna norma assicura una quota diversa da zero: Q = 100% è un limite teorico, senza fonte per gli ETF esteri. Leggi il rendiconto.
A5: Interruttore senza imposte e senza bollo (foglio 1) | B5: =IF('1 - Input'!$B$20=1,"attivo","spento") -> spento
A7: Percorso | B7: Durata in mesi | C7: Durata | D7: Imposte cumulate (orizzonte) | E7: di cui sulle distribuzioni | F7: di cui sulle vendite | G7: Minusvalenze realizzate | H7: Capitale a 10 anni | I7: Imposte a 10 anni | J7: Capitale a 15 anni | K7: Imposte a 15 anni | L7: Capitale a fine orizzonte
A8: A: caso atteso, Q = 0% | B8: =IFERROR(MATCH(1,'2 - Distribuzione'!$AI$44:$AI$403,0),"oltre 30 anni") -> 189 | C8: =IF(ISNUMBER(B8),INT(B8/12)&" anni e "&MOD(B8,12)&" mesi","oltre 30 anni") -> 15 anni e 9 mesi | D8: =INDEX('2 - Distribuzione'!$AD$44:$AD$403,12*'1 - Input'!$B$14)+INDEX('2 - Distribuzione'!$AE$44:$AE$403,12*'1 - Input'!$B$14) -> 101441.9 | E8: =INDEX('2 - Distribuzione'!$AD$44:$AD$403,12*'1 - Input'!$B$14) -> 101441.9 | F8: =INDEX('2 - Distribuzione'!$AE$44:$AE$403,12*'1 - Input'!$B$14) -> 0 | G8: =INDEX('2 - Distribuzione'!$AF$44:$AF$403,12*'1 - Input'!$B$14) -> 174289.24 | H8: =INDEX('2 - Distribuzione'!$Z$44:$Z$403,120) -> 219631.46 | I8: =INDEX('2 - Distribuzione'!$AD$44:$AD$403,120)+INDEX('2 - Distribuzione'!$AE$44:$AE$403,120) -> 85900.86 | J8: =INDEX('2 - Distribuzione'!$Z$44:$Z$403,180) -> 29873.886 | K8: =INDEX('2 - Distribuzione'!$AD$44:$AD$403,180)+INDEX('2 - Distribuzione'!$AE$44:$AE$403,180) -> 101168.32 | L8: =INDEX('2 - Distribuzione'!$Z$44:$Z$403,12*'1 - Input'!$B$14) -> 0
A9: U: Q scelta nel foglio 1 | B9: =IFERROR(MATCH(1,'2 - Distribuzione'!$BS$44:$BS$403,0),"oltre 30 anni") -> 189 | C9: =IF(ISNUMBER(B9),INT(B9/12)&" anni e "&MOD(B9,12)&" mesi","oltre 30 anni") -> 15 anni e 9 mesi | D9: =INDEX('2 - Distribuzione'!$BN$44:$BN$403,12*'1 - Input'!$B$14)+INDEX('2 - Distribuzione'!$BO$44:$BO$403,12*'1 - Input'!$B$14) -> 101441.9 | E9: =INDEX('2 - Distribuzione'!$BN$44:$BN$403,12*'1 - Input'!$B$14) -> 101441.9 | F9: =INDEX('2 - Distribuzione'!$BO$44:$BO$403,12*'1 - Input'!$B$14) -> 0 | G9: =INDEX('2 - Distribuzione'!$BP$44:$BP$403,12*'1 - Input'!$B$14) -> 174289.24 | H9: =INDEX('2 - Distribuzione'!$BJ$44:$BJ$403,120) -> 219631.46 | I9: =INDEX('2 - Distribuzione'!$BN$44:$BN$403,120)+INDEX('2 - Distribuzione'!$BO$44:$BO$403,120) -> 85900.86 | J9: =INDEX('2 - Distribuzione'!$BJ$44:$BJ$403,180) -> 29873.886 | K9: =INDEX('2 - Distribuzione'!$BN$44:$BN$403,180)+INDEX('2 - Distribuzione'!$BO$44:$BO$403,180) -> 101168.32 | L9: =INDEX('2 - Distribuzione'!$BJ$44:$BJ$403,12*'1 - Input'!$B$14) -> 0
A10: B: limite teorico, senza fonte per gli ETF esteri, Q = 100% | B10: =IFERROR(MATCH(1,'2 - Distribuzione'!$DC$44:$DC$403,0),"oltre 30 anni") -> 215 | C10: =IF(ISNUMBER(B10),INT(B10/12)&" anni e "&MOD(B10,12)&" mesi","oltre 30 anni") -> 17 anni e 11 mesi | D10: =INDEX('2 - Distribuzione'!$CX$44:$CX$403,12*'1 - Input'!$B$14)+INDEX('2 - Distribuzione'!$CY$44:$CY$403,12*'1 - Input'!$B$14) -> 72537.116 | E10: =INDEX('2 - Distribuzione'!$CX$44:$CX$403,12*'1 - Input'!$B$14) -> 6018.3403 | F10: =INDEX('2 - Distribuzione'!$CY$44:$CY$403,12*'1 - Input'!$B$14) -> 66518.776 | G10: =INDEX('2 - Distribuzione'!$CZ$44:$CZ$403,12*'1 - Input'!$B$14) -> 0 | H10: =INDEX('2 - Distribuzione'!$CT$44:$CT$403,120) -> 329797.96 | I10: =INDEX('2 - Distribuzione'!$CX$44:$CX$403,120)+INDEX('2 - Distribuzione'!$CY$44:$CY$403,120) -> 2376.9865 | J10: =INDEX('2 - Distribuzione'!$CT$44:$CT$403,180) -> 159112.64 | K10: =INDEX('2 - Distribuzione'!$CX$44:$CX$403,180)+INDEX('2 - Distribuzione'!$CY$44:$CY$403,180) -> 28161.865 | L10: =INDEX('2 - Distribuzione'!$CT$44:$CT$403,12*'1 - Input'!$B$14) -> 0
A11: Accumulo con vendite | B11: =IFERROR(MATCH(1,'3 - Accumulo'!$AI$44:$AI$403,0),"oltre 30 anni") -> 212 | C11: =IF(ISNUMBER(B11),INT(B11/12)&" anni e "&MOD(B11,12)&" mesi","oltre 30 anni") -> 17 anni e 8 mesi | D11: =INDEX('3 - Accumulo'!$AD$44:$AD$403,12*'1 - Input'!$B$14)+INDEX('3 - Accumulo'!$AE$44:$AE$403,12*'1 - Input'!$B$14) -> 69240.415 | E11: =INDEX('3 - Accumulo'!$AD$44:$AD$403,12*'1 - Input'!$B$14) -> 0 | F11: =INDEX('3 - Accumulo'!$AE$44:$AE$403,12*'1 - Input'!$B$14) -> 69240.415 | G11: =INDEX('3 - Accumulo'!$AF$44:$AF$403,12*'1 - Input'!$B$14) -> 0 | H11: =INDEX('3 - Accumulo'!$Z$44:$Z$403,120) -> 306771.86 | I11: =INDEX('3 - Accumulo'!$AD$44:$AD$403,120)+INDEX('3 - Accumulo'!$AE$44:$AE$403,120) -> 21741.44 | J11: =INDEX('3 - Accumulo'!$Z$44:$Z$403,180) -> 126688.49 | K11: =INDEX('3 - Accumulo'!$AD$44:$AD$403,180)+INDEX('3 - Accumulo'!$AE$44:$AE$403,180) -> 49778.736 | L11: =INDEX('3 - Accumulo'!$Z$44:$Z$403,12*'1 - Input'!$B$14) -> 0
A13: Differenza di durata tra B e A | B13: =IFERROR((B10-B8)/12,"non calcolabile") -> 2.1666667 | C13: =IFERROR("Tra il caso atteso e il limite teorico la durata cambia di "&FIXED(B13,1)&" anni","Uno dei due percorsi regge oltre 30 anni") -> Tra il caso atteso e il limite teorico la durata cambia di 2,2 anni
A15: Per anno: capitale a fine anno (dopo bollo) e imposte cumulate
A16: Anno | B16: Capitale A | C16: Capitale U | D16: Capitale B | E16: Capitale Accumulo con vendite | F16: Imposte A | G16: Imposte U | H16: Imposte B | I16: Imposte Accumulo con vendite
A17: 1 | B17: =INDEX('2 - Distribuzione'!$Z$44:$Z$403,12*$A17) -> 465562.82 | C17: =INDEX('2 - Distribuzione'!$BJ$44:$BJ$403,12*$A17) -> 465562.82 | D17: =INDEX('2 - Distribuzione'!$CT$44:$CT$403,12*$A17) -> 477016.24 | E17: =INDEX('3 - Accumulo'!$Z$44:$Z$403,12*$A17) -> 476789.9 | F17: =INDEX('2 - Distribuzione'!$AD$44:$AD$403,12*$A17)+INDEX('2 - Distribuzione'!$AE$44:$AE$403,12*$A17) -> 11216.604 | G17: =INDEX('2 - Distribuzione'!$BN$44:$BN$403,12*$A17)+INDEX('2 - Distribuzione'!$BO$44:$BO$403,12*$A17) -> 11216.604 | H17: =INDEX('2 - Distribuzione'!$CX$44:$CX$403,12*$A17)+INDEX('2 - Distribuzione'!$CY$44:$CY$403,12*$A17) -> 0 | I17: =INDEX('3 - Accumulo'!$AD$44:$AD$403,12*$A17)+INDEX('3 - Accumulo'!$AE$44:$AE$403,12*$A17) -> 223.37587
A18: 2 | B18: =INDEX('2 - Distribuzione'!$Z$44:$Z$403,12*$A18) -> 443463.96 | C18: =INDEX('2 - Distribuzione'!$BJ$44:$BJ$403,12*$A18) -> 443463.96 | D18: =INDEX('2 - Distribuzione'!$CT$44:$CT$403,12*$A18) -> 466410.97 | E18: =INDEX('3 - Accumulo'!$Z$44:$Z$403,12*$A18) -> 465520.5 | F18: =INDEX('2 - Distribuzione'!$AD$44:$AD$403,12*$A18)+INDEX('2 - Distribuzione'!$AE$44:$AE$403,12*$A18) -> 21928.332 | G18: =INDEX('2 - Distribuzione'!$BN$44:$BN$403,12*$A18)+INDEX('2 - Distribuzione'!$BO$44:$BO$403,12*$A18) -> 21928.332 | H18: =INDEX('2 - Distribuzione'!$CX$44:$CX$403,12*$A18)+INDEX('2 - Distribuzione'!$CY$44:$CY$403,12*$A18) -> 0 | I18: =INDEX('3 - Accumulo'!$AD$44:$AD$403,12*$A18)+INDEX('3 - Accumulo'!$AE$44:$AE$403,12*$A18) -> 864.79726
A19: 3 | B19: =INDEX('2 - Distribuzione'!$Z$44:$Z$403,12*$A19) -> 420162.21 | C19: =INDEX('2 - Distribuzione'!$BJ$44:$BJ$403,12*$A19) -> 420162.21 | D19: =INDEX('2 - Distribuzione'!$CT$44:$CT$403,12*$A19) -> 454616.55 | E19: =INDEX('3 - Accumulo'!$Z$44:$Z$403,12*$A19) -> 452596.63 | F19: =INDEX('2 - Distribuzione'!$AD$44:$AD$403,12*$A19)+INDEX('2 - Distribuzione'!$AE$44:$AE$403,12*$A19) -> 32107.421 | G19: =INDEX('2 - Distribuzione'!$BN$44:$BN$403,12*$A19)+INDEX('2 - Distribuzione'!$BO$44:$BO$403,12*$A19) -> 32107.421 | H19: =INDEX('2 - Distribuzione'!$CX$44:$CX$403,12*$A19)+INDEX('2 - Distribuzione'!$CY$44:$CY$403,12*$A19) -> 0 | I19: =INDEX('3 - Accumulo'!$AD$44:$AD$403,12*$A19)+INDEX('3 - Accumulo'!$AE$44:$AE$403,12*$A19) -> 1930.4376
A20: 4 | B20: =INDEX('2 - Distribuzione'!$Z$44:$Z$403,12*$A20) -> 395615.07 | C20: =INDEX('2 - Distribuzione'!$BJ$44:$BJ$403,12*$A20) -> 395615.07 | D20: =INDEX('2 - Distribuzione'!$CT$44:$CT$403,12*$A20) -> 441561.81 | E20: =INDEX('3 - Accumulo'!$Z$44:$Z$403,12*$A20) -> 437918.5 | F20: =INDEX('2 - Distribuzione'!$AD$44:$AD$403,12*$A20)+INDEX('2 - Distribuzione'!$AE$44:$AE$403,12*$A20) -> 41725.126 | G20: =INDEX('2 - Distribuzione'!$BN$44:$BN$403,12*$A20)+INDEX('2 - Distribuzione'!$BO$44:$BO$403,12*$A20) -> 41725.126 | H20: =INDEX('2 - Distribuzione'!$CX$44:$CX$403,12*$A20)+INDEX('2 - Distribuzione'!$CY$44:$CY$403,12*$A20) -> 0 | I20: =INDEX('3 - Accumulo'!$AD$44:$AD$403,12*$A20)+INDEX('3 - Accumulo'!$AE$44:$AE$403,12*$A20) -> 3426.2408
A21: 5 | B21: =INDEX('2 - Distribuzione'!$Z$44:$Z$403,12*$A21) -> 369778.76 | C21: =INDEX('2 - Distribuzione'!$BJ$44:$BJ$403,12*$A21) -> 369778.76 | D21: =INDEX('2 - Distribuzione'!$CT$44:$CT$403,12*$A21) -> 427171.88 | E21: =INDEX('3 - Accumulo'!$Z$44:$Z$403,12*$A21) -> 421381.4 | F21: =INDEX('2 - Distribuzione'!$AD$44:$AD$403,12*$A21)+INDEX('2 - Distribuzione'!$AE$44:$AE$403,12*$A21) -> 50751.686 | G21: =INDEX('2 - Distribuzione'!$BN$44:$BN$403,12*$A21)+INDEX('2 - Distribuzione'!$BO$44:$BO$403,12*$A21) -> 50751.686 | H21: =INDEX('2 - Distribuzione'!$CX$44:$CX$403,12*$A21)+INDEX('2 - Distribuzione'!$CY$44:$CY$403,12*$A21) -> 0 | I21: =INDEX('3 - Accumulo'!$AD$44:$AD$403,12*$A21)+INDEX('3 - Accumulo'!$AE$44:$AE$403,12*$A21) -> 5357.9324
A22: 6 | B22: =INDEX('2 - Distribuzione'!$Z$44:$Z$403,12*$A22) -> 342608.14 | C22: =INDEX('2 - Distribuzione'!$BJ$44:$BJ$403,12*$A22) -> 342608.14 | D22: =INDEX('2 - Distribuzione'!$CT$44:$CT$403,12*$A22) -> 411367.95 | E22: =INDEX('3 - Accumulo'!$Z$44:$Z$403,12*$A22) -> 402875.5 | F22: =INDEX('2 - Distribuzione'!$AD$44:$AD$403,12*$A22)+INDEX('2 - Distribuzione'!$AE$44:$AE$403,12*$A22) -> 59156.299 | G22: =INDEX('2 - Distribuzione'!$BN$44:$BN$403,12*$A22)+INDEX('2 - Distribuzione'!$BO$44:$BO$403,12*$A22) -> 59156.299 | H22: =INDEX('2 - Distribuzione'!$CX$44:$CX$403,12*$A22)+INDEX('2 - Distribuzione'!$CY$44:$CY$403,12*$A22) -> 0 | I22: =INDEX('3 - Accumulo'!$AD$44:$AD$403,12*$A22)+INDEX('3 - Accumulo'!$AE$44:$AE$403,12*$A22) -> 7731.0321
A23: 7 | B23: =INDEX('2 - Distribuzione'!$Z$44:$Z$403,12*$A23) -> 314056.73 | C23: =INDEX('2 - Distribuzione'!$BJ$44:$BJ$403,12*$A23) -> 314056.73 | D23: =INDEX('2 - Distribuzione'!$CT$44:$CT$403,12*$A23) -> 394047.13 | E23: =INDEX('3 - Accumulo'!$Z$44:$Z$403,12*$A23) -> 382285.57 | F23: =INDEX('2 - Distribuzione'!$AD$44:$AD$403,12*$A23)+INDEX('2 - Distribuzione'!$AE$44:$AE$403,12*$A23) -> 66907.086 | G23: =INDEX('2 - Distribuzione'!$BN$44:$BN$403,12*$A23)+INDEX('2 - Distribuzione'!$BO$44:$BO$403,12*$A23) -> 66907.086 | H23: =INDEX('2 - Distribuzione'!$CX$44:$CX$403,12*$A23)+INDEX('2 - Distribuzione'!$CY$44:$CY$403,12*$A23) -> 19.915833 | I23: =INDEX('3 - Accumulo'!$AD$44:$AD$403,12*$A23)+INDEX('3 - Accumulo'!$AE$44:$AE$403,12*$A23) -> 10550.866
A24: 8 | B24: =INDEX('2 - Distribuzione'!$Z$44:$Z$403,12*$A24) -> 284076.63 | C24: =INDEX('2 - Distribuzione'!$BJ$44:$BJ$403,12*$A24) -> 284076.63 | D24: =INDEX('2 - Distribuzione'!$CT$44:$CT$403,12*$A24) -> 374859.67 | E24: =INDEX('3 - Accumulo'!$Z$44:$Z$403,12*$A24) -> 359490.65 | F24: =INDEX('2 - Distribuzione'!$AD$44:$AD$403,12*$A24)+INDEX('2 - Distribuzione'!$AE$44:$AE$403,12*$A24) -> 73971.057 | G24: =INDEX('2 - Distribuzione'!$BN$44:$BN$403,12*$A24)+INDEX('2 - Distribuzione'!$BO$44:$BO$403,12*$A24) -> 73971.057 | H24: =INDEX('2 - Distribuzione'!$CX$44:$CX$403,12*$A24)+INDEX('2 - Distribuzione'!$CY$44:$CY$403,12*$A24) -> 316.35411 | I24: =INDEX('3 - Accumulo'!$AD$44:$AD$403,12*$A24)+INDEX('3 - Accumulo'!$AE$44:$AE$403,12*$A24) -> 13822.583
A25: 9 | B25: =INDEX('2 - Distribuzione'!$Z$44:$Z$403,12*$A25) -> 252618.49 | C25: =INDEX('2 - Distribuzione'!$BJ$44:$BJ$403,12*$A25) -> 252618.49 | D25: =INDEX('2 - Distribuzione'!$CT$44:$CT$403,12*$A25) -> 353540.73 | E25: =INDEX('3 - Accumulo'!$Z$44:$Z$403,12*$A25) -> 334363.82 | F25: =INDEX('2 - Distribuzione'!$AD$44:$AD$403,12*$A25)+INDEX('2 - Distribuzione'!$AE$44:$AE$403,12*$A25) -> 80314.084 | G25: =INDEX('2 - Distribuzione'!$BN$44:$BN$403,12*$A25)+INDEX('2 - Distribuzione'!$BO$44:$BO$403,12*$A25) -> 80314.084 | H25: =INDEX('2 - Distribuzione'!$CX$44:$CX$403,12*$A25)+INDEX('2 - Distribuzione'!$CY$44:$CY$403,12*$A25) -> 1045.2512 | I25: =INDEX('3 - Accumulo'!$AD$44:$AD$403,12*$A25)+INDEX('3 - Accumulo'!$AE$44:$AE$403,12*$A25) -> 17551.163
A26: 10 | B26: =INDEX('2 - Distribuzione'!$Z$44:$Z$403,12*$A26) -> 219631.46 | C26: =INDEX('2 - Distribuzione'!$BJ$44:$BJ$403,12*$A26) -> 219631.46 | D26: =INDEX('2 - Distribuzione'!$CT$44:$CT$403,12*$A26) -> 329797.96 | E26: =INDEX('3 - Accumulo'!$Z$44:$Z$403,12*$A26) -> 306771.86 | F26: =INDEX('2 - Distribuzione'!$AD$44:$AD$403,12*$A26)+INDEX('2 - Distribuzione'!$AE$44:$AE$403,12*$A26) -> 85900.86 | G26: =INDEX('2 - Distribuzione'!$BN$44:$BN$403,12*$A26)+INDEX('2 - Distribuzione'!$BO$44:$BO$403,12*$A26) -> 85900.86 | H26: =INDEX('2 - Distribuzione'!$CX$44:$CX$403,12*$A26)+INDEX('2 - Distribuzione'!$CY$44:$CY$403,12*$A26) -> 2376.9865 | I26: =INDEX('3 - Accumulo'!$AD$44:$AD$403,12*$A26)+INDEX('3 - Accumulo'!$AE$44:$AE$403,12*$A26) -> 21741.44
A27: 11 | B27: =INDEX('2 - Distribuzione'!$Z$44:$Z$403,12*$A27) -> 185063.18 | C27: =INDEX('2 - Distribuzione'!$BJ$44:$BJ$403,12*$A27) -> 185063.18 | D27: =INDEX('2 - Distribuzione'!$CT$44:$CT$403,12*$A27) -> 303282.34 | E27: =INDEX('3 - Accumulo'!$Z$44:$Z$403,12*$A27) -> 276574.91 | F27: =INDEX('2 - Distribuzione'!$AD$44:$AD$403,12*$A27)+INDEX('2 - Distribuzione'!$AE$44:$AE$403,12*$A27) -> 90694.866 | G27: =INDEX('2 - Distribuzione'!$BN$44:$BN$403,12*$A27)+INDEX('2 - Distribuzione'!$BO$44:$BO$403,12*$A27) -> 90694.866 | H27: =INDEX('2 - Distribuzione'!$CX$44:$CX$403,12*$A27)+INDEX('2 - Distribuzione'!$CY$44:$CY$403,12*$A27) -> 4523.2643 | I27: =INDEX('3 - Accumulo'!$AD$44:$AD$403,12*$A27)+INDEX('3 - Accumulo'!$AE$44:$AE$403,12*$A27) -> 26398.109
A28: 12 | B28: =INDEX('2 - Distribuzione'!$Z$44:$Z$403,12*$A28) -> 148859.68 | C28: =INDEX('2 - Distribuzione'!$BJ$44:$BJ$403,12*$A28) -> 148859.68 | D28: =INDEX('2 - Distribuzione'!$CT$44:$CT$403,12*$A28) -> 273574.2 | E28: =INDEX('3 - Accumulo'!$Z$44:$Z$403,12*$A28) -> 243626.14 | F28: =INDEX('2 - Distribuzione'!$AD$44:$AD$403,12*$A28)+INDEX('2 - Distribuzione'!$AE$44:$AE$403,12*$A28) -> 94658.335 | G28: =INDEX('2 - Distribuzione'!$BN$44:$BN$403,12*$A28)+INDEX('2 - Distribuzione'!$BO$44:$BO$403,12*$A28) -> 94658.335 | H28: =INDEX('2 - Distribuzione'!$CX$44:$CX$403,12*$A28)+INDEX('2 - Distribuzione'!$CY$44:$CY$403,12*$A28) -> 7748.1747 | I28: =INDEX('3 - Accumulo'!$AD$44:$AD$403,12*$A28)+INDEX('3 - Accumulo'!$AE$44:$AE$403,12*$A28) -> 31525.745
... A46: 30 | B46: =INDEX('2 - Distribuzione'!$Z$44:$Z$403,12*$A46) -> 0 | C46: =INDEX('2 - Distribuzione'!$BJ$44:$BJ$403,12*$A46) -> 0 | D46: =INDEX('2 - Distribuzione'!$CT$44:$CT$403,12*$A46) -> 0 | E46: =INDEX('3 - Accumulo'!$Z$44:$Z$403,12*$A46) -> 0 | F46: =INDEX('2 - Distribuzione'!$AD$44:$AD$403,12*$A46)+INDEX('2 - Distribuzione'!$AE$44:$AE$403,12*$A46) -> 101441.9 | G46: =INDEX('2 - Distribuzione'!$BN$44:$BN$403,12*$A46)+INDEX('2 - Distribuzione'!$BO$44:$BO$403,12*$A46) -> 101441.9 | H46: =INDEX('2 - Distribuzione'!$CX$44:$CX$403,12*$A46)+INDEX('2 - Distribuzione'!$CY$44:$CY$403,12*$A46) -> 72537.116 | I46: =INDEX('3 - Accumulo'!$AD$44:$AD$403,12*$A46)+INDEX('3 - Accumulo'!$AE$44:$AE$403,12*$A46) -> 69240.415

Sheet 5 - Annualizzatore
A1: Dividendo mensile: rendita o capitale che torna indietro? Il caso di Renata (caso inventato e illustrativo)
A2: Caso inventato e illustrativo, non è consulenza e non è una previsione. Fotografia di ottobre 2026, regole fiscali di oggi. Prima di decidere fai i conti sul tuo caso e parlane con professionisti abilitati.
A4: Annualizzare uno stacco
A5: Stacco per periodo (%) | B5: 0.0135 | C5: Esempio: lo stacco di un mese del fondo che guardi.
A6: Periodi in un anno | B6: 12 | C6: 12 per uno stacco mensile.
A7: Annualizzato semplice (stacco per periodi) | B7: =B5*B6 -> 0.162
A8: Annualizzato composto | B8: =(1+B5)^B6-1 -> 0.17458658
A9: Rendimento nominale dell'ipotesi di base (foglio 1) | B9: ='1 - Input'!$B$30 -> 0.0506
A10: Avviso | B10: =IF(B7>2*B9,"ATTENZIONE: uno stacco non è un rendimento annuo: il prezzo scende dello stacco e il mese può non ripetersi","") -> ATTENZIONE: uno stacco non è un rendimento annuo: il prezzo scende dello stacco e il mese può non ripetersi
A12: Quanta parte della distribuzione è capitale che torna indietro
A13: Rendimento totale annuo (nominale) | B13: =B9 -> 0.0506 | C13: Per default quello dell'ipotesi di base; scrivi un'altra formula o un altro valore per un tuo caso.
A14: Distribuzione annua del fondo (foglio 1) | B14: ='1 - Input'!$B$8 -> 0.09
A15: Distribuzione che lascia fermo il prezzo (nominale) | B15: =12*(1-(1+B13)^(-1/12)) -> 0.049260046
A16: Parte della distribuzione che è capitale che torna indietro | B16: =1-B15/B14 -> 0.45266616 | C16: Lettura economica, non fiscale. Un valore negativo vuol dire che il prezzo sale. Una sola convenzione: tutto nominale.
A18: Il fisco guarda la stessa somma in modo diverso: leggi il rendiconto del fondo. Limite teorico, senza fonte per gli etf esteri per la quota Q.
