Workbook

Sheet 0 - Indice
A1: Solo obbligazioni o sessanta quaranta? Il caso di Sergio (caso inventato e illustrativo)
A2: Caso inventato e illustrativo, non è consulenza e non è una previsione. Fotografia di ottobre 2026: tassi d'asta di fine settembre 2026, regole fiscali di oggi. Prima di decidere fai i conti sul tuo caso e parlane con professionisti abilitati.
A4: Indice
A5: 0 - Indice | B5: Questo indice
A6: 1 - Caso e ipotesi | B6: Il caso di Sergio e le ipotesi (celle gialle): capitale, spesa, pesi dei portafogli, fisco, tassi d'asta di fine settembre 2026, shock
A7: 2 - Rendimenti netti | B7: Dal rendimento lordo al netto reale per classe: canone e tassi d'asta di fine settembre 2026
A8: 3 - Scenario | B8: Anno per anno: rendimenti e fattori netti dello scenario scelto
A9: 4 - Risultati | B9: Spesa massima, anni coperti, capitale, verdetto, anni di blocco dei tassi, grafico
A10: 5 - Motore | B10: Motore del calcolo, tre portafogli (non modificare)
A12: Come usare
A13: 1. Le celle GIALLE sono input — modificale coi tuoi numeri.
A14: 2. Le celle VERDI sono output — si aggiornano automaticamente.
A15: 3. Tutti i numeri di default sono al 2026 da fonti pubbliche.
A16: 4. Niente codice nascosto: l'Excel è solo formule modificabili.
A18: Fonti dati
A19: • Aste dei titoli di Stato di fine settembre 2026: Ministero dell'economia e delle finanze (P)
A20: • Indice del rendimento alto in euro: serie pubblica, valore al 15/10/2026 (P)
A21: • Storia dei rendimenti reali: base dati internazionale di lungo periodo (Jordà-Schularick-Taylor) e serie pubbliche (P)
A22: • Tassi di default e recupero: statistiche pubblicate dall'agenzia di giudizio e dall'agenzia di rating per i titoli rischiosi (P)
A23: • Fisco di ottobre 2026: D.L. 66/2014 (12,5% e 26%), D.P.R. 642/1972 (bollo), D.Lgs. 117/2026 (P); 12,5%: D.Lgs. 239/1996 art. 2, vigente fino al 31/12/2026, poi D.Lgs. 33/2025 come modificato dal D.L. 200/2025
A24: • CALCOLI MIEI (E): il caso di Sergio, la scomposizione azioni/obbligazioni, gli scenari. Gradi: P = fonte primaria, E = stima o calcolo mio. Dati storici fino al 2020
... A31: Il motore del calcolo è nel foglio 5: non modificare. Nessuna macro, solo formule.

Sheet 1 - Caso e ipotesi
A1: Solo obbligazioni o sessanta quaranta? Il caso di Sergio (caso inventato e illustrativo)
A2: Caso inventato e illustrativo, non è consulenza e non è una previsione. Fotografia di ottobre 2026: tassi d'asta di fine settembre 2026, regole fiscali di oggi. Prima di decidere fai i conti sul tuo caso e parlane con professionisti abilitati.
A4: Il caso di Sergio
A5: Età attuale | B5: 50 | C5: anni
A6: Capitale investito (X0) | B6: 1240000 | C6: € | D6: Caso inventato di Sergio
A7: Spesa annua, euro di oggi | B7: 40000 | C7: € | D7: Di cassa: l'affitto di 9.600 € è compreso
A8: Orizzonte (N, anni da 20 a 50) | B8: 40 | C8: anni | D8: Numero intero da 20 a 50
A9: Prelievo iniziale | B9: =B7/B6 -> 0.032258065 | C9: del capitale
A10: Tre portafogli (pesi, normalizzati dal motore)
A11: Pesi | B11: A: solo obbligazioni | C11: A2: con alto rendimento | D11: B: 60/40 ribilanciato
A12: Titoli di Stato | B12: 0.6 | C12: 0.45 | D12: 0.24
A13: Indicizzati | B13: 0.4 | C13: 0.4 | D13: 0.16
A14: Alto rendimento | B14: 0 | C14: 0.15 | D14: 0
A15: Azioni | B15: 0 | C15: 0 | D15: 0.6
A16: Totale pesi (deve dare 100%) | B16: =SUM(B12:B15) -> 1 | C16: =SUM(C12:C15) -> 1 | D16: =SUM(D12:D15) -> 1
A17: Ipotesi di canone (rendimenti reali lordi)
A18: Rendimento reale lordo di canone, azioni | B18: 0.04 | C18: % l'anno | D18: Scomposizione nostra: la media 60/40 resta il 3,0%
A19: Rendimento reale lordo di canone, titoli di Stato | B19: 0.015 | C19: % l'anno
A20: Rendimento reale lordo di canone, indicizzati | B20: 0.015 | C20: % l'anno
A21: Controllo: media 60/40 (0,6 azioni + 0,4 obbligazioni) | B21: =0.6*B18+0.4*B19 -> 0.03
A22: Inflazione di canone | B22: 0.02 | C22: % l'anno
A23: Fisco di ottobre 2026
A24: Aliquota su titoli di Stato e indicizzati | B24: 0.125 | C24: % | D24: D.L. 66/2014
A25: Aliquota su alto rendimento e azioni | B25: 0.26 | C25: % | D25: Sul provento netto del fondo (dopo le perdite da default)
A26: Bollo annuo sul valore | B26: 0.002 | C26: % l'anno | D26: D.P.R. 642/1972
A27: Plusvalenza latente iniziale delle azioni | B27: 0 | C27: % | D27: Da 0% a 90%: usata solo se ci sono azioni
A28: Alto rendimento
A29: Tasso di default annuo, alto rendimento | B29: 0.0299 | C29: % l'anno | D29: Media storica per l'Europa, agenzia di giudizio
A30: Recupero medio dopo il default | B30: 0.384 | C30: % | D30: Media storica, titoli senior non garantiti
A31: Costo annuo del fondo (alto rendimento) | B31: 0 | C31: % l'anno | D31: Prima dei costi del fondo; provare 0,50%
A32: Perdita annua da default (tasso × (1 − recupero)) | B32: =B29*(1-B30) -> 0.0184184 | C32: % l'anno | D32: Calcolata: non va scritta a mano
A33: Tassi d'asta di fine settembre 2026
A34: Titolo di Stato a 10 anni, nominale lordo | B34: 0.0458 | C34: % l'anno | D34: Asta di fine settembre 2026, prezzo 95,76
A35: Indicizzato a 10 anni, reale lordo | B35: 0.0242 | C35: % l'anno | D35: Asta del 24-25 settembre 2026
A36: Alto rendimento euro, rendimento effettivo | B36: 0.0655 | C36: % l'anno | D36: Indice di mercato al 15 ottobre 2026
A37: Scenario
A38: Scenario di shock (0 nessuno, 1 Italia, 2 Stati Uniti, 3 mediana) | B38: 0 | C38: 0-3 | D38: Shock = anni Settanta: inflazione alta, bond e azioni in calo
A39: Anno di inizio dello shock (t0) | B39: 1 | C39: anno | D39: Da 1 a 40
A40: Durata dello shock | B40: 10 | C40: anni
A41: Anni di tassi d'asta tenuti (K, 0 = canone) | B41: 0 | C41: anni | D41: Da 0 a 40: 10 è il caso del video
A42: Inflazione alta | B42: 0.04 | C42: % l'anno
A43: Per quanti anni (0 = mai) | B43: 0 | C43: anni
A44: Rendimento reale degli indicizzati durante lo shock | B44: 0 | C44: % l'anno | D44: Negli anni Settanta non esistevano
A45: Tabella degli shock (media geometrica 1970-79)
A46: Shock | B46: Inflazione | C46: Titoli di Stato, reale | D46: Azioni, reale
A47: Italia 1970-79 | B47: 0.12206045 | C47: -0.061581084 | D47: -0.14029178
A48: Stati Uniti 1970-79 | B48: 0.068907683 | C48: -0.013651247 | D48: -0.0089543922
A49: Mediana 15 paesi 1970-79 | B49: 0.089423559 | C49: -0.024695999 | D49: -0.017901629

Sheet 2 - Rendimenti netti
A1: Rendimenti netti per classe: dal lordo al netto reale
A2: Caso inventato e illustrativo, non è consulenza e non è una previsione. Fotografia di ottobre 2026: tassi d'asta di fine settembre 2026, regole fiscali di oggi. Prima di decidere fai i conti sul tuo caso e parlane con professionisti abilitati.
A4: Canone (rendimenti di lungo periodo)
A5: Voce | B5: Titolo di Stato | C5: Indicizzato | D5: Alto rendimento | E5: Azioni
A6: Rendimento reale lordo | B6: ='1 - Caso e ipotesi'!B19 -> 0.015 | C6: ='1 - Caso e ipotesi'!B20 -> 0.015 | D6: ='1 - Caso e ipotesi'!B19+$B$30 -> 0.034313725 | E6: ='1 - Caso e ipotesi'!B18 -> 0.04
A7: Inflazione | B7: ='1 - Caso e ipotesi'!$B$22 -> 0.02 | C7: ='1 - Caso e ipotesi'!$B$22 -> 0.02 | D7: ='1 - Caso e ipotesi'!$B$22 -> 0.02 | E7: ='1 - Caso e ipotesi'!$B$22 -> 0.02
A8: Nominale lordo (dopo costo del fondo) | B8: =(1+B6)*(1+B7)-1 -> 0.0353 | C8: =(1+C6)*(1+C7)-1 -> 0.0353 | D8: =(1+D6)*(1+D7)-1-'1 - Caso e ipotesi'!$B$31 -> 0.055 | E8: ="—" -> —
A9: Perdita da default | B9: =0 -> 0 | C9: =0 -> 0 | D9: ='1 - Caso e ipotesi'!$B$32 -> 0.0184184 | E9: ="—" -> —
A10: Nominale dopo default | B10: =B8-B9 -> 0.0353 | C10: =C8-C9 -> 0.0353 | D10: =D8-D9 -> 0.0365816 | E10: ="—" -> —
A11: Imposta | B11: ='1 - Caso e ipotesi'!$B$24*MAX(B8,0) -> 0.0044125 | C11: ='1 - Caso e ipotesi'!$B$24*MAX(C8,0) -> 0.0044125 | D11: ='1 - Caso e ipotesi'!$B$25*MAX(D10,0) -> 0.009511216 | E11: ="—" -> —
A12: Bollo sul valore | B12: ='1 - Caso e ipotesi'!$B$26*(1+B10) -> 0.0020706 | C12: ='1 - Caso e ipotesi'!$B$26*(1+C10) -> 0.0020706 | D12: ='1 - Caso e ipotesi'!$B$26*(1+D10) -> 0.0020731632 | E12: ="—" -> —
A13: Fattore netto reale g | B13: =((1+B10)-B11-B12)/(1+B7) -> 1.008644 | C13: =((1+C10)-C11-C12)/(1+C7) -> 1.008644 | D13: =((1+D10)-D11-D12)/(1+D7) -> 1.0048992 | E13: =(1+E6)*(1-'1 - Caso e ipotesi'!$B$26) -> 1.03792
A14: Rendimento netto reale | B14: =B13-1 -> 0.0086440196 | C14: =C13-1 -> 0.0086440196 | D14: =D13-1 -> 0.0048992361 | E14: =E13-1 -> 0.03792
A17: Tassi d'asta di fine settembre 2026 (anno 1, inflazione di canone)
A18: Voce | B18: Titolo di Stato | C18: Indicizzato | D18: Alto rendimento | E18: Azioni
A19: Rendimento reale lordo | B19: =(1+'1 - Caso e ipotesi'!B34)/(1+B20)-1 -> 0.025294118 | C19: ='1 - Caso e ipotesi'!B35 -> 0.0242 | D19: =(1+'1 - Caso e ipotesi'!B36)/(1+D20)-1 -> 0.044607843 | E19: ='1 - Caso e ipotesi'!B18 -> 0.04
A20: Inflazione | B20: ='1 - Caso e ipotesi'!$B$22 -> 0.02 | C20: ='1 - Caso e ipotesi'!$B$22 -> 0.02 | D20: ='1 - Caso e ipotesi'!$B$22 -> 0.02 | E20: ='1 - Caso e ipotesi'!$B$22 -> 0.02
A21: Nominale lordo (dopo costo del fondo) | B21: =(1+B19)*(1+B20)-1 -> 0.0458 | C21: =(1+C19)*(1+C20)-1 -> 0.044684 | D21: =(1+D19)*(1+D20)-1-'1 - Caso e ipotesi'!$B$31 -> 0.0655 | E21: ="—" -> —
A22: Perdita da default | B22: =0 -> 0 | C22: =0 -> 0 | D22: ='1 - Caso e ipotesi'!$B$32 -> 0.0184184 | E22: ="—" -> —
A23: Nominale dopo default | B23: =B21-B22 -> 0.0458 | C23: =C21-C22 -> 0.044684 | D23: =D21-D22 -> 0.0470816 | E23: ="—" -> —
A24: Imposta | B24: ='1 - Caso e ipotesi'!$B$24*MAX(B21,0) -> 0.005725 | C24: ='1 - Caso e ipotesi'!$B$24*MAX(C21,0) -> 0.0055855 | D24: ='1 - Caso e ipotesi'!$B$25*MAX(D23,0) -> 0.012241216 | E24: ="—" -> —
A25: Bollo sul valore | B25: ='1 - Caso e ipotesi'!$B$26*(1+B23) -> 0.0020916 | C25: ='1 - Caso e ipotesi'!$B$26*(1+C23) -> 0.002089368 | D25: ='1 - Caso e ipotesi'!$B$26*(1+D23) -> 0.0020941632 | E25: ="—" -> —
A26: Fattore netto reale g | B26: =((1+B23)-B24-B25)/(1+B20) -> 1.0176308 | C26: =((1+C23)-C24-C25)/(1+C20) -> 1.0166756 | D26: =((1+D23)-D24-D25)/(1+D20) -> 1.0124963 | E26: =(1+E19)*(1-'1 - Caso e ipotesi'!$B$26) -> 1.03792
A27: Rendimento netto reale | B27: =B26-1 -> 0.017630784 | C27: =C26-1 -> 0.01667562 | D27: =D26-1 -> 0.012496295 | E27: =E26-1 -> 0.03792
A30: Premio reale alto rendimento sul titolo di Stato | B30: =((1+'1 - Caso e ipotesi'!B36)/(1+'1 - Caso e ipotesi'!B22)-1)-((1+'1 - Caso e ipotesi'!B34)/(1+'1 - Caso e ipotesi'!B22)-1) -> 0.019313725 | C30: Misurato sul titolo di Stato di oggi: si somma al canone dei titoli di Stato (non è lo spread di mercato)
A33: Rendimenti di oggi in chiaro (punti percentuali; il bollo è arrotondato a 0,20)
A34: Voce | B34: Titolo di Stato a 10 anni | C34: Alto rendimento
A35: Rendimento lordo nominale | B35: ='1 - Caso e ipotesi'!B34 -> 0.0458 | C35: ='1 - Caso e ipotesi'!B36 -> 0.0655
A36: Perdita da default | B36: =0 -> 0 | C36: =-'1 - Caso e ipotesi'!B32 -> -0.0184184
A37: Imposta | B37: =-'1 - Caso e ipotesi'!B24*B35 -> -0.005725 | C37: =-'1 - Caso e ipotesi'!B25*(C35+C36) -> -0.012241216
A38: Bollo (0,20 sul valore, arrotondato) | B38: =-'1 - Caso e ipotesi'!B26 -> -0.002 | C38: =-'1 - Caso e ipotesi'!B26 -> -0.002
A39: Netto nominale | B39: =SUM(B35:B38) -> 0.038075 | C39: =SUM(C35:C38) -> 0.032840384
A40: Inflazione | B40: ='1 - Caso e ipotesi'!B22 -> 0.02 | C40: ='1 - Caso e ipotesi'!B22 -> 0.02
A41: Netto reale | B41: =(1+B39)/(1+B40)-1 -> 0.017720588 | C41: =(1+C39)/(1+C40)-1 -> 0.012588612
A43: Ipotesi (I): la rivalutazione del capitale degli indicizzati è tassata al 12,5% come parte del guadagno; non è letta sul testo di legge.
A44: Il motore calcola il bollo sul valore del titolo (0,2092 punti sul 4,58%): qui è arrotondato a 0,20 per leggere i conti a mente. Per il fondo l'imposta è sul provento dopo i default. Il video usa il lordo annuo 4,583% (cedola semestrale): reale 1,78. L'imposta del fondo è 1,224, a schermo 1,23 perché la cascata torni.

Sheet 3 - Scenario
A1: Scenario anno per anno: rendimenti lordi e fattori netti reali
A2: Caso inventato e illustrativo, non è consulenza e non è una previsione. Fotografia di ottobre 2026: tassi d'asta di fine settembre 2026, regole fiscali di oggi. Prima di decidere fai i conti sul tuo caso e parlane con professionisti abilitati.
A3: Cambia lo scenario nel foglio 1 (celle B38-B44): questo foglio si aggiorna e il motore (foglio 5) lo legge.
A5: t (anno) | B5: Shock (1 = sì) | C5: Inflazione | D5: Reale lordo: titoli di Stato | E5: Reale lordo: indicizzati | F5: Reale lordo: alto rendimento | G5: Reale lordo: azioni | H5: Nominale lordo: titoli di Stato | I5: Nominale lordo: indicizzati | J5: Nominale lordo: alto rendimento | K5: Dopo default: titoli di Stato | L5: Dopo default: indicizzati | M5: Dopo default: alto rendimento | N5: g netto reale: titoli di Stato | O5: g netto reale: indicizzati | P5: g netto reale: alto rendimento | Q5: g netto reale: azioni
A6: 1 | B6: =IF(AND('1 - Caso e ipotesi'!$B$38>0,A6>='1 - Caso e ipotesi'!$B$39,A6<'1 - Caso e ipotesi'!$B$39+'1 - Caso e ipotesi'!$B$40),1,0) -> 0 | C6: =IF(B6=1,INDEX('1 - Caso e ipotesi'!$B$47:$B$49,'1 - Caso e ipotesi'!$B$38),IF(A6<='1 - Caso e ipotesi'!$B$43,'1 - Caso e ipotesi'!$B$42,'1 - Caso e ipotesi'!$B$22)) -> 0.02 | D6: =IF(B6=1,INDEX('1 - Caso e ipotesi'!$C$47:$C$49,'1 - Caso e ipotesi'!$B$38),IF(A6<='1 - Caso e ipotesi'!$B$41,(1+'1 - Caso e ipotesi'!$B$34)/(1+C6)-1,'1 - Caso e ipotesi'!$B$19)) -> 0.015 | E6: =IF(B6=1,'1 - Caso e ipotesi'!$B$44,IF(A6<='1 - Caso e ipotesi'!$B$41,'1 - Caso e ipotesi'!$B$35,'1 - Caso e ipotesi'!$B$20)) -> 0.015 | F6: =IF(B6=1,INDEX('1 - Caso e ipotesi'!$C$47:$C$49,'1 - Caso e ipotesi'!$B$38)+'2 - Rendimenti netti'!$B$30,IF(A6<='1 - Caso e ipotesi'!$B$41,(1+'1 - Caso e ipotesi'!$B$36)/(1+C6)-1,'1 - Caso e ipotesi'!$B$19+'2 - Rendimenti netti'!$B$30)) -> 0.034313725 | G6: =IF(B6=1,INDEX('1 - Caso e ipotesi'!$D$47:$D$49,'1 - Caso e ipotesi'!$B$38),'1 - Caso e ipotesi'!$B$18) -> 0.04 | H6: =(1+D6)*(1+C6)-1 -> 0.0353 | I6: =(1+E6)*(1+C6)-1 -> 0.0353 | J6: =(1+F6)*(1+C6)-1-'1 - Caso e ipotesi'!$B$31 -> 0.055 | K6: =H6 -> 0.0353 | L6: =I6 -> 0.0353 | M6: =J6-'1 - Caso e ipotesi'!$B$32 -> 0.0365816 | N6: =((1+K6)-'1 - Caso e ipotesi'!$B$24*MAX(H6,0)-'1 - Caso e ipotesi'!$B$26*(1+K6))/(1+C6) -> 1.008644 | O6: =((1+L6)-'1 - Caso e ipotesi'!$B$24*MAX(I6,0)-'1 - Caso e ipotesi'!$B$26*(1+L6))/(1+C6) -> 1.008644 | P6: =((1+M6)-'1 - Caso e ipotesi'!$B$25*MAX(M6,0)-'1 - Caso e ipotesi'!$B$26*(1+M6))/(1+C6) -> 1.0048992 | Q6: =(1+G6)*(1-'1 - Caso e ipotesi'!$B$26) -> 1.03792
A7: 2 | B7: =IF(AND('1 - Caso e ipotesi'!$B$38>0,A7>='1 - Caso e ipotesi'!$B$39,A7<'1 - Caso e ipotesi'!$B$39+'1 - Caso e ipotesi'!$B$40),1,0) -> 0 | C7: =IF(B7=1,INDEX('1 - Caso e ipotesi'!$B$47:$B$49,'1 - Caso e ipotesi'!$B$38),IF(A7<='1 - Caso e ipotesi'!$B$43,'1 - Caso e ipotesi'!$B$42,'1 - Caso e ipotesi'!$B$22)) -> 0.02 | D7: =IF(B7=1,INDEX('1 - Caso e ipotesi'!$C$47:$C$49,'1 - Caso e ipotesi'!$B$38),IF(A7<='1 - Caso e ipotesi'!$B$41,(1+'1 - Caso e ipotesi'!$B$34)/(1+C7)-1,'1 - Caso e ipotesi'!$B$19)) -> 0.015 | E7: =IF(B7=1,'1 - Caso e ipotesi'!$B$44,IF(A7<='1 - Caso e ipotesi'!$B$41,'1 - Caso e ipotesi'!$B$35,'1 - Caso e ipotesi'!$B$20)) -> 0.015 | F7: =IF(B7=1,INDEX('1 - Caso e ipotesi'!$C$47:$C$49,'1 - Caso e ipotesi'!$B$38)+'2 - Rendimenti netti'!$B$30,IF(A7<='1 - Caso e ipotesi'!$B$41,(1+'1 - Caso e ipotesi'!$B$36)/(1+C7)-1,'1 - Caso e ipotesi'!$B$19+'2 - Rendimenti netti'!$B$30)) -> 0.034313725 | G7: =IF(B7=1,INDEX('1 - Caso e ipotesi'!$D$47:$D$49,'1 - Caso e ipotesi'!$B$38),'1 - Caso e ipotesi'!$B$18) -> 0.04 | H7: =(1+D7)*(1+C7)-1 -> 0.0353 | I7: =(1+E7)*(1+C7)-1 -> 0.0353 | J7: =(1+F7)*(1+C7)-1-'1 - Caso e ipotesi'!$B$31 -> 0.055 | K7: =H7 -> 0.0353 | L7: =I7 -> 0.0353 | M7: =J7-'1 - Caso e ipotesi'!$B$32 -> 0.0365816 | N7: =((1+K7)-'1 - Caso e ipotesi'!$B$24*MAX(H7,0)-'1 - Caso e ipotesi'!$B$26*(1+K7))/(1+C7) -> 1.008644 | O7: =((1+L7)-'1 - Caso e ipotesi'!$B$24*MAX(I7,0)-'1 - Caso e ipotesi'!$B$26*(1+L7))/(1+C7) -> 1.008644 | P7: =((1+M7)-'1 - Caso e ipotesi'!$B$25*MAX(M7,0)-'1 - Caso e ipotesi'!$B$26*(1+M7))/(1+C7) -> 1.0048992 | Q7: =(1+G7)*(1-'1 - Caso e ipotesi'!$B$26) -> 1.03792
A8: 3 | B8: =IF(AND('1 - Caso e ipotesi'!$B$38>0,A8>='1 - Caso e ipotesi'!$B$39,A8<'1 - Caso e ipotesi'!$B$39+'1 - Caso e ipotesi'!$B$40),1,0) -> 0 | C8: =IF(B8=1,INDEX('1 - Caso e ipotesi'!$B$47:$B$49,'1 - Caso e ipotesi'!$B$38),IF(A8<='1 - Caso e ipotesi'!$B$43,'1 - Caso e ipotesi'!$B$42,'1 - Caso e ipotesi'!$B$22)) -> 0.02 | D8: =IF(B8=1,INDEX('1 - Caso e ipotesi'!$C$47:$C$49,'1 - Caso e ipotesi'!$B$38),IF(A8<='1 - Caso e ipotesi'!$B$41,(1+'1 - Caso e ipotesi'!$B$34)/(1+C8)-1,'1 - Caso e ipotesi'!$B$19)) -> 0.015 | E8: =IF(B8=1,'1 - Caso e ipotesi'!$B$44,IF(A8<='1 - Caso e ipotesi'!$B$41,'1 - Caso e ipotesi'!$B$35,'1 - Caso e ipotesi'!$B$20)) -> 0.015 | F8: =IF(B8=1,INDEX('1 - Caso e ipotesi'!$C$47:$C$49,'1 - Caso e ipotesi'!$B$38)+'2 - Rendimenti netti'!$B$30,IF(A8<='1 - Caso e ipotesi'!$B$41,(1+'1 - Caso e ipotesi'!$B$36)/(1+C8)-1,'1 - Caso e ipotesi'!$B$19+'2 - Rendimenti netti'!$B$30)) -> 0.034313725 | G8: =IF(B8=1,INDEX('1 - Caso e ipotesi'!$D$47:$D$49,'1 - Caso e ipotesi'!$B$38),'1 - Caso e ipotesi'!$B$18) -> 0.04 | H8: =(1+D8)*(1+C8)-1 -> 0.0353 | I8: =(1+E8)*(1+C8)-1 -> 0.0353 | J8: =(1+F8)*(1+C8)-1-'1 - Caso e ipotesi'!$B$31 -> 0.055 | K8: =H8 -> 0.0353 | L8: =I8 -> 0.0353 | M8: =J8-'1 - Caso e ipotesi'!$B$32 -> 0.0365816 | N8: =((1+K8)-'1 - Caso e ipotesi'!$B$24*MAX(H8,0)-'1 - Caso e ipotesi'!$B$26*(1+K8))/(1+C8) -> 1.008644 | O8: =((1+L8)-'1 - Caso e ipotesi'!$B$24*MAX(I8,0)-'1 - Caso e ipotesi'!$B$26*(1+L8))/(1+C8) -> 1.008644 | P8: =((1+M8)-'1 - Caso e ipotesi'!$B$25*MAX(M8,0)-'1 - Caso e ipotesi'!$B$26*(1+M8))/(1+C8) -> 1.0048992 | Q8: =(1+G8)*(1-'1 - Caso e ipotesi'!$B$26) -> 1.03792
A9: 4 | B9: =IF(AND('1 - Caso e ipotesi'!$B$38>0,A9>='1 - Caso e ipotesi'!$B$39,A9<'1 - Caso e ipotesi'!$B$39+'1 - Caso e ipotesi'!$B$40),1,0) -> 0 | C9: =IF(B9=1,INDEX('1 - Caso e ipotesi'!$B$47:$B$49,'1 - Caso e ipotesi'!$B$38),IF(A9<='1 - Caso e ipotesi'!$B$43,'1 - Caso e ipotesi'!$B$42,'1 - Caso e ipotesi'!$B$22)) -> 0.02 | D9: =IF(B9=1,INDEX('1 - Caso e ipotesi'!$C$47:$C$49,'1 - Caso e ipotesi'!$B$38),IF(A9<='1 - Caso e ipotesi'!$B$41,(1+'1 - Caso e ipotesi'!$B$34)/(1+C9)-1,'1 - Caso e ipotesi'!$B$19)) -> 0.015 | E9: =IF(B9=1,'1 - Caso e ipotesi'!$B$44,IF(A9<='1 - Caso e ipotesi'!$B$41,'1 - Caso e ipotesi'!$B$35,'1 - Caso e ipotesi'!$B$20)) -> 0.015 | F9: =IF(B9=1,INDEX('1 - Caso e ipotesi'!$C$47:$C$49,'1 - Caso e ipotesi'!$B$38)+'2 - Rendimenti netti'!$B$30,IF(A9<='1 - Caso e ipotesi'!$B$41,(1+'1 - Caso e ipotesi'!$B$36)/(1+C9)-1,'1 - Caso e ipotesi'!$B$19+'2 - Rendimenti netti'!$B$30)) -> 0.034313725 | G9: =IF(B9=1,INDEX('1 - Caso e ipotesi'!$D$47:$D$49,'1 - Caso e ipotesi'!$B$38),'1 - Caso e ipotesi'!$B$18) -> 0.04 | H9: =(1+D9)*(1+C9)-1 -> 0.0353 | I9: =(1+E9)*(1+C9)-1 -> 0.0353 | J9: =(1+F9)*(1+C9)-1-'1 - Caso e ipotesi'!$B$31 -> 0.055 | K9: =H9 -> 0.0353 | L9: =I9 -> 0.0353 | M9: =J9-'1 - Caso e ipotesi'!$B$32 -> 0.0365816 | N9: =((1+K9)-'1 - Caso e ipotesi'!$B$24*MAX(H9,0)-'1 - Caso e ipotesi'!$B$26*(1+K9))/(1+C9) -> 1.008644 | O9: =((1+L9)-'1 - Caso e ipotesi'!$B$24*MAX(I9,0)-'1 - Caso e ipotesi'!$B$26*(1+L9))/(1+C9) -> 1.008644 | P9: =((1+M9)-'1 - Caso e ipotesi'!$B$25*MAX(M9,0)-'1 - Caso e ipotesi'!$B$26*(1+M9))/(1+C9) -> 1.0048992 | Q9: =(1+G9)*(1-'1 - Caso e ipotesi'!$B$26) -> 1.03792
A10: 5 | B10: =IF(AND('1 - Caso e ipotesi'!$B$38>0,A10>='1 - Caso e ipotesi'!$B$39,A10<'1 - Caso e ipotesi'!$B$39+'1 - Caso e ipotesi'!$B$40),1,0) -> 0 | C10: =IF(B10=1,INDEX('1 - Caso e ipotesi'!$B$47:$B$49,'1 - Caso e ipotesi'!$B$38),IF(A10<='1 - Caso e ipotesi'!$B$43,'1 - Caso e ipotesi'!$B$42,'1 - Caso e ipotesi'!$B$22)) -> 0.02 | D10: =IF(B10=1,INDEX('1 - Caso e ipotesi'!$C$47:$C$49,'1 - Caso e ipotesi'!$B$38),IF(A10<='1 - Caso e ipotesi'!$B$41,(1+'1 - Caso e ipotesi'!$B$34)/(1+C10)-1,'1 - Caso e ipotesi'!$B$19)) -> 0.015 | E10: =IF(B10=1,'1 - Caso e ipotesi'!$B$44,IF(A10<='1 - Caso e ipotesi'!$B$41,'1 - Caso e ipotesi'!$B$35,'1 - Caso e ipotesi'!$B$20)) -> 0.015 | F10: =IF(B10=1,INDEX('1 - Caso e ipotesi'!$C$47:$C$49,'1 - Caso e ipotesi'!$B$38)+'2 - Rendimenti netti'!$B$30,IF(A10<='1 - Caso e ipotesi'!$B$41,(1+'1 - Caso e ipotesi'!$B$36)/(1+C10)-1,'1 - Caso e ipotesi'!$B$19+'2 - Rendimenti netti'!$B$30)) -> 0.034313725 | G10: =IF(B10=1,INDEX('1 - Caso e ipotesi'!$D$47:$D$49,'1 - Caso e ipotesi'!$B$38),'1 - Caso e ipotesi'!$B$18) -> 0.04 | H10: =(1+D10)*(1+C10)-1 -> 0.0353 | I10: =(1+E10)*(1+C10)-1 -> 0.0353 | J10: =(1+F10)*(1+C10)-1-'1 - Caso e ipotesi'!$B$31 -> 0.055 | K10: =H10 -> 0.0353 | L10: =I10 -> 0.0353 | M10: =J10-'1 - Caso e ipotesi'!$B$32 -> 0.0365816 | N10: =((1+K10)-'1 - Caso e ipotesi'!$B$24*MAX(H10,0)-'1 - Caso e ipotesi'!$B$26*(1+K10))/(1+C10) -> 1.008644 | O10: =((1+L10)-'1 - Caso e ipotesi'!$B$24*MAX(I10,0)-'1 - Caso e ipotesi'!$B$26*(1+L10))/(1+C10) -> 1.008644 | P10: =((1+M10)-'1 - Caso e ipotesi'!$B$25*MAX(M10,0)-'1 - Caso e ipotesi'!$B$26*(1+M10))/(1+C10) -> 1.0048992 | Q10: =(1+G10)*(1-'1 - Caso e ipotesi'!$B$26) -> 1.03792
A11: 6 | B11: =IF(AND('1 - Caso e ipotesi'!$B$38>0,A11>='1 - Caso e ipotesi'!$B$39,A11<'1 - Caso e ipotesi'!$B$39+'1 - Caso e ipotesi'!$B$40),1,0) -> 0 | C11: =IF(B11=1,INDEX('1 - Caso e ipotesi'!$B$47:$B$49,'1 - Caso e ipotesi'!$B$38),IF(A11<='1 - Caso e ipotesi'!$B$43,'1 - Caso e ipotesi'!$B$42,'1 - Caso e ipotesi'!$B$22)) -> 0.02 | D11: =IF(B11=1,INDEX('1 - Caso e ipotesi'!$C$47:$C$49,'1 - Caso e ipotesi'!$B$38),IF(A11<='1 - Caso e ipotesi'!$B$41,(1+'1 - Caso e ipotesi'!$B$34)/(1+C11)-1,'1 - Caso e ipotesi'!$B$19)) -> 0.015 | E11: =IF(B11=1,'1 - Caso e ipotesi'!$B$44,IF(A11<='1 - Caso e ipotesi'!$B$41,'1 - Caso e ipotesi'!$B$35,'1 - Caso e ipotesi'!$B$20)) -> 0.015 | F11: =IF(B11=1,INDEX('1 - Caso e ipotesi'!$C$47:$C$49,'1 - Caso e ipotesi'!$B$38)+'2 - Rendimenti netti'!$B$30,IF(A11<='1 - Caso e ipotesi'!$B$41,(1+'1 - Caso e ipotesi'!$B$36)/(1+C11)-1,'1 - Caso e ipotesi'!$B$19+'2 - Rendimenti netti'!$B$30)) -> 0.034313725 | G11: =IF(B11=1,INDEX('1 - Caso e ipotesi'!$D$47:$D$49,'1 - Caso e ipotesi'!$B$38),'1 - Caso e ipotesi'!$B$18) -> 0.04 | H11: =(1+D11)*(1+C11)-1 -> 0.0353 | I11: =(1+E11)*(1+C11)-1 -> 0.0353 | J11: =(1+F11)*(1+C11)-1-'1 - Caso e ipotesi'!$B$31 -> 0.055 | K11: =H11 -> 0.0353 | L11: =I11 -> 0.0353 | M11: =J11-'1 - Caso e ipotesi'!$B$32 -> 0.0365816 | N11: =((1+K11)-'1 - Caso e ipotesi'!$B$24*MAX(H11,0)-'1 - Caso e ipotesi'!$B$26*(1+K11))/(1+C11) -> 1.008644 | O11: =((1+L11)-'1 - Caso e ipotesi'!$B$24*MAX(I11,0)-'1 - Caso e ipotesi'!$B$26*(1+L11))/(1+C11) -> 1.008644 | P11: =((1+M11)-'1 - Caso e ipotesi'!$B$25*MAX(M11,0)-'1 - Caso e ipotesi'!$B$26*(1+M11))/(1+C11) -> 1.0048992 | Q11: =(1+G11)*(1-'1 - Caso e ipotesi'!$B$26) -> 1.03792
A12: 7 | B12: =IF(AND('1 - Caso e ipotesi'!$B$38>0,A12>='1 - Caso e ipotesi'!$B$39,A12<'1 - Caso e ipotesi'!$B$39+'1 - Caso e ipotesi'!$B$40),1,0) -> 0 | C12: =IF(B12=1,INDEX('1 - Caso e ipotesi'!$B$47:$B$49,'1 - Caso e ipotesi'!$B$38),IF(A12<='1 - Caso e ipotesi'!$B$43,'1 - Caso e ipotesi'!$B$42,'1 - Caso e ipotesi'!$B$22)) -> 0.02 | D12: =IF(B12=1,INDEX('1 - Caso e ipotesi'!$C$47:$C$49,'1 - Caso e ipotesi'!$B$38),IF(A12<='1 - Caso e ipotesi'!$B$41,(1+'1 - Caso e ipotesi'!$B$34)/(1+C12)-1,'1 - Caso e ipotesi'!$B$19)) -> 0.015 | E12: =IF(B12=1,'1 - Caso e ipotesi'!$B$44,IF(A12<='1 - Caso e ipotesi'!$B$41,'1 - Caso e ipotesi'!$B$35,'1 - Caso e ipotesi'!$B$20)) -> 0.015 | F12: =IF(B12=1,INDEX('1 - Caso e ipotesi'!$C$47:$C$49,'1 - Caso e ipotesi'!$B$38)+'2 - Rendimenti netti'!$B$30,IF(A12<='1 - Caso e ipotesi'!$B$41,(1+'1 - Caso e ipotesi'!$B$36)/(1+C12)-1,'1 - Caso e ipotesi'!$B$19+'2 - Rendimenti netti'!$B$30)) -> 0.034313725 | G12: =IF(B12=1,INDEX('1 - Caso e ipotesi'!$D$47:$D$49,'1 - Caso e ipotesi'!$B$38),'1 - Caso e ipotesi'!$B$18) -> 0.04 | H12: =(1+D12)*(1+C12)-1 -> 0.0353 | I12: =(1+E12)*(1+C12)-1 -> 0.0353 | J12: =(1+F12)*(1+C12)-1-'1 - Caso e ipotesi'!$B$31 -> 0.055 | K12: =H12 -> 0.0353 | L12: =I12 -> 0.0353 | M12: =J12-'1 - Caso e ipotesi'!$B$32 -> 0.0365816 | N12: =((1+K12)-'1 - Caso e ipotesi'!$B$24*MAX(H12,0)-'1 - Caso e ipotesi'!$B$26*(1+K12))/(1+C12) -> 1.008644 | O12: =((1+L12)-'1 - Caso e ipotesi'!$B$24*MAX(I12,0)-'1 - Caso e ipotesi'!$B$26*(1+L12))/(1+C12) -> 1.008644 | P12: =((1+M12)-'1 - Caso e ipotesi'!$B$25*MAX(M12,0)-'1 - Caso e ipotesi'!$B$26*(1+M12))/(1+C12) -> 1.0048992 | Q12: =(1+G12)*(1-'1 - Caso e ipotesi'!$B$26) -> 1.03792
A13: 8 | B13: =IF(AND('1 - Caso e ipotesi'!$B$38>0,A13>='1 - Caso e ipotesi'!$B$39,A13<'1 - Caso e ipotesi'!$B$39+'1 - Caso e ipotesi'!$B$40),1,0) -> 0 | C13: =IF(B13=1,INDEX('1 - Caso e ipotesi'!$B$47:$B$49,'1 - Caso e ipotesi'!$B$38),IF(A13<='1 - Caso e ipotesi'!$B$43,'1 - Caso e ipotesi'!$B$42,'1 - Caso e ipotesi'!$B$22)) -> 0.02 | D13: =IF(B13=1,INDEX('1 - Caso e ipotesi'!$C$47:$C$49,'1 - Caso e ipotesi'!$B$38),IF(A13<='1 - Caso e ipotesi'!$B$41,(1+'1 - Caso e ipotesi'!$B$34)/(1+C13)-1,'1 - Caso e ipotesi'!$B$19)) -> 0.015 | E13: =IF(B13=1,'1 - Caso e ipotesi'!$B$44,IF(A13<='1 - Caso e ipotesi'!$B$41,'1 - Caso e ipotesi'!$B$35,'1 - Caso e ipotesi'!$B$20)) -> 0.015 | F13: =IF(B13=1,INDEX('1 - Caso e ipotesi'!$C$47:$C$49,'1 - Caso e ipotesi'!$B$38)+'2 - Rendimenti netti'!$B$30,IF(A13<='1 - Caso e ipotesi'!$B$41,(1+'1 - Caso e ipotesi'!$B$36)/(1+C13)-1,'1 - Caso e ipotesi'!$B$19+'2 - Rendimenti netti'!$B$30)) -> 0.034313725 | G13: =IF(B13=1,INDEX('1 - Caso e ipotesi'!$D$47:$D$49,'1 - Caso e ipotesi'!$B$38),'1 - Caso e ipotesi'!$B$18) -> 0.04 | H13: =(1+D13)*(1+C13)-1 -> 0.0353 | I13: =(1+E13)*(1+C13)-1 -> 0.0353 | J13: =(1+F13)*(1+C13)-1-'1 - Caso e ipotesi'!$B$31 -> 0.055 | K13: =H13 -> 0.0353 | L13: =I13 -> 0.0353 | M13: =J13-'1 - Caso e ipotesi'!$B$32 -> 0.0365816 | N13: =((1+K13)-'1 - Caso e ipotesi'!$B$24*MAX(H13,0)-'1 - Caso e ipotesi'!$B$26*(1+K13))/(1+C13) -> 1.008644 | O13: =((1+L13)-'1 - Caso e ipotesi'!$B$24*MAX(I13,0)-'1 - Caso e ipotesi'!$B$26*(1+L13))/(1+C13) -> 1.008644 | P13: =((1+M13)-'1 - Caso e ipotesi'!$B$25*MAX(M13,0)-'1 - Caso e ipotesi'!$B$26*(1+M13))/(1+C13) -> 1.0048992 | Q13: =(1+G13)*(1-'1 - Caso e ipotesi'!$B$26) -> 1.03792
A14: 9 | B14: =IF(AND('1 - Caso e ipotesi'!$B$38>0,A14>='1 - Caso e ipotesi'!$B$39,A14<'1 - Caso e ipotesi'!$B$39+'1 - Caso e ipotesi'!$B$40),1,0) -> 0 | C14: =IF(B14=1,INDEX('1 - Caso e ipotesi'!$B$47:$B$49,'1 - Caso e ipotesi'!$B$38),IF(A14<='1 - Caso e ipotesi'!$B$43,'1 - Caso e ipotesi'!$B$42,'1 - Caso e ipotesi'!$B$22)) -> 0.02 | D14: =IF(B14=1,INDEX('1 - Caso e ipotesi'!$C$47:$C$49,'1 - Caso e ipotesi'!$B$38),IF(A14<='1 - Caso e ipotesi'!$B$41,(1+'1 - Caso e ipotesi'!$B$34)/(1+C14)-1,'1 - Caso e ipotesi'!$B$19)) -> 0.015 | E14: =IF(B14=1,'1 - Caso e ipotesi'!$B$44,IF(A14<='1 - Caso e ipotesi'!$B$41,'1 - Caso e ipotesi'!$B$35,'1 - Caso e ipotesi'!$B$20)) -> 0.015 | F14: =IF(B14=1,INDEX('1 - Caso e ipotesi'!$C$47:$C$49,'1 - Caso e ipotesi'!$B$38)+'2 - Rendimenti netti'!$B$30,IF(A14<='1 - Caso e ipotesi'!$B$41,(1+'1 - Caso e ipotesi'!$B$36)/(1+C14)-1,'1 - Caso e ipotesi'!$B$19+'2 - Rendimenti netti'!$B$30)) -> 0.034313725 | G14: =IF(B14=1,INDEX('1 - Caso e ipotesi'!$D$47:$D$49,'1 - Caso e ipotesi'!$B$38),'1 - Caso e ipotesi'!$B$18) -> 0.04 | H14: =(1+D14)*(1+C14)-1 -> 0.0353 | I14: =(1+E14)*(1+C14)-1 -> 0.0353 | J14: =(1+F14)*(1+C14)-1-'1 - Caso e ipotesi'!$B$31 -> 0.055 | K14: =H14 -> 0.0353 | L14: =I14 -> 0.0353 | M14: =J14-'1 - Caso e ipotesi'!$B$32 -> 0.0365816 | N14: =((1+K14)-'1 - Caso e ipotesi'!$B$24*MAX(H14,0)-'1 - Caso e ipotesi'!$B$26*(1+K14))/(1+C14) -> 1.008644 | O14: =((1+L14)-'1 - Caso e ipotesi'!$B$24*MAX(I14,0)-'1 - Caso e ipotesi'!$B$26*(1+L14))/(1+C14) -> 1.008644 | P14: =((1+M14)-'1 - Caso e ipotesi'!$B$25*MAX(M14,0)-'1 - Caso e ipotesi'!$B$26*(1+M14))/(1+C14) -> 1.0048992 | Q14: =(1+G14)*(1-'1 - Caso e ipotesi'!$B$26) -> 1.03792
A15: 10 | B15: =IF(AND('1 - Caso e ipotesi'!$B$38>0,A15>='1 - Caso e ipotesi'!$B$39,A15<'1 - Caso e ipotesi'!$B$39+'1 - Caso e ipotesi'!$B$40),1,0) -> 0 | C15: =IF(B15=1,INDEX('1 - Caso e ipotesi'!$B$47:$B$49,'1 - Caso e ipotesi'!$B$38),IF(A15<='1 - Caso e ipotesi'!$B$43,'1 - Caso e ipotesi'!$B$42,'1 - Caso e ipotesi'!$B$22)) -> 0.02 | D15: =IF(B15=1,INDEX('1 - Caso e ipotesi'!$C$47:$C$49,'1 - Caso e ipotesi'!$B$38),IF(A15<='1 - Caso e ipotesi'!$B$41,(1+'1 - Caso e ipotesi'!$B$34)/(1+C15)-1,'1 - Caso e ipotesi'!$B$19)) -> 0.015 | E15: =IF(B15=1,'1 - Caso e ipotesi'!$B$44,IF(A15<='1 - Caso e ipotesi'!$B$41,'1 - Caso e ipotesi'!$B$35,'1 - Caso e ipotesi'!$B$20)) -> 0.015 | F15: =IF(B15=1,INDEX('1 - Caso e ipotesi'!$C$47:$C$49,'1 - Caso e ipotesi'!$B$38)+'2 - Rendimenti netti'!$B$30,IF(A15<='1 - Caso e ipotesi'!$B$41,(1+'1 - Caso e ipotesi'!$B$36)/(1+C15)-1,'1 - Caso e ipotesi'!$B$19+'2 - Rendimenti netti'!$B$30)) -> 0.034313725 | G15: =IF(B15=1,INDEX('1 - Caso e ipotesi'!$D$47:$D$49,'1 - Caso e ipotesi'!$B$38),'1 - Caso e ipotesi'!$B$18) -> 0.04 | H15: =(1+D15)*(1+C15)-1 -> 0.0353 | I15: =(1+E15)*(1+C15)-1 -> 0.0353 | J15: =(1+F15)*(1+C15)-1-'1 - Caso e ipotesi'!$B$31 -> 0.055 | K15: =H15 -> 0.0353 | L15: =I15 -> 0.0353 | M15: =J15-'1 - Caso e ipotesi'!$B$32 -> 0.0365816 | N15: =((1+K15)-'1 - Caso e ipotesi'!$B$24*MAX(H15,0)-'1 - Caso e ipotesi'!$B$26*(1+K15))/(1+C15) -> 1.008644 | O15: =((1+L15)-'1 - Caso e ipotesi'!$B$24*MAX(I15,0)-'1 - Caso e ipotesi'!$B$26*(1+L15))/(1+C15) -> 1.008644 | P15: =((1+M15)-'1 - Caso e ipotesi'!$B$25*MAX(M15,0)-'1 - Caso e ipotesi'!$B$26*(1+M15))/(1+C15) -> 1.0048992 | Q15: =(1+G15)*(1-'1 - Caso e ipotesi'!$B$26) -> 1.03792
A16: 11 | B16: =IF(AND('1 - Caso e ipotesi'!$B$38>0,A16>='1 - Caso e ipotesi'!$B$39,A16<'1 - Caso e ipotesi'!$B$39+'1 - Caso e ipotesi'!$B$40),1,0) -> 0 | C16: =IF(B16=1,INDEX('1 - Caso e ipotesi'!$B$47:$B$49,'1 - Caso e ipotesi'!$B$38),IF(A16<='1 - Caso e ipotesi'!$B$43,'1 - Caso e ipotesi'!$B$42,'1 - Caso e ipotesi'!$B$22)) -> 0.02 | D16: =IF(B16=1,INDEX('1 - Caso e ipotesi'!$C$47:$C$49,'1 - Caso e ipotesi'!$B$38),IF(A16<='1 - Caso e ipotesi'!$B$41,(1+'1 - Caso e ipotesi'!$B$34)/(1+C16)-1,'1 - Caso e ipotesi'!$B$19)) -> 0.015 | E16: =IF(B16=1,'1 - Caso e ipotesi'!$B$44,IF(A16<='1 - Caso e ipotesi'!$B$41,'1 - Caso e ipotesi'!$B$35,'1 - Caso e ipotesi'!$B$20)) -> 0.015 | F16: =IF(B16=1,INDEX('1 - Caso e ipotesi'!$C$47:$C$49,'1 - Caso e ipotesi'!$B$38)+'2 - Rendimenti netti'!$B$30,IF(A16<='1 - Caso e ipotesi'!$B$41,(1+'1 - Caso e ipotesi'!$B$36)/(1+C16)-1,'1 - Caso e ipotesi'!$B$19+'2 - Rendimenti netti'!$B$30)) -> 0.034313725 | G16: =IF(B16=1,INDEX('1 - Caso e ipotesi'!$D$47:$D$49,'1 - Caso e ipotesi'!$B$38),'1 - Caso e ipotesi'!$B$18) -> 0.04 | H16: =(1+D16)*(1+C16)-1 -> 0.0353 | I16: =(1+E16)*(1+C16)-1 -> 0.0353 | J16: =(1+F16)*(1+C16)-1-'1 - Caso e ipotesi'!$B$31 -> 0.055 | K16: =H16 -> 0.0353 | L16: =I16 -> 0.0353 | M16: =J16-'1 - Caso e ipotesi'!$B$32 -> 0.0365816 | N16: =((1+K16)-'1 - Caso e ipotesi'!$B$24*MAX(H16,0)-'1 - Caso e ipotesi'!$B$26*(1+K16))/(1+C16) -> 1.008644 | O16: =((1+L16)-'1 - Caso e ipotesi'!$B$24*MAX(I16,0)-'1 - Caso e ipotesi'!$B$26*(1+L16))/(1+C16) -> 1.008644 | P16: =((1+M16)-'1 - Caso e ipotesi'!$B$25*MAX(M16,0)-'1 - Caso e ipotesi'!$B$26*(1+M16))/(1+C16) -> 1.0048992 | Q16: =(1+G16)*(1-'1 - Caso e ipotesi'!$B$26) -> 1.03792
A17: 12 | B17: =IF(AND('1 - Caso e ipotesi'!$B$38>0,A17>='1 - Caso e ipotesi'!$B$39,A17<'1 - Caso e ipotesi'!$B$39+'1 - Caso e ipotesi'!$B$40),1,0) -> 0 | C17: =IF(B17=1,INDEX('1 - Caso e ipotesi'!$B$47:$B$49,'1 - Caso e ipotesi'!$B$38),IF(A17<='1 - Caso e ipotesi'!$B$43,'1 - Caso e ipotesi'!$B$42,'1 - Caso e ipotesi'!$B$22)) -> 0.02 | D17: =IF(B17=1,INDEX('1 - Caso e ipotesi'!$C$47:$C$49,'1 - Caso e ipotesi'!$B$38),IF(A17<='1 - Caso e ipotesi'!$B$41,(1+'1 - Caso e ipotesi'!$B$34)/(1+C17)-1,'1 - Caso e ipotesi'!$B$19)) -> 0.015 | E17: =IF(B17=1,'1 - Caso e ipotesi'!$B$44,IF(A17<='1 - Caso e ipotesi'!$B$41,'1 - Caso e ipotesi'!$B$35,'1 - Caso e ipotesi'!$B$20)) -> 0.015 | F17: =IF(B17=1,INDEX('1 - Caso e ipotesi'!$C$47:$C$49,'1 - Caso e ipotesi'!$B$38)+'2 - Rendimenti netti'!$B$30,IF(A17<='1 - Caso e ipotesi'!$B$41,(1+'1 - Caso e ipotesi'!$B$36)/(1+C17)-1,'1 - Caso e ipotesi'!$B$19+'2 - Rendimenti netti'!$B$30)) -> 0.034313725 | G17: =IF(B17=1,INDEX('1 - Caso e ipotesi'!$D$47:$D$49,'1 - Caso e ipotesi'!$B$38),'1 - Caso e ipotesi'!$B$18) -> 0.04 | H17: =(1+D17)*(1+C17)-1 -> 0.0353 | I17: =(1+E17)*(1+C17)-1 -> 0.0353 | J17: =(1+F17)*(1+C17)-1-'1 - Caso e ipotesi'!$B$31 -> 0.055 | K17: =H17 -> 0.0353 | L17: =I17 -> 0.0353 | M17: =J17-'1 - Caso e ipotesi'!$B$32 -> 0.0365816 | N17: =((1+K17)-'1 - Caso e ipotesi'!$B$24*MAX(H17,0)-'1 - Caso e ipotesi'!$B$26*(1+K17))/(1+C17) -> 1.008644 | O17: =((1+L17)-'1 - Caso e ipotesi'!$B$24*MAX(I17,0)-'1 - Caso e ipotesi'!$B$26*(1+L17))/(1+C17) -> 1.008644 | P17: =((1+M17)-'1 - Caso e ipotesi'!$B$25*MAX(M17,0)-'1 - Caso e ipotesi'!$B$26*(1+M17))/(1+C17) -> 1.0048992 | Q17: =(1+G17)*(1-'1 - Caso e ipotesi'!$B$26) -> 1.03792
... A55: 50 | B55: =IF(AND('1 - Caso e ipotesi'!$B$38>0,A55>='1 - Caso e ipotesi'!$B$39,A55<'1 - Caso e ipotesi'!$B$39+'1 - Caso e ipotesi'!$B$40),1,0) -> 0 | C55: =IF(B55=1,INDEX('1 - Caso e ipotesi'!$B$47:$B$49,'1 - Caso e ipotesi'!$B$38),IF(A55<='1 - Caso e ipotesi'!$B$43,'1 - Caso e ipotesi'!$B$42,'1 - Caso e ipotesi'!$B$22)) -> 0.02 | D55: =IF(B55=1,INDEX('1 - Caso e ipotesi'!$C$47:$C$49,'1 - Caso e ipotesi'!$B$38),IF(A55<='1 - Caso e ipotesi'!$B$41,(1+'1 - Caso e ipotesi'!$B$34)/(1+C55)-1,'1 - Caso e ipotesi'!$B$19)) -> 0.015 | E55: =IF(B55=1,'1 - Caso e ipotesi'!$B$44,IF(A55<='1 - Caso e ipotesi'!$B$41,'1 - Caso e ipotesi'!$B$35,'1 - Caso e ipotesi'!$B$20)) -> 0.015 | F55: =IF(B55=1,INDEX('1 - Caso e ipotesi'!$C$47:$C$49,'1 - Caso e ipotesi'!$B$38)+'2 - Rendimenti netti'!$B$30,IF(A55<='1 - Caso e ipotesi'!$B$41,(1+'1 - Caso e ipotesi'!$B$36)/(1+C55)-1,'1 - Caso e ipotesi'!$B$19+'2 - Rendimenti netti'!$B$30)) -> 0.034313725 | G55: =IF(B55=1,INDEX('1 - Caso e ipotesi'!$D$47:$D$49,'1 - Caso e ipotesi'!$B$38),'1 - Caso e ipotesi'!$B$18) -> 0.04 | H55: =(1+D55)*(1+C55)-1 -> 0.0353 | I55: =(1+E55)*(1+C55)-1 -> 0.0353 | J55: =(1+F55)*(1+C55)-1-'1 - Caso e ipotesi'!$B$31 -> 0.055 | K55: =H55 -> 0.0353 | L55: =I55 -> 0.0353 | M55: =J55-'1 - Caso e ipotesi'!$B$32 -> 0.0365816 | N55: =((1+K55)-'1 - Caso e ipotesi'!$B$24*MAX(H55,0)-'1 - Caso e ipotesi'!$B$26*(1+K55))/(1+C55) -> 1.008644 | O55: =((1+L55)-'1 - Caso e ipotesi'!$B$24*MAX(I55,0)-'1 - Caso e ipotesi'!$B$26*(1+L55))/(1+C55) -> 1.008644 | P55: =((1+M55)-'1 - Caso e ipotesi'!$B$25*MAX(M55,0)-'1 - Caso e ipotesi'!$B$26*(1+M55))/(1+C55) -> 1.0048992 | Q55: =(1+G55)*(1-'1 - Caso e ipotesi'!$B$26) -> 1.03792

Sheet 4 - Risultati
A1: Risultati: quanto si può spendere in euro di oggi, netti
A2: Caso inventato e illustrativo, non è consulenza e non è una previsione. Fotografia di ottobre 2026: tassi d'asta di fine settembre 2026, regole fiscali di oggi. Prima di decidere fai i conti sul tuo caso e parlane con professionisti abilitati.
A4: Risultati con lo scenario scelto nel foglio 1
A5: Voce | B5: A: solo obbligazioni | C5: A2: con alto rendimento | D5: B: 60/40 ribilanciato
A6: Spesa massima su N anni (euro di oggi, netti) | B6: ='5 - Motore'!B8 -> 36484.614 | C6: ='5 - Motore'!B66 -> 36112.716 | D6: ='5 - Motore'!B124 -> 44386.962
A7: In percentuale del capitale | B7: =B6/'1 - Caso e ipotesi'!$B$6 -> 0.029423076 | C7: =C6/'1 - Caso e ipotesi'!$B$6 -> 0.029123158 | D7: =D6/'1 - Caso e ipotesi'!$B$6 -> 0.035795937
A8: Differenza con la spesa di Sergio | B8: =B6-'1 - Caso e ipotesi'!$B$7 -> -3515.3855 | C8: =C6-'1 - Caso e ipotesi'!$B$7 -> -3887.2836 | D8: =D6-'1 - Caso e ipotesi'!$B$7 -> 4386.9621
A9: Anni coperti con la spesa di Sergio | B9: ='5 - Motore'!B9 -> 35 | C9: ='5 - Motore'!B67 -> 35 | D9: ='5 - Motore'!B125 -> 47
A10: Età finale | B10: ='1 - Caso e ipotesi'!$B$5+B9 -> 85 | C10: ='1 - Caso e ipotesi'!$B$5+C9 -> 85 | D10: ='1 - Caso e ipotesi'!$B$5+D9 -> 97
A11: Capitale a fine anno 10 | B11: =INDEX('5 - Motore'!O11:O60,10) -> 931934.12 | C11: =INDEX('5 - Motore'!O69:O118,10) -> 925726.04 | D11: =INDEX('5 - Motore'!O127:O176,10) -> 1122993.8
A12: Capitale a fine anno 20 | B12: =INDEX('5 - Motore'!O11:O60,20) -> 596178.9 | C12: =INDEX('5 - Motore'!O69:O118,20) -> 585107.48 | D12: =INDEX('5 - Motore'!O127:O176,20) -> 935830.13
A13: Capitale a fine anno 30 | B13: =INDEX('5 - Motore'!O11:O60,30) -> 230245.59 | C13: =INDEX('5 - Motore'!O69:O118,30) -> 215935.94 | D13: =INDEX('5 - Motore'!O127:O176,30) -> 674572.44
A14: Capitale a fine anno N | B14: =INDEX('5 - Motore'!O11:O60,'1 - Caso e ipotesi'!$B$8) -> 0 | C14: =INDEX('5 - Motore'!O69:O118,'1 - Caso e ipotesi'!$B$8) -> 0 | D14: =INDEX('5 - Motore'!O127:O176,'1 - Caso e ipotesi'!$B$8) -> 329226.09
A15: Verdetto | B15: =IF(B6>='1 - Caso e ipotesi'!$B$7,"regge","non regge") -> non regge | C15: =IF(C6>='1 - Caso e ipotesi'!$B$7,"regge","non regge") -> non regge | D15: =IF(D6>='1 - Caso e ipotesi'!$B$7,"regge","non regge") -> regge
A16: Scenario attivo | B16: =IF('1 - Caso e ipotesi'!B38>0,"Shock "&CHOOSE('1 - Caso e ipotesi'!B38,"Italia 1970-79","Stati Uniti 1970-79","mediana 15 paesi")&" dall'anno "&'1 - Caso e ipotesi'!B39,IF('1 - Caso e ipotesi'!B41>0,"Tassi d’asta di fine settembre 2026 tenuti per "&'1 - Caso e ipotesi'!B41&" anni, poi canone","Canone, nessuno shock")) -> Canone, nessuno shock
A18: Anni di tassi d'asta tenuti: spesa massima su N anni (forma chiusa, senza azioni né shock)
A19: Anni di blocco (K) | B19: A: solo obbligazioni | C19: A2: con alto rendimento | D19: Anni di blocco effettivi
A20: 0 | B20: =IF('5 - Motore'!$E$7>0,"n.d.",'1 - Caso e ipotesi'!$B$6*$B$33^$D20*$B$32^('1 - Caso e ipotesi'!$B$8-1-$D20)/(($B$32^('1 - Caso e ipotesi'!$B$8-$D20)-1)/($B$32-1)+$B$32^('1 - Caso e ipotesi'!$B$8-1-$D20)*$B$33*($B$33^$D20-1)/($B$33-1))) -> 36484.614 | C20: =IF('5 - Motore'!$E$65>0,"n.d.",'1 - Caso e ipotesi'!$B$6*$C$33^$D20*$C$32^('1 - Caso e ipotesi'!$B$8-1-$D20)/(($C$32^('1 - Caso e ipotesi'!$B$8-$D20)-1)/($C$32-1)+$C$32^('1 - Caso e ipotesi'!$B$8-1-$D20)*$C$33*($C$33^$D20-1)/($C$33-1))) -> 36112.716 | D20: =MIN(A20,'1 - Caso e ipotesi'!$B$8-1) -> 0
A21: 5 | B21: =IF('5 - Motore'!$E$7>0,"n.d.",'1 - Caso e ipotesi'!$B$6*$B$33^$D21*$B$32^('1 - Caso e ipotesi'!$B$8-1-$D21)/(($B$32^('1 - Caso e ipotesi'!$B$8-$D21)-1)/($B$32-1)+$B$32^('1 - Caso e ipotesi'!$B$8-1-$D21)*$B$33*($B$33^$D21-1)/($B$33-1))) -> 37924.844 | C21: =IF('5 - Motore'!$E$65>0,"n.d.",'1 - Caso e ipotesi'!$B$6*$C$33^$D21*$C$32^('1 - Caso e ipotesi'!$B$8-1-$D21)/(($C$32^('1 - Caso e ipotesi'!$B$8-$D21)-1)/($C$32-1)+$C$32^('1 - Caso e ipotesi'!$B$8-1-$D21)*$C$33*($C$33^$D21-1)/($C$33-1))) -> 37505.351 | D21: =MIN(A21,'1 - Caso e ipotesi'!$B$8-1) -> 5
A22: 10 | B22: =IF('5 - Motore'!$E$7>0,"n.d.",'1 - Caso e ipotesi'!$B$6*$B$33^$D22*$B$32^('1 - Caso e ipotesi'!$B$8-1-$D22)/(($B$32^('1 - Caso e ipotesi'!$B$8-$D22)-1)/($B$32-1)+$B$32^('1 - Caso e ipotesi'!$B$8-1-$D22)*$B$33*($B$33^$D22-1)/($B$33-1))) -> 39178.301 | C22: =IF('5 - Motore'!$E$65>0,"n.d.",'1 - Caso e ipotesi'!$B$6*$C$33^$D22*$C$32^('1 - Caso e ipotesi'!$B$8-1-$D22)/(($C$32^('1 - Caso e ipotesi'!$B$8-$D22)-1)/($C$32-1)+$C$32^('1 - Caso e ipotesi'!$B$8-1-$D22)*$C$33*($C$33^$D22-1)/($C$33-1))) -> 38718.555 | D22: =MIN(A22,'1 - Caso e ipotesi'!$B$8-1) -> 10
A23: 14 | B23: =IF('5 - Motore'!$E$7>0,"n.d.",'1 - Caso e ipotesi'!$B$6*$B$33^$D23*$B$32^('1 - Caso e ipotesi'!$B$8-1-$D23)/(($B$32^('1 - Caso e ipotesi'!$B$8-$D23)-1)/($B$32-1)+$B$32^('1 - Caso e ipotesi'!$B$8-1-$D23)*$B$33*($B$33^$D23-1)/($B$33-1))) -> 40036.159 | C23: =IF('5 - Motore'!$E$65>0,"n.d.",'1 - Caso e ipotesi'!$B$6*$C$33^$D23*$C$32^('1 - Caso e ipotesi'!$B$8-1-$D23)/(($C$32^('1 - Caso e ipotesi'!$B$8-$D23)-1)/($C$32-1)+$C$32^('1 - Caso e ipotesi'!$B$8-1-$D23)*$C$33*($C$33^$D23-1)/($C$33-1))) -> 39549.839 | D23: =MIN(A23,'1 - Caso e ipotesi'!$B$8-1) -> 14
A24: 15 | B24: =IF('5 - Motore'!$E$7>0,"n.d.",'1 - Caso e ipotesi'!$B$6*$B$33^$D24*$B$32^('1 - Caso e ipotesi'!$B$8-1-$D24)/(($B$32^('1 - Caso e ipotesi'!$B$8-$D24)-1)/($B$32-1)+$B$32^('1 - Caso e ipotesi'!$B$8-1-$D24)*$B$33*($B$33^$D24-1)/($B$33-1))) -> 40229.841 | C24: =IF('5 - Motore'!$E$65>0,"n.d.",'1 - Caso e ipotesi'!$B$6*$C$33^$D24*$C$32^('1 - Caso e ipotesi'!$B$8-1-$D24)/(($C$32^('1 - Caso e ipotesi'!$B$8-$D24)-1)/($C$32-1)+$C$32^('1 - Caso e ipotesi'!$B$8-1-$D24)*$C$33*($C$33^$D24-1)/($C$33-1))) -> 39737.667 | D24: =MIN(A24,'1 - Caso e ipotesi'!$B$8-1) -> 15
A25: 20 | B25: =IF('5 - Motore'!$E$7>0,"n.d.",'1 - Caso e ipotesi'!$B$6*$B$33^$D25*$B$32^('1 - Caso e ipotesi'!$B$8-1-$D25)/(($B$32^('1 - Caso e ipotesi'!$B$8-$D25)-1)/($B$32-1)+$B$32^('1 - Caso e ipotesi'!$B$8-1-$D25)*$B$33*($B$33^$D25-1)/($B$33-1))) -> 41071.931 | C25: =IF('5 - Motore'!$E$65>0,"n.d.",'1 - Caso e ipotesi'!$B$6*$C$33^$D25*$C$32^('1 - Caso e ipotesi'!$B$8-1-$D25)/(($C$32^('1 - Caso e ipotesi'!$B$8-$D25)-1)/($C$32-1)+$C$32^('1 - Caso e ipotesi'!$B$8-1-$D25)*$C$33*($C$33^$D25-1)/($C$33-1))) -> 40555.112 | D25: =MIN(A25,'1 - Caso e ipotesi'!$B$8-1) -> 20
A26: 40 | B26: =IF('5 - Motore'!$E$7>0,"n.d.",'1 - Caso e ipotesi'!$B$6*$B$33^$D26*$B$32^('1 - Caso e ipotesi'!$B$8-1-$D26)/(($B$32^('1 - Caso e ipotesi'!$B$8-$D26)-1)/($B$32-1)+$B$32^('1 - Caso e ipotesi'!$B$8-1-$D26)*$B$33*($B$33^$D26-1)/($B$33-1))) -> 42438.639 | C26: =IF('5 - Motore'!$E$65>0,"n.d.",'1 - Caso e ipotesi'!$B$6*$C$33^$D26*$C$32^('1 - Caso e ipotesi'!$B$8-1-$D26)/(($C$32^('1 - Caso e ipotesi'!$B$8-$D26)-1)/($C$32-1)+$C$32^('1 - Caso e ipotesi'!$B$8-1-$D26)*$C$33*($C$33^$D26-1)/($C$33-1))) -> 41886.568 | D26: =MIN(A26,'1 - Caso e ipotesi'!$B$8-1) -> 39
A28: Anni di blocco minimi per la spesa di Sergio | B28: =IFERROR(MATCH(1,$D$40:$D$80,0)-1,"oltre 40") -> 14 | C28: =IFERROR(MATCH(1,$E$40:$E$80,0)-1,"oltre 40") -> 17
A30: Fattori di appoggio (dal foglio 2 e dai pesi del motore)
A31: Fattore netto reale annuo | B31: A | C31: A2
A32: Canone (Kc) | B32: =SUMPRODUCT('5 - Motore'!$B$7:$D$7,'2 - Rendimenti netti'!$B$13:$D$13)/(1-'5 - Motore'!$E$7) -> 1.008644 | C32: =SUMPRODUCT('5 - Motore'!$B$65:$D$65,'2 - Rendimenti netti'!$B$13:$D$13)/(1-'5 - Motore'!$E$65) -> 1.0080823
A33: Tassi d'asta di fine settembre (Ko) | B33: =SUMPRODUCT('5 - Motore'!$B$7:$D$7,'2 - Rendimenti netti'!$B$26:$D$26)/(1-'5 - Motore'!$E$7) -> 1.0172487 | C33: =SUMPRODUCT('5 - Motore'!$B$65:$D$65,'2 - Rendimenti netti'!$B$26:$D$26)/(1-'5 - Motore'!$E$65) -> 1.0164785
A34: La forma chiusa vale solo senza azioni, senza shock e con inflazione di canone: per tutto il resto usa la tabella sopra e il foglio 5. Il confronto con lo shock si legge cambiando le celle B38 e B39 del foglio 1.
A37: Spesa massima per ogni anno di blocco da 0 a 40
A39: Anni di blocco (K) | B39: A: solo obbligazioni | C39: A2: con alto rendimento | D39: A regge la spesa (1 = sì) | E39: A2 regge la spesa (1 = sì)
A40: 0 | B40: =IF('5 - Motore'!$E$7>0,0,'1 - Caso e ipotesi'!$B$6*$B$33^MIN($A40,'1 - Caso e ipotesi'!$B$8-1)*$B$32^('1 - Caso e ipotesi'!$B$8-1-MIN($A40,'1 - Caso e ipotesi'!$B$8-1))/(($B$32^('1 - Caso e ipotesi'!$B$8-MIN($A40,'1 - Caso e ipotesi'!$B$8-1))-1)/($B$32-1)+$B$32^('1 - Caso e ipotesi'!$B$8-1-MIN($A40,'1 - Caso e ipotesi'!$B$8-1))*$B$33*($B$33^MIN($A40,'1 - Caso e ipotesi'!$B$8-1)-1)/($B$33-1))) -> 36484.614 | C40: =IF('5 - Motore'!$E$65>0,0,'1 - Caso e ipotesi'!$B$6*$C$33^MIN($A40,'1 - Caso e ipotesi'!$B$8-1)*$C$32^('1 - Caso e ipotesi'!$B$8-1-MIN($A40,'1 - Caso e ipotesi'!$B$8-1))/(($C$32^('1 - Caso e ipotesi'!$B$8-MIN($A40,'1 - Caso e ipotesi'!$B$8-1))-1)/($C$32-1)+$C$32^('1 - Caso e ipotesi'!$B$8-1-MIN($A40,'1 - Caso e ipotesi'!$B$8-1))*$C$33*($C$33^MIN($A40,'1 - Caso e ipotesi'!$B$8-1)-1)/($C$33-1))) -> 36112.716 | D40: =IF(B40>='1 - Caso e ipotesi'!$B$7,1,0) -> 0 | E40: =IF(C40>='1 - Caso e ipotesi'!$B$7,1,0) -> 0
A41: 1 | B41: =IF('5 - Motore'!$E$7>0,0,'1 - Caso e ipotesi'!$B$6*$B$33^MIN($A41,'1 - Caso e ipotesi'!$B$8-1)*$B$32^('1 - Caso e ipotesi'!$B$8-1-MIN($A41,'1 - Caso e ipotesi'!$B$8-1))/(($B$32^('1 - Caso e ipotesi'!$B$8-MIN($A41,'1 - Caso e ipotesi'!$B$8-1))-1)/($B$32-1)+$B$32^('1 - Caso e ipotesi'!$B$8-1-MIN($A41,'1 - Caso e ipotesi'!$B$8-1))*$B$33*($B$33^MIN($A41,'1 - Caso e ipotesi'!$B$8-1)-1)/($B$33-1))) -> 36786.629 | C41: =IF('5 - Motore'!$E$65>0,0,'1 - Caso e ipotesi'!$B$6*$C$33^MIN($A41,'1 - Caso e ipotesi'!$B$8-1)*$C$32^('1 - Caso e ipotesi'!$B$8-1-MIN($A41,'1 - Caso e ipotesi'!$B$8-1))/(($C$32^('1 - Caso e ipotesi'!$B$8-MIN($A41,'1 - Caso e ipotesi'!$B$8-1))-1)/($C$32-1)+$C$32^('1 - Caso e ipotesi'!$B$8-1-MIN($A41,'1 - Caso e ipotesi'!$B$8-1))*$C$33*($C$33^MIN($A41,'1 - Caso e ipotesi'!$B$8-1)-1)/($C$33-1))) -> 36404.666 | D41: =IF(B41>='1 - Caso e ipotesi'!$B$7,1,0) -> 0 | E41: =IF(C41>='1 - Caso e ipotesi'!$B$7,1,0) -> 0
A42: 2 | B42: =IF('5 - Motore'!$E$7>0,0,'1 - Caso e ipotesi'!$B$6*$B$33^MIN($A42,'1 - Caso e ipotesi'!$B$8-1)*$B$32^('1 - Caso e ipotesi'!$B$8-1-MIN($A42,'1 - Caso e ipotesi'!$B$8-1))/(($B$32^('1 - Caso e ipotesi'!$B$8-MIN($A42,'1 - Caso e ipotesi'!$B$8-1))-1)/($B$32-1)+$B$32^('1 - Caso e ipotesi'!$B$8-1-MIN($A42,'1 - Caso e ipotesi'!$B$8-1))*$B$33*($B$33^MIN($A42,'1 - Caso e ipotesi'!$B$8-1)-1)/($B$33-1))) -> 37081.844 | C42: =IF('5 - Motore'!$E$65>0,0,'1 - Caso e ipotesi'!$B$6*$C$33^MIN($A42,'1 - Caso e ipotesi'!$B$8-1)*$C$32^('1 - Caso e ipotesi'!$B$8-1-MIN($A42,'1 - Caso e ipotesi'!$B$8-1))/(($C$32^('1 - Caso e ipotesi'!$B$8-MIN($A42,'1 - Caso e ipotesi'!$B$8-1))-1)/($C$32-1)+$C$32^('1 - Caso e ipotesi'!$B$8-1-MIN($A42,'1 - Caso e ipotesi'!$B$8-1))*$C$33*($C$33^MIN($A42,'1 - Caso e ipotesi'!$B$8-1)-1)/($C$33-1))) -> 36690.08 | D42: =IF(B42>='1 - Caso e ipotesi'!$B$7,1,0) -> 0 | E42: =IF(C42>='1 - Caso e ipotesi'!$B$7,1,0) -> 0
A43: 3 | B43: =IF('5 - Motore'!$E$7>0,0,'1 - Caso e ipotesi'!$B$6*$B$33^MIN($A43,'1 - Caso e ipotesi'!$B$8-1)*$B$32^('1 - Caso e ipotesi'!$B$8-1-MIN($A43,'1 - Caso e ipotesi'!$B$8-1))/(($B$32^('1 - Caso e ipotesi'!$B$8-MIN($A43,'1 - Caso e ipotesi'!$B$8-1))-1)/($B$32-1)+$B$32^('1 - Caso e ipotesi'!$B$8-1-MIN($A43,'1 - Caso e ipotesi'!$B$8-1))*$B$33*($B$33^MIN($A43,'1 - Caso e ipotesi'!$B$8-1)-1)/($B$33-1))) -> 37370.069 | C43: =IF('5 - Motore'!$E$65>0,0,'1 - Caso e ipotesi'!$B$6*$C$33^MIN($A43,'1 - Caso e ipotesi'!$B$8-1)*$C$32^('1 - Caso e ipotesi'!$B$8-1-MIN($A43,'1 - Caso e ipotesi'!$B$8-1))/(($C$32^('1 - Caso e ipotesi'!$B$8-MIN($A43,'1 - Caso e ipotesi'!$B$8-1))-1)/($C$32-1)+$C$32^('1 - Caso e ipotesi'!$B$8-1-MIN($A43,'1 - Caso e ipotesi'!$B$8-1))*$C$33*($C$33^MIN($A43,'1 - Caso e ipotesi'!$B$8-1)-1)/($C$33-1))) -> 36968.778 | D43: =IF(B43>='1 - Caso e ipotesi'!$B$7,1,0) -> 0 | E43: =IF(C43>='1 - Caso e ipotesi'!$B$7,1,0) -> 0
A44: 4 | B44: =IF('5 - Motore'!$E$7>0,0,'1 - Caso e ipotesi'!$B$6*$B$33^MIN($A44,'1 - Caso e ipotesi'!$B$8-1)*$B$32^('1 - Caso e ipotesi'!$B$8-1-MIN($A44,'1 - Caso e ipotesi'!$B$8-1))/(($B$32^('1 - Caso e ipotesi'!$B$8-MIN($A44,'1 - Caso e ipotesi'!$B$8-1))-1)/($B$32-1)+$B$32^('1 - Caso e ipotesi'!$B$8-1-MIN($A44,'1 - Caso e ipotesi'!$B$8-1))*$B$33*($B$33^MIN($A44,'1 - Caso e ipotesi'!$B$8-1)-1)/($B$33-1))) -> 37651.125 | C44: =IF('5 - Motore'!$E$65>0,0,'1 - Caso e ipotesi'!$B$6*$C$33^MIN($A44,'1 - Caso e ipotesi'!$B$8-1)*$C$32^('1 - Caso e ipotesi'!$B$8-1-MIN($A44,'1 - Caso e ipotesi'!$B$8-1))/(($C$32^('1 - Caso e ipotesi'!$B$8-MIN($A44,'1 - Caso e ipotesi'!$B$8-1))-1)/($C$32-1)+$C$32^('1 - Caso e ipotesi'!$B$8-1-MIN($A44,'1 - Caso e ipotesi'!$B$8-1))*$C$33*($C$33^MIN($A44,'1 - Caso e ipotesi'!$B$8-1)-1)/($C$33-1))) -> 37240.588 | D44: =IF(B44>='1 - Caso e ipotesi'!$B$7,1,0) -> 0 | E44: =IF(C44>='1 - Caso e ipotesi'!$B$7,1,0) -> 0
A45: 5 | B45: =IF('5 - Motore'!$E$7>0,0,'1 - Caso e ipotesi'!$B$6*$B$33^MIN($A45,'1 - Caso e ipotesi'!$B$8-1)*$B$32^('1 - Caso e ipotesi'!$B$8-1-MIN($A45,'1 - Caso e ipotesi'!$B$8-1))/(($B$32^('1 - Caso e ipotesi'!$B$8-MIN($A45,'1 - Caso e ipotesi'!$B$8-1))-1)/($B$32-1)+$B$32^('1 - Caso e ipotesi'!$B$8-1-MIN($A45,'1 - Caso e ipotesi'!$B$8-1))*$B$33*($B$33^MIN($A45,'1 - Caso e ipotesi'!$B$8-1)-1)/($B$33-1))) -> 37924.844 | C45: =IF('5 - Motore'!$E$65>0,0,'1 - Caso e ipotesi'!$B$6*$C$33^MIN($A45,'1 - Caso e ipotesi'!$B$8-1)*$C$32^('1 - Caso e ipotesi'!$B$8-1-MIN($A45,'1 - Caso e ipotesi'!$B$8-1))/(($C$32^('1 - Caso e ipotesi'!$B$8-MIN($A45,'1 - Caso e ipotesi'!$B$8-1))-1)/($C$32-1)+$C$32^('1 - Caso e ipotesi'!$B$8-1-MIN($A45,'1 - Caso e ipotesi'!$B$8-1))*$C$33*($C$33^MIN($A45,'1 - Caso e ipotesi'!$B$8-1)-1)/($C$33-1))) -> 37505.351 | D45: =IF(B45>='1 - Caso e ipotesi'!$B$7,1,0) -> 0 | E45: =IF(C45>='1 - Caso e ipotesi'!$B$7,1,0) -> 0
A46: 6 | B46: =IF('5 - Motore'!$E$7>0,0,'1 - Caso e ipotesi'!$B$6*$B$33^MIN($A46,'1 - Caso e ipotesi'!$B$8-1)*$B$32^('1 - Caso e ipotesi'!$B$8-1-MIN($A46,'1 - Caso e ipotesi'!$B$8-1))/(($B$32^('1 - Caso e ipotesi'!$B$8-MIN($A46,'1 - Caso e ipotesi'!$B$8-1))-1)/($B$32-1)+$B$32^('1 - Caso e ipotesi'!$B$8-1-MIN($A46,'1 - Caso e ipotesi'!$B$8-1))*$B$33*($B$33^MIN($A46,'1 - Caso e ipotesi'!$B$8-1)-1)/($B$33-1))) -> 38191.069 | C46: =IF('5 - Motore'!$E$65>0,0,'1 - Caso e ipotesi'!$B$6*$C$33^MIN($A46,'1 - Caso e ipotesi'!$B$8-1)*$C$32^('1 - Caso e ipotesi'!$B$8-1-MIN($A46,'1 - Caso e ipotesi'!$B$8-1))/(($C$32^('1 - Caso e ipotesi'!$B$8-MIN($A46,'1 - Caso e ipotesi'!$B$8-1))-1)/($C$32-1)+$C$32^('1 - Caso e ipotesi'!$B$8-1-MIN($A46,'1 - Caso e ipotesi'!$B$8-1))*$C$33*($C$33^MIN($A46,'1 - Caso e ipotesi'!$B$8-1)-1)/($C$33-1))) -> 37762.915 | D46: =IF(B46>='1 - Caso e ipotesi'!$B$7,1,0) -> 0 | E46: =IF(C46>='1 - Caso e ipotesi'!$B$7,1,0) -> 0
A47: 7 | B47: =IF('5 - Motore'!$E$7>0,0,'1 - Caso e ipotesi'!$B$6*$B$33^MIN($A47,'1 - Caso e ipotesi'!$B$8-1)*$B$32^('1 - Caso e ipotesi'!$B$8-1-MIN($A47,'1 - Caso e ipotesi'!$B$8-1))/(($B$32^('1 - Caso e ipotesi'!$B$8-MIN($A47,'1 - Caso e ipotesi'!$B$8-1))-1)/($B$32-1)+$B$32^('1 - Caso e ipotesi'!$B$8-1-MIN($A47,'1 - Caso e ipotesi'!$B$8-1))*$B$33*($B$33^MIN($A47,'1 - Caso e ipotesi'!$B$8-1)-1)/($B$33-1))) -> 38449.655 | C47: =IF('5 - Motore'!$E$65>0,0,'1 - Caso e ipotesi'!$B$6*$C$33^MIN($A47,'1 - Caso e ipotesi'!$B$8-1)*$C$32^('1 - Caso e ipotesi'!$B$8-1-MIN($A47,'1 - Caso e ipotesi'!$B$8-1))/(($C$32^('1 - Caso e ipotesi'!$B$8-MIN($A47,'1 - Caso e ipotesi'!$B$8-1))-1)/($C$32-1)+$C$32^('1 - Caso e ipotesi'!$B$8-1-MIN($A47,'1 - Caso e ipotesi'!$B$8-1))*$C$33*($C$33^MIN($A47,'1 - Caso e ipotesi'!$B$8-1)-1)/($C$33-1))) -> 38013.141 | D47: =IF(B47>='1 - Caso e ipotesi'!$B$7,1,0) -> 0 | E47: =IF(C47>='1 - Caso e ipotesi'!$B$7,1,0) -> 0
A48: 8 | B48: =IF('5 - Motore'!$E$7>0,0,'1 - Caso e ipotesi'!$B$6*$B$33^MIN($A48,'1 - Caso e ipotesi'!$B$8-1)*$B$32^('1 - Caso e ipotesi'!$B$8-1-MIN($A48,'1 - Caso e ipotesi'!$B$8-1))/(($B$32^('1 - Caso e ipotesi'!$B$8-MIN($A48,'1 - Caso e ipotesi'!$B$8-1))-1)/($B$32-1)+$B$32^('1 - Caso e ipotesi'!$B$8-1-MIN($A48,'1 - Caso e ipotesi'!$B$8-1))*$B$33*($B$33^MIN($A48,'1 - Caso e ipotesi'!$B$8-1)-1)/($B$33-1))) -> 38700.468 | C48: =IF('5 - Motore'!$E$65>0,0,'1 - Caso e ipotesi'!$B$6*$C$33^MIN($A48,'1 - Caso e ipotesi'!$B$8-1)*$C$32^('1 - Caso e ipotesi'!$B$8-1-MIN($A48,'1 - Caso e ipotesi'!$B$8-1))/(($C$32^('1 - Caso e ipotesi'!$B$8-MIN($A48,'1 - Caso e ipotesi'!$B$8-1))-1)/($C$32-1)+$C$32^('1 - Caso e ipotesi'!$B$8-1-MIN($A48,'1 - Caso e ipotesi'!$B$8-1))*$C$33*($C$33^MIN($A48,'1 - Caso e ipotesi'!$B$8-1)-1)/($C$33-1))) -> 38255.899 | D48: =IF(B48>='1 - Caso e ipotesi'!$B$7,1,0) -> 0 | E48: =IF(C48>='1 - Caso e ipotesi'!$B$7,1,0) -> 0
A49: 9 | B49: =IF('5 - Motore'!$E$7>0,0,'1 - Caso e ipotesi'!$B$6*$B$33^MIN($A49,'1 - Caso e ipotesi'!$B$8-1)*$B$32^('1 - Caso e ipotesi'!$B$8-1-MIN($A49,'1 - Caso e ipotesi'!$B$8-1))/(($B$32^('1 - Caso e ipotesi'!$B$8-MIN($A49,'1 - Caso e ipotesi'!$B$8-1))-1)/($B$32-1)+$B$32^('1 - Caso e ipotesi'!$B$8-1-MIN($A49,'1 - Caso e ipotesi'!$B$8-1))*$B$33*($B$33^MIN($A49,'1 - Caso e ipotesi'!$B$8-1)-1)/($B$33-1))) -> 38943.387 | C49: =IF('5 - Motore'!$E$65>0,0,'1 - Caso e ipotesi'!$B$6*$C$33^MIN($A49,'1 - Caso e ipotesi'!$B$8-1)*$C$32^('1 - Caso e ipotesi'!$B$8-1-MIN($A49,'1 - Caso e ipotesi'!$B$8-1))/(($C$32^('1 - Caso e ipotesi'!$B$8-MIN($A49,'1 - Caso e ipotesi'!$B$8-1))-1)/($C$32-1)+$C$32^('1 - Caso e ipotesi'!$B$8-1-MIN($A49,'1 - Caso e ipotesi'!$B$8-1))*$C$33*($C$33^MIN($A49,'1 - Caso e ipotesi'!$B$8-1)-1)/($C$33-1))) -> 38491.073 | D49: =IF(B49>='1 - Caso e ipotesi'!$B$7,1,0) -> 0 | E49: =IF(C49>='1 - Caso e ipotesi'!$B$7,1,0) -> 0
A50: 10 | B50: =IF('5 - Motore'!$E$7>0,0,'1 - Caso e ipotesi'!$B$6*$B$33^MIN($A50,'1 - Caso e ipotesi'!$B$8-1)*$B$32^('1 - Caso e ipotesi'!$B$8-1-MIN($A50,'1 - Caso e ipotesi'!$B$8-1))/(($B$32^('1 - Caso e ipotesi'!$B$8-MIN($A50,'1 - Caso e ipotesi'!$B$8-1))-1)/($B$32-1)+$B$32^('1 - Caso e ipotesi'!$B$8-1-MIN($A50,'1 - Caso e ipotesi'!$B$8-1))*$B$33*($B$33^MIN($A50,'1 - Caso e ipotesi'!$B$8-1)-1)/($B$33-1))) -> 39178.301 | C50: =IF('5 - Motore'!$E$65>0,0,'1 - Caso e ipotesi'!$B$6*$C$33^MIN($A50,'1 - Caso e ipotesi'!$B$8-1)*$C$32^('1 - Caso e ipotesi'!$B$8-1-MIN($A50,'1 - Caso e ipotesi'!$B$8-1))/(($C$32^('1 - Caso e ipotesi'!$B$8-MIN($A50,'1 - Caso e ipotesi'!$B$8-1))-1)/($C$32-1)+$C$32^('1 - Caso e ipotesi'!$B$8-1-MIN($A50,'1 - Caso e ipotesi'!$B$8-1))*$C$33*($C$33^MIN($A50,'1 - Caso e ipotesi'!$B$8-1)-1)/($C$33-1))) -> 38718.555 | D50: =IF(B50>='1 - Caso e ipotesi'!$B$7,1,0) -> 0 | E50: =IF(C50>='1 - Caso e ipotesi'!$B$7,1,0) -> 0
A51: 11 | B51: =IF('5 - Motore'!$E$7>0,0,'1 - Caso e ipotesi'!$B$6*$B$33^MIN($A51,'1 - Caso e ipotesi'!$B$8-1)*$B$32^('1 - Caso e ipotesi'!$B$8-1-MIN($A51,'1 - Caso e ipotesi'!$B$8-1))/(($B$32^('1 - Caso e ipotesi'!$B$8-MIN($A51,'1 - Caso e ipotesi'!$B$8-1))-1)/($B$32-1)+$B$32^('1 - Caso e ipotesi'!$B$8-1-MIN($A51,'1 - Caso e ipotesi'!$B$8-1))*$B$33*($B$33^MIN($A51,'1 - Caso e ipotesi'!$B$8-1)-1)/($B$33-1))) -> 39405.114 | C51: =IF('5 - Motore'!$E$65>0,0,'1 - Caso e ipotesi'!$B$6*$C$33^MIN($A51,'1 - Caso e ipotesi'!$B$8-1)*$C$32^('1 - Caso e ipotesi'!$B$8-1-MIN($A51,'1 - Caso e ipotesi'!$B$8-1))/(($C$32^('1 - Caso e ipotesi'!$B$8-MIN($A51,'1 - Caso e ipotesi'!$B$8-1))-1)/($C$32-1)+$C$32^('1 - Caso e ipotesi'!$B$8-1-MIN($A51,'1 - Caso e ipotesi'!$B$8-1))*$C$33*($C$33^MIN($A51,'1 - Caso e ipotesi'!$B$8-1)-1)/($C$33-1))) -> 38938.251 | D51: =IF(B51>='1 - Caso e ipotesi'!$B$7,1,0) -> 0 | E51: =IF(C51>='1 - Caso e ipotesi'!$B$7,1,0) -> 0
... A80: 40 | B80: =IF('5 - Motore'!$E$7>0,0,'1 - Caso e ipotesi'!$B$6*$B$33^MIN($A80,'1 - Caso e ipotesi'!$B$8-1)*$B$32^('1 - Caso e ipotesi'!$B$8-1-MIN($A80,'1 - Caso e ipotesi'!$B$8-1))/(($B$32^('1 - Caso e ipotesi'!$B$8-MIN($A80,'1 - Caso e ipotesi'!$B$8-1))-1)/($B$32-1)+$B$32^('1 - Caso e ipotesi'!$B$8-1-MIN($A80,'1 - Caso e ipotesi'!$B$8-1))*$B$33*($B$33^MIN($A80,'1 - Caso e ipotesi'!$B$8-1)-1)/($B$33-1))) -> 42438.639 | C80: =IF('5 - Motore'!$E$65>0,0,'1 - Caso e ipotesi'!$B$6*$C$33^MIN($A80,'1 - Caso e ipotesi'!$B$8-1)*$C$32^('1 - Caso e ipotesi'!$B$8-1-MIN($A80,'1 - Caso e ipotesi'!$B$8-1))/(($C$32^('1 - Caso e ipotesi'!$B$8-MIN($A80,'1 - Caso e ipotesi'!$B$8-1))-1)/($C$32-1)+$C$32^('1 - Caso e ipotesi'!$B$8-1-MIN($A80,'1 - Caso e ipotesi'!$B$8-1))*$C$33*($C$33^MIN($A80,'1 - Caso e ipotesi'!$B$8-1)-1)/($C$33-1))) -> 41886.568 | D80: =IF(B80>='1 - Caso e ipotesi'!$B$7,1,0) -> 1 | E80: =IF(C80>='1 - Caso e ipotesi'!$B$7,1,0) -> 1

Sheet 5 - Motore
A1: Motore del calcolo, non modificare
A2: Caso inventato e illustrativo, non è consulenza e non è una previsione. Fotografia di ottobre 2026: tassi d'asta di fine settembre 2026, regole fiscali di oggi. Prima di decidere fai i conti sul tuo caso e parlane con professionisti abilitati.
A3: Qui non c'è nulla da inserire. Il calcolo è lineare e senza iterazioni; scelte del modello: vendita pro-rata, ribilanciamento annuo con imposta sulla plusvalenza delle azioni vendute, base di costo che segue il valore, nessuna deducibilità delle minusvalenze, nessun costo di transazione, nessuna imposta di successione.
A5: Blocco A - Solo obbligazioni
A6: Pesi normalizzati | B6: Titoli di Stato | C6: Indicizzati | D6: Alto rendimento | E6: Azioni
A7: Peso | B7: ='1 - Caso e ipotesi'!B12/SUM('1 - Caso e ipotesi'!B$12:B$15) -> 0.6 | C7: ='1 - Caso e ipotesi'!B13/SUM('1 - Caso e ipotesi'!B$12:B$15) -> 0.4 | D7: ='1 - Caso e ipotesi'!B14/SUM('1 - Caso e ipotesi'!B$12:B$15) -> 0 | E7: ='1 - Caso e ipotesi'!B15/SUM('1 - Caso e ipotesi'!B$12:B$15) -> 0
A8: Spesa massima su N anni | B8: ='1 - Caso e ipotesi'!$B$6*INDEX(J11:J60,'1 - Caso e ipotesi'!$B$8-1)/INDEX(K11:K60,'1 - Caso e ipotesi'!$B$8) -> 36484.614
A9: Anni coperti con la spesa del foglio 1 | B9: =SUM(L11:L60) -> 35
A10: t | B10: Peso azioni a inizio anno | C10: Base di costo / valore | D10: Base dopo il ribilanciamento | E10: Plusvalenza latente | F10: Imposta sulle vendite (theta) | G10: Vendita lorda per euro speso (a) | H10: Crescita titoli non azionari | I10: Crescita del portafoglio (K) | J10: P | K10: Q | L10: Regge (1 = sì) | M10: Capitale a inizio anno | N10: Vendita lorda dell'anno | O10: Capitale a fine anno
A11: 1 | B11: =$E$7 -> 0 | C11: =1-'1 - Caso e ipotesi'!$B$27 -> 1 | D11: =IF($E$7>0,IF(B11>$E$7,C11,1-(1-C11)*B11/$E$7),C11) -> 1 | E11: =MAX(0,1-C11) -> 0 | F11: ='1 - Caso e ipotesi'!$B$25*E11*B11 -> 0 | G11: =1/(1-F11) -> 1 | H11: =IF($E$7<1,($B$7*'3 - Scenario'!N6+$C$7*'3 - Scenario'!O6+$D$7*'3 - Scenario'!P6)/(1-$E$7),0) -> 1.008644 | I11: =$E$7*'3 - Scenario'!Q6+((1-$E$7)-'1 - Caso e ipotesi'!$B$25*E11*MAX(0,B11-$E$7))*H11 -> 1.008644 | J11: =I11 -> 1.008644 | K11: =G11 -> 1 | L11: =IF(M11-N11>0,1,0) -> 1 | M11: ='1 - Caso e ipotesi'!$B$6 -> 1240000 | N11: ='1 - Caso e ipotesi'!$B$7*G11 -> 40000 | O11: =IF(L11=1,(M11-N11)*I11,0) -> 1210372.8
A12: 2 | B12: =IF($E$7>0,$E$7*'3 - Scenario'!Q6/I11,0) -> 0 | C12: =IF($E$7>0,D11/((1+'3 - Scenario'!C6)*'3 - Scenario'!Q6),C11) -> 1 | D12: =IF($E$7>0,IF(B12>$E$7,C12,1-(1-C12)*B12/$E$7),C12) -> 1 | E12: =MAX(0,1-C12) -> 0 | F12: ='1 - Caso e ipotesi'!$B$25*E12*B12 -> 0 | G12: =1/(1-F12) -> 1 | H12: =IF($E$7<1,($B$7*'3 - Scenario'!N7+$C$7*'3 - Scenario'!O7+$D$7*'3 - Scenario'!P7)/(1-$E$7),0) -> 1.008644 | I12: =$E$7*'3 - Scenario'!Q7+((1-$E$7)-'1 - Caso e ipotesi'!$B$25*E12*MAX(0,B12-$E$7))*H12 -> 1.008644 | J12: =J11*I12 -> 1.0173628 | K12: =K11*I11+G12 -> 2.008644 | L12: =IF(AND(L11=1,M12-N12>0),1,0) -> 1 | M12: =O11 -> 1210372.8 | N12: ='1 - Caso e ipotesi'!$B$7*G12 -> 40000 | O12: =IF(L12=1,(M12-N12)*I12,0) -> 1180489.5
A13: 3 | B13: =IF($E$7>0,$E$7*'3 - Scenario'!Q7/I12,0) -> 0 | C13: =IF($E$7>0,D12/((1+'3 - Scenario'!C7)*'3 - Scenario'!Q7),C12) -> 1 | D13: =IF($E$7>0,IF(B13>$E$7,C13,1-(1-C13)*B13/$E$7),C13) -> 1 | E13: =MAX(0,1-C13) -> 0 | F13: ='1 - Caso e ipotesi'!$B$25*E13*B13 -> 0 | G13: =1/(1-F13) -> 1 | H13: =IF($E$7<1,($B$7*'3 - Scenario'!N8+$C$7*'3 - Scenario'!O8+$D$7*'3 - Scenario'!P8)/(1-$E$7),0) -> 1.008644 | I13: =$E$7*'3 - Scenario'!Q8+((1-$E$7)-'1 - Caso e ipotesi'!$B$25*E13*MAX(0,B13-$E$7))*H13 -> 1.008644 | J13: =J12*I13 -> 1.0261569 | K13: =K12*I12+G13 -> 3.0260068 | L13: =IF(AND(L12=1,M13-N13>0),1,0) -> 1 | M13: =O12 -> 1180489.5 | N13: ='1 - Caso e ipotesi'!$B$7*G13 -> 40000 | O13: =IF(L13=1,(M13-N13)*I13,0) -> 1150348
A14: 4 | B14: =IF($E$7>0,$E$7*'3 - Scenario'!Q8/I13,0) -> 0 | C14: =IF($E$7>0,D13/((1+'3 - Scenario'!C8)*'3 - Scenario'!Q8),C13) -> 1 | D14: =IF($E$7>0,IF(B14>$E$7,C14,1-(1-C14)*B14/$E$7),C14) -> 1 | E14: =MAX(0,1-C14) -> 0 | F14: ='1 - Caso e ipotesi'!$B$25*E14*B14 -> 0 | G14: =1/(1-F14) -> 1 | H14: =IF($E$7<1,($B$7*'3 - Scenario'!N9+$C$7*'3 - Scenario'!O9+$D$7*'3 - Scenario'!P9)/(1-$E$7),0) -> 1.008644 | I14: =$E$7*'3 - Scenario'!Q9+((1-$E$7)-'1 - Caso e ipotesi'!$B$25*E14*MAX(0,B14-$E$7))*H14 -> 1.008644 | J14: =J13*I14 -> 1.035027 | K14: =K13*I13+G14 -> 4.0521636 | L14: =IF(AND(L13=1,M14-N14>0),1,0) -> 1 | M14: =O13 -> 1150348 | N14: ='1 - Caso e ipotesi'!$B$7*G14 -> 40000 | O14: =IF(L14=1,(M14-N14)*I14,0) -> 1119945.8
A15: 5 | B15: =IF($E$7>0,$E$7*'3 - Scenario'!Q9/I14,0) -> 0 | C15: =IF($E$7>0,D14/((1+'3 - Scenario'!C9)*'3 - Scenario'!Q9),C14) -> 1 | D15: =IF($E$7>0,IF(B15>$E$7,C15,1-(1-C15)*B15/$E$7),C15) -> 1 | E15: =MAX(0,1-C15) -> 0 | F15: ='1 - Caso e ipotesi'!$B$25*E15*B15 -> 0 | G15: =1/(1-F15) -> 1 | H15: =IF($E$7<1,($B$7*'3 - Scenario'!N10+$C$7*'3 - Scenario'!O10+$D$7*'3 - Scenario'!P10)/(1-$E$7),0) -> 1.008644 | I15: =$E$7*'3 - Scenario'!Q10+((1-$E$7)-'1 - Caso e ipotesi'!$B$25*E15*MAX(0,B15-$E$7))*H15 -> 1.008644 | J15: =J14*I15 -> 1.0439738 | K15: =K14*I14+G15 -> 5.0871906 | L15: =IF(AND(L14=1,M15-N15>0),1,0) -> 1 | M15: =O14 -> 1119945.8 | N15: ='1 - Caso e ipotesi'!$B$7*G15 -> 40000 | O15: =IF(L15=1,(M15-N15)*I15,0) -> 1089280.9
A16: 6 | B16: =IF($E$7>0,$E$7*'3 - Scenario'!Q10/I15,0) -> 0 | C16: =IF($E$7>0,D15/((1+'3 - Scenario'!C10)*'3 - Scenario'!Q10),C15) -> 1 | D16: =IF($E$7>0,IF(B16>$E$7,C16,1-(1-C16)*B16/$E$7),C16) -> 1 | E16: =MAX(0,1-C16) -> 0 | F16: ='1 - Caso e ipotesi'!$B$25*E16*B16 -> 0 | G16: =1/(1-F16) -> 1 | H16: =IF($E$7<1,($B$7*'3 - Scenario'!N11+$C$7*'3 - Scenario'!O11+$D$7*'3 - Scenario'!P11)/(1-$E$7),0) -> 1.008644 | I16: =$E$7*'3 - Scenario'!Q11+((1-$E$7)-'1 - Caso e ipotesi'!$B$25*E16*MAX(0,B16-$E$7))*H16 -> 1.008644 | J16: =J15*I16 -> 1.0529979 | K16: =K15*I15+G16 -> 6.1311644 | L16: =IF(AND(L15=1,M16-N16>0),1,0) -> 1 | M16: =O15 -> 1089280.9 | N16: ='1 - Caso e ipotesi'!$B$7*G16 -> 40000 | O16: =IF(L16=1,(M16-N16)*I16,0) -> 1058350.9
A17: 7 | B17: =IF($E$7>0,$E$7*'3 - Scenario'!Q11/I16,0) -> 0 | C17: =IF($E$7>0,D16/((1+'3 - Scenario'!C11)*'3 - Scenario'!Q11),C16) -> 1 | D17: =IF($E$7>0,IF(B17>$E$7,C17,1-(1-C17)*B17/$E$7),C17) -> 1 | E17: =MAX(0,1-C17) -> 0 | F17: ='1 - Caso e ipotesi'!$B$25*E17*B17 -> 0 | G17: =1/(1-F17) -> 1 | H17: =IF($E$7<1,($B$7*'3 - Scenario'!N12+$C$7*'3 - Scenario'!O12+$D$7*'3 - Scenario'!P12)/(1-$E$7),0) -> 1.008644 | I17: =$E$7*'3 - Scenario'!Q12+((1-$E$7)-'1 - Caso e ipotesi'!$B$25*E17*MAX(0,B17-$E$7))*H17 -> 1.008644 | J17: =J16*I17 -> 1.0621 | K17: =K16*I16+G17 -> 7.1841623 | L17: =IF(AND(L16=1,M17-N17>0),1,0) -> 1 | M17: =O16 -> 1058350.9 | N17: ='1 - Caso e ipotesi'!$B$7*G17 -> 40000 | O17: =IF(L17=1,(M17-N17)*I17,0) -> 1027153.6
A18: 8 | B18: =IF($E$7>0,$E$7*'3 - Scenario'!Q12/I17,0) -> 0 | C18: =IF($E$7>0,D17/((1+'3 - Scenario'!C12)*'3 - Scenario'!Q12),C17) -> 1 | D18: =IF($E$7>0,IF(B18>$E$7,C18,1-(1-C18)*B18/$E$7),C18) -> 1 | E18: =MAX(0,1-C18) -> 0 | F18: ='1 - Caso e ipotesi'!$B$25*E18*B18 -> 0 | G18: =1/(1-F18) -> 1 | H18: =IF($E$7<1,($B$7*'3 - Scenario'!N13+$C$7*'3 - Scenario'!O13+$D$7*'3 - Scenario'!P13)/(1-$E$7),0) -> 1.008644 | I18: =$E$7*'3 - Scenario'!Q13+((1-$E$7)-'1 - Caso e ipotesi'!$B$25*E18*MAX(0,B18-$E$7))*H18 -> 1.008644 | J18: =J17*I18 -> 1.0712809 | K18: =K17*I17+G18 -> 8.2462623 | L18: =IF(AND(L17=1,M18-N18>0),1,0) -> 1 | M18: =O17 -> 1027153.6 | N18: ='1 - Caso e ipotesi'!$B$7*G18 -> 40000 | O18: =IF(L18=1,(M18-N18)*I18,0) -> 995686.53
A19: 9 | B19: =IF($E$7>0,$E$7*'3 - Scenario'!Q13/I18,0) -> 0 | C19: =IF($E$7>0,D18/((1+'3 - Scenario'!C13)*'3 - Scenario'!Q13),C18) -> 1 | D19: =IF($E$7>0,IF(B19>$E$7,C19,1-(1-C19)*B19/$E$7),C19) -> 1 | E19: =MAX(0,1-C19) -> 0 | F19: ='1 - Caso e ipotesi'!$B$25*E19*B19 -> 0 | G19: =1/(1-F19) -> 1 | H19: =IF($E$7<1,($B$7*'3 - Scenario'!N14+$C$7*'3 - Scenario'!O14+$D$7*'3 - Scenario'!P14)/(1-$E$7),0) -> 1.008644 | I19: =$E$7*'3 - Scenario'!Q14+((1-$E$7)-'1 - Caso e ipotesi'!$B$25*E19*MAX(0,B19-$E$7))*H19 -> 1.008644 | J19: =J18*I19 -> 1.080541 | K19: =K18*I18+G19 -> 9.3175432 | L19: =IF(AND(L18=1,M19-N19>0),1,0) -> 1 | M19: =O18 -> 995686.53 | N19: ='1 - Caso e ipotesi'!$B$7*G19 -> 40000 | O19: =IF(L19=1,(M19-N19)*I19,0) -> 963947.5
A20: 10 | B20: =IF($E$7>0,$E$7*'3 - Scenario'!Q14/I19,0) -> 0 | C20: =IF($E$7>0,D19/((1+'3 - Scenario'!C14)*'3 - Scenario'!Q14),C19) -> 1 | D20: =IF($E$7>0,IF(B20>$E$7,C20,1-(1-C20)*B20/$E$7),C20) -> 1 | E20: =MAX(0,1-C20) -> 0 | F20: ='1 - Caso e ipotesi'!$B$25*E20*B20 -> 0 | G20: =1/(1-F20) -> 1 | H20: =IF($E$7<1,($B$7*'3 - Scenario'!N15+$C$7*'3 - Scenario'!O15+$D$7*'3 - Scenario'!P15)/(1-$E$7),0) -> 1.008644 | I20: =$E$7*'3 - Scenario'!Q15+((1-$E$7)-'1 - Caso e ipotesi'!$B$25*E20*MAX(0,B20-$E$7))*H20 -> 1.008644 | J20: =J19*I20 -> 1.0898812 | K20: =K19*I19+G20 -> 10.398084 | L20: =IF(AND(L19=1,M20-N20>0),1,0) -> 1 | M20: =O19 -> 963947.5 | N20: ='1 - Caso e ipotesi'!$B$7*G20 -> 40000 | O20: =IF(L20=1,(M20-N20)*I20,0) -> 931934.12
A21: 11 | B21: =IF($E$7>0,$E$7*'3 - Scenario'!Q15/I20,0) -> 0 | C21: =IF($E$7>0,D20/((1+'3 - Scenario'!C15)*'3 - Scenario'!Q15),C20) -> 1 | D21: =IF($E$7>0,IF(B21>$E$7,C21,1-(1-C21)*B21/$E$7),C21) -> 1 | E21: =MAX(0,1-C21) -> 0 | F21: ='1 - Caso e ipotesi'!$B$25*E21*B21 -> 0 | G21: =1/(1-F21) -> 1 | H21: =IF($E$7<1,($B$7*'3 - Scenario'!N16+$C$7*'3 - Scenario'!O16+$D$7*'3 - Scenario'!P16)/(1-$E$7),0) -> 1.008644 | I21: =$E$7*'3 - Scenario'!Q16+((1-$E$7)-'1 - Caso e ipotesi'!$B$25*E21*MAX(0,B21-$E$7))*H21 -> 1.008644 | J21: =J20*I21 -> 1.0993022 | K21: =K20*I20+G21 -> 11.487965 | L21: =IF(AND(L20=1,M21-N21>0),1,0) -> 1 | M21: =O20 -> 931934.12 | N21: ='1 - Caso e ipotesi'!$B$7*G21 -> 40000 | O21: =IF(L21=1,(M21-N21)*I21,0) -> 899644.02
A22: 12 | B22: =IF($E$7>0,$E$7*'3 - Scenario'!Q16/I21,0) -> 0 | C22: =IF($E$7>0,D21/((1+'3 - Scenario'!C16)*'3 - Scenario'!Q16),C21) -> 1 | D22: =IF($E$7>0,IF(B22>$E$7,C22,1-(1-C22)*B22/$E$7),C22) -> 1 | E22: =MAX(0,1-C22) -> 0 | F22: ='1 - Caso e ipotesi'!$B$25*E22*B22 -> 0 | G22: =1/(1-F22) -> 1 | H22: =IF($E$7<1,($B$7*'3 - Scenario'!N17+$C$7*'3 - Scenario'!O17+$D$7*'3 - Scenario'!P17)/(1-$E$7),0) -> 1.008644 | I22: =$E$7*'3 - Scenario'!Q17+((1-$E$7)-'1 - Caso e ipotesi'!$B$25*E22*MAX(0,B22-$E$7))*H22 -> 1.008644 | J22: =J21*I22 -> 1.1088046 | K22: =K21*I21+G22 -> 12.587268 | L22: =IF(AND(L21=1,M22-N22>0),1,0) -> 1 | M22: =O21 -> 899644.02 | N22: ='1 - Caso e ipotesi'!$B$7*G22 -> 40000 | O22: =IF(L22=1,(M22-N22)*I22,0) -> 867074.8
A23: 13 | B23: =IF($E$7>0,$E$7*'3 - Scenario'!Q17/I22,0) -> 0 | C23: =IF($E$7>0,D22/((1+'3 - Scenario'!C17)*'3 - Scenario'!Q17),C22) -> 1 | D23: =IF($E$7>0,IF(B23>$E$7,C23,1-(1-C23)*B23/$E$7),C23) -> 1 | E23: =MAX(0,1-C23) -> 0 | F23: ='1 - Caso e ipotesi'!$B$25*E23*B23 -> 0 | G23: =1/(1-F23) -> 1 | H23: =IF($E$7<1,($B$7*'3 - Scenario'!N18+$C$7*'3 - Scenario'!O18+$D$7*'3 - Scenario'!P18)/(1-$E$7),0) -> 1.008644 | I23: =$E$7*'3 - Scenario'!Q18+((1-$E$7)-'1 - Caso e ipotesi'!$B$25*E23*MAX(0,B23-$E$7))*H23 -> 1.008644 | J23: =J22*I23 -> 1.1183891 | K23: =K22*I22+G23 -> 13.696072 | L23: =IF(AND(L22=1,M23-N23>0),1,0) -> 1 | M23: =O22 -> 867074.8 | N23: ='1 - Caso e ipotesi'!$B$7*G23 -> 40000 | O23: =IF(L23=1,(M23-N23)*I23,0) -> 834224.05
... A60: 50 | B60: =IF($E$7>0,$E$7*'3 - Scenario'!Q54/I59,0) -> 0 | C60: =IF($E$7>0,D59/((1+'3 - Scenario'!C54)*'3 - Scenario'!Q54),C59) -> 1 | D60: =IF($E$7>0,IF(B60>$E$7,C60,1-(1-C60)*B60/$E$7),C60) -> 1 | E60: =MAX(0,1-C60) -> 0 | F60: ='1 - Caso e ipotesi'!$B$25*E60*B60 -> 0 | G60: =1/(1-F60) -> 1 | H60: =IF($E$7<1,($B$7*'3 - Scenario'!N55+$C$7*'3 - Scenario'!O55+$D$7*'3 - Scenario'!P55)/(1-$E$7),0) -> 1.008644 | I60: =$E$7*'3 - Scenario'!Q55+((1-$E$7)-'1 - Caso e ipotesi'!$B$25*E60*MAX(0,B60-$E$7))*H60 -> 1.008644 | J60: =J59*I60 -> 1.537786 | K60: =K59*I59+G60 -> 62.214802 | L60: =IF(AND(L59=1,M60-N60>0),1,0) -> 0 | M60: =O59 -> 0 | N60: ='1 - Caso e ipotesi'!$B$7*G60 -> 40000 | O60: =IF(L60=1,(M60-N60)*I60,0) -> 0
A63: Blocco A2 - Con alto rendimento
A64: Pesi normalizzati | B64: Titoli di Stato | C64: Indicizzati | D64: Alto rendimento | E64: Azioni
A65: Peso | B65: ='1 - Caso e ipotesi'!C12/SUM('1 - Caso e ipotesi'!C$12:C$15) -> 0.45 | C65: ='1 - Caso e ipotesi'!C13/SUM('1 - Caso e ipotesi'!C$12:C$15) -> 0.4 | D65: ='1 - Caso e ipotesi'!C14/SUM('1 - Caso e ipotesi'!C$12:C$15) -> 0.15 | E65: ='1 - Caso e ipotesi'!C15/SUM('1 - Caso e ipotesi'!C$12:C$15) -> 0
A66: Spesa massima su N anni | B66: ='1 - Caso e ipotesi'!$B$6*INDEX(J69:J118,'1 - Caso e ipotesi'!$B$8-1)/INDEX(K69:K118,'1 - Caso e ipotesi'!$B$8) -> 36112.716
A67: Anni coperti con la spesa del foglio 1 | B67: =SUM(L69:L118) -> 35
A68: t | B68: Peso azioni a inizio anno | C68: Base di costo / valore | D68: Base dopo il ribilanciamento | E68: Plusvalenza latente | F68: Imposta sulle vendite (theta) | G68: Vendita lorda per euro speso (a) | H68: Crescita titoli non azionari | I68: Crescita del portafoglio (K) | J68: P | K68: Q | L68: Regge (1 = sì) | M68: Capitale a inizio anno | N68: Vendita lorda dell'anno | O68: Capitale a fine anno
A69: 1 | B69: =$E$65 -> 0 | C69: =1-'1 - Caso e ipotesi'!$B$27 -> 1 | D69: =IF($E$65>0,IF(B69>$E$65,C69,1-(1-C69)*B69/$E$65),C69) -> 1 | E69: =MAX(0,1-C69) -> 0 | F69: ='1 - Caso e ipotesi'!$B$25*E69*B69 -> 0 | G69: =1/(1-F69) -> 1 | H69: =IF($E$65<1,($B$65*'3 - Scenario'!N6+$C$65*'3 - Scenario'!O6+$D$65*'3 - Scenario'!P6)/(1-$E$65),0) -> 1.0080823 | I69: =$E$65*'3 - Scenario'!Q6+((1-$E$65)-'1 - Caso e ipotesi'!$B$25*E69*MAX(0,B69-$E$65))*H69 -> 1.0080823 | J69: =I69 -> 1.0080823 | K69: =G69 -> 1 | L69: =IF(M69-N69>0,1,0) -> 1 | M69: ='1 - Caso e ipotesi'!$B$6 -> 1240000 | N69: ='1 - Caso e ipotesi'!$B$7*G69 -> 40000 | O69: =IF(L69=1,(M69-N69)*I69,0) -> 1209698.8
A70: 2 | B70: =IF($E$65>0,$E$65*'3 - Scenario'!Q6/I69,0) -> 0 | C70: =IF($E$65>0,D69/((1+'3 - Scenario'!C6)*'3 - Scenario'!Q6),C69) -> 1 | D70: =IF($E$65>0,IF(B70>$E$65,C70,1-(1-C70)*B70/$E$65),C70) -> 1 | E70: =MAX(0,1-C70) -> 0 | F70: ='1 - Caso e ipotesi'!$B$25*E70*B70 -> 0 | G70: =1/(1-F70) -> 1 | H70: =IF($E$65<1,($B$65*'3 - Scenario'!N7+$C$65*'3 - Scenario'!O7+$D$65*'3 - Scenario'!P7)/(1-$E$65),0) -> 1.0080823 | I70: =$E$65*'3 - Scenario'!Q7+((1-$E$65)-'1 - Caso e ipotesi'!$B$25*E70*MAX(0,B70-$E$65))*H70 -> 1.0080823 | J70: =J69*I70 -> 1.0162299 | K70: =K69*I69+G70 -> 2.0080823 | L70: =IF(AND(L69=1,M70-N70>0),1,0) -> 1 | M70: =O69 -> 1209698.8 | N70: ='1 - Caso e ipotesi'!$B$7*G70 -> 40000 | O70: =IF(L70=1,(M70-N70)*I70,0) -> 1179152.6
A71: 3 | B71: =IF($E$65>0,$E$65*'3 - Scenario'!Q7/I70,0) -> 0 | C71: =IF($E$65>0,D70/((1+'3 - Scenario'!C7)*'3 - Scenario'!Q7),C70) -> 1 | D71: =IF($E$65>0,IF(B71>$E$65,C71,1-(1-C71)*B71/$E$65),C71) -> 1 | E71: =MAX(0,1-C71) -> 0 | F71: ='1 - Caso e ipotesi'!$B$25*E71*B71 -> 0 | G71: =1/(1-F71) -> 1 | H71: =IF($E$65<1,($B$65*'3 - Scenario'!N8+$C$65*'3 - Scenario'!O8+$D$65*'3 - Scenario'!P8)/(1-$E$65),0) -> 1.0080823 | I71: =$E$65*'3 - Scenario'!Q8+((1-$E$65)-'1 - Caso e ipotesi'!$B$25*E71*MAX(0,B71-$E$65))*H71 -> 1.0080823 | J71: =J70*I71 -> 1.0244434 | K71: =K70*I70+G71 -> 3.0243122 | L71: =IF(AND(L70=1,M71-N71>0),1,0) -> 1 | M71: =O70 -> 1179152.6 | N71: ='1 - Caso e ipotesi'!$B$7*G71 -> 40000 | O71: =IF(L71=1,(M71-N71)*I71,0) -> 1148359.6
A72: 4 | B72: =IF($E$65>0,$E$65*'3 - Scenario'!Q8/I71,0) -> 0 | C72: =IF($E$65>0,D71/((1+'3 - Scenario'!C8)*'3 - Scenario'!Q8),C71) -> 1 | D72: =IF($E$65>0,IF(B72>$E$65,C72,1-(1-C72)*B72/$E$65),C72) -> 1 | E72: =MAX(0,1-C72) -> 0 | F72: ='1 - Caso e ipotesi'!$B$25*E72*B72 -> 0 | G72: =1/(1-F72) -> 1 | H72: =IF($E$65<1,($B$65*'3 - Scenario'!N9+$C$65*'3 - Scenario'!O9+$D$65*'3 - Scenario'!P9)/(1-$E$65),0) -> 1.0080823 | I72: =$E$65*'3 - Scenario'!Q9+((1-$E$65)-'1 - Caso e ipotesi'!$B$25*E72*MAX(0,B72-$E$65))*H72 -> 1.0080823 | J72: =J71*I72 -> 1.0327233 | K72: =K71*I71+G72 -> 4.0487556 | L72: =IF(AND(L71=1,M72-N72>0),1,0) -> 1 | M72: =O71 -> 1148359.6 | N72: ='1 - Caso e ipotesi'!$B$7*G72 -> 40000 | O72: =IF(L72=1,(M72-N72)*I72,0) -> 1117317.7
A73: 5 | B73: =IF($E$65>0,$E$65*'3 - Scenario'!Q9/I72,0) -> 0 | C73: =IF($E$65>0,D72/((1+'3 - Scenario'!C9)*'3 - Scenario'!Q9),C72) -> 1 | D73: =IF($E$65>0,IF(B73>$E$65,C73,1-(1-C73)*B73/$E$65),C73) -> 1 | E73: =MAX(0,1-C73) -> 0 | F73: ='1 - Caso e ipotesi'!$B$25*E73*B73 -> 0 | G73: =1/(1-F73) -> 1 | H73: =IF($E$65<1,($B$65*'3 - Scenario'!N10+$C$65*'3 - Scenario'!O10+$D$65*'3 - Scenario'!P10)/(1-$E$65),0) -> 1.0080823 | I73: =$E$65*'3 - Scenario'!Q10+((1-$E$65)-'1 - Caso e ipotesi'!$B$25*E73*MAX(0,B73-$E$65))*H73 -> 1.0080823 | J73: =J72*I73 -> 1.04107 | K73: =K72*I72+G73 -> 5.0814789 | L73: =IF(AND(L72=1,M73-N73>0),1,0) -> 1 | M73: =O72 -> 1117317.7 | N73: ='1 - Caso e ipotesi'!$B$7*G73 -> 40000 | O73: =IF(L73=1,(M73-N73)*I73,0) -> 1086024.9
A74: 6 | B74: =IF($E$65>0,$E$65*'3 - Scenario'!Q10/I73,0) -> 0 | C74: =IF($E$65>0,D73/((1+'3 - Scenario'!C10)*'3 - Scenario'!Q10),C73) -> 1 | D74: =IF($E$65>0,IF(B74>$E$65,C74,1-(1-C74)*B74/$E$65),C74) -> 1 | E74: =MAX(0,1-C74) -> 0 | F74: ='1 - Caso e ipotesi'!$B$25*E74*B74 -> 0 | G74: =1/(1-F74) -> 1 | H74: =IF($E$65<1,($B$65*'3 - Scenario'!N11+$C$65*'3 - Scenario'!O11+$D$65*'3 - Scenario'!P11)/(1-$E$65),0) -> 1.0080823 | I74: =$E$65*'3 - Scenario'!Q11+((1-$E$65)-'1 - Caso e ipotesi'!$B$25*E74*MAX(0,B74-$E$65))*H74 -> 1.0080823 | J74: =J73*I74 -> 1.0494843 | K74: =K73*I73+G74 -> 6.1225489 | L74: =IF(AND(L73=1,M74-N74>0),1,0) -> 1 | M74: =O73 -> 1086024.9 | N74: ='1 - Caso e ipotesi'!$B$7*G74 -> 40000 | O74: =IF(L74=1,(M74-N74)*I74,0) -> 1054479.2
A75: 7 | B75: =IF($E$65>0,$E$65*'3 - Scenario'!Q11/I74,0) -> 0 | C75: =IF($E$65>0,D74/((1+'3 - Scenario'!C11)*'3 - Scenario'!Q11),C74) -> 1 | D75: =IF($E$65>0,IF(B75>$E$65,C75,1-(1-C75)*B75/$E$65),C75) -> 1 | E75: =MAX(0,1-C75) -> 0 | F75: ='1 - Caso e ipotesi'!$B$25*E75*B75 -> 0 | G75: =1/(1-F75) -> 1 | H75: =IF($E$65<1,($B$65*'3 - Scenario'!N12+$C$65*'3 - Scenario'!O12+$D$65*'3 - Scenario'!P12)/(1-$E$65),0) -> 1.0080823 | I75: =$E$65*'3 - Scenario'!Q12+((1-$E$65)-'1 - Caso e ipotesi'!$B$25*E75*MAX(0,B75-$E$65))*H75 -> 1.0080823 | J75: =J74*I75 -> 1.0579665 | K75: =K74*I74+G75 -> 7.1720332 | L75: =IF(AND(L74=1,M75-N75>0),1,0) -> 1 | M75: =O74 -> 1054479.2 | N75: ='1 - Caso e ipotesi'!$B$7*G75 -> 40000 | O75: =IF(L75=1,(M75-N75)*I75,0) -> 1022678.5
A76: 8 | B76: =IF($E$65>0,$E$65*'3 - Scenario'!Q12/I75,0) -> 0 | C76: =IF($E$65>0,D75/((1+'3 - Scenario'!C12)*'3 - Scenario'!Q12),C75) -> 1 | D76: =IF($E$65>0,IF(B76>$E$65,C76,1-(1-C76)*B76/$E$65),C76) -> 1 | E76: =MAX(0,1-C76) -> 0 | F76: ='1 - Caso e ipotesi'!$B$25*E76*B76 -> 0 | G76: =1/(1-F76) -> 1 | H76: =IF($E$65<1,($B$65*'3 - Scenario'!N13+$C$65*'3 - Scenario'!O13+$D$65*'3 - Scenario'!P13)/(1-$E$65),0) -> 1.0080823 | I76: =$E$65*'3 - Scenario'!Q13+((1-$E$65)-'1 - Caso e ipotesi'!$B$25*E76*MAX(0,B76-$E$65))*H76 -> 1.0080823 | J76: =J75*I76 -> 1.0665173 | K76: =K75*I75+G76 -> 8.2299998 | L76: =IF(AND(L75=1,M76-N76>0),1,0) -> 1 | M76: =O75 -> 1022678.5 | N76: ='1 - Caso e ipotesi'!$B$7*G76 -> 40000 | O76: =IF(L76=1,(M76-N76)*I76,0) -> 990620.82
A77: 9 | B77: =IF($E$65>0,$E$65*'3 - Scenario'!Q13/I76,0) -> 0 | C77: =IF($E$65>0,D76/((1+'3 - Scenario'!C13)*'3 - Scenario'!Q13),C76) -> 1 | D77: =IF($E$65>0,IF(B77>$E$65,C77,1-(1-C77)*B77/$E$65),C77) -> 1 | E77: =MAX(0,1-C77) -> 0 | F77: ='1 - Caso e ipotesi'!$B$25*E77*B77 -> 0 | G77: =1/(1-F77) -> 1 | H77: =IF($E$65<1,($B$65*'3 - Scenario'!N14+$C$65*'3 - Scenario'!O14+$D$65*'3 - Scenario'!P14)/(1-$E$65),0) -> 1.0080823 | I77: =$E$65*'3 - Scenario'!Q14+((1-$E$65)-'1 - Caso e ipotesi'!$B$25*E77*MAX(0,B77-$E$65))*H77 -> 1.0080823 | J77: =J76*I77 -> 1.0751373 | K77: =K76*I76+G77 -> 9.2965171 | L77: =IF(AND(L76=1,M77-N77>0),1,0) -> 1 | M77: =O76 -> 990620.82 | N77: ='1 - Caso e ipotesi'!$B$7*G77 -> 40000 | O77: =IF(L77=1,(M77-N77)*I77,0) -> 958304.03
A78: 10 | B78: =IF($E$65>0,$E$65*'3 - Scenario'!Q14/I77,0) -> 0 | C78: =IF($E$65>0,D77/((1+'3 - Scenario'!C14)*'3 - Scenario'!Q14),C77) -> 1 | D78: =IF($E$65>0,IF(B78>$E$65,C78,1-(1-C78)*B78/$E$65),C78) -> 1 | E78: =MAX(0,1-C78) -> 0 | F78: ='1 - Caso e ipotesi'!$B$25*E78*B78 -> 0 | G78: =1/(1-F78) -> 1 | H78: =IF($E$65<1,($B$65*'3 - Scenario'!N15+$C$65*'3 - Scenario'!O15+$D$65*'3 - Scenario'!P15)/(1-$E$65),0) -> 1.0080823 | I78: =$E$65*'3 - Scenario'!Q15+((1-$E$65)-'1 - Caso e ipotesi'!$B$25*E78*MAX(0,B78-$E$65))*H78 -> 1.0080823 | J78: =J77*I78 -> 1.0838268 | K78: =K77*I77+G78 -> 10.371654 | L78: =IF(AND(L77=1,M78-N78>0),1,0) -> 1 | M78: =O77 -> 958304.03 | N78: ='1 - Caso e ipotesi'!$B$7*G78 -> 40000 | O78: =IF(L78=1,(M78-N78)*I78,0) -> 925726.04
A79: 11 | B79: =IF($E$65>0,$E$65*'3 - Scenario'!Q15/I78,0) -> 0 | C79: =IF($E$65>0,D78/((1+'3 - Scenario'!C15)*'3 - Scenario'!Q15),C78) -> 1 | D79: =IF($E$65>0,IF(B79>$E$65,C79,1-(1-C79)*B79/$E$65),C79) -> 1 | E79: =MAX(0,1-C79) -> 0 | F79: ='1 - Caso e ipotesi'!$B$25*E79*B79 -> 0 | G79: =1/(1-F79) -> 1 | H79: =IF($E$65<1,($B$65*'3 - Scenario'!N16+$C$65*'3 - Scenario'!O16+$D$65*'3 - Scenario'!P16)/(1-$E$65),0) -> 1.0080823 | I79: =$E$65*'3 - Scenario'!Q16+((1-$E$65)-'1 - Caso e ipotesi'!$B$25*E79*MAX(0,B79-$E$65))*H79 -> 1.0080823 | J79: =J78*I79 -> 1.0925867 | K79: =K78*I78+G79 -> 11.455481 | L79: =IF(AND(L78=1,M79-N79>0),1,0) -> 1 | M79: =O78 -> 925726.04 | N79: ='1 - Caso e ipotesi'!$B$7*G79 -> 40000 | O79: =IF(L79=1,(M79-N79)*I79,0) -> 892884.74
A80: 12 | B80: =IF($E$65>0,$E$65*'3 - Scenario'!Q16/I79,0) -> 0 | C80: =IF($E$65>0,D79/((1+'3 - Scenario'!C16)*'3 - Scenario'!Q16),C79) -> 1 | D80: =IF($E$65>0,IF(B80>$E$65,C80,1-(1-C80)*B80/$E$65),C80) -> 1 | E80: =MAX(0,1-C80) -> 0 | F80: ='1 - Caso e ipotesi'!$B$25*E80*B80 -> 0 | G80: =1/(1-F80) -> 1 | H80: =IF($E$65<1,($B$65*'3 - Scenario'!N17+$C$65*'3 - Scenario'!O17+$D$65*'3 - Scenario'!P17)/(1-$E$65),0) -> 1.0080823 | I80: =$E$65*'3 - Scenario'!Q17+((1-$E$65)-'1 - Caso e ipotesi'!$B$25*E80*MAX(0,B80-$E$65))*H80 -> 1.0080823 | J80: =J79*I80 -> 1.1014173 | K80: =K79*I79+G80 -> 12.548068 | L80: =IF(AND(L79=1,M80-N80>0),1,0) -> 1 | M80: =O79 -> 892884.74 | N80: ='1 - Caso e ipotesi'!$B$7*G80 -> 40000 | O80: =IF(L80=1,(M80-N80)*I80,0) -> 859778.01
A81: 13 | B81: =IF($E$65>0,$E$65*'3 - Scenario'!Q17/I80,0) -> 0 | C81: =IF($E$65>0,D80/((1+'3 - Scenario'!C17)*'3 - Scenario'!Q17),C80) -> 1 | D81: =IF($E$65>0,IF(B81>$E$65,C81,1-(1-C81)*B81/$E$65),C81) -> 1 | E81: =MAX(0,1-C81) -> 0 | F81: ='1 - Caso e ipotesi'!$B$25*E81*B81 -> 0 | G81: =1/(1-F81) -> 1 | H81: =IF($E$65<1,($B$65*'3 - Scenario'!N18+$C$65*'3 - Scenario'!O18+$D$65*'3 - Scenario'!P18)/(1-$E$65),0) -> 1.0080823 | I81: =$E$65*'3 - Scenario'!Q18+((1-$E$65)-'1 - Caso e ipotesi'!$B$25*E81*MAX(0,B81-$E$65))*H81 -> 1.0080823 | J81: =J80*I81 -> 1.1103193 | K81: =K80*I80+G81 -> 13.649485 | L81: =IF(AND(L80=1,M81-N81>0),1,0) -> 1 | M81: =O80 -> 859778.01 | N81: ='1 - Caso e ipotesi'!$B$7*G81 -> 40000 | O81: =IF(L81=1,(M81-N81)*I81,0) -> 826403.71
... A118: 50 | B118: =IF($E$65>0,$E$65*'3 - Scenario'!Q54/I117,0) -> 0 | C118: =IF($E$65>0,D117/((1+'3 - Scenario'!C54)*'3 - Scenario'!Q54),C117) -> 1 | D118: =IF($E$65>0,IF(B118>$E$65,C118,1-(1-C118)*B118/$E$65),C118) -> 1 | E118: =MAX(0,1-C118) -> 0 | F118: ='1 - Caso e ipotesi'!$B$25*E118*B118 -> 0 | G118: =1/(1-F118) -> 1 | H118: =IF($E$65<1,($B$65*'3 - Scenario'!N55+$C$65*'3 - Scenario'!O55+$D$65*'3 - Scenario'!P55)/(1-$E$65),0) -> 1.0080823 | I118: =$E$65*'3 - Scenario'!Q55+((1-$E$65)-'1 - Caso e ipotesi'!$B$25*E118*MAX(0,B118-$E$65))*H118 -> 1.0080823 | J118: =J117*I118 -> 1.4955451 | K118: =K117*I117+G118 -> 61.312371 | L118: =IF(AND(L117=1,M118-N118>0),1,0) -> 0 | M118: =O117 -> 0 | N118: ='1 - Caso e ipotesi'!$B$7*G118 -> 40000 | O118: =IF(L118=1,(M118-N118)*I118,0) -> 0
A121: Blocco B - Sessanta quaranta ribilanciato
A122: Pesi normalizzati | B122: Titoli di Stato | C122: Indicizzati | D122: Alto rendimento | E122: Azioni
A123: Peso | B123: ='1 - Caso e ipotesi'!D12/SUM('1 - Caso e ipotesi'!D$12:D$15) -> 0.24 | C123: ='1 - Caso e ipotesi'!D13/SUM('1 - Caso e ipotesi'!D$12:D$15) -> 0.16 | D123: ='1 - Caso e ipotesi'!D14/SUM('1 - Caso e ipotesi'!D$12:D$15) -> 0 | E123: ='1 - Caso e ipotesi'!D15/SUM('1 - Caso e ipotesi'!D$12:D$15) -> 0.6
A124: Spesa massima su N anni | B124: ='1 - Caso e ipotesi'!$B$6*INDEX(J127:J176,'1 - Caso e ipotesi'!$B$8-1)/INDEX(K127:K176,'1 - Caso e ipotesi'!$B$8) -> 44386.962
A125: Anni coperti con la spesa del foglio 1 | B125: =SUM(L127:L176) -> 47
A126: t | B126: Peso azioni a inizio anno | C126: Base di costo / valore | D126: Base dopo il ribilanciamento | E126: Plusvalenza latente | F126: Imposta sulle vendite (theta) | G126: Vendita lorda per euro speso (a) | H126: Crescita titoli non azionari | I126: Crescita del portafoglio (K) | J126: P | K126: Q | L126: Regge (1 = sì) | M126: Capitale a inizio anno | N126: Vendita lorda dell'anno | O126: Capitale a fine anno
A127: 1 | B127: =$E$123 -> 0.6 | C127: =1-'1 - Caso e ipotesi'!$B$27 -> 1 | D127: =IF($E$123>0,IF(B127>$E$123,C127,1-(1-C127)*B127/$E$123),C127) -> 1 | E127: =MAX(0,1-C127) -> 0 | F127: ='1 - Caso e ipotesi'!$B$25*E127*B127 -> 0 | G127: =1/(1-F127) -> 1 | H127: =IF($E$123<1,($B$123*'3 - Scenario'!N6+$C$123*'3 - Scenario'!O6+$D$123*'3 - Scenario'!P6)/(1-$E$123),0) -> 1.008644 | I127: =$E$123*'3 - Scenario'!Q6+((1-$E$123)-'1 - Caso e ipotesi'!$B$25*E127*MAX(0,B127-$E$123))*H127 -> 1.0262096 | J127: =I127 -> 1.0262096 | K127: =G127 -> 1 | L127: =IF(M127-N127>0,1,0) -> 1 | M127: ='1 - Caso e ipotesi'!$B$6 -> 1240000 | N127: ='1 - Caso e ipotesi'!$B$7*G127 -> 40000 | O127: =IF(L127=1,(M127-N127)*I127,0) -> 1231451.5
A128: 2 | B128: =IF($E$123>0,$E$123*'3 - Scenario'!Q6/I127,0) -> 0.60684678 | C128: =IF($E$123>0,D127/((1+'3 - Scenario'!C6)*'3 - Scenario'!Q6),C127) -> 0.94457391 | D128: =IF($E$123>0,IF(B128>$E$123,C128,1-(1-C128)*B128/$E$123),C128) -> 0.94457391 | E128: =MAX(0,1-C128) -> 0.055426086 | F128: ='1 - Caso e ipotesi'!$B$25*E128*B128 -> 0.0087451369 | G128: =1/(1-F128) -> 1.0088223 | H128: =IF($E$123<1,($B$123*'3 - Scenario'!N7+$C$123*'3 - Scenario'!O7+$D$123*'3 - Scenario'!P7)/(1-$E$123),0) -> 1.008644 | I128: =$E$123*'3 - Scenario'!Q7+((1-$E$123)-'1 - Caso e ipotesi'!$B$25*E128*MAX(0,B128-$E$123))*H128 -> 1.0261101 | J128: =J127*I128 -> 1.053004 | K128: =K127*I127+G128 -> 2.0350319 | L128: =IF(AND(L127=1,M128-N128>0),1,0) -> 1 | M128: =O127 -> 1231451.5 | N128: ='1 - Caso e ipotesi'!$B$7*G128 -> 40352.892 | O128: =IF(L128=1,(M128-N128)*I128,0) -> 1222198.3
A129: 3 | B129: =IF($E$123>0,$E$123*'3 - Scenario'!Q7/I128,0) -> 0.60690564 | C129: =IF($E$123>0,D128/((1+'3 - Scenario'!C7)*'3 - Scenario'!Q7),C128) -> 0.89221988 | D129: =IF($E$123>0,IF(B129>$E$123,C129,1-(1-C129)*B129/$E$123),C129) -> 0.89221988 | E129: =MAX(0,1-C129) -> 0.10778012 | F129: ='1 - Caso e ipotesi'!$B$25*E129*B129 -> 0.017007214 | G129: =1/(1-F129) -> 1.0173015 | H129: =IF($E$123<1,($B$123*'3 - Scenario'!N8+$C$123*'3 - Scenario'!O8+$D$123*'3 - Scenario'!P8)/(1-$E$123),0) -> 1.008644 | I129: =$E$123*'3 - Scenario'!Q8+((1-$E$123)-'1 - Caso e ipotesi'!$B$25*E129*MAX(0,B129-$E$123))*H129 -> 1.0260144 | J129: =J128*I129 -> 1.0803973 | K129: =K128*I128+G129 -> 3.1054682 | L129: =IF(AND(L128=1,M129-N129>0),1,0) -> 1 | M129: =O128 -> 1222198.3 | N129: ='1 - Caso e ipotesi'!$B$7*G129 -> 40692.059 | O129: =IF(L129=1,(M129-N129)*I129,0) -> 1212242.5
A130: 4 | B130: =IF($E$123>0,$E$123*'3 - Scenario'!Q8/I129,0) -> 0.60696223 | C130: =IF($E$123>0,D129/((1+'3 - Scenario'!C8)*'3 - Scenario'!Q8),C129) -> 0.84276762 | D130: =IF($E$123>0,IF(B130>$E$123,C130,1-(1-C130)*B130/$E$123),C130) -> 0.84276762 | E130: =MAX(0,1-C130) -> 0.15723238 | F130: ='1 - Caso e ipotesi'!$B$25*E130*B130 -> 0.02481287 | G130: =1/(1-F130) -> 1.0254442 | H130: =IF($E$123<1,($B$123*'3 - Scenario'!N9+$C$123*'3 - Scenario'!O9+$D$123*'3 - Scenario'!P9)/(1-$E$123),0) -> 1.008644 | I130: =$E$123*'3 - Scenario'!Q9+((1-$E$123)-'1 - Caso e ipotesi'!$B$25*E130*MAX(0,B130-$E$123))*H130 -> 1.0259225 | J130: =J129*I130 -> 1.1084039 | K130: =K129*I129+G130 -> 4.2116994 | L130: =IF(AND(L129=1,M130-N130>0),1,0) -> 1 | M130: =O129 -> 1212242.5 | N130: ='1 - Caso e ipotesi'!$B$7*G130 -> 41017.769 | O130: =IF(L130=1,(M130-N130)*I130,0) -> 1201585.8
A131: 5 | B131: =IF($E$123>0,$E$123*'3 - Scenario'!Q9/I130,0) -> 0.60701659 | C131: =IF($E$123>0,D130/((1+'3 - Scenario'!C9)*'3 - Scenario'!Q9),C130) -> 0.79605631 | D131: =IF($E$123>0,IF(B131>$E$123,C131,1-(1-C131)*B131/$E$123),C131) -> 0.79605631 | E131: =MAX(0,1-C131) -> 0.20394369 | F131: ='1 - Caso e ipotesi'!$B$25*E131*B131 -> 0.032187273 | G131: =1/(1-F131) -> 1.0332577 | H131: =IF($E$123<1,($B$123*'3 - Scenario'!N10+$C$123*'3 - Scenario'!O10+$D$123*'3 - Scenario'!P10)/(1-$E$123),0) -> 1.008644 | I131: =$E$123*'3 - Scenario'!Q10+((1-$E$123)-'1 - Caso e ipotesi'!$B$25*E131*MAX(0,B131-$E$123))*H131 -> 1.0258343 | J131: =J130*I131 -> 1.1370388 | K131: =K130*I130+G131 -> 5.354135 | L131: =IF(AND(L130=1,M131-N131>0),1,0) -> 1 | M131: =O130 -> 1201585.8 | N131: ='1 - Caso e ipotesi'!$B$7*G131 -> 41330.31 | O131: =IF(L131=1,(M131-N131)*I131,0) -> 1190229.9
A132: 6 | B132: =IF($E$123>0,$E$123*'3 - Scenario'!Q10/I131,0) -> 0.60706878 | C132: =IF($E$123>0,D131/((1+'3 - Scenario'!C10)*'3 - Scenario'!Q10),C131) -> 0.75193403 | D132: =IF($E$123>0,IF(B132>$E$123,C132,1-(1-C132)*B132/$E$123),C132) -> 0.75193403 | E132: =MAX(0,1-C132) -> 0.24806597 | F132: ='1 - Caso e ipotesi'!$B$25*E132*B132 -> 0.039154208 | G132: =1/(1-F132) -> 1.0407497 | H132: =IF($E$123<1,($B$123*'3 - Scenario'!N11+$C$123*'3 - Scenario'!O11+$D$123*'3 - Scenario'!P11)/(1-$E$123),0) -> 1.008644 | I132: =$E$123*'3 - Scenario'!Q11+((1-$E$123)-'1 - Caso e ipotesi'!$B$25*E132*MAX(0,B132-$E$123))*H132 -> 1.0257498 | J132: =J131*I132 -> 1.1663173 | K132: =K131*I131+G132 -> 6.5332053 | L132: =IF(AND(L131=1,M132-N132>0),1,0) -> 1 | M132: =O131 -> 1190229.9 | N132: ='1 - Caso e ipotesi'!$B$7*G132 -> 41629.989 | O132: =IF(L132=1,(M132-N132)*I132,0) -> 1178176.1
A133: 7 | B133: =IF($E$123>0,$E$123*'3 - Scenario'!Q11/I132,0) -> 0.60711884 | C133: =IF($E$123>0,D132/((1+'3 - Scenario'!C11)*'3 - Scenario'!Q11),C132) -> 0.71025727 | D133: =IF($E$123>0,IF(B133>$E$123,C133,1-(1-C133)*B133/$E$123),C133) -> 0.71025727 | E133: =MAX(0,1-C133) -> 0.28974273 | F133: ='1 - Caso e ipotesi'!$B$25*E133*B133 -> 0.045736151 | G133: =1/(1-F133) -> 1.0479282 | H133: =IF($E$123<1,($B$123*'3 - Scenario'!N12+$C$123*'3 - Scenario'!O12+$D$123*'3 - Scenario'!P12)/(1-$E$123),0) -> 1.008644 | I133: =$E$123*'3 - Scenario'!Q12+((1-$E$123)-'1 - Caso e ipotesi'!$B$25*E133*MAX(0,B133-$E$123))*H133 -> 1.0256687 | J133: =J132*I133 -> 1.1962551 | K133: =K132*I132+G133 -> 7.7493619 | L133: =IF(AND(L132=1,M133-N133>0),1,0) -> 1 | M133: =O132 -> 1178176.1 | N133: ='1 - Caso e ipotesi'!$B$7*G133 -> 41917.128 | O133: =IF(L133=1,(M133-N133)*I133,0) -> 1165425.2
A134: 8 | B134: =IF($E$123>0,$E$123*'3 - Scenario'!Q12/I133,0) -> 0.60716682 | C134: =IF($E$123>0,D133/((1+'3 - Scenario'!C12)*'3 - Scenario'!Q12),C133) -> 0.67089049 | D134: =IF($E$123>0,IF(B134>$E$123,C134,1-(1-C134)*B134/$E$123),C134) -> 0.67089049 | E134: =MAX(0,1-C134) -> 0.32910951 | F134: ='1 - Caso e ipotesi'!$B$25*E134*B134 -> 0.051954338 | G134: =1/(1-F134) -> 1.0548015 | H134: =IF($E$123<1,($B$123*'3 - Scenario'!N13+$C$123*'3 - Scenario'!O13+$D$123*'3 - Scenario'!P13)/(1-$E$123),0) -> 1.008644 | I134: =$E$123*'3 - Scenario'!Q13+((1-$E$123)-'1 - Caso e ipotesi'!$B$25*E134*MAX(0,B134-$E$123))*H134 -> 1.0255911 | J134: =J133*I134 -> 1.2268686 | K134: =K133*I133+G134 -> 9.0030794 | L134: =IF(AND(L133=1,M134-N134>0),1,0) -> 1 | M134: =O133 -> 1165425.2 | N134: ='1 - Caso e ipotesi'!$B$7*G134 -> 42192.061 | O134: =IF(L134=1,(M134-N134)*I134,0) -> 1151977.9
A135: 9 | B135: =IF($E$123>0,$E$123*'3 - Scenario'!Q13/I134,0) -> 0.60721279 | C135: =IF($E$123>0,D134/((1+'3 - Scenario'!C13)*'3 - Scenario'!Q13),C134) -> 0.63370565 | D135: =IF($E$123>0,IF(B135>$E$123,C135,1-(1-C135)*B135/$E$123),C135) -> 0.63370565 | E135: =MAX(0,1-C135) -> 0.36629435 | F135: ='1 - Caso e ipotesi'!$B$25*E135*B135 -> 0.057828839 | G135: =1/(1-F135) -> 1.0613783 | H135: =IF($E$123<1,($B$123*'3 - Scenario'!N14+$C$123*'3 - Scenario'!O14+$D$123*'3 - Scenario'!P14)/(1-$E$123),0) -> 1.008644 | I135: =$E$123*'3 - Scenario'!Q14+((1-$E$123)-'1 - Caso e ipotesi'!$B$25*E135*MAX(0,B135-$E$123))*H135 -> 1.0255167 | J135: =J134*I135 -> 1.2581743 | K135: =K134*I134+G135 -> 10.294856 | L135: =IF(AND(L134=1,M135-N135>0),1,0) -> 1 | M135: =O134 -> 1151977.9 | N135: ='1 - Caso e ipotesi'!$B$7*G135 -> 42455.131 | O135: =IF(L135=1,(M135-N135)*I135,0) -> 1137834.2
A136: 10 | B136: =IF($E$123>0,$E$123*'3 - Scenario'!Q14/I135,0) -> 0.60725678 | C136: =IF($E$123>0,D135/((1+'3 - Scenario'!C14)*'3 - Scenario'!Q14),C135) -> 0.59858183 | D136: =IF($E$123>0,IF(B136>$E$123,C136,1-(1-C136)*B136/$E$123),C136) -> 0.59858183 | E136: =MAX(0,1-C136) -> 0.40141817 | F136: ='1 - Caso e ipotesi'!$B$25*E136*B136 -> 0.063378616 | G136: =1/(1-F136) -> 1.0676673 | H136: =IF($E$123<1,($B$123*'3 - Scenario'!N15+$C$123*'3 - Scenario'!O15+$D$123*'3 - Scenario'!P15)/(1-$E$123),0) -> 1.008644 | I136: =$E$123*'3 - Scenario'!Q15+((1-$E$123)-'1 - Caso e ipotesi'!$B$25*E136*MAX(0,B136-$E$123))*H136 -> 1.0254457 | J136: =J135*I136 -> 1.2901894 | K136: =K135*I135+G136 -> 11.625214 | L136: =IF(AND(L135=1,M136-N136>0),1,0) -> 1 | M136: =O135 -> 1137834.2 | N136: ='1 - Caso e ipotesi'!$B$7*G136 -> 42706.691 | O136: =IF(L136=1,(M136-N136)*I136,0) -> 1122993.8
A137: 11 | B137: =IF($E$123>0,$E$123*'3 - Scenario'!Q15/I136,0) -> 0.60729887 | C137: =IF($E$123>0,D136/((1+'3 - Scenario'!C15)*'3 - Scenario'!Q15),C136) -> 0.56540478 | D137: =IF($E$123>0,IF(B137>$E$123,C137,1-(1-C137)*B137/$E$123),C137) -> 0.56540478 | E137: =MAX(0,1-C137) -> 0.43459522 | F137: ='1 - Caso e ipotesi'!$B$25*E137*B137 -> 0.068621588 | G137: =1/(1-F137) -> 1.0736775 | H137: =IF($E$123<1,($B$123*'3 - Scenario'!N16+$C$123*'3 - Scenario'!O16+$D$123*'3 - Scenario'!P16)/(1-$E$123),0) -> 1.008644 | I137: =$E$123*'3 - Scenario'!Q16+((1-$E$123)-'1 - Caso e ipotesi'!$B$25*E137*MAX(0,B137-$E$123))*H137 -> 1.0253777 | J137: =J136*I137 -> 1.3229314 | K137: =K136*I136+G137 -> 12.994703 | L137: =IF(AND(L136=1,M137-N137>0),1,0) -> 1 | M137: =O136 -> 1122993.8 | N137: ='1 - Caso e ipotesi'!$B$7*G137 -> 42947.098 | O137: =IF(L137=1,(M137-N137)*I137,0) -> 1107455.8
A138: 12 | B138: =IF($E$123>0,$E$123*'3 - Scenario'!Q16/I137,0) -> 0.6073391 | C138: =IF($E$123>0,D137/((1+'3 - Scenario'!C16)*'3 - Scenario'!Q16),C137) -> 0.53406661 | D138: =IF($E$123>0,IF(B138>$E$123,C138,1-(1-C138)*B138/$E$123),C138) -> 0.53406661 | E138: =MAX(0,1-C138) -> 0.46593339 | F138: ='1 - Caso e ipotesi'!$B$25*E138*B138 -> 0.073574688 | G138: =1/(1-F138) -> 1.0794178 | H138: =IF($E$123<1,($B$123*'3 - Scenario'!N17+$C$123*'3 - Scenario'!O17+$D$123*'3 - Scenario'!P17)/(1-$E$123),0) -> 1.008644 | I138: =$E$123*'3 - Scenario'!Q17+((1-$E$123)-'1 - Caso e ipotesi'!$B$25*E138*MAX(0,B138-$E$123))*H138 -> 1.0253128 | J138: =J137*I138 -> 1.3564186 | K138: =K137*I137+G138 -> 14.403897 | L138: =IF(AND(L137=1,M138-N138>0),1,0) -> 1 | M138: =O137 -> 1107455.8 | N138: ='1 - Caso e ipotesi'!$B$7*G138 -> 43176.713 | O138: =IF(L138=1,(M138-N138)*I138,0) -> 1091219
A139: 13 | B139: =IF($E$123>0,$E$123*'3 - Scenario'!Q17/I138,0) -> 0.60737755 | C139: =IF($E$123>0,D138/((1+'3 - Scenario'!C17)*'3 - Scenario'!Q17),C138) -> 0.50446539 | D139: =IF($E$123>0,IF(B139>$E$123,C139,1-(1-C139)*B139/$E$123),C139) -> 0.50446539 | E139: =MAX(0,1-C139) -> 0.49553461 | F139: ='1 - Caso e ipotesi'!$B$25*E139*B139 -> 0.078253916 | G139: =1/(1-F139) -> 1.0848975 | H139: =IF($E$123<1,($B$123*'3 - Scenario'!N18+$C$123*'3 - Scenario'!O18+$D$123*'3 - Scenario'!P18)/(1-$E$123),0) -> 1.008644 | I139: =$E$123*'3 - Scenario'!Q18+((1-$E$123)-'1 - Caso e ipotesi'!$B$25*E139*MAX(0,B139-$E$123))*H139 -> 1.0252509 | J139: =J138*I139 -> 1.3906694 | K139: =K138*I138+G139 -> 15.853399 | L139: =IF(AND(L138=1,M139-N139>0),1,0) -> 1 | M139: =O138 -> 1091219 | N139: ='1 - Caso e ipotesi'!$B$7*G139 -> 43395.899 | O139: =IF(L139=1,(M139-N139)*I139,0) -> 1074281.6
... A176: 50 | B176: =IF($E$123>0,$E$123*'3 - Scenario'!Q54/I175,0) -> 0.60800993 | C176: =IF($E$123>0,D175/((1+'3 - Scenario'!C54)*'3 - Scenario'!Q54),C175) -> 0.061173233 | D176: =IF($E$123>0,IF(B176>$E$123,C176,1-(1-C176)*B176/$E$123),C176) -> 0.061173233 | E176: =MAX(0,1-C176) -> 0.93882677 | F176: ='1 - Caso e ipotesi'!$B$25*E176*B176 -> 0.14841216 | G176: =1/(1-F176) -> 1.174277 | H176: =IF($E$123<1,($B$123*'3 - Scenario'!N55+$C$123*'3 - Scenario'!O55+$D$123*'3 - Scenario'!P55)/(1-$E$123),0) -> 1.008644 | I176: =$E$123*'3 - Scenario'!Q55+((1-$E$123)-'1 - Caso e ipotesi'!$B$25*E176*MAX(0,B176-$E$123))*H176 -> 1.0242375 | J176: =J175*I176 -> 3.4148336 | K176: =K175*I175+G176 -> 106.20375 | L176: =IF(AND(L175=1,M176-N176>0),1,0) -> 0 | M176: =O175 -> 0 | N176: ='1 - Caso e ipotesi'!$B$7*G176 -> 46971.079 | O176: =IF(L176=1,(M176-N176)*I176,0) -> 0
