Workbook
Name Cm_m26: '1 - Dati'!$C$30
Name Cm_nasc_a: '1 - Dati'!$C$26
Name Cm_nasc_m: '1 - Dati'!$C$27
Name Cm_netto: '2 - Pensioni'!$C$17
Name Cm_ord_cf: '5 - Motore e tabelle'!$H$358
Name Cm_ord_da: '5 - Motore e tabelle'!$H$353
Name Cm_ord_dm: '5 - Motore e tabelle'!$H$354
Name Cm_ord_em: '5 - Motore e tabelle'!$H$352
Name Cm_primo: '1 - Dati'!$C$29
Name Cm_ral: '1 - Dati'!$C$28
Name Cm_v71_cf: '5 - Motore e tabelle'!$I$358
Name Cm_v71_da: '5 - Motore e tabelle'!$I$353
Name Cm_v71_dm: '5 - Motore e tabelle'!$I$354
Name Cm_v71_em: '5 - Motore e tabelle'!$I$352
Name CT_eta: '5 - Motore e tabelle'!$A$106:$A$120
Name CT_val: '5 - Motore e tabelle'!$B$106:$B$120
Name Dist_tot_1: '2 - Pensioni'!$F$22
Name Dist_tot_2: '2 - Pensioni'!$F$23
Name Dist_tot_3: '2 - Pensioni'!$F$24
Name Dist_tot_4: '2 - Pensioni'!$F$25
Name Ered_2026: '1 - Dati'!$B$51
Name Ered_anno: '1 - Dati'!$B$50
Name Ered_nom: '1 - Dati'!$B$49
Name F_nom: '5 - Motore e tabelle'!$B$21
Name FZ_key: '5 - Motore e tabelle'!$A$310:$A$321
Name FZ_val: '5 - Motore e tabelle'!$E$310:$E$321
Name G_real: '5 - Motore e tabelle'!$B$22
Name imp_R1: '5 - Motore e tabelle'!$B$323
Name imp_R2: '5 - Motore e tabelle'!$B$324
Name K_raw: '5 - Motore e tabelle'!$E$138:$E$306
Name lam_A0: '5 - Motore e tabelle'!$B$24
Name lam_C0: '5 - Motore e tabelle'!$B$23
Name Leva_C: '3 - Numero FIRE'!$B$57
Name Leva_T: '3 - Numero FIRE'!$B$56
Name N_eta: '5 - Motore e tabelle'!$A$125:$A$134
Name Nodi_2013: '5 - Motore e tabelle'!$B$125:$B$134
Name Nodi_2025: '5 - Motore e tabelle'!$C$125:$C$134
Name Num_esito_1: '3 - Numero FIRE'!$B$14
Name Num_esito_2: '3 - Numero FIRE'!$C$14
Name Num_esito_3: '3 - Numero FIRE'!$D$14
Name Num_fine26_1: '3 - Numero FIRE'!$B$16
Name Num_fine26_2: '3 - Numero FIRE'!$C$16
Name Num_fine26_3: '3 - Numero FIRE'!$D$16
Name Num_marg_1: '3 - Numero FIRE'!$B$12
Name Num_marg_2: '3 - Numero FIRE'!$C$12
Name Num_marg_3: '3 - Numero FIRE'!$D$12
Name Num_patr_1: '3 - Numero FIRE'!$B$10
Name Num_patr_2: '3 - Numero FIRE'!$C$10
Name Num_patr_3: '3 - Numero FIRE'!$D$10
Name Num_ric_1: '3 - Numero FIRE'!$B$11
Name Num_ric_2: '3 - Numero FIRE'!$C$11
Name Num_ric_3: '3 - Numero FIRE'!$D$11
Name p_add: '1 - Dati'!$B$10
Name p_anni_eff: '1 - Dati'!$B$20
Name p_anni_min: '1 - Dati'!$B$19
Name p_AS: '1 - Dati'!$B$14
Name p_banda: '1 - Dati'!$B$22
Name p_bollo: '1 - Dati'!$B$8
Name p_cgt: '1 - Dati'!$B$9
Name p_comp: '1 - Dati'!$B$12

Sheet 0 - Indice
A1: FIRE in coppia: un numero o due? Il caso di Tiziano e Camilla (caso inventato e illustrativo)
A2: Strumento informativo / divulgativo. NON è consulenza finanziaria. I valori sono indicativi al 2026 e vanno verificati col tuo consulente.
A4: Indice
A5: 0 - Indice | B5: Questo indice
A6: 1 - Dati | B6: I tuoi dati (celle gialle): ipotesi, persone, spese, patrimonio, scenari, vedovanza
A7: 2 - Pensioni | B7: Stipendio netto e pensione di vecchiaia di ciascuno, regola dei 20 anni
A8: 3 - Numero FIRE | B8: Il numero FIRE: quanto serve, ponte e tratti, anni al traguardo, leve
A9: 4 - Vedovanza | B9: Vedovanza: il piano se uno dei due muore, reversibilità e successione
A10: 5 - Motore e tabelle | B10: Tabelle con fonte e data, motore del calcolo (non modificare)
A12: Come usare
A13: 1. Le celle GIALLE sono input — modificale coi tuoi numeri.
A14: 2. Le celle VERDI sono output — si aggiornano automaticamente.
A15: 3. Tutti i numeri di default sono al 2026 da fonti pubbliche.
A16: 4. Niente codice nascosto: l'Excel è solo formule modificabili.
A18: Fonti dati
A19: • Spesa delle famiglie: Istituto di statistica, indagine sulle spese 2025, tavole per componenti e stato abitativo (P)
A20: • Pensione di vecchiaia: DL 201/2011 art. 24 (testo vigente al 17/10/2026); INPS circ. 28/2026 (requisiti 2027-28); RGS 27 Tab. A1.4 (proiezione dal 2029) (P)
A21: • Coefficienti di trasformazione: decreto direttoriale 20/11/2024 (P); revisione dei coefficienti: RGS 27 Tab. A1.1 e riquadro 6.1 (P, ipotesi E)
A22: • Fisco 2026: TUIR artt. 11-13; L. 207/2024 art. 1 c. 4-9; INPS circ. 6/2026 par. 5 per la prima fascia pensionabile (P)
A23: • Reversibilità: L. 335/1995 tab. F e sentenza della Corte costituzionale 162/2022; trattamento minimo e assegno sociale: INPS circ. 153/2025 e 2026 (P)
A24: • Successioni: codice civile artt. 179, 538, 544, 582, 583; D.Lgs. 346/1990 art. 7 (P)
... A32: Sotto i 20 anni di contributi la pensione di vecchiaia arriva a 71 anni adeguati: un anno di lavoro in più può anticipare la pensione di oltre quattro anni.

Sheet 1 - Dati
A1: 1 - Dati: le celle gialle sono tue, cambiale con i numeri del tuo caso
A2: Strumento informativo / divulgativo. NON è consulenza finanziaria. I valori sono indicativi al 2026 e vanno verificati col tuo consulente.
A3: Il caso di Tiziano e Camilla è inventato e illustrativo. Ogni importo è in euro del 2026 (reali), salvo dove indicato. Le celle verdi si calcolano da sole. Il foglio non ricostruisce la storia dei risparmi: la base di costo dei conti è un dato dichiarato.
A5: Canone: ipotesi e parametri 2026 (caso base)
A6: Rendimento reale annuo | B6: 0.03 | D6: ipotesi
A7: Inflazione annua | B7: 0.02 | D7: ipotesi
A8: Bollo sul patrimonio (annuo) | B8: 0.002 | D8: imposta di bollo sugli strumenti finanziari
A9: Imposta sui guadagni di capitale | B9: 0.26 | D9: aliquota sostitutiva
A10: Addizionali regionali e comunali | B10: 0.02 | D10: convenzione del canale
A11: Rivalutazione reale del montante contributivo | B11: 0.005 | D11: ipotesi; a zero il montante cresce solo con i contributi
A12: Aliquota di computo | B12: 0.33 | D12: dipendenti: 33% della retribuzione
A13: Contributi a carico del dipendente | B13: 0.0919 | D13: INPS 2026
A14: Assegno sociale (€ al mese, per 13 mensilità) | B14: 546.24 | D14: INPS 2026
A15: Trattamento minimo annuo (provvisorio) | B15: 7954.05 | D15: INPS circ. 153/2025: 611,85 € × 13
A16: Ultimo anno del piano (orizzonte) | B16: 2078 | D16: Camilla a 95 anni
A17: Prima fascia pensionabile 2026 (€ l'anno) | B17: 56224 | D17: INPS circ. 6/2026 par. 5
... A21: Scarto della via dei 71 anni (mesi) | B21: 48 | D21: ipotesi dell'analista dal 2029: ordinario + 48 mesi; la legge dice «da adeguare»
A22: Coefficienti di trasformazione (banda) | B22: coefficienti di oggi | D22: «coefficienti di oggi» è il caso più favorevole; le altre due sono proiezioni
A24: Le due persone
B25: Tiziano | C25: Camilla
A26: Anno di nascita | B26: 1978 | C26: 1983
A27: Mese di nascita | B27: 3 | C27: 9
A28: Retribuzione annua lorda (RAL) | B28: 54000 | C28: 29000
A29: Primo anno di contributi | B29: 2004 | C29: 2008
A30: Montante contributivo al 31/12/2026 | B30: 355887.26 | C30: 156401.91 | D30: dall'estratto conto previdenziale; qui valori del caso
A31: Nome | B31: Tiziano | C31: Camilla
A33: Spese della coppia (euro l'anno)
A34: Spese comuni | B34: 39600
A35: Spese individuali di Tiziano | B35: 0
A36: Spese individuali di Camilla | B36: 0
A37: Spesa totale | B37: =p_sp_com+p_sp_T+p_sp_C -> 39600
A38: Quota della spesa se si divide a metà, sul netto di Tiziano | B38: =p_spesa/2/Tz_netto -> 0.56965498
A39: Quota della spesa se si divide a metà, sul netto di Camilla | B39: =p_spesa/2/Cm_netto -> 0.86543773
A40: Quota della spesa in proporzione al netto (uguale per entrambi) | B40: =p_spesa/(Tz_netto+Cm_netto) -> 0.6870649
A42: Patrimonio per intestatario (euro del 2026)
B43: Valore | C43: Base di costo | D43: Quota di guadagno latente
A44: Conto di Tiziano | B44: 400000 | C44: 238297.25 | D44: =1-C44/B44 -> 0.40425687
A45: Conto di Camilla | B45: 180000 | C45: 119854.49 | D45: =1-C45/B45 -> 0.33414172
A46: Conto cointestato | B46: 170000 | C46: 102895.12 | D46: =1-C46/B46 -> 0.39473459
A47: Totale | B47: =Pt_T_val+Pt_C_val+Pt_J_val -> 750000 | C47: =Pt_T_base+Pt_C_base+Pt_J_base -> 461046.86 | D47: =1-Pat_B/Pat_W -> 0.38527085
A48: Base derivata da una storia dichiarata (risparmi dal 2004 e dal 2008, eredità del 2015): se conosci la tua, sostituiscila.
A49: Eredità personale di Tiziano (importo nominale) | B49: 200000
A50: Anno dell'eredità | B50: 2015
A51: Eredità personale di Tiziano a fine 2026 (rivalutata) | B51: =Ered_nom*F_nom^(2026-Ered_anno) -> 336726.51 | D51: bene personale (art. 179 c.c.); la base di costo resta l'importo nominale
A53: Scenari di uscita: ultimo anno lavorato (2026 = già fermo)
A54: Se smettete oggi: Tiziano | B54: 2026
A55: Se smettete oggi: Camilla | B55: 2026
A56: Scenario comune: ultimo anno di entrambi | B56: 2029
A57: Scenario libero: Tiziano | B57: 2026
A58: Scenario libero: Camilla | B58: 2033
A60: Vedovanza: cosa succede se uno dei due muore (usa lo scenario comune)
A61: Chi muore (T = Tiziano, C = Camilla, nessuno) | B61: T
A62: Anno della morte | B62: 2035
A63: Regime (1 marito e moglie o unione civile; 2 conviventi) | B63: 1
A64: Testamento a favore del superstite (0 no, 1 sì) | B64: 0
A65: Famiglia d'origine (0 nessuno, 1 ascendenti, 2 fratelli) | B65: 0
A66: Figli minori (0 no, 1 sì: nessuna riduzione della reversibilità) | B66: 0
A67: Aliquota di reversibilità (solo regime 1) | B67: 0.6
A68: Spesa di chi resta: rapporto con la coppia, sotto i 65 anni (divisore) | B68: 1.4921 | D68: ISTAT 2025: il superstite spende 1/1,4921 della spesa di coppia
A69: Spesa di chi resta: dai 65 anni (divisore) | B69: 1.5648

Sheet 2 - Pensioni
A1: 2 - Pensioni: lo stipendio netto e la pensione di vecchiaia di ciascuno
A2: Strumento informativo / divulgativo. NON è consulenza finanziaria. I valori sono indicativi al 2026 e vanno verificati col tuo consulente.
A3: La pensione si calcola con il metodo contributivo: montante × coefficiente di trasformazione all'età di decorrenza. La pensione anticipata contributiva (a 65 anni e 10 mesi per Tiziano, gennaio 2044) è esclusa: richiede un assegno almeno 3,2 volte l'assegno sociale e nel caso base non lo raggiunge.
A5: Netto dello stipendio (fisco 2026, euro l'anno)
B6: Tiziano | C6: Camilla
A7: Retribuzione lorda (RAL) | B7: =Tz_ral -> 54000 | C7: =Cm_ral -> 29000
A8: Contributi del dipendente | B8: =p_contr*Tz_ral -> 4962.6 | C8: =p_contr*Cm_ral -> 2665.1
A9: Contributo aggiuntivo oltre la fascia | B9: =p_ivs_aliq*MAX(0,Tz_ral-p_ivs_soglia) -> 0 | C9: =p_ivs_aliq*MAX(0,Cm_ral-p_ivs_soglia) -> 0
A10: Reddito imponibile | B10: =Tz_ral-B8-B9 -> 49037.4 | C10: =Cm_ral-C8-C9 -> 26334.9
A11: IRPEF lorda | B11: =IF(B10<=sc_L1,sc_A1*B10,IF(B10<=sc_L2,sc_B1+sc_A2*(B10-sc_L1),sc_B2+sc_A3*(B10-sc_L2))) -> 13382.342 | C11: =IF(C10<=sc_L1,sc_A1*C10,IF(C10<=sc_L2,sc_B1+sc_A2*(C10-sc_L1),sc_B2+sc_A3*(C10-sc_L2))) -> 6057.027
A12: Detrazione per lavoro dipendente | B12: =(IF(B10<=15000,1955,IF(B10<=28000,1910+1190*(28000-B10)/13000,IF(B10<=50000,1910*(50000-B10)/22000,0)))+IF(AND(B10>25000,B10<=35000),65,0)) -> 83.571182 | C12: =(IF(C10<=15000,1955,IF(C10<=28000,1910+1190*(28000-C10)/13000,IF(C10<=50000,1910*(50000-C10)/22000,0)))+IF(AND(C10>25000,C10<=35000),65,0)) -> 2127.4207
A13: Ulteriore detrazione (20.000-40.000 €) | B13: =IF(AND(B10>20000,B10<=32000),1000,IF(AND(B10>32000,B10<=40000),1000*(40000-B10)/8000,0)) -> 0 | C13: =IF(AND(C10>20000,C10<=32000),1000,IF(AND(C10>32000,C10<=40000),1000*(40000-C10)/8000,0)) -> 1000
A14: IRPEF netta | B14: =MAX(0,B11-B12-B13) -> 13298.771 | C14: =MAX(0,C11-C12-C13) -> 2929.6063
A15: Addizionali | B15: =p_add*B10 -> 980.748 | C15: =p_add*C10 -> 526.698
A16: Somma non imponibile (reddito fino a 20.000 €) | B16: =IF(B10>20000,0,IF(B10<=8500,0.071*B10,IF(B10<=15000,0.053*B10,0.048*B10))) -> 0 | C16: =IF(C10>20000,0,IF(C10<=8500,0.071*C10,IF(C10<=15000,0.053*C10,0.048*C10))) -> 0
A17: Stipendio netto | B17: =B7-B8-B9-B14-B15+B16 -> 34757.881 | C17: =C7-C8-C9-C14-C15+C16 -> 22878.596
A18: Il netto è quanto entra davvero in cassa: RAL meno contributi, imposte e addizionali, più la somma non imponibile se spetta.
A20: Confronto: come cambia il netto se i due redditi sono distribuiti in modo diverso (stessa RAL totale)
A21: Distribuzione | B21: RAL Tiziano | C21: RAL Camilla | D21: Netto Tiziano | E21: Netto Camilla | F21: Netto della coppia
A22: Caso (54 + 29) | B22: 54000 | C22: 29000 | D22: =B22-p_contr*B22-p_ivs_aliq*MAX(0,B22-p_ivs_soglia)-MAX(0,IF((B22-p_contr*B22-p_ivs_aliq*MAX(0,B22-p_ivs_soglia))<=sc_L1,sc_A1*(B22-p_contr*B22-p_ivs_aliq*MAX(0,B22-p_ivs_soglia)),IF((B22-p_contr*B22-p_ivs_aliq*MAX(0,B22-p_ivs_soglia))<=sc_L2,sc_B1+sc_A2*((B22-p_contr*B22-p_ivs_aliq*MAX(0,B22-p_ivs_soglia))-sc_L1),sc_B2+sc_A3*((B22-p_contr*B22-p_ivs_aliq*MAX(0,B22-p_ivs_soglia))-sc_L2)))-(IF((B22-p_contr*B22-p_ivs_aliq*MAX(0,B22-p_ivs_soglia))<=15000,1955,IF((B22-p_contr*B22-p_ivs_aliq*MAX(0,B22-p_ivs_soglia))<=28000,1910+1190*(28000-(B22-p_contr*B22-p_ivs_aliq*MAX(0,B22-p_ivs_soglia)))/13000,IF((B22-p_contr*B22-p_ivs_aliq*MAX(0,B22-p_ivs_soglia))<=50000,1910*(50000-(B22-p_contr*B22-p_ivs_aliq*MAX(0,B22-p_ivs_soglia)))/22000,0)))+IF(AND((B22-p_contr*B22-p_ivs_aliq*MAX(0,B22-p_ivs_soglia))>25000,(B22-p_contr*B22-p_ivs_aliq*MAX(0,B22-p_ivs_soglia))<=35000),65,0))-IF(AND((B22-p_contr*B22-p_ivs_aliq*MAX(0,B22-p_ivs_soglia))>20000,(B22-p_contr*B22-p_ivs_aliq*MAX(0,B22-p_ivs_soglia))<=32000),1000,IF(AND((B22-p_contr*B22-p_ivs_aliq*MAX(0,B22-p_ivs_soglia))>32000,(B22-p_contr*B22-p_ivs_aliq*MAX(0,B22-p_ivs_soglia))<=40000),1000*(40000-(B22-p_contr*B22-p_ivs_aliq*MAX(0,B22-p_ivs_soglia)))/8000,0)))-p_add*(B22-p_contr*B22-p_ivs_aliq*MAX(0,B22-p_ivs_soglia))+IF((B22-p_contr*B22-p_ivs_aliq*MAX(0,B22-p_ivs_soglia))>20000,0,IF((B22-p_contr*B22-p_ivs_aliq*MAX(0,B22-p_ivs_soglia))<=8500,0.071*(B22-p_contr*B22-p_ivs_aliq*MAX(0,B22-p_ivs_soglia)),IF((B22-p_contr*B22-p_ivs_aliq*MAX(0,B22-p_ivs_soglia))<=15000,0.053*(B22-p_contr*B22-p_ivs_aliq*MAX(0,B22-p_ivs_soglia)),0.048*(B22-p_contr*B22-p_ivs_aliq*MAX(0,B22-p_ivs_soglia))))) -> 34757.881 | E22: =C22-p_contr*C22-p_ivs_aliq*MAX(0,C22-p_ivs_soglia)-MAX(0,IF((C22-p_contr*C22-p_ivs_aliq*MAX(0,C22-p_ivs_soglia))<=sc_L1,sc_A1*(C22-p_contr*C22-p_ivs_aliq*MAX(0,C22-p_ivs_soglia)),IF((C22-p_contr*C22-p_ivs_aliq*MAX(0,C22-p_ivs_soglia))<=sc_L2,sc_B1+sc_A2*((C22-p_contr*C22-p_ivs_aliq*MAX(0,C22-p_ivs_soglia))-sc_L1),sc_B2+sc_A3*((C22-p_contr*C22-p_ivs_aliq*MAX(0,C22-p_ivs_soglia))-sc_L2)))-(IF((C22-p_contr*C22-p_ivs_aliq*MAX(0,C22-p_ivs_soglia))<=15000,1955,IF((C22-p_contr*C22-p_ivs_aliq*MAX(0,C22-p_ivs_soglia))<=28000,1910+1190*(28000-(C22-p_contr*C22-p_ivs_aliq*MAX(0,C22-p_ivs_soglia)))/13000,IF((C22-p_contr*C22-p_ivs_aliq*MAX(0,C22-p_ivs_soglia))<=50000,1910*(50000-(C22-p_contr*C22-p_ivs_aliq*MAX(0,C22-p_ivs_soglia)))/22000,0)))+IF(AND((C22-p_contr*C22-p_ivs_aliq*MAX(0,C22-p_ivs_soglia))>25000,(C22-p_contr*C22-p_ivs_aliq*MAX(0,C22-p_ivs_soglia))<=35000),65,0))-IF(AND((C22-p_contr*C22-p_ivs_aliq*MAX(0,C22-p_ivs_soglia))>20000,(C22-p_contr*C22-p_ivs_aliq*MAX(0,C22-p_ivs_soglia))<=32000),1000,IF(AND((C22-p_contr*C22-p_ivs_aliq*MAX(0,C22-p_ivs_soglia))>32000,(C22-p_contr*C22-p_ivs_aliq*MAX(0,C22-p_ivs_soglia))<=40000),1000*(40000-(C22-p_contr*C22-p_ivs_aliq*MAX(0,C22-p_ivs_soglia)))/8000,0)))-p_add*(C22-p_contr*C22-p_ivs_aliq*MAX(0,C22-p_ivs_soglia))+IF((C22-p_contr*C22-p_ivs_aliq*MAX(0,C22-p_ivs_soglia))>20000,0,IF((C22-p_contr*C22-p_ivs_aliq*MAX(0,C22-p_ivs_soglia))<=8500,0.071*(C22-p_contr*C22-p_ivs_aliq*MAX(0,C22-p_ivs_soglia)),IF((C22-p_contr*C22-p_ivs_aliq*MAX(0,C22-p_ivs_soglia))<=15000,0.053*(C22-p_contr*C22-p_ivs_aliq*MAX(0,C22-p_ivs_soglia)),0.048*(C22-p_contr*C22-p_ivs_aliq*MAX(0,C22-p_ivs_soglia))))) -> 22878.596 | F22: =D22+E22 -> 57636.477
A23: Più sbilanciati (65 + 18) | B23: 65000 | C23: 18000 | D23: =B23-p_contr*B23-p_ivs_aliq*MAX(0,B23-p_ivs_soglia)-MAX(0,IF((B23-p_contr*B23-p_ivs_aliq*MAX(0,B23-p_ivs_soglia))<=sc_L1,sc_A1*(B23-p_contr*B23-p_ivs_aliq*MAX(0,B23-p_ivs_soglia)),IF((B23-p_contr*B23-p_ivs_aliq*MAX(0,B23-p_ivs_soglia))<=sc_L2,sc_B1+sc_A2*((B23-p_contr*B23-p_ivs_aliq*MAX(0,B23-p_ivs_soglia))-sc_L1),sc_B2+sc_A3*((B23-p_contr*B23-p_ivs_aliq*MAX(0,B23-p_ivs_soglia))-sc_L2)))-(IF((B23-p_contr*B23-p_ivs_aliq*MAX(0,B23-p_ivs_soglia))<=15000,1955,IF((B23-p_contr*B23-p_ivs_aliq*MAX(0,B23-p_ivs_soglia))<=28000,1910+1190*(28000-(B23-p_contr*B23-p_ivs_aliq*MAX(0,B23-p_ivs_soglia)))/13000,IF((B23-p_contr*B23-p_ivs_aliq*MAX(0,B23-p_ivs_soglia))<=50000,1910*(50000-(B23-p_contr*B23-p_ivs_aliq*MAX(0,B23-p_ivs_soglia)))/22000,0)))+IF(AND((B23-p_contr*B23-p_ivs_aliq*MAX(0,B23-p_ivs_soglia))>25000,(B23-p_contr*B23-p_ivs_aliq*MAX(0,B23-p_ivs_soglia))<=35000),65,0))-IF(AND((B23-p_contr*B23-p_ivs_aliq*MAX(0,B23-p_ivs_soglia))>20000,(B23-p_contr*B23-p_ivs_aliq*MAX(0,B23-p_ivs_soglia))<=32000),1000,IF(AND((B23-p_contr*B23-p_ivs_aliq*MAX(0,B23-p_ivs_soglia))>32000,(B23-p_contr*B23-p_ivs_aliq*MAX(0,B23-p_ivs_soglia))<=40000),1000*(40000-(B23-p_contr*B23-p_ivs_aliq*MAX(0,B23-p_ivs_soglia)))/8000,0)))-p_add*(B23-p_contr*B23-p_ivs_aliq*MAX(0,B23-p_ivs_soglia))+IF((B23-p_contr*B23-p_ivs_aliq*MAX(0,B23-p_ivs_soglia))>20000,0,IF((B23-p_contr*B23-p_ivs_aliq*MAX(0,B23-p_ivs_soglia))<=8500,0.071*(B23-p_contr*B23-p_ivs_aliq*MAX(0,B23-p_ivs_soglia)),IF((B23-p_contr*B23-p_ivs_aliq*MAX(0,B23-p_ivs_soglia))<=15000,0.053*(B23-p_contr*B23-p_ivs_aliq*MAX(0,B23-p_ivs_soglia)),0.048*(B23-p_contr*B23-p_ivs_aliq*MAX(0,B23-p_ivs_soglia))))) -> 40216.307 | E23: =C23-p_contr*C23-p_ivs_aliq*MAX(0,C23-p_ivs_soglia)-MAX(0,IF((C23-p_contr*C23-p_ivs_aliq*MAX(0,C23-p_ivs_soglia))<=sc_L1,sc_A1*(C23-p_contr*C23-p_ivs_aliq*MAX(0,C23-p_ivs_soglia)),IF((C23-p_contr*C23-p_ivs_aliq*MAX(0,C23-p_ivs_soglia))<=sc_L2,sc_B1+sc_A2*((C23-p_contr*C23-p_ivs_aliq*MAX(0,C23-p_ivs_soglia))-sc_L1),sc_B2+sc_A3*((C23-p_contr*C23-p_ivs_aliq*MAX(0,C23-p_ivs_soglia))-sc_L2)))-(IF((C23-p_contr*C23-p_ivs_aliq*MAX(0,C23-p_ivs_soglia))<=15000,1955,IF((C23-p_contr*C23-p_ivs_aliq*MAX(0,C23-p_ivs_soglia))<=28000,1910+1190*(28000-(C23-p_contr*C23-p_ivs_aliq*MAX(0,C23-p_ivs_soglia)))/13000,IF((C23-p_contr*C23-p_ivs_aliq*MAX(0,C23-p_ivs_soglia))<=50000,1910*(50000-(C23-p_contr*C23-p_ivs_aliq*MAX(0,C23-p_ivs_soglia)))/22000,0)))+IF(AND((C23-p_contr*C23-p_ivs_aliq*MAX(0,C23-p_ivs_soglia))>25000,(C23-p_contr*C23-p_ivs_aliq*MAX(0,C23-p_ivs_soglia))<=35000),65,0))-IF(AND((C23-p_contr*C23-p_ivs_aliq*MAX(0,C23-p_ivs_soglia))>20000,(C23-p_contr*C23-p_ivs_aliq*MAX(0,C23-p_ivs_soglia))<=32000),1000,IF(AND((C23-p_contr*C23-p_ivs_aliq*MAX(0,C23-p_ivs_soglia))>32000,(C23-p_contr*C23-p_ivs_aliq*MAX(0,C23-p_ivs_soglia))<=40000),1000*(40000-(C23-p_contr*C23-p_ivs_aliq*MAX(0,C23-p_ivs_soglia)))/8000,0)))-p_add*(C23-p_contr*C23-p_ivs_aliq*MAX(0,C23-p_ivs_soglia))+IF((C23-p_contr*C23-p_ivs_aliq*MAX(0,C23-p_ivs_soglia))>20000,0,IF((C23-p_contr*C23-p_ivs_aliq*MAX(0,C23-p_ivs_soglia))<=8500,0.071*(C23-p_contr*C23-p_ivs_aliq*MAX(0,C23-p_ivs_soglia)),IF((C23-p_contr*C23-p_ivs_aliq*MAX(0,C23-p_ivs_soglia))<=15000,0.053*(C23-p_contr*C23-p_ivs_aliq*MAX(0,C23-p_ivs_soglia)),0.048*(C23-p_contr*C23-p_ivs_aliq*MAX(0,C23-p_ivs_soglia))))) -> 16020.756 | F23: =D23+E23 -> 56237.063
A24: Uguali (41,5 + 41,5) | B24: 41500 | C24: 41500 | D24: =B24-p_contr*B24-p_ivs_aliq*MAX(0,B24-p_ivs_soglia)-MAX(0,IF((B24-p_contr*B24-p_ivs_aliq*MAX(0,B24-p_ivs_soglia))<=sc_L1,sc_A1*(B24-p_contr*B24-p_ivs_aliq*MAX(0,B24-p_ivs_soglia)),IF((B24-p_contr*B24-p_ivs_aliq*MAX(0,B24-p_ivs_soglia))<=sc_L2,sc_B1+sc_A2*((B24-p_contr*B24-p_ivs_aliq*MAX(0,B24-p_ivs_soglia))-sc_L1),sc_B2+sc_A3*((B24-p_contr*B24-p_ivs_aliq*MAX(0,B24-p_ivs_soglia))-sc_L2)))-(IF((B24-p_contr*B24-p_ivs_aliq*MAX(0,B24-p_ivs_soglia))<=15000,1955,IF((B24-p_contr*B24-p_ivs_aliq*MAX(0,B24-p_ivs_soglia))<=28000,1910+1190*(28000-(B24-p_contr*B24-p_ivs_aliq*MAX(0,B24-p_ivs_soglia)))/13000,IF((B24-p_contr*B24-p_ivs_aliq*MAX(0,B24-p_ivs_soglia))<=50000,1910*(50000-(B24-p_contr*B24-p_ivs_aliq*MAX(0,B24-p_ivs_soglia)))/22000,0)))+IF(AND((B24-p_contr*B24-p_ivs_aliq*MAX(0,B24-p_ivs_soglia))>25000,(B24-p_contr*B24-p_ivs_aliq*MAX(0,B24-p_ivs_soglia))<=35000),65,0))-IF(AND((B24-p_contr*B24-p_ivs_aliq*MAX(0,B24-p_ivs_soglia))>20000,(B24-p_contr*B24-p_ivs_aliq*MAX(0,B24-p_ivs_soglia))<=32000),1000,IF(AND((B24-p_contr*B24-p_ivs_aliq*MAX(0,B24-p_ivs_soglia))>32000,(B24-p_contr*B24-p_ivs_aliq*MAX(0,B24-p_ivs_soglia))<=40000),1000*(40000-(B24-p_contr*B24-p_ivs_aliq*MAX(0,B24-p_ivs_soglia)))/8000,0)))-p_add*(B24-p_contr*B24-p_ivs_aliq*MAX(0,B24-p_ivs_soglia))+IF((B24-p_contr*B24-p_ivs_aliq*MAX(0,B24-p_ivs_soglia))>20000,0,IF((B24-p_contr*B24-p_ivs_aliq*MAX(0,B24-p_ivs_soglia))<=8500,0.071*(B24-p_contr*B24-p_ivs_aliq*MAX(0,B24-p_ivs_soglia)),IF((B24-p_contr*B24-p_ivs_aliq*MAX(0,B24-p_ivs_soglia))<=15000,0.053*(B24-p_contr*B24-p_ivs_aliq*MAX(0,B24-p_ivs_soglia)),0.048*(B24-p_contr*B24-p_ivs_aliq*MAX(0,B24-p_ivs_soglia))))) -> 28654.295 | E24: =C24-p_contr*C24-p_ivs_aliq*MAX(0,C24-p_ivs_soglia)-MAX(0,IF((C24-p_contr*C24-p_ivs_aliq*MAX(0,C24-p_ivs_soglia))<=sc_L1,sc_A1*(C24-p_contr*C24-p_ivs_aliq*MAX(0,C24-p_ivs_soglia)),IF((C24-p_contr*C24-p_ivs_aliq*MAX(0,C24-p_ivs_soglia))<=sc_L2,sc_B1+sc_A2*((C24-p_contr*C24-p_ivs_aliq*MAX(0,C24-p_ivs_soglia))-sc_L1),sc_B2+sc_A3*((C24-p_contr*C24-p_ivs_aliq*MAX(0,C24-p_ivs_soglia))-sc_L2)))-(IF((C24-p_contr*C24-p_ivs_aliq*MAX(0,C24-p_ivs_soglia))<=15000,1955,IF((C24-p_contr*C24-p_ivs_aliq*MAX(0,C24-p_ivs_soglia))<=28000,1910+1190*(28000-(C24-p_contr*C24-p_ivs_aliq*MAX(0,C24-p_ivs_soglia)))/13000,IF((C24-p_contr*C24-p_ivs_aliq*MAX(0,C24-p_ivs_soglia))<=50000,1910*(50000-(C24-p_contr*C24-p_ivs_aliq*MAX(0,C24-p_ivs_soglia)))/22000,0)))+IF(AND((C24-p_contr*C24-p_ivs_aliq*MAX(0,C24-p_ivs_soglia))>25000,(C24-p_contr*C24-p_ivs_aliq*MAX(0,C24-p_ivs_soglia))<=35000),65,0))-IF(AND((C24-p_contr*C24-p_ivs_aliq*MAX(0,C24-p_ivs_soglia))>20000,(C24-p_contr*C24-p_ivs_aliq*MAX(0,C24-p_ivs_soglia))<=32000),1000,IF(AND((C24-p_contr*C24-p_ivs_aliq*MAX(0,C24-p_ivs_soglia))>32000,(C24-p_contr*C24-p_ivs_aliq*MAX(0,C24-p_ivs_soglia))<=40000),1000*(40000-(C24-p_contr*C24-p_ivs_aliq*MAX(0,C24-p_ivs_soglia)))/8000,0)))-p_add*(C24-p_contr*C24-p_ivs_aliq*MAX(0,C24-p_ivs_soglia))+IF((C24-p_contr*C24-p_ivs_aliq*MAX(0,C24-p_ivs_soglia))>20000,0,IF((C24-p_contr*C24-p_ivs_aliq*MAX(0,C24-p_ivs_soglia))<=8500,0.071*(C24-p_contr*C24-p_ivs_aliq*MAX(0,C24-p_ivs_soglia)),IF((C24-p_contr*C24-p_ivs_aliq*MAX(0,C24-p_ivs_soglia))<=15000,0.053*(C24-p_contr*C24-p_ivs_aliq*MAX(0,C24-p_ivs_soglia)),0.048*(C24-p_contr*C24-p_ivs_aliq*MAX(0,C24-p_ivs_soglia))))) -> 28654.295 | F24: =D24+E24 -> 57308.59
A25: Un solo reddito (83 + 0) | B25: 83000 | C25: 0 | D25: =B25-p_contr*B25-p_ivs_aliq*MAX(0,B25-p_ivs_soglia)-MAX(0,IF((B25-p_contr*B25-p_ivs_aliq*MAX(0,B25-p_ivs_soglia))<=sc_L1,sc_A1*(B25-p_contr*B25-p_ivs_aliq*MAX(0,B25-p_ivs_soglia)),IF((B25-p_contr*B25-p_ivs_aliq*MAX(0,B25-p_ivs_soglia))<=sc_L2,sc_B1+sc_A2*((B25-p_contr*B25-p_ivs_aliq*MAX(0,B25-p_ivs_soglia))-sc_L1),sc_B2+sc_A3*((B25-p_contr*B25-p_ivs_aliq*MAX(0,B25-p_ivs_soglia))-sc_L2)))-(IF((B25-p_contr*B25-p_ivs_aliq*MAX(0,B25-p_ivs_soglia))<=15000,1955,IF((B25-p_contr*B25-p_ivs_aliq*MAX(0,B25-p_ivs_soglia))<=28000,1910+1190*(28000-(B25-p_contr*B25-p_ivs_aliq*MAX(0,B25-p_ivs_soglia)))/13000,IF((B25-p_contr*B25-p_ivs_aliq*MAX(0,B25-p_ivs_soglia))<=50000,1910*(50000-(B25-p_contr*B25-p_ivs_aliq*MAX(0,B25-p_ivs_soglia)))/22000,0)))+IF(AND((B25-p_contr*B25-p_ivs_aliq*MAX(0,B25-p_ivs_soglia))>25000,(B25-p_contr*B25-p_ivs_aliq*MAX(0,B25-p_ivs_soglia))<=35000),65,0))-IF(AND((B25-p_contr*B25-p_ivs_aliq*MAX(0,B25-p_ivs_soglia))>20000,(B25-p_contr*B25-p_ivs_aliq*MAX(0,B25-p_ivs_soglia))<=32000),1000,IF(AND((B25-p_contr*B25-p_ivs_aliq*MAX(0,B25-p_ivs_soglia))>32000,(B25-p_contr*B25-p_ivs_aliq*MAX(0,B25-p_ivs_soglia))<=40000),1000*(40000-(B25-p_contr*B25-p_ivs_aliq*MAX(0,B25-p_ivs_soglia)))/8000,0)))-p_add*(B25-p_contr*B25-p_ivs_aliq*MAX(0,B25-p_ivs_soglia))+IF((B25-p_contr*B25-p_ivs_aliq*MAX(0,B25-p_ivs_soglia))>20000,0,IF((B25-p_contr*B25-p_ivs_aliq*MAX(0,B25-p_ivs_soglia))<=8500,0.071*(B25-p_contr*B25-p_ivs_aliq*MAX(0,B25-p_ivs_soglia)),IF((B25-p_contr*B25-p_ivs_aliq*MAX(0,B25-p_ivs_soglia))<=15000,0.053*(B25-p_contr*B25-p_ivs_aliq*MAX(0,B25-p_ivs_soglia)),0.048*(B25-p_contr*B25-p_ivs_aliq*MAX(0,B25-p_ivs_soglia))))) -> 49107.497 | E25: =C25-p_contr*C25-p_ivs_aliq*MAX(0,C25-p_ivs_soglia)-MAX(0,IF((C25-p_contr*C25-p_ivs_aliq*MAX(0,C25-p_ivs_soglia))<=sc_L1,sc_A1*(C25-p_contr*C25-p_ivs_aliq*MAX(0,C25-p_ivs_soglia)),IF((C25-p_contr*C25-p_ivs_aliq*MAX(0,C25-p_ivs_soglia))<=sc_L2,sc_B1+sc_A2*((C25-p_contr*C25-p_ivs_aliq*MAX(0,C25-p_ivs_soglia))-sc_L1),sc_B2+sc_A3*((C25-p_contr*C25-p_ivs_aliq*MAX(0,C25-p_ivs_soglia))-sc_L2)))-(IF((C25-p_contr*C25-p_ivs_aliq*MAX(0,C25-p_ivs_soglia))<=15000,1955,IF((C25-p_contr*C25-p_ivs_aliq*MAX(0,C25-p_ivs_soglia))<=28000,1910+1190*(28000-(C25-p_contr*C25-p_ivs_aliq*MAX(0,C25-p_ivs_soglia)))/13000,IF((C25-p_contr*C25-p_ivs_aliq*MAX(0,C25-p_ivs_soglia))<=50000,1910*(50000-(C25-p_contr*C25-p_ivs_aliq*MAX(0,C25-p_ivs_soglia)))/22000,0)))+IF(AND((C25-p_contr*C25-p_ivs_aliq*MAX(0,C25-p_ivs_soglia))>25000,(C25-p_contr*C25-p_ivs_aliq*MAX(0,C25-p_ivs_soglia))<=35000),65,0))-IF(AND((C25-p_contr*C25-p_ivs_aliq*MAX(0,C25-p_ivs_soglia))>20000,(C25-p_contr*C25-p_ivs_aliq*MAX(0,C25-p_ivs_soglia))<=32000),1000,IF(AND((C25-p_contr*C25-p_ivs_aliq*MAX(0,C25-p_ivs_soglia))>32000,(C25-p_contr*C25-p_ivs_aliq*MAX(0,C25-p_ivs_soglia))<=40000),1000*(40000-(C25-p_contr*C25-p_ivs_aliq*MAX(0,C25-p_ivs_soglia)))/8000,0)))-p_add*(C25-p_contr*C25-p_ivs_aliq*MAX(0,C25-p_ivs_soglia))+IF((C25-p_contr*C25-p_ivs_aliq*MAX(0,C25-p_ivs_soglia))>20000,0,IF((C25-p_contr*C25-p_ivs_aliq*MAX(0,C25-p_ivs_soglia))<=8500,0.071*(C25-p_contr*C25-p_ivs_aliq*MAX(0,C25-p_ivs_soglia)),IF((C25-p_contr*C25-p_ivs_aliq*MAX(0,C25-p_ivs_soglia))<=15000,0.053*(C25-p_contr*C25-p_ivs_aliq*MAX(0,C25-p_ivs_soglia)),0.048*(C25-p_contr*C25-p_ivs_aliq*MAX(0,C25-p_ivs_soglia))))) -> 0 | F25: =D25+E25 -> 49107.497
A26: Lordo identico, netto diverso: l'IRPEF è individuale, quindi conta come il lordo si distribuisce fra i due.
A28: Le due pensioni nei tuoi scenari (ultimo anno lavorato dalle celle gialle del foglio 1)
B29: Oggi: Tiziano | C29: Oggi: Camilla | D29: Comune: Tiziano | E29: Comune: Camilla | F29: Libero: Tiziano | G29: Libero: Camilla
A30: Ultimo anno lavorato | B30: =U_oggi_T -> 2026 | C30: =U_oggi_C -> 2026 | D30: =U_com -> 2029 | E30: =U_com -> 2029 | F30: =U_lib_T -> 2026 | G30: =U_lib_C -> 2033
A31: Anni di contributi | B31: =U_oggi_T-Tz_primo+1 -> 23 | C31: =U_oggi_C-Cm_primo+1 -> 19 | D31: =U_com-Tz_primo+1 -> 26 | E31: =U_com-Cm_primo+1 -> 22 | F31: =U_lib_T-Tz_primo+1 -> 23 | G31: =U_lib_C-Cm_primo+1 -> 26
A32: Regola applicata | B32: =IF(B31<p_anni_min,"via dei 71 anni adeguati","vecchiaia ordinaria") -> vecchiaia ordinaria | C32: =IF(C31<p_anni_min,"via dei 71 anni adeguati","vecchiaia ordinaria") -> via dei 71 anni adeguati | D32: =IF(D31<p_anni_min,"via dei 71 anni adeguati","vecchiaia ordinaria") -> vecchiaia ordinaria | E32: =IF(E31<p_anni_min,"via dei 71 anni adeguati","vecchiaia ordinaria") -> vecchiaia ordinaria | F32: =IF(F31<p_anni_min,"via dei 71 anni adeguati","vecchiaia ordinaria") -> vecchiaia ordinaria | G32: =IF(G31<p_anni_min,"via dei 71 anni adeguati","vecchiaia ordinaria") -> vecchiaia ordinaria
A33: Avviso | B33: =IF(B31<p_anni_eff,"Con meno di "&p_anni_eff&" anni effettivi la pensione di vecchiaia non spetta",IF(B31<p_anni_min,"Sotto i "&p_anni_min&" anni di contributi la pensione di vecchiaia arriva al requisito dei 71 anni adeguati (DL 201/2011 art. 24 c. 7), con almeno "&p_anni_eff&" anni effettivi. Dal 2029 il requisito è una proiezione. Un anno di lavoro in più può anticipare la pensione di oltre quattro anni.","")) | C33: =IF(C31<p_anni_eff,"Con meno di "&p_anni_eff&" anni effettivi la pensione di vecchiaia non spetta",IF(C31<p_anni_min,"Sotto i "&p_anni_min&" anni di contributi la pensione di vecchiaia arriva al requisito dei 71 anni adeguati (DL 201/2011 art. 24 c. 7), con almeno "&p_anni_eff&" anni effettivi. Dal 2029 il requisito è una proiezione. Un anno di lavoro in più può anticipare la pensione di oltre quattro anni.","")) -> Sotto i 20 anni di contributi la pensione di vecchiaia arriva al requisito dei 71 anni adeguati (DL 201/2011 art. 24 c. 7), con almeno 5 anni effettivi. Dal 2029 il requisito è una proiezione. Un anno di lavoro in più può anticipare la pensione di oltre quattro anni. | D33: =IF(D31<p_anni_eff,"Con meno di "&p_anni_eff&" anni effettivi la pensione di vecchiaia non spetta",IF(D31<p_anni_min,"Sotto i "&p_anni_min&" anni di contributi la pensione di vecchiaia arriva al requisito dei 71 anni adeguati (DL 201/2011 art. 24 c. 7), con almeno "&p_anni_eff&" anni effettivi. Dal 2029 il requisito è una proiezione. Un anno di lavoro in più può anticipare la pensione di oltre quattro anni.","")) | E33: =IF(E31<p_anni_eff,"Con meno di "&p_anni_eff&" anni effettivi la pensione di vecchiaia non spetta",IF(E31<p_anni_min,"Sotto i "&p_anni_min&" anni di contributi la pensione di vecchiaia arriva al requisito dei 71 anni adeguati (DL 201/2011 art. 24 c. 7), con almeno "&p_anni_eff&" anni effettivi. Dal 2029 il requisito è una proiezione. Un anno di lavoro in più può anticipare la pensione di oltre quattro anni.","")) | F33: =IF(F31<p_anni_eff,"Con meno di "&p_anni_eff&" anni effettivi la pensione di vecchiaia non spetta",IF(F31<p_anni_min,"Sotto i "&p_anni_min&" anni di contributi la pensione di vecchiaia arriva al requisito dei 71 anni adeguati (DL 201/2011 art. 24 c. 7), con almeno "&p_anni_eff&" anni effettivi. Dal 2029 il requisito è una proiezione. Un anno di lavoro in più può anticipare la pensione di oltre quattro anni.","")) | G33: =IF(G31<p_anni_eff,"Con meno di "&p_anni_eff&" anni effettivi la pensione di vecchiaia non spetta",IF(G31<p_anni_min,"Sotto i "&p_anni_min&" anni di contributi la pensione di vecchiaia arriva al requisito dei 71 anni adeguati (DL 201/2011 art. 24 c. 7), con almeno "&p_anni_eff&" anni effettivi. Dal 2029 il requisito è una proiezione. Un anno di lavoro in più può anticipare la pensione di oltre quattro anni.",""))
A34: Decorrenza (mese/anno) | B34: =TEXT(INDEX(PT_dm,U_oggi_T-2025),"00")&"/"&INDEX(PT_da,U_oggi_T-2025) -> 12/2046 | C34: =TEXT(INDEX(PC_dm,U_oggi_C-2025),"00")&"/"&INDEX(PC_da,U_oggi_C-2025) -> 05/2057 | D34: =TEXT(INDEX(PT_dm,U_com-2025),"00")&"/"&INDEX(PT_da,U_com-2025) -> 12/2046 | E34: =TEXT(INDEX(PC_dm,U_com-2025),"00")&"/"&INDEX(PC_da,U_com-2025) -> 12/2052 | F34: =TEXT(INDEX(PT_dm,U_lib_T-2025),"00")&"/"&INDEX(PT_da,U_lib_T-2025) -> 12/2046 | G34: =TEXT(INDEX(PC_dm,U_lib_C-2025),"00")&"/"&INDEX(PC_da,U_lib_C-2025) -> 12/2052
A35: Età alla decorrenza | B35: =INT(INDEX(PT_em,U_oggi_T-2025)/12)&" anni e "&MOD(INDEX(PT_em,U_oggi_T-2025),12)&" mesi" -> 68 anni e 9 mesi | C35: =INT(INDEX(PC_em,U_oggi_C-2025)/12)&" anni e "&MOD(INDEX(PC_em,U_oggi_C-2025),12)&" mesi" -> 73 anni e 8 mesi | D35: =INT(INDEX(PT_em,U_com-2025)/12)&" anni e "&MOD(INDEX(PT_em,U_com-2025),12)&" mesi" -> 68 anni e 9 mesi | E35: =INT(INDEX(PC_em,U_com-2025)/12)&" anni e "&MOD(INDEX(PC_em,U_com-2025),12)&" mesi" -> 69 anni e 3 mesi | F35: =INT(INDEX(PT_em,U_lib_T-2025)/12)&" anni e "&MOD(INDEX(PT_em,U_lib_T-2025),12)&" mesi" -> 68 anni e 9 mesi | G35: =INT(INDEX(PC_em,U_lib_C-2025)/12)&" anni e "&MOD(INDEX(PC_em,U_lib_C-2025),12)&" mesi" -> 69 anni e 3 mesi
A36: Pensione lorda | B36: =INDEX(PT_lorda,U_oggi_T-2025) -> 23475.13 | C36: =INDEX(PC_lorda,U_oggi_C-2025) -> 11884.227 | D36: =INDEX(PT_lorda,U_com-2025) -> 26966.501 | E36: =INDEX(PC_lorda,U_com-2025) -> 12798.692 | F36: =INDEX(PT_lorda,U_lib_T-2025) -> 23475.13 | G36: =INDEX(PC_lorda,U_lib_C-2025) -> 15377.773
A37: Pensione netta | B37: =INDEX(PT_netta,U_oggi_T-2025) -> 18597.564 | C37: =INDEX(PC_netta,U_oggi_C-2025) -> 10650.365 | D37: =INDEX(PT_netta,U_com-2025) -> 21041.391 | E37: =INDEX(PC_netta,U_com-2025) -> 11277.359 | F37: =INDEX(PT_netta,U_lib_T-2025) -> 18597.564 | G37: =INDEX(PC_netta,U_lib_C-2025) -> 13045.683
A38: Rapporto con il netto dello stipendio | B38: =B37/Tz_netto -> 0.53506034 | C38: =C37/Cm_netto -> 0.46551656 | D38: =D37/Tz_netto -> 0.60537035 | E38: =E37/Cm_netto -> 0.49292183 | F38: =F37/Tz_netto -> 0.53506034 | G38: =G37/Cm_netto -> 0.57021347
A39: Almeno l'assegno sociale annuo? | B39: =IF(B36>=p_AS*13,"sì","no") -> sì | C39: =IF(C36>=p_AS*13,"sì","no") -> sì | D39: =IF(D36>=p_AS*13,"sì","no") -> sì | E39: =IF(E36>=p_AS*13,"sì","no") -> sì | F39: =IF(F36>=p_AS*13,"sì","no") -> sì | G39: =IF(G36>=p_AS*13,"sì","no") -> sì
A41: Soglia dei 20 anni: con il primo contributo nel 2008, Camilla arriva a 20 anni se l'ultimo anno lavorato è il 2027 o dopo. Il salto fra 2026 e 2027 sposta la decorrenza di oltre quattro anni.
A46: Pensione di vecchiaia di Tiziano per ultimo anno lavorato (euro del 2026)
A47: Ultimo anno lavorato | B47: Anni di contributi | C47: Via 71 anni (1 = sì) | D47: Regola | E47: Anno decorrenza | F47: Mese decorrenza | G47: Età (mesi) | H47: Coefficiente | I47: Montante all'ultimo anno | J47: Pensione lorda | K47: Imposta netta | L47: Pensione netta | M47: Età alla decorrenza | N47: Rapporto con il netto
A48: 2026 | B48: =A48-Tz_primo+1 -> 23 | C48: =IF(B48<p_anni_min,1,0) -> 0 | D48: =IF(C48=1,"via dei 71 anni adeguati","vecchiaia ordinaria") -> vecchiaia ordinaria | E48: =IF(C48=1,Tz_v71_da,Tz_ord_da) -> 2046 | F48: =IF(C48=1,Tz_v71_dm,Tz_ord_dm) -> 12 | G48: =IF(C48=1,Tz_v71_em,Tz_ord_em) -> 825 | H48: =IF(C48=1,Tz_v71_cf,Tz_ord_cf) -> 0.0597 | I48: =Tz_m26*(1+p_g)^MAX(0,A48-2026)+p_comp*Tz_ral*IF(p_g=0,MAX(0,A48-2026),((1+p_g)^MAX(0,A48-2026)-1)/p_g) -> 355887.26 | J48: =I48*(1+p_g)^MAX(0,E48-A48)*H48 -> 23475.13 | K48: =MAX(0,IF(J48<=sc_L1,sc_A1*J48,IF(J48<=sc_L2,sc_B1+sc_A2*(J48-sc_L1),sc_B2+sc_A3*(J48-sc_L2)))-(IF(J48<=8500,1955,IF(J48<=28000,700+1255*(28000-J48)/19500,IF(J48<=50000,700*(50000-J48)/22000,0)))+IF(AND(J48>25000,J48<=29000),50,0))) -> 4408.0639 | L48: =J48-K48-IF(K48>0,p_add*J48,0) -> 18597.564 | M48: =INT(G48/12)&" anni e "&MOD(G48,12)&" mesi" -> 68 anni e 9 mesi | N48: =L48/Tz_netto -> 0.53506034
A49: 2027 | B49: =A49-Tz_primo+1 -> 24 | C49: =IF(B49<p_anni_min,1,0) -> 0 | D49: =IF(C49=1,"via dei 71 anni adeguati","vecchiaia ordinaria") -> vecchiaia ordinaria | E49: =IF(C49=1,Tz_v71_da,Tz_ord_da) -> 2046 | F49: =IF(C49=1,Tz_v71_dm,Tz_ord_dm) -> 12 | G49: =IF(C49=1,Tz_v71_em,Tz_ord_em) -> 825 | H49: =IF(C49=1,Tz_v71_cf,Tz_ord_cf) -> 0.0597 | I49: =Tz_m26*(1+p_g)^MAX(0,A49-2026)+p_comp*Tz_ral*IF(p_g=0,MAX(0,A49-2026),((1+p_g)^MAX(0,A49-2026)-1)/p_g) -> 375486.7 | J49: =I49*(1+p_g)^MAX(0,E49-A49)*H49 -> 24644.73 | K49: =MAX(0,IF(J49<=sc_L1,sc_A1*J49,IF(J49<=sc_L2,sc_B1+sc_A2*(J49-sc_L1),sc_B2+sc_A3*(J49-sc_L2)))-(IF(J49<=8500,1955,IF(J49<=28000,700+1255*(28000-J49)/19500,IF(J49<=50000,700*(50000-J49)/22000,0)))+IF(AND(J49>25000,J49<=29000),50,0))) -> 4752.3461 | L49: =J49-K49-IF(K49>0,p_add*J49,0) -> 19399.489 | M49: =INT(G49/12)&" anni e "&MOD(G49,12)&" mesi" -> 68 anni e 9 mesi | N49: =L49/Tz_netto -> 0.55813209
A50: 2028 | B50: =A50-Tz_primo+1 -> 25 | C50: =IF(B50<p_anni_min,1,0) -> 0 | D50: =IF(C50=1,"via dei 71 anni adeguati","vecchiaia ordinaria") -> vecchiaia ordinaria | E50: =IF(C50=1,Tz_v71_da,Tz_ord_da) -> 2046 | F50: =IF(C50=1,Tz_v71_dm,Tz_ord_dm) -> 12 | G50: =IF(C50=1,Tz_v71_em,Tz_ord_em) -> 825 | H50: =IF(C50=1,Tz_v71_cf,Tz_ord_cf) -> 0.0597 | I50: =Tz_m26*(1+p_g)^MAX(0,A50-2026)+p_comp*Tz_ral*IF(p_g=0,MAX(0,A50-2026),((1+p_g)^MAX(0,A50-2026)-1)/p_g) -> 395184.13 | J50: =I50*(1+p_g)^MAX(0,E50-A50)*H50 -> 25808.51 | K50: =MAX(0,IF(J50<=sc_L1,sc_A1*J50,IF(J50<=sc_L2,sc_B1+sc_A2*(J50-sc_L1),sc_B2+sc_A3*(J50-sc_L2)))-(IF(J50<=8500,1955,IF(J50<=28000,700+1255*(28000-J50)/19500,IF(J50<=50000,700*(50000-J50)/22000,0)))+IF(AND(J50>25000,J50<=29000),50,0))) -> 5044.9154 | L50: =J50-K50-IF(K50>0,p_add*J50,0) -> 20247.425 | M50: =INT(G50/12)&" anni e "&MOD(G50,12)&" mesi" -> 68 anni e 9 mesi | N50: =L50/Tz_netto -> 0.58252759
A51: 2029 | B51: =A51-Tz_primo+1 -> 26 | C51: =IF(B51<p_anni_min,1,0) -> 0 | D51: =IF(C51=1,"via dei 71 anni adeguati","vecchiaia ordinaria") -> vecchiaia ordinaria | E51: =IF(C51=1,Tz_v71_da,Tz_ord_da) -> 2046 | F51: =IF(C51=1,Tz_v71_dm,Tz_ord_dm) -> 12 | G51: =IF(C51=1,Tz_v71_em,Tz_ord_em) -> 825 | H51: =IF(C51=1,Tz_v71_cf,Tz_ord_cf) -> 0.0597 | I51: =Tz_m26*(1+p_g)^MAX(0,A51-2026)+p_comp*Tz_ral*IF(p_g=0,MAX(0,A51-2026),((1+p_g)^MAX(0,A51-2026)-1)/p_g) -> 414980.05 | J51: =I51*(1+p_g)^MAX(0,E51-A51)*H51 -> 26966.501 | K51: =MAX(0,IF(J51<=sc_L1,sc_A1*J51,IF(J51<=sc_L2,sc_B1+sc_A2*(J51-sc_L1),sc_B2+sc_A3*(J51-sc_L2)))-(IF(J51<=8500,1955,IF(J51<=28000,700+1255*(28000-J51)/19500,IF(J51<=50000,700*(50000-J51)/22000,0)))+IF(AND(J51>25000,J51<=29000),50,0))) -> 5385.7803 | L51: =J51-K51-IF(K51>0,p_add*J51,0) -> 21041.391 | M51: =INT(G51/12)&" anni e "&MOD(G51,12)&" mesi" -> 68 anni e 9 mesi | N51: =L51/Tz_netto -> 0.60537035
A52: 2030 | B52: =A52-Tz_primo+1 -> 27 | C52: =IF(B52<p_anni_min,1,0) -> 0 | D52: =IF(C52=1,"via dei 71 anni adeguati","vecchiaia ordinaria") -> vecchiaia ordinaria | E52: =IF(C52=1,Tz_v71_da,Tz_ord_da) -> 2046 | F52: =IF(C52=1,Tz_v71_dm,Tz_ord_dm) -> 12 | G52: =IF(C52=1,Tz_v71_em,Tz_ord_em) -> 825 | H52: =IF(C52=1,Tz_v71_cf,Tz_ord_cf) -> 0.0597 | I52: =Tz_m26*(1+p_g)^MAX(0,A52-2026)+p_comp*Tz_ral*IF(p_g=0,MAX(0,A52-2026),((1+p_g)^MAX(0,A52-2026)-1)/p_g) -> 434874.95 | J52: =I52*(1+p_g)^MAX(0,E52-A52)*H52 -> 28118.731 | K52: =MAX(0,IF(J52<=sc_L1,sc_A1*J52,IF(J52<=sc_L2,sc_B1+sc_A2*(J52-sc_L1),sc_B2+sc_A3*(J52-sc_L2)))-(IF(J52<=8500,1955,IF(J52<=28000,700+1255*(28000-J52)/19500,IF(J52<=50000,700*(50000-J52)/22000,0)))+IF(AND(J52>25000,J52<=29000),50,0))) -> 5732.9589 | L52: =J52-K52-IF(K52>0,p_add*J52,0) -> 21823.397 | M52: =INT(G52/12)&" anni e "&MOD(G52,12)&" mesi" -> 68 anni e 9 mesi | N52: =L52/Tz_netto -> 0.62786903
A53: 2031 | B53: =A53-Tz_primo+1 -> 28 | C53: =IF(B53<p_anni_min,1,0) -> 0 | D53: =IF(C53=1,"via dei 71 anni adeguati","vecchiaia ordinaria") -> vecchiaia ordinaria | E53: =IF(C53=1,Tz_v71_da,Tz_ord_da) -> 2046 | F53: =IF(C53=1,Tz_v71_dm,Tz_ord_dm) -> 12 | G53: =IF(C53=1,Tz_v71_em,Tz_ord_em) -> 825 | H53: =IF(C53=1,Tz_v71_cf,Tz_ord_cf) -> 0.0597 | I53: =Tz_m26*(1+p_g)^MAX(0,A53-2026)+p_comp*Tz_ral*IF(p_g=0,MAX(0,A53-2026),((1+p_g)^MAX(0,A53-2026)-1)/p_g) -> 454869.33 | J53: =I53*(1+p_g)^MAX(0,E53-A53)*H53 -> 29265.228 | K53: =MAX(0,IF(J53<=sc_L1,sc_A1*J53,IF(J53<=sc_L2,sc_B1+sc_A2*(J53-sc_L1),sc_B2+sc_A3*(J53-sc_L2)))-(IF(J53<=8500,1955,IF(J53<=28000,700+1255*(28000-J53)/19500,IF(J53<=50000,700*(50000-J53)/22000,0)))+IF(AND(J53>25000,J53<=29000),50,0))) -> 6197.7824 | L53: =J53-K53-IF(K53>0,p_add*J53,0) -> 22482.141 | M53: =INT(G53/12)&" anni e "&MOD(G53,12)&" mesi" -> 68 anni e 9 mesi | N53: =L53/Tz_netto -> 0.64682138
A54: 2032 | B54: =A54-Tz_primo+1 -> 29 | C54: =IF(B54<p_anni_min,1,0) -> 0 | D54: =IF(C54=1,"via dei 71 anni adeguati","vecchiaia ordinaria") -> vecchiaia ordinaria | E54: =IF(C54=1,Tz_v71_da,Tz_ord_da) -> 2046 | F54: =IF(C54=1,Tz_v71_dm,Tz_ord_dm) -> 12 | G54: =IF(C54=1,Tz_v71_em,Tz_ord_em) -> 825 | H54: =IF(C54=1,Tz_v71_cf,Tz_ord_cf) -> 0.0597 | I54: =Tz_m26*(1+p_g)^MAX(0,A54-2026)+p_comp*Tz_ral*IF(p_g=0,MAX(0,A54-2026),((1+p_g)^MAX(0,A54-2026)-1)/p_g) -> 474963.67 | J54: =I54*(1+p_g)^MAX(0,E54-A54)*H54 -> 30406.021 | K54: =MAX(0,IF(J54<=sc_L1,sc_A1*J54,IF(J54<=sc_L2,sc_B1+sc_A2*(J54-sc_L1),sc_B2+sc_A3*(J54-sc_L2)))-(IF(J54<=8500,1955,IF(J54<=28000,700+1255*(28000-J54)/19500,IF(J54<=50000,700*(50000-J54)/22000,0)))+IF(AND(J54>25000,J54<=29000),50,0))) -> 6610.5421 | L54: =J54-K54-IF(K54>0,p_add*J54,0) -> 23187.358 | M54: =INT(G54/12)&" anni e "&MOD(G54,12)&" mesi" -> 68 anni e 9 mesi | N54: =L54/Tz_netto -> 0.66711081
A55: 2033 | B55: =A55-Tz_primo+1 -> 30 | C55: =IF(B55<p_anni_min,1,0) -> 0 | D55: =IF(C55=1,"via dei 71 anni adeguati","vecchiaia ordinaria") -> vecchiaia ordinaria | E55: =IF(C55=1,Tz_v71_da,Tz_ord_da) -> 2046 | F55: =IF(C55=1,Tz_v71_dm,Tz_ord_dm) -> 12 | G55: =IF(C55=1,Tz_v71_em,Tz_ord_em) -> 825 | H55: =IF(C55=1,Tz_v71_cf,Tz_ord_cf) -> 0.0597 | I55: =Tz_m26*(1+p_g)^MAX(0,A55-2026)+p_comp*Tz_ral*IF(p_g=0,MAX(0,A55-2026),((1+p_g)^MAX(0,A55-2026)-1)/p_g) -> 495158.49 | J55: =I55*(1+p_g)^MAX(0,E55-A55)*H55 -> 31541.138 | K55: =MAX(0,IF(J55<=sc_L1,sc_A1*J55,IF(J55<=sc_L2,sc_B1+sc_A2*(J55-sc_L1),sc_B2+sc_A3*(J55-sc_L2)))-(IF(J55<=8500,1955,IF(J55<=28000,700+1255*(28000-J55)/19500,IF(J55<=50000,700*(50000-J55)/22000,0)))+IF(AND(J55>25000,J55<=29000),50,0))) -> 7021.2483 | L55: =J55-K55-IF(K55>0,p_add*J55,0) -> 23889.067 | M55: =INT(G55/12)&" anni e "&MOD(G55,12)&" mesi" -> 68 anni e 9 mesi | N55: =L55/Tz_netto -> 0.6872993
A56: 2034 | B56: =A56-Tz_primo+1 -> 31 | C56: =IF(B56<p_anni_min,1,0) -> 0 | D56: =IF(C56=1,"via dei 71 anni adeguati","vecchiaia ordinaria") -> vecchiaia ordinaria | E56: =IF(C56=1,Tz_v71_da,Tz_ord_da) -> 2046 | F56: =IF(C56=1,Tz_v71_dm,Tz_ord_dm) -> 12 | G56: =IF(C56=1,Tz_v71_em,Tz_ord_em) -> 825 | H56: =IF(C56=1,Tz_v71_cf,Tz_ord_cf) -> 0.0597 | I56: =Tz_m26*(1+p_g)^MAX(0,A56-2026)+p_comp*Tz_ral*IF(p_g=0,MAX(0,A56-2026),((1+p_g)^MAX(0,A56-2026)-1)/p_g) -> 515454.28 | J56: =I56*(1+p_g)^MAX(0,E56-A56)*H56 -> 32670.609 | K56: =MAX(0,IF(J56<=sc_L1,sc_A1*J56,IF(J56<=sc_L2,sc_B1+sc_A2*(J56-sc_L1),sc_B2+sc_A3*(J56-sc_L2)))-(IF(J56<=8500,1955,IF(J56<=28000,700+1255*(28000-J56)/19500,IF(J56<=50000,700*(50000-J56)/22000,0)))+IF(AND(J56>25000,J56<=29000),50,0))) -> 7429.9111 | L56: =J56-K56-IF(K56>0,p_add*J56,0) -> 24587.285 | M56: =INT(G56/12)&" anni e "&MOD(G56,12)&" mesi" -> 68 anni e 9 mesi | N56: =L56/Tz_netto -> 0.70738735
A57: 2035 | B57: =A57-Tz_primo+1 -> 32 | C57: =IF(B57<p_anni_min,1,0) -> 0 | D57: =IF(C57=1,"via dei 71 anni adeguati","vecchiaia ordinaria") -> vecchiaia ordinaria | E57: =IF(C57=1,Tz_v71_da,Tz_ord_da) -> 2046 | F57: =IF(C57=1,Tz_v71_dm,Tz_ord_dm) -> 12 | G57: =IF(C57=1,Tz_v71_em,Tz_ord_em) -> 825 | H57: =IF(C57=1,Tz_v71_cf,Tz_ord_cf) -> 0.0597 | I57: =Tz_m26*(1+p_g)^MAX(0,A57-2026)+p_comp*Tz_ral*IF(p_g=0,MAX(0,A57-2026),((1+p_g)^MAX(0,A57-2026)-1)/p_g) -> 535851.55 | J57: =I57*(1+p_g)^MAX(0,E57-A57)*H57 -> 33794.46 | K57: =MAX(0,IF(J57<=sc_L1,sc_A1*J57,IF(J57<=sc_L2,sc_B1+sc_A2*(J57-sc_L1),sc_B2+sc_A3*(J57-sc_L2)))-(IF(J57<=8500,1955,IF(J57<=28000,700+1255*(28000-J57)/19500,IF(J57<=50000,700*(50000-J57)/22000,0)))+IF(AND(J57>25000,J57<=29000),50,0))) -> 7836.5408 | L57: =J57-K57-IF(K57>0,p_add*J57,0) -> 25282.03 | M57: =INT(G57/12)&" anni e "&MOD(G57,12)&" mesi" -> 68 anni e 9 mesi | N57: =L57/Tz_netto -> 0.72737545
A58: 2036 | B58: =A58-Tz_primo+1 -> 33 | C58: =IF(B58<p_anni_min,1,0) -> 0 | D58: =IF(C58=1,"via dei 71 anni adeguati","vecchiaia ordinaria") -> vecchiaia ordinaria | E58: =IF(C58=1,Tz_v71_da,Tz_ord_da) -> 2046 | F58: =IF(C58=1,Tz_v71_dm,Tz_ord_dm) -> 12 | G58: =IF(C58=1,Tz_v71_em,Tz_ord_em) -> 825 | H58: =IF(C58=1,Tz_v71_cf,Tz_ord_cf) -> 0.0597 | I58: =Tz_m26*(1+p_g)^MAX(0,A58-2026)+p_comp*Tz_ral*IF(p_g=0,MAX(0,A58-2026),((1+p_g)^MAX(0,A58-2026)-1)/p_g) -> 556350.81 | J58: =I58*(1+p_g)^MAX(0,E58-A58)*H58 -> 34912.719 | K58: =MAX(0,IF(J58<=sc_L1,sc_A1*J58,IF(J58<=sc_L2,sc_B1+sc_A2*(J58-sc_L1),sc_B2+sc_A3*(J58-sc_L2)))-(IF(J58<=8500,1955,IF(J58<=28000,700+1255*(28000-J58)/19500,IF(J58<=50000,700*(50000-J58)/22000,0)))+IF(AND(J58>25000,J58<=29000),50,0))) -> 8241.1475 | L58: =J58-K58-IF(K58>0,p_add*J58,0) -> 25973.317 | M58: =INT(G58/12)&" anni e "&MOD(G58,12)&" mesi" -> 68 anni e 9 mesi | N58: =L58/Tz_netto -> 0.74726411
A59: 2037 | B59: =A59-Tz_primo+1 -> 34 | C59: =IF(B59<p_anni_min,1,0) -> 0 | D59: =IF(C59=1,"via dei 71 anni adeguati","vecchiaia ordinaria") -> vecchiaia ordinaria | E59: =IF(C59=1,Tz_v71_da,Tz_ord_da) -> 2046 | F59: =IF(C59=1,Tz_v71_dm,Tz_ord_dm) -> 12 | G59: =IF(C59=1,Tz_v71_em,Tz_ord_em) -> 825 | H59: =IF(C59=1,Tz_v71_cf,Tz_ord_cf) -> 0.0597 | I59: =Tz_m26*(1+p_g)^MAX(0,A59-2026)+p_comp*Tz_ral*IF(p_g=0,MAX(0,A59-2026),((1+p_g)^MAX(0,A59-2026)-1)/p_g) -> 576952.57 | J59: =I59*(1+p_g)^MAX(0,E59-A59)*H59 -> 36025.415 | K59: =MAX(0,IF(J59<=sc_L1,sc_A1*J59,IF(J59<=sc_L2,sc_B1+sc_A2*(J59-sc_L1),sc_B2+sc_A3*(J59-sc_L2)))-(IF(J59<=8500,1955,IF(J59<=28000,700+1255*(28000-J59)/19500,IF(J59<=50000,700*(50000-J59)/22000,0)))+IF(AND(J59>25000,J59<=29000),50,0))) -> 8643.7412 | L59: =J59-K59-IF(K59>0,p_add*J59,0) -> 26661.166 | M59: =INT(G59/12)&" anni e "&MOD(G59,12)&" mesi" -> 68 anni e 9 mesi | N59: =L59/Tz_netto -> 0.76705383
... A68: 2046 | B68: =A68-Tz_primo+1 -> 43 | C68: =IF(B68<p_anni_min,1,0) -> 0 | D68: =IF(C68=1,"via dei 71 anni adeguati","vecchiaia ordinaria") -> vecchiaia ordinaria | E68: =IF(C68=1,Tz_v71_da,Tz_ord_da) -> 2046 | F68: =IF(C68=1,Tz_v71_dm,Tz_ord_dm) -> 12 | G68: =IF(C68=1,Tz_v71_em,Tz_ord_em) -> 825 | H68: =IF(C68=1,Tz_v71_cf,Tz_ord_cf) -> 0.0597 | I68: =Tz_m26*(1+p_g)^MAX(0,A68-2026)+p_comp*Tz_ral*IF(p_g=0,MAX(0,A68-2026),((1+p_g)^MAX(0,A68-2026)-1)/p_g) -> 767066.1 | J68: =I68*(1+p_g)^MAX(0,E68-A68)*H68 -> 45793.846 | K68: =MAX(0,IF(J68<=sc_L1,sc_A1*J68,IF(J68<=sc_L2,sc_B1+sc_A2*(J68-sc_L1),sc_B2+sc_A3*(J68-sc_L2)))-(IF(J68<=8500,1955,IF(J68<=28000,700+1255*(28000-J68)/19500,IF(J68<=50000,700*(50000-J68)/22000,0)))+IF(AND(J68>25000,J68<=29000),50,0))) -> 12178.137 | L68: =J68-K68-IF(K68>0,p_add*J68,0) -> 32699.832 | M68: =INT(G68/12)&" anni e "&MOD(G68,12)&" mesi" -> 68 anni e 9 mesi | N68: =L68/Tz_netto -> 0.94078899
A70: Pensione di vecchiaia di Camilla per ultimo anno lavorato (euro del 2026)
A71: Ultimo anno lavorato | B71: Anni di contributi | C71: Via 71 anni (1 = sì) | D71: Regola | E71: Anno decorrenza | F71: Mese decorrenza | G71: Età (mesi) | H71: Coefficiente | I71: Montante all'ultimo anno | J71: Pensione lorda | K71: Imposta netta | L71: Pensione netta | M71: Età alla decorrenza | N71: Rapporto con il netto
A72: 2026 | B72: =A72-Cm_primo+1 -> 19 | C72: =IF(B72<p_anni_min,1,0) -> 1 | D72: =IF(C72=1,"via dei 71 anni adeguati","vecchiaia ordinaria") -> via dei 71 anni adeguati | E72: =IF(C72=1,Cm_v71_da,Cm_ord_da) -> 2057 | F72: =IF(C72=1,Cm_v71_dm,Cm_ord_dm) -> 5 | G72: =IF(C72=1,Cm_v71_em,Cm_ord_em) -> 884 | H72: =IF(C72=1,Cm_v71_cf,Cm_ord_cf) -> 0.0651 | I72: =Cm_m26*(1+p_g)^MAX(0,A72-2026)+p_comp*Cm_ral*IF(p_g=0,MAX(0,A72-2026),((1+p_g)^MAX(0,A72-2026)-1)/p_g) -> 156401.91 | J72: =I72*(1+p_g)^MAX(0,E72-A72)*H72 -> 11884.227 | K72: =MAX(0,IF(J72<=sc_L1,sc_A1*J72,IF(J72<=sc_L2,sc_B1+sc_A2*(J72-sc_L1),sc_B2+sc_A3*(J72-sc_L2)))-(IF(J72<=8500,1955,IF(J72<=28000,700+1255*(28000-J72)/19500,IF(J72<=50000,700*(50000-J72)/22000,0)))+IF(AND(J72>25000,J72<=29000),50,0))) -> 996.17772 | L72: =J72-K72-IF(K72>0,p_add*J72,0) -> 10650.365 | M72: =INT(G72/12)&" anni e "&MOD(G72,12)&" mesi" -> 73 anni e 8 mesi | N72: =L72/Cm_netto -> 0.46551656
A73: 2027 | B73: =A73-Cm_primo+1 -> 20 | C73: =IF(B73<p_anni_min,1,0) -> 0 | D73: =IF(C73=1,"via dei 71 anni adeguati","vecchiaia ordinaria") -> vecchiaia ordinaria | E73: =IF(C73=1,Cm_v71_da,Cm_ord_da) -> 2052 | F73: =IF(C73=1,Cm_v71_dm,Cm_ord_dm) -> 12 | G73: =IF(C73=1,Cm_v71_em,Cm_ord_em) -> 831 | H73: =IF(C73=1,Cm_v71_cf,Cm_ord_cf) -> 0.060825 | I73: =Cm_m26*(1+p_g)^MAX(0,A73-2026)+p_comp*Cm_ral*IF(p_g=0,MAX(0,A73-2026),((1+p_g)^MAX(0,A73-2026)-1)/p_g) -> 166753.92 | J73: =I73*(1+p_g)^MAX(0,E73-A73)*H73 -> 11489.727 | K73: =MAX(0,IF(J73<=sc_L1,sc_A1*J73,IF(J73<=sc_L2,sc_B1+sc_A2*(J73-sc_L1),sc_B2+sc_A3*(J73-sc_L2)))-(IF(J73<=8500,1955,IF(J73<=28000,700+1255*(28000-J73)/19500,IF(J73<=50000,700*(50000-J73)/22000,0)))+IF(AND(J73>25000,J73<=29000),50,0))) -> 880.05299 | L73: =J73-K73-IF(K73>0,p_add*J73,0) -> 10379.88 | M73: =INT(G73/12)&" anni e "&MOD(G73,12)&" mesi" -> 69 anni e 3 mesi | N73: =L73/Cm_netto -> 0.45369391
A74: 2028 | B74: =A74-Cm_primo+1 -> 21 | C74: =IF(B74<p_anni_min,1,0) -> 0 | D74: =IF(C74=1,"via dei 71 anni adeguati","vecchiaia ordinaria") -> vecchiaia ordinaria | E74: =IF(C74=1,Cm_v71_da,Cm_ord_da) -> 2052 | F74: =IF(C74=1,Cm_v71_dm,Cm_ord_dm) -> 12 | G74: =IF(C74=1,Cm_v71_em,Cm_ord_em) -> 831 | H74: =IF(C74=1,Cm_v71_cf,Cm_ord_cf) -> 0.060825 | I74: =Cm_m26*(1+p_g)^MAX(0,A74-2026)+p_comp*Cm_ral*IF(p_g=0,MAX(0,A74-2026),((1+p_g)^MAX(0,A74-2026)-1)/p_g) -> 177157.69 | J74: =I74*(1+p_g)^MAX(0,E74-A74)*H74 -> 12145.841 | K74: =MAX(0,IF(J74<=sc_L1,sc_A1*J74,IF(J74<=sc_L2,sc_B1+sc_A2*(J74-sc_L1),sc_B2+sc_A3*(J74-sc_L2)))-(IF(J74<=8500,1955,IF(J74<=28000,700+1255*(28000-J74)/19500,IF(J74<=50000,700*(50000-J74)/22000,0)))+IF(AND(J74>25000,J74<=29000),50,0))) -> 1073.1861 | L74: =J74-K74-IF(K74>0,p_add*J74,0) -> 10829.738 | M74: =INT(G74/12)&" anni e "&MOD(G74,12)&" mesi" -> 69 anni e 3 mesi | N74: =L74/Cm_netto -> 0.47335678
A75: 2029 | B75: =A75-Cm_primo+1 -> 22 | C75: =IF(B75<p_anni_min,1,0) -> 0 | D75: =IF(C75=1,"via dei 71 anni adeguati","vecchiaia ordinaria") -> vecchiaia ordinaria | E75: =IF(C75=1,Cm_v71_da,Cm_ord_da) -> 2052 | F75: =IF(C75=1,Cm_v71_dm,Cm_ord_dm) -> 12 | G75: =IF(C75=1,Cm_v71_em,Cm_ord_em) -> 831 | H75: =IF(C75=1,Cm_v71_cf,Cm_ord_cf) -> 0.060825 | I75: =Cm_m26*(1+p_g)^MAX(0,A75-2026)+p_comp*Cm_ral*IF(p_g=0,MAX(0,A75-2026),((1+p_g)^MAX(0,A75-2026)-1)/p_g) -> 187613.48 | J75: =I75*(1+p_g)^MAX(0,E75-A75)*H75 -> 12798.692 | K75: =MAX(0,IF(J75<=sc_L1,sc_A1*J75,IF(J75<=sc_L2,sc_B1+sc_A2*(J75-sc_L1),sc_B2+sc_A3*(J75-sc_L2)))-(IF(J75<=8500,1955,IF(J75<=28000,700+1255*(28000-J75)/19500,IF(J75<=50000,700*(50000-J75)/22000,0)))+IF(AND(J75>25000,J75<=29000),50,0))) -> 1265.3584 | L75: =J75-K75-IF(K75>0,p_add*J75,0) -> 11277.359 | M75: =INT(G75/12)&" anni e "&MOD(G75,12)&" mesi" -> 69 anni e 3 mesi | N75: =L75/Cm_netto -> 0.49292183
A76: 2030 | B76: =A76-Cm_primo+1 -> 23 | C76: =IF(B76<p_anni_min,1,0) -> 0 | D76: =IF(C76=1,"via dei 71 anni adeguati","vecchiaia ordinaria") -> vecchiaia ordinaria | E76: =IF(C76=1,Cm_v71_da,Cm_ord_da) -> 2052 | F76: =IF(C76=1,Cm_v71_dm,Cm_ord_dm) -> 12 | G76: =IF(C76=1,Cm_v71_em,Cm_ord_em) -> 831 | H76: =IF(C76=1,Cm_v71_cf,Cm_ord_cf) -> 0.060825 | I76: =Cm_m26*(1+p_g)^MAX(0,A76-2026)+p_comp*Cm_ral*IF(p_g=0,MAX(0,A76-2026),((1+p_g)^MAX(0,A76-2026)-1)/p_g) -> 198121.54 | J76: =I76*(1+p_g)^MAX(0,E76-A76)*H76 -> 13448.294 | K76: =MAX(0,IF(J76<=sc_L1,sc_A1*J76,IF(J76<=sc_L2,sc_B1+sc_A2*(J76-sc_L1),sc_B2+sc_A3*(J76-sc_L2)))-(IF(J76<=8500,1955,IF(J76<=28000,700+1255*(28000-J76)/19500,IF(J76<=50000,700*(50000-J76)/22000,0)))+IF(AND(J76>25000,J76<=29000),50,0))) -> 1456.5746 | L76: =J76-K76-IF(K76>0,p_add*J76,0) -> 11722.753 | M76: =INT(G76/12)&" anni e "&MOD(G76,12)&" mesi" -> 69 anni e 3 mesi | N76: =L76/Cm_netto -> 0.51238954
A77: 2031 | B77: =A77-Cm_primo+1 -> 24 | C77: =IF(B77<p_anni_min,1,0) -> 0 | D77: =IF(C77=1,"via dei 71 anni adeguati","vecchiaia ordinaria") -> vecchiaia ordinaria | E77: =IF(C77=1,Cm_v71_da,Cm_ord_da) -> 2052 | F77: =IF(C77=1,Cm_v71_dm,Cm_ord_dm) -> 12 | G77: =IF(C77=1,Cm_v71_em,Cm_ord_em) -> 831 | H77: =IF(C77=1,Cm_v71_cf,Cm_ord_cf) -> 0.060825 | I77: =Cm_m26*(1+p_g)^MAX(0,A77-2026)+p_comp*Cm_ral*IF(p_g=0,MAX(0,A77-2026),((1+p_g)^MAX(0,A77-2026)-1)/p_g) -> 208682.15 | J77: =I77*(1+p_g)^MAX(0,E77-A77)*H77 -> 14094.664 | K77: =MAX(0,IF(J77<=sc_L1,sc_A1*J77,IF(J77<=sc_L2,sc_B1+sc_A2*(J77-sc_L1),sc_B2+sc_A3*(J77-sc_L2)))-(IF(J77<=8500,1955,IF(J77<=28000,700+1255*(28000-J77)/19500,IF(J77<=50000,700*(50000-J77)/22000,0)))+IF(AND(J77>25000,J77<=29000),50,0))) -> 1646.8395 | L77: =J77-K77-IF(K77>0,p_add*J77,0) -> 12165.931 | M77: =INT(G77/12)&" anni e "&MOD(G77,12)&" mesi" -> 69 anni e 3 mesi | N77: =L77/Cm_netto -> 0.53176039
A78: 2032 | B78: =A78-Cm_primo+1 -> 25 | C78: =IF(B78<p_anni_min,1,0) -> 0 | D78: =IF(C78=1,"via dei 71 anni adeguati","vecchiaia ordinaria") -> vecchiaia ordinaria | E78: =IF(C78=1,Cm_v71_da,Cm_ord_da) -> 2052 | F78: =IF(C78=1,Cm_v71_dm,Cm_ord_dm) -> 12 | G78: =IF(C78=1,Cm_v71_em,Cm_ord_em) -> 831 | H78: =IF(C78=1,Cm_v71_cf,Cm_ord_cf) -> 0.060825 | I78: =Cm_m26*(1+p_g)^MAX(0,A78-2026)+p_comp*Cm_ral*IF(p_g=0,MAX(0,A78-2026),((1+p_g)^MAX(0,A78-2026)-1)/p_g) -> 219295.56 | J78: =I78*(1+p_g)^MAX(0,E78-A78)*H78 -> 14737.818 | K78: =MAX(0,IF(J78<=sc_L1,sc_A1*J78,IF(J78<=sc_L2,sc_B1+sc_A2*(J78-sc_L1),sc_B2+sc_A3*(J78-sc_L2)))-(IF(J78<=8500,1955,IF(J78<=28000,700+1255*(28000-J78)/19500,IF(J78<=50000,700*(50000-J78)/22000,0)))+IF(AND(J78>25000,J78<=29000),50,0))) -> 1836.1578 | L78: =J78-K78-IF(K78>0,p_add*J78,0) -> 12606.904 | M78: =INT(G78/12)&" anni e "&MOD(G78,12)&" mesi" -> 69 anni e 3 mesi | N78: =L78/Cm_netto -> 0.55103488
A79: 2033 | B79: =A79-Cm_primo+1 -> 26 | C79: =IF(B79<p_anni_min,1,0) -> 0 | D79: =IF(C79=1,"via dei 71 anni adeguati","vecchiaia ordinaria") -> vecchiaia ordinaria | E79: =IF(C79=1,Cm_v71_da,Cm_ord_da) -> 2052 | F79: =IF(C79=1,Cm_v71_dm,Cm_ord_dm) -> 12 | G79: =IF(C79=1,Cm_v71_em,Cm_ord_em) -> 831 | H79: =IF(C79=1,Cm_v71_cf,Cm_ord_cf) -> 0.060825 | I79: =Cm_m26*(1+p_g)^MAX(0,A79-2026)+p_comp*Cm_ral*IF(p_g=0,MAX(0,A79-2026),((1+p_g)^MAX(0,A79-2026)-1)/p_g) -> 229962.04 | J79: =I79*(1+p_g)^MAX(0,E79-A79)*H79 -> 15377.773 | K79: =MAX(0,IF(J79<=sc_L1,sc_A1*J79,IF(J79<=sc_L2,sc_B1+sc_A2*(J79-sc_L1),sc_B2+sc_A3*(J79-sc_L2)))-(IF(J79<=8500,1955,IF(J79<=28000,700+1255*(28000-J79)/19500,IF(J79<=50000,700*(50000-J79)/22000,0)))+IF(AND(J79>25000,J79<=29000),50,0))) -> 2024.5342 | L79: =J79-K79-IF(K79>0,p_add*J79,0) -> 13045.683 | M79: =INT(G79/12)&" anni e "&MOD(G79,12)&" mesi" -> 69 anni e 3 mesi | N79: =L79/Cm_netto -> 0.57021347
A80: 2034 | B80: =A80-Cm_primo+1 -> 27 | C80: =IF(B80<p_anni_min,1,0) -> 0 | D80: =IF(C80=1,"via dei 71 anni adeguati","vecchiaia ordinaria") -> vecchiaia ordinaria | E80: =IF(C80=1,Cm_v71_da,Cm_ord_da) -> 2052 | F80: =IF(C80=1,Cm_v71_dm,Cm_ord_dm) -> 12 | G80: =IF(C80=1,Cm_v71_em,Cm_ord_em) -> 831 | H80: =IF(C80=1,Cm_v71_cf,Cm_ord_cf) -> 0.060825 | I80: =Cm_m26*(1+p_g)^MAX(0,A80-2026)+p_comp*Cm_ral*IF(p_g=0,MAX(0,A80-2026),((1+p_g)^MAX(0,A80-2026)-1)/p_g) -> 240681.85 | J80: =I80*(1+p_g)^MAX(0,E80-A80)*H80 -> 16014.544 | K80: =MAX(0,IF(J80<=sc_L1,sc_A1*J80,IF(J80<=sc_L2,sc_B1+sc_A2*(J80-sc_L1),sc_B2+sc_A3*(J80-sc_L2)))-(IF(J80<=8500,1955,IF(J80<=28000,700+1255*(28000-J80)/19500,IF(J80<=50000,700*(50000-J80)/22000,0)))+IF(AND(J80>25000,J80<=29000),50,0))) -> 2211.9734 | L80: =J80-K80-IF(K80>0,p_add*J80,0) -> 13482.28 | M80: =INT(G80/12)&" anni e "&MOD(G80,12)&" mesi" -> 69 anni e 3 mesi | N80: =L80/Cm_netto -> 0.58929664
A81: 2035 | B81: =A81-Cm_primo+1 -> 28 | C81: =IF(B81<p_anni_min,1,0) -> 0 | D81: =IF(C81=1,"via dei 71 anni adeguati","vecchiaia ordinaria") -> vecchiaia ordinaria | E81: =IF(C81=1,Cm_v71_da,Cm_ord_da) -> 2052 | F81: =IF(C81=1,Cm_v71_dm,Cm_ord_dm) -> 12 | G81: =IF(C81=1,Cm_v71_em,Cm_ord_em) -> 831 | H81: =IF(C81=1,Cm_v71_cf,Cm_ord_cf) -> 0.060825 | I81: =Cm_m26*(1+p_g)^MAX(0,A81-2026)+p_comp*Cm_ral*IF(p_g=0,MAX(0,A81-2026),((1+p_g)^MAX(0,A81-2026)-1)/p_g) -> 251455.26 | J81: =I81*(1+p_g)^MAX(0,E81-A81)*H81 -> 16648.147 | K81: =MAX(0,IF(J81<=sc_L1,sc_A1*J81,IF(J81<=sc_L2,sc_B1+sc_A2*(J81-sc_L1),sc_B2+sc_A3*(J81-sc_L2)))-(IF(J81<=8500,1955,IF(J81<=28000,700+1255*(28000-J81)/19500,IF(J81<=50000,700*(50000-J81)/22000,0)))+IF(AND(J81>25000,J81<=29000),50,0))) -> 2398.4801 | L81: =J81-K81-IF(K81>0,p_add*J81,0) -> 13916.704 | M81: =INT(G81/12)&" anni e "&MOD(G81,12)&" mesi" -> 69 anni e 3 mesi | N81: =L81/Cm_netto -> 0.60828487
A82: 2036 | B82: =A82-Cm_primo+1 -> 29 | C82: =IF(B82<p_anni_min,1,0) -> 0 | D82: =IF(C82=1,"via dei 71 anni adeguati","vecchiaia ordinaria") -> vecchiaia ordinaria | E82: =IF(C82=1,Cm_v71_da,Cm_ord_da) -> 2052 | F82: =IF(C82=1,Cm_v71_dm,Cm_ord_dm) -> 12 | G82: =IF(C82=1,Cm_v71_em,Cm_ord_em) -> 831 | H82: =IF(C82=1,Cm_v71_cf,Cm_ord_cf) -> 0.060825 | I82: =Cm_m26*(1+p_g)^MAX(0,A82-2026)+p_comp*Cm_ral*IF(p_g=0,MAX(0,A82-2026),((1+p_g)^MAX(0,A82-2026)-1)/p_g) -> 262282.54 | J82: =I82*(1+p_g)^MAX(0,E82-A82)*H82 -> 17278.597 | K82: =MAX(0,IF(J82<=sc_L1,sc_A1*J82,IF(J82<=sc_L2,sc_B1+sc_A2*(J82-sc_L1),sc_B2+sc_A3*(J82-sc_L2)))-(IF(J82<=8500,1955,IF(J82<=28000,700+1255*(28000-J82)/19500,IF(J82<=50000,700*(50000-J82)/22000,0)))+IF(AND(J82>25000,J82<=29000),50,0))) -> 2584.0589 | L82: =J82-K82-IF(K82>0,p_add*J82,0) -> 14348.966 | M82: =INT(G82/12)&" anni e "&MOD(G82,12)&" mesi" -> 69 anni e 3 mesi | N82: =L82/Cm_netto -> 0.62717864
A83: 2037 | B83: =A83-Cm_primo+1 -> 30 | C83: =IF(B83<p_anni_min,1,0) -> 0 | D83: =IF(C83=1,"via dei 71 anni adeguati","vecchiaia ordinaria") -> vecchiaia ordinaria | E83: =IF(C83=1,Cm_v71_da,Cm_ord_da) -> 2052 | F83: =IF(C83=1,Cm_v71_dm,Cm_ord_dm) -> 12 | G83: =IF(C83=1,Cm_v71_em,Cm_ord_em) -> 831 | H83: =IF(C83=1,Cm_v71_cf,Cm_ord_cf) -> 0.060825 | I83: =Cm_m26*(1+p_g)^MAX(0,A83-2026)+p_comp*Cm_ral*IF(p_g=0,MAX(0,A83-2026),((1+p_g)^MAX(0,A83-2026)-1)/p_g) -> 273163.95 | J83: =I83*(1+p_g)^MAX(0,E83-A83)*H83 -> 17905.911 | K83: =MAX(0,IF(J83<=sc_L1,sc_A1*J83,IF(J83<=sc_L2,sc_B1+sc_A2*(J83-sc_L1),sc_B2+sc_A3*(J83-sc_L2)))-(IF(J83<=8500,1955,IF(J83<=28000,700+1255*(28000-J83)/19500,IF(J83<=50000,700*(50000-J83)/22000,0)))+IF(AND(J83>25000,J83<=29000),50,0))) -> 2768.7144 | L83: =J83-K83-IF(K83>0,p_add*J83,0) -> 14779.079 | M83: =INT(G83/12)&" anni e "&MOD(G83,12)&" mesi" -> 69 anni e 3 mesi | N83: =L83/Cm_netto -> 0.6459784
... A92: 2046 | B92: =A92-Cm_primo+1 -> 39 | C92: =IF(B92<p_anni_min,1,0) -> 0 | D92: =IF(C92=1,"via dei 71 anni adeguati","vecchiaia ordinaria") -> vecchiaia ordinaria | E92: =IF(C92=1,Cm_v71_da,Cm_ord_da) -> 2052 | F92: =IF(C92=1,Cm_v71_dm,Cm_ord_dm) -> 12 | G92: =IF(C92=1,Cm_v71_em,Cm_ord_em) -> 831 | H92: =IF(C92=1,Cm_v71_cf,Cm_ord_cf) -> 0.060825 | I92: =Cm_m26*(1+p_g)^MAX(0,A92-2026)+p_comp*Cm_ral*IF(p_g=0,MAX(0,A92-2026),((1+p_g)^MAX(0,A92-2026)-1)/p_g) -> 373577.91 | J92: =I92*(1+p_g)^MAX(0,E92-A92)*H92 -> 23413.141 | K92: =MAX(0,IF(J92<=sc_L1,sc_A1*J92,IF(J92<=sc_L2,sc_B1+sc_A2*(J92-sc_L1),sc_B2+sc_A3*(J92-sc_L2)))-(IF(J92<=8500,1955,IF(J92<=28000,700+1255*(28000-J92)/19500,IF(J92<=50000,700*(50000-J92)/22000,0)))+IF(AND(J92>25000,J92<=29000),50,0))) -> 4389.8169 | L92: =J92-K92-IF(K92>0,p_add*J92,0) -> 18555.061 | M92: =INT(G92/12)&" anni e "&MOD(G92,12)&" mesi" -> 69 anni e 3 mesi | N92: =L92/Cm_netto -> 0.81102274

Sheet 3 - Numero FIRE
A1: 3 - Il numero FIRE della coppia: quanto serve, e da quando
A2: Strumento informativo / divulgativo. NON è consulenza finanziaria. I valori sono indicativi al 2026 e vanno verificati col tuo consulente.
A3: Il numero è il capitale che, con le pensioni di entrambi, copre la spesa fino al 2078 (euro del 2026, rendimento reale e imposte dichiarati nel foglio 1). I tre scenari sono separati: «se smettete oggi», «scenario comune» (stesso ultimo anno per entrambi) e «scenario libero» (anni diversi).
A5: A - Numero FIRE per scenario
B6: Se smettete oggi | C6: Scenario comune | D6: Scenario libero
A7: Ultimo anno lavorato di Tiziano | B7: ='5 - Motore e tabelle'!$B$362 -> 2026 | C7: ='5 - Motore e tabelle'!$C$362 -> 2029 | D7: ='5 - Motore e tabelle'!$D$362 -> 2026
A8: Ultimo anno lavorato di Camilla | B8: ='5 - Motore e tabelle'!$B$363 -> 2026 | C8: ='5 - Motore e tabelle'!$C$363 -> 2029 | D8: ='5 - Motore e tabelle'!$D$363 -> 2033
A9: Primo dei due che smette | B9: ='5 - Motore e tabelle'!$B$365 -> 2026 | C9: ='5 - Motore e tabelle'!$C$365 -> 2029 | D9: ='5 - Motore e tabelle'!$D$365 -> 2026
A10: Patrimonio (euro reali, a inizio anno dopo m) | B10: ='5 - Motore e tabelle'!$B$371 -> 750000 | C10: ='5 - Motore e tabelle'!$C$371 -> 871827.59 | D10: ='5 - Motore e tabelle'!$D$371 -> 750000
A11: Capitale richiesto (numero FIRE) | B11: ='5 - Motore e tabelle'!$B$379 -> 962186.06 | C11: ='5 - Motore e tabelle'!$C$379 -> 819183.17 | D11: ='5 - Motore e tabelle'!$D$379 -> 737544.01
A12: Margine (patrimonio meno richiesto) | B12: ='5 - Motore e tabelle'!$B$380 -> -212186.06 | C12: ='5 - Motore e tabelle'!$C$380 -> 52644.416 | D12: ='5 - Motore e tabelle'!$D$380 -> 12455.991
A13: In parole | B13: =IF('5 - Motore e tabelle'!$B$380<0,"mancano "&FIXED(-'5 - Motore e tabelle'!$B$380,0)&" €","margine di "&FIXED('5 - Motore e tabelle'!$B$380,0)&" €") -> mancano 212.186 € | C13: =IF('5 - Motore e tabelle'!$C$380<0,"mancano "&FIXED(-'5 - Motore e tabelle'!$C$380,0)&" €","margine di "&FIXED('5 - Motore e tabelle'!$C$380,0)&" €") -> margine di 52.644 € | D13: =IF('5 - Motore e tabelle'!$D$380<0,"mancano "&FIXED(-'5 - Motore e tabelle'!$D$380,0)&" €","margine di "&FIXED('5 - Motore e tabelle'!$D$380,0)&" €") -> margine di 12.456 €
A14: Si può smettere? | B14: =IF('5 - Motore e tabelle'!$B$380>=0,"Sì","No") -> No | C14: =IF('5 - Motore e tabelle'!$C$380>=0,"Sì","No") -> Sì | D14: =IF('5 - Motore e tabelle'!$D$380>=0,"Sì","No") -> Sì
A15: Avviso | B15: =IF('5 - Motore e tabelle'!$B$381>0,"surplus dopo m scartato: il numero è prudente","") | C15: =IF('5 - Motore e tabelle'!$C$381>0,"surplus dopo m scartato: il numero è prudente","") | D15: =IF('5 - Motore e tabelle'!$D$381>0,"surplus dopo m scartato: il numero è prudente","")
A16: Capitale richiesto a fine 2026 | B16: =IF('5 - Motore e tabelle'!$B$365=2026,'5 - Motore e tabelle'!$B$379,"non definito: parte dell'accumulo è futura") -> 962186.06 | C16: =IF('5 - Motore e tabelle'!$C$365=2026,'5 - Motore e tabelle'!$C$379,"non definito: parte dell'accumulo è futura") -> non definito: parte dell'accumulo è futura | D16: =IF('5 - Motore e tabelle'!$D$365=2026,'5 - Motore e tabelle'!$D$379,"non definito: parte dell'accumulo è futura") -> 737544.01
A18: B - Ponte e tratti (convenzione: l'anno in cui parte una pensione appartiene al tratto precedente)
B19: Se smettete oggi | C19: Scenario comune | D19: Scenario libero
A20: Ponte: dal primo anno senza stipendio alla prima pensione | B20: =SUMIFS('5 - Motore e tabelle'!$B$387:$B$438,'5 - Motore e tabelle'!$A$387:$A$438,">="&('5 - Motore e tabelle'!$B$365+1),'5 - Motore e tabelle'!$A$387:$A$438,"<="&'5 - Motore e tabelle'!$B$382) -> 725683.05 | C20: =SUMIFS('5 - Motore e tabelle'!$C$387:$C$438,'5 - Motore e tabelle'!$A$387:$A$438,">="&('5 - Motore e tabelle'!$C$365+1),'5 - Motore e tabelle'!$A$387:$A$438,"<="&'5 - Motore e tabelle'!$C$382) -> 643870.85 | D20: =SUMIFS('5 - Motore e tabelle'!$D$387:$D$438,'5 - Motore e tabelle'!$A$387:$A$438,">="&('5 - Motore e tabelle'!$D$365+1),'5 - Motore e tabelle'!$A$387:$A$438,"<="&'5 - Motore e tabelle'!$D$382) -> 557843.74
A21: Una sola pensione | B21: =SUMIFS('5 - Motore e tabelle'!$B$387:$B$438,'5 - Motore e tabelle'!$A$387:$A$438,">"&'5 - Motore e tabelle'!$B$382,'5 - Motore e tabelle'!$A$387:$A$438,"<="&'5 - Motore e tabelle'!$B$383) -> 143399.84 | C21: =SUMIFS('5 - Motore e tabelle'!$C$387:$C$438,'5 - Motore e tabelle'!$A$387:$A$438,">"&'5 - Motore e tabelle'!$C$382,'5 - Motore e tabelle'!$A$387:$A$438,"<="&'5 - Motore e tabelle'!$C$383) -> 80973.978 | D21: =SUMIFS('5 - Motore e tabelle'!$D$387:$D$438,'5 - Motore e tabelle'!$A$387:$A$438,">"&'5 - Motore e tabelle'!$D$382,'5 - Motore e tabelle'!$A$387:$A$438,"<="&'5 - Motore e tabelle'!$D$383) -> 84622.943
A22: Due pensioni | B22: =SUMIFS('5 - Motore e tabelle'!$B$387:$B$438,'5 - Motore e tabelle'!$A$387:$A$438,">"&'5 - Motore e tabelle'!$B$383) -> 93103.174 | C22: =SUMIFS('5 - Motore e tabelle'!$C$387:$C$438,'5 - Motore e tabelle'!$A$387:$A$438,">"&'5 - Motore e tabelle'!$C$383) -> 94338.347 | D22: =SUMIFS('5 - Motore e tabelle'!$D$387:$D$438,'5 - Motore e tabelle'!$A$387:$A$438,">"&'5 - Motore e tabelle'!$D$383) -> 95077.332
A23: Totale | B23: =SUM(B20:B22) -> 962186.06 | C23: =SUM(C20:C22) -> 819183.17 | D23: =SUM(D20:D22) -> 737544.01
A24: Anni di ponte | B24: =MAX(0,'5 - Motore e tabelle'!$B$382-'5 - Motore e tabelle'!$B$365) -> 20 | C24: =MAX(0,'5 - Motore e tabelle'!$C$382-'5 - Motore e tabelle'!$C$365) -> 17 | D24: =MAX(0,'5 - Motore e tabelle'!$D$382-'5 - Motore e tabelle'!$D$365) -> 20
A25: Anni con una pensione | B25: ='5 - Motore e tabelle'!$B$383-'5 - Motore e tabelle'!$B$382 -> 11 | C25: ='5 - Motore e tabelle'!$C$383-'5 - Motore e tabelle'!$C$382 -> 6 | D25: ='5 - Motore e tabelle'!$D$383-'5 - Motore e tabelle'!$D$382 -> 6
A26: Anni con due pensioni | B26: =p_orizz-'5 - Motore e tabelle'!$B$383 -> 21 | C26: =p_orizz-'5 - Motore e tabelle'!$C$383 -> 26 | D26: =p_orizz-'5 - Motore e tabelle'!$D$383 -> 26
A27: Quota del ponte sul totale | B27: =B20/B23 -> 0.75420241 | C27: =C20/C23 -> 0.7859913 | D27: =D20/D23 -> 0.75635315
A28: Con l'altra convenzione (l'anno di decorrenza nel tratto successivo) i tratti cambiano, il totale no: nello scenario «se smettete oggi» sarebbe 697.682 + 163.590 + 100.915 €.
A30: C - Anni al traguardo: stesso ultimo anno lavorato per entrambi
A31: Ultimo anno lavorato di entrambi | B31: Patrimonio (reale) | C31: Capitale richiesto | D31: Margine | E31: Si può smettere?
A32: 2026 | B32: ='5 - Motore e tabelle'!$G$371 -> 750000 | C32: ='5 - Motore e tabelle'!$G$379 -> 962186.06 | D32: ='5 - Motore e tabelle'!$G$380 -> -212186.06 | E32: =IF(D32>=0,"Sì","No") -> No
A33: 2027 | B33: ='5 - Motore e tabelle'!$H$371 -> 789495.42 | C33: ='5 - Motore e tabelle'!$H$379 -> 903646.89 | D33: ='5 - Motore e tabelle'!$H$380 -> -114151.47 | E33: =IF(D33>=0,"Sì","No") -> No
A34: 2028 | B34: ='5 - Motore e tabelle'!$I$371 -> 830094.33 | C34: ='5 - Motore e tabelle'!$I$379 -> 861894.87 | D34: ='5 - Motore e tabelle'!$I$380 -> -31800.535 | E34: =IF(D34>=0,"Sì","No") -> No
A35: 2029 | B35: ='5 - Motore e tabelle'!$J$371 -> 871827.59 | C35: ='5 - Motore e tabelle'!$J$379 -> 819183.17 | D35: ='5 - Motore e tabelle'!$J$380 -> 52644.416 | E35: =IF(D35>=0,"Sì","No") -> Sì
A36: 2030 | B36: ='5 - Motore e tabelle'!$K$371 -> 914726.86 | C36: ='5 - Motore e tabelle'!$K$379 -> 774787.64 | D36: ='5 - Motore e tabelle'!$K$380 -> 139939.22 | E36: =IF(D36>=0,"Sì","No") -> Sì
A37: 2031 | B37: ='5 - Motore e tabelle'!$L$371 -> 958824.75 | C37: ='5 - Motore e tabelle'!$L$379 -> 730721.4 | D37: ='5 - Motore e tabelle'!$L$380 -> 228103.35 | E37: =IF(D37>=0,"Sì","No") -> Sì
A38: 2032 | B38: ='5 - Motore e tabelle'!$M$371 -> 1004154.7 | C38: ='5 - Motore e tabelle'!$M$379 -> 683912.26 | D38: ='5 - Motore e tabelle'!$M$380 -> 320242.47 | E38: =IF(D38>=0,"Sì","No") -> Sì
A39: 2033 | B39: ='5 - Motore e tabelle'!$N$371 -> 1050751.2 | C39: ='5 - Motore e tabelle'!$N$379 -> 635207.97 | D39: ='5 - Motore e tabelle'!$N$380 -> 415543.26 | E39: =IF(D39>=0,"Sì","No") -> Sì
A40: 2034 | B40: ='5 - Motore e tabelle'!$O$371 -> 1098649.6 | C40: ='5 - Motore e tabelle'!$O$379 -> 584559.39 | D40: ='5 - Motore e tabelle'!$O$380 -> 514090.24 | E40: =IF(D40>=0,"Sì","No") -> Sì
A41: 2035 | B41: ='5 - Motore e tabelle'!$P$371 -> 1147886.3 | C41: ='5 - Motore e tabelle'!$P$379 -> 531915.2 | D41: ='5 - Motore e tabelle'!$P$380 -> 615971.12 | E41: =IF(D41>=0,"Sì","No") -> Sì
A42: 2036 | B42: ='5 - Motore e tabelle'!$Q$371 -> 1198498.7 | C42: ='5 - Motore e tabelle'!$Q$379 -> 488515.05 | D42: ='5 - Motore e tabelle'!$Q$380 -> 709983.63 | E42: =IF(D42>=0,"Sì","No") -> Sì
A43: 2037 | B43: ='5 - Motore e tabelle'!$R$371 -> 1250525.1 | C43: ='5 - Motore e tabelle'!$R$379 -> 449977.04 | D43: ='5 - Motore e tabelle'!$R$380 -> 800548.11 | E43: =IF(D43>=0,"Sì","No") -> Sì
A44: 2038 | B44: ='5 - Motore e tabelle'!$S$371 -> 1304005.2 | C44: ='5 - Motore e tabelle'!$S$379 -> 410165.96 | D44: ='5 - Motore e tabelle'!$S$380 -> 893839.28 | E44: =IF(D44>=0,"Sì","No") -> Sì
A45: 2039 | B45: ='5 - Motore e tabelle'!$T$371 -> 1358979.6 | C45: ='5 - Motore e tabelle'!$T$379 -> 369053.58 | D45: ='5 - Motore e tabelle'!$T$380 -> 989925.98 | E45: =IF(D45>=0,"Sì","No") -> Sì
A46: 2040 | B46: ='5 - Motore e tabelle'!$U$371 -> 1415489.9 | C46: ='5 - Motore e tabelle'!$U$379 -> 326610.56 | D46: ='5 - Motore e tabelle'!$U$380 -> 1088879.3 | E46: =IF(D46>=0,"Sì","No") -> Sì
A47: 2041 | B47: ='5 - Motore e tabelle'!$V$371 -> 1473579.1 | C47: ='5 - Motore e tabelle'!$V$379 -> 282806.46 | D47: ='5 - Motore e tabelle'!$V$380 -> 1190772.6 | E47: =IF(D47>=0,"Sì","No") -> Sì
A48: 2042 | B48: ='5 - Motore e tabelle'!$W$371 -> 1533291.3 | C48: ='5 - Motore e tabelle'!$W$379 -> 237609.76 | D48: ='5 - Motore e tabelle'!$W$380 -> 1295681.5 | E48: =IF(D48>=0,"Sì","No") -> Sì
A49: 2043 | B49: ='5 - Motore e tabelle'!$X$371 -> 1594671.9 | C49: ='5 - Motore e tabelle'!$X$379 -> 190987.86 | D49: ='5 - Motore e tabelle'!$X$380 -> 1403684 | E49: =IF(D49>=0,"Sì","No") -> Sì
A50: 2044 | B50: ='5 - Motore e tabelle'!$Y$371 -> 1657767.4 | C50: ='5 - Motore e tabelle'!$Y$379 -> 142907.08 | D50: ='5 - Motore e tabelle'!$Y$380 -> 1514860.3 | E50: =IF(D50>=0,"Sì","No") -> Sì
A51: 2045 | B51: ='5 - Motore e tabelle'!$Z$371 -> 1722625.8 | C51: ='5 - Motore e tabelle'!$Z$379 -> 93332.694 | D51: ='5 - Motore e tabelle'!$Z$380 -> 1629293.1 | E51: =IF(D51>=0,"Sì","No") -> Sì
A52: Primo ultimo anno comune con margine ≥ 0 | B52: =IF(COUNT('5 - Motore e tabelle'!$G$384:$Z$384)=0,"oltre il 2045",MIN('5 - Motore e tabelle'!$G$384:$Z$384)) -> 2029
A53: Anni da fine 2026 | B53: =IF(ISNUMBER(Tra_U),Tra_U-2026,"oltre 19") -> 3
A55: D - Leve: quanto vale un anno in più di lavoro, e la spesa
A56: Un anno in più di Tiziano (riduzione del mancante, scenario «oggi») | B56: ='5 - Motore e tabelle'!$E$380-'5 - Motore e tabelle'!$B$380 -> 51516.313
A57: Un anno in più di Camilla (riduzione del mancante, scenario «oggi») | B57: ='5 - Motore e tabelle'!$F$380-'5 - Motore e tabelle'!$B$380 -> 50232.432 | C57: Camilla vale tanto perché il suo anno in più la porta a 20 anni di contributi.
A58: Variazione della spesa per la prova di sensibilità | B58: 0.1
A59: Numero FIRE con spesa ridotta (scenario «oggi») | B59: ='5 - Motore e tabelle'!$AA$379 -> 826098.54
A60: Numero FIRE con spesa aumentata (scenario «oggi») | B60: ='5 - Motore e tabelle'!$AB$379 -> 1098273.6

Sheet 4 - Vedovanza
A1: 4 - Vedovanza: che cosa succede al piano se uno dei due muore
A2: Strumento informativo / divulgativo. NON è consulenza finanziaria. I valori sono indicativi al 2026 e vanno verificati col tuo consulente.
A3: Il piano è quello dello scenario comune (foglio 1). Scegli chi muore, quando, il regime e il testamento. Reversibilità dall'anno dopo la morte, a rata piena (semplificazione). La quota ereditata conserva la base di costo del defunto (ipotesi prudente); quote costanti nel tempo. Limiti: calcolo deterministico, una famiglia d'origine per volta, il 4% di successione oltre 1.000.000 € non è modellato, non è consulenza.
A5: Ingressi (dal foglio 1) e quote ereditarie
A6: Chi muore | B6: =V_chi -> T | D6: ESITI
A7: Anno della morte | B7: =V_anno -> 2035 | D7: Anno di esaurimento del patrimonio (0 = non si esaurisce) | E7: =IF(COUNT(AA44:AA95)=0,0,MIN(AA44:AA95)) -> 0
A8: Ultimo anno lavorato (scenario comune) | B8: =U_com -> 2029 | D8: Patrimonio finale in euro reali (−1 = esaurito) | E8: =IF(Ved_esaur>0,-1,INDEX(AF44:AF95,p_orizz-2026)) -> 1151564.7
A9: Chi resta | B9: =IF(V_chi="T","Camilla",IF(V_chi="C","Tiziano","nessuno")) -> Camilla | D9: In parole | E9: =IF(Ved_esaur>0,"si esaurisce nel "&Ved_esaur,"resta "&FIXED(Ved_finale,0)&" € (reali) al "&p_orizz) -> resta 1.151.565 € (reali) al 2078
A10: Quota del defunto sul valore del patrimonio | B10: =IF(V_chi="nessuno",0,IF(V_regime=1,(IF(V_chi="T",Ered_2026,0)+(Pat_W-Ered_2026)/2)/Pat_W,(IF(V_chi="T",Pt_T_val,Pt_C_val)+Pt_J_val/2)/Pat_W)) -> 0.72448434 | D10: Reversibilità piena nel primo anno dopo la morte | E10: =IFERROR(INDEX(J44:J95,V_anno+1-2026),0) -> 10785.432
A11: Quota del defunto sulla base di costo | B11: =IF(V_chi="nessuno",0,IF(V_regime=1,(IF(V_chi="T",Ered_nom,0)+(Pat_B-Ered_nom)/2)/Pat_B,(IF(V_chi="T",Pt_T_base,Pt_C_base)+Pt_J_base/2)/Pat_B)) -> 0.71689769 | D11: Reversibilità dopo la riduzione per reddito, primo anno | E11: =IFERROR(INDEX(M44:M95,V_anno+1-2026),0) -> 10785.432
A12: Quota dell'eredità che va al superstite | B12: =INDEX(FZ_val,MATCH(V_regime&"|"&V_test&"|"&V_fam,FZ_key,0)) -> 1 | D12: Avviso | E12: =IF(AND(V_regime=1,Ved_q>0,Pat_W*Ved_q>1000000),"la quota ereditata supera 1.000.000 €: l'imposta del 4% non è modellata",IF(V_regime=2,"conviventi: nessuna reversibilità e imposta dell'8% senza franchigia",""))
A13: Imposta di successione | B13: =IF(V_regime=1,imp_R1,imp_R2) -> 0
A14: Fattore sul valore del patrimonio (q) | B14: =(1-$B$10)+$B$10*$B$12*(1-$B$13) -> 1
A15: Fattore sulla base di costo | B15: =(1-$B$11)+$B$11*$B$12*(1-$B$13) -> 1
A16: Aliquota di reversibilità applicata | B16: =IF(V_regime=1,V_aliq,0) -> 0.6
A17: Montante di Tiziano alla morte | B17: =(Tz_m26*(1+p_g)^MAX(0,MIN(V_anno,U_com)-2026)+p_comp*Tz_ral*IF(p_g=0,MAX(0,MIN(V_anno,U_com)-2026),((1+p_g)^MAX(0,MIN(V_anno,U_com)-2026)-1)/p_g))*(1+p_g)^MAX(0,V_anno-MIN(V_anno,U_com)) -> 427586.11
A18: Reversibilità indiretta di Tiziano (aliquota × montante × coefficiente dell'età) | B18: =V_aliq*$B$17*IF(MAX(V_anno-Tz_nasc_a,57)>=71,INDEX(CT_val,15),INDEX(CT_val,MAX(V_anno-Tz_nasc_a,57)-56)) -> 10785.432
A19: Pensione lorda di Tiziano (scenario comune) | B19: =INDEX(PT_lorda,U_com-2025) -> 26966.501
A20: Pensione netta di Tiziano (scenario comune) | B20: =INDEX(PT_netta,U_com-2025) -> 21041.391
A21: Anno di decorrenza di Tiziano | B21: =INDEX(PT_da,U_com-2025) -> 2046
A22: Mese di decorrenza di Tiziano | B22: =INDEX(PT_dm,U_com-2025) -> 12
A23: Montante di Camilla alla morte | B23: =(Cm_m26*(1+p_g)^MAX(0,MIN(V_anno,U_com)-2026)+p_comp*Cm_ral*IF(p_g=0,MAX(0,MIN(V_anno,U_com)-2026),((1+p_g)^MAX(0,MIN(V_anno,U_com)-2026)-1)/p_g))*(1+p_g)^MAX(0,V_anno-MIN(V_anno,U_com)) -> 193312.71
A24: Reversibilità indiretta di Camilla (aliquota × montante × coefficiente dell'età) | B24: =V_aliq*$B$23*IF(MAX(V_anno-Cm_nasc_a,57)>=71,INDEX(CT_val,15),INDEX(CT_val,MAX(V_anno-Cm_nasc_a,57)-56)) -> 4876.1197
A25: Pensione lorda di Camilla (scenario comune) | B25: =INDEX(PC_lorda,U_com-2025) -> 12798.692
A26: Pensione netta di Camilla (scenario comune) | B26: =INDEX(PC_netta,U_com-2025) -> 11277.359
A27: Anno di decorrenza di Camilla | B27: =INDEX(PC_da,U_com-2025) -> 2052
A28: Mese di decorrenza di Camilla | B28: =INDEX(PC_dm,U_com-2025) -> 12
A29: Base della reversibilità (pensione propria del defunto se già in pagamento, altrimenti indiretta) | B29: =IF(V_chi="T",IF(V_anno>=$B$21,$B$19,$B$17*IF(MAX(V_anno-Tz_nasc_a,57)>=71,INDEX(CT_val,15),INDEX(CT_val,MAX(V_anno-Tz_nasc_a,57)-56))),IF(V_anno>=$B$27,$B$25,$B$23*IF(MAX(V_anno-Cm_nasc_a,57)>=71,INDEX(CT_val,15),INDEX(CT_val,MAX(V_anno-Cm_nasc_a,57)-56)))) -> 17975.72
A30: Anno di nascita di chi resta | B30: =IF(V_chi="T",Cm_nasc_a,Tz_nasc_a) -> 1983
A31: RAL di chi resta | B31: =IF(V_chi="T",Cm_ral,Tz_ral) -> 29000
A42: Piano anno per anno (euro nominali; l'ultima colonna è il patrimonio in euro reali)
A43: Anno | B43: Dopo la morte (1 = sì) | C43: Stipendio Tiziano | D43: Pensione Tiziano | E43: Stipendio Camilla | F43: Pensione Camilla | G43: Pensione lorda di chi resta | H43: Reddito da lavoro di chi resta | I43: Reddito lordo di chi resta | J43: Reversibilità piena | K43: Moltiplicatore | L43: Riduzione | M43: Reversibilità dopo la riduzione | N43: Pensione + reversibilità (lordo) | O43: Imposta sulla pensione | P43: Netto da pensione | Q43: Netto della reversibilità (con lavoro) | R43: Entrate nette | S43: Spesa | T43: Fabbisogno (reale) | U43: Indice prezzi | V43: Fabbisogno nominale | W43: Patrimonio a inizio anno | X43: Base di costo a inizio anno | Y43: Quota di guadagno latente | Z43: Vendita lorda | AA43: Anno di esaurimento | AB43: Patrimonio dopo il prelievo | AC43: Base dopo il prelievo | AD43: Patrimonio a fine anno | AE43: Base a fine anno | AF43: Patrimonio a fine anno (euro reali)
A44: 2027 | B44: =IF(AND(V_chi<>"nessuno",A44>V_anno),1,0) -> 0 | C44: =Tz_netto*(A44<=$B$8) -> 34757.881 | D44: =$B$20*IF(A44>$B$21,1,IF(A44=$B$21,(13-$B$22)/12,0)) -> 0 | E44: =Cm_netto*(A44<=$B$8) -> 22878.596 | F44: =$B$26*IF(A44>$B$27,1,IF(A44=$B$27,(13-$B$28)/12,0)) -> 0 | G44: =IF(B44=1,IF(V_chi="T",$B$25*IF(A44>$B$27,1,IF(A44=$B$27,(13-$B$28)/12,0)),$B$19*IF(A44>$B$21,1,IF(A44=$B$21,(13-$B$22)/12,0))),0) -> 0 | H44: =IF(B44=1,$B$31*(1-p_contr)*(A44<=$B$8),0) -> 0 | I44: =G44+H44 -> 0 | J44: =IF(B44=1,$B$16*$B$29,0) -> 0 | K44: =IF(V_figli=1,1,IF(I44>tf_S5,tf_M5,IF(I44>tf_S4,tf_M4,IF(I44>tf_S3,tf_M3,1)))) -> 1 | L44: =MIN(J44*(1-K44),I44) -> 0 | M44: =J44-L44 -> 0 | N44: =G44+M44 -> 0 | O44: =MAX(0,IF(N44<=sc_L1,sc_A1*N44,IF(N44<=sc_L2,sc_B1+sc_A2*(N44-sc_L1),sc_B2+sc_A3*(N44-sc_L2)))-(IF(N44<=8500,1955,IF(N44<=28000,700+1255*(28000-N44)/19500,IF(N44<=50000,700*(50000-N44)/22000,0)))+IF(AND(N44>25000,N44<=29000),50,0))) -> 0 | P44: =IF(N44>0,N44-O44-IF(O44>0,p_add*N44,0),0) -> 0 | Q44: =IF(B44=1,MAX(M44-(IF((I44+M44)<=sc_L1,sc_A1*(I44+M44),IF((I44+M44)<=sc_L2,sc_B1+sc_A2*((I44+M44)-sc_L1),sc_B2+sc_A3*((I44+M44)-sc_L2)))-IF(I44<=sc_L1,sc_A1*I44,IF(I44<=sc_L2,sc_B1+sc_A2*(I44-sc_L1),sc_B2+sc_A3*(I44-sc_L2))))-p_add*M44,0),0) -> 0 | R44: =IF(B44=1,IF(A44>$B$8,P44,IF(V_chi="T",E44,C44)+IF(V_chi="T",F44,D44)+Q44),C44+D44+E44+F44) -> 57636.477 | S44: =IF(B44=1,p_spesa/IF(A44-$B$30>=65,V_den65,V_den64),p_spesa) -> 39600 | T44: =S44-R44 -> -18036.477 | U44: =1 -> 1 | V44: =T44*U44 -> -18036.477 | W44: =Pat_W*IF(AND(V_chi<>"nessuno",A44=V_anno+1),Ved_q,1) -> 750000 | X44: =Pat_B*IF(AND(V_chi<>"nessuno",A44=V_anno+1),Ved_qb,1) -> 461046.86 | Y44: =IF(W44>0,MAX(0,1-X44/W44),0) -> 0.38527085 | Z44: =IF(V44>0,V44/(1-p_cgt*Y44),0) -> 0 | AA44: =IF(""<>"","",IF(AND(V44>0,Z44>W44,A44<=p_orizz),A44,"")) | AB44: =IF(V44>0,W44-Z44,W44-V44) -> 768036.48 | AC44: =IF(V44>0,IF(W44>0,X44-X44*Z44/W44,X44),X44-V44) -> 479083.34 | AD44: =AB44*(1+p_rend)*(1+p_infl)*(1-p_bollo) -> 805285.32 | AE44: =AC44 -> 479083.34 | AF44: =AD44/(U44*(1+p_infl)) -> 789495.42
A45: 2028 | B45: =IF(AND(V_chi<>"nessuno",A45>V_anno),1,0) -> 0 | C45: =Tz_netto*(A45<=$B$8) -> 34757.881 | D45: =$B$20*IF(A45>$B$21,1,IF(A45=$B$21,(13-$B$22)/12,0)) -> 0 | E45: =Cm_netto*(A45<=$B$8) -> 22878.596 | F45: =$B$26*IF(A45>$B$27,1,IF(A45=$B$27,(13-$B$28)/12,0)) -> 0 | G45: =IF(B45=1,IF(V_chi="T",$B$25*IF(A45>$B$27,1,IF(A45=$B$27,(13-$B$28)/12,0)),$B$19*IF(A45>$B$21,1,IF(A45=$B$21,(13-$B$22)/12,0))),0) -> 0 | H45: =IF(B45=1,$B$31*(1-p_contr)*(A45<=$B$8),0) -> 0 | I45: =G45+H45 -> 0 | J45: =IF(B45=1,$B$16*$B$29,0) -> 0 | K45: =IF(V_figli=1,1,IF(I45>tf_S5,tf_M5,IF(I45>tf_S4,tf_M4,IF(I45>tf_S3,tf_M3,1)))) -> 1 | L45: =MIN(J45*(1-K45),I45) -> 0 | M45: =J45-L45 -> 0 | N45: =G45+M45 -> 0 | O45: =MAX(0,IF(N45<=sc_L1,sc_A1*N45,IF(N45<=sc_L2,sc_B1+sc_A2*(N45-sc_L1),sc_B2+sc_A3*(N45-sc_L2)))-(IF(N45<=8500,1955,IF(N45<=28000,700+1255*(28000-N45)/19500,IF(N45<=50000,700*(50000-N45)/22000,0)))+IF(AND(N45>25000,N45<=29000),50,0))) -> 0 | P45: =IF(N45>0,N45-O45-IF(O45>0,p_add*N45,0),0) -> 0 | Q45: =IF(B45=1,MAX(M45-(IF((I45+M45)<=sc_L1,sc_A1*(I45+M45),IF((I45+M45)<=sc_L2,sc_B1+sc_A2*((I45+M45)-sc_L1),sc_B2+sc_A3*((I45+M45)-sc_L2)))-IF(I45<=sc_L1,sc_A1*I45,IF(I45<=sc_L2,sc_B1+sc_A2*(I45-sc_L1),sc_B2+sc_A3*(I45-sc_L2))))-p_add*M45,0),0) -> 0 | R45: =IF(B45=1,IF(A45>$B$8,P45,IF(V_chi="T",E45,C45)+IF(V_chi="T",F45,D45)+Q45),C45+D45+E45+F45) -> 57636.477 | S45: =IF(B45=1,p_spesa/IF(A45-$B$30>=65,V_den65,V_den64),p_spesa) -> 39600 | T45: =S45-R45 -> -18036.477 | U45: =U44*(1+p_infl) -> 1.02 | V45: =T45*U45 -> -18397.206 | W45: =AD44*IF(AND(V_chi<>"nessuno",A45=V_anno+1),Ved_q,1) -> 805285.32 | X45: =AE44*IF(AND(V_chi<>"nessuno",A45=V_anno+1),Ved_qb,1) -> 479083.34 | Y45: =IF(W45>0,MAX(0,1-X45/W45),0) -> 0.40507628 | Z45: =IF(V45>0,V45/(1-p_cgt*Y45),0) -> 0 | AA45: =IF(AA44<>"",AA44,IF(AND(V45>0,Z45>W45,A45<=p_orizz),A45,"")) | AB45: =IF(V45>0,W45-Z45,W45-V45) -> 823682.53 | AC45: =IF(V45>0,IF(W45>0,X45-X45*Z45/W45,X45),X45-V45) -> 497480.54 | AD45: =AB45*(1+p_rend)*(1+p_infl)*(1-p_bollo) -> 863630.15 | AE45: =AC45 -> 497480.54 | AF45: =AD45/(U45*(1+p_infl)) -> 830094.33
A46: 2029 | B46: =IF(AND(V_chi<>"nessuno",A46>V_anno),1,0) -> 0 | C46: =Tz_netto*(A46<=$B$8) -> 34757.881 | D46: =$B$20*IF(A46>$B$21,1,IF(A46=$B$21,(13-$B$22)/12,0)) -> 0 | E46: =Cm_netto*(A46<=$B$8) -> 22878.596 | F46: =$B$26*IF(A46>$B$27,1,IF(A46=$B$27,(13-$B$28)/12,0)) -> 0 | G46: =IF(B46=1,IF(V_chi="T",$B$25*IF(A46>$B$27,1,IF(A46=$B$27,(13-$B$28)/12,0)),$B$19*IF(A46>$B$21,1,IF(A46=$B$21,(13-$B$22)/12,0))),0) -> 0 | H46: =IF(B46=1,$B$31*(1-p_contr)*(A46<=$B$8),0) -> 0 | I46: =G46+H46 -> 0 | J46: =IF(B46=1,$B$16*$B$29,0) -> 0 | K46: =IF(V_figli=1,1,IF(I46>tf_S5,tf_M5,IF(I46>tf_S4,tf_M4,IF(I46>tf_S3,tf_M3,1)))) -> 1 | L46: =MIN(J46*(1-K46),I46) -> 0 | M46: =J46-L46 -> 0 | N46: =G46+M46 -> 0 | O46: =MAX(0,IF(N46<=sc_L1,sc_A1*N46,IF(N46<=sc_L2,sc_B1+sc_A2*(N46-sc_L1),sc_B2+sc_A3*(N46-sc_L2)))-(IF(N46<=8500,1955,IF(N46<=28000,700+1255*(28000-N46)/19500,IF(N46<=50000,700*(50000-N46)/22000,0)))+IF(AND(N46>25000,N46<=29000),50,0))) -> 0 | P46: =IF(N46>0,N46-O46-IF(O46>0,p_add*N46,0),0) -> 0 | Q46: =IF(B46=1,MAX(M46-(IF((I46+M46)<=sc_L1,sc_A1*(I46+M46),IF((I46+M46)<=sc_L2,sc_B1+sc_A2*((I46+M46)-sc_L1),sc_B2+sc_A3*((I46+M46)-sc_L2)))-IF(I46<=sc_L1,sc_A1*I46,IF(I46<=sc_L2,sc_B1+sc_A2*(I46-sc_L1),sc_B2+sc_A3*(I46-sc_L2))))-p_add*M46,0),0) -> 0 | R46: =IF(B46=1,IF(A46>$B$8,P46,IF(V_chi="T",E46,C46)+IF(V_chi="T",F46,D46)+Q46),C46+D46+E46+F46) -> 57636.477 | S46: =IF(B46=1,p_spesa/IF(A46-$B$30>=65,V_den65,V_den64),p_spesa) -> 39600 | T46: =S46-R46 -> -18036.477 | U46: =U45*(1+p_infl) -> 1.0404 | V46: =T46*U46 -> -18765.151 | W46: =AD45*IF(AND(V_chi<>"nessuno",A46=V_anno+1),Ved_q,1) -> 863630.15 | X46: =AE45*IF(AND(V_chi<>"nessuno",A46=V_anno+1),Ved_qb,1) -> 497480.54 | Y46: =IF(W46>0,MAX(0,1-X46/W46),0) -> 0.42396575 | Z46: =IF(V46>0,V46/(1-p_cgt*Y46),0) -> 0 | AA46: =IF(AA45<>"",AA45,IF(AND(V46>0,Z46>W46,A46<=p_orizz),A46,"")) | AB46: =IF(V46>0,W46-Z46,W46-V46) -> 882395.3 | AC46: =IF(V46>0,IF(W46>0,X46-X46*Z46/W46,X46),X46-V46) -> 516245.69 | AD46: =AB46*(1+p_rend)*(1+p_infl)*(1-p_bollo) -> 925190.41 | AE46: =AC46 -> 516245.69 | AF46: =AD46/(U46*(1+p_infl)) -> 871827.59
A47: 2030 | B47: =IF(AND(V_chi<>"nessuno",A47>V_anno),1,0) -> 0 | C47: =Tz_netto*(A47<=$B$8) -> 0 | D47: =$B$20*IF(A47>$B$21,1,IF(A47=$B$21,(13-$B$22)/12,0)) -> 0 | E47: =Cm_netto*(A47<=$B$8) -> 0 | F47: =$B$26*IF(A47>$B$27,1,IF(A47=$B$27,(13-$B$28)/12,0)) -> 0 | G47: =IF(B47=1,IF(V_chi="T",$B$25*IF(A47>$B$27,1,IF(A47=$B$27,(13-$B$28)/12,0)),$B$19*IF(A47>$B$21,1,IF(A47=$B$21,(13-$B$22)/12,0))),0) -> 0 | H47: =IF(B47=1,$B$31*(1-p_contr)*(A47<=$B$8),0) -> 0 | I47: =G47+H47 -> 0 | J47: =IF(B47=1,$B$16*$B$29,0) -> 0 | K47: =IF(V_figli=1,1,IF(I47>tf_S5,tf_M5,IF(I47>tf_S4,tf_M4,IF(I47>tf_S3,tf_M3,1)))) -> 1 | L47: =MIN(J47*(1-K47),I47) -> 0 | M47: =J47-L47 -> 0 | N47: =G47+M47 -> 0 | O47: =MAX(0,IF(N47<=sc_L1,sc_A1*N47,IF(N47<=sc_L2,sc_B1+sc_A2*(N47-sc_L1),sc_B2+sc_A3*(N47-sc_L2)))-(IF(N47<=8500,1955,IF(N47<=28000,700+1255*(28000-N47)/19500,IF(N47<=50000,700*(50000-N47)/22000,0)))+IF(AND(N47>25000,N47<=29000),50,0))) -> 0 | P47: =IF(N47>0,N47-O47-IF(O47>0,p_add*N47,0),0) -> 0 | Q47: =IF(B47=1,MAX(M47-(IF((I47+M47)<=sc_L1,sc_A1*(I47+M47),IF((I47+M47)<=sc_L2,sc_B1+sc_A2*((I47+M47)-sc_L1),sc_B2+sc_A3*((I47+M47)-sc_L2)))-IF(I47<=sc_L1,sc_A1*I47,IF(I47<=sc_L2,sc_B1+sc_A2*(I47-sc_L1),sc_B2+sc_A3*(I47-sc_L2))))-p_add*M47,0),0) -> 0 | R47: =IF(B47=1,IF(A47>$B$8,P47,IF(V_chi="T",E47,C47)+IF(V_chi="T",F47,D47)+Q47),C47+D47+E47+F47) -> 0 | S47: =IF(B47=1,p_spesa/IF(A47-$B$30>=65,V_den65,V_den64),p_spesa) -> 39600 | T47: =S47-R47 -> 39600 | U47: =U46*(1+p_infl) -> 1.061208 | V47: =T47*U47 -> 42023.837 | W47: =AD46*IF(AND(V_chi<>"nessuno",A47=V_anno+1),Ved_q,1) -> 925190.41 | X47: =AE46*IF(AND(V_chi<>"nessuno",A47=V_anno+1),Ved_qb,1) -> 516245.69 | Y47: =IF(W47>0,MAX(0,1-X47/W47),0) -> 0.44201141 | Z47: =IF(V47>0,V47/(1-p_cgt*Y47),0) -> 47480.428 | AA47: =IF(AA46<>"",AA46,IF(AND(V47>0,Z47>W47,A47<=p_orizz),A47,"")) | AB47: =IF(V47>0,W47-Z47,W47-V47) -> 877709.98 | AC47: =IF(V47>0,IF(W47>0,X47-X47*Z47/W47,X47),X47-V47) -> 489752.16 | AD47: =AB47*(1+p_rend)*(1+p_infl)*(1-p_bollo) -> 920277.86 | AE47: =AC47 -> 489752.16 | AF47: =AD47/(U47*(1+p_infl)) -> 850194.49
A48: 2031 | B48: =IF(AND(V_chi<>"nessuno",A48>V_anno),1,0) -> 0 | C48: =Tz_netto*(A48<=$B$8) -> 0 | D48: =$B$20*IF(A48>$B$21,1,IF(A48=$B$21,(13-$B$22)/12,0)) -> 0 | E48: =Cm_netto*(A48<=$B$8) -> 0 | F48: =$B$26*IF(A48>$B$27,1,IF(A48=$B$27,(13-$B$28)/12,0)) -> 0 | G48: =IF(B48=1,IF(V_chi="T",$B$25*IF(A48>$B$27,1,IF(A48=$B$27,(13-$B$28)/12,0)),$B$19*IF(A48>$B$21,1,IF(A48=$B$21,(13-$B$22)/12,0))),0) -> 0 | H48: =IF(B48=1,$B$31*(1-p_contr)*(A48<=$B$8),0) -> 0 | I48: =G48+H48 -> 0 | J48: =IF(B48=1,$B$16*$B$29,0) -> 0 | K48: =IF(V_figli=1,1,IF(I48>tf_S5,tf_M5,IF(I48>tf_S4,tf_M4,IF(I48>tf_S3,tf_M3,1)))) -> 1 | L48: =MIN(J48*(1-K48),I48) -> 0 | M48: =J48-L48 -> 0 | N48: =G48+M48 -> 0 | O48: =MAX(0,IF(N48<=sc_L1,sc_A1*N48,IF(N48<=sc_L2,sc_B1+sc_A2*(N48-sc_L1),sc_B2+sc_A3*(N48-sc_L2)))-(IF(N48<=8500,1955,IF(N48<=28000,700+1255*(28000-N48)/19500,IF(N48<=50000,700*(50000-N48)/22000,0)))+IF(AND(N48>25000,N48<=29000),50,0))) -> 0 | P48: =IF(N48>0,N48-O48-IF(O48>0,p_add*N48,0),0) -> 0 | Q48: =IF(B48=1,MAX(M48-(IF((I48+M48)<=sc_L1,sc_A1*(I48+M48),IF((I48+M48)<=sc_L2,sc_B1+sc_A2*((I48+M48)-sc_L1),sc_B2+sc_A3*((I48+M48)-sc_L2)))-IF(I48<=sc_L1,sc_A1*I48,IF(I48<=sc_L2,sc_B1+sc_A2*(I48-sc_L1),sc_B2+sc_A3*(I48-sc_L2))))-p_add*M48,0),0) -> 0 | R48: =IF(B48=1,IF(A48>$B$8,P48,IF(V_chi="T",E48,C48)+IF(V_chi="T",F48,D48)+Q48),C48+D48+E48+F48) -> 0 | S48: =IF(B48=1,p_spesa/IF(A48-$B$30>=65,V_den65,V_den64),p_spesa) -> 39600 | T48: =S48-R48 -> 39600 | U48: =U47*(1+p_infl) -> 1.0824322 | V48: =T48*U48 -> 42864.314 | W48: =AD47*IF(AND(V_chi<>"nessuno",A48=V_anno+1),Ved_q,1) -> 920277.86 | X48: =AE47*IF(AND(V_chi<>"nessuno",A48=V_anno+1),Ved_qb,1) -> 489752.16 | Y48: =IF(W48>0,MAX(0,1-X48/W48),0) -> 0.46782143 | Z48: =IF(V48>0,V48/(1-p_cgt*Y48),0) -> 48800.036 | AA48: =IF(AA47<>"",AA47,IF(AND(V48>0,Z48>W48,A48<=p_orizz),A48,"")) | AB48: =IF(V48>0,W48-Z48,W48-V48) -> 871477.82 | AC48: =IF(V48>0,IF(W48>0,X48-X48*Z48/W48,X48),X48-V48) -> 463781.82 | AD48: =AB48*(1+p_rend)*(1+p_infl)*(1-p_bollo) -> 913743.45 | AE48: =AC48 -> 463781.82 | AF48: =AD48/(U48*(1+p_infl)) -> 827605.6
A49: 2032 | B49: =IF(AND(V_chi<>"nessuno",A49>V_anno),1,0) -> 0 | C49: =Tz_netto*(A49<=$B$8) -> 0 | D49: =$B$20*IF(A49>$B$21,1,IF(A49=$B$21,(13-$B$22)/12,0)) -> 0 | E49: =Cm_netto*(A49<=$B$8) -> 0 | F49: =$B$26*IF(A49>$B$27,1,IF(A49=$B$27,(13-$B$28)/12,0)) -> 0 | G49: =IF(B49=1,IF(V_chi="T",$B$25*IF(A49>$B$27,1,IF(A49=$B$27,(13-$B$28)/12,0)),$B$19*IF(A49>$B$21,1,IF(A49=$B$21,(13-$B$22)/12,0))),0) -> 0 | H49: =IF(B49=1,$B$31*(1-p_contr)*(A49<=$B$8),0) -> 0 | I49: =G49+H49 -> 0 | J49: =IF(B49=1,$B$16*$B$29,0) -> 0 | K49: =IF(V_figli=1,1,IF(I49>tf_S5,tf_M5,IF(I49>tf_S4,tf_M4,IF(I49>tf_S3,tf_M3,1)))) -> 1 | L49: =MIN(J49*(1-K49),I49) -> 0 | M49: =J49-L49 -> 0 | N49: =G49+M49 -> 0 | O49: =MAX(0,IF(N49<=sc_L1,sc_A1*N49,IF(N49<=sc_L2,sc_B1+sc_A2*(N49-sc_L1),sc_B2+sc_A3*(N49-sc_L2)))-(IF(N49<=8500,1955,IF(N49<=28000,700+1255*(28000-N49)/19500,IF(N49<=50000,700*(50000-N49)/22000,0)))+IF(AND(N49>25000,N49<=29000),50,0))) -> 0 | P49: =IF(N49>0,N49-O49-IF(O49>0,p_add*N49,0),0) -> 0 | Q49: =IF(B49=1,MAX(M49-(IF((I49+M49)<=sc_L1,sc_A1*(I49+M49),IF((I49+M49)<=sc_L2,sc_B1+sc_A2*((I49+M49)-sc_L1),sc_B2+sc_A3*((I49+M49)-sc_L2)))-IF(I49<=sc_L1,sc_A1*I49,IF(I49<=sc_L2,sc_B1+sc_A2*(I49-sc_L1),sc_B2+sc_A3*(I49-sc_L2))))-p_add*M49,0),0) -> 0 | R49: =IF(B49=1,IF(A49>$B$8,P49,IF(V_chi="T",E49,C49)+IF(V_chi="T",F49,D49)+Q49),C49+D49+E49+F49) -> 0 | S49: =IF(B49=1,p_spesa/IF(A49-$B$30>=65,V_den65,V_den64),p_spesa) -> 39600 | T49: =S49-R49 -> 39600 | U49: =U48*(1+p_infl) -> 1.1040808 | V49: =T49*U49 -> 43721.6 | W49: =AD48*IF(AND(V_chi<>"nessuno",A49=V_anno+1),Ved_q,1) -> 913743.45 | X49: =AE48*IF(AND(V_chi<>"nessuno",A49=V_anno+1),Ved_qb,1) -> 463781.82 | Y49: =IF(W49>0,MAX(0,1-X49/W49),0) -> 0.4924376 | Z49: =IF(V49>0,V49/(1-p_cgt*Y49),0) -> 50141.391 | AA49: =IF(AA48<>"",AA48,IF(AND(V49>0,Z49>W49,A49<=p_orizz),A49,"")) | AB49: =IF(V49>0,W49-Z49,W49-V49) -> 863602.06 | AC49: =IF(V49>0,IF(W49>0,X49-X49*Z49/W49,X49),X49-V49) -> 438331.94 | AD49: =AB49*(1+p_rend)*(1+p_infl)*(1-p_bollo) -> 905485.73 | AE49: =AC49 -> 438331.94 | AF49: =AD49/(U49*(1+p_infl)) -> 804045.41
A50: 2033 | B50: =IF(AND(V_chi<>"nessuno",A50>V_anno),1,0) -> 0 | C50: =Tz_netto*(A50<=$B$8) -> 0 | D50: =$B$20*IF(A50>$B$21,1,IF(A50=$B$21,(13-$B$22)/12,0)) -> 0 | E50: =Cm_netto*(A50<=$B$8) -> 0 | F50: =$B$26*IF(A50>$B$27,1,IF(A50=$B$27,(13-$B$28)/12,0)) -> 0 | G50: =IF(B50=1,IF(V_chi="T",$B$25*IF(A50>$B$27,1,IF(A50=$B$27,(13-$B$28)/12,0)),$B$19*IF(A50>$B$21,1,IF(A50=$B$21,(13-$B$22)/12,0))),0) -> 0 | H50: =IF(B50=1,$B$31*(1-p_contr)*(A50<=$B$8),0) -> 0 | I50: =G50+H50 -> 0 | J50: =IF(B50=1,$B$16*$B$29,0) -> 0 | K50: =IF(V_figli=1,1,IF(I50>tf_S5,tf_M5,IF(I50>tf_S4,tf_M4,IF(I50>tf_S3,tf_M3,1)))) -> 1 | L50: =MIN(J50*(1-K50),I50) -> 0 | M50: =J50-L50 -> 0 | N50: =G50+M50 -> 0 | O50: =MAX(0,IF(N50<=sc_L1,sc_A1*N50,IF(N50<=sc_L2,sc_B1+sc_A2*(N50-sc_L1),sc_B2+sc_A3*(N50-sc_L2)))-(IF(N50<=8500,1955,IF(N50<=28000,700+1255*(28000-N50)/19500,IF(N50<=50000,700*(50000-N50)/22000,0)))+IF(AND(N50>25000,N50<=29000),50,0))) -> 0 | P50: =IF(N50>0,N50-O50-IF(O50>0,p_add*N50,0),0) -> 0 | Q50: =IF(B50=1,MAX(M50-(IF((I50+M50)<=sc_L1,sc_A1*(I50+M50),IF((I50+M50)<=sc_L2,sc_B1+sc_A2*((I50+M50)-sc_L1),sc_B2+sc_A3*((I50+M50)-sc_L2)))-IF(I50<=sc_L1,sc_A1*I50,IF(I50<=sc_L2,sc_B1+sc_A2*(I50-sc_L1),sc_B2+sc_A3*(I50-sc_L2))))-p_add*M50,0),0) -> 0 | R50: =IF(B50=1,IF(A50>$B$8,P50,IF(V_chi="T",E50,C50)+IF(V_chi="T",F50,D50)+Q50),C50+D50+E50+F50) -> 0 | S50: =IF(B50=1,p_spesa/IF(A50-$B$30>=65,V_den65,V_den64),p_spesa) -> 39600 | T50: =S50-R50 -> 39600 | U50: =U49*(1+p_infl) -> 1.1261624 | V50: =T50*U50 -> 44596.032 | W50: =AD49*IF(AND(V_chi<>"nessuno",A50=V_anno+1),Ved_q,1) -> 905485.73 | X50: =AE49*IF(AND(V_chi<>"nessuno",A50=V_anno+1),Ved_qb,1) -> 438331.94 | Y50: =IF(W50>0,MAX(0,1-X50/W50),0) -> 0.51591513 | Z50: =IF(V50>0,V50/(1-p_cgt*Y50),0) -> 51504.776 | AA50: =IF(AA49<>"",AA49,IF(AND(V50>0,Z50>W50,A50<=p_orizz),A50,"")) | AB50: =IF(V50>0,W50-Z50,W50-V50) -> 853980.95 | AC50: =IF(V50>0,IF(W50>0,X50-X50*Z50/W50,X50),X50-V50) -> 413399.26 | AD50: =AB50*(1+p_rend)*(1+p_infl)*(1-p_bollo) -> 895398 | AE50: =AC50 -> 413399.26 | AF50: =AD50/(U50*(1+p_infl)) -> 779497.84
A51: 2034 | B51: =IF(AND(V_chi<>"nessuno",A51>V_anno),1,0) -> 0 | C51: =Tz_netto*(A51<=$B$8) -> 0 | D51: =$B$20*IF(A51>$B$21,1,IF(A51=$B$21,(13-$B$22)/12,0)) -> 0 | E51: =Cm_netto*(A51<=$B$8) -> 0 | F51: =$B$26*IF(A51>$B$27,1,IF(A51=$B$27,(13-$B$28)/12,0)) -> 0 | G51: =IF(B51=1,IF(V_chi="T",$B$25*IF(A51>$B$27,1,IF(A51=$B$27,(13-$B$28)/12,0)),$B$19*IF(A51>$B$21,1,IF(A51=$B$21,(13-$B$22)/12,0))),0) -> 0 | H51: =IF(B51=1,$B$31*(1-p_contr)*(A51<=$B$8),0) -> 0 | I51: =G51+H51 -> 0 | J51: =IF(B51=1,$B$16*$B$29,0) -> 0 | K51: =IF(V_figli=1,1,IF(I51>tf_S5,tf_M5,IF(I51>tf_S4,tf_M4,IF(I51>tf_S3,tf_M3,1)))) -> 1 | L51: =MIN(J51*(1-K51),I51) -> 0 | M51: =J51-L51 -> 0 | N51: =G51+M51 -> 0 | O51: =MAX(0,IF(N51<=sc_L1,sc_A1*N51,IF(N51<=sc_L2,sc_B1+sc_A2*(N51-sc_L1),sc_B2+sc_A3*(N51-sc_L2)))-(IF(N51<=8500,1955,IF(N51<=28000,700+1255*(28000-N51)/19500,IF(N51<=50000,700*(50000-N51)/22000,0)))+IF(AND(N51>25000,N51<=29000),50,0))) -> 0 | P51: =IF(N51>0,N51-O51-IF(O51>0,p_add*N51,0),0) -> 0 | Q51: =IF(B51=1,MAX(M51-(IF((I51+M51)<=sc_L1,sc_A1*(I51+M51),IF((I51+M51)<=sc_L2,sc_B1+sc_A2*((I51+M51)-sc_L1),sc_B2+sc_A3*((I51+M51)-sc_L2)))-IF(I51<=sc_L1,sc_A1*I51,IF(I51<=sc_L2,sc_B1+sc_A2*(I51-sc_L1),sc_B2+sc_A3*(I51-sc_L2))))-p_add*M51,0),0) -> 0 | R51: =IF(B51=1,IF(A51>$B$8,P51,IF(V_chi="T",E51,C51)+IF(V_chi="T",F51,D51)+Q51),C51+D51+E51+F51) -> 0 | S51: =IF(B51=1,p_spesa/IF(A51-$B$30>=65,V_den65,V_den64),p_spesa) -> 39600 | T51: =S51-R51 -> 39600 | U51: =U50*(1+p_infl) -> 1.1486857 | V51: =T51*U51 -> 45487.952 | W51: =AD50*IF(AND(V_chi<>"nessuno",A51=V_anno+1),Ved_q,1) -> 895398 | X51: =AE50*IF(AND(V_chi<>"nessuno",A51=V_anno+1),Ved_qb,1) -> 413399.26 | Y51: =IF(W51>0,MAX(0,1-X51/W51),0) -> 0.5383067 | Z51: =IF(V51>0,V51/(1-p_cgt*Y51),0) -> 52890.492 | AA51: =IF(AA50<>"",AA50,IF(AND(V51>0,Z51>W51,A51<=p_orizz),A51,"")) | AB51: =IF(V51>0,W51-Z51,W51-V51) -> 842507.51 | AC51: =IF(V51>0,IF(W51>0,X51-X51*Z51/W51,X51),X51-V51) -> 388980.07 | AD51: =AB51*(1+p_rend)*(1+p_infl)*(1-p_bollo) -> 883368.11 | AE51: =AC51 -> 388980.07 | AF51: =AD51/(U51*(1+p_infl)) -> 753946.18
A52: 2035 | B52: =IF(AND(V_chi<>"nessuno",A52>V_anno),1,0) -> 0 | C52: =Tz_netto*(A52<=$B$8) -> 0 | D52: =$B$20*IF(A52>$B$21,1,IF(A52=$B$21,(13-$B$22)/12,0)) -> 0 | E52: =Cm_netto*(A52<=$B$8) -> 0 | F52: =$B$26*IF(A52>$B$27,1,IF(A52=$B$27,(13-$B$28)/12,0)) -> 0 | G52: =IF(B52=1,IF(V_chi="T",$B$25*IF(A52>$B$27,1,IF(A52=$B$27,(13-$B$28)/12,0)),$B$19*IF(A52>$B$21,1,IF(A52=$B$21,(13-$B$22)/12,0))),0) -> 0 | H52: =IF(B52=1,$B$31*(1-p_contr)*(A52<=$B$8),0) -> 0 | I52: =G52+H52 -> 0 | J52: =IF(B52=1,$B$16*$B$29,0) -> 0 | K52: =IF(V_figli=1,1,IF(I52>tf_S5,tf_M5,IF(I52>tf_S4,tf_M4,IF(I52>tf_S3,tf_M3,1)))) -> 1 | L52: =MIN(J52*(1-K52),I52) -> 0 | M52: =J52-L52 -> 0 | N52: =G52+M52 -> 0 | O52: =MAX(0,IF(N52<=sc_L1,sc_A1*N52,IF(N52<=sc_L2,sc_B1+sc_A2*(N52-sc_L1),sc_B2+sc_A3*(N52-sc_L2)))-(IF(N52<=8500,1955,IF(N52<=28000,700+1255*(28000-N52)/19500,IF(N52<=50000,700*(50000-N52)/22000,0)))+IF(AND(N52>25000,N52<=29000),50,0))) -> 0 | P52: =IF(N52>0,N52-O52-IF(O52>0,p_add*N52,0),0) -> 0 | Q52: =IF(B52=1,MAX(M52-(IF((I52+M52)<=sc_L1,sc_A1*(I52+M52),IF((I52+M52)<=sc_L2,sc_B1+sc_A2*((I52+M52)-sc_L1),sc_B2+sc_A3*((I52+M52)-sc_L2)))-IF(I52<=sc_L1,sc_A1*I52,IF(I52<=sc_L2,sc_B1+sc_A2*(I52-sc_L1),sc_B2+sc_A3*(I52-sc_L2))))-p_add*M52,0),0) -> 0 | R52: =IF(B52=1,IF(A52>$B$8,P52,IF(V_chi="T",E52,C52)+IF(V_chi="T",F52,D52)+Q52),C52+D52+E52+F52) -> 0 | S52: =IF(B52=1,p_spesa/IF(A52-$B$30>=65,V_den65,V_den64),p_spesa) -> 39600 | T52: =S52-R52 -> 39600 | U52: =U51*(1+p_infl) -> 1.1716594 | V52: =T52*U52 -> 46397.711 | W52: =AD51*IF(AND(V_chi<>"nessuno",A52=V_anno+1),Ved_q,1) -> 883368.11 | X52: =AE51*IF(AND(V_chi<>"nessuno",A52=V_anno+1),Ved_qb,1) -> 388980.07 | Y52: =IF(W52>0,MAX(0,1-X52/W52),0) -> 0.55966254 | Z52: =IF(V52>0,V52/(1-p_cgt*Y52),0) -> 54298.862 | AA52: =IF(AA51<>"",AA51,IF(AND(V52>0,Z52>W52,A52<=p_orizz),A52,"")) | AB52: =IF(V52>0,W52-Z52,W52-V52) -> 829069.25 | AC52: =IF(V52>0,IF(W52>0,X52-X52*Z52/W52,X52),X52-V52) -> 365070.25 | AD52: =AB52*(1+p_rend)*(1+p_infl)*(1-p_bollo) -> 869278.11 | AE52: =AC52 -> 365070.25 | AF52: =AD52/(U52*(1+p_infl)) -> 727373.04
A53: 2036 | B53: =IF(AND(V_chi<>"nessuno",A53>V_anno),1,0) -> 1 | C53: =Tz_netto*(A53<=$B$8) -> 0 | D53: =$B$20*IF(A53>$B$21,1,IF(A53=$B$21,(13-$B$22)/12,0)) -> 0 | E53: =Cm_netto*(A53<=$B$8) -> 0 | F53: =$B$26*IF(A53>$B$27,1,IF(A53=$B$27,(13-$B$28)/12,0)) -> 0 | G53: =IF(B53=1,IF(V_chi="T",$B$25*IF(A53>$B$27,1,IF(A53=$B$27,(13-$B$28)/12,0)),$B$19*IF(A53>$B$21,1,IF(A53=$B$21,(13-$B$22)/12,0))),0) -> 0 | H53: =IF(B53=1,$B$31*(1-p_contr)*(A53<=$B$8),0) -> 0 | I53: =G53+H53 -> 0 | J53: =IF(B53=1,$B$16*$B$29,0) -> 10785.432 | K53: =IF(V_figli=1,1,IF(I53>tf_S5,tf_M5,IF(I53>tf_S4,tf_M4,IF(I53>tf_S3,tf_M3,1)))) -> 1 | L53: =MIN(J53*(1-K53),I53) -> 0 | M53: =J53-L53 -> 10785.432 | N53: =G53+M53 -> 10785.432 | O53: =MAX(0,IF(N53<=sc_L1,sc_A1*N53,IF(N53<=sc_L2,sc_B1+sc_A2*(N53-sc_L1),sc_B2+sc_A3*(N53-sc_L2)))-(IF(N53<=8500,1955,IF(N53<=28000,700+1255*(28000-N53)/19500,IF(N53<=50000,700*(50000-N53)/22000,0)))+IF(AND(N53>25000,N53<=29000),50,0))) -> 672.73744 | P53: =IF(N53>0,N53-O53-IF(O53>0,p_add*N53,0),0) -> 9896.986 | Q53: =IF(B53=1,MAX(M53-(IF((I53+M53)<=sc_L1,sc_A1*(I53+M53),IF((I53+M53)<=sc_L2,sc_B1+sc_A2*((I53+M53)-sc_L1),sc_B2+sc_A3*((I53+M53)-sc_L2)))-IF(I53<=sc_L1,sc_A1*I53,IF(I53<=sc_L2,sc_B1+sc_A2*(I53-sc_L1),sc_B2+sc_A3*(I53-sc_L2))))-p_add*M53,0),0) -> 8089.074 | R53: =IF(B53=1,IF(A53>$B$8,P53,IF(V_chi="T",E53,C53)+IF(V_chi="T",F53,D53)+Q53),C53+D53+E53+F53) -> 9896.986 | S53: =IF(B53=1,p_spesa/IF(A53-$B$30>=65,V_den65,V_den64),p_spesa) -> 26539.776 | T53: =S53-R53 -> 16642.79 | U53: =U52*(1+p_infl) -> 1.1950926 | V53: =T53*U53 -> 19889.675 | W53: =AD52*IF(AND(V_chi<>"nessuno",A53=V_anno+1),Ved_q,1) -> 869278.11 | X53: =AE52*IF(AND(V_chi<>"nessuno",A53=V_anno+1),Ved_qb,1) -> 365070.25 | Y53: =IF(W53>0,MAX(0,1-X53/W53),0) -> 0.58003056 | Z53: =IF(V53>0,V53/(1-p_cgt*Y53),0) -> 23421.881 | AA53: =IF(AA52<>"",AA52,IF(AND(V53>0,Z53>W53,A53<=p_orizz),A53,"")) | AB53: =IF(V53>0,W53-Z53,W53-V53) -> 845856.23 | AC53: =IF(V53>0,IF(W53>0,X53-X53*Z53/W53,X53),X53-V53) -> 355233.77 | AD53: =AB53*(1+p_rend)*(1+p_infl)*(1-p_bollo) -> 886879.25 | AE53: =AC53 -> 355233.77 | AF53: =AD53/(U53*(1+p_infl)) -> 727549.88
A54: 2037 | B54: =IF(AND(V_chi<>"nessuno",A54>V_anno),1,0) -> 1 | C54: =Tz_netto*(A54<=$B$8) -> 0 | D54: =$B$20*IF(A54>$B$21,1,IF(A54=$B$21,(13-$B$22)/12,0)) -> 0 | E54: =Cm_netto*(A54<=$B$8) -> 0 | F54: =$B$26*IF(A54>$B$27,1,IF(A54=$B$27,(13-$B$28)/12,0)) -> 0 | G54: =IF(B54=1,IF(V_chi="T",$B$25*IF(A54>$B$27,1,IF(A54=$B$27,(13-$B$28)/12,0)),$B$19*IF(A54>$B$21,1,IF(A54=$B$21,(13-$B$22)/12,0))),0) -> 0 | H54: =IF(B54=1,$B$31*(1-p_contr)*(A54<=$B$8),0) -> 0 | I54: =G54+H54 -> 0 | J54: =IF(B54=1,$B$16*$B$29,0) -> 10785.432 | K54: =IF(V_figli=1,1,IF(I54>tf_S5,tf_M5,IF(I54>tf_S4,tf_M4,IF(I54>tf_S3,tf_M3,1)))) -> 1 | L54: =MIN(J54*(1-K54),I54) -> 0 | M54: =J54-L54 -> 10785.432 | N54: =G54+M54 -> 10785.432 | O54: =MAX(0,IF(N54<=sc_L1,sc_A1*N54,IF(N54<=sc_L2,sc_B1+sc_A2*(N54-sc_L1),sc_B2+sc_A3*(N54-sc_L2)))-(IF(N54<=8500,1955,IF(N54<=28000,700+1255*(28000-N54)/19500,IF(N54<=50000,700*(50000-N54)/22000,0)))+IF(AND(N54>25000,N54<=29000),50,0))) -> 672.73744 | P54: =IF(N54>0,N54-O54-IF(O54>0,p_add*N54,0),0) -> 9896.986 | Q54: =IF(B54=1,MAX(M54-(IF((I54+M54)<=sc_L1,sc_A1*(I54+M54),IF((I54+M54)<=sc_L2,sc_B1+sc_A2*((I54+M54)-sc_L1),sc_B2+sc_A3*((I54+M54)-sc_L2)))-IF(I54<=sc_L1,sc_A1*I54,IF(I54<=sc_L2,sc_B1+sc_A2*(I54-sc_L1),sc_B2+sc_A3*(I54-sc_L2))))-p_add*M54,0),0) -> 8089.074 | R54: =IF(B54=1,IF(A54>$B$8,P54,IF(V_chi="T",E54,C54)+IF(V_chi="T",F54,D54)+Q54),C54+D54+E54+F54) -> 9896.986 | S54: =IF(B54=1,p_spesa/IF(A54-$B$30>=65,V_den65,V_den64),p_spesa) -> 26539.776 | T54: =S54-R54 -> 16642.79 | U54: =U53*(1+p_infl) -> 1.2189944 | V54: =T54*U54 -> 20287.468 | W54: =AD53*IF(AND(V_chi<>"nessuno",A54=V_anno+1),Ved_q,1) -> 886879.25 | X54: =AE53*IF(AND(V_chi<>"nessuno",A54=V_anno+1),Ved_qb,1) -> 355233.77 | Y54: =IF(W54>0,MAX(0,1-X54/W54),0) -> 0.59945644 | Z54: =IF(V54>0,V54/(1-p_cgt*Y54),0) -> 24033.26 | AA54: =IF(AA53<>"",AA53,IF(AND(V54>0,Z54>W54,A54<=p_orizz),A54,"")) | AB54: =IF(V54>0,W54-Z54,W54-V54) -> 862845.99 | AC54: =IF(V54>0,IF(W54>0,X54-X54*Z54/W54,X54),X54-V54) -> 345607.4 | AD54: =AB54*(1+p_rend)*(1+p_infl)*(1-p_bollo) -> 904692.98 | AE54: =AC54 -> 345607.4 | AF54: =AD54/(U54*(1+p_infl)) -> 727611.13
A55: 2038 | B55: =IF(AND(V_chi<>"nessuno",A55>V_anno),1,0) -> 1 | C55: =Tz_netto*(A55<=$B$8) -> 0 | D55: =$B$20*IF(A55>$B$21,1,IF(A55=$B$21,(13-$B$22)/12,0)) -> 0 | E55: =Cm_netto*(A55<=$B$8) -> 0 | F55: =$B$26*IF(A55>$B$27,1,IF(A55=$B$27,(13-$B$28)/12,0)) -> 0 | G55: =IF(B55=1,IF(V_chi="T",$B$25*IF(A55>$B$27,1,IF(A55=$B$27,(13-$B$28)/12,0)),$B$19*IF(A55>$B$21,1,IF(A55=$B$21,(13-$B$22)/12,0))),0) -> 0 | H55: =IF(B55=1,$B$31*(1-p_contr)*(A55<=$B$8),0) -> 0 | I55: =G55+H55 -> 0 | J55: =IF(B55=1,$B$16*$B$29,0) -> 10785.432 | K55: =IF(V_figli=1,1,IF(I55>tf_S5,tf_M5,IF(I55>tf_S4,tf_M4,IF(I55>tf_S3,tf_M3,1)))) -> 1 | L55: =MIN(J55*(1-K55),I55) -> 0 | M55: =J55-L55 -> 10785.432 | N55: =G55+M55 -> 10785.432 | O55: =MAX(0,IF(N55<=sc_L1,sc_A1*N55,IF(N55<=sc_L2,sc_B1+sc_A2*(N55-sc_L1),sc_B2+sc_A3*(N55-sc_L2)))-(IF(N55<=8500,1955,IF(N55<=28000,700+1255*(28000-N55)/19500,IF(N55<=50000,700*(50000-N55)/22000,0)))+IF(AND(N55>25000,N55<=29000),50,0))) -> 672.73744 | P55: =IF(N55>0,N55-O55-IF(O55>0,p_add*N55,0),0) -> 9896.986 | Q55: =IF(B55=1,MAX(M55-(IF((I55+M55)<=sc_L1,sc_A1*(I55+M55),IF((I55+M55)<=sc_L2,sc_B1+sc_A2*((I55+M55)-sc_L1),sc_B2+sc_A3*((I55+M55)-sc_L2)))-IF(I55<=sc_L1,sc_A1*I55,IF(I55<=sc_L2,sc_B1+sc_A2*(I55-sc_L1),sc_B2+sc_A3*(I55-sc_L2))))-p_add*M55,0),0) -> 8089.074 | R55: =IF(B55=1,IF(A55>$B$8,P55,IF(V_chi="T",E55,C55)+IF(V_chi="T",F55,D55)+Q55),C55+D55+E55+F55) -> 9896.986 | S55: =IF(B55=1,p_spesa/IF(A55-$B$30>=65,V_den65,V_den64),p_spesa) -> 26539.776 | T55: =S55-R55 -> 16642.79 | U55: =U54*(1+p_infl) -> 1.2433743 | V55: =T55*U55 -> 20693.218 | W55: =AD54*IF(AND(V_chi<>"nessuno",A55=V_anno+1),Ved_q,1) -> 904692.98 | X55: =AE54*IF(AND(V_chi<>"nessuno",A55=V_anno+1),Ved_qb,1) -> 345607.4 | Y55: =IF(W55>0,MAX(0,1-X55/W55),0) -> 0.61798377 | Z55: =IF(V55>0,V55/(1-p_cgt*Y55),0) -> 24654.618 | AA55: =IF(AA54<>"",AA54,IF(AND(V55>0,Z55>W55,A55<=p_orizz),A55,"")) | AB55: =IF(V55>0,W55-Z55,W55-V55) -> 880038.36 | AC55: =IF(V55>0,IF(W55>0,X55-X55*Z55/W55,X55),X55-V55) -> 336188.94 | AD55: =AB55*(1+p_rend)*(1+p_infl)*(1-p_bollo) -> 922719.17 | AE55: =AC55 -> 336188.94 | AF55: =AD55/(U55*(1+p_infl)) -> 727557.77
A56: 2039 | B56: =IF(AND(V_chi<>"nessuno",A56>V_anno),1,0) -> 1 | C56: =Tz_netto*(A56<=$B$8) -> 0 | D56: =$B$20*IF(A56>$B$21,1,IF(A56=$B$21,(13-$B$22)/12,0)) -> 0 | E56: =Cm_netto*(A56<=$B$8) -> 0 | F56: =$B$26*IF(A56>$B$27,1,IF(A56=$B$27,(13-$B$28)/12,0)) -> 0 | G56: =IF(B56=1,IF(V_chi="T",$B$25*IF(A56>$B$27,1,IF(A56=$B$27,(13-$B$28)/12,0)),$B$19*IF(A56>$B$21,1,IF(A56=$B$21,(13-$B$22)/12,0))),0) -> 0 | H56: =IF(B56=1,$B$31*(1-p_contr)*(A56<=$B$8),0) -> 0 | I56: =G56+H56 -> 0 | J56: =IF(B56=1,$B$16*$B$29,0) -> 10785.432 | K56: =IF(V_figli=1,1,IF(I56>tf_S5,tf_M5,IF(I56>tf_S4,tf_M4,IF(I56>tf_S3,tf_M3,1)))) -> 1 | L56: =MIN(J56*(1-K56),I56) -> 0 | M56: =J56-L56 -> 10785.432 | N56: =G56+M56 -> 10785.432 | O56: =MAX(0,IF(N56<=sc_L1,sc_A1*N56,IF(N56<=sc_L2,sc_B1+sc_A2*(N56-sc_L1),sc_B2+sc_A3*(N56-sc_L2)))-(IF(N56<=8500,1955,IF(N56<=28000,700+1255*(28000-N56)/19500,IF(N56<=50000,700*(50000-N56)/22000,0)))+IF(AND(N56>25000,N56<=29000),50,0))) -> 672.73744 | P56: =IF(N56>0,N56-O56-IF(O56>0,p_add*N56,0),0) -> 9896.986 | Q56: =IF(B56=1,MAX(M56-(IF((I56+M56)<=sc_L1,sc_A1*(I56+M56),IF((I56+M56)<=sc_L2,sc_B1+sc_A2*((I56+M56)-sc_L1),sc_B2+sc_A3*((I56+M56)-sc_L2)))-IF(I56<=sc_L1,sc_A1*I56,IF(I56<=sc_L2,sc_B1+sc_A2*(I56-sc_L1),sc_B2+sc_A3*(I56-sc_L2))))-p_add*M56,0),0) -> 8089.074 | R56: =IF(B56=1,IF(A56>$B$8,P56,IF(V_chi="T",E56,C56)+IF(V_chi="T",F56,D56)+Q56),C56+D56+E56+F56) -> 9896.986 | S56: =IF(B56=1,p_spesa/IF(A56-$B$30>=65,V_den65,V_den64),p_spesa) -> 26539.776 | T56: =S56-R56 -> 16642.79 | U56: =U55*(1+p_infl) -> 1.2682418 | V56: =T56*U56 -> 21107.082 | W56: =AD55*IF(AND(V_chi<>"nessuno",A56=V_anno+1),Ved_q,1) -> 922719.17 | X56: =AE55*IF(AND(V_chi<>"nessuno",A56=V_anno+1),Ved_qb,1) -> 336188.94 | Y56: =IF(W56>0,MAX(0,1-X56/W56),0) -> 0.63565411 | Z56: =IF(V56>0,V56/(1-p_cgt*Y56),0) -> 25286.121 | AA56: =IF(AA55<>"",AA55,IF(AND(V56>0,Z56>W56,A56<=p_orizz),A56,"")) | AB56: =IF(V56>0,W56-Z56,W56-V56) -> 897433.05 | AC56: =IF(V56>0,IF(W56>0,X56-X56*Z56/W56,X56),X56-V56) -> 326976.05 | AD56: =AB56*(1+p_rend)*(1+p_infl)*(1-p_bollo) -> 940957.47 | AE56: =AC56 -> 326976.05 | AF56: =AD56/(U56*(1+p_infl)) -> 727390.73
... A95: 2078 | B95: =IF(AND(V_chi<>"nessuno",A95>V_anno),1,0) -> 1 | C95: =Tz_netto*(A95<=$B$8) -> 0 | D95: =$B$20*IF(A95>$B$21,1,IF(A95=$B$21,(13-$B$22)/12,0)) -> 21041.391 | E95: =Cm_netto*(A95<=$B$8) -> 0 | F95: =$B$26*IF(A95>$B$27,1,IF(A95=$B$27,(13-$B$28)/12,0)) -> 11277.359 | G95: =IF(B95=1,IF(V_chi="T",$B$25*IF(A95>$B$27,1,IF(A95=$B$27,(13-$B$28)/12,0)),$B$19*IF(A95>$B$21,1,IF(A95=$B$21,(13-$B$22)/12,0))),0) -> 12798.692 | H95: =IF(B95=1,$B$31*(1-p_contr)*(A95<=$B$8),0) -> 0 | I95: =G95+H95 -> 12798.692 | J95: =IF(B95=1,$B$16*$B$29,0) -> 10785.432 | K95: =IF(V_figli=1,1,IF(I95>tf_S5,tf_M5,IF(I95>tf_S4,tf_M4,IF(I95>tf_S3,tf_M3,1)))) -> 1 | L95: =MIN(J95*(1-K95),I95) -> 0 | M95: =J95-L95 -> 10785.432 | N95: =G95+M95 -> 23584.124 | O95: =MAX(0,IF(N95<=sc_L1,sc_A1*N95,IF(N95<=sc_L2,sc_B1+sc_A2*(N95-sc_L1),sc_B2+sc_A3*(N95-sc_L2)))-(IF(N95<=8500,1955,IF(N95<=28000,700+1255*(28000-N95)/19500,IF(N95<=50000,700*(50000-N95)/22000,0)))+IF(AND(N95>25000,N95<=29000),50,0))) -> 4440.1471 | P95: =IF(N95>0,N95-O95-IF(O95>0,p_add*N95,0),0) -> 18672.294 | Q95: =IF(B95=1,MAX(M95-(IF((I95+M95)<=sc_L1,sc_A1*(I95+M95),IF((I95+M95)<=sc_L2,sc_B1+sc_A2*((I95+M95)-sc_L1),sc_B2+sc_A3*((I95+M95)-sc_L2)))-IF(I95<=sc_L1,sc_A1*I95,IF(I95<=sc_L2,sc_B1+sc_A2*(I95-sc_L1),sc_B2+sc_A3*(I95-sc_L2))))-p_add*M95,0),0) -> 8089.074 | R95: =IF(B95=1,IF(A95>$B$8,P95,IF(V_chi="T",E95,C95)+IF(V_chi="T",F95,D95)+Q95),C95+D95+E95+F95) -> 18672.294 | S95: =IF(B95=1,p_spesa/IF(A95-$B$30>=65,V_den65,V_den64),p_spesa) -> 25306.748 | T95: =S95-R95 -> 6634.4545 | U95: =U94*(1+p_infl) -> 2.7454198 | V95: =T95*U95 -> 18214.363 | W95: =AD94*IF(AND(V_chi<>"nessuno",A95=V_anno+1),Ved_q,1) -> 3099723.4 | X95: =AE94*IF(AND(V_chi<>"nessuno",A95=V_anno+1),Ved_qb,1) -> 178109.57 | Y95: =IF(W95>0,MAX(0,1-X95/W95),0) -> 0.94254017 | Z95: =IF(V95>0,V95/(1-p_cgt*Y95),0) -> 24126.915 | AA95: =IF(AA94<>"",AA94,IF(AND(V95>0,Z95>W95,A95<=p_orizz),A95,"")) | AB95: =IF(V95>0,W95-Z95,W95-V95) -> 3075596.5 | AC95: =IF(V95>0,IF(W95>0,X95-X95*Z95/W95,X95),X95-V95) -> 176723.24 | AD95: =AB95*(1+p_rend)*(1+p_infl)*(1-p_bollo) -> 3224759.2 | AE95: =AC95 -> 176723.24 | AF95: =AD95/(U95*(1+p_infl)) -> 1151564.7

Sheet 5 - Motore e tabelle
A1: 5 - Motore e tabelle (non modificare)
A2: Strumento informativo / divulgativo. NON è consulenza finanziaria. I valori sono indicativi al 2026 e vanno verificati col tuo consulente.
A3: Le tabelle sono dati di legge e di fonti ufficiali con la data accanto; le celle gialle si possono aggiornare quando le norme cambiano. Il motore del calcolo, in fondo al foglio, ripete il conto per molti scenari: non modificarlo.
A5: Scaglioni IRPEF 2026 e costanti derivate (TUIR artt. 11-13; L. 207/2024; verifica ottobre 2026 (18/10/2026))
A6: Primo scaglione, fino a (€) | B6: 28000
A7: Secondo scaglione, fino a (€) | B7: 50000
A8: Aliquota 1° scaglione | B8: 0.23
A9: Aliquota 2° scaglione | B9: 0.33
A10: Aliquota 3° scaglione | B10: 0.43
A11: Imposta a fine 1° scaglione (€) | B11: =sc_A1*sc_L1 -> 6440
A12: Imposta a fine 2° scaglione (€) | B12: =sc_B1+sc_A2*(sc_L2-sc_L1) -> 13700
A13: Detrazioni nelle formule (importi di legge, anno 2026): lavoro dipendente 1.955 € fino a 15.000 €, poi decrescente fino a 50.000 €, +65 € da 25.000 a 35.000 €; ulteriore detrazione 1.000 € da 20.000 a 32.000 €, decrescente fino a 40.000 €; pensione 1.955 € fino a 8.500 €, poi decrescente fino a 50.000 €, +50 € da 25.000 a 29.000 €. Somma non imponibile (L. 207/2024 art. 1 c. 4): 7,1% fino a 8.500 €, 5,3% fino a 15.000 €, 4,8% fino a 20.000 €, zero oltre.
A15: Riduzione della reversibilità per reddito (Tabella F, L. 335/1995; soglie provvisorie; verifica ottobre 2026 (18/10/2026))
A16: Soglia 3 volte il trattamento minimo (€) | B16: =3*p_TM -> 23862.15 | C16: Reversibilità pagata al 75% | D16: 0.75
A17: Soglia 4 volte il trattamento minimo (€) | B17: =4*p_TM -> 31816.2 | C17: Reversibilità pagata al 60% | D17: 0.6
A18: Soglia 5 volte il trattamento minimo (€) | B18: =5*p_TM -> 39770.25 | C18: Reversibilità pagata al 50% | D18: 0.5
A20: Costanti di calcolo derivate
A21: Fattore di crescita nominale annuo F | B21: =(1+p_rend)*(1+p_infl)*(1-p_bollo) -> 1.0484988
A22: Fattore di crescita reale annuo G | B22: =(1+p_rend)*(1-p_bollo) -> 1.02794
A23: Rapporto tra tasso di revisione e età (revisione continua) | B23: =-LN(58.4/64.7)/44 -> 0.0023283025 | C23: RGS 27, riquadro 6.1: coefficiente da 64,7 a 58,4 in 44 anni
A24: Rapporto tra tasso di revisione e età (revisione accelerata) | B24: =-LN(5.3/6.024)/30 -> 0.0042681557 | C24: Ipotesi dell'analista: 6,024 a 5,3 in 30 anni (età di riferimento 69)
A26: Requisiti di età per la pensione di vecchiaia (INPS circ. 28/2026 per 2027-28; RGS 27 Tab. A1.4 dal 2029; verifica ottobre 2026 (18/10/2026))
A27: Anno | B27: Ordinario (mesi) | C27: Via 71 anni (mesi) | D27: Norma / proiezione
A28: 2012 | B28: 792 | C28: =B28+p_scarto -> 840 | D28: norma
A29: 2013 | B29: 795 | C29: =B29+p_scarto -> 843 | D29: norma
A30: 2014 | B30: 795 | C30: =B30+p_scarto -> 843 | D30: norma
A31: 2015 | B31: 795 | C31: =B31+p_scarto -> 843 | D31: norma
A32: 2016 | B32: 799 | C32: =B32+p_scarto -> 847 | D32: norma
A33: 2017 | B33: 799 | C33: =B33+p_scarto -> 847 | D33: norma
A34: 2018 | B34: 799 | C34: =B34+p_scarto -> 847 | D34: norma
A35: 2019 | B35: 804 | C35: =B35+p_scarto -> 852 | D35: norma
A36: 2020 | B36: 804 | C36: =B36+p_scarto -> 852 | D36: norma
A37: 2021 | B37: 804 | C37: =B37+p_scarto -> 852 | D37: norma
A38: 2022 | B38: 804 | C38: =B38+p_scarto -> 852 | D38: norma
A39: 2023 | B39: 804 | C39: =B39+p_scarto -> 852 | D39: norma
... A100: 2084 | B100: 849 | C100: =B100+p_scarto -> 897 | D100: proiezione RGS
A101: Ultimo anno in tabella | B101: =MAX(REQ_anno) -> 2084
A102: Primo anno in tabella | B102: =MIN(REQ_anno) -> 2012
A104: Coefficienti di trasformazione 57-71 anni (DD 20/11/2024, validi 2025-26; verifica ottobre 2026 (18/10/2026))
A105: Età | B105: Coefficiente
A106: 57 | B106: 0.04204
A107: 58 | B107: 0.04308
A108: 59 | B108: 0.04419
A109: 60 | B109: 0.04536
A110: 61 | B110: 0.04661
A111: 62 | B111: 0.04795
A112: 63 | B112: 0.04936
A113: 64 | B113: 0.05088
A114: 65 | B114: 0.0525
A115: 66 | B115: 0.05423
A116: 67 | B116: 0.05608
A117: 68 | B117: 0.05808
... A120: 71 | B120: 0.0651
A121: Tra un'età e l'altra si interpola in modo lineare sui mesi; oltre 71 anni vale il coefficiente di 71 anni.
A123: Coefficienti 2013 e 2025 ai nodi (RGS 27 Tab. A1.1, per la revisione dei coefficienti), in %
A124: Età | B124: Anno 2013 | C124: Anno 2025
A125: 57 | B125: 4.304 | C125: 4.204
A126: 60 | B126: 4.661 | C126: 4.536
A127: 62 | B127: 4.94 | C127: 4.795
A128: 64 | B128: 5.259 | C128: 5.088
A129: 65 | B129: 5.435 | C129: 5.25
A130: 66 | B130: 5.624 | C130: 5.423
A131: 67 | B131: 5.826 | C131: 5.608
A132: 68 | B132: 6.046 | C132: 5.808
A133: 69 | B133: 6.283 | C133: 6.024
A134: 70 | B134: 6.541 | C134: 6.258
A136: Griglia mensile 57-71 anni: log del rapporto 2025/2013 (supporto alla revisione dei coefficienti)
A137: Mesi | B137: Età (anni) | C137: Coeff. 2025 interpolato | D137: Coeff. 2013 interpolato | E137: log del rapporto
A138: 684 | B138: =A138/12 -> 57 | C138: =IF(B138>=70,INDEX(Nodi_2025,10),INDEX(Nodi_2025,MATCH(B138,N_eta,1))+(B138-INDEX(N_eta,MATCH(B138,N_eta,1)))*(INDEX(Nodi_2025,MATCH(B138,N_eta,1)+1)-INDEX(Nodi_2025,MATCH(B138,N_eta,1)))/(INDEX(N_eta,MATCH(B138,N_eta,1)+1)-INDEX(N_eta,MATCH(B138,N_eta,1)))) -> 4.204 | D138: =IF(B138>=70,INDEX(Nodi_2013,10),INDEX(Nodi_2013,MATCH(B138,N_eta,1))+(B138-INDEX(N_eta,MATCH(B138,N_eta,1)))*(INDEX(Nodi_2013,MATCH(B138,N_eta,1)+1)-INDEX(Nodi_2013,MATCH(B138,N_eta,1)))/(INDEX(N_eta,MATCH(B138,N_eta,1)+1)-INDEX(N_eta,MATCH(B138,N_eta,1)))) -> 4.304 | E138: =LN(C138/D138) -> -0.02350837
A139: 685 | B139: =A139/12 -> 57.083333 | C139: =IF(B139>=70,INDEX(Nodi_2025,10),INDEX(Nodi_2025,MATCH(B139,N_eta,1))+(B139-INDEX(N_eta,MATCH(B139,N_eta,1)))*(INDEX(Nodi_2025,MATCH(B139,N_eta,1)+1)-INDEX(Nodi_2025,MATCH(B139,N_eta,1)))/(INDEX(N_eta,MATCH(B139,N_eta,1)+1)-INDEX(N_eta,MATCH(B139,N_eta,1)))) -> 4.2132222 | D139: =IF(B139>=70,INDEX(Nodi_2013,10),INDEX(Nodi_2013,MATCH(B139,N_eta,1))+(B139-INDEX(N_eta,MATCH(B139,N_eta,1)))*(INDEX(Nodi_2013,MATCH(B139,N_eta,1)+1)-INDEX(Nodi_2013,MATCH(B139,N_eta,1)))/(INDEX(N_eta,MATCH(B139,N_eta,1)+1)-INDEX(N_eta,MATCH(B139,N_eta,1)))) -> 4.3139167 | E139: =LN(C139/D139) -> -0.023618502
A140: 686 | B140: =A140/12 -> 57.166667 | C140: =IF(B140>=70,INDEX(Nodi_2025,10),INDEX(Nodi_2025,MATCH(B140,N_eta,1))+(B140-INDEX(N_eta,MATCH(B140,N_eta,1)))*(INDEX(Nodi_2025,MATCH(B140,N_eta,1)+1)-INDEX(Nodi_2025,MATCH(B140,N_eta,1)))/(INDEX(N_eta,MATCH(B140,N_eta,1)+1)-INDEX(N_eta,MATCH(B140,N_eta,1)))) -> 4.2224444 | D140: =IF(B140>=70,INDEX(Nodi_2013,10),INDEX(Nodi_2013,MATCH(B140,N_eta,1))+(B140-INDEX(N_eta,MATCH(B140,N_eta,1)))*(INDEX(Nodi_2013,MATCH(B140,N_eta,1)+1)-INDEX(Nodi_2013,MATCH(B140,N_eta,1)))/(INDEX(N_eta,MATCH(B140,N_eta,1)+1)-INDEX(N_eta,MATCH(B140,N_eta,1)))) -> 4.3238333 | E140: =LN(C140/D140) -> -0.023728142
A141: 687 | B141: =A141/12 -> 57.25 | C141: =IF(B141>=70,INDEX(Nodi_2025,10),INDEX(Nodi_2025,MATCH(B141,N_eta,1))+(B141-INDEX(N_eta,MATCH(B141,N_eta,1)))*(INDEX(Nodi_2025,MATCH(B141,N_eta,1)+1)-INDEX(Nodi_2025,MATCH(B141,N_eta,1)))/(INDEX(N_eta,MATCH(B141,N_eta,1)+1)-INDEX(N_eta,MATCH(B141,N_eta,1)))) -> 4.2316667 | D141: =IF(B141>=70,INDEX(Nodi_2013,10),INDEX(Nodi_2013,MATCH(B141,N_eta,1))+(B141-INDEX(N_eta,MATCH(B141,N_eta,1)))*(INDEX(Nodi_2013,MATCH(B141,N_eta,1)+1)-INDEX(Nodi_2013,MATCH(B141,N_eta,1)))/(INDEX(N_eta,MATCH(B141,N_eta,1)+1)-INDEX(N_eta,MATCH(B141,N_eta,1)))) -> 4.33375 | E141: =LN(C141/D141) -> -0.023837292
A142: 688 | B142: =A142/12 -> 57.333333 | C142: =IF(B142>=70,INDEX(Nodi_2025,10),INDEX(Nodi_2025,MATCH(B142,N_eta,1))+(B142-INDEX(N_eta,MATCH(B142,N_eta,1)))*(INDEX(Nodi_2025,MATCH(B142,N_eta,1)+1)-INDEX(Nodi_2025,MATCH(B142,N_eta,1)))/(INDEX(N_eta,MATCH(B142,N_eta,1)+1)-INDEX(N_eta,MATCH(B142,N_eta,1)))) -> 4.2408889 | D142: =IF(B142>=70,INDEX(Nodi_2013,10),INDEX(Nodi_2013,MATCH(B142,N_eta,1))+(B142-INDEX(N_eta,MATCH(B142,N_eta,1)))*(INDEX(Nodi_2013,MATCH(B142,N_eta,1)+1)-INDEX(Nodi_2013,MATCH(B142,N_eta,1)))/(INDEX(N_eta,MATCH(B142,N_eta,1)+1)-INDEX(N_eta,MATCH(B142,N_eta,1)))) -> 4.3436667 | E142: =LN(C142/D142) -> -0.023945955
A143: 689 | B143: =A143/12 -> 57.416667 | C143: =IF(B143>=70,INDEX(Nodi_2025,10),INDEX(Nodi_2025,MATCH(B143,N_eta,1))+(B143-INDEX(N_eta,MATCH(B143,N_eta,1)))*(INDEX(Nodi_2025,MATCH(B143,N_eta,1)+1)-INDEX(Nodi_2025,MATCH(B143,N_eta,1)))/(INDEX(N_eta,MATCH(B143,N_eta,1)+1)-INDEX(N_eta,MATCH(B143,N_eta,1)))) -> 4.2501111 | D143: =IF(B143>=70,INDEX(Nodi_2013,10),INDEX(Nodi_2013,MATCH(B143,N_eta,1))+(B143-INDEX(N_eta,MATCH(B143,N_eta,1)))*(INDEX(Nodi_2013,MATCH(B143,N_eta,1)+1)-INDEX(Nodi_2013,MATCH(B143,N_eta,1)))/(INDEX(N_eta,MATCH(B143,N_eta,1)+1)-INDEX(N_eta,MATCH(B143,N_eta,1)))) -> 4.3535833 | E143: =LN(C143/D143) -> -0.024054134
A144: 690 | B144: =A144/12 -> 57.5 | C144: =IF(B144>=70,INDEX(Nodi_2025,10),INDEX(Nodi_2025,MATCH(B144,N_eta,1))+(B144-INDEX(N_eta,MATCH(B144,N_eta,1)))*(INDEX(Nodi_2025,MATCH(B144,N_eta,1)+1)-INDEX(Nodi_2025,MATCH(B144,N_eta,1)))/(INDEX(N_eta,MATCH(B144,N_eta,1)+1)-INDEX(N_eta,MATCH(B144,N_eta,1)))) -> 4.2593333 | D144: =IF(B144>=70,INDEX(Nodi_2013,10),INDEX(Nodi_2013,MATCH(B144,N_eta,1))+(B144-INDEX(N_eta,MATCH(B144,N_eta,1)))*(INDEX(Nodi_2013,MATCH(B144,N_eta,1)+1)-INDEX(Nodi_2013,MATCH(B144,N_eta,1)))/(INDEX(N_eta,MATCH(B144,N_eta,1)+1)-INDEX(N_eta,MATCH(B144,N_eta,1)))) -> 4.3635 | E144: =LN(C144/D144) -> -0.024161834
A145: 691 | B145: =A145/12 -> 57.583333 | C145: =IF(B145>=70,INDEX(Nodi_2025,10),INDEX(Nodi_2025,MATCH(B145,N_eta,1))+(B145-INDEX(N_eta,MATCH(B145,N_eta,1)))*(INDEX(Nodi_2025,MATCH(B145,N_eta,1)+1)-INDEX(Nodi_2025,MATCH(B145,N_eta,1)))/(INDEX(N_eta,MATCH(B145,N_eta,1)+1)-INDEX(N_eta,MATCH(B145,N_eta,1)))) -> 4.2685556 | D145: =IF(B145>=70,INDEX(Nodi_2013,10),INDEX(Nodi_2013,MATCH(B145,N_eta,1))+(B145-INDEX(N_eta,MATCH(B145,N_eta,1)))*(INDEX(Nodi_2013,MATCH(B145,N_eta,1)+1)-INDEX(Nodi_2013,MATCH(B145,N_eta,1)))/(INDEX(N_eta,MATCH(B145,N_eta,1)+1)-INDEX(N_eta,MATCH(B145,N_eta,1)))) -> 4.3734167 | E145: =LN(C145/D145) -> -0.024269057
A146: 692 | B146: =A146/12 -> 57.666667 | C146: =IF(B146>=70,INDEX(Nodi_2025,10),INDEX(Nodi_2025,MATCH(B146,N_eta,1))+(B146-INDEX(N_eta,MATCH(B146,N_eta,1)))*(INDEX(Nodi_2025,MATCH(B146,N_eta,1)+1)-INDEX(Nodi_2025,MATCH(B146,N_eta,1)))/(INDEX(N_eta,MATCH(B146,N_eta,1)+1)-INDEX(N_eta,MATCH(B146,N_eta,1)))) -> 4.2777778 | D146: =IF(B146>=70,INDEX(Nodi_2013,10),INDEX(Nodi_2013,MATCH(B146,N_eta,1))+(B146-INDEX(N_eta,MATCH(B146,N_eta,1)))*(INDEX(Nodi_2013,MATCH(B146,N_eta,1)+1)-INDEX(Nodi_2013,MATCH(B146,N_eta,1)))/(INDEX(N_eta,MATCH(B146,N_eta,1)+1)-INDEX(N_eta,MATCH(B146,N_eta,1)))) -> 4.3833333 | E146: =LN(C146/D146) -> -0.024375806
A147: 693 | B147: =A147/12 -> 57.75 | C147: =IF(B147>=70,INDEX(Nodi_2025,10),INDEX(Nodi_2025,MATCH(B147,N_eta,1))+(B147-INDEX(N_eta,MATCH(B147,N_eta,1)))*(INDEX(Nodi_2025,MATCH(B147,N_eta,1)+1)-INDEX(Nodi_2025,MATCH(B147,N_eta,1)))/(INDEX(N_eta,MATCH(B147,N_eta,1)+1)-INDEX(N_eta,MATCH(B147,N_eta,1)))) -> 4.287 | D147: =IF(B147>=70,INDEX(Nodi_2013,10),INDEX(Nodi_2013,MATCH(B147,N_eta,1))+(B147-INDEX(N_eta,MATCH(B147,N_eta,1)))*(INDEX(Nodi_2013,MATCH(B147,N_eta,1)+1)-INDEX(Nodi_2013,MATCH(B147,N_eta,1)))/(INDEX(N_eta,MATCH(B147,N_eta,1)+1)-INDEX(N_eta,MATCH(B147,N_eta,1)))) -> 4.39325 | E147: =LN(C147/D147) -> -0.024482084
A148: 694 | B148: =A148/12 -> 57.833333 | C148: =IF(B148>=70,INDEX(Nodi_2025,10),INDEX(Nodi_2025,MATCH(B148,N_eta,1))+(B148-INDEX(N_eta,MATCH(B148,N_eta,1)))*(INDEX(Nodi_2025,MATCH(B148,N_eta,1)+1)-INDEX(Nodi_2025,MATCH(B148,N_eta,1)))/(INDEX(N_eta,MATCH(B148,N_eta,1)+1)-INDEX(N_eta,MATCH(B148,N_eta,1)))) -> 4.2962222 | D148: =IF(B148>=70,INDEX(Nodi_2013,10),INDEX(Nodi_2013,MATCH(B148,N_eta,1))+(B148-INDEX(N_eta,MATCH(B148,N_eta,1)))*(INDEX(Nodi_2013,MATCH(B148,N_eta,1)+1)-INDEX(Nodi_2013,MATCH(B148,N_eta,1)))/(INDEX(N_eta,MATCH(B148,N_eta,1)+1)-INDEX(N_eta,MATCH(B148,N_eta,1)))) -> 4.4031667 | E148: =LN(C148/D148) -> -0.024587895
A149: 695 | B149: =A149/12 -> 57.916667 | C149: =IF(B149>=70,INDEX(Nodi_2025,10),INDEX(Nodi_2025,MATCH(B149,N_eta,1))+(B149-INDEX(N_eta,MATCH(B149,N_eta,1)))*(INDEX(Nodi_2025,MATCH(B149,N_eta,1)+1)-INDEX(Nodi_2025,MATCH(B149,N_eta,1)))/(INDEX(N_eta,MATCH(B149,N_eta,1)+1)-INDEX(N_eta,MATCH(B149,N_eta,1)))) -> 4.3054444 | D149: =IF(B149>=70,INDEX(Nodi_2013,10),INDEX(Nodi_2013,MATCH(B149,N_eta,1))+(B149-INDEX(N_eta,MATCH(B149,N_eta,1)))*(INDEX(Nodi_2013,MATCH(B149,N_eta,1)+1)-INDEX(Nodi_2013,MATCH(B149,N_eta,1)))/(INDEX(N_eta,MATCH(B149,N_eta,1)+1)-INDEX(N_eta,MATCH(B149,N_eta,1)))) -> 4.4130833 | E149: =LN(C149/D149) -> -0.024693242
... A294: 840 | B294: =A294/12 -> 70 | C294: =IF(B294>=70,INDEX(Nodi_2025,10),INDEX(Nodi_2025,MATCH(B294,N_eta,1))+(B294-INDEX(N_eta,MATCH(B294,N_eta,1)))*(INDEX(Nodi_2025,MATCH(B294,N_eta,1)+1)-INDEX(Nodi_2025,MATCH(B294,N_eta,1)))/(INDEX(N_eta,MATCH(B294,N_eta,1)+1)-INDEX(N_eta,MATCH(B294,N_eta,1)))) -> 6.258 | D294: =IF(B294>=70,INDEX(Nodi_2013,10),INDEX(Nodi_2013,MATCH(B294,N_eta,1))+(B294-INDEX(N_eta,MATCH(B294,N_eta,1)))*(INDEX(Nodi_2013,MATCH(B294,N_eta,1)+1)-INDEX(Nodi_2013,MATCH(B294,N_eta,1)))/(INDEX(N_eta,MATCH(B294,N_eta,1)+1)-INDEX(N_eta,MATCH(B294,N_eta,1)))) -> 6.541 | E294: =LN(C294/D294) -> -0.044229414
A295: 841 | B295: =A295/12 -> 70.083333 | C295: =IF(B295>=70,INDEX(Nodi_2025,10),INDEX(Nodi_2025,MATCH(B295,N_eta,1))+(B295-INDEX(N_eta,MATCH(B295,N_eta,1)))*(INDEX(Nodi_2025,MATCH(B295,N_eta,1)+1)-INDEX(Nodi_2025,MATCH(B295,N_eta,1)))/(INDEX(N_eta,MATCH(B295,N_eta,1)+1)-INDEX(N_eta,MATCH(B295,N_eta,1)))) -> 6.258 | D295: =IF(B295>=70,INDEX(Nodi_2013,10),INDEX(Nodi_2013,MATCH(B295,N_eta,1))+(B295-INDEX(N_eta,MATCH(B295,N_eta,1)))*(INDEX(Nodi_2013,MATCH(B295,N_eta,1)+1)-INDEX(Nodi_2013,MATCH(B295,N_eta,1)))/(INDEX(N_eta,MATCH(B295,N_eta,1)+1)-INDEX(N_eta,MATCH(B295,N_eta,1)))) -> 6.541 | E295: =E294+(B295-70)*(E294-E282) -> -0.044407191
A296: 842 | B296: =A296/12 -> 70.166667 | C296: =IF(B296>=70,INDEX(Nodi_2025,10),INDEX(Nodi_2025,MATCH(B296,N_eta,1))+(B296-INDEX(N_eta,MATCH(B296,N_eta,1)))*(INDEX(Nodi_2025,MATCH(B296,N_eta,1)+1)-INDEX(Nodi_2025,MATCH(B296,N_eta,1)))/(INDEX(N_eta,MATCH(B296,N_eta,1)+1)-INDEX(N_eta,MATCH(B296,N_eta,1)))) -> 6.258 | D296: =IF(B296>=70,INDEX(Nodi_2013,10),INDEX(Nodi_2013,MATCH(B296,N_eta,1))+(B296-INDEX(N_eta,MATCH(B296,N_eta,1)))*(INDEX(Nodi_2013,MATCH(B296,N_eta,1)+1)-INDEX(Nodi_2013,MATCH(B296,N_eta,1)))/(INDEX(N_eta,MATCH(B296,N_eta,1)+1)-INDEX(N_eta,MATCH(B296,N_eta,1)))) -> 6.541 | E296: =E294+(B296-70)*(E294-E282) -> -0.044584969
A297: 843 | B297: =A297/12 -> 70.25 | C297: =IF(B297>=70,INDEX(Nodi_2025,10),INDEX(Nodi_2025,MATCH(B297,N_eta,1))+(B297-INDEX(N_eta,MATCH(B297,N_eta,1)))*(INDEX(Nodi_2025,MATCH(B297,N_eta,1)+1)-INDEX(Nodi_2025,MATCH(B297,N_eta,1)))/(INDEX(N_eta,MATCH(B297,N_eta,1)+1)-INDEX(N_eta,MATCH(B297,N_eta,1)))) -> 6.258 | D297: =IF(B297>=70,INDEX(Nodi_2013,10),INDEX(Nodi_2013,MATCH(B297,N_eta,1))+(B297-INDEX(N_eta,MATCH(B297,N_eta,1)))*(INDEX(Nodi_2013,MATCH(B297,N_eta,1)+1)-INDEX(Nodi_2013,MATCH(B297,N_eta,1)))/(INDEX(N_eta,MATCH(B297,N_eta,1)+1)-INDEX(N_eta,MATCH(B297,N_eta,1)))) -> 6.541 | E297: =E294+(B297-70)*(E294-E282) -> -0.044762746
A298: 844 | B298: =A298/12 -> 70.333333 | C298: =IF(B298>=70,INDEX(Nodi_2025,10),INDEX(Nodi_2025,MATCH(B298,N_eta,1))+(B298-INDEX(N_eta,MATCH(B298,N_eta,1)))*(INDEX(Nodi_2025,MATCH(B298,N_eta,1)+1)-INDEX(Nodi_2025,MATCH(B298,N_eta,1)))/(INDEX(N_eta,MATCH(B298,N_eta,1)+1)-INDEX(N_eta,MATCH(B298,N_eta,1)))) -> 6.258 | D298: =IF(B298>=70,INDEX(Nodi_2013,10),INDEX(Nodi_2013,MATCH(B298,N_eta,1))+(B298-INDEX(N_eta,MATCH(B298,N_eta,1)))*(INDEX(Nodi_2013,MATCH(B298,N_eta,1)+1)-INDEX(Nodi_2013,MATCH(B298,N_eta,1)))/(INDEX(N_eta,MATCH(B298,N_eta,1)+1)-INDEX(N_eta,MATCH(B298,N_eta,1)))) -> 6.541 | E298: =E294+(B298-70)*(E294-E282) -> -0.044940524
A299: 845 | B299: =A299/12 -> 70.416667 | C299: =IF(B299>=70,INDEX(Nodi_2025,10),INDEX(Nodi_2025,MATCH(B299,N_eta,1))+(B299-INDEX(N_eta,MATCH(B299,N_eta,1)))*(INDEX(Nodi_2025,MATCH(B299,N_eta,1)+1)-INDEX(Nodi_2025,MATCH(B299,N_eta,1)))/(INDEX(N_eta,MATCH(B299,N_eta,1)+1)-INDEX(N_eta,MATCH(B299,N_eta,1)))) -> 6.258 | D299: =IF(B299>=70,INDEX(Nodi_2013,10),INDEX(Nodi_2013,MATCH(B299,N_eta,1))+(B299-INDEX(N_eta,MATCH(B299,N_eta,1)))*(INDEX(Nodi_2013,MATCH(B299,N_eta,1)+1)-INDEX(Nodi_2013,MATCH(B299,N_eta,1)))/(INDEX(N_eta,MATCH(B299,N_eta,1)+1)-INDEX(N_eta,MATCH(B299,N_eta,1)))) -> 6.541 | E299: =E294+(B299-70)*(E294-E282) -> -0.045118302
A300: 846 | B300: =A300/12 -> 70.5 | C300: =IF(B300>=70,INDEX(Nodi_2025,10),INDEX(Nodi_2025,MATCH(B300,N_eta,1))+(B300-INDEX(N_eta,MATCH(B300,N_eta,1)))*(INDEX(Nodi_2025,MATCH(B300,N_eta,1)+1)-INDEX(Nodi_2025,MATCH(B300,N_eta,1)))/(INDEX(N_eta,MATCH(B300,N_eta,1)+1)-INDEX(N_eta,MATCH(B300,N_eta,1)))) -> 6.258 | D300: =IF(B300>=70,INDEX(Nodi_2013,10),INDEX(Nodi_2013,MATCH(B300,N_eta,1))+(B300-INDEX(N_eta,MATCH(B300,N_eta,1)))*(INDEX(Nodi_2013,MATCH(B300,N_eta,1)+1)-INDEX(Nodi_2013,MATCH(B300,N_eta,1)))/(INDEX(N_eta,MATCH(B300,N_eta,1)+1)-INDEX(N_eta,MATCH(B300,N_eta,1)))) -> 6.541 | E300: =E294+(B300-70)*(E294-E282) -> -0.045296079
A301: 847 | B301: =A301/12 -> 70.583333 | C301: =IF(B301>=70,INDEX(Nodi_2025,10),INDEX(Nodi_2025,MATCH(B301,N_eta,1))+(B301-INDEX(N_eta,MATCH(B301,N_eta,1)))*(INDEX(Nodi_2025,MATCH(B301,N_eta,1)+1)-INDEX(Nodi_2025,MATCH(B301,N_eta,1)))/(INDEX(N_eta,MATCH(B301,N_eta,1)+1)-INDEX(N_eta,MATCH(B301,N_eta,1)))) -> 6.258 | D301: =IF(B301>=70,INDEX(Nodi_2013,10),INDEX(Nodi_2013,MATCH(B301,N_eta,1))+(B301-INDEX(N_eta,MATCH(B301,N_eta,1)))*(INDEX(Nodi_2013,MATCH(B301,N_eta,1)+1)-INDEX(Nodi_2013,MATCH(B301,N_eta,1)))/(INDEX(N_eta,MATCH(B301,N_eta,1)+1)-INDEX(N_eta,MATCH(B301,N_eta,1)))) -> 6.541 | E301: =E294+(B301-70)*(E294-E282) -> -0.045473857
A302: 848 | B302: =A302/12 -> 70.666667 | C302: =IF(B302>=70,INDEX(Nodi_2025,10),INDEX(Nodi_2025,MATCH(B302,N_eta,1))+(B302-INDEX(N_eta,MATCH(B302,N_eta,1)))*(INDEX(Nodi_2025,MATCH(B302,N_eta,1)+1)-INDEX(Nodi_2025,MATCH(B302,N_eta,1)))/(INDEX(N_eta,MATCH(B302,N_eta,1)+1)-INDEX(N_eta,MATCH(B302,N_eta,1)))) -> 6.258 | D302: =IF(B302>=70,INDEX(Nodi_2013,10),INDEX(Nodi_2013,MATCH(B302,N_eta,1))+(B302-INDEX(N_eta,MATCH(B302,N_eta,1)))*(INDEX(Nodi_2013,MATCH(B302,N_eta,1)+1)-INDEX(Nodi_2013,MATCH(B302,N_eta,1)))/(INDEX(N_eta,MATCH(B302,N_eta,1)+1)-INDEX(N_eta,MATCH(B302,N_eta,1)))) -> 6.541 | E302: =E294+(B302-70)*(E294-E282) -> -0.045651634
A303: 849 | B303: =A303/12 -> 70.75 | C303: =IF(B303>=70,INDEX(Nodi_2025,10),INDEX(Nodi_2025,MATCH(B303,N_eta,1))+(B303-INDEX(N_eta,MATCH(B303,N_eta,1)))*(INDEX(Nodi_2025,MATCH(B303,N_eta,1)+1)-INDEX(Nodi_2025,MATCH(B303,N_eta,1)))/(INDEX(N_eta,MATCH(B303,N_eta,1)+1)-INDEX(N_eta,MATCH(B303,N_eta,1)))) -> 6.258 | D303: =IF(B303>=70,INDEX(Nodi_2013,10),INDEX(Nodi_2013,MATCH(B303,N_eta,1))+(B303-INDEX(N_eta,MATCH(B303,N_eta,1)))*(INDEX(Nodi_2013,MATCH(B303,N_eta,1)+1)-INDEX(Nodi_2013,MATCH(B303,N_eta,1)))/(INDEX(N_eta,MATCH(B303,N_eta,1)+1)-INDEX(N_eta,MATCH(B303,N_eta,1)))) -> 6.541 | E303: =E294+(B303-70)*(E294-E282) -> -0.045829412
A304: 850 | B304: =A304/12 -> 70.833333 | C304: =IF(B304>=70,INDEX(Nodi_2025,10),INDEX(Nodi_2025,MATCH(B304,N_eta,1))+(B304-INDEX(N_eta,MATCH(B304,N_eta,1)))*(INDEX(Nodi_2025,MATCH(B304,N_eta,1)+1)-INDEX(Nodi_2025,MATCH(B304,N_eta,1)))/(INDEX(N_eta,MATCH(B304,N_eta,1)+1)-INDEX(N_eta,MATCH(B304,N_eta,1)))) -> 6.258 | D304: =IF(B304>=70,INDEX(Nodi_2013,10),INDEX(Nodi_2013,MATCH(B304,N_eta,1))+(B304-INDEX(N_eta,MATCH(B304,N_eta,1)))*(INDEX(Nodi_2013,MATCH(B304,N_eta,1)+1)-INDEX(Nodi_2013,MATCH(B304,N_eta,1)))/(INDEX(N_eta,MATCH(B304,N_eta,1)+1)-INDEX(N_eta,MATCH(B304,N_eta,1)))) -> 6.541 | E304: =E294+(B304-70)*(E294-E282) -> -0.046007189
A305: 851 | B305: =A305/12 -> 70.916667 | C305: =IF(B305>=70,INDEX(Nodi_2025,10),INDEX(Nodi_2025,MATCH(B305,N_eta,1))+(B305-INDEX(N_eta,MATCH(B305,N_eta,1)))*(INDEX(Nodi_2025,MATCH(B305,N_eta,1)+1)-INDEX(Nodi_2025,MATCH(B305,N_eta,1)))/(INDEX(N_eta,MATCH(B305,N_eta,1)+1)-INDEX(N_eta,MATCH(B305,N_eta,1)))) -> 6.258 | D305: =IF(B305>=70,INDEX(Nodi_2013,10),INDEX(Nodi_2013,MATCH(B305,N_eta,1))+(B305-INDEX(N_eta,MATCH(B305,N_eta,1)))*(INDEX(Nodi_2013,MATCH(B305,N_eta,1)+1)-INDEX(Nodi_2013,MATCH(B305,N_eta,1)))/(INDEX(N_eta,MATCH(B305,N_eta,1)+1)-INDEX(N_eta,MATCH(B305,N_eta,1)))) -> 6.541 | E305: =E294+(B305-70)*(E294-E282) -> -0.046184967
A306: 852 | B306: =A306/12 -> 71 | C306: =IF(B306>=70,INDEX(Nodi_2025,10),INDEX(Nodi_2025,MATCH(B306,N_eta,1))+(B306-INDEX(N_eta,MATCH(B306,N_eta,1)))*(INDEX(Nodi_2025,MATCH(B306,N_eta,1)+1)-INDEX(Nodi_2025,MATCH(B306,N_eta,1)))/(INDEX(N_eta,MATCH(B306,N_eta,1)+1)-INDEX(N_eta,MATCH(B306,N_eta,1)))) -> 6.258 | D306: =IF(B306>=70,INDEX(Nodi_2013,10),INDEX(Nodi_2013,MATCH(B306,N_eta,1))+(B306-INDEX(N_eta,MATCH(B306,N_eta,1)))*(INDEX(Nodi_2013,MATCH(B306,N_eta,1)+1)-INDEX(Nodi_2013,MATCH(B306,N_eta,1)))/(INDEX(N_eta,MATCH(B306,N_eta,1)+1)-INDEX(N_eta,MATCH(B306,N_eta,1)))) -> 6.541 | E306: =E294+(B306-70)*(E294-E282) -> -0.046362745
A308: Quota dell'eredità che va al superstite (codice civile artt. 538, 544, 582, 583) e imposta di successione (D.Lgs. 346/1990 art. 7)
A309: Chiave | B309: Regime | C309: Testamento | D309: Famiglia d'origine | E309: Quota al superstite
A310: =B310&"|"&C310&"|"&D310 -> 1|0|0 | B310: 1 | C310: 0 | D310: 0 | E310: 1
A311: =B311&"|"&C311&"|"&D311 -> 1|0|1 | B311: 1 | C311: 0 | D311: 1 | E311: 0.66666667
A312: =B312&"|"&C312&"|"&D312 -> 1|0|2 | B312: 1 | C312: 0 | D312: 2 | E312: 0.66666667
A313: =B313&"|"&C313&"|"&D313 -> 1|1|0 | B313: 1 | C313: 1 | D313: 0 | E313: 1
A314: =B314&"|"&C314&"|"&D314 -> 1|1|1 | B314: 1 | C314: 1 | D314: 1 | E314: 0.75
...
