Workbook

Sheet 0-Indice
A1: Inflazione dello stile di vita — il simulatore del caso (2026)
A2: Strumento informativo / divulgativo. NON è consulenza finanziaria. I valori sono indicativi al 2026 e vanno verificati col tuo consulente.
A4: Indice
A5: P-Parametri | B5: Aliquote, detrazioni, soglie: le costanti normative, tutte in un posto solo
A6: 1-Input | B6: La scheda-caso e il vincolo aritmetico da cui esce il capitale
A7: 2-Busta-paga | B7: Il motore fiscale 2026, da RAL 15.000 a 62.000, e le due marginali
A8: 3-Aumento | B8: I due eventi: la promozione ordinaria e il rinnovo con la sostitutiva del 5%
A9: 4-Rapporto-RAL | B9: Il fattore del comma 7 IN FUNZIONE DELLA RAL, e quanto è stretta la finestra
A10: 5-Moltiplicatore | B10: Quanto capitale serve per un euro al mese, per sempre
A11: 6-Anni-al-FIRE | B11: La formula degli anni al traguardo e la controprova anno per anno
A12: 7-Scenari | B12: I quattro destini, la banda del rendimento e il doppio effetto
A13: 8-Soglia-q | B13: La soglia q*: la dimostrazione che non dipende da quanto è grande l'aumento
A14: 9-Traduttore | B14: Traduce una spesa mensile in obiettivo, anni e ore di lavoro
A15: 10-Regola-ora | B15: Quanto vale un'ora, e quanto puoi spendere per ricomprartela
A16: 11-Cruscotto | B16: Gli otto numeri e il semaforo — il foglio della demo
... A18: 13-Verifica | B18: Il confronto fra il motore e i numeri del video, con lo scarto
A20: Come usare
A21: 1. Le celle GIALLE sono input — modificale coi tuoi numeri.
A22: 2. Le celle VERDI sono output — si aggiornano automaticamente.
A23: 3. Tutti i numeri di default sono al 2026 da fonti pubbliche.
A24: 4. Niente codice nascosto: l'Excel è solo formule modificabili.
A26: Fonti dati
A27: • IRPEF 2026 23/33/43% — art. 11 TUIR, L. 199/2025 art. 1 c. 3
A28: • Detrazione da lavoro dipendente — art. 13 c. 1 TUIR
A29: • Ulteriore detrazione — L. 207/2024 art. 1 c. 6 (in vigore per tutto il 2026)
A30: • Imposta sostitutiva 5% sugli incrementi retributivi — L. 199/2025 art. 1 c. 7
A31: • Circolari Agenzia delle Entrate n. 2/E del 24/2/2026 e n. 3/E del 24/6/2026
A32: • Contributi 9,19% — art. 1 c. 769 L. 296/2006
... A40: QUESTA PARTE SCADE: l'imposta sostitutiva del 5% (fogli 3 e 4) vale SOLO sugli incrementi retributivi EROGATI NEL 2026. Il contenuto durevole del foglio è l'aliquota marginale effettiva e la soglia q*, che non dipendono da nessuna norma a termine. Refresh obbligatorio a gennaio 2027.

Sheet P-Parametri
A1: P — Parametri normativi 2026 (celle gialle: si toccano solo se cambia la legge)
A2: Strumento informativo / divulgativo. NON è consulenza finanziaria. I valori sono indicativi al 2026 e vanno verificati col tuo consulente.
A3: FOTOGRAFIA DEL 2026. Il D.Lgs. 117/2026 (testo unico delle imposte sui redditi) è entrato in vigore il 4/7/2026 ma i suoi effetti DECORRONO dal 1° gennaio 2027 (art. 377), e l'art. 376 c. 2 dispone la continuità dei rinvii: è ricodificazione, non soppressione. Per tutto il 2026 valgono le norme di questo foglio. Chi verificherà su Normattiva nel 2027 leggerà di default la versione già abrogata: bisogna scendere di una versione e leggere quella vigente nell'anno del video.
A5: IRPEF — art. 11 TUIR come modificato dalla L. 199/2025 art. 1 c. 3
A6: Primo scaglione: limite / aliquota | B6: 28000 | C6: 0.23
A7: Secondo scaglione: limite / aliquota | B7: 50000 | C7: 0.33
A8: Terzo scaglione: aliquota | C8: 0.43
A9: IRPEF cumulata a fine primo scaglione (derivata) | B9: ='P-Parametri'!$B$6*'P-Parametri'!$C$6 -> 6440
A10: IRPEF cumulata a fine secondo scaglione (derivata) | B10: ='P-Parametri'!$B$9+'P-Parametri'!$C$7*('P-Parametri'!$B$7-'P-Parametri'!$B$6) -> 13700
A11: Detrazioni e contributi
A12: Detrazione lavoro dipendente — importo pieno / soglia (art. 13 c. 1 TUIR) | B12: 1955 | C12: 15000
A13: Fascia 15.000-28.000: base / incremento / ampiezza | B13: 1910 | C13: 1190 | D13: 13000
A14: Fascia 28.000-50.000: base / ampiezza | B14: 1910 | C14: 22000
A15: Ulteriore detrazione L. 207/2024 art. 1 c. 6 — importo / da / piena fino a / azzerata a | B15: 1000 | C15: 8500 | D15: 32000 | E15: 40000
A16: Trattamento integrativo D.L. 3/2020 — importo / soglia / scarto di capienza | B16: 1200 | C16: 15000 | D16: 75
A17: Somma sul cuneo L. 207/2024 art. 1 c. 4 — tre aliquote | B17: 0.071 | C17: 0.053 | D17: 0.048
A18: Somma sul cuneo — tre soglie di reddito complessivo | B18: 8500 | C18: 15000 | D18: 20000
A19: Contributi a carico del lavoratore (art. 1 c. 769 L. 296/2006) | B19: 0.0919
A20: Addizionali regionale + comunale — IPOTESI DI CANALE, non una norma | B20: 0.02
A21: I passi «somma sul cuneo» e «trattamento integrativo» NON mordono mai sul caso (reddito complessivo 32.691,60 €): sono nel motore per completezza e perché il foglio 2 copre RAL da 15.000 a 62.000.
A22: Imposta sostitutiva sugli incrementi retributivi — L. 199/2025 art. 1 c. 7
A23: Aliquota sostitutiva di IRPEF e addizionali | B23: 0.05
A24: Tetto: reddito di lavoro dipendente 2025 | B24: 33000
A25: Anno di erogazione agevolato (la norma vale SOLO su questo) | B25: 2026
A26: QUESTA PARTE SCADE. Il comma 7 si applica agli incrementi EROGATI nel 2026. Dal 2027 l'incremento rientra in tassazione ordinaria e ogni numero dei blocchi «CCNL» e «rapporto» smette di valere. Circolari AdE 2/E del 24/2/2026 e 3/E del 24/6/2026. Il limite dei 33.000 € si verifica sommando TUTTI i redditi di lavoro dipendente percepiti nel 2025, anche da più rapporti (circ. 2/E, verbatim). È un'opzione, non un obbligo: con rinuncia scritta si sceglie la tassazione ordinaria.
A27: Canone numerico del canale
A28: Rendimento REALE su 60/40 (DMS Yearbook) — banda bassa / base / alta | B28: 0.02 | C28: 0.03 | D28: 0.04
A29: Tasso di prelievo — regola del 4% / prudente / Anarkulova 2025 | B29: 0.04 | C29: 0.03 | D29: 0.0231
A30: Inflazione dichiarata (il modello è in euro reali: non entra nei conti) | B30: 0.02
A31: Il 5% e il 7% reale dei blog americani NON sono in elenco: sono vietati dal canone del canale. Anarkulova, Cederburg, O'Doherty, Sias (2025), J. Pension Econ. Fin. 24(3):464-500 danno un prelievo sicuro del 2,31%.
A32: Riferimenti del caso
A33: Spesa media mensile ISTAT 2024, persona sola (€/mese) | B33: 1932
A34: Settimane lavorate all'anno / settimane dell'anno | B34: 43 | C34: 52
A35: QUARTO ERRORE DI FAMIGLIA. L'aggregato ISTAT «spesa media mensile per consumi» INCLUDE gli affitti figurativi dei proprietari, che sono una componente NON monetaria. Confrontarlo con un flusso di cassa è omogeneo solo se si dichiara lo stato abitativo: vedi la cella B15 del foglio 1-Input.
A36: Fiscalità finanziaria — canone di canale, dichiarata NON attiva qui
A37: Imposta sulla plusvalenza realizzata | B37: 0.26
A38: Imposta di bollo sul dossier titoli | B38: 0.002
A39: LIMITE DICHIARATO. Questo modello è in accumulo e usa il traguardo come moltiplicatore della spesa (FIRE number = m × spesa): non simula i prelievi, quindi capital gain e bollo NON entrano in nessun conto di questi fogli. Sono qui perché sono il canone del canale e perché chi riusa il foglio deve sapere che mancano — non perché siano applicati. Il rendimento è già REALE e al lordo di queste due imposte.
A40: REFRESH GENNAIO 2027 — OBBLIGATORIO. Scaglioni, detrazioni, ulteriore detrazione, trattamento integrativo e somma sul cuneo sono riscritti ogni anno dalla legge di bilancio, e l'imposta sostitutiva del comma 7 vale SOLO sul 2026.

Sheet 1-Input
A1: 1 — Input del caso (le celle GIALLE sono le uniche che si toccano)
A2: Strumento informativo / divulgativo. NON è consulenza finanziaria. I valori sono indicativi al 2026 e vanno verificati col tuo consulente.
A3: Caso ILLUSTRATIVO e COMPOSITO. Non è una persona reale e il video non promette il FIRE: promette una differenza fra due modi di usare lo stesso aumento.
A4: La scheda-caso
A5: Età | B5: 32
A6: RAL (retribuzione annua lorda) | B6: 36000
A7: Spesa annua | B7: 21000
A8: Capitale già investito | B8: 26000
A9: Aumento LORDO ricevuto (promozione, canale ordinario) | B9: 7000
A10: Quota dell'aumento assorbita in spesa q (0% / 50% / 76,17% / 100%) | B10: 1
A11: Rendimento REALE annuo r (2% / 3% / 4% — il 5% è vietato) | B11: 0.03
A12: Tasso di prelievo w (4% / 3% / 2,31%) | B12: 0.04
A13: Ore lavorate all'anno (ipotesi dichiarata: 40 h × 43 settimane) | B13: 1720
A14: Settimane su cui si conta un'ora restituita (43 = lavorative) | B14: 43
A15: Stato abitativo (affitto / proprietà) — variabile OBBLIGATORIA | B15: affitto
A16: Settore (privato / pubblico) — il comma 7 vale solo sul privato | B16: privato
A17: Anno di erogazione dell'aumento | B17: 2026
A19: Che cosa ne esce — tutto formula, niente digitato
A21: Contributi a carico del lavoratore | B21: ='P-Parametri'!$B$19*'1-Input'!$B$6 -> 3308.4
A22: Reddito complessivo (= reddito di lavoro dipendente) | B22: ='1-Input'!$B$6-'1-Input'!$B$21 -> 32691.6
A23: Netto annuo | B23: =('1-Input'!$B$6*(1-'P-Parametri'!$B$19))-(MAX(0,(IF(('1-Input'!$B$6*(1-'P-Parametri'!$B$19))<='P-Parametri'!$B$6,'P-Parametri'!$C$6*('1-Input'!$B$6*(1-'P-Parametri'!$B$19)),IF(('1-Input'!$B$6*(1-'P-Parametri'!$B$19))<='P-Parametri'!$B$7,'P-Parametri'!$B$9+'P-Parametri'!$C$7*(('1-Input'!$B$6*(1-'P-Parametri'!$B$19))-'P-Parametri'!$B$6),'P-Parametri'!$B$10+'P-Parametri'!$C$8*(('1-Input'!$B$6*(1-'P-Parametri'!$B$19))-'P-Parametri'!$B$7))))-(IF(('1-Input'!$B$6*(1-'P-Parametri'!$B$19))<='P-Parametri'!$C$12,'P-Parametri'!$B$12,IF(('1-Input'!$B$6*(1-'P-Parametri'!$B$19))<='P-Parametri'!$B$6,'P-Parametri'!$B$13+'P-Parametri'!$C$13*('P-Parametri'!$B$6-('1-Input'!$B$6*(1-'P-Parametri'!$B$19)))/'P-Parametri'!$D$13,IF(('1-Input'!$B$6*(1-'P-Parametri'!$B$19))<='P-Parametri'!$B$7,'P-Parametri'!$B$14*('P-Parametri'!$B$7-('1-Input'!$B$6*(1-'P-Parametri'!$B$19)))/'P-Parametri'!$C$14,0))))-(IF(('1-Input'!$B$6*(1-'P-Parametri'!$B$19))<='P-Parametri'!$C$15,0,IF(('1-Input'!$B$6*(1-'P-Parametri'!$B$19))<='P-Parametri'!$D$15,'P-Parametri'!$B$15,IF(('1-Input'!$B$6*(1-'P-Parametri'!$B$19))<'P-Parametri'!$E$15,'P-Parametri'!$B$15*('P-Parametri'!$E$15-('1-Input'!$B$6*(1-'P-Parametri'!$B$19)))/('P-Parametri'!$E$15-'P-Parametri'!$D$15),0))))))-(IF(MAX(0,(IF(('1-Input'!$B$6*(1-'P-Parametri'!$B$19))<='P-Parametri'!$B$6,'P-Parametri'!$C$6*('1-Input'!$B$6*(1-'P-Parametri'!$B$19)),IF(('1-Input'!$B$6*(1-'P-Parametri'!$B$19))<='P-Parametri'!$B$7,'P-Parametri'!$B$9+'P-Parametri'!$C$7*(('1-Input'!$B$6*(1-'P-Parametri'!$B$19))-'P-Parametri'!$B$6),'P-Parametri'!$B$10+'P-Parametri'!$C$8*(('1-Input'!$B$6*(1-'P-Parametri'!$B$19))-'P-Parametri'!$B$7))))-(IF(('1-Input'!$B$6*(1-'P-Parametri'!$B$19))<='P-Parametri'!$C$12,'P-Parametri'!$B$12,IF(('1-Input'!$B$6*(1-'P-Parametri'!$B$19))<='P-Parametri'!$B$6,'P-Parametri'!$B$13+'P-Parametri'!$C$13*('P-Parametri'!$B$6-('1-Input'!$B$6*(1-'P-Parametri'!$B$19)))/'P-Parametri'!$D$13,IF(('1-Input'!$B$6*(1-'P-Parametri'!$B$19))<='P-Parametri'!$B$7,'P-Parametri'!$B$14*('P-Parametri'!$B$7-('1-Input'!$B$6*(1-'P-Parametri'!$B$19)))/'P-Parametri'!$C$14,0))))-(IF(('1-Input'!$B$6*(1-'P-Parametri'!$B$19))<='P-Parametri'!$C$15,0,IF(('1-Input'!$B$6*(1-'P-Parametri'!$B$19))<='P-Parametri'!$D$15,'P-Parametri'!$B$15,IF(('1-Input'!$B$6*(1-'P-Parametri'!$B$19))<'P-Parametri'!$E$15,'P-Parametri'!$B$15*('P-Parametri'!$E$15-('1-Input'!$B$6*(1-'P-Parametri'!$B$19)))/('P-Parametri'!$E$15-'P-Parametri'!$D$15),0)))))>0,'P-Parametri'!$B$20*('1-Input'!$B$6*(1-'P-Parametri'!$B$19)),0))+(IF(AND(('1-Input'!$B$6*(1-'P-Parametri'!$B$19))<='P-Parametri'!$C$16,(IF(('1-Input'!$B$6*(1-'P-Parametri'!$B$19))<='P-Parametri'!$B$6,'P-Parametri'!$C$6*('1-Input'!$B$6*(1-'P-Parametri'!$B$19)),IF(('1-Input'!$B$6*(1-'P-Parametri'!$B$19))<='P-Parametri'!$B$7,'P-Parametri'!$B$9+'P-Parametri'!$C$7*(('1-Input'!$B$6*(1-'P-Parametri'!$B$19))-'P-Parametri'!$B$6),'P-Parametri'!$B$10+'P-Parametri'!$C$8*(('1-Input'!$B$6*(1-'P-Parametri'!$B$19))-'P-Parametri'!$B$7))))>(IF(('1-Input'!$B$6*(1-'P-Parametri'!$B$19))<='P-Parametri'!$C$12,'P-Parametri'!$B$12,IF(('1-Input'!$B$6*(1-'P-Parametri'!$B$19))<='P-Parametri'!$B$6,'P-Parametri'!$B$13+'P-Parametri'!$C$13*('P-Parametri'!$B$6-('1-Input'!$B$6*(1-'P-Parametri'!$B$19)))/'P-Parametri'!$D$13,IF(('1-Input'!$B$6*(1-'P-Parametri'!$B$19))<='P-Parametri'!$B$7,'P-Parametri'!$B$14*('P-Parametri'!$B$7-('1-Input'!$B$6*(1-'P-Parametri'!$B$19)))/'P-Parametri'!$C$14,0))))-'P-Parametri'!$D$16),'P-Parametri'!$B$16,0))+(IF(('1-Input'!$B$6*(1-'P-Parametri'!$B$19))>'P-Parametri'!$D$18,0,IF(('1-Input'!$B$6*(1-'P-Parametri'!$B$19))<='P-Parametri'!$B$18,'P-Parametri'!$B$17*('1-Input'!$B$6*(1-'P-Parametri'!$B$19)),IF(('1-Input'!$B$6*(1-'P-Parametri'!$B$19))<='P-Parametri'!$C$18,'P-Parametri'!$C$17*('1-Input'!$B$6*(1-'P-Parametri'!$B$19)),'P-Parametri'!$D$17*('1-Input'!$B$6*(1-'P-Parametri'!$B$19)))))) -> 26465.774
A24: Netto mensile — su 12 / su 13 | B24: ='1-Input'!$B$23/12 -> 2205.4812 | C24: ='1-Input'!$B$23/13 -> 2035.8288
A25: Risparmio annuo | B25: ='1-Input'!$B$23-'1-Input'!$B$7 -> 5465.7738
A26: Tasso di risparmio (sul netto) | B26: ='1-Input'!$B$25/'1-Input'!$B$23 -> 0.20652235
A27: Moltiplicatore del traguardo m = 1/w | B27: =1/'1-Input'!$B$12 -> 25
A28: FIRE number = m × spesa | B28: ='1-Input'!$B$27*'1-Input'!$B$7 -> 525000
A29: Reddito di lavoro dipendente 2025 (test del comma 7) | B29: ='1-Input'!$B$22 -> 32691.6
A30: Margine sotto il tetto dei 33.000 € | B30: ='P-Parametri'!$B$24-'1-Input'!$B$29 -> 308.4
A31: Anni al traguardo, caso base | B31: =LN(('1-Input'!$B$28+'1-Input'!$B$25/'1-Input'!$B$11)/('1-Input'!$B$8+'1-Input'!$B$25/'1-Input'!$B$11))/LN(1+'1-Input'!$B$11) -> 41.369738
A32: Netto in % della RAL | B32: ='1-Input'!$B$23/'1-Input'!$B$6 -> 0.73516038
A33: Ammissibile al comma 7? | B33: =IF(AND('1-Input'!$B$16="privato",'1-Input'!$B$29<='P-Parametri'!$B$24,'1-Input'!$B$17='P-Parametri'!$B$25),"SI — settore privato, sotto i 33.000, anno 2026","NO — verifica settore, tetto reddituale o anno di erogazione") -> SI — settore privato, sotto i 33.000, anno 2026
A34: Età al traguardo, caso base | B34: ='1-Input'!$B$5+'1-Input'!$B$31 -> 73.369738
A36: Il vincolo aritmetico: da dove viene il capitale (terzo errore di famiglia)
A37: Anno | B37: Età | C37: RAL | D37: Netto | E37: Spesa | F37: Risparmio | G37: Tasso di risparmio | H37: Montante al 1/1/2026
A38: =2019 -> 2019 | B38: =25 -> 25 | C38: 26000 | D38: =(C38*(1-'P-Parametri'!$B$19))-(MAX(0,(IF((C38*(1-'P-Parametri'!$B$19))<='P-Parametri'!$B$6,'P-Parametri'!$C$6*(C38*(1-'P-Parametri'!$B$19)),IF((C38*(1-'P-Parametri'!$B$19))<='P-Parametri'!$B$7,'P-Parametri'!$B$9+'P-Parametri'!$C$7*((C38*(1-'P-Parametri'!$B$19))-'P-Parametri'!$B$6),'P-Parametri'!$B$10+'P-Parametri'!$C$8*((C38*(1-'P-Parametri'!$B$19))-'P-Parametri'!$B$7))))-(IF((C38*(1-'P-Parametri'!$B$19))<='P-Parametri'!$C$12,'P-Parametri'!$B$12,IF((C38*(1-'P-Parametri'!$B$19))<='P-Parametri'!$B$6,'P-Parametri'!$B$13+'P-Parametri'!$C$13*('P-Parametri'!$B$6-(C38*(1-'P-Parametri'!$B$19)))/'P-Parametri'!$D$13,IF((C38*(1-'P-Parametri'!$B$19))<='P-Parametri'!$B$7,'P-Parametri'!$B$14*('P-Parametri'!$B$7-(C38*(1-'P-Parametri'!$B$19)))/'P-Parametri'!$C$14,0))))-(IF((C38*(1-'P-Parametri'!$B$19))<='P-Parametri'!$C$15,0,IF((C38*(1-'P-Parametri'!$B$19))<='P-Parametri'!$D$15,'P-Parametri'!$B$15,IF((C38*(1-'P-Parametri'!$B$19))<'P-Parametri'!$E$15,'P-Parametri'!$B$15*('P-Parametri'!$E$15-(C38*(1-'P-Parametri'!$B$19)))/('P-Parametri'!$E$15-'P-Parametri'!$D$15),0))))))-(IF(MAX(0,(IF((C38*(1-'P-Parametri'!$B$19))<='P-Parametri'!$B$6,'P-Parametri'!$C$6*(C38*(1-'P-Parametri'!$B$19)),IF((C38*(1-'P-Parametri'!$B$19))<='P-Parametri'!$B$7,'P-Parametri'!$B$9+'P-Parametri'!$C$7*((C38*(1-'P-Parametri'!$B$19))-'P-Parametri'!$B$6),'P-Parametri'!$B$10+'P-Parametri'!$C$8*((C38*(1-'P-Parametri'!$B$19))-'P-Parametri'!$B$7))))-(IF((C38*(1-'P-Parametri'!$B$19))<='P-Parametri'!$C$12,'P-Parametri'!$B$12,IF((C38*(1-'P-Parametri'!$B$19))<='P-Parametri'!$B$6,'P-Parametri'!$B$13+'P-Parametri'!$C$13*('P-Parametri'!$B$6-(C38*(1-'P-Parametri'!$B$19)))/'P-Parametri'!$D$13,IF((C38*(1-'P-Parametri'!$B$19))<='P-Parametri'!$B$7,'P-Parametri'!$B$14*('P-Parametri'!$B$7-(C38*(1-'P-Parametri'!$B$19)))/'P-Parametri'!$C$14,0))))-(IF((C38*(1-'P-Parametri'!$B$19))<='P-Parametri'!$C$15,0,IF((C38*(1-'P-Parametri'!$B$19))<='P-Parametri'!$D$15,'P-Parametri'!$B$15,IF((C38*(1-'P-Parametri'!$B$19))<'P-Parametri'!$E$15,'P-Parametri'!$B$15*('P-Parametri'!$E$15-(C38*(1-'P-Parametri'!$B$19)))/('P-Parametri'!$E$15-'P-Parametri'!$D$15),0)))))>0,'P-Parametri'!$B$20*(C38*(1-'P-Parametri'!$B$19)),0))+(IF(AND((C38*(1-'P-Parametri'!$B$19))<='P-Parametri'!$C$16,(IF((C38*(1-'P-Parametri'!$B$19))<='P-Parametri'!$B$6,'P-Parametri'!$C$6*(C38*(1-'P-Parametri'!$B$19)),IF((C38*(1-'P-Parametri'!$B$19))<='P-Parametri'!$B$7,'P-Parametri'!$B$9+'P-Parametri'!$C$7*((C38*(1-'P-Parametri'!$B$19))-'P-Parametri'!$B$6),'P-Parametri'!$B$10+'P-Parametri'!$C$8*((C38*(1-'P-Parametri'!$B$19))-'P-Parametri'!$B$7))))>(IF((C38*(1-'P-Parametri'!$B$19))<='P-Parametri'!$C$12,'P-Parametri'!$B$12,IF((C38*(1-'P-Parametri'!$B$19))<='P-Parametri'!$B$6,'P-Parametri'!$B$13+'P-Parametri'!$C$13*('P-Parametri'!$B$6-(C38*(1-'P-Parametri'!$B$19)))/'P-Parametri'!$D$13,IF((C38*(1-'P-Parametri'!$B$19))<='P-Parametri'!$B$7,'P-Parametri'!$B$14*('P-Parametri'!$B$7-(C38*(1-'P-Parametri'!$B$19)))/'P-Parametri'!$C$14,0))))-'P-Parametri'!$D$16),'P-Parametri'!$B$16,0))+(IF((C38*(1-'P-Parametri'!$B$19))>'P-Parametri'!$D$18,0,IF((C38*(1-'P-Parametri'!$B$19))<='P-Parametri'!$B$18,'P-Parametri'!$B$17*(C38*(1-'P-Parametri'!$B$19)),IF((C38*(1-'P-Parametri'!$B$19))<='P-Parametri'!$C$18,'P-Parametri'!$C$17*(C38*(1-'P-Parametri'!$B$19)),'P-Parametri'!$D$17*(C38*(1-'P-Parametri'!$B$19)))))) -> 21019.749 | E38: 19500 | F38: =D38-E38 -> 1519.7489 | G38: =F38/D38 -> 0.072301003 | H38: =F38*(1+'1-Input'!$B$11)^(2025-A38) -> 1814.6597
A39: =2020 -> 2020 | B39: =26 -> 26 | C39: 27500 | D39: =(C39*(1-'P-Parametri'!$B$19))-(MAX(0,(IF((C39*(1-'P-Parametri'!$B$19))<='P-Parametri'!$B$6,'P-Parametri'!$C$6*(C39*(1-'P-Parametri'!$B$19)),IF((C39*(1-'P-Parametri'!$B$19))<='P-Parametri'!$B$7,'P-Parametri'!$B$9+'P-Parametri'!$C$7*((C39*(1-'P-Parametri'!$B$19))-'P-Parametri'!$B$6),'P-Parametri'!$B$10+'P-Parametri'!$C$8*((C39*(1-'P-Parametri'!$B$19))-'P-Parametri'!$B$7))))-(IF((C39*(1-'P-Parametri'!$B$19))<='P-Parametri'!$C$12,'P-Parametri'!$B$12,IF((C39*(1-'P-Parametri'!$B$19))<='P-Parametri'!$B$6,'P-Parametri'!$B$13+'P-Parametri'!$C$13*('P-Parametri'!$B$6-(C39*(1-'P-Parametri'!$B$19)))/'P-Parametri'!$D$13,IF((C39*(1-'P-Parametri'!$B$19))<='P-Parametri'!$B$7,'P-Parametri'!$B$14*('P-Parametri'!$B$7-(C39*(1-'P-Parametri'!$B$19)))/'P-Parametri'!$C$14,0))))-(IF((C39*(1-'P-Parametri'!$B$19))<='P-Parametri'!$C$15,0,IF((C39*(1-'P-Parametri'!$B$19))<='P-Parametri'!$D$15,'P-Parametri'!$B$15,IF((C39*(1-'P-Parametri'!$B$19))<'P-Parametri'!$E$15,'P-Parametri'!$B$15*('P-Parametri'!$E$15-(C39*(1-'P-Parametri'!$B$19)))/('P-Parametri'!$E$15-'P-Parametri'!$D$15),0))))))-(IF(MAX(0,(IF((C39*(1-'P-Parametri'!$B$19))<='P-Parametri'!$B$6,'P-Parametri'!$C$6*(C39*(1-'P-Parametri'!$B$19)),IF((C39*(1-'P-Parametri'!$B$19))<='P-Parametri'!$B$7,'P-Parametri'!$B$9+'P-Parametri'!$C$7*((C39*(1-'P-Parametri'!$B$19))-'P-Parametri'!$B$6),'P-Parametri'!$B$10+'P-Parametri'!$C$8*((C39*(1-'P-Parametri'!$B$19))-'P-Parametri'!$B$7))))-(IF((C39*(1-'P-Parametri'!$B$19))<='P-Parametri'!$C$12,'P-Parametri'!$B$12,IF((C39*(1-'P-Parametri'!$B$19))<='P-Parametri'!$B$6,'P-Parametri'!$B$13+'P-Parametri'!$C$13*('P-Parametri'!$B$6-(C39*(1-'P-Parametri'!$B$19)))/'P-Parametri'!$D$13,IF((C39*(1-'P-Parametri'!$B$19))<='P-Parametri'!$B$7,'P-Parametri'!$B$14*('P-Parametri'!$B$7-(C39*(1-'P-Parametri'!$B$19)))/'P-Parametri'!$C$14,0))))-(IF((C39*(1-'P-Parametri'!$B$19))<='P-Parametri'!$C$15,0,IF((C39*(1-'P-Parametri'!$B$19))<='P-Parametri'!$D$15,'P-Parametri'!$B$15,IF((C39*(1-'P-Parametri'!$B$19))<'P-Parametri'!$E$15,'P-Parametri'!$B$15*('P-Parametri'!$E$15-(C39*(1-'P-Parametri'!$B$19)))/('P-Parametri'!$E$15-'P-Parametri'!$D$15),0)))))>0,'P-Parametri'!$B$20*(C39*(1-'P-Parametri'!$B$19)),0))+(IF(AND((C39*(1-'P-Parametri'!$B$19))<='P-Parametri'!$C$16,(IF((C39*(1-'P-Parametri'!$B$19))<='P-Parametri'!$B$6,'P-Parametri'!$C$6*(C39*(1-'P-Parametri'!$B$19)),IF((C39*(1-'P-Parametri'!$B$19))<='P-Parametri'!$B$7,'P-Parametri'!$B$9+'P-Parametri'!$C$7*((C39*(1-'P-Parametri'!$B$19))-'P-Parametri'!$B$6),'P-Parametri'!$B$10+'P-Parametri'!$C$8*((C39*(1-'P-Parametri'!$B$19))-'P-Parametri'!$B$7))))>(IF((C39*(1-'P-Parametri'!$B$19))<='P-Parametri'!$C$12,'P-Parametri'!$B$12,IF((C39*(1-'P-Parametri'!$B$19))<='P-Parametri'!$B$6,'P-Parametri'!$B$13+'P-Parametri'!$C$13*('P-Parametri'!$B$6-(C39*(1-'P-Parametri'!$B$19)))/'P-Parametri'!$D$13,IF((C39*(1-'P-Parametri'!$B$19))<='P-Parametri'!$B$7,'P-Parametri'!$B$14*('P-Parametri'!$B$7-(C39*(1-'P-Parametri'!$B$19)))/'P-Parametri'!$C$14,0))))-'P-Parametri'!$D$16),'P-Parametri'!$B$16,0))+(IF((C39*(1-'P-Parametri'!$B$19))>'P-Parametri'!$D$18,0,IF((C39*(1-'P-Parametri'!$B$19))<='P-Parametri'!$B$18,'P-Parametri'!$B$17*(C39*(1-'P-Parametri'!$B$19)),IF((C39*(1-'P-Parametri'!$B$19))<='P-Parametri'!$C$18,'P-Parametri'!$C$17*(C39*(1-'P-Parametri'!$B$19)),'P-Parametri'!$D$17*(C39*(1-'P-Parametri'!$B$19)))))) -> 21916.672 | E39: 19750 | F39: =D39-E39 -> 2166.6723 | G39: =F39/D39 -> 0.098859548 | H39: =F39*(1+'1-Input'!$B$11)^(2025-A39) -> 2511.767
A40: =2021 -> 2021 | B40: =27 -> 27 | C40: 29000 | D40: =(C40*(1-'P-Parametri'!$B$19))-(MAX(0,(IF((C40*(1-'P-Parametri'!$B$19))<='P-Parametri'!$B$6,'P-Parametri'!$C$6*(C40*(1-'P-Parametri'!$B$19)),IF((C40*(1-'P-Parametri'!$B$19))<='P-Parametri'!$B$7,'P-Parametri'!$B$9+'P-Parametri'!$C$7*((C40*(1-'P-Parametri'!$B$19))-'P-Parametri'!$B$6),'P-Parametri'!$B$10+'P-Parametri'!$C$8*((C40*(1-'P-Parametri'!$B$19))-'P-Parametri'!$B$7))))-(IF((C40*(1-'P-Parametri'!$B$19))<='P-Parametri'!$C$12,'P-Parametri'!$B$12,IF((C40*(1-'P-Parametri'!$B$19))<='P-Parametri'!$B$6,'P-Parametri'!$B$13+'P-Parametri'!$C$13*('P-Parametri'!$B$6-(C40*(1-'P-Parametri'!$B$19)))/'P-Parametri'!$D$13,IF((C40*(1-'P-Parametri'!$B$19))<='P-Parametri'!$B$7,'P-Parametri'!$B$14*('P-Parametri'!$B$7-(C40*(1-'P-Parametri'!$B$19)))/'P-Parametri'!$C$14,0))))-(IF((C40*(1-'P-Parametri'!$B$19))<='P-Parametri'!$C$15,0,IF((C40*(1-'P-Parametri'!$B$19))<='P-Parametri'!$D$15,'P-Parametri'!$B$15,IF((C40*(1-'P-Parametri'!$B$19))<'P-Parametri'!$E$15,'P-Parametri'!$B$15*('P-Parametri'!$E$15-(C40*(1-'P-Parametri'!$B$19)))/('P-Parametri'!$E$15-'P-Parametri'!$D$15),0))))))-(IF(MAX(0,(IF((C40*(1-'P-Parametri'!$B$19))<='P-Parametri'!$B$6,'P-Parametri'!$C$6*(C40*(1-'P-Parametri'!$B$19)),IF((C40*(1-'P-Parametri'!$B$19))<='P-Parametri'!$B$7,'P-Parametri'!$B$9+'P-Parametri'!$C$7*((C40*(1-'P-Parametri'!$B$19))-'P-Parametri'!$B$6),'P-Parametri'!$B$10+'P-Parametri'!$C$8*((C40*(1-'P-Parametri'!$B$19))-'P-Parametri'!$B$7))))-(IF((C40*(1-'P-Parametri'!$B$19))<='P-Parametri'!$C$12,'P-Parametri'!$B$12,IF((C40*(1-'P-Parametri'!$B$19))<='P-Parametri'!$B$6,'P-Parametri'!$B$13+'P-Parametri'!$C$13*('P-Parametri'!$B$6-(C40*(1-'P-Parametri'!$B$19)))/'P-Parametri'!$D$13,IF((C40*(1-'P-Parametri'!$B$19))<='P-Parametri'!$B$7,'P-Parametri'!$B$14*('P-Parametri'!$B$7-(C40*(1-'P-Parametri'!$B$19)))/'P-Parametri'!$C$14,0))))-(IF((C40*(1-'P-Parametri'!$B$19))<='P-Parametri'!$C$15,0,IF((C40*(1-'P-Parametri'!$B$19))<='P-Parametri'!$D$15,'P-Parametri'!$B$15,IF((C40*(1-'P-Parametri'!$B$19))<'P-Parametri'!$E$15,'P-Parametri'!$B$15*('P-Parametri'!$E$15-(C40*(1-'P-Parametri'!$B$19)))/('P-Parametri'!$E$15-'P-Parametri'!$D$15),0)))))>0,'P-Parametri'!$B$20*(C40*(1-'P-Parametri'!$B$19)),0))+(IF(AND((C40*(1-'P-Parametri'!$B$19))<='P-Parametri'!$C$16,(IF((C40*(1-'P-Parametri'!$B$19))<='P-Parametri'!$B$6,'P-Parametri'!$C$6*(C40*(1-'P-Parametri'!$B$19)),IF((C40*(1-'P-Parametri'!$B$19))<='P-Parametri'!$B$7,'P-Parametri'!$B$9+'P-Parametri'!$C$7*((C40*(1-'P-Parametri'!$B$19))-'P-Parametri'!$B$6),'P-Parametri'!$B$10+'P-Parametri'!$C$8*((C40*(1-'P-Parametri'!$B$19))-'P-Parametri'!$B$7))))>(IF((C40*(1-'P-Parametri'!$B$19))<='P-Parametri'!$C$12,'P-Parametri'!$B$12,IF((C40*(1-'P-Parametri'!$B$19))<='P-Parametri'!$B$6,'P-Parametri'!$B$13+'P-Parametri'!$C$13*('P-Parametri'!$B$6-(C40*(1-'P-Parametri'!$B$19)))/'P-Parametri'!$D$13,IF((C40*(1-'P-Parametri'!$B$19))<='P-Parametri'!$B$7,'P-Parametri'!$B$14*('P-Parametri'!$B$7-(C40*(1-'P-Parametri'!$B$19)))/'P-Parametri'!$C$14,0))))-'P-Parametri'!$D$16),'P-Parametri'!$B$16,0))+(IF((C40*(1-'P-Parametri'!$B$19))>'P-Parametri'!$D$18,0,IF((C40*(1-'P-Parametri'!$B$19))<='P-Parametri'!$B$18,'P-Parametri'!$B$17*(C40*(1-'P-Parametri'!$B$19)),IF((C40*(1-'P-Parametri'!$B$19))<='P-Parametri'!$C$18,'P-Parametri'!$C$17*(C40*(1-'P-Parametri'!$B$19)),'P-Parametri'!$D$17*(C40*(1-'P-Parametri'!$B$19)))))) -> 22813.596 | E40: 20000 | F40: =D40-E40 -> 2813.5957 | G40: =F40/D40 -> 0.12332978 | H40: =F40*(1+'1-Input'!$B$11)^(2025-A40) -> 3166.7267
A41: =2022 -> 2022 | B41: =28 -> 28 | C41: 30500 | D41: =(C41*(1-'P-Parametri'!$B$19))-(MAX(0,(IF((C41*(1-'P-Parametri'!$B$19))<='P-Parametri'!$B$6,'P-Parametri'!$C$6*(C41*(1-'P-Parametri'!$B$19)),IF((C41*(1-'P-Parametri'!$B$19))<='P-Parametri'!$B$7,'P-Parametri'!$B$9+'P-Parametri'!$C$7*((C41*(1-'P-Parametri'!$B$19))-'P-Parametri'!$B$6),'P-Parametri'!$B$10+'P-Parametri'!$C$8*((C41*(1-'P-Parametri'!$B$19))-'P-Parametri'!$B$7))))-(IF((C41*(1-'P-Parametri'!$B$19))<='P-Parametri'!$C$12,'P-Parametri'!$B$12,IF((C41*(1-'P-Parametri'!$B$19))<='P-Parametri'!$B$6,'P-Parametri'!$B$13+'P-Parametri'!$C$13*('P-Parametri'!$B$6-(C41*(1-'P-Parametri'!$B$19)))/'P-Parametri'!$D$13,IF((C41*(1-'P-Parametri'!$B$19))<='P-Parametri'!$B$7,'P-Parametri'!$B$14*('P-Parametri'!$B$7-(C41*(1-'P-Parametri'!$B$19)))/'P-Parametri'!$C$14,0))))-(IF((C41*(1-'P-Parametri'!$B$19))<='P-Parametri'!$C$15,0,IF((C41*(1-'P-Parametri'!$B$19))<='P-Parametri'!$D$15,'P-Parametri'!$B$15,IF((C41*(1-'P-Parametri'!$B$19))<'P-Parametri'!$E$15,'P-Parametri'!$B$15*('P-Parametri'!$E$15-(C41*(1-'P-Parametri'!$B$19)))/('P-Parametri'!$E$15-'P-Parametri'!$D$15),0))))))-(IF(MAX(0,(IF((C41*(1-'P-Parametri'!$B$19))<='P-Parametri'!$B$6,'P-Parametri'!$C$6*(C41*(1-'P-Parametri'!$B$19)),IF((C41*(1-'P-Parametri'!$B$19))<='P-Parametri'!$B$7,'P-Parametri'!$B$9+'P-Parametri'!$C$7*((C41*(1-'P-Parametri'!$B$19))-'P-Parametri'!$B$6),'P-Parametri'!$B$10+'P-Parametri'!$C$8*((C41*(1-'P-Parametri'!$B$19))-'P-Parametri'!$B$7))))-(IF((C41*(1-'P-Parametri'!$B$19))<='P-Parametri'!$C$12,'P-Parametri'!$B$12,IF((C41*(1-'P-Parametri'!$B$19))<='P-Parametri'!$B$6,'P-Parametri'!$B$13+'P-Parametri'!$C$13*('P-Parametri'!$B$6-(C41*(1-'P-Parametri'!$B$19)))/'P-Parametri'!$D$13,IF((C41*(1-'P-Parametri'!$B$19))<='P-Parametri'!$B$7,'P-Parametri'!$B$14*('P-Parametri'!$B$7-(C41*(1-'P-Parametri'!$B$19)))/'P-Parametri'!$C$14,0))))-(IF((C41*(1-'P-Parametri'!$B$19))<='P-Parametri'!$C$15,0,IF((C41*(1-'P-Parametri'!$B$19))<='P-Parametri'!$D$15,'P-Parametri'!$B$15,IF((C41*(1-'P-Parametri'!$B$19))<'P-Parametri'!$E$15,'P-Parametri'!$B$15*('P-Parametri'!$E$15-(C41*(1-'P-Parametri'!$B$19)))/('P-Parametri'!$E$15-'P-Parametri'!$D$15),0)))))>0,'P-Parametri'!$B$20*(C41*(1-'P-Parametri'!$B$19)),0))+(IF(AND((C41*(1-'P-Parametri'!$B$19))<='P-Parametri'!$C$16,(IF((C41*(1-'P-Parametri'!$B$19))<='P-Parametri'!$B$6,'P-Parametri'!$C$6*(C41*(1-'P-Parametri'!$B$19)),IF((C41*(1-'P-Parametri'!$B$19))<='P-Parametri'!$B$7,'P-Parametri'!$B$9+'P-Parametri'!$C$7*((C41*(1-'P-Parametri'!$B$19))-'P-Parametri'!$B$6),'P-Parametri'!$B$10+'P-Parametri'!$C$8*((C41*(1-'P-Parametri'!$B$19))-'P-Parametri'!$B$7))))>(IF((C41*(1-'P-Parametri'!$B$19))<='P-Parametri'!$C$12,'P-Parametri'!$B$12,IF((C41*(1-'P-Parametri'!$B$19))<='P-Parametri'!$B$6,'P-Parametri'!$B$13+'P-Parametri'!$C$13*('P-Parametri'!$B$6-(C41*(1-'P-Parametri'!$B$19)))/'P-Parametri'!$D$13,IF((C41*(1-'P-Parametri'!$B$19))<='P-Parametri'!$B$7,'P-Parametri'!$B$14*('P-Parametri'!$B$7-(C41*(1-'P-Parametri'!$B$19)))/'P-Parametri'!$C$14,0))))-'P-Parametri'!$D$16),'P-Parametri'!$B$16,0))+(IF((C41*(1-'P-Parametri'!$B$19))>'P-Parametri'!$D$18,0,IF((C41*(1-'P-Parametri'!$B$19))<='P-Parametri'!$B$18,'P-Parametri'!$B$17*(C41*(1-'P-Parametri'!$B$19)),IF((C41*(1-'P-Parametri'!$B$19))<='P-Parametri'!$C$18,'P-Parametri'!$C$17*(C41*(1-'P-Parametri'!$B$19)),'P-Parametri'!$D$17*(C41*(1-'P-Parametri'!$B$19)))))) -> 23710.519 | E41: 20250 | F41: =D41-E41 -> 3460.5191 | G41: =F41/D41 -> 0.14594868 | H41: =F41*(1+'1-Input'!$B$11)^(2025-A41) -> 3781.4026
A42: =2023 -> 2023 | B42: =29 -> 29 | C42: 32000 | D42: =(C42*(1-'P-Parametri'!$B$19))-(MAX(0,(IF((C42*(1-'P-Parametri'!$B$19))<='P-Parametri'!$B$6,'P-Parametri'!$C$6*(C42*(1-'P-Parametri'!$B$19)),IF((C42*(1-'P-Parametri'!$B$19))<='P-Parametri'!$B$7,'P-Parametri'!$B$9+'P-Parametri'!$C$7*((C42*(1-'P-Parametri'!$B$19))-'P-Parametri'!$B$6),'P-Parametri'!$B$10+'P-Parametri'!$C$8*((C42*(1-'P-Parametri'!$B$19))-'P-Parametri'!$B$7))))-(IF((C42*(1-'P-Parametri'!$B$19))<='P-Parametri'!$C$12,'P-Parametri'!$B$12,IF((C42*(1-'P-Parametri'!$B$19))<='P-Parametri'!$B$6,'P-Parametri'!$B$13+'P-Parametri'!$C$13*('P-Parametri'!$B$6-(C42*(1-'P-Parametri'!$B$19)))/'P-Parametri'!$D$13,IF((C42*(1-'P-Parametri'!$B$19))<='P-Parametri'!$B$7,'P-Parametri'!$B$14*('P-Parametri'!$B$7-(C42*(1-'P-Parametri'!$B$19)))/'P-Parametri'!$C$14,0))))-(IF((C42*(1-'P-Parametri'!$B$19))<='P-Parametri'!$C$15,0,IF((C42*(1-'P-Parametri'!$B$19))<='P-Parametri'!$D$15,'P-Parametri'!$B$15,IF((C42*(1-'P-Parametri'!$B$19))<'P-Parametri'!$E$15,'P-Parametri'!$B$15*('P-Parametri'!$E$15-(C42*(1-'P-Parametri'!$B$19)))/('P-Parametri'!$E$15-'P-Parametri'!$D$15),0))))))-(IF(MAX(0,(IF((C42*(1-'P-Parametri'!$B$19))<='P-Parametri'!$B$6,'P-Parametri'!$C$6*(C42*(1-'P-Parametri'!$B$19)),IF((C42*(1-'P-Parametri'!$B$19))<='P-Parametri'!$B$7,'P-Parametri'!$B$9+'P-Parametri'!$C$7*((C42*(1-'P-Parametri'!$B$19))-'P-Parametri'!$B$6),'P-Parametri'!$B$10+'P-Parametri'!$C$8*((C42*(1-'P-Parametri'!$B$19))-'P-Parametri'!$B$7))))-(IF((C42*(1-'P-Parametri'!$B$19))<='P-Parametri'!$C$12,'P-Parametri'!$B$12,IF((C42*(1-'P-Parametri'!$B$19))<='P-Parametri'!$B$6,'P-Parametri'!$B$13+'P-Parametri'!$C$13*('P-Parametri'!$B$6-(C42*(1-'P-Parametri'!$B$19)))/'P-Parametri'!$D$13,IF((C42*(1-'P-Parametri'!$B$19))<='P-Parametri'!$B$7,'P-Parametri'!$B$14*('P-Parametri'!$B$7-(C42*(1-'P-Parametri'!$B$19)))/'P-Parametri'!$C$14,0))))-(IF((C42*(1-'P-Parametri'!$B$19))<='P-Parametri'!$C$15,0,IF((C42*(1-'P-Parametri'!$B$19))<='P-Parametri'!$D$15,'P-Parametri'!$B$15,IF((C42*(1-'P-Parametri'!$B$19))<'P-Parametri'!$E$15,'P-Parametri'!$B$15*('P-Parametri'!$E$15-(C42*(1-'P-Parametri'!$B$19)))/('P-Parametri'!$E$15-'P-Parametri'!$D$15),0)))))>0,'P-Parametri'!$B$20*(C42*(1-'P-Parametri'!$B$19)),0))+(IF(AND((C42*(1-'P-Parametri'!$B$19))<='P-Parametri'!$C$16,(IF((C42*(1-'P-Parametri'!$B$19))<='P-Parametri'!$B$6,'P-Parametri'!$C$6*(C42*(1-'P-Parametri'!$B$19)),IF((C42*(1-'P-Parametri'!$B$19))<='P-Parametri'!$B$7,'P-Parametri'!$B$9+'P-Parametri'!$C$7*((C42*(1-'P-Parametri'!$B$19))-'P-Parametri'!$B$6),'P-Parametri'!$B$10+'P-Parametri'!$C$8*((C42*(1-'P-Parametri'!$B$19))-'P-Parametri'!$B$7))))>(IF((C42*(1-'P-Parametri'!$B$19))<='P-Parametri'!$C$12,'P-Parametri'!$B$12,IF((C42*(1-'P-Parametri'!$B$19))<='P-Parametri'!$B$6,'P-Parametri'!$B$13+'P-Parametri'!$C$13*('P-Parametri'!$B$6-(C42*(1-'P-Parametri'!$B$19)))/'P-Parametri'!$D$13,IF((C42*(1-'P-Parametri'!$B$19))<='P-Parametri'!$B$7,'P-Parametri'!$B$14*('P-Parametri'!$B$7-(C42*(1-'P-Parametri'!$B$19)))/'P-Parametri'!$C$14,0))))-'P-Parametri'!$D$16),'P-Parametri'!$B$16,0))+(IF((C42*(1-'P-Parametri'!$B$19))>'P-Parametri'!$D$18,0,IF((C42*(1-'P-Parametri'!$B$19))<='P-Parametri'!$B$18,'P-Parametri'!$B$17*(C42*(1-'P-Parametri'!$B$19)),IF((C42*(1-'P-Parametri'!$B$19))<='P-Parametri'!$C$18,'P-Parametri'!$C$17*(C42*(1-'P-Parametri'!$B$19)),'P-Parametri'!$D$17*(C42*(1-'P-Parametri'!$B$19)))))) -> 24506.522 | E42: 20500 | F42: =D42-E42 -> 4006.5222 | G42: =F42/D42 -> 0.163488 | H42: =F42*(1+'1-Input'!$B$11)^(2025-A42) -> 4250.5194
A43: =2024 -> 2024 | B43: =30 -> 30 | C43: 34000 | D43: =(C43*(1-'P-Parametri'!$B$19))-(MAX(0,(IF((C43*(1-'P-Parametri'!$B$19))<='P-Parametri'!$B$6,'P-Parametri'!$C$6*(C43*(1-'P-Parametri'!$B$19)),IF((C43*(1-'P-Parametri'!$B$19))<='P-Parametri'!$B$7,'P-Parametri'!$B$9+'P-Parametri'!$C$7*((C43*(1-'P-Parametri'!$B$19))-'P-Parametri'!$B$6),'P-Parametri'!$B$10+'P-Parametri'!$C$8*((C43*(1-'P-Parametri'!$B$19))-'P-Parametri'!$B$7))))-(IF((C43*(1-'P-Parametri'!$B$19))<='P-Parametri'!$C$12,'P-Parametri'!$B$12,IF((C43*(1-'P-Parametri'!$B$19))<='P-Parametri'!$B$6,'P-Parametri'!$B$13+'P-Parametri'!$C$13*('P-Parametri'!$B$6-(C43*(1-'P-Parametri'!$B$19)))/'P-Parametri'!$D$13,IF((C43*(1-'P-Parametri'!$B$19))<='P-Parametri'!$B$7,'P-Parametri'!$B$14*('P-Parametri'!$B$7-(C43*(1-'P-Parametri'!$B$19)))/'P-Parametri'!$C$14,0))))-(IF((C43*(1-'P-Parametri'!$B$19))<='P-Parametri'!$C$15,0,IF((C43*(1-'P-Parametri'!$B$19))<='P-Parametri'!$D$15,'P-Parametri'!$B$15,IF((C43*(1-'P-Parametri'!$B$19))<'P-Parametri'!$E$15,'P-Parametri'!$B$15*('P-Parametri'!$E$15-(C43*(1-'P-Parametri'!$B$19)))/('P-Parametri'!$E$15-'P-Parametri'!$D$15),0))))))-(IF(MAX(0,(IF((C43*(1-'P-Parametri'!$B$19))<='P-Parametri'!$B$6,'P-Parametri'!$C$6*(C43*(1-'P-Parametri'!$B$19)),IF((C43*(1-'P-Parametri'!$B$19))<='P-Parametri'!$B$7,'P-Parametri'!$B$9+'P-Parametri'!$C$7*((C43*(1-'P-Parametri'!$B$19))-'P-Parametri'!$B$6),'P-Parametri'!$B$10+'P-Parametri'!$C$8*((C43*(1-'P-Parametri'!$B$19))-'P-Parametri'!$B$7))))-(IF((C43*(1-'P-Parametri'!$B$19))<='P-Parametri'!$C$12,'P-Parametri'!$B$12,IF((C43*(1-'P-Parametri'!$B$19))<='P-Parametri'!$B$6,'P-Parametri'!$B$13+'P-Parametri'!$C$13*('P-Parametri'!$B$6-(C43*(1-'P-Parametri'!$B$19)))/'P-Parametri'!$D$13,IF((C43*(1-'P-Parametri'!$B$19))<='P-Parametri'!$B$7,'P-Parametri'!$B$14*('P-Parametri'!$B$7-(C43*(1-'P-Parametri'!$B$19)))/'P-Parametri'!$C$14,0))))-(IF((C43*(1-'P-Parametri'!$B$19))<='P-Parametri'!$C$15,0,IF((C43*(1-'P-Parametri'!$B$19))<='P-Parametri'!$D$15,'P-Parametri'!$B$15,IF((C43*(1-'P-Parametri'!$B$19))<'P-Parametri'!$E$15,'P-Parametri'!$B$15*('P-Parametri'!$E$15-(C43*(1-'P-Parametri'!$B$19)))/('P-Parametri'!$E$15-'P-Parametri'!$D$15),0)))))>0,'P-Parametri'!$B$20*(C43*(1-'P-Parametri'!$B$19)),0))+(IF(AND((C43*(1-'P-Parametri'!$B$19))<='P-Parametri'!$C$16,(IF((C43*(1-'P-Parametri'!$B$19))<='P-Parametri'!$B$6,'P-Parametri'!$C$6*(C43*(1-'P-Parametri'!$B$19)),IF((C43*(1-'P-Parametri'!$B$19))<='P-Parametri'!$B$7,'P-Parametri'!$B$9+'P-Parametri'!$C$7*((C43*(1-'P-Parametri'!$B$19))-'P-Parametri'!$B$6),'P-Parametri'!$B$10+'P-Parametri'!$C$8*((C43*(1-'P-Parametri'!$B$19))-'P-Parametri'!$B$7))))>(IF((C43*(1-'P-Parametri'!$B$19))<='P-Parametri'!$C$12,'P-Parametri'!$B$12,IF((C43*(1-'P-Parametri'!$B$19))<='P-Parametri'!$B$6,'P-Parametri'!$B$13+'P-Parametri'!$C$13*('P-Parametri'!$B$6-(C43*(1-'P-Parametri'!$B$19)))/'P-Parametri'!$D$13,IF((C43*(1-'P-Parametri'!$B$19))<='P-Parametri'!$B$7,'P-Parametri'!$B$14*('P-Parametri'!$B$7-(C43*(1-'P-Parametri'!$B$19)))/'P-Parametri'!$C$14,0))))-'P-Parametri'!$D$16),'P-Parametri'!$B$16,0))+(IF((C43*(1-'P-Parametri'!$B$19))>'P-Parametri'!$D$18,0,IF((C43*(1-'P-Parametri'!$B$19))<='P-Parametri'!$B$18,'P-Parametri'!$B$17*(C43*(1-'P-Parametri'!$B$19)),IF((C43*(1-'P-Parametri'!$B$19))<='P-Parametri'!$C$18,'P-Parametri'!$C$17*(C43*(1-'P-Parametri'!$B$19)),'P-Parametri'!$D$17*(C43*(1-'P-Parametri'!$B$19)))))) -> 25529.373 | E43: 20750 | F43: =D43-E43 -> 4779.373 | G43: =F43/D43 -> 0.18721075 | H43: =F43*(1+'1-Input'!$B$11)^(2025-A43) -> 4922.7542
A44: =2025 -> 2025 | B44: =31 -> 31 | C44: 36000 | D44: =(C44*(1-'P-Parametri'!$B$19))-(MAX(0,(IF((C44*(1-'P-Parametri'!$B$19))<='P-Parametri'!$B$6,'P-Parametri'!$C$6*(C44*(1-'P-Parametri'!$B$19)),IF((C44*(1-'P-Parametri'!$B$19))<='P-Parametri'!$B$7,'P-Parametri'!$B$9+'P-Parametri'!$C$7*((C44*(1-'P-Parametri'!$B$19))-'P-Parametri'!$B$6),'P-Parametri'!$B$10+'P-Parametri'!$C$8*((C44*(1-'P-Parametri'!$B$19))-'P-Parametri'!$B$7))))-(IF((C44*(1-'P-Parametri'!$B$19))<='P-Parametri'!$C$12,'P-Parametri'!$B$12,IF((C44*(1-'P-Parametri'!$B$19))<='P-Parametri'!$B$6,'P-Parametri'!$B$13+'P-Parametri'!$C$13*('P-Parametri'!$B$6-(C44*(1-'P-Parametri'!$B$19)))/'P-Parametri'!$D$13,IF((C44*(1-'P-Parametri'!$B$19))<='P-Parametri'!$B$7,'P-Parametri'!$B$14*('P-Parametri'!$B$7-(C44*(1-'P-Parametri'!$B$19)))/'P-Parametri'!$C$14,0))))-(IF((C44*(1-'P-Parametri'!$B$19))<='P-Parametri'!$C$15,0,IF((C44*(1-'P-Parametri'!$B$19))<='P-Parametri'!$D$15,'P-Parametri'!$B$15,IF((C44*(1-'P-Parametri'!$B$19))<'P-Parametri'!$E$15,'P-Parametri'!$B$15*('P-Parametri'!$E$15-(C44*(1-'P-Parametri'!$B$19)))/('P-Parametri'!$E$15-'P-Parametri'!$D$15),0))))))-(IF(MAX(0,(IF((C44*(1-'P-Parametri'!$B$19))<='P-Parametri'!$B$6,'P-Parametri'!$C$6*(C44*(1-'P-Parametri'!$B$19)),IF((C44*(1-'P-Parametri'!$B$19))<='P-Parametri'!$B$7,'P-Parametri'!$B$9+'P-Parametri'!$C$7*((C44*(1-'P-Parametri'!$B$19))-'P-Parametri'!$B$6),'P-Parametri'!$B$10+'P-Parametri'!$C$8*((C44*(1-'P-Parametri'!$B$19))-'P-Parametri'!$B$7))))-(IF((C44*(1-'P-Parametri'!$B$19))<='P-Parametri'!$C$12,'P-Parametri'!$B$12,IF((C44*(1-'P-Parametri'!$B$19))<='P-Parametri'!$B$6,'P-Parametri'!$B$13+'P-Parametri'!$C$13*('P-Parametri'!$B$6-(C44*(1-'P-Parametri'!$B$19)))/'P-Parametri'!$D$13,IF((C44*(1-'P-Parametri'!$B$19))<='P-Parametri'!$B$7,'P-Parametri'!$B$14*('P-Parametri'!$B$7-(C44*(1-'P-Parametri'!$B$19)))/'P-Parametri'!$C$14,0))))-(IF((C44*(1-'P-Parametri'!$B$19))<='P-Parametri'!$C$15,0,IF((C44*(1-'P-Parametri'!$B$19))<='P-Parametri'!$D$15,'P-Parametri'!$B$15,IF((C44*(1-'P-Parametri'!$B$19))<'P-Parametri'!$E$15,'P-Parametri'!$B$15*('P-Parametri'!$E$15-(C44*(1-'P-Parametri'!$B$19)))/('P-Parametri'!$E$15-'P-Parametri'!$D$15),0)))))>0,'P-Parametri'!$B$20*(C44*(1-'P-Parametri'!$B$19)),0))+(IF(AND((C44*(1-'P-Parametri'!$B$19))<='P-Parametri'!$C$16,(IF((C44*(1-'P-Parametri'!$B$19))<='P-Parametri'!$B$6,'P-Parametri'!$C$6*(C44*(1-'P-Parametri'!$B$19)),IF((C44*(1-'P-Parametri'!$B$19))<='P-Parametri'!$B$7,'P-Parametri'!$B$9+'P-Parametri'!$C$7*((C44*(1-'P-Parametri'!$B$19))-'P-Parametri'!$B$6),'P-Parametri'!$B$10+'P-Parametri'!$C$8*((C44*(1-'P-Parametri'!$B$19))-'P-Parametri'!$B$7))))>(IF((C44*(1-'P-Parametri'!$B$19))<='P-Parametri'!$C$12,'P-Parametri'!$B$12,IF((C44*(1-'P-Parametri'!$B$19))<='P-Parametri'!$B$6,'P-Parametri'!$B$13+'P-Parametri'!$C$13*('P-Parametri'!$B$6-(C44*(1-'P-Parametri'!$B$19)))/'P-Parametri'!$D$13,IF((C44*(1-'P-Parametri'!$B$19))<='P-Parametri'!$B$7,'P-Parametri'!$B$14*('P-Parametri'!$B$7-(C44*(1-'P-Parametri'!$B$19)))/'P-Parametri'!$C$14,0))))-'P-Parametri'!$D$16),'P-Parametri'!$B$16,0))+(IF((C44*(1-'P-Parametri'!$B$19))>'P-Parametri'!$D$18,0,IF((C44*(1-'P-Parametri'!$B$19))<='P-Parametri'!$B$18,'P-Parametri'!$B$17*(C44*(1-'P-Parametri'!$B$19)),IF((C44*(1-'P-Parametri'!$B$19))<='P-Parametri'!$C$18,'P-Parametri'!$C$17*(C44*(1-'P-Parametri'!$B$19)),'P-Parametri'!$D$17*(C44*(1-'P-Parametri'!$B$19)))))) -> 26465.774 | E44: 21000 | F44: =D44-E44 -> 5465.7738 | G44: =F44/D44 -> 0.20652235 | H44: =F44*(1+'1-Input'!$B$11)^(2025-A44) -> 5465.7738
A45: MONTANTE al 1/1/2026 | H45: =SUM(H38:H44) -> 25913.603
A46: Scarto contro il capitale dichiarato in B8 | H46: ='1-Input'!$B$8-H45 -> 86.396515
A47: TERZO ERRORE DI FAMIGLIA — il caso che non chiude. Il capitale NON è un parametro libero: è il montante di sette anni di lavoro, con la carriera e la spesa dichiarate. Il tasso di risparmio implicito sale da poco più del 7% al 20,65% e non lo supera mai: è possibile, è modesto, non richiede né eredità né fortuna. Le sette righe applicano la fiscalità 2026 a redditi 2019-2025: è un'approssimazione dichiarata (serve a mostrare la meccanica del risparmio, non a ricostruire sette buste paga storiche).
A49: Stato abitativo — quarto errore di famiglia, e va guardato in faccia
A50: Spesa ISTAT persona sola, annua | B50: ='P-Parametri'!$B$33*12 -> 23184
A51: Spesa del caso in % dell'aggregato ISTAT | B51: ='1-Input'!$B$7/('P-Parametri'!$B$33*12) -> 0.9057971
A52: Il confronto è omogeneo? | B52: =IF('1-Input'!$B$15="affitto","SI, ed è CONSERVATIVO: in affitto i 21.000 sono tutti cassa, mentre l'aggregato ISTAT include gli affitti figurativi di chi la casa ce l'ha","NO: con la casa di proprietà una parte dell'aggregato ISTAT non è un flusso monetario e il confronto va rifatto") -> SI, ed è CONSERVATIVO: in affitto i 21.000 sono tutti cassa, mentre l'aggregato ISTAT include gli affitti figurativi di chi la casa ce l'ha
A53: L'aggregato ISTAT media proprietari e affittuari e include la componente non monetaria degli affitti figurativi: per la persona sola over 65 la divisione «abitazione» pesa il 48,2% della spesa e gli affitti figurativi ne sono oltre i due terzi. Chi ha la casa pagata non spende in cassa quella cifra. Per questo lo stato abitativo è una variabile della scheda-caso e non un dettaglio.

Sheet 2-Busta-paga
A1: 2 — Busta paga 2026: il motore fiscale, riga per riga
A2: Strumento informativo / divulgativo. NON è consulenza finanziaria. I valori sono indicativi al 2026 e vanno verificati col tuo consulente.
A3: Dipendente privato, nessun carico familiare, anno intero. Otto passi, ognuno in una colonna: contributi 9,19% → reddito complessivo → IRPEF lorda a scaglioni → detrazione da lavoro (art. 13 c. 1 TUIR) → ulteriore detrazione (L. 207/2024 c. 6) → somma sul cuneo (c. 4) → trattamento integrativo (D.L. 3/2020) → addizionali. Zero costanti nelle celle: tutto viene da P-Parametri.
A4: DUE MARGINALI, E NON SONO LA STESSA COSA. La colonna «marginale su +1.000 €» è la differenza fra due righe del motore completo: è quello che sente in busta chi prende mille euro in più. La colonna «marginale di banda» è la derivata analitica dentro la fascia. Coincidono ovunque tranne dove un incremento di mille euro ATTRAVERSA una soglia: lì l'osservata è una media pesata delle due fasce. Esempio: a RAL 55.000 la banda dà 48,86% ma la marginale su +1.000 € è 49,98%, perché l'incremento entra nel terzo scaglione. Il numero che va a video per il confronto con il 60,21% è 49,98%.
A7: RAL | B7: Contributi | C7: Reddito compl. | D7: IRPEF lorda | E7: Detr. lavoro | F7: Ulteriore detr. | G7: Somma cuneo | H7: Tratt. integr. | I7: IRPEF netta | J7: Addizionali | K7: NETTO | L7: Netto / RAL | M7: Marg. su +1.000 € | N7: Marg. di banda | O7: Scarto
A8: =15000 -> 15000 | B8: ='P-Parametri'!$B$19*$A8 -> 1378.5 | C8: =$A8-B8 -> 13621.5 | D8: =IF($C8<='P-Parametri'!$B$6,'P-Parametri'!$C$6*$C8,IF($C8<='P-Parametri'!$B$7,'P-Parametri'!$B$9+'P-Parametri'!$C$7*($C8-'P-Parametri'!$B$6),'P-Parametri'!$B$10+'P-Parametri'!$C$8*($C8-'P-Parametri'!$B$7))) -> 3132.945 | E8: =IF($C8<='P-Parametri'!$C$12,'P-Parametri'!$B$12,IF($C8<='P-Parametri'!$B$6,'P-Parametri'!$B$13+'P-Parametri'!$C$13*('P-Parametri'!$B$6-$C8)/'P-Parametri'!$D$13,IF($C8<='P-Parametri'!$B$7,'P-Parametri'!$B$14*('P-Parametri'!$B$7-$C8)/'P-Parametri'!$C$14,0))) -> 1955 | F8: =IF($C8<='P-Parametri'!$C$15,0,IF($C8<='P-Parametri'!$D$15,'P-Parametri'!$B$15,IF($C8<'P-Parametri'!$E$15,'P-Parametri'!$B$15*('P-Parametri'!$E$15-$C8)/('P-Parametri'!$E$15-'P-Parametri'!$D$15),0))) -> 1000 | G8: =IF($C8>'P-Parametri'!$D$18,0,IF($C8<='P-Parametri'!$B$18,'P-Parametri'!$B$17*$C8,IF($C8<='P-Parametri'!$C$18,'P-Parametri'!$C$17*$C8,'P-Parametri'!$D$17*$C8))) -> 721.9395 | H8: =IF(AND($C8<='P-Parametri'!$C$16,D8>E8-'P-Parametri'!$D$16),'P-Parametri'!$B$16,0) -> 1200 | I8: =MAX(0,D8-E8-F8) -> 177.945 | J8: =IF(I8>0,'P-Parametri'!$B$20*$C8,0) -> 272.43 | K8: =$C8-I8-J8+H8+G8 -> 15093.065 | L8: =K8/$A8 -> 1.0062043 | M8: =1-(K10-K8)/1000 -> 0.2707957 | N8: ='P-Parametri'!$B$19+(1-'P-Parametri'!$B$19)*((IF(($A8*(1-'P-Parametri'!$B$19))<='P-Parametri'!$B$6,'P-Parametri'!$C$6,IF(($A8*(1-'P-Parametri'!$B$19))<='P-Parametri'!$B$7,'P-Parametri'!$C$7,'P-Parametri'!$C$8)))+(IF(($A8*(1-'P-Parametri'!$B$19))<='P-Parametri'!$C$12,0,IF(($A8*(1-'P-Parametri'!$B$19))<='P-Parametri'!$B$6,'P-Parametri'!$C$13/'P-Parametri'!$D$13,IF(($A8*(1-'P-Parametri'!$B$19))<='P-Parametri'!$B$7,'P-Parametri'!$B$14/'P-Parametri'!$C$14,0))))+(IF(AND(($A8*(1-'P-Parametri'!$B$19))>'P-Parametri'!$D$15,($A8*(1-'P-Parametri'!$B$19))<'P-Parametri'!$E$15),'P-Parametri'!$B$15/('P-Parametri'!$E$15-'P-Parametri'!$D$15),0))+'P-Parametri'!$B$20) -> 0.318925 | O8: =M8-N8 -> -0.0481293
A9: =15500 -> 15500 | B9: ='P-Parametri'!$B$19*$A9 -> 1424.45 | C9: =$A9-B9 -> 14075.55 | D9: =IF($C9<='P-Parametri'!$B$6,'P-Parametri'!$C$6*$C9,IF($C9<='P-Parametri'!$B$7,'P-Parametri'!$B$9+'P-Parametri'!$C$7*($C9-'P-Parametri'!$B$6),'P-Parametri'!$B$10+'P-Parametri'!$C$8*($C9-'P-Parametri'!$B$7))) -> 3237.3765 | E9: =IF($C9<='P-Parametri'!$C$12,'P-Parametri'!$B$12,IF($C9<='P-Parametri'!$B$6,'P-Parametri'!$B$13+'P-Parametri'!$C$13*('P-Parametri'!$B$6-$C9)/'P-Parametri'!$D$13,IF($C9<='P-Parametri'!$B$7,'P-Parametri'!$B$14*('P-Parametri'!$B$7-$C9)/'P-Parametri'!$C$14,0))) -> 1955 | F9: =IF($C9<='P-Parametri'!$C$15,0,IF($C9<='P-Parametri'!$D$15,'P-Parametri'!$B$15,IF($C9<'P-Parametri'!$E$15,'P-Parametri'!$B$15*('P-Parametri'!$E$15-$C9)/('P-Parametri'!$E$15-'P-Parametri'!$D$15),0))) -> 1000 | G9: =IF($C9>'P-Parametri'!$D$18,0,IF($C9<='P-Parametri'!$B$18,'P-Parametri'!$B$17*$C9,IF($C9<='P-Parametri'!$C$18,'P-Parametri'!$C$17*$C9,'P-Parametri'!$D$17*$C9))) -> 746.00415 | H9: =IF(AND($C9<='P-Parametri'!$C$16,D9>E9-'P-Parametri'!$D$16),'P-Parametri'!$B$16,0) -> 1200 | I9: =MAX(0,D9-E9-F9) -> 282.3765 | J9: =IF(I9>0,'P-Parametri'!$B$20*$C9,0) -> 281.511 | K9: =$C9-I9-J9+H9+G9 -> 15457.667 | L9: =K9/$A9 -> 0.99726882 | M9: =1-(K11-K9)/1000 -> 0.2707957 | N9: ='P-Parametri'!$B$19+(1-'P-Parametri'!$B$19)*((IF(($A9*(1-'P-Parametri'!$B$19))<='P-Parametri'!$B$6,'P-Parametri'!$C$6,IF(($A9*(1-'P-Parametri'!$B$19))<='P-Parametri'!$B$7,'P-Parametri'!$C$7,'P-Parametri'!$C$8)))+(IF(($A9*(1-'P-Parametri'!$B$19))<='P-Parametri'!$C$12,0,IF(($A9*(1-'P-Parametri'!$B$19))<='P-Parametri'!$B$6,'P-Parametri'!$C$13/'P-Parametri'!$D$13,IF(($A9*(1-'P-Parametri'!$B$19))<='P-Parametri'!$B$7,'P-Parametri'!$B$14/'P-Parametri'!$C$14,0))))+(IF(AND(($A9*(1-'P-Parametri'!$B$19))>'P-Parametri'!$D$15,($A9*(1-'P-Parametri'!$B$19))<'P-Parametri'!$E$15),'P-Parametri'!$B$15/('P-Parametri'!$E$15-'P-Parametri'!$D$15),0))+'P-Parametri'!$B$20) -> 0.318925 | O9: =M9-N9 -> -0.0481293
A10: =16000 -> 16000 | B10: ='P-Parametri'!$B$19*$A10 -> 1470.4 | C10: =$A10-B10 -> 14529.6 | D10: =IF($C10<='P-Parametri'!$B$6,'P-Parametri'!$C$6*$C10,IF($C10<='P-Parametri'!$B$7,'P-Parametri'!$B$9+'P-Parametri'!$C$7*($C10-'P-Parametri'!$B$6),'P-Parametri'!$B$10+'P-Parametri'!$C$8*($C10-'P-Parametri'!$B$7))) -> 3341.808 | E10: =IF($C10<='P-Parametri'!$C$12,'P-Parametri'!$B$12,IF($C10<='P-Parametri'!$B$6,'P-Parametri'!$B$13+'P-Parametri'!$C$13*('P-Parametri'!$B$6-$C10)/'P-Parametri'!$D$13,IF($C10<='P-Parametri'!$B$7,'P-Parametri'!$B$14*('P-Parametri'!$B$7-$C10)/'P-Parametri'!$C$14,0))) -> 1955 | F10: =IF($C10<='P-Parametri'!$C$15,0,IF($C10<='P-Parametri'!$D$15,'P-Parametri'!$B$15,IF($C10<'P-Parametri'!$E$15,'P-Parametri'!$B$15*('P-Parametri'!$E$15-$C10)/('P-Parametri'!$E$15-'P-Parametri'!$D$15),0))) -> 1000 | G10: =IF($C10>'P-Parametri'!$D$18,0,IF($C10<='P-Parametri'!$B$18,'P-Parametri'!$B$17*$C10,IF($C10<='P-Parametri'!$C$18,'P-Parametri'!$C$17*$C10,'P-Parametri'!$D$17*$C10))) -> 770.0688 | H10: =IF(AND($C10<='P-Parametri'!$C$16,D10>E10-'P-Parametri'!$D$16),'P-Parametri'!$B$16,0) -> 1200 | I10: =MAX(0,D10-E10-F10) -> 386.808 | J10: =IF(I10>0,'P-Parametri'!$B$20*$C10,0) -> 290.592 | K10: =$C10-I10-J10+H10+G10 -> 15822.269 | L10: =K10/$A10 -> 0.9888918 | M10: =1-(K12-K10)/1000 -> 0.6435592 | N10: ='P-Parametri'!$B$19+(1-'P-Parametri'!$B$19)*((IF(($A10*(1-'P-Parametri'!$B$19))<='P-Parametri'!$B$6,'P-Parametri'!$C$6,IF(($A10*(1-'P-Parametri'!$B$19))<='P-Parametri'!$B$7,'P-Parametri'!$C$7,'P-Parametri'!$C$8)))+(IF(($A10*(1-'P-Parametri'!$B$19))<='P-Parametri'!$C$12,0,IF(($A10*(1-'P-Parametri'!$B$19))<='P-Parametri'!$B$6,'P-Parametri'!$C$13/'P-Parametri'!$D$13,IF(($A10*(1-'P-Parametri'!$B$19))<='P-Parametri'!$B$7,'P-Parametri'!$B$14/'P-Parametri'!$C$14,0))))+(IF(AND(($A10*(1-'P-Parametri'!$B$19))>'P-Parametri'!$D$15,($A10*(1-'P-Parametri'!$B$19))<'P-Parametri'!$E$15),'P-Parametri'!$B$15/('P-Parametri'!$E$15-'P-Parametri'!$D$15),0))+'P-Parametri'!$B$20) -> 0.318925 | O10: =M10-N10 -> 0.3246342
A11: =16500 -> 16500 | B11: ='P-Parametri'!$B$19*$A11 -> 1516.35 | C11: =$A11-B11 -> 14983.65 | D11: =IF($C11<='P-Parametri'!$B$6,'P-Parametri'!$C$6*$C11,IF($C11<='P-Parametri'!$B$7,'P-Parametri'!$B$9+'P-Parametri'!$C$7*($C11-'P-Parametri'!$B$6),'P-Parametri'!$B$10+'P-Parametri'!$C$8*($C11-'P-Parametri'!$B$7))) -> 3446.2395 | E11: =IF($C11<='P-Parametri'!$C$12,'P-Parametri'!$B$12,IF($C11<='P-Parametri'!$B$6,'P-Parametri'!$B$13+'P-Parametri'!$C$13*('P-Parametri'!$B$6-$C11)/'P-Parametri'!$D$13,IF($C11<='P-Parametri'!$B$7,'P-Parametri'!$B$14*('P-Parametri'!$B$7-$C11)/'P-Parametri'!$C$14,0))) -> 1955 | F11: =IF($C11<='P-Parametri'!$C$15,0,IF($C11<='P-Parametri'!$D$15,'P-Parametri'!$B$15,IF($C11<'P-Parametri'!$E$15,'P-Parametri'!$B$15*('P-Parametri'!$E$15-$C11)/('P-Parametri'!$E$15-'P-Parametri'!$D$15),0))) -> 1000 | G11: =IF($C11>'P-Parametri'!$D$18,0,IF($C11<='P-Parametri'!$B$18,'P-Parametri'!$B$17*$C11,IF($C11<='P-Parametri'!$C$18,'P-Parametri'!$C$17*$C11,'P-Parametri'!$D$17*$C11))) -> 794.13345 | H11: =IF(AND($C11<='P-Parametri'!$C$16,D11>E11-'P-Parametri'!$D$16),'P-Parametri'!$B$16,0) -> 1200 | I11: =MAX(0,D11-E11-F11) -> 491.2395 | J11: =IF(I11>0,'P-Parametri'!$B$20*$C11,0) -> 299.673 | K11: =$C11-I11-J11+H11+G11 -> 16186.871 | L11: =K11/$A11 -> 0.98102248 | M11: =1-(K13-K11)/1000 -> 0.53231695 | N11: ='P-Parametri'!$B$19+(1-'P-Parametri'!$B$19)*((IF(($A11*(1-'P-Parametri'!$B$19))<='P-Parametri'!$B$6,'P-Parametri'!$C$6,IF(($A11*(1-'P-Parametri'!$B$19))<='P-Parametri'!$B$7,'P-Parametri'!$C$7,'P-Parametri'!$C$8)))+(IF(($A11*(1-'P-Parametri'!$B$19))<='P-Parametri'!$C$12,0,IF(($A11*(1-'P-Parametri'!$B$19))<='P-Parametri'!$B$6,'P-Parametri'!$C$13/'P-Parametri'!$D$13,IF(($A11*(1-'P-Parametri'!$B$19))<='P-Parametri'!$B$7,'P-Parametri'!$B$14/'P-Parametri'!$C$14,0))))+(IF(AND(($A11*(1-'P-Parametri'!$B$19))>'P-Parametri'!$D$15,($A11*(1-'P-Parametri'!$B$19))<'P-Parametri'!$E$15),'P-Parametri'!$B$15/('P-Parametri'!$E$15-'P-Parametri'!$D$15),0))+'P-Parametri'!$B$20) -> 0.318925 | O11: =M11-N11 -> 0.21339195
A12: =17000 -> 17000 | B12: ='P-Parametri'!$B$19*$A12 -> 1562.3 | C12: =$A12-B12 -> 15437.7 | D12: =IF($C12<='P-Parametri'!$B$6,'P-Parametri'!$C$6*$C12,IF($C12<='P-Parametri'!$B$7,'P-Parametri'!$B$9+'P-Parametri'!$C$7*($C12-'P-Parametri'!$B$6),'P-Parametri'!$B$10+'P-Parametri'!$C$8*($C12-'P-Parametri'!$B$7))) -> 3550.671 | E12: =IF($C12<='P-Parametri'!$C$12,'P-Parametri'!$B$12,IF($C12<='P-Parametri'!$B$6,'P-Parametri'!$B$13+'P-Parametri'!$C$13*('P-Parametri'!$B$6-$C12)/'P-Parametri'!$D$13,IF($C12<='P-Parametri'!$B$7,'P-Parametri'!$B$14*('P-Parametri'!$B$7-$C12)/'P-Parametri'!$C$14,0))) -> 3059.9336 | F12: =IF($C12<='P-Parametri'!$C$15,0,IF($C12<='P-Parametri'!$D$15,'P-Parametri'!$B$15,IF($C12<'P-Parametri'!$E$15,'P-Parametri'!$B$15*('P-Parametri'!$E$15-$C12)/('P-Parametri'!$E$15-'P-Parametri'!$D$15),0))) -> 1000 | G12: =IF($C12>'P-Parametri'!$D$18,0,IF($C12<='P-Parametri'!$B$18,'P-Parametri'!$B$17*$C12,IF($C12<='P-Parametri'!$C$18,'P-Parametri'!$C$17*$C12,'P-Parametri'!$D$17*$C12))) -> 741.0096 | H12: =IF(AND($C12<='P-Parametri'!$C$16,D12>E12-'P-Parametri'!$D$16),'P-Parametri'!$B$16,0) -> 0 | I12: =MAX(0,D12-E12-F12) -> 0 | J12: =IF(I12>0,'P-Parametri'!$B$20*$C12,0) -> 0 | K12: =$C12-I12-J12+H12+G12 -> 16178.71 | L12: =K12/$A12 -> 0.9516888 | M12: =1-(K14-K12)/1000 -> 0.0483112 | N12: ='P-Parametri'!$B$19+(1-'P-Parametri'!$B$19)*((IF(($A12*(1-'P-Parametri'!$B$19))<='P-Parametri'!$B$6,'P-Parametri'!$C$6,IF(($A12*(1-'P-Parametri'!$B$19))<='P-Parametri'!$B$7,'P-Parametri'!$C$7,'P-Parametri'!$C$8)))+(IF(($A12*(1-'P-Parametri'!$B$19))<='P-Parametri'!$C$12,0,IF(($A12*(1-'P-Parametri'!$B$19))<='P-Parametri'!$B$6,'P-Parametri'!$C$13/'P-Parametri'!$D$13,IF(($A12*(1-'P-Parametri'!$B$19))<='P-Parametri'!$B$7,'P-Parametri'!$B$14/'P-Parametri'!$C$14,0))))+(IF(AND(($A12*(1-'P-Parametri'!$B$19))>'P-Parametri'!$D$15,($A12*(1-'P-Parametri'!$B$19))<'P-Parametri'!$E$15),'P-Parametri'!$B$15/('P-Parametri'!$E$15-'P-Parametri'!$D$15),0))+'P-Parametri'!$B$20) -> 0.40205108 | O12: =M12-N12 -> -0.35373988
A13: =17500 -> 17500 | B13: ='P-Parametri'!$B$19*$A13 -> 1608.25 | C13: =$A13-B13 -> 15891.75 | D13: =IF($C13<='P-Parametri'!$B$6,'P-Parametri'!$C$6*$C13,IF($C13<='P-Parametri'!$B$7,'P-Parametri'!$B$9+'P-Parametri'!$C$7*($C13-'P-Parametri'!$B$6),'P-Parametri'!$B$10+'P-Parametri'!$C$8*($C13-'P-Parametri'!$B$7))) -> 3655.1025 | E13: =IF($C13<='P-Parametri'!$C$12,'P-Parametri'!$B$12,IF($C13<='P-Parametri'!$B$6,'P-Parametri'!$B$13+'P-Parametri'!$C$13*('P-Parametri'!$B$6-$C13)/'P-Parametri'!$D$13,IF($C13<='P-Parametri'!$B$7,'P-Parametri'!$B$14*('P-Parametri'!$B$7-$C13)/'P-Parametri'!$C$14,0))) -> 3018.3706 | F13: =IF($C13<='P-Parametri'!$C$15,0,IF($C13<='P-Parametri'!$D$15,'P-Parametri'!$B$15,IF($C13<'P-Parametri'!$E$15,'P-Parametri'!$B$15*('P-Parametri'!$E$15-$C13)/('P-Parametri'!$E$15-'P-Parametri'!$D$15),0))) -> 1000 | G13: =IF($C13>'P-Parametri'!$D$18,0,IF($C13<='P-Parametri'!$B$18,'P-Parametri'!$B$17*$C13,IF($C13<='P-Parametri'!$C$18,'P-Parametri'!$C$17*$C13,'P-Parametri'!$D$17*$C13))) -> 762.804 | H13: =IF(AND($C13<='P-Parametri'!$C$16,D13>E13-'P-Parametri'!$D$16),'P-Parametri'!$B$16,0) -> 0 | I13: =MAX(0,D13-E13-F13) -> 0 | J13: =IF(I13>0,'P-Parametri'!$B$20*$C13,0) -> 0 | K13: =$C13-I13-J13+H13+G13 -> 16654.554 | L13: =K13/$A13 -> 0.9516888 | M13: =1-(K15-K13)/1000 -> 0.0483112 | N13: ='P-Parametri'!$B$19+(1-'P-Parametri'!$B$19)*((IF(($A13*(1-'P-Parametri'!$B$19))<='P-Parametri'!$B$6,'P-Parametri'!$C$6,IF(($A13*(1-'P-Parametri'!$B$19))<='P-Parametri'!$B$7,'P-Parametri'!$C$7,'P-Parametri'!$C$8)))+(IF(($A13*(1-'P-Parametri'!$B$19))<='P-Parametri'!$C$12,0,IF(($A13*(1-'P-Parametri'!$B$19))<='P-Parametri'!$B$6,'P-Parametri'!$C$13/'P-Parametri'!$D$13,IF(($A13*(1-'P-Parametri'!$B$19))<='P-Parametri'!$B$7,'P-Parametri'!$B$14/'P-Parametri'!$C$14,0))))+(IF(AND(($A13*(1-'P-Parametri'!$B$19))>'P-Parametri'!$D$15,($A13*(1-'P-Parametri'!$B$19))<'P-Parametri'!$E$15),'P-Parametri'!$B$15/('P-Parametri'!$E$15-'P-Parametri'!$D$15),0))+'P-Parametri'!$B$20) -> 0.40205108 | O13: =M13-N13 -> -0.35373988
A14: =18000 -> 18000 | B14: ='P-Parametri'!$B$19*$A14 -> 1654.2 | C14: =$A14-B14 -> 16345.8 | D14: =IF($C14<='P-Parametri'!$B$6,'P-Parametri'!$C$6*$C14,IF($C14<='P-Parametri'!$B$7,'P-Parametri'!$B$9+'P-Parametri'!$C$7*($C14-'P-Parametri'!$B$6),'P-Parametri'!$B$10+'P-Parametri'!$C$8*($C14-'P-Parametri'!$B$7))) -> 3759.534 | E14: =IF($C14<='P-Parametri'!$C$12,'P-Parametri'!$B$12,IF($C14<='P-Parametri'!$B$6,'P-Parametri'!$B$13+'P-Parametri'!$C$13*('P-Parametri'!$B$6-$C14)/'P-Parametri'!$D$13,IF($C14<='P-Parametri'!$B$7,'P-Parametri'!$B$14*('P-Parametri'!$B$7-$C14)/'P-Parametri'!$C$14,0))) -> 2976.8075 | F14: =IF($C14<='P-Parametri'!$C$15,0,IF($C14<='P-Parametri'!$D$15,'P-Parametri'!$B$15,IF($C14<'P-Parametri'!$E$15,'P-Parametri'!$B$15*('P-Parametri'!$E$15-$C14)/('P-Parametri'!$E$15-'P-Parametri'!$D$15),0))) -> 1000 | G14: =IF($C14>'P-Parametri'!$D$18,0,IF($C14<='P-Parametri'!$B$18,'P-Parametri'!$B$17*$C14,IF($C14<='P-Parametri'!$C$18,'P-Parametri'!$C$17*$C14,'P-Parametri'!$D$17*$C14))) -> 784.5984 | H14: =IF(AND($C14<='P-Parametri'!$C$16,D14>E14-'P-Parametri'!$D$16),'P-Parametri'!$B$16,0) -> 0 | I14: =MAX(0,D14-E14-F14) -> 0 | J14: =IF(I14>0,'P-Parametri'!$B$20*$C14,0) -> 0 | K14: =$C14-I14-J14+H14+G14 -> 17130.398 | L14: =K14/$A14 -> 0.9516888 | M14: =1-(K16-K14)/1000 -> 0.46810474 | N14: ='P-Parametri'!$B$19+(1-'P-Parametri'!$B$19)*((IF(($A14*(1-'P-Parametri'!$B$19))<='P-Parametri'!$B$6,'P-Parametri'!$C$6,IF(($A14*(1-'P-Parametri'!$B$19))<='P-Parametri'!$B$7,'P-Parametri'!$C$7,'P-Parametri'!$C$8)))+(IF(($A14*(1-'P-Parametri'!$B$19))<='P-Parametri'!$C$12,0,IF(($A14*(1-'P-Parametri'!$B$19))<='P-Parametri'!$B$6,'P-Parametri'!$C$13/'P-Parametri'!$D$13,IF(($A14*(1-'P-Parametri'!$B$19))<='P-Parametri'!$B$7,'P-Parametri'!$B$14/'P-Parametri'!$C$14,0))))+(IF(AND(($A14*(1-'P-Parametri'!$B$19))>'P-Parametri'!$D$15,($A14*(1-'P-Parametri'!$B$19))<'P-Parametri'!$E$15),'P-Parametri'!$B$15/('P-Parametri'!$E$15-'P-Parametri'!$D$15),0))+'P-Parametri'!$B$20) -> 0.40205108 | O14: =M14-N14 -> 0.066053662
A15: =18500 -> 18500 | B15: ='P-Parametri'!$B$19*$A15 -> 1700.15 | C15: =$A15-B15 -> 16799.85 | D15: =IF($C15<='P-Parametri'!$B$6,'P-Parametri'!$C$6*$C15,IF($C15<='P-Parametri'!$B$7,'P-Parametri'!$B$9+'P-Parametri'!$C$7*($C15-'P-Parametri'!$B$6),'P-Parametri'!$B$10+'P-Parametri'!$C$8*($C15-'P-Parametri'!$B$7))) -> 3863.9655 | E15: =IF($C15<='P-Parametri'!$C$12,'P-Parametri'!$B$12,IF($C15<='P-Parametri'!$B$6,'P-Parametri'!$B$13+'P-Parametri'!$C$13*('P-Parametri'!$B$6-$C15)/'P-Parametri'!$D$13,IF($C15<='P-Parametri'!$B$7,'P-Parametri'!$B$14*('P-Parametri'!$B$7-$C15)/'P-Parametri'!$C$14,0))) -> 2935.2445 | F15: =IF($C15<='P-Parametri'!$C$15,0,IF($C15<='P-Parametri'!$D$15,'P-Parametri'!$B$15,IF($C15<'P-Parametri'!$E$15,'P-Parametri'!$B$15*('P-Parametri'!$E$15-$C15)/('P-Parametri'!$E$15-'P-Parametri'!$D$15),0))) -> 1000 | G15: =IF($C15>'P-Parametri'!$D$18,0,IF($C15<='P-Parametri'!$B$18,'P-Parametri'!$B$17*$C15,IF($C15<='P-Parametri'!$C$18,'P-Parametri'!$C$17*$C15,'P-Parametri'!$D$17*$C15))) -> 806.3928 | H15: =IF(AND($C15<='P-Parametri'!$C$16,D15>E15-'P-Parametri'!$D$16),'P-Parametri'!$B$16,0) -> 0 | I15: =MAX(0,D15-E15-F15) -> 0 | J15: =IF(I15>0,'P-Parametri'!$B$20*$C15,0) -> 0 | K15: =$C15-I15-J15+H15+G15 -> 17606.243 | L15: =K15/$A15 -> 0.9516888 | M15: =1-(K17-K15)/1000 -> 0.62318028 | N15: ='P-Parametri'!$B$19+(1-'P-Parametri'!$B$19)*((IF(($A15*(1-'P-Parametri'!$B$19))<='P-Parametri'!$B$6,'P-Parametri'!$C$6,IF(($A15*(1-'P-Parametri'!$B$19))<='P-Parametri'!$B$7,'P-Parametri'!$C$7,'P-Parametri'!$C$8)))+(IF(($A15*(1-'P-Parametri'!$B$19))<='P-Parametri'!$C$12,0,IF(($A15*(1-'P-Parametri'!$B$19))<='P-Parametri'!$B$6,'P-Parametri'!$C$13/'P-Parametri'!$D$13,IF(($A15*(1-'P-Parametri'!$B$19))<='P-Parametri'!$B$7,'P-Parametri'!$B$14/'P-Parametri'!$C$14,0))))+(IF(AND(($A15*(1-'P-Parametri'!$B$19))>'P-Parametri'!$D$15,($A15*(1-'P-Parametri'!$B$19))<'P-Parametri'!$E$15),'P-Parametri'!$B$15/('P-Parametri'!$E$15-'P-Parametri'!$D$15),0))+'P-Parametri'!$B$20) -> 0.40205108 | O15: =M15-N15 -> 0.2211292
A16: =19000 -> 19000 | B16: ='P-Parametri'!$B$19*$A16 -> 1746.1 | C16: =$A16-B16 -> 17253.9 | D16: =IF($C16<='P-Parametri'!$B$6,'P-Parametri'!$C$6*$C16,IF($C16<='P-Parametri'!$B$7,'P-Parametri'!$B$9+'P-Parametri'!$C$7*($C16-'P-Parametri'!$B$6),'P-Parametri'!$B$10+'P-Parametri'!$C$8*($C16-'P-Parametri'!$B$7))) -> 3968.397 | E16: =IF($C16<='P-Parametri'!$C$12,'P-Parametri'!$B$12,IF($C16<='P-Parametri'!$B$6,'P-Parametri'!$B$13+'P-Parametri'!$C$13*('P-Parametri'!$B$6-$C16)/'P-Parametri'!$D$13,IF($C16<='P-Parametri'!$B$7,'P-Parametri'!$B$14*('P-Parametri'!$B$7-$C16)/'P-Parametri'!$C$14,0))) -> 2893.6815 | F16: =IF($C16<='P-Parametri'!$C$15,0,IF($C16<='P-Parametri'!$D$15,'P-Parametri'!$B$15,IF($C16<'P-Parametri'!$E$15,'P-Parametri'!$B$15*('P-Parametri'!$E$15-$C16)/('P-Parametri'!$E$15-'P-Parametri'!$D$15),0))) -> 1000 | G16: =IF($C16>'P-Parametri'!$D$18,0,IF($C16<='P-Parametri'!$B$18,'P-Parametri'!$B$17*$C16,IF($C16<='P-Parametri'!$C$18,'P-Parametri'!$C$17*$C16,'P-Parametri'!$D$17*$C16))) -> 828.1872 | H16: =IF(AND($C16<='P-Parametri'!$C$16,D16>E16-'P-Parametri'!$D$16),'P-Parametri'!$B$16,0) -> 0 | I16: =MAX(0,D16-E16-F16) -> 74.715538 | J16: =IF(I16>0,'P-Parametri'!$B$20*$C16,0) -> 345.078 | K16: =$C16-I16-J16+H16+G16 -> 17662.294 | L16: =K16/$A16 -> 0.9295944 | M16: =1-(K18-K16)/1000 -> 0.35846228 | N16: ='P-Parametri'!$B$19+(1-'P-Parametri'!$B$19)*((IF(($A16*(1-'P-Parametri'!$B$19))<='P-Parametri'!$B$6,'P-Parametri'!$C$6,IF(($A16*(1-'P-Parametri'!$B$19))<='P-Parametri'!$B$7,'P-Parametri'!$C$7,'P-Parametri'!$C$8)))+(IF(($A16*(1-'P-Parametri'!$B$19))<='P-Parametri'!$C$12,0,IF(($A16*(1-'P-Parametri'!$B$19))<='P-Parametri'!$B$6,'P-Parametri'!$C$13/'P-Parametri'!$D$13,IF(($A16*(1-'P-Parametri'!$B$19))<='P-Parametri'!$B$7,'P-Parametri'!$B$14/'P-Parametri'!$C$14,0))))+(IF(AND(($A16*(1-'P-Parametri'!$B$19))>'P-Parametri'!$D$15,($A16*(1-'P-Parametri'!$B$19))<'P-Parametri'!$E$15),'P-Parametri'!$B$15/('P-Parametri'!$E$15-'P-Parametri'!$D$15),0))+'P-Parametri'!$B$20) -> 0.40205108 | O16: =M16-N16 -> -0.0435888
A17: =19500 -> 19500 | B17: ='P-Parametri'!$B$19*$A17 -> 1792.05 | C17: =$A17-B17 -> 17707.95 | D17: =IF($C17<='P-Parametri'!$B$6,'P-Parametri'!$C$6*$C17,IF($C17<='P-Parametri'!$B$7,'P-Parametri'!$B$9+'P-Parametri'!$C$7*($C17-'P-Parametri'!$B$6),'P-Parametri'!$B$10+'P-Parametri'!$C$8*($C17-'P-Parametri'!$B$7))) -> 4072.8285 | E17: =IF($C17<='P-Parametri'!$C$12,'P-Parametri'!$B$12,IF($C17<='P-Parametri'!$B$6,'P-Parametri'!$B$13+'P-Parametri'!$C$13*('P-Parametri'!$B$6-$C17)/'P-Parametri'!$D$13,IF($C17<='P-Parametri'!$B$7,'P-Parametri'!$B$14*('P-Parametri'!$B$7-$C17)/'P-Parametri'!$C$14,0))) -> 2852.1184 | F17: =IF($C17<='P-Parametri'!$C$15,0,IF($C17<='P-Parametri'!$D$15,'P-Parametri'!$B$15,IF($C17<'P-Parametri'!$E$15,'P-Parametri'!$B$15*('P-Parametri'!$E$15-$C17)/('P-Parametri'!$E$15-'P-Parametri'!$D$15),0))) -> 1000 | G17: =IF($C17>'P-Parametri'!$D$18,0,IF($C17<='P-Parametri'!$B$18,'P-Parametri'!$B$17*$C17,IF($C17<='P-Parametri'!$C$18,'P-Parametri'!$C$17*$C17,'P-Parametri'!$D$17*$C17))) -> 849.9816 | H17: =IF(AND($C17<='P-Parametri'!$C$16,D17>E17-'P-Parametri'!$D$16),'P-Parametri'!$B$16,0) -> 0 | I17: =MAX(0,D17-E17-F17) -> 220.71008 | J17: =IF(I17>0,'P-Parametri'!$B$20*$C17,0) -> 354.159 | K17: =$C17-I17-J17+H17+G17 -> 17983.063 | L17: =K17/$A17 -> 0.92220833 | M17: =1-(K19-K17)/1000 -> 0.35846228 | N17: ='P-Parametri'!$B$19+(1-'P-Parametri'!$B$19)*((IF(($A17*(1-'P-Parametri'!$B$19))<='P-Parametri'!$B$6,'P-Parametri'!$C$6,IF(($A17*(1-'P-Parametri'!$B$19))<='P-Parametri'!$B$7,'P-Parametri'!$C$7,'P-Parametri'!$C$8)))+(IF(($A17*(1-'P-Parametri'!$B$19))<='P-Parametri'!$C$12,0,IF(($A17*(1-'P-Parametri'!$B$19))<='P-Parametri'!$B$6,'P-Parametri'!$C$13/'P-Parametri'!$D$13,IF(($A17*(1-'P-Parametri'!$B$19))<='P-Parametri'!$B$7,'P-Parametri'!$B$14/'P-Parametri'!$C$14,0))))+(IF(AND(($A17*(1-'P-Parametri'!$B$19))>'P-Parametri'!$D$15,($A17*(1-'P-Parametri'!$B$19))<'P-Parametri'!$E$15),'P-Parametri'!$B$15/('P-Parametri'!$E$15-'P-Parametri'!$D$15),0))+'P-Parametri'!$B$20) -> 0.40205108 | O17: =M17-N17 -> -0.0435888
A18: =20000 -> 20000 | B18: ='P-Parametri'!$B$19*$A18 -> 1838 | C18: =$A18-B18 -> 18162 | D18: =IF($C18<='P-Parametri'!$B$6,'P-Parametri'!$C$6*$C18,IF($C18<='P-Parametri'!$B$7,'P-Parametri'!$B$9+'P-Parametri'!$C$7*($C18-'P-Parametri'!$B$6),'P-Parametri'!$B$10+'P-Parametri'!$C$8*($C18-'P-Parametri'!$B$7))) -> 4177.26 | E18: =IF($C18<='P-Parametri'!$C$12,'P-Parametri'!$B$12,IF($C18<='P-Parametri'!$B$6,'P-Parametri'!$B$13+'P-Parametri'!$C$13*('P-Parametri'!$B$6-$C18)/'P-Parametri'!$D$13,IF($C18<='P-Parametri'!$B$7,'P-Parametri'!$B$14*('P-Parametri'!$B$7-$C18)/'P-Parametri'!$C$14,0))) -> 2810.5554 | F18: =IF($C18<='P-Parametri'!$C$15,0,IF($C18<='P-Parametri'!$D$15,'P-Parametri'!$B$15,IF($C18<'P-Parametri'!$E$15,'P-Parametri'!$B$15*('P-Parametri'!$E$15-$C18)/('P-Parametri'!$E$15-'P-Parametri'!$D$15),0))) -> 1000 | G18: =IF($C18>'P-Parametri'!$D$18,0,IF($C18<='P-Parametri'!$B$18,'P-Parametri'!$B$17*$C18,IF($C18<='P-Parametri'!$C$18,'P-Parametri'!$C$17*$C18,'P-Parametri'!$D$17*$C18))) -> 871.776 | H18: =IF(AND($C18<='P-Parametri'!$C$16,D18>E18-'P-Parametri'!$D$16),'P-Parametri'!$B$16,0) -> 0 | I18: =MAX(0,D18-E18-F18) -> 366.70462 | J18: =IF(I18>0,'P-Parametri'!$B$20*$C18,0) -> 363.24 | K18: =$C18-I18-J18+H18+G18 -> 18303.831 | L18: =K18/$A18 -> 0.91519157 | M18: =1-(K20-K18)/1000 -> 0.35846228 | N18: ='P-Parametri'!$B$19+(1-'P-Parametri'!$B$19)*((IF(($A18*(1-'P-Parametri'!$B$19))<='P-Parametri'!$B$6,'P-Parametri'!$C$6,IF(($A18*(1-'P-Parametri'!$B$19))<='P-Parametri'!$B$7,'P-Parametri'!$C$7,'P-Parametri'!$C$8)))+(IF(($A18*(1-'P-Parametri'!$B$19))<='P-Parametri'!$C$12,0,IF(($A18*(1-'P-Parametri'!$B$19))<='P-Parametri'!$B$6,'P-Parametri'!$C$13/'P-Parametri'!$D$13,IF(($A18*(1-'P-Parametri'!$B$19))<='P-Parametri'!$B$7,'P-Parametri'!$B$14/'P-Parametri'!$C$14,0))))+(IF(AND(($A18*(1-'P-Parametri'!$B$19))>'P-Parametri'!$D$15,($A18*(1-'P-Parametri'!$B$19))<'P-Parametri'!$E$15),'P-Parametri'!$B$15/('P-Parametri'!$E$15-'P-Parametri'!$D$15),0))+'P-Parametri'!$B$20) -> 0.40205108 | O18: =M18-N18 -> -0.0435888
A19: =20500 -> 20500 | B19: ='P-Parametri'!$B$19*$A19 -> 1883.95 | C19: =$A19-B19 -> 18616.05 | D19: =IF($C19<='P-Parametri'!$B$6,'P-Parametri'!$C$6*$C19,IF($C19<='P-Parametri'!$B$7,'P-Parametri'!$B$9+'P-Parametri'!$C$7*($C19-'P-Parametri'!$B$6),'P-Parametri'!$B$10+'P-Parametri'!$C$8*($C19-'P-Parametri'!$B$7))) -> 4281.6915 | E19: =IF($C19<='P-Parametri'!$C$12,'P-Parametri'!$B$12,IF($C19<='P-Parametri'!$B$6,'P-Parametri'!$B$13+'P-Parametri'!$C$13*('P-Parametri'!$B$6-$C19)/'P-Parametri'!$D$13,IF($C19<='P-Parametri'!$B$7,'P-Parametri'!$B$14*('P-Parametri'!$B$7-$C19)/'P-Parametri'!$C$14,0))) -> 2768.9923 | F19: =IF($C19<='P-Parametri'!$C$15,0,IF($C19<='P-Parametri'!$D$15,'P-Parametri'!$B$15,IF($C19<'P-Parametri'!$E$15,'P-Parametri'!$B$15*('P-Parametri'!$E$15-$C19)/('P-Parametri'!$E$15-'P-Parametri'!$D$15),0))) -> 1000 | G19: =IF($C19>'P-Parametri'!$D$18,0,IF($C19<='P-Parametri'!$B$18,'P-Parametri'!$B$17*$C19,IF($C19<='P-Parametri'!$C$18,'P-Parametri'!$C$17*$C19,'P-Parametri'!$D$17*$C19))) -> 893.5704 | H19: =IF(AND($C19<='P-Parametri'!$C$16,D19>E19-'P-Parametri'!$D$16),'P-Parametri'!$B$16,0) -> 0 | I19: =MAX(0,D19-E19-F19) -> 512.69915 | J19: =IF(I19>0,'P-Parametri'!$B$20*$C19,0) -> 372.321 | K19: =$C19-I19-J19+H19+G19 -> 18624.6 | L19: =K19/$A19 -> 0.90851709 | M19: =1-(K21-K19)/1000 -> 0.35846228 | N19: ='P-Parametri'!$B$19+(1-'P-Parametri'!$B$19)*((IF(($A19*(1-'P-Parametri'!$B$19))<='P-Parametri'!$B$6,'P-Parametri'!$C$6,IF(($A19*(1-'P-Parametri'!$B$19))<='P-Parametri'!$B$7,'P-Parametri'!$C$7,'P-Parametri'!$C$8)))+(IF(($A19*(1-'P-Parametri'!$B$19))<='P-Parametri'!$C$12,0,IF(($A19*(1-'P-Parametri'!$B$19))<='P-Parametri'!$B$6,'P-Parametri'!$C$13/'P-Parametri'!$D$13,IF(($A19*(1-'P-Parametri'!$B$19))<='P-Parametri'!$B$7,'P-Parametri'!$B$14/'P-Parametri'!$C$14,0))))+(IF(AND(($A19*(1-'P-Parametri'!$B$19))>'P-Parametri'!$D$15,($A19*(1-'P-Parametri'!$B$19))<'P-Parametri'!$E$15),'P-Parametri'!$B$15/('P-Parametri'!$E$15-'P-Parametri'!$D$15),0))+'P-Parametri'!$B$20) -> 0.40205108 | O19: =M19-N19 -> -0.0435888
A20: =21000 -> 21000 | B20: ='P-Parametri'!$B$19*$A20 -> 1929.9 | C20: =$A20-B20 -> 19070.1 | D20: =IF($C20<='P-Parametri'!$B$6,'P-Parametri'!$C$6*$C20,IF($C20<='P-Parametri'!$B$7,'P-Parametri'!$B$9+'P-Parametri'!$C$7*($C20-'P-Parametri'!$B$6),'P-Parametri'!$B$10+'P-Parametri'!$C$8*($C20-'P-Parametri'!$B$7))) -> 4386.123 | E20: =IF($C20<='P-Parametri'!$C$12,'P-Parametri'!$B$12,IF($C20<='P-Parametri'!$B$6,'P-Parametri'!$B$13+'P-Parametri'!$C$13*('P-Parametri'!$B$6-$C20)/'P-Parametri'!$D$13,IF($C20<='P-Parametri'!$B$7,'P-Parametri'!$B$14*('P-Parametri'!$B$7-$C20)/'P-Parametri'!$C$14,0))) -> 2727.4293 | F20: =IF($C20<='P-Parametri'!$C$15,0,IF($C20<='P-Parametri'!$D$15,'P-Parametri'!$B$15,IF($C20<'P-Parametri'!$E$15,'P-Parametri'!$B$15*('P-Parametri'!$E$15-$C20)/('P-Parametri'!$E$15-'P-Parametri'!$D$15),0))) -> 1000 | G20: =IF($C20>'P-Parametri'!$D$18,0,IF($C20<='P-Parametri'!$B$18,'P-Parametri'!$B$17*$C20,IF($C20<='P-Parametri'!$C$18,'P-Parametri'!$C$17*$C20,'P-Parametri'!$D$17*$C20))) -> 915.3648 | H20: =IF(AND($C20<='P-Parametri'!$C$16,D20>E20-'P-Parametri'!$D$16),'P-Parametri'!$B$16,0) -> 0 | I20: =MAX(0,D20-E20-F20) -> 658.69369 | J20: =IF(I20>0,'P-Parametri'!$B$20*$C20,0) -> 381.402 | K20: =$C20-I20-J20+H20+G20 -> 18945.369 | L20: =K20/$A20 -> 0.90216043 | M20: =1-(K22-K20)/1000 -> 0.35846228 | N20: ='P-Parametri'!$B$19+(1-'P-Parametri'!$B$19)*((IF(($A20*(1-'P-Parametri'!$B$19))<='P-Parametri'!$B$6,'P-Parametri'!$C$6,IF(($A20*(1-'P-Parametri'!$B$19))<='P-Parametri'!$B$7,'P-Parametri'!$C$7,'P-Parametri'!$C$8)))+(IF(($A20*(1-'P-Parametri'!$B$19))<='P-Parametri'!$C$12,0,IF(($A20*(1-'P-Parametri'!$B$19))<='P-Parametri'!$B$6,'P-Parametri'!$C$13/'P-Parametri'!$D$13,IF(($A20*(1-'P-Parametri'!$B$19))<='P-Parametri'!$B$7,'P-Parametri'!$B$14/'P-Parametri'!$C$14,0))))+(IF(AND(($A20*(1-'P-Parametri'!$B$19))>'P-Parametri'!$D$15,($A20*(1-'P-Parametri'!$B$19))<'P-Parametri'!$E$15),'P-Parametri'!$B$15/('P-Parametri'!$E$15-'P-Parametri'!$D$15),0))+'P-Parametri'!$B$20) -> 0.40205108 | O20: =M20-N20 -> -0.0435888
A21: =21500 -> 21500 | B21: ='P-Parametri'!$B$19*$A21 -> 1975.85 | C21: =$A21-B21 -> 19524.15 | D21: =IF($C21<='P-Parametri'!$B$6,'P-Parametri'!$C$6*$C21,IF($C21<='P-Parametri'!$B$7,'P-Parametri'!$B$9+'P-Parametri'!$C$7*($C21-'P-Parametri'!$B$6),'P-Parametri'!$B$10+'P-Parametri'!$C$8*($C21-'P-Parametri'!$B$7))) -> 4490.5545 | E21: =IF($C21<='P-Parametri'!$C$12,'P-Parametri'!$B$12,IF($C21<='P-Parametri'!$B$6,'P-Parametri'!$B$13+'P-Parametri'!$C$13*('P-Parametri'!$B$6-$C21)/'P-Parametri'!$D$13,IF($C21<='P-Parametri'!$B$7,'P-Parametri'!$B$14*('P-Parametri'!$B$7-$C21)/'P-Parametri'!$C$14,0))) -> 2685.8663 | F21: =IF($C21<='P-Parametri'!$C$15,0,IF($C21<='P-Parametri'!$D$15,'P-Parametri'!$B$15,IF($C21<'P-Parametri'!$E$15,'P-Parametri'!$B$15*('P-Parametri'!$E$15-$C21)/('P-Parametri'!$E$15-'P-Parametri'!$D$15),0))) -> 1000 | G21: =IF($C21>'P-Parametri'!$D$18,0,IF($C21<='P-Parametri'!$B$18,'P-Parametri'!$B$17*$C21,IF($C21<='P-Parametri'!$C$18,'P-Parametri'!$C$17*$C21,'P-Parametri'!$D$17*$C21))) -> 937.1592 | H21: =IF(AND($C21<='P-Parametri'!$C$16,D21>E21-'P-Parametri'!$D$16),'P-Parametri'!$B$16,0) -> 0 | I21: =MAX(0,D21-E21-F21) -> 804.68823 | J21: =IF(I21>0,'P-Parametri'!$B$20*$C21,0) -> 390.483 | K21: =$C21-I21-J21+H21+G21 -> 19266.138 | L21: =K21/$A21 -> 0.89609944 | M21: =1-(K23-K21)/1000 -> 1.3392103 | N21: ='P-Parametri'!$B$19+(1-'P-Parametri'!$B$19)*((IF(($A21*(1-'P-Parametri'!$B$19))<='P-Parametri'!$B$6,'P-Parametri'!$C$6,IF(($A21*(1-'P-Parametri'!$B$19))<='P-Parametri'!$B$7,'P-Parametri'!$C$7,'P-Parametri'!$C$8)))+(IF(($A21*(1-'P-Parametri'!$B$19))<='P-Parametri'!$C$12,0,IF(($A21*(1-'P-Parametri'!$B$19))<='P-Parametri'!$B$6,'P-Parametri'!$C$13/'P-Parametri'!$D$13,IF(($A21*(1-'P-Parametri'!$B$19))<='P-Parametri'!$B$7,'P-Parametri'!$B$14/'P-Parametri'!$C$14,0))))+(IF(AND(($A21*(1-'P-Parametri'!$B$19))>'P-Parametri'!$D$15,($A21*(1-'P-Parametri'!$B$19))<'P-Parametri'!$E$15),'P-Parametri'!$B$15/('P-Parametri'!$E$15-'P-Parametri'!$D$15),0))+'P-Parametri'!$B$20) -> 0.40205108 | O21: =M21-N21 -> 0.9371592
A22: =22000 -> 22000 | B22: ='P-Parametri'!$B$19*$A22 -> 2021.8 | C22: =$A22-B22 -> 19978.2 | D22: =IF($C22<='P-Parametri'!$B$6,'P-Parametri'!$C$6*$C22,IF($C22<='P-Parametri'!$B$7,'P-Parametri'!$B$9+'P-Parametri'!$C$7*($C22-'P-Parametri'!$B$6),'P-Parametri'!$B$10+'P-Parametri'!$C$8*($C22-'P-Parametri'!$B$7))) -> 4594.986 | E22: =IF($C22<='P-Parametri'!$C$12,'P-Parametri'!$B$12,IF($C22<='P-Parametri'!$B$6,'P-Parametri'!$B$13+'P-Parametri'!$C$13*('P-Parametri'!$B$6-$C22)/'P-Parametri'!$D$13,IF($C22<='P-Parametri'!$B$7,'P-Parametri'!$B$14*('P-Parametri'!$B$7-$C22)/'P-Parametri'!$C$14,0))) -> 2644.3032 | F22: =IF($C22<='P-Parametri'!$C$15,0,IF($C22<='P-Parametri'!$D$15,'P-Parametri'!$B$15,IF($C22<'P-Parametri'!$E$15,'P-Parametri'!$B$15*('P-Parametri'!$E$15-$C22)/('P-Parametri'!$E$15-'P-Parametri'!$D$15),0))) -> 1000 | G22: =IF($C22>'P-Parametri'!$D$18,0,IF($C22<='P-Parametri'!$B$18,'P-Parametri'!$B$17*$C22,IF($C22<='P-Parametri'!$C$18,'P-Parametri'!$C$17*$C22,'P-Parametri'!$D$17*$C22))) -> 958.9536 | H22: =IF(AND($C22<='P-Parametri'!$C$16,D22>E22-'P-Parametri'!$D$16),'P-Parametri'!$B$16,0) -> 0 | I22: =MAX(0,D22-E22-F22) -> 950.68277 | J22: =IF(I22>0,'P-Parametri'!$B$20*$C22,0) -> 399.564 | K22: =$C22-I22-J22+H22+G22 -> 19586.907 | L22: =K22/$A22 -> 0.89031395 | M22: =1-(K24-K22)/1000 -> 1.3610047 | N22: ='P-Parametri'!$B$19+(1-'P-Parametri'!$B$19)*((IF(($A22*(1-'P-Parametri'!$B$19))<='P-Parametri'!$B$6,'P-Parametri'!$C$6,IF(($A22*(1-'P-Parametri'!$B$19))<='P-Parametri'!$B$7,'P-Parametri'!$C$7,'P-Parametri'!$C$8)))+(IF(($A22*(1-'P-Parametri'!$B$19))<='P-Parametri'!$C$12,0,IF(($A22*(1-'P-Parametri'!$B$19))<='P-Parametri'!$B$6,'P-Parametri'!$C$13/'P-Parametri'!$D$13,IF(($A22*(1-'P-Parametri'!$B$19))<='P-Parametri'!$B$7,'P-Parametri'!$B$14/'P-Parametri'!$C$14,0))))+(IF(AND(($A22*(1-'P-Parametri'!$B$19))>'P-Parametri'!$D$15,($A22*(1-'P-Parametri'!$B$19))<'P-Parametri'!$E$15),'P-Parametri'!$B$15/('P-Parametri'!$E$15-'P-Parametri'!$D$15),0))+'P-Parametri'!$B$20) -> 0.40205108 | O22: =M22-N22 -> 0.9589536
A23: =22500 -> 22500 | B23: ='P-Parametri'!$B$19*$A23 -> 2067.75 | C23: =$A23-B23 -> 20432.25 | D23: =IF($C23<='P-Parametri'!$B$6,'P-Parametri'!$C$6*$C23,IF($C23<='P-Parametri'!$B$7,'P-Parametri'!$B$9+'P-Parametri'!$C$7*($C23-'P-Parametri'!$B$6),'P-Parametri'!$B$10+'P-Parametri'!$C$8*($C23-'P-Parametri'!$B$7))) -> 4699.4175 | E23: =IF($C23<='P-Parametri'!$C$12,'P-Parametri'!$B$12,IF($C23<='P-Parametri'!$B$6,'P-Parametri'!$B$13+'P-Parametri'!$C$13*('P-Parametri'!$B$6-$C23)/'P-Parametri'!$D$13,IF($C23<='P-Parametri'!$B$7,'P-Parametri'!$B$14*('P-Parametri'!$B$7-$C23)/'P-Parametri'!$C$14,0))) -> 2602.7402 | F23: =IF($C23<='P-Parametri'!$C$15,0,IF($C23<='P-Parametri'!$D$15,'P-Parametri'!$B$15,IF($C23<'P-Parametri'!$E$15,'P-Parametri'!$B$15*('P-Parametri'!$E$15-$C23)/('P-Parametri'!$E$15-'P-Parametri'!$D$15),0))) -> 1000 | G23: =IF($C23>'P-Parametri'!$D$18,0,IF($C23<='P-Parametri'!$B$18,'P-Parametri'!$B$17*$C23,IF($C23<='P-Parametri'!$C$18,'P-Parametri'!$C$17*$C23,'P-Parametri'!$D$17*$C23))) -> 0 | H23: =IF(AND($C23<='P-Parametri'!$C$16,D23>E23-'P-Parametri'!$D$16),'P-Parametri'!$B$16,0) -> 0 | I23: =MAX(0,D23-E23-F23) -> 1096.6773 | J23: =IF(I23>0,'P-Parametri'!$B$20*$C23,0) -> 408.645 | K23: =$C23-I23-J23+H23+G23 -> 18926.928 | L23: =K23/$A23 -> 0.84119679 | M23: =1-(K25-K23)/1000 -> 0.40205108 | N23: ='P-Parametri'!$B$19+(1-'P-Parametri'!$B$19)*((IF(($A23*(1-'P-Parametri'!$B$19))<='P-Parametri'!$B$6,'P-Parametri'!$C$6,IF(($A23*(1-'P-Parametri'!$B$19))<='P-Parametri'!$B$7,'P-Parametri'!$C$7,'P-Parametri'!$C$8)))+(IF(($A23*(1-'P-Parametri'!$B$19))<='P-Parametri'!$C$12,0,IF(($A23*(1-'P-Parametri'!$B$19))<='P-Parametri'!$B$6,'P-Parametri'!$C$13/'P-Parametri'!$D$13,IF(($A23*(1-'P-Parametri'!$B$19))<='P-Parametri'!$B$7,'P-Parametri'!$B$14/'P-Parametri'!$C$14,0))))+(IF(AND(($A23*(1-'P-Parametri'!$B$19))>'P-Parametri'!$D$15,($A23*(1-'P-Parametri'!$B$19))<'P-Parametri'!$E$15),'P-Parametri'!$B$15/('P-Parametri'!$E$15-'P-Parametri'!$D$15),0))+'P-Parametri'!$B$20) -> 0.40205108 | O23: =M23-N23 -> -1.8873791e-15
A24: =23000 -> 23000 | B24: ='P-Parametri'!$B$19*$A24 -> 2113.7 | C24: =$A24-B24 -> 20886.3 | D24: =IF($C24<='P-Parametri'!$B$6,'P-Parametri'!$C$6*$C24,IF($C24<='P-Parametri'!$B$7,'P-Parametri'!$B$9+'P-Parametri'!$C$7*($C24-'P-Parametri'!$B$6),'P-Parametri'!$B$10+'P-Parametri'!$C$8*($C24-'P-Parametri'!$B$7))) -> 4803.849 | E24: =IF($C24<='P-Parametri'!$C$12,'P-Parametri'!$B$12,IF($C24<='P-Parametri'!$B$6,'P-Parametri'!$B$13+'P-Parametri'!$C$13*('P-Parametri'!$B$6-$C24)/'P-Parametri'!$D$13,IF($C24<='P-Parametri'!$B$7,'P-Parametri'!$B$14*('P-Parametri'!$B$7-$C24)/'P-Parametri'!$C$14,0))) -> 2561.1772 | F24: =IF($C24<='P-Parametri'!$C$15,0,IF($C24<='P-Parametri'!$D$15,'P-Parametri'!$B$15,IF($C24<'P-Parametri'!$E$15,'P-Parametri'!$B$15*('P-Parametri'!$E$15-$C24)/('P-Parametri'!$E$15-'P-Parametri'!$D$15),0))) -> 1000 | G24: =IF($C24>'P-Parametri'!$D$18,0,IF($C24<='P-Parametri'!$B$18,'P-Parametri'!$B$17*$C24,IF($C24<='P-Parametri'!$C$18,'P-Parametri'!$C$17*$C24,'P-Parametri'!$D$17*$C24))) -> 0 | H24: =IF(AND($C24<='P-Parametri'!$C$16,D24>E24-'P-Parametri'!$D$16),'P-Parametri'!$B$16,0) -> 0 | I24: =MAX(0,D24-E24-F24) -> 1242.6718 | J24: =IF(I24>0,'P-Parametri'!$B$20*$C24,0) -> 417.726 | K24: =$C24-I24-J24+H24+G24 -> 19225.902 | L24: =K24/$A24 -> 0.83590879 | M24: =1-(K26-K24)/1000 -> 0.40205108 | N24: ='P-Parametri'!$B$19+(1-'P-Parametri'!$B$19)*((IF(($A24*(1-'P-Parametri'!$B$19))<='P-Parametri'!$B$6,'P-Parametri'!$C$6,IF(($A24*(1-'P-Parametri'!$B$19))<='P-Parametri'!$B$7,'P-Parametri'!$C$7,'P-Parametri'!$C$8)))+(IF(($A24*(1-'P-Parametri'!$B$19))<='P-Parametri'!$C$12,0,IF(($A24*(1-'P-Parametri'!$B$19))<='P-Parametri'!$B$6,'P-Parametri'!$C$13/'P-Parametri'!$D$13,IF(($A24*(1-'P-Parametri'!$B$19))<='P-Parametri'!$B$7,'P-Parametri'!$B$14/'P-Parametri'!$C$14,0))))+(IF(AND(($A24*(1-'P-Parametri'!$B$19))>'P-Parametri'!$D$15,($A24*(1-'P-Parametri'!$B$19))<'P-Parametri'!$E$15),'P-Parametri'!$B$15/('P-Parametri'!$E$15-'P-Parametri'!$D$15),0))+'P-Parametri'!$B$20) -> 0.40205108 | O24: =M24-N24 -> -1.8873791e-15
A25: =23500 -> 23500 | B25: ='P-Parametri'!$B$19*$A25 -> 2159.65 | C25: =$A25-B25 -> 21340.35 | D25: =IF($C25<='P-Parametri'!$B$6,'P-Parametri'!$C$6*$C25,IF($C25<='P-Parametri'!$B$7,'P-Parametri'!$B$9+'P-Parametri'!$C$7*($C25-'P-Parametri'!$B$6),'P-Parametri'!$B$10+'P-Parametri'!$C$8*($C25-'P-Parametri'!$B$7))) -> 4908.2805 | E25: =IF($C25<='P-Parametri'!$C$12,'P-Parametri'!$B$12,IF($C25<='P-Parametri'!$B$6,'P-Parametri'!$B$13+'P-Parametri'!$C$13*('P-Parametri'!$B$6-$C25)/'P-Parametri'!$D$13,IF($C25<='P-Parametri'!$B$7,'P-Parametri'!$B$14*('P-Parametri'!$B$7-$C25)/'P-Parametri'!$C$14,0))) -> 2519.6141 | F25: =IF($C25<='P-Parametri'!$C$15,0,IF($C25<='P-Parametri'!$D$15,'P-Parametri'!$B$15,IF($C25<'P-Parametri'!$E$15,'P-Parametri'!$B$15*('P-Parametri'!$E$15-$C25)/('P-Parametri'!$E$15-'P-Parametri'!$D$15),0))) -> 1000 | G25: =IF($C25>'P-Parametri'!$D$18,0,IF($C25<='P-Parametri'!$B$18,'P-Parametri'!$B$17*$C25,IF($C25<='P-Parametri'!$C$18,'P-Parametri'!$C$17*$C25,'P-Parametri'!$D$17*$C25))) -> 0 | H25: =IF(AND($C25<='P-Parametri'!$C$16,D25>E25-'P-Parametri'!$D$16),'P-Parametri'!$B$16,0) -> 0 | I25: =MAX(0,D25-E25-F25) -> 1388.6664 | J25: =IF(I25>0,'P-Parametri'!$B$20*$C25,0) -> 426.807 | K25: =$C25-I25-J25+H25+G25 -> 19524.877 | L25: =K25/$A25 -> 0.83084581 | M25: =1-(K27-K25)/1000 -> 0.40205108 | N25: ='P-Parametri'!$B$19+(1-'P-Parametri'!$B$19)*((IF(($A25*(1-'P-Parametri'!$B$19))<='P-Parametri'!$B$6,'P-Parametri'!$C$6,IF(($A25*(1-'P-Parametri'!$B$19))<='P-Parametri'!$B$7,'P-Parametri'!$C$7,'P-Parametri'!$C$8)))+(IF(($A25*(1-'P-Parametri'!$B$19))<='P-Parametri'!$C$12,0,IF(($A25*(1-'P-Parametri'!$B$19))<='P-Parametri'!$B$6,'P-Parametri'!$C$13/'P-Parametri'!$D$13,IF(($A25*(1-'P-Parametri'!$B$19))<='P-Parametri'!$B$7,'P-Parametri'!$B$14/'P-Parametri'!$C$14,0))))+(IF(AND(($A25*(1-'P-Parametri'!$B$19))>'P-Parametri'!$D$15,($A25*(1-'P-Parametri'!$B$19))<'P-Parametri'!$E$15),'P-Parametri'!$B$15/('P-Parametri'!$E$15-'P-Parametri'!$D$15),0))+'P-Parametri'!$B$20) -> 0.40205108 | O25: =M25-N25 -> 1.6653345e-15
A26: =24000 -> 24000 | B26: ='P-Parametri'!$B$19*$A26 -> 2205.6 | C26: =$A26-B26 -> 21794.4 | D26: =IF($C26<='P-Parametri'!$B$6,'P-Parametri'!$C$6*$C26,IF($C26<='P-Parametri'!$B$7,'P-Parametri'!$B$9+'P-Parametri'!$C$7*($C26-'P-Parametri'!$B$6),'P-Parametri'!$B$10+'P-Parametri'!$C$8*($C26-'P-Parametri'!$B$7))) -> 5012.712 | E26: =IF($C26<='P-Parametri'!$C$12,'P-Parametri'!$B$12,IF($C26<='P-Parametri'!$B$6,'P-Parametri'!$B$13+'P-Parametri'!$C$13*('P-Parametri'!$B$6-$C26)/'P-Parametri'!$D$13,IF($C26<='P-Parametri'!$B$7,'P-Parametri'!$B$14*('P-Parametri'!$B$7-$C26)/'P-Parametri'!$C$14,0))) -> 2478.0511 | F26: =IF($C26<='P-Parametri'!$C$15,0,IF($C26<='P-Parametri'!$D$15,'P-Parametri'!$B$15,IF($C26<'P-Parametri'!$E$15,'P-Parametri'!$B$15*('P-Parametri'!$E$15-$C26)/('P-Parametri'!$E$15-'P-Parametri'!$D$15),0))) -> 1000 | G26: =IF($C26>'P-Parametri'!$D$18,0,IF($C26<='P-Parametri'!$B$18,'P-Parametri'!$B$17*$C26,IF($C26<='P-Parametri'!$C$18,'P-Parametri'!$C$17*$C26,'P-Parametri'!$D$17*$C26))) -> 0 | H26: =IF(AND($C26<='P-Parametri'!$C$16,D26>E26-'P-Parametri'!$D$16),'P-Parametri'!$B$16,0) -> 0 | I26: =MAX(0,D26-E26-F26) -> 1534.6609 | J26: =IF(I26>0,'P-Parametri'!$B$20*$C26,0) -> 435.888 | K26: =$C26-I26-J26+H26+G26 -> 19823.851 | L26: =K26/$A26 -> 0.82599379 | M26: =1-(K28-K26)/1000 -> 0.40205108 | N26: ='P-Parametri'!$B$19+(1-'P-Parametri'!$B$19)*((IF(($A26*(1-'P-Parametri'!$B$19))<='P-Parametri'!$B$6,'P-Parametri'!$C$6,IF(($A26*(1-'P-Parametri'!$B$19))<='P-Parametri'!$B$7,'P-Parametri'!$C$7,'P-Parametri'!$C$8)))+(IF(($A26*(1-'P-Parametri'!$B$19))<='P-Parametri'!$C$12,0,IF(($A26*(1-'P-Parametri'!$B$19))<='P-Parametri'!$B$6,'P-Parametri'!$C$13/'P-Parametri'!$D$13,IF(($A26*(1-'P-Parametri'!$B$19))<='P-Parametri'!$B$7,'P-Parametri'!$B$14/'P-Parametri'!$C$14,0))))+(IF(AND(($A26*(1-'P-Parametri'!$B$19))>'P-Parametri'!$D$15,($A26*(1-'P-Parametri'!$B$19))<'P-Parametri'!$E$15),'P-Parametri'!$B$15/('P-Parametri'!$E$15-'P-Parametri'!$D$15),0))+'P-Parametri'!$B$20) -> 0.40205108 | O26: =M26-N26 -> 1.6653345e-15
A27: =24500 -> 24500 | B27: ='P-Parametri'!$B$19*$A27 -> 2251.55 | C27: =$A27-B27 -> 22248.45 | D27: =IF($C27<='P-Parametri'!$B$6,'P-Parametri'!$C$6*$C27,IF($C27<='P-Parametri'!$B$7,'P-Parametri'!$B$9+'P-Parametri'!$C$7*($C27-'P-Parametri'!$B$6),'P-Parametri'!$B$10+'P-Parametri'!$C$8*($C27-'P-Parametri'!$B$7))) -> 5117.1435 | E27: =IF($C27<='P-Parametri'!$C$12,'P-Parametri'!$B$12,IF($C27<='P-Parametri'!$B$6,'P-Parametri'!$B$13+'P-Parametri'!$C$13*('P-Parametri'!$B$6-$C27)/'P-Parametri'!$D$13,IF($C27<='P-Parametri'!$B$7,'P-Parametri'!$B$14*('P-Parametri'!$B$7-$C27)/'P-Parametri'!$C$14,0))) -> 2436.488 | F27: =IF($C27<='P-Parametri'!$C$15,0,IF($C27<='P-Parametri'!$D$15,'P-Parametri'!$B$15,IF($C27<'P-Parametri'!$E$15,'P-Parametri'!$B$15*('P-Parametri'!$E$15-$C27)/('P-Parametri'!$E$15-'P-Parametri'!$D$15),0))) -> 1000 | G27: =IF($C27>'P-Parametri'!$D$18,0,IF($C27<='P-Parametri'!$B$18,'P-Parametri'!$B$17*$C27,IF($C27<='P-Parametri'!$C$18,'P-Parametri'!$C$17*$C27,'P-Parametri'!$D$17*$C27))) -> 0 | H27: =IF(AND($C27<='P-Parametri'!$C$16,D27>E27-'P-Parametri'!$D$16),'P-Parametri'!$B$16,0) -> 0 | I27: =MAX(0,D27-E27-F27) -> 1680.6555 | J27: =IF(I27>0,'P-Parametri'!$B$20*$C27,0) -> 444.969 | K27: =$C27-I27-J27+H27+G27 -> 20122.826 | L27: =K27/$A27 -> 0.82133982 | M27: =1-(K29-K27)/1000 -> 0.40205108 | N27: ='P-Parametri'!$B$19+(1-'P-Parametri'!$B$19)*((IF(($A27*(1-'P-Parametri'!$B$19))<='P-Parametri'!$B$6,'P-Parametri'!$C$6,IF(($A27*(1-'P-Parametri'!$B$19))<='P-Parametri'!$B$7,'P-Parametri'!$C$7,'P-Parametri'!$C$8)))+(IF(($A27*(1-'P-Parametri'!$B$19))<='P-Parametri'!$C$12,0,IF(($A27*(1-'P-Parametri'!$B$19))<='P-Parametri'!$B$6,'P-Parametri'!$C$13/'P-Parametri'!$D$13,IF(($A27*(1-'P-Parametri'!$B$19))<='P-Parametri'!$B$7,'P-Parametri'!$B$14/'P-Parametri'!$C$14,0))))+(IF(AND(($A27*(1-'P-Parametri'!$B$19))>'P-Parametri'!$D$15,($A27*(1-'P-Parametri'!$B$19))<'P-Parametri'!$E$15),'P-Parametri'!$B$15/('P-Parametri'!$E$15-'P-Parametri'!$D$15),0))+'P-Parametri'!$B$20) -> 0.40205108 | O27: =M27-N27 -> 1.6653345e-15
A28: =25000 -> 25000 | B28: ='P-Parametri'!$B$19*$A28 -> 2297.5 | C28: =$A28-B28 -> 22702.5 | D28: =IF($C28<='P-Parametri'!$B$6,'P-Parametri'!$C$6*$C28,IF($C28<='P-Parametri'!$B$7,'P-Parametri'!$B$9+'P-Parametri'!$C$7*($C28-'P-Parametri'!$B$6),'P-Parametri'!$B$10+'P-Parametri'!$C$8*($C28-'P-Parametri'!$B$7))) -> 5221.575 | E28: =IF($C28<='P-Parametri'!$C$12,'P-Parametri'!$B$12,IF($C28<='P-Parametri'!$B$6,'P-Parametri'!$B$13+'P-Parametri'!$C$13*('P-Parametri'!$B$6-$C28)/'P-Parametri'!$D$13,IF($C28<='P-Parametri'!$B$7,'P-Parametri'!$B$14*('P-Parametri'!$B$7-$C28)/'P-Parametri'!$C$14,0))) -> 2394.925 | F28: =IF($C28<='P-Parametri'!$C$15,0,IF($C28<='P-Parametri'!$D$15,'P-Parametri'!$B$15,IF($C28<'P-Parametri'!$E$15,'P-Parametri'!$B$15*('P-Parametri'!$E$15-$C28)/('P-Parametri'!$E$15-'P-Parametri'!$D$15),0))) -> 1000 | G28: =IF($C28>'P-Parametri'!$D$18,0,IF($C28<='P-Parametri'!$B$18,'P-Parametri'!$B$17*$C28,IF($C28<='P-Parametri'!$C$18,'P-Parametri'!$C$17*$C28,'P-Parametri'!$D$17*$C28))) -> 0 | H28: =IF(AND($C28<='P-Parametri'!$C$16,D28>E28-'P-Parametri'!$D$16),'P-Parametri'!$B$16,0) -> 0 | I28: =MAX(0,D28-E28-F28) -> 1826.65 | J28: =IF(I28>0,'P-Parametri'!$B$20*$C28,0) -> 454.05 | K28: =$C28-I28-J28+H28+G28 -> 20421.8 | L28: =K28/$A28 -> 0.816872 | M28: =1-(K30-K28)/1000 -> 0.40205108 | N28: ='P-Parametri'!$B$19+(1-'P-Parametri'!$B$19)*((IF(($A28*(1-'P-Parametri'!$B$19))<='P-Parametri'!$B$6,'P-Parametri'!$C$6,IF(($A28*(1-'P-Parametri'!$B$19))<='P-Parametri'!$B$7,'P-Parametri'!$C$7,'P-Parametri'!$C$8)))+(IF(($A28*(1-'P-Parametri'!$B$19))<='P-Parametri'!$C$12,0,IF(($A28*(1-'P-Parametri'!$B$19))<='P-Parametri'!$B$6,'P-Parametri'!$C$13/'P-Parametri'!$D$13,IF(($A28*(1-'P-Parametri'!$B$19))<='P-Parametri'!$B$7,'P-Parametri'!$B$14/'P-Parametri'!$C$14,0))))+(IF(AND(($A28*(1-'P-Parametri'!$B$19))>'P-Parametri'!$D$15,($A28*(1-'P-Parametri'!$B$19))<'P-Parametri'!$E$15),'P-Parametri'!$B$15/('P-Parametri'!$E$15-'P-Parametri'!$D$15),0))+'P-Parametri'!$B$20) -> 0.40205108 | O28: =M28-N28 -> 1.6653345e-15
A29: =25500 -> 25500 | B29: ='P-Parametri'!$B$19*$A29 -> 2343.45 | C29: =$A29-B29 -> 23156.55 | D29: =IF($C29<='P-Parametri'!$B$6,'P-Parametri'!$C$6*$C29,IF($C29<='P-Parametri'!$B$7,'P-Parametri'!$B$9+'P-Parametri'!$C$7*($C29-'P-Parametri'!$B$6),'P-Parametri'!$B$10+'P-Parametri'!$C$8*($C29-'P-Parametri'!$B$7))) -> 5326.0065 | E29: =IF($C29<='P-Parametri'!$C$12,'P-Parametri'!$B$12,IF($C29<='P-Parametri'!$B$6,'P-Parametri'!$B$13+'P-Parametri'!$C$13*('P-Parametri'!$B$6-$C29)/'P-Parametri'!$D$13,IF($C29<='P-Parametri'!$B$7,'P-Parametri'!$B$14*('P-Parametri'!$B$7-$C29)/'P-Parametri'!$C$14,0))) -> 2353.362 | F29: =IF($C29<='P-Parametri'!$C$15,0,IF($C29<='P-Parametri'!$D$15,'P-Parametri'!$B$15,IF($C29<'P-Parametri'!$E$15,'P-Parametri'!$B$15*('P-Parametri'!$E$15-$C29)/('P-Parametri'!$E$15-'P-Parametri'!$D$15),0))) -> 1000 | G29: =IF($C29>'P-Parametri'!$D$18,0,IF($C29<='P-Parametri'!$B$18,'P-Parametri'!$B$17*$C29,IF($C29<='P-Parametri'!$C$18,'P-Parametri'!$C$17*$C29,'P-Parametri'!$D$17*$C29))) -> 0 | H29: =IF(AND($C29<='P-Parametri'!$C$16,D29>E29-'P-Parametri'!$D$16),'P-Parametri'!$B$16,0) -> 0 | I29: =MAX(0,D29-E29-F29) -> 1972.6445 | J29: =IF(I29>0,'P-Parametri'!$B$20*$C29,0) -> 463.131 | K29: =$C29-I29-J29+H29+G29 -> 20720.774 | L29: =K29/$A29 -> 0.81257939 | M29: =1-(K31-K29)/1000 -> 0.40205108 | N29: ='P-Parametri'!$B$19+(1-'P-Parametri'!$B$19)*((IF(($A29*(1-'P-Parametri'!$B$19))<='P-Parametri'!$B$6,'P-Parametri'!$C$6,IF(($A29*(1-'P-Parametri'!$B$19))<='P-Parametri'!$B$7,'P-Parametri'!$C$7,'P-Parametri'!$C$8)))+(IF(($A29*(1-'P-Parametri'!$B$19))<='P-Parametri'!$C$12,0,IF(($A29*(1-'P-Parametri'!$B$19))<='P-Parametri'!$B$6,'P-Parametri'!$C$13/'P-Parametri'!$D$13,IF(($A29*(1-'P-Parametri'!$B$19))<='P-Parametri'!$B$7,'P-Parametri'!$B$14/'P-Parametri'!$C$14,0))))+(IF(AND(($A29*(1-'P-Parametri'!$B$19))>'P-Parametri'!$D$15,($A29*(1-'P-Parametri'!$B$19))<'P-Parametri'!$E$15),'P-Parametri'!$B$15/('P-Parametri'!$E$15-'P-Parametri'!$D$15),0))+'P-Parametri'!$B$20) -> 0.40205108 | O29: =M29-N29 -> -1.8873791e-15
A30: =26000 -> 26000 | B30: ='P-Parametri'!$B$19*$A30 -> 2389.4 | C30: =$A30-B30 -> 23610.6 | D30: =IF($C30<='P-Parametri'!$B$6,'P-Parametri'!$C$6*$C30,IF($C30<='P-Parametri'!$B$7,'P-Parametri'!$B$9+'P-Parametri'!$C$7*($C30-'P-Parametri'!$B$6),'P-Parametri'!$B$10+'P-Parametri'!$C$8*($C30-'P-Parametri'!$B$7))) -> 5430.438 | E30: =IF($C30<='P-Parametri'!$C$12,'P-Parametri'!$B$12,IF($C30<='P-Parametri'!$B$6,'P-Parametri'!$B$13+'P-Parametri'!$C$13*('P-Parametri'!$B$6-$C30)/'P-Parametri'!$D$13,IF($C30<='P-Parametri'!$B$7,'P-Parametri'!$B$14*('P-Parametri'!$B$7-$C30)/'P-Parametri'!$C$14,0))) -> 2311.7989 | F30: =IF($C30<='P-Parametri'!$C$15,0,IF($C30<='P-Parametri'!$D$15,'P-Parametri'!$B$15,IF($C30<'P-Parametri'!$E$15,'P-Parametri'!$B$15*('P-Parametri'!$E$15-$C30)/('P-Parametri'!$E$15-'P-Parametri'!$D$15),0))) -> 1000 | G30: =IF($C30>'P-Parametri'!$D$18,0,IF($C30<='P-Parametri'!$B$18,'P-Parametri'!$B$17*$C30,IF($C30<='P-Parametri'!$C$18,'P-Parametri'!$C$17*$C30,'P-Parametri'!$D$17*$C30))) -> 0 | H30: =IF(AND($C30<='P-Parametri'!$C$16,D30>E30-'P-Parametri'!$D$16),'P-Parametri'!$B$16,0) -> 0 | I30: =MAX(0,D30-E30-F30) -> 2118.6391 | J30: =IF(I30>0,'P-Parametri'!$B$20*$C30,0) -> 472.212 | K30: =$C30-I30-J30+H30+G30 -> 21019.749 | L30: =K30/$A30 -> 0.80845188 | M30: =1-(K32-K30)/1000 -> 0.40205108 | N30: ='P-Parametri'!$B$19+(1-'P-Parametri'!$B$19)*((IF(($A30*(1-'P-Parametri'!$B$19))<='P-Parametri'!$B$6,'P-Parametri'!$C$6,IF(($A30*(1-'P-Parametri'!$B$19))<='P-Parametri'!$B$7,'P-Parametri'!$C$7,'P-Parametri'!$C$8)))+(IF(($A30*(1-'P-Parametri'!$B$19))<='P-Parametri'!$C$12,0,IF(($A30*(1-'P-Parametri'!$B$19))<='P-Parametri'!$B$6,'P-Parametri'!$C$13/'P-Parametri'!$D$13,IF(($A30*(1-'P-Parametri'!$B$19))<='P-Parametri'!$B$7,'P-Parametri'!$B$14/'P-Parametri'!$C$14,0))))+(IF(AND(($A30*(1-'P-Parametri'!$B$19))>'P-Parametri'!$D$15,($A30*(1-'P-Parametri'!$B$19))<'P-Parametri'!$E$15),'P-Parametri'!$B$15/('P-Parametri'!$E$15-'P-Parametri'!$D$15),0))+'P-Parametri'!$B$20) -> 0.40205108 | O30: =M30-N30 -> -1.8873791e-15
A31: =26500 -> 26500 | B31: ='P-Parametri'!$B$19*$A31 -> 2435.35 | C31: =$A31-B31 -> 24064.65 | D31: =IF($C31<='P-Parametri'!$B$6,'P-Parametri'!$C$6*$C31,IF($C31<='P-Parametri'!$B$7,'P-Parametri'!$B$9+'P-Parametri'!$C$7*($C31-'P-Parametri'!$B$6),'P-Parametri'!$B$10+'P-Parametri'!$C$8*($C31-'P-Parametri'!$B$7))) -> 5534.8695 | E31: =IF($C31<='P-Parametri'!$C$12,'P-Parametri'!$B$12,IF($C31<='P-Parametri'!$B$6,'P-Parametri'!$B$13+'P-Parametri'!$C$13*('P-Parametri'!$B$6-$C31)/'P-Parametri'!$D$13,IF($C31<='P-Parametri'!$B$7,'P-Parametri'!$B$14*('P-Parametri'!$B$7-$C31)/'P-Parametri'!$C$14,0))) -> 2270.2359 | F31: =IF($C31<='P-Parametri'!$C$15,0,IF($C31<='P-Parametri'!$D$15,'P-Parametri'!$B$15,IF($C31<'P-Parametri'!$E$15,'P-Parametri'!$B$15*('P-Parametri'!$E$15-$C31)/('P-Parametri'!$E$15-'P-Parametri'!$D$15),0))) -> 1000 | G31: =IF($C31>'P-Parametri'!$D$18,0,IF($C31<='P-Parametri'!$B$18,'P-Parametri'!$B$17*$C31,IF($C31<='P-Parametri'!$C$18,'P-Parametri'!$C$17*$C31,'P-Parametri'!$D$17*$C31))) -> 0 | H31: =IF(AND($C31<='P-Parametri'!$C$16,D31>E31-'P-Parametri'!$D$16),'P-Parametri'!$B$16,0) -> 0 | I31: =MAX(0,D31-E31-F31) -> 2264.6336 | J31: =IF(I31>0,'P-Parametri'!$B$20*$C31,0) -> 481.293 | K31: =$C31-I31-J31+H31+G31 -> 21318.723 | L31: =K31/$A31 -> 0.80448013 | M31: =1-(K33-K31)/1000 -> 0.40205108 | N31: ='P-Parametri'!$B$19+(1-'P-Parametri'!$B$19)*((IF(($A31*(1-'P-Parametri'!$B$19))<='P-Parametri'!$B$6,'P-Parametri'!$C$6,IF(($A31*(1-'P-Parametri'!$B$19))<='P-Parametri'!$B$7,'P-Parametri'!$C$7,'P-Parametri'!$C$8)))+(IF(($A31*(1-'P-Parametri'!$B$19))<='P-Parametri'!$C$12,0,IF(($A31*(1-'P-Parametri'!$B$19))<='P-Parametri'!$B$6,'P-Parametri'!$C$13/'P-Parametri'!$D$13,IF(($A31*(1-'P-Parametri'!$B$19))<='P-Parametri'!$B$7,'P-Parametri'!$B$14/'P-Parametri'!$C$14,0))))+(IF(AND(($A31*(1-'P-Parametri'!$B$19))>'P-Parametri'!$D$15,($A31*(1-'P-Parametri'!$B$19))<'P-Parametri'!$E$15),'P-Parametri'!$B$15/('P-Parametri'!$E$15-'P-Parametri'!$D$15),0))+'P-Parametri'!$B$20) -> 0.40205108 | O31: =M31-N31 -> 1.6653345e-15
A32: =27000 -> 27000 | B32: ='P-Parametri'!$B$19*$A32 -> 2481.3 | C32: =$A32-B32 -> 24518.7 | D32: =IF($C32<='P-Parametri'!$B$6,'P-Parametri'!$C$6*$C32,IF($C32<='P-Parametri'!$B$7,'P-Parametri'!$B$9+'P-Parametri'!$C$7*($C32-'P-Parametri'!$B$6),'P-Parametri'!$B$10+'P-Parametri'!$C$8*($C32-'P-Parametri'!$B$7))) -> 5639.301 | E32: =IF($C32<='P-Parametri'!$C$12,'P-Parametri'!$B$12,IF($C32<='P-Parametri'!$B$6,'P-Parametri'!$B$13+'P-Parametri'!$C$13*('P-Parametri'!$B$6-$C32)/'P-Parametri'!$D$13,IF($C32<='P-Parametri'!$B$7,'P-Parametri'!$B$14*('P-Parametri'!$B$7-$C32)/'P-Parametri'!$C$14,0))) -> 2228.6728 | F32: =IF($C32<='P-Parametri'!$C$15,0,IF($C32<='P-Parametri'!$D$15,'P-Parametri'!$B$15,IF($C32<'P-Parametri'!$E$15,'P-Parametri'!$B$15*('P-Parametri'!$E$15-$C32)/('P-Parametri'!$E$15-'P-Parametri'!$D$15),0))) -> 1000 | G32: =IF($C32>'P-Parametri'!$D$18,0,IF($C32<='P-Parametri'!$B$18,'P-Parametri'!$B$17*$C32,IF($C32<='P-Parametri'!$C$18,'P-Parametri'!$C$17*$C32,'P-Parametri'!$D$17*$C32))) -> 0 | H32: =IF(AND($C32<='P-Parametri'!$C$16,D32>E32-'P-Parametri'!$D$16),'P-Parametri'!$B$16,0) -> 0 | I32: =MAX(0,D32-E32-F32) -> 2410.6282 | J32: =IF(I32>0,'P-Parametri'!$B$20*$C32,0) -> 490.374 | K32: =$C32-I32-J32+H32+G32 -> 21617.698 | L32: =K32/$A32 -> 0.80065548 | M32: =1-(K34-K32)/1000 -> 0.40205108 | N32: ='P-Parametri'!$B$19+(1-'P-Parametri'!$B$19)*((IF(($A32*(1-'P-Parametri'!$B$19))<='P-Parametri'!$B$6,'P-Parametri'!$C$6,IF(($A32*(1-'P-Parametri'!$B$19))<='P-Parametri'!$B$7,'P-Parametri'!$C$7,'P-Parametri'!$C$8)))+(IF(($A32*(1-'P-Parametri'!$B$19))<='P-Parametri'!$C$12,0,IF(($A32*(1-'P-Parametri'!$B$19))<='P-Parametri'!$B$6,'P-Parametri'!$C$13/'P-Parametri'!$D$13,IF(($A32*(1-'P-Parametri'!$B$19))<='P-Parametri'!$B$7,'P-Parametri'!$B$14/'P-Parametri'!$C$14,0))))+(IF(AND(($A32*(1-'P-Parametri'!$B$19))>'P-Parametri'!$D$15,($A32*(1-'P-Parametri'!$B$19))<'P-Parametri'!$E$15),'P-Parametri'!$B$15/('P-Parametri'!$E$15-'P-Parametri'!$D$15),0))+'P-Parametri'!$B$20) -> 0.40205108 | O32: =M32-N32 -> -1.8873791e-15
A33: =27500 -> 27500 | B33: ='P-Parametri'!$B$19*$A33 -> 2527.25 | C33: =$A33-B33 -> 24972.75 | D33: =IF($C33<='P-Parametri'!$B$6,'P-Parametri'!$C$6*$C33,IF($C33<='P-Parametri'!$B$7,'P-Parametri'!$B$9+'P-Parametri'!$C$7*($C33-'P-Parametri'!$B$6),'P-Parametri'!$B$10+'P-Parametri'!$C$8*($C33-'P-Parametri'!$B$7))) -> 5743.7325 | E33: =IF($C33<='P-Parametri'!$C$12,'P-Parametri'!$B$12,IF($C33<='P-Parametri'!$B$6,'P-Parametri'!$B$13+'P-Parametri'!$C$13*('P-Parametri'!$B$6-$C33)/'P-Parametri'!$D$13,IF($C33<='P-Parametri'!$B$7,'P-Parametri'!$B$14*('P-Parametri'!$B$7-$C33)/'P-Parametri'!$C$14,0))) -> 2187.1098 | F33: =IF($C33<='P-Parametri'!$C$15,0,IF($C33<='P-Parametri'!$D$15,'P-Parametri'!$B$15,IF($C33<'P-Parametri'!$E$15,'P-Parametri'!$B$15*('P-Parametri'!$E$15-$C33)/('P-Parametri'!$E$15-'P-Parametri'!$D$15),0))) -> 1000 | G33: =IF($C33>'P-Parametri'!$D$18,0,IF($C33<='P-Parametri'!$B$18,'P-Parametri'!$B$17*$C33,IF($C33<='P-Parametri'!$C$18,'P-Parametri'!$C$17*$C33,'P-Parametri'!$D$17*$C33))) -> 0 | H33: =IF(AND($C33<='P-Parametri'!$C$16,D33>E33-'P-Parametri'!$D$16),'P-Parametri'!$B$16,0) -> 0 | I33: =MAX(0,D33-E33-F33) -> 2556.6227 | J33: =IF(I33>0,'P-Parametri'!$B$20*$C33,0) -> 499.455 | K33: =$C33-I33-J33+H33+G33 -> 21916.672 | L33: =K33/$A33 -> 0.7969699 | M33: =1-(K35-K33)/1000 -> 0.40205108 | N33: ='P-Parametri'!$B$19+(1-'P-Parametri'!$B$19)*((IF(($A33*(1-'P-Parametri'!$B$19))<='P-Parametri'!$B$6,'P-Parametri'!$C$6,IF(($A33*(1-'P-Parametri'!$B$19))<='P-Parametri'!$B$7,'P-Parametri'!$C$7,'P-Parametri'!$C$8)))+(IF(($A33*(1-'P-Parametri'!$B$19))<='P-Parametri'!$C$12,0,IF(($A33*(1-'P-Parametri'!$B$19))<='P-Parametri'!$B$6,'P-Parametri'!$C$13/'P-Parametri'!$D$13,IF(($A33*(1-'P-Parametri'!$B$19))<='P-Parametri'!$B$7,'P-Parametri'!$B$14/'P-Parametri'!$C$14,0))))+(IF(AND(($A33*(1-'P-Parametri'!$B$19))>'P-Parametri'!$D$15,($A33*(1-'P-Parametri'!$B$19))<'P-Parametri'!$E$15),'P-Parametri'!$B$15/('P-Parametri'!$E$15-'P-Parametri'!$D$15),0))+'P-Parametri'!$B$20) -> 0.40205108 | O33: =M33-N33 -> -1.8873791e-15
A34: =28000 -> 28000 | B34: ='P-Parametri'!$B$19*$A34 -> 2573.2 | C34: =$A34-B34 -> 25426.8 | D34: =IF($C34<='P-Parametri'!$B$6,'P-Parametri'!$C$6*$C34,IF($C34<='P-Parametri'!$B$7,'P-Parametri'!$B$9+'P-Parametri'!$C$7*($C34-'P-Parametri'!$B$6),'P-Parametri'!$B$10+'P-Parametri'!$C$8*($C34-'P-Parametri'!$B$7))) -> 5848.164 | E34: =IF($C34<='P-Parametri'!$C$12,'P-Parametri'!$B$12,IF($C34<='P-Parametri'!$B$6,'P-Parametri'!$B$13+'P-Parametri'!$C$13*('P-Parametri'!$B$6-$C34)/'P-Parametri'!$D$13,IF($C34<='P-Parametri'!$B$7,'P-Parametri'!$B$14*('P-Parametri'!$B$7-$C34)/'P-Parametri'!$C$14,0))) -> 2145.5468 | F34: =IF($C34<='P-Parametri'!$C$15,0,IF($C34<='P-Parametri'!$D$15,'P-Parametri'!$B$15,IF($C34<'P-Parametri'!$E$15,'P-Parametri'!$B$15*('P-Parametri'!$E$15-$C34)/('P-Parametri'!$E$15-'P-Parametri'!$D$15),0))) -> 1000 | G34: =IF($C34>'P-Parametri'!$D$18,0,IF($C34<='P-Parametri'!$B$18,'P-Parametri'!$B$17*$C34,IF($C34<='P-Parametri'!$C$18,'P-Parametri'!$C$17*$C34,'P-Parametri'!$D$17*$C34))) -> 0 | H34: =IF(AND($C34<='P-Parametri'!$C$16,D34>E34-'P-Parametri'!$D$16),'P-Parametri'!$B$16,0) -> 0 | I34: =MAX(0,D34-E34-F34) -> 2702.6172 | J34: =IF(I34>0,'P-Parametri'!$B$20*$C34,0) -> 508.536 | K34: =$C34-I34-J34+H34+G34 -> 22215.647 | L34: =K34/$A34 -> 0.79341596 | M34: =1-(K36-K34)/1000 -> 0.40205108 | N34: ='P-Parametri'!$B$19+(1-'P-Parametri'!$B$19)*((IF(($A34*(1-'P-Parametri'!$B$19))<='P-Parametri'!$B$6,'P-Parametri'!$C$6,IF(($A34*(1-'P-Parametri'!$B$19))<='P-Parametri'!$B$7,'P-Parametri'!$C$7,'P-Parametri'!$C$8)))+(IF(($A34*(1-'P-Parametri'!$B$19))<='P-Parametri'!$C$12,0,IF(($A34*(1-'P-Parametri'!$B$19))<='P-Parametri'!$B$6,'P-Parametri'!$C$13/'P-Parametri'!$D$13,IF(($A34*(1-'P-Parametri'!$B$19))<='P-Parametri'!$B$7,'P-Parametri'!$B$14/'P-Parametri'!$C$14,0))))+(IF(AND(($A34*(1-'P-Parametri'!$B$19))>'P-Parametri'!$D$15,($A34*(1-'P-Parametri'!$B$19))<'P-Parametri'!$E$15),'P-Parametri'!$B$15/('P-Parametri'!$E$15-'P-Parametri'!$D$15),0))+'P-Parametri'!$B$20) -> 0.40205108 | O34: =M34-N34 -> 1.6653345e-15
A35: =28500 -> 28500 | B35: ='P-Parametri'!$B$19*$A35 -> 2619.15 | C35: =$A35-B35 -> 25880.85 | D35: =IF($C35<='P-Parametri'!$B$6,'P-Parametri'!$C$6*$C35,IF($C35<='P-Parametri'!$B$7,'P-Parametri'!$B$9+'P-Parametri'!$C$7*($C35-'P-Parametri'!$B$6),'P-Parametri'!$B$10+'P-Parametri'!$C$8*($C35-'P-Parametri'!$B$7))) -> 5952.5955 | E35: =IF($C35<='P-Parametri'!$C$12,'P-Parametri'!$B$12,IF($C35<='P-Parametri'!$B$6,'P-Parametri'!$B$13+'P-Parametri'!$C$13*('P-Parametri'!$B$6-$C35)/'P-Parametri'!$D$13,IF($C35<='P-Parametri'!$B$7,'P-Parametri'!$B$14*('P-Parametri'!$B$7-$C35)/'P-Parametri'!$C$14,0))) -> 2103.9837 | F35: =IF($C35<='P-Parametri'!$C$15,0,IF($C35<='P-Parametri'!$D$15,'P-Parametri'!$B$15,IF($C35<'P-Parametri'!$E$15,'P-Parametri'!$B$15*('P-Parametri'!$E$15-$C35)/('P-Parametri'!$E$15-'P-Parametri'!$D$15),0))) -> 1000 | G35: =IF($C35>'P-Parametri'!$D$18,0,IF($C35<='P-Parametri'!$B$18,'P-Parametri'!$B$17*$C35,IF($C35<='P-Parametri'!$C$18,'P-Parametri'!$C$17*$C35,'P-Parametri'!$D$17*$C35))) -> 0 | H35: =IF(AND($C35<='P-Parametri'!$C$16,D35>E35-'P-Parametri'!$D$16),'P-Parametri'!$B$16,0) -> 0 | I35: =MAX(0,D35-E35-F35) -> 2848.6118 | J35: =IF(I35>0,'P-Parametri'!$B$20*$C35,0) -> 517.617 | K35: =$C35-I35-J35+H35+G35 -> 22514.621 | L35: =K35/$A35 -> 0.78998671 | M35: =1-(K37-K35)/1000 -> 0.40205108 | N35: ='P-Parametri'!$B$19+(1-'P-Parametri'!$B$19)*((IF(($A35*(1-'P-Parametri'!$B$19))<='P-Parametri'!$B$6,'P-Parametri'!$C$6,IF(($A35*(1-'P-Parametri'!$B$19))<='P-Parametri'!$B$7,'P-Parametri'!$C$7,'P-Parametri'!$C$8)))+(IF(($A35*(1-'P-Parametri'!$B$19))<='P-Parametri'!$C$12,0,IF(($A35*(1-'P-Parametri'!$B$19))<='P-Parametri'!$B$6,'P-Parametri'!$C$13/'P-Parametri'!$D$13,IF(($A35*(1-'P-Parametri'!$B$19))<='P-Parametri'!$B$7,'P-Parametri'!$B$14/'P-Parametri'!$C$14,0))))+(IF(AND(($A35*(1-'P-Parametri'!$B$19))>'P-Parametri'!$D$15,($A35*(1-'P-Parametri'!$B$19))<'P-Parametri'!$E$15),'P-Parametri'!$B$15/('P-Parametri'!$E$15-'P-Parametri'!$D$15),0))+'P-Parametri'!$B$20) -> 0.40205108 | O35: =M35-N35 -> -1.8873791e-15
A36: =29000 -> 29000 | B36: ='P-Parametri'!$B$19*$A36 -> 2665.1 | C36: =$A36-B36 -> 26334.9 | D36: =IF($C36<='P-Parametri'!$B$6,'P-Parametri'!$C$6*$C36,IF($C36<='P-Parametri'!$B$7,'P-Parametri'!$B$9+'P-Parametri'!$C$7*($C36-'P-Parametri'!$B$6),'P-Parametri'!$B$10+'P-Parametri'!$C$8*($C36-'P-Parametri'!$B$7))) -> 6057.027 | E36: =IF($C36<='P-Parametri'!$C$12,'P-Parametri'!$B$12,IF($C36<='P-Parametri'!$B$6,'P-Parametri'!$B$13+'P-Parametri'!$C$13*('P-Parametri'!$B$6-$C36)/'P-Parametri'!$D$13,IF($C36<='P-Parametri'!$B$7,'P-Parametri'!$B$14*('P-Parametri'!$B$7-$C36)/'P-Parametri'!$C$14,0))) -> 2062.4207 | F36: =IF($C36<='P-Parametri'!$C$15,0,IF($C36<='P-Parametri'!$D$15,'P-Parametri'!$B$15,IF($C36<'P-Parametri'!$E$15,'P-Parametri'!$B$15*('P-Parametri'!$E$15-$C36)/('P-Parametri'!$E$15-'P-Parametri'!$D$15),0))) -> 1000 | G36: =IF($C36>'P-Parametri'!$D$18,0,IF($C36<='P-Parametri'!$B$18,'P-Parametri'!$B$17*$C36,IF($C36<='P-Parametri'!$C$18,'P-Parametri'!$C$17*$C36,'P-Parametri'!$D$17*$C36))) -> 0 | H36: =IF(AND($C36<='P-Parametri'!$C$16,D36>E36-'P-Parametri'!$D$16),'P-Parametri'!$B$16,0) -> 0 | I36: =MAX(0,D36-E36-F36) -> 2994.6063 | J36: =IF(I36>0,'P-Parametri'!$B$20*$C36,0) -> 526.698 | K36: =$C36-I36-J36+H36+G36 -> 22813.596 | L36: =K36/$A36 -> 0.78667571 | M36: =1-(K38-K36)/1000 -> 0.40205108 | N36: ='P-Parametri'!$B$19+(1-'P-Parametri'!$B$19)*((IF(($A36*(1-'P-Parametri'!$B$19))<='P-Parametri'!$B$6,'P-Parametri'!$C$6,IF(($A36*(1-'P-Parametri'!$B$19))<='P-Parametri'!$B$7,'P-Parametri'!$C$7,'P-Parametri'!$C$8)))+(IF(($A36*(1-'P-Parametri'!$B$19))<='P-Parametri'!$C$12,0,IF(($A36*(1-'P-Parametri'!$B$19))<='P-Parametri'!$B$6,'P-Parametri'!$C$13/'P-Parametri'!$D$13,IF(($A36*(1-'P-Parametri'!$B$19))<='P-Parametri'!$B$7,'P-Parametri'!$B$14/'P-Parametri'!$C$14,0))))+(IF(AND(($A36*(1-'P-Parametri'!$B$19))>'P-Parametri'!$D$15,($A36*(1-'P-Parametri'!$B$19))<'P-Parametri'!$E$15),'P-Parametri'!$B$15/('P-Parametri'!$E$15-'P-Parametri'!$D$15),0))+'P-Parametri'!$B$20) -> 0.40205108 | O36: =M36-N36 -> 1.6653345e-15
A37: =29500 -> 29500 | B37: ='P-Parametri'!$B$19*$A37 -> 2711.05 | C37: =$A37-B37 -> 26788.95 | D37: =IF($C37<='P-Parametri'!$B$6,'P-Parametri'!$C$6*$C37,IF($C37<='P-Parametri'!$B$7,'P-Parametri'!$B$9+'P-Parametri'!$C$7*($C37-'P-Parametri'!$B$6),'P-Parametri'!$B$10+'P-Parametri'!$C$8*($C37-'P-Parametri'!$B$7))) -> 6161.4585 | E37: =IF($C37<='P-Parametri'!$C$12,'P-Parametri'!$B$12,IF($C37<='P-Parametri'!$B$6,'P-Parametri'!$B$13+'P-Parametri'!$C$13*('P-Parametri'!$B$6-$C37)/'P-Parametri'!$D$13,IF($C37<='P-Parametri'!$B$7,'P-Parametri'!$B$14*('P-Parametri'!$B$7-$C37)/'P-Parametri'!$C$14,0))) -> 2020.8577 | F37: =IF($C37<='P-Parametri'!$C$15,0,IF($C37<='P-Parametri'!$D$15,'P-Parametri'!$B$15,IF($C37<'P-Parametri'!$E$15,'P-Parametri'!$B$15*('P-Parametri'!$E$15-$C37)/('P-Parametri'!$E$15-'P-Parametri'!$D$15),0))) -> 1000 | G37: =IF($C37>'P-Parametri'!$D$18,0,IF($C37<='P-Parametri'!$B$18,'P-Parametri'!$B$17*$C37,IF($C37<='P-Parametri'!$C$18,'P-Parametri'!$C$17*$C37,'P-Parametri'!$D$17*$C37))) -> 0 | H37: =IF(AND($C37<='P-Parametri'!$C$16,D37>E37-'P-Parametri'!$D$16),'P-Parametri'!$B$16,0) -> 0 | I37: =MAX(0,D37-E37-F37) -> 3140.6008 | J37: =IF(I37>0,'P-Parametri'!$B$20*$C37,0) -> 535.779 | K37: =$C37-I37-J37+H37+G37 -> 23112.57 | L37: =K37/$A37 -> 0.78347695 | M37: =1-(K39-K37)/1000 -> 0.40205108 | N37: ='P-Parametri'!$B$19+(1-'P-Parametri'!$B$19)*((IF(($A37*(1-'P-Parametri'!$B$19))<='P-Parametri'!$B$6,'P-Parametri'!$C$6,IF(($A37*(1-'P-Parametri'!$B$19))<='P-Parametri'!$B$7,'P-Parametri'!$C$7,'P-Parametri'!$C$8)))+(IF(($A37*(1-'P-Parametri'!$B$19))<='P-Parametri'!$C$12,0,IF(($A37*(1-'P-Parametri'!$B$19))<='P-Parametri'!$B$6,'P-Parametri'!$C$13/'P-Parametri'!$D$13,IF(($A37*(1-'P-Parametri'!$B$19))<='P-Parametri'!$B$7,'P-Parametri'!$B$14/'P-Parametri'!$C$14,0))))+(IF(AND(($A37*(1-'P-Parametri'!$B$19))>'P-Parametri'!$D$15,($A37*(1-'P-Parametri'!$B$19))<'P-Parametri'!$E$15),'P-Parametri'!$B$15/('P-Parametri'!$E$15-'P-Parametri'!$D$15),0))+'P-Parametri'!$B$20) -> 0.40205108 | O37: =M37-N37 -> 1.6653345e-15
A38: =30000 -> 30000 | B38: ='P-Parametri'!$B$19*$A38 -> 2757 | C38: =$A38-B38 -> 27243 | D38: =IF($C38<='P-Parametri'!$B$6,'P-Parametri'!$C$6*$C38,IF($C38<='P-Parametri'!$B$7,'P-Parametri'!$B$9+'P-Parametri'!$C$7*($C38-'P-Parametri'!$B$6),'P-Parametri'!$B$10+'P-Parametri'!$C$8*($C38-'P-Parametri'!$B$7))) -> 6265.89 | E38: =IF($C38<='P-Parametri'!$C$12,'P-Parametri'!$B$12,IF($C38<='P-Parametri'!$B$6,'P-Parametri'!$B$13+'P-Parametri'!$C$13*('P-Parametri'!$B$6-$C38)/'P-Parametri'!$D$13,IF($C38<='P-Parametri'!$B$7,'P-Parametri'!$B$14*('P-Parametri'!$B$7-$C38)/'P-Parametri'!$C$14,0))) -> 1979.2946 | F38: =IF($C38<='P-Parametri'!$C$15,0,IF($C38<='P-Parametri'!$D$15,'P-Parametri'!$B$15,IF($C38<'P-Parametri'!$E$15,'P-Parametri'!$B$15*('P-Parametri'!$E$15-$C38)/('P-Parametri'!$E$15-'P-Parametri'!$D$15),0))) -> 1000 | G38: =IF($C38>'P-Parametri'!$D$18,0,IF($C38<='P-Parametri'!$B$18,'P-Parametri'!$B$17*$C38,IF($C38<='P-Parametri'!$C$18,'P-Parametri'!$C$17*$C38,'P-Parametri'!$D$17*$C38))) -> 0 | H38: =IF(AND($C38<='P-Parametri'!$C$16,D38>E38-'P-Parametri'!$D$16),'P-Parametri'!$B$16,0) -> 0 | I38: =MAX(0,D38-E38-F38) -> 3286.5954 | J38: =IF(I38>0,'P-Parametri'!$B$20*$C38,0) -> 544.86 | K38: =$C38-I38-J38+H38+G38 -> 23411.545 | L38: =K38/$A38 -> 0.78038482 | M38: =1-(K40-K38)/1000 -> 0.41644784 | N38: ='P-Parametri'!$B$19+(1-'P-Parametri'!$B$19)*((IF(($A38*(1-'P-Parametri'!$B$19))<='P-Parametri'!$B$6,'P-Parametri'!$C$6,IF(($A38*(1-'P-Parametri'!$B$19))<='P-Parametri'!$B$7,'P-Parametri'!$C$7,'P-Parametri'!$C$8)))+(IF(($A38*(1-'P-Parametri'!$B$19))<='P-Parametri'!$C$12,0,IF(($A38*(1-'P-Parametri'!$B$19))<='P-Parametri'!$B$6,'P-Parametri'!$C$13/'P-Parametri'!$D$13,IF(($A38*(1-'P-Parametri'!$B$19))<='P-Parametri'!$B$7,'P-Parametri'!$B$14/'P-Parametri'!$C$14,0))))+(IF(AND(($A38*(1-'P-Parametri'!$B$19))>'P-Parametri'!$D$15,($A38*(1-'P-Parametri'!$B$19))<'P-Parametri'!$E$15),'P-Parametri'!$B$15/('P-Parametri'!$E$15-'P-Parametri'!$D$15),0))+'P-Parametri'!$B$20) -> 0.40205108 | O38: =M38-N38 -> 0.014396766
A39: =30500 -> 30500 | B39: ='P-Parametri'!$B$19*$A39 -> 2802.95 | C39: =$A39-B39 -> 27697.05 | D39: =IF($C39<='P-Parametri'!$B$6,'P-Parametri'!$C$6*$C39,IF($C39<='P-Parametri'!$B$7,'P-Parametri'!$B$9+'P-Parametri'!$C$7*($C39-'P-Parametri'!$B$6),'P-Parametri'!$B$10+'P-Parametri'!$C$8*($C39-'P-Parametri'!$B$7))) -> 6370.3215 | E39: =IF($C39<='P-Parametri'!$C$12,'P-Parametri'!$B$12,IF($C39<='P-Parametri'!$B$6,'P-Parametri'!$B$13+'P-Parametri'!$C$13*('P-Parametri'!$B$6-$C39)/'P-Parametri'!$D$13,IF($C39<='P-Parametri'!$B$7,'P-Parametri'!$B$14*('P-Parametri'!$B$7-$C39)/'P-Parametri'!$C$14,0))) -> 1937.7316 | F39: =IF($C39<='P-Parametri'!$C$15,0,IF($C39<='P-Parametri'!$D$15,'P-Parametri'!$B$15,IF($C39<'P-Parametri'!$E$15,'P-Parametri'!$B$15*('P-Parametri'!$E$15-$C39)/('P-Parametri'!$E$15-'P-Parametri'!$D$15),0))) -> 1000 | G39: =IF($C39>'P-Parametri'!$D$18,0,IF($C39<='P-Parametri'!$B$18,'P-Parametri'!$B$17*$C39,IF($C39<='P-Parametri'!$C$18,'P-Parametri'!$C$17*$C39,'P-Parametri'!$D$17*$C39))) -> 0 | H39: =IF(AND($C39<='P-Parametri'!$C$16,D39>E39-'P-Parametri'!$D$16),'P-Parametri'!$B$16,0) -> 0 | I39: =MAX(0,D39-E39-F39) -> 3432.5899 | J39: =IF(I39>0,'P-Parametri'!$B$20*$C39,0) -> 553.941 | K39: =$C39-I39-J39+H39+G39 -> 23710.519 | L39: =K39/$A39 -> 0.77739407 | M39: =1-(K41-K39)/1000 -> 0.4597096 | N39: ='P-Parametri'!$B$19+(1-'P-Parametri'!$B$19)*((IF(($A39*(1-'P-Parametri'!$B$19))<='P-Parametri'!$B$6,'P-Parametri'!$C$6,IF(($A39*(1-'P-Parametri'!$B$19))<='P-Parametri'!$B$7,'P-Parametri'!$C$7,'P-Parametri'!$C$8)))+(IF(($A39*(1-'P-Parametri'!$B$19))<='P-Parametri'!$C$12,0,IF(($A39*(1-'P-Parametri'!$B$19))<='P-Parametri'!$B$6,'P-Parametri'!$C$13/'P-Parametri'!$D$13,IF(($A39*(1-'P-Parametri'!$B$19))<='P-Parametri'!$B$7,'P-Parametri'!$B$14/'P-Parametri'!$C$14,0))))+(IF(AND(($A39*(1-'P-Parametri'!$B$19))>'P-Parametri'!$D$15,($A39*(1-'P-Parametri'!$B$19))<'P-Parametri'!$E$15),'P-Parametri'!$B$15/('P-Parametri'!$E$15-'P-Parametri'!$D$15),0))+'P-Parametri'!$B$20) -> 0.40205108 | O39: =M39-N39 -> 0.057658523
A40: =31000 -> 31000 | B40: ='P-Parametri'!$B$19*$A40 -> 2848.9 | C40: =$A40-B40 -> 28151.1 | D40: =IF($C40<='P-Parametri'!$B$6,'P-Parametri'!$C$6*$C40,IF($C40<='P-Parametri'!$B$7,'P-Parametri'!$B$9+'P-Parametri'!$C$7*($C40-'P-Parametri'!$B$6),'P-Parametri'!$B$10+'P-Parametri'!$C$8*($C40-'P-Parametri'!$B$7))) -> 6489.863 | E40: =IF($C40<='P-Parametri'!$C$12,'P-Parametri'!$B$12,IF($C40<='P-Parametri'!$B$6,'P-Parametri'!$B$13+'P-Parametri'!$C$13*('P-Parametri'!$B$6-$C40)/'P-Parametri'!$D$13,IF($C40<='P-Parametri'!$B$7,'P-Parametri'!$B$14*('P-Parametri'!$B$7-$C40)/'P-Parametri'!$C$14,0))) -> 1896.8818 | F40: =IF($C40<='P-Parametri'!$C$15,0,IF($C40<='P-Parametri'!$D$15,'P-Parametri'!$B$15,IF($C40<'P-Parametri'!$E$15,'P-Parametri'!$B$15*('P-Parametri'!$E$15-$C40)/('P-Parametri'!$E$15-'P-Parametri'!$D$15),0))) -> 1000 | G40: =IF($C40>'P-Parametri'!$D$18,0,IF($C40<='P-Parametri'!$B$18,'P-Parametri'!$B$17*$C40,IF($C40<='P-Parametri'!$C$18,'P-Parametri'!$C$17*$C40,'P-Parametri'!$D$17*$C40))) -> 0 | H40: =IF(AND($C40<='P-Parametri'!$C$16,D40>E40-'P-Parametri'!$D$16),'P-Parametri'!$B$16,0) -> 0 | I40: =MAX(0,D40-E40-F40) -> 3592.9812 | J40: =IF(I40>0,'P-Parametri'!$B$20*$C40,0) -> 563.022 | K40: =$C40-I40-J40+H40+G40 -> 23995.097 | L40: =K40/$A40 -> 0.77403538 | M40: =1-(K42-K40)/1000 -> 0.48857459 | N40: ='P-Parametri'!$B$19+(1-'P-Parametri'!$B$19)*((IF(($A40*(1-'P-Parametri'!$B$19))<='P-Parametri'!$B$6,'P-Parametri'!$C$6,IF(($A40*(1-'P-Parametri'!$B$19))<='P-Parametri'!$B$7,'P-Parametri'!$C$7,'P-Parametri'!$C$8)))+(IF(($A40*(1-'P-Parametri'!$B$19))<='P-Parametri'!$C$12,0,IF(($A40*(1-'P-Parametri'!$B$19))<='P-Parametri'!$B$6,'P-Parametri'!$C$13/'P-Parametri'!$D$13,IF(($A40*(1-'P-Parametri'!$B$19))<='P-Parametri'!$B$7,'P-Parametri'!$B$14/'P-Parametri'!$C$14,0))))+(IF(AND(($A40*(1-'P-Parametri'!$B$19))>'P-Parametri'!$D$15,($A40*(1-'P-Parametri'!$B$19))<'P-Parametri'!$E$15),'P-Parametri'!$B$15/('P-Parametri'!$E$15-'P-Parametri'!$D$15),0))+'P-Parametri'!$B$20) -> 0.48857459 | O40: =M40-N40 -> -3.5527137e-15
A41: =31500 -> 31500 | B41: ='P-Parametri'!$B$19*$A41 -> 2894.85 | C41: =$A41-B41 -> 28605.15 | D41: =IF($C41<='P-Parametri'!$B$6,'P-Parametri'!$C$6*$C41,IF($C41<='P-Parametri'!$B$7,'P-Parametri'!$B$9+'P-Parametri'!$C$7*($C41-'P-Parametri'!$B$6),'P-Parametri'!$B$10+'P-Parametri'!$C$8*($C41-'P-Parametri'!$B$7))) -> 6639.6995 | E41: =IF($C41<='P-Parametri'!$C$12,'P-Parametri'!$B$12,IF($C41<='P-Parametri'!$B$6,'P-Parametri'!$B$13+'P-Parametri'!$C$13*('P-Parametri'!$B$6-$C41)/'P-Parametri'!$D$13,IF($C41<='P-Parametri'!$B$7,'P-Parametri'!$B$14*('P-Parametri'!$B$7-$C41)/'P-Parametri'!$C$14,0))) -> 1857.462 | F41: =IF($C41<='P-Parametri'!$C$15,0,IF($C41<='P-Parametri'!$D$15,'P-Parametri'!$B$15,IF($C41<'P-Parametri'!$E$15,'P-Parametri'!$B$15*('P-Parametri'!$E$15-$C41)/('P-Parametri'!$E$15-'P-Parametri'!$D$15),0))) -> 1000 | G41: =IF($C41>'P-Parametri'!$D$18,0,IF($C41<='P-Parametri'!$B$18,'P-Parametri'!$B$17*$C41,IF($C41<='P-Parametri'!$C$18,'P-Parametri'!$C$17*$C41,'P-Parametri'!$D$17*$C41))) -> 0 | H41: =IF(AND($C41<='P-Parametri'!$C$16,D41>E41-'P-Parametri'!$D$16),'P-Parametri'!$B$16,0) -> 0 | I41: =MAX(0,D41-E41-F41) -> 3782.2375 | J41: =IF(I41>0,'P-Parametri'!$B$20*$C41,0) -> 572.103 | K41: =$C41-I41-J41+H41+G41 -> 24250.809 | L41: =K41/$A41 -> 0.76986697 | M41: =1-(K43-K41)/1000 -> 0.48857459 | N41: ='P-Parametri'!$B$19+(1-'P-Parametri'!$B$19)*((IF(($A41*(1-'P-Parametri'!$B$19))<='P-Parametri'!$B$6,'P-Parametri'!$C$6,IF(($A41*(1-'P-Parametri'!$B$19))<='P-Parametri'!$B$7,'P-Parametri'!$C$7,'P-Parametri'!$C$8)))+(IF(($A41*(1-'P-Parametri'!$B$19))<='P-Parametri'!$C$12,0,IF(($A41*(1-'P-Parametri'!$B$19))<='P-Parametri'!$B$6,'P-Parametri'!$C$13/'P-Parametri'!$D$13,IF(($A41*(1-'P-Parametri'!$B$19))<='P-Parametri'!$B$7,'P-Parametri'!$B$14/'P-Parametri'!$C$14,0))))+(IF(AND(($A41*(1-'P-Parametri'!$B$19))>'P-Parametri'!$D$15,($A41*(1-'P-Parametri'!$B$19))<'P-Parametri'!$E$15),'P-Parametri'!$B$15/('P-Parametri'!$E$15-'P-Parametri'!$D$15),0))+'P-Parametri'!$B$20) -> 0.48857459 | O41: =M41-N41 -> 3.7747583e-15
A42: =32000 -> 32000 | B42: ='P-Parametri'!$B$19*$A42 -> 2940.8 | C42: =$A42-B42 -> 29059.2 | D42: =IF($C42<='P-Parametri'!$B$6,'P-Parametri'!$C$6*$C42,IF($C42<='P-Parametri'!$B$7,'P-Parametri'!$B$9+'P-Parametri'!$C$7*($C42-'P-Parametri'!$B$6),'P-Parametri'!$B$10+'P-Parametri'!$C$8*($C42-'P-Parametri'!$B$7))) -> 6789.536 | E42: =IF($C42<='P-Parametri'!$C$12,'P-Parametri'!$B$12,IF($C42<='P-Parametri'!$B$6,'P-Parametri'!$B$13+'P-Parametri'!$C$13*('P-Parametri'!$B$6-$C42)/'P-Parametri'!$D$13,IF($C42<='P-Parametri'!$B$7,'P-Parametri'!$B$14*('P-Parametri'!$B$7-$C42)/'P-Parametri'!$C$14,0))) -> 1818.0422 | F42: =IF($C42<='P-Parametri'!$C$15,0,IF($C42<='P-Parametri'!$D$15,'P-Parametri'!$B$15,IF($C42<'P-Parametri'!$E$15,'P-Parametri'!$B$15*('P-Parametri'!$E$15-$C42)/('P-Parametri'!$E$15-'P-Parametri'!$D$15),0))) -> 1000 | G42: =IF($C42>'P-Parametri'!$D$18,0,IF($C42<='P-Parametri'!$B$18,'P-Parametri'!$B$17*$C42,IF($C42<='P-Parametri'!$C$18,'P-Parametri'!$C$17*$C42,'P-Parametri'!$D$17*$C42))) -> 0 | H42: =IF(AND($C42<='P-Parametri'!$C$16,D42>E42-'P-Parametri'!$D$16),'P-Parametri'!$B$16,0) -> 0 | I42: =MAX(0,D42-E42-F42) -> 3971.4938 | J42: =IF(I42>0,'P-Parametri'!$B$20*$C42,0) -> 581.184 | K42: =$C42-I42-J42+H42+G42 -> 24506.522 | L42: =K42/$A42 -> 0.76582882 | M42: =1-(K44-K42)/1000 -> 0.48857459 | N42: ='P-Parametri'!$B$19+(1-'P-Parametri'!$B$19)*((IF(($A42*(1-'P-Parametri'!$B$19))<='P-Parametri'!$B$6,'P-Parametri'!$C$6,IF(($A42*(1-'P-Parametri'!$B$19))<='P-Parametri'!$B$7,'P-Parametri'!$C$7,'P-Parametri'!$C$8)))+(IF(($A42*(1-'P-Parametri'!$B$19))<='P-Parametri'!$C$12,0,IF(($A42*(1-'P-Parametri'!$B$19))<='P-Parametri'!$B$6,'P-Parametri'!$C$13/'P-Parametri'!$D$13,IF(($A42*(1-'P-Parametri'!$B$19))<='P-Parametri'!$B$7,'P-Parametri'!$B$14/'P-Parametri'!$C$14,0))))+(IF(AND(($A42*(1-'P-Parametri'!$B$19))>'P-Parametri'!$D$15,($A42*(1-'P-Parametri'!$B$19))<'P-Parametri'!$E$15),'P-Parametri'!$B$15/('P-Parametri'!$E$15-'P-Parametri'!$D$15),0))+'P-Parametri'!$B$20) -> 0.48857459 | O42: =M42-N42 -> 3.7747583e-15
A43: =32500 -> 32500 | B43: ='P-Parametri'!$B$19*$A43 -> 2986.75 | C43: =$A43-B43 -> 29513.25 | D43: =IF($C43<='P-Parametri'!$B$6,'P-Parametri'!$C$6*$C43,IF($C43<='P-Parametri'!$B$7,'P-Parametri'!$B$9+'P-Parametri'!$C$7*($C43-'P-Parametri'!$B$6),'P-Parametri'!$B$10+'P-Parametri'!$C$8*($C43-'P-Parametri'!$B$7))) -> 6939.3725 | E43: =IF($C43<='P-Parametri'!$C$12,'P-Parametri'!$B$12,IF($C43<='P-Parametri'!$B$6,'P-Parametri'!$B$13+'P-Parametri'!$C$13*('P-Parametri'!$B$6-$C43)/'P-Parametri'!$D$13,IF($C43<='P-Parametri'!$B$7,'P-Parametri'!$B$14*('P-Parametri'!$B$7-$C43)/'P-Parametri'!$C$14,0))) -> 1778.6224 | F43: =IF($C43<='P-Parametri'!$C$15,0,IF($C43<='P-Parametri'!$D$15,'P-Parametri'!$B$15,IF($C43<'P-Parametri'!$E$15,'P-Parametri'!$B$15*('P-Parametri'!$E$15-$C43)/('P-Parametri'!$E$15-'P-Parametri'!$D$15),0))) -> 1000 | G43: =IF($C43>'P-Parametri'!$D$18,0,IF($C43<='P-Parametri'!$B$18,'P-Parametri'!$B$17*$C43,IF($C43<='P-Parametri'!$C$18,'P-Parametri'!$C$17*$C43,'P-Parametri'!$D$17*$C43))) -> 0 | H43: =IF(AND($C43<='P-Parametri'!$C$16,D43>E43-'P-Parametri'!$D$16),'P-Parametri'!$B$16,0) -> 0 | I43: =MAX(0,D43-E43-F43) -> 4160.7501 | J43: =IF(I43>0,'P-Parametri'!$B$20*$C43,0) -> 590.265 | K43: =$C43-I43-J43+H43+G43 -> 24762.235 | L43: =K43/$A43 -> 0.76191492 | M43: =1-(K45-K43)/1000 -> 0.48857459 | N43: ='P-Parametri'!$B$19+(1-'P-Parametri'!$B$19)*((IF(($A43*(1-'P-Parametri'!$B$19))<='P-Parametri'!$B$6,'P-Parametri'!$C$6,IF(($A43*(1-'P-Parametri'!$B$19))<='P-Parametri'!$B$7,'P-Parametri'!$C$7,'P-Parametri'!$C$8)))+(IF(($A43*(1-'P-Parametri'!$B$19))<='P-Parametri'!$C$12,0,IF(($A43*(1-'P-Parametri'!$B$19))<='P-Parametri'!$B$6,'P-Parametri'!$C$13/'P-Parametri'!$D$13,IF(($A43*(1-'P-Parametri'!$B$19))<='P-Parametri'!$B$7,'P-Parametri'!$B$14/'P-Parametri'!$C$14,0))))+(IF(AND(($A43*(1-'P-Parametri'!$B$19))>'P-Parametri'!$D$15,($A43*(1-'P-Parametri'!$B$19))<'P-Parametri'!$E$15),'P-Parametri'!$B$15/('P-Parametri'!$E$15-'P-Parametri'!$D$15),0))+'P-Parametri'!$B$20) -> 0.48857459 | O43: =M43-N43 -> 0
A44: =33000 -> 33000 | B44: ='P-Parametri'!$B$19*$A44 -> 3032.7 | C44: =$A44-B44 -> 29967.3 | D44: =IF($C44<='P-Parametri'!$B$6,'P-Parametri'!$C$6*$C44,IF($C44<='P-Parametri'!$B$7,'P-Parametri'!$B$9+'P-Parametri'!$C$7*($C44-'P-Parametri'!$B$6),'P-Parametri'!$B$10+'P-Parametri'!$C$8*($C44-'P-Parametri'!$B$7))) -> 7089.209 | E44: =IF($C44<='P-Parametri'!$C$12,'P-Parametri'!$B$12,IF($C44<='P-Parametri'!$B$6,'P-Parametri'!$B$13+'P-Parametri'!$C$13*('P-Parametri'!$B$6-$C44)/'P-Parametri'!$D$13,IF($C44<='P-Parametri'!$B$7,'P-Parametri'!$B$14*('P-Parametri'!$B$7-$C44)/'P-Parametri'!$C$14,0))) -> 1739.2026 | F44: =IF($C44<='P-Parametri'!$C$15,0,IF($C44<='P-Parametri'!$D$15,'P-Parametri'!$B$15,IF($C44<'P-Parametri'!$E$15,'P-Parametri'!$B$15*('P-Parametri'!$E$15-$C44)/('P-Parametri'!$E$15-'P-Parametri'!$D$15),0))) -> 1000 | G44: =IF($C44>'P-Parametri'!$D$18,0,IF($C44<='P-Parametri'!$B$18,'P-Parametri'!$B$17*$C44,IF($C44<='P-Parametri'!$C$18,'P-Parametri'!$C$17*$C44,'P-Parametri'!$D$17*$C44))) -> 0 | H44: =IF(AND($C44<='P-Parametri'!$C$16,D44>E44-'P-Parametri'!$D$16),'P-Parametri'!$B$16,0) -> 0 | I44: =MAX(0,D44-E44-F44) -> 4350.0064 | J44: =IF(I44>0,'P-Parametri'!$B$20*$C44,0) -> 599.346 | K44: =$C44-I44-J44+H44+G44 -> 25017.948 | L44: =K44/$A44 -> 0.75811962 | M44: =1-(K46-K44)/1000 -> 0.48857459 | N44: ='P-Parametri'!$B$19+(1-'P-Parametri'!$B$19)*((IF(($A44*(1-'P-Parametri'!$B$19))<='P-Parametri'!$B$6,'P-Parametri'!$C$6,IF(($A44*(1-'P-Parametri'!$B$19))<='P-Parametri'!$B$7,'P-Parametri'!$C$7,'P-Parametri'!$C$8)))+(IF(($A44*(1-'P-Parametri'!$B$19))<='P-Parametri'!$C$12,0,IF(($A44*(1-'P-Parametri'!$B$19))<='P-Parametri'!$B$6,'P-Parametri'!$C$13/'P-Parametri'!$D$13,IF(($A44*(1-'P-Parametri'!$B$19))<='P-Parametri'!$B$7,'P-Parametri'!$B$14/'P-Parametri'!$C$14,0))))+(IF(AND(($A44*(1-'P-Parametri'!$B$19))>'P-Parametri'!$D$15,($A44*(1-'P-Parametri'!$B$19))<'P-Parametri'!$E$15),'P-Parametri'!$B$15/('P-Parametri'!$E$15-'P-Parametri'!$D$15),0))+'P-Parametri'!$B$20) -> 0.48857459 | O44: =M44-N44 -> -3.5527137e-15
A45: =33500 -> 33500 | B45: ='P-Parametri'!$B$19*$A45 -> 3078.65 | C45: =$A45-B45 -> 30421.35 | D45: =IF($C45<='P-Parametri'!$B$6,'P-Parametri'!$C$6*$C45,IF($C45<='P-Parametri'!$B$7,'P-Parametri'!$B$9+'P-Parametri'!$C$7*($C45-'P-Parametri'!$B$6),'P-Parametri'!$B$10+'P-Parametri'!$C$8*($C45-'P-Parametri'!$B$7))) -> 7239.0455 | E45: =IF($C45<='P-Parametri'!$C$12,'P-Parametri'!$B$12,IF($C45<='P-Parametri'!$B$6,'P-Parametri'!$B$13+'P-Parametri'!$C$13*('P-Parametri'!$B$6-$C45)/'P-Parametri'!$D$13,IF($C45<='P-Parametri'!$B$7,'P-Parametri'!$B$14*('P-Parametri'!$B$7-$C45)/'P-Parametri'!$C$14,0))) -> 1699.7828 | F45: =IF($C45<='P-Parametri'!$C$15,0,IF($C45<='P-Parametri'!$D$15,'P-Parametri'!$B$15,IF($C45<'P-Parametri'!$E$15,'P-Parametri'!$B$15*('P-Parametri'!$E$15-$C45)/('P-Parametri'!$E$15-'P-Parametri'!$D$15),0))) -> 1000 | G45: =IF($C45>'P-Parametri'!$D$18,0,IF($C45<='P-Parametri'!$B$18,'P-Parametri'!$B$17*$C45,IF($C45<='P-Parametri'!$C$18,'P-Parametri'!$C$17*$C45,'P-Parametri'!$D$17*$C45))) -> 0 | H45: =IF(AND($C45<='P-Parametri'!$C$16,D45>E45-'P-Parametri'!$D$16),'P-Parametri'!$B$16,0) -> 0 | I45: =MAX(0,D45-E45-F45) -> 4539.2627 | J45: =IF(I45>0,'P-Parametri'!$B$20*$C45,0) -> 608.427 | K45: =$C45-I45-J45+H45+G45 -> 25273.66 | L45: =K45/$A45 -> 0.75443762 | M45: =1-(K47-K45)/1000 -> 0.48857459 | N45: ='P-Parametri'!$B$19+(1-'P-Parametri'!$B$19)*((IF(($A45*(1-'P-Parametri'!$B$19))<='P-Parametri'!$B$6,'P-Parametri'!$C$6,IF(($A45*(1-'P-Parametri'!$B$19))<='P-Parametri'!$B$7,'P-Parametri'!$C$7,'P-Parametri'!$C$8)))+(IF(($A45*(1-'P-Parametri'!$B$19))<='P-Parametri'!$C$12,0,IF(($A45*(1-'P-Parametri'!$B$19))<='P-Parametri'!$B$6,'P-Parametri'!$C$13/'P-Parametri'!$D$13,IF(($A45*(1-'P-Parametri'!$B$19))<='P-Parametri'!$B$7,'P-Parametri'!$B$14/'P-Parametri'!$C$14,0))))+(IF(AND(($A45*(1-'P-Parametri'!$B$19))>'P-Parametri'!$D$15,($A45*(1-'P-Parametri'!$B$19))<'P-Parametri'!$E$15),'P-Parametri'!$B$15/('P-Parametri'!$E$15-'P-Parametri'!$D$15),0))+'P-Parametri'!$B$20) -> 0.48857459 | O45: =M45-N45 -> 0
A46: =34000 -> 34000 | B46: ='P-Parametri'!$B$19*$A46 -> 3124.6 | C46: =$A46-B46 -> 30875.4 | D46: =IF($C46<='P-Parametri'!$B$6,'P-Parametri'!$C$6*$C46,IF($C46<='P-Parametri'!$B$7,'P-Parametri'!$B$9+'P-Parametri'!$C$7*($C46-'P-Parametri'!$B$6),'P-Parametri'!$B$10+'P-Parametri'!$C$8*($C46-'P-Parametri'!$B$7))) -> 7388.882 | E46: =IF($C46<='P-Parametri'!$C$12,'P-Parametri'!$B$12,IF($C46<='P-Parametri'!$B$6,'P-Parametri'!$B$13+'P-Parametri'!$C$13*('P-Parametri'!$B$6-$C46)/'P-Parametri'!$D$13,IF($C46<='P-Parametri'!$B$7,'P-Parametri'!$B$14*('P-Parametri'!$B$7-$C46)/'P-Parametri'!$C$14,0))) -> 1660.363 | F46: =IF($C46<='P-Parametri'!$C$15,0,IF($C46<='P-Parametri'!$D$15,'P-Parametri'!$B$15,IF($C46<'P-Parametri'!$E$15,'P-Parametri'!$B$15*('P-Parametri'!$E$15-$C46)/('P-Parametri'!$E$15-'P-Parametri'!$D$15),0))) -> 1000 | G46: =IF($C46>'P-Parametri'!$D$18,0,IF($C46<='P-Parametri'!$B$18,'P-Parametri'!$B$17*$C46,IF($C46<='P-Parametri'!$C$18,'P-Parametri'!$C$17*$C46,'P-Parametri'!$D$17*$C46))) -> 0 | H46: =IF(AND($C46<='P-Parametri'!$C$16,D46>E46-'P-Parametri'!$D$16),'P-Parametri'!$B$16,0) -> 0 | I46: =MAX(0,D46-E46-F46) -> 4728.519 | J46: =IF(I46>0,'P-Parametri'!$B$20*$C46,0) -> 617.508 | K46: =$C46-I46-J46+H46+G46 -> 25529.373 | L46: =K46/$A46 -> 0.75086391 | M46: =1-(K48-K46)/1000 -> 0.48857459 | N46: ='P-Parametri'!$B$19+(1-'P-Parametri'!$B$19)*((IF(($A46*(1-'P-Parametri'!$B$19))<='P-Parametri'!$B$6,'P-Parametri'!$C$6,IF(($A46*(1-'P-Parametri'!$B$19))<='P-Parametri'!$B$7,'P-Parametri'!$C$7,'P-Parametri'!$C$8)))+(IF(($A46*(1-'P-Parametri'!$B$19))<='P-Parametri'!$C$12,0,IF(($A46*(1-'P-Parametri'!$B$19))<='P-Parametri'!$B$6,'P-Parametri'!$C$13/'P-Parametri'!$D$13,IF(($A46*(1-'P-Parametri'!$B$19))<='P-Parametri'!$B$7,'P-Parametri'!$B$14/'P-Parametri'!$C$14,0))))+(IF(AND(($A46*(1-'P-Parametri'!$B$19))>'P-Parametri'!$D$15,($A46*(1-'P-Parametri'!$B$19))<'P-Parametri'!$E$15),'P-Parametri'!$B$15/('P-Parametri'!$E$15-'P-Parametri'!$D$15),0))+'P-Parametri'!$B$20) -> 0.48857459 | O46: =M46-N46 -> 0
A47: =34500 -> 34500 | B47: ='P-Parametri'!$B$19*$A47 -> 3170.55 | C47: =$A47-B47 -> 31329.45 | D47: =IF($C47<='P-Parametri'!$B$6,'P-Parametri'!$C$6*$C47,IF($C47<='P-Parametri'!$B$7,'P-Parametri'!$B$9+'P-Parametri'!$C$7*($C47-'P-Parametri'!$B$6),'P-Parametri'!$B$10+'P-Parametri'!$C$8*($C47-'P-Parametri'!$B$7))) -> 7538.7185 | E47: =IF($C47<='P-Parametri'!$C$12,'P-Parametri'!$B$12,IF($C47<='P-Parametri'!$B$6,'P-Parametri'!$B$13+'P-Parametri'!$C$13*('P-Parametri'!$B$6-$C47)/'P-Parametri'!$D$13,IF($C47<='P-Parametri'!$B$7,'P-Parametri'!$B$14*('P-Parametri'!$B$7-$C47)/'P-Parametri'!$C$14,0))) -> 1620.9432 | F47: =IF($C47<='P-Parametri'!$C$15,0,IF($C47<='P-Parametri'!$D$15,'P-Parametri'!$B$15,IF($C47<'P-Parametri'!$E$15,'P-Parametri'!$B$15*('P-Parametri'!$E$15-$C47)/('P-Parametri'!$E$15-'P-Parametri'!$D$15),0))) -> 1000 | G47: =IF($C47>'P-Parametri'!$D$18,0,IF($C47<='P-Parametri'!$B$18,'P-Parametri'!$B$17*$C47,IF($C47<='P-Parametri'!$C$18,'P-Parametri'!$C$17*$C47,'P-Parametri'!$D$17*$C47))) -> 0 | H47: =IF(AND($C47<='P-Parametri'!$C$16,D47>E47-'P-Parametri'!$D$16),'P-Parametri'!$B$16,0) -> 0 | I47: =MAX(0,D47-E47-F47) -> 4917.7753 | J47: =IF(I47>0,'P-Parametri'!$B$20*$C47,0) -> 626.589 | K47: =$C47-I47-J47+H47+G47 -> 25785.086 | L47: =K47/$A47 -> 0.74739379 | M47: =1-(K49-K47)/1000 -> 0.51826834 | N47: ='P-Parametri'!$B$19+(1-'P-Parametri'!$B$19)*((IF(($A47*(1-'P-Parametri'!$B$19))<='P-Parametri'!$B$6,'P-Parametri'!$C$6,IF(($A47*(1-'P-Parametri'!$B$19))<='P-Parametri'!$B$7,'P-Parametri'!$C$7,'P-Parametri'!$C$8)))+(IF(($A47*(1-'P-Parametri'!$B$19))<='P-Parametri'!$C$12,0,IF(($A47*(1-'P-Parametri'!$B$19))<='P-Parametri'!$B$6,'P-Parametri'!$C$13/'P-Parametri'!$D$13,IF(($A47*(1-'P-Parametri'!$B$19))<='P-Parametri'!$B$7,'P-Parametri'!$B$14/'P-Parametri'!$C$14,0))))+(IF(AND(($A47*(1-'P-Parametri'!$B$19))>'P-Parametri'!$D$15,($A47*(1-'P-Parametri'!$B$19))<'P-Parametri'!$E$15),'P-Parametri'!$B$15/('P-Parametri'!$E$15-'P-Parametri'!$D$15),0))+'P-Parametri'!$B$20) -> 0.48857459 | O47: =M47-N47 -> 0.02969375
A48: =35000 -> 35000 | B48: ='P-Parametri'!$B$19*$A48 -> 3216.5 | C48: =$A48-B48 -> 31783.5 | D48: =IF($C48<='P-Parametri'!$B$6,'P-Parametri'!$C$6*$C48,IF($C48<='P-Parametri'!$B$7,'P-Parametri'!$B$9+'P-Parametri'!$C$7*($C48-'P-Parametri'!$B$6),'P-Parametri'!$B$10+'P-Parametri'!$C$8*($C48-'P-Parametri'!$B$7))) -> 7688.555 | E48: =IF($C48<='P-Parametri'!$C$12,'P-Parametri'!$B$12,IF($C48<='P-Parametri'!$B$6,'P-Parametri'!$B$13+'P-Parametri'!$C$13*('P-Parametri'!$B$6-$C48)/'P-Parametri'!$D$13,IF($C48<='P-Parametri'!$B$7,'P-Parametri'!$B$14*('P-Parametri'!$B$7-$C48)/'P-Parametri'!$C$14,0))) -> 1581.5234 | F48: =IF($C48<='P-Parametri'!$C$15,0,IF($C48<='P-Parametri'!$D$15,'P-Parametri'!$B$15,IF($C48<'P-Parametri'!$E$15,'P-Parametri'!$B$15*('P-Parametri'!$E$15-$C48)/('P-Parametri'!$E$15-'P-Parametri'!$D$15),0))) -> 1000 | G48: =IF($C48>'P-Parametri'!$D$18,0,IF($C48<='P-Parametri'!$B$18,'P-Parametri'!$B$17*$C48,IF($C48<='P-Parametri'!$C$18,'P-Parametri'!$C$17*$C48,'P-Parametri'!$D$17*$C48))) -> 0 | H48: =IF(AND($C48<='P-Parametri'!$C$16,D48>E48-'P-Parametri'!$D$16),'P-Parametri'!$B$16,0) -> 0 | I48: =MAX(0,D48-E48-F48) -> 5107.0316 | J48: =IF(I48>0,'P-Parametri'!$B$20*$C48,0) -> 635.67 | K48: =$C48-I48-J48+H48+G48 -> 26040.798 | L48: =K48/$A48 -> 0.74402281 | M48: =1-(K50-K48)/1000 -> 0.57502459 | N48: ='P-Parametri'!$B$19+(1-'P-Parametri'!$B$19)*((IF(($A48*(1-'P-Parametri'!$B$19))<='P-Parametri'!$B$6,'P-Parametri'!$C$6,IF(($A48*(1-'P-Parametri'!$B$19))<='P-Parametri'!$B$7,'P-Parametri'!$C$7,'P-Parametri'!$C$8)))+(IF(($A48*(1-'P-Parametri'!$B$19))<='P-Parametri'!$C$12,0,IF(($A48*(1-'P-Parametri'!$B$19))<='P-Parametri'!$B$6,'P-Parametri'!$C$13/'P-Parametri'!$D$13,IF(($A48*(1-'P-Parametri'!$B$19))<='P-Parametri'!$B$7,'P-Parametri'!$B$14/'P-Parametri'!$C$14,0))))+(IF(AND(($A48*(1-'P-Parametri'!$B$19))>'P-Parametri'!$D$15,($A48*(1-'P-Parametri'!$B$19))<'P-Parametri'!$E$15),'P-Parametri'!$B$15/('P-Parametri'!$E$15-'P-Parametri'!$D$15),0))+'P-Parametri'!$B$20) -> 0.48857459 | O48: =M48-N48 -> 0.08645
A49: =35500 -> 35500 | B49: ='P-Parametri'!$B$19*$A49 -> 3262.45 | C49: =$A49-B49 -> 32237.55 | D49: =IF($C49<='P-Parametri'!$B$6,'P-Parametri'!$C$6*$C49,IF($C49<='P-Parametri'!$B$7,'P-Parametri'!$B$9+'P-Parametri'!$C$7*($C49-'P-Parametri'!$B$6),'P-Parametri'!$B$10+'P-Parametri'!$C$8*($C49-'P-Parametri'!$B$7))) -> 7838.3915 | E49: =IF($C49<='P-Parametri'!$C$12,'P-Parametri'!$B$12,IF($C49<='P-Parametri'!$B$6,'P-Parametri'!$B$13+'P-Parametri'!$C$13*('P-Parametri'!$B$6-$C49)/'P-Parametri'!$D$13,IF($C49<='P-Parametri'!$B$7,'P-Parametri'!$B$14*('P-Parametri'!$B$7-$C49)/'P-Parametri'!$C$14,0))) -> 1542.1036 | F49: =IF($C49<='P-Parametri'!$C$15,0,IF($C49<='P-Parametri'!$D$15,'P-Parametri'!$B$15,IF($C49<'P-Parametri'!$E$15,'P-Parametri'!$B$15*('P-Parametri'!$E$15-$C49)/('P-Parametri'!$E$15-'P-Parametri'!$D$15),0))) -> 970.30625 | G49: =IF($C49>'P-Parametri'!$D$18,0,IF($C49<='P-Parametri'!$B$18,'P-Parametri'!$B$17*$C49,IF($C49<='P-Parametri'!$C$18,'P-Parametri'!$C$17*$C49,'P-Parametri'!$D$17*$C49))) -> 0 | H49: =IF(AND($C49<='P-Parametri'!$C$16,D49>E49-'P-Parametri'!$D$16),'P-Parametri'!$B$16,0) -> 0 | I49: =MAX(0,D49-E49-F49) -> 5325.9816 | J49: =IF(I49>0,'P-Parametri'!$B$20*$C49,0) -> 644.751 | K49: =$C49-I49-J49+H49+G49 -> 26266.817 | L49: =K49/$A49 -> 0.73991035 | M49: =1-(K51-K49)/1000 -> 0.60208709 | N49: ='P-Parametri'!$B$19+(1-'P-Parametri'!$B$19)*((IF(($A49*(1-'P-Parametri'!$B$19))<='P-Parametri'!$B$6,'P-Parametri'!$C$6,IF(($A49*(1-'P-Parametri'!$B$19))<='P-Parametri'!$B$7,'P-Parametri'!$C$7,'P-Parametri'!$C$8)))+(IF(($A49*(1-'P-Parametri'!$B$19))<='P-Parametri'!$C$12,0,IF(($A49*(1-'P-Parametri'!$B$19))<='P-Parametri'!$B$6,'P-Parametri'!$C$13/'P-Parametri'!$D$13,IF(($A49*(1-'P-Parametri'!$B$19))<='P-Parametri'!$B$7,'P-Parametri'!$B$14/'P-Parametri'!$C$14,0))))+(IF(AND(($A49*(1-'P-Parametri'!$B$19))>'P-Parametri'!$D$15,($A49*(1-'P-Parametri'!$B$19))<'P-Parametri'!$E$15),'P-Parametri'!$B$15/('P-Parametri'!$E$15-'P-Parametri'!$D$15),0))+'P-Parametri'!$B$20) -> 0.60208709 | O49: =M49-N49 -> -2.8865799e-15
A50: =36000 -> 36000 | B50: ='P-Parametri'!$B$19*$A50 -> 3308.4 | C50: =$A50-B50 -> 32691.6 | D50: =IF($C50<='P-Parametri'!$B$6,'P-Parametri'!$C$6*$C50,IF($C50<='P-Parametri'!$B$7,'P-Parametri'!$B$9+'P-Parametri'!$C$7*($C50-'P-Parametri'!$B$6),'P-Parametri'!$B$10+'P-Parametri'!$C$8*($C50-'P-Parametri'!$B$7))) -> 7988.228 | E50: =IF($C50<='P-Parametri'!$C$12,'P-Parametri'!$B$12,IF($C50<='P-Parametri'!$B$6,'P-Parametri'!$B$13+'P-Parametri'!$C$13*('P-Parametri'!$B$6-$C50)/'P-Parametri'!$D$13,IF($C50<='P-Parametri'!$B$7,'P-Parametri'!$B$14*('P-Parametri'!$B$7-$C50)/'P-Parametri'!$C$14,0))) -> 1502.6838 | F50: =IF($C50<='P-Parametri'!$C$15,0,IF($C50<='P-Parametri'!$D$15,'P-Parametri'!$B$15,IF($C50<'P-Parametri'!$E$15,'P-Parametri'!$B$15*('P-Parametri'!$E$15-$C50)/('P-Parametri'!$E$15-'P-Parametri'!$D$15),0))) -> 913.55 | G50: =IF($C50>'P-Parametri'!$D$18,0,IF($C50<='P-Parametri'!$B$18,'P-Parametri'!$B$17*$C50,IF($C50<='P-Parametri'!$C$18,'P-Parametri'!$C$17*$C50,'P-Parametri'!$D$17*$C50))) -> 0 | H50: =IF(AND($C50<='P-Parametri'!$C$16,D50>E50-'P-Parametri'!$D$16),'P-Parametri'!$B$16,0) -> 0 | I50: =MAX(0,D50-E50-F50) -> 5571.9942 | J50: =IF(I50>0,'P-Parametri'!$B$20*$C50,0) -> 653.832 | K50: =$C50-I50-J50+H50+G50 -> 26465.774 | L50: =K50/$A50 -> 0.73516038 | M50: =1-(K52-K50)/1000 -> 0.60208709 | N50: ='P-Parametri'!$B$19+(1-'P-Parametri'!$B$19)*((IF(($A50*(1-'P-Parametri'!$B$19))<='P-Parametri'!$B$6,'P-Parametri'!$C$6,IF(($A50*(1-'P-Parametri'!$B$19))<='P-Parametri'!$B$7,'P-Parametri'!$C$7,'P-Parametri'!$C$8)))+(IF(($A50*(1-'P-Parametri'!$B$19))<='P-Parametri'!$C$12,0,IF(($A50*(1-'P-Parametri'!$B$19))<='P-Parametri'!$B$6,'P-Parametri'!$C$13/'P-Parametri'!$D$13,IF(($A50*(1-'P-Parametri'!$B$19))<='P-Parametri'!$B$7,'P-Parametri'!$B$14/'P-Parametri'!$C$14,0))))+(IF(AND(($A50*(1-'P-Parametri'!$B$19))>'P-Parametri'!$D$15,($A50*(1-'P-Parametri'!$B$19))<'P-Parametri'!$E$15),'P-Parametri'!$B$15/('P-Parametri'!$E$15-'P-Parametri'!$D$15),0))+'P-Parametri'!$B$20) -> 0.60208709 | O50: =M50-N50 -> 4.4408921e-15
A51: =36500 -> 36500 | B51: ='P-Parametri'!$B$19*$A51 -> 3354.35 | C51: =$A51-B51 -> 33145.65 | D51: =IF($C51<='P-Parametri'!$B$6,'P-Parametri'!$C$6*$C51,IF($C51<='P-Parametri'!$B$7,'P-Parametri'!$B$9+'P-Parametri'!$C$7*($C51-'P-Parametri'!$B$6),'P-Parametri'!$B$10+'P-Parametri'!$C$8*($C51-'P-Parametri'!$B$7))) -> 8138.0645 | E51: =IF($C51<='P-Parametri'!$C$12,'P-Parametri'!$B$12,IF($C51<='P-Parametri'!$B$6,'P-Parametri'!$B$13+'P-Parametri'!$C$13*('P-Parametri'!$B$6-$C51)/'P-Parametri'!$D$13,IF($C51<='P-Parametri'!$B$7,'P-Parametri'!$B$14*('P-Parametri'!$B$7-$C51)/'P-Parametri'!$C$14,0))) -> 1463.264 | F51: =IF($C51<='P-Parametri'!$C$15,0,IF($C51<='P-Parametri'!$D$15,'P-Parametri'!$B$15,IF($C51<'P-Parametri'!$E$15,'P-Parametri'!$B$15*('P-Parametri'!$E$15-$C51)/('P-Parametri'!$E$15-'P-Parametri'!$D$15),0))) -> 856.79375 | G51: =IF($C51>'P-Parametri'!$D$18,0,IF($C51<='P-Parametri'!$B$18,'P-Parametri'!$B$17*$C51,IF($C51<='P-Parametri'!$C$18,'P-Parametri'!$C$17*$C51,'P-Parametri'!$D$17*$C51))) -> 0 | H51: =IF(AND($C51<='P-Parametri'!$C$16,D51>E51-'P-Parametri'!$D$16),'P-Parametri'!$B$16,0) -> 0 | I51: =MAX(0,D51-E51-F51) -> 5818.0067 | J51: =IF(I51>0,'P-Parametri'!$B$20*$C51,0) -> 662.913 | K51: =$C51-I51-J51+H51+G51 -> 26664.73 | L51: =K51/$A51 -> 0.73054056 | M51: =1-(K53-K51)/1000 -> 0.60208709 | N51: ='P-Parametri'!$B$19+(1-'P-Parametri'!$B$19)*((IF(($A51*(1-'P-Parametri'!$B$19))<='P-Parametri'!$B$6,'P-Parametri'!$C$6,IF(($A51*(1-'P-Parametri'!$B$19))<='P-Parametri'!$B$7,'P-Parametri'!$C$7,'P-Parametri'!$C$8)))+(IF(($A51*(1-'P-Parametri'!$B$19))<='P-Parametri'!$C$12,0,IF(($A51*(1-'P-Parametri'!$B$19))<='P-Parametri'!$B$6,'P-Parametri'!$C$13/'P-Parametri'!$D$13,IF(($A51*(1-'P-Parametri'!$B$19))<='P-Parametri'!$B$7,'P-Parametri'!$B$14/'P-Parametri'!$C$14,0))))+(IF(AND(($A51*(1-'P-Parametri'!$B$19))>'P-Parametri'!$D$15,($A51*(1-'P-Parametri'!$B$19))<'P-Parametri'!$E$15),'P-Parametri'!$B$15/('P-Parametri'!$E$15-'P-Parametri'!$D$15),0))+'P-Parametri'!$B$20) -> 0.60208709 | O51: =M51-N51 -> 8.8817842e-16
A52: =37000 -> 37000 | B52: ='P-Parametri'!$B$19*$A52 -> 3400.3 | C52: =$A52-B52 -> 33599.7 | D52: =IF($C52<='P-Parametri'!$B$6,'P-Parametri'!$C$6*$C52,IF($C52<='P-Parametri'!$B$7,'P-Parametri'!$B$9+'P-Parametri'!$C$7*($C52-'P-Parametri'!$B$6),'P-Parametri'!$B$10+'P-Parametri'!$C$8*($C52-'P-Parametri'!$B$7))) -> 8287.901 | E52: =IF($C52<='P-Parametri'!$C$12,'P-Parametri'!$B$12,IF($C52<='P-Parametri'!$B$6,'P-Parametri'!$B$13+'P-Parametri'!$C$13*('P-Parametri'!$B$6-$C52)/'P-Parametri'!$D$13,IF($C52<='P-Parametri'!$B$7,'P-Parametri'!$B$14*('P-Parametri'!$B$7-$C52)/'P-Parametri'!$C$14,0))) -> 1423.8442 | F52: =IF($C52<='P-Parametri'!$C$15,0,IF($C52<='P-Parametri'!$D$15,'P-Parametri'!$B$15,IF($C52<'P-Parametri'!$E$15,'P-Parametri'!$B$15*('P-Parametri'!$E$15-$C52)/('P-Parametri'!$E$15-'P-Parametri'!$D$15),0))) -> 800.0375 | G52: =IF($C52>'P-Parametri'!$D$18,0,IF($C52<='P-Parametri'!$B$18,'P-Parametri'!$B$17*$C52,IF($C52<='P-Parametri'!$C$18,'P-Parametri'!$C$17*$C52,'P-Parametri'!$D$17*$C52))) -> 0 | H52: =IF(AND($C52<='P-Parametri'!$C$16,D52>E52-'P-Parametri'!$D$16),'P-Parametri'!$B$16,0) -> 0 | I52: =MAX(0,D52-E52-F52) -> 6064.0193 | J52: =IF(I52>0,'P-Parametri'!$B$20*$C52,0) -> 671.994 | K52: =$C52-I52-J52+H52+G52 -> 26863.687 | L52: =K52/$A52 -> 0.72604559 | M52: =1-(K54-K52)/1000 -> 0.60208709 | N52: ='P-Parametri'!$B$19+(1-'P-Parametri'!$B$19)*((IF(($A52*(1-'P-Parametri'!$B$19))<='P-Parametri'!$B$6,'P-Parametri'!$C$6,IF(($A52*(1-'P-Parametri'!$B$19))<='P-Parametri'!$B$7,'P-Parametri'!$C$7,'P-Parametri'!$C$8)))+(IF(($A52*(1-'P-Parametri'!$B$19))<='P-Parametri'!$C$12,0,IF(($A52*(1-'P-Parametri'!$B$19))<='P-Parametri'!$B$6,'P-Parametri'!$C$13/'P-Parametri'!$D$13,IF(($A52*(1-'P-Parametri'!$B$19))<='P-Parametri'!$B$7,'P-Parametri'!$B$14/'P-Parametri'!$C$14,0))))+(IF(AND(($A52*(1-'P-Parametri'!$B$19))>'P-Parametri'!$D$15,($A52*(1-'P-Parametri'!$B$19))<'P-Parametri'!$E$15),'P-Parametri'!$B$15/('P-Parametri'!$E$15-'P-Parametri'!$D$15),0))+'P-Parametri'!$B$20) -> 0.60208709 | O52: =M52-N52 -> -6.4392935e-15
A53: =37500 -> 37500 | B53: ='P-Parametri'!$B$19*$A53 -> 3446.25 | C53: =$A53-B53 -> 34053.75 | D53: =IF($C53<='P-Parametri'!$B$6,'P-Parametri'!$C$6*$C53,IF($C53<='P-Parametri'!$B$7,'P-Parametri'!$B$9+'P-Parametri'!$C$7*($C53-'P-Parametri'!$B$6),'P-Parametri'!$B$10+'P-Parametri'!$C$8*($C53-'P-Parametri'!$B$7))) -> 8437.7375 | E53: =IF($C53<='P-Parametri'!$C$12,'P-Parametri'!$B$12,IF($C53<='P-Parametri'!$B$6,'P-Parametri'!$B$13+'P-Parametri'!$C$13*('P-Parametri'!$B$6-$C53)/'P-Parametri'!$D$13,IF($C53<='P-Parametri'!$B$7,'P-Parametri'!$B$14*('P-Parametri'!$B$7-$C53)/'P-Parametri'!$C$14,0))) -> 1384.4244 | F53: =IF($C53<='P-Parametri'!$C$15,0,IF($C53<='P-Parametri'!$D$15,'P-Parametri'!$B$15,IF($C53<'P-Parametri'!$E$15,'P-Parametri'!$B$15*('P-Parametri'!$E$15-$C53)/('P-Parametri'!$E$15-'P-Parametri'!$D$15),0))) -> 743.28125 | G53: =IF($C53>'P-Parametri'!$D$18,0,IF($C53<='P-Parametri'!$B$18,'P-Parametri'!$B$17*$C53,IF($C53<='P-Parametri'!$C$18,'P-Parametri'!$C$17*$C53,'P-Parametri'!$D$17*$C53))) -> 0 | H53: =IF(AND($C53<='P-Parametri'!$C$16,D53>E53-'P-Parametri'!$D$16),'P-Parametri'!$B$16,0) -> 0 | I53: =MAX(0,D53-E53-F53) -> 6310.0318 | J53: =IF(I53>0,'P-Parametri'!$B$20*$C53,0) -> 681.075 | K53: =$C53-I53-J53+H53+G53 -> 27062.643 | L53: =K53/$A53 -> 0.72167048 | M53: =1-(K55-K53)/1000 -> 0.60208709 | N53: ='P-Parametri'!$B$19+(1-'P-Parametri'!$B$19)*((IF(($A53*(1-'P-Parametri'!$B$19))<='P-Parametri'!$B$6,'P-Parametri'!$C$6,IF(($A53*(1-'P-Parametri'!$B$19))<='P-Parametri'!$B$7,'P-Parametri'!$C$7,'P-Parametri'!$C$8)))+(IF(($A53*(1-'P-Parametri'!$B$19))<='P-Parametri'!$C$12,0,IF(($A53*(1-'P-Parametri'!$B$19))<='P-Parametri'!$B$6,'P-Parametri'!$C$13/'P-Parametri'!$D$13,IF(($A53*(1-'P-Parametri'!$B$19))<='P-Parametri'!$B$7,'P-Parametri'!$B$14/'P-Parametri'!$C$14,0))))+(IF(AND(($A53*(1-'P-Parametri'!$B$19))>'P-Parametri'!$D$15,($A53*(1-'P-Parametri'!$B$19))<'P-Parametri'!$E$15),'P-Parametri'!$B$15/('P-Parametri'!$E$15-'P-Parametri'!$D$15),0))+'P-Parametri'!$B$20) -> 0.60208709 | O53: =M53-N53 -> 8.8817842e-16
A54: =38000 -> 38000 | B54: ='P-Parametri'!$B$19*$A54 -> 3492.2 | C54: =$A54-B54 -> 34507.8 | D54: =IF($C54<='P-Parametri'!$B$6,'P-Parametri'!$C$6*$C54,IF($C54<='P-Parametri'!$B$7,'P-Parametri'!$B$9+'P-Parametri'!$C$7*($C54-'P-Parametri'!$B$6),'P-Parametri'!$B$10+'P-Parametri'!$C$8*($C54-'P-Parametri'!$B$7))) -> 8587.574 | E54: =IF($C54<='P-Parametri'!$C$12,'P-Parametri'!$B$12,IF($C54<='P-Parametri'!$B$6,'P-Parametri'!$B$13+'P-Parametri'!$C$13*('P-Parametri'!$B$6-$C54)/'P-Parametri'!$D$13,IF($C54<='P-Parametri'!$B$7,'P-Parametri'!$B$14*('P-Parametri'!$B$7-$C54)/'P-Parametri'!$C$14,0))) -> 1345.0046 | F54: =IF($C54<='P-Parametri'!$C$15,0,IF($C54<='P-Parametri'!$D$15,'P-Parametri'!$B$15,IF($C54<'P-Parametri'!$E$15,'P-Parametri'!$B$15*('P-Parametri'!$E$15-$C54)/('P-Parametri'!$E$15-'P-Parametri'!$D$15),0))) -> 686.525 | G54: =IF($C54>'P-Parametri'!$D$18,0,IF($C54<='P-Parametri'!$B$18,'P-Parametri'!$B$17*$C54,IF($C54<='P-Parametri'!$C$18,'P-Parametri'!$C$17*$C54,'P-Parametri'!$D$17*$C54))) -> 0 | H54: =IF(AND($C54<='P-Parametri'!$C$16,D54>E54-'P-Parametri'!$D$16),'P-Parametri'!$B$16,0) -> 0 | I54: =MAX(0,D54-E54-F54) -> 6556.0444 | J54: =IF(I54>0,'P-Parametri'!$B$20*$C54,0) -> 690.156 | K54: =$C54-I54-J54+H54+G54 -> 27261.6 | L54: =K54/$A54 -> 0.71741052 | M54: =1-(K56-K54)/1000 -> 0.60208709 | N54: ='P-Parametri'!$B$19+(1-'P-Parametri'!$B$19)*((IF(($A54*(1-'P-Parametri'!$B$19))<='P-Parametri'!$B$6,'P-Parametri'!$C$6,IF(($A54*(1-'P-Parametri'!$B$19))<='P-Parametri'!$B$7,'P-Parametri'!$C$7,'P-Parametri'!$C$8)))+(IF(($A54*(1-'P-Parametri'!$B$19))<='P-Parametri'!$C$12,0,IF(($A54*(1-'P-Parametri'!$B$19))<='P-Parametri'!$B$6,'P-Parametri'!$C$13/'P-Parametri'!$D$13,IF(($A54*(1-'P-Parametri'!$B$19))<='P-Parametri'!$B$7,'P-Parametri'!$B$14/'P-Parametri'!$C$14,0))))+(IF(AND(($A54*(1-'P-Parametri'!$B$19))>'P-Parametri'!$D$15,($A54*(1-'P-Parametri'!$B$19))<'P-Parametri'!$E$15),'P-Parametri'!$B$15/('P-Parametri'!$E$15-'P-Parametri'!$D$15),0))+'P-Parametri'!$B$20) -> 0.60208709 | O54: =M54-N54 -> 4.4408921e-15
A55: =38500 -> 38500 | B55: ='P-Parametri'!$B$19*$A55 -> 3538.15 | C55: =$A55-B55 -> 34961.85 | D55: =IF($C55<='P-Parametri'!$B$6,'P-Parametri'!$C$6*$C55,IF($C55<='P-Parametri'!$B$7,'P-Parametri'!$B$9+'P-Parametri'!$C$7*($C55-'P-Parametri'!$B$6),'P-Parametri'!$B$10+'P-Parametri'!$C$8*($C55-'P-Parametri'!$B$7))) -> 8737.4105 | E55: =IF($C55<='P-Parametri'!$C$12,'P-Parametri'!$B$12,IF($C55<='P-Parametri'!$B$6,'P-Parametri'!$B$13+'P-Parametri'!$C$13*('P-Parametri'!$B$6-$C55)/'P-Parametri'!$D$13,IF($C55<='P-Parametri'!$B$7,'P-Parametri'!$B$14*('P-Parametri'!$B$7-$C55)/'P-Parametri'!$C$14,0))) -> 1305.5848 | F55: =IF($C55<='P-Parametri'!$C$15,0,IF($C55<='P-Parametri'!$D$15,'P-Parametri'!$B$15,IF($C55<'P-Parametri'!$E$15,'P-Parametri'!$B$15*('P-Parametri'!$E$15-$C55)/('P-Parametri'!$E$15-'P-Parametri'!$D$15),0))) -> 629.76875 | G55: =IF($C55>'P-Parametri'!$D$18,0,IF($C55<='P-Parametri'!$B$18,'P-Parametri'!$B$17*$C55,IF($C55<='P-Parametri'!$C$18,'P-Parametri'!$C$17*$C55,'P-Parametri'!$D$17*$C55))) -> 0 | H55: =IF(AND($C55<='P-Parametri'!$C$16,D55>E55-'P-Parametri'!$D$16),'P-Parametri'!$B$16,0) -> 0 | I55: =MAX(0,D55-E55-F55) -> 6802.0569 | J55: =IF(I55>0,'P-Parametri'!$B$20*$C55,0) -> 699.237 | K55: =$C55-I55-J55+H55+G55 -> 27460.556 | L55: =K55/$A55 -> 0.7132612 | M55: =1-(K57-K55)/1000 -> 0.60208709 | N55: ='P-Parametri'!$B$19+(1-'P-Parametri'!$B$19)*((IF(($A55*(1-'P-Parametri'!$B$19))<='P-Parametri'!$B$6,'P-Parametri'!$C$6,IF(($A55*(1-'P-Parametri'!$B$19))<='P-Parametri'!$B$7,'P-Parametri'!$C$7,'P-Parametri'!$C$8)))+(IF(($A55*(1-'P-Parametri'!$B$19))<='P-Parametri'!$C$12,0,IF(($A55*(1-'P-Parametri'!$B$19))<='P-Parametri'!$B$6,'P-Parametri'!$C$13/'P-Parametri'!$D$13,IF(($A55*(1-'P-Parametri'!$B$19))<='P-Parametri'!$B$7,'P-Parametri'!$B$14/'P-Parametri'!$C$14,0))))+(IF(AND(($A55*(1-'P-Parametri'!$B$19))>'P-Parametri'!$D$15,($A55*(1-'P-Parametri'!$B$19))<'P-Parametri'!$E$15),'P-Parametri'!$B$15/('P-Parametri'!$E$15-'P-Parametri'!$D$15),0))+'P-Parametri'!$B$20) -> 0.60208709 | O55: =M55-N55 -> 8.8817842e-16
A56: =39000 -> 39000 | B56: ='P-Parametri'!$B$19*$A56 -> 3584.1 | C56: =$A56-B56 -> 35415.9 | D56: =IF($C56<='P-Parametri'!$B$6,'P-Parametri'!$C$6*$C56,IF($C56<='P-Parametri'!$B$7,'P-Parametri'!$B$9+'P-Parametri'!$C$7*($C56-'P-Parametri'!$B$6),'P-Parametri'!$B$10+'P-Parametri'!$C$8*($C56-'P-Parametri'!$B$7))) -> 8887.247 | E56: =IF($C56<='P-Parametri'!$C$12,'P-Parametri'!$B$12,IF($C56<='P-Parametri'!$B$6,'P-Parametri'!$B$13+'P-Parametri'!$C$13*('P-Parametri'!$B$6-$C56)/'P-Parametri'!$D$13,IF($C56<='P-Parametri'!$B$7,'P-Parametri'!$B$14*('P-Parametri'!$B$7-$C56)/'P-Parametri'!$C$14,0))) -> 1266.165 | F56: =IF($C56<='P-Parametri'!$C$15,0,IF($C56<='P-Parametri'!$D$15,'P-Parametri'!$B$15,IF($C56<'P-Parametri'!$E$15,'P-Parametri'!$B$15*('P-Parametri'!$E$15-$C56)/('P-Parametri'!$E$15-'P-Parametri'!$D$15),0))) -> 573.0125 | G56: =IF($C56>'P-Parametri'!$D$18,0,IF($C56<='P-Parametri'!$B$18,'P-Parametri'!$B$17*$C56,IF($C56<='P-Parametri'!$C$18,'P-Parametri'!$C$17*$C56,'P-Parametri'!$D$17*$C56))) -> 0 | H56: =IF(AND($C56<='P-Parametri'!$C$16,D56>E56-'P-Parametri'!$D$16),'P-Parametri'!$B$16,0) -> 0 | I56: =MAX(0,D56-E56-F56) -> 7048.0695 | J56: =IF(I56>0,'P-Parametri'!$B$20*$C56,0) -> 708.318 | K56: =$C56-I56-J56+H56+G56 -> 27659.513 | L56: =K56/$A56 -> 0.70921827 | M56: =1-(K58-K56)/1000 -> 0.60208709 | N56: ='P-Parametri'!$B$19+(1-'P-Parametri'!$B$19)*((IF(($A56*(1-'P-Parametri'!$B$19))<='P-Parametri'!$B$6,'P-Parametri'!$C$6,IF(($A56*(1-'P-Parametri'!$B$19))<='P-Parametri'!$B$7,'P-Parametri'!$C$7,'P-Parametri'!$C$8)))+(IF(($A56*(1-'P-Parametri'!$B$19))<='P-Parametri'!$C$12,0,IF(($A56*(1-'P-Parametri'!$B$19))<='P-Parametri'!$B$6,'P-Parametri'!$C$13/'P-Parametri'!$D$13,IF(($A56*(1-'P-Parametri'!$B$19))<='P-Parametri'!$B$7,'P-Parametri'!$B$14/'P-Parametri'!$C$14,0))))+(IF(AND(($A56*(1-'P-Parametri'!$B$19))>'P-Parametri'!$D$15,($A56*(1-'P-Parametri'!$B$19))<'P-Parametri'!$E$15),'P-Parametri'!$B$15/('P-Parametri'!$E$15-'P-Parametri'!$D$15),0))+'P-Parametri'!$B$20) -> 0.60208709 | O56: =M56-N56 -> -2.8865799e-15
A57: =39500 -> 39500 | B57: ='P-Parametri'!$B$19*$A57 -> 3630.05 | C57: =$A57-B57 -> 35869.95 | D57: =IF($C57<='P-Parametri'!$B$6,'P-Parametri'!$C$6*$C57,IF($C57<='P-Parametri'!$B$7,'P-Parametri'!$B$9+'P-Parametri'!$C$7*($C57-'P-Parametri'!$B$6),'P-Parametri'!$B$10+'P-Parametri'!$C$8*($C57-'P-Parametri'!$B$7))) -> 9037.0835 | E57: =IF($C57<='P-Parametri'!$C$12,'P-Parametri'!$B$12,IF($C57<='P-Parametri'!$B$6,'P-Parametri'!$B$13+'P-Parametri'!$C$13*('P-Parametri'!$B$6-$C57)/'P-Parametri'!$D$13,IF($C57<='P-Parametri'!$B$7,'P-Parametri'!$B$14*('P-Parametri'!$B$7-$C57)/'P-Parametri'!$C$14,0))) -> 1226.7453 | F57: =IF($C57<='P-Parametri'!$C$15,0,IF($C57<='P-Parametri'!$D$15,'P-Parametri'!$B$15,IF($C57<'P-Parametri'!$E$15,'P-Parametri'!$B$15*('P-Parametri'!$E$15-$C57)/('P-Parametri'!$E$15-'P-Parametri'!$D$15),0))) -> 516.25625 | G57: =IF($C57>'P-Parametri'!$D$18,0,IF($C57<='P-Parametri'!$B$18,'P-Parametri'!$B$17*$C57,IF($C57<='P-Parametri'!$C$18,'P-Parametri'!$C$17*$C57,'P-Parametri'!$D$17*$C57))) -> 0 | H57: =IF(AND($C57<='P-Parametri'!$C$16,D57>E57-'P-Parametri'!$D$16),'P-Parametri'!$B$16,0) -> 0 | I57: =MAX(0,D57-E57-F57) -> 7294.082 | J57: =IF(I57>0,'P-Parametri'!$B$20*$C57,0) -> 717.399 | K57: =$C57-I57-J57+H57+G57 -> 27858.469 | L57: =K57/$A57 -> 0.7052777 | M57: =1-(K59-K57)/1000 -> 0.60208709 | N57: ='P-Parametri'!$B$19+(1-'P-Parametri'!$B$19)*((IF(($A57*(1-'P-Parametri'!$B$19))<='P-Parametri'!$B$6,'P-Parametri'!$C$6,IF(($A57*(1-'P-Parametri'!$B$19))<='P-Parametri'!$B$7,'P-Parametri'!$C$7,'P-Parametri'!$C$8)))+(IF(($A57*(1-'P-Parametri'!$B$19))<='P-Parametri'!$C$12,0,IF(($A57*(1-'P-Parametri'!$B$19))<='P-Parametri'!$B$6,'P-Parametri'!$C$13/'P-Parametri'!$D$13,IF(($A57*(1-'P-Parametri'!$B$19))<='P-Parametri'!$B$7,'P-Parametri'!$B$14/'P-Parametri'!$C$14,0))))+(IF(AND(($A57*(1-'P-Parametri'!$B$19))>'P-Parametri'!$D$15,($A57*(1-'P-Parametri'!$B$19))<'P-Parametri'!$E$15),'P-Parametri'!$B$15/('P-Parametri'!$E$15-'P-Parametri'!$D$15),0))+'P-Parametri'!$B$20) -> 0.60208709 | O57: =M57-N57 -> -2.8865799e-15
A58: =40000 -> 40000 | B58: ='P-Parametri'!$B$19*$A58 -> 3676 | C58: =$A58-B58 -> 36324 | D58: =IF($C58<='P-Parametri'!$B$6,'P-Parametri'!$C$6*$C58,IF($C58<='P-Parametri'!$B$7,'P-Parametri'!$B$9+'P-Parametri'!$C$7*($C58-'P-Parametri'!$B$6),'P-Parametri'!$B$10+'P-Parametri'!$C$8*($C58-'P-Parametri'!$B$7))) -> 9186.92 | E58: =IF($C58<='P-Parametri'!$C$12,'P-Parametri'!$B$12,IF($C58<='P-Parametri'!$B$6,'P-Parametri'!$B$13+'P-Parametri'!$C$13*('P-Parametri'!$B$6-$C58)/'P-Parametri'!$D$13,IF($C58<='P-Parametri'!$B$7,'P-Parametri'!$B$14*('P-Parametri'!$B$7-$C58)/'P-Parametri'!$C$14,0))) -> 1187.3255 | F58: =IF($C58<='P-Parametri'!$C$15,0,IF($C58<='P-Parametri'!$D$15,'P-Parametri'!$B$15,IF($C58<'P-Parametri'!$E$15,'P-Parametri'!$B$15*('P-Parametri'!$E$15-$C58)/('P-Parametri'!$E$15-'P-Parametri'!$D$15),0))) -> 459.5 | G58: =IF($C58>'P-Parametri'!$D$18,0,IF($C58<='P-Parametri'!$B$18,'P-Parametri'!$B$17*$C58,IF($C58<='P-Parametri'!$C$18,'P-Parametri'!$C$17*$C58,'P-Parametri'!$D$17*$C58))) -> 0 | H58: =IF(AND($C58<='P-Parametri'!$C$16,D58>E58-'P-Parametri'!$D$16),'P-Parametri'!$B$16,0) -> 0 | I58: =MAX(0,D58-E58-F58) -> 7540.0945 | J58: =IF(I58>0,'P-Parametri'!$B$20*$C58,0) -> 726.48 | K58: =$C58-I58-J58+H58+G58 -> 28057.425 | L58: =K58/$A58 -> 0.70143564 | M58: =1-(K60-K58)/1000 -> 0.60208709 | N58: ='P-Parametri'!$B$19+(1-'P-Parametri'!$B$19)*((IF(($A58*(1-'P-Parametri'!$B$19))<='P-Parametri'!$B$6,'P-Parametri'!$C$6,IF(($A58*(1-'P-Parametri'!$B$19))<='P-Parametri'!$B$7,'P-Parametri'!$C$7,'P-Parametri'!$C$8)))+(IF(($A58*(1-'P-Parametri'!$B$19))<='P-Parametri'!$C$12,0,IF(($A58*(1-'P-Parametri'!$B$19))<='P-Parametri'!$B$6,'P-Parametri'!$C$13/'P-Parametri'!$D$13,IF(($A58*(1-'P-Parametri'!$B$19))<='P-Parametri'!$B$7,'P-Parametri'!$B$14/'P-Parametri'!$C$14,0))))+(IF(AND(($A58*(1-'P-Parametri'!$B$19))>'P-Parametri'!$D$15,($A58*(1-'P-Parametri'!$B$19))<'P-Parametri'!$E$15),'P-Parametri'!$B$15/('P-Parametri'!$E$15-'P-Parametri'!$D$15),0))+'P-Parametri'!$B$20) -> 0.60208709 | O58: =M58-N58 -> 4.4408921e-15
A59: =40500 -> 40500 | B59: ='P-Parametri'!$B$19*$A59 -> 3721.95 | C59: =$A59-B59 -> 36778.05 | D59: =IF($C59<='P-Parametri'!$B$6,'P-Parametri'!$C$6*$C59,IF($C59<='P-Parametri'!$B$7,'P-Parametri'!$B$9+'P-Parametri'!$C$7*($C59-'P-Parametri'!$B$6),'P-Parametri'!$B$10+'P-Parametri'!$C$8*($C59-'P-Parametri'!$B$7))) -> 9336.7565 | E59: =IF($C59<='P-Parametri'!$C$12,'P-Parametri'!$B$12,IF($C59<='P-Parametri'!$B$6,'P-Parametri'!$B$13+'P-Parametri'!$C$13*('P-Parametri'!$B$6-$C59)/'P-Parametri'!$D$13,IF($C59<='P-Parametri'!$B$7,'P-Parametri'!$B$14*('P-Parametri'!$B$7-$C59)/'P-Parametri'!$C$14,0))) -> 1147.9057 | F59: =IF($C59<='P-Parametri'!$C$15,0,IF($C59<='P-Parametri'!$D$15,'P-Parametri'!$B$15,IF($C59<'P-Parametri'!$E$15,'P-Parametri'!$B$15*('P-Parametri'!$E$15-$C59)/('P-Parametri'!$E$15-'P-Parametri'!$D$15),0))) -> 402.74375 | G59: =IF($C59>'P-Parametri'!$D$18,0,IF($C59<='P-Parametri'!$B$18,'P-Parametri'!$B$17*$C59,IF($C59<='P-Parametri'!$C$18,'P-Parametri'!$C$17*$C59,'P-Parametri'!$D$17*$C59))) -> 0 | H59: =IF(AND($C59<='P-Parametri'!$C$16,D59>E59-'P-Parametri'!$D$16),'P-Parametri'!$B$16,0) -> 0 | I59: =MAX(0,D59-E59-F59) -> 7786.1071 | J59: =IF(I59>0,'P-Parametri'!$B$20*$C59,0) -> 735.561 | K59: =$C59-I59-J59+H59+G59 -> 28256.382 | L59: =K59/$A59 -> 0.69768844 | M59: =1-(K61-K59)/1000 -> 0.60208709 | N59: ='P-Parametri'!$B$19+(1-'P-Parametri'!$B$19)*((IF(($A59*(1-'P-Parametri'!$B$19))<='P-Parametri'!$B$6,'P-Parametri'!$C$6,IF(($A59*(1-'P-Parametri'!$B$19))<='P-Parametri'!$B$7,'P-Parametri'!$C$7,'P-Parametri'!$C$8)))+(IF(($A59*(1-'P-Parametri'!$B$19))<='P-Parametri'!$C$12,0,IF(($A59*(1-'P-Parametri'!$B$19))<='P-Parametri'!$B$6,'P-Parametri'!$C$13/'P-Parametri'!$D$13,IF(($A59*(1-'P-Parametri'!$B$19))<='P-Parametri'!$B$7,'P-Parametri'!$B$14/'P-Parametri'!$C$14,0))))+(IF(AND(($A59*(1-'P-Parametri'!$B$19))>'P-Parametri'!$D$15,($A59*(1-'P-Parametri'!$B$19))<'P-Parametri'!$E$15),'P-Parametri'!$B$15/('P-Parametri'!$E$15-'P-Parametri'!$D$15),0))+'P-Parametri'!$B$20) -> 0.60208709 | O59: =M59-N59 -> 8.8817842e-16
A60: =41000 -> 41000 | B60: ='P-Parametri'!$B$19*$A60 -> 3767.9 | C60: =$A60-B60 -> 37232.1 | D60: =IF($C60<='P-Parametri'!$B$6,'P-Parametri'!$C$6*$C60,IF($C60<='P-Parametri'!$B$7,'P-Parametri'!$B$9+'P-Parametri'!$C$7*($C60-'P-Parametri'!$B$6),'P-Parametri'!$B$10+'P-Parametri'!$C$8*($C60-'P-Parametri'!$B$7))) -> 9486.593 | E60: =IF($C60<='P-Parametri'!$C$12,'P-Parametri'!$B$12,IF($C60<='P-Parametri'!$B$6,'P-Parametri'!$B$13+'P-Parametri'!$C$13*('P-Parametri'!$B$6-$C60)/'P-Parametri'!$D$13,IF($C60<='P-Parametri'!$B$7,'P-Parametri'!$B$14*('P-Parametri'!$B$7-$C60)/'P-Parametri'!$C$14,0))) -> 1108.4859 | F60: =IF($C60<='P-Parametri'!$C$15,0,IF($C60<='P-Parametri'!$D$15,'P-Parametri'!$B$15,IF($C60<'P-Parametri'!$E$15,'P-Parametri'!$B$15*('P-Parametri'!$E$15-$C60)/('P-Parametri'!$E$15-'P-Parametri'!$D$15),0))) -> 345.9875 | G60: =IF($C60>'P-Parametri'!$D$18,0,IF($C60<='P-Parametri'!$B$18,'P-Parametri'!$B$17*$C60,IF($C60<='P-Parametri'!$C$18,'P-Parametri'!$C$17*$C60,'P-Parametri'!$D$17*$C60))) -> 0 | H60: =IF(AND($C60<='P-Parametri'!$C$16,D60>E60-'P-Parametri'!$D$16),'P-Parametri'!$B$16,0) -> 0 | I60: =MAX(0,D60-E60-F60) -> 8032.1196 | J60: =IF(I60>0,'P-Parametri'!$B$20*$C60,0) -> 744.642 | K60: =$C60-I60-J60+H60+G60 -> 28455.338 | L60: =K60/$A60 -> 0.69403264 | M60: =1-(K62-K60)/1000 -> 0.60208709 | N60: ='P-Parametri'!$B$19+(1-'P-Parametri'!$B$19)*((IF(($A60*(1-'P-Parametri'!$B$19))<='P-Parametri'!$B$6,'P-Parametri'!$C$6,IF(($A60*(1-'P-Parametri'!$B$19))<='P-Parametri'!$B$7,'P-Parametri'!$C$7,'P-Parametri'!$C$8)))+(IF(($A60*(1-'P-Parametri'!$B$19))<='P-Parametri'!$C$12,0,IF(($A60*(1-'P-Parametri'!$B$19))<='P-Parametri'!$B$6,'P-Parametri'!$C$13/'P-Parametri'!$D$13,IF(($A60*(1-'P-Parametri'!$B$19))<='P-Parametri'!$B$7,'P-Parametri'!$B$14/'P-Parametri'!$C$14,0))))+(IF(AND(($A60*(1-'P-Parametri'!$B$19))>'P-Parametri'!$D$15,($A60*(1-'P-Parametri'!$B$19))<'P-Parametri'!$E$15),'P-Parametri'!$B$15/('P-Parametri'!$E$15-'P-Parametri'!$D$15),0))+'P-Parametri'!$B$20) -> 0.60208709 | O60: =M60-N60 -> -2.8865799e-15
A61: =41500 -> 41500 | B61: ='P-Parametri'!$B$19*$A61 -> 3813.85 | C61: =$A61-B61 -> 37686.15 | D61: =IF($C61<='P-Parametri'!$B$6,'P-Parametri'!$C$6*$C61,IF($C61<='P-Parametri'!$B$7,'P-Parametri'!$B$9+'P-Parametri'!$C$7*($C61-'P-Parametri'!$B$6),'P-Parametri'!$B$10+'P-Parametri'!$C$8*($C61-'P-Parametri'!$B$7))) -> 9636.4295 | E61: =IF($C61<='P-Parametri'!$C$12,'P-Parametri'!$B$12,IF($C61<='P-Parametri'!$B$6,'P-Parametri'!$B$13+'P-Parametri'!$C$13*('P-Parametri'!$B$6-$C61)/'P-Parametri'!$D$13,IF($C61<='P-Parametri'!$B$7,'P-Parametri'!$B$14*('P-Parametri'!$B$7-$C61)/'P-Parametri'!$C$14,0))) -> 1069.0661 | F61: =IF($C61<='P-Parametri'!$C$15,0,IF($C61<='P-Parametri'!$D$15,'P-Parametri'!$B$15,IF($C61<'P-Parametri'!$E$15,'P-Parametri'!$B$15*('P-Parametri'!$E$15-$C61)/('P-Parametri'!$E$15-'P-Parametri'!$D$15),0))) -> 289.23125 | G61: =IF($C61>'P-Parametri'!$D$18,0,IF($C61<='P-Parametri'!$B$18,'P-Parametri'!$B$17*$C61,IF($C61<='P-Parametri'!$C$18,'P-Parametri'!$C$17*$C61,'P-Parametri'!$D$17*$C61))) -> 0 | H61: =IF(AND($C61<='P-Parametri'!$C$16,D61>E61-'P-Parametri'!$D$16),'P-Parametri'!$B$16,0) -> 0 | I61: =MAX(0,D61-E61-F61) -> 8278.1322 | J61: =IF(I61>0,'P-Parametri'!$B$20*$C61,0) -> 753.723 | K61: =$C61-I61-J61+H61+G61 -> 28654.295 | L61: =K61/$A61 -> 0.69046494 | M61: =1-(K63-K61)/1000 -> 0.60208709 | N61: ='P-Parametri'!$B$19+(1-'P-Parametri'!$B$19)*((IF(($A61*(1-'P-Parametri'!$B$19))<='P-Parametri'!$B$6,'P-Parametri'!$C$6,IF(($A61*(1-'P-Parametri'!$B$19))<='P-Parametri'!$B$7,'P-Parametri'!$C$7,'P-Parametri'!$C$8)))+(IF(($A61*(1-'P-Parametri'!$B$19))<='P-Parametri'!$C$12,0,IF(($A61*(1-'P-Parametri'!$B$19))<='P-Parametri'!$B$6,'P-Parametri'!$C$13/'P-Parametri'!$D$13,IF(($A61*(1-'P-Parametri'!$B$19))<='P-Parametri'!$B$7,'P-Parametri'!$B$14/'P-Parametri'!$C$14,0))))+(IF(AND(($A61*(1-'P-Parametri'!$B$19))>'P-Parametri'!$D$15,($A61*(1-'P-Parametri'!$B$19))<'P-Parametri'!$E$15),'P-Parametri'!$B$15/('P-Parametri'!$E$15-'P-Parametri'!$D$15),0))+'P-Parametri'!$B$20) -> 0.60208709 | O61: =M61-N61 -> -2.8865799e-15
A62: =42000 -> 42000 | B62: ='P-Parametri'!$B$19*$A62 -> 3859.8 | C62: =$A62-B62 -> 38140.2 | D62: =IF($C62<='P-Parametri'!$B$6,'P-Parametri'!$C$6*$C62,IF($C62<='P-Parametri'!$B$7,'P-Parametri'!$B$9+'P-Parametri'!$C$7*($C62-'P-Parametri'!$B$6),'P-Parametri'!$B$10+'P-Parametri'!$C$8*($C62-'P-Parametri'!$B$7))) -> 9786.266 | E62: =IF($C62<='P-Parametri'!$C$12,'P-Parametri'!$B$12,IF($C62<='P-Parametri'!$B$6,'P-Parametri'!$B$13+'P-Parametri'!$C$13*('P-Parametri'!$B$6-$C62)/'P-Parametri'!$D$13,IF($C62<='P-Parametri'!$B$7,'P-Parametri'!$B$14*('P-Parametri'!$B$7-$C62)/'P-Parametri'!$C$14,0))) -> 1029.6463 | F62: =IF($C62<='P-Parametri'!$C$15,0,IF($C62<='P-Parametri'!$D$15,'P-Parametri'!$B$15,IF($C62<'P-Parametri'!$E$15,'P-Parametri'!$B$15*('P-Parametri'!$E$15-$C62)/('P-Parametri'!$E$15-'P-Parametri'!$D$15),0))) -> 232.475 | G62: =IF($C62>'P-Parametri'!$D$18,0,IF($C62<='P-Parametri'!$B$18,'P-Parametri'!$B$17*$C62,IF($C62<='P-Parametri'!$C$18,'P-Parametri'!$C$17*$C62,'P-Parametri'!$D$17*$C62))) -> 0 | H62: =IF(AND($C62<='P-Parametri'!$C$16,D62>E62-'P-Parametri'!$D$16),'P-Parametri'!$B$16,0) -> 0 | I62: =MAX(0,D62-E62-F62) -> 8524.1447 | J62: =IF(I62>0,'P-Parametri'!$B$20*$C62,0) -> 762.804 | K62: =$C62-I62-J62+H62+G62 -> 28853.251 | L62: =K62/$A62 -> 0.68698217 | M62: =1-(K64-K62)/1000 -> 0.60208709 | N62: ='P-Parametri'!$B$19+(1-'P-Parametri'!$B$19)*((IF(($A62*(1-'P-Parametri'!$B$19))<='P-Parametri'!$B$6,'P-Parametri'!$C$6,IF(($A62*(1-'P-Parametri'!$B$19))<='P-Parametri'!$B$7,'P-Parametri'!$C$7,'P-Parametri'!$C$8)))+(IF(($A62*(1-'P-Parametri'!$B$19))<='P-Parametri'!$C$12,0,IF(($A62*(1-'P-Parametri'!$B$19))<='P-Parametri'!$B$6,'P-Parametri'!$C$13/'P-Parametri'!$D$13,IF(($A62*(1-'P-Parametri'!$B$19))<='P-Parametri'!$B$7,'P-Parametri'!$B$14/'P-Parametri'!$C$14,0))))+(IF(AND(($A62*(1-'P-Parametri'!$B$19))>'P-Parametri'!$D$15,($A62*(1-'P-Parametri'!$B$19))<'P-Parametri'!$E$15),'P-Parametri'!$B$15/('P-Parametri'!$E$15-'P-Parametri'!$D$15),0))+'P-Parametri'!$B$20) -> 0.60208709 | O62: =M62-N62 -> 8.8817842e-16
A63: =42500 -> 42500 | B63: ='P-Parametri'!$B$19*$A63 -> 3905.75 | C63: =$A63-B63 -> 38594.25 | D63: =IF($C63<='P-Parametri'!$B$6,'P-Parametri'!$C$6*$C63,IF($C63<='P-Parametri'!$B$7,'P-Parametri'!$B$9+'P-Parametri'!$C$7*($C63-'P-Parametri'!$B$6),'P-Parametri'!$B$10+'P-Parametri'!$C$8*($C63-'P-Parametri'!$B$7))) -> 9936.1025 | E63: =IF($C63<='P-Parametri'!$C$12,'P-Parametri'!$B$12,IF($C63<='P-Parametri'!$B$6,'P-Parametri'!$B$13+'P-Parametri'!$C$13*('P-Parametri'!$B$6-$C63)/'P-Parametri'!$D$13,IF($C63<='P-Parametri'!$B$7,'P-Parametri'!$B$14*('P-Parametri'!$B$7-$C63)/'P-Parametri'!$C$14,0))) -> 990.22648 | F63: =IF($C63<='P-Parametri'!$C$15,0,IF($C63<='P-Parametri'!$D$15,'P-Parametri'!$B$15,IF($C63<'P-Parametri'!$E$15,'P-Parametri'!$B$15*('P-Parametri'!$E$15-$C63)/('P-Parametri'!$E$15-'P-Parametri'!$D$15),0))) -> 175.71875 | G63: =IF($C63>'P-Parametri'!$D$18,0,IF($C63<='P-Parametri'!$B$18,'P-Parametri'!$B$17*$C63,IF($C63<='P-Parametri'!$C$18,'P-Parametri'!$C$17*$C63,'P-Parametri'!$D$17*$C63))) -> 0 | H63: =IF(AND($C63<='P-Parametri'!$C$16,D63>E63-'P-Parametri'!$D$16),'P-Parametri'!$B$16,0) -> 0 | I63: =MAX(0,D63-E63-F63) -> 8770.1573 | J63: =IF(I63>0,'P-Parametri'!$B$20*$C63,0) -> 771.885 | K63: =$C63-I63-J63+H63+G63 -> 29052.208 | L63: =K63/$A63 -> 0.68358136 | M63: =1-(K65-K63)/1000 -> 0.60208709 | N63: ='P-Parametri'!$B$19+(1-'P-Parametri'!$B$19)*((IF(($A63*(1-'P-Parametri'!$B$19))<='P-Parametri'!$B$6,'P-Parametri'!$C$6,IF(($A63*(1-'P-Parametri'!$B$19))<='P-Parametri'!$B$7,'P-Parametri'!$C$7,'P-Parametri'!$C$8)))+(IF(($A63*(1-'P-Parametri'!$B$19))<='P-Parametri'!$C$12,0,IF(($A63*(1-'P-Parametri'!$B$19))<='P-Parametri'!$B$6,'P-Parametri'!$C$13/'P-Parametri'!$D$13,IF(($A63*(1-'P-Parametri'!$B$19))<='P-Parametri'!$B$7,'P-Parametri'!$B$14/'P-Parametri'!$C$14,0))))+(IF(AND(($A63*(1-'P-Parametri'!$B$19))>'P-Parametri'!$D$15,($A63*(1-'P-Parametri'!$B$19))<'P-Parametri'!$E$15),'P-Parametri'!$B$15/('P-Parametri'!$E$15-'P-Parametri'!$D$15),0))+'P-Parametri'!$B$20) -> 0.60208709 | O63: =M63-N63 -> 8.8817842e-16
A64: =43000 -> 43000 | B64: ='P-Parametri'!$B$19*$A64 -> 3951.7 | C64: =$A64-B64 -> 39048.3 | D64: =IF($C64<='P-Parametri'!$B$6,'P-Parametri'!$C$6*$C64,IF($C64<='P-Parametri'!$B$7,'P-Parametri'!$B$9+'P-Parametri'!$C$7*($C64-'P-Parametri'!$B$6),'P-Parametri'!$B$10+'P-Parametri'!$C$8*($C64-'P-Parametri'!$B$7))) -> 10085.939 | E64: =IF($C64<='P-Parametri'!$C$12,'P-Parametri'!$B$12,IF($C64<='P-Parametri'!$B$6,'P-Parametri'!$B$13+'P-Parametri'!$C$13*('P-Parametri'!$B$6-$C64)/'P-Parametri'!$D$13,IF($C64<='P-Parametri'!$B$7,'P-Parametri'!$B$14*('P-Parametri'!$B$7-$C64)/'P-Parametri'!$C$14,0))) -> 950.80668 | F64: =IF($C64<='P-Parametri'!$C$15,0,IF($C64<='P-Parametri'!$D$15,'P-Parametri'!$B$15,IF($C64<'P-Parametri'!$E$15,'P-Parametri'!$B$15*('P-Parametri'!$E$15-$C64)/('P-Parametri'!$E$15-'P-Parametri'!$D$15),0))) -> 118.9625 | G64: =IF($C64>'P-Parametri'!$D$18,0,IF($C64<='P-Parametri'!$B$18,'P-Parametri'!$B$17*$C64,IF($C64<='P-Parametri'!$C$18,'P-Parametri'!$C$17*$C64,'P-Parametri'!$D$17*$C64))) -> 0 | H64: =IF(AND($C64<='P-Parametri'!$C$16,D64>E64-'P-Parametri'!$D$16),'P-Parametri'!$B$16,0) -> 0 | I64: =MAX(0,D64-E64-F64) -> 9016.1698 | J64: =IF(I64>0,'P-Parametri'!$B$20*$C64,0) -> 780.966 | K64: =$C64-I64-J64+H64+G64 -> 29251.164 | L64: =K64/$A64 -> 0.68025963 | M64: =1-(K66-K64)/1000 -> 0.60208709 | N64: ='P-Parametri'!$B$19+(1-'P-Parametri'!$B$19)*((IF(($A64*(1-'P-Parametri'!$B$19))<='P-Parametri'!$B$6,'P-Parametri'!$C$6,IF(($A64*(1-'P-Parametri'!$B$19))<='P-Parametri'!$B$7,'P-Parametri'!$C$7,'P-Parametri'!$C$8)))+(IF(($A64*(1-'P-Parametri'!$B$19))<='P-Parametri'!$C$12,0,IF(($A64*(1-'P-Parametri'!$B$19))<='P-Parametri'!$B$6,'P-Parametri'!$C$13/'P-Parametri'!$D$13,IF(($A64*(1-'P-Parametri'!$B$19))<='P-Parametri'!$B$7,'P-Parametri'!$B$14/'P-Parametri'!$C$14,0))))+(IF(AND(($A64*(1-'P-Parametri'!$B$19))>'P-Parametri'!$D$15,($A64*(1-'P-Parametri'!$B$19))<'P-Parametri'!$E$15),'P-Parametri'!$B$15/('P-Parametri'!$E$15-'P-Parametri'!$D$15),0))+'P-Parametri'!$B$20) -> 0.60208709 | O64: =M64-N64 -> 8.8817842e-16
A65: =43500 -> 43500 | B65: ='P-Parametri'!$B$19*$A65 -> 3997.65 | C65: =$A65-B65 -> 39502.35 | D65: =IF($C65<='P-Parametri'!$B$6,'P-Parametri'!$C$6*$C65,IF($C65<='P-Parametri'!$B$7,'P-Parametri'!$B$9+'P-Parametri'!$C$7*($C65-'P-Parametri'!$B$6),'P-Parametri'!$B$10+'P-Parametri'!$C$8*($C65-'P-Parametri'!$B$7))) -> 10235.775 | E65: =IF($C65<='P-Parametri'!$C$12,'P-Parametri'!$B$12,IF($C65<='P-Parametri'!$B$6,'P-Parametri'!$B$13+'P-Parametri'!$C$13*('P-Parametri'!$B$6-$C65)/'P-Parametri'!$D$13,IF($C65<='P-Parametri'!$B$7,'P-Parametri'!$B$14*('P-Parametri'!$B$7-$C65)/'P-Parametri'!$C$14,0))) -> 911.38689 | F65: =IF($C65<='P-Parametri'!$C$15,0,IF($C65<='P-Parametri'!$D$15,'P-Parametri'!$B$15,IF($C65<'P-Parametri'!$E$15,'P-Parametri'!$B$15*('P-Parametri'!$E$15-$C65)/('P-Parametri'!$E$15-'P-Parametri'!$D$15),0))) -> 62.20625 | G65: =IF($C65>'P-Parametri'!$D$18,0,IF($C65<='P-Parametri'!$B$18,'P-Parametri'!$B$17*$C65,IF($C65<='P-Parametri'!$C$18,'P-Parametri'!$C$17*$C65,'P-Parametri'!$D$17*$C65))) -> 0 | H65: =IF(AND($C65<='P-Parametri'!$C$16,D65>E65-'P-Parametri'!$D$16),'P-Parametri'!$B$16,0) -> 0 | I65: =MAX(0,D65-E65-F65) -> 9262.1824 | J65: =IF(I65>0,'P-Parametri'!$B$20*$C65,0) -> 790.047 | K65: =$C65-I65-J65+H65+G65 -> 29450.121 | L65: =K65/$A65 -> 0.67701427 | M65: =1-(K67-K65)/1000 -> 0.55078084 | N65: ='P-Parametri'!$B$19+(1-'P-Parametri'!$B$19)*((IF(($A65*(1-'P-Parametri'!$B$19))<='P-Parametri'!$B$6,'P-Parametri'!$C$6,IF(($A65*(1-'P-Parametri'!$B$19))<='P-Parametri'!$B$7,'P-Parametri'!$C$7,'P-Parametri'!$C$8)))+(IF(($A65*(1-'P-Parametri'!$B$19))<='P-Parametri'!$C$12,0,IF(($A65*(1-'P-Parametri'!$B$19))<='P-Parametri'!$B$6,'P-Parametri'!$C$13/'P-Parametri'!$D$13,IF(($A65*(1-'P-Parametri'!$B$19))<='P-Parametri'!$B$7,'P-Parametri'!$B$14/'P-Parametri'!$C$14,0))))+(IF(AND(($A65*(1-'P-Parametri'!$B$19))>'P-Parametri'!$D$15,($A65*(1-'P-Parametri'!$B$19))<'P-Parametri'!$E$15),'P-Parametri'!$B$15/('P-Parametri'!$E$15-'P-Parametri'!$D$15),0))+'P-Parametri'!$B$20) -> 0.60208709 | O65: =M65-N65 -> -0.05130625
A66: =44000 -> 44000 | B66: ='P-Parametri'!$B$19*$A66 -> 4043.6 | C66: =$A66-B66 -> 39956.4 | D66: =IF($C66<='P-Parametri'!$B$6,'P-Parametri'!$C$6*$C66,IF($C66<='P-Parametri'!$B$7,'P-Parametri'!$B$9+'P-Parametri'!$C$7*($C66-'P-Parametri'!$B$6),'P-Parametri'!$B$10+'P-Parametri'!$C$8*($C66-'P-Parametri'!$B$7))) -> 10385.612 | E66: =IF($C66<='P-Parametri'!$C$12,'P-Parametri'!$B$12,IF($C66<='P-Parametri'!$B$6,'P-Parametri'!$B$13+'P-Parametri'!$C$13*('P-Parametri'!$B$6-$C66)/'P-Parametri'!$D$13,IF($C66<='P-Parametri'!$B$7,'P-Parametri'!$B$14*('P-Parametri'!$B$7-$C66)/'P-Parametri'!$C$14,0))) -> 871.96709 | F66: =IF($C66<='P-Parametri'!$C$15,0,IF($C66<='P-Parametri'!$D$15,'P-Parametri'!$B$15,IF($C66<'P-Parametri'!$E$15,'P-Parametri'!$B$15*('P-Parametri'!$E$15-$C66)/('P-Parametri'!$E$15-'P-Parametri'!$D$15),0))) -> 5.45 | G66: =IF($C66>'P-Parametri'!$D$18,0,IF($C66<='P-Parametri'!$B$18,'P-Parametri'!$B$17*$C66,IF($C66<='P-Parametri'!$C$18,'P-Parametri'!$C$17*$C66,'P-Parametri'!$D$17*$C66))) -> 0 | H66: =IF(AND($C66<='P-Parametri'!$C$16,D66>E66-'P-Parametri'!$D$16),'P-Parametri'!$B$16,0) -> 0 | I66: =MAX(0,D66-E66-F66) -> 9508.1949 | J66: =IF(I66>0,'P-Parametri'!$B$20*$C66,0) -> 799.128 | K66: =$C66-I66-J66+H66+G66 -> 29649.077 | L66: =K66/$A66 -> 0.67384266 | M66: =1-(K68-K66)/1000 -> 0.49402459 | N66: ='P-Parametri'!$B$19+(1-'P-Parametri'!$B$19)*((IF(($A66*(1-'P-Parametri'!$B$19))<='P-Parametri'!$B$6,'P-Parametri'!$C$6,IF(($A66*(1-'P-Parametri'!$B$19))<='P-Parametri'!$B$7,'P-Parametri'!$C$7,'P-Parametri'!$C$8)))+(IF(($A66*(1-'P-Parametri'!$B$19))<='P-Parametri'!$C$12,0,IF(($A66*(1-'P-Parametri'!$B$19))<='P-Parametri'!$B$6,'P-Parametri'!$C$13/'P-Parametri'!$D$13,IF(($A66*(1-'P-Parametri'!$B$19))<='P-Parametri'!$B$7,'P-Parametri'!$B$14/'P-Parametri'!$C$14,0))))+(IF(AND(($A66*(1-'P-Parametri'!$B$19))>'P-Parametri'!$D$15,($A66*(1-'P-Parametri'!$B$19))<'P-Parametri'!$E$15),'P-Parametri'!$B$15/('P-Parametri'!$E$15-'P-Parametri'!$D$15),0))+'P-Parametri'!$B$20) -> 0.60208709 | O66: =M66-N66 -> -0.1080625
A67: =44500 -> 44500 | B67: ='P-Parametri'!$B$19*$A67 -> 4089.55 | C67: =$A67-B67 -> 40410.45 | D67: =IF($C67<='P-Parametri'!$B$6,'P-Parametri'!$C$6*$C67,IF($C67<='P-Parametri'!$B$7,'P-Parametri'!$B$9+'P-Parametri'!$C$7*($C67-'P-Parametri'!$B$6),'P-Parametri'!$B$10+'P-Parametri'!$C$8*($C67-'P-Parametri'!$B$7))) -> 10535.448 | E67: =IF($C67<='P-Parametri'!$C$12,'P-Parametri'!$B$12,IF($C67<='P-Parametri'!$B$6,'P-Parametri'!$B$13+'P-Parametri'!$C$13*('P-Parametri'!$B$6-$C67)/'P-Parametri'!$D$13,IF($C67<='P-Parametri'!$B$7,'P-Parametri'!$B$14*('P-Parametri'!$B$7-$C67)/'P-Parametri'!$C$14,0))) -> 832.5473 | F67: =IF($C67<='P-Parametri'!$C$15,0,IF($C67<='P-Parametri'!$D$15,'P-Parametri'!$B$15,IF($C67<'P-Parametri'!$E$15,'P-Parametri'!$B$15*('P-Parametri'!$E$15-$C67)/('P-Parametri'!$E$15-'P-Parametri'!$D$15),0))) -> 0 | G67: =IF($C67>'P-Parametri'!$D$18,0,IF($C67<='P-Parametri'!$B$18,'P-Parametri'!$B$17*$C67,IF($C67<='P-Parametri'!$C$18,'P-Parametri'!$C$17*$C67,'P-Parametri'!$D$17*$C67))) -> 0 | H67: =IF(AND($C67<='P-Parametri'!$C$16,D67>E67-'P-Parametri'!$D$16),'P-Parametri'!$B$16,0) -> 0 | I67: =MAX(0,D67-E67-F67) -> 9702.9012 | J67: =IF(I67>0,'P-Parametri'!$B$20*$C67,0) -> 808.209 | K67: =$C67-I67-J67+H67+G67 -> 29899.34 | L67: =K67/$A67 -> 0.67189528 | M67: =1-(K69-K67)/1000 -> 0.48857459 | N67: ='P-Parametri'!$B$19+(1-'P-Parametri'!$B$19)*((IF(($A67*(1-'P-Parametri'!$B$19))<='P-Parametri'!$B$6,'P-Parametri'!$C$6,IF(($A67*(1-'P-Parametri'!$B$19))<='P-Parametri'!$B$7,'P-Parametri'!$C$7,'P-Parametri'!$C$8)))+(IF(($A67*(1-'P-Parametri'!$B$19))<='P-Parametri'!$C$12,0,IF(($A67*(1-'P-Parametri'!$B$19))<='P-Parametri'!$B$6,'P-Parametri'!$C$13/'P-Parametri'!$D$13,IF(($A67*(1-'P-Parametri'!$B$19))<='P-Parametri'!$B$7,'P-Parametri'!$B$14/'P-Parametri'!$C$14,0))))+(IF(AND(($A67*(1-'P-Parametri'!$B$19))>'P-Parametri'!$D$15,($A67*(1-'P-Parametri'!$B$19))<'P-Parametri'!$E$15),'P-Parametri'!$B$15/('P-Parametri'!$E$15-'P-Parametri'!$D$15),0))+'P-Parametri'!$B$20) -> 0.48857459 | O67: =M67-N67 -> 0
A68: =45000 -> 45000 | B68: ='P-Parametri'!$B$19*$A68 -> 4135.5 | C68: =$A68-B68 -> 40864.5 | D68: =IF($C68<='P-Parametri'!$B$6,'P-Parametri'!$C$6*$C68,IF($C68<='P-Parametri'!$B$7,'P-Parametri'!$B$9+'P-Parametri'!$C$7*($C68-'P-Parametri'!$B$6),'P-Parametri'!$B$10+'P-Parametri'!$C$8*($C68-'P-Parametri'!$B$7))) -> 10685.285 | E68: =IF($C68<='P-Parametri'!$C$12,'P-Parametri'!$B$12,IF($C68<='P-Parametri'!$B$6,'P-Parametri'!$B$13+'P-Parametri'!$C$13*('P-Parametri'!$B$6-$C68)/'P-Parametri'!$D$13,IF($C68<='P-Parametri'!$B$7,'P-Parametri'!$B$14*('P-Parametri'!$B$7-$C68)/'P-Parametri'!$C$14,0))) -> 793.1275 | F68: =IF($C68<='P-Parametri'!$C$15,0,IF($C68<='P-Parametri'!$D$15,'P-Parametri'!$B$15,IF($C68<'P-Parametri'!$E$15,'P-Parametri'!$B$15*('P-Parametri'!$E$15-$C68)/('P-Parametri'!$E$15-'P-Parametri'!$D$15),0))) -> 0 | G68: =IF($C68>'P-Parametri'!$D$18,0,IF($C68<='P-Parametri'!$B$18,'P-Parametri'!$B$17*$C68,IF($C68<='P-Parametri'!$C$18,'P-Parametri'!$C$17*$C68,'P-Parametri'!$D$17*$C68))) -> 0 | H68: =IF(AND($C68<='P-Parametri'!$C$16,D68>E68-'P-Parametri'!$D$16),'P-Parametri'!$B$16,0) -> 0 | I68: =MAX(0,D68-E68-F68) -> 9892.1575 | J68: =IF(I68>0,'P-Parametri'!$B$20*$C68,0) -> 817.29 | K68: =$C68-I68-J68+H68+G68 -> 30155.052 | L68: =K68/$A68 -> 0.67011228 | M68: =1-(K70-K68)/1000 -> 0.48857459 | N68: ='P-Parametri'!$B$19+(1-'P-Parametri'!$B$19)*((IF(($A68*(1-'P-Parametri'!$B$19))<='P-Parametri'!$B$6,'P-Parametri'!$C$6,IF(($A68*(1-'P-Parametri'!$B$19))<='P-Parametri'!$B$7,'P-Parametri'!$C$7,'P-Parametri'!$C$8)))+(IF(($A68*(1-'P-Parametri'!$B$19))<='P-Parametri'!$C$12,0,IF(($A68*(1-'P-Parametri'!$B$19))<='P-Parametri'!$B$6,'P-Parametri'!$C$13/'P-Parametri'!$D$13,IF(($A68*(1-'P-Parametri'!$B$19))<='P-Parametri'!$B$7,'P-Parametri'!$B$14/'P-Parametri'!$C$14,0))))+(IF(AND(($A68*(1-'P-Parametri'!$B$19))>'P-Parametri'!$D$15,($A68*(1-'P-Parametri'!$B$19))<'P-Parametri'!$E$15),'P-Parametri'!$B$15/('P-Parametri'!$E$15-'P-Parametri'!$D$15),0))+'P-Parametri'!$B$20) -> 0.48857459 | O68: =M68-N68 -> 0
A69: =45500 -> 45500 | B69: ='P-Parametri'!$B$19*$A69 -> 4181.45 | C69: =$A69-B69 -> 41318.55 | D69: =IF($C69<='P-Parametri'!$B$6,'P-Parametri'!$C$6*$C69,IF($C69<='P-Parametri'!$B$7,'P-Parametri'!$B$9+'P-Parametri'!$C$7*($C69-'P-Parametri'!$B$6),'P-Parametri'!$B$10+'P-Parametri'!$C$8*($C69-'P-Parametri'!$B$7))) -> 10835.122 | E69: =IF($C69<='P-Parametri'!$C$12,'P-Parametri'!$B$12,IF($C69<='P-Parametri'!$B$6,'P-Parametri'!$B$13+'P-Parametri'!$C$13*('P-Parametri'!$B$6-$C69)/'P-Parametri'!$D$13,IF($C69<='P-Parametri'!$B$7,'P-Parametri'!$B$14*('P-Parametri'!$B$7-$C69)/'P-Parametri'!$C$14,0))) -> 753.7077 | F69: =IF($C69<='P-Parametri'!$C$15,0,IF($C69<='P-Parametri'!$D$15,'P-Parametri'!$B$15,IF($C69<'P-Parametri'!$E$15,'P-Parametri'!$B$15*('P-Parametri'!$E$15-$C69)/('P-Parametri'!$E$15-'P-Parametri'!$D$15),0))) -> 0 | G69: =IF($C69>'P-Parametri'!$D$18,0,IF($C69<='P-Parametri'!$B$18,'P-Parametri'!$B$17*$C69,IF($C69<='P-Parametri'!$C$18,'P-Parametri'!$C$17*$C69,'P-Parametri'!$D$17*$C69))) -> 0 | H69: =IF(AND($C69<='P-Parametri'!$C$16,D69>E69-'P-Parametri'!$D$16),'P-Parametri'!$B$16,0) -> 0 | I69: =MAX(0,D69-E69-F69) -> 10081.414 | J69: =IF(I69>0,'P-Parametri'!$B$20*$C69,0) -> 826.371 | K69: =$C69-I69-J69+H69+G69 -> 30410.765 | L69: =K69/$A69 -> 0.66836847 | M69: =1-(K71-K69)/1000 -> 0.48857459 | N69: ='P-Parametri'!$B$19+(1-'P-Parametri'!$B$19)*((IF(($A69*(1-'P-Parametri'!$B$19))<='P-Parametri'!$B$6,'P-Parametri'!$C$6,IF(($A69*(1-'P-Parametri'!$B$19))<='P-Parametri'!$B$7,'P-Parametri'!$C$7,'P-Parametri'!$C$8)))+(IF(($A69*(1-'P-Parametri'!$B$19))<='P-Parametri'!$C$12,0,IF(($A69*(1-'P-Parametri'!$B$19))<='P-Parametri'!$B$6,'P-Parametri'!$C$13/'P-Parametri'!$D$13,IF(($A69*(1-'P-Parametri'!$B$19))<='P-Parametri'!$B$7,'P-Parametri'!$B$14/'P-Parametri'!$C$14,0))))+(IF(AND(($A69*(1-'P-Parametri'!$B$19))>'P-Parametri'!$D$15,($A69*(1-'P-Parametri'!$B$19))<'P-Parametri'!$E$15),'P-Parametri'!$B$15/('P-Parametri'!$E$15-'P-Parametri'!$D$15),0))+'P-Parametri'!$B$20) -> 0.48857459 | O69: =M69-N69 -> 0
A70: =46000 -> 46000 | B70: ='P-Parametri'!$B$19*$A70 -> 4227.4 | C70: =$A70-B70 -> 41772.6 | D70: =IF($C70<='P-Parametri'!$B$6,'P-Parametri'!$C$6*$C70,IF($C70<='P-Parametri'!$B$7,'P-Parametri'!$B$9+'P-Parametri'!$C$7*($C70-'P-Parametri'!$B$6),'P-Parametri'!$B$10+'P-Parametri'!$C$8*($C70-'P-Parametri'!$B$7))) -> 10984.958 | E70: =IF($C70<='P-Parametri'!$C$12,'P-Parametri'!$B$12,IF($C70<='P-Parametri'!$B$6,'P-Parametri'!$B$13+'P-Parametri'!$C$13*('P-Parametri'!$B$6-$C70)/'P-Parametri'!$D$13,IF($C70<='P-Parametri'!$B$7,'P-Parametri'!$B$14*('P-Parametri'!$B$7-$C70)/'P-Parametri'!$C$14,0))) -> 714.28791 | F70: =IF($C70<='P-Parametri'!$C$15,0,IF($C70<='P-Parametri'!$D$15,'P-Parametri'!$B$15,IF($C70<'P-Parametri'!$E$15,'P-Parametri'!$B$15*('P-Parametri'!$E$15-$C70)/('P-Parametri'!$E$15-'P-Parametri'!$D$15),0))) -> 0 | G70: =IF($C70>'P-Parametri'!$D$18,0,IF($C70<='P-Parametri'!$B$18,'P-Parametri'!$B$17*$C70,IF($C70<='P-Parametri'!$C$18,'P-Parametri'!$C$17*$C70,'P-Parametri'!$D$17*$C70))) -> 0 | H70: =IF(AND($C70<='P-Parametri'!$C$16,D70>E70-'P-Parametri'!$D$16),'P-Parametri'!$B$16,0) -> 0 | I70: =MAX(0,D70-E70-F70) -> 10270.67 | J70: =IF(I70>0,'P-Parametri'!$B$20*$C70,0) -> 835.452 | K70: =$C70-I70-J70+H70+G70 -> 30666.478 | L70: =K70/$A70 -> 0.66666256 | M70: =1-(K72-K70)/1000 -> 0.48857459 | N70: ='P-Parametri'!$B$19+(1-'P-Parametri'!$B$19)*((IF(($A70*(1-'P-Parametri'!$B$19))<='P-Parametri'!$B$6,'P-Parametri'!$C$6,IF(($A70*(1-'P-Parametri'!$B$19))<='P-Parametri'!$B$7,'P-Parametri'!$C$7,'P-Parametri'!$C$8)))+(IF(($A70*(1-'P-Parametri'!$B$19))<='P-Parametri'!$C$12,0,IF(($A70*(1-'P-Parametri'!$B$19))<='P-Parametri'!$B$6,'P-Parametri'!$C$13/'P-Parametri'!$D$13,IF(($A70*(1-'P-Parametri'!$B$19))<='P-Parametri'!$B$7,'P-Parametri'!$B$14/'P-Parametri'!$C$14,0))))+(IF(AND(($A70*(1-'P-Parametri'!$B$19))>'P-Parametri'!$D$15,($A70*(1-'P-Parametri'!$B$19))<'P-Parametri'!$E$15),'P-Parametri'!$B$15/('P-Parametri'!$E$15-'P-Parametri'!$D$15),0))+'P-Parametri'!$B$20) -> 0.48857459 | O70: =M70-N70 -> 0
A71: =46500 -> 46500 | B71: ='P-Parametri'!$B$19*$A71 -> 4273.35 | C71: =$A71-B71 -> 42226.65 | D71: =IF($C71<='P-Parametri'!$B$6,'P-Parametri'!$C$6*$C71,IF($C71<='P-Parametri'!$B$7,'P-Parametri'!$B$9+'P-Parametri'!$C$7*($C71-'P-Parametri'!$B$6),'P-Parametri'!$B$10+'P-Parametri'!$C$8*($C71-'P-Parametri'!$B$7))) -> 11134.794 | E71: =IF($C71<='P-Parametri'!$C$12,'P-Parametri'!$B$12,IF($C71<='P-Parametri'!$B$6,'P-Parametri'!$B$13+'P-Parametri'!$C$13*('P-Parametri'!$B$6-$C71)/'P-Parametri'!$D$13,IF($C71<='P-Parametri'!$B$7,'P-Parametri'!$B$14*('P-Parametri'!$B$7-$C71)/'P-Parametri'!$C$14,0))) -> 674.86811 | F71: =IF($C71<='P-Parametri'!$C$15,0,IF($C71<='P-Parametri'!$D$15,'P-Parametri'!$B$15,IF($C71<'P-Parametri'!$E$15,'P-Parametri'!$B$15*('P-Parametri'!$E$15-$C71)/('P-Parametri'!$E$15-'P-Parametri'!$D$15),0))) -> 0 | G71: =IF($C71>'P-Parametri'!$D$18,0,IF($C71<='P-Parametri'!$B$18,'P-Parametri'!$B$17*$C71,IF($C71<='P-Parametri'!$C$18,'P-Parametri'!$C$17*$C71,'P-Parametri'!$D$17*$C71))) -> 0 | H71: =IF(AND($C71<='P-Parametri'!$C$16,D71>E71-'P-Parametri'!$D$16),'P-Parametri'!$B$16,0) -> 0 | I71: =MAX(0,D71-E71-F71) -> 10459.926 | J71: =IF(I71>0,'P-Parametri'!$B$20*$C71,0) -> 844.533 | K71: =$C71-I71-J71+H71+G71 -> 30922.191 | L71: =K71/$A71 -> 0.66499335 | M71: =1-(K73-K71)/1000 -> 0.48857459 | N71: ='P-Parametri'!$B$19+(1-'P-Parametri'!$B$19)*((IF(($A71*(1-'P-Parametri'!$B$19))<='P-Parametri'!$B$6,'P-Parametri'!$C$6,IF(($A71*(1-'P-Parametri'!$B$19))<='P-Parametri'!$B$7,'P-Parametri'!$C$7,'P-Parametri'!$C$8)))+(IF(($A71*(1-'P-Parametri'!$B$19))<='P-Parametri'!$C$12,0,IF(($A71*(1-'P-Parametri'!$B$19))<='P-Parametri'!$B$6,'P-Parametri'!$C$13/'P-Parametri'!$D$13,IF(($A71*(1-'P-Parametri'!$B$19))<='P-Parametri'!$B$7,'P-Parametri'!$B$14/'P-Parametri'!$C$14,0))))+(IF(AND(($A71*(1-'P-Parametri'!$B$19))>'P-Parametri'!$D$15,($A71*(1-'P-Parametri'!$B$19))<'P-Parametri'!$E$15),'P-Parametri'!$B$15/('P-Parametri'!$E$15-'P-Parametri'!$D$15),0))+'P-Parametri'!$B$20) -> 0.48857459 | O71: =M71-N71 -> 3.7747583e-15
A72: =47000 -> 47000 | B72: ='P-Parametri'!$B$19*$A72 -> 4319.3 | C72: =$A72-B72 -> 42680.7 | D72: =IF($C72<='P-Parametri'!$B$6,'P-Parametri'!$C$6*$C72,IF($C72<='P-Parametri'!$B$7,'P-Parametri'!$B$9+'P-Parametri'!$C$7*($C72-'P-Parametri'!$B$6),'P-Parametri'!$B$10+'P-Parametri'!$C$8*($C72-'P-Parametri'!$B$7))) -> 11284.631 | E72: =IF($C72<='P-Parametri'!$C$12,'P-Parametri'!$B$12,IF($C72<='P-Parametri'!$B$6,'P-Parametri'!$B$13+'P-Parametri'!$C$13*('P-Parametri'!$B$6-$C72)/'P-Parametri'!$D$13,IF($C72<='P-Parametri'!$B$7,'P-Parametri'!$B$14*('P-Parametri'!$B$7-$C72)/'P-Parametri'!$C$14,0))) -> 635.44832 | F72: =IF($C72<='P-Parametri'!$C$15,0,IF($C72<='P-Parametri'!$D$15,'P-Parametri'!$B$15,IF($C72<'P-Parametri'!$E$15,'P-Parametri'!$B$15*('P-Parametri'!$E$15-$C72)/('P-Parametri'!$E$15-'P-Parametri'!$D$15),0))) -> 0 | G72: =IF($C72>'P-Parametri'!$D$18,0,IF($C72<='P-Parametri'!$B$18,'P-Parametri'!$B$17*$C72,IF($C72<='P-Parametri'!$C$18,'P-Parametri'!$C$17*$C72,'P-Parametri'!$D$17*$C72))) -> 0 | H72: =IF(AND($C72<='P-Parametri'!$C$16,D72>E72-'P-Parametri'!$D$16),'P-Parametri'!$B$16,0) -> 0 | I72: =MAX(0,D72-E72-F72) -> 10649.183 | J72: =IF(I72>0,'P-Parametri'!$B$20*$C72,0) -> 853.614 | K72: =$C72-I72-J72+H72+G72 -> 31177.903 | L72: =K72/$A72 -> 0.66335965 | M72: =1-(K74-K72)/1000 -> 0.48857459 | N72: ='P-Parametri'!$B$19+(1-'P-Parametri'!$B$19)*((IF(($A72*(1-'P-Parametri'!$B$19))<='P-Parametri'!$B$6,'P-Parametri'!$C$6,IF(($A72*(1-'P-Parametri'!$B$19))<='P-Parametri'!$B$7,'P-Parametri'!$C$7,'P-Parametri'!$C$8)))+(IF(($A72*(1-'P-Parametri'!$B$19))<='P-Parametri'!$C$12,0,IF(($A72*(1-'P-Parametri'!$B$19))<='P-Parametri'!$B$6,'P-Parametri'!$C$13/'P-Parametri'!$D$13,IF(($A72*(1-'P-Parametri'!$B$19))<='P-Parametri'!$B$7,'P-Parametri'!$B$14/'P-Parametri'!$C$14,0))))+(IF(AND(($A72*(1-'P-Parametri'!$B$19))>'P-Parametri'!$D$15,($A72*(1-'P-Parametri'!$B$19))<'P-Parametri'!$E$15),'P-Parametri'!$B$15/('P-Parametri'!$E$15-'P-Parametri'!$D$15),0))+'P-Parametri'!$B$20) -> 0.48857459 | O72: =M72-N72 -> -3.5527137e-15
A73: =47500 -> 47500 | B73: ='P-Parametri'!$B$19*$A73 -> 4365.25 | C73: =$A73-B73 -> 43134.75 | D73: =IF($C73<='P-Parametri'!$B$6,'P-Parametri'!$C$6*$C73,IF($C73<='P-Parametri'!$B$7,'P-Parametri'!$B$9+'P-Parametri'!$C$7*($C73-'P-Parametri'!$B$6),'P-Parametri'!$B$10+'P-Parametri'!$C$8*($C73-'P-Parametri'!$B$7))) -> 11434.468 | E73: =IF($C73<='P-Parametri'!$C$12,'P-Parametri'!$B$12,IF($C73<='P-Parametri'!$B$6,'P-Parametri'!$B$13+'P-Parametri'!$C$13*('P-Parametri'!$B$6-$C73)/'P-Parametri'!$D$13,IF($C73<='P-Parametri'!$B$7,'P-Parametri'!$B$14*('P-Parametri'!$B$7-$C73)/'P-Parametri'!$C$14,0))) -> 596.02852 | F73: =IF($C73<='P-Parametri'!$C$15,0,IF($C73<='P-Parametri'!$D$15,'P-Parametri'!$B$15,IF($C73<'P-Parametri'!$E$15,'P-Parametri'!$B$15*('P-Parametri'!$E$15-$C73)/('P-Parametri'!$E$15-'P-Parametri'!$D$15),0))) -> 0 | G73: =IF($C73>'P-Parametri'!$D$18,0,IF($C73<='P-Parametri'!$B$18,'P-Parametri'!$B$17*$C73,IF($C73<='P-Parametri'!$C$18,'P-Parametri'!$C$17*$C73,'P-Parametri'!$D$17*$C73))) -> 0 | H73: =IF(AND($C73<='P-Parametri'!$C$16,D73>E73-'P-Parametri'!$D$16),'P-Parametri'!$B$16,0) -> 0 | I73: =MAX(0,D73-E73-F73) -> 10838.439 | J73: =IF(I73>0,'P-Parametri'!$B$20*$C73,0) -> 862.695 | K73: =$C73-I73-J73+H73+G73 -> 31433.616 | L73: =K73/$A73 -> 0.66176034 | M73: =1-(K75-K73)/1000 -> 0.48857459 | N73: ='P-Parametri'!$B$19+(1-'P-Parametri'!$B$19)*((IF(($A73*(1-'P-Parametri'!$B$19))<='P-Parametri'!$B$6,'P-Parametri'!$C$6,IF(($A73*(1-'P-Parametri'!$B$19))<='P-Parametri'!$B$7,'P-Parametri'!$C$7,'P-Parametri'!$C$8)))+(IF(($A73*(1-'P-Parametri'!$B$19))<='P-Parametri'!$C$12,0,IF(($A73*(1-'P-Parametri'!$B$19))<='P-Parametri'!$B$6,'P-Parametri'!$C$13/'P-Parametri'!$D$13,IF(($A73*(1-'P-Parametri'!$B$19))<='P-Parametri'!$B$7,'P-Parametri'!$B$14/'P-Parametri'!$C$14,0))))+(IF(AND(($A73*(1-'P-Parametri'!$B$19))>'P-Parametri'!$D$15,($A73*(1-'P-Parametri'!$B$19))<'P-Parametri'!$E$15),'P-Parametri'!$B$15/('P-Parametri'!$E$15-'P-Parametri'!$D$15),0))+'P-Parametri'!$B$20) -> 0.48857459 | O73: =M73-N73 -> -3.5527137e-15
A74: =48000 -> 48000 | B74: ='P-Parametri'!$B$19*$A74 -> 4411.2 | C74: =$A74-B74 -> 43588.8 | D74: =IF($C74<='P-Parametri'!$B$6,'P-Parametri'!$C$6*$C74,IF($C74<='P-Parametri'!$B$7,'P-Parametri'!$B$9+'P-Parametri'!$C$7*($C74-'P-Parametri'!$B$6),'P-Parametri'!$B$10+'P-Parametri'!$C$8*($C74-'P-Parametri'!$B$7))) -> 11584.304 | E74: =IF($C74<='P-Parametri'!$C$12,'P-Parametri'!$B$12,IF($C74<='P-Parametri'!$B$6,'P-Parametri'!$B$13+'P-Parametri'!$C$13*('P-Parametri'!$B$6-$C74)/'P-Parametri'!$D$13,IF($C74<='P-Parametri'!$B$7,'P-Parametri'!$B$14*('P-Parametri'!$B$7-$C74)/'P-Parametri'!$C$14,0))) -> 556.60873 | F74: =IF($C74<='P-Parametri'!$C$15,0,IF($C74<='P-Parametri'!$D$15,'P-Parametri'!$B$15,IF($C74<'P-Parametri'!$E$15,'P-Parametri'!$B$15*('P-Parametri'!$E$15-$C74)/('P-Parametri'!$E$15-'P-Parametri'!$D$15),0))) -> 0 | G74: =IF($C74>'P-Parametri'!$D$18,0,IF($C74<='P-Parametri'!$B$18,'P-Parametri'!$B$17*$C74,IF($C74<='P-Parametri'!$C$18,'P-Parametri'!$C$17*$C74,'P-Parametri'!$D$17*$C74))) -> 0 | H74: =IF(AND($C74<='P-Parametri'!$C$16,D74>E74-'P-Parametri'!$D$16),'P-Parametri'!$B$16,0) -> 0 | I74: =MAX(0,D74-E74-F74) -> 11027.695 | J74: =IF(I74>0,'P-Parametri'!$B$20*$C74,0) -> 871.776 | K74: =$C74-I74-J74+H74+G74 -> 31689.329 | L74: =K74/$A74 -> 0.66019435 | M74: =1-(K76-K74)/1000 -> 0.48857459 | N74: ='P-Parametri'!$B$19+(1-'P-Parametri'!$B$19)*((IF(($A74*(1-'P-Parametri'!$B$19))<='P-Parametri'!$B$6,'P-Parametri'!$C$6,IF(($A74*(1-'P-Parametri'!$B$19))<='P-Parametri'!$B$7,'P-Parametri'!$C$7,'P-Parametri'!$C$8)))+(IF(($A74*(1-'P-Parametri'!$B$19))<='P-Parametri'!$C$12,0,IF(($A74*(1-'P-Parametri'!$B$19))<='P-Parametri'!$B$6,'P-Parametri'!$C$13/'P-Parametri'!$D$13,IF(($A74*(1-'P-Parametri'!$B$19))<='P-Parametri'!$B$7,'P-Parametri'!$B$14/'P-Parametri'!$C$14,0))))+(IF(AND(($A74*(1-'P-Parametri'!$B$19))>'P-Parametri'!$D$15,($A74*(1-'P-Parametri'!$B$19))<'P-Parametri'!$E$15),'P-Parametri'!$B$15/('P-Parametri'!$E$15-'P-Parametri'!$D$15),0))+'P-Parametri'!$B$20) -> 0.48857459 | O74: =M74-N74 -> 3.7747583e-15
A75: =48500 -> 48500 | B75: ='P-Parametri'!$B$19*$A75 -> 4457.15 | C75: =$A75-B75 -> 44042.85 | D75: =IF($C75<='P-Parametri'!$B$6,'P-Parametri'!$C$6*$C75,IF($C75<='P-Parametri'!$B$7,'P-Parametri'!$B$9+'P-Parametri'!$C$7*($C75-'P-Parametri'!$B$6),'P-Parametri'!$B$10+'P-Parametri'!$C$8*($C75-'P-Parametri'!$B$7))) -> 11734.14 | E75: =IF($C75<='P-Parametri'!$C$12,'P-Parametri'!$B$12,IF($C75<='P-Parametri'!$B$6,'P-Parametri'!$B$13+'P-Parametri'!$C$13*('P-Parametri'!$B$6-$C75)/'P-Parametri'!$D$13,IF($C75<='P-Parametri'!$B$7,'P-Parametri'!$B$14*('P-Parametri'!$B$7-$C75)/'P-Parametri'!$C$14,0))) -> 517.18893 | F75: =IF($C75<='P-Parametri'!$C$15,0,IF($C75<='P-Parametri'!$D$15,'P-Parametri'!$B$15,IF($C75<'P-Parametri'!$E$15,'P-Parametri'!$B$15*('P-Parametri'!$E$15-$C75)/('P-Parametri'!$E$15-'P-Parametri'!$D$15),0))) -> 0 | G75: =IF($C75>'P-Parametri'!$D$18,0,IF($C75<='P-Parametri'!$B$18,'P-Parametri'!$B$17*$C75,IF($C75<='P-Parametri'!$C$18,'P-Parametri'!$C$17*$C75,'P-Parametri'!$D$17*$C75))) -> 0 | H75: =IF(AND($C75<='P-Parametri'!$C$16,D75>E75-'P-Parametri'!$D$16),'P-Parametri'!$B$16,0) -> 0 | I75: =MAX(0,D75-E75-F75) -> 11216.952 | J75: =IF(I75>0,'P-Parametri'!$B$20*$C75,0) -> 880.857 | K75: =$C75-I75-J75+H75+G75 -> 31945.041 | L75: =K75/$A75 -> 0.65866065 | M75: =1-(K77-K75)/1000 -> 0.48857459 | N75: ='P-Parametri'!$B$19+(1-'P-Parametri'!$B$19)*((IF(($A75*(1-'P-Parametri'!$B$19))<='P-Parametri'!$B$6,'P-Parametri'!$C$6,IF(($A75*(1-'P-Parametri'!$B$19))<='P-Parametri'!$B$7,'P-Parametri'!$C$7,'P-Parametri'!$C$8)))+(IF(($A75*(1-'P-Parametri'!$B$19))<='P-Parametri'!$C$12,0,IF(($A75*(1-'P-Parametri'!$B$19))<='P-Parametri'!$B$6,'P-Parametri'!$C$13/'P-Parametri'!$D$13,IF(($A75*(1-'P-Parametri'!$B$19))<='P-Parametri'!$B$7,'P-Parametri'!$B$14/'P-Parametri'!$C$14,0))))+(IF(AND(($A75*(1-'P-Parametri'!$B$19))>'P-Parametri'!$D$15,($A75*(1-'P-Parametri'!$B$19))<'P-Parametri'!$E$15),'P-Parametri'!$B$15/('P-Parametri'!$E$15-'P-Parametri'!$D$15),0))+'P-Parametri'!$B$20) -> 0.48857459 | O75: =M75-N75 -> 3.7747583e-15
A76: =49000 -> 49000 | B76: ='P-Parametri'!$B$19*$A76 -> 4503.1 | C76: =$A76-B76 -> 44496.9 | D76: =IF($C76<='P-Parametri'!$B$6,'P-Parametri'!$C$6*$C76,IF($C76<='P-Parametri'!$B$7,'P-Parametri'!$B$9+'P-Parametri'!$C$7*($C76-'P-Parametri'!$B$6),'P-Parametri'!$B$10+'P-Parametri'!$C$8*($C76-'P-Parametri'!$B$7))) -> 11883.977 | E76: =IF($C76<='P-Parametri'!$C$12,'P-Parametri'!$B$12,IF($C76<='P-Parametri'!$B$6,'P-Parametri'!$B$13+'P-Parametri'!$C$13*('P-Parametri'!$B$6-$C76)/'P-Parametri'!$D$13,IF($C76<='P-Parametri'!$B$7,'P-Parametri'!$B$14*('P-Parametri'!$B$7-$C76)/'P-Parametri'!$C$14,0))) -> 477.76914 | F76: =IF($C76<='P-Parametri'!$C$15,0,IF($C76<='P-Parametri'!$D$15,'P-Parametri'!$B$15,IF($C76<'P-Parametri'!$E$15,'P-Parametri'!$B$15*('P-Parametri'!$E$15-$C76)/('P-Parametri'!$E$15-'P-Parametri'!$D$15),0))) -> 0 | G76: =IF($C76>'P-Parametri'!$D$18,0,IF($C76<='P-Parametri'!$B$18,'P-Parametri'!$B$17*$C76,IF($C76<='P-Parametri'!$C$18,'P-Parametri'!$C$17*$C76,'P-Parametri'!$D$17*$C76))) -> 0 | H76: =IF(AND($C76<='P-Parametri'!$C$16,D76>E76-'P-Parametri'!$D$16),'P-Parametri'!$B$16,0) -> 0 | I76: =MAX(0,D76-E76-F76) -> 11406.208 | J76: =IF(I76>0,'P-Parametri'!$B$20*$C76,0) -> 889.938 | K76: =$C76-I76-J76+H76+G76 -> 32200.754 | L76: =K76/$A76 -> 0.65715825 | M76: =1-(K78-K76)/1000 -> 0.48857459 | N76: ='P-Parametri'!$B$19+(1-'P-Parametri'!$B$19)*((IF(($A76*(1-'P-Parametri'!$B$19))<='P-Parametri'!$B$6,'P-Parametri'!$C$6,IF(($A76*(1-'P-Parametri'!$B$19))<='P-Parametri'!$B$7,'P-Parametri'!$C$7,'P-Parametri'!$C$8)))+(IF(($A76*(1-'P-Parametri'!$B$19))<='P-Parametri'!$C$12,0,IF(($A76*(1-'P-Parametri'!$B$19))<='P-Parametri'!$B$6,'P-Parametri'!$C$13/'P-Parametri'!$D$13,IF(($A76*(1-'P-Parametri'!$B$19))<='P-Parametri'!$B$7,'P-Parametri'!$B$14/'P-Parametri'!$C$14,0))))+(IF(AND(($A76*(1-'P-Parametri'!$B$19))>'P-Parametri'!$D$15,($A76*(1-'P-Parametri'!$B$19))<'P-Parametri'!$E$15),'P-Parametri'!$B$15/('P-Parametri'!$E$15-'P-Parametri'!$D$15),0))+'P-Parametri'!$B$20) -> 0.48857459 | O76: =M76-N76 -> 0
A77: =49500 -> 49500 | B77: ='P-Parametri'!$B$19*$A77 -> 4549.05 | C77: =$A77-B77 -> 44950.95 | D77: =IF($C77<='P-Parametri'!$B$6,'P-Parametri'!$C$6*$C77,IF($C77<='P-Parametri'!$B$7,'P-Parametri'!$B$9+'P-Parametri'!$C$7*($C77-'P-Parametri'!$B$6),'P-Parametri'!$B$10+'P-Parametri'!$C$8*($C77-'P-Parametri'!$B$7))) -> 12033.814 | E77: =IF($C77<='P-Parametri'!$C$12,'P-Parametri'!$B$12,IF($C77<='P-Parametri'!$B$6,'P-Parametri'!$B$13+'P-Parametri'!$C$13*('P-Parametri'!$B$6-$C77)/'P-Parametri'!$D$13,IF($C77<='P-Parametri'!$B$7,'P-Parametri'!$B$14*('P-Parametri'!$B$7-$C77)/'P-Parametri'!$C$14,0))) -> 438.34934 | F77: =IF($C77<='P-Parametri'!$C$15,0,IF($C77<='P-Parametri'!$D$15,'P-Parametri'!$B$15,IF($C77<'P-Parametri'!$E$15,'P-Parametri'!$B$15*('P-Parametri'!$E$15-$C77)/('P-Parametri'!$E$15-'P-Parametri'!$D$15),0))) -> 0 | G77: =IF($C77>'P-Parametri'!$D$18,0,IF($C77<='P-Parametri'!$B$18,'P-Parametri'!$B$17*$C77,IF($C77<='P-Parametri'!$C$18,'P-Parametri'!$C$17*$C77,'P-Parametri'!$D$17*$C77))) -> 0 | H77: =IF(AND($C77<='P-Parametri'!$C$16,D77>E77-'P-Parametri'!$D$16),'P-Parametri'!$B$16,0) -> 0 | I77: =MAX(0,D77-E77-F77) -> 11595.464 | J77: =IF(I77>0,'P-Parametri'!$B$20*$C77,0) -> 899.019 | K77: =$C77-I77-J77+H77+G77 -> 32456.467 | L77: =K77/$A77 -> 0.6556862 | M77: =1-(K79-K77)/1000 -> 0.48857459 | N77: ='P-Parametri'!$B$19+(1-'P-Parametri'!$B$19)*((IF(($A77*(1-'P-Parametri'!$B$19))<='P-Parametri'!$B$6,'P-Parametri'!$C$6,IF(($A77*(1-'P-Parametri'!$B$19))<='P-Parametri'!$B$7,'P-Parametri'!$C$7,'P-Parametri'!$C$8)))+(IF(($A77*(1-'P-Parametri'!$B$19))<='P-Parametri'!$C$12,0,IF(($A77*(1-'P-Parametri'!$B$19))<='P-Parametri'!$B$6,'P-Parametri'!$C$13/'P-Parametri'!$D$13,IF(($A77*(1-'P-Parametri'!$B$19))<='P-Parametri'!$B$7,'P-Parametri'!$B$14/'P-Parametri'!$C$14,0))))+(IF(AND(($A77*(1-'P-Parametri'!$B$19))>'P-Parametri'!$D$15,($A77*(1-'P-Parametri'!$B$19))<'P-Parametri'!$E$15),'P-Parametri'!$B$15/('P-Parametri'!$E$15-'P-Parametri'!$D$15),0))+'P-Parametri'!$B$20) -> 0.48857459 | O77: =M77-N77 -> -7.2164497e-15
A78: =50000 -> 50000 | B78: ='P-Parametri'!$B$19*$A78 -> 4595 | C78: =$A78-B78 -> 45405 | D78: =IF($C78<='P-Parametri'!$B$6,'P-Parametri'!$C$6*$C78,IF($C78<='P-Parametri'!$B$7,'P-Parametri'!$B$9+'P-Parametri'!$C$7*($C78-'P-Parametri'!$B$6),'P-Parametri'!$B$10+'P-Parametri'!$C$8*($C78-'P-Parametri'!$B$7))) -> 12183.65 | E78: =IF($C78<='P-Parametri'!$C$12,'P-Parametri'!$B$12,IF($C78<='P-Parametri'!$B$6,'P-Parametri'!$B$13+'P-Parametri'!$C$13*('P-Parametri'!$B$6-$C78)/'P-Parametri'!$D$13,IF($C78<='P-Parametri'!$B$7,'P-Parametri'!$B$14*('P-Parametri'!$B$7-$C78)/'P-Parametri'!$C$14,0))) -> 398.92955 | F78: =IF($C78<='P-Parametri'!$C$15,0,IF($C78<='P-Parametri'!$D$15,'P-Parametri'!$B$15,IF($C78<'P-Parametri'!$E$15,'P-Parametri'!$B$15*('P-Parametri'!$E$15-$C78)/('P-Parametri'!$E$15-'P-Parametri'!$D$15),0))) -> 0 | G78: =IF($C78>'P-Parametri'!$D$18,0,IF($C78<='P-Parametri'!$B$18,'P-Parametri'!$B$17*$C78,IF($C78<='P-Parametri'!$C$18,'P-Parametri'!$C$17*$C78,'P-Parametri'!$D$17*$C78))) -> 0 | H78: =IF(AND($C78<='P-Parametri'!$C$16,D78>E78-'P-Parametri'!$D$16),'P-Parametri'!$B$16,0) -> 0 | I78: =MAX(0,D78-E78-F78) -> 11784.72 | J78: =IF(I78>0,'P-Parametri'!$B$20*$C78,0) -> 908.1 | K78: =$C78-I78-J78+H78+G78 -> 32712.18 | L78: =K78/$A78 -> 0.65424359 | M78: =1-(K80-K78)/1000 -> 0.48857459 | N78: ='P-Parametri'!$B$19+(1-'P-Parametri'!$B$19)*((IF(($A78*(1-'P-Parametri'!$B$19))<='P-Parametri'!$B$6,'P-Parametri'!$C$6,IF(($A78*(1-'P-Parametri'!$B$19))<='P-Parametri'!$B$7,'P-Parametri'!$C$7,'P-Parametri'!$C$8)))+(IF(($A78*(1-'P-Parametri'!$B$19))<='P-Parametri'!$C$12,0,IF(($A78*(1-'P-Parametri'!$B$19))<='P-Parametri'!$B$6,'P-Parametri'!$C$13/'P-Parametri'!$D$13,IF(($A78*(1-'P-Parametri'!$B$19))<='P-Parametri'!$B$7,'P-Parametri'!$B$14/'P-Parametri'!$C$14,0))))+(IF(AND(($A78*(1-'P-Parametri'!$B$19))>'P-Parametri'!$D$15,($A78*(1-'P-Parametri'!$B$19))<'P-Parametri'!$E$15),'P-Parametri'!$B$15/('P-Parametri'!$E$15-'P-Parametri'!$D$15),0))+'P-Parametri'!$B$20) -> 0.48857459 | O78: =M78-N78 -> 0
A79: =50500 -> 50500 | B79: ='P-Parametri'!$B$19*$A79 -> 4640.95 | C79: =$A79-B79 -> 45859.05 | D79: =IF($C79<='P-Parametri'!$B$6,'P-Parametri'!$C$6*$C79,IF($C79<='P-Parametri'!$B$7,'P-Parametri'!$B$9+'P-Parametri'!$C$7*($C79-'P-Parametri'!$B$6),'P-Parametri'!$B$10+'P-Parametri'!$C$8*($C79-'P-Parametri'!$B$7))) -> 12333.487 | E79: =IF($C79<='P-Parametri'!$C$12,'P-Parametri'!$B$12,IF($C79<='P-Parametri'!$B$6,'P-Parametri'!$B$13+'P-Parametri'!$C$13*('P-Parametri'!$B$6-$C79)/'P-Parametri'!$D$13,IF($C79<='P-Parametri'!$B$7,'P-Parametri'!$B$14*('P-Parametri'!$B$7-$C79)/'P-Parametri'!$C$14,0))) -> 359.50975 | F79: =IF($C79<='P-Parametri'!$C$15,0,IF($C79<='P-Parametri'!$D$15,'P-Parametri'!$B$15,IF($C79<'P-Parametri'!$E$15,'P-Parametri'!$B$15*('P-Parametri'!$E$15-$C79)/('P-Parametri'!$E$15-'P-Parametri'!$D$15),0))) -> 0 | G79: =IF($C79>'P-Parametri'!$D$18,0,IF($C79<='P-Parametri'!$B$18,'P-Parametri'!$B$17*$C79,IF($C79<='P-Parametri'!$C$18,'P-Parametri'!$C$17*$C79,'P-Parametri'!$D$17*$C79))) -> 0 | H79: =IF(AND($C79<='P-Parametri'!$C$16,D79>E79-'P-Parametri'!$D$16),'P-Parametri'!$B$16,0) -> 0 | I79: =MAX(0,D79-E79-F79) -> 11973.977 | J79: =IF(I79>0,'P-Parametri'!$B$20*$C79,0) -> 917.181 | K79: =$C79-I79-J79+H79+G79 -> 32967.892 | L79: =K79/$A79 -> 0.65282955 | M79: =1-(K81-K79)/1000 -> 0.48857459 | N79: ='P-Parametri'!$B$19+(1-'P-Parametri'!$B$19)*((IF(($A79*(1-'P-Parametri'!$B$19))<='P-Parametri'!$B$6,'P-Parametri'!$C$6,IF(($A79*(1-'P-Parametri'!$B$19))<='P-Parametri'!$B$7,'P-Parametri'!$C$7,'P-Parametri'!$C$8)))+(IF(($A79*(1-'P-Parametri'!$B$19))<='P-Parametri'!$C$12,0,IF(($A79*(1-'P-Parametri'!$B$19))<='P-Parametri'!$B$6,'P-Parametri'!$C$13/'P-Parametri'!$D$13,IF(($A79*(1-'P-Parametri'!$B$19))<='P-Parametri'!$B$7,'P-Parametri'!$B$14/'P-Parametri'!$C$14,0))))+(IF(AND(($A79*(1-'P-Parametri'!$B$19))>'P-Parametri'!$D$15,($A79*(1-'P-Parametri'!$B$19))<'P-Parametri'!$E$15),'P-Parametri'!$B$15/('P-Parametri'!$E$15-'P-Parametri'!$D$15),0))+'P-Parametri'!$B$20) -> 0.48857459 | O79: =M79-N79 -> 7.4384943e-15
A80: =51000 -> 51000 | B80: ='P-Parametri'!$B$19*$A80 -> 4686.9 | C80: =$A80-B80 -> 46313.1 | D80: =IF($C80<='P-Parametri'!$B$6,'P-Parametri'!$C$6*$C80,IF($C80<='P-Parametri'!$B$7,'P-Parametri'!$B$9+'P-Parametri'!$C$7*($C80-'P-Parametri'!$B$6),'P-Parametri'!$B$10+'P-Parametri'!$C$8*($C80-'P-Parametri'!$B$7))) -> 12483.323 | E80: =IF($C80<='P-Parametri'!$C$12,'P-Parametri'!$B$12,IF($C80<='P-Parametri'!$B$6,'P-Parametri'!$B$13+'P-Parametri'!$C$13*('P-Parametri'!$B$6-$C80)/'P-Parametri'!$D$13,IF($C80<='P-Parametri'!$B$7,'P-Parametri'!$B$14*('P-Parametri'!$B$7-$C80)/'P-Parametri'!$C$14,0))) -> 320.08995 | F80: =IF($C80<='P-Parametri'!$C$15,0,IF($C80<='P-Parametri'!$D$15,'P-Parametri'!$B$15,IF($C80<'P-Parametri'!$E$15,'P-Parametri'!$B$15*('P-Parametri'!$E$15-$C80)/('P-Parametri'!$E$15-'P-Parametri'!$D$15),0))) -> 0 | G80: =IF($C80>'P-Parametri'!$D$18,0,IF($C80<='P-Parametri'!$B$18,'P-Parametri'!$B$17*$C80,IF($C80<='P-Parametri'!$C$18,'P-Parametri'!$C$17*$C80,'P-Parametri'!$D$17*$C80))) -> 0 | H80: =IF(AND($C80<='P-Parametri'!$C$16,D80>E80-'P-Parametri'!$D$16),'P-Parametri'!$B$16,0) -> 0 | I80: =MAX(0,D80-E80-F80) -> 12163.233 | J80: =IF(I80>0,'P-Parametri'!$B$20*$C80,0) -> 926.262 | K80: =$C80-I80-J80+H80+G80 -> 33223.605 | L80: =K80/$A80 -> 0.65144323 | M80: =1-(K82-K80)/1000 -> 0.48857459 | N80: ='P-Parametri'!$B$19+(1-'P-Parametri'!$B$19)*((IF(($A80*(1-'P-Parametri'!$B$19))<='P-Parametri'!$B$6,'P-Parametri'!$C$6,IF(($A80*(1-'P-Parametri'!$B$19))<='P-Parametri'!$B$7,'P-Parametri'!$C$7,'P-Parametri'!$C$8)))+(IF(($A80*(1-'P-Parametri'!$B$19))<='P-Parametri'!$C$12,0,IF(($A80*(1-'P-Parametri'!$B$19))<='P-Parametri'!$B$6,'P-Parametri'!$C$13/'P-Parametri'!$D$13,IF(($A80*(1-'P-Parametri'!$B$19))<='P-Parametri'!$B$7,'P-Parametri'!$B$14/'P-Parametri'!$C$14,0))))+(IF(AND(($A80*(1-'P-Parametri'!$B$19))>'P-Parametri'!$D$15,($A80*(1-'P-Parametri'!$B$19))<'P-Parametri'!$E$15),'P-Parametri'!$B$15/('P-Parametri'!$E$15-'P-Parametri'!$D$15),0))+'P-Parametri'!$B$20) -> 0.48857459 | O80: =M80-N80 -> 0
A81: =51500 -> 51500 | B81: ='P-Parametri'!$B$19*$A81 -> 4732.85 | C81: =$A81-B81 -> 46767.15 | D81: =IF($C81<='P-Parametri'!$B$6,'P-Parametri'!$C$6*$C81,IF($C81<='P-Parametri'!$B$7,'P-Parametri'!$B$9+'P-Parametri'!$C$7*($C81-'P-Parametri'!$B$6),'P-Parametri'!$B$10+'P-Parametri'!$C$8*($C81-'P-Parametri'!$B$7))) -> 12633.16 | E81: =IF($C81<='P-Parametri'!$C$12,'P-Parametri'!$B$12,IF($C81<='P-Parametri'!$B$6,'P-Parametri'!$B$13+'P-Parametri'!$C$13*('P-Parametri'!$B$6-$C81)/'P-Parametri'!$D$13,IF($C81<='P-Parametri'!$B$7,'P-Parametri'!$B$14*('P-Parametri'!$B$7-$C81)/'P-Parametri'!$C$14,0))) -> 280.67016 | F81: =IF($C81<='P-Parametri'!$C$15,0,IF($C81<='P-Parametri'!$D$15,'P-Parametri'!$B$15,IF($C81<'P-Parametri'!$E$15,'P-Parametri'!$B$15*('P-Parametri'!$E$15-$C81)/('P-Parametri'!$E$15-'P-Parametri'!$D$15),0))) -> 0 | G81: =IF($C81>'P-Parametri'!$D$18,0,IF($C81<='P-Parametri'!$B$18,'P-Parametri'!$B$17*$C81,IF($C81<='P-Parametri'!$C$18,'P-Parametri'!$C$17*$C81,'P-Parametri'!$D$17*$C81))) -> 0 | H81: =IF(AND($C81<='P-Parametri'!$C$16,D81>E81-'P-Parametri'!$D$16),'P-Parametri'!$B$16,0) -> 0 | I81: =MAX(0,D81-E81-F81) -> 12352.489 | J81: =IF(I81>0,'P-Parametri'!$B$20*$C81,0) -> 935.343 | K81: =$C81-I81-J81+H81+G81 -> 33479.318 | L81: =K81/$A81 -> 0.65008384 | M81: =1-(K83-K81)/1000 -> 0.48857459 | N81: ='P-Parametri'!$B$19+(1-'P-Parametri'!$B$19)*((IF(($A81*(1-'P-Parametri'!$B$19))<='P-Parametri'!$B$6,'P-Parametri'!$C$6,IF(($A81*(1-'P-Parametri'!$B$19))<='P-Parametri'!$B$7,'P-Parametri'!$C$7,'P-Parametri'!$C$8)))+(IF(($A81*(1-'P-Parametri'!$B$19))<='P-Parametri'!$C$12,0,IF(($A81*(1-'P-Parametri'!$B$19))<='P-Parametri'!$B$6,'P-Parametri'!$C$13/'P-Parametri'!$D$13,IF(($A81*(1-'P-Parametri'!$B$19))<='P-Parametri'!$B$7,'P-Parametri'!$B$14/'P-Parametri'!$C$14,0))))+(IF(AND(($A81*(1-'P-Parametri'!$B$19))>'P-Parametri'!$D$15,($A81*(1-'P-Parametri'!$B$19))<'P-Parametri'!$E$15),'P-Parametri'!$B$15/('P-Parametri'!$E$15-'P-Parametri'!$D$15),0))+'P-Parametri'!$B$20) -> 0.48857459 | O81: =M81-N81 -> -7.2164497e-15
A82: =52000 -> 52000 | B82: ='P-Parametri'!$B$19*$A82 -> 4778.8 | C82: =$A82-B82 -> 47221.2 | D82: =IF($C82<='P-Parametri'!$B$6,'P-Parametri'!$C$6*$C82,IF($C82<='P-Parametri'!$B$7,'P-Parametri'!$B$9+'P-Parametri'!$C$7*($C82-'P-Parametri'!$B$6),'P-Parametri'!$B$10+'P-Parametri'!$C$8*($C82-'P-Parametri'!$B$7))) -> 12782.996 | E82: =IF($C82<='P-Parametri'!$C$12,'P-Parametri'!$B$12,IF($C82<='P-Parametri'!$B$6,'P-Parametri'!$B$13+'P-Parametri'!$C$13*('P-Parametri'!$B$6-$C82)/'P-Parametri'!$D$13,IF($C82<='P-Parametri'!$B$7,'P-Parametri'!$B$14*('P-Parametri'!$B$7-$C82)/'P-Parametri'!$C$14,0))) -> 241.25036 | F82: =IF($C82<='P-Parametri'!$C$15,0,IF($C82<='P-Parametri'!$D$15,'P-Parametri'!$B$15,IF($C82<'P-Parametri'!$E$15,'P-Parametri'!$B$15*('P-Parametri'!$E$15-$C82)/('P-Parametri'!$E$15-'P-Parametri'!$D$15),0))) -> 0 | G82: =IF($C82>'P-Parametri'!$D$18,0,IF($C82<='P-Parametri'!$B$18,'P-Parametri'!$B$17*$C82,IF($C82<='P-Parametri'!$C$18,'P-Parametri'!$C$17*$C82,'P-Parametri'!$D$17*$C82))) -> 0 | H82: =IF(AND($C82<='P-Parametri'!$C$16,D82>E82-'P-Parametri'!$D$16),'P-Parametri'!$B$16,0) -> 0 | I82: =MAX(0,D82-E82-F82) -> 12541.746 | J82: =IF(I82>0,'P-Parametri'!$B$20*$C82,0) -> 944.424 | K82: =$C82-I82-J82+H82+G82 -> 33735.03 | L82: =K82/$A82 -> 0.64875058 | M82: =1-(K84-K82)/1000 -> 0.48857459 | N82: ='P-Parametri'!$B$19+(1-'P-Parametri'!$B$19)*((IF(($A82*(1-'P-Parametri'!$B$19))<='P-Parametri'!$B$6,'P-Parametri'!$C$6,IF(($A82*(1-'P-Parametri'!$B$19))<='P-Parametri'!$B$7,'P-Parametri'!$C$7,'P-Parametri'!$C$8)))+(IF(($A82*(1-'P-Parametri'!$B$19))<='P-Parametri'!$C$12,0,IF(($A82*(1-'P-Parametri'!$B$19))<='P-Parametri'!$B$6,'P-Parametri'!$C$13/'P-Parametri'!$D$13,IF(($A82*(1-'P-Parametri'!$B$19))<='P-Parametri'!$B$7,'P-Parametri'!$B$14/'P-Parametri'!$C$14,0))))+(IF(AND(($A82*(1-'P-Parametri'!$B$19))>'P-Parametri'!$D$15,($A82*(1-'P-Parametri'!$B$19))<'P-Parametri'!$E$15),'P-Parametri'!$B$15/('P-Parametri'!$E$15-'P-Parametri'!$D$15),0))+'P-Parametri'!$B$20) -> 0.48857459 | O82: =M82-N82 -> 0
A83: =52500 -> 52500 | B83: ='P-Parametri'!$B$19*$A83 -> 4824.75 | C83: =$A83-B83 -> 47675.25 | D83: =IF($C83<='P-Parametri'!$B$6,'P-Parametri'!$C$6*$C83,IF($C83<='P-Parametri'!$B$7,'P-Parametri'!$B$9+'P-Parametri'!$C$7*($C83-'P-Parametri'!$B$6),'P-Parametri'!$B$10+'P-Parametri'!$C$8*($C83-'P-Parametri'!$B$7))) -> 12932.833 | E83: =IF($C83<='P-Parametri'!$C$12,'P-Parametri'!$B$12,IF($C83<='P-Parametri'!$B$6,'P-Parametri'!$B$13+'P-Parametri'!$C$13*('P-Parametri'!$B$6-$C83)/'P-Parametri'!$D$13,IF($C83<='P-Parametri'!$B$7,'P-Parametri'!$B$14*('P-Parametri'!$B$7-$C83)/'P-Parametri'!$C$14,0))) -> 201.83057 | F83: =IF($C83<='P-Parametri'!$C$15,0,IF($C83<='P-Parametri'!$D$15,'P-Parametri'!$B$15,IF($C83<'P-Parametri'!$E$15,'P-Parametri'!$B$15*('P-Parametri'!$E$15-$C83)/('P-Parametri'!$E$15-'P-Parametri'!$D$15),0))) -> 0 | G83: =IF($C83>'P-Parametri'!$D$18,0,IF($C83<='P-Parametri'!$B$18,'P-Parametri'!$B$17*$C83,IF($C83<='P-Parametri'!$C$18,'P-Parametri'!$C$17*$C83,'P-Parametri'!$D$17*$C83))) -> 0 | H83: =IF(AND($C83<='P-Parametri'!$C$16,D83>E83-'P-Parametri'!$D$16),'P-Parametri'!$B$16,0) -> 0 | I83: =MAX(0,D83-E83-F83) -> 12731.002 | J83: =IF(I83>0,'P-Parametri'!$B$20*$C83,0) -> 953.505 | K83: =$C83-I83-J83+H83+G83 -> 33990.743 | L83: =K83/$A83 -> 0.64744273 | M83: =1-(K85-K83)/1000 -> 0.48857459 | N83: ='P-Parametri'!$B$19+(1-'P-Parametri'!$B$19)*((IF(($A83*(1-'P-Parametri'!$B$19))<='P-Parametri'!$B$6,'P-Parametri'!$C$6,IF(($A83*(1-'P-Parametri'!$B$19))<='P-Parametri'!$B$7,'P-Parametri'!$C$7,'P-Parametri'!$C$8)))+(IF(($A83*(1-'P-Parametri'!$B$19))<='P-Parametri'!$C$12,0,IF(($A83*(1-'P-Parametri'!$B$19))<='P-Parametri'!$B$6,'P-Parametri'!$C$13/'P-Parametri'!$D$13,IF(($A83*(1-'P-Parametri'!$B$19))<='P-Parametri'!$B$7,'P-Parametri'!$B$14/'P-Parametri'!$C$14,0))))+(IF(AND(($A83*(1-'P-Parametri'!$B$19))>'P-Parametri'!$D$15,($A83*(1-'P-Parametri'!$B$19))<'P-Parametri'!$E$15),'P-Parametri'!$B$15/('P-Parametri'!$E$15-'P-Parametri'!$D$15),0))+'P-Parametri'!$B$20) -> 0.48857459 | O83: =M83-N83 -> 7.4384943e-15
A84: =53000 -> 53000 | B84: ='P-Parametri'!$B$19*$A84 -> 4870.7 | C84: =$A84-B84 -> 48129.3 | D84: =IF($C84<='P-Parametri'!$B$6,'P-Parametri'!$C$6*$C84,IF($C84<='P-Parametri'!$B$7,'P-Parametri'!$B$9+'P-Parametri'!$C$7*($C84-'P-Parametri'!$B$6),'P-Parametri'!$B$10+'P-Parametri'!$C$8*($C84-'P-Parametri'!$B$7))) -> 13082.669 | E84: =IF($C84<='P-Parametri'!$C$12,'P-Parametri'!$B$12,IF($C84<='P-Parametri'!$B$6,'P-Parametri'!$B$13+'P-Parametri'!$C$13*('P-Parametri'!$B$6-$C84)/'P-Parametri'!$D$13,IF($C84<='P-Parametri'!$B$7,'P-Parametri'!$B$14*('P-Parametri'!$B$7-$C84)/'P-Parametri'!$C$14,0))) -> 162.41077 | F84: =IF($C84<='P-Parametri'!$C$15,0,IF($C84<='P-Parametri'!$D$15,'P-Parametri'!$B$15,IF($C84<'P-Parametri'!$E$15,'P-Parametri'!$B$15*('P-Parametri'!$E$15-$C84)/('P-Parametri'!$E$15-'P-Parametri'!$D$15),0))) -> 0 | G84: =IF($C84>'P-Parametri'!$D$18,0,IF($C84<='P-Parametri'!$B$18,'P-Parametri'!$B$17*$C84,IF($C84<='P-Parametri'!$C$18,'P-Parametri'!$C$17*$C84,'P-Parametri'!$D$17*$C84))) -> 0 | H84: =IF(AND($C84<='P-Parametri'!$C$16,D84>E84-'P-Parametri'!$D$16),'P-Parametri'!$B$16,0) -> 0 | I84: =MAX(0,D84-E84-F84) -> 12920.258 | J84: =IF(I84>0,'P-Parametri'!$B$20*$C84,0) -> 962.586 | K84: =$C84-I84-J84+H84+G84 -> 34246.456 | L84: =K84/$A84 -> 0.64615954 | M84: =1-(K86-K84)/1000 -> 0.48857459 | N84: ='P-Parametri'!$B$19+(1-'P-Parametri'!$B$19)*((IF(($A84*(1-'P-Parametri'!$B$19))<='P-Parametri'!$B$6,'P-Parametri'!$C$6,IF(($A84*(1-'P-Parametri'!$B$19))<='P-Parametri'!$B$7,'P-Parametri'!$C$7,'P-Parametri'!$C$8)))+(IF(($A84*(1-'P-Parametri'!$B$19))<='P-Parametri'!$C$12,0,IF(($A84*(1-'P-Parametri'!$B$19))<='P-Parametri'!$B$6,'P-Parametri'!$C$13/'P-Parametri'!$D$13,IF(($A84*(1-'P-Parametri'!$B$19))<='P-Parametri'!$B$7,'P-Parametri'!$B$14/'P-Parametri'!$C$14,0))))+(IF(AND(($A84*(1-'P-Parametri'!$B$19))>'P-Parametri'!$D$15,($A84*(1-'P-Parametri'!$B$19))<'P-Parametri'!$E$15),'P-Parametri'!$B$15/('P-Parametri'!$E$15-'P-Parametri'!$D$15),0))+'P-Parametri'!$B$20) -> 0.48857459 | O84: =M84-N84 -> 0
A85: =53500 -> 53500 | B85: ='P-Parametri'!$B$19*$A85 -> 4916.65 | C85: =$A85-B85 -> 48583.35 | D85: =IF($C85<='P-Parametri'!$B$6,'P-Parametri'!$C$6*$C85,IF($C85<='P-Parametri'!$B$7,'P-Parametri'!$B$9+'P-Parametri'!$C$7*($C85-'P-Parametri'!$B$6),'P-Parametri'!$B$10+'P-Parametri'!$C$8*($C85-'P-Parametri'!$B$7))) -> 13232.505 | E85: =IF($C85<='P-Parametri'!$C$12,'P-Parametri'!$B$12,IF($C85<='P-Parametri'!$B$6,'P-Parametri'!$B$13+'P-Parametri'!$C$13*('P-Parametri'!$B$6-$C85)/'P-Parametri'!$D$13,IF($C85<='P-Parametri'!$B$7,'P-Parametri'!$B$14*('P-Parametri'!$B$7-$C85)/'P-Parametri'!$C$14,0))) -> 122.99098 | F85: =IF($C85<='P-Parametri'!$C$15,0,IF($C85<='P-Parametri'!$D$15,'P-Parametri'!$B$15,IF($C85<'P-Parametri'!$E$15,'P-Parametri'!$B$15*('P-Parametri'!$E$15-$C85)/('P-Parametri'!$E$15-'P-Parametri'!$D$15),0))) -> 0 | G85: =IF($C85>'P-Parametri'!$D$18,0,IF($C85<='P-Parametri'!$B$18,'P-Parametri'!$B$17*$C85,IF($C85<='P-Parametri'!$C$18,'P-Parametri'!$C$17*$C85,'P-Parametri'!$D$17*$C85))) -> 0 | H85: =IF(AND($C85<='P-Parametri'!$C$16,D85>E85-'P-Parametri'!$D$16),'P-Parametri'!$B$16,0) -> 0 | I85: =MAX(0,D85-E85-F85) -> 13109.515 | J85: =IF(I85>0,'P-Parametri'!$B$20*$C85,0) -> 971.667 | K85: =$C85-I85-J85+H85+G85 -> 34502.168 | L85: =K85/$A85 -> 0.64490035 | M85: =1-(K87-K85)/1000 -> 0.48857459 | N85: ='P-Parametri'!$B$19+(1-'P-Parametri'!$B$19)*((IF(($A85*(1-'P-Parametri'!$B$19))<='P-Parametri'!$B$6,'P-Parametri'!$C$6,IF(($A85*(1-'P-Parametri'!$B$19))<='P-Parametri'!$B$7,'P-Parametri'!$C$7,'P-Parametri'!$C$8)))+(IF(($A85*(1-'P-Parametri'!$B$19))<='P-Parametri'!$C$12,0,IF(($A85*(1-'P-Parametri'!$B$19))<='P-Parametri'!$B$6,'P-Parametri'!$C$13/'P-Parametri'!$D$13,IF(($A85*(1-'P-Parametri'!$B$19))<='P-Parametri'!$B$7,'P-Parametri'!$B$14/'P-Parametri'!$C$14,0))))+(IF(AND(($A85*(1-'P-Parametri'!$B$19))>'P-Parametri'!$D$15,($A85*(1-'P-Parametri'!$B$19))<'P-Parametri'!$E$15),'P-Parametri'!$B$15/('P-Parametri'!$E$15-'P-Parametri'!$D$15),0))+'P-Parametri'!$B$20) -> 0.48857459 | O85: =M85-N85 -> -7.2164497e-15
