Workbook

Sheet 0 - Indice
A1: Marco FIRE — Mutuo vs Investimento 2026
A2: Strumento informativo / divulgativo. NON è consulenza finanziaria. I valori sono indicativi al 2026 e vanno verificati col tuo consulente.
A4: Indice
A5: 1 - Scenario A vs B | B5: Estingui vs investi + PAC con rata
A6: 2 - Break-even | B6: Rendimento minimo per cui conviene investire
A7: 3 - Detrazione interessi | B7: Calcolo risparmio fiscale 19%
A9: Come usare
A10: 1. Le celle GIALLE sono input — modificale coi tuoi numeri.
A11: 2. Le celle VERDI sono output — si aggiornano automaticamente.
A12: 3. Tutti i numeri di default sono al 2026 da fonti pubbliche.
A13: 4. Niente codice nascosto: l'Excel è solo formule modificabili.
A15: Fonti dati
A16: • Tassi mutuo Italia maggio 2026: TAN fisso ~2,99% / variabile ~2,25%
A17: • Detrazione interessi mutuo prima casa 19% su max 4.000 €/anno (TUIR art. 15)
A18: • Tassazione plusvalenze ETF 26% (azionari/corporate) / 12,5% (titoli Stato white-list)
A20: Aggiornamenti: github.com/marcofire-it/marco-fire-simulatori

Sheet 1 - Scenario A vs B
A1: Estingui mutuo vs Investi liquidità
A2: Strumento informativo / divulgativo. NON è consulenza finanziaria. I valori sono indicativi al 2026 e vanno verificati col tuo consulente.
A4: INPUT
A5: Capitale residuo mutuo (€) | B5: 100000
A6: TAN fisso mutuo (%) | B6: 0.0299
A7: Anni residui mutuo | B7: 15
A8: Rata mensile attuale (€) | B8: 690
A9: Liquidità disponibile (€) | B9: 100000
A10: Rendimento PAC/lump (%) | B10: 0.07
A11: Tassa capital gain (%) | B11: 0.26
A13: Scenario A — estingui + investi la rata
A14: Liquidità usata per estinguere | B14: =MIN(B5,B9)
A15: PAC mensile (= rata risparmiata) | B15: =B8
A16: FV PAC lordo | B16: =B15*(((1+(1+B10)^(1/12)-1)^(B7*12)-1)/((1+B10)^(1/12)-1))
A17: Totale versato in PAC | B17: =B15*B7*12
A18: Plusvalenza PAC | B18: =B16-B17
A19: Capitale finale NETTO scenario A | B19: =B17+B18*(1-B11)
A21: Scenario B — tieni mutuo + investi 100k subito
A22: Lump sum investito | B22: =B9
A23: FV lump sum lordo | B23: =B22*(1+B10)^B7
A24: Plusvalenza lump sum | B24: =B23-B22
A25: FV netto investimento | B25: =B22+B24*(1-B11)
A26: Interessi mutuo totali (orientativo) | B26: =B5*B6*B7/2
A27: Detrazione 19% su interessi (max 4k/y) | B27: =MIN(B26*0.19, B7*4000*0.19)
A28: Costo netto mutuo (interessi - detrazione) | B28: =B26-B27
A29: Capitale finale NETTO scenario B | B29: =B25-B28
A31: Confronto
A32: Differenza B vs A | B32: =B29-B19
A33: Conviene | B33: =IF(B32>0, "Investire (Scenario B)", IF(B32<0, "Estinguere (Scenario A)", "Indifferente"))

Sheet 2 - Break-even
A1: Break-even del rendimento
A2: Strumento informativo / divulgativo. NON è consulenza finanziaria. I valori sono indicativi al 2026 e vanno verificati col tuo consulente.
A4: Tabella: rendimenti netti A vs B per varie ipotesi
A5: Rendimento PAC | B5: Netto A | C5: Netto B
A6: 2.00% | B6: ='1 - Scenario A vs B'!B15*(((1+(1+0.02)^(1/12)-1)^('1 - Scenario A vs B'!B7*12)-1)/((1+0.02)^(1/12)-1)) | C6: ='1 - Scenario A vs B'!B22*(1+0.02)^'1 - Scenario A vs B'!B7
A7: 3.00% | B7: ='1 - Scenario A vs B'!B15*(((1+(1+0.03)^(1/12)-1)^('1 - Scenario A vs B'!B7*12)-1)/((1+0.03)^(1/12)-1)) | C7: ='1 - Scenario A vs B'!B22*(1+0.03)^'1 - Scenario A vs B'!B7
A8: 3.45% | B8: ='1 - Scenario A vs B'!B15*(((1+(1+0.0345)^(1/12)-1)^('1 - Scenario A vs B'!B7*12)-1)/((1+0.0345)^(1/12)-1)) | C8: ='1 - Scenario A vs B'!B22*(1+0.0345)^'1 - Scenario A vs B'!B7
A9: 4.00% | B9: ='1 - Scenario A vs B'!B15*(((1+(1+0.04)^(1/12)-1)^('1 - Scenario A vs B'!B7*12)-1)/((1+0.04)^(1/12)-1)) | C9: ='1 - Scenario A vs B'!B22*(1+0.04)^'1 - Scenario A vs B'!B7
A10: 5.00% | B10: ='1 - Scenario A vs B'!B15*(((1+(1+0.05)^(1/12)-1)^('1 - Scenario A vs B'!B7*12)-1)/((1+0.05)^(1/12)-1)) | C10: ='1 - Scenario A vs B'!B22*(1+0.05)^'1 - Scenario A vs B'!B7
A11: 6.00% | B11: ='1 - Scenario A vs B'!B15*(((1+(1+0.06)^(1/12)-1)^('1 - Scenario A vs B'!B7*12)-1)/((1+0.06)^(1/12)-1)) | C11: ='1 - Scenario A vs B'!B22*(1+0.06)^'1 - Scenario A vs B'!B7
A12: 7.00% | B12: ='1 - Scenario A vs B'!B15*(((1+(1+0.07)^(1/12)-1)^('1 - Scenario A vs B'!B7*12)-1)/((1+0.07)^(1/12)-1)) | C12: ='1 - Scenario A vs B'!B22*(1+0.07)^'1 - Scenario A vs B'!B7
A14: Break-even tipico (mutuo 2,99% + tassa 26% + detrazione 19%): ≈ 3,3% netto annuo. Sopra, B (investi) vince; sotto, A (estingui).

Sheet 3 - Detrazione interessi
A1: Detrazione 19% interessi mutuo prima casa
A2: Strumento informativo / divulgativo. NON è consulenza finanziaria. I valori sono indicativi al 2026 e vanno verificati col tuo consulente.
A4: INPUT
A5: Interessi pagati nell'anno (€) | B5: 3500
A6: Aliquota detrazione (%) | B6: 0.19
A7: Tetto annuo interessi detraibili (€) | B7: 4000
A9: OUTPUT
A10: Quota detraibile (≤ tetto) | B10: =MIN(B5,B7)
A11: Detrazione fiscale (= 19% × quota) | B11: =B10*B6
A12: Costo netto interessi (interessi - detrazione) | B12: =B5-B11
