Workbook

Sheet 0 - Indice
A1: La pensione si allontana — il simulatore (ottobre 2026)
A2: Strumento informativo / divulgativo. NON è consulenza finanziaria. I valori sono indicativi al 2026 e vanno verificati col tuo consulente.
A4: Indice
A5: 1 - Il tuo traguardo | B5: La tua data di nascita: prima rata di vecchiaia, mesi oltre i 67, ponte, RITA, anticipata
A6: 2 - Il costo del ponte | B6: Quanto capitale serve per arrivare alla prima rata e quanto costa un mese in più
A7: 3 - Le tre forze | B7: Il caso di Irene: storia di risparmio, messaggio in due passi, età / inflazione / stipendi, stop minimo nei mondi
A8: 4 - Le leve | B8: Spesa, TFR, part-time, fondo pensione, riscatto, volontari, soglia: mesi di anticipo; rendimento di pareggio
A9: 5 - La manovra | B9: Le proposte al 29/09/2026, la tua manovra, la soglia dell'anticipata, le previsioni da verificare
A11: Come usare
A12: 1. Le celle GIALLE sono input — modificale coi tuoi numeri.
A13: 2. Le celle VERDI sono output — si aggiornano automaticamente.
A14: 3. Tutti i numeri di default sono al 2026 da fonti pubbliche.
A15: 4. Niente codice nascosto: l'Excel è solo formule modificabili.
A16: 5. Le celle BIANCHE sono dati ufficiali (tabelle RGS, coefficienti, righe INPS, FOI, PIL ISTAT): non modificarle; la fonte è nella colonna accanto.
A17: Fonti dati
A18: • RGS, Rapporto n. 27 (22/09/2026): Tab. A1.4 p. 211 e A1.5 p. 212 (requisiti; dal 2029 proiezioni), Tab. A1.1 p. 197 (coefficienti), Riquadro 5.1 p. 159, Riquadro 6.1 pp. 184-185, §1.2 (PIL reale 0,5%)
A19: • RGS, Rapporto n. 26 (agosto 2025), base ISTAT 2023: la curva di un anno fa
A20: • Decreto direttoriale 20/11/2024: coefficienti di trasformazione 2025-2026
A21: • INPS, messaggio n. 707 del 27/02/2026: coefficienti di rivalutazione del montante; circolare n. 28/2026 (requisiti 2027-2028); circolare n. 153/2025 (assegno sociale 2026: 546,24 €)
A22: • ISTAT, Pil e indebitamento AP 2022-2024 (03/03/2025); Conti economici nazionali (22/09/2026); indice FOI; inflazione acquisita 2026
... A35: Campo del simulatore: nati fra il 1960 e il 2000, stop fra 40 e 65 anni (foglio 1, riga 8). Fuori campo le celle mostrano un messaggio, non un numero.

Sheet 1 - Il tuo traguardo
A1: Il tuo traguardo: quando arriva la prima rata di vecchiaia
A2: Strumento informativo / divulgativo. NON è consulenza finanziaria. I valori sono indicativi al 2026 e vanno verificati col tuo consulente.
A4: I tuoi dati
A5: Data di nascita | B5: 30756 | C5: Esempio del video: Irene, nata il 15/03/1984
A6: Età a cui vuoi smettere di lavorare: anni | B6: 50
A7: … più mesi | B7: 0
A8: Data di nascita ed età di stop valgono anche nei fogli 2-5 (il caso di Irene). Campo del simulatore: nati fra il 1960 e il 2000; stop fisso fra 40 e 65 anni e 11 mesi, da gennaio 2027 a dicembre 2066 (il caso accumula fino a dicembre 2067). Gli stop minimi si cercano fra 40 e 65 anni: fuori da lì le celle scrivono «già ora» (se regge già da gennaio 2027), «prima dei 40 anni» o «dopo i 65 anni (fuori scala)». Fuori campo compare un messaggio, mai un numero.
A10: La tua prima rata di vecchiaia (curva RGS 27: dal 2029 è una proiezione, non una norma)
A11: Età in cui maturi il requisito | B11: =IFERROR(INT(($B$48-$B$46)/12)&" anni"&IF(MOD(($B$48-$B$46),12)>0," e "&MOD(($B$48-$B$46),12)&IF(MOD(($B$48-$B$46),12)=1," mese"," mesi"),""),"fuori dal campo del simulatore (foglio 1, riga 8)") -> 69 anni e 3 mesi
A12: Mese in cui lo maturi | B12: =IFERROR(CHOOSE(MOD($B$48,12)+1,"gennaio","febbraio","marzo","aprile","maggio","giugno","luglio","agosto","settembre","ottobre","novembre","dicembre")&" "&INT($B$48/12),"fuori dal campo del simulatore (foglio 1, riga 8)") -> giugno 2053
A13: Prima rata (il 1° del mese dopo) | B13: =IFERROR("1° "&CHOOSE(MOD($B$49,12)+1,"gennaio","febbraio","marzo","aprile","maggio","giugno","luglio","agosto","settembre","ottobre","novembre","dicembre")&" "&INT($B$49/12),"fuori dal campo del simulatore (foglio 1, riga 8)") -> 1° luglio 2053
A14: Mesi oltre i 67 anni | B14: =IFERROR($B$48-$B$46-804,"fuori dal campo del simulatore (foglio 1, riga 8)") -> 27
A15: Stop dal lavoro | B15: =IFERROR(INT(($B$47-$B$46)/12)&" anni"&IF(MOD(($B$47-$B$46),12)>0," e "&MOD(($B$47-$B$46),12)&IF(MOD(($B$47-$B$46),12)=1," mese"," mesi"),"")&", "&CHOOSE(MOD($B$47,12)+1,"gennaio","febbraio","marzo","aprile","maggio","giugno","luglio","agosto","settembre","ottobre","novembre","dicembre")&" "&INT($B$47/12),"fuori dal campo del simulatore (foglio 1, riga 8)") -> 50 anni, marzo 2034
A16: Mesi di ponte (dallo stop alla prima rata) | B16: =IFERROR($B$49-$B$47,"fuori dal campo del simulatore (foglio 1, riga 8)") -> 232
A17: Anni di ponte | B17: =IFERROR(INT(($B$49-$B$47)/12)&" anni"&IF(MOD(($B$49-$B$47),12)>0," e "&MOD(($B$49-$B$47),12)&IF(MOD(($B$49-$B$47),12)=1," mese"," mesi"),""),"fuori dal campo del simulatore (foglio 1, riga 8)") -> 19 anni e 4 mesi
A18: La RITA del fondo pensione si apre a | B18: =IFERROR(INT(($B$48-$B$46-120)/12)&" anni"&IF(MOD(($B$48-$B$46-120),12)>0," e "&MOD(($B$48-$B$46-120),12)&IF(MOD(($B$48-$B$46-120),12)=1," mese"," mesi"),""),"fuori dal campo del simulatore (foglio 1, riga 8)") -> 59 anni e 3 mesi | C18: RITA: fino a 10 anni prima dell'età di vecchiaia, dopo 24 mesi senza lavoro (D.Lgs. 252/2005 art. 11 c. 4-bis): si sposta con il traguardo
A20: Pensione anticipata contributiva (64 anni + adeguamenti, 20 anni di contributi; soglia di importo: foglio 5)
A21: Età in cui maturi il requisito | B21: =IFERROR(INT(($B$50-$B$46)/12)&" anni"&IF(MOD(($B$50-$B$46),12)>0," e "&MOD(($B$50-$B$46),12)&IF(MOD(($B$50-$B$46),12)=1," mese"," mesi"),""),"fuori dal campo del simulatore (foglio 1, riga 8)") -> 66 anni
A22: Mese in cui lo maturi | B22: =IFERROR(CHOOSE(MOD($B$50,12)+1,"gennaio","febbraio","marzo","aprile","maggio","giugno","luglio","agosto","settembre","ottobre","novembre","dicembre")&" "&INT($B$50/12),"fuori dal campo del simulatore (foglio 1, riga 8)") -> marzo 2050
A23: Decorrenza (dopo la finestra di 3 mesi) | B23: =IFERROR("1° "&CHOOSE(MOD($B$51,12)+1,"gennaio","febbraio","marzo","aprile","maggio","giugno","luglio","agosto","settembre","ottobre","novembre","dicembre")&" "&INT($B$51/12),"fuori dal campo del simulatore (foglio 1, riga 8)") -> 1° luglio 2050
A24: Età alla decorrenza | B24: =IFERROR(INT(($B$51-$B$46-1)/12)&" anni"&IF(MOD(($B$51-$B$46-1),12)>0," e "&MOD(($B$51-$B$46-1),12)&IF(MOD(($B$51-$B$46-1),12)=1," mese"," mesi"),""),"fuori dal campo del simulatore (foglio 1, riga 8)") -> 66 anni e 3 mesi
A26: La stessa data con la curva di un anno fa (RGS 26, agosto 2025, base ISTAT 2023)
A27: Età della prima rata con la curva RGS 26 | B27: =IFERROR(INT(($B$52-$B$46)/12)&" anni"&IF(MOD(($B$52-$B$46),12)>0," e "&MOD(($B$52-$B$46),12)&IF(MOD(($B$52-$B$46),12)=1," mese"," mesi"),""),"fuori dal campo del simulatore (foglio 1, riga 8)") -> 69 anni e 2 mesi
A28: Prima rata con la curva RGS 26 | B28: =IFERROR("1° "&CHOOSE(MOD($B$53,12)+1,"gennaio","febbraio","marzo","aprile","maggio","giugno","luglio","agosto","settembre","ottobre","novembre","dicembre")&" "&INT($B$53/12),"fuori dal campo del simulatore (foglio 1, riga 8)") -> 1° giugno 2053
A29: Spostamento in un anno (mesi) | B29: =IFERROR($B$49-$B$53,"fuori dal campo del simulatore (foglio 1, riga 8)") -> 1
A31: Le generazioni: prima rata di vecchiaia (proiezione RGS 27), nati a gennaio e a dicembre
A32: Anno di nascita | B32: Nati a gennaio: età | C32: Nati a gennaio: prima rata | D32: Nati a dicembre: età | E32: Nati a dicembre: prima rata | F32: Mesi oltre i 67 (gennaio / dicembre) | G32: RITA da (nati a gennaio)
A33: 1966 | B33: =IFERROR(INT(($C$56-$B$56)/12)&" anni"&IF(MOD(($C$56-$B$56),12)>0," e "&MOD(($C$56-$B$56),12)&IF(MOD(($C$56-$B$56),12)=1," mese"," mesi"),""),"fuori dal campo del simulatore (foglio 1, riga 8)") -> 67 anni e 9 mesi | C33: =IFERROR("1° "&CHOOSE(MOD(($C$56+1),12)+1,"gennaio","febbraio","marzo","aprile","maggio","giugno","luglio","agosto","settembre","ottobre","novembre","dicembre")&" "&INT(($C$56+1)/12),"fuori dal campo del simulatore (foglio 1, riga 8)") -> 1° novembre 2033 | D33: =IFERROR(INT(($E$56-$D$56)/12)&" anni"&IF(MOD(($E$56-$D$56),12)>0," e "&MOD(($E$56-$D$56),12)&IF(MOD(($E$56-$D$56),12)=1," mese"," mesi"),""),"fuori dal campo del simulatore (foglio 1, riga 8)") -> 67 anni e 9 mesi | E33: =IFERROR("1° "&CHOOSE(MOD(($E$56+1),12)+1,"gennaio","febbraio","marzo","aprile","maggio","giugno","luglio","agosto","settembre","ottobre","novembre","dicembre")&" "&INT(($E$56+1)/12),"fuori dal campo del simulatore (foglio 1, riga 8)") -> 1° ottobre 2034 | F33: =IFERROR("+"&($C$56-$B$56-804)&" / +"&($E$56-$D$56-804),"fuori dal campo del simulatore (foglio 1, riga 8)") -> +9 / +9 | G33: =IFERROR(INT(($C$56-$B$56-120)/12)&" anni"&IF(MOD(($C$56-$B$56-120),12)>0," e "&MOD(($C$56-$B$56-120),12)&IF(MOD(($C$56-$B$56-120),12)=1," mese"," mesi"),""),"fuori dal campo del simulatore (foglio 1, riga 8)") -> 57 anni e 9 mesi
A34: 1970 | B34: =IFERROR(INT(($C$57-$B$57)/12)&" anni"&IF(MOD(($C$57-$B$57),12)>0," e "&MOD(($C$57-$B$57),12)&IF(MOD(($C$57-$B$57),12)=1," mese"," mesi"),""),"fuori dal campo del simulatore (foglio 1, riga 8)") -> 68 anni | C34: =IFERROR("1° "&CHOOSE(MOD(($C$57+1),12)+1,"gennaio","febbraio","marzo","aprile","maggio","giugno","luglio","agosto","settembre","ottobre","novembre","dicembre")&" "&INT(($C$57+1)/12),"fuori dal campo del simulatore (foglio 1, riga 8)") -> 1° febbraio 2038 | D34: =IFERROR(INT(($E$57-$D$57)/12)&" anni"&IF(MOD(($E$57-$D$57),12)>0," e "&MOD(($E$57-$D$57),12)&IF(MOD(($E$57-$D$57),12)=1," mese"," mesi"),""),"fuori dal campo del simulatore (foglio 1, riga 8)") -> 68 anni | E34: =IFERROR("1° "&CHOOSE(MOD(($E$57+1),12)+1,"gennaio","febbraio","marzo","aprile","maggio","giugno","luglio","agosto","settembre","ottobre","novembre","dicembre")&" "&INT(($E$57+1)/12),"fuori dal campo del simulatore (foglio 1, riga 8)") -> 1° gennaio 2039 | F34: =IFERROR("+"&($C$57-$B$57-804)&" / +"&($E$57-$D$57-804),"fuori dal campo del simulatore (foglio 1, riga 8)") -> +12 / +12 | G34: =IFERROR(INT(($C$57-$B$57-120)/12)&" anni"&IF(MOD(($C$57-$B$57-120),12)>0," e "&MOD(($C$57-$B$57-120),12)&IF(MOD(($C$57-$B$57-120),12)=1," mese"," mesi"),""),"fuori dal campo del simulatore (foglio 1, riga 8)") -> 58 anni
A35: 1975 | B35: =IFERROR(INT(($C$58-$B$58)/12)&" anni"&IF(MOD(($C$58-$B$58),12)>0," e "&MOD(($C$58-$B$58),12)&IF(MOD(($C$58-$B$58),12)=1," mese"," mesi"),""),"fuori dal campo del simulatore (foglio 1, riga 8)") -> 68 anni e 6 mesi | C35: =IFERROR("1° "&CHOOSE(MOD(($C$58+1),12)+1,"gennaio","febbraio","marzo","aprile","maggio","giugno","luglio","agosto","settembre","ottobre","novembre","dicembre")&" "&INT(($C$58+1)/12),"fuori dal campo del simulatore (foglio 1, riga 8)") -> 1° agosto 2043 | D35: =IFERROR(INT(($E$58-$D$58)/12)&" anni"&IF(MOD(($E$58-$D$58),12)>0," e "&MOD(($E$58-$D$58),12)&IF(MOD(($E$58-$D$58),12)=1," mese"," mesi"),""),"fuori dal campo del simulatore (foglio 1, riga 8)") -> 68 anni e 6 mesi | E35: =IFERROR("1° "&CHOOSE(MOD(($E$58+1),12)+1,"gennaio","febbraio","marzo","aprile","maggio","giugno","luglio","agosto","settembre","ottobre","novembre","dicembre")&" "&INT(($E$58+1)/12),"fuori dal campo del simulatore (foglio 1, riga 8)") -> 1° luglio 2044 | F35: =IFERROR("+"&($C$58-$B$58-804)&" / +"&($E$58-$D$58-804),"fuori dal campo del simulatore (foglio 1, riga 8)") -> +18 / +18 | G35: =IFERROR(INT(($C$58-$B$58-120)/12)&" anni"&IF(MOD(($C$58-$B$58-120),12)>0," e "&MOD(($C$58-$B$58-120),12)&IF(MOD(($C$58-$B$58-120),12)=1," mese"," mesi"),""),"fuori dal campo del simulatore (foglio 1, riga 8)") -> 58 anni e 6 mesi
A36: 1980 | B36: =IFERROR(INT(($C$59-$B$59)/12)&" anni"&IF(MOD(($C$59-$B$59),12)>0," e "&MOD(($C$59-$B$59),12)&IF(MOD(($C$59-$B$59),12)=1," mese"," mesi"),""),"fuori dal campo del simulatore (foglio 1, riga 8)") -> 68 anni e 10 mesi | C36: =IFERROR("1° "&CHOOSE(MOD(($C$59+1),12)+1,"gennaio","febbraio","marzo","aprile","maggio","giugno","luglio","agosto","settembre","ottobre","novembre","dicembre")&" "&INT(($C$59+1)/12),"fuori dal campo del simulatore (foglio 1, riga 8)") -> 1° dicembre 2048 | D36: =IFERROR(INT(($E$59-$D$59)/12)&" anni"&IF(MOD(($E$59-$D$59),12)>0," e "&MOD(($E$59-$D$59),12)&IF(MOD(($E$59-$D$59),12)=1," mese"," mesi"),""),"fuori dal campo del simulatore (foglio 1, riga 8)") -> 69 anni | E36: =IFERROR("1° "&CHOOSE(MOD(($E$59+1),12)+1,"gennaio","febbraio","marzo","aprile","maggio","giugno","luglio","agosto","settembre","ottobre","novembre","dicembre")&" "&INT(($E$59+1)/12),"fuori dal campo del simulatore (foglio 1, riga 8)") -> 1° gennaio 2050 | F36: =IFERROR("+"&($C$59-$B$59-804)&" / +"&($E$59-$D$59-804),"fuori dal campo del simulatore (foglio 1, riga 8)") -> +22 / +24 | G36: =IFERROR(INT(($C$59-$B$59-120)/12)&" anni"&IF(MOD(($C$59-$B$59-120),12)>0," e "&MOD(($C$59-$B$59-120),12)&IF(MOD(($C$59-$B$59-120),12)=1," mese"," mesi"),""),"fuori dal campo del simulatore (foglio 1, riga 8)") -> 58 anni e 10 mesi
A37: 1984 | B37: =IFERROR(INT(($C$60-$B$60)/12)&" anni"&IF(MOD(($C$60-$B$60),12)>0," e "&MOD(($C$60-$B$60),12)&IF(MOD(($C$60-$B$60),12)=1," mese"," mesi"),""),"fuori dal campo del simulatore (foglio 1, riga 8)") -> 69 anni e 3 mesi | C37: =IFERROR("1° "&CHOOSE(MOD(($C$60+1),12)+1,"gennaio","febbraio","marzo","aprile","maggio","giugno","luglio","agosto","settembre","ottobre","novembre","dicembre")&" "&INT(($C$60+1)/12),"fuori dal campo del simulatore (foglio 1, riga 8)") -> 1° maggio 2053 | D37: =IFERROR(INT(($E$60-$D$60)/12)&" anni"&IF(MOD(($E$60-$D$60),12)>0," e "&MOD(($E$60-$D$60),12)&IF(MOD(($E$60-$D$60),12)=1," mese"," mesi"),""),"fuori dal campo del simulatore (foglio 1, riga 8)") -> 69 anni e 3 mesi | E37: =IFERROR("1° "&CHOOSE(MOD(($E$60+1),12)+1,"gennaio","febbraio","marzo","aprile","maggio","giugno","luglio","agosto","settembre","ottobre","novembre","dicembre")&" "&INT(($E$60+1)/12),"fuori dal campo del simulatore (foglio 1, riga 8)") -> 1° aprile 2054 | F37: =IFERROR("+"&($C$60-$B$60-804)&" / +"&($E$60-$D$60-804),"fuori dal campo del simulatore (foglio 1, riga 8)") -> +27 / +27 | G37: =IFERROR(INT(($C$60-$B$60-120)/12)&" anni"&IF(MOD(($C$60-$B$60-120),12)>0," e "&MOD(($C$60-$B$60-120),12)&IF(MOD(($C$60-$B$60-120),12)=1," mese"," mesi"),""),"fuori dal campo del simulatore (foglio 1, riga 8)") -> 59 anni e 3 mesi
A38: 1990 | B38: =IFERROR(INT(($C$61-$B$61)/12)&" anni"&IF(MOD(($C$61-$B$61),12)>0," e "&MOD(($C$61-$B$61),12)&IF(MOD(($C$61-$B$61),12)=1," mese"," mesi"),""),"fuori dal campo del simulatore (foglio 1, riga 8)") -> 69 anni e 9 mesi | C38: =IFERROR("1° "&CHOOSE(MOD(($C$61+1),12)+1,"gennaio","febbraio","marzo","aprile","maggio","giugno","luglio","agosto","settembre","ottobre","novembre","dicembre")&" "&INT(($C$61+1)/12),"fuori dal campo del simulatore (foglio 1, riga 8)") -> 1° novembre 2059 | D38: =IFERROR(INT(($E$61-$D$61)/12)&" anni"&IF(MOD(($E$61-$D$61),12)>0," e "&MOD(($E$61-$D$61),12)&IF(MOD(($E$61-$D$61),12)=1," mese"," mesi"),""),"fuori dal campo del simulatore (foglio 1, riga 8)") -> 69 anni e 9 mesi | E38: =IFERROR("1° "&CHOOSE(MOD(($E$61+1),12)+1,"gennaio","febbraio","marzo","aprile","maggio","giugno","luglio","agosto","settembre","ottobre","novembre","dicembre")&" "&INT(($E$61+1)/12),"fuori dal campo del simulatore (foglio 1, riga 8)") -> 1° ottobre 2060 | F38: =IFERROR("+"&($C$61-$B$61-804)&" / +"&($E$61-$D$61-804),"fuori dal campo del simulatore (foglio 1, riga 8)") -> +33 / +33 | G38: =IFERROR(INT(($C$61-$B$61-120)/12)&" anni"&IF(MOD(($C$61-$B$61-120),12)>0," e "&MOD(($C$61-$B$61-120),12)&IF(MOD(($C$61-$B$61-120),12)=1," mese"," mesi"),""),"fuori dal campo del simulatore (foglio 1, riga 8)") -> 59 anni e 9 mesi
A39: 2000 | B39: =IFERROR(INT(($C$62-$B$62)/12)&" anni"&IF(MOD(($C$62-$B$62),12)>0," e "&MOD(($C$62-$B$62),12)&IF(MOD(($C$62-$B$62),12)=1," mese"," mesi"),""),"fuori dal campo del simulatore (foglio 1, riga 8)") -> 70 anni e 3 mesi | C39: =IFERROR("1° "&CHOOSE(MOD(($C$62+1),12)+1,"gennaio","febbraio","marzo","aprile","maggio","giugno","luglio","agosto","settembre","ottobre","novembre","dicembre")&" "&INT(($C$62+1)/12),"fuori dal campo del simulatore (foglio 1, riga 8)") -> 1° maggio 2070 | D39: =IFERROR(INT(($E$62-$D$62)/12)&" anni"&IF(MOD(($E$62-$D$62),12)>0," e "&MOD(($E$62-$D$62),12)&IF(MOD(($E$62-$D$62),12)=1," mese"," mesi"),""),"fuori dal campo del simulatore (foglio 1, riga 8)") -> 70 anni e 4 mesi | E39: =IFERROR("1° "&CHOOSE(MOD(($E$62+1),12)+1,"gennaio","febbraio","marzo","aprile","maggio","giugno","luglio","agosto","settembre","ottobre","novembre","dicembre")&" "&INT(($E$62+1)/12),"fuori dal campo del simulatore (foglio 1, riga 8)") -> 1° maggio 2071 | F39: =IFERROR("+"&($C$62-$B$62-804)&" / +"&($E$62-$D$62-804),"fuori dal campo del simulatore (foglio 1, riga 8)") -> +39 / +40 | G39: =IFERROR(INT(($C$62-$B$62-120)/12)&" anni"&IF(MOD(($C$62-$B$62-120),12)>0," e "&MOD(($C$62-$B$62-120),12)&IF(MOD(($C$62-$B$62-120),12)=1," mese"," mesi"),""),"fuori dal campo del simulatore (foglio 1, riga 8)") -> 60 anni e 3 mesi
A40: Dopo il 2028 le età sono proiezioni della Ragioneria (scenario demografico ISTAT mediano, base 2024), non norme: la data vera si fissa con i decreti biennali sulla speranza di vita. Nato/a il 15 del mese: la prima rata parte il 1° del mese dopo la maturazione.
A44: Motore del calcolo — non modificare
A45: Indici di mese = anno × 12 + mese − 1. Maturazione = primo mese in cui l'età raggiunge il requisito dell'anno solare (MATCH sulla colonna «ultimo mese di nascita che matura nell'anno»).
A46: Mese di nascita (indice) | B46: =YEAR($B$5)*12+MONTH($B$5)-1 -> 23810
A47: Mese di stop (indice) | B47: =$B$46+12*$B$6+$B$7 -> 24410
A48: Maturazione vecchiaia RGS 27 (indice) | B48: =MAX(12*(2011+(IFERROR(MATCH($B$46-0.5,$F$65:$F$137,1),0)+1)),$B$46+INDEX($B$65:$B$137,(IFERROR(MATCH($B$46-0.5,$F$65:$F$137,1),0)+1))) -> 24641
A49: Prima rata vecchiaia RGS 27 (indice) | B49: =$B$48+1 -> 24642
A50: Maturazione anticipata contributiva (indice) | B50: =MAX(12*(2025+(IFERROR(MATCH($B$46-0.5,$G$79:$G$137,1),0)+1)),$B$46+INDEX($D$79:$D$137,(IFERROR(MATCH($B$46-0.5,$G$79:$G$137,1),0)+1))) -> 24602
A51: Decorrenza anticipata (indice): finestra di 3 mesi + 1° del mese dopo | B51: =$B$50+4 -> 24606
A52: Maturazione vecchiaia RGS 26 (indice) | B52: =MAX(12*(2011+(IFERROR(MATCH($B$46-0.5,$H$65:$H$137,1),0)+1)),$B$46+INDEX($E$65:$E$137,(IFERROR(MATCH($B$46-0.5,$H$65:$H$137,1),0)+1))) -> 24640
A53: Prima rata vecchiaia RGS 26 (indice) | B53: =$B$52+1 -> 24641
A55: Coorte | B55: Nascita a gennaio (indice) | C55: Maturazione (gennaio) | D55: Nascita a dicembre (indice) | E55: Maturazione (dicembre)
A56: =$A$33 -> 1966 | B56: =$A$56*12 -> 23592 | C56: =MAX(12*(2011+(IFERROR(MATCH($B$56-0.5,$F$65:$F$137,1),0)+1)),$B$56+INDEX($B$65:$B$137,(IFERROR(MATCH($B$56-0.5,$F$65:$F$137,1),0)+1))) -> 24405 | D56: =$A$56*12+11 -> 23603 | E56: =MAX(12*(2011+(IFERROR(MATCH($D$56-0.5,$F$65:$F$137,1),0)+1)),$D$56+INDEX($B$65:$B$137,(IFERROR(MATCH($D$56-0.5,$F$65:$F$137,1),0)+1))) -> 24416
A57: =$A$34 -> 1970 | B57: =$A$57*12 -> 23640 | C57: =MAX(12*(2011+(IFERROR(MATCH($B$57-0.5,$F$65:$F$137,1),0)+1)),$B$57+INDEX($B$65:$B$137,(IFERROR(MATCH($B$57-0.5,$F$65:$F$137,1),0)+1))) -> 24456 | D57: =$A$57*12+11 -> 23651 | E57: =MAX(12*(2011+(IFERROR(MATCH($D$57-0.5,$F$65:$F$137,1),0)+1)),$D$57+INDEX($B$65:$B$137,(IFERROR(MATCH($D$57-0.5,$F$65:$F$137,1),0)+1))) -> 24467
A58: =$A$35 -> 1975 | B58: =$A$58*12 -> 23700 | C58: =MAX(12*(2011+(IFERROR(MATCH($B$58-0.5,$F$65:$F$137,1),0)+1)),$B$58+INDEX($B$65:$B$137,(IFERROR(MATCH($B$58-0.5,$F$65:$F$137,1),0)+1))) -> 24522 | D58: =$A$58*12+11 -> 23711 | E58: =MAX(12*(2011+(IFERROR(MATCH($D$58-0.5,$F$65:$F$137,1),0)+1)),$D$58+INDEX($B$65:$B$137,(IFERROR(MATCH($D$58-0.5,$F$65:$F$137,1),0)+1))) -> 24533
A59: =$A$36 -> 1980 | B59: =$A$59*12 -> 23760 | C59: =MAX(12*(2011+(IFERROR(MATCH($B$59-0.5,$F$65:$F$137,1),0)+1)),$B$59+INDEX($B$65:$B$137,(IFERROR(MATCH($B$59-0.5,$F$65:$F$137,1),0)+1))) -> 24586 | D59: =$A$59*12+11 -> 23771 | E59: =MAX(12*(2011+(IFERROR(MATCH($D$59-0.5,$F$65:$F$137,1),0)+1)),$D$59+INDEX($B$65:$B$137,(IFERROR(MATCH($D$59-0.5,$F$65:$F$137,1),0)+1))) -> 24599
A60: =$A$37 -> 1984 | B60: =$A$60*12 -> 23808 | C60: =MAX(12*(2011+(IFERROR(MATCH($B$60-0.5,$F$65:$F$137,1),0)+1)),$B$60+INDEX($B$65:$B$137,(IFERROR(MATCH($B$60-0.5,$F$65:$F$137,1),0)+1))) -> 24639 | D60: =$A$60*12+11 -> 23819 | E60: =MAX(12*(2011+(IFERROR(MATCH($D$60-0.5,$F$65:$F$137,1),0)+1)),$D$60+INDEX($B$65:$B$137,(IFERROR(MATCH($D$60-0.5,$F$65:$F$137,1),0)+1))) -> 24650
A61: =$A$38 -> 1990 | B61: =$A$61*12 -> 23880 | C61: =MAX(12*(2011+(IFERROR(MATCH($B$61-0.5,$F$65:$F$137,1),0)+1)),$B$61+INDEX($B$65:$B$137,(IFERROR(MATCH($B$61-0.5,$F$65:$F$137,1),0)+1))) -> 24717 | D61: =$A$61*12+11 -> 23891 | E61: =MAX(12*(2011+(IFERROR(MATCH($D$61-0.5,$F$65:$F$137,1),0)+1)),$D$61+INDEX($B$65:$B$137,(IFERROR(MATCH($D$61-0.5,$F$65:$F$137,1),0)+1))) -> 24728
A62: =$A$39 -> 2000 | B62: =$A$62*12 -> 24000 | C62: =MAX(12*(2011+(IFERROR(MATCH($B$62-0.5,$F$65:$F$137,1),0)+1)),$B$62+INDEX($B$65:$B$137,(IFERROR(MATCH($B$62-0.5,$F$65:$F$137,1),0)+1))) -> 24843 | D62: =$A$62*12+11 -> 24011 | E62: =MAX(12*(2011+(IFERROR(MATCH($D$62-0.5,$F$65:$F$137,1),0)+1)),$D$62+INDEX($B$65:$B$137,(IFERROR(MATCH($D$62-0.5,$F$65:$F$137,1),0)+1))) -> 24855
A64: Anno | B64: Vecchiaia RGS 27 (mesi di età) | C64: Vecchiaia RGS 27 (età) | D64: Anticipata contributiva RGS 27 (mesi di età) | E64: Vecchiaia RGS 26 (mesi di età) | F64: Ultimo mese di nascita che matura nell'anno (RGS 27) | G64: Idem, anticipata | H64: Idem, RGS 26 | I64: Fonte
A65: 2012 | B65: 792 | C65: =INT($B65/12)&" anni"&IF(MOD($B65,12)>0," e "&MOD($B65,12)&IF(MOD($B65,12)=1," mese"," mesi"),"") -> 66 anni | E65: 792 | F65: =12*$A65+11-$B65 -> 23363 | H65: =12*$A65+11-$E65 -> 23363 | I65: RGS, Rapporto n. 27 (22/09/2026), Tab. A1.4 p. 211, colonna «Lavoratori dipendenti e autonomi»; anticipata: Tab. A1.5 p. 212, ultima colonna (canale dei contributivi puri). Dal 2029 proiezioni ISTAT mediano base 2024.
A66: 2013 | B66: 795 | C66: =INT($B66/12)&" anni"&IF(MOD($B66,12)>0," e "&MOD($B66,12)&IF(MOD($B66,12)=1," mese"," mesi"),"") -> 66 anni e 3 mesi | E66: 795 | F66: =12*$A66+11-$B66 -> 23372 | H66: =12*$A66+11-$E66 -> 23372 | I66: RGS 26: Rapporto n. 26 (agosto 2025), App. 1 p. 206, base ISTAT 2023 (curva di un anno fa).
A67: 2014 | B67: 795 | C67: =INT($B67/12)&" anni"&IF(MOD($B67,12)>0," e "&MOD($B67,12)&IF(MOD($B67,12)=1," mese"," mesi"),"") -> 66 anni e 3 mesi | E67: 795 | F67: =12*$A67+11-$B67 -> 23384 | H67: =12*$A67+11-$E67 -> 23384 | I67: Oltre il 2084 la tabella si ferma: nati dopo il 2014 fuori scala.
A68: 2015 | B68: 795 | C68: =INT($B68/12)&" anni"&IF(MOD($B68,12)>0," e "&MOD($B68,12)&IF(MOD($B68,12)=1," mese"," mesi"),"") -> 66 anni e 3 mesi | E68: 795 | F68: =12*$A68+11-$B68 -> 23396 | H68: =12*$A68+11-$E68 -> 23396
A69: 2016 | B69: 799 | C69: =INT($B69/12)&" anni"&IF(MOD($B69,12)>0," e "&MOD($B69,12)&IF(MOD($B69,12)=1," mese"," mesi"),"") -> 66 anni e 7 mesi | E69: 799 | F69: =12*$A69+11-$B69 -> 23404 | H69: =12*$A69+11-$E69 -> 23404
A70: 2017 | B70: 799 | C70: =INT($B70/12)&" anni"&IF(MOD($B70,12)>0," e "&MOD($B70,12)&IF(MOD($B70,12)=1," mese"," mesi"),"") -> 66 anni e 7 mesi | E70: 799 | F70: =12*$A70+11-$B70 -> 23416 | H70: =12*$A70+11-$E70 -> 23416
A71: 2018 | B71: 799 | C71: =INT($B71/12)&" anni"&IF(MOD($B71,12)>0," e "&MOD($B71,12)&IF(MOD($B71,12)=1," mese"," mesi"),"") -> 66 anni e 7 mesi | E71: 799 | F71: =12*$A71+11-$B71 -> 23428 | H71: =12*$A71+11-$E71 -> 23428
A72: 2019 | B72: 804 | C72: =INT($B72/12)&" anni"&IF(MOD($B72,12)>0," e "&MOD($B72,12)&IF(MOD($B72,12)=1," mese"," mesi"),"") -> 67 anni | E72: 804 | F72: =12*$A72+11-$B72 -> 23435 | H72: =12*$A72+11-$E72 -> 23435
A73: 2020 | B73: 804 | C73: =INT($B73/12)&" anni"&IF(MOD($B73,12)>0," e "&MOD($B73,12)&IF(MOD($B73,12)=1," mese"," mesi"),"") -> 67 anni | E73: 804 | F73: =12*$A73+11-$B73 -> 23447 | H73: =12*$A73+11-$E73 -> 23447
A74: 2021 | B74: 804 | C74: =INT($B74/12)&" anni"&IF(MOD($B74,12)>0," e "&MOD($B74,12)&IF(MOD($B74,12)=1," mese"," mesi"),"") -> 67 anni | E74: 804 | F74: =12*$A74+11-$B74 -> 23459 | H74: =12*$A74+11-$E74 -> 23459
A75: 2022 | B75: 804 | C75: =INT($B75/12)&" anni"&IF(MOD($B75,12)>0," e "&MOD($B75,12)&IF(MOD($B75,12)=1," mese"," mesi"),"") -> 67 anni | E75: 804 | F75: =12*$A75+11-$B75 -> 23471 | H75: =12*$A75+11-$E75 -> 23471
A76: 2023 | B76: 804 | C76: =INT($B76/12)&" anni"&IF(MOD($B76,12)>0," e "&MOD($B76,12)&IF(MOD($B76,12)=1," mese"," mesi"),"") -> 67 anni | E76: 804 | F76: =12*$A76+11-$B76 -> 23483 | H76: =12*$A76+11-$E76 -> 23483
A77: 2024 | B77: 804 | C77: =INT($B77/12)&" anni"&IF(MOD($B77,12)>0," e "&MOD($B77,12)&IF(MOD($B77,12)=1," mese"," mesi"),"") -> 67 anni | E77: 804 | F77: =12*$A77+11-$B77 -> 23495 | H77: =12*$A77+11-$E77 -> 23495
A78: 2025 | B78: 804 | C78: =INT($B78/12)&" anni"&IF(MOD($B78,12)>0," e "&MOD($B78,12)&IF(MOD($B78,12)=1," mese"," mesi"),"") -> 67 anni | E78: 804 | F78: =12*$A78+11-$B78 -> 23507 | H78: =12*$A78+11-$E78 -> 23507
A79: 2026 | B79: 804 | C79: =INT($B79/12)&" anni"&IF(MOD($B79,12)>0," e "&MOD($B79,12)&IF(MOD($B79,12)=1," mese"," mesi"),"") -> 67 anni | D79: 768 | E79: 804 | F79: =12*$A79+11-$B79 -> 23519 | G79: =12*$A79+11-$D79 -> 23555 | H79: =12*$A79+11-$E79 -> 23519
A80: 2027 | B80: 805 | C80: =INT($B80/12)&" anni"&IF(MOD($B80,12)>0," e "&MOD($B80,12)&IF(MOD($B80,12)=1," mese"," mesi"),"") -> 67 anni e 1 mese | D80: 769 | E80: 807 | F80: =12*$A80+11-$B80 -> 23530 | G80: =12*$A80+11-$D80 -> 23566 | H80: =12*$A80+11-$E80 -> 23528
A81: 2028 | B81: 807 | C81: =INT($B81/12)&" anni"&IF(MOD($B81,12)>0," e "&MOD($B81,12)&IF(MOD($B81,12)=1," mese"," mesi"),"") -> 67 anni e 3 mesi | D81: 771 | E81: 807 | F81: =12*$A81+11-$B81 -> 23540 | G81: =12*$A81+11-$D81 -> 23576 | H81: =12*$A81+11-$E81 -> 23540
A82: 2029 | B82: 810 | C82: =INT($B82/12)&" anni"&IF(MOD($B82,12)>0," e "&MOD($B82,12)&IF(MOD($B82,12)=1," mese"," mesi"),"") -> 67 anni e 6 mesi | D82: 774 | E82: 809 | F82: =12*$A82+11-$B82 -> 23549 | G82: =12*$A82+11-$D82 -> 23585 | H82: =12*$A82+11-$E82 -> 23550
A83: 2030 | B83: 810 | C83: =INT($B83/12)&" anni"&IF(MOD($B83,12)>0," e "&MOD($B83,12)&IF(MOD($B83,12)=1," mese"," mesi"),"") -> 67 anni e 6 mesi | D83: 774 | E83: 809 | F83: =12*$A83+11-$B83 -> 23561 | G83: =12*$A83+11-$D83 -> 23597 | H83: =12*$A83+11-$E83 -> 23562
A84: 2031 | B84: 812 | C84: =INT($B84/12)&" anni"&IF(MOD($B84,12)>0," e "&MOD($B84,12)&IF(MOD($B84,12)=1," mese"," mesi"),"") -> 67 anni e 8 mesi | D84: 776 | E84: 811 | F84: =12*$A84+11-$B84 -> 23571 | G84: =12*$A84+11-$D84 -> 23607 | H84: =12*$A84+11-$E84 -> 23572
A85: 2032 | B85: 812 | C85: =INT($B85/12)&" anni"&IF(MOD($B85,12)>0," e "&MOD($B85,12)&IF(MOD($B85,12)=1," mese"," mesi"),"") -> 67 anni e 8 mesi | D85: 776 | E85: 811 | F85: =12*$A85+11-$B85 -> 23583 | G85: =12*$A85+11-$D85 -> 23619 | H85: =12*$A85+11-$E85 -> 23584
A86: 2033 | B86: 813 | C86: =INT($B86/12)&" anni"&IF(MOD($B86,12)>0," e "&MOD($B86,12)&IF(MOD($B86,12)=1," mese"," mesi"),"") -> 67 anni e 9 mesi | D86: 777 | E86: 812 | F86: =12*$A86+11-$B86 -> 23594 | G86: =12*$A86+11-$D86 -> 23630 | H86: =12*$A86+11-$E86 -> 23595
A87: 2034 | B87: 813 | C87: =INT($B87/12)&" anni"&IF(MOD($B87,12)>0," e "&MOD($B87,12)&IF(MOD($B87,12)=1," mese"," mesi"),"") -> 67 anni e 9 mesi | D87: 777 | E87: 812 | F87: =12*$A87+11-$B87 -> 23606 | G87: =12*$A87+11-$D87 -> 23642 | H87: =12*$A87+11-$E87 -> 23607
A88: 2035 | B88: 814 | C88: =INT($B88/12)&" anni"&IF(MOD($B88,12)>0," e "&MOD($B88,12)&IF(MOD($B88,12)=1," mese"," mesi"),"") -> 67 anni e 10 mesi | D88: 778 | E88: 814 | F88: =12*$A88+11-$B88 -> 23617 | G88: =12*$A88+11-$D88 -> 23653 | H88: =12*$A88+11-$E88 -> 23617
A89: 2036 | B89: 814 | C89: =INT($B89/12)&" anni"&IF(MOD($B89,12)>0," e "&MOD($B89,12)&IF(MOD($B89,12)=1," mese"," mesi"),"") -> 67 anni e 10 mesi | D89: 778 | E89: 814 | F89: =12*$A89+11-$B89 -> 23629 | G89: =12*$A89+11-$D89 -> 23665 | H89: =12*$A89+11-$E89 -> 23629
A90: 2037 | B90: 816 | C90: =INT($B90/12)&" anni"&IF(MOD($B90,12)>0," e "&MOD($B90,12)&IF(MOD($B90,12)=1," mese"," mesi"),"") -> 68 anni | D90: 780 | E90: 815 | F90: =12*$A90+11-$B90 -> 23639 | G90: =12*$A90+11-$D90 -> 23675 | H90: =12*$A90+11-$E90 -> 23640
... A137: 2084 | B137: 849 | C137: =INT($B137/12)&" anni"&IF(MOD($B137,12)>0," e "&MOD($B137,12)&IF(MOD($B137,12)=1," mese"," mesi"),"") -> 70 anni e 9 mesi | D137: 813 | E137: 848 | F137: =12*$A137+11-$B137 -> 24170 | G137: =12*$A137+11-$D137 -> 24206 | H137: =12*$A137+11-$E137 -> 24171

Sheet 2 - Il costo del ponte
A1: Il costo del ponte: quanto capitale serve per arrivare alla prima rata
A2: Strumento informativo / divulgativo. NON è consulenza finanziaria. I valori sono indicativi al 2026 e vanno verificati col tuo consulente.
A4: Ipotesi (rendimento, inflazione, imposte e bollo valgono anche nei fogli 3-5)
A5: Spesa annua nel ponte (euro di oggi) | B5: 24000 | C5: Tabella generale del video: 24.000 €. Il caso di Irene (22.000 €) sta nel foglio 3.
A6: Rendimento reale del portafoglio | B6: 0.03 | C6: Canone del canale (portafoglio 60/40).
A7: Inflazione dopo il 2026 | B7: 0.02 | C7: Obiettivo BCE, canone del canale.
A8: Plusvalenza latente allo stop (quota del patrimonio) | B8: 0.2 | C8: Ipotesi generale delle tabelle; per Irene il foglio 3 la calcola dalla sua storia.
A9: Imposta sulle plusvalenze | B9: 0.26 | C9: Pagata solo sulla quota di guadagno di ciò che vendi (base di costo tracciata).
A10: Imposta di bollo annua | B10: 0.002 | C10: Sul valore del dossier.
A12: Risultati (data di nascita ed età di stop dal foglio 1)
A13: Stop dal lavoro | B13: =IFERROR(INT(('1 - Il tuo traguardo'!$B$47-'1 - Il tuo traguardo'!$B$46)/12)&" anni"&IF(MOD(('1 - Il tuo traguardo'!$B$47-'1 - Il tuo traguardo'!$B$46),12)>0," e "&MOD(('1 - Il tuo traguardo'!$B$47-'1 - Il tuo traguardo'!$B$46),12)&IF(MOD(('1 - Il tuo traguardo'!$B$47-'1 - Il tuo traguardo'!$B$46),12)=1," mese"," mesi"),"")&", "&CHOOSE(MOD('1 - Il tuo traguardo'!$B$47,12)+1,"gennaio","febbraio","marzo","aprile","maggio","giugno","luglio","agosto","settembre","ottobre","novembre","dicembre")&" "&INT('1 - Il tuo traguardo'!$B$47/12),"fuori dal campo del simulatore (foglio 1, riga 8)") -> 50 anni, marzo 2034
A14: Prima rata di vecchiaia (foglio 1) | B14: =IFERROR("1° "&CHOOSE(MOD('1 - Il tuo traguardo'!$B$49,12)+1,"gennaio","febbraio","marzo","aprile","maggio","giugno","luglio","agosto","settembre","ottobre","novembre","dicembre")&" "&INT('1 - Il tuo traguardo'!$B$49/12),"fuori dal campo del simulatore (foglio 1, riga 8)") -> 1° luglio 2053
A15: Mesi di ponte | B15: =IFERROR($B$37,"fuori dal campo del simulatore (foglio 1, riga 8)") -> 232
A16: Capitale del ponte allo stop (euro di oggi) | B16: =IFERROR($X$41,"fuori dal campo del simulatore (foglio 1, riga 8)") -> 412708.86
A17: Capitale con un mese di requisito in più | B17: =IFERROR($X$86,"fuori dal campo del simulatore (foglio 1, riga 8)") -> 414145.7
A18: Un mese in più di requisito costa | B18: =IFERROR($X$86-$X$41,"fuori dal campo del simulatore (foglio 1, riga 8)") -> 1436.8424
A19: … in mesi di spesa | B19: =IFERROR(($X$86-$X$41)/('2 - Il costo del ponte'!$B$5/12),"fuori dal campo del simulatore (foglio 1, riga 8)") -> 0.71842122
A20: Moltiplicatore implicito: capitale / valore attuale della spesa al rendimento reale | B20: =IFERROR($X$41/$D$41,"fuori dal campo del simulatore (foglio 1, riga 8)") -> 1.1507396
A21: Moltiplicatore fiscale medio del canale (per confronto) | B21: 1.173 | C21: Fonte: posso_smettere_01/02 (canale): costo medio di imposte e bollo sul capitale
A22: Il ponte si paga col portafoglio (prelievo a inizio anno, 26% sulla quota di plusvalenza, bollo). Tabella del video: nati nel 1984, stop a 50 anni, 24.000 € di spesa, latente 20%.
A26: Motore del calcolo — non modificare
A27: Capitale necessario = il più piccolo capitale per cui il minimo del percorso (saldo dopo ogni prelievo e saldo finale, in euro dello stop) non scende sotto zero; trovato con la secante (2 inneschi + 4 correzioni).
A29: Rendimento reale (foglio 2) | B29: ='2 - Il costo del ponte'!$B$6 -> 0.03
A30: Inflazione dopo il 2026 (foglio 2) | B30: ='2 - Il costo del ponte'!$B$7 -> 0.02
A31: Imposta sulle plusvalenze (foglio 2) | B31: ='2 - Il costo del ponte'!$B$9 -> 0.26
A32: 1 − bollo (foglio 2) | B32: =1-'2 - Il costo del ponte'!$B$10 -> 0.998
A33: Crescita reale annua del portafoglio (1 + r), prima del bollo | B33: =1+$B$29 -> 1.03
A34: Inflazione: la base di costo nominale perde (1 + inflazione) ogni anno in euro reali | B34: =1+$B$30 -> 1.02
A36: Ricerca 1 — capitale del ponte | B36: Capitale necessario: | C36: =$X$41 -> 412708.86
A37: Mesi di ponte (foglio 1) | B37: ='1 - Il tuo traguardo'!$B$49-'1 - Il tuo traguardo'!$B$47 -> 232
A38: Spesa annua | B38: ='2 - Il costo del ponte'!$B$5 -> 24000
A39: Plusvalenza latente allo stop | B39: ='2 - Il costo del ponte'!$B$8 -> 0.2
A40: Numero di prelievi annui | B40: =ROUNDUP($B$37/12,0) -> 20
A41: Capitale provato (secante: 2 inneschi + 4 correzioni) | D41: =IF(SUMPRODUCT($C$44:$C$79,1/$B$33^$B$44:$B$79)<=0,1000,SUMPRODUCT($C$44:$C$79,1/$B$33^$B$44:$B$79)) -> 358646.6 | H41: =1.15*$D$41 -> 412443.59 | L41: =IF($H$42=$D$42,$H$41,$H$41-$H$42*($H$41-$D$41)/($H$42-$D$42)) -> 412705.67 | P41: =IF($L$42=$H$42,$L$41,$L$41-$L$42*($L$41-$H$41)/($L$42-$H$42)) -> 412708.86 | T41: =IF($P$42=$L$42,$P$41,$P$41-$P$42*($P$41-$L$41)/($P$42-$L$42)) -> 412708.86 | X41: =IF($T$42=$P$42,$T$41,$T$41-$T$42*($T$41-$P$41)/($T$42-$P$42)) -> 412708.86
A42: Minimo del percorso con quel capitale (euro dello stop) | D42: =MIN($F$44:$F$79) -> -78448.803 | H42: =MIN($J$44:$J$79) -> -380.31471 | L42: =MIN($N$44:$N$79) -> -4.5781937 | P42: =MIN($R$44:$R$79) -> -2.1955771e-11 | T42: =MIN($V$44:$V$79) -> -2.1955771e-11
B43: k (anni dallo stop) | C43: Fabbisogno (euro dello stop) | D43: Prova 1: Patrimonio prima del prelievo | E43: Prova 1: Prelievo lordo | F43: Prova 1: Patrimonio dopo il prelievo | G43: Prova 1: Base di costo (all'anno dopo) | H43: Prova 2: Patrimonio prima del prelievo | I43: Prova 2: Prelievo lordo | J43: Prova 2: Patrimonio dopo il prelievo | K43: Prova 2: Base di costo (all'anno dopo) | L43: Prova 3: Patrimonio prima del prelievo | M43: Prova 3: Prelievo lordo | N43: Prova 3: Patrimonio dopo il prelievo | O43: Prova 3: Base di costo (all'anno dopo) | P43: Prova 4: Patrimonio prima del prelievo | Q43: Prova 4: Prelievo lordo | R43: Prova 4: Patrimonio dopo il prelievo | S43: Prova 4: Base di costo (all'anno dopo) | T43: Prova 5: Patrimonio prima del prelievo | U43: Prova 5: Prelievo lordo | V43: Prova 5: Patrimonio dopo il prelievo | W43: Prova 5: Base di costo (all'anno dopo) | X43: Capitale necessario
B44: 0 | C44: =$B$38*MIN(12,MAX(0,$B$37-12*$B44))/12 -> 24000 | D44: =$D$41 -> 358646.6 | E44: =IF(AND(C44>0,D44>0),C44/(1-$B$31*MAX(0,1-$D$41*(1-$B$39)/D44)),0) -> 25316.456 | F44: =IF(E44>0,IF(E44<=D44,D44-E44,C44*(D44/E44-1)),D44-C44) -> 333330.15 | G44: =IF(E44>0,IF(E44<=D44,$D$41*(1-$B$39)*(1-E44/D44),0),IF(AND(C44<0,F44>0),$D$41*(1-$B$39)-C44,$D$41*(1-$B$39)))/$B$34 -> 261435.41 | H44: =$H$41 -> 412443.59 | I44: =IF(AND(C44>0,H44>0),C44/(1-$B$31*MAX(0,1-$H$41*(1-$B$39)/H44)),0) -> 25316.456 | J44: =IF(I44>0,IF(I44<=H44,H44-I44,C44*(H44/I44-1)),H44-C44) -> 387127.14 | K44: =IF(I44>0,IF(I44<=H44,$H$41*(1-$B$39)*(1-I44/H44),0),IF(AND(C44<0,J44>0),$H$41*(1-$B$39)-C44,$H$41*(1-$B$39)))/$B$34 -> 303629.13 | L44: =$L$41 -> 412705.67 | M44: =IF(AND(C44>0,L44>0),C44/(1-$B$31*MAX(0,1-$L$41*(1-$B$39)/L44)),0) -> 25316.456 | N44: =IF(M44>0,IF(M44<=L44,L44-M44,C44*(L44/M44-1)),L44-C44) -> 387389.21 | O44: =IF(M44>0,IF(M44<=L44,$L$41*(1-$B$39)*(1-M44/L44),0),IF(AND(C44<0,N44>0),$L$41*(1-$B$39)-C44,$L$41*(1-$B$39)))/$B$34 -> 303834.68 | P44: =$P$41 -> 412708.86 | Q44: =IF(AND(C44>0,P44>0),C44/(1-$B$31*MAX(0,1-$P$41*(1-$B$39)/P44)),0) -> 25316.456 | R44: =IF(Q44>0,IF(Q44<=P44,P44-Q44,C44*(P44/Q44-1)),P44-C44) -> 387392.4 | S44: =IF(Q44>0,IF(Q44<=P44,$P$41*(1-$B$39)*(1-Q44/P44),0),IF(AND(C44<0,R44>0),$P$41*(1-$B$39)-C44,$P$41*(1-$B$39)))/$B$34 -> 303837.18 | T44: =$T$41 -> 412708.86 | U44: =IF(AND(C44>0,T44>0),C44/(1-$B$31*MAX(0,1-$T$41*(1-$B$39)/T44)),0) -> 25316.456 | V44: =IF(U44>0,IF(U44<=T44,T44-U44,C44*(T44/U44-1)),T44-C44) -> 387392.4 | W44: =IF(U44>0,IF(U44<=T44,$T$41*(1-$B$39)*(1-U44/T44),0),IF(AND(C44<0,V44>0),$T$41*(1-$B$39)-C44,$T$41*(1-$B$39)))/$B$34 -> 303837.18
B45: 1 | C45: =$B$38*MIN(12,MAX(0,$B$37-12*$B45))/12 -> 24000 | D45: =IF($B45>$B$40,F44,F44*$B$33*IF(F44>0,$B$32,1)) -> 342643.39 | E45: =IF(AND(C45>0,D45>0),C45/(1-$B$31*MAX(0,1-G44/D45)),0) -> 25576.024 | F45: =IF(E45>0,IF(E45<=D45,D45-E45,C45*(D45/E45-1)),D45-C45) -> 317067.37 | G45: =IF(E45>0,IF(E45<=D45,G44*(1-E45/D45),0),IF(AND(C45<0,F45>0),G44-C45,G44))/$B$34 -> 237177.47 | H45: =IF($B45>$B$40,J44,J44*$B$33*IF(J44>0,$B$32,1)) -> 397943.47 | I45: =IF(AND(C45>0,H45>0),C45/(1-$B$31*MAX(0,1-K44/H45)),0) -> 25576.024 | J45: =IF(I45>0,IF(I45<=H45,H45-I45,C45*(H45/I45-1)),H45-C45) -> 372367.45 | K45: =IF(I45>0,IF(I45<=H45,K44*(1-I45/H45),0),IF(AND(C45<0,J45>0),K44-C45,K44))/$B$34 -> 278543.86 | L45: =IF($B45>$B$40,N44,N44*$B$33*IF(N44>0,$B$32,1)) -> 398212.87 | M45: =IF(AND(C45>0,L45>0),C45/(1-$B$31*MAX(0,1-O44/L45)),0) -> 25576.024 | N45: =IF(M45>0,IF(M45<=L45,L45-M45,C45*(L45/M45-1)),L45-C45) -> 372636.84 | O45: =IF(M45>0,IF(M45<=L45,O44*(1-M45/L45),0),IF(AND(C45<0,N45>0),O44-C45,O44))/$B$34 -> 278745.37 | P45: =IF($B45>$B$40,R44,R44*$B$33*IF(R44>0,$B$32,1)) -> 398216.15 | Q45: =IF(AND(C45>0,P45>0),C45/(1-$B$31*MAX(0,1-S44/P45)),0) -> 25576.024 | R45: =IF(Q45>0,IF(Q45<=P45,P45-Q45,C45*(P45/Q45-1)),P45-C45) -> 372640.12 | S45: =IF(Q45>0,IF(Q45<=P45,S44*(1-Q45/P45),0),IF(AND(C45<0,R45>0),S44-C45,S44))/$B$34 -> 278747.83 | T45: =IF($B45>$B$40,V44,V44*$B$33*IF(V44>0,$B$32,1)) -> 398216.15 | U45: =IF(AND(C45>0,T45>0),C45/(1-$B$31*MAX(0,1-W44/T45)),0) -> 25576.024 | V45: =IF(U45>0,IF(U45<=T45,T45-U45,C45*(T45/U45-1)),T45-C45) -> 372640.12 | W45: =IF(U45>0,IF(U45<=T45,W44*(1-U45/T45),0),IF(AND(C45<0,V45>0),W44-C45,W44))/$B$34 -> 278747.83
B46: 2 | C46: =$B$38*MIN(12,MAX(0,$B$37-12*$B46))/12 -> 24000 | D46: =IF($B46>$B$40,F45,F45*$B$33*IF(F45>0,$B$32,1)) -> 325926.23 | E46: =IF(AND(C46>0,D46>0),C46/(1-$B$31*MAX(0,1-G45/D46)),0) -> 25828.593 | F46: =IF(E46>0,IF(E46<=D46,D46-E46,C46*(D46/E46-1)),D46-C46) -> 300097.64 | G46: =IF(E46>0,IF(E46<=D46,G45*(1-E46/D46),0),IF(AND(C46<0,F46>0),G45-C46,G45))/$B$34 -> 214099.92 | H46: =IF($B46>$B$40,J45,J45*$B$33*IF(J45>0,$B$32,1)) -> 382771.39 | I46: =IF(AND(C46>0,H46>0),C46/(1-$B$31*MAX(0,1-K45/H46)),0) -> 25828.593 | J46: =IF(I46>0,IF(I46<=H46,H46-I46,C46*(H46/I46-1)),H46-C46) -> 356942.8 | K46: =IF(I46>0,IF(I46<=H46,K45*(1-I46/H46),0),IF(AND(C46<0,J46>0),K45-C46,K45))/$B$34 -> 254655.21 | L46: =IF($B46>$B$40,N45,N45*$B$33*IF(N45>0,$B$32,1)) -> 383048.32 | M46: =IF(AND(C46>0,L46>0),C46/(1-$B$31*MAX(0,1-O45/L46)),0) -> 25828.593 | N46: =IF(M46>0,IF(M46<=L46,L46-M46,C46*(L46/M46-1)),L46-C46) -> 357219.72 | O46: =IF(M46>0,IF(M46<=L46,O45*(1-M46/L46),0),IF(AND(C46<0,N46>0),O45-C46,O45))/$B$34 -> 254852.78 | P46: =IF($B46>$B$40,R45,R45*$B$33*IF(R45>0,$B$32,1)) -> 383051.69 | Q46: =IF(AND(C46>0,P46>0),C46/(1-$B$31*MAX(0,1-S45/P46)),0) -> 25828.593 | R46: =IF(Q46>0,IF(Q46<=P46,P46-Q46,C46*(P46/Q46-1)),P46-C46) -> 357223.1 | S46: =IF(Q46>0,IF(Q46<=P46,S45*(1-Q46/P46),0),IF(AND(C46<0,R46>0),S45-C46,S45))/$B$34 -> 254855.18 | T46: =IF($B46>$B$40,V45,V45*$B$33*IF(V45>0,$B$32,1)) -> 383051.69 | U46: =IF(AND(C46>0,T46>0),C46/(1-$B$31*MAX(0,1-W45/T46)),0) -> 25828.593 | V46: =IF(U46>0,IF(U46<=T46,T46-U46,C46*(T46/U46-1)),T46-C46) -> 357223.1 | W46: =IF(U46>0,IF(U46<=T46,W45*(1-U46/T46),0),IF(AND(C46<0,V46>0),W45-C46,W45))/$B$34 -> 254855.18
B47: 3 | C47: =$B$38*MIN(12,MAX(0,$B$37-12*$B47))/12 -> 24000 | D47: =IF($B47>$B$40,F46,F46*$B$33*IF(F46>0,$B$32,1)) -> 308482.36 | E47: =IF(AND(C47>0,D47>0),C47/(1-$B$31*MAX(0,1-G46/D47)),0) -> 26074.172 | F47: =IF(E47>0,IF(E47<=D47,D47-E47,C47*(D47/E47-1)),D47-C47) -> 282408.19 | G47: =IF(E47>0,IF(E47<=D47,G46*(1-E47/D47),0),IF(AND(C47<0,F47>0),G46-C47,G46))/$B$34 -> 192160.13 | H47: =IF($B47>$B$40,J46,J46*$B$33*IF(J46>0,$B$32,1)) -> 366915.78 | I47: =IF(AND(C47>0,H47>0),C47/(1-$B$31*MAX(0,1-K46/H47)),0) -> 26074.172 | J47: =IF(I47>0,IF(I47<=H47,H47-I47,C47*(H47/I47-1)),H47-C47) -> 340841.61 | K47: =IF(I47>0,IF(I47<=H47,K46*(1-I47/H47),0),IF(AND(C47<0,J47>0),K46-C47,K46))/$B$34 -> 231920.22 | L47: =IF($B47>$B$40,N46,N46*$B$33*IF(N46>0,$B$32,1)) -> 367200.44 | M47: =IF(AND(C47>0,L47>0),C47/(1-$B$31*MAX(0,1-O46/L47)),0) -> 26074.172 | N47: =IF(M47>0,IF(M47<=L47,L47-M47,C47*(L47/M47-1)),L47-C47) -> 341126.27 | O47: =IF(M47>0,IF(M47<=L47,O46*(1-M47/L47),0),IF(AND(C47<0,N47>0),O46-C47,O46))/$B$34 -> 232113.91 | P47: =IF($B47>$B$40,R46,R46*$B$33*IF(R46>0,$B$32,1)) -> 367203.91 | Q47: =IF(AND(C47>0,P47>0),C47/(1-$B$31*MAX(0,1-S46/P47)),0) -> 26074.172 | R47: =IF(Q47>0,IF(Q47<=P47,P47-Q47,C47*(P47/Q47-1)),P47-C47) -> 341129.74 | S47: =IF(Q47>0,IF(Q47<=P47,S46*(1-Q47/P47),0),IF(AND(C47<0,R47>0),S46-C47,S46))/$B$34 -> 232116.27 | T47: =IF($B47>$B$40,V46,V46*$B$33*IF(V46>0,$B$32,1)) -> 367203.91 | U47: =IF(AND(C47>0,T47>0),C47/(1-$B$31*MAX(0,1-W46/T47)),0) -> 26074.172 | V47: =IF(U47>0,IF(U47<=T47,T47-U47,C47*(T47/U47-1)),T47-C47) -> 341129.74 | W47: =IF(U47>0,IF(U47<=T47,W46*(1-U47/T47),0),IF(AND(C47<0,V47>0),W46-C47,W46))/$B$34 -> 232116.27
B48: 4 | C48: =$B$38*MIN(12,MAX(0,$B$37-12*$B48))/12 -> 24000 | D48: =IF($B48>$B$40,F47,F47*$B$33*IF(F47>0,$B$32,1)) -> 290298.68 | E48: =IF(AND(C48>0,D48>0),C48/(1-$B$31*MAX(0,1-G47/D48)),0) -> 26312.782 | F48: =IF(E48>0,IF(E48<=D48,D48-E48,C48*(D48/E48-1)),D48-C48) -> 263985.9 | G48: =IF(E48>0,IF(E48<=D48,G47*(1-E48/D48),0),IF(AND(C48<0,F48>0),G47-C48,G47))/$B$34 -> 171316.34 | H48: =IF($B48>$B$40,J47,J47*$B$33*IF(J47>0,$B$32,1)) -> 350364.72 | I48: =IF(AND(C48>0,H48>0),C48/(1-$B$31*MAX(0,1-K47/H48)),0) -> 26312.782 | J48: =IF(I48>0,IF(I48<=H48,H48-I48,C48*(H48/I48-1)),H48-C48) -> 324051.94 | K48: =IF(I48>0,IF(I48<=H48,K47*(1-I48/H48),0),IF(AND(C48<0,J48>0),K47-C48,K47))/$B$34 -> 210296.81 | L48: =IF($B48>$B$40,N47,N47*$B$33*IF(N47>0,$B$32,1)) -> 350657.34 | M48: =IF(AND(C48>0,L48>0),C48/(1-$B$31*MAX(0,1-O47/L48)),0) -> 26312.782 | N48: =IF(M48>0,IF(M48<=L48,L48-M48,C48*(L48/M48-1)),L48-C48) -> 324344.56 | O48: =IF(M48>0,IF(M48<=L48,O47*(1-M48/L48),0),IF(AND(C48<0,N48>0),O47-C48,O47))/$B$34 -> 210486.71 | P48: =IF($B48>$B$40,R47,R47*$B$33*IF(R47>0,$B$32,1)) -> 350660.9 | Q48: =IF(AND(C48>0,P48>0),C48/(1-$B$31*MAX(0,1-S47/P48)),0) -> 26312.782 | R48: =IF(Q48>0,IF(Q48<=P48,P48-Q48,C48*(P48/Q48-1)),P48-C48) -> 324348.12 | S48: =IF(Q48>0,IF(Q48<=P48,S47*(1-Q48/P48),0),IF(AND(C48<0,R48>0),S47-C48,S47))/$B$34 -> 210489.02 | T48: =IF($B48>$B$40,V47,V47*$B$33*IF(V47>0,$B$32,1)) -> 350660.9 | U48: =IF(AND(C48>0,T48>0),C48/(1-$B$31*MAX(0,1-W47/T48)),0) -> 26312.782 | V48: =IF(U48>0,IF(U48<=T48,T48-U48,C48*(T48/U48-1)),T48-C48) -> 324348.12 | W48: =IF(U48>0,IF(U48<=T48,W47*(1-U48/T48),0),IF(AND(C48<0,V48>0),W47-C48,W47))/$B$34 -> 210489.02
B49: 5 | C49: =$B$38*MIN(12,MAX(0,$B$37-12*$B49))/12 -> 24000 | D49: =IF($B49>$B$40,F48,F48*$B$33*IF(F48>0,$B$32,1)) -> 271361.66 | E49: =IF(AND(C49>0,D49>0),C49/(1-$B$31*MAX(0,1-G48/D49)),0) -> 26544.459 | F49: =IF(E49>0,IF(E49<=D49,D49-E49,C49*(D49/E49-1)),D49-C49) -> 244817.2 | G49: =IF(E49>0,IF(E49<=D49,G48*(1-E49/D49),0),IF(AND(C49<0,F49>0),G48-C49,G48))/$B$34 -> 151527.71 | H49: =IF($B49>$B$40,J48,J48*$B$33*IF(J48>0,$B$32,1)) -> 333105.95 | I49: =IF(AND(C49>0,H49>0),C49/(1-$B$31*MAX(0,1-K48/H49)),0) -> 26544.459 | J49: =IF(I49>0,IF(I49<=H49,H49-I49,C49*(H49/I49-1)),H49-C49) -> 306561.49 | K49: =IF(I49>0,IF(I49<=H49,K48*(1-I49/H49),0),IF(AND(C49<0,J49>0),K48-C49,K48))/$B$34 -> 189743.86 | L49: =IF($B49>$B$40,N48,N48*$B$33*IF(N48>0,$B$32,1)) -> 333406.74 | M49: =IF(AND(C49>0,L49>0),C49/(1-$B$31*MAX(0,1-O48/L49)),0) -> 26544.459 | N49: =IF(M49>0,IF(M49<=L49,L49-M49,C49*(L49/M49-1)),L49-C49) -> 306862.28 | O49: =IF(M49>0,IF(M49<=L49,O48*(1-M49/L49),0),IF(AND(C49<0,N49>0),O48-C49,O48))/$B$34 -> 189930.03 | P49: =IF($B49>$B$40,R48,R48*$B$33*IF(R48>0,$B$32,1)) -> 333410.41 | Q49: =IF(AND(C49>0,P49>0),C49/(1-$B$31*MAX(0,1-S48/P49)),0) -> 26544.459 | R49: =IF(Q49>0,IF(Q49<=P49,P49-Q49,C49*(P49/Q49-1)),P49-C49) -> 306865.95 | S49: =IF(Q49>0,IF(Q49<=P49,S48*(1-Q49/P49),0),IF(AND(C49<0,R49>0),S48-C49,S48))/$B$34 -> 189932.3 | T49: =IF($B49>$B$40,V48,V48*$B$33*IF(V48>0,$B$32,1)) -> 333410.41 | U49: =IF(AND(C49>0,T49>0),C49/(1-$B$31*MAX(0,1-W48/T49)),0) -> 26544.459 | V49: =IF(U49>0,IF(U49<=T49,T49-U49,C49*(T49/U49-1)),T49-C49) -> 306865.95 | W49: =IF(U49>0,IF(U49<=T49,W48*(1-U49/T49),0),IF(AND(C49<0,V49>0),W48-C49,W48))/$B$34 -> 189932.3
B50: 6 | C50: =$B$38*MIN(12,MAX(0,$B$37-12*$B50))/12 -> 24000 | D50: =IF($B50>$B$40,F49,F49*$B$33*IF(F49>0,$B$32,1)) -> 251657.39 | E50: =IF(AND(C50>0,D50>0),C50/(1-$B$31*MAX(0,1-G49/D50)),0) -> 26769.254 | F50: =IF(E50>0,IF(E50<=D50,D50-E50,C50*(D50/E50-1)),D50-C50) -> 224888.14 | G50: =IF(E50>0,IF(E50<=D50,G49*(1-E50/D50),0),IF(AND(C50<0,F50>0),G49-C50,G49))/$B$34 -> 132754.34 | H50: =IF($B50>$B$40,J49,J49*$B$33*IF(J49>0,$B$32,1)) -> 315126.82 | I50: =IF(AND(C50>0,H50>0),C50/(1-$B$31*MAX(0,1-K49/H50)),0) -> 26769.254 | J50: =IF(I50>0,IF(I50<=H50,H50-I50,C50*(H50/I50-1)),H50-C50) -> 288357.57 | K50: =IF(I50>0,IF(I50<=H50,K49*(1-I50/H50),0),IF(AND(C50<0,J50>0),K49-C50,K49))/$B$34 -> 170221.16 | L50: =IF($B50>$B$40,N49,N49*$B$33*IF(N49>0,$B$32,1)) -> 315436.02 | M50: =IF(AND(C50>0,L50>0),C50/(1-$B$31*MAX(0,1-O49/L50)),0) -> 26769.254 | N50: =IF(M50>0,IF(M50<=L50,L50-M50,C50*(L50/M50-1)),L50-C50) -> 288666.76 | O50: =IF(M50>0,IF(M50<=L50,O49*(1-M50/L50),0),IF(AND(C50<0,N50>0),O49-C50,O49))/$B$34 -> 170403.68 | P50: =IF($B50>$B$40,R49,R49*$B$33*IF(R49>0,$B$32,1)) -> 315439.78 | Q50: =IF(AND(C50>0,P50>0),C50/(1-$B$31*MAX(0,1-S49/P50)),0) -> 26769.254 | R50: =IF(Q50>0,IF(Q50<=P50,P50-Q50,C50*(P50/Q50-1)),P50-C50) -> 288670.53 | S50: =IF(Q50>0,IF(Q50<=P50,S49*(1-Q50/P50),0),IF(AND(C50<0,R50>0),S49-C50,S49))/$B$34 -> 170405.9 | T50: =IF($B50>$B$40,V49,V49*$B$33*IF(V49>0,$B$32,1)) -> 315439.78 | U50: =IF(AND(C50>0,T50>0),C50/(1-$B$31*MAX(0,1-W49/T50)),0) -> 26769.254 | V50: =IF(U50>0,IF(U50<=T50,T50-U50,C50*(T50/U50-1)),T50-C50) -> 288670.53 | W50: =IF(U50>0,IF(U50<=T50,W49*(1-U50/T50),0),IF(AND(C50<0,V50>0),W49-C50,W49))/$B$34 -> 170405.9
B51: 7 | C51: =$B$38*MIN(12,MAX(0,$B$37-12*$B51))/12 -> 24000 | D51: =IF($B51>$B$40,F50,F50*$B$33*IF(F50>0,$B$32,1)) -> 231171.52 | E51: =IF(AND(C51>0,D51>0),C51/(1-$B$31*MAX(0,1-G50/D51)),0) -> 26987.227 | F51: =IF(E51>0,IF(E51<=D51,D51-E51,C51*(D51/E51-1)),D51-C51) -> 204184.29 | G51: =IF(E51>0,IF(E51<=D51,G50*(1-E51/D51),0),IF(AND(C51<0,F51>0),G50-C51,G50))/$B$34 -> 114957.3 | H51: =IF($B51>$B$40,J50,J50*$B$33*IF(J50>0,$B$32,1)) -> 296414.28 | I51: =IF(AND(C51>0,H51>0),C51/(1-$B$31*MAX(0,1-K50/H51)),0) -> 26987.227 | J51: =IF(I51>0,IF(I51<=H51,H51-I51,C51*(H51/I51-1)),H51-C51) -> 269427.05 | K51: =IF(I51>0,IF(I51<=H51,K50*(1-I51/H51),0),IF(AND(C51<0,J51>0),K50-C51,K50))/$B$34 -> 151689.48 | L51: =IF($B51>$B$40,N50,N50*$B$33*IF(N50>0,$B$32,1)) -> 296732.11 | M51: =IF(AND(C51>0,L51>0),C51/(1-$B$31*MAX(0,1-O50/L51)),0) -> 26987.227 | N51: =IF(M51>0,IF(M51<=L51,L51-M51,C51*(L51/M51-1)),L51-C51) -> 269744.88 | O51: =IF(M51>0,IF(M51<=L51,O50*(1-M51/L51),0),IF(AND(C51<0,N51>0),O50-C51,O50))/$B$34 -> 151868.42 | P51: =IF($B51>$B$40,R50,R50*$B$33*IF(R50>0,$B$32,1)) -> 296735.98 | Q51: =IF(AND(C51>0,P51>0),C51/(1-$B$31*MAX(0,1-S50/P51)),0) -> 26987.227 | R51: =IF(Q51>0,IF(Q51<=P51,P51-Q51,C51*(P51/Q51-1)),P51-C51) -> 269748.76 | S51: =IF(Q51>0,IF(Q51<=P51,S50*(1-Q51/P51),0),IF(AND(C51<0,R51>0),S50-C51,S50))/$B$34 -> 151870.6 | T51: =IF($B51>$B$40,V50,V50*$B$33*IF(V50>0,$B$32,1)) -> 296735.98 | U51: =IF(AND(C51>0,T51>0),C51/(1-$B$31*MAX(0,1-W50/T51)),0) -> 26987.227 | V51: =IF(U51>0,IF(U51<=T51,T51-U51,C51*(T51/U51-1)),T51-C51) -> 269748.76 | W51: =IF(U51>0,IF(U51<=T51,W50*(1-U51/T51),0),IF(AND(C51<0,V51>0),W50-C51,W50))/$B$34 -> 151870.6
B52: 8 | C52: =$B$38*MIN(12,MAX(0,$B$37-12*$B52))/12 -> 24000 | D52: =IF($B52>$B$40,F51,F51*$B$33*IF(F51>0,$B$32,1)) -> 209889.2 | E52: =IF(AND(C52>0,D52>0),C52/(1-$B$31*MAX(0,1-G51/D52)),0) -> 27198.45 | F52: =IF(E52>0,IF(E52<=D52,D52-E52,C52*(D52/E52-1)),D52-C52) -> 182690.75 | G52: =IF(E52>0,IF(E52<=D52,G51*(1-E52/D52),0),IF(AND(C52<0,F52>0),G51-C52,G51))/$B$34 -> 98098.613 | H52: =IF($B52>$B$40,J51,J51*$B$33*IF(J51>0,$B$32,1)) -> 276954.84 | I52: =IF(AND(C52>0,H52>0),C52/(1-$B$31*MAX(0,1-K51/H52)),0) -> 27198.45 | J52: =IF(I52>0,IF(I52<=H52,H52-I52,C52*(H52/I52-1)),H52-C52) -> 249756.39 | K52: =IF(I52>0,IF(I52<=H52,K51*(1-I52/H52),0),IF(AND(C52<0,J52>0),K51-C52,K51))/$B$34 -> 134110.54 | L52: =IF($B52>$B$40,N51,N51*$B$33*IF(N51>0,$B$32,1)) -> 277281.56 | M52: =IF(AND(C52>0,L52>0),C52/(1-$B$31*MAX(0,1-O51/L52)),0) -> 27198.45 | N52: =IF(M52>0,IF(M52<=L52,L52-M52,C52*(L52/M52-1)),L52-C52) -> 250083.11 | O52: =IF(M52>0,IF(M52<=L52,O51*(1-M52/L52),0),IF(AND(C52<0,N52>0),O51-C52,O51))/$B$34 -> 134285.98 | P52: =IF($B52>$B$40,R51,R51*$B$33*IF(R51>0,$B$32,1)) -> 277285.54 | Q52: =IF(AND(C52>0,P52>0),C52/(1-$B$31*MAX(0,1-S51/P52)),0) -> 27198.45 | R52: =IF(Q52>0,IF(Q52<=P52,P52-Q52,C52*(P52/Q52-1)),P52-C52) -> 250087.09 | S52: =IF(Q52>0,IF(Q52<=P52,S51*(1-Q52/P52),0),IF(AND(C52<0,R52>0),S51-C52,S51))/$B$34 -> 134288.12 | T52: =IF($B52>$B$40,V51,V51*$B$33*IF(V51>0,$B$32,1)) -> 277285.54 | U52: =IF(AND(C52>0,T52>0),C52/(1-$B$31*MAX(0,1-W51/T52)),0) -> 27198.45 | V52: =IF(U52>0,IF(U52<=T52,T52-U52,C52*(T52/U52-1)),T52-C52) -> 250087.09 | W52: =IF(U52>0,IF(U52<=T52,W51*(1-U52/T52),0),IF(AND(C52<0,V52>0),W51-C52,W51))/$B$34 -> 134288.12
B53: 9 | C53: =$B$38*MIN(12,MAX(0,$B$37-12*$B53))/12 -> 24000 | D53: =IF($B53>$B$40,F52,F52*$B$33*IF(F52>0,$B$32,1)) -> 187795.13 | E53: =IF(AND(C53>0,D53>0),C53/(1-$B$31*MAX(0,1-G52/D53)),0) -> 27403.007 | F53: =IF(E53>0,IF(E53<=D53,D53-E53,C53*(D53/E53-1)),D53-C53) -> 160392.12 | G53: =IF(E53>0,IF(E53<=D53,G52*(1-E53/D53),0),IF(AND(C53<0,F53>0),G52-C53,G52))/$B$34 -> 82141.268 | H53: =IF($B53>$B$40,J52,J52*$B$33*IF(J52>0,$B$32,1)) -> 256734.59 | I53: =IF(AND(C53>0,H53>0),C53/(1-$B$31*MAX(0,1-K52/H53)),0) -> 27403.007 | J53: =IF(I53>0,IF(I53<=H53,H53-I53,C53*(H53/I53-1)),H53-C53) -> 229331.58 | K53: =IF(I53>0,IF(I53<=H53,K52*(1-I53/H53),0),IF(AND(C53<0,J53>0),K52-C53,K52))/$B$34 -> 117447.08 | L53: =IF($B53>$B$40,N52,N52*$B$33*IF(N52>0,$B$32,1)) -> 257070.43 | M53: =IF(AND(C53>0,L53>0),C53/(1-$B$31*MAX(0,1-O52/L53)),0) -> 27403.007 | N53: =IF(M53>0,IF(M53<=L53,L53-M53,C53*(L53/M53-1)),L53-C53) -> 229667.42 | O53: =IF(M53>0,IF(M53<=L53,O52*(1-M53/L53),0),IF(AND(C53<0,N53>0),O52-C53,O52))/$B$34 -> 117619.08 | P53: =IF($B53>$B$40,R52,R52*$B$33*IF(R52>0,$B$32,1)) -> 257074.52 | Q53: =IF(AND(C53>0,P53>0),C53/(1-$B$31*MAX(0,1-S52/P53)),0) -> 27403.007 | R53: =IF(Q53>0,IF(Q53<=P53,P53-Q53,C53*(P53/Q53-1)),P53-C53) -> 229671.51 | S53: =IF(Q53>0,IF(Q53<=P53,S52*(1-Q53/P53),0),IF(AND(C53<0,R53>0),S52-C53,S52))/$B$34 -> 117621.17 | T53: =IF($B53>$B$40,V52,V52*$B$33*IF(V52>0,$B$32,1)) -> 257074.52 | U53: =IF(AND(C53>0,T53>0),C53/(1-$B$31*MAX(0,1-W52/T53)),0) -> 27403.007 | V53: =IF(U53>0,IF(U53<=T53,T53-U53,C53*(T53/U53-1)),T53-C53) -> 229671.51 | W53: =IF(U53>0,IF(U53<=T53,W52*(1-U53/T53),0),IF(AND(C53<0,V53>0),W52-C53,W52))/$B$34 -> 117621.17
B54: 10 | C54: =$B$38*MIN(12,MAX(0,$B$37-12*$B54))/12 -> 24000 | D54: =IF($B54>$B$40,F53,F53*$B$33*IF(F53>0,$B$32,1)) -> 164873.48 | E54: =IF(AND(C54>0,D54>0),C54/(1-$B$31*MAX(0,1-G53/D54)),0) -> 27600.989 | F54: =IF(E54>0,IF(E54<=D54,D54-E54,C54*(D54/E54-1)),D54-C54) -> 137272.49 | G54: =IF(E54>0,IF(E54<=D54,G53*(1-E54/D54),0),IF(AND(C54<0,F54>0),G53-C54,G53))/$B$34 -> 67049.252 | H54: =IF($B54>$B$40,J53,J53*$B$33*IF(J53>0,$B$32,1)) -> 235739.1 | I54: =IF(AND(C54>0,H54>0),C54/(1-$B$31*MAX(0,1-K53/H54)),0) -> 27600.989 | J54: =IF(I54>0,IF(I54<=H54,H54-I54,C54*(H54/I54-1)),H54-C54) -> 208138.12 | K54: =IF(I54>0,IF(I54<=H54,K53*(1-I54/H54),0),IF(AND(C54<0,J54>0),K53-C54,K53))/$B$34 -> 101662.8 | L54: =IF($B54>$B$40,N53,N53*$B$33*IF(N53>0,$B$32,1)) -> 236084.33 | M54: =IF(AND(C54>0,L54>0),C54/(1-$B$31*MAX(0,1-O53/L54)),0) -> 27600.989 | N54: =IF(M54>0,IF(M54<=L54,L54-M54,C54*(L54/M54-1)),L54-C54) -> 208483.34 | O54: =IF(M54>0,IF(M54<=L54,O53*(1-M54/L54),0),IF(AND(C54<0,N54>0),O53-C54,O53))/$B$34 -> 101831.42 | P54: =IF($B54>$B$40,R53,R53*$B$33*IF(R53>0,$B$32,1)) -> 236088.54 | Q54: =IF(AND(C54>0,P54>0),C54/(1-$B$31*MAX(0,1-S53/P54)),0) -> 27600.989 | R54: =IF(Q54>0,IF(Q54<=P54,P54-Q54,C54*(P54/Q54-1)),P54-C54) -> 208487.55 | S54: =IF(Q54>0,IF(Q54<=P54,S53*(1-Q54/P54),0),IF(AND(C54<0,R54>0),S53-C54,S53))/$B$34 -> 101833.47 | T54: =IF($B54>$B$40,V53,V53*$B$33*IF(V53>0,$B$32,1)) -> 236088.54 | U54: =IF(AND(C54>0,T54>0),C54/(1-$B$31*MAX(0,1-W53/T54)),0) -> 27600.989 | V54: =IF(U54>0,IF(U54<=T54,T54-U54,C54*(T54/U54-1)),T54-C54) -> 208487.55 | W54: =IF(U54>0,IF(U54<=T54,W53*(1-U54/T54),0),IF(AND(C54<0,V54>0),W53-C54,W53))/$B$34 -> 101833.47
B55: 11 | C55: =$B$38*MIN(12,MAX(0,$B$37-12*$B55))/12 -> 24000 | D55: =IF($B55>$B$40,F54,F54*$B$33*IF(F54>0,$B$32,1)) -> 141107.88 | E55: =IF(AND(C55>0,D55>0),C55/(1-$B$31*MAX(0,1-G54/D55)),0) -> 27792.498 | F55: =IF(E55>0,IF(E55<=D55,D55-E55,C55*(D55/E55-1)),D55-C55) -> 113315.38 | G55: =IF(E55>0,IF(E55<=D55,G54*(1-E55/D55),0),IF(AND(C55<0,F55>0),G54-C55,G54))/$B$34 -> 52787.534 | H55: =IF($B55>$B$40,J54,J54*$B$33*IF(J54>0,$B$32,1)) -> 213953.49 | I55: =IF(AND(C55>0,H55>0),C55/(1-$B$31*MAX(0,1-K54/H55)),0) -> 27792.498 | J55: =IF(I55>0,IF(I55<=H55,H55-I55,C55*(H55/I55-1)),H55-C55) -> 186161 | K55: =IF(I55>0,IF(I55<=H55,K54*(1-I55/H55),0),IF(AND(C55<0,J55>0),K54-C55,K54))/$B$34 -> 86722.381 | L55: =IF($B55>$B$40,N54,N54*$B$33*IF(N54>0,$B$32,1)) -> 214308.37 | M55: =IF(AND(C55>0,L55>0),C55/(1-$B$31*MAX(0,1-O54/L55)),0) -> 27792.498 | N55: =IF(M55>0,IF(M55<=L55,L55-M55,C55*(L55/M55-1)),L55-C55) -> 186515.87 | O55: =IF(M55>0,IF(M55<=L55,O54*(1-M55/L55),0),IF(AND(C55<0,N55>0),O54-C55,O54))/$B$34 -> 86887.697 | P55: =IF($B55>$B$40,R54,R54*$B$33*IF(R54>0,$B$32,1)) -> 214312.69 | Q55: =IF(AND(C55>0,P55>0),C55/(1-$B$31*MAX(0,1-S54/P55)),0) -> 27792.498 | R55: =IF(Q55>0,IF(Q55<=P55,P55-Q55,C55*(P55/Q55-1)),P55-C55) -> 186520.19 | S55: =IF(Q55>0,IF(Q55<=P55,S54*(1-Q55/P55),0),IF(AND(C55<0,R55>0),S54-C55,S54))/$B$34 -> 86889.711 | T55: =IF($B55>$B$40,V54,V54*$B$33*IF(V54>0,$B$32,1)) -> 214312.69 | U55: =IF(AND(C55>0,T55>0),C55/(1-$B$31*MAX(0,1-W54/T55)),0) -> 27792.498 | V55: =IF(U55>0,IF(U55<=T55,T55-U55,C55*(T55/U55-1)),T55-C55) -> 186520.19 | W55: =IF(U55>0,IF(U55<=T55,W54*(1-U55/T55),0),IF(AND(C55<0,V55>0),W54-C55,W54))/$B$34 -> 86889.711
B56: 12 | C56: =$B$38*MIN(12,MAX(0,$B$37-12*$B56))/12 -> 24000 | D56: =IF($B56>$B$40,F55,F55*$B$33*IF(F55>0,$B$32,1)) -> 116481.41 | E56: =IF(AND(C56>0,D56>0),C56/(1-$B$31*MAX(0,1-G55/D56)),0) -> 27977.64 | F56: =IF(E56>0,IF(E56<=D56,D56-E56,C56*(D56/E56-1)),D56-C56) -> 88503.774 | G56: =IF(E56>0,IF(E56<=D56,G55*(1-E56/D56),0),IF(AND(C56<0,F56>0),G55-C56,G55))/$B$34 -> 39322.068 | H56: =IF($B56>$B$40,J55,J55*$B$33*IF(J55>0,$B$32,1)) -> 191362.33 | I56: =IF(AND(C56>0,H56>0),C56/(1-$B$31*MAX(0,1-K55/H56)),0) -> 27977.64 | J56: =IF(I56>0,IF(I56<=H56,H56-I56,C56*(H56/I56-1)),H56-C56) -> 163384.69 | K56: =IF(I56>0,IF(I56<=H56,K55*(1-I56/H56),0),IF(AND(C56<0,J56>0),K55-C56,K55))/$B$34 -> 72591.527 | L56: =IF($B56>$B$40,N55,N55*$B$33*IF(N55>0,$B$32,1)) -> 191727.12 | M56: =IF(AND(C56>0,L56>0),C56/(1-$B$31*MAX(0,1-O55/L56)),0) -> 27977.64 | N56: =IF(M56>0,IF(M56<=L56,L56-M56,C56*(L56/M56-1)),L56-C56) -> 163749.48 | O56: =IF(M56>0,IF(M56<=L56,O55*(1-M56/L56),0),IF(AND(C56<0,N56>0),O55-C56,O55))/$B$34 -> 72753.601 | P56: =IF($B56>$B$40,R55,R55*$B$33*IF(R55>0,$B$32,1)) -> 191731.57 | Q56: =IF(AND(C56>0,P56>0),C56/(1-$B$31*MAX(0,1-S55/P56)),0) -> 27977.64 | R56: =IF(Q56>0,IF(Q56<=P56,P56-Q56,C56*(P56/Q56-1)),P56-C56) -> 163753.93 | S56: =IF(Q56>0,IF(Q56<=P56,S55*(1-Q56/P56),0),IF(AND(C56<0,R56>0),S55-C56,S55))/$B$34 -> 72755.576 | T56: =IF($B56>$B$40,V55,V55*$B$33*IF(V55>0,$B$32,1)) -> 191731.57 | U56: =IF(AND(C56>0,T56>0),C56/(1-$B$31*MAX(0,1-W55/T56)),0) -> 27977.64 | V56: =IF(U56>0,IF(U56<=T56,T56-U56,C56*(T56/U56-1)),T56-C56) -> 163753.93 | W56: =IF(U56>0,IF(U56<=T56,W55*(1-U56/T56),0),IF(AND(C56<0,V56>0),W55-C56,W55))/$B$34 -> 72755.576
... B79: 35 | C79: =$B$38*MIN(12,MAX(0,$B$37-12*$B79))/12 -> 0 | D79: =IF($B79>$B$40,F78,F78*$B$33*IF(F78>0,$B$32,1)) -> -78448.803 | E79: =IF(AND(C79>0,D79>0),C79/(1-$B$31*MAX(0,1-G78/D79)),0) -> 0 | F79: =IF(E79>0,IF(E79<=D79,D79-E79,C79*(D79/E79-1)),D79-C79) -> -78448.803 | G79: =IF(E79>0,IF(E79<=D79,G78*(1-E79/D79),0),IF(AND(C79<0,F79>0),G78-C79,G78))/$B$34 -> 0 | H79: =IF($B79>$B$40,J78,J78*$B$33*IF(J78>0,$B$32,1)) -> -380.31471 | I79: =IF(AND(C79>0,H79>0),C79/(1-$B$31*MAX(0,1-K78/H79)),0) -> 0 | J79: =IF(I79>0,IF(I79<=H79,H79-I79,C79*(H79/I79-1)),H79-C79) -> -380.31471 | K79: =IF(I79>0,IF(I79<=H79,K78*(1-I79/H79),0),IF(AND(C79<0,J79>0),K78-C79,K78))/$B$34 -> 0 | L79: =IF($B79>$B$40,N78,N78*$B$33*IF(N78>0,$B$32,1)) -> -4.5781937 | M79: =IF(AND(C79>0,L79>0),C79/(1-$B$31*MAX(0,1-O78/L79)),0) -> 0 | N79: =IF(M79>0,IF(M79<=L79,L79-M79,C79*(L79/M79-1)),L79-C79) -> -4.5781937 | O79: =IF(M79>0,IF(M79<=L79,O78*(1-M79/L79),0),IF(AND(C79<0,N79>0),O78-C79,O78))/$B$34 -> 0 | P79: =IF($B79>$B$40,R78,R78*$B$33*IF(R78>0,$B$32,1)) -> -2.1955771e-11 | Q79: =IF(AND(C79>0,P79>0),C79/(1-$B$31*MAX(0,1-S78/P79)),0) -> 0 | R79: =IF(Q79>0,IF(Q79<=P79,P79-Q79,C79*(P79/Q79-1)),P79-C79) -> -2.1955771e-11 | S79: =IF(Q79>0,IF(Q79<=P79,S78*(1-Q79/P79),0),IF(AND(C79<0,R79>0),S78-C79,S78))/$B$34 -> 0 | T79: =IF($B79>$B$40,V78,V78*$B$33*IF(V78>0,$B$32,1)) -> -2.1955771e-11 | U79: =IF(AND(C79>0,T79>0),C79/(1-$B$31*MAX(0,1-W78/T79)),0) -> 0 | V79: =IF(U79>0,IF(U79<=T79,T79-U79,C79*(T79/U79-1)),T79-C79) -> -2.1955771e-11 | W79: =IF(U79>0,IF(U79<=T79,W78*(1-U79/T79),0),IF(AND(C79<0,V79>0),W78-C79,W78))/$B$34 -> 0
A81: Ricerca 2 — capitale del ponte con un mese in più | B81: Capitale necessario: | C81: =$X$86 -> 414145.7
A82: Mesi di ponte + 1 (un mese di requisito in più) | B82: ='1 - Il tuo traguardo'!$B$49-'1 - Il tuo traguardo'!$B$47+1 -> 233
A83: Spesa annua | B83: ='2 - Il costo del ponte'!$B$5 -> 24000
A84: Plusvalenza latente allo stop | B84: ='2 - Il costo del ponte'!$B$8 -> 0.2
A85: Numero di prelievi annui | B85: =ROUNDUP($B$82/12,0) -> 20
A86: Capitale provato (secante: 2 inneschi + 4 correzioni) | D86: =IF(SUMPRODUCT($C$89:$C$124,1/$B$33^$B$89:$B$124)<=0,1000,SUMPRODUCT($C$89:$C$124,1/$B$33^$B$89:$B$124)) -> 359787.17 | H86: =1.15*$D$86 -> 413755.25 | L86: =IF($H$87=$D$87,$H$86,$H$86-$H$87*($H$86-$D$86)/($H$87-$D$87)) -> 414141.19 | P86: =IF($L$87=$H$87,$L$86,$L$86-$L$87*($L$86-$H$86)/($L$87-$H$87)) -> 414145.7 | T86: =IF($P$87=$L$87,$P$86,$P$86-$P$87*($P$86-$L$86)/($P$87-$L$87)) -> 414145.7 | X86: =IF($T$87=$P$87,$T$86,$T$86-$T$87*($T$86-$P$86)/($T$87-$P$87)) -> 414145.7
A87: Minimo del percorso con quel capitale (euro dello stop) | D87: =MIN($F$89:$F$124) -> -78837.953 | H87: =MIN($J$89:$J$124) -> -559.79176 | L87: =MIN($N$89:$N$124) -> -6.4659963 | P87: =MIN($R$89:$R$124) -> -9.3769437e-11 | T87: =MIN($V$89:$V$124) -> -8.9195318e-11
B88: k (anni dallo stop) | C88: Fabbisogno (euro dello stop) | D88: Prova 1: Patrimonio prima del prelievo | E88: Prova 1: Prelievo lordo | F88: Prova 1: Patrimonio dopo il prelievo | G88: Prova 1: Base di costo (all'anno dopo) | H88: Prova 2: Patrimonio prima del prelievo | I88: Prova 2: Prelievo lordo | J88: Prova 2: Patrimonio dopo il prelievo | K88: Prova 2: Base di costo (all'anno dopo) | L88: Prova 3: Patrimonio prima del prelievo | M88: Prova 3: Prelievo lordo | N88: Prova 3: Patrimonio dopo il prelievo | O88: Prova 3: Base di costo (all'anno dopo) | P88: Prova 4: Patrimonio prima del prelievo | Q88: Prova 4: Prelievo lordo | R88: Prova 4: Patrimonio dopo il prelievo | S88: Prova 4: Base di costo (all'anno dopo) | T88: Prova 5: Patrimonio prima del prelievo | U88: Prova 5: Prelievo lordo | V88: Prova 5: Patrimonio dopo il prelievo | W88: Prova 5: Base di costo (all'anno dopo) | X88: Capitale necessario
B89: 0 | C89: =$B$83*MIN(12,MAX(0,$B$82-12*$B89))/12 -> 24000 | D89: =$D$86 -> 359787.17 | E89: =IF(AND(C89>0,D89>0),C89/(1-$B$31*MAX(0,1-$D$86*(1-$B$84)/D89)),0) -> 25316.456 | F89: =IF(E89>0,IF(E89<=D89,D89-E89,C89*(D89/E89-1)),D89-C89) -> 334470.72 | G89: =IF(E89>0,IF(E89<=D89,$D$86*(1-$B$84)*(1-E89/D89),0),IF(AND(C89<0,F89>0),$D$86*(1-$B$84)-C89,$D$86*(1-$B$84)))/$B$34 -> 262329.98 | H89: =$H$86 -> 413755.25 | I89: =IF(AND(C89>0,H89>0),C89/(1-$B$31*MAX(0,1-$H$86*(1-$B$84)/H89)),0) -> 25316.456 | J89: =IF(I89>0,IF(I89<=H89,H89-I89,C89*(H89/I89-1)),H89-C89) -> 388438.79 | K89: =IF(I89>0,IF(I89<=H89,$H$86*(1-$B$84)*(1-I89/H89),0),IF(AND(C89<0,J89>0),$H$86*(1-$B$84)-C89,$H$86*(1-$B$84)))/$B$34 -> 304657.88 | L89: =$L$86 -> 414141.19 | M89: =IF(AND(C89>0,L89>0),C89/(1-$B$31*MAX(0,1-$L$86*(1-$B$84)/L89)),0) -> 25316.456 | N89: =IF(M89>0,IF(M89<=L89,L89-M89,C89*(L89/M89-1)),L89-C89) -> 388824.74 | O89: =IF(M89>0,IF(M89<=L89,$L$86*(1-$B$84)*(1-M89/L89),0),IF(AND(C89<0,N89>0),$L$86*(1-$B$84)-C89,$L$86*(1-$B$84)))/$B$34 -> 304960.58 | P89: =$P$86 -> 414145.7 | Q89: =IF(AND(C89>0,P89>0),C89/(1-$B$31*MAX(0,1-$P$86*(1-$B$84)/P89)),0) -> 25316.456 | R89: =IF(Q89>0,IF(Q89<=P89,P89-Q89,C89*(P89/Q89-1)),P89-C89) -> 388829.25 | S89: =IF(Q89>0,IF(Q89<=P89,$P$86*(1-$B$84)*(1-Q89/P89),0),IF(AND(C89<0,R89>0),$P$86*(1-$B$84)-C89,$P$86*(1-$B$84)))/$B$34 -> 304964.12 | T89: =$T$86 -> 414145.7 | U89: =IF(AND(C89>0,T89>0),C89/(1-$B$31*MAX(0,1-$T$86*(1-$B$84)/T89)),0) -> 25316.456 | V89: =IF(U89>0,IF(U89<=T89,T89-U89,C89*(T89/U89-1)),T89-C89) -> 388829.25 | W89: =IF(U89>0,IF(U89<=T89,$T$86*(1-$B$84)*(1-U89/T89),0),IF(AND(C89<0,V89>0),$T$86*(1-$B$84)-C89,$T$86*(1-$B$84)))/$B$34 -> 304964.12
B90: 1 | C90: =$B$83*MIN(12,MAX(0,$B$82-12*$B90))/12 -> 24000 | D90: =IF($B90>$B$85,F89,F89*$B$33*IF(F89>0,$B$32,1)) -> 343815.83 | E90: =IF(AND(C90>0,D90>0),C90/(1-$B$31*MAX(0,1-G89/D90)),0) -> 25576.024 | F90: =IF(E90>0,IF(E90<=D90,D90-E90,C90*(D90/E90-1)),D90-C90) -> 318239.81 | G90: =IF(E90>0,IF(E90<=D90,G89*(1-E90/D90),0),IF(AND(C90<0,F90>0),G89-C90,G89))/$B$34 -> 238054.49 | H90: =IF($B90>$B$85,J89,J89*$B$33*IF(J89>0,$B$32,1)) -> 399291.77 | I90: =IF(AND(C90>0,H90>0),C90/(1-$B$31*MAX(0,1-K89/H90)),0) -> 25576.024 | J90: =IF(I90>0,IF(I90<=H90,H90-I90,C90*(H90/I90-1)),H90-C90) -> 373715.75 | K90: =IF(I90>0,IF(I90<=H90,K89*(1-I90/H90),0),IF(AND(C90<0,J90>0),K89-C90,K89))/$B$34 -> 279552.44 | L90: =IF($B90>$B$85,N89,N89*$B$33*IF(N89>0,$B$32,1)) -> 399688.5 | M90: =IF(AND(C90>0,L90>0),C90/(1-$B$31*MAX(0,1-O89/L90)),0) -> 25576.024 | N90: =IF(M90>0,IF(M90<=L90,L90-M90,C90*(L90/M90-1)),L90-C90) -> 374112.48 | O90: =IF(M90>0,IF(M90<=L90,O89*(1-M90/L90),0),IF(AND(C90<0,N90>0),O89-C90,O89))/$B$34 -> 279849.2 | P90: =IF($B90>$B$85,R89,R89*$B$33*IF(R89>0,$B$32,1)) -> 399693.14 | Q90: =IF(AND(C90>0,P90>0),C90/(1-$B$31*MAX(0,1-S89/P90)),0) -> 25576.024 | R90: =IF(Q90>0,IF(Q90<=P90,P90-Q90,C90*(P90/Q90-1)),P90-C90) -> 374117.11 | S90: =IF(Q90>0,IF(Q90<=P90,S89*(1-Q90/P90),0),IF(AND(C90<0,R90>0),S89-C90,S89))/$B$34 -> 279852.67 | T90: =IF($B90>$B$85,V89,V89*$B$33*IF(V89>0,$B$32,1)) -> 399693.14 | U90: =IF(AND(C90>0,T90>0),C90/(1-$B$31*MAX(0,1-W89/T90)),0) -> 25576.024 | V90: =IF(U90>0,IF(U90<=T90,T90-U90,C90*(T90/U90-1)),T90-C90) -> 374117.11 | W90: =IF(U90>0,IF(U90<=T90,W89*(1-U90/T90),0),IF(AND(C90<0,V90>0),W89-C90,W89))/$B$34 -> 279852.67
B91: 2 | C91: =$B$83*MIN(12,MAX(0,$B$82-12*$B91))/12 -> 24000 | D91: =IF($B91>$B$85,F90,F90*$B$33*IF(F90>0,$B$32,1)) -> 327131.43 | E91: =IF(AND(C91>0,D91>0),C91/(1-$B$31*MAX(0,1-G90/D91)),0) -> 25828.593 | F91: =IF(E91>0,IF(E91<=D91,D91-E91,C91*(D91/E91-1)),D91-C91) -> 301302.83 | G91: =IF(E91>0,IF(E91<=D91,G90*(1-E91/D91),0),IF(AND(C91<0,F91>0),G90-C91,G90))/$B$34 -> 214959.75 | H91: =IF($B91>$B$85,J90,J90*$B$33*IF(J90>0,$B$32,1)) -> 384157.37 | I91: =IF(AND(C91>0,H91>0),C91/(1-$B$31*MAX(0,1-K90/H91)),0) -> 25828.593 | J91: =IF(I91>0,IF(I91<=H91,H91-I91,C91*(H91/I91-1)),H91-C91) -> 358328.78 | K91: =IF(I91>0,IF(I91<=H91,K90*(1-I91/H91),0),IF(AND(C91<0,J91>0),K90-C91,K90))/$B$34 -> 255644.01 | L91: =IF($B91>$B$85,N90,N90*$B$33*IF(N90>0,$B$32,1)) -> 384565.18 | M91: =IF(AND(C91>0,L91>0),C91/(1-$B$31*MAX(0,1-O90/L91)),0) -> 25828.593 | N91: =IF(M91>0,IF(M91<=L91,L91-M91,C91*(L91/M91-1)),L91-C91) -> 358736.59 | O91: =IF(M91>0,IF(M91<=L91,O90*(1-M91/L91),0),IF(AND(C91<0,N91>0),O90-C91,O90))/$B$34 -> 255934.96 | P91: =IF($B91>$B$85,R90,R90*$B$33*IF(R90>0,$B$32,1)) -> 384569.94 | Q91: =IF(AND(C91>0,P91>0),C91/(1-$B$31*MAX(0,1-S90/P91)),0) -> 25828.593 | R91: =IF(Q91>0,IF(Q91<=P91,P91-Q91,C91*(P91/Q91-1)),P91-C91) -> 358741.35 | S91: =IF(Q91>0,IF(Q91<=P91,S90*(1-Q91/P91),0),IF(AND(C91<0,R91>0),S90-C91,S90))/$B$34 -> 255938.36 | T91: =IF($B91>$B$85,V90,V90*$B$33*IF(V90>0,$B$32,1)) -> 384569.94 | U91: =IF(AND(C91>0,T91>0),C91/(1-$B$31*MAX(0,1-W90/T91)),0) -> 25828.593 | V91: =IF(U91>0,IF(U91<=T91,T91-U91,C91*(T91/U91-1)),T91-C91) -> 358741.35 | W91: =IF(U91>0,IF(U91<=T91,W90*(1-U91/T91),0),IF(AND(C91<0,V91>0),W90-C91,W90))/$B$34 -> 255938.36
B92: 3 | C92: =$B$83*MIN(12,MAX(0,$B$82-12*$B92))/12 -> 24000 | D92: =IF($B92>$B$85,F91,F91*$B$33*IF(F91>0,$B$32,1)) -> 309721.23 | E92: =IF(AND(C92>0,D92>0),C92/(1-$B$31*MAX(0,1-G91/D92)),0) -> 26074.172 | F92: =IF(E92>0,IF(E92<=D92,D92-E92,C92*(D92/E92-1)),D92-C92) -> 283647.06 | G92: =IF(E92>0,IF(E92<=D92,G91*(1-E92/D92),0),IF(AND(C92<0,F92>0),G91-C92,G91))/$B$34 -> 193003.1 | H92: =IF($B92>$B$85,J91,J91*$B$33*IF(J91>0,$B$32,1)) -> 368340.48 | I92: =IF(AND(C92>0,H92>0),C92/(1-$B$31*MAX(0,1-K91/H92)),0) -> 26074.172 | J92: =IF(I92>0,IF(I92<=H92,H92-I92,C92*(H92/I92-1)),H92-C92) -> 342266.31 | K92: =IF(I92>0,IF(I92<=H92,K91*(1-I92/H92),0),IF(AND(C92<0,J92>0),K91-C92,K91))/$B$34 -> 232889.63 | L92: =IF($B92>$B$85,N91,N91*$B$33*IF(N91>0,$B$32,1)) -> 368759.69 | M92: =IF(AND(C92>0,L92>0),C92/(1-$B$31*MAX(0,1-O91/L92)),0) -> 26074.172 | N92: =IF(M92>0,IF(M92<=L92,L92-M92,C92*(L92/M92-1)),L92-C92) -> 342685.51 | O92: =IF(M92>0,IF(M92<=L92,O91*(1-M92/L92),0),IF(AND(C92<0,N92>0),O91-C92,O91))/$B$34 -> 233174.87 | P92: =IF($B92>$B$85,R91,R91*$B$33*IF(R91>0,$B$32,1)) -> 368764.59 | Q92: =IF(AND(C92>0,P92>0),C92/(1-$B$31*MAX(0,1-S91/P92)),0) -> 26074.172 | R92: =IF(Q92>0,IF(Q92<=P92,P92-Q92,C92*(P92/Q92-1)),P92-C92) -> 342690.41 | S92: =IF(Q92>0,IF(Q92<=P92,S91*(1-Q92/P92),0),IF(AND(C92<0,R92>0),S91-C92,S91))/$B$34 -> 233178.21 | T92: =IF($B92>$B$85,V91,V91*$B$33*IF(V91>0,$B$32,1)) -> 368764.59 | U92: =IF(AND(C92>0,T92>0),C92/(1-$B$31*MAX(0,1-W91/T92)),0) -> 26074.172 | V92: =IF(U92>0,IF(U92<=T92,T92-U92,C92*(T92/U92-1)),T92-C92) -> 342690.41 | W92: =IF(U92>0,IF(U92<=T92,W91*(1-U92/T92),0),IF(AND(C92<0,V92>0),W91-C92,W91))/$B$34 -> 233178.21
B93: 4 | C93: =$B$83*MIN(12,MAX(0,$B$82-12*$B93))/12 -> 24000 | D93: =IF($B93>$B$85,F92,F92*$B$33*IF(F92>0,$B$32,1)) -> 291572.16 | E93: =IF(AND(C93>0,D93>0),C93/(1-$B$31*MAX(0,1-G92/D93)),0) -> 26312.782 | F93: =IF(E93>0,IF(E93<=D93,D93-E93,C93*(D93/E93-1)),D93-C93) -> 265259.38 | G93: =IF(E93>0,IF(E93<=D93,G92*(1-E93/D93),0),IF(AND(C93<0,F93>0),G92-C93,G92))/$B$34 -> 172142.78 | H93: =IF($B93>$B$85,J92,J92*$B$33*IF(J92>0,$B$32,1)) -> 351829.23 | I93: =IF(AND(C93>0,H93>0),C93/(1-$B$31*MAX(0,1-K92/H93)),0) -> 26312.782 | J93: =IF(I93>0,IF(I93<=H93,H93-I93,C93*(H93/I93-1)),H93-C93) -> 325516.45 | K93: =IF(I93>0,IF(I93<=H93,K92*(1-I93/H93),0),IF(AND(C93<0,J93>0),K92-C93,K92))/$B$34 -> 211247.22 | L93: =IF($B93>$B$85,N92,N92*$B$33*IF(N92>0,$B$32,1)) -> 352260.15 | M93: =IF(AND(C93>0,L93>0),C93/(1-$B$31*MAX(0,1-O92/L93)),0) -> 26312.782 | N93: =IF(M93>0,IF(M93<=L93,L93-M93,C93*(L93/M93-1)),L93-C93) -> 325947.37 | O93: =IF(M93>0,IF(M93<=L93,O92*(1-M93/L93),0),IF(AND(C93<0,N93>0),O92-C93,O92))/$B$34 -> 211526.87 | P93: =IF($B93>$B$85,R92,R92*$B$33*IF(R92>0,$B$32,1)) -> 352265.18 | Q93: =IF(AND(C93>0,P93>0),C93/(1-$B$31*MAX(0,1-S92/P93)),0) -> 26312.782 | R93: =IF(Q93>0,IF(Q93<=P93,P93-Q93,C93*(P93/Q93-1)),P93-C93) -> 325952.4 | S93: =IF(Q93>0,IF(Q93<=P93,S92*(1-Q93/P93),0),IF(AND(C93<0,R93>0),S92-C93,S92))/$B$34 -> 211530.14 | T93: =IF($B93>$B$85,V92,V92*$B$33*IF(V92>0,$B$32,1)) -> 352265.18 | U93: =IF(AND(C93>0,T93>0),C93/(1-$B$31*MAX(0,1-W92/T93)),0) -> 26312.782 | V93: =IF(U93>0,IF(U93<=T93,T93-U93,C93*(T93/U93-1)),T93-C93) -> 325952.4 | W93: =IF(U93>0,IF(U93<=T93,W92*(1-U93/T93),0),IF(AND(C93<0,V93>0),W92-C93,W92))/$B$34 -> 211530.14
B94: 5 | C94: =$B$83*MIN(12,MAX(0,$B$82-12*$B94))/12 -> 24000 | D94: =IF($B94>$B$85,F93,F93*$B$33*IF(F93>0,$B$32,1)) -> 272670.73 | E94: =IF(AND(C94>0,D94>0),C94/(1-$B$31*MAX(0,1-G93/D94)),0) -> 26544.459 | F94: =IF(E94>0,IF(E94<=D94,D94-E94,C94*(D94/E94-1)),D94-C94) -> 246126.27 | G94: =IF(E94>0,IF(E94<=D94,G93*(1-E94/D94),0),IF(AND(C94<0,F94>0),G93-C94,G93))/$B$34 -> 152337.95 | H94: =IF($B94>$B$85,J93,J93*$B$33*IF(J93>0,$B$32,1)) -> 334611.38 | I94: =IF(AND(C94>0,H94>0),C94/(1-$B$31*MAX(0,1-K93/H94)),0) -> 26544.459 | J94: =IF(I94>0,IF(I94<=H94,H94-I94,C94*(H94/I94-1)),H94-C94) -> 308066.92 | K94: =IF(I94>0,IF(I94<=H94,K93*(1-I94/H94),0),IF(AND(C94<0,J94>0),K93-C94,K93))/$B$34 -> 190675.63 | L94: =IF($B94>$B$85,N93,N93*$B$33*IF(N93>0,$B$32,1)) -> 335054.34 | M94: =IF(AND(C94>0,L94>0),C94/(1-$B$31*MAX(0,1-O93/L94)),0) -> 26544.459 | N94: =IF(M94>0,IF(M94<=L94,L94-M94,C94*(L94/M94-1)),L94-C94) -> 308509.88 | O94: =IF(M94>0,IF(M94<=L94,O93*(1-M94/L94),0),IF(AND(C94<0,N94>0),O93-C94,O93))/$B$34 -> 190949.8 | P94: =IF($B94>$B$85,R93,R93*$B$33*IF(R93>0,$B$32,1)) -> 335059.51 | Q94: =IF(AND(C94>0,P94>0),C94/(1-$B$31*MAX(0,1-S93/P94)),0) -> 26544.459 | R94: =IF(Q94>0,IF(Q94<=P94,P94-Q94,C94*(P94/Q94-1)),P94-C94) -> 308515.05 | S94: =IF(Q94>0,IF(Q94<=P94,S93*(1-Q94/P94),0),IF(AND(C94<0,R94>0),S93-C94,S93))/$B$34 -> 190953 | T94: =IF($B94>$B$85,V93,V93*$B$33*IF(V93>0,$B$32,1)) -> 335059.51 | U94: =IF(AND(C94>0,T94>0),C94/(1-$B$31*MAX(0,1-W93/T94)),0) -> 26544.459 | V94: =IF(U94>0,IF(U94<=T94,T94-U94,C94*(T94/U94-1)),T94-C94) -> 308515.05 | W94: =IF(U94>0,IF(U94<=T94,W93*(1-U94/T94),0),IF(AND(C94<0,V94>0),W93-C94,W93))/$B$34 -> 190953
B95: 6 | C95: =$B$83*MIN(12,MAX(0,$B$82-12*$B95))/12 -> 24000 | D95: =IF($B95>$B$85,F94,F94*$B$33*IF(F94>0,$B$32,1)) -> 253003.04 | E95: =IF(AND(C95>0,D95>0),C95/(1-$B$31*MAX(0,1-G94/D95)),0) -> 26769.254 | F95: =IF(E95>0,IF(E95<=D95,D95-E95,C95*(D95/E95-1)),D95-C95) -> 226233.78 | G95: =IF(E95>0,IF(E95<=D95,G94*(1-E95/D95),0),IF(AND(C95<0,F95>0),G94-C95,G94))/$B$34 -> 133548.69 | H95: =IF($B95>$B$85,J94,J94*$B$33*IF(J94>0,$B$32,1)) -> 316674.31 | I95: =IF(AND(C95>0,H95>0),C95/(1-$B$31*MAX(0,1-K94/H95)),0) -> 26769.254 | J95: =IF(I95>0,IF(I95<=H95,H95-I95,C95*(H95/I95-1)),H95-C95) -> 289905.05 | K95: =IF(I95>0,IF(I95<=H95,K94*(1-I95/H95),0),IF(AND(C95<0,J95>0),K94-C95,K94))/$B$34 -> 171134.66 | L95: =IF($B95>$B$85,N94,N94*$B$33*IF(N94>0,$B$32,1)) -> 317129.64 | M95: =IF(AND(C95>0,L95>0),C95/(1-$B$31*MAX(0,1-O94/L95)),0) -> 26769.254 | N95: =IF(M95>0,IF(M95<=L95,L95-M95,C95*(L95/M95-1)),L95-C95) -> 290360.39 | O95: =IF(M95>0,IF(M95<=L95,O94*(1-M95/L95),0),IF(AND(C95<0,N95>0),O94-C95,O94))/$B$34 -> 171403.45 | P95: =IF($B95>$B$85,R94,R94*$B$33*IF(R94>0,$B$32,1)) -> 317134.96 | Q95: =IF(AND(C95>0,P95>0),C95/(1-$B$31*MAX(0,1-S94/P95)),0) -> 26769.254 | R95: =IF(Q95>0,IF(Q95<=P95,P95-Q95,C95*(P95/Q95-1)),P95-C95) -> 290365.71 | S95: =IF(Q95>0,IF(Q95<=P95,S94*(1-Q95/P95),0),IF(AND(C95<0,R95>0),S94-C95,S94))/$B$34 -> 171406.59 | T95: =IF($B95>$B$85,V94,V94*$B$33*IF(V94>0,$B$32,1)) -> 317134.96 | U95: =IF(AND(C95>0,T95>0),C95/(1-$B$31*MAX(0,1-W94/T95)),0) -> 26769.254 | V95: =IF(U95>0,IF(U95<=T95,T95-U95,C95*(T95/U95-1)),T95-C95) -> 290365.71 | W95: =IF(U95>0,IF(U95<=T95,W94*(1-U95/T95),0),IF(AND(C95<0,V95>0),W94-C95,W94))/$B$34 -> 171406.59
B96: 7 | C96: =$B$83*MIN(12,MAX(0,$B$82-12*$B96))/12 -> 24000 | D96: =IF($B96>$B$85,F95,F95*$B$33*IF(F95>0,$B$32,1)) -> 232554.75 | E96: =IF(AND(C96>0,D96>0),C96/(1-$B$31*MAX(0,1-G95/D96)),0) -> 26987.227 | F96: =IF(E96>0,IF(E96<=D96,D96-E96,C96*(D96/E96-1)),D96-C96) -> 205567.53 | G96: =IF(E96>0,IF(E96<=D96,G95*(1-E96/D96),0),IF(AND(C96<0,F96>0),G95-C96,G95))/$B$34 -> 115736.08 | H96: =IF($B96>$B$85,J95,J95*$B$33*IF(J95>0,$B$32,1)) -> 298005 | I96: =IF(AND(C96>0,H96>0),C96/(1-$B$31*MAX(0,1-K95/H96)),0) -> 26987.227 | J96: =IF(I96>0,IF(I96<=H96,H96-I96,C96*(H96/I96-1)),H96-C96) -> 271017.78 | K96: =IF(I96>0,IF(I96<=H96,K95*(1-I96/H96),0),IF(AND(C96<0,J96>0),K95-C96,K95))/$B$34 -> 152585.07 | L96: =IF($B96>$B$85,N95,N95*$B$33*IF(N95>0,$B$32,1)) -> 298473.06 | M96: =IF(AND(C96>0,L96>0),C96/(1-$B$31*MAX(0,1-O95/L96)),0) -> 26987.227 | N96: =IF(M96>0,IF(M96<=L96,L96-M96,C96*(L96/M96-1)),L96-C96) -> 271485.83 | O96: =IF(M96>0,IF(M96<=L96,O95*(1-M96/L96),0),IF(AND(C96<0,N96>0),O95-C96,O95))/$B$34 -> 152848.58 | P96: =IF($B96>$B$85,R95,R95*$B$33*IF(R95>0,$B$32,1)) -> 298478.53 | Q96: =IF(AND(C96>0,P96>0),C96/(1-$B$31*MAX(0,1-S95/P96)),0) -> 26987.227 | R96: =IF(Q96>0,IF(Q96<=P96,P96-Q96,C96*(P96/Q96-1)),P96-C96) -> 271491.3 | S96: =IF(Q96>0,IF(Q96<=P96,S95*(1-Q96/P96),0),IF(AND(C96<0,R96>0),S95-C96,S95))/$B$34 -> 152851.66 | T96: =IF($B96>$B$85,V95,V95*$B$33*IF(V95>0,$B$32,1)) -> 298478.53 | U96: =IF(AND(C96>0,T96>0),C96/(1-$B$31*MAX(0,1-W95/T96)),0) -> 26987.227 | V96: =IF(U96>0,IF(U96<=T96,T96-U96,C96*(T96/U96-1)),T96-C96) -> 271491.3 | W96: =IF(U96>0,IF(U96<=T96,W95*(1-U96/T96),0),IF(AND(C96<0,V96>0),W95-C96,W95))/$B$34 -> 152851.66
B97: 8 | C97: =$B$83*MIN(12,MAX(0,$B$82-12*$B97))/12 -> 24000 | D97: =IF($B97>$B$85,F96,F96*$B$33*IF(F96>0,$B$32,1)) -> 211311.08 | E97: =IF(AND(C97>0,D97>0),C97/(1-$B$31*MAX(0,1-G96/D97)),0) -> 27198.45 | F97: =IF(E97>0,IF(E97<=D97,D97-E97,C97*(D97/E97-1)),D97-C97) -> 184112.63 | G97: =IF(E97>0,IF(E97<=D97,G96*(1-E97/D97),0),IF(AND(C97<0,F97>0),G96-C97,G96))/$B$34 -> 98862.117 | H97: =IF($B97>$B$85,J96,J96*$B$33*IF(J96>0,$B$32,1)) -> 278590.01 | I97: =IF(AND(C97>0,H97>0),C97/(1-$B$31*MAX(0,1-K96/H97)),0) -> 27198.45 | J97: =IF(I97>0,IF(I97<=H97,H97-I97,C97*(H97/I97-1)),H97-C97) -> 251391.56 | K97: =IF(I97>0,IF(I97<=H97,K96*(1-I97/H97),0),IF(AND(C97<0,J97>0),K96-C97,K96))/$B$34 -> 134988.57 | L97: =IF($B97>$B$85,N96,N96*$B$33*IF(N96>0,$B$32,1)) -> 279071.14 | M97: =IF(AND(C97>0,L97>0),C97/(1-$B$31*MAX(0,1-O96/L97)),0) -> 27198.45 | N97: =IF(M97>0,IF(M97<=L97,L97-M97,C97*(L97/M97-1)),L97-C97) -> 251872.7 | O97: =IF(M97>0,IF(M97<=L97,O96*(1-M97/L97),0),IF(AND(C97<0,N97>0),O96-C97,O96))/$B$34 -> 135246.93 | P97: =IF($B97>$B$85,R96,R96*$B$33*IF(R96>0,$B$32,1)) -> 279076.77 | Q97: =IF(AND(C97>0,P97>0),C97/(1-$B$31*MAX(0,1-S96/P97)),0) -> 27198.45 | R97: =IF(Q97>0,IF(Q97<=P97,P97-Q97,C97*(P97/Q97-1)),P97-C97) -> 251878.32 | S97: =IF(Q97>0,IF(Q97<=P97,S96*(1-Q97/P97),0),IF(AND(C97<0,R97>0),S96-C97,S96))/$B$34 -> 135249.94 | T97: =IF($B97>$B$85,V96,V96*$B$33*IF(V96>0,$B$32,1)) -> 279076.77 | U97: =IF(AND(C97>0,T97>0),C97/(1-$B$31*MAX(0,1-W96/T97)),0) -> 27198.45 | V97: =IF(U97>0,IF(U97<=T97,T97-U97,C97*(T97/U97-1)),T97-C97) -> 251878.32 | W97: =IF(U97>0,IF(U97<=T97,W96*(1-U97/T97),0),IF(AND(C97<0,V97>0),W96-C97,W96))/$B$34 -> 135249.94
B98: 9 | C98: =$B$83*MIN(12,MAX(0,$B$82-12*$B98))/12 -> 24000 | D98: =IF($B98>$B$85,F97,F97*$B$33*IF(F97>0,$B$32,1)) -> 189256.74 | E98: =IF(AND(C98>0,D98>0),C98/(1-$B$31*MAX(0,1-G97/D98)),0) -> 27403.007 | F98: =IF(E98>0,IF(E98<=D98,D98-E98,C98*(D98/E98-1)),D98-C98) -> 161853.73 | G98: =IF(E98>0,IF(E98<=D98,G97*(1-E98/D98),0),IF(AND(C98<0,F98>0),G97-C98,G97))/$B$34 -> 82889.801 | H98: =IF($B98>$B$85,J97,J97*$B$33*IF(J97>0,$B$32,1)) -> 258415.44 | I98: =IF(AND(C98>0,H98>0),C98/(1-$B$31*MAX(0,1-K97/H98)),0) -> 27403.007 | J98: =IF(I98>0,IF(I98<=H98,H98-I98,C98*(H98/I98-1)),H98-C98) -> 231012.44 | K98: =IF(I98>0,IF(I98<=H98,K97*(1-I98/H98),0),IF(AND(C98<0,J98>0),K97-C98,K97))/$B$34 -> 118307.9 | L98: =IF($B98>$B$85,N97,N97*$B$33*IF(N97>0,$B$32,1)) -> 258910.02 | M98: =IF(AND(C98>0,L98>0),C98/(1-$B$31*MAX(0,1-O97/L98)),0) -> 27403.007 | N98: =IF(M98>0,IF(M98<=L98,L98-M98,C98*(L98/M98-1)),L98-C98) -> 231507.01 | O98: =IF(M98>0,IF(M98<=L98,O97*(1-M98/L98),0),IF(AND(C98<0,N98>0),O97-C98,O97))/$B$34 -> 118561.18 | P98: =IF($B98>$B$85,R97,R97*$B$33*IF(R97>0,$B$32,1)) -> 258915.8 | Q98: =IF(AND(C98>0,P98>0),C98/(1-$B$31*MAX(0,1-S97/P98)),0) -> 27403.007 | R98: =IF(Q98>0,IF(Q98<=P98,P98-Q98,C98*(P98/Q98-1)),P98-C98) -> 231512.79 | S98: =IF(Q98>0,IF(Q98<=P98,S97*(1-Q98/P98),0),IF(AND(C98<0,R98>0),S97-C98,S97))/$B$34 -> 118564.14 | T98: =IF($B98>$B$85,V97,V97*$B$33*IF(V97>0,$B$32,1)) -> 258915.8 | U98: =IF(AND(C98>0,T98>0),C98/(1-$B$31*MAX(0,1-W97/T98)),0) -> 27403.007 | V98: =IF(U98>0,IF(U98<=T98,T98-U98,C98*(T98/U98-1)),T98-C98) -> 231512.79 | W98: =IF(U98>0,IF(U98<=T98,W97*(1-U98/T98),0),IF(AND(C98<0,V98>0),W97-C98,W97))/$B$34 -> 118564.14
B99: 10 | C99: =$B$83*MIN(12,MAX(0,$B$82-12*$B99))/12 -> 24000 | D99: =IF($B99>$B$85,F98,F98*$B$33*IF(F98>0,$B$32,1)) -> 166375.93 | E99: =IF(AND(C99>0,D99>0),C99/(1-$B$31*MAX(0,1-G98/D99)),0) -> 27600.989 | F99: =IF(E99>0,IF(E99<=D99,D99-E99,C99*(D99/E99-1)),D99-C99) -> 138774.94 | G99: =IF(E99>0,IF(E99<=D99,G98*(1-E99/D99),0),IF(AND(C99<0,F99>0),G98-C99,G98))/$B$34 -> 67783.108 | H99: =IF($B99>$B$85,J98,J98*$B$33*IF(J98>0,$B$32,1)) -> 237466.92 | I99: =IF(AND(C99>0,H99>0),C99/(1-$B$31*MAX(0,1-K98/H99)),0) -> 27600.989 | J99: =IF(I99>0,IF(I99<=H99,H99-I99,C99*(H99/I99-1)),H99-C99) -> 209865.93 | K99: =IF(I99>0,IF(I99<=H99,K98*(1-I99/H99),0),IF(AND(C99<0,J99>0),K98-C99,K98))/$B$34 -> 102506.73 | L99: =IF($B99>$B$85,N98,N98*$B$33*IF(N98>0,$B$32,1)) -> 237975.32 | M99: =IF(AND(C99>0,L99>0),C99/(1-$B$31*MAX(0,1-O98/L99)),0) -> 27600.989 | N99: =IF(M99>0,IF(M99<=L99,L99-M99,C99*(L99/M99-1)),L99-C99) -> 210374.33 | O99: =IF(M99>0,IF(M99<=L99,O98*(1-M99/L99),0),IF(AND(C99<0,N99>0),O98-C99,O98))/$B$34 -> 102755.05 | P99: =IF($B99>$B$85,R98,R98*$B$33*IF(R98>0,$B$32,1)) -> 237981.26 | Q99: =IF(AND(C99>0,P99>0),C99/(1-$B$31*MAX(0,1-S98/P99)),0) -> 27600.989 | R99: =IF(Q99>0,IF(Q99<=P99,P99-Q99,C99*(P99/Q99-1)),P99-C99) -> 210380.27 | S99: =IF(Q99>0,IF(Q99<=P99,S98*(1-Q99/P99),0),IF(AND(C99<0,R99>0),S98-C99,S98))/$B$34 -> 102757.95 | T99: =IF($B99>$B$85,V98,V98*$B$33*IF(V98>0,$B$32,1)) -> 237981.26 | U99: =IF(AND(C99>0,T99>0),C99/(1-$B$31*MAX(0,1-W98/T99)),0) -> 27600.989 | V99: =IF(U99>0,IF(U99<=T99,T99-U99,C99*(T99/U99-1)),T99-C99) -> 210380.27 | W99: =IF(U99>0,IF(U99<=T99,W98*(1-U99/T99),0),IF(AND(C99<0,V99>0),W98-C99,W98))/$B$34 -> 102757.95
B100: 11 | C100: =$B$83*MIN(12,MAX(0,$B$82-12*$B100))/12 -> 24000 | D100: =IF($B100>$B$85,F99,F99*$B$33*IF(F99>0,$B$32,1)) -> 142652.31 | E100: =IF(AND(C100>0,D100>0),C100/(1-$B$31*MAX(0,1-G99/D100)),0) -> 27792.498 | F100: =IF(E100>0,IF(E100<=D100,D100-E100,C100*(D100/E100-1)),D100-C100) -> 114859.81 | G100: =IF(E100>0,IF(E100<=D100,G99*(1-E100/D100),0),IF(AND(C100<0,F100>0),G99-C100,G99))/$B$34 -> 53507 | H100: =IF($B100>$B$85,J99,J99*$B$33*IF(J99>0,$B$32,1)) -> 215729.59 | I100: =IF(AND(C100>0,H100>0),C100/(1-$B$31*MAX(0,1-K99/H100)),0) -> 27792.498 | J100: =IF(I100>0,IF(I100<=H100,H100-I100,C100*(H100/I100-1)),H100-C100) -> 187937.09 | K100: =IF(I100>0,IF(I100<=H100,K99*(1-I100/H100),0),IF(AND(C100<0,J100>0),K99-C100,K99))/$B$34 -> 87549.768 | L100: =IF($B100>$B$85,N99,N99*$B$33*IF(N99>0,$B$32,1)) -> 216252.19 | M100: =IF(AND(C100>0,L100>0),C100/(1-$B$31*MAX(0,1-O99/L100)),0) -> 27792.498 | N100: =IF(M100>0,IF(M100<=L100,L100-M100,C100*(L100/M100-1)),L100-C100) -> 188459.69 | O100: =IF(M100>0,IF(M100<=L100,O99*(1-M100/L100),0),IF(AND(C100<0,N100>0),O99-C100,O99))/$B$34 -> 87793.218 | P100: =IF($B100>$B$85,R99,R99*$B$33*IF(R99>0,$B$32,1)) -> 216258.29 | Q100: =IF(AND(C100>0,P100>0),C100/(1-$B$31*MAX(0,1-S99/P100)),0) -> 27792.498 | R100: =IF(Q100>0,IF(Q100<=P100,P100-Q100,C100*(P100/Q100-1)),P100-C100) -> 188465.8 | S100: =IF(Q100>0,IF(Q100<=P100,S99*(1-Q100/P100),0),IF(AND(C100<0,R100>0),S99-C100,S99))/$B$34 -> 87796.063 | T100: =IF($B100>$B$85,V99,V99*$B$33*IF(V99>0,$B$32,1)) -> 216258.29 | U100: =IF(AND(C100>0,T100>0),C100/(1-$B$31*MAX(0,1-W99/T100)),0) -> 27792.498 | V100: =IF(U100>0,IF(U100<=T100,T100-U100,C100*(T100/U100-1)),T100-C100) -> 188465.8 | W100: =IF(U100>0,IF(U100<=T100,W99*(1-U100/T100),0),IF(AND(C100<0,V100>0),W99-C100,W99))/$B$34 -> 87796.063
B101: 12 | C101: =$B$83*MIN(12,MAX(0,$B$82-12*$B101))/12 -> 24000 | D101: =IF($B101>$B$85,F100,F100*$B$33*IF(F100>0,$B$32,1)) -> 118069 | E101: =IF(AND(C101>0,D101>0),C101/(1-$B$31*MAX(0,1-G100/D101)),0) -> 27977.64 | F101: =IF(E101>0,IF(E101<=D101,D101-E101,C101*(D101/E101-1)),D101-C101) -> 90091.355 | G101: =IF(E101>0,IF(E101<=D101,G100*(1-E101/D101),0),IF(AND(C101<0,F101>0),G100-C101,G100))/$B$34 -> 40027.428 | H101: =IF($B101>$B$85,J100,J100*$B$33*IF(J100>0,$B$32,1)) -> 193188.05 | I101: =IF(AND(C101>0,H101>0),C101/(1-$B$31*MAX(0,1-K100/H101)),0) -> 27977.64 | J101: =IF(I101>0,IF(I101<=H101,H101-I101,C101*(H101/I101-1)),H101-C101) -> 165210.41 | K101: =IF(I101>0,IF(I101<=H101,K100*(1-I101/H101),0),IF(AND(C101<0,J101>0),K100-C101,K100))/$B$34 -> 73402.69 | L101: =IF($B101>$B$85,N100,N100*$B$33*IF(N100>0,$B$32,1)) -> 193725.25 | M101: =IF(AND(C101>0,L101>0),C101/(1-$B$31*MAX(0,1-O100/L101)),0) -> 27977.64 | N101: =IF(M101>0,IF(M101<=L101,L101-M101,C101*(L101/M101-1)),L101-C101) -> 165747.61 | O101: =IF(M101>0,IF(M101<=L101,O100*(1-M101/L101),0),IF(AND(C101<0,N101>0),O100-C101,O100))/$B$34 -> 73641.367 | P101: =IF($B101>$B$85,R100,R100*$B$33*IF(R100>0,$B$32,1)) -> 193731.53 | Q101: =IF(AND(C101>0,P101>0),C101/(1-$B$31*MAX(0,1-S100/P101)),0) -> 27977.64 | R101: =IF(Q101>0,IF(Q101<=P101,P101-Q101,C101*(P101/Q101-1)),P101-C101) -> 165753.89 | S101: =IF(Q101>0,IF(Q101<=P101,S100*(1-Q101/P101),0),IF(AND(C101<0,R101>0),S100-C101,S100))/$B$34 -> 73644.156 | T101: =IF($B101>$B$85,V100,V100*$B$33*IF(V100>0,$B$32,1)) -> 193731.53 | U101: =IF(AND(C101>0,T101>0),C101/(1-$B$31*MAX(0,1-W100/T101)),0) -> 27977.64 | V101: =IF(U101>0,IF(U101<=T101,T101-U101,C101*(T101/U101-1)),T101-C101) -> 165753.89 | W101: =IF(U101>0,IF(U101<=T101,W100*(1-U101/T101),0),IF(AND(C101<0,V101>0),W100-C101,W100))/$B$34 -> 73644.156
... B124: 35 | C124: =$B$83*MIN(12,MAX(0,$B$82-12*$B124))/12 -> 0 | D124: =IF($B124>$B$85,F123,F123*$B$33*IF(F123>0,$B$32,1)) -> -78837.953 | E124: =IF(AND(C124>0,D124>0),C124/(1-$B$31*MAX(0,1-G123/D124)),0) -> 0 | F124: =IF(E124>0,IF(E124<=D124,D124-E124,C124*(D124/E124-1)),D124-C124) -> -78837.953 | G124: =IF(E124>0,IF(E124<=D124,G123*(1-E124/D124),0),IF(AND(C124<0,F124>0),G123-C124,G123))/$B$34 -> 0 | H124: =IF($B124>$B$85,J123,J123*$B$33*IF(J123>0,$B$32,1)) -> -559.79176 | I124: =IF(AND(C124>0,H124>0),C124/(1-$B$31*MAX(0,1-K123/H124)),0) -> 0 | J124: =IF(I124>0,IF(I124<=H124,H124-I124,C124*(H124/I124-1)),H124-C124) -> -559.79176 | K124: =IF(I124>0,IF(I124<=H124,K123*(1-I124/H124),0),IF(AND(C124<0,J124>0),K123-C124,K123))/$B$34 -> 0 | L124: =IF($B124>$B$85,N123,N123*$B$33*IF(N123>0,$B$32,1)) -> -6.4659963 | M124: =IF(AND(C124>0,L124>0),C124/(1-$B$31*MAX(0,1-O123/L124)),0) -> 0 | N124: =IF(M124>0,IF(M124<=L124,L124-M124,C124*(L124/M124-1)),L124-C124) -> -6.4659963 | O124: =IF(M124>0,IF(M124<=L124,O123*(1-M124/L124),0),IF(AND(C124<0,N124>0),O123-C124,O123))/$B$34 -> 0 | P124: =IF($B124>$B$85,R123,R123*$B$33*IF(R123>0,$B$32,1)) -> -9.3769437e-11 | Q124: =IF(AND(C124>0,P124>0),C124/(1-$B$31*MAX(0,1-S123/P124)),0) -> 0 | R124: =IF(Q124>0,IF(Q124<=P124,P124-Q124,C124*(P124/Q124-1)),P124-C124) -> -9.3769437e-11 | S124: =IF(Q124>0,IF(Q124<=P124,S123*(1-Q124/P124),0),IF(AND(C124<0,R124>0),S123-C124,S123))/$B$34 -> 0 | T124: =IF($B124>$B$85,V123,V123*$B$33*IF(V123>0,$B$32,1)) -> -8.9195318e-11 | U124: =IF(AND(C124>0,T124>0),C124/(1-$B$31*MAX(0,1-W123/T124)),0) -> 0 | V124: =IF(U124>0,IF(U124<=T124,T124-U124,C124*(T124/U124-1)),T124-C124) -> -8.9195318e-11 | W124: =IF(U124>0,IF(U124<=T124,W123*(1-U124/T124),0),IF(AND(C124<0,V124>0),W123-C124,W123))/$B$34 -> 0

Sheet 3 - Le tre forze
A1: Le tre forze: età, inflazione e stipendi sul caso di Irene
A2: Strumento informativo / divulgativo. NON è consulenza finanziaria. I valori sono indicativi al 2026 e vanno verificati col tuo consulente.
A4: Il caso (celle gialle modificabili)
A5: RAL nel primo anno di lavoro | B5: 27000 | C5: Irene: 27.000 € nel 2009, cresciuta del 4,05% l'anno
A6: RAL 2026 | B6: 53000 | C6: Dal 2027 costante in termini reali
A7: Anno del primo contributo (dal 2009 in poi) | B7: 2009 | C7: Contributiva pura: primo contributo dopo il 1995
A8: Spesa annua in cassa, da occupata e da FIRE (euro di oggi) | B8: 22000 | C8: Affitto compreso: 650 €/mese
A9: Età fino a cui deve durare il piano | B9: 92 | C9: Convenzione del canale
A10: Aliquota contributiva IVS | B10: 0.33 | C10: Dipendenti del settore privato
A11: Inflazione 2026 (acquisita ad agosto) | B11: 0.029 | C11: ISTAT, prezzi al consumo agosto 2026 (inflazione acquisita)
A12: Shock di inflazione: 2027 | B12: 0.03 | C12: Prova di stress, non previsione: rendimenti nominali invariati
A13: Shock di inflazione: 2028 | B13: 0.03
A14: Stipendi reali: variazione 2027 | B14: -0.006 | C14: Contratti sotto i prezzi, senza recupero
A15: Stipendi reali: variazione 2028 | B15: -0.006
A16: Punto della banda per il dettaglio | B16: centrale | C16: «a regole di oggi», «centrale» (revisione a circa 0,2 l'anno), «se la revisione accelera»
A17: Nascita e stop fisso dal foglio 1; rendimento, inflazione, imposte e bollo dal foglio 2. Gli stop di questo foglio non contano il TFR, che resta un cuscinetto: lo aggiunge la leva del foglio 4.
A19: La storia di risparmio 2009-2026: patrimonio e base di costo derivati dalla stessa storia
A20: Netto 2026 (regole 2026) | B20: =IFERROR(Q180,"fuori dal campo del simulatore (foglio 1, riga 8)") -> 34246.456 | C20: Versamenti mensili = quota × netto dell'anno; 3% reale + inflazione FOI, bollo 0,20%
A21: Risparmio 2026 | B21: =IFERROR(Q180-$B$8,"fuori dal campo del simulatore (foglio 1, riga 8)") -> 12246.456
A22: Quota di risparmio sul netto (la stessa ogni anno) | B22: =IFERROR(1-$B$8/Q180,"fuori dal campo del simulatore (foglio 1, riga 8)") -> 0.35759776
A23: Patrimonio al 31/12/2026 | B23: =IFERROR(S180,"fuori dal campo del simulatore (foglio 1, riga 8)") -> 254467.88
A24: Versato (base di costo) | B24: =IFERROR(T180,"fuori dal campo del simulatore (foglio 1, riga 8)") -> 166895.72
A25: Crescita | B25: =IFERROR($B$23-$B$24,"fuori dal campo del simulatore (foglio 1, riga 8)") -> 87572.167
A26: Plusvalenza latente | B26: =IFERROR(1-$B$24/$B$23,"fuori dal campo del simulatore (foglio 1, riga 8)") -> 0.34413839
A28: Allo stop fisso del foglio 1
A29: Stop fisso | B29: =IFERROR(INT(($B$130-$B$129)/12)&" anni"&IF(MOD(($B$130-$B$129),12)>0," e "&MOD(($B$130-$B$129),12)&IF(MOD(($B$130-$B$129),12)=1," mese"," mesi"),"")&", "&CHOOSE(MOD($B$130,12)+1,"gennaio","febbraio","marzo","aprile","maggio","giugno","luglio","agosto","settembre","ottobre","novembre","dicembre")&" "&INT($B$130/12),"fuori dal campo del simulatore (foglio 1, riga 8)") -> 50 anni, marzo 2034
A30: Patrimonio allo stop (euro di oggi) | B30: =IFERROR(IF(NOT($B$137),"stop fisso fuori campo (foglio 1, riga 8)",$B$1340),"fuori dal campo del simulatore (foglio 1, riga 8)") -> 406949.98
A31: … con lo shock di inflazione | B31: =IFERROR(IF(NOT($B$137),"stop fisso fuori campo (foglio 1, riga 8)",$B$822),"fuori dal campo del simulatore (foglio 1, riga 8)") -> 400687.23
A32: Mesi di ponte con i 67 anni di ieri | B32: =IFERROR(IF(NOT($B$137),"stop fisso fuori campo (foglio 1, riga 8)",$B$2006),"fuori dal campo del simulatore (foglio 1, riga 8)") -> 205
A33: Mesi di ponte con la curva RGS 27 | B33: =IFERROR(IF(NOT($B$137),"stop fisso fuori campo (foglio 1, riga 8)",$B$2054),"fuori dal campo del simulatore (foglio 1, riga 8)") -> 232
A34: Un mese di lavoro vale (margine a stop + 12 mesi meno margine allo stop, diviso 12) | B34: =IFERROR(IF(NOT($B$137),"stop fisso fuori campo (foglio 1, riga 8)",($E$1927-$E$1335)/12),"fuori dal campo del simulatore (foglio 1, riga 8)") -> 4029.2228
A35: Risparmio annuo con gli stipendi fermi (2028) | B35: =IFERROR(12*AB182,"fuori dal campo del simulatore (foglio 1, riga 8)") -> 11922.165
A36: Rivalutazione del montante stimata per il 2026 (riga 2025) | B36: =IFERROR(J179-1,"fuori dal campo del simulatore (foglio 1, riga 8)") -> 0.062636827 | C36: Stima: riga ufficiale 2024 e PIL 2025 ISTAT; contro l'inflazione acquisita del 2,9%
A38: Il messaggio in due passi (stop fisso; mesi di lavoro = euro / valore di un mese di lavoro)
A39: Voce | B39: A regole di oggi | C39: Centrale | D39: Se la revisione accelera
A40: Ponte in più (euro) | B40: =IFERROR(IF(NOT($B$137),"stop fisso fuori campo (foglio 1, riga 8)",($X$2057-$X$2009)),"fuori dal campo del simulatore (foglio 1, riga 8)") -> 37833.541 | C40: =IFERROR(IF(NOT($B$137),"stop fisso fuori campo (foglio 1, riga 8)",($X$2057-$X$2009)),"fuori dal campo del simulatore (foglio 1, riga 8)") -> 37833.541 | D40: =IFERROR(IF(NOT($B$137),"stop fisso fuori campo (foglio 1, riga 8)",($X$2057-$X$2009)),"fuori dal campo del simulatore (foglio 1, riga 8)") -> 37833.541
A41: Ponte in più (mesi di lavoro) | B41: =IFERROR(IF(NOT($B$137),"stop fisso fuori campo (foglio 1, riga 8)",($X$2057-$X$2009)/$B$34),"fuori dal campo del simulatore (foglio 1, riga 8)") -> 9.3897863 | C41: =IFERROR(IF(NOT($B$137),"stop fisso fuori campo (foglio 1, riga 8)",($X$2057-$X$2009)/$B$34),"fuori dal campo del simulatore (foglio 1, riga 8)") -> 9.3897863 | D41: =IFERROR(IF(NOT($B$137),"stop fisso fuori campo (foglio 1, riga 8)",($X$2057-$X$2009)/$B$34),"fuori dal campo del simulatore (foglio 1, riga 8)") -> 9.3897863
A42: In media, un mese di ponte costa | B42: =IFERROR(IF(NOT($B$137),"stop fisso fuori campo (foglio 1, riga 8)",($X$2057-$X$2009)/($B$134-$B$135)),"fuori dal campo del simulatore (foglio 1, riga 8)") -> 1401.2422 | C42: =IFERROR(IF(NOT($B$137),"stop fisso fuori campo (foglio 1, riga 8)",($X$2057-$X$2009)/($B$134-$B$135)),"fuori dal campo del simulatore (foglio 1, riga 8)") -> 1401.2422 | D42: =IFERROR(IF(NOT($B$137),"stop fisso fuori campo (foglio 1, riga 8)",($X$2057-$X$2009)/($B$134-$B$135)),"fuori dal campo del simulatore (foglio 1, riga 8)") -> 1401.2422
A43: La pensione più alta restituisce (euro) | B43: =IFERROR(IF(NOT($B$137),"stop fisso fuori campo (foglio 1, riga 8)",($X$759-$X$2009)-($X$1055-$X$2057)),"fuori dal campo del simulatore (foglio 1, riga 8)") -> 24982.394 | C43: =IFERROR(IF(NOT($B$137),"stop fisso fuori campo (foglio 1, riga 8)",($X$759-$X$2009)-($X$1351-$X$2057)),"fuori dal campo del simulatore (foglio 1, riga 8)") -> 8801.2504 | D43: =IFERROR(IF(NOT($B$137),"stop fisso fuori campo (foglio 1, riga 8)",($X$759-$X$2009)-($X$1647-$X$2057)),"fuori dal campo del simulatore (foglio 1, riga 8)") -> -2612.3712
A44: La pensione più alta restituisce (mesi di lavoro) | B44: =IFERROR(IF(NOT($B$137),"stop fisso fuori campo (foglio 1, riga 8)",(($X$759-$X$2009)-($X$1055-$X$2057))/$B$34),"fuori dal campo del simulatore (foglio 1, riga 8)") -> 6.2003011 | C44: =IFERROR(IF(NOT($B$137),"stop fisso fuori campo (foglio 1, riga 8)",(($X$759-$X$2009)-($X$1351-$X$2057))/$B$34),"fuori dal campo del simulatore (foglio 1, riga 8)") -> 2.1843544 | D44: =IFERROR(IF(NOT($B$137),"stop fisso fuori campo (foglio 1, riga 8)",(($X$759-$X$2009)-($X$1647-$X$2057))/$B$34),"fuori dal campo del simulatore (foglio 1, riga 8)") -> -0.6483561
A45: Costo netto dell'età (euro) | B45: =IFERROR(IF(NOT($B$137),"stop fisso fuori campo (foglio 1, riga 8)",$X$1055-$X$759),"fuori dal campo del simulatore (foglio 1, riga 8)") -> 12851.146 | C45: =IFERROR(IF(NOT($B$137),"stop fisso fuori campo (foglio 1, riga 8)",$X$1351-$X$759),"fuori dal campo del simulatore (foglio 1, riga 8)") -> 29032.29 | D45: =IFERROR(IF(NOT($B$137),"stop fisso fuori campo (foglio 1, riga 8)",$X$1647-$X$759),"fuori dal campo del simulatore (foglio 1, riga 8)") -> 40445.912
A46: Costo netto dell'età (mesi di lavoro) | B46: =IFERROR(IF(NOT($B$137),"stop fisso fuori campo (foglio 1, riga 8)",($X$1055-$X$759)/$B$34),"fuori dal campo del simulatore (foglio 1, riga 8)") -> 3.1894852 | C46: =IFERROR(IF(NOT($B$137),"stop fisso fuori campo (foglio 1, riga 8)",($X$1351-$X$759)/$B$34),"fuori dal campo del simulatore (foglio 1, riga 8)") -> 7.2054319 | D46: =IFERROR(IF(NOT($B$137),"stop fisso fuori campo (foglio 1, riga 8)",($X$1647-$X$759)/$B$34),"fuori dal campo del simulatore (foglio 1, riga 8)") -> 10.038142
A47: Pensione lorda allo stop fisso (€/mese) | B47: =IFERROR(IF(NOT($B$137),"stop fisso fuori campo (foglio 1, riga 8)",$B$1048/13),"fuori dal campo del simulatore (foglio 1, riga 8)") -> 2128.3867 | C47: =IFERROR(IF(NOT($B$137),"stop fisso fuori campo (foglio 1, riga 8)",$B$1344/13),"fuori dal campo del simulatore (foglio 1, riga 8)") -> 1987.5786 | D47: =IFERROR(IF(NOT($B$137),"stop fisso fuori campo (foglio 1, riga 8)",$B$1640/13),"fuori dal campo del simulatore (foglio 1, riga 8)") -> 1893.867
A48: Pensione netta allo stop fisso (€/mese) | B48: =IFERROR(IF(NOT($B$137),"stop fisso fuori campo (foglio 1, riga 8)",$B$1050/13),"fuori dal campo del simulatore (foglio 1, riga 8)") -> 1655.6209 | C48: =IFERROR(IF(NOT($B$137),"stop fisso fuori campo (foglio 1, riga 8)",$B$1346/13),"fuori dal campo del simulatore (foglio 1, riga 8)") -> 1559.0771 | D48: =IFERROR(IF(NOT($B$137),"stop fisso fuori campo (foglio 1, riga 8)",$B$1642/13),"fuori dal campo del simulatore (foglio 1, riga 8)") -> 1490.9784
A49: Pensione di ieri: 67 anni, coefficienti di oggi (lorda / netta, €/mese) | B49: =IFERROR(IF(NOT($B$137),"stop fisso fuori campo (foglio 1, riga 8)",$B$752/13),"fuori dal campo del simulatore (foglio 1, riga 8)") -> 1942.8725 | C49: =IFERROR(IF(NOT($B$137),"stop fisso fuori campo (foglio 1, riga 8)",$B$754/13),"fuori dal campo del simulatore (foglio 1, riga 8)") -> 1528.4248
A51: Le tre forze: Shapley a tre (mesi di lavoro allo stop fisso; media su tutti gli ordini)
A52: Forza | B52: A regole di oggi | C52: Centrale | D52: Se la revisione accelera
A53: Età (requisito + revisione dei coefficienti) | B53: =IFERROR(IF(NOT($B$137),"stop fisso fuori campo (foglio 1, riga 8)",-(($E$1039-$E$743)/3+($E$1113-$E$817)/6+($E$1187-$E$891)/6+($E$1261-$E$965)/3)/$B$34),"fuori dal campo del simulatore (foglio 1, riga 8)") -> 3.18876 | C53: =IFERROR(IF(NOT($B$137),"stop fisso fuori campo (foglio 1, riga 8)",-(($E$1335-$E$743)/3+($E$1409-$E$817)/6+($E$1483-$E$891)/6+($E$1557-$E$965)/3)/$B$34),"fuori dal campo del simulatore (foglio 1, riga 8)") -> 7.2030482 | D53: =IFERROR(IF(NOT($B$137),"stop fisso fuori campo (foglio 1, riga 8)",-(($E$1631-$E$743)/3+($E$1705-$E$817)/6+($E$1779-$E$891)/6+($E$1853-$E$965)/3)/$B$34),"fuori dal campo del simulatore (foglio 1, riga 8)") -> 10.034659
A54: Inflazione | B54: =IFERROR(IF(NOT($B$137),"stop fisso fuori campo (foglio 1, riga 8)",-(($E$817-$E$743)/3+($E$1113-$E$1039)/6+($E$965-$E$891)/6+($E$1261-$E$1187)/3)/$B$34),"fuori dal campo del simulatore (foglio 1, riga 8)") -> 1.3745516 | C54: =IFERROR(IF(NOT($B$137),"stop fisso fuori campo (foglio 1, riga 8)",-(($E$817-$E$743)/3+($E$1409-$E$1335)/6+($E$965-$E$891)/6+($E$1557-$E$1483)/3)/$B$34),"fuori dal campo del simulatore (foglio 1, riga 8)") -> 1.3793358 | D54: =IFERROR(IF(NOT($B$137),"stop fisso fuori campo (foglio 1, riga 8)",-(($E$817-$E$743)/3+($E$1705-$E$1631)/6+($E$965-$E$891)/6+($E$1853-$E$1779)/3)/$B$34),"fuori dal campo del simulatore (foglio 1, riga 8)") -> 1.3825113
A55: Stipendi | B55: =IFERROR(IF(NOT($B$137),"stop fisso fuori campo (foglio 1, riga 8)",-(($E$891-$E$743)/3+($E$1187-$E$1039)/6+($E$965-$E$817)/6+($E$1261-$E$1113)/3)/$B$34),"fuori dal campo del simulatore (foglio 1, riga 8)") -> 0.83306981 | C55: =IFERROR(IF(NOT($B$137),"stop fisso fuori campo (foglio 1, riga 8)",-(($E$891-$E$743)/3+($E$1483-$E$1335)/6+($E$965-$E$817)/6+($E$1557-$E$1409)/3)/$B$34),"fuori dal campo del simulatore (foglio 1, riga 8)") -> 0.82659346 | D55: =IFERROR(IF(NOT($B$137),"stop fisso fuori campo (foglio 1, riga 8)",-(($E$891-$E$743)/3+($E$1779-$E$1631)/6+($E$965-$E$817)/6+($E$1853-$E$1705)/3)/$B$34),"fuori dal campo del simulatore (foglio 1, riga 8)") -> 0.82229561
A56: Totale | B56: =IFERROR(IF(NOT($B$137),"stop fisso fuori campo (foglio 1, riga 8)",-($E$1261-$E$743)/$B$34),"fuori dal campo del simulatore (foglio 1, riga 8)") -> 5.3963814 | C56: =IFERROR(IF(NOT($B$137),"stop fisso fuori campo (foglio 1, riga 8)",-($E$1557-$E$743)/$B$34),"fuori dal campo del simulatore (foglio 1, riga 8)") -> 9.4089775 | D56: =IFERROR(IF(NOT($B$137),"stop fisso fuori campo (foglio 1, riga 8)",-($E$1853-$E$743)/$B$34),"fuori dal campo del simulatore (foglio 1, riga 8)") -> 12.239466
A58: Margine allo stop fisso (euro) | B58: A regole di oggi | C58: Centrale | D58: Se la revisione accelera
A59: Mondo di ieri (67 anni, coefficienti di oggi) | B59: =IFERROR(IF(NOT($B$137),"stop fisso fuori campo (foglio 1, riga 8)",$E$743),"fuori dal campo del simulatore (foglio 1, riga 8)") -> 15839.197 | C59: =IFERROR(IF(NOT($B$137),"stop fisso fuori campo (foglio 1, riga 8)",$E$743),"fuori dal campo del simulatore (foglio 1, riga 8)") -> 15839.197 | D59: =IFERROR(IF(NOT($B$137),"stop fisso fuori campo (foglio 1, riga 8)",$E$743),"fuori dal campo del simulatore (foglio 1, riga 8)") -> 15839.197
A60: Con età | B60: =IFERROR(IF(NOT($B$137),"stop fisso fuori campo (foglio 1, riga 8)",$E$1039),"fuori dal campo del simulatore (foglio 1, riga 8)") -> 2988.0505 | C60: =IFERROR(IF(NOT($B$137),"stop fisso fuori campo (foglio 1, riga 8)",$E$1335),"fuori dal campo del simulatore (foglio 1, riga 8)") -> -13193.093 | D60: =IFERROR(IF(NOT($B$137),"stop fisso fuori campo (foglio 1, riga 8)",$E$1631),"fuori dal campo del simulatore (foglio 1, riga 8)") -> -24606.715
A61: Con inflazione | B61: =IFERROR(IF(NOT($B$137),"stop fisso fuori campo (foglio 1, riga 8)",$E$817),"fuori dal campo del simulatore (foglio 1, riga 8)") -> 10311.44 | C61: =IFERROR(IF(NOT($B$137),"stop fisso fuori campo (foglio 1, riga 8)",$E$817),"fuori dal campo del simulatore (foglio 1, riga 8)") -> 10311.44 | D61: =IFERROR(IF(NOT($B$137),"stop fisso fuori campo (foglio 1, riga 8)",$E$817),"fuori dal campo del simulatore (foglio 1, riga 8)") -> 10311.44
A62: Con stipendi | B62: =IFERROR(IF(NOT($B$137),"stop fisso fuori campo (foglio 1, riga 8)",$E$891),"fuori dal campo del simulatore (foglio 1, riga 8)") -> 12472.674 | C62: =IFERROR(IF(NOT($B$137),"stop fisso fuori campo (foglio 1, riga 8)",$E$891),"fuori dal campo del simulatore (foglio 1, riga 8)") -> 12472.674 | D62: =IFERROR(IF(NOT($B$137),"stop fisso fuori campo (foglio 1, riga 8)",$E$891),"fuori dal campo del simulatore (foglio 1, riga 8)") -> 12472.674
A63: Con età + inflazione | B63: =IFERROR(IF(NOT($B$137),"stop fisso fuori campo (foglio 1, riga 8)",$E$1113),"fuori dal campo del simulatore (foglio 1, riga 8)") -> -2557.3554 | C63: =IFERROR(IF(NOT($B$137),"stop fisso fuori campo (foglio 1, riga 8)",$E$1409),"fuori dal campo del simulatore (foglio 1, riga 8)") -> -18777.324 | D63: =IFERROR(IF(NOT($B$137),"stop fisso fuori campo (foglio 1, riga 8)",$E$1705),"fuori dal campo del simulatore (foglio 1, riga 8)") -> -30216.715
A64: Con età + stipendi | B64: =IFERROR(IF(NOT($B$137),"stop fisso fuori campo (foglio 1, riga 8)",$E$1187),"fuori dal campo del simulatore (foglio 1, riga 8)") -> -355.08718 | C64: =IFERROR(IF(NOT($B$137),"stop fisso fuori campo (foglio 1, riga 8)",$E$1483),"fuori dal campo del simulatore (foglio 1, riga 8)") -> -16484.313 | D64: =IFERROR(IF(NOT($B$137),"stop fisso fuori campo (foglio 1, riga 8)",$E$1779),"fuori dal campo del simulatore (foglio 1, riga 8)") -> -27863.481
A65: Con inflazione + stipendi | B65: =IFERROR(IF(NOT($B$137),"stop fisso fuori campo (foglio 1, riga 8)",$E$965),"fuori dal campo del simulatore (foglio 1, riga 8)") -> 6941.2221 | C65: =IFERROR(IF(NOT($B$137),"stop fisso fuori campo (foglio 1, riga 8)",$E$965),"fuori dal campo del simulatore (foglio 1, riga 8)") -> 6941.2221 | D65: =IFERROR(IF(NOT($B$137),"stop fisso fuori campo (foglio 1, riga 8)",$E$965),"fuori dal campo del simulatore (foglio 1, riga 8)") -> 6941.2221
A66: Con età + inflazione + stipendi | B66: =IFERROR(IF(NOT($B$137),"stop fisso fuori campo (foglio 1, riga 8)",$E$1261),"fuori dal campo del simulatore (foglio 1, riga 8)") -> -5904.0258 | C66: =IFERROR(IF(NOT($B$137),"stop fisso fuori campo (foglio 1, riga 8)",$E$1557),"fuori dal campo del simulatore (foglio 1, riga 8)") -> -22071.669 | D66: =IFERROR(IF(NOT($B$137),"stop fisso fuori campo (foglio 1, riga 8)",$E$1853),"fuori dal campo del simulatore (foglio 1, riga 8)") -> -33476.336
A68: Stop minimo nei mondi (senza TFR: lo aggiunge il foglio 4)
A69: Mondo | B69: Stop minimo | C69: Mese | D69: Pensione lorda allo stop minimo (€/mese) | E69: Pensione netta (€/mese)
A70: Ieri: 67 anni, coefficienti di oggi | B70: =IFERROR(IF($E$2099=0,INT(($C$2099-$B$129)/12)&" anni"&IF(MOD(($C$2099-$B$129),12)>0," e "&MOD(($C$2099-$B$129),12)&IF(MOD(($C$2099-$B$129),12)=1," mese"," mesi"),""),$G$2099),"fuori dal campo del simulatore (foglio 1, riga 8)") -> 49 anni e 9 mesi | C70: =IFERROR(IF($E$2099<>0,"n.d. (fuori scala)",CHOOSE(MOD($C$2099,12)+1,"gennaio","febbraio","marzo","aprile","maggio","giugno","luglio","agosto","settembre","ottobre","novembre","dicembre")&" "&INT($C$2099/12)),"fuori dal campo del simulatore (foglio 1, riga 8)") -> dicembre 2033 | D70: =IFERROR(IF($E$2099<>0,"n.d. (fuori scala)",$I$2708),"fuori dal campo del simulatore (foglio 1, riga 8)") -> 1922.8105 | E70: =IFERROR(IF($E$2099<>0,"n.d. (fuori scala)",$J$2708),"fuori dal campo del simulatore (foglio 1, riga 8)") -> 1510.8233
A71: 67 anni, revisione centrale | B71: =IFERROR(IF($E$2175=0,INT(($C$2175-$B$129)/12)&" anni"&IF(MOD(($C$2175-$B$129),12)>0," e "&MOD(($C$2175-$B$129),12)&IF(MOD(($C$2175-$B$129),12)=1," mese"," mesi"),""),$G$2175),"fuori dal campo del simulatore (foglio 1, riga 8)") -> 50 anni | C71: =IFERROR(IF($E$2175<>0,"n.d. (fuori scala)",CHOOSE(MOD($C$2175,12)+1,"gennaio","febbraio","marzo","aprile","maggio","giugno","luglio","agosto","settembre","ottobre","novembre","dicembre")&" "&INT($C$2175/12)),"fuori dal campo del simulatore (foglio 1, riga 8)") -> marzo 2034 | D71: =IFERROR(IF($E$2175<>0,"n.d. (fuori scala)",$I$2709),"fuori dal campo del simulatore (foglio 1, riga 8)") -> 1835.8199 | E71: =IFERROR(IF($E$2175<>0,"n.d. (fuori scala)",$J$2709),"fuori dal campo del simulatore (foglio 1, riga 8)") -> 1451.1789
A72: Curva RGS 27, a regole di oggi | B72: =IFERROR(IF($E$2251=0,INT(($C$2251-$B$129)/12)&" anni"&IF(MOD(($C$2251-$B$129),12)>0," e "&MOD(($C$2251-$B$129),12)&IF(MOD(($C$2251-$B$129),12)=1," mese"," mesi"),""),$G$2251),"fuori dal campo del simulatore (foglio 1, riga 8)") -> 50 anni | C72: =IFERROR(IF($E$2251<>0,"n.d. (fuori scala)",CHOOSE(MOD($C$2251,12)+1,"gennaio","febbraio","marzo","aprile","maggio","giugno","luglio","agosto","settembre","ottobre","novembre","dicembre")&" "&INT($C$2251/12)),"fuori dal campo del simulatore (foglio 1, riga 8)") -> marzo 2034 | D72: =IFERROR(IF($E$2251<>0,"n.d. (fuori scala)",$I$2710),"fuori dal campo del simulatore (foglio 1, riga 8)") -> 2128.3867 | E72: =IFERROR(IF($E$2251<>0,"n.d. (fuori scala)",$J$2710),"fuori dal campo del simulatore (foglio 1, riga 8)") -> 1655.6209
A73: Curva RGS 27, centrale | B73: =IFERROR(IF($E$2327=0,INT(($C$2327-$B$129)/12)&" anni"&IF(MOD(($C$2327-$B$129),12)>0," e "&MOD(($C$2327-$B$129),12)&IF(MOD(($C$2327-$B$129),12)=1," mese"," mesi"),""),$G$2327),"fuori dal campo del simulatore (foglio 1, riga 8)") -> 50 anni e 4 mesi | C73: =IFERROR(IF($E$2327<>0,"n.d. (fuori scala)",CHOOSE(MOD($C$2327,12)+1,"gennaio","febbraio","marzo","aprile","maggio","giugno","luglio","agosto","settembre","ottobre","novembre","dicembre")&" "&INT($C$2327/12)),"fuori dal campo del simulatore (foglio 1, riga 8)") -> luglio 2034 | D73: =IFERROR(IF($E$2327<>0,"n.d. (fuori scala)",$I$2711),"fuori dal campo del simulatore (foglio 1, riga 8)") -> 2014.8979 | E73: =IFERROR(IF($E$2327<>0,"n.d. (fuori scala)",$J$2711),"fuori dal campo del simulatore (foglio 1, riga 8)") -> 1577.8083
A74: Curva RGS 27, se la revisione accelera | B74: =IFERROR(IF($E$2403=0,INT(($C$2403-$B$129)/12)&" anni"&IF(MOD(($C$2403-$B$129),12)>0," e "&MOD(($C$2403-$B$129),12)&IF(MOD(($C$2403-$B$129),12)=1," mese"," mesi"),""),$G$2403),"fuori dal campo del simulatore (foglio 1, riga 8)") -> 50 anni e 7 mesi | C74: =IFERROR(IF($E$2403<>0,"n.d. (fuori scala)",CHOOSE(MOD($C$2403,12)+1,"gennaio","febbraio","marzo","aprile","maggio","giugno","luglio","agosto","settembre","ottobre","novembre","dicembre")&" "&INT($C$2403/12)),"fuori dal campo del simulatore (foglio 1, riga 8)") -> ottobre 2034 | D74: =IFERROR(IF($E$2403<>0,"n.d. (fuori scala)",$I$2712),"fuori dal campo del simulatore (foglio 1, riga 8)") -> 1939.4217 | E74: =IFERROR(IF($E$2403<>0,"n.d. (fuori scala)",$J$2712),"fuori dal campo del simulatore (foglio 1, riga 8)") -> 1526.0587
A75: Con le tre forze, a regole di oggi | B75: =IFERROR(IF($E$2479=0,INT(($C$2479-$B$129)/12)&" anni"&IF(MOD(($C$2479-$B$129),12)>0," e "&MOD(($C$2479-$B$129),12)&IF(MOD(($C$2479-$B$129),12)=1," mese"," mesi"),""),$G$2479),"fuori dal campo del simulatore (foglio 1, riga 8)") -> 50 anni e 2 mesi | C75: =IFERROR(IF($E$2479<>0,"n.d. (fuori scala)",CHOOSE(MOD($C$2479,12)+1,"gennaio","febbraio","marzo","aprile","maggio","giugno","luglio","agosto","settembre","ottobre","novembre","dicembre")&" "&INT($C$2479/12)),"fuori dal campo del simulatore (foglio 1, riga 8)") -> maggio 2034 | D75: =IFERROR(IF($E$2479<>0,"n.d. (fuori scala)",$I$2713),"fuori dal campo del simulatore (foglio 1, riga 8)") -> 2140.963 | E75: =IFERROR(IF($E$2479<>0,"n.d. (fuori scala)",$J$2713),"fuori dal campo del simulatore (foglio 1, riga 8)") -> 1664.2437
A76: Con le tre forze, centrale | B76: =IFERROR(IF($E$2555=0,INT(($C$2555-$B$129)/12)&" anni"&IF(MOD(($C$2555-$B$129),12)>0," e "&MOD(($C$2555-$B$129),12)&IF(MOD(($C$2555-$B$129),12)=1," mese"," mesi"),""),$G$2555),"fuori dal campo del simulatore (foglio 1, riga 8)") -> 50 anni e 6 mesi | C76: =IFERROR(IF($E$2555<>0,"n.d. (fuori scala)",CHOOSE(MOD($C$2555,12)+1,"gennaio","febbraio","marzo","aprile","maggio","giugno","luglio","agosto","settembre","ottobre","novembre","dicembre")&" "&INT($C$2555/12)),"fuori dal campo del simulatore (foglio 1, riga 8)") -> settembre 2034 | D76: =IFERROR(IF($E$2555<>0,"n.d. (fuori scala)",$I$2714),"fuori dal campo del simulatore (foglio 1, riga 8)") -> 2026.3153 | E76: =IFERROR(IF($E$2555<>0,"n.d. (fuori scala)",$J$2714),"fuori dal campo del simulatore (foglio 1, riga 8)") -> 1585.6366
A77: Con le tre forze, se la revisione accelera | B77: =IFERROR(IF($E$2631=0,INT(($C$2631-$B$129)/12)&" anni"&IF(MOD(($C$2631-$B$129),12)>0," e "&MOD(($C$2631-$B$129),12)&IF(MOD(($C$2631-$B$129),12)=1," mese"," mesi"),""),$G$2631),"fuori dal campo del simulatore (foglio 1, riga 8)") -> 50 anni e 9 mesi | C77: =IFERROR(IF($E$2631<>0,"n.d. (fuori scala)",CHOOSE(MOD($C$2631,12)+1,"gennaio","febbraio","marzo","aprile","maggio","giugno","luglio","agosto","settembre","ottobre","novembre","dicembre")&" "&INT($C$2631/12)),"fuori dal campo del simulatore (foglio 1, riga 8)") -> dicembre 2034 | D77: =IFERROR(IF($E$2631<>0,"n.d. (fuori scala)",$I$2715),"fuori dal campo del simulatore (foglio 1, riga 8)") -> 1950.0672 | E77: =IFERROR(IF($E$2631<>0,"n.d. (fuori scala)",$J$2715),"fuori dal campo del simulatore (foglio 1, riga 8)") -> 1533.3577
A78: Stop minimo = primo mese in cui il patrimonio allo stop regge spesa e imposte fino all'età di fine piano (bisezione in 9 passi fra 40 e 65 anni; fuori da lì il foglio scrive «già ora», «prima dei 40 anni» o «dopo i 65 anni»). Con le tre forze = shock di inflazione e stipendi fermi insieme.
A80: Rinviare volontariamente la prima rata (centrale, stop fisso)
A81: Rinvio | B81: Età alla prima rata | C81: Pensione in più | D81: Anni di incasso per recuperare le rate perse
A82: +12 mesi | B82: =IFERROR(IF(NOT($B$137),"stop fisso fuori campo (foglio 1, riga 8)",INT(($B$134-$B$129-1+12)/12)&" anni"&IF(MOD(($B$134-$B$129-1+12),12)>0," e "&MOD(($B$134-$B$129-1+12),12)&IF(MOD(($B$134-$B$129-1+12),12)=1," mese"," mesi"),"")),"fuori dal campo del simulatore (foglio 1, riga 8)") -> 70 anni e 3 mesi | C82: =IFERROR(IF(NOT($B$137),"stop fisso fuori campo (foglio 1, riga 8)",$F$2719),"fuori dal campo del simulatore (foglio 1, riga 8)") -> 0.038097316 | D82: =IFERROR(IF(NOT($B$137),"stop fisso fuori campo (foglio 1, riga 8)",$G$2719),"fuori dal campo del simulatore (foglio 1, riga 8)") -> 26.248568
A83: +21 mesi | B83: =IFERROR(IF(NOT($B$137),"stop fisso fuori campo (foglio 1, riga 8)",INT(($B$134-$B$129-1+21)/12)&" anni"&IF(MOD(($B$134-$B$129-1+21),12)>0," e "&MOD(($B$134-$B$129-1+21),12)&IF(MOD(($B$134-$B$129-1+21),12)=1," mese"," mesi"),"")),"fuori dal campo del simulatore (foglio 1, riga 8)") -> 71 anni | C83: =IFERROR(IF(NOT($B$137),"stop fisso fuori campo (foglio 1, riga 8)",$F$2720),"fuori dal campo del simulatore (foglio 1, riga 8)") -> 0.06734364 | D83: =IFERROR(IF(NOT($B$137),"stop fisso fuori campo (foglio 1, riga 8)",$G$2720),"fuori dal campo del simulatore (foglio 1, riga 8)") -> 25.986121
A85: Dettaglio della banda scelta in B16
A86: Pensione lorda allo stop fisso (€/mese) | B86: =IFERROR(IF(NOT($B$137),"stop fisso fuori campo (foglio 1, riga 8)",INDEX($B$47:$D$47,MATCH($B$16,{"a regole di oggi","centrale","se la revisione accelera"},0))),"fuori dal campo del simulatore (foglio 1, riga 8)") -> 1987.5786
A87: Costo netto dell'età (mesi di lavoro) | B87: =IFERROR(IF(NOT($B$137),"stop fisso fuori campo (foglio 1, riga 8)",INDEX($B$46:$D$46,MATCH($B$16,{"a regole di oggi","centrale","se la revisione accelera"},0))),"fuori dal campo del simulatore (foglio 1, riga 8)") -> 7.2054319
A88: Le tre forze insieme (mesi di lavoro) | B88: =IFERROR(IF(NOT($B$137),"stop fisso fuori campo (foglio 1, riga 8)",INDEX($B$56:$D$56,MATCH($B$16,{"a regole di oggi","centrale","se la revisione accelera"},0))),"fuori dal campo del simulatore (foglio 1, riga 8)") -> 9.4089775
A89: Stop minimo senza forze | B89: =IFERROR(CHOOSE(MATCH($B$16,{"a regole di oggi","centrale","se la revisione accelera"},0),$B$72,$B$73,$B$74),"fuori dal campo del simulatore (foglio 1, riga 8)") -> 50 anni e 4 mesi
A90: Stop minimo con le tre forze | B90: =IFERROR(CHOOSE(MATCH($B$16,{"a regole di oggi","centrale","se la revisione accelera"},0),$B$75,$B$76,$B$77),"fuori dal campo del simulatore (foglio 1, riga 8)") -> 50 anni e 6 mesi
A100: Motore del calcolo — non modificare
A101: Tutto in euro del 2026. Accumulo mensile dal 1/1/2027, montante con le righe INPS (msg. 707/2026) e le righe future dalla media quinquennale del PIL nominale, coefficiente alla decorrenza con la deriva della banda, decumulo annuo fino all'età di fine piano. Stesse regole del motore dell'analisi (analista/motore.py).
A103: Rendimento reale (foglio 2) | B103: ='2 - Il costo del ponte'!$B$6 -> 0.03
A104: Inflazione dopo il 2026 (foglio 2) | B104: ='2 - Il costo del ponte'!$B$7 -> 0.02
A105: Imposta sulle plusvalenze (foglio 2) | B105: ='2 - Il costo del ponte'!$B$9 -> 0.26
A106: 1 − bollo (foglio 2) | B106: =1-'2 - Il costo del ponte'!$B$10 -> 0.998
A107: Crescita reale annua del portafoglio (1 + r), prima del bollo | B107: =1+$B$103 -> 1.03
A108: Inflazione: la base di costo nominale perde (1 + inflazione) ogni anno in euro reali | B108: =1+$B$104 -> 1.02
A110: Contributi a carico del lavoratore (FPLD) | B110: 0.0919 | C110: INPS: 9,19% della retribuzione
A111: Addizionali regionale e comunale (convenzione del canale) | B111: 0.02 | C111: Convenzione di posso_smettere_02
A112: PIL nominale 2024, milioni (vintage 22/09/2026) | B112: 2210595 | C112: ISTAT, Conti economici nazionali 2010-2025 (22/09/2026)
A113: PIL nominale 2025, milioni (vintage 22/09/2026) | B113: 2265003 | C113: ISTAT, Conti economici nazionali 2010-2025 (22/09/2026)
A114: Crescita del PIL nominale 2020 | B114: -0.078 | C114: ISTAT, Annuario statistico 2021 cap. 12 (usata per stimare la riga 2025 per identità)
A115: PIL reale 2026 (DFP) | B115: 0.006 | C115: Documento di finanza pubblica 2026 (RGS 27 §1.1)
A116: PIL reale medio di lungo periodo | B116: 0.005 | C116: RGS 27 §1.2 p. 42 (0,5% medio 2026-2070)
A117: Assegno sociale 2026 (€/mese) | B117: 546.24 | C117: INPS, circolare n. 153/2025
A118: Multiplo della soglia anticipata fino al 2029 | B118: 3 | C118: Art. 24 c. 11 D.L. 201/2011
A119: Multiplo della soglia anticipata dal 2030 | B119: 3.2 | C119: Art. 24 c. 11 D.L. 201/2011, ultimo periodo
A120: Tasso di sostituzione 2070, coefficienti rivisti | B120: 58.4 | C120: RGS 27, Riquadro 6.1 pp. 184-185
...

Sheet 4 - Le leve
A1: Le leve di Irene: che cosa sposta davvero lo stop
A2: Strumento informativo / divulgativo. NON è consulenza finanziaria. I valori sono indicativi al 2026 e vanno verificati col tuo consulente.
A4: Le leve (celle gialle modificabili)
A5: Spesa: taglio percentuale | B5: 0.1 | C5: Da 22.000 a 19.800 €
A6: Part-time nel ponte: anni | B6: 3 | C6: Nei primi anni dopo lo stop
A7: Part-time: RAL annua | B7: 14000 | C7: Con i contributi al 33%
A8: TFR in azienda incassato allo stop (Sì / No) | B8: Sì | C8: Art. 2120 c.c.: si liquida alla cessazione del rapporto
A9: Aliquota media sul TFR (vuoto = stimata dal foglio) | C9: Tassazione separata, approssimata con l'IRPEF sul reddito di riferimento
A10: Fondo pensione: versamento annuo | B10: 5300 | C10: Limite di deducibilità 2026 (L. 199/2025 art. 1 c. 201, fonti secondarie concordi)
A11: Fondo pensione: aliquota marginale IRPEF | B11: 0.33
A12: Fondo pensione: tassazione della prestazione | B12: 0.15 | C12: Solo l'arbitraggio fiscale, niente altro
A13: Riscatto della laurea agevolato: anni | B13: 5
A14: Riscatto: costo per anno (agevolato 2026) | B14: 6206.64 | C14: INPS, riscatto agevolato 2026: minimale × 33%
A15: Riscatto: aliquota di deduzione | B15: 0.33
A16: Contributi volontari: anni dopo lo stop | B16: 3
A17: Contributi volontari: aliquota sulla RAL 2026 | B17: 0.33
A18: Lavorare fino alla soglia dell'anticipata: quale soglia | B18: proiezione RGS | C18: «proiezione RGS» (componente legata al PIL) o «pavimento» (3,2 volte l'assegno sociale)
A20: Risultati: stop minimo e mesi di anticipo (centrale; gli stop non contano il TFR, salvo la sua leva)
A21: Leva | B21: Stop minimo | C21: Mese | D21: Mesi di anticipo (+ = prima, − = dopo)
A22: Nessuna leva (centrale, dal foglio 3) | B22: =IFERROR(IF('3 - Le tre forze'!$E$2327=0,INT(('3 - Le tre forze'!$C$2327-$B$76)/12)&" anni"&IF(MOD(('3 - Le tre forze'!$C$2327-$B$76),12)>0," e "&MOD(('3 - Le tre forze'!$C$2327-$B$76),12)&IF(MOD(('3 - Le tre forze'!$C$2327-$B$76),12)=1," mese"," mesi"),""),'3 - Le tre forze'!$G$2327),"fuori dal campo del simulatore (foglio 1, riga 8)") -> 50 anni e 4 mesi | C22: =IFERROR(IF('3 - Le tre forze'!$E$2327<>0,"n.d. (fuori scala)",CHOOSE(MOD('3 - Le tre forze'!$C$2327,12)+1,"gennaio","febbraio","marzo","aprile","maggio","giugno","luglio","agosto","settembre","ottobre","novembre","dicembre")&" "&INT('3 - Le tre forze'!$C$2327/12)),"fuori dal campo del simulatore (foglio 1, riga 8)") -> luglio 2034 | D22: =IFERROR(0,"fuori dal campo del simulatore (foglio 1, riga 8)") -> 0
A23: =IFERROR("Spesa −"&ROUND($B$5*100,0)&"% da occupata e da FIRE","fuori dal campo del simulatore (foglio 1, riga 8)") -> Spesa −10% da occupata e da FIRE | B23: =IFERROR(IF($E$101=0,INT(($C$101-$B$76)/12)&" anni"&IF(MOD(($C$101-$B$76),12)>0," e "&MOD(($C$101-$B$76),12)&IF(MOD(($C$101-$B$76),12)=1," mese"," mesi"),""),$G$101),"fuori dal campo del simulatore (foglio 1, riga 8)") -> 48 anni e 6 mesi | C23: =IFERROR(IF($E$101<>0,"n.d. (fuori scala)",CHOOSE(MOD($C$101,12)+1,"gennaio","febbraio","marzo","aprile","maggio","giugno","luglio","agosto","settembre","ottobre","novembre","dicembre")&" "&INT($C$101/12)),"fuori dal campo del simulatore (foglio 1, riga 8)") -> settembre 2032 | D23: =IFERROR(IF(OR('3 - Le tre forze'!$E$2327<>0,$E$101<>0),"non calcolabile: stop fuori scala",'3 - Le tre forze'!$C$2327-$C$101),"fuori dal campo del simulatore (foglio 1, riga 8)") -> 22
A24: =IFERROR("Spesa −"&ROUND($B$5*100,0)&"% solo da FIRE","fuori dal campo del simulatore (foglio 1, riga 8)") -> Spesa −10% solo da FIRE | B24: =IFERROR(IF($E$180=0,INT(($C$180-$B$76)/12)&" anni"&IF(MOD(($C$180-$B$76),12)>0," e "&MOD(($C$180-$B$76),12)&IF(MOD(($C$180-$B$76),12)=1," mese"," mesi"),""),$G$180),"fuori dal campo del simulatore (foglio 1, riga 8)") -> 48 anni e 10 mesi | C24: =IFERROR(IF($E$180<>0,"n.d. (fuori scala)",CHOOSE(MOD($C$180,12)+1,"gennaio","febbraio","marzo","aprile","maggio","giugno","luglio","agosto","settembre","ottobre","novembre","dicembre")&" "&INT($C$180/12)),"fuori dal campo del simulatore (foglio 1, riga 8)") -> gennaio 2033 | D24: =IFERROR(IF(OR('3 - Le tre forze'!$E$2327<>0,$E$180<>0),"non calcolabile: stop fuori scala",'3 - Le tre forze'!$C$2327-$C$180),"fuori dal campo del simulatore (foglio 1, riga 8)") -> 18
A25: TFR in azienda incassato allo stop | B25: =IFERROR(IF($E$259=0,INT(($C$259-$B$76)/12)&" anni"&IF(MOD(($C$259-$B$76),12)>0," e "&MOD(($C$259-$B$76),12)&IF(MOD(($C$259-$B$76),12)=1," mese"," mesi"),""),$G$259),"fuori dal campo del simulatore (foglio 1, riga 8)") -> 48 anni e 11 mesi | C25: =IFERROR(IF($E$259<>0,"n.d. (fuori scala)",CHOOSE(MOD($C$259,12)+1,"gennaio","febbraio","marzo","aprile","maggio","giugno","luglio","agosto","settembre","ottobre","novembre","dicembre")&" "&INT($C$259/12)),"fuori dal campo del simulatore (foglio 1, riga 8)") -> febbraio 2033 | D25: =IFERROR(IF(OR('3 - Le tre forze'!$E$2327<>0,$E$259<>0),"non calcolabile: stop fuori scala",'3 - Le tre forze'!$C$2327-$C$259),"fuori dal campo del simulatore (foglio 1, riga 8)") -> 17
A26: Part-time nei primi anni del ponte | B26: =IFERROR(IF($E$343=0,INT(($C$343-$B$76)/12)&" anni"&IF(MOD(($C$343-$B$76),12)>0," e "&MOD(($C$343-$B$76),12)&IF(MOD(($C$343-$B$76),12)=1," mese"," mesi"),""),$G$343),"fuori dal campo del simulatore (foglio 1, riga 8)") -> 49 anni e 4 mesi | C26: =IFERROR(IF($E$343<>0,"n.d. (fuori scala)",CHOOSE(MOD($C$343,12)+1,"gennaio","febbraio","marzo","aprile","maggio","giugno","luglio","agosto","settembre","ottobre","novembre","dicembre")&" "&INT($C$343/12)),"fuori dal campo del simulatore (foglio 1, riga 8)") -> luglio 2033 | D26: =IFERROR(IF(OR('3 - Le tre forze'!$E$2327<>0,$E$343<>0),"non calcolabile: stop fuori scala",'3 - Le tre forze'!$C$2327-$C$343),"fuori dal campo del simulatore (foglio 1, riga 8)") -> 12
A27: Fondo pensione (solo il vantaggio fiscale) | B27: =IFERROR(IF($E$422=0,INT(($C$422-$B$76)/12)&" anni"&IF(MOD(($C$422-$B$76),12)>0," e "&MOD(($C$422-$B$76),12)&IF(MOD(($C$422-$B$76),12)=1," mese"," mesi"),""),$G$422),"fuori dal campo del simulatore (foglio 1, riga 8)") -> 50 anni e 2 mesi | C27: =IFERROR(IF($E$422<>0,"n.d. (fuori scala)",CHOOSE(MOD($C$422,12)+1,"gennaio","febbraio","marzo","aprile","maggio","giugno","luglio","agosto","settembre","ottobre","novembre","dicembre")&" "&INT($C$422/12)),"fuori dal campo del simulatore (foglio 1, riga 8)") -> maggio 2034 | D27: =IFERROR(IF(OR('3 - Le tre forze'!$E$2327<>0,$E$422<>0),"non calcolabile: stop fuori scala",'3 - Le tre forze'!$C$2327-$C$422),"fuori dal campo del simulatore (foglio 1, riga 8)") -> 2
A28: Riscatto della laurea agevolato | B28: =IFERROR(IF($E$501=0,INT(($C$501-$B$76)/12)&" anni"&IF(MOD(($C$501-$B$76),12)>0," e "&MOD(($C$501-$B$76),12)&IF(MOD(($C$501-$B$76),12)=1," mese"," mesi"),""),$G$501),"fuori dal campo del simulatore (foglio 1, riga 8)") -> 50 anni e 6 mesi | C28: =IFERROR(IF($E$501<>0,"n.d. (fuori scala)",CHOOSE(MOD($C$501,12)+1,"gennaio","febbraio","marzo","aprile","maggio","giugno","luglio","agosto","settembre","ottobre","novembre","dicembre")&" "&INT($C$501/12)),"fuori dal campo del simulatore (foglio 1, riga 8)") -> settembre 2034 | D28: =IFERROR(IF(OR('3 - Le tre forze'!$E$2327<>0,$E$501<>0),"non calcolabile: stop fuori scala",'3 - Le tre forze'!$C$2327-$C$501),"fuori dal campo del simulatore (foglio 1, riga 8)") -> -2
A29: Contributi volontari dopo lo stop | B29: =IFERROR(IF($E$580=0,INT(($C$580-$B$76)/12)&" anni"&IF(MOD(($C$580-$B$76),12)>0," e "&MOD(($C$580-$B$76),12)&IF(MOD(($C$580-$B$76),12)=1," mese"," mesi"),""),$G$580),"fuori dal campo del simulatore (foglio 1, riga 8)") -> 51 anni e 3 mesi | C29: =IFERROR(IF($E$580<>0,"n.d. (fuori scala)",CHOOSE(MOD($C$580,12)+1,"gennaio","febbraio","marzo","aprile","maggio","giugno","luglio","agosto","settembre","ottobre","novembre","dicembre")&" "&INT($C$580/12)),"fuori dal campo del simulatore (foglio 1, riga 8)") -> giugno 2035 | D29: =IFERROR(IF(OR('3 - Le tre forze'!$E$2327<>0,$E$580<>0),"non calcolabile: stop fuori scala",'3 - Le tre forze'!$C$2327-$C$580),"fuori dal campo del simulatore (foglio 1, riga 8)") -> -11
A30: Lavorare fino alla soglia dell'anticipata e uscire con l'anticipata | B30: =IFERROR(IF($E$659=0,INT(($C$659-$B$76)/12)&" anni"&IF(MOD(($C$659-$B$76),12)>0," e "&MOD(($C$659-$B$76),12)&IF(MOD(($C$659-$B$76),12)=1," mese"," mesi"),""),$G$659),"fuori dal campo del simulatore (foglio 1, riga 8)") -> 51 anni e 10 mesi | C30: =IFERROR(IF($E$659<>0,"n.d. (fuori scala)",CHOOSE(MOD($C$659,12)+1,"gennaio","febbraio","marzo","aprile","maggio","giugno","luglio","agosto","settembre","ottobre","novembre","dicembre")&" "&INT($C$659/12)),"fuori dal campo del simulatore (foglio 1, riga 8)") -> gennaio 2036 | D30: =IFERROR(IF(OR('3 - Le tre forze'!$E$2327<>0,$E$659<>0),"non calcolabile: stop fuori scala",'3 - Le tre forze'!$C$2327-$C$659),"fuori dal campo del simulatore (foglio 1, riga 8)") -> -18
A32: Con il TFR: TFR netto allo stop (euro di oggi) | B32: =IFERROR(IF($E$259<>0,"n.d. (fuori scala)",$B$748),"fuori dal campo del simulatore (foglio 1, riga 8)") -> 60743.011 | C32: Gli stop del video non contano il TFR: con il TFR lo stop centrale è quello della riga 25
A33: Con il TFR: aliquota media stimata | B33: =IFERROR(IF($E$259<>0,"n.d. (fuori scala)",$B$746),"fuori dal campo del simulatore (foglio 1, riga 8)") -> 0.27131374
A35: Classifica delle leve (mesi di anticipo, dal più grande)
A36: Posizione | B36: Leva | C36: Mesi di anticipo
A37: 1 | B37: =IFERROR(INDEX($A$23:$A$30,MATCH(LARGE($B$1146:$B$1153,1),$B$1146:$B$1153,0)),"fuori dal campo del simulatore (foglio 1, riga 8)") -> Spesa −10% da occupata e da FIRE | C37: =IFERROR(INDEX($D$23:$D$30,MATCH(LARGE($B$1146:$B$1153,1),$B$1146:$B$1153,0)),"fuori dal campo del simulatore (foglio 1, riga 8)") -> 22
A38: 2 | B38: =IFERROR(INDEX($A$23:$A$30,MATCH(LARGE($B$1146:$B$1153,2),$B$1146:$B$1153,0)),"fuori dal campo del simulatore (foglio 1, riga 8)") -> Spesa −10% solo da FIRE | C38: =IFERROR(INDEX($D$23:$D$30,MATCH(LARGE($B$1146:$B$1153,2),$B$1146:$B$1153,0)),"fuori dal campo del simulatore (foglio 1, riga 8)") -> 18
A39: 3 | B39: =IFERROR(INDEX($A$23:$A$30,MATCH(LARGE($B$1146:$B$1153,3),$B$1146:$B$1153,0)),"fuori dal campo del simulatore (foglio 1, riga 8)") -> TFR in azienda incassato allo stop | C39: =IFERROR(INDEX($D$23:$D$30,MATCH(LARGE($B$1146:$B$1153,3),$B$1146:$B$1153,0)),"fuori dal campo del simulatore (foglio 1, riga 8)") -> 17
A40: 4 | B40: =IFERROR(INDEX($A$23:$A$30,MATCH(LARGE($B$1146:$B$1153,4),$B$1146:$B$1153,0)),"fuori dal campo del simulatore (foglio 1, riga 8)") -> Part-time nei primi anni del ponte | C40: =IFERROR(INDEX($D$23:$D$30,MATCH(LARGE($B$1146:$B$1153,4),$B$1146:$B$1153,0)),"fuori dal campo del simulatore (foglio 1, riga 8)") -> 12
A41: 5 | B41: =IFERROR(INDEX($A$23:$A$30,MATCH(LARGE($B$1146:$B$1153,5),$B$1146:$B$1153,0)),"fuori dal campo del simulatore (foglio 1, riga 8)") -> Fondo pensione (solo il vantaggio fiscale) | C41: =IFERROR(INDEX($D$23:$D$30,MATCH(LARGE($B$1146:$B$1153,5),$B$1146:$B$1153,0)),"fuori dal campo del simulatore (foglio 1, riga 8)") -> 2
A42: 6 | B42: =IFERROR(INDEX($A$23:$A$30,MATCH(LARGE($B$1146:$B$1153,6),$B$1146:$B$1153,0)),"fuori dal campo del simulatore (foglio 1, riga 8)") -> Riscatto della laurea agevolato | C42: =IFERROR(INDEX($D$23:$D$30,MATCH(LARGE($B$1146:$B$1153,6),$B$1146:$B$1153,0)),"fuori dal campo del simulatore (foglio 1, riga 8)") -> -2
A43: 7 | B43: =IFERROR(INDEX($A$23:$A$30,MATCH(LARGE($B$1146:$B$1153,7),$B$1146:$B$1153,0)),"fuori dal campo del simulatore (foglio 1, riga 8)") -> Contributi volontari dopo lo stop | C43: =IFERROR(INDEX($D$23:$D$30,MATCH(LARGE($B$1146:$B$1153,7),$B$1146:$B$1153,0)),"fuori dal campo del simulatore (foglio 1, riga 8)") -> -11
A44: 8 | B44: =IFERROR(INDEX($A$23:$A$30,MATCH(LARGE($B$1146:$B$1153,8),$B$1146:$B$1153,0)),"fuori dal campo del simulatore (foglio 1, riga 8)") -> Lavorare fino alla soglia dell'anticipata e uscire con l'anticipata | C44: =IFERROR(INDEX($D$23:$D$30,MATCH(LARGE($B$1146:$B$1153,8),$B$1146:$B$1153,0)),"fuori dal campo del simulatore (foglio 1, riga 8)") -> -18
A47: Forze contro leve
A48: Le tre forze insieme, centrale (mesi di lavoro, foglio 3) | B48: =IFERROR('3 - Le tre forze'!$C$56,"fuori dal campo del simulatore (foglio 1, riga 8)") -> 9.4089775
A49: La spesa ridotta, da occupata e da FIRE (mesi di anticipo) | B49: =IFERROR($D$23,"fuori dal campo del simulatore (foglio 1, riga 8)") -> 22
A51: Lavorare fino alla soglia dell'anticipata: quanto vale
A52: Stop a cui la pensione anticipata raggiunge la soglia scelta | B52: =IFERROR(IF($E$659=0,INT(($C$659-$B$76)/12)&" anni"&IF(MOD(($C$659-$B$76),12)>0," e "&MOD(($C$659-$B$76),12)&IF(MOD(($C$659-$B$76),12)=1," mese"," mesi"),""),$G$659),"fuori dal campo del simulatore (foglio 1, riga 8)") -> 51 anni e 10 mesi
A53: Pensione anticipata lorda a quello stop (€/mese) | B53: =IFERROR(IF($E$659<>0,"non calcolabile: stop fuori scala",$B$762/13),"fuori dal campo del simulatore (foglio 1, riga 8)") -> 1923.7033
A54: Margine a quello stop con l'anticipata | B54: =IFERROR(IF($E$659<>0,"non calcolabile: stop fuori scala",$E$750),"fuori dal campo del simulatore (foglio 1, riga 8)") -> 98703.588
A55: Margine a quello stop con la sola vecchiaia | B55: =IFERROR(IF($E$659<>0,"non calcolabile: stop fuori scala",$E$827),"fuori dal campo del simulatore (foglio 1, riga 8)") -> 76673.139
A56: Guadagno dell'anticipata (euro) | B56: =IFERROR(IF($E$659<>0,"non calcolabile: stop fuori scala",$E$750-$E$827),"fuori dal campo del simulatore (foglio 1, riga 8)") -> 22030.449
A57: … in mesi di lavoro (foglio 3) | B57: =IFERROR(IF(NOT('3 - Le tre forze'!$B$137),"stop fisso fuori campo (foglio 1, riga 8)",IF($E$659<>0,"non calcolabile: stop fuori scala",($E$750-$E$827)/'3 - Le tre forze'!$B$34)),"fuori dal campo del simulatore (foglio 1, riga 8)") -> 5.4676672
A59: Rendimento reale di pareggio (centrale, senza leve): quanto rendimento compra un anno di lavoro
A60: Stop | B60: Rendimento reale che basta
A61: =IFERROR(IF('3 - Le tre forze'!$E$2327<>0,"n.d. (fuori scala)",INT(($B$905-$B$76)/12)&" anni"&IF(MOD(($B$905-$B$76),12)>0," e "&MOD(($B$905-$B$76),12)&IF(MOD(($B$905-$B$76),12)=1," mese"," mesi"),"")),"fuori dal campo del simulatore (foglio 1, riga 8)") -> 50 anni e 4 mesi | B61: =IFERROR(IF('3 - Le tre forze'!$E$2327<>0,"non calcolabile: stop fuori scala",$X$921),"fuori dal campo del simulatore (foglio 1, riga 8)") -> 0.029521156
A62: =IFERROR(IF('3 - Le tre forze'!$E$2327<>0,"n.d. (fuori scala)",INT(($B$985-$B$76)/12)&" anni"&IF(MOD(($B$985-$B$76),12)>0," e "&MOD(($B$985-$B$76),12)&IF(MOD(($B$985-$B$76),12)=1," mese"," mesi"),"")),"fuori dal campo del simulatore (foglio 1, riga 8)") -> 51 anni e 4 mesi | B62: =IFERROR(IF('3 - Le tre forze'!$E$2327<>0,"non calcolabile: stop fuori scala",$X$1001),"fuori dal campo del simulatore (foglio 1, riga 8)") -> 0.020950648
A63: =IFERROR(IF('3 - Le tre forze'!$E$2327<>0,"n.d. (fuori scala)",INT(($B$1065-$B$76)/12)&" anni"&IF(MOD(($B$1065-$B$76),12)>0," e "&MOD(($B$1065-$B$76),12)&IF(MOD(($B$1065-$B$76),12)=1," mese"," mesi"),"")),"fuori dal campo del simulatore (foglio 1, riga 8)") -> 52 anni e 4 mesi | B63: =IFERROR(IF('3 - Le tre forze'!$E$2327<>0,"non calcolabile: stop fuori scala",$X$1081),"fuori dal campo del simulatore (foglio 1, riga 8)") -> 0.011763004
A66: Motore del calcolo — non modificare
A67: Ogni leva: bisezione in 9 passi sullo stop minimo (fra 40 e 65 anni), scenario centrale. Accumulo, montante e coefficienti dal motore del foglio 3.
A69: Rendimento reale (foglio 2) | B69: ='2 - Il costo del ponte'!$B$6 -> 0.03
A70: Inflazione dopo il 2026 (foglio 2) | B70: ='2 - Il costo del ponte'!$B$7 -> 0.02
A71: Imposta sulle plusvalenze (foglio 2) | B71: ='2 - Il costo del ponte'!$B$9 -> 0.26
A72: 1 − bollo (foglio 2) | B72: =1-'2 - Il costo del ponte'!$B$10 -> 0.998
A73: Crescita reale annua del portafoglio (1 + r), prima del bollo | B73: =1+$B$69 -> 1.03
A74: Inflazione: la base di costo nominale perde (1 + inflazione) ogni anno in euro reali | B74: =1+$B$70 -> 1.02
A76: Mese di nascita | B76: ='3 - Le tre forze'!$B$129 -> 23810
A77: Mese di fine piano | B77: ='3 - Le tre forze'!$B$132 -> 24914
A78: Gennaio 2027 | B78: ='3 - Le tre forze'!$B$133 -> 24324
A79: Prima rata vecchiaia (RGS 27) | B79: ='3 - Le tre forze'!$B$134 -> 24642
A80: Decorrenza anticipata | B80: ='3 - Le tre forze'!$B$136 -> 24606
A81: Spesa annua | B81: ='3 - Le tre forze'!$B$8 -> 22000
A82: Addizionali | B82: ='3 - Le tre forze'!$B$111 -> 0.02
A83: Contributi a carico del lavoratore | B83: ='3 - Le tre forze'!$B$110 -> 0.0919
A84: Aliquota IVS | B84: ='3 - Le tre forze'!$B$10 -> 0.33
A85: RAL 2026 | B85: ='3 - Le tre forze'!$B$6 -> 53000
A86: Anno del primo contributo | B86: ='3 - Le tre forze'!$B$7 -> 2009
A87: Montante → pensione, vecchiaia centrale | B87: ='3 - Le tre forze'!$C$737*'3 - Le tre forze'!$J$153 -> 0.087272429
A88: Montante → pensione, anticipata centrale | B88: ='3 - Le tre forze'!$C$739*'3 - Le tre forze'!$J$158 -> 0.078545955
A89: Coefficiente dell'anticipata (centrale) | B89: ='3 - Le tre forze'!$J$158 -> 0.051892051
A90: Part-time: imponibile | B90: =$B$7*(1-$B$83) -> 12713.4
A91: Part-time: netto annuo | B91: =$B$90*(1-$B$82)-MAX(0,IF($B$90<=28000,0.23*$B$90,IF($B$90<=50000,6440+0.33*($B$90-28000),13700+0.43*($B$90-50000)))-(IF($B$90<=15000,1955,IF($B$90<=28000,1910+1190*(28000-$B$90)/13000,IF($B$90<=50000,1910*(50000-$B$90)/22000,0)))+IF(AND($B$90>25000,$B$90<=35000),65,0))-IF(AND($B$90>20000,$B$90<=32000),1000,IF(AND($B$90>32000,$B$90<=40000),1000*(40000-$B$90)/8000,0))) -> 11490.05
A92: Part-time: contributi annui (reali) | B92: =$B$84*$B$7 -> 4620
A93: Riscatto: costo totale | B93: =$B$13*$B$14 -> 31033.2
A94: Contributi volontari annui (reali) | B94: =$B$17*$B$85 -> 17490
A95: Spesa ridotta: risparmio mensile in più | B95: =$B$81*$B$5/12 -> 183.33333
A96: Fondo pensione: vantaggio fiscale mensile | B96: =$B$10*($B$11-$B$12)/12 -> 79.5
A97: Soglia 2050 se morde la proiezione RGS (€/mese) | B97: ='5 - La manovra'!$B$32 -> 1919.7375
A98: Soglia 2050, pavimento (€/mese) | B98: ='5 - La manovra'!$B$30 -> 1747.968
A99: Soglia scelta in B18 | B99: =IF($B$18="pavimento",$B$98,$B$97) -> 1919.7375
A101: Stop minimo — Spesa ridotta da occupata e da FIRE | B101: Stop minimo (indice): | C101: =IF($AQ$123,$AQ$104,$AQ$103) -> 24392 | D101: Stato (0 = dentro la scala 40-65 anni): | E101: =IF($B$76+780<$B$78,2,IF($C$101<=$C$102+1,-1,IF($C$101>=$B$76+781,1,0))) -> 0 | F101: Messaggio: | G101: =CHOOSE($E$101+2,IF($C$102+1<$B$78,"già ora (prima di gennaio 2027)",IF($C$102+1=$B$78,"già ora (da gennaio 2027)","prima dei 40 anni")),"dentro la scala","dopo i 65 anni (fuori scala)","fuori scala: i 65 anni cadono prima del 2027") -> dentro la scala
A102: Estremo basso (non sostenibile) | C102: =MAX($B$76+478,$B$78-2) -> 24322 | H102: =IF($C$123,$C$102,$C$104) -> 24322 | M102: =IF($H$123,$H$102,$H$104) -> 24389 | R102: =IF($M$123,$M$102,$M$104) -> 24389 | W102: =IF($R$123,$R$102,$R$104) -> 24389 | AB102: =IF($W$123,$W$102,$W$104) -> 24389 | AG102: =IF($AB$123,$AB$102,$AB$104) -> 24389 | AL102: =IF($AG$123,$AG$102,$AG$104) -> 24391 | AQ102: =IF($AL$123,$AL$102,$AL$104) -> 24391
A103: Estremo alto (sostenibile) | C103: =MAX($B$76+781,$C$102+3) -> 24591 | H103: =IF($C$123,$C$104,$C$103) -> 24456 | M103: =IF($H$123,$H$104,$H$103) -> 24456 | R103: =IF($M$123,$M$104,$M$103) -> 24422 | W103: =IF($R$123,$R$104,$R$103) -> 24405 | AB103: =IF($W$123,$W$104,$W$103) -> 24397 | AG103: =IF($AB$123,$AB$104,$AB$103) -> 24393 | AL103: =IF($AG$123,$AG$104,$AG$103) -> 24393 | AQ103: =IF($AL$123,$AL$104,$AL$103) -> 24392
A104: Candidato: mese di stop (indice) | C104: =INT(($C$102+$C$103)/2) -> 24456 | H104: =INT(($H$102+$H$103)/2) -> 24389 | M104: =INT(($M$102+$M$103)/2) -> 24422 | R104: =INT(($R$102+$R$103)/2) -> 24405 | W104: =INT(($W$102+$W$103)/2) -> 24397 | AB104: =INT(($AB$102+$AB$103)/2) -> 24393 | AG104: =INT(($AG$102+$AG$103)/2) -> 24391 | AL104: =INT(($AL$102+$AL$103)/2) -> 24392 | AQ104: =INT(($AQ$102+$AQ$103)/2) -> 24391
A105: Mesi di accumulo dal 1/1/2027 | C105: =MAX(0,$C$104-$B$78) -> 132 | H105: =MAX(0,$H$104-$B$78) -> 65 | M105: =MAX(0,$M$104-$B$78) -> 98 | R105: =MAX(0,$R$104-$B$78) -> 81 | W105: =MAX(0,$W$104-$B$78) -> 73 | AB105: =MAX(0,$AB$104-$B$78) -> 69 | AG105: =MAX(0,$AG$104-$B$78) -> 67 | AL105: =MAX(0,$AL$104-$B$78) -> 68 | AQ105: =MAX(0,$AQ$104-$B$78) -> 67
A106: Anno dello stop | C106: =INT($C$104/12) -> 2038 | H106: =INT($H$104/12) -> 2032 | M106: =INT($M$104/12) -> 2035 | R106: =INT($R$104/12) -> 2033 | W106: =INT($W$104/12) -> 2033 | AB106: =INT($AB$104/12) -> 2032 | AG106: =INT($AG$104/12) -> 2032 | AL106: =INT($AL$104/12) -> 2032 | AQ106: =INT($AQ$104/12) -> 2032
A107: Frazione dell'anno lavorata | C107: =MOD($C$104,12)/12 -> 0 | H107: =MOD($H$104,12)/12 -> 0.41666667 | M107: =MOD($M$104,12)/12 -> 0.16666667 | R107: =MOD($R$104,12)/12 -> 0.75 | W107: =MOD($W$104,12)/12 -> 0.083333333 | AB107: =MOD($AB$104,12)/12 -> 0.75 | AG107: =MOD($AG$104,12)/12 -> 0.58333333 | AL107: =MOD($AL$104,12)/12 -> 0.66666667 | AQ107: =MOD($AQ$104,12)/12 -> 0.58333333
A108: Versamento mensile in più (o in meno) | C108: =$B$95 -> 183.33333 | H108: =$B$95 -> 183.33333 | M108: =$B$95 -> 183.33333 | R108: =$B$95 -> 183.33333 | W108: =$B$95 -> 183.33333 | AB108: =$B$95 -> 183.33333 | AG108: =$B$95 -> 183.33333 | AL108: =$B$95 -> 183.33333 | AQ108: =$B$95 -> 183.33333
A109: Patrimonio allo stop (euro 2026) | C109: =INDEX('3 - Le tre forze'!$F$242:$F$734,$C$105+1)+$C$108*INDEX('3 - Le tre forze'!$N$242:$N$734,$C$105+1) -> 529983.41 | H109: =INDEX('3 - Le tre forze'!$F$242:$F$734,$H$105+1)+$H$108*INDEX('3 - Le tre forze'!$N$242:$N$734,$H$105+1) -> 379729.25 | M109: =INDEX('3 - Le tre forze'!$F$242:$F$734,$M$105+1)+$M$108*INDEX('3 - Le tre forze'!$N$242:$N$734,$M$105+1) -> 450848.46 | R109: =INDEX('3 - Le tre forze'!$F$242:$F$734,$R$105+1)+$R$108*INDEX('3 - Le tre forze'!$N$242:$N$734,$R$105+1) -> 413538.56 | W109: =INDEX('3 - Le tre forze'!$F$242:$F$734,$W$105+1)+$W$108*INDEX('3 - Le tre forze'!$N$242:$N$734,$W$105+1) -> 396478.63 | AB109: =INDEX('3 - Le tre forze'!$F$242:$F$734,$AB$105+1)+$AB$108*INDEX('3 - Le tre forze'!$N$242:$N$734,$AB$105+1) -> 388065.48 | AG109: =INDEX('3 - Le tre forze'!$F$242:$F$734,$AG$105+1)+$AG$108*INDEX('3 - Le tre forze'!$N$242:$N$734,$AG$105+1) -> 383887.79 | AL109: =INDEX('3 - Le tre forze'!$F$242:$F$734,$AL$105+1)+$AL$108*INDEX('3 - Le tre forze'!$N$242:$N$734,$AL$105+1) -> 385974.24 | AQ109: =INDEX('3 - Le tre forze'!$F$242:$F$734,$AQ$105+1)+$AQ$108*INDEX('3 - Le tre forze'!$N$242:$N$734,$AQ$105+1) -> 383887.79
A110: Base di costo nominale | C110: =INDEX('3 - Le tre forze'!$J$242:$J$734,$C$105+1)+$C$108*INDEX('3 - Le tre forze'!$O$242:$O$734,$C$105+1) -> 344589.21 | H110: =INDEX('3 - Le tre forze'!$J$242:$J$734,$H$105+1)+$H$108*INDEX('3 - Le tre forze'!$O$242:$O$734,$H$105+1) -> 249566.49 | M110: =INDEX('3 - Le tre forze'!$J$242:$J$734,$M$105+1)+$M$108*INDEX('3 - Le tre forze'!$O$242:$O$734,$M$105+1) -> 295056.44 | R110: =INDEX('3 - Le tre forze'!$J$242:$J$734,$R$105+1)+$R$108*INDEX('3 - Le tre forze'!$O$242:$O$734,$R$105+1) -> 271312.96 | W110: =INDEX('3 - Le tre forze'!$J$242:$J$734,$W$105+1)+$W$108*INDEX('3 - Le tre forze'!$O$242:$O$734,$W$105+1) -> 260367.95 | AB110: =INDEX('3 - Le tre forze'!$J$242:$J$734,$AB$105+1)+$AB$108*INDEX('3 - Le tre forze'!$O$242:$O$734,$AB$105+1) -> 254949.4 | AG110: =INDEX('3 - Le tre forze'!$J$242:$J$734,$AG$105+1)+$AG$108*INDEX('3 - Le tre forze'!$O$242:$O$734,$AG$105+1) -> 252253.51 | AL110: =INDEX('3 - Le tre forze'!$J$242:$J$734,$AL$105+1)+$AL$108*INDEX('3 - Le tre forze'!$O$242:$O$734,$AL$105+1) -> 253600.34 | AQ110: =INDEX('3 - Le tre forze'!$J$242:$J$734,$AQ$105+1)+$AQ$108*INDEX('3 - Le tre forze'!$O$242:$O$734,$AQ$105+1) -> 252253.51
A111: Plusvalenza latente allo stop | C111: =MAX(0,1-$C$110/($C$109*INDEX('3 - Le tre forze'!$D$242:$D$734,$C$105+1))) -> 0.47707729 | H111: =MAX(0,1-$H$110/($H$109*INDEX('3 - Le tre forze'!$D$242:$D$734,$H$105+1))) -> 0.409625 | M111: =MAX(0,1-$M$110/($M$109*INDEX('3 - Le tre forze'!$D$242:$D$734,$M$105+1))) -> 0.44327622 | R111: =MAX(0,1-$R$110/($R$109*INDEX('3 - Le tre forze'!$D$242:$D$734,$R$105+1))) -> 0.42601127 | W111: =MAX(0,1-$W$110/($W$109*INDEX('3 - Le tre forze'!$D$242:$D$734,$W$105+1))) -> 0.41782972 | AB111: =MAX(0,1-$AB$110/($AB$109*INDEX('3 - Le tre forze'!$D$242:$D$734,$AB$105+1))) -> 0.41372956 | AG111: =MAX(0,1-$AG$110/($AG$109*INDEX('3 - Le tre forze'!$D$242:$D$734,$AG$105+1))) -> 0.41167774 | AL111: =MAX(0,1-$AL$110/($AL$109*INDEX('3 - Le tre forze'!$D$242:$D$734,$AL$105+1))) -> 0.41270378 | AQ111: =MAX(0,1-$AQ$110/($AQ$109*INDEX('3 - Le tre forze'!$D$242:$D$734,$AQ$105+1))) -> 0.41167774
A112: Patrimonio allo stop | C112: =$C$109 -> 529983.41 | H112: =$H$109 -> 379729.25 | M112: =$M$109 -> 450848.46 | R112: =$R$109 -> 413538.56 | W112: =$W$109 -> 396478.63 | AB112: =$AB$109 -> 388065.48 | AG112: =$AG$109 -> 383887.79 | AL112: =$AL$109 -> 385974.24 | AQ112: =$AQ$109 -> 383887.79
A113: Plusvalenza latente | C113: =$C$111 -> 0.47707729 | H113: =$H$111 -> 0.409625 | M113: =$M$111 -> 0.44327622 | R113: =$R$111 -> 0.42601127 | W113: =$W$111 -> 0.41782972 | AB113: =$AB$111 -> 0.41372956 | AG113: =$AG$111 -> 0.41167774 | AL113: =$AL$111 -> 0.41270378 | AQ113: =$AQ$111 -> 0.41167774
...

Sheet 5 - La manovra
A1: La manovra 2027 e la soglia dell'anticipata: che cosa cambia per Irene
A2: Strumento informativo / divulgativo. NON è consulenza finanziaria. I valori sono indicativi al 2026 e vanno verificati col tuo consulente.
A4: Stato delle proposte al 29/09/2026 (fonti secondarie datate; il Documento programmatico di finanza pubblica è atteso entro il 02/10: da riscrivere il giorno prima della narrazione)
A5: Proposta | B5: Chi, quando (fonte) | C5: Stato | D5: Effetto su Irene (mesi di anticipo) | E5: Perché
A6: Sterilizzare il mese di aumento del 2027 | B6: Lega; circa 1,1 miliardi (Il Messaggero 07/09); forse selettiva (BusinessOnline 20/09, fiducia bassa) | C6: proposta | D6: =IFERROR($B$79-$B$183,"fuori dal campo del simulatore (foglio 1, riga 8)") -> 0 | E6: La prima rata non cambia: il mese del 2027 non tocca chi matura nel 2053
A7: Quota 64 per il sistema misto, con ricalcolo contributivo | B7: Durigon 09-10/09 (Il Giornale, QuiFinanza); Salvini a Pontida 20/09 (ANSA); Durigon 26/09: «puntiamo a quota 64» (ANSA) | C7: ipotesi, nessun testo (aPensione 02/09) | D7: =IFERROR(IF($B$83>=1996,0,"non calcolato: sistema misto"),"fuori dal campo del simulatore (foglio 1, riga 8)") -> 0 | E7: Riguarda il sistema misto: Irene è nel contributivo puro
A8: TFR in rendita per raggiungere la soglia | B8: Schema di quota 64 (QuiFinanza 09/09; Virgilio 07/09; CGIL, Il Fatto Quotidiano 07/09); «il meccanismo non è definito» (aPensione 02/09) | C8: ipotesi | D8: =IFERROR($B$46,"fuori dal campo del simulatore (foglio 1, riga 8)") -> 0 | E8: Il TFR in azienda si liquida alla cessazione del rapporto (art. 2120 c.c.): Irene lo incassa sedici anni prima della soglia
A9: Soglia ridotta o annullata per chi è senza lavoro | B9: Durigon 17/09 (ANSA) | C9: ipotesi | D9: =IFERROR(IF(OR('3 - Le tre forze'!$E$2327<>0,$E$273<>0),"non calcolabile: stop fuori scala",$B$89-$C$273),"fuori dal campo del simulatore (foglio 1, riga 8)") -> 5 | E9: Se valesse per i contributivi puri: anticipata a 66 anni e 3 mesi
A10: Quota 41 flessibile | B10: Lega (Il Messaggero 07/09) | C10: nessun testo | D10: =IFERROR(IF('3 - Le tre forze'!$E$2327<>0,"non calcolabile: stop fuori scala",IF(($B$89-12*$B$83)/12<41,0,"non calcolato: 41 anni di contributi raggiunti")),"fuori dal campo del simulatore (foglio 1, riga 8)") -> 0 | E10: Servono 41 anni di contributi: Irene ne avrà circa 25
A11: Pensioni minime a 700-800 € | B11: Tajani (Il Messaggero 07/09) | C11: proposta | D11: =IFERROR(IF($B$83>=1996,0,"non calcolato: sistema misto"),"fuori dal campo del simulatore (foglio 1, riga 8)") -> 0 | E11: Niente integrazione al minimo nel contributivo puro (L. 335/1995 art. 1 c. 16)
A12: Blocco strutturale dell'età a 67 anni | B12: nessuno | C12: — | D12: =IFERROR(IF(OR('3 - Le tre forze'!$E$2327<>0,'3 - Le tre forze'!$E$2175<>0),"non calcolabile: stop fuori scala",$B$89-$B$90),"fuori dal campo del simulatore (foglio 1, riga 8)") -> 4 | E12: La revisione dei coefficienti continuerebbe (foglio 3, mondo «67 anni, revisione centrale»)
A13: Anche se passasse tutto, al massimo (mesi di anticipo) | D13: =IFERROR(IF(SUMPRODUCT(--ISTEXT($D$6:$D$12))>0,"non calcolabile: una riga non ha un numero",MAX($D$6:$D$12)),"fuori dal campo del simulatore (foglio 1, riga 8)") -> 5
A14: Calendario: Documento programmatico di finanza pubblica atteso entro il 02/10, Documento programmatico di bilancio entro il 15/10, DDL alle Camere entro il 20/10 (L. 196/2009 art. 7), legge entro il 31/12. Già legge: 67 anni e 1 mese nel 2027, 67 anni e 3 mesi nel 2028 (L. 199/2025 c. 185; INPS circ. 28/2026).
A16: La tua manovra (celle gialle)
A17: Requisito di vecchiaia nel 2027 | B17: 67 anni e 1 mese
A18: Età di vecchiaia bloccata a 67 anni dall'anno (vuoto = nessun blocco)
A19: Soglia dell'anticipata contributiva | B19: proiezione RGS | C19: «proiezione RGS»: la più alta fra componente legata al PIL e pavimento; «pavimento»: 3,2 volte l'assegno sociale; «nessuna soglia»: la proposta per chi è senza lavoro
A20: Il TFR vale per raggiungere la soglia (Sì / No) | B20: No
A21: Il tuo TFR è ancora da liquidare quando chiedi la pensione (Sì / No) | B21: No | C21: Chi lascia il lavoro incassa il TFR alla cessazione: per Irene è «No». Con «Sì» e «Sì» il foglio converte in rendita, alla decorrenza dell'anticipata, il capitale che manca alla soglia: quei soldi escono dal portafoglio e non finanziano più il ponte (effetto teorico: il TFR a Irene non serve)
A22: Prima rata di vecchiaia con la tua manovra | B22: =IFERROR("1° "&CHOOSE(MOD($B$181,12)+1,"gennaio","febbraio","marzo","aprile","maggio","giugno","luglio","agosto","settembre","ottobre","novembre","dicembre")&" "&INT($B$181/12)&", a "&INT(($B$180-$B$76)/12)&" anni"&IF(MOD(($B$180-$B$76),12)>0," e "&MOD(($B$180-$B$76),12)&IF(MOD(($B$180-$B$76),12)=1," mese"," mesi"),""),"fuori dal campo del simulatore (foglio 1, riga 8)") -> 1° luglio 2053, a 69 anni e 3 mesi
A23: Stop minimo con la tua manovra | B23: =IFERROR(IF($E$188=0,INT(($C$188-$B$76)/12)&" anni"&IF(MOD(($C$188-$B$76),12)>0," e "&MOD(($C$188-$B$76),12)&IF(MOD(($C$188-$B$76),12)=1," mese"," mesi"),"")&", "&CHOOSE(MOD($C$188,12)+1,"gennaio","febbraio","marzo","aprile","maggio","giugno","luglio","agosto","settembre","ottobre","novembre","dicembre")&" "&INT($C$188/12),$G$188),"fuori dal campo del simulatore (foglio 1, riga 8)") -> 50 anni e 4 mesi, luglio 2034
A24: Canale di uscita | B24: =IFERROR(IF($E$188<>0,"n.d. (fuori scala)",IF($B$440,IF(AND($B$103,$B$439<$B$102),"anticipata contributiva, con capitale proprio convertito (teorico)","anticipata contributiva"),"vecchiaia")),"fuori dal campo del simulatore (foglio 1, riga 8)") -> vecchiaia
A25: Differenza sulle regole di oggi (mesi di anticipo) | B25: =IFERROR(IF(OR('3 - Le tre forze'!$E$2327<>0,$E$188<>0),"non calcolabile: stop fuori scala",$B$89-$C$188),"fuori dal campo del simulatore (foglio 1, riga 8)") -> 0
A27: La soglia dell'anticipata nel 2050 (euro di oggi): pavimento e proiezione RGS
A28: Anticipata di Irene: decorrenza | B28: =IFERROR("1° "&CHOOSE(MOD($B$80,12)+1,"gennaio","febbraio","marzo","aprile","maggio","giugno","luglio","agosto","settembre","ottobre","novembre","dicembre")&" "&INT($B$80/12)&", a "&INT(($B$80-$B$76-1)/12)&" anni"&IF(MOD(($B$80-$B$76-1),12)>0," e "&MOD(($B$80-$B$76-1),12)&IF(MOD(($B$80-$B$76-1),12)=1," mese"," mesi"),""),"fuori dal campo del simulatore (foglio 1, riga 8)") -> 1° luglio 2050, a 66 anni e 3 mesi
A29: Assegno sociale 2026 (€/mese; in euro di oggi resta uguale) | B29: =IFERROR($B$84,"fuori dal campo del simulatore (foglio 1, riga 8)") -> 546.24 | C29: INPS, circolare n. 153/2025 (assegno sociale 2026: 546,24 €), dato del motore del foglio 3
A30: Pavimento: 3,2 volte l'assegno sociale (€/mese) | B30: =IFERROR($B$93,"fuori dal campo del simulatore (foglio 1, riga 8)") -> 1747.968 | C30: Art. 24 c. 11 D.L. 201/2011: dal 2030 3,2 volte l'assegno sociale (lo stesso numero di pensione_64_soglia)
A31: Componente legata al PIL: proiezione RGS (€/mese) | B31: =IFERROR($B$92,"fuori dal campo del simulatore (foglio 1, riga 8)") -> 1919.7375 | C31: RGS 27, Tab. A1.5 nota (****): 1.638,72 € nel 2026 rivalutati con la media quinquennale del PIL nominale; è una proiezione, non la norma
A32: Soglia se morde la proiezione RGS (la più alta delle due) | B32: =IFERROR(MAX($B$30,$B$31),"fuori dal campo del simulatore (foglio 1, riga 8)") -> 1919.7375
A33: Pensione anticipata di Irene allo stop minimo centrale (€/mese lordi) | B33: =IFERROR(IF('3 - Le tre forze'!$E$2327<>0,"non calcolabile: stop fuori scala",$B$97),"fuori dal campo del simulatore (foglio 1, riga 8)") -> 1813.4259
A34: … in % della proiezione RGS | B34: =IFERROR(IF('3 - Le tre forze'!$E$2327<>0,"non calcolabile: stop fuori scala",$B$33/$B$32),"fuori dal campo del simulatore (foglio 1, riga 8)") -> 0.9446218
A35: … in % del pavimento | B35: =IFERROR(IF('3 - Le tre forze'!$E$2327<>0,"non calcolabile: stop fuori scala",$B$33/$B$30),"fuori dal campo del simulatore (foglio 1, riga 8)") -> 1.037448
A36: La soglia scelta nel foglio 4 si raggiunge lavorando fino a | B36: =IFERROR('4 - Le leve'!$B$52,"fuori dal campo del simulatore (foglio 1, riga 8)") -> 51 anni e 10 mesi
A37: Controllo a uno stop a scelta: anni | B37: 51
A38: … più mesi | B38: 0
A39: Pensione anticipata a quello stop (€/mese lordi) | B39: =IFERROR($B$101,"fuori dal campo del simulatore (foglio 1, riga 8)") -> 1862.54
A40: … in % della proiezione RGS | B40: =IFERROR($B$39/$B$32,"fuori dal campo del simulatore (foglio 1, riga 8)") -> 0.97020556
A41: … in % del pavimento | B41: =IFERROR($B$39/$B$30,"fuori dal campo del simulatore (foglio 1, riga 8)") -> 1.0655458
A43: Il TFR per la soglia
A44: Allo stop minimo centrale mancano (€/mese lordi, proiezione RGS) | B44: =IFERROR(IF('3 - Le tre forze'!$E$2327<>0,"non calcolabile: stop fuori scala",MAX(0,$B$32-$B$33)),"fuori dal campo del simulatore (foglio 1, riga 8)") -> 106.31161
A45: Capitale da convertire in rendita per colmarli (euro di oggi) | B45: =IFERROR(IF('3 - Le tre forze'!$E$2327<>0,"non calcolabile: stop fuori scala",$B$44*13/$B$88),"fuori dal campo del simulatore (foglio 1, riga 8)") -> 26633.191
A46: Effetto su Irene (mesi di anticipo; con «Sì / Sì» è un effetto teorico: il TFR a Irene non serve) | B46: =IFERROR(IF(NOT($B$103),0,IF(OR('3 - Le tre forze'!$E$2327<>0,$E$352<>0),"non calcolabile: stop fuori scala",$B$89-$C$352)),"fuori dal campo del simulatore (foglio 1, riga 8)") -> 0
A47: Se valesse il capitale proprio convertito alla decorrenza, stop minimo (effetto teorico) | B47: =IFERROR(IF($E$352<>0,$G$352,INT(($C$352-$B$76)/12)&" anni"&IF(MOD(($C$352-$B$76),12)>0," e "&MOD(($C$352-$B$76),12)&IF(MOD(($C$352-$B$76),12)=1," mese"," mesi"),"")&IF('3 - Le tre forze'!$E$2327=0," ("&TEXT($B$89-$C$352,"+0;-0;0")&IF(ABS($B$89-$C$352)=1," mese"," mesi")&" sulle regole di oggi)"," (confronto non calcolabile: stop centrale fuori scala)")),"fuori dal campo del simulatore (foglio 1, riga 8)") -> 50 anni e 1 mese (+3 mesi sulle regole di oggi)
A48: Con le celle B20-B21 a «No» l'effetto è zero: il TFR in azienda si liquida alla cessazione del rapporto e Irene lo avrà incassato sedici anni prima della soglia.
A49: La soglia della vecchiaia (1 volta l'assegno sociale, componente PIL), anno della prima rata
A50: Soglia della vecchiaia (€/mese, euro di oggi) | B50: =IFERROR(MAX($B$95,$B$84),"fuori dal campo del simulatore (foglio 1, riga 8)") -> 649.55926
A51: Pensione di vecchiaia allo stop minimo centrale (€/mese lordi) | B51: =IFERROR(IF('3 - Le tre forze'!$E$2327<>0,"non calcolabile: stop fuori scala",'3 - Le tre forze'!$I$2711),"fuori dal campo del simulatore (foglio 1, riga 8)") -> 2014.8979
A52: Volte la soglia | B52: =IFERROR(IF('3 - Le tre forze'!$E$2327<>0,"non calcolabile: stop fuori scala",$B$51/$B$50),"fuori dal campo del simulatore (foglio 1, riga 8)") -> 3.1019463
A54: Le mie previsioni (da verificare: compila «Com'è andata»)
A55: # | B55: Previsione | C55: Presa se | D55: Mancata se | E55: Quando si verifica | F55: Probabilità (mia) | G55: Com'è andata
A56: P1 | B56: Il DDL non porta la vecchiaia 2027 a 67 anni per la generalità dei lavoratori | C56: Il testo trasmesso lascia 67 anni e 1 mese per la generalità (esenzioni di categoria ammesse) | D56: Il testo fissa 67 anni per tutti nel 2027 | E56: DDL trasmesso alle Camere (entro il 20/10; se in ritardo, alla trasmissione) | F56: 55%
A57: P2 | B57: Nessuna modifica al meccanismo degli adeguamenti dal 2029 | C57: La legge pubblicata non modifica l'art. 12 c. 12-bis D.L. 78/2010 né l'art. 24 c. 13 D.L. 201/2011 e non vi deroga per gli adeguamenti dal 1/1/2029 | D57: Qualunque modifica o deroga testuale per quegli adeguamenti | E57: Legge in Gazzetta Ufficiale | F57: 90%
A58: P4 | B58: La soglia dell'anticipata contributiva non viene abolita né ridotta per la generalità dei contributivi puri | C58: Art. 24 c. 11: multipli 3,0 / 3,2 invariati per la generalità (categorie ammesse) | D58: Abolita o ridotta per tutti | E58: Legge in Gazzetta Ufficiale | F58: 75%
A59: P5 | B59: Quota 41 flessibile non entra | C59: Assente in ogni forma | D59: Presente in qualunque forma | E59: Legge in Gazzetta Ufficiale | F59: 75%
A60: P6 | B60: Se entra l'uso del TFR per la soglia, vale solo per il TFR non liquidato alla domanda di pensione | C60: La norma è riferita al TFR maturato e non liquidato (presso il datore o il Fondo di Tesoreria) alla data della domanda | D60: La norma consente di computare TFR già liquidato o capitale versato di tasca propria | E60: Legge in Gazzetta Ufficiale. Se la norma non c'è, la previsione è annullata (non valutabile) | F60: condizionale
A61: P7 | B61: La circolare INPS di inizio 2027 fissa la soglia dell'anticipata contributiva a esattamente 3 volte l'assegno sociale 2027 (il pavimento), non sopra | C61: La circolare riporta una soglia pari a 3 × l'assegno sociale 2027 | D61: La circolare riporta un importo superiore | E61: Circolare INPS di inizio 2027 | F61: 80%
A62: Regola: fa fede il testo del DDL trasmesso alle Camere; se non è trasmesso entro il 20/10 la verifica slitta alla trasmissione (il comunicato del Consiglio dei ministri vale solo come indicazione provvisoria). Seconda verifica: la legge in Gazzetta Ufficiale. P3 è assorbita in P2.
A66: Motore del calcolo — non modificare
A67: Soglia dell'anticipata: componente legata al PIL come nella nota (****) della Tab. A1.5 RGS 27 (importo 2026 rivalutato con la media quinquennale del PIL nominale), pavimento = 3,2 volte l'assegno sociale dal 2030. Bisezioni come nel foglio 4.
A69: Rendimento reale (foglio 2) | B69: ='2 - Il costo del ponte'!$B$6 -> 0.03
A70: Inflazione dopo il 2026 (foglio 2) | B70: ='2 - Il costo del ponte'!$B$7 -> 0.02
A71: Imposta sulle plusvalenze (foglio 2) | B71: ='2 - Il costo del ponte'!$B$9 -> 0.26
A72: 1 − bollo (foglio 2) | B72: =1-'2 - Il costo del ponte'!$B$10 -> 0.998
A73: Crescita reale annua del portafoglio (1 + r), prima del bollo | B73: =1+$B$69 -> 1.03
A74: Inflazione: la base di costo nominale perde (1 + inflazione) ogni anno in euro reali | B74: =1+$B$70 -> 1.02
A76: Mese di nascita | B76: ='3 - Le tre forze'!$B$129 -> 23810
A77: Mese di fine piano | B77: ='3 - Le tre forze'!$B$132 -> 24914
A78: Gennaio 2027 | B78: ='3 - Le tre forze'!$B$133 -> 24324
A79: Prima rata vecchiaia (RGS 27) | B79: ='3 - Le tre forze'!$B$134 -> 24642
A80: Decorrenza anticipata | B80: ='3 - Le tre forze'!$B$136 -> 24606
A81: Spesa annua | B81: ='3 - Le tre forze'!$B$8 -> 22000
A82: Addizionali | B82: ='3 - Le tre forze'!$B$111 -> 0.02
A83: Anno del primo contributo | B83: ='3 - Le tre forze'!$B$7 -> 2009
A84: Assegno sociale 2026 | B84: ='3 - Le tre forze'!$B$117 -> 546.24
A85: Multiplo fino al 2029 | B85: ='3 - Le tre forze'!$B$118 -> 3
A86: Multiplo dal 2030 | B86: ='3 - Le tre forze'!$B$119 -> 3.2
A87: Montante → pensione, anticipata centrale | B87: ='3 - Le tre forze'!$C$739*'3 - Le tre forze'!$J$158 -> 0.078545955
A88: Coefficiente dell'anticipata (centrale) | B88: ='3 - Le tre forze'!$J$158 -> 0.051892051
A89: Stop minimo centrale (foglio 3) | B89: ='3 - Le tre forze'!$C$2327 -> 24414
A90: Stop minimo con l'età bloccata a 67 (foglio 3, mondo «67 anni, revisione centrale») | B90: ='3 - Le tre forze'!$C$2175 -> 24410
A91: Anno della decorrenza anticipata | B91: =INT($B$80/12) -> 2050
A92: Soglia anticipata: componente legata al PIL (proiezione RGS), euro 2026 | B92: =$B$85*$B$84*INDEX('3 - Le tre forze'!$L$163:$L$239,$B$91-2008)/INDEX('3 - Le tre forze'!$L$163:$L$239,2026-2008)/INDEX('3 - Le tre forze'!$E$163:$E$239,$B$91-2008) -> 1919.7375
A93: Soglia anticipata: pavimento, euro 2026 | B93: =IF($B$91>=2030,$B$86,$B$85)*$B$84 -> 1747.968
A94: Anno della prima rata di vecchiaia | B94: =INT($B$79/12) -> 2053
A95: Soglia vecchiaia: componente legata al PIL (proiezione RGS), euro 2026 | B95: =$B$84*INDEX('3 - Le tre forze'!$L$163:$L$239,$B$94-2008)/INDEX('3 - Le tre forze'!$L$163:$L$239,2026-2008)/INDEX('3 - Le tre forze'!$E$163:$E$239,$B$94-2008) -> 649.55926
A96: Contributi rivalutati allo stop minimo centrale | B96: ='3 - Le tre forze'!$E$2711 -> 300136.86
A97: Pensione anticipata lorda allo stop minimo centrale (€/mese) | B97: =$B$96*$B$87/13 -> 1813.4259
A98: Stop a scelta (indice) | B98: =$B$76+12*$B$37+$B$38 -> 24422
A99: Anno | B99: =INT($B$98/12) -> 2035
A100: Frazione | B100: =MOD($B$98,12)/12 -> 0.16666667
A101: Pensione anticipata lorda allo stop a scelta (€/mese) | B101: =(INDEX('3 - Le tre forze'!$AK$163:$AK$239,($B$99-1)-2008)+INDEX('3 - Le tre forze'!$AG$163:$AG$239,$B$99-2008)*$B$100/INDEX('3 - Le tre forze'!$L$163:$L$239,$B$99-2008))*$B$87/13 -> 1862.54
A102: Soglia della tua manovra (€/mese; 0 = nessuna) | B102: =IF($B$19="nessuna soglia",0,IF($B$19="pavimento",$B$93,MAX($B$92,$B$93))) -> 1919.7375
A103: Il TFR vale e c'è ancora alla domanda | B103: =AND($B$20="Sì",$B$21="Sì") -> FALSE
A105: Anno | B105: Vecchiaia RGS 27 (mesi) | C105: La tua manovra (mesi) | D105: Ultimo mese di nascita che matura (tua manovra) | E105: Mese 2027 sterilizzato (mesi) | F105: Ultimo mese di nascita che matura (sterilizzato)
A106: ='1 - Il tuo traguardo'!$A$65 -> 2012 | B106: ='1 - Il tuo traguardo'!$B$65 -> 792 | C106: =IF(AND(NOT(ISBLANK($B$18)),$A106>=$B$18),MIN($B106,804),IF(AND($A106=2027,$B$17="67 anni"),804,$B106)) -> 792 | D106: =12*$A106+11-$C106 -> 23363 | E106: =IF($A106=2027,804,$B106) -> 792 | F106: =12*$A106+11-$E106 -> 23363
A107: ='1 - Il tuo traguardo'!$A$66 -> 2013 | B107: ='1 - Il tuo traguardo'!$B$66 -> 795 | C107: =IF(AND(NOT(ISBLANK($B$18)),$A107>=$B$18),MIN($B107,804),IF(AND($A107=2027,$B$17="67 anni"),804,$B107)) -> 795 | D107: =12*$A107+11-$C107 -> 23372 | E107: =IF($A107=2027,804,$B107) -> 795 | F107: =12*$A107+11-$E107 -> 23372
A108: ='1 - Il tuo traguardo'!$A$67 -> 2014 | B108: ='1 - Il tuo traguardo'!$B$67 -> 795 | C108: =IF(AND(NOT(ISBLANK($B$18)),$A108>=$B$18),MIN($B108,804),IF(AND($A108=2027,$B$17="67 anni"),804,$B108)) -> 795 | D108: =12*$A108+11-$C108 -> 23384 | E108: =IF($A108=2027,804,$B108) -> 795 | F108: =12*$A108+11-$E108 -> 23384
A109: ='1 - Il tuo traguardo'!$A$68 -> 2015 | B109: ='1 - Il tuo traguardo'!$B$68 -> 795 | C109: =IF(AND(NOT(ISBLANK($B$18)),$A109>=$B$18),MIN($B109,804),IF(AND($A109=2027,$B$17="67 anni"),804,$B109)) -> 795 | D109: =12*$A109+11-$C109 -> 23396 | E109: =IF($A109=2027,804,$B109) -> 795 | F109: =12*$A109+11-$E109 -> 23396
A110: ='1 - Il tuo traguardo'!$A$69 -> 2016 | B110: ='1 - Il tuo traguardo'!$B$69 -> 799 | C110: =IF(AND(NOT(ISBLANK($B$18)),$A110>=$B$18),MIN($B110,804),IF(AND($A110=2027,$B$17="67 anni"),804,$B110)) -> 799 | D110: =12*$A110+11-$C110 -> 23404 | E110: =IF($A110=2027,804,$B110) -> 799 | F110: =12*$A110+11-$E110 -> 23404
A111: ='1 - Il tuo traguardo'!$A$70 -> 2017 | B111: ='1 - Il tuo traguardo'!$B$70 -> 799 | C111: =IF(AND(NOT(ISBLANK($B$18)),$A111>=$B$18),MIN($B111,804),IF(AND($A111=2027,$B$17="67 anni"),804,$B111)) -> 799 | D111: =12*$A111+11-$C111 -> 23416 | E111: =IF($A111=2027,804,$B111) -> 799 | F111: =12*$A111+11-$E111 -> 23416
...
