Workbook

Sheet 0 - Indice
A1: Marco FIRE — Ponte Pensione 2026 (uscire a 64 anni)
A2: Strumento informativo / divulgativo. NON è consulenza finanziaria. I valori sono indicativi al 2026 e vanno verificati col tuo consulente.
A4: Indice
A5: 1 - SOGLIA 64 | B5: Montante, assegno, soglia 3,0x (3,2x dal 2030) ed esito
A6: 2 - VIE USCITA | B6: Tutte le vie 2026-2028, condizioni e regole NASpI
A7: 3 - PONTE | B7: Mesi da coprire, capitale bruciato e residuo alla prima rata
A8: 4 - VOLONTARI | B8: Costo, beneficio e pareggio nei tre profili fiscali
A9: 5 - PART-TIME | B9: Costo permanente del part-time e tassi di sostituzione
A11: Come usare
A12: 1. Le celle GIALLE sono input — modificale coi tuoi numeri.
A13: 2. Le celle VERDI sono output — si aggiornano automaticamente.
A14: 3. Tutti i numeri di default sono al 2026 da fonti pubbliche.
A15: 4. Niente codice nascosto: l'Excel è solo formule modificabili.
A17: Fonti dati
A18: • D.L. 201/2011 art. 24 c. 11 (conv. L. 214/2011), testo vigente — anticipata contributiva: 64 anni, 20 anni effettivi, soglia 3,0x l'assegno sociale (3,2x dal 1/1/2030), tetto 5x il trattamento minimo, finestra 3 mesi
A19: • L. 199/2025 art. 1 c. 195 (G.U. 301 del 30/12/2025, S.O. 42) — abrogato il comma 7-bis (computo della rendita del fondo pensione) e soppresso l'ultimo periodo del comma 11
A20: • L. 199/2025 art. 1 c. 185 — adeguamento alla speranza di vita: +1 mese nel 2027, +2 mesi ulteriori nel 2028
A21: • INPS, circolare n. 19 del 25/02/2026 — istruzioni applicative; APE sociale prorogata (63 anni e 5 mesi); Opzione Donna e anticipata flessibile non prorogate
A22: • INPS, circolare n. 153 del 19/12/2025 — assegno sociale 2026: 546,24 €/mese; trattamento minimo 2026: 611,85 €/mese
A23: • D.M. 20 novembre 2024 — coefficienti di trasformazione 2025-2026: 5,088% a 64 anni, 5,608% a 67 anni
... A29: Aggiornamenti: github.com/marcofire-it/marco-fire-simulatori

Sheet 1 - SOGLIA 64
A1: Superi la soglia per uscire a 64 anni?
A2: Strumento informativo / divulgativo. NON è consulenza finanziaria. I valori sono indicativi al 2026 e vanno verificati col tuo consulente.
A4: INPUT — cambia solo le celle gialle
A5: Il tuo montante contributivo (€) — da estratto conto INPS | B5: 350000
A6: Anno in cui vorresti uscire | B6: 2026
A7: Figli (solo lavoratrici madri; 0 = regola generale) | B7: 0
A8: Assegno sociale mensile (€) — INPS circ. 153/2025 | B8: 546.24
A9: Coefficiente di trasformazione a 64 anni | B9: 0.05088
A10: Trattamento minimo mensile (€) — INPS circ. 153/2025 | B10: 611.85
A11: Anni di contribuzione EFFETTIVA già maturati | B11: 20
A12: Il montante NON è il tuo capitale in banca: è la somma dei contributi versati da te e dal datore di lavoro, rivalutata anno per anno con la media quinquennale del PIL nominale. Lo leggi sull'estratto conto contributivo INPS. Il coefficiente 5,088% vale per il biennio 2025-2026 (D.M. 20/11/2024) e per l'uscita esattamente a 64 anni.
A14: LA SOGLIA CHE DEVI SUPERARE
A15: Moltiplicatore applicabile | B15: =IF(B7>=2,2.6,IF(B7=1,2.8,IF(B6>=2030,3.2,3)))
A16: Soglia MENSILE lorda (€) | B16: =B8*B15
A17: Soglia ANNUA lorda (13 mensilità) (€) | B17: =B16*13
A18: Montante MINIMO che serve (€) | B18: =IFERROR(B17/B9,NA())
A19: Dal 1° gennaio 2030 il moltiplicatore della regola generale sale da 3,0 a 3,2 volte l'assegno sociale (art. 24 c. 11 D.L. 201/2011, penultimo periodo: NON è stato toccato dalla L. 199/2025). Le soglie ridotte per le lavoratrici madri restano 2,8x e 2,6x.
A21: IL TUO ASSEGNO
A22: Assegno LORDO annuo (montante × coefficiente) | B22: =B5*B9
A23: Assegno LORDO mensile (13 mensilità) | B23: =B22/13
A24: Differenza rispetto alla soglia (€/mese) | B24: =B23-B16
A25: ESITO | B25: =IF(B11<20,"NO — mancano anni di contribuzione effettiva",IF(B23>=B16,"SOPRA SOGLIA — porta aperta","SOTTO SOGLIA — porta chiusa"))
A26: Montante ancora mancante (€) | B26: =IFERROR(MAX(0,(B17-B22)/B9),NA())
A27: Anni di contribuzione effettiva mancanti | B27: =MAX(0,20-B11)
A29: TETTO SULLE MENSILITÀ DI ANTICIPO (fino a 67 anni)
A30: Massimo erogabile: 5 × trattamento minimo (€/mese) | B30: =B10*5
A31: Il tuo assegno supera il tetto? | B31: =IF(B23>B30,"SÌ — fino a 67 anni ricevi al massimo il tetto","No")
A33: MONTANTE MINIMO per ciascuna soglia (valori 2026)
A34: Soglia | B34: Moltiplicatore | C34: €/mese | D34: Montante minimo
A35: Regola generale (fino al 2029) | B35: =3.0 | C35: =$B$8*3.0 | D35: =IFERROR($B$8*3.0*13/$B$9,NA())
A36: Regola generale (dal 2030) | B36: =3.2 | C36: =$B$8*3.2 | D36: =IFERROR($B$8*3.2*13/$B$9,NA())
A37: Lavoratrice madre, 1 figlio | B37: =2.8 | C37: =$B$8*2.8 | D37: =IFERROR($B$8*2.8*13/$B$9,NA())
A38: Lavoratrice madre, 2+ figli | B38: =2.6 | C38: =$B$8*2.6 | D38: =IFERROR($B$8*2.6*13/$B$9,NA())
A40: ATTENZIONE — novità 2026: fino al 31/12/2025 l'art. 24 c. 7-bis del D.L. 201/2011 avrebbe consentito di sommare il valore teorico della rendita di un fondo pensione per raggiungere la soglia. Quel comma è stato ABROGATO dall'art. 1 c. 195 della L. 199/2025 e non era comunque mai diventato operativo (mancava il decreto attuativo). Oggi la soglia si raggiunge SOLO con l'assegno pubblico. In compenso è caduto anche il requisito contributivo maggiorato (25 anni, 30 dal 2030) e il divieto di lavorare dopo l'uscita, che erano il prezzo di quella facoltà.

Sheet 2 - VIE USCITA
A1: Le vie d'uscita e come si muovono nel 2027-2028
A2: Strumento informativo / divulgativo. NON è consulenza finanziaria. I valori sono indicativi al 2026 e vanno verificati col tuo consulente.
A4: REQUISITI PER ANNO
A5: Via d'uscita | B5: 2026 | C5: 2027 | D5: 2028 | E5: Finestra
A6: Vecchiaia | B6: 67 anni + 20 anni | C6: 67 anni e 1 mese + 20 | D6: 67 anni e 3 mesi + 20 | E6: —
A7: Anticipata ordinaria (uomini) | B7: 42 anni e 10 mesi | C7: 42 anni e 11 mesi | D7: 43 anni e 1 mese | E7: 3 mesi
A8: Anticipata ordinaria (donne) | B8: 41 anni e 10 mesi | C8: 41 anni e 11 mesi | D8: 42 anni e 1 mese | E8: 3 mesi
A9: Anticipata contributiva | B9: 64 anni + 20 effettivi | C9: 64 anni e 1 mese + 20 e 1 | D9: 64 anni e 3 mesi + 20 e 3 | E9: 3 mesi
A10: APE sociale | B10: 63 anni e 5 mesi | C10: prorogata al 31/12/2026 | D10: da verificare | E10: —
A11: Opzione Donna | B11: NON prorogata | C11: — | D11: — | E11: —
A12: Anticipata flessibile (Quota 103) | B12: NON prorogata | C12: — | D12: — | E12: —
A14: L'adeguamento alla speranza di vita è stato graduato dall'art. 1 c. 185 della L. 199/2025: +1 mese nel 2027 e ulteriori +2 mesi nel 2028. Nella via contributiva si muove ANCHE il requisito contributivo, non solo l'età: nel 2028 servono 20 anni e 3 mesi di contribuzione effettiva.
A16: CONDIZIONI DELLA VIA CONTRIBUTIVA (art. 24 c. 11)
A17: Primo accredito contributivo | B17: successivo al 1° gennaio 1996
A18: Contribuzione effettiva | B18: almeno 20 anni (2026)
A19: Cosa NON conta | B19: la contribuzione figurativa (NASpI, malattia, ecc.)
A20: Cosa conta | B20: obbligatoria da lavoro, volontaria, da riscatto
A21: Importo prima rata | B21: ≥ 3,0 volte l'assegno sociale (2,8 / 2,6 madri)
A22: Tetto fino a 67 anni | B22: 5 volte il trattamento minimo
A23: Decorrenza | B23: trascorsi 3 mesi dalla maturazione dei requisiti
A24: Rendita del fondo pensione | B24: NON computabile dal 1/1/2026 (L. 199/2025 c. 195)
A26: NASpI 2026 — solo per chi perde il lavoro involontariamente
A27: Presupposto di legge | B27: cessazione INVOLONTARIA del rapporto (D.Lgs. 22/2015 art. 3)
A28: Requisito contributivo | B28: 13 settimane di contribuzione nei 4 anni precedenti
A29: Durata | B29: metà delle settimane contributive degli ultimi 4 anni, max 24 mesi
A30: Importo | B30: 75% della retribuzione fino a 1.456,72 € + 25% dell'eccedenza
A31: Importo massimo 2026 | B31: 1.584,70 €/mese (INPS circ. 4/2026)
A32: Riduzione | B32: -3% al mese dal 6° mese (dall'8° se 55 anni compiuti alla domanda)
A33: Effetto previdenziale | B33: contribuzione FIGURATIVA: non vale per i 20 anni effettivi
A35: Questa sezione è puramente descrittiva della norma. Le dimissioni volontarie non danno diritto alla NASpI: il foglio serve a calcolare durata e importo a chi la NASpI spetta già, non a pianificare un'uscita.

Sheet 3 - PONTE
A1: Il ponte: quanto ti costa arrivare alla prima rata
A2: Strumento informativo / divulgativo. NON è consulenza finanziaria. I valori sono indicativi al 2026 e vanno verificati col tuo consulente.
A4: INPUT
A5: Età a cui vuoi smettere di lavorare | B5: 60
A6: Età di maturazione dei requisiti (64 nel 2026) | B6: 64
A7: Mesi di finestra (3 per la via contributiva) | B7: 3
A8: Spesa annua da coprire (€) | B8: 24000
A9: Capitale disponibile per il ponte (€) | B9: 150000
A10: Rendimento REALE netto ipotizzato (%) | B10: 0.01
A11: Rendimento REALE = al netto di inflazione, imposte e costi. L'1% è una ipotesi prudente per un portafoglio difensivo in fase di prelievo. Non usare rendimenti nominali: rivaluteresti il capitale e non le spese, che è l'errore più comune in queste simulazioni.
A13: QUANTO DURA E QUANTO COSTA IL PONTE
A14: Mesi da coprire da solo | B14: =MAX(0,(B6-B5)*12+B7)
A15: Anni equivalenti | B15: =B14/12
A16: Capitale bruciato, senza rendimenti (€) | B16: =B8/12*B14
A17: Capitale residuo alla prima rata (con rendimento) (€) | B17: =F30
A18: Il capitale basta? | B18: =IF(F30>0,"SÌ","NO — il ponte non regge")
A19: Capitale minimo necessario, senza rendimenti (€) | B19: =B16
A21: PIANO ANNO PER ANNO
A22: Anno del ponte | B22: Mesi coperti | C22: Spesa dell'anno | D22: Capitale iniziale | E22: Rendimento | F22: Capitale finale
A23: Anno 1 | B23: =MAX(0,MIN(12,$B$14-0)) | C23: =$B$8/12*B23 | D23: =$B$9 | E23: =IF(B23=0,0,($B$9-C23)*$B$10) | F23: =IF(B23=0,$B$9,$B$9-C23+E23)
A24: Anno 2 | B24: =MAX(0,MIN(12,$B$14-12)) | C24: =$B$8/12*B24 | D24: =F23 | E24: =IF(B24=0,0,(F23-C24)*$B$10) | F24: =IF(B24=0,F23,F23-C24+E24)
A25: Anno 3 | B25: =MAX(0,MIN(12,$B$14-24)) | C25: =$B$8/12*B25 | D25: =F24 | E25: =IF(B25=0,0,(F24-C25)*$B$10) | F25: =IF(B25=0,F24,F24-C25+E25)
A26: Anno 4 | B26: =MAX(0,MIN(12,$B$14-36)) | C26: =$B$8/12*B26 | D26: =F25 | E26: =IF(B26=0,0,(F25-C26)*$B$10) | F26: =IF(B26=0,F25,F25-C26+E26)
A27: Anno 5 | B27: =MAX(0,MIN(12,$B$14-48)) | C27: =$B$8/12*B27 | D27: =F26 | E27: =IF(B27=0,0,(F26-C27)*$B$10) | F27: =IF(B27=0,F26,F26-C27+E27)
A28: Anno 6 | B28: =MAX(0,MIN(12,$B$14-60)) | C28: =$B$8/12*B28 | D28: =F27 | E28: =IF(B28=0,0,(F27-C28)*$B$10) | F28: =IF(B28=0,F27,F27-C28+E28)
A29: Anno 7 | B29: =MAX(0,MIN(12,$B$14-72)) | C29: =$B$8/12*B29 | D29: =F28 | E29: =IF(B29=0,0,(F28-C29)*$B$10) | F29: =IF(B29=0,F28,F28-C29+E29)
A30: Anno 8 | B30: =MAX(0,MIN(12,$B$14-84)) | C30: =$B$8/12*B30 | D30: =F29 | E30: =IF(B30=0,0,(F29-C30)*$B$10) | F30: =IF(B30=0,F29,F29-C30+E30)
A31: TOTALE speso nel ponte | C31: =SUM(C23:C30) | D31: Residuo alla prima rata | F31: =F30
A33: Il piano copre fino a 8 anni di ponte: se ne servono di più, il residuo va letto come indicativo. Ricorda che nei mesi del ponte non versi contributi: se non hai ancora i 20 anni di contribuzione effettiva, il ponte da solo non ti porta alla pensione. Vedi il foglio 4.
A35: RIEPILOGO — contributi volontari (dal foglio 4)
A36: Costo di 1 anno di contributi volontari (€) | B36: ='4 - VOLONTARI'!B15
A37: Anni per rientrare, deducendo al 43% e tassando al 33% | B37: ='4 - VOLONTARI'!B24
A38: Anni per rientrare SENZA redditi da dedurre | B38: ='4 - VOLONTARI'!B26

Sheet 4 - VOLONTARI
A1: Contributi volontari: il conto vero
A2: Strumento informativo / divulgativo. NON è consulenza finanziaria. I valori sono indicativi al 2026 e vanno verificati col tuo consulente.
A4: INPUT
A5: Retribuzione lorda annua di riferimento (€) | B5: 35000
A6: Aliquota contributiva volontaria (%) — INPS circ. 27/2026 | B6: 0.33
A7: Retribuzione minima settimanale imponibile 2026 (€) | B7: 244.74
A8: Anni di versamento volontario previsti | B8: 1
A9: Coefficiente di trasformazione a 64 anni | B9: 0.05088
A10: Aliquota marginale con cui DEDUCI oggi (%) | B10: 0.43
A11: Aliquota con cui tasserai la pensione (%) | B11: 0.33
A13: COSTO
A14: Contributo settimanale (€) | B14: =MAX(B5/52,B7)*B6
A15: Costo LORDO di 1 anno (52 settimane) (€) | B15: =B14*52
A16: Costo LORDO totale (€) | B16: =B15*B8
A17: Deduzione IRPEF (art. 10 c. 1 lett. e TUIR) (€) | B17: =B16*B10
A18: COSTO NETTO se hai redditi capienti (€) | B18: =B16-B17
A19: Costo minimo di legge, 1 anno (retribuzione minima) (€) | B19: =B7*B6*52
A21: BENEFICIO E PAREGGIO
A22: Pensione LORDA annua in più (€) | B22: =B16*B9
A23: Pensione lorda mensile in più (13 mensilità) (€) | B23: =B22/13
A24: Anni per rientrare — deduci oggi, tassi da pensionato | B24: =IFERROR(B18/(B22*(1-B11)),NA())
A25: Anni per rientrare — al lordo (nessun effetto fiscale) | B25: =IFERROR(B16/B22,NA())
A26: Anni per rientrare — SENZA redditi da dedurre | B26: =IFERROR(B16/(B22*(1-B11)),NA())
A27: Verdetto | B27: =IF(B24<=15,"Conviene","Pareggio troppo lontano: usali per l'accesso, non per l'importo")
A28: Ipotesi prudenziale: il montante non viene rivalutato (in realtà si rivaluta con la media quinquennale del PIL nominale, che negli ultimi anni è stata positiva). Con la rivalutazione il pareggio si accorcia di 1-3 anni, non di più. Il punto resta: i volontari hanno senso per comprare gli ANNI mancanti, non per alzare l'importo.
A30: PAREGGIO al variare del profilo fiscale
A31: Situazione | B31: Costo netto | C31: Beneficio netto/anno | D31: Anni per rientrare
A32: Deduci al 43%, tassi al 33% | B32: =$B$16*(1-0.43) | C32: =$B$22*(1-$B$11) | D32: =IFERROR($B$16*(1-0.43)/($B$22*(1-$B$11)),NA())
A33: Deduci al 33%, tassi al 33% | B33: =$B$16*(1-0.33) | C33: =$B$22*(1-$B$11) | D33: =IFERROR($B$16*(1-0.33)/($B$22*(1-$B$11)),NA())
A34: Deduci al 23%, tassi al 23% | B34: =$B$16*(1-0.23) | C34: =$B$22*(1-$B$11) | D34: =IFERROR($B$16*(1-0.23)/($B$22*(1-$B$11)),NA())
A35: Nessun reddito da dedurre | B35: =$B$16*(1-0.0) | C35: =$B$22*(1-$B$11) | D35: =IFERROR($B$16*(1-0.0)/($B$22*(1-$B$11)),NA())
A37: REQUISITI PER L'AUTORIZZAZIONE (D.Lgs. 184/1997 art. 6)
A38: Opzione A | B38: 260 contributi settimanali (5 anni) in qualunque epoca
A39: Opzione B | B39: 156 settimane (3 anni) nel quinquennio precedente la domanda
A40: Contribuzione utile | B40: solo effettiva: obbligatoria, volontaria, da riscatto
A41: Esclusa | B41: qualsiasi contribuzione figurativa
A42: Incompatibilità | B42: i volontari non si versano nei periodi già coperti da lavoro

Sheet 5 - PART-TIME
A1: La strategia part-time: quanto costa davvero
A2: Strumento informativo / divulgativo. NON è consulenza finanziaria. I valori sono indicativi al 2026 e vanno verificati col tuo consulente.
A4: INPUT
A5: Imponibile attuale a tempo pieno (€/anno) | B5: 35000
A6: Imponibile a part-time (€/anno) | B6: 20000
A7: Per quanti anni | B7: 10
A8: Aliquota di computo IVS (%) | B8: 0.33
A9: Coefficiente di trasformazione a 64 anni | B9: 0.05088
A11: EFFETTO SULLA PENSIONE
A12: Montante accantonato a tempo pieno (€) | B12: =B5*B8*B7
A13: Montante accantonato a part-time (€) | B13: =B6*B8*B7
A14: Montante PERSO (€) | B14: =B12-B13
A15: Assegno annuo perso (€) | B15: =B14*B9
A16: Assegno mensile perso, a vita (€) | B16: =B15/13
A18: IMPATTO SULLA SOGLIA DEI 64 ANNI
A19: Assegno mensile senza part-time (foglio 1) (€) | B19: ='1 - SOGLIA 64'!B23
A20: Assegno mensile dopo il part-time (€) | B20: =B19-B16
A21: Soglia da superare (foglio 1) (€) | B21: ='1 - SOGLIA 64'!B16
A22: Il part-time ti fa scendere sotto soglia? | B22: =IF(AND(B19>=B21,B20<B21),"SÌ — ti chiude la porta dei 64 anni",IF(B20<B21,"Eri già sotto soglia","No, resti sopra"))
A24: Il part-time riduce il montante in modo proporzionale all'imponibile, e l'effetto è permanente: te lo porti dietro per tutta la pensione. Va confrontato con il valore del tempo libero guadagnato, che questo foglio non può misurare. Ma il costo va conosciuto prima, non dopo.
A26: TASSI DI SOSTITUZIONE — dipendenti privati, 2030 (RGS 2025)
A27: Canale di uscita | B27: Lordo | C27: Netto
A28: Pensione di vecchiaia | B28: =0.708 | C28: =0.758
A29: Pensionamento anticipato contributivo | B29: =0.594 | C29: =0.651
A30: Differenza | B30: =B29-B28 | C30: =C29-C28
A32: Fonte: MEF — Ragioneria Generale dello Stato, «Le tendenze di medio-lungo periodo del sistema pensionistico e socio-sanitario», Aggiornamento 2025 (Rapporto n. 26), Tab. 6.1.a e 6.3.a, scenario nazionale base, anno 2030. Per i lavoratori autonomi lo stesso rapporto stima un tasso lordo del 39,5% e definisce l'accesso alla via contributiva «un'eventualità poco probabile».
