Workbook

Sheet 0 - Indice
A1: Marco FIRE — Posso smettere? Il simulatore a sei numeri
A2: Strumento informativo / divulgativo. NON è consulenza finanziaria. I valori sono indicativi al 2026 e vanno verificati col tuo consulente.
A4: Indice
A5: 1 - I TUOI 6 NUMERI | B5: Sei numeri, un verdetto: il ponte fino alla pensione regge o no
A6: 2 - ANNO PER ANNO | B6: Il decumulo anno per anno, con imposta sulla plusvalenza e bollo
A7: 3 - MATRICE | B7: A che età finisce il capitale, per spesa e per rendimento
A8: 4 - SEQUENZA | B8: Stesso rendimento medio, ordine diverso: quanto cambia il risultato
A10: Come usare
A11: 1. Le celle GIALLE sono input — modificale coi tuoi numeri.
A12: 2. Le celle VERDI sono output — si aggiornano automaticamente.
A13: 3. Tutti i numeri di default sono al 2026 da fonti pubbliche.
A14: 4. Niente codice nascosto: l'Excel è solo formule modificabili.
A16: Fonti dati
A17: • D.L. 66/2014 art. 3 e TUIR — imposta sostitutiva 26% sui redditi di natura finanziaria; 12,5% su titoli di Stato italiani ed emittenti white list
A18: • D.P.R. 642/1972, Tariffa allegata art. 13 c. 2-ter — imposta di bollo sui prodotti finanziari: 0,2% annuo del valore di mercato
A19: • Bengen W. (1994), Determining Withdrawal Rates Using Historical Data — SAFEMAX 4,15% su orizzonte di 30 anni
A20: • Cooley P., Hubbard C., Walz D. (1998), Trinity Study — tassi di prelievo sostenibili e probabilità di successo per orizzonte e allocazione
A21: • Morningstar (2025), The State of Retirement Income — tasso di prelievo iniziale sicuro 3,9% nello scenario base
A22: • Rendimenti reali di lungo periodo di azionario e obbligazionario: ipotesi dichiarate, non previsioni. Cambia la cella gialla e guarda quanto conta
A24: Aggiornamenti: github.com/marcofire-it/marco-fire-simulatori

Sheet 1 - I TUOI 6 NUMERI
A1: Posso smettere? Il tuo caso in sei numeri
A2: Strumento informativo / divulgativo. NON è consulenza finanziaria. I valori sono indicativi al 2026 e vanno verificati col tuo consulente.
A4: I TUOI 6 NUMERI — cambia solo le celle gialle
A5: 1. Quanti anni hai oggi | B5: 45
A6: 2. Capitale investito oggi (€) | B6: 400000
A7: 3. Quanto spendi davvero in un anno, netto (€) | B7: 24000
A8: 4. Rendimento REALE atteso del portafoglio (%) | B8: 0.03
A9: 5. Plusvalenza latente sul portafoglio oggi (%) | B9: 0.2
A10: 6. A che età arriva la pensione pubblica | B10: 67 | D10: Oggi la vecchiaia è a 67 anni, 67 e 1 mese nel 2027, 67 e 3 mesi dal 2028. Ma per chi ci arriva intorno al 2050 la Ragioneria dello Stato proietta 69 anni: se hai meno di 50 anni, prova a scrivere 69 qui.
A11: Il numero 3 è quello che decide tutto, ed è anche l'unico che nessuno conosce davvero: prendi l'estratto conto degli ultimi dodici mesi e somma, non stimare a memoria. Il numero 5 è la plusvalenza NON ancora realizzata: se hai investito 320.000 € e oggi il portafoglio ne vale 400.000, la plusvalenza latente è 80.000 su 400.000, cioè il 20%.
A13: IPOTESI TECNICHE — puoi cambiarle, ma sappi cosa fai
A14: Inflazione media attesa (%) | B14: 0.02
A15: Aliquota sulle plusvalenze (%) | B15: 0.26
A16: Imposta di bollo annua sul dossier (%) | B16: 0.002
A17: Base fiscale iniziale (quanto hai versato) | B17: =B6*(1-B9)
A18: Rendimento NOMINALE corrispondente | B18: =(1+B8)*(1+B14)-1
A20: IL VERDETTO
A21: Anni interi in cui il capitale regge | B21: =COUNTIF('2 - ANNO PER ANNO'!J7:J52,">0")
A22: Età a cui il capitale finisce | B22: =B5+B21
A23: Anni da coprire fino alla pensione | B23: =MAX(0,B10-B5)
A24: VERDETTO SUL PONTE | B24: =IF(B21>=B23,"SI - il ponte fino alla pensione regge","NO - il capitale finisce prima della pensione")
A25: Anni che ti mancano (0 = ce la fai) | B25: =MAX(0,B23-B21)
A26: Capitale in euro di oggi il giorno della pensione | B26: =IFERROR(MAX(0,INDEX('2 - ANNO PER ANNO'!L7:L52,MATCH(B10-1,'2 - ANNO PER ANNO'!A7:A52,0))),0)
A28: IL PRIMO ANNO, VOCE PER VOCE
A29: Spesa netta che vuoi avere in mano | B29: =B7
A30: Prelievo LORDO necessario | B30: ='2 - ANNO PER ANNO'!G7
A31: Di cui imposta sulla plusvalenza | B31: ='2 - ANNO PER ANNO'!H7
A32: Imposta di bollo sul dossier | B32: ='2 - ANNO PER ANNO'!I7
A33: USCITA TOTALE dal portafoglio nel primo anno | B33: ='2 - ANNO PER ANNO'!G7+'2 - ANNO PER ANNO'!I7
A34: Tasso di prelievo effettivo sul capitale | B34: =IFERROR(B33/B6,0)
A35: Confronto: tasso di prelievo «sicuro» Morningstar 2025 | B35: =0.039
A37: Quanto capitale servirebbe per coprire tutto il ponte
A38: Valori calcolati con questo stesso modello, partendo da 45 anni con rendimento reale 3% e plusvalenza latente 20%. Sono il capitale MINIMO che, con quella spesa, arriva esattamente alla pensione: sotto quella cifra il ponte non regge. La seconda colonna usa i 67 anni di oggi, la terza i 69 anni proiettati dalla Ragioneria dello Stato per chi va in pensione intorno al 2050. Verificali: scrivi la cifra nella cella gialla del capitale, metti 67 o 69 nell'età della pensione, e guarda il verdetto qui sopra.
A39: Spesa annua netta | B39: Per arrivare a 67 (22 anni) | C39: Per arrivare a 69 (24 anni)
A40: 18.000 € | B40: 344000 | C40: 368000
A41: 24.000 € | B41: 459000 | C41: 491000
A42: 30.000 € | B42: 573000 | C42: 613000
A43: 36.000 € | B43: 688000 | C43: 736000
A45: Attenzione al confronto con la «regola del 4%»: quella regola nasce su orizzonti di 30 anni, su mercati americani e SENZA la fiscalità italiana. Qui il tasso di prelievo che vedi sopra è già comprensivo di imposta sulla plusvalenza e di bollo, ed è quindi più alto di quello che scriveresti guardando solo la spesa.

Sheet 2 - ANNO PER ANNO
A1: Il ponte, anno per anno
A2: Strumento informativo / divulgativo. NON è consulenza finanziaria. I valori sono indicativi al 2026 e vanno verificati col tuo consulente.
A3: Tutti i valori sono NOMINALI (euro correnti dell'anno) tranne l'ultima colonna, che riporta il capitale in euro di oggi. La colonna «quota plusvalenza» è la parte di ogni vendita che risulta guadagno: cresce nel tempo perché la base fiscale si consuma, e per questo l'imposta pesa sempre di più. Riga in cui il capitale finale diventa negativo = anno in cui il capitale si esaurisce.
A6: Età | B6: Anno | C6: Capitale inizio | D6: Spesa netta | E6: Base fiscale | F6: Quota plus. | G6: Prelievo lordo | H6: Imposta | I6: Bollo | J6: Capitale fine | L6: Capitale in € di oggi
A7: ='1 - I TUOI 6 NUMERI'!$B$5+0 | B7: =2026+0 | C7: ='1 - I TUOI 6 NUMERI'!$B$6 | D7: ='1 - I TUOI 6 NUMERI'!$B$7*(1+'1 - I TUOI 6 NUMERI'!$B$14)^0 | E7: ='1 - I TUOI 6 NUMERI'!$B$17 | F7: =IF(C7<=0,0,MEDIAN(0,(C7-E7)/C7,1)) | G7: =IF(C7<=0,0,D7/(1-'1 - I TUOI 6 NUMERI'!$B$15*F7)) | H7: ='1 - I TUOI 6 NUMERI'!$B$15*G7*F7 | I7: =IF(C7<=0,0,'1 - I TUOI 6 NUMERI'!$B$16*C7) | J7: =IF(C7<=0,0,(C7-G7-I7)*(1+'1 - I TUOI 6 NUMERI'!$B$18)) | L7: =J7/(1+'1 - I TUOI 6 NUMERI'!$B$14)^1
A8: ='1 - I TUOI 6 NUMERI'!$B$5+1 | B8: =2026+1 | C8: =J7 | D8: ='1 - I TUOI 6 NUMERI'!$B$7*(1+'1 - I TUOI 6 NUMERI'!$B$14)^1 | E8: =MAX(0,E7-G7*(1-F7)) | F8: =IF(C8<=0,0,MEDIAN(0,(C8-E8)/C8,1)) | G8: =IF(C8<=0,0,D8/(1-'1 - I TUOI 6 NUMERI'!$B$15*F8)) | H8: ='1 - I TUOI 6 NUMERI'!$B$15*G8*F8 | I8: =IF(C8<=0,0,'1 - I TUOI 6 NUMERI'!$B$16*C8) | J8: =IF(C8<=0,0,(C8-G8-I8)*(1+'1 - I TUOI 6 NUMERI'!$B$18)) | L8: =J8/(1+'1 - I TUOI 6 NUMERI'!$B$14)^2
A9: ='1 - I TUOI 6 NUMERI'!$B$5+2 | B9: =2026+2 | C9: =J8 | D9: ='1 - I TUOI 6 NUMERI'!$B$7*(1+'1 - I TUOI 6 NUMERI'!$B$14)^2 | E9: =MAX(0,E8-G8*(1-F8)) | F9: =IF(C9<=0,0,MEDIAN(0,(C9-E9)/C9,1)) | G9: =IF(C9<=0,0,D9/(1-'1 - I TUOI 6 NUMERI'!$B$15*F9)) | H9: ='1 - I TUOI 6 NUMERI'!$B$15*G9*F9 | I9: =IF(C9<=0,0,'1 - I TUOI 6 NUMERI'!$B$16*C9) | J9: =IF(C9<=0,0,(C9-G9-I9)*(1+'1 - I TUOI 6 NUMERI'!$B$18)) | L9: =J9/(1+'1 - I TUOI 6 NUMERI'!$B$14)^3
A10: ='1 - I TUOI 6 NUMERI'!$B$5+3 | B10: =2026+3 | C10: =J9 | D10: ='1 - I TUOI 6 NUMERI'!$B$7*(1+'1 - I TUOI 6 NUMERI'!$B$14)^3 | E10: =MAX(0,E9-G9*(1-F9)) | F10: =IF(C10<=0,0,MEDIAN(0,(C10-E10)/C10,1)) | G10: =IF(C10<=0,0,D10/(1-'1 - I TUOI 6 NUMERI'!$B$15*F10)) | H10: ='1 - I TUOI 6 NUMERI'!$B$15*G10*F10 | I10: =IF(C10<=0,0,'1 - I TUOI 6 NUMERI'!$B$16*C10) | J10: =IF(C10<=0,0,(C10-G10-I10)*(1+'1 - I TUOI 6 NUMERI'!$B$18)) | L10: =J10/(1+'1 - I TUOI 6 NUMERI'!$B$14)^4
A11: ='1 - I TUOI 6 NUMERI'!$B$5+4 | B11: =2026+4 | C11: =J10 | D11: ='1 - I TUOI 6 NUMERI'!$B$7*(1+'1 - I TUOI 6 NUMERI'!$B$14)^4 | E11: =MAX(0,E10-G10*(1-F10)) | F11: =IF(C11<=0,0,MEDIAN(0,(C11-E11)/C11,1)) | G11: =IF(C11<=0,0,D11/(1-'1 - I TUOI 6 NUMERI'!$B$15*F11)) | H11: ='1 - I TUOI 6 NUMERI'!$B$15*G11*F11 | I11: =IF(C11<=0,0,'1 - I TUOI 6 NUMERI'!$B$16*C11) | J11: =IF(C11<=0,0,(C11-G11-I11)*(1+'1 - I TUOI 6 NUMERI'!$B$18)) | L11: =J11/(1+'1 - I TUOI 6 NUMERI'!$B$14)^5
A12: ='1 - I TUOI 6 NUMERI'!$B$5+5 | B12: =2026+5 | C12: =J11 | D12: ='1 - I TUOI 6 NUMERI'!$B$7*(1+'1 - I TUOI 6 NUMERI'!$B$14)^5 | E12: =MAX(0,E11-G11*(1-F11)) | F12: =IF(C12<=0,0,MEDIAN(0,(C12-E12)/C12,1)) | G12: =IF(C12<=0,0,D12/(1-'1 - I TUOI 6 NUMERI'!$B$15*F12)) | H12: ='1 - I TUOI 6 NUMERI'!$B$15*G12*F12 | I12: =IF(C12<=0,0,'1 - I TUOI 6 NUMERI'!$B$16*C12) | J12: =IF(C12<=0,0,(C12-G12-I12)*(1+'1 - I TUOI 6 NUMERI'!$B$18)) | L12: =J12/(1+'1 - I TUOI 6 NUMERI'!$B$14)^6
A13: ='1 - I TUOI 6 NUMERI'!$B$5+6 | B13: =2026+6 | C13: =J12 | D13: ='1 - I TUOI 6 NUMERI'!$B$7*(1+'1 - I TUOI 6 NUMERI'!$B$14)^6 | E13: =MAX(0,E12-G12*(1-F12)) | F13: =IF(C13<=0,0,MEDIAN(0,(C13-E13)/C13,1)) | G13: =IF(C13<=0,0,D13/(1-'1 - I TUOI 6 NUMERI'!$B$15*F13)) | H13: ='1 - I TUOI 6 NUMERI'!$B$15*G13*F13 | I13: =IF(C13<=0,0,'1 - I TUOI 6 NUMERI'!$B$16*C13) | J13: =IF(C13<=0,0,(C13-G13-I13)*(1+'1 - I TUOI 6 NUMERI'!$B$18)) | L13: =J13/(1+'1 - I TUOI 6 NUMERI'!$B$14)^7
A14: ='1 - I TUOI 6 NUMERI'!$B$5+7 | B14: =2026+7 | C14: =J13 | D14: ='1 - I TUOI 6 NUMERI'!$B$7*(1+'1 - I TUOI 6 NUMERI'!$B$14)^7 | E14: =MAX(0,E13-G13*(1-F13)) | F14: =IF(C14<=0,0,MEDIAN(0,(C14-E14)/C14,1)) | G14: =IF(C14<=0,0,D14/(1-'1 - I TUOI 6 NUMERI'!$B$15*F14)) | H14: ='1 - I TUOI 6 NUMERI'!$B$15*G14*F14 | I14: =IF(C14<=0,0,'1 - I TUOI 6 NUMERI'!$B$16*C14) | J14: =IF(C14<=0,0,(C14-G14-I14)*(1+'1 - I TUOI 6 NUMERI'!$B$18)) | L14: =J14/(1+'1 - I TUOI 6 NUMERI'!$B$14)^8
A15: ='1 - I TUOI 6 NUMERI'!$B$5+8 | B15: =2026+8 | C15: =J14 | D15: ='1 - I TUOI 6 NUMERI'!$B$7*(1+'1 - I TUOI 6 NUMERI'!$B$14)^8 | E15: =MAX(0,E14-G14*(1-F14)) | F15: =IF(C15<=0,0,MEDIAN(0,(C15-E15)/C15,1)) | G15: =IF(C15<=0,0,D15/(1-'1 - I TUOI 6 NUMERI'!$B$15*F15)) | H15: ='1 - I TUOI 6 NUMERI'!$B$15*G15*F15 | I15: =IF(C15<=0,0,'1 - I TUOI 6 NUMERI'!$B$16*C15) | J15: =IF(C15<=0,0,(C15-G15-I15)*(1+'1 - I TUOI 6 NUMERI'!$B$18)) | L15: =J15/(1+'1 - I TUOI 6 NUMERI'!$B$14)^9
A16: ='1 - I TUOI 6 NUMERI'!$B$5+9 | B16: =2026+9 | C16: =J15 | D16: ='1 - I TUOI 6 NUMERI'!$B$7*(1+'1 - I TUOI 6 NUMERI'!$B$14)^9 | E16: =MAX(0,E15-G15*(1-F15)) | F16: =IF(C16<=0,0,MEDIAN(0,(C16-E16)/C16,1)) | G16: =IF(C16<=0,0,D16/(1-'1 - I TUOI 6 NUMERI'!$B$15*F16)) | H16: ='1 - I TUOI 6 NUMERI'!$B$15*G16*F16 | I16: =IF(C16<=0,0,'1 - I TUOI 6 NUMERI'!$B$16*C16) | J16: =IF(C16<=0,0,(C16-G16-I16)*(1+'1 - I TUOI 6 NUMERI'!$B$18)) | L16: =J16/(1+'1 - I TUOI 6 NUMERI'!$B$14)^10
A17: ='1 - I TUOI 6 NUMERI'!$B$5+10 | B17: =2026+10 | C17: =J16 | D17: ='1 - I TUOI 6 NUMERI'!$B$7*(1+'1 - I TUOI 6 NUMERI'!$B$14)^10 | E17: =MAX(0,E16-G16*(1-F16)) | F17: =IF(C17<=0,0,MEDIAN(0,(C17-E17)/C17,1)) | G17: =IF(C17<=0,0,D17/(1-'1 - I TUOI 6 NUMERI'!$B$15*F17)) | H17: ='1 - I TUOI 6 NUMERI'!$B$15*G17*F17 | I17: =IF(C17<=0,0,'1 - I TUOI 6 NUMERI'!$B$16*C17) | J17: =IF(C17<=0,0,(C17-G17-I17)*(1+'1 - I TUOI 6 NUMERI'!$B$18)) | L17: =J17/(1+'1 - I TUOI 6 NUMERI'!$B$14)^11
A18: ='1 - I TUOI 6 NUMERI'!$B$5+11 | B18: =2026+11 | C18: =J17 | D18: ='1 - I TUOI 6 NUMERI'!$B$7*(1+'1 - I TUOI 6 NUMERI'!$B$14)^11 | E18: =MAX(0,E17-G17*(1-F17)) | F18: =IF(C18<=0,0,MEDIAN(0,(C18-E18)/C18,1)) | G18: =IF(C18<=0,0,D18/(1-'1 - I TUOI 6 NUMERI'!$B$15*F18)) | H18: ='1 - I TUOI 6 NUMERI'!$B$15*G18*F18 | I18: =IF(C18<=0,0,'1 - I TUOI 6 NUMERI'!$B$16*C18) | J18: =IF(C18<=0,0,(C18-G18-I18)*(1+'1 - I TUOI 6 NUMERI'!$B$18)) | L18: =J18/(1+'1 - I TUOI 6 NUMERI'!$B$14)^12
A19: ='1 - I TUOI 6 NUMERI'!$B$5+12 | B19: =2026+12 | C19: =J18 | D19: ='1 - I TUOI 6 NUMERI'!$B$7*(1+'1 - I TUOI 6 NUMERI'!$B$14)^12 | E19: =MAX(0,E18-G18*(1-F18)) | F19: =IF(C19<=0,0,MEDIAN(0,(C19-E19)/C19,1)) | G19: =IF(C19<=0,0,D19/(1-'1 - I TUOI 6 NUMERI'!$B$15*F19)) | H19: ='1 - I TUOI 6 NUMERI'!$B$15*G19*F19 | I19: =IF(C19<=0,0,'1 - I TUOI 6 NUMERI'!$B$16*C19) | J19: =IF(C19<=0,0,(C19-G19-I19)*(1+'1 - I TUOI 6 NUMERI'!$B$18)) | L19: =J19/(1+'1 - I TUOI 6 NUMERI'!$B$14)^13
A20: ='1 - I TUOI 6 NUMERI'!$B$5+13 | B20: =2026+13 | C20: =J19 | D20: ='1 - I TUOI 6 NUMERI'!$B$7*(1+'1 - I TUOI 6 NUMERI'!$B$14)^13 | E20: =MAX(0,E19-G19*(1-F19)) | F20: =IF(C20<=0,0,MEDIAN(0,(C20-E20)/C20,1)) | G20: =IF(C20<=0,0,D20/(1-'1 - I TUOI 6 NUMERI'!$B$15*F20)) | H20: ='1 - I TUOI 6 NUMERI'!$B$15*G20*F20 | I20: =IF(C20<=0,0,'1 - I TUOI 6 NUMERI'!$B$16*C20) | J20: =IF(C20<=0,0,(C20-G20-I20)*(1+'1 - I TUOI 6 NUMERI'!$B$18)) | L20: =J20/(1+'1 - I TUOI 6 NUMERI'!$B$14)^14
A21: ='1 - I TUOI 6 NUMERI'!$B$5+14 | B21: =2026+14 | C21: =J20 | D21: ='1 - I TUOI 6 NUMERI'!$B$7*(1+'1 - I TUOI 6 NUMERI'!$B$14)^14 | E21: =MAX(0,E20-G20*(1-F20)) | F21: =IF(C21<=0,0,MEDIAN(0,(C21-E21)/C21,1)) | G21: =IF(C21<=0,0,D21/(1-'1 - I TUOI 6 NUMERI'!$B$15*F21)) | H21: ='1 - I TUOI 6 NUMERI'!$B$15*G21*F21 | I21: =IF(C21<=0,0,'1 - I TUOI 6 NUMERI'!$B$16*C21) | J21: =IF(C21<=0,0,(C21-G21-I21)*(1+'1 - I TUOI 6 NUMERI'!$B$18)) | L21: =J21/(1+'1 - I TUOI 6 NUMERI'!$B$14)^15
A22: ='1 - I TUOI 6 NUMERI'!$B$5+15 | B22: =2026+15 | C22: =J21 | D22: ='1 - I TUOI 6 NUMERI'!$B$7*(1+'1 - I TUOI 6 NUMERI'!$B$14)^15 | E22: =MAX(0,E21-G21*(1-F21)) | F22: =IF(C22<=0,0,MEDIAN(0,(C22-E22)/C22,1)) | G22: =IF(C22<=0,0,D22/(1-'1 - I TUOI 6 NUMERI'!$B$15*F22)) | H22: ='1 - I TUOI 6 NUMERI'!$B$15*G22*F22 | I22: =IF(C22<=0,0,'1 - I TUOI 6 NUMERI'!$B$16*C22) | J22: =IF(C22<=0,0,(C22-G22-I22)*(1+'1 - I TUOI 6 NUMERI'!$B$18)) | L22: =J22/(1+'1 - I TUOI 6 NUMERI'!$B$14)^16
A23: ='1 - I TUOI 6 NUMERI'!$B$5+16 | B23: =2026+16 | C23: =J22 | D23: ='1 - I TUOI 6 NUMERI'!$B$7*(1+'1 - I TUOI 6 NUMERI'!$B$14)^16 | E23: =MAX(0,E22-G22*(1-F22)) | F23: =IF(C23<=0,0,MEDIAN(0,(C23-E23)/C23,1)) | G23: =IF(C23<=0,0,D23/(1-'1 - I TUOI 6 NUMERI'!$B$15*F23)) | H23: ='1 - I TUOI 6 NUMERI'!$B$15*G23*F23 | I23: =IF(C23<=0,0,'1 - I TUOI 6 NUMERI'!$B$16*C23) | J23: =IF(C23<=0,0,(C23-G23-I23)*(1+'1 - I TUOI 6 NUMERI'!$B$18)) | L23: =J23/(1+'1 - I TUOI 6 NUMERI'!$B$14)^17
A24: ='1 - I TUOI 6 NUMERI'!$B$5+17 | B24: =2026+17 | C24: =J23 | D24: ='1 - I TUOI 6 NUMERI'!$B$7*(1+'1 - I TUOI 6 NUMERI'!$B$14)^17 | E24: =MAX(0,E23-G23*(1-F23)) | F24: =IF(C24<=0,0,MEDIAN(0,(C24-E24)/C24,1)) | G24: =IF(C24<=0,0,D24/(1-'1 - I TUOI 6 NUMERI'!$B$15*F24)) | H24: ='1 - I TUOI 6 NUMERI'!$B$15*G24*F24 | I24: =IF(C24<=0,0,'1 - I TUOI 6 NUMERI'!$B$16*C24) | J24: =IF(C24<=0,0,(C24-G24-I24)*(1+'1 - I TUOI 6 NUMERI'!$B$18)) | L24: =J24/(1+'1 - I TUOI 6 NUMERI'!$B$14)^18
A25: ='1 - I TUOI 6 NUMERI'!$B$5+18 | B25: =2026+18 | C25: =J24 | D25: ='1 - I TUOI 6 NUMERI'!$B$7*(1+'1 - I TUOI 6 NUMERI'!$B$14)^18 | E25: =MAX(0,E24-G24*(1-F24)) | F25: =IF(C25<=0,0,MEDIAN(0,(C25-E25)/C25,1)) | G25: =IF(C25<=0,0,D25/(1-'1 - I TUOI 6 NUMERI'!$B$15*F25)) | H25: ='1 - I TUOI 6 NUMERI'!$B$15*G25*F25 | I25: =IF(C25<=0,0,'1 - I TUOI 6 NUMERI'!$B$16*C25) | J25: =IF(C25<=0,0,(C25-G25-I25)*(1+'1 - I TUOI 6 NUMERI'!$B$18)) | L25: =J25/(1+'1 - I TUOI 6 NUMERI'!$B$14)^19
A26: ='1 - I TUOI 6 NUMERI'!$B$5+19 | B26: =2026+19 | C26: =J25 | D26: ='1 - I TUOI 6 NUMERI'!$B$7*(1+'1 - I TUOI 6 NUMERI'!$B$14)^19 | E26: =MAX(0,E25-G25*(1-F25)) | F26: =IF(C26<=0,0,MEDIAN(0,(C26-E26)/C26,1)) | G26: =IF(C26<=0,0,D26/(1-'1 - I TUOI 6 NUMERI'!$B$15*F26)) | H26: ='1 - I TUOI 6 NUMERI'!$B$15*G26*F26 | I26: =IF(C26<=0,0,'1 - I TUOI 6 NUMERI'!$B$16*C26) | J26: =IF(C26<=0,0,(C26-G26-I26)*(1+'1 - I TUOI 6 NUMERI'!$B$18)) | L26: =J26/(1+'1 - I TUOI 6 NUMERI'!$B$14)^20
A27: ='1 - I TUOI 6 NUMERI'!$B$5+20 | B27: =2026+20 | C27: =J26 | D27: ='1 - I TUOI 6 NUMERI'!$B$7*(1+'1 - I TUOI 6 NUMERI'!$B$14)^20 | E27: =MAX(0,E26-G26*(1-F26)) | F27: =IF(C27<=0,0,MEDIAN(0,(C27-E27)/C27,1)) | G27: =IF(C27<=0,0,D27/(1-'1 - I TUOI 6 NUMERI'!$B$15*F27)) | H27: ='1 - I TUOI 6 NUMERI'!$B$15*G27*F27 | I27: =IF(C27<=0,0,'1 - I TUOI 6 NUMERI'!$B$16*C27) | J27: =IF(C27<=0,0,(C27-G27-I27)*(1+'1 - I TUOI 6 NUMERI'!$B$18)) | L27: =J27/(1+'1 - I TUOI 6 NUMERI'!$B$14)^21
A28: ='1 - I TUOI 6 NUMERI'!$B$5+21 | B28: =2026+21 | C28: =J27 | D28: ='1 - I TUOI 6 NUMERI'!$B$7*(1+'1 - I TUOI 6 NUMERI'!$B$14)^21 | E28: =MAX(0,E27-G27*(1-F27)) | F28: =IF(C28<=0,0,MEDIAN(0,(C28-E28)/C28,1)) | G28: =IF(C28<=0,0,D28/(1-'1 - I TUOI 6 NUMERI'!$B$15*F28)) | H28: ='1 - I TUOI 6 NUMERI'!$B$15*G28*F28 | I28: =IF(C28<=0,0,'1 - I TUOI 6 NUMERI'!$B$16*C28) | J28: =IF(C28<=0,0,(C28-G28-I28)*(1+'1 - I TUOI 6 NUMERI'!$B$18)) | L28: =J28/(1+'1 - I TUOI 6 NUMERI'!$B$14)^22
A29: ='1 - I TUOI 6 NUMERI'!$B$5+22 | B29: =2026+22 | C29: =J28 | D29: ='1 - I TUOI 6 NUMERI'!$B$7*(1+'1 - I TUOI 6 NUMERI'!$B$14)^22 | E29: =MAX(0,E28-G28*(1-F28)) | F29: =IF(C29<=0,0,MEDIAN(0,(C29-E29)/C29,1)) | G29: =IF(C29<=0,0,D29/(1-'1 - I TUOI 6 NUMERI'!$B$15*F29)) | H29: ='1 - I TUOI 6 NUMERI'!$B$15*G29*F29 | I29: =IF(C29<=0,0,'1 - I TUOI 6 NUMERI'!$B$16*C29) | J29: =IF(C29<=0,0,(C29-G29-I29)*(1+'1 - I TUOI 6 NUMERI'!$B$18)) | L29: =J29/(1+'1 - I TUOI 6 NUMERI'!$B$14)^23
A30: ='1 - I TUOI 6 NUMERI'!$B$5+23 | B30: =2026+23 | C30: =J29 | D30: ='1 - I TUOI 6 NUMERI'!$B$7*(1+'1 - I TUOI 6 NUMERI'!$B$14)^23 | E30: =MAX(0,E29-G29*(1-F29)) | F30: =IF(C30<=0,0,MEDIAN(0,(C30-E30)/C30,1)) | G30: =IF(C30<=0,0,D30/(1-'1 - I TUOI 6 NUMERI'!$B$15*F30)) | H30: ='1 - I TUOI 6 NUMERI'!$B$15*G30*F30 | I30: =IF(C30<=0,0,'1 - I TUOI 6 NUMERI'!$B$16*C30) | J30: =IF(C30<=0,0,(C30-G30-I30)*(1+'1 - I TUOI 6 NUMERI'!$B$18)) | L30: =J30/(1+'1 - I TUOI 6 NUMERI'!$B$14)^24
A31: ='1 - I TUOI 6 NUMERI'!$B$5+24 | B31: =2026+24 | C31: =J30 | D31: ='1 - I TUOI 6 NUMERI'!$B$7*(1+'1 - I TUOI 6 NUMERI'!$B$14)^24 | E31: =MAX(0,E30-G30*(1-F30)) | F31: =IF(C31<=0,0,MEDIAN(0,(C31-E31)/C31,1)) | G31: =IF(C31<=0,0,D31/(1-'1 - I TUOI 6 NUMERI'!$B$15*F31)) | H31: ='1 - I TUOI 6 NUMERI'!$B$15*G31*F31 | I31: =IF(C31<=0,0,'1 - I TUOI 6 NUMERI'!$B$16*C31) | J31: =IF(C31<=0,0,(C31-G31-I31)*(1+'1 - I TUOI 6 NUMERI'!$B$18)) | L31: =J31/(1+'1 - I TUOI 6 NUMERI'!$B$14)^25
A32: ='1 - I TUOI 6 NUMERI'!$B$5+25 | B32: =2026+25 | C32: =J31 | D32: ='1 - I TUOI 6 NUMERI'!$B$7*(1+'1 - I TUOI 6 NUMERI'!$B$14)^25 | E32: =MAX(0,E31-G31*(1-F31)) | F32: =IF(C32<=0,0,MEDIAN(0,(C32-E32)/C32,1)) | G32: =IF(C32<=0,0,D32/(1-'1 - I TUOI 6 NUMERI'!$B$15*F32)) | H32: ='1 - I TUOI 6 NUMERI'!$B$15*G32*F32 | I32: =IF(C32<=0,0,'1 - I TUOI 6 NUMERI'!$B$16*C32) | J32: =IF(C32<=0,0,(C32-G32-I32)*(1+'1 - I TUOI 6 NUMERI'!$B$18)) | L32: =J32/(1+'1 - I TUOI 6 NUMERI'!$B$14)^26
A33: ='1 - I TUOI 6 NUMERI'!$B$5+26 | B33: =2026+26 | C33: =J32 | D33: ='1 - I TUOI 6 NUMERI'!$B$7*(1+'1 - I TUOI 6 NUMERI'!$B$14)^26 | E33: =MAX(0,E32-G32*(1-F32)) | F33: =IF(C33<=0,0,MEDIAN(0,(C33-E33)/C33,1)) | G33: =IF(C33<=0,0,D33/(1-'1 - I TUOI 6 NUMERI'!$B$15*F33)) | H33: ='1 - I TUOI 6 NUMERI'!$B$15*G33*F33 | I33: =IF(C33<=0,0,'1 - I TUOI 6 NUMERI'!$B$16*C33) | J33: =IF(C33<=0,0,(C33-G33-I33)*(1+'1 - I TUOI 6 NUMERI'!$B$18)) | L33: =J33/(1+'1 - I TUOI 6 NUMERI'!$B$14)^27
A34: ='1 - I TUOI 6 NUMERI'!$B$5+27 | B34: =2026+27 | C34: =J33 | D34: ='1 - I TUOI 6 NUMERI'!$B$7*(1+'1 - I TUOI 6 NUMERI'!$B$14)^27 | E34: =MAX(0,E33-G33*(1-F33)) | F34: =IF(C34<=0,0,MEDIAN(0,(C34-E34)/C34,1)) | G34: =IF(C34<=0,0,D34/(1-'1 - I TUOI 6 NUMERI'!$B$15*F34)) | H34: ='1 - I TUOI 6 NUMERI'!$B$15*G34*F34 | I34: =IF(C34<=0,0,'1 - I TUOI 6 NUMERI'!$B$16*C34) | J34: =IF(C34<=0,0,(C34-G34-I34)*(1+'1 - I TUOI 6 NUMERI'!$B$18)) | L34: =J34/(1+'1 - I TUOI 6 NUMERI'!$B$14)^28
A35: ='1 - I TUOI 6 NUMERI'!$B$5+28 | B35: =2026+28 | C35: =J34 | D35: ='1 - I TUOI 6 NUMERI'!$B$7*(1+'1 - I TUOI 6 NUMERI'!$B$14)^28 | E35: =MAX(0,E34-G34*(1-F34)) | F35: =IF(C35<=0,0,MEDIAN(0,(C35-E35)/C35,1)) | G35: =IF(C35<=0,0,D35/(1-'1 - I TUOI 6 NUMERI'!$B$15*F35)) | H35: ='1 - I TUOI 6 NUMERI'!$B$15*G35*F35 | I35: =IF(C35<=0,0,'1 - I TUOI 6 NUMERI'!$B$16*C35) | J35: =IF(C35<=0,0,(C35-G35-I35)*(1+'1 - I TUOI 6 NUMERI'!$B$18)) | L35: =J35/(1+'1 - I TUOI 6 NUMERI'!$B$14)^29
A36: ='1 - I TUOI 6 NUMERI'!$B$5+29 | B36: =2026+29 | C36: =J35 | D36: ='1 - I TUOI 6 NUMERI'!$B$7*(1+'1 - I TUOI 6 NUMERI'!$B$14)^29 | E36: =MAX(0,E35-G35*(1-F35)) | F36: =IF(C36<=0,0,MEDIAN(0,(C36-E36)/C36,1)) | G36: =IF(C36<=0,0,D36/(1-'1 - I TUOI 6 NUMERI'!$B$15*F36)) | H36: ='1 - I TUOI 6 NUMERI'!$B$15*G36*F36 | I36: =IF(C36<=0,0,'1 - I TUOI 6 NUMERI'!$B$16*C36) | J36: =IF(C36<=0,0,(C36-G36-I36)*(1+'1 - I TUOI 6 NUMERI'!$B$18)) | L36: =J36/(1+'1 - I TUOI 6 NUMERI'!$B$14)^30
A37: ='1 - I TUOI 6 NUMERI'!$B$5+30 | B37: =2026+30 | C37: =J36 | D37: ='1 - I TUOI 6 NUMERI'!$B$7*(1+'1 - I TUOI 6 NUMERI'!$B$14)^30 | E37: =MAX(0,E36-G36*(1-F36)) | F37: =IF(C37<=0,0,MEDIAN(0,(C37-E37)/C37,1)) | G37: =IF(C37<=0,0,D37/(1-'1 - I TUOI 6 NUMERI'!$B$15*F37)) | H37: ='1 - I TUOI 6 NUMERI'!$B$15*G37*F37 | I37: =IF(C37<=0,0,'1 - I TUOI 6 NUMERI'!$B$16*C37) | J37: =IF(C37<=0,0,(C37-G37-I37)*(1+'1 - I TUOI 6 NUMERI'!$B$18)) | L37: =J37/(1+'1 - I TUOI 6 NUMERI'!$B$14)^31
A38: ='1 - I TUOI 6 NUMERI'!$B$5+31 | B38: =2026+31 | C38: =J37 | D38: ='1 - I TUOI 6 NUMERI'!$B$7*(1+'1 - I TUOI 6 NUMERI'!$B$14)^31 | E38: =MAX(0,E37-G37*(1-F37)) | F38: =IF(C38<=0,0,MEDIAN(0,(C38-E38)/C38,1)) | G38: =IF(C38<=0,0,D38/(1-'1 - I TUOI 6 NUMERI'!$B$15*F38)) | H38: ='1 - I TUOI 6 NUMERI'!$B$15*G38*F38 | I38: =IF(C38<=0,0,'1 - I TUOI 6 NUMERI'!$B$16*C38) | J38: =IF(C38<=0,0,(C38-G38-I38)*(1+'1 - I TUOI 6 NUMERI'!$B$18)) | L38: =J38/(1+'1 - I TUOI 6 NUMERI'!$B$14)^32
A39: ='1 - I TUOI 6 NUMERI'!$B$5+32 | B39: =2026+32 | C39: =J38 | D39: ='1 - I TUOI 6 NUMERI'!$B$7*(1+'1 - I TUOI 6 NUMERI'!$B$14)^32 | E39: =MAX(0,E38-G38*(1-F38)) | F39: =IF(C39<=0,0,MEDIAN(0,(C39-E39)/C39,1)) | G39: =IF(C39<=0,0,D39/(1-'1 - I TUOI 6 NUMERI'!$B$15*F39)) | H39: ='1 - I TUOI 6 NUMERI'!$B$15*G39*F39 | I39: =IF(C39<=0,0,'1 - I TUOI 6 NUMERI'!$B$16*C39) | J39: =IF(C39<=0,0,(C39-G39-I39)*(1+'1 - I TUOI 6 NUMERI'!$B$18)) | L39: =J39/(1+'1 - I TUOI 6 NUMERI'!$B$14)^33
A40: ='1 - I TUOI 6 NUMERI'!$B$5+33 | B40: =2026+33 | C40: =J39 | D40: ='1 - I TUOI 6 NUMERI'!$B$7*(1+'1 - I TUOI 6 NUMERI'!$B$14)^33 | E40: =MAX(0,E39-G39*(1-F39)) | F40: =IF(C40<=0,0,MEDIAN(0,(C40-E40)/C40,1)) | G40: =IF(C40<=0,0,D40/(1-'1 - I TUOI 6 NUMERI'!$B$15*F40)) | H40: ='1 - I TUOI 6 NUMERI'!$B$15*G40*F40 | I40: =IF(C40<=0,0,'1 - I TUOI 6 NUMERI'!$B$16*C40) | J40: =IF(C40<=0,0,(C40-G40-I40)*(1+'1 - I TUOI 6 NUMERI'!$B$18)) | L40: =J40/(1+'1 - I TUOI 6 NUMERI'!$B$14)^34
A41: ='1 - I TUOI 6 NUMERI'!$B$5+34 | B41: =2026+34 | C41: =J40 | D41: ='1 - I TUOI 6 NUMERI'!$B$7*(1+'1 - I TUOI 6 NUMERI'!$B$14)^34 | E41: =MAX(0,E40-G40*(1-F40)) | F41: =IF(C41<=0,0,MEDIAN(0,(C41-E41)/C41,1)) | G41: =IF(C41<=0,0,D41/(1-'1 - I TUOI 6 NUMERI'!$B$15*F41)) | H41: ='1 - I TUOI 6 NUMERI'!$B$15*G41*F41 | I41: =IF(C41<=0,0,'1 - I TUOI 6 NUMERI'!$B$16*C41) | J41: =IF(C41<=0,0,(C41-G41-I41)*(1+'1 - I TUOI 6 NUMERI'!$B$18)) | L41: =J41/(1+'1 - I TUOI 6 NUMERI'!$B$14)^35
A42: ='1 - I TUOI 6 NUMERI'!$B$5+35 | B42: =2026+35 | C42: =J41 | D42: ='1 - I TUOI 6 NUMERI'!$B$7*(1+'1 - I TUOI 6 NUMERI'!$B$14)^35 | E42: =MAX(0,E41-G41*(1-F41)) | F42: =IF(C42<=0,0,MEDIAN(0,(C42-E42)/C42,1)) | G42: =IF(C42<=0,0,D42/(1-'1 - I TUOI 6 NUMERI'!$B$15*F42)) | H42: ='1 - I TUOI 6 NUMERI'!$B$15*G42*F42 | I42: =IF(C42<=0,0,'1 - I TUOI 6 NUMERI'!$B$16*C42) | J42: =IF(C42<=0,0,(C42-G42-I42)*(1+'1 - I TUOI 6 NUMERI'!$B$18)) | L42: =J42/(1+'1 - I TUOI 6 NUMERI'!$B$14)^36
A43: ='1 - I TUOI 6 NUMERI'!$B$5+36 | B43: =2026+36 | C43: =J42 | D43: ='1 - I TUOI 6 NUMERI'!$B$7*(1+'1 - I TUOI 6 NUMERI'!$B$14)^36 | E43: =MAX(0,E42-G42*(1-F42)) | F43: =IF(C43<=0,0,MEDIAN(0,(C43-E43)/C43,1)) | G43: =IF(C43<=0,0,D43/(1-'1 - I TUOI 6 NUMERI'!$B$15*F43)) | H43: ='1 - I TUOI 6 NUMERI'!$B$15*G43*F43 | I43: =IF(C43<=0,0,'1 - I TUOI 6 NUMERI'!$B$16*C43) | J43: =IF(C43<=0,0,(C43-G43-I43)*(1+'1 - I TUOI 6 NUMERI'!$B$18)) | L43: =J43/(1+'1 - I TUOI 6 NUMERI'!$B$14)^37
A44: ='1 - I TUOI 6 NUMERI'!$B$5+37 | B44: =2026+37 | C44: =J43 | D44: ='1 - I TUOI 6 NUMERI'!$B$7*(1+'1 - I TUOI 6 NUMERI'!$B$14)^37 | E44: =MAX(0,E43-G43*(1-F43)) | F44: =IF(C44<=0,0,MEDIAN(0,(C44-E44)/C44,1)) | G44: =IF(C44<=0,0,D44/(1-'1 - I TUOI 6 NUMERI'!$B$15*F44)) | H44: ='1 - I TUOI 6 NUMERI'!$B$15*G44*F44 | I44: =IF(C44<=0,0,'1 - I TUOI 6 NUMERI'!$B$16*C44) | J44: =IF(C44<=0,0,(C44-G44-I44)*(1+'1 - I TUOI 6 NUMERI'!$B$18)) | L44: =J44/(1+'1 - I TUOI 6 NUMERI'!$B$14)^38
A45: ='1 - I TUOI 6 NUMERI'!$B$5+38 | B45: =2026+38 | C45: =J44 | D45: ='1 - I TUOI 6 NUMERI'!$B$7*(1+'1 - I TUOI 6 NUMERI'!$B$14)^38 | E45: =MAX(0,E44-G44*(1-F44)) | F45: =IF(C45<=0,0,MEDIAN(0,(C45-E45)/C45,1)) | G45: =IF(C45<=0,0,D45/(1-'1 - I TUOI 6 NUMERI'!$B$15*F45)) | H45: ='1 - I TUOI 6 NUMERI'!$B$15*G45*F45 | I45: =IF(C45<=0,0,'1 - I TUOI 6 NUMERI'!$B$16*C45) | J45: =IF(C45<=0,0,(C45-G45-I45)*(1+'1 - I TUOI 6 NUMERI'!$B$18)) | L45: =J45/(1+'1 - I TUOI 6 NUMERI'!$B$14)^39
A46: ='1 - I TUOI 6 NUMERI'!$B$5+39 | B46: =2026+39 | C46: =J45 | D46: ='1 - I TUOI 6 NUMERI'!$B$7*(1+'1 - I TUOI 6 NUMERI'!$B$14)^39 | E46: =MAX(0,E45-G45*(1-F45)) | F46: =IF(C46<=0,0,MEDIAN(0,(C46-E46)/C46,1)) | G46: =IF(C46<=0,0,D46/(1-'1 - I TUOI 6 NUMERI'!$B$15*F46)) | H46: ='1 - I TUOI 6 NUMERI'!$B$15*G46*F46 | I46: =IF(C46<=0,0,'1 - I TUOI 6 NUMERI'!$B$16*C46) | J46: =IF(C46<=0,0,(C46-G46-I46)*(1+'1 - I TUOI 6 NUMERI'!$B$18)) | L46: =J46/(1+'1 - I TUOI 6 NUMERI'!$B$14)^40
A47: ='1 - I TUOI 6 NUMERI'!$B$5+40 | B47: =2026+40 | C47: =J46 | D47: ='1 - I TUOI 6 NUMERI'!$B$7*(1+'1 - I TUOI 6 NUMERI'!$B$14)^40 | E47: =MAX(0,E46-G46*(1-F46)) | F47: =IF(C47<=0,0,MEDIAN(0,(C47-E47)/C47,1)) | G47: =IF(C47<=0,0,D47/(1-'1 - I TUOI 6 NUMERI'!$B$15*F47)) | H47: ='1 - I TUOI 6 NUMERI'!$B$15*G47*F47 | I47: =IF(C47<=0,0,'1 - I TUOI 6 NUMERI'!$B$16*C47) | J47: =IF(C47<=0,0,(C47-G47-I47)*(1+'1 - I TUOI 6 NUMERI'!$B$18)) | L47: =J47/(1+'1 - I TUOI 6 NUMERI'!$B$14)^41
A48: ='1 - I TUOI 6 NUMERI'!$B$5+41 | B48: =2026+41 | C48: =J47 | D48: ='1 - I TUOI 6 NUMERI'!$B$7*(1+'1 - I TUOI 6 NUMERI'!$B$14)^41 | E48: =MAX(0,E47-G47*(1-F47)) | F48: =IF(C48<=0,0,MEDIAN(0,(C48-E48)/C48,1)) | G48: =IF(C48<=0,0,D48/(1-'1 - I TUOI 6 NUMERI'!$B$15*F48)) | H48: ='1 - I TUOI 6 NUMERI'!$B$15*G48*F48 | I48: =IF(C48<=0,0,'1 - I TUOI 6 NUMERI'!$B$16*C48) | J48: =IF(C48<=0,0,(C48-G48-I48)*(1+'1 - I TUOI 6 NUMERI'!$B$18)) | L48: =J48/(1+'1 - I TUOI 6 NUMERI'!$B$14)^42
A49: ='1 - I TUOI 6 NUMERI'!$B$5+42 | B49: =2026+42 | C49: =J48 | D49: ='1 - I TUOI 6 NUMERI'!$B$7*(1+'1 - I TUOI 6 NUMERI'!$B$14)^42 | E49: =MAX(0,E48-G48*(1-F48)) | F49: =IF(C49<=0,0,MEDIAN(0,(C49-E49)/C49,1)) | G49: =IF(C49<=0,0,D49/(1-'1 - I TUOI 6 NUMERI'!$B$15*F49)) | H49: ='1 - I TUOI 6 NUMERI'!$B$15*G49*F49 | I49: =IF(C49<=0,0,'1 - I TUOI 6 NUMERI'!$B$16*C49) | J49: =IF(C49<=0,0,(C49-G49-I49)*(1+'1 - I TUOI 6 NUMERI'!$B$18)) | L49: =J49/(1+'1 - I TUOI 6 NUMERI'!$B$14)^43
A50: ='1 - I TUOI 6 NUMERI'!$B$5+43 | B50: =2026+43 | C50: =J49 | D50: ='1 - I TUOI 6 NUMERI'!$B$7*(1+'1 - I TUOI 6 NUMERI'!$B$14)^43 | E50: =MAX(0,E49-G49*(1-F49)) | F50: =IF(C50<=0,0,MEDIAN(0,(C50-E50)/C50,1)) | G50: =IF(C50<=0,0,D50/(1-'1 - I TUOI 6 NUMERI'!$B$15*F50)) | H50: ='1 - I TUOI 6 NUMERI'!$B$15*G50*F50 | I50: =IF(C50<=0,0,'1 - I TUOI 6 NUMERI'!$B$16*C50) | J50: =IF(C50<=0,0,(C50-G50-I50)*(1+'1 - I TUOI 6 NUMERI'!$B$18)) | L50: =J50/(1+'1 - I TUOI 6 NUMERI'!$B$14)^44
A51: ='1 - I TUOI 6 NUMERI'!$B$5+44 | B51: =2026+44 | C51: =J50 | D51: ='1 - I TUOI 6 NUMERI'!$B$7*(1+'1 - I TUOI 6 NUMERI'!$B$14)^44 | E51: =MAX(0,E50-G50*(1-F50)) | F51: =IF(C51<=0,0,MEDIAN(0,(C51-E51)/C51,1)) | G51: =IF(C51<=0,0,D51/(1-'1 - I TUOI 6 NUMERI'!$B$15*F51)) | H51: ='1 - I TUOI 6 NUMERI'!$B$15*G51*F51 | I51: =IF(C51<=0,0,'1 - I TUOI 6 NUMERI'!$B$16*C51) | J51: =IF(C51<=0,0,(C51-G51-I51)*(1+'1 - I TUOI 6 NUMERI'!$B$18)) | L51: =J51/(1+'1 - I TUOI 6 NUMERI'!$B$14)^45
A52: ='1 - I TUOI 6 NUMERI'!$B$5+45 | B52: =2026+45 | C52: =J51 | D52: ='1 - I TUOI 6 NUMERI'!$B$7*(1+'1 - I TUOI 6 NUMERI'!$B$14)^45 | E52: =MAX(0,E51-G51*(1-F51)) | F52: =IF(C52<=0,0,MEDIAN(0,(C52-E52)/C52,1)) | G52: =IF(C52<=0,0,D52/(1-'1 - I TUOI 6 NUMERI'!$B$15*F52)) | H52: ='1 - I TUOI 6 NUMERI'!$B$15*G52*F52 | I52: =IF(C52<=0,0,'1 - I TUOI 6 NUMERI'!$B$16*C52) | J52: =IF(C52<=0,0,(C52-G52-I52)*(1+'1 - I TUOI 6 NUMERI'!$B$18)) | L52: =J52/(1+'1 - I TUOI 6 NUMERI'!$B$14)^46
A54: Totale imposte pagate | C54: =SUM(H7:H52)
A55: Totale bollo pagato | C55: =SUM(I7:I52)
A57: Se sommi le due righe qui sopra ottieni il conto che quasi nessuna simulazione di decumulo mostra: quanto se ne va in tasse e bollo lungo tutto il percorso. È la ragione per cui la stessa spesa che «sulla carta» durerebbe più di vent'anni, nella realtà italiana ne dura parecchi di meno.

Sheet 3 - MATRICE
A1: A che età finisce il capitale
A2: Strumento informativo / divulgativo. NON è consulenza finanziaria. I valori sono indicativi al 2026 e vanno verificati col tuo consulente.
A4: Righe: quanto spendi in un anno. Colonne: quanto rende il portafoglio in termini REALI, cioè già al netto dell'inflazione. Ogni cella è l'età a cui il capitale arriva a zero, calcolata con lo stesso motore del foglio 2 e con il TUO capitale e la TUA plusvalenza latente. La riga che conta è quella della tua spesa vera.
A6: Spesa annua netta | B6: Reale 1% | C6: Reale 3% | D6: Reale 5%
A7: 18.000 € | B7: ='1 - I TUOI 6 NUMERI'!$B$5+COUNTIF(G22:G67,">0") | C7: ='1 - I TUOI 6 NUMERI'!$B$5+COUNTIF(I22:I67,">0") | D7: ='1 - I TUOI 6 NUMERI'!$B$5+COUNTIF(K22:K67,">0")
A8: 24.000 € | B8: ='1 - I TUOI 6 NUMERI'!$B$5+COUNTIF(M22:M67,">0") | C8: ='1 - I TUOI 6 NUMERI'!$B$5+COUNTIF(O22:O67,">0") | D8: ='1 - I TUOI 6 NUMERI'!$B$5+COUNTIF(Q22:Q67,">0")
A9: 30.000 € | B9: ='1 - I TUOI 6 NUMERI'!$B$5+COUNTIF(S22:S67,">0") | C9: ='1 - I TUOI 6 NUMERI'!$B$5+COUNTIF(U22:U67,">0") | D9: ='1 - I TUOI 6 NUMERI'!$B$5+COUNTIF(W22:W67,">0")
A10: 36.000 € | B10: ='1 - I TUOI 6 NUMERI'!$B$5+COUNTIF(Y22:Y67,">0") | C10: ='1 - I TUOI 6 NUMERI'!$B$5+COUNTIF(AA22:AA67,">0") | D10: ='1 - I TUOI 6 NUMERI'!$B$5+COUNTIF(AC22:AC67,">0")
A12: Età della pensione pubblica | B12: ='1 - I TUOI 6 NUMERI'!$B$10
A13: Confronta ogni cella con questo numero: se l'età nella cella è più bassa, quel piano non arriva alla pensione. Nota che il rendimento non è una tua scelta: è la variabile su cui non hai nessun controllo, e sposta il risultato di anni.
F19: MOTORE DI CALCOLO — non modificare
F20: t | G20: 18k @ 1% | I20: 18k @ 3% | K20: 18k @ 5% | M20: 24k @ 1% | O20: 24k @ 3% | Q20: 24k @ 5% | S20: 30k @ 1% | U20: 30k @ 3% | W20: 30k @ 5% | Y20: 36k @ 1% | AA20: 36k @ 3% | AC20: 36k @ 5%
G21: cap. fine | H21: base | I21: cap. fine | J21: base | K21: cap. fine | L21: base | M21: cap. fine | N21: base | O21: cap. fine | P21: base | Q21: cap. fine | R21: base | S21: cap. fine | T21: base | U21: cap. fine | V21: base | W21: cap. fine | X21: base | Y21: cap. fine | Z21: base | AA21: cap. fine | AB21: base | AC21: cap. fine | AD21: base
F22: 0 | G22: =IF('1 - I TUOI 6 NUMERI'!$B$6<=0,0,('1 - I TUOI 6 NUMERI'!$B$6-(IF('1 - I TUOI 6 NUMERI'!$B$6<=0,0,(18000*(1+'1 - I TUOI 6 NUMERI'!$B$14)^0)/(1-'1 - I TUOI 6 NUMERI'!$B$15*(IF('1 - I TUOI 6 NUMERI'!$B$6<=0,0,MEDIAN(0,('1 - I TUOI 6 NUMERI'!$B$6-'1 - I TUOI 6 NUMERI'!$B$17)/'1 - I TUOI 6 NUMERI'!$B$6,1))))))-(IF('1 - I TUOI 6 NUMERI'!$B$6<=0,0,'1 - I TUOI 6 NUMERI'!$B$16*'1 - I TUOI 6 NUMERI'!$B$6)))*(1+((1+0.01)*(1+'1 - I TUOI 6 NUMERI'!$B$14)-1))) | H22: =MAX(0,'1 - I TUOI 6 NUMERI'!$B$17-(IF('1 - I TUOI 6 NUMERI'!$B$6<=0,0,(18000*(1+'1 - I TUOI 6 NUMERI'!$B$14)^0)/(1-'1 - I TUOI 6 NUMERI'!$B$15*(IF('1 - I TUOI 6 NUMERI'!$B$6<=0,0,MEDIAN(0,('1 - I TUOI 6 NUMERI'!$B$6-'1 - I TUOI 6 NUMERI'!$B$17)/'1 - I TUOI 6 NUMERI'!$B$6,1))))))*(1-(IF('1 - I TUOI 6 NUMERI'!$B$6<=0,0,MEDIAN(0,('1 - I TUOI 6 NUMERI'!$B$6-'1 - I TUOI 6 NUMERI'!$B$17)/'1 - I TUOI 6 NUMERI'!$B$6,1))))) | I22: =IF('1 - I TUOI 6 NUMERI'!$B$6<=0,0,('1 - I TUOI 6 NUMERI'!$B$6-(IF('1 - I TUOI 6 NUMERI'!$B$6<=0,0,(18000*(1+'1 - I TUOI 6 NUMERI'!$B$14)^0)/(1-'1 - I TUOI 6 NUMERI'!$B$15*(IF('1 - I TUOI 6 NUMERI'!$B$6<=0,0,MEDIAN(0,('1 - I TUOI 6 NUMERI'!$B$6-'1 - I TUOI 6 NUMERI'!$B$17)/'1 - I TUOI 6 NUMERI'!$B$6,1))))))-(IF('1 - I TUOI 6 NUMERI'!$B$6<=0,0,'1 - I TUOI 6 NUMERI'!$B$16*'1 - I TUOI 6 NUMERI'!$B$6)))*(1+((1+0.03)*(1+'1 - I TUOI 6 NUMERI'!$B$14)-1))) | J22: =MAX(0,'1 - I TUOI 6 NUMERI'!$B$17-(IF('1 - I TUOI 6 NUMERI'!$B$6<=0,0,(18000*(1+'1 - I TUOI 6 NUMERI'!$B$14)^0)/(1-'1 - I TUOI 6 NUMERI'!$B$15*(IF('1 - I TUOI 6 NUMERI'!$B$6<=0,0,MEDIAN(0,('1 - I TUOI 6 NUMERI'!$B$6-'1 - I TUOI 6 NUMERI'!$B$17)/'1 - I TUOI 6 NUMERI'!$B$6,1))))))*(1-(IF('1 - I TUOI 6 NUMERI'!$B$6<=0,0,MEDIAN(0,('1 - I TUOI 6 NUMERI'!$B$6-'1 - I TUOI 6 NUMERI'!$B$17)/'1 - I TUOI 6 NUMERI'!$B$6,1))))) | K22: =IF('1 - I TUOI 6 NUMERI'!$B$6<=0,0,('1 - I TUOI 6 NUMERI'!$B$6-(IF('1 - I TUOI 6 NUMERI'!$B$6<=0,0,(18000*(1+'1 - I TUOI 6 NUMERI'!$B$14)^0)/(1-'1 - I TUOI 6 NUMERI'!$B$15*(IF('1 - I TUOI 6 NUMERI'!$B$6<=0,0,MEDIAN(0,('1 - I TUOI 6 NUMERI'!$B$6-'1 - I TUOI 6 NUMERI'!$B$17)/'1 - I TUOI 6 NUMERI'!$B$6,1))))))-(IF('1 - I TUOI 6 NUMERI'!$B$6<=0,0,'1 - I TUOI 6 NUMERI'!$B$16*'1 - I TUOI 6 NUMERI'!$B$6)))*(1+((1+0.05)*(1+'1 - I TUOI 6 NUMERI'!$B$14)-1))) | L22: =MAX(0,'1 - I TUOI 6 NUMERI'!$B$17-(IF('1 - I TUOI 6 NUMERI'!$B$6<=0,0,(18000*(1+'1 - I TUOI 6 NUMERI'!$B$14)^0)/(1-'1 - I TUOI 6 NUMERI'!$B$15*(IF('1 - I TUOI 6 NUMERI'!$B$6<=0,0,MEDIAN(0,('1 - I TUOI 6 NUMERI'!$B$6-'1 - I TUOI 6 NUMERI'!$B$17)/'1 - I TUOI 6 NUMERI'!$B$6,1))))))*(1-(IF('1 - I TUOI 6 NUMERI'!$B$6<=0,0,MEDIAN(0,('1 - I TUOI 6 NUMERI'!$B$6-'1 - I TUOI 6 NUMERI'!$B$17)/'1 - I TUOI 6 NUMERI'!$B$6,1))))) | M22: =IF('1 - I TUOI 6 NUMERI'!$B$6<=0,0,('1 - I TUOI 6 NUMERI'!$B$6-(IF('1 - I TUOI 6 NUMERI'!$B$6<=0,0,(24000*(1+'1 - I TUOI 6 NUMERI'!$B$14)^0)/(1-'1 - I TUOI 6 NUMERI'!$B$15*(IF('1 - I TUOI 6 NUMERI'!$B$6<=0,0,MEDIAN(0,('1 - I TUOI 6 NUMERI'!$B$6-'1 - I TUOI 6 NUMERI'!$B$17)/'1 - I TUOI 6 NUMERI'!$B$6,1))))))-(IF('1 - I TUOI 6 NUMERI'!$B$6<=0,0,'1 - I TUOI 6 NUMERI'!$B$16*'1 - I TUOI 6 NUMERI'!$B$6)))*(1+((1+0.01)*(1+'1 - I TUOI 6 NUMERI'!$B$14)-1))) | N22: =MAX(0,'1 - I TUOI 6 NUMERI'!$B$17-(IF('1 - I TUOI 6 NUMERI'!$B$6<=0,0,(24000*(1+'1 - I TUOI 6 NUMERI'!$B$14)^0)/(1-'1 - I TUOI 6 NUMERI'!$B$15*(IF('1 - I TUOI 6 NUMERI'!$B$6<=0,0,MEDIAN(0,('1 - I TUOI 6 NUMERI'!$B$6-'1 - I TUOI 6 NUMERI'!$B$17)/'1 - I TUOI 6 NUMERI'!$B$6,1))))))*(1-(IF('1 - I TUOI 6 NUMERI'!$B$6<=0,0,MEDIAN(0,('1 - I TUOI 6 NUMERI'!$B$6-'1 - I TUOI 6 NUMERI'!$B$17)/'1 - I TUOI 6 NUMERI'!$B$6,1))))) | O22: =IF('1 - I TUOI 6 NUMERI'!$B$6<=0,0,('1 - I TUOI 6 NUMERI'!$B$6-(IF('1 - I TUOI 6 NUMERI'!$B$6<=0,0,(24000*(1+'1 - I TUOI 6 NUMERI'!$B$14)^0)/(1-'1 - I TUOI 6 NUMERI'!$B$15*(IF('1 - I TUOI 6 NUMERI'!$B$6<=0,0,MEDIAN(0,('1 - I TUOI 6 NUMERI'!$B$6-'1 - I TUOI 6 NUMERI'!$B$17)/'1 - I TUOI 6 NUMERI'!$B$6,1))))))-(IF('1 - I TUOI 6 NUMERI'!$B$6<=0,0,'1 - I TUOI 6 NUMERI'!$B$16*'1 - I TUOI 6 NUMERI'!$B$6)))*(1+((1+0.03)*(1+'1 - I TUOI 6 NUMERI'!$B$14)-1))) | P22: =MAX(0,'1 - I TUOI 6 NUMERI'!$B$17-(IF('1 - I TUOI 6 NUMERI'!$B$6<=0,0,(24000*(1+'1 - I TUOI 6 NUMERI'!$B$14)^0)/(1-'1 - I TUOI 6 NUMERI'!$B$15*(IF('1 - I TUOI 6 NUMERI'!$B$6<=0,0,MEDIAN(0,('1 - I TUOI 6 NUMERI'!$B$6-'1 - I TUOI 6 NUMERI'!$B$17)/'1 - I TUOI 6 NUMERI'!$B$6,1))))))*(1-(IF('1 - I TUOI 6 NUMERI'!$B$6<=0,0,MEDIAN(0,('1 - I TUOI 6 NUMERI'!$B$6-'1 - I TUOI 6 NUMERI'!$B$17)/'1 - I TUOI 6 NUMERI'!$B$6,1))))) | Q22: =IF('1 - I TUOI 6 NUMERI'!$B$6<=0,0,('1 - I TUOI 6 NUMERI'!$B$6-(IF('1 - I TUOI 6 NUMERI'!$B$6<=0,0,(24000*(1+'1 - I TUOI 6 NUMERI'!$B$14)^0)/(1-'1 - I TUOI 6 NUMERI'!$B$15*(IF('1 - I TUOI 6 NUMERI'!$B$6<=0,0,MEDIAN(0,('1 - I TUOI 6 NUMERI'!$B$6-'1 - I TUOI 6 NUMERI'!$B$17)/'1 - I TUOI 6 NUMERI'!$B$6,1))))))-(IF('1 - I TUOI 6 NUMERI'!$B$6<=0,0,'1 - I TUOI 6 NUMERI'!$B$16*'1 - I TUOI 6 NUMERI'!$B$6)))*(1+((1+0.05)*(1+'1 - I TUOI 6 NUMERI'!$B$14)-1))) | R22: =MAX(0,'1 - I TUOI 6 NUMERI'!$B$17-(IF('1 - I TUOI 6 NUMERI'!$B$6<=0,0,(24000*(1+'1 - I TUOI 6 NUMERI'!$B$14)^0)/(1-'1 - I TUOI 6 NUMERI'!$B$15*(IF('1 - I TUOI 6 NUMERI'!$B$6<=0,0,MEDIAN(0,('1 - I TUOI 6 NUMERI'!$B$6-'1 - I TUOI 6 NUMERI'!$B$17)/'1 - I TUOI 6 NUMERI'!$B$6,1))))))*(1-(IF('1 - I TUOI 6 NUMERI'!$B$6<=0,0,MEDIAN(0,('1 - I TUOI 6 NUMERI'!$B$6-'1 - I TUOI 6 NUMERI'!$B$17)/'1 - I TUOI 6 NUMERI'!$B$6,1))))) | S22: =IF('1 - I TUOI 6 NUMERI'!$B$6<=0,0,('1 - I TUOI 6 NUMERI'!$B$6-(IF('1 - I TUOI 6 NUMERI'!$B$6<=0,0,(30000*(1+'1 - I TUOI 6 NUMERI'!$B$14)^0)/(1-'1 - I TUOI 6 NUMERI'!$B$15*(IF('1 - I TUOI 6 NUMERI'!$B$6<=0,0,MEDIAN(0,('1 - I TUOI 6 NUMERI'!$B$6-'1 - I TUOI 6 NUMERI'!$B$17)/'1 - I TUOI 6 NUMERI'!$B$6,1))))))-(IF('1 - I TUOI 6 NUMERI'!$B$6<=0,0,'1 - I TUOI 6 NUMERI'!$B$16*'1 - I TUOI 6 NUMERI'!$B$6)))*(1+((1+0.01)*(1+'1 - I TUOI 6 NUMERI'!$B$14)-1))) | T22: =MAX(0,'1 - I TUOI 6 NUMERI'!$B$17-(IF('1 - I TUOI 6 NUMERI'!$B$6<=0,0,(30000*(1+'1 - I TUOI 6 NUMERI'!$B$14)^0)/(1-'1 - I TUOI 6 NUMERI'!$B$15*(IF('1 - I TUOI 6 NUMERI'!$B$6<=0,0,MEDIAN(0,('1 - I TUOI 6 NUMERI'!$B$6-'1 - I TUOI 6 NUMERI'!$B$17)/'1 - I TUOI 6 NUMERI'!$B$6,1))))))*(1-(IF('1 - I TUOI 6 NUMERI'!$B$6<=0,0,MEDIAN(0,('1 - I TUOI 6 NUMERI'!$B$6-'1 - I TUOI 6 NUMERI'!$B$17)/'1 - I TUOI 6 NUMERI'!$B$6,1))))) | U22: =IF('1 - I TUOI 6 NUMERI'!$B$6<=0,0,('1 - I TUOI 6 NUMERI'!$B$6-(IF('1 - I TUOI 6 NUMERI'!$B$6<=0,0,(30000*(1+'1 - I TUOI 6 NUMERI'!$B$14)^0)/(1-'1 - I TUOI 6 NUMERI'!$B$15*(IF('1 - I TUOI 6 NUMERI'!$B$6<=0,0,MEDIAN(0,('1 - I TUOI 6 NUMERI'!$B$6-'1 - I TUOI 6 NUMERI'!$B$17)/'1 - I TUOI 6 NUMERI'!$B$6,1))))))-(IF('1 - I TUOI 6 NUMERI'!$B$6<=0,0,'1 - I TUOI 6 NUMERI'!$B$16*'1 - I TUOI 6 NUMERI'!$B$6)))*(1+((1+0.03)*(1+'1 - I TUOI 6 NUMERI'!$B$14)-1))) | V22: =MAX(0,'1 - I TUOI 6 NUMERI'!$B$17-(IF('1 - I TUOI 6 NUMERI'!$B$6<=0,0,(30000*(1+'1 - I TUOI 6 NUMERI'!$B$14)^0)/(1-'1 - I TUOI 6 NUMERI'!$B$15*(IF('1 - I TUOI 6 NUMERI'!$B$6<=0,0,MEDIAN(0,('1 - I TUOI 6 NUMERI'!$B$6-'1 - I TUOI 6 NUMERI'!$B$17)/'1 - I TUOI 6 NUMERI'!$B$6,1))))))*(1-(IF('1 - I TUOI 6 NUMERI'!$B$6<=0,0,MEDIAN(0,('1 - I TUOI 6 NUMERI'!$B$6-'1 - I TUOI 6 NUMERI'!$B$17)/'1 - I TUOI 6 NUMERI'!$B$6,1))))) | W22: =IF('1 - I TUOI 6 NUMERI'!$B$6<=0,0,('1 - I TUOI 6 NUMERI'!$B$6-(IF('1 - I TUOI 6 NUMERI'!$B$6<=0,0,(30000*(1+'1 - I TUOI 6 NUMERI'!$B$14)^0)/(1-'1 - I TUOI 6 NUMERI'!$B$15*(IF('1 - I TUOI 6 NUMERI'!$B$6<=0,0,MEDIAN(0,('1 - I TUOI 6 NUMERI'!$B$6-'1 - I TUOI 6 NUMERI'!$B$17)/'1 - I TUOI 6 NUMERI'!$B$6,1))))))-(IF('1 - I TUOI 6 NUMERI'!$B$6<=0,0,'1 - I TUOI 6 NUMERI'!$B$16*'1 - I TUOI 6 NUMERI'!$B$6)))*(1+((1+0.05)*(1+'1 - I TUOI 6 NUMERI'!$B$14)-1))) | X22: =MAX(0,'1 - I TUOI 6 NUMERI'!$B$17-(IF('1 - I TUOI 6 NUMERI'!$B$6<=0,0,(30000*(1+'1 - I TUOI 6 NUMERI'!$B$14)^0)/(1-'1 - I TUOI 6 NUMERI'!$B$15*(IF('1 - I TUOI 6 NUMERI'!$B$6<=0,0,MEDIAN(0,('1 - I TUOI 6 NUMERI'!$B$6-'1 - I TUOI 6 NUMERI'!$B$17)/'1 - I TUOI 6 NUMERI'!$B$6,1))))))*(1-(IF('1 - I TUOI 6 NUMERI'!$B$6<=0,0,MEDIAN(0,('1 - I TUOI 6 NUMERI'!$B$6-'1 - I TUOI 6 NUMERI'!$B$17)/'1 - I TUOI 6 NUMERI'!$B$6,1))))) | Y22: =IF('1 - I TUOI 6 NUMERI'!$B$6<=0,0,('1 - I TUOI 6 NUMERI'!$B$6-(IF('1 - I TUOI 6 NUMERI'!$B$6<=0,0,(36000*(1+'1 - I TUOI 6 NUMERI'!$B$14)^0)/(1-'1 - I TUOI 6 NUMERI'!$B$15*(IF('1 - I TUOI 6 NUMERI'!$B$6<=0,0,MEDIAN(0,('1 - I TUOI 6 NUMERI'!$B$6-'1 - I TUOI 6 NUMERI'!$B$17)/'1 - I TUOI 6 NUMERI'!$B$6,1))))))-(IF('1 - I TUOI 6 NUMERI'!$B$6<=0,0,'1 - I TUOI 6 NUMERI'!$B$16*'1 - I TUOI 6 NUMERI'!$B$6)))*(1+((1+0.01)*(1+'1 - I TUOI 6 NUMERI'!$B$14)-1))) | Z22: =MAX(0,'1 - I TUOI 6 NUMERI'!$B$17-(IF('1 - I TUOI 6 NUMERI'!$B$6<=0,0,(36000*(1+'1 - I TUOI 6 NUMERI'!$B$14)^0)/(1-'1 - I TUOI 6 NUMERI'!$B$15*(IF('1 - I TUOI 6 NUMERI'!$B$6<=0,0,MEDIAN(0,('1 - I TUOI 6 NUMERI'!$B$6-'1 - I TUOI 6 NUMERI'!$B$17)/'1 - I TUOI 6 NUMERI'!$B$6,1))))))*(1-(IF('1 - I TUOI 6 NUMERI'!$B$6<=0,0,MEDIAN(0,('1 - I TUOI 6 NUMERI'!$B$6-'1 - I TUOI 6 NUMERI'!$B$17)/'1 - I TUOI 6 NUMERI'!$B$6,1))))) | AA22: =IF('1 - I TUOI 6 NUMERI'!$B$6<=0,0,('1 - I TUOI 6 NUMERI'!$B$6-(IF('1 - I TUOI 6 NUMERI'!$B$6<=0,0,(36000*(1+'1 - I TUOI 6 NUMERI'!$B$14)^0)/(1-'1 - I TUOI 6 NUMERI'!$B$15*(IF('1 - I TUOI 6 NUMERI'!$B$6<=0,0,MEDIAN(0,('1 - I TUOI 6 NUMERI'!$B$6-'1 - I TUOI 6 NUMERI'!$B$17)/'1 - I TUOI 6 NUMERI'!$B$6,1))))))-(IF('1 - I TUOI 6 NUMERI'!$B$6<=0,0,'1 - I TUOI 6 NUMERI'!$B$16*'1 - I TUOI 6 NUMERI'!$B$6)))*(1+((1+0.03)*(1+'1 - I TUOI 6 NUMERI'!$B$14)-1))) | AB22: =MAX(0,'1 - I TUOI 6 NUMERI'!$B$17-(IF('1 - I TUOI 6 NUMERI'!$B$6<=0,0,(36000*(1+'1 - I TUOI 6 NUMERI'!$B$14)^0)/(1-'1 - I TUOI 6 NUMERI'!$B$15*(IF('1 - I TUOI 6 NUMERI'!$B$6<=0,0,MEDIAN(0,('1 - I TUOI 6 NUMERI'!$B$6-'1 - I TUOI 6 NUMERI'!$B$17)/'1 - I TUOI 6 NUMERI'!$B$6,1))))))*(1-(IF('1 - I TUOI 6 NUMERI'!$B$6<=0,0,MEDIAN(0,('1 - I TUOI 6 NUMERI'!$B$6-'1 - I TUOI 6 NUMERI'!$B$17)/'1 - I TUOI 6 NUMERI'!$B$6,1))))) | AC22: =IF('1 - I TUOI 6 NUMERI'!$B$6<=0,0,('1 - I TUOI 6 NUMERI'!$B$6-(IF('1 - I TUOI 6 NUMERI'!$B$6<=0,0,(36000*(1+'1 - I TUOI 6 NUMERI'!$B$14)^0)/(1-'1 - I TUOI 6 NUMERI'!$B$15*(IF('1 - I TUOI 6 NUMERI'!$B$6<=0,0,MEDIAN(0,('1 - I TUOI 6 NUMERI'!$B$6-'1 - I TUOI 6 NUMERI'!$B$17)/'1 - I TUOI 6 NUMERI'!$B$6,1))))))-(IF('1 - I TUOI 6 NUMERI'!$B$6<=0,0,'1 - I TUOI 6 NUMERI'!$B$16*'1 - I TUOI 6 NUMERI'!$B$6)))*(1+((1+0.05)*(1+'1 - I TUOI 6 NUMERI'!$B$14)-1))) | AD22: =MAX(0,'1 - I TUOI 6 NUMERI'!$B$17-(IF('1 - I TUOI 6 NUMERI'!$B$6<=0,0,(36000*(1+'1 - I TUOI 6 NUMERI'!$B$14)^0)/(1-'1 - I TUOI 6 NUMERI'!$B$15*(IF('1 - I TUOI 6 NUMERI'!$B$6<=0,0,MEDIAN(0,('1 - I TUOI 6 NUMERI'!$B$6-'1 - I TUOI 6 NUMERI'!$B$17)/'1 - I TUOI 6 NUMERI'!$B$6,1))))))*(1-(IF('1 - I TUOI 6 NUMERI'!$B$6<=0,0,MEDIAN(0,('1 - I TUOI 6 NUMERI'!$B$6-'1 - I TUOI 6 NUMERI'!$B$17)/'1 - I TUOI 6 NUMERI'!$B$6,1)))))
F23: 1 | G23: =IF(G22<=0,0,(G22-(IF(G22<=0,0,(18000*(1+'1 - I TUOI 6 NUMERI'!$B$14)^1)/(1-'1 - I TUOI 6 NUMERI'!$B$15*(IF(G22<=0,0,MEDIAN(0,(G22-H22)/G22,1))))))-(IF(G22<=0,0,'1 - I TUOI 6 NUMERI'!$B$16*G22)))*(1+((1+0.01)*(1+'1 - I TUOI 6 NUMERI'!$B$14)-1))) | H23: =MAX(0,H22-(IF(G22<=0,0,(18000*(1+'1 - I TUOI 6 NUMERI'!$B$14)^1)/(1-'1 - I TUOI 6 NUMERI'!$B$15*(IF(G22<=0,0,MEDIAN(0,(G22-H22)/G22,1))))))*(1-(IF(G22<=0,0,MEDIAN(0,(G22-H22)/G22,1))))) | I23: =IF(I22<=0,0,(I22-(IF(I22<=0,0,(18000*(1+'1 - I TUOI 6 NUMERI'!$B$14)^1)/(1-'1 - I TUOI 6 NUMERI'!$B$15*(IF(I22<=0,0,MEDIAN(0,(I22-J22)/I22,1))))))-(IF(I22<=0,0,'1 - I TUOI 6 NUMERI'!$B$16*I22)))*(1+((1+0.03)*(1+'1 - I TUOI 6 NUMERI'!$B$14)-1))) | J23: =MAX(0,J22-(IF(I22<=0,0,(18000*(1+'1 - I TUOI 6 NUMERI'!$B$14)^1)/(1-'1 - I TUOI 6 NUMERI'!$B$15*(IF(I22<=0,0,MEDIAN(0,(I22-J22)/I22,1))))))*(1-(IF(I22<=0,0,MEDIAN(0,(I22-J22)/I22,1))))) | K23: =IF(K22<=0,0,(K22-(IF(K22<=0,0,(18000*(1+'1 - I TUOI 6 NUMERI'!$B$14)^1)/(1-'1 - I TUOI 6 NUMERI'!$B$15*(IF(K22<=0,0,MEDIAN(0,(K22-L22)/K22,1))))))-(IF(K22<=0,0,'1 - I TUOI 6 NUMERI'!$B$16*K22)))*(1+((1+0.05)*(1+'1 - I TUOI 6 NUMERI'!$B$14)-1))) | L23: =MAX(0,L22-(IF(K22<=0,0,(18000*(1+'1 - I TUOI 6 NUMERI'!$B$14)^1)/(1-'1 - I TUOI 6 NUMERI'!$B$15*(IF(K22<=0,0,MEDIAN(0,(K22-L22)/K22,1))))))*(1-(IF(K22<=0,0,MEDIAN(0,(K22-L22)/K22,1))))) | M23: =IF(M22<=0,0,(M22-(IF(M22<=0,0,(24000*(1+'1 - I TUOI 6 NUMERI'!$B$14)^1)/(1-'1 - I TUOI 6 NUMERI'!$B$15*(IF(M22<=0,0,MEDIAN(0,(M22-N22)/M22,1))))))-(IF(M22<=0,0,'1 - I TUOI 6 NUMERI'!$B$16*M22)))*(1+((1+0.01)*(1+'1 - I TUOI 6 NUMERI'!$B$14)-1))) | N23: =MAX(0,N22-(IF(M22<=0,0,(24000*(1+'1 - I TUOI 6 NUMERI'!$B$14)^1)/(1-'1 - I TUOI 6 NUMERI'!$B$15*(IF(M22<=0,0,MEDIAN(0,(M22-N22)/M22,1))))))*(1-(IF(M22<=0,0,MEDIAN(0,(M22-N22)/M22,1))))) | O23: =IF(O22<=0,0,(O22-(IF(O22<=0,0,(24000*(1+'1 - I TUOI 6 NUMERI'!$B$14)^1)/(1-'1 - I TUOI 6 NUMERI'!$B$15*(IF(O22<=0,0,MEDIAN(0,(O22-P22)/O22,1))))))-(IF(O22<=0,0,'1 - I TUOI 6 NUMERI'!$B$16*O22)))*(1+((1+0.03)*(1+'1 - I TUOI 6 NUMERI'!$B$14)-1))) | P23: =MAX(0,P22-(IF(O22<=0,0,(24000*(1+'1 - I TUOI 6 NUMERI'!$B$14)^1)/(1-'1 - I TUOI 6 NUMERI'!$B$15*(IF(O22<=0,0,MEDIAN(0,(O22-P22)/O22,1))))))*(1-(IF(O22<=0,0,MEDIAN(0,(O22-P22)/O22,1))))) | Q23: =IF(Q22<=0,0,(Q22-(IF(Q22<=0,0,(24000*(1+'1 - I TUOI 6 NUMERI'!$B$14)^1)/(1-'1 - I TUOI 6 NUMERI'!$B$15*(IF(Q22<=0,0,MEDIAN(0,(Q22-R22)/Q22,1))))))-(IF(Q22<=0,0,'1 - I TUOI 6 NUMERI'!$B$16*Q22)))*(1+((1+0.05)*(1+'1 - I TUOI 6 NUMERI'!$B$14)-1))) | R23: =MAX(0,R22-(IF(Q22<=0,0,(24000*(1+'1 - I TUOI 6 NUMERI'!$B$14)^1)/(1-'1 - I TUOI 6 NUMERI'!$B$15*(IF(Q22<=0,0,MEDIAN(0,(Q22-R22)/Q22,1))))))*(1-(IF(Q22<=0,0,MEDIAN(0,(Q22-R22)/Q22,1))))) | S23: =IF(S22<=0,0,(S22-(IF(S22<=0,0,(30000*(1+'1 - I TUOI 6 NUMERI'!$B$14)^1)/(1-'1 - I TUOI 6 NUMERI'!$B$15*(IF(S22<=0,0,MEDIAN(0,(S22-T22)/S22,1))))))-(IF(S22<=0,0,'1 - I TUOI 6 NUMERI'!$B$16*S22)))*(1+((1+0.01)*(1+'1 - I TUOI 6 NUMERI'!$B$14)-1))) | T23: =MAX(0,T22-(IF(S22<=0,0,(30000*(1+'1 - I TUOI 6 NUMERI'!$B$14)^1)/(1-'1 - I TUOI 6 NUMERI'!$B$15*(IF(S22<=0,0,MEDIAN(0,(S22-T22)/S22,1))))))*(1-(IF(S22<=0,0,MEDIAN(0,(S22-T22)/S22,1))))) | U23: =IF(U22<=0,0,(U22-(IF(U22<=0,0,(30000*(1+'1 - I TUOI 6 NUMERI'!$B$14)^1)/(1-'1 - I TUOI 6 NUMERI'!$B$15*(IF(U22<=0,0,MEDIAN(0,(U22-V22)/U22,1))))))-(IF(U22<=0,0,'1 - I TUOI 6 NUMERI'!$B$16*U22)))*(1+((1+0.03)*(1+'1 - I TUOI 6 NUMERI'!$B$14)-1))) | V23: =MAX(0,V22-(IF(U22<=0,0,(30000*(1+'1 - I TUOI 6 NUMERI'!$B$14)^1)/(1-'1 - I TUOI 6 NUMERI'!$B$15*(IF(U22<=0,0,MEDIAN(0,(U22-V22)/U22,1))))))*(1-(IF(U22<=0,0,MEDIAN(0,(U22-V22)/U22,1))))) | W23: =IF(W22<=0,0,(W22-(IF(W22<=0,0,(30000*(1+'1 - I TUOI 6 NUMERI'!$B$14)^1)/(1-'1 - I TUOI 6 NUMERI'!$B$15*(IF(W22<=0,0,MEDIAN(0,(W22-X22)/W22,1))))))-(IF(W22<=0,0,'1 - I TUOI 6 NUMERI'!$B$16*W22)))*(1+((1+0.05)*(1+'1 - I TUOI 6 NUMERI'!$B$14)-1))) | X23: =MAX(0,X22-(IF(W22<=0,0,(30000*(1+'1 - I TUOI 6 NUMERI'!$B$14)^1)/(1-'1 - I TUOI 6 NUMERI'!$B$15*(IF(W22<=0,0,MEDIAN(0,(W22-X22)/W22,1))))))*(1-(IF(W22<=0,0,MEDIAN(0,(W22-X22)/W22,1))))) | Y23: =IF(Y22<=0,0,(Y22-(IF(Y22<=0,0,(36000*(1+'1 - I TUOI 6 NUMERI'!$B$14)^1)/(1-'1 - I TUOI 6 NUMERI'!$B$15*(IF(Y22<=0,0,MEDIAN(0,(Y22-Z22)/Y22,1))))))-(IF(Y22<=0,0,'1 - I TUOI 6 NUMERI'!$B$16*Y22)))*(1+((1+0.01)*(1+'1 - I TUOI 6 NUMERI'!$B$14)-1))) | Z23: =MAX(0,Z22-(IF(Y22<=0,0,(36000*(1+'1 - I TUOI 6 NUMERI'!$B$14)^1)/(1-'1 - I TUOI 6 NUMERI'!$B$15*(IF(Y22<=0,0,MEDIAN(0,(Y22-Z22)/Y22,1))))))*(1-(IF(Y22<=0,0,MEDIAN(0,(Y22-Z22)/Y22,1))))) | AA23: =IF(AA22<=0,0,(AA22-(IF(AA22<=0,0,(36000*(1+'1 - I TUOI 6 NUMERI'!$B$14)^1)/(1-'1 - I TUOI 6 NUMERI'!$B$15*(IF(AA22<=0,0,MEDIAN(0,(AA22-AB22)/AA22,1))))))-(IF(AA22<=0,0,'1 - I TUOI 6 NUMERI'!$B$16*AA22)))*(1+((1+0.03)*(1+'1 - I TUOI 6 NUMERI'!$B$14)-1))) | AB23: =MAX(0,AB22-(IF(AA22<=0,0,(36000*(1+'1 - I TUOI 6 NUMERI'!$B$14)^1)/(1-'1 - I TUOI 6 NUMERI'!$B$15*(IF(AA22<=0,0,MEDIAN(0,(AA22-AB22)/AA22,1))))))*(1-(IF(AA22<=0,0,MEDIAN(0,(AA22-AB22)/AA22,1))))) | AC23: =IF(AC22<=0,0,(AC22-(IF(AC22<=0,0,(36000*(1+'1 - I TUOI 6 NUMERI'!$B$14)^1)/(1-'1 - I TUOI 6 NUMERI'!$B$15*(IF(AC22<=0,0,MEDIAN(0,(AC22-AD22)/AC22,1))))))-(IF(AC22<=0,0,'1 - I TUOI 6 NUMERI'!$B$16*AC22)))*(1+((1+0.05)*(1+'1 - I TUOI 6 NUMERI'!$B$14)-1))) | AD23: =MAX(0,AD22-(IF(AC22<=0,0,(36000*(1+'1 - I TUOI 6 NUMERI'!$B$14)^1)/(1-'1 - I TUOI 6 NUMERI'!$B$15*(IF(AC22<=0,0,MEDIAN(0,(AC22-AD22)/AC22,1))))))*(1-(IF(AC22<=0,0,MEDIAN(0,(AC22-AD22)/AC22,1)))))
F24: 2 | G24: =IF(G23<=0,0,(G23-(IF(G23<=0,0,(18000*(1+'1 - I TUOI 6 NUMERI'!$B$14)^2)/(1-'1 - I TUOI 6 NUMERI'!$B$15*(IF(G23<=0,0,MEDIAN(0,(G23-H23)/G23,1))))))-(IF(G23<=0,0,'1 - I TUOI 6 NUMERI'!$B$16*G23)))*(1+((1+0.01)*(1+'1 - I TUOI 6 NUMERI'!$B$14)-1))) | H24: =MAX(0,H23-(IF(G23<=0,0,(18000*(1+'1 - I TUOI 6 NUMERI'!$B$14)^2)/(1-'1 - I TUOI 6 NUMERI'!$B$15*(IF(G23<=0,0,MEDIAN(0,(G23-H23)/G23,1))))))*(1-(IF(G23<=0,0,MEDIAN(0,(G23-H23)/G23,1))))) | I24: =IF(I23<=0,0,(I23-(IF(I23<=0,0,(18000*(1+'1 - I TUOI 6 NUMERI'!$B$14)^2)/(1-'1 - I TUOI 6 NUMERI'!$B$15*(IF(I23<=0,0,MEDIAN(0,(I23-J23)/I23,1))))))-(IF(I23<=0,0,'1 - I TUOI 6 NUMERI'!$B$16*I23)))*(1+((1+0.03)*(1+'1 - I TUOI 6 NUMERI'!$B$14)-1))) | J24: =MAX(0,J23-(IF(I23<=0,0,(18000*(1+'1 - I TUOI 6 NUMERI'!$B$14)^2)/(1-'1 - I TUOI 6 NUMERI'!$B$15*(IF(I23<=0,0,MEDIAN(0,(I23-J23)/I23,1))))))*(1-(IF(I23<=0,0,MEDIAN(0,(I23-J23)/I23,1))))) | K24: =IF(K23<=0,0,(K23-(IF(K23<=0,0,(18000*(1+'1 - I TUOI 6 NUMERI'!$B$14)^2)/(1-'1 - I TUOI 6 NUMERI'!$B$15*(IF(K23<=0,0,MEDIAN(0,(K23-L23)/K23,1))))))-(IF(K23<=0,0,'1 - I TUOI 6 NUMERI'!$B$16*K23)))*(1+((1+0.05)*(1+'1 - I TUOI 6 NUMERI'!$B$14)-1))) | L24: =MAX(0,L23-(IF(K23<=0,0,(18000*(1+'1 - I TUOI 6 NUMERI'!$B$14)^2)/(1-'1 - I TUOI 6 NUMERI'!$B$15*(IF(K23<=0,0,MEDIAN(0,(K23-L23)/K23,1))))))*(1-(IF(K23<=0,0,MEDIAN(0,(K23-L23)/K23,1))))) | M24: =IF(M23<=0,0,(M23-(IF(M23<=0,0,(24000*(1+'1 - I TUOI 6 NUMERI'!$B$14)^2)/(1-'1 - I TUOI 6 NUMERI'!$B$15*(IF(M23<=0,0,MEDIAN(0,(M23-N23)/M23,1))))))-(IF(M23<=0,0,'1 - I TUOI 6 NUMERI'!$B$16*M23)))*(1+((1+0.01)*(1+'1 - I TUOI 6 NUMERI'!$B$14)-1))) | N24: =MAX(0,N23-(IF(M23<=0,0,(24000*(1+'1 - I TUOI 6 NUMERI'!$B$14)^2)/(1-'1 - I TUOI 6 NUMERI'!$B$15*(IF(M23<=0,0,MEDIAN(0,(M23-N23)/M23,1))))))*(1-(IF(M23<=0,0,MEDIAN(0,(M23-N23)/M23,1))))) | O24: =IF(O23<=0,0,(O23-(IF(O23<=0,0,(24000*(1+'1 - I TUOI 6 NUMERI'!$B$14)^2)/(1-'1 - I TUOI 6 NUMERI'!$B$15*(IF(O23<=0,0,MEDIAN(0,(O23-P23)/O23,1))))))-(IF(O23<=0,0,'1 - I TUOI 6 NUMERI'!$B$16*O23)))*(1+((1+0.03)*(1+'1 - I TUOI 6 NUMERI'!$B$14)-1))) | P24: =MAX(0,P23-(IF(O23<=0,0,(24000*(1+'1 - I TUOI 6 NUMERI'!$B$14)^2)/(1-'1 - I TUOI 6 NUMERI'!$B$15*(IF(O23<=0,0,MEDIAN(0,(O23-P23)/O23,1))))))*(1-(IF(O23<=0,0,MEDIAN(0,(O23-P23)/O23,1))))) | Q24: =IF(Q23<=0,0,(Q23-(IF(Q23<=0,0,(24000*(1+'1 - I TUOI 6 NUMERI'!$B$14)^2)/(1-'1 - I TUOI 6 NUMERI'!$B$15*(IF(Q23<=0,0,MEDIAN(0,(Q23-R23)/Q23,1))))))-(IF(Q23<=0,0,'1 - I TUOI 6 NUMERI'!$B$16*Q23)))*(1+((1+0.05)*(1+'1 - I TUOI 6 NUMERI'!$B$14)-1))) | R24: =MAX(0,R23-(IF(Q23<=0,0,(24000*(1+'1 - I TUOI 6 NUMERI'!$B$14)^2)/(1-'1 - I TUOI 6 NUMERI'!$B$15*(IF(Q23<=0,0,MEDIAN(0,(Q23-R23)/Q23,1))))))*(1-(IF(Q23<=0,0,MEDIAN(0,(Q23-R23)/Q23,1))))) | S24: =IF(S23<=0,0,(S23-(IF(S23<=0,0,(30000*(1+'1 - I TUOI 6 NUMERI'!$B$14)^2)/(1-'1 - I TUOI 6 NUMERI'!$B$15*(IF(S23<=0,0,MEDIAN(0,(S23-T23)/S23,1))))))-(IF(S23<=0,0,'1 - I TUOI 6 NUMERI'!$B$16*S23)))*(1+((1+0.01)*(1+'1 - I TUOI 6 NUMERI'!$B$14)-1))) | T24: =MAX(0,T23-(IF(S23<=0,0,(30000*(1+'1 - I TUOI 6 NUMERI'!$B$14)^2)/(1-'1 - I TUOI 6 NUMERI'!$B$15*(IF(S23<=0,0,MEDIAN(0,(S23-T23)/S23,1))))))*(1-(IF(S23<=0,0,MEDIAN(0,(S23-T23)/S23,1))))) | U24: =IF(U23<=0,0,(U23-(IF(U23<=0,0,(30000*(1+'1 - I TUOI 6 NUMERI'!$B$14)^2)/(1-'1 - I TUOI 6 NUMERI'!$B$15*(IF(U23<=0,0,MEDIAN(0,(U23-V23)/U23,1))))))-(IF(U23<=0,0,'1 - I TUOI 6 NUMERI'!$B$16*U23)))*(1+((1+0.03)*(1+'1 - I TUOI 6 NUMERI'!$B$14)-1))) | V24: =MAX(0,V23-(IF(U23<=0,0,(30000*(1+'1 - I TUOI 6 NUMERI'!$B$14)^2)/(1-'1 - I TUOI 6 NUMERI'!$B$15*(IF(U23<=0,0,MEDIAN(0,(U23-V23)/U23,1))))))*(1-(IF(U23<=0,0,MEDIAN(0,(U23-V23)/U23,1))))) | W24: =IF(W23<=0,0,(W23-(IF(W23<=0,0,(30000*(1+'1 - I TUOI 6 NUMERI'!$B$14)^2)/(1-'1 - I TUOI 6 NUMERI'!$B$15*(IF(W23<=0,0,MEDIAN(0,(W23-X23)/W23,1))))))-(IF(W23<=0,0,'1 - I TUOI 6 NUMERI'!$B$16*W23)))*(1+((1+0.05)*(1+'1 - I TUOI 6 NUMERI'!$B$14)-1))) | X24: =MAX(0,X23-(IF(W23<=0,0,(30000*(1+'1 - I TUOI 6 NUMERI'!$B$14)^2)/(1-'1 - I TUOI 6 NUMERI'!$B$15*(IF(W23<=0,0,MEDIAN(0,(W23-X23)/W23,1))))))*(1-(IF(W23<=0,0,MEDIAN(0,(W23-X23)/W23,1))))) | Y24: =IF(Y23<=0,0,(Y23-(IF(Y23<=0,0,(36000*(1+'1 - I TUOI 6 NUMERI'!$B$14)^2)/(1-'1 - I TUOI 6 NUMERI'!$B$15*(IF(Y23<=0,0,MEDIAN(0,(Y23-Z23)/Y23,1))))))-(IF(Y23<=0,0,'1 - I TUOI 6 NUMERI'!$B$16*Y23)))*(1+((1+0.01)*(1+'1 - I TUOI 6 NUMERI'!$B$14)-1))) | Z24: =MAX(0,Z23-(IF(Y23<=0,0,(36000*(1+'1 - I TUOI 6 NUMERI'!$B$14)^2)/(1-'1 - I TUOI 6 NUMERI'!$B$15*(IF(Y23<=0,0,MEDIAN(0,(Y23-Z23)/Y23,1))))))*(1-(IF(Y23<=0,0,MEDIAN(0,(Y23-Z23)/Y23,1))))) | AA24: =IF(AA23<=0,0,(AA23-(IF(AA23<=0,0,(36000*(1+'1 - I TUOI 6 NUMERI'!$B$14)^2)/(1-'1 - I TUOI 6 NUMERI'!$B$15*(IF(AA23<=0,0,MEDIAN(0,(AA23-AB23)/AA23,1))))))-(IF(AA23<=0,0,'1 - I TUOI 6 NUMERI'!$B$16*AA23)))*(1+((1+0.03)*(1+'1 - I TUOI 6 NUMERI'!$B$14)-1))) | AB24: =MAX(0,AB23-(IF(AA23<=0,0,(36000*(1+'1 - I TUOI 6 NUMERI'!$B$14)^2)/(1-'1 - I TUOI 6 NUMERI'!$B$15*(IF(AA23<=0,0,MEDIAN(0,(AA23-AB23)/AA23,1))))))*(1-(IF(AA23<=0,0,MEDIAN(0,(AA23-AB23)/AA23,1))))) | AC24: =IF(AC23<=0,0,(AC23-(IF(AC23<=0,0,(36000*(1+'1 - I TUOI 6 NUMERI'!$B$14)^2)/(1-'1 - I TUOI 6 NUMERI'!$B$15*(IF(AC23<=0,0,MEDIAN(0,(AC23-AD23)/AC23,1))))))-(IF(AC23<=0,0,'1 - I TUOI 6 NUMERI'!$B$16*AC23)))*(1+((1+0.05)*(1+'1 - I TUOI 6 NUMERI'!$B$14)-1))) | AD24: =MAX(0,AD23-(IF(AC23<=0,0,(36000*(1+'1 - I TUOI 6 NUMERI'!$B$14)^2)/(1-'1 - I TUOI 6 NUMERI'!$B$15*(IF(AC23<=0,0,MEDIAN(0,(AC23-AD23)/AC23,1))))))*(1-(IF(AC23<=0,0,MEDIAN(0,(AC23-AD23)/AC23,1)))))
F25: 3 | G25: =IF(G24<=0,0,(G24-(IF(G24<=0,0,(18000*(1+'1 - I TUOI 6 NUMERI'!$B$14)^3)/(1-'1 - I TUOI 6 NUMERI'!$B$15*(IF(G24<=0,0,MEDIAN(0,(G24-H24)/G24,1))))))-(IF(G24<=0,0,'1 - I TUOI 6 NUMERI'!$B$16*G24)))*(1+((1+0.01)*(1+'1 - I TUOI 6 NUMERI'!$B$14)-1))) | H25: =MAX(0,H24-(IF(G24<=0,0,(18000*(1+'1 - I TUOI 6 NUMERI'!$B$14)^3)/(1-'1 - I TUOI 6 NUMERI'!$B$15*(IF(G24<=0,0,MEDIAN(0,(G24-H24)/G24,1))))))*(1-(IF(G24<=0,0,MEDIAN(0,(G24-H24)/G24,1))))) | I25: =IF(I24<=0,0,(I24-(IF(I24<=0,0,(18000*(1+'1 - I TUOI 6 NUMERI'!$B$14)^3)/(1-'1 - I TUOI 6 NUMERI'!$B$15*(IF(I24<=0,0,MEDIAN(0,(I24-J24)/I24,1))))))-(IF(I24<=0,0,'1 - I TUOI 6 NUMERI'!$B$16*I24)))*(1+((1+0.03)*(1+'1 - I TUOI 6 NUMERI'!$B$14)-1))) | J25: =MAX(0,J24-(IF(I24<=0,0,(18000*(1+'1 - I TUOI 6 NUMERI'!$B$14)^3)/(1-'1 - I TUOI 6 NUMERI'!$B$15*(IF(I24<=0,0,MEDIAN(0,(I24-J24)/I24,1))))))*(1-(IF(I24<=0,0,MEDIAN(0,(I24-J24)/I24,1))))) | K25: =IF(K24<=0,0,(K24-(IF(K24<=0,0,(18000*(1+'1 - I TUOI 6 NUMERI'!$B$14)^3)/(1-'1 - I TUOI 6 NUMERI'!$B$15*(IF(K24<=0,0,MEDIAN(0,(K24-L24)/K24,1))))))-(IF(K24<=0,0,'1 - I TUOI 6 NUMERI'!$B$16*K24)))*(1+((1+0.05)*(1+'1 - I TUOI 6 NUMERI'!$B$14)-1))) | L25: =MAX(0,L24-(IF(K24<=0,0,(18000*(1+'1 - I TUOI 6 NUMERI'!$B$14)^3)/(1-'1 - I TUOI 6 NUMERI'!$B$15*(IF(K24<=0,0,MEDIAN(0,(K24-L24)/K24,1))))))*(1-(IF(K24<=0,0,MEDIAN(0,(K24-L24)/K24,1))))) | M25: =IF(M24<=0,0,(M24-(IF(M24<=0,0,(24000*(1+'1 - I TUOI 6 NUMERI'!$B$14)^3)/(1-'1 - I TUOI 6 NUMERI'!$B$15*(IF(M24<=0,0,MEDIAN(0,(M24-N24)/M24,1))))))-(IF(M24<=0,0,'1 - I TUOI 6 NUMERI'!$B$16*M24)))*(1+((1+0.01)*(1+'1 - I TUOI 6 NUMERI'!$B$14)-1))) | N25: =MAX(0,N24-(IF(M24<=0,0,(24000*(1+'1 - I TUOI 6 NUMERI'!$B$14)^3)/(1-'1 - I TUOI 6 NUMERI'!$B$15*(IF(M24<=0,0,MEDIAN(0,(M24-N24)/M24,1))))))*(1-(IF(M24<=0,0,MEDIAN(0,(M24-N24)/M24,1))))) | O25: =IF(O24<=0,0,(O24-(IF(O24<=0,0,(24000*(1+'1 - I TUOI 6 NUMERI'!$B$14)^3)/(1-'1 - I TUOI 6 NUMERI'!$B$15*(IF(O24<=0,0,MEDIAN(0,(O24-P24)/O24,1))))))-(IF(O24<=0,0,'1 - I TUOI 6 NUMERI'!$B$16*O24)))*(1+((1+0.03)*(1+'1 - I TUOI 6 NUMERI'!$B$14)-1))) | P25: =MAX(0,P24-(IF(O24<=0,0,(24000*(1+'1 - I TUOI 6 NUMERI'!$B$14)^3)/(1-'1 - I TUOI 6 NUMERI'!$B$15*(IF(O24<=0,0,MEDIAN(0,(O24-P24)/O24,1))))))*(1-(IF(O24<=0,0,MEDIAN(0,(O24-P24)/O24,1))))) | Q25: =IF(Q24<=0,0,(Q24-(IF(Q24<=0,0,(24000*(1+'1 - I TUOI 6 NUMERI'!$B$14)^3)/(1-'1 - I TUOI 6 NUMERI'!$B$15*(IF(Q24<=0,0,MEDIAN(0,(Q24-R24)/Q24,1))))))-(IF(Q24<=0,0,'1 - I TUOI 6 NUMERI'!$B$16*Q24)))*(1+((1+0.05)*(1+'1 - I TUOI 6 NUMERI'!$B$14)-1))) | R25: =MAX(0,R24-(IF(Q24<=0,0,(24000*(1+'1 - I TUOI 6 NUMERI'!$B$14)^3)/(1-'1 - I TUOI 6 NUMERI'!$B$15*(IF(Q24<=0,0,MEDIAN(0,(Q24-R24)/Q24,1))))))*(1-(IF(Q24<=0,0,MEDIAN(0,(Q24-R24)/Q24,1))))) | S25: =IF(S24<=0,0,(S24-(IF(S24<=0,0,(30000*(1+'1 - I TUOI 6 NUMERI'!$B$14)^3)/(1-'1 - I TUOI 6 NUMERI'!$B$15*(IF(S24<=0,0,MEDIAN(0,(S24-T24)/S24,1))))))-(IF(S24<=0,0,'1 - I TUOI 6 NUMERI'!$B$16*S24)))*(1+((1+0.01)*(1+'1 - I TUOI 6 NUMERI'!$B$14)-1))) | T25: =MAX(0,T24-(IF(S24<=0,0,(30000*(1+'1 - I TUOI 6 NUMERI'!$B$14)^3)/(1-'1 - I TUOI 6 NUMERI'!$B$15*(IF(S24<=0,0,MEDIAN(0,(S24-T24)/S24,1))))))*(1-(IF(S24<=0,0,MEDIAN(0,(S24-T24)/S24,1))))) | U25: =IF(U24<=0,0,(U24-(IF(U24<=0,0,(30000*(1+'1 - I TUOI 6 NUMERI'!$B$14)^3)/(1-'1 - I TUOI 6 NUMERI'!$B$15*(IF(U24<=0,0,MEDIAN(0,(U24-V24)/U24,1))))))-(IF(U24<=0,0,'1 - I TUOI 6 NUMERI'!$B$16*U24)))*(1+((1+0.03)*(1+'1 - I TUOI 6 NUMERI'!$B$14)-1))) | V25: =MAX(0,V24-(IF(U24<=0,0,(30000*(1+'1 - I TUOI 6 NUMERI'!$B$14)^3)/(1-'1 - I TUOI 6 NUMERI'!$B$15*(IF(U24<=0,0,MEDIAN(0,(U24-V24)/U24,1))))))*(1-(IF(U24<=0,0,MEDIAN(0,(U24-V24)/U24,1))))) | W25: =IF(W24<=0,0,(W24-(IF(W24<=0,0,(30000*(1+'1 - I TUOI 6 NUMERI'!$B$14)^3)/(1-'1 - I TUOI 6 NUMERI'!$B$15*(IF(W24<=0,0,MEDIAN(0,(W24-X24)/W24,1))))))-(IF(W24<=0,0,'1 - I TUOI 6 NUMERI'!$B$16*W24)))*(1+((1+0.05)*(1+'1 - I TUOI 6 NUMERI'!$B$14)-1))) | X25: =MAX(0,X24-(IF(W24<=0,0,(30000*(1+'1 - I TUOI 6 NUMERI'!$B$14)^3)/(1-'1 - I TUOI 6 NUMERI'!$B$15*(IF(W24<=0,0,MEDIAN(0,(W24-X24)/W24,1))))))*(1-(IF(W24<=0,0,MEDIAN(0,(W24-X24)/W24,1))))) | Y25: =IF(Y24<=0,0,(Y24-(IF(Y24<=0,0,(36000*(1+'1 - I TUOI 6 NUMERI'!$B$14)^3)/(1-'1 - I TUOI 6 NUMERI'!$B$15*(IF(Y24<=0,0,MEDIAN(0,(Y24-Z24)/Y24,1))))))-(IF(Y24<=0,0,'1 - I TUOI 6 NUMERI'!$B$16*Y24)))*(1+((1+0.01)*(1+'1 - I TUOI 6 NUMERI'!$B$14)-1))) | Z25: =MAX(0,Z24-(IF(Y24<=0,0,(36000*(1+'1 - I TUOI 6 NUMERI'!$B$14)^3)/(1-'1 - I TUOI 6 NUMERI'!$B$15*(IF(Y24<=0,0,MEDIAN(0,(Y24-Z24)/Y24,1))))))*(1-(IF(Y24<=0,0,MEDIAN(0,(Y24-Z24)/Y24,1))))) | AA25: =IF(AA24<=0,0,(AA24-(IF(AA24<=0,0,(36000*(1+'1 - I TUOI 6 NUMERI'!$B$14)^3)/(1-'1 - I TUOI 6 NUMERI'!$B$15*(IF(AA24<=0,0,MEDIAN(0,(AA24-AB24)/AA24,1))))))-(IF(AA24<=0,0,'1 - I TUOI 6 NUMERI'!$B$16*AA24)))*(1+((1+0.03)*(1+'1 - I TUOI 6 NUMERI'!$B$14)-1))) | AB25: =MAX(0,AB24-(IF(AA24<=0,0,(36000*(1+'1 - I TUOI 6 NUMERI'!$B$14)^3)/(1-'1 - I TUOI 6 NUMERI'!$B$15*(IF(AA24<=0,0,MEDIAN(0,(AA24-AB24)/AA24,1))))))*(1-(IF(AA24<=0,0,MEDIAN(0,(AA24-AB24)/AA24,1))))) | AC25: =IF(AC24<=0,0,(AC24-(IF(AC24<=0,0,(36000*(1+'1 - I TUOI 6 NUMERI'!$B$14)^3)/(1-'1 - I TUOI 6 NUMERI'!$B$15*(IF(AC24<=0,0,MEDIAN(0,(AC24-AD24)/AC24,1))))))-(IF(AC24<=0,0,'1 - I TUOI 6 NUMERI'!$B$16*AC24)))*(1+((1+0.05)*(1+'1 - I TUOI 6 NUMERI'!$B$14)-1))) | AD25: =MAX(0,AD24-(IF(AC24<=0,0,(36000*(1+'1 - I TUOI 6 NUMERI'!$B$14)^3)/(1-'1 - I TUOI 6 NUMERI'!$B$15*(IF(AC24<=0,0,MEDIAN(0,(AC24-AD24)/AC24,1))))))*(1-(IF(AC24<=0,0,MEDIAN(0,(AC24-AD24)/AC24,1)))))
F26: 4 | G26: =IF(G25<=0,0,(G25-(IF(G25<=0,0,(18000*(1+'1 - I TUOI 6 NUMERI'!$B$14)^4)/(1-'1 - I TUOI 6 NUMERI'!$B$15*(IF(G25<=0,0,MEDIAN(0,(G25-H25)/G25,1))))))-(IF(G25<=0,0,'1 - I TUOI 6 NUMERI'!$B$16*G25)))*(1+((1+0.01)*(1+'1 - I TUOI 6 NUMERI'!$B$14)-1))) | H26: =MAX(0,H25-(IF(G25<=0,0,(18000*(1+'1 - I TUOI 6 NUMERI'!$B$14)^4)/(1-'1 - I TUOI 6 NUMERI'!$B$15*(IF(G25<=0,0,MEDIAN(0,(G25-H25)/G25,1))))))*(1-(IF(G25<=0,0,MEDIAN(0,(G25-H25)/G25,1))))) | I26: =IF(I25<=0,0,(I25-(IF(I25<=0,0,(18000*(1+'1 - I TUOI 6 NUMERI'!$B$14)^4)/(1-'1 - I TUOI 6 NUMERI'!$B$15*(IF(I25<=0,0,MEDIAN(0,(I25-J25)/I25,1))))))-(IF(I25<=0,0,'1 - I TUOI 6 NUMERI'!$B$16*I25)))*(1+((1+0.03)*(1+'1 - I TUOI 6 NUMERI'!$B$14)-1))) | J26: =MAX(0,J25-(IF(I25<=0,0,(18000*(1+'1 - I TUOI 6 NUMERI'!$B$14)^4)/(1-'1 - I TUOI 6 NUMERI'!$B$15*(IF(I25<=0,0,MEDIAN(0,(I25-J25)/I25,1))))))*(1-(IF(I25<=0,0,MEDIAN(0,(I25-J25)/I25,1))))) | K26: =IF(K25<=0,0,(K25-(IF(K25<=0,0,(18000*(1+'1 - I TUOI 6 NUMERI'!$B$14)^4)/(1-'1 - I TUOI 6 NUMERI'!$B$15*(IF(K25<=0,0,MEDIAN(0,(K25-L25)/K25,1))))))-(IF(K25<=0,0,'1 - I TUOI 6 NUMERI'!$B$16*K25)))*(1+((1+0.05)*(1+'1 - I TUOI 6 NUMERI'!$B$14)-1))) | L26: =MAX(0,L25-(IF(K25<=0,0,(18000*(1+'1 - I TUOI 6 NUMERI'!$B$14)^4)/(1-'1 - I TUOI 6 NUMERI'!$B$15*(IF(K25<=0,0,MEDIAN(0,(K25-L25)/K25,1))))))*(1-(IF(K25<=0,0,MEDIAN(0,(K25-L25)/K25,1))))) | M26: =IF(M25<=0,0,(M25-(IF(M25<=0,0,(24000*(1+'1 - I TUOI 6 NUMERI'!$B$14)^4)/(1-'1 - I TUOI 6 NUMERI'!$B$15*(IF(M25<=0,0,MEDIAN(0,(M25-N25)/M25,1))))))-(IF(M25<=0,0,'1 - I TUOI 6 NUMERI'!$B$16*M25)))*(1+((1+0.01)*(1+'1 - I TUOI 6 NUMERI'!$B$14)-1))) | N26: =MAX(0,N25-(IF(M25<=0,0,(24000*(1+'1 - I TUOI 6 NUMERI'!$B$14)^4)/(1-'1 - I TUOI 6 NUMERI'!$B$15*(IF(M25<=0,0,MEDIAN(0,(M25-N25)/M25,1))))))*(1-(IF(M25<=0,0,MEDIAN(0,(M25-N25)/M25,1))))) | O26: =IF(O25<=0,0,(O25-(IF(O25<=0,0,(24000*(1+'1 - I TUOI 6 NUMERI'!$B$14)^4)/(1-'1 - I TUOI 6 NUMERI'!$B$15*(IF(O25<=0,0,MEDIAN(0,(O25-P25)/O25,1))))))-(IF(O25<=0,0,'1 - I TUOI 6 NUMERI'!$B$16*O25)))*(1+((1+0.03)*(1+'1 - I TUOI 6 NUMERI'!$B$14)-1))) | P26: =MAX(0,P25-(IF(O25<=0,0,(24000*(1+'1 - I TUOI 6 NUMERI'!$B$14)^4)/(1-'1 - I TUOI 6 NUMERI'!$B$15*(IF(O25<=0,0,MEDIAN(0,(O25-P25)/O25,1))))))*(1-(IF(O25<=0,0,MEDIAN(0,(O25-P25)/O25,1))))) | Q26: =IF(Q25<=0,0,(Q25-(IF(Q25<=0,0,(24000*(1+'1 - I TUOI 6 NUMERI'!$B$14)^4)/(1-'1 - I TUOI 6 NUMERI'!$B$15*(IF(Q25<=0,0,MEDIAN(0,(Q25-R25)/Q25,1))))))-(IF(Q25<=0,0,'1 - I TUOI 6 NUMERI'!$B$16*Q25)))*(1+((1+0.05)*(1+'1 - I TUOI 6 NUMERI'!$B$14)-1))) | R26: =MAX(0,R25-(IF(Q25<=0,0,(24000*(1+'1 - I TUOI 6 NUMERI'!$B$14)^4)/(1-'1 - I TUOI 6 NUMERI'!$B$15*(IF(Q25<=0,0,MEDIAN(0,(Q25-R25)/Q25,1))))))*(1-(IF(Q25<=0,0,MEDIAN(0,(Q25-R25)/Q25,1))))) | S26: =IF(S25<=0,0,(S25-(IF(S25<=0,0,(30000*(1+'1 - I TUOI 6 NUMERI'!$B$14)^4)/(1-'1 - I TUOI 6 NUMERI'!$B$15*(IF(S25<=0,0,MEDIAN(0,(S25-T25)/S25,1))))))-(IF(S25<=0,0,'1 - I TUOI 6 NUMERI'!$B$16*S25)))*(1+((1+0.01)*(1+'1 - I TUOI 6 NUMERI'!$B$14)-1))) | T26: =MAX(0,T25-(IF(S25<=0,0,(30000*(1+'1 - I TUOI 6 NUMERI'!$B$14)^4)/(1-'1 - I TUOI 6 NUMERI'!$B$15*(IF(S25<=0,0,MEDIAN(0,(S25-T25)/S25,1))))))*(1-(IF(S25<=0,0,MEDIAN(0,(S25-T25)/S25,1))))) | U26: =IF(U25<=0,0,(U25-(IF(U25<=0,0,(30000*(1+'1 - I TUOI 6 NUMERI'!$B$14)^4)/(1-'1 - I TUOI 6 NUMERI'!$B$15*(IF(U25<=0,0,MEDIAN(0,(U25-V25)/U25,1))))))-(IF(U25<=0,0,'1 - I TUOI 6 NUMERI'!$B$16*U25)))*(1+((1+0.03)*(1+'1 - I TUOI 6 NUMERI'!$B$14)-1))) | V26: =MAX(0,V25-(IF(U25<=0,0,(30000*(1+'1 - I TUOI 6 NUMERI'!$B$14)^4)/(1-'1 - I TUOI 6 NUMERI'!$B$15*(IF(U25<=0,0,MEDIAN(0,(U25-V25)/U25,1))))))*(1-(IF(U25<=0,0,MEDIAN(0,(U25-V25)/U25,1))))) | W26: =IF(W25<=0,0,(W25-(IF(W25<=0,0,(30000*(1+'1 - I TUOI 6 NUMERI'!$B$14)^4)/(1-'1 - I TUOI 6 NUMERI'!$B$15*(IF(W25<=0,0,MEDIAN(0,(W25-X25)/W25,1))))))-(IF(W25<=0,0,'1 - I TUOI 6 NUMERI'!$B$16*W25)))*(1+((1+0.05)*(1+'1 - I TUOI 6 NUMERI'!$B$14)-1))) | X26: =MAX(0,X25-(IF(W25<=0,0,(30000*(1+'1 - I TUOI 6 NUMERI'!$B$14)^4)/(1-'1 - I TUOI 6 NUMERI'!$B$15*(IF(W25<=0,0,MEDIAN(0,(W25-X25)/W25,1))))))*(1-(IF(W25<=0,0,MEDIAN(0,(W25-X25)/W25,1))))) | Y26: =IF(Y25<=0,0,(Y25-(IF(Y25<=0,0,(36000*(1+'1 - I TUOI 6 NUMERI'!$B$14)^4)/(1-'1 - I TUOI 6 NUMERI'!$B$15*(IF(Y25<=0,0,MEDIAN(0,(Y25-Z25)/Y25,1))))))-(IF(Y25<=0,0,'1 - I TUOI 6 NUMERI'!$B$16*Y25)))*(1+((1+0.01)*(1+'1 - I TUOI 6 NUMERI'!$B$14)-1))) | Z26: =MAX(0,Z25-(IF(Y25<=0,0,(36000*(1+'1 - I TUOI 6 NUMERI'!$B$14)^4)/(1-'1 - I TUOI 6 NUMERI'!$B$15*(IF(Y25<=0,0,MEDIAN(0,(Y25-Z25)/Y25,1))))))*(1-(IF(Y25<=0,0,MEDIAN(0,(Y25-Z25)/Y25,1))))) | AA26: =IF(AA25<=0,0,(AA25-(IF(AA25<=0,0,(36000*(1+'1 - I TUOI 6 NUMERI'!$B$14)^4)/(1-'1 - I TUOI 6 NUMERI'!$B$15*(IF(AA25<=0,0,MEDIAN(0,(AA25-AB25)/AA25,1))))))-(IF(AA25<=0,0,'1 - I TUOI 6 NUMERI'!$B$16*AA25)))*(1+((1+0.03)*(1+'1 - I TUOI 6 NUMERI'!$B$14)-1))) | AB26: =MAX(0,AB25-(IF(AA25<=0,0,(36000*(1+'1 - I TUOI 6 NUMERI'!$B$14)^4)/(1-'1 - I TUOI 6 NUMERI'!$B$15*(IF(AA25<=0,0,MEDIAN(0,(AA25-AB25)/AA25,1))))))*(1-(IF(AA25<=0,0,MEDIAN(0,(AA25-AB25)/AA25,1))))) | AC26: =IF(AC25<=0,0,(AC25-(IF(AC25<=0,0,(36000*(1+'1 - I TUOI 6 NUMERI'!$B$14)^4)/(1-'1 - I TUOI 6 NUMERI'!$B$15*(IF(AC25<=0,0,MEDIAN(0,(AC25-AD25)/AC25,1))))))-(IF(AC25<=0,0,'1 - I TUOI 6 NUMERI'!$B$16*AC25)))*(1+((1+0.05)*(1+'1 - I TUOI 6 NUMERI'!$B$14)-1))) | AD26: =MAX(0,AD25-(IF(AC25<=0,0,(36000*(1+'1 - I TUOI 6 NUMERI'!$B$14)^4)/(1-'1 - I TUOI 6 NUMERI'!$B$15*(IF(AC25<=0,0,MEDIAN(0,(AC25-AD25)/AC25,1))))))*(1-(IF(AC25<=0,0,MEDIAN(0,(AC25-AD25)/AC25,1)))))
F27: 5 | G27: =IF(G26<=0,0,(G26-(IF(G26<=0,0,(18000*(1+'1 - I TUOI 6 NUMERI'!$B$14)^5)/(1-'1 - I TUOI 6 NUMERI'!$B$15*(IF(G26<=0,0,MEDIAN(0,(G26-H26)/G26,1))))))-(IF(G26<=0,0,'1 - I TUOI 6 NUMERI'!$B$16*G26)))*(1+((1+0.01)*(1+'1 - I TUOI 6 NUMERI'!$B$14)-1))) | H27: =MAX(0,H26-(IF(G26<=0,0,(18000*(1+'1 - I TUOI 6 NUMERI'!$B$14)^5)/(1-'1 - I TUOI 6 NUMERI'!$B$15*(IF(G26<=0,0,MEDIAN(0,(G26-H26)/G26,1))))))*(1-(IF(G26<=0,0,MEDIAN(0,(G26-H26)/G26,1))))) | I27: =IF(I26<=0,0,(I26-(IF(I26<=0,0,(18000*(1+'1 - I TUOI 6 NUMERI'!$B$14)^5)/(1-'1 - I TUOI 6 NUMERI'!$B$15*(IF(I26<=0,0,MEDIAN(0,(I26-J26)/I26,1))))))-(IF(I26<=0,0,'1 - I TUOI 6 NUMERI'!$B$16*I26)))*(1+((1+0.03)*(1+'1 - I TUOI 6 NUMERI'!$B$14)-1))) | J27: =MAX(0,J26-(IF(I26<=0,0,(18000*(1+'1 - I TUOI 6 NUMERI'!$B$14)^5)/(1-'1 - I TUOI 6 NUMERI'!$B$15*(IF(I26<=0,0,MEDIAN(0,(I26-J26)/I26,1))))))*(1-(IF(I26<=0,0,MEDIAN(0,(I26-J26)/I26,1))))) | K27: =IF(K26<=0,0,(K26-(IF(K26<=0,0,(18000*(1+'1 - I TUOI 6 NUMERI'!$B$14)^5)/(1-'1 - I TUOI 6 NUMERI'!$B$15*(IF(K26<=0,0,MEDIAN(0,(K26-L26)/K26,1))))))-(IF(K26<=0,0,'1 - I TUOI 6 NUMERI'!$B$16*K26)))*(1+((1+0.05)*(1+'1 - I TUOI 6 NUMERI'!$B$14)-1))) | L27: =MAX(0,L26-(IF(K26<=0,0,(18000*(1+'1 - I TUOI 6 NUMERI'!$B$14)^5)/(1-'1 - I TUOI 6 NUMERI'!$B$15*(IF(K26<=0,0,MEDIAN(0,(K26-L26)/K26,1))))))*(1-(IF(K26<=0,0,MEDIAN(0,(K26-L26)/K26,1))))) | M27: =IF(M26<=0,0,(M26-(IF(M26<=0,0,(24000*(1+'1 - I TUOI 6 NUMERI'!$B$14)^5)/(1-'1 - I TUOI 6 NUMERI'!$B$15*(IF(M26<=0,0,MEDIAN(0,(M26-N26)/M26,1))))))-(IF(M26<=0,0,'1 - I TUOI 6 NUMERI'!$B$16*M26)))*(1+((1+0.01)*(1+'1 - I TUOI 6 NUMERI'!$B$14)-1))) | N27: =MAX(0,N26-(IF(M26<=0,0,(24000*(1+'1 - I TUOI 6 NUMERI'!$B$14)^5)/(1-'1 - I TUOI 6 NUMERI'!$B$15*(IF(M26<=0,0,MEDIAN(0,(M26-N26)/M26,1))))))*(1-(IF(M26<=0,0,MEDIAN(0,(M26-N26)/M26,1))))) | O27: =IF(O26<=0,0,(O26-(IF(O26<=0,0,(24000*(1+'1 - I TUOI 6 NUMERI'!$B$14)^5)/(1-'1 - I TUOI 6 NUMERI'!$B$15*(IF(O26<=0,0,MEDIAN(0,(O26-P26)/O26,1))))))-(IF(O26<=0,0,'1 - I TUOI 6 NUMERI'!$B$16*O26)))*(1+((1+0.03)*(1+'1 - I TUOI 6 NUMERI'!$B$14)-1))) | P27: =MAX(0,P26-(IF(O26<=0,0,(24000*(1+'1 - I TUOI 6 NUMERI'!$B$14)^5)/(1-'1 - I TUOI 6 NUMERI'!$B$15*(IF(O26<=0,0,MEDIAN(0,(O26-P26)/O26,1))))))*(1-(IF(O26<=0,0,MEDIAN(0,(O26-P26)/O26,1))))) | Q27: =IF(Q26<=0,0,(Q26-(IF(Q26<=0,0,(24000*(1+'1 - I TUOI 6 NUMERI'!$B$14)^5)/(1-'1 - I TUOI 6 NUMERI'!$B$15*(IF(Q26<=0,0,MEDIAN(0,(Q26-R26)/Q26,1))))))-(IF(Q26<=0,0,'1 - I TUOI 6 NUMERI'!$B$16*Q26)))*(1+((1+0.05)*(1+'1 - I TUOI 6 NUMERI'!$B$14)-1))) | R27: =MAX(0,R26-(IF(Q26<=0,0,(24000*(1+'1 - I TUOI 6 NUMERI'!$B$14)^5)/(1-'1 - I TUOI 6 NUMERI'!$B$15*(IF(Q26<=0,0,MEDIAN(0,(Q26-R26)/Q26,1))))))*(1-(IF(Q26<=0,0,MEDIAN(0,(Q26-R26)/Q26,1))))) | S27: =IF(S26<=0,0,(S26-(IF(S26<=0,0,(30000*(1+'1 - I TUOI 6 NUMERI'!$B$14)^5)/(1-'1 - I TUOI 6 NUMERI'!$B$15*(IF(S26<=0,0,MEDIAN(0,(S26-T26)/S26,1))))))-(IF(S26<=0,0,'1 - I TUOI 6 NUMERI'!$B$16*S26)))*(1+((1+0.01)*(1+'1 - I TUOI 6 NUMERI'!$B$14)-1))) | T27: =MAX(0,T26-(IF(S26<=0,0,(30000*(1+'1 - I TUOI 6 NUMERI'!$B$14)^5)/(1-'1 - I TUOI 6 NUMERI'!$B$15*(IF(S26<=0,0,MEDIAN(0,(S26-T26)/S26,1))))))*(1-(IF(S26<=0,0,MEDIAN(0,(S26-T26)/S26,1))))) | U27: =IF(U26<=0,0,(U26-(IF(U26<=0,0,(30000*(1+'1 - I TUOI 6 NUMERI'!$B$14)^5)/(1-'1 - I TUOI 6 NUMERI'!$B$15*(IF(U26<=0,0,MEDIAN(0,(U26-V26)/U26,1))))))-(IF(U26<=0,0,'1 - I TUOI 6 NUMERI'!$B$16*U26)))*(1+((1+0.03)*(1+'1 - I TUOI 6 NUMERI'!$B$14)-1))) | V27: =MAX(0,V26-(IF(U26<=0,0,(30000*(1+'1 - I TUOI 6 NUMERI'!$B$14)^5)/(1-'1 - I TUOI 6 NUMERI'!$B$15*(IF(U26<=0,0,MEDIAN(0,(U26-V26)/U26,1))))))*(1-(IF(U26<=0,0,MEDIAN(0,(U26-V26)/U26,1))))) | W27: =IF(W26<=0,0,(W26-(IF(W26<=0,0,(30000*(1+'1 - I TUOI 6 NUMERI'!$B$14)^5)/(1-'1 - I TUOI 6 NUMERI'!$B$15*(IF(W26<=0,0,MEDIAN(0,(W26-X26)/W26,1))))))-(IF(W26<=0,0,'1 - I TUOI 6 NUMERI'!$B$16*W26)))*(1+((1+0.05)*(1+'1 - I TUOI 6 NUMERI'!$B$14)-1))) | X27: =MAX(0,X26-(IF(W26<=0,0,(30000*(1+'1 - I TUOI 6 NUMERI'!$B$14)^5)/(1-'1 - I TUOI 6 NUMERI'!$B$15*(IF(W26<=0,0,MEDIAN(0,(W26-X26)/W26,1))))))*(1-(IF(W26<=0,0,MEDIAN(0,(W26-X26)/W26,1))))) | Y27: =IF(Y26<=0,0,(Y26-(IF(Y26<=0,0,(36000*(1+'1 - I TUOI 6 NUMERI'!$B$14)^5)/(1-'1 - I TUOI 6 NUMERI'!$B$15*(IF(Y26<=0,0,MEDIAN(0,(Y26-Z26)/Y26,1))))))-(IF(Y26<=0,0,'1 - I TUOI 6 NUMERI'!$B$16*Y26)))*(1+((1+0.01)*(1+'1 - I TUOI 6 NUMERI'!$B$14)-1))) | Z27: =MAX(0,Z26-(IF(Y26<=0,0,(36000*(1+'1 - I TUOI 6 NUMERI'!$B$14)^5)/(1-'1 - I TUOI 6 NUMERI'!$B$15*(IF(Y26<=0,0,MEDIAN(0,(Y26-Z26)/Y26,1))))))*(1-(IF(Y26<=0,0,MEDIAN(0,(Y26-Z26)/Y26,1))))) | AA27: =IF(AA26<=0,0,(AA26-(IF(AA26<=0,0,(36000*(1+'1 - I TUOI 6 NUMERI'!$B$14)^5)/(1-'1 - I TUOI 6 NUMERI'!$B$15*(IF(AA26<=0,0,MEDIAN(0,(AA26-AB26)/AA26,1))))))-(IF(AA26<=0,0,'1 - I TUOI 6 NUMERI'!$B$16*AA26)))*(1+((1+0.03)*(1+'1 - I TUOI 6 NUMERI'!$B$14)-1))) | AB27: =MAX(0,AB26-(IF(AA26<=0,0,(36000*(1+'1 - I TUOI 6 NUMERI'!$B$14)^5)/(1-'1 - I TUOI 6 NUMERI'!$B$15*(IF(AA26<=0,0,MEDIAN(0,(AA26-AB26)/AA26,1))))))*(1-(IF(AA26<=0,0,MEDIAN(0,(AA26-AB26)/AA26,1))))) | AC27: =IF(AC26<=0,0,(AC26-(IF(AC26<=0,0,(36000*(1+'1 - I TUOI 6 NUMERI'!$B$14)^5)/(1-'1 - I TUOI 6 NUMERI'!$B$15*(IF(AC26<=0,0,MEDIAN(0,(AC26-AD26)/AC26,1))))))-(IF(AC26<=0,0,'1 - I TUOI 6 NUMERI'!$B$16*AC26)))*(1+((1+0.05)*(1+'1 - I TUOI 6 NUMERI'!$B$14)-1))) | AD27: =MAX(0,AD26-(IF(AC26<=0,0,(36000*(1+'1 - I TUOI 6 NUMERI'!$B$14)^5)/(1-'1 - I TUOI 6 NUMERI'!$B$15*(IF(AC26<=0,0,MEDIAN(0,(AC26-AD26)/AC26,1))))))*(1-(IF(AC26<=0,0,MEDIAN(0,(AC26-AD26)/AC26,1)))))
F28: 6 | G28: =IF(G27<=0,0,(G27-(IF(G27<=0,0,(18000*(1+'1 - I TUOI 6 NUMERI'!$B$14)^6)/(1-'1 - I TUOI 6 NUMERI'!$B$15*(IF(G27<=0,0,MEDIAN(0,(G27-H27)/G27,1))))))-(IF(G27<=0,0,'1 - I TUOI 6 NUMERI'!$B$16*G27)))*(1+((1+0.01)*(1+'1 - I TUOI 6 NUMERI'!$B$14)-1))) | H28: =MAX(0,H27-(IF(G27<=0,0,(18000*(1+'1 - I TUOI 6 NUMERI'!$B$14)^6)/(1-'1 - I TUOI 6 NUMERI'!$B$15*(IF(G27<=0,0,MEDIAN(0,(G27-H27)/G27,1))))))*(1-(IF(G27<=0,0,MEDIAN(0,(G27-H27)/G27,1))))) | I28: =IF(I27<=0,0,(I27-(IF(I27<=0,0,(18000*(1+'1 - I TUOI 6 NUMERI'!$B$14)^6)/(1-'1 - I TUOI 6 NUMERI'!$B$15*(IF(I27<=0,0,MEDIAN(0,(I27-J27)/I27,1))))))-(IF(I27<=0,0,'1 - I TUOI 6 NUMERI'!$B$16*I27)))*(1+((1+0.03)*(1+'1 - I TUOI 6 NUMERI'!$B$14)-1))) | J28: =MAX(0,J27-(IF(I27<=0,0,(18000*(1+'1 - I TUOI 6 NUMERI'!$B$14)^6)/(1-'1 - I TUOI 6 NUMERI'!$B$15*(IF(I27<=0,0,MEDIAN(0,(I27-J27)/I27,1))))))*(1-(IF(I27<=0,0,MEDIAN(0,(I27-J27)/I27,1))))) | K28: =IF(K27<=0,0,(K27-(IF(K27<=0,0,(18000*(1+'1 - I TUOI 6 NUMERI'!$B$14)^6)/(1-'1 - I TUOI 6 NUMERI'!$B$15*(IF(K27<=0,0,MEDIAN(0,(K27-L27)/K27,1))))))-(IF(K27<=0,0,'1 - I TUOI 6 NUMERI'!$B$16*K27)))*(1+((1+0.05)*(1+'1 - I TUOI 6 NUMERI'!$B$14)-1))) | L28: =MAX(0,L27-(IF(K27<=0,0,(18000*(1+'1 - I TUOI 6 NUMERI'!$B$14)^6)/(1-'1 - I TUOI 6 NUMERI'!$B$15*(IF(K27<=0,0,MEDIAN(0,(K27-L27)/K27,1))))))*(1-(IF(K27<=0,0,MEDIAN(0,(K27-L27)/K27,1))))) | M28: =IF(M27<=0,0,(M27-(IF(M27<=0,0,(24000*(1+'1 - I TUOI 6 NUMERI'!$B$14)^6)/(1-'1 - I TUOI 6 NUMERI'!$B$15*(IF(M27<=0,0,MEDIAN(0,(M27-N27)/M27,1))))))-(IF(M27<=0,0,'1 - I TUOI 6 NUMERI'!$B$16*M27)))*(1+((1+0.01)*(1+'1 - I TUOI 6 NUMERI'!$B$14)-1))) | N28: =MAX(0,N27-(IF(M27<=0,0,(24000*(1+'1 - I TUOI 6 NUMERI'!$B$14)^6)/(1-'1 - I TUOI 6 NUMERI'!$B$15*(IF(M27<=0,0,MEDIAN(0,(M27-N27)/M27,1))))))*(1-(IF(M27<=0,0,MEDIAN(0,(M27-N27)/M27,1))))) | O28: =IF(O27<=0,0,(O27-(IF(O27<=0,0,(24000*(1+'1 - I TUOI 6 NUMERI'!$B$14)^6)/(1-'1 - I TUOI 6 NUMERI'!$B$15*(IF(O27<=0,0,MEDIAN(0,(O27-P27)/O27,1))))))-(IF(O27<=0,0,'1 - I TUOI 6 NUMERI'!$B$16*O27)))*(1+((1+0.03)*(1+'1 - I TUOI 6 NUMERI'!$B$14)-1))) | P28: =MAX(0,P27-(IF(O27<=0,0,(24000*(1+'1 - I TUOI 6 NUMERI'!$B$14)^6)/(1-'1 - I TUOI 6 NUMERI'!$B$15*(IF(O27<=0,0,MEDIAN(0,(O27-P27)/O27,1))))))*(1-(IF(O27<=0,0,MEDIAN(0,(O27-P27)/O27,1))))) | Q28: =IF(Q27<=0,0,(Q27-(IF(Q27<=0,0,(24000*(1+'1 - I TUOI 6 NUMERI'!$B$14)^6)/(1-'1 - I TUOI 6 NUMERI'!$B$15*(IF(Q27<=0,0,MEDIAN(0,(Q27-R27)/Q27,1))))))-(IF(Q27<=0,0,'1 - I TUOI 6 NUMERI'!$B$16*Q27)))*(1+((1+0.05)*(1+'1 - I TUOI 6 NUMERI'!$B$14)-1))) | R28: =MAX(0,R27-(IF(Q27<=0,0,(24000*(1+'1 - I TUOI 6 NUMERI'!$B$14)^6)/(1-'1 - I TUOI 6 NUMERI'!$B$15*(IF(Q27<=0,0,MEDIAN(0,(Q27-R27)/Q27,1))))))*(1-(IF(Q27<=0,0,MEDIAN(0,(Q27-R27)/Q27,1))))) | S28: =IF(S27<=0,0,(S27-(IF(S27<=0,0,(30000*(1+'1 - I TUOI 6 NUMERI'!$B$14)^6)/(1-'1 - I TUOI 6 NUMERI'!$B$15*(IF(S27<=0,0,MEDIAN(0,(S27-T27)/S27,1))))))-(IF(S27<=0,0,'1 - I TUOI 6 NUMERI'!$B$16*S27)))*(1+((1+0.01)*(1+'1 - I TUOI 6 NUMERI'!$B$14)-1))) | T28: =MAX(0,T27-(IF(S27<=0,0,(30000*(1+'1 - I TUOI 6 NUMERI'!$B$14)^6)/(1-'1 - I TUOI 6 NUMERI'!$B$15*(IF(S27<=0,0,MEDIAN(0,(S27-T27)/S27,1))))))*(1-(IF(S27<=0,0,MEDIAN(0,(S27-T27)/S27,1))))) | U28: =IF(U27<=0,0,(U27-(IF(U27<=0,0,(30000*(1+'1 - I TUOI 6 NUMERI'!$B$14)^6)/(1-'1 - I TUOI 6 NUMERI'!$B$15*(IF(U27<=0,0,MEDIAN(0,(U27-V27)/U27,1))))))-(IF(U27<=0,0,'1 - I TUOI 6 NUMERI'!$B$16*U27)))*(1+((1+0.03)*(1+'1 - I TUOI 6 NUMERI'!$B$14)-1))) | V28: =MAX(0,V27-(IF(U27<=0,0,(30000*(1+'1 - I TUOI 6 NUMERI'!$B$14)^6)/(1-'1 - I TUOI 6 NUMERI'!$B$15*(IF(U27<=0,0,MEDIAN(0,(U27-V27)/U27,1))))))*(1-(IF(U27<=0,0,MEDIAN(0,(U27-V27)/U27,1))))) | W28: =IF(W27<=0,0,(W27-(IF(W27<=0,0,(30000*(1+'1 - I TUOI 6 NUMERI'!$B$14)^6)/(1-'1 - I TUOI 6 NUMERI'!$B$15*(IF(W27<=0,0,MEDIAN(0,(W27-X27)/W27,1))))))-(IF(W27<=0,0,'1 - I TUOI 6 NUMERI'!$B$16*W27)))*(1+((1+0.05)*(1+'1 - I TUOI 6 NUMERI'!$B$14)-1))) | X28: =MAX(0,X27-(IF(W27<=0,0,(30000*(1+'1 - I TUOI 6 NUMERI'!$B$14)^6)/(1-'1 - I TUOI 6 NUMERI'!$B$15*(IF(W27<=0,0,MEDIAN(0,(W27-X27)/W27,1))))))*(1-(IF(W27<=0,0,MEDIAN(0,(W27-X27)/W27,1))))) | Y28: =IF(Y27<=0,0,(Y27-(IF(Y27<=0,0,(36000*(1+'1 - I TUOI 6 NUMERI'!$B$14)^6)/(1-'1 - I TUOI 6 NUMERI'!$B$15*(IF(Y27<=0,0,MEDIAN(0,(Y27-Z27)/Y27,1))))))-(IF(Y27<=0,0,'1 - I TUOI 6 NUMERI'!$B$16*Y27)))*(1+((1+0.01)*(1+'1 - I TUOI 6 NUMERI'!$B$14)-1))) | Z28: =MAX(0,Z27-(IF(Y27<=0,0,(36000*(1+'1 - I TUOI 6 NUMERI'!$B$14)^6)/(1-'1 - I TUOI 6 NUMERI'!$B$15*(IF(Y27<=0,0,MEDIAN(0,(Y27-Z27)/Y27,1))))))*(1-(IF(Y27<=0,0,MEDIAN(0,(Y27-Z27)/Y27,1))))) | AA28: =IF(AA27<=0,0,(AA27-(IF(AA27<=0,0,(36000*(1+'1 - I TUOI 6 NUMERI'!$B$14)^6)/(1-'1 - I TUOI 6 NUMERI'!$B$15*(IF(AA27<=0,0,MEDIAN(0,(AA27-AB27)/AA27,1))))))-(IF(AA27<=0,0,'1 - I TUOI 6 NUMERI'!$B$16*AA27)))*(1+((1+0.03)*(1+'1 - I TUOI 6 NUMERI'!$B$14)-1))) | AB28: =MAX(0,AB27-(IF(AA27<=0,0,(36000*(1+'1 - I TUOI 6 NUMERI'!$B$14)^6)/(1-'1 - I TUOI 6 NUMERI'!$B$15*(IF(AA27<=0,0,MEDIAN(0,(AA27-AB27)/AA27,1))))))*(1-(IF(AA27<=0,0,MEDIAN(0,(AA27-AB27)/AA27,1))))) | AC28: =IF(AC27<=0,0,(AC27-(IF(AC27<=0,0,(36000*(1+'1 - I TUOI 6 NUMERI'!$B$14)^6)/(1-'1 - I TUOI 6 NUMERI'!$B$15*(IF(AC27<=0,0,MEDIAN(0,(AC27-AD27)/AC27,1))))))-(IF(AC27<=0,0,'1 - I TUOI 6 NUMERI'!$B$16*AC27)))*(1+((1+0.05)*(1+'1 - I TUOI 6 NUMERI'!$B$14)-1))) | AD28: =MAX(0,AD27-(IF(AC27<=0,0,(36000*(1+'1 - I TUOI 6 NUMERI'!$B$14)^6)/(1-'1 - I TUOI 6 NUMERI'!$B$15*(IF(AC27<=0,0,MEDIAN(0,(AC27-AD27)/AC27,1))))))*(1-(IF(AC27<=0,0,MEDIAN(0,(AC27-AD27)/AC27,1)))))
F29: 7 | G29: =IF(G28<=0,0,(G28-(IF(G28<=0,0,(18000*(1+'1 - I TUOI 6 NUMERI'!$B$14)^7)/(1-'1 - I TUOI 6 NUMERI'!$B$15*(IF(G28<=0,0,MEDIAN(0,(G28-H28)/G28,1))))))-(IF(G28<=0,0,'1 - I TUOI 6 NUMERI'!$B$16*G28)))*(1+((1+0.01)*(1+'1 - I TUOI 6 NUMERI'!$B$14)-1))) | H29: =MAX(0,H28-(IF(G28<=0,0,(18000*(1+'1 - I TUOI 6 NUMERI'!$B$14)^7)/(1-'1 - I TUOI 6 NUMERI'!$B$15*(IF(G28<=0,0,MEDIAN(0,(G28-H28)/G28,1))))))*(1-(IF(G28<=0,0,MEDIAN(0,(G28-H28)/G28,1))))) | I29: =IF(I28<=0,0,(I28-(IF(I28<=0,0,(18000*(1+'1 - I TUOI 6 NUMERI'!$B$14)^7)/(1-'1 - I TUOI 6 NUMERI'!$B$15*(IF(I28<=0,0,MEDIAN(0,(I28-J28)/I28,1))))))-(IF(I28<=0,0,'1 - I TUOI 6 NUMERI'!$B$16*I28)))*(1+((1+0.03)*(1+'1 - I TUOI 6 NUMERI'!$B$14)-1))) | J29: =MAX(0,J28-(IF(I28<=0,0,(18000*(1+'1 - I TUOI 6 NUMERI'!$B$14)^7)/(1-'1 - I TUOI 6 NUMERI'!$B$15*(IF(I28<=0,0,MEDIAN(0,(I28-J28)/I28,1))))))*(1-(IF(I28<=0,0,MEDIAN(0,(I28-J28)/I28,1))))) | K29: =IF(K28<=0,0,(K28-(IF(K28<=0,0,(18000*(1+'1 - I TUOI 6 NUMERI'!$B$14)^7)/(1-'1 - I TUOI 6 NUMERI'!$B$15*(IF(K28<=0,0,MEDIAN(0,(K28-L28)/K28,1))))))-(IF(K28<=0,0,'1 - I TUOI 6 NUMERI'!$B$16*K28)))*(1+((1+0.05)*(1+'1 - I TUOI 6 NUMERI'!$B$14)-1))) | L29: =MAX(0,L28-(IF(K28<=0,0,(18000*(1+'1 - I TUOI 6 NUMERI'!$B$14)^7)/(1-'1 - I TUOI 6 NUMERI'!$B$15*(IF(K28<=0,0,MEDIAN(0,(K28-L28)/K28,1))))))*(1-(IF(K28<=0,0,MEDIAN(0,(K28-L28)/K28,1))))) | M29: =IF(M28<=0,0,(M28-(IF(M28<=0,0,(24000*(1+'1 - I TUOI 6 NUMERI'!$B$14)^7)/(1-'1 - I TUOI 6 NUMERI'!$B$15*(IF(M28<=0,0,MEDIAN(0,(M28-N28)/M28,1))))))-(IF(M28<=0,0,'1 - I TUOI 6 NUMERI'!$B$16*M28)))*(1+((1+0.01)*(1+'1 - I TUOI 6 NUMERI'!$B$14)-1))) | N29: =MAX(0,N28-(IF(M28<=0,0,(24000*(1+'1 - I TUOI 6 NUMERI'!$B$14)^7)/(1-'1 - I TUOI 6 NUMERI'!$B$15*(IF(M28<=0,0,MEDIAN(0,(M28-N28)/M28,1))))))*(1-(IF(M28<=0,0,MEDIAN(0,(M28-N28)/M28,1))))) | O29: =IF(O28<=0,0,(O28-(IF(O28<=0,0,(24000*(1+'1 - I TUOI 6 NUMERI'!$B$14)^7)/(1-'1 - I TUOI 6 NUMERI'!$B$15*(IF(O28<=0,0,MEDIAN(0,(O28-P28)/O28,1))))))-(IF(O28<=0,0,'1 - I TUOI 6 NUMERI'!$B$16*O28)))*(1+((1+0.03)*(1+'1 - I TUOI 6 NUMERI'!$B$14)-1))) | P29: =MAX(0,P28-(IF(O28<=0,0,(24000*(1+'1 - I TUOI 6 NUMERI'!$B$14)^7)/(1-'1 - I TUOI 6 NUMERI'!$B$15*(IF(O28<=0,0,MEDIAN(0,(O28-P28)/O28,1))))))*(1-(IF(O28<=0,0,MEDIAN(0,(O28-P28)/O28,1))))) | Q29: =IF(Q28<=0,0,(Q28-(IF(Q28<=0,0,(24000*(1+'1 - I TUOI 6 NUMERI'!$B$14)^7)/(1-'1 - I TUOI 6 NUMERI'!$B$15*(IF(Q28<=0,0,MEDIAN(0,(Q28-R28)/Q28,1))))))-(IF(Q28<=0,0,'1 - I TUOI 6 NUMERI'!$B$16*Q28)))*(1+((1+0.05)*(1+'1 - I TUOI 6 NUMERI'!$B$14)-1))) | R29: =MAX(0,R28-(IF(Q28<=0,0,(24000*(1+'1 - I TUOI 6 NUMERI'!$B$14)^7)/(1-'1 - I TUOI 6 NUMERI'!$B$15*(IF(Q28<=0,0,MEDIAN(0,(Q28-R28)/Q28,1))))))*(1-(IF(Q28<=0,0,MEDIAN(0,(Q28-R28)/Q28,1))))) | S29: =IF(S28<=0,0,(S28-(IF(S28<=0,0,(30000*(1+'1 - I TUOI 6 NUMERI'!$B$14)^7)/(1-'1 - I TUOI 6 NUMERI'!$B$15*(IF(S28<=0,0,MEDIAN(0,(S28-T28)/S28,1))))))-(IF(S28<=0,0,'1 - I TUOI 6 NUMERI'!$B$16*S28)))*(1+((1+0.01)*(1+'1 - I TUOI 6 NUMERI'!$B$14)-1))) | T29: =MAX(0,T28-(IF(S28<=0,0,(30000*(1+'1 - I TUOI 6 NUMERI'!$B$14)^7)/(1-'1 - I TUOI 6 NUMERI'!$B$15*(IF(S28<=0,0,MEDIAN(0,(S28-T28)/S28,1))))))*(1-(IF(S28<=0,0,MEDIAN(0,(S28-T28)/S28,1))))) | U29: =IF(U28<=0,0,(U28-(IF(U28<=0,0,(30000*(1+'1 - I TUOI 6 NUMERI'!$B$14)^7)/(1-'1 - I TUOI 6 NUMERI'!$B$15*(IF(U28<=0,0,MEDIAN(0,(U28-V28)/U28,1))))))-(IF(U28<=0,0,'1 - I TUOI 6 NUMERI'!$B$16*U28)))*(1+((1+0.03)*(1+'1 - I TUOI 6 NUMERI'!$B$14)-1))) | V29: =MAX(0,V28-(IF(U28<=0,0,(30000*(1+'1 - I TUOI 6 NUMERI'!$B$14)^7)/(1-'1 - I TUOI 6 NUMERI'!$B$15*(IF(U28<=0,0,MEDIAN(0,(U28-V28)/U28,1))))))*(1-(IF(U28<=0,0,MEDIAN(0,(U28-V28)/U28,1))))) | W29: =IF(W28<=0,0,(W28-(IF(W28<=0,0,(30000*(1+'1 - I TUOI 6 NUMERI'!$B$14)^7)/(1-'1 - I TUOI 6 NUMERI'!$B$15*(IF(W28<=0,0,MEDIAN(0,(W28-X28)/W28,1))))))-(IF(W28<=0,0,'1 - I TUOI 6 NUMERI'!$B$16*W28)))*(1+((1+0.05)*(1+'1 - I TUOI 6 NUMERI'!$B$14)-1))) | X29: =MAX(0,X28-(IF(W28<=0,0,(30000*(1+'1 - I TUOI 6 NUMERI'!$B$14)^7)/(1-'1 - I TUOI 6 NUMERI'!$B$15*(IF(W28<=0,0,MEDIAN(0,(W28-X28)/W28,1))))))*(1-(IF(W28<=0,0,MEDIAN(0,(W28-X28)/W28,1))))) | Y29: =IF(Y28<=0,0,(Y28-(IF(Y28<=0,0,(36000*(1+'1 - I TUOI 6 NUMERI'!$B$14)^7)/(1-'1 - I TUOI 6 NUMERI'!$B$15*(IF(Y28<=0,0,MEDIAN(0,(Y28-Z28)/Y28,1))))))-(IF(Y28<=0,0,'1 - I TUOI 6 NUMERI'!$B$16*Y28)))*(1+((1+0.01)*(1+'1 - I TUOI 6 NUMERI'!$B$14)-1))) | Z29: =MAX(0,Z28-(IF(Y28<=0,0,(36000*(1+'1 - I TUOI 6 NUMERI'!$B$14)^7)/(1-'1 - I TUOI 6 NUMERI'!$B$15*(IF(Y28<=0,0,MEDIAN(0,(Y28-Z28)/Y28,1))))))*(1-(IF(Y28<=0,0,MEDIAN(0,(Y28-Z28)/Y28,1))))) | AA29: =IF(AA28<=0,0,(AA28-(IF(AA28<=0,0,(36000*(1+'1 - I TUOI 6 NUMERI'!$B$14)^7)/(1-'1 - I TUOI 6 NUMERI'!$B$15*(IF(AA28<=0,0,MEDIAN(0,(AA28-AB28)/AA28,1))))))-(IF(AA28<=0,0,'1 - I TUOI 6 NUMERI'!$B$16*AA28)))*(1+((1+0.03)*(1+'1 - I TUOI 6 NUMERI'!$B$14)-1))) | AB29: =MAX(0,AB28-(IF(AA28<=0,0,(36000*(1+'1 - I TUOI 6 NUMERI'!$B$14)^7)/(1-'1 - I TUOI 6 NUMERI'!$B$15*(IF(AA28<=0,0,MEDIAN(0,(AA28-AB28)/AA28,1))))))*(1-(IF(AA28<=0,0,MEDIAN(0,(AA28-AB28)/AA28,1))))) | AC29: =IF(AC28<=0,0,(AC28-(IF(AC28<=0,0,(36000*(1+'1 - I TUOI 6 NUMERI'!$B$14)^7)/(1-'1 - I TUOI 6 NUMERI'!$B$15*(IF(AC28<=0,0,MEDIAN(0,(AC28-AD28)/AC28,1))))))-(IF(AC28<=0,0,'1 - I TUOI 6 NUMERI'!$B$16*AC28)))*(1+((1+0.05)*(1+'1 - I TUOI 6 NUMERI'!$B$14)-1))) | AD29: =MAX(0,AD28-(IF(AC28<=0,0,(36000*(1+'1 - I TUOI 6 NUMERI'!$B$14)^7)/(1-'1 - I TUOI 6 NUMERI'!$B$15*(IF(AC28<=0,0,MEDIAN(0,(AC28-AD28)/AC28,1))))))*(1-(IF(AC28<=0,0,MEDIAN(0,(AC28-AD28)/AC28,1)))))
F30: 8 | G30: =IF(G29<=0,0,(G29-(IF(G29<=0,0,(18000*(1+'1 - I TUOI 6 NUMERI'!$B$14)^8)/(1-'1 - I TUOI 6 NUMERI'!$B$15*(IF(G29<=0,0,MEDIAN(0,(G29-H29)/G29,1))))))-(IF(G29<=0,0,'1 - I TUOI 6 NUMERI'!$B$16*G29)))*(1+((1+0.01)*(1+'1 - I TUOI 6 NUMERI'!$B$14)-1))) | H30: =MAX(0,H29-(IF(G29<=0,0,(18000*(1+'1 - I TUOI 6 NUMERI'!$B$14)^8)/(1-'1 - I TUOI 6 NUMERI'!$B$15*(IF(G29<=0,0,MEDIAN(0,(G29-H29)/G29,1))))))*(1-(IF(G29<=0,0,MEDIAN(0,(G29-H29)/G29,1))))) | I30: =IF(I29<=0,0,(I29-(IF(I29<=0,0,(18000*(1+'1 - I TUOI 6 NUMERI'!$B$14)^8)/(1-'1 - I TUOI 6 NUMERI'!$B$15*(IF(I29<=0,0,MEDIAN(0,(I29-J29)/I29,1))))))-(IF(I29<=0,0,'1 - I TUOI 6 NUMERI'!$B$16*I29)))*(1+((1+0.03)*(1+'1 - I TUOI 6 NUMERI'!$B$14)-1))) | J30: =MAX(0,J29-(IF(I29<=0,0,(18000*(1+'1 - I TUOI 6 NUMERI'!$B$14)^8)/(1-'1 - I TUOI 6 NUMERI'!$B$15*(IF(I29<=0,0,MEDIAN(0,(I29-J29)/I29,1))))))*(1-(IF(I29<=0,0,MEDIAN(0,(I29-J29)/I29,1))))) | K30: =IF(K29<=0,0,(K29-(IF(K29<=0,0,(18000*(1+'1 - I TUOI 6 NUMERI'!$B$14)^8)/(1-'1 - I TUOI 6 NUMERI'!$B$15*(IF(K29<=0,0,MEDIAN(0,(K29-L29)/K29,1))))))-(IF(K29<=0,0,'1 - I TUOI 6 NUMERI'!$B$16*K29)))*(1+((1+0.05)*(1+'1 - I TUOI 6 NUMERI'!$B$14)-1))) | L30: =MAX(0,L29-(IF(K29<=0,0,(18000*(1+'1 - I TUOI 6 NUMERI'!$B$14)^8)/(1-'1 - I TUOI 6 NUMERI'!$B$15*(IF(K29<=0,0,MEDIAN(0,(K29-L29)/K29,1))))))*(1-(IF(K29<=0,0,MEDIAN(0,(K29-L29)/K29,1))))) | M30: =IF(M29<=0,0,(M29-(IF(M29<=0,0,(24000*(1+'1 - I TUOI 6 NUMERI'!$B$14)^8)/(1-'1 - I TUOI 6 NUMERI'!$B$15*(IF(M29<=0,0,MEDIAN(0,(M29-N29)/M29,1))))))-(IF(M29<=0,0,'1 - I TUOI 6 NUMERI'!$B$16*M29)))*(1+((1+0.01)*(1+'1 - I TUOI 6 NUMERI'!$B$14)-1))) | N30: =MAX(0,N29-(IF(M29<=0,0,(24000*(1+'1 - I TUOI 6 NUMERI'!$B$14)^8)/(1-'1 - I TUOI 6 NUMERI'!$B$15*(IF(M29<=0,0,MEDIAN(0,(M29-N29)/M29,1))))))*(1-(IF(M29<=0,0,MEDIAN(0,(M29-N29)/M29,1))))) | O30: =IF(O29<=0,0,(O29-(IF(O29<=0,0,(24000*(1+'1 - I TUOI 6 NUMERI'!$B$14)^8)/(1-'1 - I TUOI 6 NUMERI'!$B$15*(IF(O29<=0,0,MEDIAN(0,(O29-P29)/O29,1))))))-(IF(O29<=0,0,'1 - I TUOI 6 NUMERI'!$B$16*O29)))*(1+((1+0.03)*(1+'1 - I TUOI 6 NUMERI'!$B$14)-1))) | P30: =MAX(0,P29-(IF(O29<=0,0,(24000*(1+'1 - I TUOI 6 NUMERI'!$B$14)^8)/(1-'1 - I TUOI 6 NUMERI'!$B$15*(IF(O29<=0,0,MEDIAN(0,(O29-P29)/O29,1))))))*(1-(IF(O29<=0,0,MEDIAN(0,(O29-P29)/O29,1))))) | Q30: =IF(Q29<=0,0,(Q29-(IF(Q29<=0,0,(24000*(1+'1 - I TUOI 6 NUMERI'!$B$14)^8)/(1-'1 - I TUOI 6 NUMERI'!$B$15*(IF(Q29<=0,0,MEDIAN(0,(Q29-R29)/Q29,1))))))-(IF(Q29<=0,0,'1 - I TUOI 6 NUMERI'!$B$16*Q29)))*(1+((1+0.05)*(1+'1 - I TUOI 6 NUMERI'!$B$14)-1))) | R30: =MAX(0,R29-(IF(Q29<=0,0,(24000*(1+'1 - I TUOI 6 NUMERI'!$B$14)^8)/(1-'1 - I TUOI 6 NUMERI'!$B$15*(IF(Q29<=0,0,MEDIAN(0,(Q29-R29)/Q29,1))))))*(1-(IF(Q29<=0,0,MEDIAN(0,(Q29-R29)/Q29,1))))) | S30: =IF(S29<=0,0,(S29-(IF(S29<=0,0,(30000*(1+'1 - I TUOI 6 NUMERI'!$B$14)^8)/(1-'1 - I TUOI 6 NUMERI'!$B$15*(IF(S29<=0,0,MEDIAN(0,(S29-T29)/S29,1))))))-(IF(S29<=0,0,'1 - I TUOI 6 NUMERI'!$B$16*S29)))*(1+((1+0.01)*(1+'1 - I TUOI 6 NUMERI'!$B$14)-1))) | T30: =MAX(0,T29-(IF(S29<=0,0,(30000*(1+'1 - I TUOI 6 NUMERI'!$B$14)^8)/(1-'1 - I TUOI 6 NUMERI'!$B$15*(IF(S29<=0,0,MEDIAN(0,(S29-T29)/S29,1))))))*(1-(IF(S29<=0,0,MEDIAN(0,(S29-T29)/S29,1))))) | U30: =IF(U29<=0,0,(U29-(IF(U29<=0,0,(30000*(1+'1 - I TUOI 6 NUMERI'!$B$14)^8)/(1-'1 - I TUOI 6 NUMERI'!$B$15*(IF(U29<=0,0,MEDIAN(0,(U29-V29)/U29,1))))))-(IF(U29<=0,0,'1 - I TUOI 6 NUMERI'!$B$16*U29)))*(1+((1+0.03)*(1+'1 - I TUOI 6 NUMERI'!$B$14)-1))) | V30: =MAX(0,V29-(IF(U29<=0,0,(30000*(1+'1 - I TUOI 6 NUMERI'!$B$14)^8)/(1-'1 - I TUOI 6 NUMERI'!$B$15*(IF(U29<=0,0,MEDIAN(0,(U29-V29)/U29,1))))))*(1-(IF(U29<=0,0,MEDIAN(0,(U29-V29)/U29,1))))) | W30: =IF(W29<=0,0,(W29-(IF(W29<=0,0,(30000*(1+'1 - I TUOI 6 NUMERI'!$B$14)^8)/(1-'1 - I TUOI 6 NUMERI'!$B$15*(IF(W29<=0,0,MEDIAN(0,(W29-X29)/W29,1))))))-(IF(W29<=0,0,'1 - I TUOI 6 NUMERI'!$B$16*W29)))*(1+((1+0.05)*(1+'1 - I TUOI 6 NUMERI'!$B$14)-1))) | X30: =MAX(0,X29-(IF(W29<=0,0,(30000*(1+'1 - I TUOI 6 NUMERI'!$B$14)^8)/(1-'1 - I TUOI 6 NUMERI'!$B$15*(IF(W29<=0,0,MEDIAN(0,(W29-X29)/W29,1))))))*(1-(IF(W29<=0,0,MEDIAN(0,(W29-X29)/W29,1))))) | Y30: =IF(Y29<=0,0,(Y29-(IF(Y29<=0,0,(36000*(1+'1 - I TUOI 6 NUMERI'!$B$14)^8)/(1-'1 - I TUOI 6 NUMERI'!$B$15*(IF(Y29<=0,0,MEDIAN(0,(Y29-Z29)/Y29,1))))))-(IF(Y29<=0,0,'1 - I TUOI 6 NUMERI'!$B$16*Y29)))*(1+((1+0.01)*(1+'1 - I TUOI 6 NUMERI'!$B$14)-1))) | Z30: =MAX(0,Z29-(IF(Y29<=0,0,(36000*(1+'1 - I TUOI 6 NUMERI'!$B$14)^8)/(1-'1 - I TUOI 6 NUMERI'!$B$15*(IF(Y29<=0,0,MEDIAN(0,(Y29-Z29)/Y29,1))))))*(1-(IF(Y29<=0,0,MEDIAN(0,(Y29-Z29)/Y29,1))))) | AA30: =IF(AA29<=0,0,(AA29-(IF(AA29<=0,0,(36000*(1+'1 - I TUOI 6 NUMERI'!$B$14)^8)/(1-'1 - I TUOI 6 NUMERI'!$B$15*(IF(AA29<=0,0,MEDIAN(0,(AA29-AB29)/AA29,1))))))-(IF(AA29<=0,0,'1 - I TUOI 6 NUMERI'!$B$16*AA29)))*(1+((1+0.03)*(1+'1 - I TUOI 6 NUMERI'!$B$14)-1))) | AB30: =MAX(0,AB29-(IF(AA29<=0,0,(36000*(1+'1 - I TUOI 6 NUMERI'!$B$14)^8)/(1-'1 - I TUOI 6 NUMERI'!$B$15*(IF(AA29<=0,0,MEDIAN(0,(AA29-AB29)/AA29,1))))))*(1-(IF(AA29<=0,0,MEDIAN(0,(AA29-AB29)/AA29,1))))) | AC30: =IF(AC29<=0,0,(AC29-(IF(AC29<=0,0,(36000*(1+'1 - I TUOI 6 NUMERI'!$B$14)^8)/(1-'1 - I TUOI 6 NUMERI'!$B$15*(IF(AC29<=0,0,MEDIAN(0,(AC29-AD29)/AC29,1))))))-(IF(AC29<=0,0,'1 - I TUOI 6 NUMERI'!$B$16*AC29)))*(1+((1+0.05)*(1+'1 - I TUOI 6 NUMERI'!$B$14)-1))) | AD30: =MAX(0,AD29-(IF(AC29<=0,0,(36000*(1+'1 - I TUOI 6 NUMERI'!$B$14)^8)/(1-'1 - I TUOI 6 NUMERI'!$B$15*(IF(AC29<=0,0,MEDIAN(0,(AC29-AD29)/AC29,1))))))*(1-(IF(AC29<=0,0,MEDIAN(0,(AC29-AD29)/AC29,1)))))
F31: 9 | G31: =IF(G30<=0,0,(G30-(IF(G30<=0,0,(18000*(1+'1 - I TUOI 6 NUMERI'!$B$14)^9)/(1-'1 - I TUOI 6 NUMERI'!$B$15*(IF(G30<=0,0,MEDIAN(0,(G30-H30)/G30,1))))))-(IF(G30<=0,0,'1 - I TUOI 6 NUMERI'!$B$16*G30)))*(1+((1+0.01)*(1+'1 - I TUOI 6 NUMERI'!$B$14)-1))) | H31: =MAX(0,H30-(IF(G30<=0,0,(18000*(1+'1 - I TUOI 6 NUMERI'!$B$14)^9)/(1-'1 - I TUOI 6 NUMERI'!$B$15*(IF(G30<=0,0,MEDIAN(0,(G30-H30)/G30,1))))))*(1-(IF(G30<=0,0,MEDIAN(0,(G30-H30)/G30,1))))) | I31: =IF(I30<=0,0,(I30-(IF(I30<=0,0,(18000*(1+'1 - I TUOI 6 NUMERI'!$B$14)^9)/(1-'1 - I TUOI 6 NUMERI'!$B$15*(IF(I30<=0,0,MEDIAN(0,(I30-J30)/I30,1))))))-(IF(I30<=0,0,'1 - I TUOI 6 NUMERI'!$B$16*I30)))*(1+((1+0.03)*(1+'1 - I TUOI 6 NUMERI'!$B$14)-1))) | J31: =MAX(0,J30-(IF(I30<=0,0,(18000*(1+'1 - I TUOI 6 NUMERI'!$B$14)^9)/(1-'1 - I TUOI 6 NUMERI'!$B$15*(IF(I30<=0,0,MEDIAN(0,(I30-J30)/I30,1))))))*(1-(IF(I30<=0,0,MEDIAN(0,(I30-J30)/I30,1))))) | K31: =IF(K30<=0,0,(K30-(IF(K30<=0,0,(18000*(1+'1 - I TUOI 6 NUMERI'!$B$14)^9)/(1-'1 - I TUOI 6 NUMERI'!$B$15*(IF(K30<=0,0,MEDIAN(0,(K30-L30)/K30,1))))))-(IF(K30<=0,0,'1 - I TUOI 6 NUMERI'!$B$16*K30)))*(1+((1+0.05)*(1+'1 - I TUOI 6 NUMERI'!$B$14)-1))) | L31: =MAX(0,L30-(IF(K30<=0,0,(18000*(1+'1 - I TUOI 6 NUMERI'!$B$14)^9)/(1-'1 - I TUOI 6 NUMERI'!$B$15*(IF(K30<=0,0,MEDIAN(0,(K30-L30)/K30,1))))))*(1-(IF(K30<=0,0,MEDIAN(0,(K30-L30)/K30,1))))) | M31: =IF(M30<=0,0,(M30-(IF(M30<=0,0,(24000*(1+'1 - I TUOI 6 NUMERI'!$B$14)^9)/(1-'1 - I TUOI 6 NUMERI'!$B$15*(IF(M30<=0,0,MEDIAN(0,(M30-N30)/M30,1))))))-(IF(M30<=0,0,'1 - I TUOI 6 NUMERI'!$B$16*M30)))*(1+((1+0.01)*(1+'1 - I TUOI 6 NUMERI'!$B$14)-1))) | N31: =MAX(0,N30-(IF(M30<=0,0,(24000*(1+'1 - I TUOI 6 NUMERI'!$B$14)^9)/(1-'1 - I TUOI 6 NUMERI'!$B$15*(IF(M30<=0,0,MEDIAN(0,(M30-N30)/M30,1))))))*(1-(IF(M30<=0,0,MEDIAN(0,(M30-N30)/M30,1))))) | O31: =IF(O30<=0,0,(O30-(IF(O30<=0,0,(24000*(1+'1 - I TUOI 6 NUMERI'!$B$14)^9)/(1-'1 - I TUOI 6 NUMERI'!$B$15*(IF(O30<=0,0,MEDIAN(0,(O30-P30)/O30,1))))))-(IF(O30<=0,0,'1 - I TUOI 6 NUMERI'!$B$16*O30)))*(1+((1+0.03)*(1+'1 - I TUOI 6 NUMERI'!$B$14)-1))) | P31: =MAX(0,P30-(IF(O30<=0,0,(24000*(1+'1 - I TUOI 6 NUMERI'!$B$14)^9)/(1-'1 - I TUOI 6 NUMERI'!$B$15*(IF(O30<=0,0,MEDIAN(0,(O30-P30)/O30,1))))))*(1-(IF(O30<=0,0,MEDIAN(0,(O30-P30)/O30,1))))) | Q31: =IF(Q30<=0,0,(Q30-(IF(Q30<=0,0,(24000*(1+'1 - I TUOI 6 NUMERI'!$B$14)^9)/(1-'1 - I TUOI 6 NUMERI'!$B$15*(IF(Q30<=0,0,MEDIAN(0,(Q30-R30)/Q30,1))))))-(IF(Q30<=0,0,'1 - I TUOI 6 NUMERI'!$B$16*Q30)))*(1+((1+0.05)*(1+'1 - I TUOI 6 NUMERI'!$B$14)-1))) | R31: =MAX(0,R30-(IF(Q30<=0,0,(24000*(1+'1 - I TUOI 6 NUMERI'!$B$14)^9)/(1-'1 - I TUOI 6 NUMERI'!$B$15*(IF(Q30<=0,0,MEDIAN(0,(Q30-R30)/Q30,1))))))*(1-(IF(Q30<=0,0,MEDIAN(0,(Q30-R30)/Q30,1))))) | S31: =IF(S30<=0,0,(S30-(IF(S30<=0,0,(30000*(1+'1 - I TUOI 6 NUMERI'!$B$14)^9)/(1-'1 - I TUOI 6 NUMERI'!$B$15*(IF(S30<=0,0,MEDIAN(0,(S30-T30)/S30,1))))))-(IF(S30<=0,0,'1 - I TUOI 6 NUMERI'!$B$16*S30)))*(1+((1+0.01)*(1+'1 - I TUOI 6 NUMERI'!$B$14)-1))) | T31: =MAX(0,T30-(IF(S30<=0,0,(30000*(1+'1 - I TUOI 6 NUMERI'!$B$14)^9)/(1-'1 - I TUOI 6 NUMERI'!$B$15*(IF(S30<=0,0,MEDIAN(0,(S30-T30)/S30,1))))))*(1-(IF(S30<=0,0,MEDIAN(0,(S30-T30)/S30,1))))) | U31: =IF(U30<=0,0,(U30-(IF(U30<=0,0,(30000*(1+'1 - I TUOI 6 NUMERI'!$B$14)^9)/(1-'1 - I TUOI 6 NUMERI'!$B$15*(IF(U30<=0,0,MEDIAN(0,(U30-V30)/U30,1))))))-(IF(U30<=0,0,'1 - I TUOI 6 NUMERI'!$B$16*U30)))*(1+((1+0.03)*(1+'1 - I TUOI 6 NUMERI'!$B$14)-1))) | V31: =MAX(0,V30-(IF(U30<=0,0,(30000*(1+'1 - I TUOI 6 NUMERI'!$B$14)^9)/(1-'1 - I TUOI 6 NUMERI'!$B$15*(IF(U30<=0,0,MEDIAN(0,(U30-V30)/U30,1))))))*(1-(IF(U30<=0,0,MEDIAN(0,(U30-V30)/U30,1))))) | W31: =IF(W30<=0,0,(W30-(IF(W30<=0,0,(30000*(1+'1 - I TUOI 6 NUMERI'!$B$14)^9)/(1-'1 - I TUOI 6 NUMERI'!$B$15*(IF(W30<=0,0,MEDIAN(0,(W30-X30)/W30,1))))))-(IF(W30<=0,0,'1 - I TUOI 6 NUMERI'!$B$16*W30)))*(1+((1+0.05)*(1+'1 - I TUOI 6 NUMERI'!$B$14)-1))) | X31: =MAX(0,X30-(IF(W30<=0,0,(30000*(1+'1 - I TUOI 6 NUMERI'!$B$14)^9)/(1-'1 - I TUOI 6 NUMERI'!$B$15*(IF(W30<=0,0,MEDIAN(0,(W30-X30)/W30,1))))))*(1-(IF(W30<=0,0,MEDIAN(0,(W30-X30)/W30,1))))) | Y31: =IF(Y30<=0,0,(Y30-(IF(Y30<=0,0,(36000*(1+'1 - I TUOI 6 NUMERI'!$B$14)^9)/(1-'1 - I TUOI 6 NUMERI'!$B$15*(IF(Y30<=0,0,MEDIAN(0,(Y30-Z30)/Y30,1))))))-(IF(Y30<=0,0,'1 - I TUOI 6 NUMERI'!$B$16*Y30)))*(1+((1+0.01)*(1+'1 - I TUOI 6 NUMERI'!$B$14)-1))) | Z31: =MAX(0,Z30-(IF(Y30<=0,0,(36000*(1+'1 - I TUOI 6 NUMERI'!$B$14)^9)/(1-'1 - I TUOI 6 NUMERI'!$B$15*(IF(Y30<=0,0,MEDIAN(0,(Y30-Z30)/Y30,1))))))*(1-(IF(Y30<=0,0,MEDIAN(0,(Y30-Z30)/Y30,1))))) | AA31: =IF(AA30<=0,0,(AA30-(IF(AA30<=0,0,(36000*(1+'1 - I TUOI 6 NUMERI'!$B$14)^9)/(1-'1 - I TUOI 6 NUMERI'!$B$15*(IF(AA30<=0,0,MEDIAN(0,(AA30-AB30)/AA30,1))))))-(IF(AA30<=0,0,'1 - I TUOI 6 NUMERI'!$B$16*AA30)))*(1+((1+0.03)*(1+'1 - I TUOI 6 NUMERI'!$B$14)-1))) | AB31: =MAX(0,AB30-(IF(AA30<=0,0,(36000*(1+'1 - I TUOI 6 NUMERI'!$B$14)^9)/(1-'1 - I TUOI 6 NUMERI'!$B$15*(IF(AA30<=0,0,MEDIAN(0,(AA30-AB30)/AA30,1))))))*(1-(IF(AA30<=0,0,MEDIAN(0,(AA30-AB30)/AA30,1))))) | AC31: =IF(AC30<=0,0,(AC30-(IF(AC30<=0,0,(36000*(1+'1 - I TUOI 6 NUMERI'!$B$14)^9)/(1-'1 - I TUOI 6 NUMERI'!$B$15*(IF(AC30<=0,0,MEDIAN(0,(AC30-AD30)/AC30,1))))))-(IF(AC30<=0,0,'1 - I TUOI 6 NUMERI'!$B$16*AC30)))*(1+((1+0.05)*(1+'1 - I TUOI 6 NUMERI'!$B$14)-1))) | AD31: =MAX(0,AD30-(IF(AC30<=0,0,(36000*(1+'1 - I TUOI 6 NUMERI'!$B$14)^9)/(1-'1 - I TUOI 6 NUMERI'!$B$15*(IF(AC30<=0,0,MEDIAN(0,(AC30-AD30)/AC30,1))))))*(1-(IF(AC30<=0,0,MEDIAN(0,(AC30-AD30)/AC30,1)))))
F32: 10 | G32: =IF(G31<=0,0,(G31-(IF(G31<=0,0,(18000*(1+'1 - I TUOI 6 NUMERI'!$B$14)^10)/(1-'1 - I TUOI 6 NUMERI'!$B$15*(IF(G31<=0,0,MEDIAN(0,(G31-H31)/G31,1))))))-(IF(G31<=0,0,'1 - I TUOI 6 NUMERI'!$B$16*G31)))*(1+((1+0.01)*(1+'1 - I TUOI 6 NUMERI'!$B$14)-1))) | H32: =MAX(0,H31-(IF(G31<=0,0,(18000*(1+'1 - I TUOI 6 NUMERI'!$B$14)^10)/(1-'1 - I TUOI 6 NUMERI'!$B$15*(IF(G31<=0,0,MEDIAN(0,(G31-H31)/G31,1))))))*(1-(IF(G31<=0,0,MEDIAN(0,(G31-H31)/G31,1))))) | I32: =IF(I31<=0,0,(I31-(IF(I31<=0,0,(18000*(1+'1 - I TUOI 6 NUMERI'!$B$14)^10)/(1-'1 - I TUOI 6 NUMERI'!$B$15*(IF(I31<=0,0,MEDIAN(0,(I31-J31)/I31,1))))))-(IF(I31<=0,0,'1 - I TUOI 6 NUMERI'!$B$16*I31)))*(1+((1+0.03)*(1+'1 - I TUOI 6 NUMERI'!$B$14)-1))) | J32: =MAX(0,J31-(IF(I31<=0,0,(18000*(1+'1 - I TUOI 6 NUMERI'!$B$14)^10)/(1-'1 - I TUOI 6 NUMERI'!$B$15*(IF(I31<=0,0,MEDIAN(0,(I31-J31)/I31,1))))))*(1-(IF(I31<=0,0,MEDIAN(0,(I31-J31)/I31,1))))) | K32: =IF(K31<=0,0,(K31-(IF(K31<=0,0,(18000*(1+'1 - I TUOI 6 NUMERI'!$B$14)^10)/(1-'1 - I TUOI 6 NUMERI'!$B$15*(IF(K31<=0,0,MEDIAN(0,(K31-L31)/K31,1))))))-(IF(K31<=0,0,'1 - I TUOI 6 NUMERI'!$B$16*K31)))*(1+((1+0.05)*(1+'1 - I TUOI 6 NUMERI'!$B$14)-1))) | L32: =MAX(0,L31-(IF(K31<=0,0,(18000*(1+'1 - I TUOI 6 NUMERI'!$B$14)^10)/(1-'1 - I TUOI 6 NUMERI'!$B$15*(IF(K31<=0,0,MEDIAN(0,(K31-L31)/K31,1))))))*(1-(IF(K31<=0,0,MEDIAN(0,(K31-L31)/K31,1))))) | M32: =IF(M31<=0,0,(M31-(IF(M31<=0,0,(24000*(1+'1 - I TUOI 6 NUMERI'!$B$14)^10)/(1-'1 - I TUOI 6 NUMERI'!$B$15*(IF(M31<=0,0,MEDIAN(0,(M31-N31)/M31,1))))))-(IF(M31<=0,0,'1 - I TUOI 6 NUMERI'!$B$16*M31)))*(1+((1+0.01)*(1+'1 - I TUOI 6 NUMERI'!$B$14)-1))) | N32: =MAX(0,N31-(IF(M31<=0,0,(24000*(1+'1 - I TUOI 6 NUMERI'!$B$14)^10)/(1-'1 - I TUOI 6 NUMERI'!$B$15*(IF(M31<=0,0,MEDIAN(0,(M31-N31)/M31,1))))))*(1-(IF(M31<=0,0,MEDIAN(0,(M31-N31)/M31,1))))) | O32: =IF(O31<=0,0,(O31-(IF(O31<=0,0,(24000*(1+'1 - I TUOI 6 NUMERI'!$B$14)^10)/(1-'1 - I TUOI 6 NUMERI'!$B$15*(IF(O31<=0,0,MEDIAN(0,(O31-P31)/O31,1))))))-(IF(O31<=0,0,'1 - I TUOI 6 NUMERI'!$B$16*O31)))*(1+((1+0.03)*(1+'1 - I TUOI 6 NUMERI'!$B$14)-1))) | P32: =MAX(0,P31-(IF(O31<=0,0,(24000*(1+'1 - I TUOI 6 NUMERI'!$B$14)^10)/(1-'1 - I TUOI 6 NUMERI'!$B$15*(IF(O31<=0,0,MEDIAN(0,(O31-P31)/O31,1))))))*(1-(IF(O31<=0,0,MEDIAN(0,(O31-P31)/O31,1))))) | Q32: =IF(Q31<=0,0,(Q31-(IF(Q31<=0,0,(24000*(1+'1 - I TUOI 6 NUMERI'!$B$14)^10)/(1-'1 - I TUOI 6 NUMERI'!$B$15*(IF(Q31<=0,0,MEDIAN(0,(Q31-R31)/Q31,1))))))-(IF(Q31<=0,0,'1 - I TUOI 6 NUMERI'!$B$16*Q31)))*(1+((1+0.05)*(1+'1 - I TUOI 6 NUMERI'!$B$14)-1))) | R32: =MAX(0,R31-(IF(Q31<=0,0,(24000*(1+'1 - I TUOI 6 NUMERI'!$B$14)^10)/(1-'1 - I TUOI 6 NUMERI'!$B$15*(IF(Q31<=0,0,MEDIAN(0,(Q31-R31)/Q31,1))))))*(1-(IF(Q31<=0,0,MEDIAN(0,(Q31-R31)/Q31,1))))) | S32: =IF(S31<=0,0,(S31-(IF(S31<=0,0,(30000*(1+'1 - I TUOI 6 NUMERI'!$B$14)^10)/(1-'1 - I TUOI 6 NUMERI'!$B$15*(IF(S31<=0,0,MEDIAN(0,(S31-T31)/S31,1))))))-(IF(S31<=0,0,'1 - I TUOI 6 NUMERI'!$B$16*S31)))*(1+((1+0.01)*(1+'1 - I TUOI 6 NUMERI'!$B$14)-1))) | T32: =MAX(0,T31-(IF(S31<=0,0,(30000*(1+'1 - I TUOI 6 NUMERI'!$B$14)^10)/(1-'1 - I TUOI 6 NUMERI'!$B$15*(IF(S31<=0,0,MEDIAN(0,(S31-T31)/S31,1))))))*(1-(IF(S31<=0,0,MEDIAN(0,(S31-T31)/S31,1))))) | U32: =IF(U31<=0,0,(U31-(IF(U31<=0,0,(30000*(1+'1 - I TUOI 6 NUMERI'!$B$14)^10)/(1-'1 - I TUOI 6 NUMERI'!$B$15*(IF(U31<=0,0,MEDIAN(0,(U31-V31)/U31,1))))))-(IF(U31<=0,0,'1 - I TUOI 6 NUMERI'!$B$16*U31)))*(1+((1+0.03)*(1+'1 - I TUOI 6 NUMERI'!$B$14)-1))) | V32: =MAX(0,V31-(IF(U31<=0,0,(30000*(1+'1 - I TUOI 6 NUMERI'!$B$14)^10)/(1-'1 - I TUOI 6 NUMERI'!$B$15*(IF(U31<=0,0,MEDIAN(0,(U31-V31)/U31,1))))))*(1-(IF(U31<=0,0,MEDIAN(0,(U31-V31)/U31,1))))) | W32: =IF(W31<=0,0,(W31-(IF(W31<=0,0,(30000*(1+'1 - I TUOI 6 NUMERI'!$B$14)^10)/(1-'1 - I TUOI 6 NUMERI'!$B$15*(IF(W31<=0,0,MEDIAN(0,(W31-X31)/W31,1))))))-(IF(W31<=0,0,'1 - I TUOI 6 NUMERI'!$B$16*W31)))*(1+((1+0.05)*(1+'1 - I TUOI 6 NUMERI'!$B$14)-1))) | X32: =MAX(0,X31-(IF(W31<=0,0,(30000*(1+'1 - I TUOI 6 NUMERI'!$B$14)^10)/(1-'1 - I TUOI 6 NUMERI'!$B$15*(IF(W31<=0,0,MEDIAN(0,(W31-X31)/W31,1))))))*(1-(IF(W31<=0,0,MEDIAN(0,(W31-X31)/W31,1))))) | Y32: =IF(Y31<=0,0,(Y31-(IF(Y31<=0,0,(36000*(1+'1 - I TUOI 6 NUMERI'!$B$14)^10)/(1-'1 - I TUOI 6 NUMERI'!$B$15*(IF(Y31<=0,0,MEDIAN(0,(Y31-Z31)/Y31,1))))))-(IF(Y31<=0,0,'1 - I TUOI 6 NUMERI'!$B$16*Y31)))*(1+((1+0.01)*(1+'1 - I TUOI 6 NUMERI'!$B$14)-1))) | Z32: =MAX(0,Z31-(IF(Y31<=0,0,(36000*(1+'1 - I TUOI 6 NUMERI'!$B$14)^10)/(1-'1 - I TUOI 6 NUMERI'!$B$15*(IF(Y31<=0,0,MEDIAN(0,(Y31-Z31)/Y31,1))))))*(1-(IF(Y31<=0,0,MEDIAN(0,(Y31-Z31)/Y31,1))))) | AA32: =IF(AA31<=0,0,(AA31-(IF(AA31<=0,0,(36000*(1+'1 - I TUOI 6 NUMERI'!$B$14)^10)/(1-'1 - I TUOI 6 NUMERI'!$B$15*(IF(AA31<=0,0,MEDIAN(0,(AA31-AB31)/AA31,1))))))-(IF(AA31<=0,0,'1 - I TUOI 6 NUMERI'!$B$16*AA31)))*(1+((1+0.03)*(1+'1 - I TUOI 6 NUMERI'!$B$14)-1))) | AB32: =MAX(0,AB31-(IF(AA31<=0,0,(36000*(1+'1 - I TUOI 6 NUMERI'!$B$14)^10)/(1-'1 - I TUOI 6 NUMERI'!$B$15*(IF(AA31<=0,0,MEDIAN(0,(AA31-AB31)/AA31,1))))))*(1-(IF(AA31<=0,0,MEDIAN(0,(AA31-AB31)/AA31,1))))) | AC32: =IF(AC31<=0,0,(AC31-(IF(AC31<=0,0,(36000*(1+'1 - I TUOI 6 NUMERI'!$B$14)^10)/(1-'1 - I TUOI 6 NUMERI'!$B$15*(IF(AC31<=0,0,MEDIAN(0,(AC31-AD31)/AC31,1))))))-(IF(AC31<=0,0,'1 - I TUOI 6 NUMERI'!$B$16*AC31)))*(1+((1+0.05)*(1+'1 - I TUOI 6 NUMERI'!$B$14)-1))) | AD32: =MAX(0,AD31-(IF(AC31<=0,0,(36000*(1+'1 - I TUOI 6 NUMERI'!$B$14)^10)/(1-'1 - I TUOI 6 NUMERI'!$B$15*(IF(AC31<=0,0,MEDIAN(0,(AC31-AD31)/AC31,1))))))*(1-(IF(AC31<=0,0,MEDIAN(0,(AC31-AD31)/AC31,1)))))
F33: 11 | G33: =IF(G32<=0,0,(G32-(IF(G32<=0,0,(18000*(1+'1 - I TUOI 6 NUMERI'!$B$14)^11)/(1-'1 - I TUOI 6 NUMERI'!$B$15*(IF(G32<=0,0,MEDIAN(0,(G32-H32)/G32,1))))))-(IF(G32<=0,0,'1 - I TUOI 6 NUMERI'!$B$16*G32)))*(1+((1+0.01)*(1+'1 - I TUOI 6 NUMERI'!$B$14)-1))) | H33: =MAX(0,H32-(IF(G32<=0,0,(18000*(1+'1 - I TUOI 6 NUMERI'!$B$14)^11)/(1-'1 - I TUOI 6 NUMERI'!$B$15*(IF(G32<=0,0,MEDIAN(0,(G32-H32)/G32,1))))))*(1-(IF(G32<=0,0,MEDIAN(0,(G32-H32)/G32,1))))) | I33: =IF(I32<=0,0,(I32-(IF(I32<=0,0,(18000*(1+'1 - I TUOI 6 NUMERI'!$B$14)^11)/(1-'1 - I TUOI 6 NUMERI'!$B$15*(IF(I32<=0,0,MEDIAN(0,(I32-J32)/I32,1))))))-(IF(I32<=0,0,'1 - I TUOI 6 NUMERI'!$B$16*I32)))*(1+((1+0.03)*(1+'1 - I TUOI 6 NUMERI'!$B$14)-1))) | J33: =MAX(0,J32-(IF(I32<=0,0,(18000*(1+'1 - I TUOI 6 NUMERI'!$B$14)^11)/(1-'1 - I TUOI 6 NUMERI'!$B$15*(IF(I32<=0,0,MEDIAN(0,(I32-J32)/I32,1))))))*(1-(IF(I32<=0,0,MEDIAN(0,(I32-J32)/I32,1))))) | K33: =IF(K32<=0,0,(K32-(IF(K32<=0,0,(18000*(1+'1 - I TUOI 6 NUMERI'!$B$14)^11)/(1-'1 - I TUOI 6 NUMERI'!$B$15*(IF(K32<=0,0,MEDIAN(0,(K32-L32)/K32,1))))))-(IF(K32<=0,0,'1 - I TUOI 6 NUMERI'!$B$16*K32)))*(1+((1+0.05)*(1+'1 - I TUOI 6 NUMERI'!$B$14)-1))) | L33: =MAX(0,L32-(IF(K32<=0,0,(18000*(1+'1 - I TUOI 6 NUMERI'!$B$14)^11)/(1-'1 - I TUOI 6 NUMERI'!$B$15*(IF(K32<=0,0,MEDIAN(0,(K32-L32)/K32,1))))))*(1-(IF(K32<=0,0,MEDIAN(0,(K32-L32)/K32,1))))) | M33: =IF(M32<=0,0,(M32-(IF(M32<=0,0,(24000*(1+'1 - I TUOI 6 NUMERI'!$B$14)^11)/(1-'1 - I TUOI 6 NUMERI'!$B$15*(IF(M32<=0,0,MEDIAN(0,(M32-N32)/M32,1))))))-(IF(M32<=0,0,'1 - I TUOI 6 NUMERI'!$B$16*M32)))*(1+((1+0.01)*(1+'1 - I TUOI 6 NUMERI'!$B$14)-1))) | N33: =MAX(0,N32-(IF(M32<=0,0,(24000*(1+'1 - I TUOI 6 NUMERI'!$B$14)^11)/(1-'1 - I TUOI 6 NUMERI'!$B$15*(IF(M32<=0,0,MEDIAN(0,(M32-N32)/M32,1))))))*(1-(IF(M32<=0,0,MEDIAN(0,(M32-N32)/M32,1))))) | O33: =IF(O32<=0,0,(O32-(IF(O32<=0,0,(24000*(1+'1 - I TUOI 6 NUMERI'!$B$14)^11)/(1-'1 - I TUOI 6 NUMERI'!$B$15*(IF(O32<=0,0,MEDIAN(0,(O32-P32)/O32,1))))))-(IF(O32<=0,0,'1 - I TUOI 6 NUMERI'!$B$16*O32)))*(1+((1+0.03)*(1+'1 - I TUOI 6 NUMERI'!$B$14)-1))) | P33: =MAX(0,P32-(IF(O32<=0,0,(24000*(1+'1 - I TUOI 6 NUMERI'!$B$14)^11)/(1-'1 - I TUOI 6 NUMERI'!$B$15*(IF(O32<=0,0,MEDIAN(0,(O32-P32)/O32,1))))))*(1-(IF(O32<=0,0,MEDIAN(0,(O32-P32)/O32,1))))) | Q33: =IF(Q32<=0,0,(Q32-(IF(Q32<=0,0,(24000*(1+'1 - I TUOI 6 NUMERI'!$B$14)^11)/(1-'1 - I TUOI 6 NUMERI'!$B$15*(IF(Q32<=0,0,MEDIAN(0,(Q32-R32)/Q32,1))))))-(IF(Q32<=0,0,'1 - I TUOI 6 NUMERI'!$B$16*Q32)))*(1+((1+0.05)*(1+'1 - I TUOI 6 NUMERI'!$B$14)-1))) | R33: =MAX(0,R32-(IF(Q32<=0,0,(24000*(1+'1 - I TUOI 6 NUMERI'!$B$14)^11)/(1-'1 - I TUOI 6 NUMERI'!$B$15*(IF(Q32<=0,0,MEDIAN(0,(Q32-R32)/Q32,1))))))*(1-(IF(Q32<=0,0,MEDIAN(0,(Q32-R32)/Q32,1))))) | S33: =IF(S32<=0,0,(S32-(IF(S32<=0,0,(30000*(1+'1 - I TUOI 6 NUMERI'!$B$14)^11)/(1-'1 - I TUOI 6 NUMERI'!$B$15*(IF(S32<=0,0,MEDIAN(0,(S32-T32)/S32,1))))))-(IF(S32<=0,0,'1 - I TUOI 6 NUMERI'!$B$16*S32)))*(1+((1+0.01)*(1+'1 - I TUOI 6 NUMERI'!$B$14)-1))) | T33: =MAX(0,T32-(IF(S32<=0,0,(30000*(1+'1 - I TUOI 6 NUMERI'!$B$14)^11)/(1-'1 - I TUOI 6 NUMERI'!$B$15*(IF(S32<=0,0,MEDIAN(0,(S32-T32)/S32,1))))))*(1-(IF(S32<=0,0,MEDIAN(0,(S32-T32)/S32,1))))) | U33: =IF(U32<=0,0,(U32-(IF(U32<=0,0,(30000*(1+'1 - I TUOI 6 NUMERI'!$B$14)^11)/(1-'1 - I TUOI 6 NUMERI'!$B$15*(IF(U32<=0,0,MEDIAN(0,(U32-V32)/U32,1))))))-(IF(U32<=0,0,'1 - I TUOI 6 NUMERI'!$B$16*U32)))*(1+((1+0.03)*(1+'1 - I TUOI 6 NUMERI'!$B$14)-1))) | V33: =MAX(0,V32-(IF(U32<=0,0,(30000*(1+'1 - I TUOI 6 NUMERI'!$B$14)^11)/(1-'1 - I TUOI 6 NUMERI'!$B$15*(IF(U32<=0,0,MEDIAN(0,(U32-V32)/U32,1))))))*(1-(IF(U32<=0,0,MEDIAN(0,(U32-V32)/U32,1))))) | W33: =IF(W32<=0,0,(W32-(IF(W32<=0,0,(30000*(1+'1 - I TUOI 6 NUMERI'!$B$14)^11)/(1-'1 - I TUOI 6 NUMERI'!$B$15*(IF(W32<=0,0,MEDIAN(0,(W32-X32)/W32,1))))))-(IF(W32<=0,0,'1 - I TUOI 6 NUMERI'!$B$16*W32)))*(1+((1+0.05)*(1+'1 - I TUOI 6 NUMERI'!$B$14)-1))) | X33: =MAX(0,X32-(IF(W32<=0,0,(30000*(1+'1 - I TUOI 6 NUMERI'!$B$14)^11)/(1-'1 - I TUOI 6 NUMERI'!$B$15*(IF(W32<=0,0,MEDIAN(0,(W32-X32)/W32,1))))))*(1-(IF(W32<=0,0,MEDIAN(0,(W32-X32)/W32,1))))) | Y33: =IF(Y32<=0,0,(Y32-(IF(Y32<=0,0,(36000*(1+'1 - I TUOI 6 NUMERI'!$B$14)^11)/(1-'1 - I TUOI 6 NUMERI'!$B$15*(IF(Y32<=0,0,MEDIAN(0,(Y32-Z32)/Y32,1))))))-(IF(Y32<=0,0,'1 - I TUOI 6 NUMERI'!$B$16*Y32)))*(1+((1+0.01)*(1+'1 - I TUOI 6 NUMERI'!$B$14)-1))) | Z33: =MAX(0,Z32-(IF(Y32<=0,0,(36000*(1+'1 - I TUOI 6 NUMERI'!$B$14)^11)/(1-'1 - I TUOI 6 NUMERI'!$B$15*(IF(Y32<=0,0,MEDIAN(0,(Y32-Z32)/Y32,1))))))*(1-(IF(Y32<=0,0,MEDIAN(0,(Y32-Z32)/Y32,1))))) | AA33: =IF(AA32<=0,0,(AA32-(IF(AA32<=0,0,(36000*(1+'1 - I TUOI 6 NUMERI'!$B$14)^11)/(1-'1 - I TUOI 6 NUMERI'!$B$15*(IF(AA32<=0,0,MEDIAN(0,(AA32-AB32)/AA32,1))))))-(IF(AA32<=0,0,'1 - I TUOI 6 NUMERI'!$B$16*AA32)))*(1+((1+0.03)*(1+'1 - I TUOI 6 NUMERI'!$B$14)-1))) | AB33: =MAX(0,AB32-(IF(AA32<=0,0,(36000*(1+'1 - I TUOI 6 NUMERI'!$B$14)^11)/(1-'1 - I TUOI 6 NUMERI'!$B$15*(IF(AA32<=0,0,MEDIAN(0,(AA32-AB32)/AA32,1))))))*(1-(IF(AA32<=0,0,MEDIAN(0,(AA32-AB32)/AA32,1))))) | AC33: =IF(AC32<=0,0,(AC32-(IF(AC32<=0,0,(36000*(1+'1 - I TUOI 6 NUMERI'!$B$14)^11)/(1-'1 - I TUOI 6 NUMERI'!$B$15*(IF(AC32<=0,0,MEDIAN(0,(AC32-AD32)/AC32,1))))))-(IF(AC32<=0,0,'1 - I TUOI 6 NUMERI'!$B$16*AC32)))*(1+((1+0.05)*(1+'1 - I TUOI 6 NUMERI'!$B$14)-1))) | AD33: =MAX(0,AD32-(IF(AC32<=0,0,(36000*(1+'1 - I TUOI 6 NUMERI'!$B$14)^11)/(1-'1 - I TUOI 6 NUMERI'!$B$15*(IF(AC32<=0,0,MEDIAN(0,(AC32-AD32)/AC32,1))))))*(1-(IF(AC32<=0,0,MEDIAN(0,(AC32-AD32)/AC32,1)))))
F34: 12 | G34: =IF(G33<=0,0,(G33-(IF(G33<=0,0,(18000*(1+'1 - I TUOI 6 NUMERI'!$B$14)^12)/(1-'1 - I TUOI 6 NUMERI'!$B$15*(IF(G33<=0,0,MEDIAN(0,(G33-H33)/G33,1))))))-(IF(G33<=0,0,'1 - I TUOI 6 NUMERI'!$B$16*G33)))*(1+((1+0.01)*(1+'1 - I TUOI 6 NUMERI'!$B$14)-1))) | H34: =MAX(0,H33-(IF(G33<=0,0,(18000*(1+'1 - I TUOI 6 NUMERI'!$B$14)^12)/(1-'1 - I TUOI 6 NUMERI'!$B$15*(IF(G33<=0,0,MEDIAN(0,(G33-H33)/G33,1))))))*(1-(IF(G33<=0,0,MEDIAN(0,(G33-H33)/G33,1))))) | I34: =IF(I33<=0,0,(I33-(IF(I33<=0,0,(18000*(1+'1 - I TUOI 6 NUMERI'!$B$14)^12)/(1-'1 - I TUOI 6 NUMERI'!$B$15*(IF(I33<=0,0,MEDIAN(0,(I33-J33)/I33,1))))))-(IF(I33<=0,0,'1 - I TUOI 6 NUMERI'!$B$16*I33)))*(1+((1+0.03)*(1+'1 - I TUOI 6 NUMERI'!$B$14)-1))) | J34: =MAX(0,J33-(IF(I33<=0,0,(18000*(1+'1 - I TUOI 6 NUMERI'!$B$14)^12)/(1-'1 - I TUOI 6 NUMERI'!$B$15*(IF(I33<=0,0,MEDIAN(0,(I33-J33)/I33,1))))))*(1-(IF(I33<=0,0,MEDIAN(0,(I33-J33)/I33,1))))) | K34: =IF(K33<=0,0,(K33-(IF(K33<=0,0,(18000*(1+'1 - I TUOI 6 NUMERI'!$B$14)^12)/(1-'1 - I TUOI 6 NUMERI'!$B$15*(IF(K33<=0,0,MEDIAN(0,(K33-L33)/K33,1))))))-(IF(K33<=0,0,'1 - I TUOI 6 NUMERI'!$B$16*K33)))*(1+((1+0.05)*(1+'1 - I TUOI 6 NUMERI'!$B$14)-1))) | L34: =MAX(0,L33-(IF(K33<=0,0,(18000*(1+'1 - I TUOI 6 NUMERI'!$B$14)^12)/(1-'1 - I TUOI 6 NUMERI'!$B$15*(IF(K33<=0,0,MEDIAN(0,(K33-L33)/K33,1))))))*(1-(IF(K33<=0,0,MEDIAN(0,(K33-L33)/K33,1))))) | M34: =IF(M33<=0,0,(M33-(IF(M33<=0,0,(24000*(1+'1 - I TUOI 6 NUMERI'!$B$14)^12)/(1-'1 - I TUOI 6 NUMERI'!$B$15*(IF(M33<=0,0,MEDIAN(0,(M33-N33)/M33,1))))))-(IF(M33<=0,0,'1 - I TUOI 6 NUMERI'!$B$16*M33)))*(1+((1+0.01)*(1+'1 - I TUOI 6 NUMERI'!$B$14)-1))) | N34: =MAX(0,N33-(IF(M33<=0,0,(24000*(1+'1 - I TUOI 6 NUMERI'!$B$14)^12)/(1-'1 - I TUOI 6 NUMERI'!$B$15*(IF(M33<=0,0,MEDIAN(0,(M33-N33)/M33,1))))))*(1-(IF(M33<=0,0,MEDIAN(0,(M33-N33)/M33,1))))) | O34: =IF(O33<=0,0,(O33-(IF(O33<=0,0,(24000*(1+'1 - I TUOI 6 NUMERI'!$B$14)^12)/(1-'1 - I TUOI 6 NUMERI'!$B$15*(IF(O33<=0,0,MEDIAN(0,(O33-P33)/O33,1))))))-(IF(O33<=0,0,'1 - I TUOI 6 NUMERI'!$B$16*O33)))*(1+((1+0.03)*(1+'1 - I TUOI 6 NUMERI'!$B$14)-1))) | P34: =MAX(0,P33-(IF(O33<=0,0,(24000*(1+'1 - I TUOI 6 NUMERI'!$B$14)^12)/(1-'1 - I TUOI 6 NUMERI'!$B$15*(IF(O33<=0,0,MEDIAN(0,(O33-P33)/O33,1))))))*(1-(IF(O33<=0,0,MEDIAN(0,(O33-P33)/O33,1))))) | Q34: =IF(Q33<=0,0,(Q33-(IF(Q33<=0,0,(24000*(1+'1 - I TUOI 6 NUMERI'!$B$14)^12)/(1-'1 - I TUOI 6 NUMERI'!$B$15*(IF(Q33<=0,0,MEDIAN(0,(Q33-R33)/Q33,1))))))-(IF(Q33<=0,0,'1 - I TUOI 6 NUMERI'!$B$16*Q33)))*(1+((1+0.05)*(1+'1 - I TUOI 6 NUMERI'!$B$14)-1))) | R34: =MAX(0,R33-(IF(Q33<=0,0,(24000*(1+'1 - I TUOI 6 NUMERI'!$B$14)^12)/(1-'1 - I TUOI 6 NUMERI'!$B$15*(IF(Q33<=0,0,MEDIAN(0,(Q33-R33)/Q33,1))))))*(1-(IF(Q33<=0,0,MEDIAN(0,(Q33-R33)/Q33,1))))) | S34: =IF(S33<=0,0,(S33-(IF(S33<=0,0,(30000*(1+'1 - I TUOI 6 NUMERI'!$B$14)^12)/(1-'1 - I TUOI 6 NUMERI'!$B$15*(IF(S33<=0,0,MEDIAN(0,(S33-T33)/S33,1))))))-(IF(S33<=0,0,'1 - I TUOI 6 NUMERI'!$B$16*S33)))*(1+((1+0.01)*(1+'1 - I TUOI 6 NUMERI'!$B$14)-1))) | T34: =MAX(0,T33-(IF(S33<=0,0,(30000*(1+'1 - I TUOI 6 NUMERI'!$B$14)^12)/(1-'1 - I TUOI 6 NUMERI'!$B$15*(IF(S33<=0,0,MEDIAN(0,(S33-T33)/S33,1))))))*(1-(IF(S33<=0,0,MEDIAN(0,(S33-T33)/S33,1))))) | U34: =IF(U33<=0,0,(U33-(IF(U33<=0,0,(30000*(1+'1 - I TUOI 6 NUMERI'!$B$14)^12)/(1-'1 - I TUOI 6 NUMERI'!$B$15*(IF(U33<=0,0,MEDIAN(0,(U33-V33)/U33,1))))))-(IF(U33<=0,0,'1 - I TUOI 6 NUMERI'!$B$16*U33)))*(1+((1+0.03)*(1+'1 - I TUOI 6 NUMERI'!$B$14)-1))) | V34: =MAX(0,V33-(IF(U33<=0,0,(30000*(1+'1 - I TUOI 6 NUMERI'!$B$14)^12)/(1-'1 - I TUOI 6 NUMERI'!$B$15*(IF(U33<=0,0,MEDIAN(0,(U33-V33)/U33,1))))))*(1-(IF(U33<=0,0,MEDIAN(0,(U33-V33)/U33,1))))) | W34: =IF(W33<=0,0,(W33-(IF(W33<=0,0,(30000*(1+'1 - I TUOI 6 NUMERI'!$B$14)^12)/(1-'1 - I TUOI 6 NUMERI'!$B$15*(IF(W33<=0,0,MEDIAN(0,(W33-X33)/W33,1))))))-(IF(W33<=0,0,'1 - I TUOI 6 NUMERI'!$B$16*W33)))*(1+((1+0.05)*(1+'1 - I TUOI 6 NUMERI'!$B$14)-1))) | X34: =MAX(0,X33-(IF(W33<=0,0,(30000*(1+'1 - I TUOI 6 NUMERI'!$B$14)^12)/(1-'1 - I TUOI 6 NUMERI'!$B$15*(IF(W33<=0,0,MEDIAN(0,(W33-X33)/W33,1))))))*(1-(IF(W33<=0,0,MEDIAN(0,(W33-X33)/W33,1))))) | Y34: =IF(Y33<=0,0,(Y33-(IF(Y33<=0,0,(36000*(1+'1 - I TUOI 6 NUMERI'!$B$14)^12)/(1-'1 - I TUOI 6 NUMERI'!$B$15*(IF(Y33<=0,0,MEDIAN(0,(Y33-Z33)/Y33,1))))))-(IF(Y33<=0,0,'1 - I TUOI 6 NUMERI'!$B$16*Y33)))*(1+((1+0.01)*(1+'1 - I TUOI 6 NUMERI'!$B$14)-1))) | Z34: =MAX(0,Z33-(IF(Y33<=0,0,(36000*(1+'1 - I TUOI 6 NUMERI'!$B$14)^12)/(1-'1 - I TUOI 6 NUMERI'!$B$15*(IF(Y33<=0,0,MEDIAN(0,(Y33-Z33)/Y33,1))))))*(1-(IF(Y33<=0,0,MEDIAN(0,(Y33-Z33)/Y33,1))))) | AA34: =IF(AA33<=0,0,(AA33-(IF(AA33<=0,0,(36000*(1+'1 - I TUOI 6 NUMERI'!$B$14)^12)/(1-'1 - I TUOI 6 NUMERI'!$B$15*(IF(AA33<=0,0,MEDIAN(0,(AA33-AB33)/AA33,1))))))-(IF(AA33<=0,0,'1 - I TUOI 6 NUMERI'!$B$16*AA33)))*(1+((1+0.03)*(1+'1 - I TUOI 6 NUMERI'!$B$14)-1))) | AB34: =MAX(0,AB33-(IF(AA33<=0,0,(36000*(1+'1 - I TUOI 6 NUMERI'!$B$14)^12)/(1-'1 - I TUOI 6 NUMERI'!$B$15*(IF(AA33<=0,0,MEDIAN(0,(AA33-AB33)/AA33,1))))))*(1-(IF(AA33<=0,0,MEDIAN(0,(AA33-AB33)/AA33,1))))) | AC34: =IF(AC33<=0,0,(AC33-(IF(AC33<=0,0,(36000*(1+'1 - I TUOI 6 NUMERI'!$B$14)^12)/(1-'1 - I TUOI 6 NUMERI'!$B$15*(IF(AC33<=0,0,MEDIAN(0,(AC33-AD33)/AC33,1))))))-(IF(AC33<=0,0,'1 - I TUOI 6 NUMERI'!$B$16*AC33)))*(1+((1+0.05)*(1+'1 - I TUOI 6 NUMERI'!$B$14)-1))) | AD34: =MAX(0,AD33-(IF(AC33<=0,0,(36000*(1+'1 - I TUOI 6 NUMERI'!$B$14)^12)/(1-'1 - I TUOI 6 NUMERI'!$B$15*(IF(AC33<=0,0,MEDIAN(0,(AC33-AD33)/AC33,1))))))*(1-(IF(AC33<=0,0,MEDIAN(0,(AC33-AD33)/AC33,1)))))
F35: 13 | G35: =IF(G34<=0,0,(G34-(IF(G34<=0,0,(18000*(1+'1 - I TUOI 6 NUMERI'!$B$14)^13)/(1-'1 - I TUOI 6 NUMERI'!$B$15*(IF(G34<=0,0,MEDIAN(0,(G34-H34)/G34,1))))))-(IF(G34<=0,0,'1 - I TUOI 6 NUMERI'!$B$16*G34)))*(1+((1+0.01)*(1+'1 - I TUOI 6 NUMERI'!$B$14)-1))) | H35: =MAX(0,H34-(IF(G34<=0,0,(18000*(1+'1 - I TUOI 6 NUMERI'!$B$14)^13)/(1-'1 - I TUOI 6 NUMERI'!$B$15*(IF(G34<=0,0,MEDIAN(0,(G34-H34)/G34,1))))))*(1-(IF(G34<=0,0,MEDIAN(0,(G34-H34)/G34,1))))) | I35: =IF(I34<=0,0,(I34-(IF(I34<=0,0,(18000*(1+'1 - I TUOI 6 NUMERI'!$B$14)^13)/(1-'1 - I TUOI 6 NUMERI'!$B$15*(IF(I34<=0,0,MEDIAN(0,(I34-J34)/I34,1))))))-(IF(I34<=0,0,'1 - I TUOI 6 NUMERI'!$B$16*I34)))*(1+((1+0.03)*(1+'1 - I TUOI 6 NUMERI'!$B$14)-1))) | J35: =MAX(0,J34-(IF(I34<=0,0,(18000*(1+'1 - I TUOI 6 NUMERI'!$B$14)^13)/(1-'1 - I TUOI 6 NUMERI'!$B$15*(IF(I34<=0,0,MEDIAN(0,(I34-J34)/I34,1))))))*(1-(IF(I34<=0,0,MEDIAN(0,(I34-J34)/I34,1))))) | K35: =IF(K34<=0,0,(K34-(IF(K34<=0,0,(18000*(1+'1 - I TUOI 6 NUMERI'!$B$14)^13)/(1-'1 - I TUOI 6 NUMERI'!$B$15*(IF(K34<=0,0,MEDIAN(0,(K34-L34)/K34,1))))))-(IF(K34<=0,0,'1 - I TUOI 6 NUMERI'!$B$16*K34)))*(1+((1+0.05)*(1+'1 - I TUOI 6 NUMERI'!$B$14)-1))) | L35: =MAX(0,L34-(IF(K34<=0,0,(18000*(1+'1 - I TUOI 6 NUMERI'!$B$14)^13)/(1-'1 - I TUOI 6 NUMERI'!$B$15*(IF(K34<=0,0,MEDIAN(0,(K34-L34)/K34,1))))))*(1-(IF(K34<=0,0,MEDIAN(0,(K34-L34)/K34,1))))) | M35: =IF(M34<=0,0,(M34-(IF(M34<=0,0,(24000*(1+'1 - I TUOI 6 NUMERI'!$B$14)^13)/(1-'1 - I TUOI 6 NUMERI'!$B$15*(IF(M34<=0,0,MEDIAN(0,(M34-N34)/M34,1))))))-(IF(M34<=0,0,'1 - I TUOI 6 NUMERI'!$B$16*M34)))*(1+((1+0.01)*(1+'1 - I TUOI 6 NUMERI'!$B$14)-1))) | N35: =MAX(0,N34-(IF(M34<=0,0,(24000*(1+'1 - I TUOI 6 NUMERI'!$B$14)^13)/(1-'1 - I TUOI 6 NUMERI'!$B$15*(IF(M34<=0,0,MEDIAN(0,(M34-N34)/M34,1))))))*(1-(IF(M34<=0,0,MEDIAN(0,(M34-N34)/M34,1))))) | O35: =IF(O34<=0,0,(O34-(IF(O34<=0,0,(24000*(1+'1 - I TUOI 6 NUMERI'!$B$14)^13)/(1-'1 - I TUOI 6 NUMERI'!$B$15*(IF(O34<=0,0,MEDIAN(0,(O34-P34)/O34,1))))))-(IF(O34<=0,0,'1 - I TUOI 6 NUMERI'!$B$16*O34)))*(1+((1+0.03)*(1+'1 - I TUOI 6 NUMERI'!$B$14)-1))) | P35: =MAX(0,P34-(IF(O34<=0,0,(24000*(1+'1 - I TUOI 6 NUMERI'!$B$14)^13)/(1-'1 - I TUOI 6 NUMERI'!$B$15*(IF(O34<=0,0,MEDIAN(0,(O34-P34)/O34,1))))))*(1-(IF(O34<=0,0,MEDIAN(0,(O34-P34)/O34,1))))) | Q35: =IF(Q34<=0,0,(Q34-(IF(Q34<=0,0,(24000*(1+'1 - I TUOI 6 NUMERI'!$B$14)^13)/(1-'1 - I TUOI 6 NUMERI'!$B$15*(IF(Q34<=0,0,MEDIAN(0,(Q34-R34)/Q34,1))))))-(IF(Q34<=0,0,'1 - I TUOI 6 NUMERI'!$B$16*Q34)))*(1+((1+0.05)*(1+'1 - I TUOI 6 NUMERI'!$B$14)-1))) | R35: =MAX(0,R34-(IF(Q34<=0,0,(24000*(1+'1 - I TUOI 6 NUMERI'!$B$14)^13)/(1-'1 - I TUOI 6 NUMERI'!$B$15*(IF(Q34<=0,0,MEDIAN(0,(Q34-R34)/Q34,1))))))*(1-(IF(Q34<=0,0,MEDIAN(0,(Q34-R34)/Q34,1))))) | S35: =IF(S34<=0,0,(S34-(IF(S34<=0,0,(30000*(1+'1 - I TUOI 6 NUMERI'!$B$14)^13)/(1-'1 - I TUOI 6 NUMERI'!$B$15*(IF(S34<=0,0,MEDIAN(0,(S34-T34)/S34,1))))))-(IF(S34<=0,0,'1 - I TUOI 6 NUMERI'!$B$16*S34)))*(1+((1+0.01)*(1+'1 - I TUOI 6 NUMERI'!$B$14)-1))) | T35: =MAX(0,T34-(IF(S34<=0,0,(30000*(1+'1 - I TUOI 6 NUMERI'!$B$14)^13)/(1-'1 - I TUOI 6 NUMERI'!$B$15*(IF(S34<=0,0,MEDIAN(0,(S34-T34)/S34,1))))))*(1-(IF(S34<=0,0,MEDIAN(0,(S34-T34)/S34,1))))) | U35: =IF(U34<=0,0,(U34-(IF(U34<=0,0,(30000*(1+'1 - I TUOI 6 NUMERI'!$B$14)^13)/(1-'1 - I TUOI 6 NUMERI'!$B$15*(IF(U34<=0,0,MEDIAN(0,(U34-V34)/U34,1))))))-(IF(U34<=0,0,'1 - I TUOI 6 NUMERI'!$B$16*U34)))*(1+((1+0.03)*(1+'1 - I TUOI 6 NUMERI'!$B$14)-1))) | V35: =MAX(0,V34-(IF(U34<=0,0,(30000*(1+'1 - I TUOI 6 NUMERI'!$B$14)^13)/(1-'1 - I TUOI 6 NUMERI'!$B$15*(IF(U34<=0,0,MEDIAN(0,(U34-V34)/U34,1))))))*(1-(IF(U34<=0,0,MEDIAN(0,(U34-V34)/U34,1))))) | W35: =IF(W34<=0,0,(W34-(IF(W34<=0,0,(30000*(1+'1 - I TUOI 6 NUMERI'!$B$14)^13)/(1-'1 - I TUOI 6 NUMERI'!$B$15*(IF(W34<=0,0,MEDIAN(0,(W34-X34)/W34,1))))))-(IF(W34<=0,0,'1 - I TUOI 6 NUMERI'!$B$16*W34)))*(1+((1+0.05)*(1+'1 - I TUOI 6 NUMERI'!$B$14)-1))) | X35: =MAX(0,X34-(IF(W34<=0,0,(30000*(1+'1 - I TUOI 6 NUMERI'!$B$14)^13)/(1-'1 - I TUOI 6 NUMERI'!$B$15*(IF(W34<=0,0,MEDIAN(0,(W34-X34)/W34,1))))))*(1-(IF(W34<=0,0,MEDIAN(0,(W34-X34)/W34,1))))) | Y35: =IF(Y34<=0,0,(Y34-(IF(Y34<=0,0,(36000*(1+'1 - I TUOI 6 NUMERI'!$B$14)^13)/(1-'1 - I TUOI 6 NUMERI'!$B$15*(IF(Y34<=0,0,MEDIAN(0,(Y34-Z34)/Y34,1))))))-(IF(Y34<=0,0,'1 - I TUOI 6 NUMERI'!$B$16*Y34)))*(1+((1+0.01)*(1+'1 - I TUOI 6 NUMERI'!$B$14)-1))) | Z35: =MAX(0,Z34-(IF(Y34<=0,0,(36000*(1+'1 - I TUOI 6 NUMERI'!$B$14)^13)/(1-'1 - I TUOI 6 NUMERI'!$B$15*(IF(Y34<=0,0,MEDIAN(0,(Y34-Z34)/Y34,1))))))*(1-(IF(Y34<=0,0,MEDIAN(0,(Y34-Z34)/Y34,1))))) | AA35: =IF(AA34<=0,0,(AA34-(IF(AA34<=0,0,(36000*(1+'1 - I TUOI 6 NUMERI'!$B$14)^13)/(1-'1 - I TUOI 6 NUMERI'!$B$15*(IF(AA34<=0,0,MEDIAN(0,(AA34-AB34)/AA34,1))))))-(IF(AA34<=0,0,'1 - I TUOI 6 NUMERI'!$B$16*AA34)))*(1+((1+0.03)*(1+'1 - I TUOI 6 NUMERI'!$B$14)-1))) | AB35: =MAX(0,AB34-(IF(AA34<=0,0,(36000*(1+'1 - I TUOI 6 NUMERI'!$B$14)^13)/(1-'1 - I TUOI 6 NUMERI'!$B$15*(IF(AA34<=0,0,MEDIAN(0,(AA34-AB34)/AA34,1))))))*(1-(IF(AA34<=0,0,MEDIAN(0,(AA34-AB34)/AA34,1))))) | AC35: =IF(AC34<=0,0,(AC34-(IF(AC34<=0,0,(36000*(1+'1 - I TUOI 6 NUMERI'!$B$14)^13)/(1-'1 - I TUOI 6 NUMERI'!$B$15*(IF(AC34<=0,0,MEDIAN(0,(AC34-AD34)/AC34,1))))))-(IF(AC34<=0,0,'1 - I TUOI 6 NUMERI'!$B$16*AC34)))*(1+((1+0.05)*(1+'1 - I TUOI 6 NUMERI'!$B$14)-1))) | AD35: =MAX(0,AD34-(IF(AC34<=0,0,(36000*(1+'1 - I TUOI 6 NUMERI'!$B$14)^13)/(1-'1 - I TUOI 6 NUMERI'!$B$15*(IF(AC34<=0,0,MEDIAN(0,(AC34-AD34)/AC34,1))))))*(1-(IF(AC34<=0,0,MEDIAN(0,(AC34-AD34)/AC34,1)))))
F36: 14 | G36: =IF(G35<=0,0,(G35-(IF(G35<=0,0,(18000*(1+'1 - I TUOI 6 NUMERI'!$B$14)^14)/(1-'1 - I TUOI 6 NUMERI'!$B$15*(IF(G35<=0,0,MEDIAN(0,(G35-H35)/G35,1))))))-(IF(G35<=0,0,'1 - I TUOI 6 NUMERI'!$B$16*G35)))*(1+((1+0.01)*(1+'1 - I TUOI 6 NUMERI'!$B$14)-1))) | H36: =MAX(0,H35-(IF(G35<=0,0,(18000*(1+'1 - I TUOI 6 NUMERI'!$B$14)^14)/(1-'1 - I TUOI 6 NUMERI'!$B$15*(IF(G35<=0,0,MEDIAN(0,(G35-H35)/G35,1))))))*(1-(IF(G35<=0,0,MEDIAN(0,(G35-H35)/G35,1))))) | I36: =IF(I35<=0,0,(I35-(IF(I35<=0,0,(18000*(1+'1 - I TUOI 6 NUMERI'!$B$14)^14)/(1-'1 - I TUOI 6 NUMERI'!$B$15*(IF(I35<=0,0,MEDIAN(0,(I35-J35)/I35,1))))))-(IF(I35<=0,0,'1 - I TUOI 6 NUMERI'!$B$16*I35)))*(1+((1+0.03)*(1+'1 - I TUOI 6 NUMERI'!$B$14)-1))) | J36: =MAX(0,J35-(IF(I35<=0,0,(18000*(1+'1 - I TUOI 6 NUMERI'!$B$14)^14)/(1-'1 - I TUOI 6 NUMERI'!$B$15*(IF(I35<=0,0,MEDIAN(0,(I35-J35)/I35,1))))))*(1-(IF(I35<=0,0,MEDIAN(0,(I35-J35)/I35,1))))) | K36: =IF(K35<=0,0,(K35-(IF(K35<=0,0,(18000*(1+'1 - I TUOI 6 NUMERI'!$B$14)^14)/(1-'1 - I TUOI 6 NUMERI'!$B$15*(IF(K35<=0,0,MEDIAN(0,(K35-L35)/K35,1))))))-(IF(K35<=0,0,'1 - I TUOI 6 NUMERI'!$B$16*K35)))*(1+((1+0.05)*(1+'1 - I TUOI 6 NUMERI'!$B$14)-1))) | L36: =MAX(0,L35-(IF(K35<=0,0,(18000*(1+'1 - I TUOI 6 NUMERI'!$B$14)^14)/(1-'1 - I TUOI 6 NUMERI'!$B$15*(IF(K35<=0,0,MEDIAN(0,(K35-L35)/K35,1))))))*(1-(IF(K35<=0,0,MEDIAN(0,(K35-L35)/K35,1))))) | M36: =IF(M35<=0,0,(M35-(IF(M35<=0,0,(24000*(1+'1 - I TUOI 6 NUMERI'!$B$14)^14)/(1-'1 - I TUOI 6 NUMERI'!$B$15*(IF(M35<=0,0,MEDIAN(0,(M35-N35)/M35,1))))))-(IF(M35<=0,0,'1 - I TUOI 6 NUMERI'!$B$16*M35)))*(1+((1+0.01)*(1+'1 - I TUOI 6 NUMERI'!$B$14)-1))) | N36: =MAX(0,N35-(IF(M35<=0,0,(24000*(1+'1 - I TUOI 6 NUMERI'!$B$14)^14)/(1-'1 - I TUOI 6 NUMERI'!$B$15*(IF(M35<=0,0,MEDIAN(0,(M35-N35)/M35,1))))))*(1-(IF(M35<=0,0,MEDIAN(0,(M35-N35)/M35,1))))) | O36: =IF(O35<=0,0,(O35-(IF(O35<=0,0,(24000*(1+'1 - I TUOI 6 NUMERI'!$B$14)^14)/(1-'1 - I TUOI 6 NUMERI'!$B$15*(IF(O35<=0,0,MEDIAN(0,(O35-P35)/O35,1))))))-(IF(O35<=0,0,'1 - I TUOI 6 NUMERI'!$B$16*O35)))*(1+((1+0.03)*(1+'1 - I TUOI 6 NUMERI'!$B$14)-1))) | P36: =MAX(0,P35-(IF(O35<=0,0,(24000*(1+'1 - I TUOI 6 NUMERI'!$B$14)^14)/(1-'1 - I TUOI 6 NUMERI'!$B$15*(IF(O35<=0,0,MEDIAN(0,(O35-P35)/O35,1))))))*(1-(IF(O35<=0,0,MEDIAN(0,(O35-P35)/O35,1))))) | Q36: =IF(Q35<=0,0,(Q35-(IF(Q35<=0,0,(24000*(1+'1 - I TUOI 6 NUMERI'!$B$14)^14)/(1-'1 - I TUOI 6 NUMERI'!$B$15*(IF(Q35<=0,0,MEDIAN(0,(Q35-R35)/Q35,1))))))-(IF(Q35<=0,0,'1 - I TUOI 6 NUMERI'!$B$16*Q35)))*(1+((1+0.05)*(1+'1 - I TUOI 6 NUMERI'!$B$14)-1))) | R36: =MAX(0,R35-(IF(Q35<=0,0,(24000*(1+'1 - I TUOI 6 NUMERI'!$B$14)^14)/(1-'1 - I TUOI 6 NUMERI'!$B$15*(IF(Q35<=0,0,MEDIAN(0,(Q35-R35)/Q35,1))))))*(1-(IF(Q35<=0,0,MEDIAN(0,(Q35-R35)/Q35,1))))) | S36: =IF(S35<=0,0,(S35-(IF(S35<=0,0,(30000*(1+'1 - I TUOI 6 NUMERI'!$B$14)^14)/(1-'1 - I TUOI 6 NUMERI'!$B$15*(IF(S35<=0,0,MEDIAN(0,(S35-T35)/S35,1))))))-(IF(S35<=0,0,'1 - I TUOI 6 NUMERI'!$B$16*S35)))*(1+((1+0.01)*(1+'1 - I TUOI 6 NUMERI'!$B$14)-1))) | T36: =MAX(0,T35-(IF(S35<=0,0,(30000*(1+'1 - I TUOI 6 NUMERI'!$B$14)^14)/(1-'1 - I TUOI 6 NUMERI'!$B$15*(IF(S35<=0,0,MEDIAN(0,(S35-T35)/S35,1))))))*(1-(IF(S35<=0,0,MEDIAN(0,(S35-T35)/S35,1))))) | U36: =IF(U35<=0,0,(U35-(IF(U35<=0,0,(30000*(1+'1 - I TUOI 6 NUMERI'!$B$14)^14)/(1-'1 - I TUOI 6 NUMERI'!$B$15*(IF(U35<=0,0,MEDIAN(0,(U35-V35)/U35,1))))))-(IF(U35<=0,0,'1 - I TUOI 6 NUMERI'!$B$16*U35)))*(1+((1+0.03)*(1+'1 - I TUOI 6 NUMERI'!$B$14)-1))) | V36: =MAX(0,V35-(IF(U35<=0,0,(30000*(1+'1 - I TUOI 6 NUMERI'!$B$14)^14)/(1-'1 - I TUOI 6 NUMERI'!$B$15*(IF(U35<=0,0,MEDIAN(0,(U35-V35)/U35,1))))))*(1-(IF(U35<=0,0,MEDIAN(0,(U35-V35)/U35,1))))) | W36: =IF(W35<=0,0,(W35-(IF(W35<=0,0,(30000*(1+'1 - I TUOI 6 NUMERI'!$B$14)^14)/(1-'1 - I TUOI 6 NUMERI'!$B$15*(IF(W35<=0,0,MEDIAN(0,(W35-X35)/W35,1))))))-(IF(W35<=0,0,'1 - I TUOI 6 NUMERI'!$B$16*W35)))*(1+((1+0.05)*(1+'1 - I TUOI 6 NUMERI'!$B$14)-1))) | X36: =MAX(0,X35-(IF(W35<=0,0,(30000*(1+'1 - I TUOI 6 NUMERI'!$B$14)^14)/(1-'1 - I TUOI 6 NUMERI'!$B$15*(IF(W35<=0,0,MEDIAN(0,(W35-X35)/W35,1))))))*(1-(IF(W35<=0,0,MEDIAN(0,(W35-X35)/W35,1))))) | Y36: =IF(Y35<=0,0,(Y35-(IF(Y35<=0,0,(36000*(1+'1 - I TUOI 6 NUMERI'!$B$14)^14)/(1-'1 - I TUOI 6 NUMERI'!$B$15*(IF(Y35<=0,0,MEDIAN(0,(Y35-Z35)/Y35,1))))))-(IF(Y35<=0,0,'1 - I TUOI 6 NUMERI'!$B$16*Y35)))*(1+((1+0.01)*(1+'1 - I TUOI 6 NUMERI'!$B$14)-1))) | Z36: =MAX(0,Z35-(IF(Y35<=0,0,(36000*(1+'1 - I TUOI 6 NUMERI'!$B$14)^14)/(1-'1 - I TUOI 6 NUMERI'!$B$15*(IF(Y35<=0,0,MEDIAN(0,(Y35-Z35)/Y35,1))))))*(1-(IF(Y35<=0,0,MEDIAN(0,(Y35-Z35)/Y35,1))))) | AA36: =IF(AA35<=0,0,(AA35-(IF(AA35<=0,0,(36000*(1+'1 - I TUOI 6 NUMERI'!$B$14)^14)/(1-'1 - I TUOI 6 NUMERI'!$B$15*(IF(AA35<=0,0,MEDIAN(0,(AA35-AB35)/AA35,1))))))-(IF(AA35<=0,0,'1 - I TUOI 6 NUMERI'!$B$16*AA35)))*(1+((1+0.03)*(1+'1 - I TUOI 6 NUMERI'!$B$14)-1))) | AB36: =MAX(0,AB35-(IF(AA35<=0,0,(36000*(1+'1 - I TUOI 6 NUMERI'!$B$14)^14)/(1-'1 - I TUOI 6 NUMERI'!$B$15*(IF(AA35<=0,0,MEDIAN(0,(AA35-AB35)/AA35,1))))))*(1-(IF(AA35<=0,0,MEDIAN(0,(AA35-AB35)/AA35,1))))) | AC36: =IF(AC35<=0,0,(AC35-(IF(AC35<=0,0,(36000*(1+'1 - I TUOI 6 NUMERI'!$B$14)^14)/(1-'1 - I TUOI 6 NUMERI'!$B$15*(IF(AC35<=0,0,MEDIAN(0,(AC35-AD35)/AC35,1))))))-(IF(AC35<=0,0,'1 - I TUOI 6 NUMERI'!$B$16*AC35)))*(1+((1+0.05)*(1+'1 - I TUOI 6 NUMERI'!$B$14)-1))) | AD36: =MAX(0,AD35-(IF(AC35<=0,0,(36000*(1+'1 - I TUOI 6 NUMERI'!$B$14)^14)/(1-'1 - I TUOI 6 NUMERI'!$B$15*(IF(AC35<=0,0,MEDIAN(0,(AC35-AD35)/AC35,1))))))*(1-(IF(AC35<=0,0,MEDIAN(0,(AC35-AD35)/AC35,1)))))
F37: 15 | G37: =IF(G36<=0,0,(G36-(IF(G36<=0,0,(18000*(1+'1 - I TUOI 6 NUMERI'!$B$14)^15)/(1-'1 - I TUOI 6 NUMERI'!$B$15*(IF(G36<=0,0,MEDIAN(0,(G36-H36)/G36,1))))))-(IF(G36<=0,0,'1 - I TUOI 6 NUMERI'!$B$16*G36)))*(1+((1+0.01)*(1+'1 - I TUOI 6 NUMERI'!$B$14)-1))) | H37: =MAX(0,H36-(IF(G36<=0,0,(18000*(1+'1 - I TUOI 6 NUMERI'!$B$14)^15)/(1-'1 - I TUOI 6 NUMERI'!$B$15*(IF(G36<=0,0,MEDIAN(0,(G36-H36)/G36,1))))))*(1-(IF(G36<=0,0,MEDIAN(0,(G36-H36)/G36,1))))) | I37: =IF(I36<=0,0,(I36-(IF(I36<=0,0,(18000*(1+'1 - I TUOI 6 NUMERI'!$B$14)^15)/(1-'1 - I TUOI 6 NUMERI'!$B$15*(IF(I36<=0,0,MEDIAN(0,(I36-J36)/I36,1))))))-(IF(I36<=0,0,'1 - I TUOI 6 NUMERI'!$B$16*I36)))*(1+((1+0.03)*(1+'1 - I TUOI 6 NUMERI'!$B$14)-1))) | J37: =MAX(0,J36-(IF(I36<=0,0,(18000*(1+'1 - I TUOI 6 NUMERI'!$B$14)^15)/(1-'1 - I TUOI 6 NUMERI'!$B$15*(IF(I36<=0,0,MEDIAN(0,(I36-J36)/I36,1))))))*(1-(IF(I36<=0,0,MEDIAN(0,(I36-J36)/I36,1))))) | K37: =IF(K36<=0,0,(K36-(IF(K36<=0,0,(18000*(1+'1 - I TUOI 6 NUMERI'!$B$14)^15)/(1-'1 - I TUOI 6 NUMERI'!$B$15*(IF(K36<=0,0,MEDIAN(0,(K36-L36)/K36,1))))))-(IF(K36<=0,0,'1 - I TUOI 6 NUMERI'!$B$16*K36)))*(1+((1+0.05)*(1+'1 - I TUOI 6 NUMERI'!$B$14)-1))) | L37: =MAX(0,L36-(IF(K36<=0,0,(18000*(1+'1 - I TUOI 6 NUMERI'!$B$14)^15)/(1-'1 - I TUOI 6 NUMERI'!$B$15*(IF(K36<=0,0,MEDIAN(0,(K36-L36)/K36,1))))))*(1-(IF(K36<=0,0,MEDIAN(0,(K36-L36)/K36,1))))) | M37: =IF(M36<=0,0,(M36-(IF(M36<=0,0,(24000*(1+'1 - I TUOI 6 NUMERI'!$B$14)^15)/(1-'1 - I TUOI 6 NUMERI'!$B$15*(IF(M36<=0,0,MEDIAN(0,(M36-N36)/M36,1))))))-(IF(M36<=0,0,'1 - I TUOI 6 NUMERI'!$B$16*M36)))*(1+((1+0.01)*(1+'1 - I TUOI 6 NUMERI'!$B$14)-1))) | N37: =MAX(0,N36-(IF(M36<=0,0,(24000*(1+'1 - I TUOI 6 NUMERI'!$B$14)^15)/(1-'1 - I TUOI 6 NUMERI'!$B$15*(IF(M36<=0,0,MEDIAN(0,(M36-N36)/M36,1))))))*(1-(IF(M36<=0,0,MEDIAN(0,(M36-N36)/M36,1))))) | O37: =IF(O36<=0,0,(O36-(IF(O36<=0,0,(24000*(1+'1 - I TUOI 6 NUMERI'!$B$14)^15)/(1-'1 - I TUOI 6 NUMERI'!$B$15*(IF(O36<=0,0,MEDIAN(0,(O36-P36)/O36,1))))))-(IF(O36<=0,0,'1 - I TUOI 6 NUMERI'!$B$16*O36)))*(1+((1+0.03)*(1+'1 - I TUOI 6 NUMERI'!$B$14)-1))) | P37: =MAX(0,P36-(IF(O36<=0,0,(24000*(1+'1 - I TUOI 6 NUMERI'!$B$14)^15)/(1-'1 - I TUOI 6 NUMERI'!$B$15*(IF(O36<=0,0,MEDIAN(0,(O36-P36)/O36,1))))))*(1-(IF(O36<=0,0,MEDIAN(0,(O36-P36)/O36,1))))) | Q37: =IF(Q36<=0,0,(Q36-(IF(Q36<=0,0,(24000*(1+'1 - I TUOI 6 NUMERI'!$B$14)^15)/(1-'1 - I TUOI 6 NUMERI'!$B$15*(IF(Q36<=0,0,MEDIAN(0,(Q36-R36)/Q36,1))))))-(IF(Q36<=0,0,'1 - I TUOI 6 NUMERI'!$B$16*Q36)))*(1+((1+0.05)*(1+'1 - I TUOI 6 NUMERI'!$B$14)-1))) | R37: =MAX(0,R36-(IF(Q36<=0,0,(24000*(1+'1 - I TUOI 6 NUMERI'!$B$14)^15)/(1-'1 - I TUOI 6 NUMERI'!$B$15*(IF(Q36<=0,0,MEDIAN(0,(Q36-R36)/Q36,1))))))*(1-(IF(Q36<=0,0,MEDIAN(0,(Q36-R36)/Q36,1))))) | S37: =IF(S36<=0,0,(S36-(IF(S36<=0,0,(30000*(1+'1 - I TUOI 6 NUMERI'!$B$14)^15)/(1-'1 - I TUOI 6 NUMERI'!$B$15*(IF(S36<=0,0,MEDIAN(0,(S36-T36)/S36,1))))))-(IF(S36<=0,0,'1 - I TUOI 6 NUMERI'!$B$16*S36)))*(1+((1+0.01)*(1+'1 - I TUOI 6 NUMERI'!$B$14)-1))) | T37: =MAX(0,T36-(IF(S36<=0,0,(30000*(1+'1 - I TUOI 6 NUMERI'!$B$14)^15)/(1-'1 - I TUOI 6 NUMERI'!$B$15*(IF(S36<=0,0,MEDIAN(0,(S36-T36)/S36,1))))))*(1-(IF(S36<=0,0,MEDIAN(0,(S36-T36)/S36,1))))) | U37: =IF(U36<=0,0,(U36-(IF(U36<=0,0,(30000*(1+'1 - I TUOI 6 NUMERI'!$B$14)^15)/(1-'1 - I TUOI 6 NUMERI'!$B$15*(IF(U36<=0,0,MEDIAN(0,(U36-V36)/U36,1))))))-(IF(U36<=0,0,'1 - I TUOI 6 NUMERI'!$B$16*U36)))*(1+((1+0.03)*(1+'1 - I TUOI 6 NUMERI'!$B$14)-1))) | V37: =MAX(0,V36-(IF(U36<=0,0,(30000*(1+'1 - I TUOI 6 NUMERI'!$B$14)^15)/(1-'1 - I TUOI 6 NUMERI'!$B$15*(IF(U36<=0,0,MEDIAN(0,(U36-V36)/U36,1))))))*(1-(IF(U36<=0,0,MEDIAN(0,(U36-V36)/U36,1))))) | W37: =IF(W36<=0,0,(W36-(IF(W36<=0,0,(30000*(1+'1 - I TUOI 6 NUMERI'!$B$14)^15)/(1-'1 - I TUOI 6 NUMERI'!$B$15*(IF(W36<=0,0,MEDIAN(0,(W36-X36)/W36,1))))))-(IF(W36<=0,0,'1 - I TUOI 6 NUMERI'!$B$16*W36)))*(1+((1+0.05)*(1+'1 - I TUOI 6 NUMERI'!$B$14)-1))) | X37: =MAX(0,X36-(IF(W36<=0,0,(30000*(1+'1 - I TUOI 6 NUMERI'!$B$14)^15)/(1-'1 - I TUOI 6 NUMERI'!$B$15*(IF(W36<=0,0,MEDIAN(0,(W36-X36)/W36,1))))))*(1-(IF(W36<=0,0,MEDIAN(0,(W36-X36)/W36,1))))) | Y37: =IF(Y36<=0,0,(Y36-(IF(Y36<=0,0,(36000*(1+'1 - I TUOI 6 NUMERI'!$B$14)^15)/(1-'1 - I TUOI 6 NUMERI'!$B$15*(IF(Y36<=0,0,MEDIAN(0,(Y36-Z36)/Y36,1))))))-(IF(Y36<=0,0,'1 - I TUOI 6 NUMERI'!$B$16*Y36)))*(1+((1+0.01)*(1+'1 - I TUOI 6 NUMERI'!$B$14)-1))) | Z37: =MAX(0,Z36-(IF(Y36<=0,0,(36000*(1+'1 - I TUOI 6 NUMERI'!$B$14)^15)/(1-'1 - I TUOI 6 NUMERI'!$B$15*(IF(Y36<=0,0,MEDIAN(0,(Y36-Z36)/Y36,1))))))*(1-(IF(Y36<=0,0,MEDIAN(0,(Y36-Z36)/Y36,1))))) | AA37: =IF(AA36<=0,0,(AA36-(IF(AA36<=0,0,(36000*(1+'1 - I TUOI 6 NUMERI'!$B$14)^15)/(1-'1 - I TUOI 6 NUMERI'!$B$15*(IF(AA36<=0,0,MEDIAN(0,(AA36-AB36)/AA36,1))))))-(IF(AA36<=0,0,'1 - I TUOI 6 NUMERI'!$B$16*AA36)))*(1+((1+0.03)*(1+'1 - I TUOI 6 NUMERI'!$B$14)-1))) | AB37: =MAX(0,AB36-(IF(AA36<=0,0,(36000*(1+'1 - I TUOI 6 NUMERI'!$B$14)^15)/(1-'1 - I TUOI 6 NUMERI'!$B$15*(IF(AA36<=0,0,MEDIAN(0,(AA36-AB36)/AA36,1))))))*(1-(IF(AA36<=0,0,MEDIAN(0,(AA36-AB36)/AA36,1))))) | AC37: =IF(AC36<=0,0,(AC36-(IF(AC36<=0,0,(36000*(1+'1 - I TUOI 6 NUMERI'!$B$14)^15)/(1-'1 - I TUOI 6 NUMERI'!$B$15*(IF(AC36<=0,0,MEDIAN(0,(AC36-AD36)/AC36,1))))))-(IF(AC36<=0,0,'1 - I TUOI 6 NUMERI'!$B$16*AC36)))*(1+((1+0.05)*(1+'1 - I TUOI 6 NUMERI'!$B$14)-1))) | AD37: =MAX(0,AD36-(IF(AC36<=0,0,(36000*(1+'1 - I TUOI 6 NUMERI'!$B$14)^15)/(1-'1 - I TUOI 6 NUMERI'!$B$15*(IF(AC36<=0,0,MEDIAN(0,(AC36-AD36)/AC36,1))))))*(1-(IF(AC36<=0,0,MEDIAN(0,(AC36-AD36)/AC36,1)))))
F38: 16 | G38: =IF(G37<=0,0,(G37-(IF(G37<=0,0,(18000*(1+'1 - I TUOI 6 NUMERI'!$B$14)^16)/(1-'1 - I TUOI 6 NUMERI'!$B$15*(IF(G37<=0,0,MEDIAN(0,(G37-H37)/G37,1))))))-(IF(G37<=0,0,'1 - I TUOI 6 NUMERI'!$B$16*G37)))*(1+((1+0.01)*(1+'1 - I TUOI 6 NUMERI'!$B$14)-1))) | H38: =MAX(0,H37-(IF(G37<=0,0,(18000*(1+'1 - I TUOI 6 NUMERI'!$B$14)^16)/(1-'1 - I TUOI 6 NUMERI'!$B$15*(IF(G37<=0,0,MEDIAN(0,(G37-H37)/G37,1))))))*(1-(IF(G37<=0,0,MEDIAN(0,(G37-H37)/G37,1))))) | I38: =IF(I37<=0,0,(I37-(IF(I37<=0,0,(18000*(1+'1 - I TUOI 6 NUMERI'!$B$14)^16)/(1-'1 - I TUOI 6 NUMERI'!$B$15*(IF(I37<=0,0,MEDIAN(0,(I37-J37)/I37,1))))))-(IF(I37<=0,0,'1 - I TUOI 6 NUMERI'!$B$16*I37)))*(1+((1+0.03)*(1+'1 - I TUOI 6 NUMERI'!$B$14)-1))) | J38: =MAX(0,J37-(IF(I37<=0,0,(18000*(1+'1 - I TUOI 6 NUMERI'!$B$14)^16)/(1-'1 - I TUOI 6 NUMERI'!$B$15*(IF(I37<=0,0,MEDIAN(0,(I37-J37)/I37,1))))))*(1-(IF(I37<=0,0,MEDIAN(0,(I37-J37)/I37,1))))) | K38: =IF(K37<=0,0,(K37-(IF(K37<=0,0,(18000*(1+'1 - I TUOI 6 NUMERI'!$B$14)^16)/(1-'1 - I TUOI 6 NUMERI'!$B$15*(IF(K37<=0,0,MEDIAN(0,(K37-L37)/K37,1))))))-(IF(K37<=0,0,'1 - I TUOI 6 NUMERI'!$B$16*K37)))*(1+((1+0.05)*(1+'1 - I TUOI 6 NUMERI'!$B$14)-1))) | L38: =MAX(0,L37-(IF(K37<=0,0,(18000*(1+'1 - I TUOI 6 NUMERI'!$B$14)^16)/(1-'1 - I TUOI 6 NUMERI'!$B$15*(IF(K37<=0,0,MEDIAN(0,(K37-L37)/K37,1))))))*(1-(IF(K37<=0,0,MEDIAN(0,(K37-L37)/K37,1))))) | M38: =IF(M37<=0,0,(M37-(IF(M37<=0,0,(24000*(1+'1 - I TUOI 6 NUMERI'!$B$14)^16)/(1-'1 - I TUOI 6 NUMERI'!$B$15*(IF(M37<=0,0,MEDIAN(0,(M37-N37)/M37,1))))))-(IF(M37<=0,0,'1 - I TUOI 6 NUMERI'!$B$16*M37)))*(1+((1+0.01)*(1+'1 - I TUOI 6 NUMERI'!$B$14)-1))) | N38: =MAX(0,N37-(IF(M37<=0,0,(24000*(1+'1 - I TUOI 6 NUMERI'!$B$14)^16)/(1-'1 - I TUOI 6 NUMERI'!$B$15*(IF(M37<=0,0,MEDIAN(0,(M37-N37)/M37,1))))))*(1-(IF(M37<=0,0,MEDIAN(0,(M37-N37)/M37,1))))) | O38: =IF(O37<=0,0,(O37-(IF(O37<=0,0,(24000*(1+'1 - I TUOI 6 NUMERI'!$B$14)^16)/(1-'1 - I TUOI 6 NUMERI'!$B$15*(IF(O37<=0,0,MEDIAN(0,(O37-P37)/O37,1))))))-(IF(O37<=0,0,'1 - I TUOI 6 NUMERI'!$B$16*O37)))*(1+((1+0.03)*(1+'1 - I TUOI 6 NUMERI'!$B$14)-1))) | P38: =MAX(0,P37-(IF(O37<=0,0,(24000*(1+'1 - I TUOI 6 NUMERI'!$B$14)^16)/(1-'1 - I TUOI 6 NUMERI'!$B$15*(IF(O37<=0,0,MEDIAN(0,(O37-P37)/O37,1))))))*(1-(IF(O37<=0,0,MEDIAN(0,(O37-P37)/O37,1))))) | Q38: =IF(Q37<=0,0,(Q37-(IF(Q37<=0,0,(24000*(1+'1 - I TUOI 6 NUMERI'!$B$14)^16)/(1-'1 - I TUOI 6 NUMERI'!$B$15*(IF(Q37<=0,0,MEDIAN(0,(Q37-R37)/Q37,1))))))-(IF(Q37<=0,0,'1 - I TUOI 6 NUMERI'!$B$16*Q37)))*(1+((1+0.05)*(1+'1 - I TUOI 6 NUMERI'!$B$14)-1))) | R38: =MAX(0,R37-(IF(Q37<=0,0,(24000*(1+'1 - I TUOI 6 NUMERI'!$B$14)^16)/(1-'1 - I TUOI 6 NUMERI'!$B$15*(IF(Q37<=0,0,MEDIAN(0,(Q37-R37)/Q37,1))))))*(1-(IF(Q37<=0,0,MEDIAN(0,(Q37-R37)/Q37,1))))) | S38: =IF(S37<=0,0,(S37-(IF(S37<=0,0,(30000*(1+'1 - I TUOI 6 NUMERI'!$B$14)^16)/(1-'1 - I TUOI 6 NUMERI'!$B$15*(IF(S37<=0,0,MEDIAN(0,(S37-T37)/S37,1))))))-(IF(S37<=0,0,'1 - I TUOI 6 NUMERI'!$B$16*S37)))*(1+((1+0.01)*(1+'1 - I TUOI 6 NUMERI'!$B$14)-1))) | T38: =MAX(0,T37-(IF(S37<=0,0,(30000*(1+'1 - I TUOI 6 NUMERI'!$B$14)^16)/(1-'1 - I TUOI 6 NUMERI'!$B$15*(IF(S37<=0,0,MEDIAN(0,(S37-T37)/S37,1))))))*(1-(IF(S37<=0,0,MEDIAN(0,(S37-T37)/S37,1))))) | U38: =IF(U37<=0,0,(U37-(IF(U37<=0,0,(30000*(1+'1 - I TUOI 6 NUMERI'!$B$14)^16)/(1-'1 - I TUOI 6 NUMERI'!$B$15*(IF(U37<=0,0,MEDIAN(0,(U37-V37)/U37,1))))))-(IF(U37<=0,0,'1 - I TUOI 6 NUMERI'!$B$16*U37)))*(1+((1+0.03)*(1+'1 - I TUOI 6 NUMERI'!$B$14)-1))) | V38: =MAX(0,V37-(IF(U37<=0,0,(30000*(1+'1 - I TUOI 6 NUMERI'!$B$14)^16)/(1-'1 - I TUOI 6 NUMERI'!$B$15*(IF(U37<=0,0,MEDIAN(0,(U37-V37)/U37,1))))))*(1-(IF(U37<=0,0,MEDIAN(0,(U37-V37)/U37,1))))) | W38: =IF(W37<=0,0,(W37-(IF(W37<=0,0,(30000*(1+'1 - I TUOI 6 NUMERI'!$B$14)^16)/(1-'1 - I TUOI 6 NUMERI'!$B$15*(IF(W37<=0,0,MEDIAN(0,(W37-X37)/W37,1))))))-(IF(W37<=0,0,'1 - I TUOI 6 NUMERI'!$B$16*W37)))*(1+((1+0.05)*(1+'1 - I TUOI 6 NUMERI'!$B$14)-1))) | X38: =MAX(0,X37-(IF(W37<=0,0,(30000*(1+'1 - I TUOI 6 NUMERI'!$B$14)^16)/(1-'1 - I TUOI 6 NUMERI'!$B$15*(IF(W37<=0,0,MEDIAN(0,(W37-X37)/W37,1))))))*(1-(IF(W37<=0,0,MEDIAN(0,(W37-X37)/W37,1))))) | Y38: =IF(Y37<=0,0,(Y37-(IF(Y37<=0,0,(36000*(1+'1 - I TUOI 6 NUMERI'!$B$14)^16)/(1-'1 - I TUOI 6 NUMERI'!$B$15*(IF(Y37<=0,0,MEDIAN(0,(Y37-Z37)/Y37,1))))))-(IF(Y37<=0,0,'1 - I TUOI 6 NUMERI'!$B$16*Y37)))*(1+((1+0.01)*(1+'1 - I TUOI 6 NUMERI'!$B$14)-1))) | Z38: =MAX(0,Z37-(IF(Y37<=0,0,(36000*(1+'1 - I TUOI 6 NUMERI'!$B$14)^16)/(1-'1 - I TUOI 6 NUMERI'!$B$15*(IF(Y37<=0,0,MEDIAN(0,(Y37-Z37)/Y37,1))))))*(1-(IF(Y37<=0,0,MEDIAN(0,(Y37-Z37)/Y37,1))))) | AA38: =IF(AA37<=0,0,(AA37-(IF(AA37<=0,0,(36000*(1+'1 - I TUOI 6 NUMERI'!$B$14)^16)/(1-'1 - I TUOI 6 NUMERI'!$B$15*(IF(AA37<=0,0,MEDIAN(0,(AA37-AB37)/AA37,1))))))-(IF(AA37<=0,0,'1 - I TUOI 6 NUMERI'!$B$16*AA37)))*(1+((1+0.03)*(1+'1 - I TUOI 6 NUMERI'!$B$14)-1))) | AB38: =MAX(0,AB37-(IF(AA37<=0,0,(36000*(1+'1 - I TUOI 6 NUMERI'!$B$14)^16)/(1-'1 - I TUOI 6 NUMERI'!$B$15*(IF(AA37<=0,0,MEDIAN(0,(AA37-AB37)/AA37,1))))))*(1-(IF(AA37<=0,0,MEDIAN(0,(AA37-AB37)/AA37,1))))) | AC38: =IF(AC37<=0,0,(AC37-(IF(AC37<=0,0,(36000*(1+'1 - I TUOI 6 NUMERI'!$B$14)^16)/(1-'1 - I TUOI 6 NUMERI'!$B$15*(IF(AC37<=0,0,MEDIAN(0,(AC37-AD37)/AC37,1))))))-(IF(AC37<=0,0,'1 - I TUOI 6 NUMERI'!$B$16*AC37)))*(1+((1+0.05)*(1+'1 - I TUOI 6 NUMERI'!$B$14)-1))) | AD38: =MAX(0,AD37-(IF(AC37<=0,0,(36000*(1+'1 - I TUOI 6 NUMERI'!$B$14)^16)/(1-'1 - I TUOI 6 NUMERI'!$B$15*(IF(AC37<=0,0,MEDIAN(0,(AC37-AD37)/AC37,1))))))*(1-(IF(AC37<=0,0,MEDIAN(0,(AC37-AD37)/AC37,1)))))
F39: 17 | G39: =IF(G38<=0,0,(G38-(IF(G38<=0,0,(18000*(1+'1 - I TUOI 6 NUMERI'!$B$14)^17)/(1-'1 - I TUOI 6 NUMERI'!$B$15*(IF(G38<=0,0,MEDIAN(0,(G38-H38)/G38,1))))))-(IF(G38<=0,0,'1 - I TUOI 6 NUMERI'!$B$16*G38)))*(1+((1+0.01)*(1+'1 - I TUOI 6 NUMERI'!$B$14)-1))) | H39: =MAX(0,H38-(IF(G38<=0,0,(18000*(1+'1 - I TUOI 6 NUMERI'!$B$14)^17)/(1-'1 - I TUOI 6 NUMERI'!$B$15*(IF(G38<=0,0,MEDIAN(0,(G38-H38)/G38,1))))))*(1-(IF(G38<=0,0,MEDIAN(0,(G38-H38)/G38,1))))) | I39: =IF(I38<=0,0,(I38-(IF(I38<=0,0,(18000*(1+'1 - I TUOI 6 NUMERI'!$B$14)^17)/(1-'1 - I TUOI 6 NUMERI'!$B$15*(IF(I38<=0,0,MEDIAN(0,(I38-J38)/I38,1))))))-(IF(I38<=0,0,'1 - I TUOI 6 NUMERI'!$B$16*I38)))*(1+((1+0.03)*(1+'1 - I TUOI 6 NUMERI'!$B$14)-1))) | J39: =MAX(0,J38-(IF(I38<=0,0,(18000*(1+'1 - I TUOI 6 NUMERI'!$B$14)^17)/(1-'1 - I TUOI 6 NUMERI'!$B$15*(IF(I38<=0,0,MEDIAN(0,(I38-J38)/I38,1))))))*(1-(IF(I38<=0,0,MEDIAN(0,(I38-J38)/I38,1))))) | K39: =IF(K38<=0,0,(K38-(IF(K38<=0,0,(18000*(1+'1 - I TUOI 6 NUMERI'!$B$14)^17)/(1-'1 - I TUOI 6 NUMERI'!$B$15*(IF(K38<=0,0,MEDIAN(0,(K38-L38)/K38,1))))))-(IF(K38<=0,0,'1 - I TUOI 6 NUMERI'!$B$16*K38)))*(1+((1+0.05)*(1+'1 - I TUOI 6 NUMERI'!$B$14)-1))) | L39: =MAX(0,L38-(IF(K38<=0,0,(18000*(1+'1 - I TUOI 6 NUMERI'!$B$14)^17)/(1-'1 - I TUOI 6 NUMERI'!$B$15*(IF(K38<=0,0,MEDIAN(0,(K38-L38)/K38,1))))))*(1-(IF(K38<=0,0,MEDIAN(0,(K38-L38)/K38,1))))) | M39: =IF(M38<=0,0,(M38-(IF(M38<=0,0,(24000*(1+'1 - I TUOI 6 NUMERI'!$B$14)^17)/(1-'1 - I TUOI 6 NUMERI'!$B$15*(IF(M38<=0,0,MEDIAN(0,(M38-N38)/M38,1))))))-(IF(M38<=0,0,'1 - I TUOI 6 NUMERI'!$B$16*M38)))*(1+((1+0.01)*(1+'1 - I TUOI 6 NUMERI'!$B$14)-1))) | N39: =MAX(0,N38-(IF(M38<=0,0,(24000*(1+'1 - I TUOI 6 NUMERI'!$B$14)^17)/(1-'1 - I TUOI 6 NUMERI'!$B$15*(IF(M38<=0,0,MEDIAN(0,(M38-N38)/M38,1))))))*(1-(IF(M38<=0,0,MEDIAN(0,(M38-N38)/M38,1))))) | O39: =IF(O38<=0,0,(O38-(IF(O38<=0,0,(24000*(1+'1 - I TUOI 6 NUMERI'!$B$14)^17)/(1-'1 - I TUOI 6 NUMERI'!$B$15*(IF(O38<=0,0,MEDIAN(0,(O38-P38)/O38,1))))))-(IF(O38<=0,0,'1 - I TUOI 6 NUMERI'!$B$16*O38)))*(1+((1+0.03)*(1+'1 - I TUOI 6 NUMERI'!$B$14)-1))) | P39: =MAX(0,P38-(IF(O38<=0,0,(24000*(1+'1 - I TUOI 6 NUMERI'!$B$14)^17)/(1-'1 - I TUOI 6 NUMERI'!$B$15*(IF(O38<=0,0,MEDIAN(0,(O38-P38)/O38,1))))))*(1-(IF(O38<=0,0,MEDIAN(0,(O38-P38)/O38,1))))) | Q39: =IF(Q38<=0,0,(Q38-(IF(Q38<=0,0,(24000*(1+'1 - I TUOI 6 NUMERI'!$B$14)^17)/(1-'1 - I TUOI 6 NUMERI'!$B$15*(IF(Q38<=0,0,MEDIAN(0,(Q38-R38)/Q38,1))))))-(IF(Q38<=0,0,'1 - I TUOI 6 NUMERI'!$B$16*Q38)))*(1+((1+0.05)*(1+'1 - I TUOI 6 NUMERI'!$B$14)-1))) | R39: =MAX(0,R38-(IF(Q38<=0,0,(24000*(1+'1 - I TUOI 6 NUMERI'!$B$14)^17)/(1-'1 - I TUOI 6 NUMERI'!$B$15*(IF(Q38<=0,0,MEDIAN(0,(Q38-R38)/Q38,1))))))*(1-(IF(Q38<=0,0,MEDIAN(0,(Q38-R38)/Q38,1))))) | S39: =IF(S38<=0,0,(S38-(IF(S38<=0,0,(30000*(1+'1 - I TUOI 6 NUMERI'!$B$14)^17)/(1-'1 - I TUOI 6 NUMERI'!$B$15*(IF(S38<=0,0,MEDIAN(0,(S38-T38)/S38,1))))))-(IF(S38<=0,0,'1 - I TUOI 6 NUMERI'!$B$16*S38)))*(1+((1+0.01)*(1+'1 - I TUOI 6 NUMERI'!$B$14)-1))) | T39: =MAX(0,T38-(IF(S38<=0,0,(30000*(1+'1 - I TUOI 6 NUMERI'!$B$14)^17)/(1-'1 - I TUOI 6 NUMERI'!$B$15*(IF(S38<=0,0,MEDIAN(0,(S38-T38)/S38,1))))))*(1-(IF(S38<=0,0,MEDIAN(0,(S38-T38)/S38,1))))) | U39: =IF(U38<=0,0,(U38-(IF(U38<=0,0,(30000*(1+'1 - I TUOI 6 NUMERI'!$B$14)^17)/(1-'1 - I TUOI 6 NUMERI'!$B$15*(IF(U38<=0,0,MEDIAN(0,(U38-V38)/U38,1))))))-(IF(U38<=0,0,'1 - I TUOI 6 NUMERI'!$B$16*U38)))*(1+((1+0.03)*(1+'1 - I TUOI 6 NUMERI'!$B$14)-1))) | V39: =MAX(0,V38-(IF(U38<=0,0,(30000*(1+'1 - I TUOI 6 NUMERI'!$B$14)^17)/(1-'1 - I TUOI 6 NUMERI'!$B$15*(IF(U38<=0,0,MEDIAN(0,(U38-V38)/U38,1))))))*(1-(IF(U38<=0,0,MEDIAN(0,(U38-V38)/U38,1))))) | W39: =IF(W38<=0,0,(W38-(IF(W38<=0,0,(30000*(1+'1 - I TUOI 6 NUMERI'!$B$14)^17)/(1-'1 - I TUOI 6 NUMERI'!$B$15*(IF(W38<=0,0,MEDIAN(0,(W38-X38)/W38,1))))))-(IF(W38<=0,0,'1 - I TUOI 6 NUMERI'!$B$16*W38)))*(1+((1+0.05)*(1+'1 - I TUOI 6 NUMERI'!$B$14)-1))) | X39: =MAX(0,X38-(IF(W38<=0,0,(30000*(1+'1 - I TUOI 6 NUMERI'!$B$14)^17)/(1-'1 - I TUOI 6 NUMERI'!$B$15*(IF(W38<=0,0,MEDIAN(0,(W38-X38)/W38,1))))))*(1-(IF(W38<=0,0,MEDIAN(0,(W38-X38)/W38,1))))) | Y39: =IF(Y38<=0,0,(Y38-(IF(Y38<=0,0,(36000*(1+'1 - I TUOI 6 NUMERI'!$B$14)^17)/(1-'1 - I TUOI 6 NUMERI'!$B$15*(IF(Y38<=0,0,MEDIAN(0,(Y38-Z38)/Y38,1))))))-(IF(Y38<=0,0,'1 - I TUOI 6 NUMERI'!$B$16*Y38)))*(1+((1+0.01)*(1+'1 - I TUOI 6 NUMERI'!$B$14)-1))) | Z39: =MAX(0,Z38-(IF(Y38<=0,0,(36000*(1+'1 - I TUOI 6 NUMERI'!$B$14)^17)/(1-'1 - I TUOI 6 NUMERI'!$B$15*(IF(Y38<=0,0,MEDIAN(0,(Y38-Z38)/Y38,1))))))*(1-(IF(Y38<=0,0,MEDIAN(0,(Y38-Z38)/Y38,1))))) | AA39: =IF(AA38<=0,0,(AA38-(IF(AA38<=0,0,(36000*(1+'1 - I TUOI 6 NUMERI'!$B$14)^17)/(1-'1 - I TUOI 6 NUMERI'!$B$15*(IF(AA38<=0,0,MEDIAN(0,(AA38-AB38)/AA38,1))))))-(IF(AA38<=0,0,'1 - I TUOI 6 NUMERI'!$B$16*AA38)))*(1+((1+0.03)*(1+'1 - I TUOI 6 NUMERI'!$B$14)-1))) | AB39: =MAX(0,AB38-(IF(AA38<=0,0,(36000*(1+'1 - I TUOI 6 NUMERI'!$B$14)^17)/(1-'1 - I TUOI 6 NUMERI'!$B$15*(IF(AA38<=0,0,MEDIAN(0,(AA38-AB38)/AA38,1))))))*(1-(IF(AA38<=0,0,MEDIAN(0,(AA38-AB38)/AA38,1))))) | AC39: =IF(AC38<=0,0,(AC38-(IF(AC38<=0,0,(36000*(1+'1 - I TUOI 6 NUMERI'!$B$14)^17)/(1-'1 - I TUOI 6 NUMERI'!$B$15*(IF(AC38<=0,0,MEDIAN(0,(AC38-AD38)/AC38,1))))))-(IF(AC38<=0,0,'1 - I TUOI 6 NUMERI'!$B$16*AC38)))*(1+((1+0.05)*(1+'1 - I TUOI 6 NUMERI'!$B$14)-1))) | AD39: =MAX(0,AD38-(IF(AC38<=0,0,(36000*(1+'1 - I TUOI 6 NUMERI'!$B$14)^17)/(1-'1 - I TUOI 6 NUMERI'!$B$15*(IF(AC38<=0,0,MEDIAN(0,(AC38-AD38)/AC38,1))))))*(1-(IF(AC38<=0,0,MEDIAN(0,(AC38-AD38)/AC38,1)))))
F40: 18 | G40: =IF(G39<=0,0,(G39-(IF(G39<=0,0,(18000*(1+'1 - I TUOI 6 NUMERI'!$B$14)^18)/(1-'1 - I TUOI 6 NUMERI'!$B$15*(IF(G39<=0,0,MEDIAN(0,(G39-H39)/G39,1))))))-(IF(G39<=0,0,'1 - I TUOI 6 NUMERI'!$B$16*G39)))*(1+((1+0.01)*(1+'1 - I TUOI 6 NUMERI'!$B$14)-1))) | H40: =MAX(0,H39-(IF(G39<=0,0,(18000*(1+'1 - I TUOI 6 NUMERI'!$B$14)^18)/(1-'1 - I TUOI 6 NUMERI'!$B$15*(IF(G39<=0,0,MEDIAN(0,(G39-H39)/G39,1))))))*(1-(IF(G39<=0,0,MEDIAN(0,(G39-H39)/G39,1))))) | I40: =IF(I39<=0,0,(I39-(IF(I39<=0,0,(18000*(1+'1 - I TUOI 6 NUMERI'!$B$14)^18)/(1-'1 - I TUOI 6 NUMERI'!$B$15*(IF(I39<=0,0,MEDIAN(0,(I39-J39)/I39,1))))))-(IF(I39<=0,0,'1 - I TUOI 6 NUMERI'!$B$16*I39)))*(1+((1+0.03)*(1+'1 - I TUOI 6 NUMERI'!$B$14)-1))) | J40: =MAX(0,J39-(IF(I39<=0,0,(18000*(1+'1 - I TUOI 6 NUMERI'!$B$14)^18)/(1-'1 - I TUOI 6 NUMERI'!$B$15*(IF(I39<=0,0,MEDIAN(0,(I39-J39)/I39,1))))))*(1-(IF(I39<=0,0,MEDIAN(0,(I39-J39)/I39,1))))) | K40: =IF(K39<=0,0,(K39-(IF(K39<=0,0,(18000*(1+'1 - I TUOI 6 NUMERI'!$B$14)^18)/(1-'1 - I TUOI 6 NUMERI'!$B$15*(IF(K39<=0,0,MEDIAN(0,(K39-L39)/K39,1))))))-(IF(K39<=0,0,'1 - I TUOI 6 NUMERI'!$B$16*K39)))*(1+((1+0.05)*(1+'1 - I TUOI 6 NUMERI'!$B$14)-1))) | L40: =MAX(0,L39-(IF(K39<=0,0,(18000*(1+'1 - I TUOI 6 NUMERI'!$B$14)^18)/(1-'1 - I TUOI 6 NUMERI'!$B$15*(IF(K39<=0,0,MEDIAN(0,(K39-L39)/K39,1))))))*(1-(IF(K39<=0,0,MEDIAN(0,(K39-L39)/K39,1))))) | M40: =IF(M39<=0,0,(M39-(IF(M39<=0,0,(24000*(1+'1 - I TUOI 6 NUMERI'!$B$14)^18)/(1-'1 - I TUOI 6 NUMERI'!$B$15*(IF(M39<=0,0,MEDIAN(0,(M39-N39)/M39,1))))))-(IF(M39<=0,0,'1 - I TUOI 6 NUMERI'!$B$16*M39)))*(1+((1+0.01)*(1+'1 - I TUOI 6 NUMERI'!$B$14)-1))) | N40: =MAX(0,N39-(IF(M39<=0,0,(24000*(1+'1 - I TUOI 6 NUMERI'!$B$14)^18)/(1-'1 - I TUOI 6 NUMERI'!$B$15*(IF(M39<=0,0,MEDIAN(0,(M39-N39)/M39,1))))))*(1-(IF(M39<=0,0,MEDIAN(0,(M39-N39)/M39,1))))) | O40: =IF(O39<=0,0,(O39-(IF(O39<=0,0,(24000*(1+'1 - I TUOI 6 NUMERI'!$B$14)^18)/(1-'1 - I TUOI 6 NUMERI'!$B$15*(IF(O39<=0,0,MEDIAN(0,(O39-P39)/O39,1))))))-(IF(O39<=0,0,'1 - I TUOI 6 NUMERI'!$B$16*O39)))*(1+((1+0.03)*(1+'1 - I TUOI 6 NUMERI'!$B$14)-1))) | P40: =MAX(0,P39-(IF(O39<=0,0,(24000*(1+'1 - I TUOI 6 NUMERI'!$B$14)^18)/(1-'1 - I TUOI 6 NUMERI'!$B$15*(IF(O39<=0,0,MEDIAN(0,(O39-P39)/O39,1))))))*(1-(IF(O39<=0,0,MEDIAN(0,(O39-P39)/O39,1))))) | Q40: =IF(Q39<=0,0,(Q39-(IF(Q39<=0,0,(24000*(1+'1 - I TUOI 6 NUMERI'!$B$14)^18)/(1-'1 - I TUOI 6 NUMERI'!$B$15*(IF(Q39<=0,0,MEDIAN(0,(Q39-R39)/Q39,1))))))-(IF(Q39<=0,0,'1 - I TUOI 6 NUMERI'!$B$16*Q39)))*(1+((1+0.05)*(1+'1 - I TUOI 6 NUMERI'!$B$14)-1))) | R40: =MAX(0,R39-(IF(Q39<=0,0,(24000*(1+'1 - I TUOI 6 NUMERI'!$B$14)^18)/(1-'1 - I TUOI 6 NUMERI'!$B$15*(IF(Q39<=0,0,MEDIAN(0,(Q39-R39)/Q39,1))))))*(1-(IF(Q39<=0,0,MEDIAN(0,(Q39-R39)/Q39,1))))) | S40: =IF(S39<=0,0,(S39-(IF(S39<=0,0,(30000*(1+'1 - I TUOI 6 NUMERI'!$B$14)^18)/(1-'1 - I TUOI 6 NUMERI'!$B$15*(IF(S39<=0,0,MEDIAN(0,(S39-T39)/S39,1))))))-(IF(S39<=0,0,'1 - I TUOI 6 NUMERI'!$B$16*S39)))*(1+((1+0.01)*(1+'1 - I TUOI 6 NUMERI'!$B$14)-1))) | T40: =MAX(0,T39-(IF(S39<=0,0,(30000*(1+'1 - I TUOI 6 NUMERI'!$B$14)^18)/(1-'1 - I TUOI 6 NUMERI'!$B$15*(IF(S39<=0,0,MEDIAN(0,(S39-T39)/S39,1))))))*(1-(IF(S39<=0,0,MEDIAN(0,(S39-T39)/S39,1))))) | U40: =IF(U39<=0,0,(U39-(IF(U39<=0,0,(30000*(1+'1 - I TUOI 6 NUMERI'!$B$14)^18)/(1-'1 - I TUOI 6 NUMERI'!$B$15*(IF(U39<=0,0,MEDIAN(0,(U39-V39)/U39,1))))))-(IF(U39<=0,0,'1 - I TUOI 6 NUMERI'!$B$16*U39)))*(1+((1+0.03)*(1+'1 - I TUOI 6 NUMERI'!$B$14)-1))) | V40: =MAX(0,V39-(IF(U39<=0,0,(30000*(1+'1 - I TUOI 6 NUMERI'!$B$14)^18)/(1-'1 - I TUOI 6 NUMERI'!$B$15*(IF(U39<=0,0,MEDIAN(0,(U39-V39)/U39,1))))))*(1-(IF(U39<=0,0,MEDIAN(0,(U39-V39)/U39,1))))) | W40: =IF(W39<=0,0,(W39-(IF(W39<=0,0,(30000*(1+'1 - I TUOI 6 NUMERI'!$B$14)^18)/(1-'1 - I TUOI 6 NUMERI'!$B$15*(IF(W39<=0,0,MEDIAN(0,(W39-X39)/W39,1))))))-(IF(W39<=0,0,'1 - I TUOI 6 NUMERI'!$B$16*W39)))*(1+((1+0.05)*(1+'1 - I TUOI 6 NUMERI'!$B$14)-1))) | X40: =MAX(0,X39-(IF(W39<=0,0,(30000*(1+'1 - I TUOI 6 NUMERI'!$B$14)^18)/(1-'1 - I TUOI 6 NUMERI'!$B$15*(IF(W39<=0,0,MEDIAN(0,(W39-X39)/W39,1))))))*(1-(IF(W39<=0,0,MEDIAN(0,(W39-X39)/W39,1))))) | Y40: =IF(Y39<=0,0,(Y39-(IF(Y39<=0,0,(36000*(1+'1 - I TUOI 6 NUMERI'!$B$14)^18)/(1-'1 - I TUOI 6 NUMERI'!$B$15*(IF(Y39<=0,0,MEDIAN(0,(Y39-Z39)/Y39,1))))))-(IF(Y39<=0,0,'1 - I TUOI 6 NUMERI'!$B$16*Y39)))*(1+((1+0.01)*(1+'1 - I TUOI 6 NUMERI'!$B$14)-1))) | Z40: =MAX(0,Z39-(IF(Y39<=0,0,(36000*(1+'1 - I TUOI 6 NUMERI'!$B$14)^18)/(1-'1 - I TUOI 6 NUMERI'!$B$15*(IF(Y39<=0,0,MEDIAN(0,(Y39-Z39)/Y39,1))))))*(1-(IF(Y39<=0,0,MEDIAN(0,(Y39-Z39)/Y39,1))))) | AA40: =IF(AA39<=0,0,(AA39-(IF(AA39<=0,0,(36000*(1+'1 - I TUOI 6 NUMERI'!$B$14)^18)/(1-'1 - I TUOI 6 NUMERI'!$B$15*(IF(AA39<=0,0,MEDIAN(0,(AA39-AB39)/AA39,1))))))-(IF(AA39<=0,0,'1 - I TUOI 6 NUMERI'!$B$16*AA39)))*(1+((1+0.03)*(1+'1 - I TUOI 6 NUMERI'!$B$14)-1))) | AB40: =MAX(0,AB39-(IF(AA39<=0,0,(36000*(1+'1 - I TUOI 6 NUMERI'!$B$14)^18)/(1-'1 - I TUOI 6 NUMERI'!$B$15*(IF(AA39<=0,0,MEDIAN(0,(AA39-AB39)/AA39,1))))))*(1-(IF(AA39<=0,0,MEDIAN(0,(AA39-AB39)/AA39,1))))) | AC40: =IF(AC39<=0,0,(AC39-(IF(AC39<=0,0,(36000*(1+'1 - I TUOI 6 NUMERI'!$B$14)^18)/(1-'1 - I TUOI 6 NUMERI'!$B$15*(IF(AC39<=0,0,MEDIAN(0,(AC39-AD39)/AC39,1))))))-(IF(AC39<=0,0,'1 - I TUOI 6 NUMERI'!$B$16*AC39)))*(1+((1+0.05)*(1+'1 - I TUOI 6 NUMERI'!$B$14)-1))) | AD40: =MAX(0,AD39-(IF(AC39<=0,0,(36000*(1+'1 - I TUOI 6 NUMERI'!$B$14)^18)/(1-'1 - I TUOI 6 NUMERI'!$B$15*(IF(AC39<=0,0,MEDIAN(0,(AC39-AD39)/AC39,1))))))*(1-(IF(AC39<=0,0,MEDIAN(0,(AC39-AD39)/AC39,1)))))
F41: 19 | G41: =IF(G40<=0,0,(G40-(IF(G40<=0,0,(18000*(1+'1 - I TUOI 6 NUMERI'!$B$14)^19)/(1-'1 - I TUOI 6 NUMERI'!$B$15*(IF(G40<=0,0,MEDIAN(0,(G40-H40)/G40,1))))))-(IF(G40<=0,0,'1 - I TUOI 6 NUMERI'!$B$16*G40)))*(1+((1+0.01)*(1+'1 - I TUOI 6 NUMERI'!$B$14)-1))) | H41: =MAX(0,H40-(IF(G40<=0,0,(18000*(1+'1 - I TUOI 6 NUMERI'!$B$14)^19)/(1-'1 - I TUOI 6 NUMERI'!$B$15*(IF(G40<=0,0,MEDIAN(0,(G40-H40)/G40,1))))))*(1-(IF(G40<=0,0,MEDIAN(0,(G40-H40)/G40,1))))) | I41: =IF(I40<=0,0,(I40-(IF(I40<=0,0,(18000*(1+'1 - I TUOI 6 NUMERI'!$B$14)^19)/(1-'1 - I TUOI 6 NUMERI'!$B$15*(IF(I40<=0,0,MEDIAN(0,(I40-J40)/I40,1))))))-(IF(I40<=0,0,'1 - I TUOI 6 NUMERI'!$B$16*I40)))*(1+((1+0.03)*(1+'1 - I TUOI 6 NUMERI'!$B$14)-1))) | J41: =MAX(0,J40-(IF(I40<=0,0,(18000*(1+'1 - I TUOI 6 NUMERI'!$B$14)^19)/(1-'1 - I TUOI 6 NUMERI'!$B$15*(IF(I40<=0,0,MEDIAN(0,(I40-J40)/I40,1))))))*(1-(IF(I40<=0,0,MEDIAN(0,(I40-J40)/I40,1))))) | K41: =IF(K40<=0,0,(K40-(IF(K40<=0,0,(18000*(1+'1 - I TUOI 6 NUMERI'!$B$14)^19)/(1-'1 - I TUOI 6 NUMERI'!$B$15*(IF(K40<=0,0,MEDIAN(0,(K40-L40)/K40,1))))))-(IF(K40<=0,0,'1 - I TUOI 6 NUMERI'!$B$16*K40)))*(1+((1+0.05)*(1+'1 - I TUOI 6 NUMERI'!$B$14)-1))) | L41: =MAX(0,L40-(IF(K40<=0,0,(18000*(1+'1 - I TUOI 6 NUMERI'!$B$14)^19)/(1-'1 - I TUOI 6 NUMERI'!$B$15*(IF(K40<=0,0,MEDIAN(0,(K40-L40)/K40,1))))))*(1-(IF(K40<=0,0,MEDIAN(0,(K40-L40)/K40,1))))) | M41: =IF(M40<=0,0,(M40-(IF(M40<=0,0,(24000*(1+'1 - I TUOI 6 NUMERI'!$B$14)^19)/(1-'1 - I TUOI 6 NUMERI'!$B$15*(IF(M40<=0,0,MEDIAN(0,(M40-N40)/M40,1))))))-(IF(M40<=0,0,'1 - I TUOI 6 NUMERI'!$B$16*M40)))*(1+((1+0.01)*(1+'1 - I TUOI 6 NUMERI'!$B$14)-1))) | N41: =MAX(0,N40-(IF(M40<=0,0,(24000*(1+'1 - I TUOI 6 NUMERI'!$B$14)^19)/(1-'1 - I TUOI 6 NUMERI'!$B$15*(IF(M40<=0,0,MEDIAN(0,(M40-N40)/M40,1))))))*(1-(IF(M40<=0,0,MEDIAN(0,(M40-N40)/M40,1))))) | O41: =IF(O40<=0,0,(O40-(IF(O40<=0,0,(24000*(1+'1 - I TUOI 6 NUMERI'!$B$14)^19)/(1-'1 - I TUOI 6 NUMERI'!$B$15*(IF(O40<=0,0,MEDIAN(0,(O40-P40)/O40,1))))))-(IF(O40<=0,0,'1 - I TUOI 6 NUMERI'!$B$16*O40)))*(1+((1+0.03)*(1+'1 - I TUOI 6 NUMERI'!$B$14)-1))) | P41: =MAX(0,P40-(IF(O40<=0,0,(24000*(1+'1 - I TUOI 6 NUMERI'!$B$14)^19)/(1-'1 - I TUOI 6 NUMERI'!$B$15*(IF(O40<=0,0,MEDIAN(0,(O40-P40)/O40,1))))))*(1-(IF(O40<=0,0,MEDIAN(0,(O40-P40)/O40,1))))) | Q41: =IF(Q40<=0,0,(Q40-(IF(Q40<=0,0,(24000*(1+'1 - I TUOI 6 NUMERI'!$B$14)^19)/(1-'1 - I TUOI 6 NUMERI'!$B$15*(IF(Q40<=0,0,MEDIAN(0,(Q40-R40)/Q40,1))))))-(IF(Q40<=0,0,'1 - I TUOI 6 NUMERI'!$B$16*Q40)))*(1+((1+0.05)*(1+'1 - I TUOI 6 NUMERI'!$B$14)-1))) | R41: =MAX(0,R40-(IF(Q40<=0,0,(24000*(1+'1 - I TUOI 6 NUMERI'!$B$14)^19)/(1-'1 - I TUOI 6 NUMERI'!$B$15*(IF(Q40<=0,0,MEDIAN(0,(Q40-R40)/Q40,1))))))*(1-(IF(Q40<=0,0,MEDIAN(0,(Q40-R40)/Q40,1))))) | S41: =IF(S40<=0,0,(S40-(IF(S40<=0,0,(30000*(1+'1 - I TUOI 6 NUMERI'!$B$14)^19)/(1-'1 - I TUOI 6 NUMERI'!$B$15*(IF(S40<=0,0,MEDIAN(0,(S40-T40)/S40,1))))))-(IF(S40<=0,0,'1 - I TUOI 6 NUMERI'!$B$16*S40)))*(1+((1+0.01)*(1+'1 - I TUOI 6 NUMERI'!$B$14)-1))) | T41: =MAX(0,T40-(IF(S40<=0,0,(30000*(1+'1 - I TUOI 6 NUMERI'!$B$14)^19)/(1-'1 - I TUOI 6 NUMERI'!$B$15*(IF(S40<=0,0,MEDIAN(0,(S40-T40)/S40,1))))))*(1-(IF(S40<=0,0,MEDIAN(0,(S40-T40)/S40,1))))) | U41: =IF(U40<=0,0,(U40-(IF(U40<=0,0,(30000*(1+'1 - I TUOI 6 NUMERI'!$B$14)^19)/(1-'1 - I TUOI 6 NUMERI'!$B$15*(IF(U40<=0,0,MEDIAN(0,(U40-V40)/U40,1))))))-(IF(U40<=0,0,'1 - I TUOI 6 NUMERI'!$B$16*U40)))*(1+((1+0.03)*(1+'1 - I TUOI 6 NUMERI'!$B$14)-1))) | V41: =MAX(0,V40-(IF(U40<=0,0,(30000*(1+'1 - I TUOI 6 NUMERI'!$B$14)^19)/(1-'1 - I TUOI 6 NUMERI'!$B$15*(IF(U40<=0,0,MEDIAN(0,(U40-V40)/U40,1))))))*(1-(IF(U40<=0,0,MEDIAN(0,(U40-V40)/U40,1))))) | W41: =IF(W40<=0,0,(W40-(IF(W40<=0,0,(30000*(1+'1 - I TUOI 6 NUMERI'!$B$14)^19)/(1-'1 - I TUOI 6 NUMERI'!$B$15*(IF(W40<=0,0,MEDIAN(0,(W40-X40)/W40,1))))))-(IF(W40<=0,0,'1 - I TUOI 6 NUMERI'!$B$16*W40)))*(1+((1+0.05)*(1+'1 - I TUOI 6 NUMERI'!$B$14)-1))) | X41: =MAX(0,X40-(IF(W40<=0,0,(30000*(1+'1 - I TUOI 6 NUMERI'!$B$14)^19)/(1-'1 - I TUOI 6 NUMERI'!$B$15*(IF(W40<=0,0,MEDIAN(0,(W40-X40)/W40,1))))))*(1-(IF(W40<=0,0,MEDIAN(0,(W40-X40)/W40,1))))) | Y41: =IF(Y40<=0,0,(Y40-(IF(Y40<=0,0,(36000*(1+'1 - I TUOI 6 NUMERI'!$B$14)^19)/(1-'1 - I TUOI 6 NUMERI'!$B$15*(IF(Y40<=0,0,MEDIAN(0,(Y40-Z40)/Y40,1))))))-(IF(Y40<=0,0,'1 - I TUOI 6 NUMERI'!$B$16*Y40)))*(1+((1+0.01)*(1+'1 - I TUOI 6 NUMERI'!$B$14)-1))) | Z41: =MAX(0,Z40-(IF(Y40<=0,0,(36000*(1+'1 - I TUOI 6 NUMERI'!$B$14)^19)/(1-'1 - I TUOI 6 NUMERI'!$B$15*(IF(Y40<=0,0,MEDIAN(0,(Y40-Z40)/Y40,1))))))*(1-(IF(Y40<=0,0,MEDIAN(0,(Y40-Z40)/Y40,1))))) | AA41: =IF(AA40<=0,0,(AA40-(IF(AA40<=0,0,(36000*(1+'1 - I TUOI 6 NUMERI'!$B$14)^19)/(1-'1 - I TUOI 6 NUMERI'!$B$15*(IF(AA40<=0,0,MEDIAN(0,(AA40-AB40)/AA40,1))))))-(IF(AA40<=0,0,'1 - I TUOI 6 NUMERI'!$B$16*AA40)))*(1+((1+0.03)*(1+'1 - I TUOI 6 NUMERI'!$B$14)-1))) | AB41: =MAX(0,AB40-(IF(AA40<=0,0,(36000*(1+'1 - I TUOI 6 NUMERI'!$B$14)^19)/(1-'1 - I TUOI 6 NUMERI'!$B$15*(IF(AA40<=0,0,MEDIAN(0,(AA40-AB40)/AA40,1))))))*(1-(IF(AA40<=0,0,MEDIAN(0,(AA40-AB40)/AA40,1))))) | AC41: =IF(AC40<=0,0,(AC40-(IF(AC40<=0,0,(36000*(1+'1 - I TUOI 6 NUMERI'!$B$14)^19)/(1-'1 - I TUOI 6 NUMERI'!$B$15*(IF(AC40<=0,0,MEDIAN(0,(AC40-AD40)/AC40,1))))))-(IF(AC40<=0,0,'1 - I TUOI 6 NUMERI'!$B$16*AC40)))*(1+((1+0.05)*(1+'1 - I TUOI 6 NUMERI'!$B$14)-1))) | AD41: =MAX(0,AD40-(IF(AC40<=0,0,(36000*(1+'1 - I TUOI 6 NUMERI'!$B$14)^19)/(1-'1 - I TUOI 6 NUMERI'!$B$15*(IF(AC40<=0,0,MEDIAN(0,(AC40-AD40)/AC40,1))))))*(1-(IF(AC40<=0,0,MEDIAN(0,(AC40-AD40)/AC40,1)))))
F42: 20 | G42: =IF(G41<=0,0,(G41-(IF(G41<=0,0,(18000*(1+'1 - I TUOI 6 NUMERI'!$B$14)^20)/(1-'1 - I TUOI 6 NUMERI'!$B$15*(IF(G41<=0,0,MEDIAN(0,(G41-H41)/G41,1))))))-(IF(G41<=0,0,'1 - I TUOI 6 NUMERI'!$B$16*G41)))*(1+((1+0.01)*(1+'1 - I TUOI 6 NUMERI'!$B$14)-1))) | H42: =MAX(0,H41-(IF(G41<=0,0,(18000*(1+'1 - I TUOI 6 NUMERI'!$B$14)^20)/(1-'1 - I TUOI 6 NUMERI'!$B$15*(IF(G41<=0,0,MEDIAN(0,(G41-H41)/G41,1))))))*(1-(IF(G41<=0,0,MEDIAN(0,(G41-H41)/G41,1))))) | I42: =IF(I41<=0,0,(I41-(IF(I41<=0,0,(18000*(1+'1 - I TUOI 6 NUMERI'!$B$14)^20)/(1-'1 - I TUOI 6 NUMERI'!$B$15*(IF(I41<=0,0,MEDIAN(0,(I41-J41)/I41,1))))))-(IF(I41<=0,0,'1 - I TUOI 6 NUMERI'!$B$16*I41)))*(1+((1+0.03)*(1+'1 - I TUOI 6 NUMERI'!$B$14)-1))) | J42: =MAX(0,J41-(IF(I41<=0,0,(18000*(1+'1 - I TUOI 6 NUMERI'!$B$14)^20)/(1-'1 - I TUOI 6 NUMERI'!$B$15*(IF(I41<=0,0,MEDIAN(0,(I41-J41)/I41,1))))))*(1-(IF(I41<=0,0,MEDIAN(0,(I41-J41)/I41,1))))) | K42: =IF(K41<=0,0,(K41-(IF(K41<=0,0,(18000*(1+'1 - I TUOI 6 NUMERI'!$B$14)^20)/(1-'1 - I TUOI 6 NUMERI'!$B$15*(IF(K41<=0,0,MEDIAN(0,(K41-L41)/K41,1))))))-(IF(K41<=0,0,'1 - I TUOI 6 NUMERI'!$B$16*K41)))*(1+((1+0.05)*(1+'1 - I TUOI 6 NUMERI'!$B$14)-1))) | L42: =MAX(0,L41-(IF(K41<=0,0,(18000*(1+'1 - I TUOI 6 NUMERI'!$B$14)^20)/(1-'1 - I TUOI 6 NUMERI'!$B$15*(IF(K41<=0,0,MEDIAN(0,(K41-L41)/K41,1))))))*(1-(IF(K41<=0,0,MEDIAN(0,(K41-L41)/K41,1))))) | M42: =IF(M41<=0,0,(M41-(IF(M41<=0,0,(24000*(1+'1 - I TUOI 6 NUMERI'!$B$14)^20)/(1-'1 - I TUOI 6 NUMERI'!$B$15*(IF(M41<=0,0,MEDIAN(0,(M41-N41)/M41,1))))))-(IF(M41<=0,0,'1 - I TUOI 6 NUMERI'!$B$16*M41)))*(1+((1+0.01)*(1+'1 - I TUOI 6 NUMERI'!$B$14)-1))) | N42: =MAX(0,N41-(IF(M41<=0,0,(24000*(1+'1 - I TUOI 6 NUMERI'!$B$14)^20)/(1-'1 - I TUOI 6 NUMERI'!$B$15*(IF(M41<=0,0,MEDIAN(0,(M41-N41)/M41,1))))))*(1-(IF(M41<=0,0,MEDIAN(0,(M41-N41)/M41,1))))) | O42: =IF(O41<=0,0,(O41-(IF(O41<=0,0,(24000*(1+'1 - I TUOI 6 NUMERI'!$B$14)^20)/(1-'1 - I TUOI 6 NUMERI'!$B$15*(IF(O41<=0,0,MEDIAN(0,(O41-P41)/O41,1))))))-(IF(O41<=0,0,'1 - I TUOI 6 NUMERI'!$B$16*O41)))*(1+((1+0.03)*(1+'1 - I TUOI 6 NUMERI'!$B$14)-1))) | P42: =MAX(0,P41-(IF(O41<=0,0,(24000*(1+'1 - I TUOI 6 NUMERI'!$B$14)^20)/(1-'1 - I TUOI 6 NUMERI'!$B$15*(IF(O41<=0,0,MEDIAN(0,(O41-P41)/O41,1))))))*(1-(IF(O41<=0,0,MEDIAN(0,(O41-P41)/O41,1))))) | Q42: =IF(Q41<=0,0,(Q41-(IF(Q41<=0,0,(24000*(1+'1 - I TUOI 6 NUMERI'!$B$14)^20)/(1-'1 - I TUOI 6 NUMERI'!$B$15*(IF(Q41<=0,0,MEDIAN(0,(Q41-R41)/Q41,1))))))-(IF(Q41<=0,0,'1 - I TUOI 6 NUMERI'!$B$16*Q41)))*(1+((1+0.05)*(1+'1 - I TUOI 6 NUMERI'!$B$14)-1))) | R42: =MAX(0,R41-(IF(Q41<=0,0,(24000*(1+'1 - I TUOI 6 NUMERI'!$B$14)^20)/(1-'1 - I TUOI 6 NUMERI'!$B$15*(IF(Q41<=0,0,MEDIAN(0,(Q41-R41)/Q41,1))))))*(1-(IF(Q41<=0,0,MEDIAN(0,(Q41-R41)/Q41,1))))) | S42: =IF(S41<=0,0,(S41-(IF(S41<=0,0,(30000*(1+'1 - I TUOI 6 NUMERI'!$B$14)^20)/(1-'1 - I TUOI 6 NUMERI'!$B$15*(IF(S41<=0,0,MEDIAN(0,(S41-T41)/S41,1))))))-(IF(S41<=0,0,'1 - I TUOI 6 NUMERI'!$B$16*S41)))*(1+((1+0.01)*(1+'1 - I TUOI 6 NUMERI'!$B$14)-1))) | T42: =MAX(0,T41-(IF(S41<=0,0,(30000*(1+'1 - I TUOI 6 NUMERI'!$B$14)^20)/(1-'1 - I TUOI 6 NUMERI'!$B$15*(IF(S41<=0,0,MEDIAN(0,(S41-T41)/S41,1))))))*(1-(IF(S41<=0,0,MEDIAN(0,(S41-T41)/S41,1))))) | U42: =IF(U41<=0,0,(U41-(IF(U41<=0,0,(30000*(1+'1 - I TUOI 6 NUMERI'!$B$14)^20)/(1-'1 - I TUOI 6 NUMERI'!$B$15*(IF(U41<=0,0,MEDIAN(0,(U41-V41)/U41,1))))))-(IF(U41<=0,0,'1 - I TUOI 6 NUMERI'!$B$16*U41)))*(1+((1+0.03)*(1+'1 - I TUOI 6 NUMERI'!$B$14)-1))) | V42: =MAX(0,V41-(IF(U41<=0,0,(30000*(1+'1 - I TUOI 6 NUMERI'!$B$14)^20)/(1-'1 - I TUOI 6 NUMERI'!$B$15*(IF(U41<=0,0,MEDIAN(0,(U41-V41)/U41,1))))))*(1-(IF(U41<=0,0,MEDIAN(0,(U41-V41)/U41,1))))) | W42: =IF(W41<=0,0,(W41-(IF(W41<=0,0,(30000*(1+'1 - I TUOI 6 NUMERI'!$B$14)^20)/(1-'1 - I TUOI 6 NUMERI'!$B$15*(IF(W41<=0,0,MEDIAN(0,(W41-X41)/W41,1))))))-(IF(W41<=0,0,'1 - I TUOI 6 NUMERI'!$B$16*W41)))*(1+((1+0.05)*(1+'1 - I TUOI 6 NUMERI'!$B$14)-1))) | X42: =MAX(0,X41-(IF(W41<=0,0,(30000*(1+'1 - I TUOI 6 NUMERI'!$B$14)^20)/(1-'1 - I TUOI 6 NUMERI'!$B$15*(IF(W41<=0,0,MEDIAN(0,(W41-X41)/W41,1))))))*(1-(IF(W41<=0,0,MEDIAN(0,(W41-X41)/W41,1))))) | Y42: =IF(Y41<=0,0,(Y41-(IF(Y41<=0,0,(36000*(1+'1 - I TUOI 6 NUMERI'!$B$14)^20)/(1-'1 - I TUOI 6 NUMERI'!$B$15*(IF(Y41<=0,0,MEDIAN(0,(Y41-Z41)/Y41,1))))))-(IF(Y41<=0,0,'1 - I TUOI 6 NUMERI'!$B$16*Y41)))*(1+((1+0.01)*(1+'1 - I TUOI 6 NUMERI'!$B$14)-1))) | Z42: =MAX(0,Z41-(IF(Y41<=0,0,(36000*(1+'1 - I TUOI 6 NUMERI'!$B$14)^20)/(1-'1 - I TUOI 6 NUMERI'!$B$15*(IF(Y41<=0,0,MEDIAN(0,(Y41-Z41)/Y41,1))))))*(1-(IF(Y41<=0,0,MEDIAN(0,(Y41-Z41)/Y41,1))))) | AA42: =IF(AA41<=0,0,(AA41-(IF(AA41<=0,0,(36000*(1+'1 - I TUOI 6 NUMERI'!$B$14)^20)/(1-'1 - I TUOI 6 NUMERI'!$B$15*(IF(AA41<=0,0,MEDIAN(0,(AA41-AB41)/AA41,1))))))-(IF(AA41<=0,0,'1 - I TUOI 6 NUMERI'!$B$16*AA41)))*(1+((1+0.03)*(1+'1 - I TUOI 6 NUMERI'!$B$14)-1))) | AB42: =MAX(0,AB41-(IF(AA41<=0,0,(36000*(1+'1 - I TUOI 6 NUMERI'!$B$14)^20)/(1-'1 - I TUOI 6 NUMERI'!$B$15*(IF(AA41<=0,0,MEDIAN(0,(AA41-AB41)/AA41,1))))))*(1-(IF(AA41<=0,0,MEDIAN(0,(AA41-AB41)/AA41,1))))) | AC42: =IF(AC41<=0,0,(AC41-(IF(AC41<=0,0,(36000*(1+'1 - I TUOI 6 NUMERI'!$B$14)^20)/(1-'1 - I TUOI 6 NUMERI'!$B$15*(IF(AC41<=0,0,MEDIAN(0,(AC41-AD41)/AC41,1))))))-(IF(AC41<=0,0,'1 - I TUOI 6 NUMERI'!$B$16*AC41)))*(1+((1+0.05)*(1+'1 - I TUOI 6 NUMERI'!$B$14)-1))) | AD42: =MAX(0,AD41-(IF(AC41<=0,0,(36000*(1+'1 - I TUOI 6 NUMERI'!$B$14)^20)/(1-'1 - I TUOI 6 NUMERI'!$B$15*(IF(AC41<=0,0,MEDIAN(0,(AC41-AD41)/AC41,1))))))*(1-(IF(AC41<=0,0,MEDIAN(0,(AC41-AD41)/AC41,1)))))
F43: 21 | G43: =IF(G42<=0,0,(G42-(IF(G42<=0,0,(18000*(1+'1 - I TUOI 6 NUMERI'!$B$14)^21)/(1-'1 - I TUOI 6 NUMERI'!$B$15*(IF(G42<=0,0,MEDIAN(0,(G42-H42)/G42,1))))))-(IF(G42<=0,0,'1 - I TUOI 6 NUMERI'!$B$16*G42)))*(1+((1+0.01)*(1+'1 - I TUOI 6 NUMERI'!$B$14)-1))) | H43: =MAX(0,H42-(IF(G42<=0,0,(18000*(1+'1 - I TUOI 6 NUMERI'!$B$14)^21)/(1-'1 - I TUOI 6 NUMERI'!$B$15*(IF(G42<=0,0,MEDIAN(0,(G42-H42)/G42,1))))))*(1-(IF(G42<=0,0,MEDIAN(0,(G42-H42)/G42,1))))) | I43: =IF(I42<=0,0,(I42-(IF(I42<=0,0,(18000*(1+'1 - I TUOI 6 NUMERI'!$B$14)^21)/(1-'1 - I TUOI 6 NUMERI'!$B$15*(IF(I42<=0,0,MEDIAN(0,(I42-J42)/I42,1))))))-(IF(I42<=0,0,'1 - I TUOI 6 NUMERI'!$B$16*I42)))*(1+((1+0.03)*(1+'1 - I TUOI 6 NUMERI'!$B$14)-1))) | J43: =MAX(0,J42-(IF(I42<=0,0,(18000*(1+'1 - I TUOI 6 NUMERI'!$B$14)^21)/(1-'1 - I TUOI 6 NUMERI'!$B$15*(IF(I42<=0,0,MEDIAN(0,(I42-J42)/I42,1))))))*(1-(IF(I42<=0,0,MEDIAN(0,(I42-J42)/I42,1))))) | K43: =IF(K42<=0,0,(K42-(IF(K42<=0,0,(18000*(1+'1 - I TUOI 6 NUMERI'!$B$14)^21)/(1-'1 - I TUOI 6 NUMERI'!$B$15*(IF(K42<=0,0,MEDIAN(0,(K42-L42)/K42,1))))))-(IF(K42<=0,0,'1 - I TUOI 6 NUMERI'!$B$16*K42)))*(1+((1+0.05)*(1+'1 - I TUOI 6 NUMERI'!$B$14)-1))) | L43: =MAX(0,L42-(IF(K42<=0,0,(18000*(1+'1 - I TUOI 6 NUMERI'!$B$14)^21)/(1-'1 - I TUOI 6 NUMERI'!$B$15*(IF(K42<=0,0,MEDIAN(0,(K42-L42)/K42,1))))))*(1-(IF(K42<=0,0,MEDIAN(0,(K42-L42)/K42,1))))) | M43: =IF(M42<=0,0,(M42-(IF(M42<=0,0,(24000*(1+'1 - I TUOI 6 NUMERI'!$B$14)^21)/(1-'1 - I TUOI 6 NUMERI'!$B$15*(IF(M42<=0,0,MEDIAN(0,(M42-N42)/M42,1))))))-(IF(M42<=0,0,'1 - I TUOI 6 NUMERI'!$B$16*M42)))*(1+((1+0.01)*(1+'1 - I TUOI 6 NUMERI'!$B$14)-1))) | N43: =MAX(0,N42-(IF(M42<=0,0,(24000*(1+'1 - I TUOI 6 NUMERI'!$B$14)^21)/(1-'1 - I TUOI 6 NUMERI'!$B$15*(IF(M42<=0,0,MEDIAN(0,(M42-N42)/M42,1))))))*(1-(IF(M42<=0,0,MEDIAN(0,(M42-N42)/M42,1))))) | O43: =IF(O42<=0,0,(O42-(IF(O42<=0,0,(24000*(1+'1 - I TUOI 6 NUMERI'!$B$14)^21)/(1-'1 - I TUOI 6 NUMERI'!$B$15*(IF(O42<=0,0,MEDIAN(0,(O42-P42)/O42,1))))))-(IF(O42<=0,0,'1 - I TUOI 6 NUMERI'!$B$16*O42)))*(1+((1+0.03)*(1+'1 - I TUOI 6 NUMERI'!$B$14)-1))) | P43: =MAX(0,P42-(IF(O42<=0,0,(24000*(1+'1 - I TUOI 6 NUMERI'!$B$14)^21)/(1-'1 - I TUOI 6 NUMERI'!$B$15*(IF(O42<=0,0,MEDIAN(0,(O42-P42)/O42,1))))))*(1-(IF(O42<=0,0,MEDIAN(0,(O42-P42)/O42,1))))) | Q43: =IF(Q42<=0,0,(Q42-(IF(Q42<=0,0,(24000*(1+'1 - I TUOI 6 NUMERI'!$B$14)^21)/(1-'1 - I TUOI 6 NUMERI'!$B$15*(IF(Q42<=0,0,MEDIAN(0,(Q42-R42)/Q42,1))))))-(IF(Q42<=0,0,'1 - I TUOI 6 NUMERI'!$B$16*Q42)))*(1+((1+0.05)*(1+'1 - I TUOI 6 NUMERI'!$B$14)-1))) | R43: =MAX(0,R42-(IF(Q42<=0,0,(24000*(1+'1 - I TUOI 6 NUMERI'!$B$14)^21)/(1-'1 - I TUOI 6 NUMERI'!$B$15*(IF(Q42<=0,0,MEDIAN(0,(Q42-R42)/Q42,1))))))*(1-(IF(Q42<=0,0,MEDIAN(0,(Q42-R42)/Q42,1))))) | S43: =IF(S42<=0,0,(S42-(IF(S42<=0,0,(30000*(1+'1 - I TUOI 6 NUMERI'!$B$14)^21)/(1-'1 - I TUOI 6 NUMERI'!$B$15*(IF(S42<=0,0,MEDIAN(0,(S42-T42)/S42,1))))))-(IF(S42<=0,0,'1 - I TUOI 6 NUMERI'!$B$16*S42)))*(1+((1+0.01)*(1+'1 - I TUOI 6 NUMERI'!$B$14)-1))) | T43: =MAX(0,T42-(IF(S42<=0,0,(30000*(1+'1 - I TUOI 6 NUMERI'!$B$14)^21)/(1-'1 - I TUOI 6 NUMERI'!$B$15*(IF(S42<=0,0,MEDIAN(0,(S42-T42)/S42,1))))))*(1-(IF(S42<=0,0,MEDIAN(0,(S42-T42)/S42,1))))) | U43: =IF(U42<=0,0,(U42-(IF(U42<=0,0,(30000*(1+'1 - I TUOI 6 NUMERI'!$B$14)^21)/(1-'1 - I TUOI 6 NUMERI'!$B$15*(IF(U42<=0,0,MEDIAN(0,(U42-V42)/U42,1))))))-(IF(U42<=0,0,'1 - I TUOI 6 NUMERI'!$B$16*U42)))*(1+((1+0.03)*(1+'1 - I TUOI 6 NUMERI'!$B$14)-1))) | V43: =MAX(0,V42-(IF(U42<=0,0,(30000*(1+'1 - I TUOI 6 NUMERI'!$B$14)^21)/(1-'1 - I TUOI 6 NUMERI'!$B$15*(IF(U42<=0,0,MEDIAN(0,(U42-V42)/U42,1))))))*(1-(IF(U42<=0,0,MEDIAN(0,(U42-V42)/U42,1))))) | W43: =IF(W42<=0,0,(W42-(IF(W42<=0,0,(30000*(1+'1 - I TUOI 6 NUMERI'!$B$14)^21)/(1-'1 - I TUOI 6 NUMERI'!$B$15*(IF(W42<=0,0,MEDIAN(0,(W42-X42)/W42,1))))))-(IF(W42<=0,0,'1 - I TUOI 6 NUMERI'!$B$16*W42)))*(1+((1+0.05)*(1+'1 - I TUOI 6 NUMERI'!$B$14)-1))) | X43: =MAX(0,X42-(IF(W42<=0,0,(30000*(1+'1 - I TUOI 6 NUMERI'!$B$14)^21)/(1-'1 - I TUOI 6 NUMERI'!$B$15*(IF(W42<=0,0,MEDIAN(0,(W42-X42)/W42,1))))))*(1-(IF(W42<=0,0,MEDIAN(0,(W42-X42)/W42,1))))) | Y43: =IF(Y42<=0,0,(Y42-(IF(Y42<=0,0,(36000*(1+'1 - I TUOI 6 NUMERI'!$B$14)^21)/(1-'1 - I TUOI 6 NUMERI'!$B$15*(IF(Y42<=0,0,MEDIAN(0,(Y42-Z42)/Y42,1))))))-(IF(Y42<=0,0,'1 - I TUOI 6 NUMERI'!$B$16*Y42)))*(1+((1+0.01)*(1+'1 - I TUOI 6 NUMERI'!$B$14)-1))) | Z43: =MAX(0,Z42-(IF(Y42<=0,0,(36000*(1+'1 - I TUOI 6 NUMERI'!$B$14)^21)/(1-'1 - I TUOI 6 NUMERI'!$B$15*(IF(Y42<=0,0,MEDIAN(0,(Y42-Z42)/Y42,1))))))*(1-(IF(Y42<=0,0,MEDIAN(0,(Y42-Z42)/Y42,1))))) | AA43: =IF(AA42<=0,0,(AA42-(IF(AA42<=0,0,(36000*(1+'1 - I TUOI 6 NUMERI'!$B$14)^21)/(1-'1 - I TUOI 6 NUMERI'!$B$15*(IF(AA42<=0,0,MEDIAN(0,(AA42-AB42)/AA42,1))))))-(IF(AA42<=0,0,'1 - I TUOI 6 NUMERI'!$B$16*AA42)))*(1+((1+0.03)*(1+'1 - I TUOI 6 NUMERI'!$B$14)-1))) | AB43: =MAX(0,AB42-(IF(AA42<=0,0,(36000*(1+'1 - I TUOI 6 NUMERI'!$B$14)^21)/(1-'1 - I TUOI 6 NUMERI'!$B$15*(IF(AA42<=0,0,MEDIAN(0,(AA42-AB42)/AA42,1))))))*(1-(IF(AA42<=0,0,MEDIAN(0,(AA42-AB42)/AA42,1))))) | AC43: =IF(AC42<=0,0,(AC42-(IF(AC42<=0,0,(36000*(1+'1 - I TUOI 6 NUMERI'!$B$14)^21)/(1-'1 - I TUOI 6 NUMERI'!$B$15*(IF(AC42<=0,0,MEDIAN(0,(AC42-AD42)/AC42,1))))))-(IF(AC42<=0,0,'1 - I TUOI 6 NUMERI'!$B$16*AC42)))*(1+((1+0.05)*(1+'1 - I TUOI 6 NUMERI'!$B$14)-1))) | AD43: =MAX(0,AD42-(IF(AC42<=0,0,(36000*(1+'1 - I TUOI 6 NUMERI'!$B$14)^21)/(1-'1 - I TUOI 6 NUMERI'!$B$15*(IF(AC42<=0,0,MEDIAN(0,(AC42-AD42)/AC42,1))))))*(1-(IF(AC42<=0,0,MEDIAN(0,(AC42-AD42)/AC42,1)))))
F44: 22 | G44: =IF(G43<=0,0,(G43-(IF(G43<=0,0,(18000*(1+'1 - I TUOI 6 NUMERI'!$B$14)^22)/(1-'1 - I TUOI 6 NUMERI'!$B$15*(IF(G43<=0,0,MEDIAN(0,(G43-H43)/G43,1))))))-(IF(G43<=0,0,'1 - I TUOI 6 NUMERI'!$B$16*G43)))*(1+((1+0.01)*(1+'1 - I TUOI 6 NUMERI'!$B$14)-1))) | H44: =MAX(0,H43-(IF(G43<=0,0,(18000*(1+'1 - I TUOI 6 NUMERI'!$B$14)^22)/(1-'1 - I TUOI 6 NUMERI'!$B$15*(IF(G43<=0,0,MEDIAN(0,(G43-H43)/G43,1))))))*(1-(IF(G43<=0,0,MEDIAN(0,(G43-H43)/G43,1))))) | I44: =IF(I43<=0,0,(I43-(IF(I43<=0,0,(18000*(1+'1 - I TUOI 6 NUMERI'!$B$14)^22)/(1-'1 - I TUOI 6 NUMERI'!$B$15*(IF(I43<=0,0,MEDIAN(0,(I43-J43)/I43,1))))))-(IF(I43<=0,0,'1 - I TUOI 6 NUMERI'!$B$16*I43)))*(1+((1+0.03)*(1+'1 - I TUOI 6 NUMERI'!$B$14)-1))) | J44: =MAX(0,J43-(IF(I43<=0,0,(18000*(1+'1 - I TUOI 6 NUMERI'!$B$14)^22)/(1-'1 - I TUOI 6 NUMERI'!$B$15*(IF(I43<=0,0,MEDIAN(0,(I43-J43)/I43,1))))))*(1-(IF(I43<=0,0,MEDIAN(0,(I43-J43)/I43,1))))) | K44: =IF(K43<=0,0,(K43-(IF(K43<=0,0,(18000*(1+'1 - I TUOI 6 NUMERI'!$B$14)^22)/(1-'1 - I TUOI 6 NUMERI'!$B$15*(IF(K43<=0,0,MEDIAN(0,(K43-L43)/K43,1))))))-(IF(K43<=0,0,'1 - I TUOI 6 NUMERI'!$B$16*K43)))*(1+((1+0.05)*(1+'1 - I TUOI 6 NUMERI'!$B$14)-1))) | L44: =MAX(0,L43-(IF(K43<=0,0,(18000*(1+'1 - I TUOI 6 NUMERI'!$B$14)^22)/(1-'1 - I TUOI 6 NUMERI'!$B$15*(IF(K43<=0,0,MEDIAN(0,(K43-L43)/K43,1))))))*(1-(IF(K43<=0,0,MEDIAN(0,(K43-L43)/K43,1))))) | M44: =IF(M43<=0,0,(M43-(IF(M43<=0,0,(24000*(1+'1 - I TUOI 6 NUMERI'!$B$14)^22)/(1-'1 - I TUOI 6 NUMERI'!$B$15*(IF(M43<=0,0,MEDIAN(0,(M43-N43)/M43,1))))))-(IF(M43<=0,0,'1 - I TUOI 6 NUMERI'!$B$16*M43)))*(1+((1+0.01)*(1+'1 - I TUOI 6 NUMERI'!$B$14)-1))) | N44: =MAX(0,N43-(IF(M43<=0,0,(24000*(1+'1 - I TUOI 6 NUMERI'!$B$14)^22)/(1-'1 - I TUOI 6 NUMERI'!$B$15*(IF(M43<=0,0,MEDIAN(0,(M43-N43)/M43,1))))))*(1-(IF(M43<=0,0,MEDIAN(0,(M43-N43)/M43,1))))) | O44: =IF(O43<=0,0,(O43-(IF(O43<=0,0,(24000*(1+'1 - I TUOI 6 NUMERI'!$B$14)^22)/(1-'1 - I TUOI 6 NUMERI'!$B$15*(IF(O43<=0,0,MEDIAN(0,(O43-P43)/O43,1))))))-(IF(O43<=0,0,'1 - I TUOI 6 NUMERI'!$B$16*O43)))*(1+((1+0.03)*(1+'1 - I TUOI 6 NUMERI'!$B$14)-1))) | P44: =MAX(0,P43-(IF(O43<=0,0,(24000*(1+'1 - I TUOI 6 NUMERI'!$B$14)^22)/(1-'1 - I TUOI 6 NUMERI'!$B$15*(IF(O43<=0,0,MEDIAN(0,(O43-P43)/O43,1))))))*(1-(IF(O43<=0,0,MEDIAN(0,(O43-P43)/O43,1))))) | Q44: =IF(Q43<=0,0,(Q43-(IF(Q43<=0,0,(24000*(1+'1 - I TUOI 6 NUMERI'!$B$14)^22)/(1-'1 - I TUOI 6 NUMERI'!$B$15*(IF(Q43<=0,0,MEDIAN(0,(Q43-R43)/Q43,1))))))-(IF(Q43<=0,0,'1 - I TUOI 6 NUMERI'!$B$16*Q43)))*(1+((1+0.05)*(1+'1 - I TUOI 6 NUMERI'!$B$14)-1))) | R44: =MAX(0,R43-(IF(Q43<=0,0,(24000*(1+'1 - I TUOI 6 NUMERI'!$B$14)^22)/(1-'1 - I TUOI 6 NUMERI'!$B$15*(IF(Q43<=0,0,MEDIAN(0,(Q43-R43)/Q43,1))))))*(1-(IF(Q43<=0,0,MEDIAN(0,(Q43-R43)/Q43,1))))) | S44: =IF(S43<=0,0,(S43-(IF(S43<=0,0,(30000*(1+'1 - I TUOI 6 NUMERI'!$B$14)^22)/(1-'1 - I TUOI 6 NUMERI'!$B$15*(IF(S43<=0,0,MEDIAN(0,(S43-T43)/S43,1))))))-(IF(S43<=0,0,'1 - I TUOI 6 NUMERI'!$B$16*S43)))*(1+((1+0.01)*(1+'1 - I TUOI 6 NUMERI'!$B$14)-1))) | T44: =MAX(0,T43-(IF(S43<=0,0,(30000*(1+'1 - I TUOI 6 NUMERI'!$B$14)^22)/(1-'1 - I TUOI 6 NUMERI'!$B$15*(IF(S43<=0,0,MEDIAN(0,(S43-T43)/S43,1))))))*(1-(IF(S43<=0,0,MEDIAN(0,(S43-T43)/S43,1))))) | U44: =IF(U43<=0,0,(U43-(IF(U43<=0,0,(30000*(1+'1 - I TUOI 6 NUMERI'!$B$14)^22)/(1-'1 - I TUOI 6 NUMERI'!$B$15*(IF(U43<=0,0,MEDIAN(0,(U43-V43)/U43,1))))))-(IF(U43<=0,0,'1 - I TUOI 6 NUMERI'!$B$16*U43)))*(1+((1+0.03)*(1+'1 - I TUOI 6 NUMERI'!$B$14)-1))) | V44: =MAX(0,V43-(IF(U43<=0,0,(30000*(1+'1 - I TUOI 6 NUMERI'!$B$14)^22)/(1-'1 - I TUOI 6 NUMERI'!$B$15*(IF(U43<=0,0,MEDIAN(0,(U43-V43)/U43,1))))))*(1-(IF(U43<=0,0,MEDIAN(0,(U43-V43)/U43,1))))) | W44: =IF(W43<=0,0,(W43-(IF(W43<=0,0,(30000*(1+'1 - I TUOI 6 NUMERI'!$B$14)^22)/(1-'1 - I TUOI 6 NUMERI'!$B$15*(IF(W43<=0,0,MEDIAN(0,(W43-X43)/W43,1))))))-(IF(W43<=0,0,'1 - I TUOI 6 NUMERI'!$B$16*W43)))*(1+((1+0.05)*(1+'1 - I TUOI 6 NUMERI'!$B$14)-1))) | X44: =MAX(0,X43-(IF(W43<=0,0,(30000*(1+'1 - I TUOI 6 NUMERI'!$B$14)^22)/(1-'1 - I TUOI 6 NUMERI'!$B$15*(IF(W43<=0,0,MEDIAN(0,(W43-X43)/W43,1))))))*(1-(IF(W43<=0,0,MEDIAN(0,(W43-X43)/W43,1))))) | Y44: =IF(Y43<=0,0,(Y43-(IF(Y43<=0,0,(36000*(1+'1 - I TUOI 6 NUMERI'!$B$14)^22)/(1-'1 - I TUOI 6 NUMERI'!$B$15*(IF(Y43<=0,0,MEDIAN(0,(Y43-Z43)/Y43,1))))))-(IF(Y43<=0,0,'1 - I TUOI 6 NUMERI'!$B$16*Y43)))*(1+((1+0.01)*(1+'1 - I TUOI 6 NUMERI'!$B$14)-1))) | Z44: =MAX(0,Z43-(IF(Y43<=0,0,(36000*(1+'1 - I TUOI 6 NUMERI'!$B$14)^22)/(1-'1 - I TUOI 6 NUMERI'!$B$15*(IF(Y43<=0,0,MEDIAN(0,(Y43-Z43)/Y43,1))))))*(1-(IF(Y43<=0,0,MEDIAN(0,(Y43-Z43)/Y43,1))))) | AA44: =IF(AA43<=0,0,(AA43-(IF(AA43<=0,0,(36000*(1+'1 - I TUOI 6 NUMERI'!$B$14)^22)/(1-'1 - I TUOI 6 NUMERI'!$B$15*(IF(AA43<=0,0,MEDIAN(0,(AA43-AB43)/AA43,1))))))-(IF(AA43<=0,0,'1 - I TUOI 6 NUMERI'!$B$16*AA43)))*(1+((1+0.03)*(1+'1 - I TUOI 6 NUMERI'!$B$14)-1))) | AB44: =MAX(0,AB43-(IF(AA43<=0,0,(36000*(1+'1 - I TUOI 6 NUMERI'!$B$14)^22)/(1-'1 - I TUOI 6 NUMERI'!$B$15*(IF(AA43<=0,0,MEDIAN(0,(AA43-AB43)/AA43,1))))))*(1-(IF(AA43<=0,0,MEDIAN(0,(AA43-AB43)/AA43,1))))) | AC44: =IF(AC43<=0,0,(AC43-(IF(AC43<=0,0,(36000*(1+'1 - I TUOI 6 NUMERI'!$B$14)^22)/(1-'1 - I TUOI 6 NUMERI'!$B$15*(IF(AC43<=0,0,MEDIAN(0,(AC43-AD43)/AC43,1))))))-(IF(AC43<=0,0,'1 - I TUOI 6 NUMERI'!$B$16*AC43)))*(1+((1+0.05)*(1+'1 - I TUOI 6 NUMERI'!$B$14)-1))) | AD44: =MAX(0,AD43-(IF(AC43<=0,0,(36000*(1+'1 - I TUOI 6 NUMERI'!$B$14)^22)/(1-'1 - I TUOI 6 NUMERI'!$B$15*(IF(AC43<=0,0,MEDIAN(0,(AC43-AD43)/AC43,1))))))*(1-(IF(AC43<=0,0,MEDIAN(0,(AC43-AD43)/AC43,1)))))
F45: 23 | G45: =IF(G44<=0,0,(G44-(IF(G44<=0,0,(18000*(1+'1 - I TUOI 6 NUMERI'!$B$14)^23)/(1-'1 - I TUOI 6 NUMERI'!$B$15*(IF(G44<=0,0,MEDIAN(0,(G44-H44)/G44,1))))))-(IF(G44<=0,0,'1 - I TUOI 6 NUMERI'!$B$16*G44)))*(1+((1+0.01)*(1+'1 - I TUOI 6 NUMERI'!$B$14)-1))) | H45: =MAX(0,H44-(IF(G44<=0,0,(18000*(1+'1 - I TUOI 6 NUMERI'!$B$14)^23)/(1-'1 - I TUOI 6 NUMERI'!$B$15*(IF(G44<=0,0,MEDIAN(0,(G44-H44)/G44,1))))))*(1-(IF(G44<=0,0,MEDIAN(0,(G44-H44)/G44,1))))) | I45: =IF(I44<=0,0,(I44-(IF(I44<=0,0,(18000*(1+'1 - I TUOI 6 NUMERI'!$B$14)^23)/(1-'1 - I TUOI 6 NUMERI'!$B$15*(IF(I44<=0,0,MEDIAN(0,(I44-J44)/I44,1))))))-(IF(I44<=0,0,'1 - I TUOI 6 NUMERI'!$B$16*I44)))*(1+((1+0.03)*(1+'1 - I TUOI 6 NUMERI'!$B$14)-1))) | J45: =MAX(0,J44-(IF(I44<=0,0,(18000*(1+'1 - I TUOI 6 NUMERI'!$B$14)^23)/(1-'1 - I TUOI 6 NUMERI'!$B$15*(IF(I44<=0,0,MEDIAN(0,(I44-J44)/I44,1))))))*(1-(IF(I44<=0,0,MEDIAN(0,(I44-J44)/I44,1))))) | K45: =IF(K44<=0,0,(K44-(IF(K44<=0,0,(18000*(1+'1 - I TUOI 6 NUMERI'!$B$14)^23)/(1-'1 - I TUOI 6 NUMERI'!$B$15*(IF(K44<=0,0,MEDIAN(0,(K44-L44)/K44,1))))))-(IF(K44<=0,0,'1 - I TUOI 6 NUMERI'!$B$16*K44)))*(1+((1+0.05)*(1+'1 - I TUOI 6 NUMERI'!$B$14)-1))) | L45: =MAX(0,L44-(IF(K44<=0,0,(18000*(1+'1 - I TUOI 6 NUMERI'!$B$14)^23)/(1-'1 - I TUOI 6 NUMERI'!$B$15*(IF(K44<=0,0,MEDIAN(0,(K44-L44)/K44,1))))))*(1-(IF(K44<=0,0,MEDIAN(0,(K44-L44)/K44,1))))) | M45: =IF(M44<=0,0,(M44-(IF(M44<=0,0,(24000*(1+'1 - I TUOI 6 NUMERI'!$B$14)^23)/(1-'1 - I TUOI 6 NUMERI'!$B$15*(IF(M44<=0,0,MEDIAN(0,(M44-N44)/M44,1))))))-(IF(M44<=0,0,'1 - I TUOI 6 NUMERI'!$B$16*M44)))*(1+((1+0.01)*(1+'1 - I TUOI 6 NUMERI'!$B$14)-1))) | N45: =MAX(0,N44-(IF(M44<=0,0,(24000*(1+'1 - I TUOI 6 NUMERI'!$B$14)^23)/(1-'1 - I TUOI 6 NUMERI'!$B$15*(IF(M44<=0,0,MEDIAN(0,(M44-N44)/M44,1))))))*(1-(IF(M44<=0,0,MEDIAN(0,(M44-N44)/M44,1))))) | O45: =IF(O44<=0,0,(O44-(IF(O44<=0,0,(24000*(1+'1 - I TUOI 6 NUMERI'!$B$14)^23)/(1-'1 - I TUOI 6 NUMERI'!$B$15*(IF(O44<=0,0,MEDIAN(0,(O44-P44)/O44,1))))))-(IF(O44<=0,0,'1 - I TUOI 6 NUMERI'!$B$16*O44)))*(1+((1+0.03)*(1+'1 - I TUOI 6 NUMERI'!$B$14)-1))) | P45: =MAX(0,P44-(IF(O44<=0,0,(24000*(1+'1 - I TUOI 6 NUMERI'!$B$14)^23)/(1-'1 - I TUOI 6 NUMERI'!$B$15*(IF(O44<=0,0,MEDIAN(0,(O44-P44)/O44,1))))))*(1-(IF(O44<=0,0,MEDIAN(0,(O44-P44)/O44,1))))) | Q45: =IF(Q44<=0,0,(Q44-(IF(Q44<=0,0,(24000*(1+'1 - I TUOI 6 NUMERI'!$B$14)^23)/(1-'1 - I TUOI 6 NUMERI'!$B$15*(IF(Q44<=0,0,MEDIAN(0,(Q44-R44)/Q44,1))))))-(IF(Q44<=0,0,'1 - I TUOI 6 NUMERI'!$B$16*Q44)))*(1+((1+0.05)*(1+'1 - I TUOI 6 NUMERI'!$B$14)-1))) | R45: =MAX(0,R44-(IF(Q44<=0,0,(24000*(1+'1 - I TUOI 6 NUMERI'!$B$14)^23)/(1-'1 - I TUOI 6 NUMERI'!$B$15*(IF(Q44<=0,0,MEDIAN(0,(Q44-R44)/Q44,1))))))*(1-(IF(Q44<=0,0,MEDIAN(0,(Q44-R44)/Q44,1))))) | S45: =IF(S44<=0,0,(S44-(IF(S44<=0,0,(30000*(1+'1 - I TUOI 6 NUMERI'!$B$14)^23)/(1-'1 - I TUOI 6 NUMERI'!$B$15*(IF(S44<=0,0,MEDIAN(0,(S44-T44)/S44,1))))))-(IF(S44<=0,0,'1 - I TUOI 6 NUMERI'!$B$16*S44)))*(1+((1+0.01)*(1+'1 - I TUOI 6 NUMERI'!$B$14)-1))) | T45: =MAX(0,T44-(IF(S44<=0,0,(30000*(1+'1 - I TUOI 6 NUMERI'!$B$14)^23)/(1-'1 - I TUOI 6 NUMERI'!$B$15*(IF(S44<=0,0,MEDIAN(0,(S44-T44)/S44,1))))))*(1-(IF(S44<=0,0,MEDIAN(0,(S44-T44)/S44,1))))) | U45: =IF(U44<=0,0,(U44-(IF(U44<=0,0,(30000*(1+'1 - I TUOI 6 NUMERI'!$B$14)^23)/(1-'1 - I TUOI 6 NUMERI'!$B$15*(IF(U44<=0,0,MEDIAN(0,(U44-V44)/U44,1))))))-(IF(U44<=0,0,'1 - I TUOI 6 NUMERI'!$B$16*U44)))*(1+((1+0.03)*(1+'1 - I TUOI 6 NUMERI'!$B$14)-1))) | V45: =MAX(0,V44-(IF(U44<=0,0,(30000*(1+'1 - I TUOI 6 NUMERI'!$B$14)^23)/(1-'1 - I TUOI 6 NUMERI'!$B$15*(IF(U44<=0,0,MEDIAN(0,(U44-V44)/U44,1))))))*(1-(IF(U44<=0,0,MEDIAN(0,(U44-V44)/U44,1))))) | W45: =IF(W44<=0,0,(W44-(IF(W44<=0,0,(30000*(1+'1 - I TUOI 6 NUMERI'!$B$14)^23)/(1-'1 - I TUOI 6 NUMERI'!$B$15*(IF(W44<=0,0,MEDIAN(0,(W44-X44)/W44,1))))))-(IF(W44<=0,0,'1 - I TUOI 6 NUMERI'!$B$16*W44)))*(1+((1+0.05)*(1+'1 - I TUOI 6 NUMERI'!$B$14)-1))) | X45: =MAX(0,X44-(IF(W44<=0,0,(30000*(1+'1 - I TUOI 6 NUMERI'!$B$14)^23)/(1-'1 - I TUOI 6 NUMERI'!$B$15*(IF(W44<=0,0,MEDIAN(0,(W44-X44)/W44,1))))))*(1-(IF(W44<=0,0,MEDIAN(0,(W44-X44)/W44,1))))) | Y45: =IF(Y44<=0,0,(Y44-(IF(Y44<=0,0,(36000*(1+'1 - I TUOI 6 NUMERI'!$B$14)^23)/(1-'1 - I TUOI 6 NUMERI'!$B$15*(IF(Y44<=0,0,MEDIAN(0,(Y44-Z44)/Y44,1))))))-(IF(Y44<=0,0,'1 - I TUOI 6 NUMERI'!$B$16*Y44)))*(1+((1+0.01)*(1+'1 - I TUOI 6 NUMERI'!$B$14)-1))) | Z45: =MAX(0,Z44-(IF(Y44<=0,0,(36000*(1+'1 - I TUOI 6 NUMERI'!$B$14)^23)/(1-'1 - I TUOI 6 NUMERI'!$B$15*(IF(Y44<=0,0,MEDIAN(0,(Y44-Z44)/Y44,1))))))*(1-(IF(Y44<=0,0,MEDIAN(0,(Y44-Z44)/Y44,1))))) | AA45: =IF(AA44<=0,0,(AA44-(IF(AA44<=0,0,(36000*(1+'1 - I TUOI 6 NUMERI'!$B$14)^23)/(1-'1 - I TUOI 6 NUMERI'!$B$15*(IF(AA44<=0,0,MEDIAN(0,(AA44-AB44)/AA44,1))))))-(IF(AA44<=0,0,'1 - I TUOI 6 NUMERI'!$B$16*AA44)))*(1+((1+0.03)*(1+'1 - I TUOI 6 NUMERI'!$B$14)-1))) | AB45: =MAX(0,AB44-(IF(AA44<=0,0,(36000*(1+'1 - I TUOI 6 NUMERI'!$B$14)^23)/(1-'1 - I TUOI 6 NUMERI'!$B$15*(IF(AA44<=0,0,MEDIAN(0,(AA44-AB44)/AA44,1))))))*(1-(IF(AA44<=0,0,MEDIAN(0,(AA44-AB44)/AA44,1))))) | AC45: =IF(AC44<=0,0,(AC44-(IF(AC44<=0,0,(36000*(1+'1 - I TUOI 6 NUMERI'!$B$14)^23)/(1-'1 - I TUOI 6 NUMERI'!$B$15*(IF(AC44<=0,0,MEDIAN(0,(AC44-AD44)/AC44,1))))))-(IF(AC44<=0,0,'1 - I TUOI 6 NUMERI'!$B$16*AC44)))*(1+((1+0.05)*(1+'1 - I TUOI 6 NUMERI'!$B$14)-1))) | AD45: =MAX(0,AD44-(IF(AC44<=0,0,(36000*(1+'1 - I TUOI 6 NUMERI'!$B$14)^23)/(1-'1 - I TUOI 6 NUMERI'!$B$15*(IF(AC44<=0,0,MEDIAN(0,(AC44-AD44)/AC44,1))))))*(1-(IF(AC44<=0,0,MEDIAN(0,(AC44-AD44)/AC44,1)))))
F46: 24 | G46: =IF(G45<=0,0,(G45-(IF(G45<=0,0,(18000*(1+'1 - I TUOI 6 NUMERI'!$B$14)^24)/(1-'1 - I TUOI 6 NUMERI'!$B$15*(IF(G45<=0,0,MEDIAN(0,(G45-H45)/G45,1))))))-(IF(G45<=0,0,'1 - I TUOI 6 NUMERI'!$B$16*G45)))*(1+((1+0.01)*(1+'1 - I TUOI 6 NUMERI'!$B$14)-1))) | H46: =MAX(0,H45-(IF(G45<=0,0,(18000*(1+'1 - I TUOI 6 NUMERI'!$B$14)^24)/(1-'1 - I TUOI 6 NUMERI'!$B$15*(IF(G45<=0,0,MEDIAN(0,(G45-H45)/G45,1))))))*(1-(IF(G45<=0,0,MEDIAN(0,(G45-H45)/G45,1))))) | I46: =IF(I45<=0,0,(I45-(IF(I45<=0,0,(18000*(1+'1 - I TUOI 6 NUMERI'!$B$14)^24)/(1-'1 - I TUOI 6 NUMERI'!$B$15*(IF(I45<=0,0,MEDIAN(0,(I45-J45)/I45,1))))))-(IF(I45<=0,0,'1 - I TUOI 6 NUMERI'!$B$16*I45)))*(1+((1+0.03)*(1+'1 - I TUOI 6 NUMERI'!$B$14)-1))) | J46: =MAX(0,J45-(IF(I45<=0,0,(18000*(1+'1 - I TUOI 6 NUMERI'!$B$14)^24)/(1-'1 - I TUOI 6 NUMERI'!$B$15*(IF(I45<=0,0,MEDIAN(0,(I45-J45)/I45,1))))))*(1-(IF(I45<=0,0,MEDIAN(0,(I45-J45)/I45,1))))) | K46: =IF(K45<=0,0,(K45-(IF(K45<=0,0,(18000*(1+'1 - I TUOI 6 NUMERI'!$B$14)^24)/(1-'1 - I TUOI 6 NUMERI'!$B$15*(IF(K45<=0,0,MEDIAN(0,(K45-L45)/K45,1))))))-(IF(K45<=0,0,'1 - I TUOI 6 NUMERI'!$B$16*K45)))*(1+((1+0.05)*(1+'1 - I TUOI 6 NUMERI'!$B$14)-1))) | L46: =MAX(0,L45-(IF(K45<=0,0,(18000*(1+'1 - I TUOI 6 NUMERI'!$B$14)^24)/(1-'1 - I TUOI 6 NUMERI'!$B$15*(IF(K45<=0,0,MEDIAN(0,(K45-L45)/K45,1))))))*(1-(IF(K45<=0,0,MEDIAN(0,(K45-L45)/K45,1))))) | M46: =IF(M45<=0,0,(M45-(IF(M45<=0,0,(24000*(1+'1 - I TUOI 6 NUMERI'!$B$14)^24)/(1-'1 - I TUOI 6 NUMERI'!$B$15*(IF(M45<=0,0,MEDIAN(0,(M45-N45)/M45,1))))))-(IF(M45<=0,0,'1 - I TUOI 6 NUMERI'!$B$16*M45)))*(1+((1+0.01)*(1+'1 - I TUOI 6 NUMERI'!$B$14)-1))) | N46: =MAX(0,N45-(IF(M45<=0,0,(24000*(1+'1 - I TUOI 6 NUMERI'!$B$14)^24)/(1-'1 - I TUOI 6 NUMERI'!$B$15*(IF(M45<=0,0,MEDIAN(0,(M45-N45)/M45,1))))))*(1-(IF(M45<=0,0,MEDIAN(0,(M45-N45)/M45,1))))) | O46: =IF(O45<=0,0,(O45-(IF(O45<=0,0,(24000*(1+'1 - I TUOI 6 NUMERI'!$B$14)^24)/(1-'1 - I TUOI 6 NUMERI'!$B$15*(IF(O45<=0,0,MEDIAN(0,(O45-P45)/O45,1))))))-(IF(O45<=0,0,'1 - I TUOI 6 NUMERI'!$B$16*O45)))*(1+((1+0.03)*(1+'1 - I TUOI 6 NUMERI'!$B$14)-1))) | P46: =MAX(0,P45-(IF(O45<=0,0,(24000*(1+'1 - I TUOI 6 NUMERI'!$B$14)^24)/(1-'1 - I TUOI 6 NUMERI'!$B$15*(IF(O45<=0,0,MEDIAN(0,(O45-P45)/O45,1))))))*(1-(IF(O45<=0,0,MEDIAN(0,(O45-P45)/O45,1))))) | Q46: =IF(Q45<=0,0,(Q45-(IF(Q45<=0,0,(24000*(1+'1 - I TUOI 6 NUMERI'!$B$14)^24)/(1-'1 - I TUOI 6 NUMERI'!$B$15*(IF(Q45<=0,0,MEDIAN(0,(Q45-R45)/Q45,1))))))-(IF(Q45<=0,0,'1 - I TUOI 6 NUMERI'!$B$16*Q45)))*(1+((1+0.05)*(1+'1 - I TUOI 6 NUMERI'!$B$14)-1))) | R46: =MAX(0,R45-(IF(Q45<=0,0,(24000*(1+'1 - I TUOI 6 NUMERI'!$B$14)^24)/(1-'1 - I TUOI 6 NUMERI'!$B$15*(IF(Q45<=0,0,MEDIAN(0,(Q45-R45)/Q45,1))))))*(1-(IF(Q45<=0,0,MEDIAN(0,(Q45-R45)/Q45,1))))) | S46: =IF(S45<=0,0,(S45-(IF(S45<=0,0,(30000*(1+'1 - I TUOI 6 NUMERI'!$B$14)^24)/(1-'1 - I TUOI 6 NUMERI'!$B$15*(IF(S45<=0,0,MEDIAN(0,(S45-T45)/S45,1))))))-(IF(S45<=0,0,'1 - I TUOI 6 NUMERI'!$B$16*S45)))*(1+((1+0.01)*(1+'1 - I TUOI 6 NUMERI'!$B$14)-1))) | T46: =MAX(0,T45-(IF(S45<=0,0,(30000*(1+'1 - I TUOI 6 NUMERI'!$B$14)^24)/(1-'1 - I TUOI 6 NUMERI'!$B$15*(IF(S45<=0,0,MEDIAN(0,(S45-T45)/S45,1))))))*(1-(IF(S45<=0,0,MEDIAN(0,(S45-T45)/S45,1))))) | U46: =IF(U45<=0,0,(U45-(IF(U45<=0,0,(30000*(1+'1 - I TUOI 6 NUMERI'!$B$14)^24)/(1-'1 - I TUOI 6 NUMERI'!$B$15*(IF(U45<=0,0,MEDIAN(0,(U45-V45)/U45,1))))))-(IF(U45<=0,0,'1 - I TUOI 6 NUMERI'!$B$16*U45)))*(1+((1+0.03)*(1+'1 - I TUOI 6 NUMERI'!$B$14)-1))) | V46: =MAX(0,V45-(IF(U45<=0,0,(30000*(1+'1 - I TUOI 6 NUMERI'!$B$14)^24)/(1-'1 - I TUOI 6 NUMERI'!$B$15*(IF(U45<=0,0,MEDIAN(0,(U45-V45)/U45,1))))))*(1-(IF(U45<=0,0,MEDIAN(0,(U45-V45)/U45,1))))) | W46: =IF(W45<=0,0,(W45-(IF(W45<=0,0,(30000*(1+'1 - I TUOI 6 NUMERI'!$B$14)^24)/(1-'1 - I TUOI 6 NUMERI'!$B$15*(IF(W45<=0,0,MEDIAN(0,(W45-X45)/W45,1))))))-(IF(W45<=0,0,'1 - I TUOI 6 NUMERI'!$B$16*W45)))*(1+((1+0.05)*(1+'1 - I TUOI 6 NUMERI'!$B$14)-1))) | X46: =MAX(0,X45-(IF(W45<=0,0,(30000*(1+'1 - I TUOI 6 NUMERI'!$B$14)^24)/(1-'1 - I TUOI 6 NUMERI'!$B$15*(IF(W45<=0,0,MEDIAN(0,(W45-X45)/W45,1))))))*(1-(IF(W45<=0,0,MEDIAN(0,(W45-X45)/W45,1))))) | Y46: =IF(Y45<=0,0,(Y45-(IF(Y45<=0,0,(36000*(1+'1 - I TUOI 6 NUMERI'!$B$14)^24)/(1-'1 - I TUOI 6 NUMERI'!$B$15*(IF(Y45<=0,0,MEDIAN(0,(Y45-Z45)/Y45,1))))))-(IF(Y45<=0,0,'1 - I TUOI 6 NUMERI'!$B$16*Y45)))*(1+((1+0.01)*(1+'1 - I TUOI 6 NUMERI'!$B$14)-1))) | Z46: =MAX(0,Z45-(IF(Y45<=0,0,(36000*(1+'1 - I TUOI 6 NUMERI'!$B$14)^24)/(1-'1 - I TUOI 6 NUMERI'!$B$15*(IF(Y45<=0,0,MEDIAN(0,(Y45-Z45)/Y45,1))))))*(1-(IF(Y45<=0,0,MEDIAN(0,(Y45-Z45)/Y45,1))))) | AA46: =IF(AA45<=0,0,(AA45-(IF(AA45<=0,0,(36000*(1+'1 - I TUOI 6 NUMERI'!$B$14)^24)/(1-'1 - I TUOI 6 NUMERI'!$B$15*(IF(AA45<=0,0,MEDIAN(0,(AA45-AB45)/AA45,1))))))-(IF(AA45<=0,0,'1 - I TUOI 6 NUMERI'!$B$16*AA45)))*(1+((1+0.03)*(1+'1 - I TUOI 6 NUMERI'!$B$14)-1))) | AB46: =MAX(0,AB45-(IF(AA45<=0,0,(36000*(1+'1 - I TUOI 6 NUMERI'!$B$14)^24)/(1-'1 - I TUOI 6 NUMERI'!$B$15*(IF(AA45<=0,0,MEDIAN(0,(AA45-AB45)/AA45,1))))))*(1-(IF(AA45<=0,0,MEDIAN(0,(AA45-AB45)/AA45,1))))) | AC46: =IF(AC45<=0,0,(AC45-(IF(AC45<=0,0,(36000*(1+'1 - I TUOI 6 NUMERI'!$B$14)^24)/(1-'1 - I TUOI 6 NUMERI'!$B$15*(IF(AC45<=0,0,MEDIAN(0,(AC45-AD45)/AC45,1))))))-(IF(AC45<=0,0,'1 - I TUOI 6 NUMERI'!$B$16*AC45)))*(1+((1+0.05)*(1+'1 - I TUOI 6 NUMERI'!$B$14)-1))) | AD46: =MAX(0,AD45-(IF(AC45<=0,0,(36000*(1+'1 - I TUOI 6 NUMERI'!$B$14)^24)/(1-'1 - I TUOI 6 NUMERI'!$B$15*(IF(AC45<=0,0,MEDIAN(0,(AC45-AD45)/AC45,1))))))*(1-(IF(AC45<=0,0,MEDIAN(0,(AC45-AD45)/AC45,1)))))
F47: 25 | G47: =IF(G46<=0,0,(G46-(IF(G46<=0,0,(18000*(1+'1 - I TUOI 6 NUMERI'!$B$14)^25)/(1-'1 - I TUOI 6 NUMERI'!$B$15*(IF(G46<=0,0,MEDIAN(0,(G46-H46)/G46,1))))))-(IF(G46<=0,0,'1 - I TUOI 6 NUMERI'!$B$16*G46)))*(1+((1+0.01)*(1+'1 - I TUOI 6 NUMERI'!$B$14)-1))) | H47: =MAX(0,H46-(IF(G46<=0,0,(18000*(1+'1 - I TUOI 6 NUMERI'!$B$14)^25)/(1-'1 - I TUOI 6 NUMERI'!$B$15*(IF(G46<=0,0,MEDIAN(0,(G46-H46)/G46,1))))))*(1-(IF(G46<=0,0,MEDIAN(0,(G46-H46)/G46,1))))) | I47: =IF(I46<=0,0,(I46-(IF(I46<=0,0,(18000*(1+'1 - I TUOI 6 NUMERI'!$B$14)^25)/(1-'1 - I TUOI 6 NUMERI'!$B$15*(IF(I46<=0,0,MEDIAN(0,(I46-J46)/I46,1))))))-(IF(I46<=0,0,'1 - I TUOI 6 NUMERI'!$B$16*I46)))*(1+((1+0.03)*(1+'1 - I TUOI 6 NUMERI'!$B$14)-1))) | J47: =MAX(0,J46-(IF(I46<=0,0,(18000*(1+'1 - I TUOI 6 NUMERI'!$B$14)^25)/(1-'1 - I TUOI 6 NUMERI'!$B$15*(IF(I46<=0,0,MEDIAN(0,(I46-J46)/I46,1))))))*(1-(IF(I46<=0,0,MEDIAN(0,(I46-J46)/I46,1))))) | K47: =IF(K46<=0,0,(K46-(IF(K46<=0,0,(18000*(1+'1 - I TUOI 6 NUMERI'!$B$14)^25)/(1-'1 - I TUOI 6 NUMERI'!$B$15*(IF(K46<=0,0,MEDIAN(0,(K46-L46)/K46,1))))))-(IF(K46<=0,0,'1 - I TUOI 6 NUMERI'!$B$16*K46)))*(1+((1+0.05)*(1+'1 - I TUOI 6 NUMERI'!$B$14)-1))) | L47: =MAX(0,L46-(IF(K46<=0,0,(18000*(1+'1 - I TUOI 6 NUMERI'!$B$14)^25)/(1-'1 - I TUOI 6 NUMERI'!$B$15*(IF(K46<=0,0,MEDIAN(0,(K46-L46)/K46,1))))))*(1-(IF(K46<=0,0,MEDIAN(0,(K46-L46)/K46,1))))) | M47: =IF(M46<=0,0,(M46-(IF(M46<=0,0,(24000*(1+'1 - I TUOI 6 NUMERI'!$B$14)^25)/(1-'1 - I TUOI 6 NUMERI'!$B$15*(IF(M46<=0,0,MEDIAN(0,(M46-N46)/M46,1))))))-(IF(M46<=0,0,'1 - I TUOI 6 NUMERI'!$B$16*M46)))*(1+((1+0.01)*(1+'1 - I TUOI 6 NUMERI'!$B$14)-1))) | N47: =MAX(0,N46-(IF(M46<=0,0,(24000*(1+'1 - I TUOI 6 NUMERI'!$B$14)^25)/(1-'1 - I TUOI 6 NUMERI'!$B$15*(IF(M46<=0,0,MEDIAN(0,(M46-N46)/M46,1))))))*(1-(IF(M46<=0,0,MEDIAN(0,(M46-N46)/M46,1))))) | O47: =IF(O46<=0,0,(O46-(IF(O46<=0,0,(24000*(1+'1 - I TUOI 6 NUMERI'!$B$14)^25)/(1-'1 - I TUOI 6 NUMERI'!$B$15*(IF(O46<=0,0,MEDIAN(0,(O46-P46)/O46,1))))))-(IF(O46<=0,0,'1 - I TUOI 6 NUMERI'!$B$16*O46)))*(1+((1+0.03)*(1+'1 - I TUOI 6 NUMERI'!$B$14)-1))) | P47: =MAX(0,P46-(IF(O46<=0,0,(24000*(1+'1 - I TUOI 6 NUMERI'!$B$14)^25)/(1-'1 - I TUOI 6 NUMERI'!$B$15*(IF(O46<=0,0,MEDIAN(0,(O46-P46)/O46,1))))))*(1-(IF(O46<=0,0,MEDIAN(0,(O46-P46)/O46,1))))) | Q47: =IF(Q46<=0,0,(Q46-(IF(Q46<=0,0,(24000*(1+'1 - I TUOI 6 NUMERI'!$B$14)^25)/(1-'1 - I TUOI 6 NUMERI'!$B$15*(IF(Q46<=0,0,MEDIAN(0,(Q46-R46)/Q46,1))))))-(IF(Q46<=0,0,'1 - I TUOI 6 NUMERI'!$B$16*Q46)))*(1+((1+0.05)*(1+'1 - I TUOI 6 NUMERI'!$B$14)-1))) | R47: =MAX(0,R46-(IF(Q46<=0,0,(24000*(1+'1 - I TUOI 6 NUMERI'!$B$14)^25)/(1-'1 - I TUOI 6 NUMERI'!$B$15*(IF(Q46<=0,0,MEDIAN(0,(Q46-R46)/Q46,1))))))*(1-(IF(Q46<=0,0,MEDIAN(0,(Q46-R46)/Q46,1))))) | S47: =IF(S46<=0,0,(S46-(IF(S46<=0,0,(30000*(1+'1 - I TUOI 6 NUMERI'!$B$14)^25)/(1-'1 - I TUOI 6 NUMERI'!$B$15*(IF(S46<=0,0,MEDIAN(0,(S46-T46)/S46,1))))))-(IF(S46<=0,0,'1 - I TUOI 6 NUMERI'!$B$16*S46)))*(1+((1+0.01)*(1+'1 - I TUOI 6 NUMERI'!$B$14)-1))) | T47: =MAX(0,T46-(IF(S46<=0,0,(30000*(1+'1 - I TUOI 6 NUMERI'!$B$14)^25)/(1-'1 - I TUOI 6 NUMERI'!$B$15*(IF(S46<=0,0,MEDIAN(0,(S46-T46)/S46,1))))))*(1-(IF(S46<=0,0,MEDIAN(0,(S46-T46)/S46,1))))) | U47: =IF(U46<=0,0,(U46-(IF(U46<=0,0,(30000*(1+'1 - I TUOI 6 NUMERI'!$B$14)^25)/(1-'1 - I TUOI 6 NUMERI'!$B$15*(IF(U46<=0,0,MEDIAN(0,(U46-V46)/U46,1))))))-(IF(U46<=0,0,'1 - I TUOI 6 NUMERI'!$B$16*U46)))*(1+((1+0.03)*(1+'1 - I TUOI 6 NUMERI'!$B$14)-1))) | V47: =MAX(0,V46-(IF(U46<=0,0,(30000*(1+'1 - I TUOI 6 NUMERI'!$B$14)^25)/(1-'1 - I TUOI 6 NUMERI'!$B$15*(IF(U46<=0,0,MEDIAN(0,(U46-V46)/U46,1))))))*(1-(IF(U46<=0,0,MEDIAN(0,(U46-V46)/U46,1))))) | W47: =IF(W46<=0,0,(W46-(IF(W46<=0,0,(30000*(1+'1 - I TUOI 6 NUMERI'!$B$14)^25)/(1-'1 - I TUOI 6 NUMERI'!$B$15*(IF(W46<=0,0,MEDIAN(0,(W46-X46)/W46,1))))))-(IF(W46<=0,0,'1 - I TUOI 6 NUMERI'!$B$16*W46)))*(1+((1+0.05)*(1+'1 - I TUOI 6 NUMERI'!$B$14)-1))) | X47: =MAX(0,X46-(IF(W46<=0,0,(30000*(1+'1 - I TUOI 6 NUMERI'!$B$14)^25)/(1-'1 - I TUOI 6 NUMERI'!$B$15*(IF(W46<=0,0,MEDIAN(0,(W46-X46)/W46,1))))))*(1-(IF(W46<=0,0,MEDIAN(0,(W46-X46)/W46,1))))) | Y47: =IF(Y46<=0,0,(Y46-(IF(Y46<=0,0,(36000*(1+'1 - I TUOI 6 NUMERI'!$B$14)^25)/(1-'1 - I TUOI 6 NUMERI'!$B$15*(IF(Y46<=0,0,MEDIAN(0,(Y46-Z46)/Y46,1))))))-(IF(Y46<=0,0,'1 - I TUOI 6 NUMERI'!$B$16*Y46)))*(1+((1+0.01)*(1+'1 - I TUOI 6 NUMERI'!$B$14)-1))) | Z47: =MAX(0,Z46-(IF(Y46<=0,0,(36000*(1+'1 - I TUOI 6 NUMERI'!$B$14)^25)/(1-'1 - I TUOI 6 NUMERI'!$B$15*(IF(Y46<=0,0,MEDIAN(0,(Y46-Z46)/Y46,1))))))*(1-(IF(Y46<=0,0,MEDIAN(0,(Y46-Z46)/Y46,1))))) | AA47: =IF(AA46<=0,0,(AA46-(IF(AA46<=0,0,(36000*(1+'1 - I TUOI 6 NUMERI'!$B$14)^25)/(1-'1 - I TUOI 6 NUMERI'!$B$15*(IF(AA46<=0,0,MEDIAN(0,(AA46-AB46)/AA46,1))))))-(IF(AA46<=0,0,'1 - I TUOI 6 NUMERI'!$B$16*AA46)))*(1+((1+0.03)*(1+'1 - I TUOI 6 NUMERI'!$B$14)-1))) | AB47: =MAX(0,AB46-(IF(AA46<=0,0,(36000*(1+'1 - I TUOI 6 NUMERI'!$B$14)^25)/(1-'1 - I TUOI 6 NUMERI'!$B$15*(IF(AA46<=0,0,MEDIAN(0,(AA46-AB46)/AA46,1))))))*(1-(IF(AA46<=0,0,MEDIAN(0,(AA46-AB46)/AA46,1))))) | AC47: =IF(AC46<=0,0,(AC46-(IF(AC46<=0,0,(36000*(1+'1 - I TUOI 6 NUMERI'!$B$14)^25)/(1-'1 - I TUOI 6 NUMERI'!$B$15*(IF(AC46<=0,0,MEDIAN(0,(AC46-AD46)/AC46,1))))))-(IF(AC46<=0,0,'1 - I TUOI 6 NUMERI'!$B$16*AC46)))*(1+((1+0.05)*(1+'1 - I TUOI 6 NUMERI'!$B$14)-1))) | AD47: =MAX(0,AD46-(IF(AC46<=0,0,(36000*(1+'1 - I TUOI 6 NUMERI'!$B$14)^25)/(1-'1 - I TUOI 6 NUMERI'!$B$15*(IF(AC46<=0,0,MEDIAN(0,(AC46-AD46)/AC46,1))))))*(1-(IF(AC46<=0,0,MEDIAN(0,(AC46-AD46)/AC46,1)))))
F48: 26 | G48: =IF(G47<=0,0,(G47-(IF(G47<=0,0,(18000*(1+'1 - I TUOI 6 NUMERI'!$B$14)^26)/(1-'1 - I TUOI 6 NUMERI'!$B$15*(IF(G47<=0,0,MEDIAN(0,(G47-H47)/G47,1))))))-(IF(G47<=0,0,'1 - I TUOI 6 NUMERI'!$B$16*G47)))*(1+((1+0.01)*(1+'1 - I TUOI 6 NUMERI'!$B$14)-1))) | H48: =MAX(0,H47-(IF(G47<=0,0,(18000*(1+'1 - I TUOI 6 NUMERI'!$B$14)^26)/(1-'1 - I TUOI 6 NUMERI'!$B$15*(IF(G47<=0,0,MEDIAN(0,(G47-H47)/G47,1))))))*(1-(IF(G47<=0,0,MEDIAN(0,(G47-H47)/G47,1))))) | I48: =IF(I47<=0,0,(I47-(IF(I47<=0,0,(18000*(1+'1 - I TUOI 6 NUMERI'!$B$14)^26)/(1-'1 - I TUOI 6 NUMERI'!$B$15*(IF(I47<=0,0,MEDIAN(0,(I47-J47)/I47,1))))))-(IF(I47<=0,0,'1 - I TUOI 6 NUMERI'!$B$16*I47)))*(1+((1+0.03)*(1+'1 - I TUOI 6 NUMERI'!$B$14)-1))) | J48: =MAX(0,J47-(IF(I47<=0,0,(18000*(1+'1 - I TUOI 6 NUMERI'!$B$14)^26)/(1-'1 - I TUOI 6 NUMERI'!$B$15*(IF(I47<=0,0,MEDIAN(0,(I47-J47)/I47,1))))))*(1-(IF(I47<=0,0,MEDIAN(0,(I47-J47)/I47,1))))) | K48: =IF(K47<=0,0,(K47-(IF(K47<=0,0,(18000*(1+'1 - I TUOI 6 NUMERI'!$B$14)^26)/(1-'1 - I TUOI 6 NUMERI'!$B$15*(IF(K47<=0,0,MEDIAN(0,(K47-L47)/K47,1))))))-(IF(K47<=0,0,'1 - I TUOI 6 NUMERI'!$B$16*K47)))*(1+((1+0.05)*(1+'1 - I TUOI 6 NUMERI'!$B$14)-1))) | L48: =MAX(0,L47-(IF(K47<=0,0,(18000*(1+'1 - I TUOI 6 NUMERI'!$B$14)^26)/(1-'1 - I TUOI 6 NUMERI'!$B$15*(IF(K47<=0,0,MEDIAN(0,(K47-L47)/K47,1))))))*(1-(IF(K47<=0,0,MEDIAN(0,(K47-L47)/K47,1))))) | M48: =IF(M47<=0,0,(M47-(IF(M47<=0,0,(24000*(1+'1 - I TUOI 6 NUMERI'!$B$14)^26)/(1-'1 - I TUOI 6 NUMERI'!$B$15*(IF(M47<=0,0,MEDIAN(0,(M47-N47)/M47,1))))))-(IF(M47<=0,0,'1 - I TUOI 6 NUMERI'!$B$16*M47)))*(1+((1+0.01)*(1+'1 - I TUOI 6 NUMERI'!$B$14)-1))) | N48: =MAX(0,N47-(IF(M47<=0,0,(24000*(1+'1 - I TUOI 6 NUMERI'!$B$14)^26)/(1-'1 - I TUOI 6 NUMERI'!$B$15*(IF(M47<=0,0,MEDIAN(0,(M47-N47)/M47,1))))))*(1-(IF(M47<=0,0,MEDIAN(0,(M47-N47)/M47,1))))) | O48: =IF(O47<=0,0,(O47-(IF(O47<=0,0,(24000*(1+'1 - I TUOI 6 NUMERI'!$B$14)^26)/(1-'1 - I TUOI 6 NUMERI'!$B$15*(IF(O47<=0,0,MEDIAN(0,(O47-P47)/O47,1))))))-(IF(O47<=0,0,'1 - I TUOI 6 NUMERI'!$B$16*O47)))*(1+((1+0.03)*(1+'1 - I TUOI 6 NUMERI'!$B$14)-1))) | P48: =MAX(0,P47-(IF(O47<=0,0,(24000*(1+'1 - I TUOI 6 NUMERI'!$B$14)^26)/(1-'1 - I TUOI 6 NUMERI'!$B$15*(IF(O47<=0,0,MEDIAN(0,(O47-P47)/O47,1))))))*(1-(IF(O47<=0,0,MEDIAN(0,(O47-P47)/O47,1))))) | Q48: =IF(Q47<=0,0,(Q47-(IF(Q47<=0,0,(24000*(1+'1 - I TUOI 6 NUMERI'!$B$14)^26)/(1-'1 - I TUOI 6 NUMERI'!$B$15*(IF(Q47<=0,0,MEDIAN(0,(Q47-R47)/Q47,1))))))-(IF(Q47<=0,0,'1 - I TUOI 6 NUMERI'!$B$16*Q47)))*(1+((1+0.05)*(1+'1 - I TUOI 6 NUMERI'!$B$14)-1))) | R48: =MAX(0,R47-(IF(Q47<=0,0,(24000*(1+'1 - I TUOI 6 NUMERI'!$B$14)^26)/(1-'1 - I TUOI 6 NUMERI'!$B$15*(IF(Q47<=0,0,MEDIAN(0,(Q47-R47)/Q47,1))))))*(1-(IF(Q47<=0,0,MEDIAN(0,(Q47-R47)/Q47,1))))) | S48: =IF(S47<=0,0,(S47-(IF(S47<=0,0,(30000*(1+'1 - I TUOI 6 NUMERI'!$B$14)^26)/(1-'1 - I TUOI 6 NUMERI'!$B$15*(IF(S47<=0,0,MEDIAN(0,(S47-T47)/S47,1))))))-(IF(S47<=0,0,'1 - I TUOI 6 NUMERI'!$B$16*S47)))*(1+((1+0.01)*(1+'1 - I TUOI 6 NUMERI'!$B$14)-1))) | T48: =MAX(0,T47-(IF(S47<=0,0,(30000*(1+'1 - I TUOI 6 NUMERI'!$B$14)^26)/(1-'1 - I TUOI 6 NUMERI'!$B$15*(IF(S47<=0,0,MEDIAN(0,(S47-T47)/S47,1))))))*(1-(IF(S47<=0,0,MEDIAN(0,(S47-T47)/S47,1))))) | U48: =IF(U47<=0,0,(U47-(IF(U47<=0,0,(30000*(1+'1 - I TUOI 6 NUMERI'!$B$14)^26)/(1-'1 - I TUOI 6 NUMERI'!$B$15*(IF(U47<=0,0,MEDIAN(0,(U47-V47)/U47,1))))))-(IF(U47<=0,0,'1 - I TUOI 6 NUMERI'!$B$16*U47)))*(1+((1+0.03)*(1+'1 - I TUOI 6 NUMERI'!$B$14)-1))) | V48: =MAX(0,V47-(IF(U47<=0,0,(30000*(1+'1 - I TUOI 6 NUMERI'!$B$14)^26)/(1-'1 - I TUOI 6 NUMERI'!$B$15*(IF(U47<=0,0,MEDIAN(0,(U47-V47)/U47,1))))))*(1-(IF(U47<=0,0,MEDIAN(0,(U47-V47)/U47,1))))) | W48: =IF(W47<=0,0,(W47-(IF(W47<=0,0,(30000*(1+'1 - I TUOI 6 NUMERI'!$B$14)^26)/(1-'1 - I TUOI 6 NUMERI'!$B$15*(IF(W47<=0,0,MEDIAN(0,(W47-X47)/W47,1))))))-(IF(W47<=0,0,'1 - I TUOI 6 NUMERI'!$B$16*W47)))*(1+((1+0.05)*(1+'1 - I TUOI 6 NUMERI'!$B$14)-1))) | X48: =MAX(0,X47-(IF(W47<=0,0,(30000*(1+'1 - I TUOI 6 NUMERI'!$B$14)^26)/(1-'1 - I TUOI 6 NUMERI'!$B$15*(IF(W47<=0,0,MEDIAN(0,(W47-X47)/W47,1))))))*(1-(IF(W47<=0,0,MEDIAN(0,(W47-X47)/W47,1))))) | Y48: =IF(Y47<=0,0,(Y47-(IF(Y47<=0,0,(36000*(1+'1 - I TUOI 6 NUMERI'!$B$14)^26)/(1-'1 - I TUOI 6 NUMERI'!$B$15*(IF(Y47<=0,0,MEDIAN(0,(Y47-Z47)/Y47,1))))))-(IF(Y47<=0,0,'1 - I TUOI 6 NUMERI'!$B$16*Y47)))*(1+((1+0.01)*(1+'1 - I TUOI 6 NUMERI'!$B$14)-1))) | Z48: =MAX(0,Z47-(IF(Y47<=0,0,(36000*(1+'1 - I TUOI 6 NUMERI'!$B$14)^26)/(1-'1 - I TUOI 6 NUMERI'!$B$15*(IF(Y47<=0,0,MEDIAN(0,(Y47-Z47)/Y47,1))))))*(1-(IF(Y47<=0,0,MEDIAN(0,(Y47-Z47)/Y47,1))))) | AA48: =IF(AA47<=0,0,(AA47-(IF(AA47<=0,0,(36000*(1+'1 - I TUOI 6 NUMERI'!$B$14)^26)/(1-'1 - I TUOI 6 NUMERI'!$B$15*(IF(AA47<=0,0,MEDIAN(0,(AA47-AB47)/AA47,1))))))-(IF(AA47<=0,0,'1 - I TUOI 6 NUMERI'!$B$16*AA47)))*(1+((1+0.03)*(1+'1 - I TUOI 6 NUMERI'!$B$14)-1))) | AB48: =MAX(0,AB47-(IF(AA47<=0,0,(36000*(1+'1 - I TUOI 6 NUMERI'!$B$14)^26)/(1-'1 - I TUOI 6 NUMERI'!$B$15*(IF(AA47<=0,0,MEDIAN(0,(AA47-AB47)/AA47,1))))))*(1-(IF(AA47<=0,0,MEDIAN(0,(AA47-AB47)/AA47,1))))) | AC48: =IF(AC47<=0,0,(AC47-(IF(AC47<=0,0,(36000*(1+'1 - I TUOI 6 NUMERI'!$B$14)^26)/(1-'1 - I TUOI 6 NUMERI'!$B$15*(IF(AC47<=0,0,MEDIAN(0,(AC47-AD47)/AC47,1))))))-(IF(AC47<=0,0,'1 - I TUOI 6 NUMERI'!$B$16*AC47)))*(1+((1+0.05)*(1+'1 - I TUOI 6 NUMERI'!$B$14)-1))) | AD48: =MAX(0,AD47-(IF(AC47<=0,0,(36000*(1+'1 - I TUOI 6 NUMERI'!$B$14)^26)/(1-'1 - I TUOI 6 NUMERI'!$B$15*(IF(AC47<=0,0,MEDIAN(0,(AC47-AD47)/AC47,1))))))*(1-(IF(AC47<=0,0,MEDIAN(0,(AC47-AD47)/AC47,1)))))
F49: 27 | G49: =IF(G48<=0,0,(G48-(IF(G48<=0,0,(18000*(1+'1 - I TUOI 6 NUMERI'!$B$14)^27)/(1-'1 - I TUOI 6 NUMERI'!$B$15*(IF(G48<=0,0,MEDIAN(0,(G48-H48)/G48,1))))))-(IF(G48<=0,0,'1 - I TUOI 6 NUMERI'!$B$16*G48)))*(1+((1+0.01)*(1+'1 - I TUOI 6 NUMERI'!$B$14)-1))) | H49: =MAX(0,H48-(IF(G48<=0,0,(18000*(1+'1 - I TUOI 6 NUMERI'!$B$14)^27)/(1-'1 - I TUOI 6 NUMERI'!$B$15*(IF(G48<=0,0,MEDIAN(0,(G48-H48)/G48,1))))))*(1-(IF(G48<=0,0,MEDIAN(0,(G48-H48)/G48,1))))) | I49: =IF(I48<=0,0,(I48-(IF(I48<=0,0,(18000*(1+'1 - I TUOI 6 NUMERI'!$B$14)^27)/(1-'1 - I TUOI 6 NUMERI'!$B$15*(IF(I48<=0,0,MEDIAN(0,(I48-J48)/I48,1))))))-(IF(I48<=0,0,'1 - I TUOI 6 NUMERI'!$B$16*I48)))*(1+((1+0.03)*(1+'1 - I TUOI 6 NUMERI'!$B$14)-1))) | J49: =MAX(0,J48-(IF(I48<=0,0,(18000*(1+'1 - I TUOI 6 NUMERI'!$B$14)^27)/(1-'1 - I TUOI 6 NUMERI'!$B$15*(IF(I48<=0,0,MEDIAN(0,(I48-J48)/I48,1))))))*(1-(IF(I48<=0,0,MEDIAN(0,(I48-J48)/I48,1))))) | K49: =IF(K48<=0,0,(K48-(IF(K48<=0,0,(18000*(1+'1 - I TUOI 6 NUMERI'!$B$14)^27)/(1-'1 - I TUOI 6 NUMERI'!$B$15*(IF(K48<=0,0,MEDIAN(0,(K48-L48)/K48,1))))))-(IF(K48<=0,0,'1 - I TUOI 6 NUMERI'!$B$16*K48)))*(1+((1+0.05)*(1+'1 - I TUOI 6 NUMERI'!$B$14)-1))) | L49: =MAX(0,L48-(IF(K48<=0,0,(18000*(1+'1 - I TUOI 6 NUMERI'!$B$14)^27)/(1-'1 - I TUOI 6 NUMERI'!$B$15*(IF(K48<=0,0,MEDIAN(0,(K48-L48)/K48,1))))))*(1-(IF(K48<=0,0,MEDIAN(0,(K48-L48)/K48,1))))) | M49: =IF(M48<=0,0,(M48-(IF(M48<=0,0,(24000*(1+'1 - I TUOI 6 NUMERI'!$B$14)^27)/(1-'1 - I TUOI 6 NUMERI'!$B$15*(IF(M48<=0,0,MEDIAN(0,(M48-N48)/M48,1))))))-(IF(M48<=0,0,'1 - I TUOI 6 NUMERI'!$B$16*M48)))*(1+((1+0.01)*(1+'1 - I TUOI 6 NUMERI'!$B$14)-1))) | N49: =MAX(0,N48-(IF(M48<=0,0,(24000*(1+'1 - I TUOI 6 NUMERI'!$B$14)^27)/(1-'1 - I TUOI 6 NUMERI'!$B$15*(IF(M48<=0,0,MEDIAN(0,(M48-N48)/M48,1))))))*(1-(IF(M48<=0,0,MEDIAN(0,(M48-N48)/M48,1))))) | O49: =IF(O48<=0,0,(O48-(IF(O48<=0,0,(24000*(1+'1 - I TUOI 6 NUMERI'!$B$14)^27)/(1-'1 - I TUOI 6 NUMERI'!$B$15*(IF(O48<=0,0,MEDIAN(0,(O48-P48)/O48,1))))))-(IF(O48<=0,0,'1 - I TUOI 6 NUMERI'!$B$16*O48)))*(1+((1+0.03)*(1+'1 - I TUOI 6 NUMERI'!$B$14)-1))) | P49: =MAX(0,P48-(IF(O48<=0,0,(24000*(1+'1 - I TUOI 6 NUMERI'!$B$14)^27)/(1-'1 - I TUOI 6 NUMERI'!$B$15*(IF(O48<=0,0,MEDIAN(0,(O48-P48)/O48,1))))))*(1-(IF(O48<=0,0,MEDIAN(0,(O48-P48)/O48,1))))) | Q49: =IF(Q48<=0,0,(Q48-(IF(Q48<=0,0,(24000*(1+'1 - I TUOI 6 NUMERI'!$B$14)^27)/(1-'1 - I TUOI 6 NUMERI'!$B$15*(IF(Q48<=0,0,MEDIAN(0,(Q48-R48)/Q48,1))))))-(IF(Q48<=0,0,'1 - I TUOI 6 NUMERI'!$B$16*Q48)))*(1+((1+0.05)*(1+'1 - I TUOI 6 NUMERI'!$B$14)-1))) | R49: =MAX(0,R48-(IF(Q48<=0,0,(24000*(1+'1 - I TUOI 6 NUMERI'!$B$14)^27)/(1-'1 - I TUOI 6 NUMERI'!$B$15*(IF(Q48<=0,0,MEDIAN(0,(Q48-R48)/Q48,1))))))*(1-(IF(Q48<=0,0,MEDIAN(0,(Q48-R48)/Q48,1))))) | S49: =IF(S48<=0,0,(S48-(IF(S48<=0,0,(30000*(1+'1 - I TUOI 6 NUMERI'!$B$14)^27)/(1-'1 - I TUOI 6 NUMERI'!$B$15*(IF(S48<=0,0,MEDIAN(0,(S48-T48)/S48,1))))))-(IF(S48<=0,0,'1 - I TUOI 6 NUMERI'!$B$16*S48)))*(1+((1+0.01)*(1+'1 - I TUOI 6 NUMERI'!$B$14)-1))) | T49: =MAX(0,T48-(IF(S48<=0,0,(30000*(1+'1 - I TUOI 6 NUMERI'!$B$14)^27)/(1-'1 - I TUOI 6 NUMERI'!$B$15*(IF(S48<=0,0,MEDIAN(0,(S48-T48)/S48,1))))))*(1-(IF(S48<=0,0,MEDIAN(0,(S48-T48)/S48,1))))) | U49: =IF(U48<=0,0,(U48-(IF(U48<=0,0,(30000*(1+'1 - I TUOI 6 NUMERI'!$B$14)^27)/(1-'1 - I TUOI 6 NUMERI'!$B$15*(IF(U48<=0,0,MEDIAN(0,(U48-V48)/U48,1))))))-(IF(U48<=0,0,'1 - I TUOI 6 NUMERI'!$B$16*U48)))*(1+((1+0.03)*(1+'1 - I TUOI 6 NUMERI'!$B$14)-1))) | V49: =MAX(0,V48-(IF(U48<=0,0,(30000*(1+'1 - I TUOI 6 NUMERI'!$B$14)^27)/(1-'1 - I TUOI 6 NUMERI'!$B$15*(IF(U48<=0,0,MEDIAN(0,(U48-V48)/U48,1))))))*(1-(IF(U48<=0,0,MEDIAN(0,(U48-V48)/U48,1))))) | W49: =IF(W48<=0,0,(W48-(IF(W48<=0,0,(30000*(1+'1 - I TUOI 6 NUMERI'!$B$14)^27)/(1-'1 - I TUOI 6 NUMERI'!$B$15*(IF(W48<=0,0,MEDIAN(0,(W48-X48)/W48,1))))))-(IF(W48<=0,0,'1 - I TUOI 6 NUMERI'!$B$16*W48)))*(1+((1+0.05)*(1+'1 - I TUOI 6 NUMERI'!$B$14)-1))) | X49: =MAX(0,X48-(IF(W48<=0,0,(30000*(1+'1 - I TUOI 6 NUMERI'!$B$14)^27)/(1-'1 - I TUOI 6 NUMERI'!$B$15*(IF(W48<=0,0,MEDIAN(0,(W48-X48)/W48,1))))))*(1-(IF(W48<=0,0,MEDIAN(0,(W48-X48)/W48,1))))) | Y49: =IF(Y48<=0,0,(Y48-(IF(Y48<=0,0,(36000*(1+'1 - I TUOI 6 NUMERI'!$B$14)^27)/(1-'1 - I TUOI 6 NUMERI'!$B$15*(IF(Y48<=0,0,MEDIAN(0,(Y48-Z48)/Y48,1))))))-(IF(Y48<=0,0,'1 - I TUOI 6 NUMERI'!$B$16*Y48)))*(1+((1+0.01)*(1+'1 - I TUOI 6 NUMERI'!$B$14)-1))) | Z49: =MAX(0,Z48-(IF(Y48<=0,0,(36000*(1+'1 - I TUOI 6 NUMERI'!$B$14)^27)/(1-'1 - I TUOI 6 NUMERI'!$B$15*(IF(Y48<=0,0,MEDIAN(0,(Y48-Z48)/Y48,1))))))*(1-(IF(Y48<=0,0,MEDIAN(0,(Y48-Z48)/Y48,1))))) | AA49: =IF(AA48<=0,0,(AA48-(IF(AA48<=0,0,(36000*(1+'1 - I TUOI 6 NUMERI'!$B$14)^27)/(1-'1 - I TUOI 6 NUMERI'!$B$15*(IF(AA48<=0,0,MEDIAN(0,(AA48-AB48)/AA48,1))))))-(IF(AA48<=0,0,'1 - I TUOI 6 NUMERI'!$B$16*AA48)))*(1+((1+0.03)*(1+'1 - I TUOI 6 NUMERI'!$B$14)-1))) | AB49: =MAX(0,AB48-(IF(AA48<=0,0,(36000*(1+'1 - I TUOI 6 NUMERI'!$B$14)^27)/(1-'1 - I TUOI 6 NUMERI'!$B$15*(IF(AA48<=0,0,MEDIAN(0,(AA48-AB48)/AA48,1))))))*(1-(IF(AA48<=0,0,MEDIAN(0,(AA48-AB48)/AA48,1))))) | AC49: =IF(AC48<=0,0,(AC48-(IF(AC48<=0,0,(36000*(1+'1 - I TUOI 6 NUMERI'!$B$14)^27)/(1-'1 - I TUOI 6 NUMERI'!$B$15*(IF(AC48<=0,0,MEDIAN(0,(AC48-AD48)/AC48,1))))))-(IF(AC48<=0,0,'1 - I TUOI 6 NUMERI'!$B$16*AC48)))*(1+((1+0.05)*(1+'1 - I TUOI 6 NUMERI'!$B$14)-1))) | AD49: =MAX(0,AD48-(IF(AC48<=0,0,(36000*(1+'1 - I TUOI 6 NUMERI'!$B$14)^27)/(1-'1 - I TUOI 6 NUMERI'!$B$15*(IF(AC48<=0,0,MEDIAN(0,(AC48-AD48)/AC48,1))))))*(1-(IF(AC48<=0,0,MEDIAN(0,(AC48-AD48)/AC48,1)))))
F50: 28 | G50: =IF(G49<=0,0,(G49-(IF(G49<=0,0,(18000*(1+'1 - I TUOI 6 NUMERI'!$B$14)^28)/(1-'1 - I TUOI 6 NUMERI'!$B$15*(IF(G49<=0,0,MEDIAN(0,(G49-H49)/G49,1))))))-(IF(G49<=0,0,'1 - I TUOI 6 NUMERI'!$B$16*G49)))*(1+((1+0.01)*(1+'1 - I TUOI 6 NUMERI'!$B$14)-1))) | H50: =MAX(0,H49-(IF(G49<=0,0,(18000*(1+'1 - I TUOI 6 NUMERI'!$B$14)^28)/(1-'1 - I TUOI 6 NUMERI'!$B$15*(IF(G49<=0,0,MEDIAN(0,(G49-H49)/G49,1))))))*(1-(IF(G49<=0,0,MEDIAN(0,(G49-H49)/G49,1))))) | I50: =IF(I49<=0,0,(I49-(IF(I49<=0,0,(18000*(1+'1 - I TUOI 6 NUMERI'!$B$14)^28)/(1-'1 - I TUOI 6 NUMERI'!$B$15*(IF(I49<=0,0,MEDIAN(0,(I49-J49)/I49,1))))))-(IF(I49<=0,0,'1 - I TUOI 6 NUMERI'!$B$16*I49)))*(1+((1+0.03)*(1+'1 - I TUOI 6 NUMERI'!$B$14)-1))) | J50: =MAX(0,J49-(IF(I49<=0,0,(18000*(1+'1 - I TUOI 6 NUMERI'!$B$14)^28)/(1-'1 - I TUOI 6 NUMERI'!$B$15*(IF(I49<=0,0,MEDIAN(0,(I49-J49)/I49,1))))))*(1-(IF(I49<=0,0,MEDIAN(0,(I49-J49)/I49,1))))) | K50: =IF(K49<=0,0,(K49-(IF(K49<=0,0,(18000*(1+'1 - I TUOI 6 NUMERI'!$B$14)^28)/(1-'1 - I TUOI 6 NUMERI'!$B$15*(IF(K49<=0,0,MEDIAN(0,(K49-L49)/K49,1))))))-(IF(K49<=0,0,'1 - I TUOI 6 NUMERI'!$B$16*K49)))*(1+((1+0.05)*(1+'1 - I TUOI 6 NUMERI'!$B$14)-1))) | L50: =MAX(0,L49-(IF(K49<=0,0,(18000*(1+'1 - I TUOI 6 NUMERI'!$B$14)^28)/(1-'1 - I TUOI 6 NUMERI'!$B$15*(IF(K49<=0,0,MEDIAN(0,(K49-L49)/K49,1))))))*(1-(IF(K49<=0,0,MEDIAN(0,(K49-L49)/K49,1))))) | M50: =IF(M49<=0,0,(M49-(IF(M49<=0,0,(24000*(1+'1 - I TUOI 6 NUMERI'!$B$14)^28)/(1-'1 - I TUOI 6 NUMERI'!$B$15*(IF(M49<=0,0,MEDIAN(0,(M49-N49)/M49,1))))))-(IF(M49<=0,0,'1 - I TUOI 6 NUMERI'!$B$16*M49)))*(1+((1+0.01)*(1+'1 - I TUOI 6 NUMERI'!$B$14)-1))) | N50: =MAX(0,N49-(IF(M49<=0,0,(24000*(1+'1 - I TUOI 6 NUMERI'!$B$14)^28)/(1-'1 - I TUOI 6 NUMERI'!$B$15*(IF(M49<=0,0,MEDIAN(0,(M49-N49)/M49,1))))))*(1-(IF(M49<=0,0,MEDIAN(0,(M49-N49)/M49,1))))) | O50: =IF(O49<=0,0,(O49-(IF(O49<=0,0,(24000*(1+'1 - I TUOI 6 NUMERI'!$B$14)^28)/(1-'1 - I TUOI 6 NUMERI'!$B$15*(IF(O49<=0,0,MEDIAN(0,(O49-P49)/O49,1))))))-(IF(O49<=0,0,'1 - I TUOI 6 NUMERI'!$B$16*O49)))*(1+((1+0.03)*(1+'1 - I TUOI 6 NUMERI'!$B$14)-1))) | P50: =MAX(0,P49-(IF(O49<=0,0,(24000*(1+'1 - I TUOI 6 NUMERI'!$B$14)^28)/(1-'1 - I TUOI 6 NUMERI'!$B$15*(IF(O49<=0,0,MEDIAN(0,(O49-P49)/O49,1))))))*(1-(IF(O49<=0,0,MEDIAN(0,(O49-P49)/O49,1))))) | Q50: =IF(Q49<=0,0,(Q49-(IF(Q49<=0,0,(24000*(1+'1 - I TUOI 6 NUMERI'!$B$14)^28)/(1-'1 - I TUOI 6 NUMERI'!$B$15*(IF(Q49<=0,0,MEDIAN(0,(Q49-R49)/Q49,1))))))-(IF(Q49<=0,0,'1 - I TUOI 6 NUMERI'!$B$16*Q49)))*(1+((1+0.05)*(1+'1 - I TUOI 6 NUMERI'!$B$14)-1))) | R50: =MAX(0,R49-(IF(Q49<=0,0,(24000*(1+'1 - I TUOI 6 NUMERI'!$B$14)^28)/(1-'1 - I TUOI 6 NUMERI'!$B$15*(IF(Q49<=0,0,MEDIAN(0,(Q49-R49)/Q49,1))))))*(1-(IF(Q49<=0,0,MEDIAN(0,(Q49-R49)/Q49,1))))) | S50: =IF(S49<=0,0,(S49-(IF(S49<=0,0,(30000*(1+'1 - I TUOI 6 NUMERI'!$B$14)^28)/(1-'1 - I TUOI 6 NUMERI'!$B$15*(IF(S49<=0,0,MEDIAN(0,(S49-T49)/S49,1))))))-(IF(S49<=0,0,'1 - I TUOI 6 NUMERI'!$B$16*S49)))*(1+((1+0.01)*(1+'1 - I TUOI 6 NUMERI'!$B$14)-1))) | T50: =MAX(0,T49-(IF(S49<=0,0,(30000*(1+'1 - I TUOI 6 NUMERI'!$B$14)^28)/(1-'1 - I TUOI 6 NUMERI'!$B$15*(IF(S49<=0,0,MEDIAN(0,(S49-T49)/S49,1))))))*(1-(IF(S49<=0,0,MEDIAN(0,(S49-T49)/S49,1))))) | U50: =IF(U49<=0,0,(U49-(IF(U49<=0,0,(30000*(1+'1 - I TUOI 6 NUMERI'!$B$14)^28)/(1-'1 - I TUOI 6 NUMERI'!$B$15*(IF(U49<=0,0,MEDIAN(0,(U49-V49)/U49,1))))))-(IF(U49<=0,0,'1 - I TUOI 6 NUMERI'!$B$16*U49)))*(1+((1+0.03)*(1+'1 - I TUOI 6 NUMERI'!$B$14)-1))) | V50: =MAX(0,V49-(IF(U49<=0,0,(30000*(1+'1 - I TUOI 6 NUMERI'!$B$14)^28)/(1-'1 - I TUOI 6 NUMERI'!$B$15*(IF(U49<=0,0,MEDIAN(0,(U49-V49)/U49,1))))))*(1-(IF(U49<=0,0,MEDIAN(0,(U49-V49)/U49,1))))) | W50: =IF(W49<=0,0,(W49-(IF(W49<=0,0,(30000*(1+'1 - I TUOI 6 NUMERI'!$B$14)^28)/(1-'1 - I TUOI 6 NUMERI'!$B$15*(IF(W49<=0,0,MEDIAN(0,(W49-X49)/W49,1))))))-(IF(W49<=0,0,'1 - I TUOI 6 NUMERI'!$B$16*W49)))*(1+((1+0.05)*(1+'1 - I TUOI 6 NUMERI'!$B$14)-1))) | X50: =MAX(0,X49-(IF(W49<=0,0,(30000*(1+'1 - I TUOI 6 NUMERI'!$B$14)^28)/(1-'1 - I TUOI 6 NUMERI'!$B$15*(IF(W49<=0,0,MEDIAN(0,(W49-X49)/W49,1))))))*(1-(IF(W49<=0,0,MEDIAN(0,(W49-X49)/W49,1))))) | Y50: =IF(Y49<=0,0,(Y49-(IF(Y49<=0,0,(36000*(1+'1 - I TUOI 6 NUMERI'!$B$14)^28)/(1-'1 - I TUOI 6 NUMERI'!$B$15*(IF(Y49<=0,0,MEDIAN(0,(Y49-Z49)/Y49,1))))))-(IF(Y49<=0,0,'1 - I TUOI 6 NUMERI'!$B$16*Y49)))*(1+((1+0.01)*(1+'1 - I TUOI 6 NUMERI'!$B$14)-1))) | Z50: =MAX(0,Z49-(IF(Y49<=0,0,(36000*(1+'1 - I TUOI 6 NUMERI'!$B$14)^28)/(1-'1 - I TUOI 6 NUMERI'!$B$15*(IF(Y49<=0,0,MEDIAN(0,(Y49-Z49)/Y49,1))))))*(1-(IF(Y49<=0,0,MEDIAN(0,(Y49-Z49)/Y49,1))))) | AA50: =IF(AA49<=0,0,(AA49-(IF(AA49<=0,0,(36000*(1+'1 - I TUOI 6 NUMERI'!$B$14)^28)/(1-'1 - I TUOI 6 NUMERI'!$B$15*(IF(AA49<=0,0,MEDIAN(0,(AA49-AB49)/AA49,1))))))-(IF(AA49<=0,0,'1 - I TUOI 6 NUMERI'!$B$16*AA49)))*(1+((1+0.03)*(1+'1 - I TUOI 6 NUMERI'!$B$14)-1))) | AB50: =MAX(0,AB49-(IF(AA49<=0,0,(36000*(1+'1 - I TUOI 6 NUMERI'!$B$14)^28)/(1-'1 - I TUOI 6 NUMERI'!$B$15*(IF(AA49<=0,0,MEDIAN(0,(AA49-AB49)/AA49,1))))))*(1-(IF(AA49<=0,0,MEDIAN(0,(AA49-AB49)/AA49,1))))) | AC50: =IF(AC49<=0,0,(AC49-(IF(AC49<=0,0,(36000*(1+'1 - I TUOI 6 NUMERI'!$B$14)^28)/(1-'1 - I TUOI 6 NUMERI'!$B$15*(IF(AC49<=0,0,MEDIAN(0,(AC49-AD49)/AC49,1))))))-(IF(AC49<=0,0,'1 - I TUOI 6 NUMERI'!$B$16*AC49)))*(1+((1+0.05)*(1+'1 - I TUOI 6 NUMERI'!$B$14)-1))) | AD50: =MAX(0,AD49-(IF(AC49<=0,0,(36000*(1+'1 - I TUOI 6 NUMERI'!$B$14)^28)/(1-'1 - I TUOI 6 NUMERI'!$B$15*(IF(AC49<=0,0,MEDIAN(0,(AC49-AD49)/AC49,1))))))*(1-(IF(AC49<=0,0,MEDIAN(0,(AC49-AD49)/AC49,1)))))
F51: 29 | G51: =IF(G50<=0,0,(G50-(IF(G50<=0,0,(18000*(1+'1 - I TUOI 6 NUMERI'!$B$14)^29)/(1-'1 - I TUOI 6 NUMERI'!$B$15*(IF(G50<=0,0,MEDIAN(0,(G50-H50)/G50,1))))))-(IF(G50<=0,0,'1 - I TUOI 6 NUMERI'!$B$16*G50)))*(1+((1+0.01)*(1+'1 - I TUOI 6 NUMERI'!$B$14)-1))) | H51: =MAX(0,H50-(IF(G50<=0,0,(18000*(1+'1 - I TUOI 6 NUMERI'!$B$14)^29)/(1-'1 - I TUOI 6 NUMERI'!$B$15*(IF(G50<=0,0,MEDIAN(0,(G50-H50)/G50,1))))))*(1-(IF(G50<=0,0,MEDIAN(0,(G50-H50)/G50,1))))) | I51: =IF(I50<=0,0,(I50-(IF(I50<=0,0,(18000*(1+'1 - I TUOI 6 NUMERI'!$B$14)^29)/(1-'1 - I TUOI 6 NUMERI'!$B$15*(IF(I50<=0,0,MEDIAN(0,(I50-J50)/I50,1))))))-(IF(I50<=0,0,'1 - I TUOI 6 NUMERI'!$B$16*I50)))*(1+((1+0.03)*(1+'1 - I TUOI 6 NUMERI'!$B$14)-1))) | J51: =MAX(0,J50-(IF(I50<=0,0,(18000*(1+'1 - I TUOI 6 NUMERI'!$B$14)^29)/(1-'1 - I TUOI 6 NUMERI'!$B$15*(IF(I50<=0,0,MEDIAN(0,(I50-J50)/I50,1))))))*(1-(IF(I50<=0,0,MEDIAN(0,(I50-J50)/I50,1))))) | K51: =IF(K50<=0,0,(K50-(IF(K50<=0,0,(18000*(1+'1 - I TUOI 6 NUMERI'!$B$14)^29)/(1-'1 - I TUOI 6 NUMERI'!$B$15*(IF(K50<=0,0,MEDIAN(0,(K50-L50)/K50,1))))))-(IF(K50<=0,0,'1 - I TUOI 6 NUMERI'!$B$16*K50)))*(1+((1+0.05)*(1+'1 - I TUOI 6 NUMERI'!$B$14)-1))) | L51: =MAX(0,L50-(IF(K50<=0,0,(18000*(1+'1 - I TUOI 6 NUMERI'!$B$14)^29)/(1-'1 - I TUOI 6 NUMERI'!$B$15*(IF(K50<=0,0,MEDIAN(0,(K50-L50)/K50,1))))))*(1-(IF(K50<=0,0,MEDIAN(0,(K50-L50)/K50,1))))) | M51: =IF(M50<=0,0,(M50-(IF(M50<=0,0,(24000*(1+'1 - I TUOI 6 NUMERI'!$B$14)^29)/(1-'1 - I TUOI 6 NUMERI'!$B$15*(IF(M50<=0,0,MEDIAN(0,(M50-N50)/M50,1))))))-(IF(M50<=0,0,'1 - I TUOI 6 NUMERI'!$B$16*M50)))*(1+((1+0.01)*(1+'1 - I TUOI 6 NUMERI'!$B$14)-1))) | N51: =MAX(0,N50-(IF(M50<=0,0,(24000*(1+'1 - I TUOI 6 NUMERI'!$B$14)^29)/(1-'1 - I TUOI 6 NUMERI'!$B$15*(IF(M50<=0,0,MEDIAN(0,(M50-N50)/M50,1))))))*(1-(IF(M50<=0,0,MEDIAN(0,(M50-N50)/M50,1))))) | O51: =IF(O50<=0,0,(O50-(IF(O50<=0,0,(24000*(1+'1 - I TUOI 6 NUMERI'!$B$14)^29)/(1-'1 - I TUOI 6 NUMERI'!$B$15*(IF(O50<=0,0,MEDIAN(0,(O50-P50)/O50,1))))))-(IF(O50<=0,0,'1 - I TUOI 6 NUMERI'!$B$16*O50)))*(1+((1+0.03)*(1+'1 - I TUOI 6 NUMERI'!$B$14)-1))) | P51: =MAX(0,P50-(IF(O50<=0,0,(24000*(1+'1 - I TUOI 6 NUMERI'!$B$14)^29)/(1-'1 - I TUOI 6 NUMERI'!$B$15*(IF(O50<=0,0,MEDIAN(0,(O50-P50)/O50,1))))))*(1-(IF(O50<=0,0,MEDIAN(0,(O50-P50)/O50,1))))) | Q51: =IF(Q50<=0,0,(Q50-(IF(Q50<=0,0,(24000*(1+'1 - I TUOI 6 NUMERI'!$B$14)^29)/(1-'1 - I TUOI 6 NUMERI'!$B$15*(IF(Q50<=0,0,MEDIAN(0,(Q50-R50)/Q50,1))))))-(IF(Q50<=0,0,'1 - I TUOI 6 NUMERI'!$B$16*Q50)))*(1+((1+0.05)*(1+'1 - I TUOI 6 NUMERI'!$B$14)-1))) | R51: =MAX(0,R50-(IF(Q50<=0,0,(24000*(1+'1 - I TUOI 6 NUMERI'!$B$14)^29)/(1-'1 - I TUOI 6 NUMERI'!$B$15*(IF(Q50<=0,0,MEDIAN(0,(Q50-R50)/Q50,1))))))*(1-(IF(Q50<=0,0,MEDIAN(0,(Q50-R50)/Q50,1))))) | S51: =IF(S50<=0,0,(S50-(IF(S50<=0,0,(30000*(1+'1 - I TUOI 6 NUMERI'!$B$14)^29)/(1-'1 - I TUOI 6 NUMERI'!$B$15*(IF(S50<=0,0,MEDIAN(0,(S50-T50)/S50,1))))))-(IF(S50<=0,0,'1 - I TUOI 6 NUMERI'!$B$16*S50)))*(1+((1+0.01)*(1+'1 - I TUOI 6 NUMERI'!$B$14)-1))) | T51: =MAX(0,T50-(IF(S50<=0,0,(30000*(1+'1 - I TUOI 6 NUMERI'!$B$14)^29)/(1-'1 - I TUOI 6 NUMERI'!$B$15*(IF(S50<=0,0,MEDIAN(0,(S50-T50)/S50,1))))))*(1-(IF(S50<=0,0,MEDIAN(0,(S50-T50)/S50,1))))) | U51: =IF(U50<=0,0,(U50-(IF(U50<=0,0,(30000*(1+'1 - I TUOI 6 NUMERI'!$B$14)^29)/(1-'1 - I TUOI 6 NUMERI'!$B$15*(IF(U50<=0,0,MEDIAN(0,(U50-V50)/U50,1))))))-(IF(U50<=0,0,'1 - I TUOI 6 NUMERI'!$B$16*U50)))*(1+((1+0.03)*(1+'1 - I TUOI 6 NUMERI'!$B$14)-1))) | V51: =MAX(0,V50-(IF(U50<=0,0,(30000*(1+'1 - I TUOI 6 NUMERI'!$B$14)^29)/(1-'1 - I TUOI 6 NUMERI'!$B$15*(IF(U50<=0,0,MEDIAN(0,(U50-V50)/U50,1))))))*(1-(IF(U50<=0,0,MEDIAN(0,(U50-V50)/U50,1))))) | W51: =IF(W50<=0,0,(W50-(IF(W50<=0,0,(30000*(1+'1 - I TUOI 6 NUMERI'!$B$14)^29)/(1-'1 - I TUOI 6 NUMERI'!$B$15*(IF(W50<=0,0,MEDIAN(0,(W50-X50)/W50,1))))))-(IF(W50<=0,0,'1 - I TUOI 6 NUMERI'!$B$16*W50)))*(1+((1+0.05)*(1+'1 - I TUOI 6 NUMERI'!$B$14)-1))) | X51: =MAX(0,X50-(IF(W50<=0,0,(30000*(1+'1 - I TUOI 6 NUMERI'!$B$14)^29)/(1-'1 - I TUOI 6 NUMERI'!$B$15*(IF(W50<=0,0,MEDIAN(0,(W50-X50)/W50,1))))))*(1-(IF(W50<=0,0,MEDIAN(0,(W50-X50)/W50,1))))) | Y51: =IF(Y50<=0,0,(Y50-(IF(Y50<=0,0,(36000*(1+'1 - I TUOI 6 NUMERI'!$B$14)^29)/(1-'1 - I TUOI 6 NUMERI'!$B$15*(IF(Y50<=0,0,MEDIAN(0,(Y50-Z50)/Y50,1))))))-(IF(Y50<=0,0,'1 - I TUOI 6 NUMERI'!$B$16*Y50)))*(1+((1+0.01)*(1+'1 - I TUOI 6 NUMERI'!$B$14)-1))) | Z51: =MAX(0,Z50-(IF(Y50<=0,0,(36000*(1+'1 - I TUOI 6 NUMERI'!$B$14)^29)/(1-'1 - I TUOI 6 NUMERI'!$B$15*(IF(Y50<=0,0,MEDIAN(0,(Y50-Z50)/Y50,1))))))*(1-(IF(Y50<=0,0,MEDIAN(0,(Y50-Z50)/Y50,1))))) | AA51: =IF(AA50<=0,0,(AA50-(IF(AA50<=0,0,(36000*(1+'1 - I TUOI 6 NUMERI'!$B$14)^29)/(1-'1 - I TUOI 6 NUMERI'!$B$15*(IF(AA50<=0,0,MEDIAN(0,(AA50-AB50)/AA50,1))))))-(IF(AA50<=0,0,'1 - I TUOI 6 NUMERI'!$B$16*AA50)))*(1+((1+0.03)*(1+'1 - I TUOI 6 NUMERI'!$B$14)-1))) | AB51: =MAX(0,AB50-(IF(AA50<=0,0,(36000*(1+'1 - I TUOI 6 NUMERI'!$B$14)^29)/(1-'1 - I TUOI 6 NUMERI'!$B$15*(IF(AA50<=0,0,MEDIAN(0,(AA50-AB50)/AA50,1))))))*(1-(IF(AA50<=0,0,MEDIAN(0,(AA50-AB50)/AA50,1))))) | AC51: =IF(AC50<=0,0,(AC50-(IF(AC50<=0,0,(36000*(1+'1 - I TUOI 6 NUMERI'!$B$14)^29)/(1-'1 - I TUOI 6 NUMERI'!$B$15*(IF(AC50<=0,0,MEDIAN(0,(AC50-AD50)/AC50,1))))))-(IF(AC50<=0,0,'1 - I TUOI 6 NUMERI'!$B$16*AC50)))*(1+((1+0.05)*(1+'1 - I TUOI 6 NUMERI'!$B$14)-1))) | AD51: =MAX(0,AD50-(IF(AC50<=0,0,(36000*(1+'1 - I TUOI 6 NUMERI'!$B$14)^29)/(1-'1 - I TUOI 6 NUMERI'!$B$15*(IF(AC50<=0,0,MEDIAN(0,(AC50-AD50)/AC50,1))))))*(1-(IF(AC50<=0,0,MEDIAN(0,(AC50-AD50)/AC50,1)))))
