Workbook
Name Aliq: '1 - Parametri'!$B$30
Name Aliq_eff: '1 - Parametri'!$B$39
Name Alt_pens1: '4 - Fisco e pensione'!$C$13
Name Alt_pens2: '4 - Fisco e pensione'!$C$14
Name Alt_pens3: '4 - Fisco e pensione'!$C$15
Name Anni: '1 - Parametri'!$B$44
Name Anni_ipotesi: '1 - Parametri'!$B$48
Name Anni_osservati: '1 - Parametri'!$B$47
Name Anno_inizio: '1 - Parametri'!$B$15
Name Anno_pens: '1 - Parametri'!$B$35
Name Bollo: '1 - Parametri'!$B$31
Name Bollo_anno1: '4 - Fisco e pensione'!$B$20
Name Bollo_eff: '1 - Parametri'!$B$40
Name Cap_con_pens: '4 - Fisco e pensione'!$B$7
Name Cap_diff: '4 - Fisco e pensione'!$B$8
Name Cap_senza_pens: '4 - Fisco e pensione'!$B$6
Name Durata_testo: '1 - Parametri'!$B$45
Name Eta_fine: '1 - Parametri'!$B$11
Name Eta_inizio: '1 - Parametri'!$B$10
Name Eta_rif_VPW: '1 - Parametri'!$B$19
Name GK_banda: '1 - Parametri'!$B$22
Name GK_taglio: '1 - Parametri'!$B$23
Name GK_ultimi: '1 - Parametri'!$B$24
Name GK_variante: '1 - Parametri'!$B$21
Name Imposta_anno1: '4 - Fisco e pensione'!$B$19
Name Infl_c: '1 - Parametri'!$B$17
Name Lat_anno_pens: '4 - Fisco e pensione'!$B$33
Name Lat_anno1: '4 - Fisco e pensione'!$B$32
Name Lat_ponte2: '1 - Parametri'!$B$37
Name Lat_ultimo: '4 - Fisco e pensione'!$B$34
Name Latente_eff: '1 - Parametri'!$B$41
Name Latente0: '1 - Parametri'!$B$29
Name Mese_pens: '1 - Parametri'!$B$34
Name Mesi_ultimo: '1 - Parametri'!$B$12
Name Modalita: '1 - Parametri'!$B$6
Name Patrimonio: '1 - Parametri'!$B$7
Name Pav_pct: '1 - Parametri'!$B$27
Name Pens_eta_testo: '1 - Parametri'!$B$46
Name Pens_mesi_req: '1 - Parametri'!$B$36
Name Pensione: '1 - Parametri'!$B$33
Name Ponte_L: '4 - Fisco e pensione'!$C$41
Name Ponte_M: '4 - Fisco e pensione'!$C$42
Name Ponte_N: '4 - Fisco e pensione'!$C$43
Name r_VPW: '1 - Parametri'!$B$20
Name Rend_c: '1 - Parametri'!$B$16
Name Serie: '1 - Parametri'!$B$14
Name Spesa_netta: '1 - Parametri'!$B$9
Name Spesa0: '1 - Parametri'!$B$42
Name Tasso: '1 - Parametri'!$B$8
Name Tasso_con_bollo: '4 - Fisco e pensione'!$B$23
Name Tasso_lordo_eq: '4 - Fisco e pensione'!$B$22
Name Tasso0: '1 - Parametri'!$B$43
Name Uscita_anno1: '4 - Fisco e pensione'!$B$21
Name Venduto_anno1: '4 - Fisco e pensione'!$B$18
Name VG_pav: '1 - Parametri'!$B$26
Name VG_tetto: '1 - Parametri'!$B$25

Sheet 0 - Indice
A1: Regole di prelievo: quanto posso spendere quest'anno? (caso inventato e illustrativo)
A2: Strumento informativo / divulgativo. NON è consulenza finanziaria. I valori sono indicativi al 2026 e vanno verificati col tuo consulente.
A4: Indice
A5: 0 - Indice | B5: Questo indice
A6: 1 - Parametri | B6: I tuoi dati (celle gialle) e la sintesi per regola
A7: 2 - Sequenza storica | B7: Le sei regole su una sequenza storica, anno per anno
A8: 3 - Rendimento costante | B8: Le stesse sei regole con rendimento costante
A9: 4 - Fisco e pensione | B9: Fisco, plusvalenza latente, pensione e ponte
A10: 5 - Dati | B10: Serie annuali e tabella di controllo della percentuale variabile
A12: Come usare
A13: 1. Le celle GIALLE sono input — modificale coi tuoi numeri.
A14: 2. Le celle VERDI sono output — si aggiornano automaticamente.
A15: 3. Tutti i numeri di default sono al 2026 da fonti pubbliche.
A16: 4. Niente codice nascosto: l'Excel è solo formule modificabili.
A18: Fonti dati
A19: • Primo studio sul quattro per cento: Bengen, Journal of Financial Planning, ottobre 1994
A20: • Regola dei guardrail: Guyton e Klinger, Journal of Financial Planning, marzo 2006 (qui senza il tetto del 6% all'inflazione)
A21: • Regole con pavimento e con tetto e pavimento: Morningstar, State of Retirement Income 2025 (3/12/2025)
A22: • Tabella della percentuale variabile: wiki Bogleheads, «Variable percentage withdrawal»
A23: • Serie USA dal 1871: Shiller. Serie in euro: indice azionario mondiale (rendimento netto), titolo di Stato tedesco a 10 anni, inflazione armonizzata italiana (HICP)
A24: • Pensione: Ragioneria generale dello Stato, Le tendenze di medio-lungo periodo, rapporto n. 27 (22/09/2026)
... A34: Il motore del calcolo è in fondo ai fogli 2, 3 e 4: non modificare. Nessuna macro, solo formule.

Sheet 1 - Parametri
A1: 1 - Parametri: le celle gialle sono i tuoi dati
A2: Strumento informativo / divulgativo. NON è consulenza finanziaria. I valori sono indicativi al 2026 e vanno verificati col tuo consulente.
A3: Il caso di default è Corrado, inventato e illustrativo: 51 anni, 1.056.000 € in un portafoglio 60/40, casa senza mutuo, 38.000 € netti l'anno fino a 93 anni. Importi in euro di oggi (reali). Il foglio 2 usa una sequenza storica, il foglio 3 un rendimento costante.
A5: Modalità e caso
A6: Modalità (lordo / tassato) | B6: tassato | C6: Lordo = backtest di distribuzione: la regola decide il venduto, nessuna imposta. Tassato = caso Corrado: la regola decide la spesa netta, in cassa.
A7: Patrimonio iniziale (€) | B7: 1056000 | C7: Valore di mercato a inizio piano, in euro di oggi.
A8: Tasso di prelievo iniziale (solo modalità lordo) | B8: 0.04 | C8: Spesa iniziale lorda = patrimonio × tasso: 42.240 € con i default.
A9: Spesa netta annua (solo modalità tassato) (€) | B9: 38000 | C9: Quanto vuoi avere in cassa ogni anno, in euro di oggi.
A10: Età a inizio piano (anni) | B10: 51 | C10: Età all'inizio del primo anno di prelievi.
A11: Età a fine piano (anni) | B11: 93 | C11: La durata del piano è età finale meno età iniziale (massimo 59 anni).
A12: Mesi dell'ultimo anno del piano | B12: 2 | C12: Con 93 anni al 15/03/2068 l'ultimo anno ha 2 mesi. Con 12 il piano è di 42 anni pieni (usato nei vettori di prova).
A13: Sequenza dei rendimenti
A14: Serie storica (EUR / USA) | B14: EUR | C14: EUR: partenze 2000-2025. USA: partenze 1871-2025. Oltre l'ultimo dato la sequenza prosegue al rendimento costante.
A15: Anno di partenza della sequenza (gennaio) | B15: 2000 | C15: Prova 2007 o 2010 per vedere un altro inizio; un anno senza dati dà il rendimento costante per tutto il piano.
A16: Rendimento reale costante | B16: 0.03 | C16: Ipotesi al canone: usata nel foglio 3 e dopo l'ultimo dato storico.
A17: Inflazione costante | B17: 0.02 | C17: Ipotesi al canone.
A18: Parametri delle regole
A19: Percentuale variabile: età di esaurimento | B19: 100 | C19: L'età a cui la percentuale variabile porta il capitale a zero.
A20: Percentuale variabile: rendimento reale ipotizzato | B20: 0.03 | C20: Default 3% (canone). Alternativa 3,76% (tabella del 60/40 di una comunità di investitori americani).
A21: Guardrail: variante (1 = 2006, 2 = 2004, 3 = senza congelamento) | B21: 1 | C21: 1 = proposta del 2006 (non indicizza dopo un anno negativo solo se il tasso supererebbe l'iniziale). Qui senza il tetto del 6% all'inflazione degli autori.
A22: Guardrail: banda sul tasso iniziale | B22: 0.2 | C22: Se il tasso corrente esce da ±20% del tasso iniziale scatta la correzione.
A23: Guardrail: taglio o aumento | B23: 0.1 | C23: Correzione della spesa quando si esce dalla banda.
A24: Guardrail: anni finali senza taglio | B24: 15 | C24: Negli ultimi anni del piano il taglio è spento.
A25: Tetto e pavimento: massimo aumento annuo | B25: 0.05 | C25: La spesa non cresce più del 5% l'anno.
A26: Tetto e pavimento: massimo calo annuo | B26: -0.025 | C26: La spesa non cala più del 2,5% l'anno.
A27: Percentuale con pavimento: quota della spesa iniziale | B27: 0.9 | C27: Pavimento al 90% della spesa iniziale.
A28: Fisco
A29: Plusvalenza latente iniziale | B29: 0.43435582 | C29: 1 − base di costo / valore: 1 − 597.580 / 1.056.460 = 43,4% (valore pieno: con 0,434 le uscite divergono di più di 1 €).
A30: Aliquota sulla plusvalenza | B30: 0.26 | C30: Norma di oggi (nuovo testo unico fiscale, effetti dal 1/1/2027).
A31: Bollo annuo sul valore | B31: 0.002 | C31: 0,20% del valore a fine anno.
A32: Pensione (proiezione RGS n. 27, revisione centrale)
A33: Pensione netta annua (€) | B33: 30711.544 | C33: Proiezione della Ragioneria generale dello Stato, rapporto n. 27, in euro di oggi (valore pieno: 30.712 € mostrati). Alternative: 31.829 · 29.951 · 29.349 (ipotesi di scuola).
A34: Mese della prima rata nell'anno di pensione | B34: 10 | C34: Ottobre 2043: tre rate nel primo anno.
A35: Anno del piano in cui parte la pensione | B35: 17 | C35: Anno 17 del piano. Se superiore a 60 la pensione non entra nel calcolo.
A36: Requisito della pensione (mesi di età compiuti) | B36: 822 | C36: 822 mesi: vedi la lettura in anni e mesi qui sotto.
A37: Seconda ipotesi di plusvalenza latente per il ponte | B37: 0.6 | C37: Usata nel foglio 4.
A38: Derivati (formule)
A39: Aliquota effettiva | B39: =IF(Modalita="tassato",Aliq,0) -> 0.26 | C39: Zero in modalità lordo.
A40: Bollo effettivo | B40: =IF(Modalita="tassato",Bollo,0) -> 0.002 | C40: Zero in modalità lordo.
A41: Plusvalenza latente effettiva | B41: =IF(Modalita="tassato",Latente0,0) -> 0.43435582 | C41: Zero in modalità lordo.
A42: Spesa iniziale pianificata (€) | B42: =IF(Modalita="tassato",Spesa_netta,Patrimonio*Tasso) -> 38000 | C42: In modalità tassato è la spesa netta; in lordo è il venduto.
A43: Tasso di prelievo iniziale lordo equivalente | B43: =Spesa0/(Patrimonio*(1-Aliq_eff*Latente_eff)) -> 0.040566078 | C43: Spesa iniziale divisa per il patrimonio, al lordo dell'imposta sul venduto: 4,057% con i default.
A44: Anni del piano | B44: =Eta_fine-Eta_inizio -> 42 | C44: Con i default 42.
A45: Durata del piano | B45: =INT(((Anni-1)*12+Mesi_ultimo)/12)&" anni e "&MOD((Anni-1)*12+Mesi_ultimo,12)&" mesi" -> 41 anni e 2 mesi | C45: Anni pieni più i mesi dell'ultimo anno.
A46: Età alla prima rata di pensione | B46: =INT(Pens_mesi_req/12)&" anni e "&MOD(Pens_mesi_req,12)&" mesi" -> 68 anni e 6 mesi | C46: Requisito del caso: 68 anni e 6 mesi.
A47: Anni osservati nella sequenza (foglio 2) | B47: =SUMPRODUCT(('2 - Sequenza storica'!$A$71:$A$130<=Anni)*'2 - Sequenza storica'!$D$71:$D$130) -> 26 | C47: Anni con dati storici; gli altri sono ipotesi al canone.
A48: Anni di ipotesi al canone (foglio 2) | B48: =Anni-Anni_osservati -> 16 | C48: Da qui in poi non è storia, è un'ipotesi.
A50: Sintesi per regola: foglio 2 (sequenza storica, poi ipotesi al canone)
A51: Anno peggiore = sull'intero piano, storia più ipotesi; il video cita i soli anni di storia. Anni magri = anni con spesa sotto l'80% (o il 75%) della spesa desiderata, uguale per tutte le regole. «Anno di esaurimento»: primo anno in cui il capitale non basta; «no» se regge fino a fine piano. Capitale in euro di oggi.
A52: Regola | B52: Spesa anno 1 | C52: Mediana della spesa | D52: Anno peggiore (spesa minima) | E52: Anni magri (sotto l'80%) | F52: Anni sotto il 75% | G52: Variabilità annua (dev. standard) | H52: Capitale a fine piano | I52: Anno di esaurimento
A53: Fisso indicizzato | B53: ='2 - Sequenza storica'!D6 -> 38000 | C53: =MEDIAN('2 - Sequenza storica'!D$6:D$65) -> 38000 | D53: =MIN('2 - Sequenza storica'!D$6:D$65) -> 0 | E53: =COUNTIF('2 - Sequenza storica'!D$6:D$65,"<"&0.8*Spesa0) -> 13 | F53: =COUNTIF('2 - Sequenza storica'!D$6:D$65,"<"&0.75*Spesa0) -> 13 | G53: =IFERROR(STDEVP('2 - Sequenza storica'!AQ$72:AQ$130),"") -> 0.18310332 | H53: =INDEX('2 - Sequenza storica'!N$71:N$130,Anni+1) -> 0 | I53: =IFERROR(MATCH(1,INDEX('2 - Sequenza storica'!L$71:L$130,1):INDEX('2 - Sequenza storica'!L$71:L$130,Anni),0),"no") -> 29
A54: Percentuale costante | B54: ='2 - Sequenza storica'!E6 -> 38000 | C54: =MEDIAN('2 - Sequenza storica'!E$6:E$65) -> 23872.407 | D54: =MIN('2 - Sequenza storica'!E$6:E$65) -> 19562.99 | E54: =COUNTIF('2 - Sequenza storica'!E$6:E$65,"<"&0.8*Spesa0) -> 39 | F54: =COUNTIF('2 - Sequenza storica'!E$6:E$65,"<"&0.75*Spesa0) -> 37 | G54: =IFERROR(STDEVP('2 - Sequenza storica'!AR$72:AR$130),"") -> 0.072016441 | H54: =INDEX('2 - Sequenza storica'!S$71:S$130,Anni+1) -> 626056.22 | I54: =IFERROR(MATCH(1,INDEX('2 - Sequenza storica'!Q$71:Q$130,1):INDEX('2 - Sequenza storica'!Q$71:Q$130,Anni),0),"no") -> no
A55: Percentuale con pavimento | B55: ='2 - Sequenza storica'!F6 -> 38000 | C55: =MEDIAN('2 - Sequenza storica'!F$6:F$65) -> 34200 | D55: =MIN('2 - Sequenza storica'!F$6:F$65) -> 0 | E55: =COUNTIF('2 - Sequenza storica'!F$6:F$65,"<"&0.8*Spesa0) -> 8 | F55: =COUNTIF('2 - Sequenza storica'!F$6:F$65,"<"&0.75*Spesa0) -> 8 | G55: =IFERROR(STDEVP('2 - Sequenza storica'!AS$72:AS$130),"") -> 0.18934856 | H55: =INDEX('2 - Sequenza storica'!X$71:X$130,Anni+1) -> 0 | I55: =IFERROR(MATCH(1,INDEX('2 - Sequenza storica'!V$71:V$130,1):INDEX('2 - Sequenza storica'!V$71:V$130,Anni),0),"no") -> 35
A56: Percentuale variabile | B56: ='2 - Sequenza storica'!G6 -> 35662.76 | C56: =MEDIAN('2 - Sequenza storica'!G$6:G$65) -> 30412.151 | D56: =MIN('2 - Sequenza storica'!G$6:G$65) -> 21184.431 | E56: =COUNTIF('2 - Sequenza storica'!G$6:G$65,"<"&0.8*Spesa0) -> 21 | F56: =COUNTIF('2 - Sequenza storica'!G$6:G$65,"<"&0.75*Spesa0) -> 11 | G56: =IFERROR(STDEVP('2 - Sequenza storica'!AT$72:AT$130),"") -> 0.072875133 | H56: =INDEX('2 - Sequenza storica'!AD$71:AD$130,Anni+1) -> 251626.48 | I56: =IFERROR(MATCH(1,INDEX('2 - Sequenza storica'!AB$71:AB$130,1):INDEX('2 - Sequenza storica'!AB$71:AB$130,Anni),0),"no") -> no
A57: Guardrail (senza tetto all'inflazione) | B57: ='2 - Sequenza storica'!H6 -> 38000 | C57: =MEDIAN('2 - Sequenza storica'!H$6:H$65) -> 22666.716 | D57: =MIN('2 - Sequenza storica'!H$6:H$65) -> 20481.744 | E57: =COUNTIF('2 - Sequenza storica'!H$6:H$65,"<"&0.8*Spesa0) -> 38 | F57: =COUNTIF('2 - Sequenza storica'!H$6:H$65,"<"&0.75*Spesa0) -> 34 | G57: =IFERROR(STDEVP('2 - Sequenza storica'!AU$72:AU$130),"") -> 0.035110307 | H57: =INDEX('2 - Sequenza storica'!AK$71:AK$130,Anni+1) -> 667073.25 | I57: =IFERROR(MATCH(1,INDEX('2 - Sequenza storica'!AI$71:AI$130,1):INDEX('2 - Sequenza storica'!AI$71:AI$130,Anni),0),"no") -> no
A58: Tetto e pavimento (+5% / −2,5%) | B58: ='2 - Sequenza storica'!I6 -> 38000 | C58: =MEDIAN('2 - Sequenza storica'!I$6:I$65) -> 23014.333 | D58: =MIN('2 - Sequenza storica'!I$6:I$65) -> 15193.992 | E58: =COUNTIF('2 - Sequenza storica'!I$6:I$65,"<"&0.8*Spesa0) -> 33 | F58: =COUNTIF('2 - Sequenza storica'!I$6:I$65,"<"&0.75*Spesa0) -> 30 | G58: =IFERROR(STDEVP('2 - Sequenza storica'!AV$72:AV$130),"") -> 0.0087973987 | H58: =INDEX('2 - Sequenza storica'!AP$71:AP$130,Anni+1) -> 486239.23 | I58: =IFERROR(MATCH(1,INDEX('2 - Sequenza storica'!AN$71:AN$130,1):INDEX('2 - Sequenza storica'!AN$71:AN$130,Anni),0),"no") -> no
A60: Sintesi per regola: foglio 3 (rendimento costante)
A61: Stesse regole, con rendimento reale e inflazione costanti (celle gialle Rend_c e Infl_c): nessun dato storico, solo ipotesi.
A62: Regola | B62: Spesa anno 1 | C62: Mediana della spesa | D62: Anno peggiore (spesa minima) | E62: Anni magri (sotto l'80%) | F62: Anni sotto il 75% | G62: Variabilità annua (dev. standard) | H62: Capitale a fine piano | I62: Anno di esaurimento
A63: Fisso indicizzato | B63: ='3 - Rendimento costante'!D6 -> 38000 | C63: =MEDIAN('3 - Rendimento costante'!D$6:D$65) -> 38000 | D63: =MIN('3 - Rendimento costante'!D$6:D$65) -> 0 | E63: =COUNTIF('3 - Rendimento costante'!D$6:D$65,"<"&0.8*Spesa0) -> 7 | F63: =COUNTIF('3 - Rendimento costante'!D$6:D$65,"<"&0.75*Spesa0) -> 7 | G63: =IFERROR(STDEVP('3 - Rendimento costante'!AQ$72:AQ$130),"") -> 0.21251534 | H63: =INDEX('3 - Rendimento costante'!N$71:N$130,Anni+1) -> 0 | I63: =IFERROR(MATCH(1,INDEX('3 - Rendimento costante'!L$71:L$130,1):INDEX('3 - Rendimento costante'!L$71:L$130,Anni),0),"no") -> 36
A64: Percentuale costante | B64: ='3 - Rendimento costante'!E6 -> 38000 | C64: =MEDIAN('3 - Rendimento costante'!E$6:E$65) -> 25659.587 | D64: =MIN('3 - Rendimento costante'!E$6:E$65) -> 18474.109 | E64: =COUNTIF('3 - Rendimento costante'!E$6:E$65,"<"&0.8*Spesa0) -> 30 | F64: =COUNTIF('3 - Rendimento costante'!E$6:E$65,"<"&0.75*Spesa0) -> 27 | G64: =IFERROR(STDEVP('3 - Rendimento costante'!AR$72:AR$130),"") -> 0.0018298872 | H64: =INDEX('3 - Rendimento costante'!S$71:S$130,Anni+1) -> 590123.64 | I64: =IFERROR(MATCH(1,INDEX('3 - Rendimento costante'!Q$71:Q$130,1):INDEX('3 - Rendimento costante'!Q$71:Q$130,Anni),0),"no") -> no
A65: Percentuale con pavimento | B65: ='3 - Rendimento costante'!F6 -> 38000 | C65: =MEDIAN('3 - Rendimento costante'!F$6:F$65) -> 34200 | D65: =MIN('3 - Rendimento costante'!F$6:F$65) -> 797.03326 | E65: =COUNTIF('3 - Rendimento costante'!F$6:F$65,"<"&0.8*Spesa0) -> 1 | F65: =COUNTIF('3 - Rendimento costante'!F$6:F$65,"<"&0.75*Spesa0) -> 1 | G65: =IFERROR(STDEVP('3 - Rendimento costante'!AS$72:AS$130),"") -> 0.15041308 | H65: =INDEX('3 - Rendimento costante'!X$71:X$130,Anni+1) -> 0 | I65: =IFERROR(MATCH(1,INDEX('3 - Rendimento costante'!V$71:V$130,1):INDEX('3 - Rendimento costante'!V$71:V$130,Anni),0),"no") -> 42
A66: Percentuale variabile | B66: ='3 - Rendimento costante'!G6 -> 35662.76 | C66: =MEDIAN('3 - Rendimento costante'!G$6:G$65) -> 30703.969 | D66: =MIN('3 - Rendimento costante'!G$6:G$65) -> 28187.125 | E66: =COUNTIF('3 - Rendimento costante'!G$6:G$65,"<"&0.8*Spesa0) -> 19 | F66: =COUNTIF('3 - Rendimento costante'!G$6:G$65,"<"&0.75*Spesa0) -> 4 | G66: =IFERROR(STDEVP('3 - Rendimento costante'!AT$72:AT$130),"") -> 0.001851706 | H66: =INDEX('3 - Rendimento costante'!AD$71:AD$130,Anni+1) -> 237184.35 | I66: =IFERROR(MATCH(1,INDEX('3 - Rendimento costante'!AB$71:AB$130,1):INDEX('3 - Rendimento costante'!AB$71:AB$130,Anni),0),"no") -> no
A67: Guardrail (senza tetto all'inflazione) | B67: ='3 - Rendimento costante'!H6 -> 38000 | C67: =MEDIAN('3 - Rendimento costante'!H$6:H$65) -> 26316.9 | D67: =MIN('3 - Rendimento costante'!H$6:H$65) -> 22438.62 | E67: =COUNTIF('3 - Rendimento costante'!H$6:H$65,"<"&0.8*Spesa0) -> 25 | F67: =COUNTIF('3 - Rendimento costante'!H$6:H$65,"<"&0.75*Spesa0) -> 25 | G67: =IFERROR(STDEVP('3 - Rendimento costante'!AU$72:AU$130),"") -> 0.032722946 | H67: =INDEX('3 - Rendimento costante'!AK$71:AK$130,Anni+1) -> 409607.07 | I67: =IFERROR(MATCH(1,INDEX('3 - Rendimento costante'!AI$71:AI$130,1):INDEX('3 - Rendimento costante'!AI$71:AI$130,Anni),0),"no") -> no
A68: Tetto e pavimento (+5% / −2,5%) | B68: ='3 - Rendimento costante'!I6 -> 38000 | C68: =MEDIAN('3 - Rendimento costante'!I$6:I$65) -> 25659.587 | D68: =MIN('3 - Rendimento costante'!I$6:I$65) -> 18474.109 | E68: =COUNTIF('3 - Rendimento costante'!I$6:I$65,"<"&0.8*Spesa0) -> 30 | F68: =COUNTIF('3 - Rendimento costante'!I$6:I$65,"<"&0.75*Spesa0) -> 27 | G68: =IFERROR(STDEVP('3 - Rendimento costante'!AV$72:AV$130),"") -> 0.0018298872 | H68: =INDEX('3 - Rendimento costante'!AP$71:AP$130,Anni+1) -> 590123.64 | I68: =IFERROR(MATCH(1,INDEX('3 - Rendimento costante'!AN$71:AN$130,1):INDEX('3 - Rendimento costante'!AN$71:AN$130,Anni),0),"no") -> no

Sheet 2 - Sequenza storica
A1: 2 - Sequenza storica: spesa pagata e capitale, anno per anno (euro di oggi)
A2: Strumento informativo / divulgativo. NON è consulenza finanziaria. I valori sono indicativi al 2026 e vanno verificati col tuo consulente.
A3: Risultati: spesa pagata (euro in cassa se «tassato», venduto lordo se «lordo») e capitale a inizio anno
A4: ="Sequenza: "&Serie&" dal "&Anno_inizio&" · anni osservati: "&Anni_osservati&" · anni di ipotesi al canone: "&Anni_ipotesi&" · modalità: "&Modalita -> Sequenza: EUR dal 2000 · anni osservati: 26 · anni di ipotesi al canone: 16 · modalità: tassato
A5: t | B5: Età | C5: Anno | D5: Spesa pagata: Fisso indicizzato | E5: Spesa pagata: Percentuale costante | F5: Spesa pagata: Percentuale con pavimento | G5: Spesa pagata: Percentuale variabile | H5: Spesa pagata: Guardrail (senza tetto all'inflazione) | I5: Spesa pagata: Tetto e pavimento (+5% / −2,5%) | J5: Capitale inizio anno: Fisso indicizzato | K5: Capitale inizio anno: Percentuale costante | L5: Capitale inizio anno: Percentuale con pavimento | M5: Capitale inizio anno: Percentuale variabile | N5: Capitale inizio anno: Guardrail (senza tetto all'inflazione) | O5: Capitale inizio anno: Tetto e pavimento (+5% / −2,5%) | P5: Dato storico o ipotesi
A6: =A71 -> 1 | B6: =IF($A6>Anni,"",B71) -> 51 | C6: =IF($A6>Anni,"",C71) -> 2000 | D6: =IF($A6>Anni,"",M71) -> 38000 | E6: =IF($A6>Anni,"",R71) -> 38000 | F6: =IF($A6>Anni,"",W71) -> 38000 | G6: =IF($A6>Anni,"",AC71) -> 35662.76 | H6: =IF($A6>Anni,"",AJ71) -> 38000 | I6: =IF($A6>Anni,"",AO71) -> 38000 | J6: =IF($A6>Anni,"",N71) -> 1056000 | K6: =IF($A6>Anni,"",S71) -> 1056000 | L6: =IF($A6>Anni,"",X71) -> 1056000 | M6: =IF($A6>Anni,"",AD71) -> 1056000 | N6: =IF($A6>Anni,"",AK71) -> 1056000 | O6: =IF($A6>Anni,"",AP71) -> 1056000 | P6: =IF($A6>Anni,"",IF(D71=1,"osservato","ipotesi")) -> osservato
A7: =A72 -> 2 | B7: =IF($A7>Anni,"",B72) -> 52 | C7: =IF($A7>Anni,"",C72) -> 2001 | D7: =IF($A7>Anni,"",M72) -> 38000 | E7: =IF($A7>Anni,"",R72) -> 36810.118 | F7: =IF($A7>Anni,"",W72) -> 36810.118 | G7: =IF($A7>Anni,"",AC72) -> 34957.976 | H7: =IF($A7>Anni,"",AJ72) -> 38000 | I7: =IF($A7>Anni,"",AO72) -> 37050 | J7: =IF($A7>Anni,"",N72) -> 1029708.4 | K7: =IF($A7>Anni,"",S72) -> 1029708.4 | L7: =IF($A7>Anni,"",X72) -> 1029708.4 | M7: =IF($A7>Anni,"",AD72) -> 1032386.2 | N7: =IF($A7>Anni,"",AK72) -> 1029708.4 | O7: =IF($A7>Anni,"",AP72) -> 1029708.4 | P7: =IF($A7>Anni,"",IF(D72=1,"osservato","ipotesi")) -> osservato
A8: =A73 -> 3 | B8: =IF($A8>Anni,"",B73) -> 53 | C8: =IF($A8>Anni,"",C73) -> 2002 | D8: =IF($A8>Anni,"",M73) -> 38000 | E8: =IF($A8>Anni,"",R73) -> 32361.467 | F8: =IF($A8>Anni,"",W73) -> 34200 | G8: =IF($A8>Anni,"",AC73) -> 31099.612 | H8: =IF($A8>Anni,"",AJ73) -> 37157.757 | I8: =IF($A8>Anni,"",AO73) -> 36123.75 | J8: =IF($A8>Anni,"",N73) -> 892443.2 | K8: =IF($A8>Anni,"",S73) -> 893664.6 | L8: =IF($A8>Anni,"",X73) -> 893664.6 | M8: =IF($A8>Anni,"",AD73) -> 897988.1 | N8: =IF($A8>Anni,"",AK73) -> 892443.2 | O8: =IF($A8>Anni,"",AP73) -> 893418.36 | P8: =IF($A8>Anni,"",IF(D73=1,"osservato","ipotesi")) -> osservato
A9: =A74 -> 4 | B9: =IF($A9>Anni,"",B74) -> 54 | C9: =IF($A9>Anni,"",C74) -> 2003 | D9: =IF($A9>Anni,"",M74) -> 38000 | E9: =IF($A9>Anni,"",R74) -> 26006.674 | F9: =IF($A9>Anni,"",W74) -> 34200 | G9: =IF($A9>Anni,"",AC74) -> 25290.609 | H9: =IF($A9>Anni,"",AJ74) -> 32509.505 | I9: =IF($A9>Anni,"",AO74) -> 35220.656 | J9: =IF($A9>Anni,"",N74) -> 688278.51 | K9: =IF($A9>Anni,"",S74) -> 694383.14 | L9: =IF($A9>Anni,"",X74) -> 692715.16 | M9: =IF($A9>Anni,"",AD74) -> 699029.37 | N9: =IF($A9>Anni,"",AK74) -> 689042.62 | O9: =IF($A9>Anni,"",AP74) -> 690770.46 | P9: =IF($A9>Anni,"",IF(D74=1,"osservato","ipotesi")) -> osservato
A10: =A75 -> 5 | B10: =IF($A10>Anni,"",B75) -> 55 | C10: =IF($A10>Anni,"",C75) -> 2004 | D10: =IF($A10>Anni,"",M75) -> 38000 | E10: =IF($A10>Anni,"",R75) -> 26959.76 | F10: =IF($A10>Anni,"",W75) -> 34200 | G10: =IF($A10>Anni,"",AC75) -> 26530.058 | H10: =IF($A10>Anni,"",AJ75) -> 29258.554 | I10: =IF($A10>Anni,"",AO75) -> 34340.14 | J10: =IF($A10>Anni,"",N75) -> 715476.36 | K10: =IF($A10>Anni,"",S75) -> 736588.25 | L10: =IF($A10>Anni,"",X75) -> 724932.29 | M10: =IF($A10>Anni,"",AD75) -> 742582.78 | N10: =IF($A10>Anni,"",AK75) -> 722896.24 | O10: =IF($A10>Anni,"",AP75) -> 721559.89 | P10: =IF($A10>Anni,"",IF(D75=1,"osservato","ipotesi")) -> osservato
A11: =A76 -> 6 | B11: =IF($A11>Anni,"",B76) -> 56 | C11: =IF($A11>Anni,"",C76) -> 2005 | D11: =IF($A11>Anni,"",M76) -> 38000 | E11: =IF($A11>Anni,"",R76) -> 26924.161 | F11: =IF($A11>Anni,"",W76) -> 34200 | G11: =IF($A11>Anni,"",AC76) -> 26810.942 | H11: =IF($A11>Anni,"",AJ76) -> 29258.554 | I11: =IF($A11>Anni,"",AO76) -> 33481.636 | J11: =IF($A11>Anni,"",N76) -> 709816.36 | K11: =IF($A11>Anni,"",S76) -> 744970.09 | L11: =IF($A11>Anni,"",X76) -> 724223.96 | M11: =IF($A11>Anni,"",AD76) -> 751791.21 | N11: =IF($A11>Anni,"",AK76) -> 727850.99 | O11: =IF($A11>Anni,"",AP76) -> 720505.25 | P11: =IF($A11>Anni,"",IF(D76=1,"osservato","ipotesi")) -> osservato
A12: =A77 -> 7 | B12: =IF($A12>Anni,"",B77) -> 57 | C12: =IF($A12>Anni,"",C77) -> 2006 | D12: =IF($A12>Anni,"",M77) -> 38000 | E12: =IF($A12>Anni,"",R77) -> 28803.531 | F12: =IF($A12>Anni,"",W77) -> 34200 | G12: =IF($A12>Anni,"",AC77) -> 29024.405 | H12: =IF($A12>Anni,"",AJ77) -> 29258.554 | I12: =IF($A12>Anni,"",AO77) -> 32644.595 | J12: =IF($A12>Anni,"",N77) -> 762479.54 | K12: =IF($A12>Anni,"",S77) -> 816863.52 | L12: =IF($A12>Anni,"",X77) -> 783820.1 | M12: =IF($A12>Anni,"",AD77) -> 824804.39 | N12: =IF($A12>Anni,"",AK77) -> 794304.14 | O12: =IF($A12>Anni,"",AP77) -> 780491.61 | P12: =IF($A12>Anni,"",IF(D77=1,"osservato","ipotesi")) -> osservato
A13: =A78 -> 8 | B13: =IF($A13>Anni,"",B78) -> 58 | C13: =IF($A13>Anni,"",C78) -> 2007 | D13: =IF($A13>Anni,"",M78) -> 38000 | E13: =IF($A13>Anni,"",R78) -> 28184.307 | F13: =IF($A13>Anni,"",W78) -> 34200 | G13: =IF($A13>Anni,"",AC78) -> 28739.066 | H13: =IF($A13>Anni,"",AJ78) -> 29258.554 | I13: =IF($A13>Anni,"",AO78) -> 31828.481 | J13: =IF($A13>Anni,"",N78) -> 737887.98 | K13: =IF($A13>Anni,"",S78) -> 804580.64 | L13: =IF($A13>Anni,"",X78) -> 764284.42 | M13: =IF($A13>Anni,"",AD78) -> 812471.94 | N13: =IF($A13>Anni,"",AK78) -> 780883.57 | O13: =IF($A13>Anni,"",AP78) -> 762704.39 | P13: =IF($A13>Anni,"",IF(D78=1,"osservato","ipotesi")) -> osservato
A14: =A79 -> 9 | B14: =IF($A14>Anni,"",B79) -> 59 | C14: =IF($A14>Anni,"",C79) -> 2008 | D14: =IF($A14>Anni,"",M79) -> 38000 | E14: =IF($A14>Anni,"",R79) -> 24895.373 | F14: =IF($A14>Anni,"",W79) -> 34200 | G14: =IF($A14>Anni,"",AC79) -> 25688.08 | H14: =IF($A14>Anni,"",AJ79) -> 28363.898 | I14: =IF($A14>Anni,"",AO79) -> 31032.769 | J14: =IF($A14>Anni,"",N79) -> 633176.44 | K14: =IF($A14>Anni,"",S79) -> 704406.88 | L14: =IF($A14>Anni,"",X79) -> 661279.1 | M14: =IF($A14>Anni,"",AD79) -> 711021.56 | N14: =IF($A14>Anni,"",AK79) -> 681647.81 | O14: =IF($A14>Anni,"",AP79) -> 662343.36 | P14: =IF($A14>Anni,"",IF(D79=1,"osservato","ipotesi")) -> osservato
A15: =A80 -> 10 | B15: =IF($A15>Anni,"",B80) -> 60 | C15: =IF($A15>Anni,"",C80) -> 2009 | D15: =IF($A15>Anni,"",M80) -> 38000 | E15: =IF($A15>Anni,"",R80) -> 20288.788 | F15: =IF($A15>Anni,"",W80) -> 34200 | G15: =IF($A15>Anni,"",AC80) -> 21184.431 | H15: =IF($A15>Anni,"",AJ80) -> 25185.24 | I15: =IF($A15>Anni,"",AO80) -> 30256.949 | J15: =IF($A15>Anni,"",N80) -> 486442.45 | K15: =IF($A15>Anni,"",S80) -> 557624.98 | L15: =IF($A15>Anni,"",X80) -> 513228.58 | M15: =IF($A15>Anni,"",AD80) -> 562331.98 | N15: =IF($A15>Anni,"",AK80) -> 535561.74 | O15: =IF($A15>Anni,"",AP80) -> 517106.21 | P15: =IF($A15>Anni,"",IF(D80=1,"osservato","ipotesi")) -> osservato
A16: =A81 -> 11 | B16: =IF($A16>Anni,"",B81) -> 61 | C16: =IF($A16>Anni,"",C81) -> 2010 | D16: =IF($A16>Anni,"",M81) -> 38000 | E16: =IF($A16>Anni,"",R81) -> 21967.594 | F16: =IF($A16>Anni,"",W81) -> 34200 | G16: =IF($A16>Anni,"",AC81) -> 23210.843 | H16: =IF($A16>Anni,"",AJ81) -> 22666.716 | I16: =IF($A16>Anni,"",AO81) -> 29500.526 | J16: =IF($A16>Anni,"",N81) -> 514498.22 | K16: =IF($A16>Anni,"",S81) -> 619847.53 | L16: =IF($A16>Anni,"",X81) -> 550440.83 | M16: =IF($A16>Anni,"",AD81) -> 624144.05 | N16: =IF($A16>Anni,"",AK81) -> 587960.45 | O16: =IF($A16>Anni,"",AP81) -> 560026.8 | P16: =IF($A16>Anni,"",IF(D81=1,"osservato","ipotesi")) -> osservato
A17: =A82 -> 12 | B17: =IF($A17>Anni,"",B82) -> 62 | C17: =IF($A17>Anni,"",C82) -> 2011 | D17: =IF($A17>Anni,"",M82) -> 38000 | E17: =IF($A17>Anni,"",R82) -> 23079.086 | F17: =IF($A17>Anni,"",W82) -> 34200 | G17: =IF($A17>Anni,"",AC82) -> 24675.998 | H17: =IF($A17>Anni,"",AJ82) -> 22666.716 | I17: =IF($A17>Anni,"",AO82) -> 28763.012 | J17: =IF($A17>Anni,"",N82) -> 525493.43 | K17: =IF($A17>Anni,"",S82) -> 663505.08 | L17: =IF($A17>Anni,"",X82) -> 570447.12 | M17: =IF($A17>Anni,"",AD82) -> 666710.98 | N17: =IF($A17>Anni,"",AK82) -> 627036.11 | O17: =IF($A17>Anni,"",AP82) -> 587143.61 | P17: =IF($A17>Anni,"",IF(D82=1,"osservato","ipotesi")) -> osservato
... A47: =A112 -> 42 | B47: =IF($A47>Anni,"",B112) -> 92 | C47: =IF($A47>Anni,"",C112) -> 2041 | D47: =IF($A47>Anni,"",M112) -> 0 | E47: =IF($A47>Anni,"",R112) -> 19562.99 | F47: =IF($A47>Anni,"",W112) -> 0 | G47: =IF($A47>Anni,"",AC112) -> 29848.501 | H47: =IF($A47>Anni,"",AJ112) -> 20481.744 | I47: =IF($A47>Anni,"",AO112) -> 15193.992 | J47: =IF($A47>Anni,"",N112) -> 0 | K47: =IF($A47>Anni,"",S112) -> 634790.62 | L47: =IF($A47>Anni,"",X112) -> 0 | M47: =IF($A47>Anni,"",AD112) -> 284077.02 | N47: =IF($A47>Anni,"",AK112) -> 675902.15 | O47: =IF($A47>Anni,"",AP112) -> 493022.97 | P47: =IF($A47>Anni,"",IF(D112=1,"osservato","ipotesi")) -> ipotesi
A48: =A113 -> 43 | B48: =IF($A48>Anni,"",B113) | C48: =IF($A48>Anni,"",C113) | D48: =IF($A48>Anni,"",M113) | E48: =IF($A48>Anni,"",R113) | F48: =IF($A48>Anni,"",W113) | G48: =IF($A48>Anni,"",AC113) | H48: =IF($A48>Anni,"",AJ113) | I48: =IF($A48>Anni,"",AO113) | J48: =IF($A48>Anni,"",N113) | K48: =IF($A48>Anni,"",S113) | L48: =IF($A48>Anni,"",X113) | M48: =IF($A48>Anni,"",AD113) | N48: =IF($A48>Anni,"",AK113) | O48: =IF($A48>Anni,"",AP113) | P48: =IF($A48>Anni,"",IF(D113=1,"osservato","ipotesi")) | R48: Il grafico mostra i primi 42 anni (righe 6-47); la tabella a sinistra mostra l'intero piano.
A49: =A114 -> 44 | B49: =IF($A49>Anni,"",B114) | C49: =IF($A49>Anni,"",C114) | D49: =IF($A49>Anni,"",M114) | E49: =IF($A49>Anni,"",R114) | F49: =IF($A49>Anni,"",W114) | G49: =IF($A49>Anni,"",AC114) | H49: =IF($A49>Anni,"",AJ114) | I49: =IF($A49>Anni,"",AO114) | J49: =IF($A49>Anni,"",N114) | K49: =IF($A49>Anni,"",S114) | L49: =IF($A49>Anni,"",X114) | M49: =IF($A49>Anni,"",AD114) | N49: =IF($A49>Anni,"",AK114) | O49: =IF($A49>Anni,"",AP114) | P49: =IF($A49>Anni,"",IF(D114=1,"osservato","ipotesi"))
A50: =A115 -> 45 | B50: =IF($A50>Anni,"",B115) | C50: =IF($A50>Anni,"",C115) | D50: =IF($A50>Anni,"",M115) | E50: =IF($A50>Anni,"",R115) | F50: =IF($A50>Anni,"",W115) | G50: =IF($A50>Anni,"",AC115) | H50: =IF($A50>Anni,"",AJ115) | I50: =IF($A50>Anni,"",AO115) | J50: =IF($A50>Anni,"",N115) | K50: =IF($A50>Anni,"",S115) | L50: =IF($A50>Anni,"",X115) | M50: =IF($A50>Anni,"",AD115) | N50: =IF($A50>Anni,"",AK115) | O50: =IF($A50>Anni,"",AP115) | P50: =IF($A50>Anni,"",IF(D115=1,"osservato","ipotesi"))
A51: =A116 -> 46 | B51: =IF($A51>Anni,"",B116) | C51: =IF($A51>Anni,"",C116) | D51: =IF($A51>Anni,"",M116) | E51: =IF($A51>Anni,"",R116) | F51: =IF($A51>Anni,"",W116) | G51: =IF($A51>Anni,"",AC116) | H51: =IF($A51>Anni,"",AJ116) | I51: =IF($A51>Anni,"",AO116) | J51: =IF($A51>Anni,"",N116) | K51: =IF($A51>Anni,"",S116) | L51: =IF($A51>Anni,"",X116) | M51: =IF($A51>Anni,"",AD116) | N51: =IF($A51>Anni,"",AK116) | O51: =IF($A51>Anni,"",AP116) | P51: =IF($A51>Anni,"",IF(D116=1,"osservato","ipotesi"))
A52: =A117 -> 47 | B52: =IF($A52>Anni,"",B117) | C52: =IF($A52>Anni,"",C117) | D52: =IF($A52>Anni,"",M117) | E52: =IF($A52>Anni,"",R117) | F52: =IF($A52>Anni,"",W117) | G52: =IF($A52>Anni,"",AC117) | H52: =IF($A52>Anni,"",AJ117) | I52: =IF($A52>Anni,"",AO117) | J52: =IF($A52>Anni,"",N117) | K52: =IF($A52>Anni,"",S117) | L52: =IF($A52>Anni,"",X117) | M52: =IF($A52>Anni,"",AD117) | N52: =IF($A52>Anni,"",AK117) | O52: =IF($A52>Anni,"",AP117) | P52: =IF($A52>Anni,"",IF(D117=1,"osservato","ipotesi"))
A53: =A118 -> 48 | B53: =IF($A53>Anni,"",B118) | C53: =IF($A53>Anni,"",C118) | D53: =IF($A53>Anni,"",M118) | E53: =IF($A53>Anni,"",R118) | F53: =IF($A53>Anni,"",W118) | G53: =IF($A53>Anni,"",AC118) | H53: =IF($A53>Anni,"",AJ118) | I53: =IF($A53>Anni,"",AO118) | J53: =IF($A53>Anni,"",N118) | K53: =IF($A53>Anni,"",S118) | L53: =IF($A53>Anni,"",X118) | M53: =IF($A53>Anni,"",AD118) | N53: =IF($A53>Anni,"",AK118) | O53: =IF($A53>Anni,"",AP118) | P53: =IF($A53>Anni,"",IF(D118=1,"osservato","ipotesi"))
A54: =A119 -> 49 | B54: =IF($A54>Anni,"",B119) | C54: =IF($A54>Anni,"",C119) | D54: =IF($A54>Anni,"",M119) | E54: =IF($A54>Anni,"",R119) | F54: =IF($A54>Anni,"",W119) | G54: =IF($A54>Anni,"",AC119) | H54: =IF($A54>Anni,"",AJ119) | I54: =IF($A54>Anni,"",AO119) | J54: =IF($A54>Anni,"",N119) | K54: =IF($A54>Anni,"",S119) | L54: =IF($A54>Anni,"",X119) | M54: =IF($A54>Anni,"",AD119) | N54: =IF($A54>Anni,"",AK119) | O54: =IF($A54>Anni,"",AP119) | P54: =IF($A54>Anni,"",IF(D119=1,"osservato","ipotesi"))
A55: =A120 -> 50 | B55: =IF($A55>Anni,"",B120) | C55: =IF($A55>Anni,"",C120) | D55: =IF($A55>Anni,"",M120) | E55: =IF($A55>Anni,"",R120) | F55: =IF($A55>Anni,"",W120) | G55: =IF($A55>Anni,"",AC120) | H55: =IF($A55>Anni,"",AJ120) | I55: =IF($A55>Anni,"",AO120) | J55: =IF($A55>Anni,"",N120) | K55: =IF($A55>Anni,"",S120) | L55: =IF($A55>Anni,"",X120) | M55: =IF($A55>Anni,"",AD120) | N55: =IF($A55>Anni,"",AK120) | O55: =IF($A55>Anni,"",AP120) | P55: =IF($A55>Anni,"",IF(D120=1,"osservato","ipotesi"))
A56: =A121 -> 51 | B56: =IF($A56>Anni,"",B121) | C56: =IF($A56>Anni,"",C121) | D56: =IF($A56>Anni,"",M121) | E56: =IF($A56>Anni,"",R121) | F56: =IF($A56>Anni,"",W121) | G56: =IF($A56>Anni,"",AC121) | H56: =IF($A56>Anni,"",AJ121) | I56: =IF($A56>Anni,"",AO121) | J56: =IF($A56>Anni,"",N121) | K56: =IF($A56>Anni,"",S121) | L56: =IF($A56>Anni,"",X121) | M56: =IF($A56>Anni,"",AD121) | N56: =IF($A56>Anni,"",AK121) | O56: =IF($A56>Anni,"",AP121) | P56: =IF($A56>Anni,"",IF(D121=1,"osservato","ipotesi"))
A57: =A122 -> 52 | B57: =IF($A57>Anni,"",B122) | C57: =IF($A57>Anni,"",C122) | D57: =IF($A57>Anni,"",M122) | E57: =IF($A57>Anni,"",R122) | F57: =IF($A57>Anni,"",W122) | G57: =IF($A57>Anni,"",AC122) | H57: =IF($A57>Anni,"",AJ122) | I57: =IF($A57>Anni,"",AO122) | J57: =IF($A57>Anni,"",N122) | K57: =IF($A57>Anni,"",S122) | L57: =IF($A57>Anni,"",X122) | M57: =IF($A57>Anni,"",AD122) | N57: =IF($A57>Anni,"",AK122) | O57: =IF($A57>Anni,"",AP122) | P57: =IF($A57>Anni,"",IF(D122=1,"osservato","ipotesi"))
A58: =A123 -> 53 | B58: =IF($A58>Anni,"",B123) | C58: =IF($A58>Anni,"",C123) | D58: =IF($A58>Anni,"",M123) | E58: =IF($A58>Anni,"",R123) | F58: =IF($A58>Anni,"",W123) | G58: =IF($A58>Anni,"",AC123) | H58: =IF($A58>Anni,"",AJ123) | I58: =IF($A58>Anni,"",AO123) | J58: =IF($A58>Anni,"",N123) | K58: =IF($A58>Anni,"",S123) | L58: =IF($A58>Anni,"",X123) | M58: =IF($A58>Anni,"",AD123) | N58: =IF($A58>Anni,"",AK123) | O58: =IF($A58>Anni,"",AP123) | P58: =IF($A58>Anni,"",IF(D123=1,"osservato","ipotesi"))
A59: =A124 -> 54 | B59: =IF($A59>Anni,"",B124) | C59: =IF($A59>Anni,"",C124) | D59: =IF($A59>Anni,"",M124) | E59: =IF($A59>Anni,"",R124) | F59: =IF($A59>Anni,"",W124) | G59: =IF($A59>Anni,"",AC124) | H59: =IF($A59>Anni,"",AJ124) | I59: =IF($A59>Anni,"",AO124) | J59: =IF($A59>Anni,"",N124) | K59: =IF($A59>Anni,"",S124) | L59: =IF($A59>Anni,"",X124) | M59: =IF($A59>Anni,"",AD124) | N59: =IF($A59>Anni,"",AK124) | O59: =IF($A59>Anni,"",AP124) | P59: =IF($A59>Anni,"",IF(D124=1,"osservato","ipotesi"))
A60: =A125 -> 55 | B60: =IF($A60>Anni,"",B125) | C60: =IF($A60>Anni,"",C125) | D60: =IF($A60>Anni,"",M125) | E60: =IF($A60>Anni,"",R125) | F60: =IF($A60>Anni,"",W125) | G60: =IF($A60>Anni,"",AC125) | H60: =IF($A60>Anni,"",AJ125) | I60: =IF($A60>Anni,"",AO125) | J60: =IF($A60>Anni,"",N125) | K60: =IF($A60>Anni,"",S125) | L60: =IF($A60>Anni,"",X125) | M60: =IF($A60>Anni,"",AD125) | N60: =IF($A60>Anni,"",AK125) | O60: =IF($A60>Anni,"",AP125) | P60: =IF($A60>Anni,"",IF(D125=1,"osservato","ipotesi"))
... A65: =A130 -> 60 | B65: =IF($A65>Anni,"",B130) | C65: =IF($A65>Anni,"",C130) | D65: =IF($A65>Anni,"",M130) | E65: =IF($A65>Anni,"",R130) | F65: =IF($A65>Anni,"",W130) | G65: =IF($A65>Anni,"",AC130) | H65: =IF($A65>Anni,"",AJ130) | I65: =IF($A65>Anni,"",AO130) | J65: =IF($A65>Anni,"",N130) | K65: =IF($A65>Anni,"",S130) | L65: =IF($A65>Anni,"",X130) | M65: =IF($A65>Anni,"",AD130) | N65: =IF($A65>Anni,"",AK130) | O65: =IF($A65>Anni,"",AP130) | P65: =IF($A65>Anni,"",IF(D130=1,"osservato","ipotesi"))
A68: Motore del calcolo, non modificare
A69: Anno e rendimenti | J69: Fisso indicizzato | O69: Percentuale costante | T69: Percentuale con pavimento | Y69: Percentuale variabile | AE69: Guardrail (senza tetto all'inflazione) | AL69: Tetto e pavimento | AQ69: Cambio % annuo della spesa pagata
A70: t | B70: Età | C70: Anno | D70: Dato storico (1/0) | E70: Rendimento nominale 60/40 | F70: Inflazione | G70: Fattore nominale dopo bollo (g) | H70: Base di costo / valore (k) | I70: Quota netta del venduto (q) | J70: Fisso: pianificata | K70: Fisso: venduto | L70: Fisso: esaurimento | M70: Fisso: pagata | N70: Fisso: capitale (W) | O70: Perc. costante: pianificata | P70: Perc. costante: venduto | Q70: Perc. costante: esaurimento | R70: Perc. costante: pagata | S70: Perc. costante: capitale (W) | T70: Perc. con pav.: pianificata | U70: Perc. con pav.: venduto | V70: Perc. con pav.: esaurimento | W70: Perc. con pav.: pagata | X70: Perc. con pav.: capitale (W) | Y70: Perc. variabile: percentuale | Z70: Perc. variabile: pianificata | AA70: Perc. variabile: venduto | AB70: Perc. variabile: esaurimento | AC70: Perc. variabile: pagata | AD70: Perc. variabile: capitale (W) | AE70: Guardrail: prima della regola | AF70: Guardrail: tasso corrente | AG70: Guardrail: pianificata | AH70: Guardrail: venduto | AI70: Guardrail: esaurimento | AJ70: Guardrail: pagata | AK70: Guardrail: capitale (W) | AL70: Tetto e pav.: pianificata | AM70: Tetto e pav.: venduto | AN70: Tetto e pav.: esaurimento | AO70: Tetto e pav.: pagata | AP70: Tetto e pav.: capitale (W) | AQ70: Cambio % fisso | AR70: Cambio % perc. costante | AS70: Cambio % perc. con pav. | AT70: Cambio % perc. variabile | AU70: Cambio % guardrail | AV70: Cambio % tetto e pav.
A71: 1 | B71: =Eta_inizio+A71-1 -> 51 | C71: =Anno_inizio+A71-1 -> 2000 | D71: =IF(COUNTIFS('5 - Dati'!$A$6:$A$186,Serie,'5 - Dati'!$B$6:$B$186,C71)>0,1,0) -> 1 | E71: =IF(D71=1,SUMIFS('5 - Dati'!$F$6:$F$186,'5 - Dati'!$A$6:$A$186,Serie,'5 - Dati'!$B$6:$B$186,C71),(1+Rend_c)*(1+Infl_c)-1) -> 0.04340975 | F71: =IF(D71=1,SUMIFS('5 - Dati'!$E$6:$E$186,'5 - Dati'!$A$6:$A$186,Serie,'5 - Dati'!$B$6:$B$186,C71),Infl_c) -> 0.02459017 | G71: =(1+E71)*(1-Bollo_eff) -> 1.0413229 | H71: =1-Latente_eff -> 0.56564418 | I71: =1-Aliq_eff*MAX(0,1-H71) -> 0.88706749 | J71: =Spesa0 -> 38000 | K71: =J71/I71 -> 42837.778 | L71: =IF(K71>N71+0.000000001,1,0) -> 0 | M71: =MIN(K71,N71)*I71 -> 38000 | N71: =Patrimonio -> 1056000 | O71: =Tasso0*S71*I71 -> 38000 | P71: =O71/I71 -> 42837.778 | Q71: =IF(P71>S71+0.000000001,1,0) -> 0 | R71: =MIN(P71,S71)*I71 -> 38000 | S71: =Patrimonio -> 1056000 | T71: =MAX(Tasso0*X71*I71,Pav_pct*Spesa0) -> 38000 | U71: =T71/I71 -> 42837.778 | V71: =IF(U71>X71+0.000000001,1,0) -> 0 | W71: =MIN(U71,X71)*I71 -> 38000 | X71: =Patrimonio -> 1056000 | Y71: =IF(Eta_rif_VPW-B71<=1,1,IF(r_VPW=0,1/(Eta_rif_VPW-B71),r_VPW/(1-(1+r_VPW)^(-(Eta_rif_VPW-B71)))/(1+r_VPW))) -> 0.038071008 | Z71: =Y71*AD71*I71 -> 35662.76 | AA71: =Z71/I71 -> 40202.985 | AB71: =IF(AA71>AD71+0.000000001,1,0) -> 0 | AC71: =MIN(AA71,AD71)*I71 -> 35662.76 | AD71: =Patrimonio -> 1056000 | AE71: =Spesa0 -> 38000 | AF71: =IF(AK71*I71<=0,9.9,AE71/(AK71*I71)) -> 0.040566078 | AG71: =IF(AND(AF71>Tasso0*(1+GK_banda),A71<=Anni-GK_ultimi),AE71*(1-GK_taglio),IF(AF71<Tasso0*(1-GK_banda),AE71*(1+GK_taglio),AE71)) -> 38000 | AH71: =AG71/I71 -> 42837.778 | AI71: =IF(AH71>AK71+0.000000001,1,0) -> 0 | AJ71: =MIN(AH71,AK71)*I71 -> 38000 | AK71: =Patrimonio -> 1056000 | AL71: =Spesa0 -> 38000 | AM71: =AL71/I71 -> 42837.778 | AN71: =IF(AM71>AP71+0.000000001,1,0) -> 0 | AO71: =MIN(AM71,AP71)*I71 -> 38000 | AP71: =Patrimonio -> 1056000
A72: =A71+1 -> 2 | B72: =Eta_inizio+A72-1 -> 52 | C72: =Anno_inizio+A72-1 -> 2001 | D72: =IF(COUNTIFS('5 - Dati'!$A$6:$A$186,Serie,'5 - Dati'!$B$6:$B$186,C72)>0,1,0) -> 1 | E72: =IF(D72=1,SUMIFS('5 - Dati'!$F$6:$F$186,'5 - Dati'!$A$6:$A$186,Serie,'5 - Dati'!$B$6:$B$186,C72),(1+Rend_c)*(1+Infl_c)-1) -> -0.073065986 | F72: =IF(D72=1,SUMIFS('5 - Dati'!$E$6:$E$186,'5 - Dati'!$A$6:$A$186,Serie,'5 - Dati'!$B$6:$B$186,C72),Infl_c) -> 0.02266669 | G72: =(1+E72)*(1-Bollo_eff) -> 0.92508015 | H72: =H71/G71 -> 0.54319766 | I72: =1-Aliq_eff*MAX(0,1-H72) -> 0.88123139 | J72: =Spesa0 -> 38000 | K72: =J72/I72 -> 43121.478 | L72: =IF(K72>N72+0.000000001,1,0) -> 0 | M72: =MIN(K72,N72)*I72 -> 38000 | N72: =(N71-MIN(K71,N71))*G71/(1+F71) -> 1029708.4 | O72: =Tasso0*S72*I72 -> 36810.118 | P72: =O72/I72 -> 41771.229 | Q72: =IF(P72>S72+0.000000001,1,0) -> 0 | R72: =MIN(P72,S72)*I72 -> 36810.118 | S72: =(S71-MIN(P71,S71))*G71/(1+F71) -> 1029708.4 | T72: =MAX(Tasso0*X72*I72,Pav_pct*Spesa0) -> 36810.118 | U72: =T72/I72 -> 41771.229 | V72: =IF(U72>X72+0.000000001,1,0) -> 0 | W72: =MIN(U72,X72)*I72 -> 36810.118 | X72: =(X71-MIN(U71,X71))*G71/(1+F71) -> 1029708.4 | Y72: =IF(Eta_rif_VPW-B72<=1,1,IF(r_VPW=0,1/(Eta_rif_VPW-B72),r_VPW/(1-(1+r_VPW)^(-(Eta_rif_VPW-B72)))/(1+r_VPW))) -> 0.038425023 | Z72: =Y72*AD72*I72 -> 34957.976 | AA72: =Z72/I72 -> 39669.463 | AB72: =IF(AA72>AD72+0.000000001,1,0) -> 0 | AC72: =MIN(AA72,AD72)*I72 -> 34957.976 | AD72: =(AD71-MIN(AA71,AD71))*G71/(1+F71) -> 1032386.2 | AE72: =IF(OR(E71>=0,GK_variante=3),AG71,IF(GK_variante=2,AG71/(1+F71),IF(AK72*I72<=0,AG71/(1+F71),IF(AG71/(AK72*I72)>Tasso0,AG71/(1+F71),AG71)))) -> 38000 | AF72: =IF(AK72*I72<=0,9.9,AE72/(AK72*I72)) -> 0.04187737 | AG72: =IF(AND(AF72>Tasso0*(1+GK_banda),A72<=Anni-GK_ultimi),AE72*(1-GK_taglio),IF(AF72<Tasso0*(1-GK_banda),AE72*(1+GK_taglio),AE72)) -> 38000 | AH72: =AG72/I72 -> 43121.478 | AI72: =IF(AH72>AK72+0.000000001,1,0) -> 0 | AJ72: =MIN(AH72,AK72)*I72 -> 38000 | AK72: =(AK71-MIN(AH71,AK71))*G71/(1+F71) -> 1029708.4 | AL72: =MIN(MAX(Tasso0*AP72*I72,AL71*(1+VG_pav)),AL71*(1+VG_tetto)) -> 37050 | AM72: =AL72/I72 -> 42043.441 | AN72: =IF(AM72>AP72+0.000000001,1,0) -> 0 | AO72: =MIN(AM72,AP72)*I72 -> 37050 | AP72: =(AP71-MIN(AM71,AP71))*G71/(1+F71) -> 1029708.4 | AQ72: =IF(AND(A72<=Anni,M71>0),M72/M71-1,"") -> 0 | AR72: =IF(AND(A72<=Anni,R71>0),R72/R71-1,"") -> -0.031312681 | AS72: =IF(AND(A72<=Anni,W71>0),W72/W71-1,"") -> -0.031312681 | AT72: =IF(AND(A72<=Anni,AC71>0),AC72/AC71-1,"") -> -0.019762483 | AU72: =IF(AND(A72<=Anni,AJ71>0),AJ72/AJ71-1,"") -> 0 | AV72: =IF(AND(A72<=Anni,AO71>0),AO72/AO71-1,"") -> -0.025
A73: =A72+1 -> 3 | B73: =Eta_inizio+A73-1 -> 53 | C73: =Anno_inizio+A73-1 -> 2002 | D73: =IF(COUNTIFS('5 - Dati'!$A$6:$A$186,Serie,'5 - Dati'!$B$6:$B$186,C73)>0,1,0) -> 1 | E73: =IF(D73=1,SUMIFS('5 - Dati'!$F$6:$F$186,'5 - Dati'!$A$6:$A$186,Serie,'5 - Dati'!$B$6:$B$186,C73),(1+Rend_c)*(1+Infl_c)-1) -> -0.16524189 | F73: =IF(D73=1,SUMIFS('5 - Dati'!$E$6:$E$186,'5 - Dati'!$A$6:$A$186,Serie,'5 - Dati'!$B$6:$B$186,C73),Infl_c) -> 0.02868319 | G73: =(1+E73)*(1-Bollo_eff) -> 0.83308859 | H73: =H72/G72 -> 0.58718983 | I73: =1-Aliq_eff*MAX(0,1-H73) -> 0.89266936 | J73: =Spesa0 -> 38000 | K73: =J73/I73 -> 42568.953 | L73: =IF(K73>N73+0.000000001,1,0) -> 0 | M73: =MIN(K73,N73)*I73 -> 38000 | N73: =(N72-MIN(K72,N72))*G72/(1+F72) -> 892443.2 | O73: =Tasso0*S73*I73 -> 32361.467 | P73: =O73/I73 -> 36252.467 | Q73: =IF(P73>S73+0.000000001,1,0) -> 0 | R73: =MIN(P73,S73)*I73 -> 32361.467 | S73: =(S72-MIN(P72,S72))*G72/(1+F72) -> 893664.6 | T73: =MAX(Tasso0*X73*I73,Pav_pct*Spesa0) -> 34200 | U73: =T73/I73 -> 38312.058 | V73: =IF(U73>X73+0.000000001,1,0) -> 0 | W73: =MIN(U73,X73)*I73 -> 34200 | X73: =(X72-MIN(U72,X72))*G72/(1+F72) -> 893664.6 | Y73: =IF(Eta_rif_VPW-B73<=1,1,IF(r_VPW=0,1/(Eta_rif_VPW-B73),r_VPW/(1-(1+r_VPW)^(-(Eta_rif_VPW-B73)))/(1+r_VPW))) -> 0.038796608 | Z73: =Y73*AD73*I73 -> 31099.612 | AA73: =Z73/I73 -> 34838.893 | AB73: =IF(AA73>AD73+0.000000001,1,0) -> 0 | AC73: =MIN(AA73,AD73)*I73 -> 31099.612 | AD73: =(AD72-MIN(AA72,AD72))*G72/(1+F72) -> 897988.1 | AE73: =IF(OR(E72>=0,GK_variante=3),AG72,IF(GK_variante=2,AG72/(1+F72),IF(AK73*I73<=0,AG72/(1+F72),IF(AG72/(AK73*I73)>Tasso0,AG72/(1+F72),AG72)))) -> 37157.757 | AF73: =IF(AK73*I73<=0,9.9,AE73/(AK73*I73)) -> 0.046642119 | AG73: =IF(AND(AF73>Tasso0*(1+GK_banda),A73<=Anni-GK_ultimi),AE73*(1-GK_taglio),IF(AF73<Tasso0*(1-GK_banda),AE73*(1+GK_taglio),AE73)) -> 37157.757 | AH73: =AG73/I73 -> 41625.442 | AI73: =IF(AH73>AK73+0.000000001,1,0) -> 0 | AJ73: =MIN(AH73,AK73)*I73 -> 37157.757 | AK73: =(AK72-MIN(AH72,AK72))*G72/(1+F72) -> 892443.2 | AL73: =MIN(MAX(Tasso0*AP73*I73,AL72*(1+VG_pav)),AL72*(1+VG_tetto)) -> 36123.75 | AM73: =AL73/I73 -> 40467.111 | AN73: =IF(AM73>AP73+0.000000001,1,0) -> 0 | AO73: =MIN(AM73,AP73)*I73 -> 36123.75 | AP73: =(AP72-MIN(AM72,AP72))*G72/(1+F72) -> 893418.36 | AQ73: =IF(AND(A73<=Anni,M72>0),M73/M72-1,"") -> 0 | AR73: =IF(AND(A73<=Anni,R72>0),R73/R72-1,"") -> -0.12085404 | AS73: =IF(AND(A73<=Anni,W72>0),W73/W72-1,"") -> -0.070907627 | AT73: =IF(AND(A73<=Anni,AC72>0),AC73/AC72-1,"") -> -0.11037149 | AU73: =IF(AND(A73<=Anni,AJ72>0),AJ73/AJ72-1,"") -> -0.022164299 | AV73: =IF(AND(A73<=Anni,AO72>0),AO73/AO72-1,"") -> -0.025
A74: =A73+1 -> 4 | B74: =Eta_inizio+A74-1 -> 54 | C74: =Anno_inizio+A74-1 -> 2003 | D74: =IF(COUNTIFS('5 - Dati'!$A$6:$A$186,Serie,'5 - Dati'!$B$6:$B$186,C74)>0,1,0) -> 1 | E74: =IF(D74=1,SUMIFS('5 - Dati'!$F$6:$F$186,'5 - Dati'!$A$6:$A$186,Serie,'5 - Dati'!$B$6:$B$186,C74),(1+Rend_c)*(1+Infl_c)-1) -> 0.13171752 | F74: =IF(D74=1,SUMIFS('5 - Dati'!$E$6:$E$186,'5 - Dati'!$A$6:$A$186,Serie,'5 - Dati'!$B$6:$B$186,C74),Infl_c) -> 0.02154625 | G74: =(1+E74)*(1-Bollo_eff) -> 1.1294541 | H74: =H73/G73 -> 0.7048348 | I74: =1-Aliq_eff*MAX(0,1-H74) -> 0.92325705 | J74: =Spesa0 -> 38000 | K74: =J74/I74 -> 41158.635 | L74: =IF(K74>N74+0.000000001,1,0) -> 0 | M74: =MIN(K74,N74)*I74 -> 38000 | N74: =(N73-MIN(K73,N73))*G73/(1+F73) -> 688278.51 | O74: =Tasso0*S74*I74 -> 26006.674 | P74: =O74/I74 -> 28168.4 | Q74: =IF(P74>S74+0.000000001,1,0) -> 0 | R74: =MIN(P74,S74)*I74 -> 26006.674 | S74: =(S73-MIN(P73,S73))*G73/(1+F73) -> 694383.14 | T74: =MAX(Tasso0*X74*I74,Pav_pct*Spesa0) -> 34200 | U74: =T74/I74 -> 37042.772 | V74: =IF(U74>X74+0.000000001,1,0) -> 0 | W74: =MIN(U74,X74)*I74 -> 34200 | X74: =(X73-MIN(U73,X73))*G73/(1+F73) -> 692715.16 | Y74: =IF(Eta_rif_VPW-B74<=1,1,IF(r_VPW=0,1/(Eta_rif_VPW-B74),r_VPW/(1-(1+r_VPW)^(-(Eta_rif_VPW-B74)))/(1+r_VPW))) -> 0.03918693 | Z74: =Y74*AD74*I74 -> 25290.609 | AA74: =Z74/I74 -> 27392.815 | AB74: =IF(AA74>AD74+0.000000001,1,0) -> 0 | AC74: =MIN(AA74,AD74)*I74 -> 25290.609 | AD74: =(AD73-MIN(AA73,AD73))*G73/(1+F73) -> 699029.37 | AE74: =IF(OR(E73>=0,GK_variante=3),AG73,IF(GK_variante=2,AG73/(1+F73),IF(AK74*I74<=0,AG73/(1+F73),IF(AG73/(AK74*I74)>Tasso0,AG73/(1+F73),AG73)))) -> 36121.672 | AF74: =IF(AK74*I74<=0,9.9,AE74/(AK74*I74)) -> 0.056780488 | AG74: =IF(AND(AF74>Tasso0*(1+GK_banda),A74<=Anni-GK_ultimi),AE74*(1-GK_taglio),IF(AF74<Tasso0*(1-GK_banda),AE74*(1+GK_taglio),AE74)) -> 32509.505 | AH74: =AG74/I74 -> 35211.759 | AI74: =IF(AH74>AK74+0.000000001,1,0) -> 0 | AJ74: =MIN(AH74,AK74)*I74 -> 32509.505 | AK74: =(AK73-MIN(AH73,AK73))*G73/(1+F73) -> 689042.62 | AL74: =MIN(MAX(Tasso0*AP74*I74,AL73*(1+VG_pav)),AL73*(1+VG_tetto)) -> 35220.656 | AM74: =AL74/I74 -> 38148.267 | AN74: =IF(AM74>AP74+0.000000001,1,0) -> 0 | AO74: =MIN(AM74,AP74)*I74 -> 35220.656 | AP74: =(AP73-MIN(AM73,AP73))*G73/(1+F73) -> 690770.46 | AQ74: =IF(AND(A74<=Anni,M73>0),M74/M73-1,"") -> 0 | AR74: =IF(AND(A74<=Anni,R73>0),R74/R73-1,"") -> -0.19636911 | AS74: =IF(AND(A74<=Anni,W73>0),W74/W73-1,"") -> 0 | AT74: =IF(AND(A74<=Anni,AC73>0),AC74/AC73-1,"") -> -0.18678698 | AU74: =IF(AND(A74<=Anni,AJ73>0),AJ74/AJ73-1,"") -> -0.12509506 | AV74: =IF(AND(A74<=Anni,AO73>0),AO74/AO73-1,"") -> -0.025
A75: =A74+1 -> 5 | B75: =Eta_inizio+A75-1 -> 55 | C75: =Anno_inizio+A75-1 -> 2004 | D75: =IF(COUNTIFS('5 - Dati'!$A$6:$A$186,Serie,'5 - Dati'!$B$6:$B$186,C75)>0,1,0) -> 1 | E75: =IF(D75=1,SUMIFS('5 - Dati'!$F$6:$F$186,'5 - Dati'!$A$6:$A$186,Serie,'5 - Dati'!$B$6:$B$186,C75),(1+Rend_c)*(1+Infl_c)-1) -> 0.077222002 | F75: =IF(D75=1,SUMIFS('5 - Dati'!$E$6:$E$186,'5 - Dati'!$A$6:$A$186,Serie,'5 - Dati'!$B$6:$B$186,C75),Infl_c) -> 0.01985112 | G75: =(1+E75)*(1-Bollo_eff) -> 1.0750676 | H75: =H74/G74 -> 0.6240491 | I75: =1-Aliq_eff*MAX(0,1-H75) -> 0.90225277 | J75: =Spesa0 -> 38000 | K75: =J75/I75 -> 42116.801 | L75: =IF(K75>N75+0.000000001,1,0) -> 0 | M75: =MIN(K75,N75)*I75 -> 38000 | N75: =(N74-MIN(K74,N74))*G74/(1+F74) -> 715476.36 | O75: =Tasso0*S75*I75 -> 26959.76 | P75: =O75/I75 -> 29880.496 | Q75: =IF(P75>S75+0.000000001,1,0) -> 0 | R75: =MIN(P75,S75)*I75 -> 26959.76 | S75: =(S74-MIN(P74,S74))*G74/(1+F74) -> 736588.25 | T75: =MAX(Tasso0*X75*I75,Pav_pct*Spesa0) -> 34200 | U75: =T75/I75 -> 37905.121 | V75: =IF(U75>X75+0.000000001,1,0) -> 0 | W75: =MIN(U75,X75)*I75 -> 34200 | X75: =(X74-MIN(U74,X74))*G74/(1+F74) -> 724932.29 | Y75: =IF(Eta_rif_VPW-B75<=1,1,IF(r_VPW=0,1/(Eta_rif_VPW-B75),r_VPW/(1-(1+r_VPW)^(-(Eta_rif_VPW-B75)))/(1+r_VPW))) -> 0.039597258 | Z75: =Y75*AD75*I75 -> 26530.058 | AA75: =Z75/I75 -> 29404.242 | AB75: =IF(AA75>AD75+0.000000001,1,0) -> 0 | AC75: =MIN(AA75,AD75)*I75 -> 26530.058 | AD75: =(AD74-MIN(AA74,AD74))*G74/(1+F74) -> 742582.78 | AE75: =IF(OR(E74>=0,GK_variante=3),AG74,IF(GK_variante=2,AG74/(1+F74),IF(AK75*I75<=0,AG74/(1+F74),IF(AG74/(AK75*I75)>Tasso0,AG74/(1+F74),AG74)))) -> 32509.505 | AF75: =IF(AK75*I75<=0,9.9,AE75/(AK75*I75)) -> 0.049843229 | AG75: =IF(AND(AF75>Tasso0*(1+GK_banda),A75<=Anni-GK_ultimi),AE75*(1-GK_taglio),IF(AF75<Tasso0*(1-GK_banda),AE75*(1+GK_taglio),AE75)) -> 29258.554 | AH75: =AG75/I75 -> 32428.334 | AI75: =IF(AH75>AK75+0.000000001,1,0) -> 0 | AJ75: =MIN(AH75,AK75)*I75 -> 29258.554 | AK75: =(AK74-MIN(AH74,AK74))*G74/(1+F74) -> 722896.24 | AL75: =MIN(MAX(Tasso0*AP75*I75,AL74*(1+VG_pav)),AL74*(1+VG_tetto)) -> 34340.14 | AM75: =AL75/I75 -> 38060.443 | AN75: =IF(AM75>AP75+0.000000001,1,0) -> 0 | AO75: =MIN(AM75,AP75)*I75 -> 34340.14 | AP75: =(AP74-MIN(AM74,AP74))*G74/(1+F74) -> 721559.89 | AQ75: =IF(AND(A75<=Anni,M74>0),M75/M74-1,"") -> 0 | AR75: =IF(AND(A75<=Anni,R74>0),R75/R74-1,"") -> 0.036647742 | AS75: =IF(AND(A75<=Anni,W74>0),W75/W74-1,"") -> 0 | AT75: =IF(AND(A75<=Anni,AC74>0),AC75/AC74-1,"") -> 0.049008269 | AU75: =IF(AND(A75<=Anni,AJ74>0),AJ75/AJ74-1,"") -> -0.1 | AV75: =IF(AND(A75<=Anni,AO74>0),AO75/AO74-1,"") -> -0.025
A76: =A75+1 -> 6 | B76: =Eta_inizio+A76-1 -> 56 | C76: =Anno_inizio+A76-1 -> 2005 | D76: =IF(COUNTIFS('5 - Dati'!$A$6:$A$186,Serie,'5 - Dati'!$B$6:$B$186,C76)>0,1,0) -> 1 | E76: =IF(D76=1,SUMIFS('5 - Dati'!$F$6:$F$186,'5 - Dati'!$A$6:$A$186,Serie,'5 - Dati'!$B$6:$B$186,C76),(1+Rend_c)*(1+Infl_c)-1) -> 0.1702335 | F76: =IF(D76=1,SUMIFS('5 - Dati'!$E$6:$E$186,'5 - Dati'!$A$6:$A$186,Serie,'5 - Dati'!$B$6:$B$186,C76),Infl_c) -> 0.02189781 | G76: =(1+E76)*(1-Bollo_eff) -> 1.167893 | H76: =H75/G75 -> 0.58047431 | I76: =1-Aliq_eff*MAX(0,1-H76) -> 0.89092332 | J76: =Spesa0 -> 38000 | K76: =J76/I76 -> 42652.38 | L76: =IF(K76>N76+0.000000001,1,0) -> 0 | M76: =MIN(K76,N76)*I76 -> 38000 | N76: =(N75-MIN(K75,N75))*G75/(1+F75) -> 709816.36 | O76: =Tasso0*S76*I76 -> 26924.161 | P76: =O76/I76 -> 30220.514 | Q76: =IF(P76>S76+0.000000001,1,0) -> 0 | R76: =MIN(P76,S76)*I76 -> 26924.161 | S76: =(S75-MIN(P75,S75))*G75/(1+F75) -> 744970.09 | T76: =MAX(Tasso0*X76*I76,Pav_pct*Spesa0) -> 34200 | U76: =T76/I76 -> 38387.142 | V76: =IF(U76>X76+0.000000001,1,0) -> 0 | W76: =MIN(U76,X76)*I76 -> 34200 | X76: =(X75-MIN(U75,X75))*G75/(1+F75) -> 724223.96 | Y76: =IF(Eta_rif_VPW-B76<=1,1,IF(r_VPW=0,1/(Eta_rif_VPW-B76),r_VPW/(1-(1+r_VPW)^(-(Eta_rif_VPW-B76)))/(1+r_VPW))) -> 0.040028978 | Z76: =Y76*AD76*I76 -> 26810.942 | AA76: =Z76/I76 -> 30093.433 | AB76: =IF(AA76>AD76+0.000000001,1,0) -> 0 | AC76: =MIN(AA76,AD76)*I76 -> 26810.942 | AD76: =(AD75-MIN(AA75,AD75))*G75/(1+F75) -> 751791.21 | AE76: =IF(OR(E75>=0,GK_variante=3),AG75,IF(GK_variante=2,AG75/(1+F75),IF(AK76*I76<=0,AG75/(1+F75),IF(AG75/(AK76*I76)>Tasso0,AG75/(1+F75),AG75)))) -> 29258.554 | AF76: =IF(AK76*I76<=0,9.9,AE76/(AK76*I76)) -> 0.045120101 | AG76: =IF(AND(AF76>Tasso0*(1+GK_banda),A76<=Anni-GK_ultimi),AE76*(1-GK_taglio),IF(AF76<Tasso0*(1-GK_banda),AE76*(1+GK_taglio),AE76)) -> 29258.554 | AH76: =AG76/I76 -> 32840.71 | AI76: =IF(AH76>AK76+0.000000001,1,0) -> 0 | AJ76: =MIN(AH76,AK76)*I76 -> 29258.554 | AK76: =(AK75-MIN(AH75,AK75))*G75/(1+F75) -> 727850.99 | AL76: =MIN(MAX(Tasso0*AP76*I76,AL75*(1+VG_pav)),AL75*(1+VG_tetto)) -> 33481.636 | AM76: =AL76/I76 -> 37580.828 | AN76: =IF(AM76>AP76+0.000000001,1,0) -> 0 | AO76: =MIN(AM76,AP76)*I76 -> 33481.636 | AP76: =(AP75-MIN(AM75,AP75))*G75/(1+F75) -> 720505.25 | AQ76: =IF(AND(A76<=Anni,M75>0),M76/M75-1,"") -> 0 | AR76: =IF(AND(A76<=Anni,R75>0),R76/R75-1,"") -> -0.0013204567 | AS76: =IF(AND(A76<=Anni,W75>0),W76/W75-1,"") -> 0 | AT76: =IF(AND(A76<=Anni,AC75>0),AC76/AC75-1,"") -> 0.010587355 | AU76: =IF(AND(A76<=Anni,AJ75>0),AJ76/AJ75-1,"") -> 0 | AV76: =IF(AND(A76<=Anni,AO75>0),AO76/AO75-1,"") -> -0.025
A77: =A76+1 -> 7 | B77: =Eta_inizio+A77-1 -> 57 | C77: =Anno_inizio+A77-1 -> 2006 | D77: =IF(COUNTIFS('5 - Dati'!$A$6:$A$186,Serie,'5 - Dati'!$B$6:$B$186,C77)>0,1,0) -> 1 | E77: =IF(D77=1,SUMIFS('5 - Dati'!$F$6:$F$186,'5 - Dati'!$A$6:$A$186,Serie,'5 - Dati'!$B$6:$B$186,C77),(1+Rend_c)*(1+Infl_c)-1) -> 0.048259824 | F77: =IF(D77=1,SUMIFS('5 - Dati'!$E$6:$E$186,'5 - Dati'!$A$6:$A$186,Serie,'5 - Dati'!$B$6:$B$186,C77),Infl_c) -> 0.01904762 | G77: =(1+E77)*(1-Bollo_eff) -> 1.0461633 | H77: =H76/G76 -> 0.49702695 | I77: =1-Aliq_eff*MAX(0,1-H77) -> 0.86922701 | J77: =Spesa0 -> 38000 | K77: =J77/I77 -> 43717.003 | L77: =IF(K77>N77+0.000000001,1,0) -> 0 | M77: =MIN(K77,N77)*I77 -> 38000 | N77: =(N76-MIN(K76,N76))*G76/(1+F76) -> 762479.54 | O77: =Tasso0*S77*I77 -> 28803.531 | P77: =O77/I77 -> 33136.949 | Q77: =IF(P77>S77+0.000000001,1,0) -> 0 | R77: =MIN(P77,S77)*I77 -> 28803.531 | S77: =(S76-MIN(P76,S76))*G76/(1+F76) -> 816863.52 | T77: =MAX(Tasso0*X77*I77,Pav_pct*Spesa0) -> 34200 | U77: =T77/I77 -> 39345.303 | V77: =IF(U77>X77+0.000000001,1,0) -> 0 | W77: =MIN(U77,X77)*I77 -> 34200 | X77: =(X76-MIN(U76,X76))*G76/(1+F76) -> 783820.1 | Y77: =IF(Eta_rif_VPW-B77<=1,1,IF(r_VPW=0,1/(Eta_rif_VPW-B77),r_VPW/(1-(1+r_VPW)^(-(Eta_rif_VPW-B77)))/(1+r_VPW))) -> 0.040483602 | Z77: =Y77*AD77*I77 -> 29024.405 | AA77: =Z77/I77 -> 33391.053 | AB77: =IF(AA77>AD77+0.000000001,1,0) -> 0 | AC77: =MIN(AA77,AD77)*I77 -> 29024.405 | AD77: =(AD76-MIN(AA76,AD76))*G76/(1+F76) -> 824804.39 | AE77: =IF(OR(E76>=0,GK_variante=3),AG76,IF(GK_variante=2,AG76/(1+F76),IF(AK77*I77<=0,AG76/(1+F76),IF(AG76/(AK77*I77)>Tasso0,AG76/(1+F76),AG76)))) -> 29258.554 | AF77: =IF(AK77*I77<=0,9.9,AE77/(AK77*I77)) -> 0.042377255 | AG77: =IF(AND(AF77>Tasso0*(1+GK_banda),A77<=Anni-GK_ultimi),AE77*(1-GK_taglio),IF(AF77<Tasso0*(1-GK_banda),AE77*(1+GK_taglio),AE77)) -> 29258.554 | AH77: =AG77/I77 -> 33660.429 | AI77: =IF(AH77>AK77+0.000000001,1,0) -> 0 | AJ77: =MIN(AH77,AK77)*I77 -> 29258.554 | AK77: =(AK76-MIN(AH76,AK76))*G76/(1+F76) -> 794304.14 | AL77: =MIN(MAX(Tasso0*AP77*I77,AL76*(1+VG_pav)),AL76*(1+VG_tetto)) -> 32644.595 | AM77: =AL77/I77 -> 37555.892 | AN77: =IF(AM77>AP77+0.000000001,1,0) -> 0 | AO77: =MIN(AM77,AP77)*I77 -> 32644.595 | AP77: =(AP76-MIN(AM76,AP76))*G76/(1+F76) -> 780491.61 | AQ77: =IF(AND(A77<=Anni,M76>0),M77/M76-1,"") -> 0 | AR77: =IF(AND(A77<=Anni,R76>0),R77/R76-1,"") -> 0.069802365 | AS77: =IF(AND(A77<=Anni,W76>0),W77/W76-1,"") -> 0 | AT77: =IF(AND(A77<=Anni,AC76>0),AC77/AC76-1,"") -> 0.082558213 | AU77: =IF(AND(A77<=Anni,AJ76>0),AJ77/AJ76-1,"") -> -1.110223e-16 | AV77: =IF(AND(A77<=Anni,AO76>0),AO77/AO76-1,"") -> -0.025
A78: =A77+1 -> 8 | B78: =Eta_inizio+A78-1 -> 58 | C78: =Anno_inizio+A78-1 -> 2007 | D78: =IF(COUNTIFS('5 - Dati'!$A$6:$A$186,Serie,'5 - Dati'!$B$6:$B$186,C78)>0,1,0) -> 1 | E78: =IF(D78=1,SUMIFS('5 - Dati'!$F$6:$F$186,'5 - Dati'!$A$6:$A$186,Serie,'5 - Dati'!$B$6:$B$186,C78),(1+Rend_c)*(1+Infl_c)-1) -> -0.056818348 | F78: =IF(D78=1,SUMIFS('5 - Dati'!$E$6:$E$186,'5 - Dati'!$A$6:$A$186,Serie,'5 - Dati'!$B$6:$B$186,C78),Infl_c) -> 0.03154206 | G78: =(1+E78)*(1-Bollo_eff) -> 0.94129529 | H78: =H77/G77 -> 0.47509499 | I78: =1-Aliq_eff*MAX(0,1-H78) -> 0.8635247 | J78: =Spesa0 -> 38000 | K78: =J78/I78 -> 44005.69 | L78: =IF(K78>N78+0.000000001,1,0) -> 0 | M78: =MIN(K78,N78)*I78 -> 38000 | N78: =(N77-MIN(K77,N77))*G77/(1+F77) -> 737887.98 | O78: =Tasso0*S78*I78 -> 28184.307 | P78: =O78/I78 -> 32638.681 | Q78: =IF(P78>S78+0.000000001,1,0) -> 0 | R78: =MIN(P78,S78)*I78 -> 28184.307 | S78: =(S77-MIN(P77,S77))*G77/(1+F77) -> 804580.64 | T78: =MAX(Tasso0*X78*I78,Pav_pct*Spesa0) -> 34200 | U78: =T78/I78 -> 39605.121 | V78: =IF(U78>X78+0.000000001,1,0) -> 0 | W78: =MIN(U78,X78)*I78 -> 34200 | X78: =(X77-MIN(U77,X77))*G77/(1+F77) -> 764284.42 | Y78: =IF(Eta_rif_VPW-B78<=1,1,IF(r_VPW=0,1/(Eta_rif_VPW-B78),r_VPW/(1-(1+r_VPW)^(-(Eta_rif_VPW-B78)))/(1+r_VPW))) -> 0.040962789 | Z78: =Y78*AD78*I78 -> 28739.066 | AA78: =Z78/I78 -> 33281.117 | AB78: =IF(AA78>AD78+0.000000001,1,0) -> 0 | AC78: =MIN(AA78,AD78)*I78 -> 28739.066 | AD78: =(AD77-MIN(AA77,AD77))*G77/(1+F77) -> 812471.94 | AE78: =IF(OR(E77>=0,GK_variante=3),AG77,IF(GK_variante=2,AG77/(1+F77),IF(AK78*I78<=0,AG77/(1+F77),IF(AG77/(AK78*I78)>Tasso0,AG77/(1+F77),AG77)))) -> 29258.554 | AF78: =IF(AK78*I78<=0,9.9,AE78/(AK78*I78)) -> 0.043390216 | AG78: =IF(AND(AF78>Tasso0*(1+GK_banda),A78<=Anni-GK_ultimi),AE78*(1-GK_taglio),IF(AF78<Tasso0*(1-GK_banda),AE78*(1+GK_taglio),AE78)) -> 29258.554 | AH78: =AG78/I78 -> 33882.707 | AI78: =IF(AH78>AK78+0.000000001,1,0) -> 0 | AJ78: =MIN(AH78,AK78)*I78 -> 29258.554 | AK78: =(AK77-MIN(AH77,AK77))*G77/(1+F77) -> 780883.57 | AL78: =MIN(MAX(Tasso0*AP78*I78,AL77*(1+VG_pav)),AL77*(1+VG_tetto)) -> 31828.481 | AM78: =AL78/I78 -> 36858.796 | AN78: =IF(AM78>AP78+0.000000001,1,0) -> 0 | AO78: =MIN(AM78,AP78)*I78 -> 31828.481 | AP78: =(AP77-MIN(AM77,AP77))*G77/(1+F77) -> 762704.39 | AQ78: =IF(AND(A78<=Anni,M77>0),M78/M77-1,"") -> 0 | AR78: =IF(AND(A78<=Anni,R77>0),R78/R77-1,"") -> -0.021498208 | AS78: =IF(AND(A78<=Anni,W77>0),W78/W77-1,"") -> 0 | AT78: =IF(AND(A78<=Anni,AC77>0),AC78/AC77-1,"") -> -0.0098309868 | AU78: =IF(AND(A78<=Anni,AJ77>0),AJ78/AJ77-1,"") -> 0 | AV78: =IF(AND(A78<=Anni,AO77>0),AO78/AO77-1,"") -> -0.025
A79: =A78+1 -> 9 | B79: =Eta_inizio+A79-1 -> 59 | C79: =Anno_inizio+A79-1 -> 2008 | D79: =IF(COUNTIFS('5 - Dati'!$A$6:$A$186,Serie,'5 - Dati'!$B$6:$B$186,C79)>0,1,0) -> 1 | E79: =IF(D79=1,SUMIFS('5 - Dati'!$F$6:$F$186,'5 - Dati'!$A$6:$A$186,Serie,'5 - Dati'!$B$6:$B$186,C79),(1+Rend_c)*(1+Infl_c)-1) -> -0.16201672 | F79: =IF(D79=1,SUMIFS('5 - Dati'!$E$6:$E$186,'5 - Dati'!$A$6:$A$186,Serie,'5 - Dati'!$B$6:$B$186,C79),Infl_c) -> 0.01359004 | G79: =(1+E79)*(1-Bollo_eff) -> 0.83630731 | H79: =H78/G78 -> 0.50472471 | I79: =1-Aliq_eff*MAX(0,1-H79) -> 0.87122842 | J79: =Spesa0 -> 38000 | K79: =J79/I79 -> 43616.575 | L79: =IF(K79>N79+0.000000001,1,0) -> 0 | M79: =MIN(K79,N79)*I79 -> 38000 | N79: =(N78-MIN(K78,N78))*G78/(1+F78) -> 633176.44 | O79: =Tasso0*S79*I79 -> 24895.373 | P79: =O79/I79 -> 28575.024 | Q79: =IF(P79>S79+0.000000001,1,0) -> 0 | R79: =MIN(P79,S79)*I79 -> 24895.373 | S79: =(S78-MIN(P78,S78))*G78/(1+F78) -> 704406.88 | T79: =MAX(Tasso0*X79*I79,Pav_pct*Spesa0) -> 34200 | U79: =T79/I79 -> 39254.918 | V79: =IF(U79>X79+0.000000001,1,0) -> 0 | W79: =MIN(U79,X79)*I79 -> 34200 | X79: =(X78-MIN(U78,X78))*G78/(1+F78) -> 661279.1 | Y79: =IF(Eta_rif_VPW-B79<=1,1,IF(r_VPW=0,1/(Eta_rif_VPW-B79),r_VPW/(1-(1+r_VPW)^(-(Eta_rif_VPW-B79)))/(1+r_VPW))) -> 0.041468358 | Z79: =Y79*AD79*I79 -> 25688.08 | AA79: =Z79/I79 -> 29484.897 | AB79: =IF(AA79>AD79+0.000000001,1,0) -> 0 | AC79: =MIN(AA79,AD79)*I79 -> 25688.08 | AD79: =(AD78-MIN(AA78,AD78))*G78/(1+F78) -> 711021.56 | AE79: =IF(OR(E78>=0,GK_variante=3),AG78,IF(GK_variante=2,AG78/(1+F78),IF(AK79*I79<=0,AG78/(1+F78),IF(AG78/(AK79*I79)>Tasso0,AG78/(1+F78),AG78)))) -> 28363.898 | AF79: =IF(AK79*I79<=0,9.9,AE79/(AK79*I79)) -> 0.047761047 | AG79: =IF(AND(AF79>Tasso0*(1+GK_banda),A79<=Anni-GK_ultimi),AE79*(1-GK_taglio),IF(AF79<Tasso0*(1-GK_banda),AE79*(1+GK_taglio),AE79)) -> 28363.898 | AH79: =AG79/I79 -> 32556.213 | AI79: =IF(AH79>AK79+0.000000001,1,0) -> 0 | AJ79: =MIN(AH79,AK79)*I79 -> 28363.898 | AK79: =(AK78-MIN(AH78,AK78))*G78/(1+F78) -> 681647.81 | AL79: =MIN(MAX(Tasso0*AP79*I79,AL78*(1+VG_pav)),AL78*(1+VG_tetto)) -> 31032.769 | AM79: =AL79/I79 -> 35619.555 | AN79: =IF(AM79>AP79+0.000000001,1,0) -> 0 | AO79: =MIN(AM79,AP79)*I79 -> 31032.769 | AP79: =(AP78-MIN(AM78,AP78))*G78/(1+F78) -> 662343.36 | AQ79: =IF(AND(A79<=Anni,M78>0),M79/M78-1,"") -> 0 | AR79: =IF(AND(A79<=Anni,R78>0),R79/R78-1,"") -> -0.11669378 | AS79: =IF(AND(A79<=Anni,W78>0),W79/W78-1,"") -> 0 | AT79: =IF(AND(A79<=Anni,AC78>0),AC79/AC78-1,"") -> -0.10616163 | AU79: =IF(AND(A79<=Anni,AJ78>0),AJ79/AJ78-1,"") -> -0.03057758 | AV79: =IF(AND(A79<=Anni,AO78>0),AO79/AO78-1,"") -> -0.025
A80: =A79+1 -> 10 | B80: =Eta_inizio+A80-1 -> 60 | C80: =Anno_inizio+A80-1 -> 2009 | D80: =IF(COUNTIFS('5 - Dati'!$A$6:$A$186,Serie,'5 - Dati'!$B$6:$B$186,C80)>0,1,0) -> 1 | E80: =IF(D80=1,SUMIFS('5 - Dati'!$F$6:$F$186,'5 - Dati'!$A$6:$A$186,Serie,'5 - Dati'!$B$6:$B$186,C80),(1+Rend_c)*(1+Infl_c)-1) -> 0.17647119 | F80: =IF(D80=1,SUMIFS('5 - Dati'!$E$6:$E$186,'5 - Dati'!$A$6:$A$186,Serie,'5 - Dati'!$B$6:$B$186,C80),Infl_c) -> 0.01340782 | G80: =(1+E80)*(1-Bollo_eff) -> 1.1741182 | H80: =H79/G79 -> 0.60351584 | I80: =1-Aliq_eff*MAX(0,1-H80) -> 0.89691412 | J80: =Spesa0 -> 38000 | K80: =J80/I80 -> 42367.49 | L80: =IF(K80>N80+0.000000001,1,0) -> 0 | M80: =MIN(K80,N80)*I80 -> 38000 | N80: =(N79-MIN(K79,N79))*G79/(1+F79) -> 486442.45 | O80: =Tasso0*S80*I80 -> 20288.788 | P80: =O80/I80 -> 22620.658 | Q80: =IF(P80>S80+0.000000001,1,0) -> 0 | R80: =MIN(P80,S80)*I80 -> 20288.788 | S80: =(S79-MIN(P79,S79))*G79/(1+F79) -> 557624.98 | T80: =MAX(Tasso0*X80*I80,Pav_pct*Spesa0) -> 34200 | U80: =T80/I80 -> 38130.741 | V80: =IF(U80>X80+0.000000001,1,0) -> 0 | W80: =MIN(U80,X80)*I80 -> 34200 | X80: =(X79-MIN(U79,X79))*G79/(1+F79) -> 513228.58 | Y80: =IF(Eta_rif_VPW-B80<=1,1,IF(r_VPW=0,1/(Eta_rif_VPW-B80),r_VPW/(1-(1+r_VPW)^(-(Eta_rif_VPW-B80)))/(1+r_VPW))) -> 0.042002309 | Z80: =Y80*AD80*I80 -> 21184.431 | AA80: =Z80/I80 -> 23619.242 | AB80: =IF(AA80>AD80+0.000000001,1,0) -> 0 | AC80: =MIN(AA80,AD80)*I80 -> 21184.431 | AD80: =(AD79-MIN(AA79,AD79))*G79/(1+F79) -> 562331.98 | AE80: =IF(OR(E79>=0,GK_variante=3),AG79,IF(GK_variante=2,AG79/(1+F79),IF(AK80*I80<=0,AG79/(1+F79),IF(AG79/(AK80*I80)>Tasso0,AG79/(1+F79),AG79)))) -> 27983.6 | AF80: =IF(AK80*I80<=0,9.9,AE80/(AK80*I80)) -> 0.058256338 | AG80: =IF(AND(AF80>Tasso0*(1+GK_banda),A80<=Anni-GK_ultimi),AE80*(1-GK_taglio),IF(AF80<Tasso0*(1-GK_banda),AE80*(1+GK_taglio),AE80)) -> 25185.24 | AH80: =AG80/I80 -> 28079.879 | AI80: =IF(AH80>AK80+0.000000001,1,0) -> 0 | AJ80: =MIN(AH80,AK80)*I80 -> 25185.24 | AK80: =(AK79-MIN(AH79,AK79))*G79/(1+F79) -> 535561.74 | AL80: =MIN(MAX(Tasso0*AP80*I80,AL79*(1+VG_pav)),AL79*(1+VG_tetto)) -> 30256.949 | AM80: =AL80/I80 -> 33734.5 | AN80: =IF(AM80>AP80+0.000000001,1,0) -> 0 | AO80: =MIN(AM80,AP80)*I80 -> 30256.949 | AP80: =(AP79-MIN(AM79,AP79))*G79/(1+F79) -> 517106.21 | AQ80: =IF(AND(A80<=Anni,M79>0),M80/M79-1,"") -> 0 | AR80: =IF(AND(A80<=Anni,R79>0),R80/R79-1,"") -> -0.18503782 | AS80: =IF(AND(A80<=Anni,W79>0),W80/W79-1,"") -> 0 | AT80: =IF(AND(A80<=Anni,AC79>0),AC80/AC79-1,"") -> -0.17532058 | AU80: =IF(AND(A80<=Anni,AJ79>0),AJ80/AJ79-1,"") -> -0.11206704 | AV80: =IF(AND(A80<=Anni,AO79>0),AO80/AO79-1,"") -> -0.025
A81: =A80+1 -> 11 | B81: =Eta_inizio+A81-1 -> 61 | C81: =Anno_inizio+A81-1 -> 2010 | D81: =IF(COUNTIFS('5 - Dati'!$A$6:$A$186,Serie,'5 - Dati'!$B$6:$B$186,C81)>0,1,0) -> 1 | E81: =IF(D81=1,SUMIFS('5 - Dati'!$F$6:$F$186,'5 - Dati'!$A$6:$A$186,Serie,'5 - Dati'!$B$6:$B$186,C81),(1+Rend_c)*(1+Infl_c)-1) -> 0.14011382 | F81: =IF(D81=1,SUMIFS('5 - Dati'!$E$6:$E$186,'5 - Dati'!$A$6:$A$186,Serie,'5 - Dati'!$B$6:$B$186,C81),Infl_c) -> 0.01984564 | G81: =(1+E81)*(1-Bollo_eff) -> 1.1378336 | H81: =H80/G80 -> 0.51401624 | I81: =1-Aliq_eff*MAX(0,1-H81) -> 0.87364422 | J81: =Spesa0 -> 38000 | K81: =J81/I81 -> 43495.967 | L81: =IF(K81>N81+0.000000001,1,0) -> 0 | M81: =MIN(K81,N81)*I81 -> 38000 | N81: =(N80-MIN(K80,N80))*G80/(1+F80) -> 514498.22 | O81: =Tasso0*S81*I81 -> 21967.594 | P81: =O81/I81 -> 25144.783 | Q81: =IF(P81>S81+0.000000001,1,0) -> 0 | R81: =MIN(P81,S81)*I81 -> 21967.594 | S81: =(S80-MIN(P80,S80))*G80/(1+F80) -> 619847.53 | T81: =MAX(Tasso0*X81*I81,Pav_pct*Spesa0) -> 34200 | U81: =T81/I81 -> 39146.37 | V81: =IF(U81>X81+0.000000001,1,0) -> 0 | W81: =MIN(U81,X81)*I81 -> 34200 | X81: =(X80-MIN(U80,X80))*G80/(1+F80) -> 550440.83 | Y81: =IF(Eta_rif_VPW-B81<=1,1,IF(r_VPW=0,1/(Eta_rif_VPW-B81),r_VPW/(1-(1+r_VPW)^(-(Eta_rif_VPW-B81)))/(1+r_VPW))) -> 0.042566846 | Z81: =Y81*AD81*I81 -> 23210.843 | AA81: =Z81/I81 -> 26567.844 | AB81: =IF(AA81>AD81+0.000000001,1,0) -> 0 | AC81: =MIN(AA81,AD81)*I81 -> 23210.843 | AD81: =(AD80-MIN(AA80,AD80))*G80/(1+F80) -> 624144.05 | AE81: =IF(OR(E80>=0,GK_variante=3),AG80,IF(GK_variante=2,AG80/(1+F80),IF(AK81*I81<=0,AG80/(1+F80),IF(AG80/(AK81*I81)>Tasso0,AG80/(1+F80),AG80)))) -> 25185.24 | AF81: =IF(AK81*I81<=0,9.9,AE81/(AK81*I81)) -> 0.049030167 | AG81: =IF(AND(AF81>Tasso0*(1+GK_banda),A81<=Anni-GK_ultimi),AE81*(1-GK_taglio),IF(AF81<Tasso0*(1-GK_banda),AE81*(1+GK_taglio),AE81)) -> 22666.716 | AH81: =AG81/I81 -> 25945.019 | AI81: =IF(AH81>AK81+0.000000001,1,0) -> 0 | AJ81: =MIN(AH81,AK81)*I81 -> 22666.716 | AK81: =(AK80-MIN(AH80,AK80))*G80/(1+F80) -> 587960.45 | AL81: =MIN(MAX(Tasso0*AP81*I81,AL80*(1+VG_pav)),AL80*(1+VG_tetto)) -> 29500.526 | AM81: =AL81/I81 -> 33767.207 | AN81: =IF(AM81>AP81+0.000000001,1,0) -> 0 | AO81: =MIN(AM81,AP81)*I81 -> 29500.526 | AP81: =(AP80-MIN(AM80,AP80))*G80/(1+F80) -> 560026.8 | AQ81: =IF(AND(A81<=Anni,M80>0),M81/M80-1,"") -> 0 | AR81: =IF(AND(A81<=Anni,R80>0),R81/R80-1,"") -> 0.08274554 | AS81: =IF(AND(A81<=Anni,W80>0),W81/W80-1,"") -> 0 | AT81: =IF(AND(A81<=Anni,AC80>0),AC81/AC80-1,"") -> 0.095655717 | AU81: =IF(AND(A81<=Anni,AJ80>0),AJ81/AJ80-1,"") -> -0.1 | AV81: =IF(AND(A81<=Anni,AO80>0),AO81/AO80-1,"") -> -0.025
A82: =A81+1 -> 12 | B82: =Eta_inizio+A82-1 -> 62 | C82: =Anno_inizio+A82-1 -> 2011 | D82: =IF(COUNTIFS('5 - Dati'!$A$6:$A$186,Serie,'5 - Dati'!$B$6:$B$186,C82)>0,1,0) -> 1 | E82: =IF(D82=1,SUMIFS('5 - Dati'!$F$6:$F$186,'5 - Dati'!$A$6:$A$186,Serie,'5 - Dati'!$B$6:$B$186,C82),(1+Rend_c)*(1+Infl_c)-1) -> 0.071929896 | F82: =IF(D82=1,SUMIFS('5 - Dati'!$E$6:$E$186,'5 - Dati'!$A$6:$A$186,Serie,'5 - Dati'!$B$6:$B$186,C82),Infl_c) -> 0.03351352 | G82: =(1+E82)*(1-Bollo_eff) -> 1.069786 | H82: =H81/G81 -> 0.45174992 | I82: =1-Aliq_eff*MAX(0,1-H82) -> 0.85745498 | J82: =Spesa0 -> 38000 | K82: =J82/I82 -> 44317.196 | L82: =IF(K82>N82+0.000000001,1,0) -> 0 | M82: =MIN(K82,N82)*I82 -> 38000 | N82: =(N81-MIN(K81,N81))*G81/(1+F81) -> 525493.43 | O82: =Tasso0*S82*I82 -> 23079.086 | P82: =O82/I82 -> 26915.799 | Q82: =IF(P82>S82+0.000000001,1,0) -> 0 | R82: =MIN(P82,S82)*I82 -> 23079.086 | S82: =(S81-MIN(P81,S81))*G81/(1+F81) -> 663505.08 | T82: =MAX(Tasso0*X82*I82,Pav_pct*Spesa0) -> 34200 | U82: =T82/I82 -> 39885.476 | V82: =IF(U82>X82+0.000000001,1,0) -> 0 | W82: =MIN(U82,X82)*I82 -> 34200 | X82: =(X81-MIN(U81,X81))*G81/(1+F81) -> 570447.12 | Y82: =IF(Eta_rif_VPW-B82<=1,1,IF(r_VPW=0,1/(Eta_rif_VPW-B82),r_VPW/(1-(1+r_VPW)^(-(Eta_rif_VPW-B82)))/(1+r_VPW))) -> 0.043164408 | Z82: =Y82*AD82*I82 -> 24675.998 | AA82: =Z82/I82 -> 28778.185 | AB82: =IF(AA82>AD82+0.000000001,1,0) -> 0 | AC82: =MIN(AA82,AD82)*I82 -> 24675.998 | AD82: =(AD81-MIN(AA81,AD81))*G81/(1+F81) -> 666710.98 | AE82: =IF(OR(E81>=0,GK_variante=3),AG81,IF(GK_variante=2,AG81/(1+F81),IF(AK82*I82<=0,AG81/(1+F81),IF(AG81/(AK82*I82)>Tasso0,AG81/(1+F81),AG81)))) -> 22666.716 | AF82: =IF(AK82*I82<=0,9.9,AE82/(AK82*I82)) -> 0.042158459 | AG82: =IF(AND(AF82>Tasso0*(1+GK_banda),A82<=Anni-GK_ultimi),AE82*(1-GK_taglio),IF(AF82<Tasso0*(1-GK_banda),AE82*(1+GK_taglio),AE82)) -> 22666.716 | AH82: =AG82/I82 -> 26434.876 | AI82: =IF(AH82>AK82+0.000000001,1,0) -> 0 | AJ82: =MIN(AH82,AK82)*I82 -> 22666.716 | AK82: =(AK81-MIN(AH81,AK81))*G81/(1+F81) -> 627036.11 | AL82: =MIN(MAX(Tasso0*AP82*I82,AL81*(1+VG_pav)),AL81*(1+VG_tetto)) -> 28763.012 | AM82: =AL82/I82 -> 33544.633 | AN82: =IF(AM82>AP82+0.000000001,1,0) -> 0 | AO82: =MIN(AM82,AP82)*I82 -> 28763.012 | AP82: =(AP81-MIN(AM81,AP81))*G81/(1+F81) -> 587143.61 | AQ82: =IF(AND(A82<=Anni,M81>0),M82/M81-1,"") -> 0 | AR82: =IF(AND(A82<=Anni,R81>0),R82/R81-1,"") -> 0.050596856 | AS82: =IF(AND(A82<=Anni,W81>0),W82/W81-1,"") -> 0 | AT82: =IF(AND(A82<=Anni,AC81>0),AC82/AC81-1,"") -> 0.063123706 | AU82: =IF(AND(A82<=Anni,AJ81>0),AJ82/AJ81-1,"") -> 0 | AV82: =IF(AND(A82<=Anni,AO81>0),AO82/AO81-1,"") -> -0.025
A83: =A82+1 -> 13 | B83: =Eta_inizio+A83-1 -> 63 | C83: =Anno_inizio+A83-1 -> 2012 | D83: =IF(COUNTIFS('5 - Dati'!$A$6:$A$186,Serie,'5 - Dati'!$B$6:$B$186,C83)>0,1,0) -> 1 | E83: =IF(D83=1,SUMIFS('5 - Dati'!$F$6:$F$186,'5 - Dati'!$A$6:$A$186,Serie,'5 - Dati'!$B$6:$B$186,C83),(1+Rend_c)*(1+Infl_c)-1) -> 0.089548654 | F83: =IF(D83=1,SUMIFS('5 - Dati'!$E$6:$E$186,'5 - Dati'!$A$6:$A$186,Serie,'5 - Dati'!$B$6:$B$186,C83),Infl_c) -> 0.02405856 | G83: =(1+E83)*(1-Bollo_eff) -> 1.0873696 | H83: =H82/G82 -> 0.42228063 | I83: =1-Aliq_eff*MAX(0,1-H83) -> 0.84979296 | J83: =Spesa0 -> 38000 | K83: =J83/I83 -> 44716.774 | L83: =IF(K83>N83+0.000000001,1,0) -> 0 | M83: =MIN(K83,N83)*I83 -> 38000 | N83: =(N82-MIN(K82,N82))*G82/(1+F82) -> 498063.75 | O83: =Tasso0*S83*I83 -> 22715.183 | P83: =O83/I83 -> 26730.255 | Q83: =IF(P83>S83+0.000000001,1,0) -> 0 | R83: =MIN(P83,S83)*I83 -> 22715.183 | S83: =(S82-MIN(P82,S82))*G82/(1+F82) -> 658931.22 | T83: =MAX(Tasso0*X83*I83,Pav_pct*Spesa0) -> 34200 | U83: =T83/I83 -> 40245.097 | V83: =IF(U83>X83+0.000000001,1,0) -> 0 | W83: =MIN(U83,X83)*I83 -> 34200 | X83: =(X82-MIN(U82,X82))*G82/(1+F82) -> 549182.41 | Y83: =IF(Eta_rif_VPW-B83<=1,1,IF(r_VPW=0,1/(Eta_rif_VPW-B83),r_VPW/(1-(1+r_VPW)^(-(Eta_rif_VPW-B83)))/(1+r_VPW))) -> 0.043797694 | Z83: =Y83*AD83*I83 -> 24576.502 | AA83: =Z83/I83 -> 28920.576 | AB83: =IF(AA83>AD83+0.000000001,1,0) -> 0 | AC83: =MIN(AA83,AD83)*I83 -> 24576.502 | AD83: =(AD82-MIN(AA82,AD82))*G82/(1+F82) -> 660321.88 | AE83: =IF(OR(E82>=0,GK_variante=3),AG82,IF(GK_variante=2,AG82/(1+F82),IF(AK83*I83<=0,AG82/(1+F82),IF(AG82/(AK83*I83)>Tasso0,AG82/(1+F82),AG82)))) -> 22666.716 | AF83: =IF(AK83*I83<=0,9.9,AE83/(AK83*I83)) -> 0.042905058 | AG83: =IF(AND(AF83>Tasso0*(1+GK_banda),A83<=Anni-GK_ultimi),AE83*(1-GK_taglio),IF(AF83<Tasso0*(1-GK_banda),AE83*(1+GK_taglio),AE83)) -> 22666.716 | AH83: =AG83/I83 -> 26673.222 | AI83: =IF(AH83>AK83+0.000000001,1,0) -> 0 | AJ83: =MIN(AH83,AK83)*I83 -> 22666.716 | AK83: =(AK82-MIN(AH82,AK82))*G82/(1+F82) -> 621680.12 | AL83: =MIN(MAX(Tasso0*AP83*I83,AL82*(1+VG_pav)),AL82*(1+VG_tetto)) -> 28043.937 | AM83: =AL83/I83 -> 33000.905 | AN83: =IF(AM83>AP83+0.000000001,1,0) -> 0 | AO83: =MIN(AM83,AP83)*I83 -> 28043.937 | AP83: =(AP82-MIN(AM82,AP82))*G82/(1+F82) -> 573028.26 | AQ83: =IF(AND(A83<=Anni,M82>0),M83/M82-1,"") -> 0 | AR83: =IF(AND(A83<=Anni,R82>0),R83/R82-1,"") -> -0.015767648 | AS83: =IF(AND(A83<=Anni,W82>0),W83/W82-1,"") -> 0 | AT83: =IF(AND(A83<=Anni,AC82>0),AC83/AC82-1,"") -> -0.0040320987 | AU83: =IF(AND(A83<=Anni,AJ82>0),AJ83/AJ82-1,"") -> 0 | AV83: =IF(AND(A83<=Anni,AO82>0),AO83/AO82-1,"") -> -0.025
... A130: =A129+1 -> 60 | B130: =Eta_inizio+A130-1 -> 110 | C130: =Anno_inizio+A130-1 -> 2059 | D130: =IF(COUNTIFS('5 - Dati'!$A$6:$A$186,Serie,'5 - Dati'!$B$6:$B$186,C130)>0,1,0) -> 0 | E130: =IF(D130=1,SUMIFS('5 - Dati'!$F$6:$F$186,'5 - Dati'!$A$6:$A$186,Serie,'5 - Dati'!$B$6:$B$186,C130),(1+Rend_c)*(1+Infl_c)-1) -> 0.0506 | F130: =IF(D130=1,SUMIFS('5 - Dati'!$E$6:$E$186,'5 - Dati'!$A$6:$A$186,Serie,'5 - Dati'!$B$6:$B$186,C130),Infl_c) -> 0.02 | G130: =(1+E130)*(1-Bollo_eff) -> 1.0484988 | H130: =H129/G129 -> 0.03230385 | I130: =1-Aliq_eff*MAX(0,1-H130) -> 0.748399 | J130: =Spesa0 -> 38000 | K130: =J130/I130 -> 50775.054 | L130: =IF(K130>N130+0.000000001,1,0) -> 1 | M130: =MIN(K130,N130)*I130 -> 0 | N130: =(N129-MIN(K129,N129))*G129/(1+F129) -> 0 | O130: =Tasso0*S130*I130 -> 15018.196 | P130: =O130/I130 -> 20067.097 | Q130: =IF(P130>S130+0.000000001,1,0) -> 0 | R130: =MIN(P130,S130)*I130 -> 15018.196 | S130: =(S129-MIN(P129,S129))*G129/(1+F129) -> 494676.8 | T130: =MAX(Tasso0*X130*I130,Pav_pct*Spesa0) -> 34200 | U130: =T130/I130 -> 45697.549 | V130: =IF(U130>X130+0.000000001,1,0) -> 1 | W130: =MIN(U130,X130)*I130 -> 0 | X130: =(X129-MIN(U129,X129))*G129/(1+F129) -> 0 | Y130: =IF(Eta_rif_VPW-B130<=1,1,IF(r_VPW=0,1/(Eta_rif_VPW-B130),r_VPW/(1-(1+r_VPW)^(-(Eta_rif_VPW-B130)))/(1+r_VPW))) -> 1 | Z130: =Y130*AD130*I130 -> 0 | AA130: =Z130/I130 -> 0 | AB130: =IF(AA130>AD130+0.000000001,1,0) -> 0 | AC130: =MIN(AA130,AD130)*I130 -> 0 | AD130: =(AD129-MIN(AA129,AD129))*G129/(1+F129) -> 0 | AE130: =IF(OR(E129>=0,GK_variante=3),AG129,IF(GK_variante=2,AG129/(1+F129),IF(AK130*I130<=0,AG129/(1+F129),IF(AG129/(AK130*I130)>Tasso0,AG129/(1+F129),AG129)))) -> 20481.744 | AF130: =IF(AK130*I130<=0,9.9,AE130/(AK130*I130)) -> 0.058453832 | AG130: =IF(AND(AF130>Tasso0*(1+GK_banda),A130<=Anni-GK_ultimi),AE130*(1-GK_taglio),IF(AF130<Tasso0*(1-GK_banda),AE130*(1+GK_taglio),AE130)) -> 20481.744 | AH130: =AG130/I130 -> 27367.412 | AI130: =IF(AH130>AK130+0.000000001,1,0) -> 0 | AJ130: =MIN(AH130,AK130)*I130 -> 20481.744 | AK130: =(AK129-MIN(AH129,AK129))*G129/(1+F129) -> 468188.5 | AL130: =MIN(MAX(Tasso0*AP130*I130,AL129*(1+VG_pav)),AL129*(1+VG_tetto)) -> 11664.185 | AM130: =AL130/I130 -> 15585.517 | AN130: =IF(AM130>AP130+0.000000001,1,0) -> 0 | AO130: =MIN(AM130,AP130)*I130 -> 11664.185 | AP130: =(AP129-MIN(AM129,AP129))*G129/(1+F129) -> 384200.74 | AQ130: =IF(AND(A130<=Anni,M129>0),M130/M129-1,"") | AR130: =IF(AND(A130<=Anni,R129>0),R130/R129-1,"") | AS130: =IF(AND(A130<=Anni,W129>0),W130/W129-1,"") | AT130: =IF(AND(A130<=Anni,AC129>0),AC130/AC129-1,"") | AU130: =IF(AND(A130<=Anni,AJ129>0),AJ130/AJ129-1,"") | AV130: =IF(AND(A130<=Anni,AO129>0),AO130/AO129-1,"")

Sheet 3 - Rendimento costante
A1: 3 - Rendimento costante: spesa pagata e capitale, anno per anno (euro di oggi)
A2: Strumento informativo / divulgativo. NON è consulenza finanziaria. I valori sono indicativi al 2026 e vanno verificati col tuo consulente.
A3: Risultati: spesa pagata (euro in cassa se «tassato», venduto lordo se «lordo») e capitale a inizio anno
A4: ="Rendimento reale costante "&TEXT(Rend_c,"0.00%")&" e inflazione "&TEXT(Infl_c,"0.00%")&" · nessun dato storico · modalità: "&Modalita -> Rendimento reale costante 003% e inflazione 002% · nessun dato storico · modalità: tassato
A5: t | B5: Età | C5: Anno | D5: Spesa pagata: Fisso indicizzato | E5: Spesa pagata: Percentuale costante | F5: Spesa pagata: Percentuale con pavimento | G5: Spesa pagata: Percentuale variabile | H5: Spesa pagata: Guardrail (senza tetto all'inflazione) | I5: Spesa pagata: Tetto e pavimento (+5% / −2,5%) | J5: Capitale inizio anno: Fisso indicizzato | K5: Capitale inizio anno: Percentuale costante | L5: Capitale inizio anno: Percentuale con pavimento | M5: Capitale inizio anno: Percentuale variabile | N5: Capitale inizio anno: Guardrail (senza tetto all'inflazione) | O5: Capitale inizio anno: Tetto e pavimento (+5% / −2,5%) | P5: Dato storico o ipotesi
A6: =A71 -> 1 | B6: =IF($A6>Anni,"",B71) -> 51 | C6: =IF($A6>Anni,"",C71) -> 2000 | D6: =IF($A6>Anni,"",M71) -> 38000 | E6: =IF($A6>Anni,"",R71) -> 38000 | F6: =IF($A6>Anni,"",W71) -> 38000 | G6: =IF($A6>Anni,"",AC71) -> 35662.76 | H6: =IF($A6>Anni,"",AJ71) -> 38000 | I6: =IF($A6>Anni,"",AO71) -> 38000 | J6: =IF($A6>Anni,"",N71) -> 1056000 | K6: =IF($A6>Anni,"",S71) -> 1056000 | L6: =IF($A6>Anni,"",X71) -> 1056000 | M6: =IF($A6>Anni,"",AD71) -> 1056000 | N6: =IF($A6>Anni,"",AK71) -> 1056000 | O6: =IF($A6>Anni,"",AP71) -> 1056000 | P6: =IF($A6>Anni,"",IF(D71=1,"osservato","ipotesi")) -> ipotesi
A7: =A72 -> 2 | B7: =IF($A7>Anni,"",B72) -> 52 | C7: =IF($A7>Anni,"",C72) -> 2001 | D7: =IF($A7>Anni,"",M72) -> 38000 | E7: =IF($A7>Anni,"",R72) -> 37189.737 | F7: =IF($A7>Anni,"",W72) -> 37189.737 | G7: =IF($A7>Anni,"",AC72) -> 35318.494 | H7: =IF($A7>Anni,"",AJ72) -> 38000 | I7: =IF($A7>Anni,"",AO72) -> 37189.737 | J7: =IF($A7>Anni,"",N72) -> 1041470 | K7: =IF($A7>Anni,"",S72) -> 1041470 | L7: =IF($A7>Anni,"",X72) -> 1041470 | M7: =IF($A7>Anni,"",AD72) -> 1044178.4 | N7: =IF($A7>Anni,"",AK72) -> 1041470 | O7: =IF($A7>Anni,"",AP72) -> 1041470 | P7: =IF($A7>Anni,"",IF(D72=1,"osservato","ipotesi")) -> ipotesi
A8: =A73 -> 3 | B8: =IF($A8>Anni,"",B73) -> 53 | C8: =IF($A8>Anni,"",C73) -> 2002 | D8: =IF($A8>Anni,"",M73) -> 38000 | E8: =IF($A8>Anni,"",R73) -> 36407.689 | F8: =IF($A8>Anni,"",W73) -> 36407.689 | G8: =IF($A8>Anni,"",AC73) -> 34988.062 | H8: =IF($A8>Anni,"",AJ73) -> 38000 | I8: =IF($A8>Anni,"",AO73) -> 36407.689 | J8: =IF($A8>Anni,"",N73) -> 1026193.7 | K8: =IF($A8>Anni,"",S73) -> 1027139.9 | L8: =IF($A8>Anni,"",X73) -> 1027139.9 | M8: =IF($A8>Anni,"",AD73) -> 1032109.1 | N8: =IF($A8>Anni,"",AK73) -> 1026193.7 | O8: =IF($A8>Anni,"",AP73) -> 1027139.9 | P8: =IF($A8>Anni,"",IF(D73=1,"osservato","ipotesi")) -> ipotesi
A9: =A74 -> 4 | B9: =IF($A9>Anni,"",B74) -> 54 | C9: =IF($A9>Anni,"",C74) -> 2003 | D9: =IF($A9>Anni,"",M74) -> 38000 | E9: =IF($A9>Anni,"",R74) -> 35652.454 | F9: =IF($A9>Anni,"",W74) -> 35652.454 | G9: =IF($A9>Anni,"",AC74) -> 34670.803 | H9: =IF($A9>Anni,"",AJ74) -> 38000 | I9: =IF($A9>Anni,"",AO74) -> 35652.454 | J9: =IF($A9>Anni,"",N74) -> 1010161.1 | K9: =IF($A9>Anni,"",S74) -> 1013007 | L9: =IF($A9>Anni,"",X74) -> 1013007 | M9: =IF($A9>Anni,"",AD74) -> 1019785.1 | N9: =IF($A9>Anni,"",AK74) -> 1010161.1 | O9: =IF($A9>Anni,"",AP74) -> 1013007 | P9: =IF($A9>Anni,"",IF(D74=1,"osservato","ipotesi")) -> ipotesi
A10: =A75 -> 5 | B10: =IF($A10>Anni,"",B75) -> 55 | C10: =IF($A10>Anni,"",C75) -> 2004 | D10: =IF($A10>Anni,"",M75) -> 38000 | E10: =IF($A10>Anni,"",R75) -> 34922.709 | F10: =IF($A10>Anni,"",W75) -> 34922.709 | G10: =IF($A10>Anni,"",AC75) -> 34366.089 | H10: =IF($A10>Anni,"",AJ75) -> 38000 | I10: =IF($A10>Anni,"",AO75) -> 34922.709 | J10: =IF($A10>Anni,"",N75) -> 993361.67 | K10: =IF($A10>Anni,"",S75) -> 999068.49 | L10: =IF($A10>Anni,"",X75) -> 999068.49 | M10: =IF($A10>Anni,"",AD75) -> 1007199.1 | N10: =IF($A10>Anni,"",AK75) -> 993361.67 | O10: =IF($A10>Anni,"",AP75) -> 999068.49 | P10: =IF($A10>Anni,"",IF(D75=1,"osservato","ipotesi")) -> ipotesi
A11: =A76 -> 6 | B11: =IF($A11>Anni,"",B76) -> 56 | C11: =IF($A11>Anni,"",C76) -> 2005 | D11: =IF($A11>Anni,"",M76) -> 38000 | E11: =IF($A11>Anni,"",R76) -> 34217.207 | F11: =IF($A11>Anni,"",W76) -> 34217.207 | G11: =IF($A11>Anni,"",AC76) -> 34073.32 | H11: =IF($A11>Anni,"",AJ76) -> 38000 | I11: =IF($A11>Anni,"",AO76) -> 34217.207 | J11: =IF($A11>Anni,"",N76) -> 975784.52 | K11: =IF($A11>Anni,"",S76) -> 985321.81 | L11: =IF($A11>Anni,"",X76) -> 985321.81 | M11: =IF($A11>Anni,"",AD76) -> 994343.65 | N11: =IF($A11>Anni,"",AK76) -> 975784.52 | O11: =IF($A11>Anni,"",AP76) -> 985321.81 | P11: =IF($A11>Anni,"",IF(D76=1,"osservato","ipotesi")) -> ipotesi
A12: =A77 -> 7 | B12: =IF($A12>Anni,"",B77) -> 57 | C12: =IF($A12>Anni,"",C77) -> 2006 | D12: =IF($A12>Anni,"",M77) -> 38000 | E12: =IF($A12>Anni,"",R77) -> 33534.772 | F12: =IF($A12>Anni,"",W77) -> 34200 | G12: =IF($A12>Anni,"",AC77) -> 33791.927 | H12: =IF($A12>Anni,"",AJ77) -> 38000 | I12: =IF($A12>Anni,"",AO77) -> 33534.772 | J12: =IF($A12>Anni,"",N77) -> 957418.21 | K12: =IF($A12>Anni,"",S77) -> 971764.28 | L12: =IF($A12>Anni,"",X77) -> 971764.28 | M12: =IF($A12>Anni,"",AD77) -> 981210.97 | N12: =IF($A12>Anni,"",AK77) -> 957418.21 | O12: =IF($A12>Anni,"",AP77) -> 971764.28 | P12: =IF($A12>Anni,"",IF(D77=1,"osservato","ipotesi")) -> ipotesi
A13: =A78 -> 8 | B13: =IF($A13>Anni,"",B78) -> 58 | C13: =IF($A13>Anni,"",C78) -> 2007 | D13: =IF($A13>Anni,"",M78) -> 38000 | E13: =IF($A13>Anni,"",R78) -> 32874.293 | F13: =IF($A13>Anni,"",W78) -> 34200 | G13: =IF($A13>Anni,"",AC78) -> 33521.367 | H13: =IF($A13>Anni,"",AJ78) -> 38000 | I13: =IF($A13>Anni,"",AO78) -> 32874.293 | J13: =IF($A13>Anni,"",N78) -> 938250.79 | K13: =IF($A13>Anni,"",S78) -> 958393.3 | L13: =IF($A13>Anni,"",X78) -> 957589.46 | M13: =IF($A13>Anni,"",AD78) -> 967793.19 | N13: =IF($A13>Anni,"",AK78) -> 938250.79 | O13: =IF($A13>Anni,"",AP78) -> 958393.3 | P13: =IF($A13>Anni,"",IF(D78=1,"osservato","ipotesi")) -> ipotesi
A14: =A79 -> 9 | B14: =IF($A14>Anni,"",B79) -> 59 | C14: =IF($A14>Anni,"",C79) -> 2008 | D14: =IF($A14>Anni,"",M79) -> 38000 | E14: =IF($A14>Anni,"",R79) -> 32234.722 | F14: =IF($A14>Anni,"",W79) -> 34200 | G14: =IF($A14>Anni,"",AC79) -> 33261.125 | H14: =IF($A14>Anni,"",AJ79) -> 34200 | I14: =IF($A14>Anni,"",AO79) -> 32234.722 | J14: =IF($A14>Anni,"",N79) -> 918269.8 | K14: =IF($A14>Anni,"",S79) -> 945206.29 | L14: =IF($A14>Anni,"",X79) -> 942768.37 | M14: =IF($A14>Anni,"",AD79) -> 954082.18 | N14: =IF($A14>Anni,"",AK79) -> 918269.8 | O14: =IF($A14>Anni,"",AP79) -> 945206.29 | P14: =IF($A14>Anni,"",IF(D79=1,"osservato","ipotesi")) -> ipotesi
A15: =A80 -> 10 | B15: =IF($A15>Anni,"",B80) -> 60 | C15: =IF($A15>Anni,"",C80) -> 2009 | D15: =IF($A15>Anni,"",M80) -> 38000 | E15: =IF($A15>Anni,"",R80) -> 31615.068 | F15: =IF($A15>Anni,"",W80) -> 34200 | G15: =IF($A15>Anni,"",AC80) -> 33010.708 | H15: =IF($A15>Anni,"",AJ80) -> 34200 | I15: =IF($A15>Anni,"",AO80) -> 31615.068 | J15: =IF($A15>Anni,"",N80) -> 897462.21 | K15: =IF($A15>Anni,"",S80) -> 932200.73 | L15: =IF($A15>Anni,"",X80) -> 927291.67 | M15: =IF($A15>Anni,"",AD80) -> 940069.59 | N15: =IF($A15>Anni,"",AK80) -> 902108.62 | O15: =IF($A15>Anni,"",AP80) -> 932200.73 | P15: =IF($A15>Anni,"",IF(D80=1,"osservato","ipotesi")) -> ipotesi
A16: =A81 -> 11 | B16: =IF($A16>Anni,"",B81) -> 61 | C16: =IF($A16>Anni,"",C81) -> 2010 | D16: =IF($A16>Anni,"",M81) -> 38000 | E16: =IF($A16>Anni,"",R81) -> 31014.399 | F16: =IF($A16>Anni,"",W81) -> 34200 | G16: =IF($A16>Anni,"",AC81) -> 32769.648 | H16: =IF($A16>Anni,"",AJ81) -> 34200 | I16: =IF($A16>Anni,"",AO81) -> 31014.399 | J16: =IF($A16>Anni,"",N81) -> 875814.41 | K16: =IF($A16>Anni,"",S81) -> 919374.12 | L16: =IF($A16>Anni,"",X81) -> 911149.6 | M16: =IF($A16>Anni,"",AD81) -> 925746.83 | N16: =IF($A16>Anni,"",AK81) -> 885262.93 | O16: =IF($A16>Anni,"",AP81) -> 919374.12 | P16: =IF($A16>Anni,"",IF(D81=1,"osservato","ipotesi")) -> ipotesi
A17: =A82 -> 12 | B17: =IF($A17>Anni,"",B82) -> 62 | C17: =IF($A17>Anni,"",C82) -> 2011 | D17: =IF($A17>Anni,"",M82) -> 38000 | E17: =IF($A17>Anni,"",R82) -> 30431.831 | F17: =IF($A17>Anni,"",W82) -> 34200 | G17: =IF($A17>Anni,"",AC82) -> 32537.501 | H17: =IF($A17>Anni,"",AJ82) -> 34200 | I17: =IF($A17>Anni,"",AO82) -> 30431.831 | J17: =IF($A17>Anni,"",N82) -> 853312.21 | K17: =IF($A17>Anni,"",S82) -> 906724 | L17: =IF($A17>Anni,"",X82) -> 894331.9 | M17: =IF($A17>Anni,"",AD82) -> 911105.06 | N17: =IF($A17>Anni,"",AK82) -> 867721.96 | O17: =IF($A17>Anni,"",AP82) -> 906724 | P17: =IF($A17>Anni,"",IF(D82=1,"osservato","ipotesi")) -> ipotesi
... A47: =A112 -> 42 | B47: =IF($A47>Anni,"",B112) -> 92 | C47: =IF($A47>Anni,"",C112) -> 2041 | D47: =IF($A47>Anni,"",M112) -> 0 | E47: =IF($A47>Anni,"",R112) -> 18474.109 | F47: =IF($A47>Anni,"",W112) -> 797.03326 | G47: =IF($A47>Anni,"",AC112) -> 28187.125 | H47: =IF($A47>Anni,"",AJ112) -> 22438.62 | I47: =IF($A47>Anni,"",AO112) -> 18474.109 | J47: =IF($A47>Anni,"",N112) -> 0 | K47: =IF($A47>Anni,"",S112) -> 598356.73 | L47: =IF($A47>Anni,"",X112) -> 1047.2157 | M47: =IF($A47>Anni,"",AD112) -> 267772.38 | N47: =IF($A47>Anni,"",AK112) -> 427955.64 | O47: =IF($A47>Anni,"",AP112) -> 598356.73 | P47: =IF($A47>Anni,"",IF(D112=1,"osservato","ipotesi")) -> ipotesi
A48: =A113 -> 43 | B48: =IF($A48>Anni,"",B113) | C48: =IF($A48>Anni,"",C113) | D48: =IF($A48>Anni,"",M113) | E48: =IF($A48>Anni,"",R113) | F48: =IF($A48>Anni,"",W113) | G48: =IF($A48>Anni,"",AC113) | H48: =IF($A48>Anni,"",AJ113) | I48: =IF($A48>Anni,"",AO113) | J48: =IF($A48>Anni,"",N113) | K48: =IF($A48>Anni,"",S113) | L48: =IF($A48>Anni,"",X113) | M48: =IF($A48>Anni,"",AD113) | N48: =IF($A48>Anni,"",AK113) | O48: =IF($A48>Anni,"",AP113) | P48: =IF($A48>Anni,"",IF(D113=1,"osservato","ipotesi")) | R48: Il grafico mostra i primi 42 anni (righe 6-47); la tabella a sinistra mostra l'intero piano.
A49: =A114 -> 44 | B49: =IF($A49>Anni,"",B114) | C49: =IF($A49>Anni,"",C114) | D49: =IF($A49>Anni,"",M114) | E49: =IF($A49>Anni,"",R114) | F49: =IF($A49>Anni,"",W114) | G49: =IF($A49>Anni,"",AC114) | H49: =IF($A49>Anni,"",AJ114) | I49: =IF($A49>Anni,"",AO114) | J49: =IF($A49>Anni,"",N114) | K49: =IF($A49>Anni,"",S114) | L49: =IF($A49>Anni,"",X114) | M49: =IF($A49>Anni,"",AD114) | N49: =IF($A49>Anni,"",AK114) | O49: =IF($A49>Anni,"",AP114) | P49: =IF($A49>Anni,"",IF(D114=1,"osservato","ipotesi"))
A50: =A115 -> 45 | B50: =IF($A50>Anni,"",B115) | C50: =IF($A50>Anni,"",C115) | D50: =IF($A50>Anni,"",M115) | E50: =IF($A50>Anni,"",R115) | F50: =IF($A50>Anni,"",W115) | G50: =IF($A50>Anni,"",AC115) | H50: =IF($A50>Anni,"",AJ115) | I50: =IF($A50>Anni,"",AO115) | J50: =IF($A50>Anni,"",N115) | K50: =IF($A50>Anni,"",S115) | L50: =IF($A50>Anni,"",X115) | M50: =IF($A50>Anni,"",AD115) | N50: =IF($A50>Anni,"",AK115) | O50: =IF($A50>Anni,"",AP115) | P50: =IF($A50>Anni,"",IF(D115=1,"osservato","ipotesi"))
A51: =A116 -> 46 | B51: =IF($A51>Anni,"",B116) | C51: =IF($A51>Anni,"",C116) | D51: =IF($A51>Anni,"",M116) | E51: =IF($A51>Anni,"",R116) | F51: =IF($A51>Anni,"",W116) | G51: =IF($A51>Anni,"",AC116) | H51: =IF($A51>Anni,"",AJ116) | I51: =IF($A51>Anni,"",AO116) | J51: =IF($A51>Anni,"",N116) | K51: =IF($A51>Anni,"",S116) | L51: =IF($A51>Anni,"",X116) | M51: =IF($A51>Anni,"",AD116) | N51: =IF($A51>Anni,"",AK116) | O51: =IF($A51>Anni,"",AP116) | P51: =IF($A51>Anni,"",IF(D116=1,"osservato","ipotesi"))
A52: =A117 -> 47 | B52: =IF($A52>Anni,"",B117) | C52: =IF($A52>Anni,"",C117) | D52: =IF($A52>Anni,"",M117) | E52: =IF($A52>Anni,"",R117) | F52: =IF($A52>Anni,"",W117) | G52: =IF($A52>Anni,"",AC117) | H52: =IF($A52>Anni,"",AJ117) | I52: =IF($A52>Anni,"",AO117) | J52: =IF($A52>Anni,"",N117) | K52: =IF($A52>Anni,"",S117) | L52: =IF($A52>Anni,"",X117) | M52: =IF($A52>Anni,"",AD117) | N52: =IF($A52>Anni,"",AK117) | O52: =IF($A52>Anni,"",AP117) | P52: =IF($A52>Anni,"",IF(D117=1,"osservato","ipotesi"))
A53: =A118 -> 48 | B53: =IF($A53>Anni,"",B118) | C53: =IF($A53>Anni,"",C118) | D53: =IF($A53>Anni,"",M118) | E53: =IF($A53>Anni,"",R118) | F53: =IF($A53>Anni,"",W118) | G53: =IF($A53>Anni,"",AC118) | H53: =IF($A53>Anni,"",AJ118) | I53: =IF($A53>Anni,"",AO118) | J53: =IF($A53>Anni,"",N118) | K53: =IF($A53>Anni,"",S118) | L53: =IF($A53>Anni,"",X118) | M53: =IF($A53>Anni,"",AD118) | N53: =IF($A53>Anni,"",AK118) | O53: =IF($A53>Anni,"",AP118) | P53: =IF($A53>Anni,"",IF(D118=1,"osservato","ipotesi"))
A54: =A119 -> 49 | B54: =IF($A54>Anni,"",B119) | C54: =IF($A54>Anni,"",C119) | D54: =IF($A54>Anni,"",M119) | E54: =IF($A54>Anni,"",R119) | F54: =IF($A54>Anni,"",W119) | G54: =IF($A54>Anni,"",AC119) | H54: =IF($A54>Anni,"",AJ119) | I54: =IF($A54>Anni,"",AO119) | J54: =IF($A54>Anni,"",N119) | K54: =IF($A54>Anni,"",S119) | L54: =IF($A54>Anni,"",X119) | M54: =IF($A54>Anni,"",AD119) | N54: =IF($A54>Anni,"",AK119) | O54: =IF($A54>Anni,"",AP119) | P54: =IF($A54>Anni,"",IF(D119=1,"osservato","ipotesi"))
A55: =A120 -> 50 | B55: =IF($A55>Anni,"",B120) | C55: =IF($A55>Anni,"",C120) | D55: =IF($A55>Anni,"",M120) | E55: =IF($A55>Anni,"",R120) | F55: =IF($A55>Anni,"",W120) | G55: =IF($A55>Anni,"",AC120) | H55: =IF($A55>Anni,"",AJ120) | I55: =IF($A55>Anni,"",AO120) | J55: =IF($A55>Anni,"",N120) | K55: =IF($A55>Anni,"",S120) | L55: =IF($A55>Anni,"",X120) | M55: =IF($A55>Anni,"",AD120) | N55: =IF($A55>Anni,"",AK120) | O55: =IF($A55>Anni,"",AP120) | P55: =IF($A55>Anni,"",IF(D120=1,"osservato","ipotesi"))
A56: =A121 -> 51 | B56: =IF($A56>Anni,"",B121) | C56: =IF($A56>Anni,"",C121) | D56: =IF($A56>Anni,"",M121) | E56: =IF($A56>Anni,"",R121) | F56: =IF($A56>Anni,"",W121) | G56: =IF($A56>Anni,"",AC121) | H56: =IF($A56>Anni,"",AJ121) | I56: =IF($A56>Anni,"",AO121) | J56: =IF($A56>Anni,"",N121) | K56: =IF($A56>Anni,"",S121) | L56: =IF($A56>Anni,"",X121) | M56: =IF($A56>Anni,"",AD121) | N56: =IF($A56>Anni,"",AK121) | O56: =IF($A56>Anni,"",AP121) | P56: =IF($A56>Anni,"",IF(D121=1,"osservato","ipotesi"))
A57: =A122 -> 52 | B57: =IF($A57>Anni,"",B122) | C57: =IF($A57>Anni,"",C122) | D57: =IF($A57>Anni,"",M122) | E57: =IF($A57>Anni,"",R122) | F57: =IF($A57>Anni,"",W122) | G57: =IF($A57>Anni,"",AC122) | H57: =IF($A57>Anni,"",AJ122) | I57: =IF($A57>Anni,"",AO122) | J57: =IF($A57>Anni,"",N122) | K57: =IF($A57>Anni,"",S122) | L57: =IF($A57>Anni,"",X122) | M57: =IF($A57>Anni,"",AD122) | N57: =IF($A57>Anni,"",AK122) | O57: =IF($A57>Anni,"",AP122) | P57: =IF($A57>Anni,"",IF(D122=1,"osservato","ipotesi"))
A58: =A123 -> 53 | B58: =IF($A58>Anni,"",B123) | C58: =IF($A58>Anni,"",C123) | D58: =IF($A58>Anni,"",M123) | E58: =IF($A58>Anni,"",R123) | F58: =IF($A58>Anni,"",W123) | G58: =IF($A58>Anni,"",AC123) | H58: =IF($A58>Anni,"",AJ123) | I58: =IF($A58>Anni,"",AO123) | J58: =IF($A58>Anni,"",N123) | K58: =IF($A58>Anni,"",S123) | L58: =IF($A58>Anni,"",X123) | M58: =IF($A58>Anni,"",AD123) | N58: =IF($A58>Anni,"",AK123) | O58: =IF($A58>Anni,"",AP123) | P58: =IF($A58>Anni,"",IF(D123=1,"osservato","ipotesi"))
A59: =A124 -> 54 | B59: =IF($A59>Anni,"",B124) | C59: =IF($A59>Anni,"",C124) | D59: =IF($A59>Anni,"",M124) | E59: =IF($A59>Anni,"",R124) | F59: =IF($A59>Anni,"",W124) | G59: =IF($A59>Anni,"",AC124) | H59: =IF($A59>Anni,"",AJ124) | I59: =IF($A59>Anni,"",AO124) | J59: =IF($A59>Anni,"",N124) | K59: =IF($A59>Anni,"",S124) | L59: =IF($A59>Anni,"",X124) | M59: =IF($A59>Anni,"",AD124) | N59: =IF($A59>Anni,"",AK124) | O59: =IF($A59>Anni,"",AP124) | P59: =IF($A59>Anni,"",IF(D124=1,"osservato","ipotesi"))
A60: =A125 -> 55 | B60: =IF($A60>Anni,"",B125) | C60: =IF($A60>Anni,"",C125) | D60: =IF($A60>Anni,"",M125) | E60: =IF($A60>Anni,"",R125) | F60: =IF($A60>Anni,"",W125) | G60: =IF($A60>Anni,"",AC125) | H60: =IF($A60>Anni,"",AJ125) | I60: =IF($A60>Anni,"",AO125) | J60: =IF($A60>Anni,"",N125) | K60: =IF($A60>Anni,"",S125) | L60: =IF($A60>Anni,"",X125) | M60: =IF($A60>Anni,"",AD125) | N60: =IF($A60>Anni,"",AK125) | O60: =IF($A60>Anni,"",AP125) | P60: =IF($A60>Anni,"",IF(D125=1,"osservato","ipotesi"))
... A65: =A130 -> 60 | B65: =IF($A65>Anni,"",B130) | C65: =IF($A65>Anni,"",C130) | D65: =IF($A65>Anni,"",M130) | E65: =IF($A65>Anni,"",R130) | F65: =IF($A65>Anni,"",W130) | G65: =IF($A65>Anni,"",AC130) | H65: =IF($A65>Anni,"",AJ130) | I65: =IF($A65>Anni,"",AO130) | J65: =IF($A65>Anni,"",N130) | K65: =IF($A65>Anni,"",S130) | L65: =IF($A65>Anni,"",X130) | M65: =IF($A65>Anni,"",AD130) | N65: =IF($A65>Anni,"",AK130) | O65: =IF($A65>Anni,"",AP130) | P65: =IF($A65>Anni,"",IF(D130=1,"osservato","ipotesi"))
A68: Motore del calcolo, non modificare
A69: Anno e rendimenti | J69: Fisso indicizzato | O69: Percentuale costante | T69: Percentuale con pavimento | Y69: Percentuale variabile | AE69: Guardrail (senza tetto all'inflazione) | AL69: Tetto e pavimento | AQ69: Cambio % annuo della spesa pagata
A70: t | B70: Età | C70: Anno | D70: Dato storico (1/0) | E70: Rendimento nominale 60/40 | F70: Inflazione | G70: Fattore nominale dopo bollo (g) | H70: Base di costo / valore (k) | I70: Quota netta del venduto (q) | J70: Fisso: pianificata | K70: Fisso: venduto | L70: Fisso: esaurimento | M70: Fisso: pagata | N70: Fisso: capitale (W) | O70: Perc. costante: pianificata | P70: Perc. costante: venduto | Q70: Perc. costante: esaurimento | R70: Perc. costante: pagata | S70: Perc. costante: capitale (W) | T70: Perc. con pav.: pianificata | U70: Perc. con pav.: venduto | V70: Perc. con pav.: esaurimento | W70: Perc. con pav.: pagata | X70: Perc. con pav.: capitale (W) | Y70: Perc. variabile: percentuale | Z70: Perc. variabile: pianificata | AA70: Perc. variabile: venduto | AB70: Perc. variabile: esaurimento | AC70: Perc. variabile: pagata | AD70: Perc. variabile: capitale (W) | AE70: Guardrail: prima della regola | AF70: Guardrail: tasso corrente | AG70: Guardrail: pianificata | AH70: Guardrail: venduto | AI70: Guardrail: esaurimento | AJ70: Guardrail: pagata | AK70: Guardrail: capitale (W) | AL70: Tetto e pav.: pianificata | AM70: Tetto e pav.: venduto | AN70: Tetto e pav.: esaurimento | AO70: Tetto e pav.: pagata | AP70: Tetto e pav.: capitale (W) | AQ70: Cambio % fisso | AR70: Cambio % perc. costante | AS70: Cambio % perc. con pav. | AT70: Cambio % perc. variabile | AU70: Cambio % guardrail | AV70: Cambio % tetto e pav.
A71: 1 | B71: =Eta_inizio+A71-1 -> 51 | C71: =Anno_inizio+A71-1 -> 2000 | D71: =0 -> 0 | E71: =IF(D71=1,SUMIFS('5 - Dati'!$F$6:$F$186,'5 - Dati'!$A$6:$A$186,Serie,'5 - Dati'!$B$6:$B$186,C71),(1+Rend_c)*(1+Infl_c)-1) -> 0.0506 | F71: =IF(D71=1,SUMIFS('5 - Dati'!$E$6:$E$186,'5 - Dati'!$A$6:$A$186,Serie,'5 - Dati'!$B$6:$B$186,C71),Infl_c) -> 0.02 | G71: =(1+E71)*(1-Bollo_eff) -> 1.0484988 | H71: =1-Latente_eff -> 0.56564418 | I71: =1-Aliq_eff*MAX(0,1-H71) -> 0.88706749 | J71: =Spesa0 -> 38000 | K71: =J71/I71 -> 42837.778 | L71: =IF(K71>N71+0.000000001,1,0) -> 0 | M71: =MIN(K71,N71)*I71 -> 38000 | N71: =Patrimonio -> 1056000 | O71: =Tasso0*S71*I71 -> 38000 | P71: =O71/I71 -> 42837.778 | Q71: =IF(P71>S71+0.000000001,1,0) -> 0 | R71: =MIN(P71,S71)*I71 -> 38000 | S71: =Patrimonio -> 1056000 | T71: =MAX(Tasso0*X71*I71,Pav_pct*Spesa0) -> 38000 | U71: =T71/I71 -> 42837.778 | V71: =IF(U71>X71+0.000000001,1,0) -> 0 | W71: =MIN(U71,X71)*I71 -> 38000 | X71: =Patrimonio -> 1056000 | Y71: =IF(Eta_rif_VPW-B71<=1,1,IF(r_VPW=0,1/(Eta_rif_VPW-B71),r_VPW/(1-(1+r_VPW)^(-(Eta_rif_VPW-B71)))/(1+r_VPW))) -> 0.038071008 | Z71: =Y71*AD71*I71 -> 35662.76 | AA71: =Z71/I71 -> 40202.985 | AB71: =IF(AA71>AD71+0.000000001,1,0) -> 0 | AC71: =MIN(AA71,AD71)*I71 -> 35662.76 | AD71: =Patrimonio -> 1056000 | AE71: =Spesa0 -> 38000 | AF71: =IF(AK71*I71<=0,9.9,AE71/(AK71*I71)) -> 0.040566078 | AG71: =IF(AND(AF71>Tasso0*(1+GK_banda),A71<=Anni-GK_ultimi),AE71*(1-GK_taglio),IF(AF71<Tasso0*(1-GK_banda),AE71*(1+GK_taglio),AE71)) -> 38000 | AH71: =AG71/I71 -> 42837.778 | AI71: =IF(AH71>AK71+0.000000001,1,0) -> 0 | AJ71: =MIN(AH71,AK71)*I71 -> 38000 | AK71: =Patrimonio -> 1056000 | AL71: =Spesa0 -> 38000 | AM71: =AL71/I71 -> 42837.778 | AN71: =IF(AM71>AP71+0.000000001,1,0) -> 0 | AO71: =MIN(AM71,AP71)*I71 -> 38000 | AP71: =Patrimonio -> 1056000
A72: =A71+1 -> 2 | B72: =Eta_inizio+A72-1 -> 52 | C72: =Anno_inizio+A72-1 -> 2001 | D72: =0 -> 0 | E72: =IF(D72=1,SUMIFS('5 - Dati'!$F$6:$F$186,'5 - Dati'!$A$6:$A$186,Serie,'5 - Dati'!$B$6:$B$186,C72),(1+Rend_c)*(1+Infl_c)-1) -> 0.0506 | F72: =IF(D72=1,SUMIFS('5 - Dati'!$E$6:$E$186,'5 - Dati'!$A$6:$A$186,Serie,'5 - Dati'!$B$6:$B$186,C72),Infl_c) -> 0.02 | G72: =(1+E72)*(1-Bollo_eff) -> 1.0484988 | H72: =H71/G71 -> 0.53948004 | I72: =1-Aliq_eff*MAX(0,1-H72) -> 0.88026481 | J72: =Spesa0 -> 38000 | K72: =J72/I72 -> 43168.828 | L72: =IF(K72>N72+0.000000001,1,0) -> 0 | M72: =MIN(K72,N72)*I72 -> 38000 | N72: =(N71-MIN(K71,N71))*G71/(1+F71) -> 1041470 | O72: =Tasso0*S72*I72 -> 37189.737 | P72: =O72/I72 -> 42248.352 | Q72: =IF(P72>S72+0.000000001,1,0) -> 0 | R72: =MIN(P72,S72)*I72 -> 37189.737 | S72: =(S71-MIN(P71,S71))*G71/(1+F71) -> 1041470 | T72: =MAX(Tasso0*X72*I72,Pav_pct*Spesa0) -> 37189.737 | U72: =T72/I72 -> 42248.352 | V72: =IF(U72>X72+0.000000001,1,0) -> 0 | W72: =MIN(U72,X72)*I72 -> 37189.737 | X72: =(X71-MIN(U71,X71))*G71/(1+F71) -> 1041470 | Y72: =IF(Eta_rif_VPW-B72<=1,1,IF(r_VPW=0,1/(Eta_rif_VPW-B72),r_VPW/(1-(1+r_VPW)^(-(Eta_rif_VPW-B72)))/(1+r_VPW))) -> 0.038425023 | Z72: =Y72*AD72*I72 -> 35318.494 | AA72: =Z72/I72 -> 40122.579 | AB72: =IF(AA72>AD72+0.000000001,1,0) -> 0 | AC72: =MIN(AA72,AD72)*I72 -> 35318.494 | AD72: =(AD71-MIN(AA71,AD71))*G71/(1+F71) -> 1044178.4 | AE72: =IF(OR(E71>=0,GK_variante=3),AG71,IF(GK_variante=2,AG71/(1+F71),IF(AK72*I72<=0,AG71/(1+F71),IF(AG71/(AK72*I72)>Tasso0,AG71/(1+F71),AG71)))) -> 38000 | AF72: =IF(AK72*I72<=0,9.9,AE72/(AK72*I72)) -> 0.041449901 | AG72: =IF(AND(AF72>Tasso0*(1+GK_banda),A72<=Anni-GK_ultimi),AE72*(1-GK_taglio),IF(AF72<Tasso0*(1-GK_banda),AE72*(1+GK_taglio),AE72)) -> 38000 | AH72: =AG72/I72 -> 43168.828 | AI72: =IF(AH72>AK72+0.000000001,1,0) -> 0 | AJ72: =MIN(AH72,AK72)*I72 -> 38000 | AK72: =(AK71-MIN(AH71,AK71))*G71/(1+F71) -> 1041470 | AL72: =MIN(MAX(Tasso0*AP72*I72,AL71*(1+VG_pav)),AL71*(1+VG_tetto)) -> 37189.737 | AM72: =AL72/I72 -> 42248.352 | AN72: =IF(AM72>AP72+0.000000001,1,0) -> 0 | AO72: =MIN(AM72,AP72)*I72 -> 37189.737 | AP72: =(AP71-MIN(AM71,AP71))*G71/(1+F71) -> 1041470 | AQ72: =IF(AND(A72<=Anni,M71>0),M72/M71-1,"") -> 0 | AR72: =IF(AND(A72<=Anni,R71>0),R72/R71-1,"") -> -0.021322699 | AS72: =IF(AND(A72<=Anni,W71>0),W72/W71-1,"") -> -0.021322699 | AT72: =IF(AND(A72<=Anni,AC71>0),AC72/AC71-1,"") -> -0.0096533858 | AU72: =IF(AND(A72<=Anni,AJ71>0),AJ72/AJ71-1,"") -> 0 | AV72: =IF(AND(A72<=Anni,AO71>0),AO72/AO71-1,"") -> -0.021322699
A73: =A72+1 -> 3 | B73: =Eta_inizio+A73-1 -> 53 | C73: =Anno_inizio+A73-1 -> 2002 | D73: =0 -> 0 | E73: =IF(D73=1,SUMIFS('5 - Dati'!$F$6:$F$186,'5 - Dati'!$A$6:$A$186,Serie,'5 - Dati'!$B$6:$B$186,C73),(1+Rend_c)*(1+Infl_c)-1) -> 0.0506 | F73: =IF(D73=1,SUMIFS('5 - Dati'!$E$6:$E$186,'5 - Dati'!$A$6:$A$186,Serie,'5 - Dati'!$B$6:$B$186,C73),Infl_c) -> 0.02 | G73: =(1+E73)*(1-Bollo_eff) -> 1.0484988 | H73: =H72/G72 -> 0.51452614 | I73: =1-Aliq_eff*MAX(0,1-H73) -> 0.8737768 | J73: =Spesa0 -> 38000 | K73: =J73/I73 -> 43489.367 | L73: =IF(K73>N73+0.000000001,1,0) -> 0 | M73: =MIN(K73,N73)*I73 -> 38000 | N73: =(N72-MIN(K72,N72))*G72/(1+F72) -> 1026193.7 | O73: =Tasso0*S73*I73 -> 36407.689 | P73: =O73/I73 -> 41667.036 | Q73: =IF(P73>S73+0.000000001,1,0) -> 0 | R73: =MIN(P73,S73)*I73 -> 36407.689 | S73: =(S72-MIN(P72,S72))*G72/(1+F72) -> 1027139.9 | T73: =MAX(Tasso0*X73*I73,Pav_pct*Spesa0) -> 36407.689 | U73: =T73/I73 -> 41667.036 | V73: =IF(U73>X73+0.000000001,1,0) -> 0 | W73: =MIN(U73,X73)*I73 -> 36407.689 | X73: =(X72-MIN(U72,X72))*G72/(1+F72) -> 1027139.9 | Y73: =IF(Eta_rif_VPW-B73<=1,1,IF(r_VPW=0,1/(Eta_rif_VPW-B73),r_VPW/(1-(1+r_VPW)^(-(Eta_rif_VPW-B73)))/(1+r_VPW))) -> 0.038796608 | Z73: =Y73*AD73*I73 -> 34988.062 | AA73: =Z73/I73 -> 40042.333 | AB73: =IF(AA73>AD73+0.000000001,1,0) -> 0 | AC73: =MIN(AA73,AD73)*I73 -> 34988.062 | AD73: =(AD72-MIN(AA72,AD72))*G72/(1+F72) -> 1032109.1 | AE73: =IF(OR(E72>=0,GK_variante=3),AG72,IF(GK_variante=2,AG72/(1+F72),IF(AK73*I73<=0,AG72/(1+F72),IF(AG72/(AK73*I73)>Tasso0,AG72/(1+F72),AG72)))) -> 38000 | AF73: =IF(AK73*I73<=0,9.9,AE73/(AK73*I73)) -> 0.042379297 | AG73: =IF(AND(AF73>Tasso0*(1+GK_banda),A73<=Anni-GK_ultimi),AE73*(1-GK_taglio),IF(AF73<Tasso0*(1-GK_banda),AE73*(1+GK_taglio),AE73)) -> 38000 | AH73: =AG73/I73 -> 43489.367 | AI73: =IF(AH73>AK73+0.000000001,1,0) -> 0 | AJ73: =MIN(AH73,AK73)*I73 -> 38000 | AK73: =(AK72-MIN(AH72,AK72))*G72/(1+F72) -> 1026193.7 | AL73: =MIN(MAX(Tasso0*AP73*I73,AL72*(1+VG_pav)),AL72*(1+VG_tetto)) -> 36407.689 | AM73: =AL73/I73 -> 41667.036 | AN73: =IF(AM73>AP73+0.000000001,1,0) -> 0 | AO73: =MIN(AM73,AP73)*I73 -> 36407.689 | AP73: =(AP72-MIN(AM72,AP72))*G72/(1+F72) -> 1027139.9 | AQ73: =IF(AND(A73<=Anni,M72>0),M73/M72-1,"") -> 0 | AR73: =IF(AND(A73<=Anni,R72>0),R73/R72-1,"") -> -0.021028604 | AS73: =IF(AND(A73<=Anni,W72>0),W73/W72-1,"") -> -0.021028604 | AT73: =IF(AND(A73<=Anni,AC72>0),AC73/AC72-1,"") -> -0.0093557843 | AU73: =IF(AND(A73<=Anni,AJ72>0),AJ73/AJ72-1,"") -> 0 | AV73: =IF(AND(A73<=Anni,AO72>0),AO73/AO72-1,"") -> -0.021028604
A74: =A73+1 -> 4 | B74: =Eta_inizio+A74-1 -> 54 | C74: =Anno_inizio+A74-1 -> 2003 | D74: =0 -> 0 | E74: =IF(D74=1,SUMIFS('5 - Dati'!$F$6:$F$186,'5 - Dati'!$A$6:$A$186,Serie,'5 - Dati'!$B$6:$B$186,C74),(1+Rend_c)*(1+Infl_c)-1) -> 0.0506 | F74: =IF(D74=1,SUMIFS('5 - Dati'!$E$6:$E$186,'5 - Dati'!$A$6:$A$186,Serie,'5 - Dati'!$B$6:$B$186,C74),Infl_c) -> 0.02 | G74: =(1+E74)*(1-Bollo_eff) -> 1.0484988 | H74: =H73/G73 -> 0.4907265 | I74: =1-Aliq_eff*MAX(0,1-H74) -> 0.86758889 | J74: =Spesa0 -> 38000 | K74: =J74/I74 -> 43799.547 | L74: =IF(K74>N74+0.000000001,1,0) -> 0 | M74: =MIN(K74,N74)*I74 -> 38000 | N74: =(N73-MIN(K73,N73))*G73/(1+F73) -> 1010161.1 | O74: =Tasso0*S74*I74 -> 35652.454 | P74: =O74/I74 -> 41093.719 | Q74: =IF(P74>S74+0.000000001,1,0) -> 0 | R74: =MIN(P74,S74)*I74 -> 35652.454 | S74: =(S73-MIN(P73,S73))*G73/(1+F73) -> 1013007 | T74: =MAX(Tasso0*X74*I74,Pav_pct*Spesa0) -> 35652.454 | U74: =T74/I74 -> 41093.719 | V74: =IF(U74>X74+0.000000001,1,0) -> 0 | W74: =MIN(U74,X74)*I74 -> 35652.454 | X74: =(X73-MIN(U73,X73))*G73/(1+F73) -> 1013007 | Y74: =IF(Eta_rif_VPW-B74<=1,1,IF(r_VPW=0,1/(Eta_rif_VPW-B74),r_VPW/(1-(1+r_VPW)^(-(Eta_rif_VPW-B74)))/(1+r_VPW))) -> 0.03918693 | Z74: =Y74*AD74*I74 -> 34670.803 | AA74: =Z74/I74 -> 39962.249 | AB74: =IF(AA74>AD74+0.000000001,1,0) -> 0 | AC74: =MIN(AA74,AD74)*I74 -> 34670.803 | AD74: =(AD73-MIN(AA73,AD73))*G73/(1+F73) -> 1019785.1 | AE74: =IF(OR(E73>=0,GK_variante=3),AG73,IF(GK_variante=2,AG73/(1+F73),IF(AK74*I74<=0,AG73/(1+F73),IF(AG73/(AK74*I74)>Tasso0,AG73/(1+F73),AG73)))) -> 38000 | AF74: =IF(AK74*I74<=0,9.9,AE74/(AK74*I74)) -> 0.043358973 | AG74: =IF(AND(AF74>Tasso0*(1+GK_banda),A74<=Anni-GK_ultimi),AE74*(1-GK_taglio),IF(AF74<Tasso0*(1-GK_banda),AE74*(1+GK_taglio),AE74)) -> 38000 | AH74: =AG74/I74 -> 43799.547 | AI74: =IF(AH74>AK74+0.000000001,1,0) -> 0 | AJ74: =MIN(AH74,AK74)*I74 -> 38000 | AK74: =(AK73-MIN(AH73,AK73))*G73/(1+F73) -> 1010161.1 | AL74: =MIN(MAX(Tasso0*AP74*I74,AL73*(1+VG_pav)),AL73*(1+VG_tetto)) -> 35652.454 | AM74: =AL74/I74 -> 41093.719 | AN74: =IF(AM74>AP74+0.000000001,1,0) -> 0 | AO74: =MIN(AM74,AP74)*I74 -> 35652.454 | AP74: =(AP73-MIN(AM73,AP73))*G73/(1+F73) -> 1013007 | AQ74: =IF(AND(A74<=Anni,M73>0),M74/M73-1,"") -> 0 | AR74: =IF(AND(A74<=Anni,R73>0),R74/R73-1,"") -> -0.020743847 | AS74: =IF(AND(A74<=Anni,W73>0),W74/W73-1,"") -> -0.020743847 | AT74: =IF(AND(A74<=Anni,AC73>0),AC74/AC73-1,"") -> -0.0090676312 | AU74: =IF(AND(A74<=Anni,AJ73>0),AJ74/AJ73-1,"") -> 0 | AV74: =IF(AND(A74<=Anni,AO73>0),AO74/AO73-1,"") -> -0.020743847
A75: =A74+1 -> 5 | B75: =Eta_inizio+A75-1 -> 55 | C75: =Anno_inizio+A75-1 -> 2004 | D75: =0 -> 0 | E75: =IF(D75=1,SUMIFS('5 - Dati'!$F$6:$F$186,'5 - Dati'!$A$6:$A$186,Serie,'5 - Dati'!$B$6:$B$186,C75),(1+Rend_c)*(1+Infl_c)-1) -> 0.0506 | F75: =IF(D75=1,SUMIFS('5 - Dati'!$E$6:$E$186,'5 - Dati'!$A$6:$A$186,Serie,'5 - Dati'!$B$6:$B$186,C75),Infl_c) -> 0.02 | G75: =(1+E75)*(1-Bollo_eff) -> 1.0484988 | H75: =H74/G74 -> 0.46802771 | I75: =1-Aliq_eff*MAX(0,1-H75) -> 0.86168721 | J75: =Spesa0 -> 38000 | K75: =J75/I75 -> 44099.529 | L75: =IF(K75>N75+0.000000001,1,0) -> 0 | M75: =MIN(K75,N75)*I75 -> 38000 | N75: =(N74-MIN(K74,N74))*G74/(1+F74) -> 993361.67 | O75: =Tasso0*S75*I75 -> 34922.709 | P75: =O75/I75 -> 40528.29 | Q75: =IF(P75>S75+0.000000001,1,0) -> 0 | R75: =MIN(P75,S75)*I75 -> 34922.709 | S75: =(S74-MIN(P74,S74))*G74/(1+F74) -> 999068.49 | T75: =MAX(Tasso0*X75*I75,Pav_pct*Spesa0) -> 34922.709 | U75: =T75/I75 -> 40528.29 | V75: =IF(U75>X75+0.000000001,1,0) -> 0 | W75: =MIN(U75,X75)*I75 -> 34922.709 | X75: =(X74-MIN(U74,X74))*G74/(1+F74) -> 999068.49 | Y75: =IF(Eta_rif_VPW-B75<=1,1,IF(r_VPW=0,1/(Eta_rif_VPW-B75),r_VPW/(1-(1+r_VPW)^(-(Eta_rif_VPW-B75)))/(1+r_VPW))) -> 0.039597258 | Z75: =Y75*AD75*I75 -> 34366.089 | AA75: =Z75/I75 -> 39882.324 | AB75: =IF(AA75>AD75+0.000000001,1,0) -> 0 | AC75: =MIN(AA75,AD75)*I75 -> 34366.089 | AD75: =(AD74-MIN(AA74,AD74))*G74/(1+F74) -> 1007199.1 | AE75: =IF(OR(E74>=0,GK_variante=3),AG74,IF(GK_variante=2,AG74/(1+F74),IF(AK75*I75<=0,AG74/(1+F74),IF(AG74/(AK75*I75)>Tasso0,AG74/(1+F74),AG74)))) -> 38000 | AF75: =IF(AK75*I75<=0,9.9,AE75/(AK75*I75)) -> 0.044394233 | AG75: =IF(AND(AF75>Tasso0*(1+GK_banda),A75<=Anni-GK_ultimi),AE75*(1-GK_taglio),IF(AF75<Tasso0*(1-GK_banda),AE75*(1+GK_taglio),AE75)) -> 38000 | AH75: =AG75/I75 -> 44099.529 | AI75: =IF(AH75>AK75+0.000000001,1,0) -> 0 | AJ75: =MIN(AH75,AK75)*I75 -> 38000 | AK75: =(AK74-MIN(AH74,AK74))*G74/(1+F74) -> 993361.67 | AL75: =MIN(MAX(Tasso0*AP75*I75,AL74*(1+VG_pav)),AL74*(1+VG_tetto)) -> 34922.709 | AM75: =AL75/I75 -> 40528.29 | AN75: =IF(AM75>AP75+0.000000001,1,0) -> 0 | AO75: =MIN(AM75,AP75)*I75 -> 34922.709 | AP75: =(AP74-MIN(AM74,AP74))*G74/(1+F74) -> 999068.49 | AQ75: =IF(AND(A75<=Anni,M74>0),M75/M74-1,"") -> 0 | AR75: =IF(AND(A75<=Anni,R74>0),R75/R74-1,"") -> -0.020468293 | AS75: =IF(AND(A75<=Anni,W74>0),W75/W74-1,"") -> -0.020468293 | AT75: =IF(AND(A75<=Anni,AC74>0),AC75/AC74-1,"") -> -0.0087887915 | AU75: =IF(AND(A75<=Anni,AJ74>0),AJ75/AJ74-1,"") -> 0 | AV75: =IF(AND(A75<=Anni,AO74>0),AO75/AO74-1,"") -> -0.020468293
A76: =A75+1 -> 6 | B76: =Eta_inizio+A76-1 -> 56 | C76: =Anno_inizio+A76-1 -> 2005 | D76: =0 -> 0 | E76: =IF(D76=1,SUMIFS('5 - Dati'!$F$6:$F$186,'5 - Dati'!$A$6:$A$186,Serie,'5 - Dati'!$B$6:$B$186,C76),(1+Rend_c)*(1+Infl_c)-1) -> 0.0506 | F76: =IF(D76=1,SUMIFS('5 - Dati'!$E$6:$E$186,'5 - Dati'!$A$6:$A$186,Serie,'5 - Dati'!$B$6:$B$186,C76),Infl_c) -> 0.02 | G76: =(1+E76)*(1-Bollo_eff) -> 1.0484988 | H76: =H75/G75 -> 0.44637887 | I76: =1-Aliq_eff*MAX(0,1-H76) -> 0.85605851 | J76: =Spesa0 -> 38000 | K76: =J76/I76 -> 44389.489 | L76: =IF(K76>N76+0.000000001,1,0) -> 0 | M76: =MIN(K76,N76)*I76 -> 38000 | N76: =(N75-MIN(K75,N75))*G75/(1+F75) -> 975784.52 | O76: =Tasso0*S76*I76 -> 34217.207 | P76: =O76/I76 -> 39970.641 | Q76: =IF(P76>S76+0.000000001,1,0) -> 0 | R76: =MIN(P76,S76)*I76 -> 34217.207 | S76: =(S75-MIN(P75,S75))*G75/(1+F75) -> 985321.81 | T76: =MAX(Tasso0*X76*I76,Pav_pct*Spesa0) -> 34217.207 | U76: =T76/I76 -> 39970.641 | V76: =IF(U76>X76+0.000000001,1,0) -> 0 | W76: =MIN(U76,X76)*I76 -> 34217.207 | X76: =(X75-MIN(U75,X75))*G75/(1+F75) -> 985321.81 | Y76: =IF(Eta_rif_VPW-B76<=1,1,IF(r_VPW=0,1/(Eta_rif_VPW-B76),r_VPW/(1-(1+r_VPW)^(-(Eta_rif_VPW-B76)))/(1+r_VPW))) -> 0.040028978 | Z76: =Y76*AD76*I76 -> 34073.32 | AA76: =Z76/I76 -> 39802.56 | AB76: =IF(AA76>AD76+0.000000001,1,0) -> 0 | AC76: =MIN(AA76,AD76)*I76 -> 34073.32 | AD76: =(AD75-MIN(AA75,AD75))*G75/(1+F75) -> 994343.65 | AE76: =IF(OR(E75>=0,GK_variante=3),AG75,IF(GK_variante=2,AG75/(1+F75),IF(AK76*I76<=0,AG75/(1+F75),IF(AG75/(AK76*I76)>Tasso0,AG75/(1+F75),AG75)))) -> 38000 | AF76: =IF(AK76*I76<=0,9.9,AE76/(AK76*I76)) -> 0.045491078 | AG76: =IF(AND(AF76>Tasso0*(1+GK_banda),A76<=Anni-GK_ultimi),AE76*(1-GK_taglio),IF(AF76<Tasso0*(1-GK_banda),AE76*(1+GK_taglio),AE76)) -> 38000 | AH76: =AG76/I76 -> 44389.489 | AI76: =IF(AH76>AK76+0.000000001,1,0) -> 0 | AJ76: =MIN(AH76,AK76)*I76 -> 38000 | AK76: =(AK75-MIN(AH75,AK75))*G75/(1+F75) -> 975784.52 | AL76: =MIN(MAX(Tasso0*AP76*I76,AL75*(1+VG_pav)),AL75*(1+VG_tetto)) -> 34217.207 | AM76: =AL76/I76 -> 39970.641 | AN76: =IF(AM76>AP76+0.000000001,1,0) -> 0 | AO76: =MIN(AM76,AP76)*I76 -> 34217.207 | AP76: =(AP75-MIN(AM75,AP75))*G75/(1+F75) -> 985321.81 | AQ76: =IF(AND(A76<=Anni,M75>0),M76/M75-1,"") -> 0 | AR76: =IF(AND(A76<=Anni,R75>0),R76/R75-1,"") -> -0.020201797 | AS76: =IF(AND(A76<=Anni,W75>0),W76/W75-1,"") -> -0.020201797 | AT76: =IF(AND(A76<=Anni,AC75>0),AC76/AC75-1,"") -> -0.0085191184 | AU76: =IF(AND(A76<=Anni,AJ75>0),AJ76/AJ75-1,"") -> 0 | AV76: =IF(AND(A76<=Anni,AO75>0),AO76/AO75-1,"") -> -0.020201797
A77: =A76+1 -> 7 | B77: =Eta_inizio+A77-1 -> 57 | C77: =Anno_inizio+A77-1 -> 2006 | D77: =0 -> 0 | E77: =IF(D77=1,SUMIFS('5 - Dati'!$F$6:$F$186,'5 - Dati'!$A$6:$A$186,Serie,'5 - Dati'!$B$6:$B$186,C77),(1+Rend_c)*(1+Infl_c)-1) -> 0.0506 | F77: =IF(D77=1,SUMIFS('5 - Dati'!$E$6:$E$186,'5 - Dati'!$A$6:$A$186,Serie,'5 - Dati'!$B$6:$B$186,C77),Infl_c) -> 0.02 | G77: =(1+E77)*(1-Bollo_eff) -> 1.0484988 | H77: =H76/G76 -> 0.42573141 | I77: =1-Aliq_eff*MAX(0,1-H77) -> 0.85069017 | J77: =Spesa0 -> 38000 | K77: =J77/I77 -> 44669.612 | L77: =IF(K77>N77+0.000000001,1,0) -> 0 | M77: =MIN(K77,N77)*I77 -> 38000 | N77: =(N76-MIN(K76,N76))*G76/(1+F76) -> 957418.21 | O77: =Tasso0*S77*I77 -> 33534.772 | P77: =O77/I77 -> 39420.665 | Q77: =IF(P77>S77+0.000000001,1,0) -> 0 | R77: =MIN(P77,S77)*I77 -> 33534.772 | S77: =(S76-MIN(P76,S76))*G76/(1+F76) -> 971764.28 | T77: =MAX(Tasso0*X77*I77,Pav_pct*Spesa0) -> 34200 | U77: =T77/I77 -> 40202.651 | V77: =IF(U77>X77+0.000000001,1,0) -> 0 | W77: =MIN(U77,X77)*I77 -> 34200 | X77: =(X76-MIN(U76,X76))*G76/(1+F76) -> 971764.28 | Y77: =IF(Eta_rif_VPW-B77<=1,1,IF(r_VPW=0,1/(Eta_rif_VPW-B77),r_VPW/(1-(1+r_VPW)^(-(Eta_rif_VPW-B77)))/(1+r_VPW))) -> 0.040483602 | Z77: =Y77*AD77*I77 -> 33791.927 | AA77: =Z77/I77 -> 39722.954 | AB77: =IF(AA77>AD77+0.000000001,1,0) -> 0 | AC77: =MIN(AA77,AD77)*I77 -> 33791.927 | AD77: =(AD76-MIN(AA76,AD76))*G76/(1+F76) -> 981210.97 | AE77: =IF(OR(E76>=0,GK_variante=3),AG76,IF(GK_variante=2,AG76/(1+F76),IF(AK77*I77<=0,AG76/(1+F76),IF(AG76/(AK77*I77)>Tasso0,AG76/(1+F76),AG76)))) -> 38000 | AF77: =IF(AK77*I77<=0,9.9,AE77/(AK77*I77)) -> 0.046656322 | AG77: =IF(AND(AF77>Tasso0*(1+GK_banda),A77<=Anni-GK_ultimi),AE77*(1-GK_taglio),IF(AF77<Tasso0*(1-GK_banda),AE77*(1+GK_taglio),AE77)) -> 38000 | AH77: =AG77/I77 -> 44669.612 | AI77: =IF(AH77>AK77+0.000000001,1,0) -> 0 | AJ77: =MIN(AH77,AK77)*I77 -> 38000 | AK77: =(AK76-MIN(AH76,AK76))*G76/(1+F76) -> 957418.21 | AL77: =MIN(MAX(Tasso0*AP77*I77,AL76*(1+VG_pav)),AL76*(1+VG_tetto)) -> 33534.772 | AM77: =AL77/I77 -> 39420.665 | AN77: =IF(AM77>AP77+0.000000001,1,0) -> 0 | AO77: =MIN(AM77,AP77)*I77 -> 33534.772 | AP77: =(AP76-MIN(AM76,AP76))*G76/(1+F76) -> 971764.28 | AQ77: =IF(AND(A77<=Anni,M76>0),M77/M76-1,"") -> 0 | AR77: =IF(AND(A77<=Anni,R76>0),R77/R76-1,"") -> -0.019944205 | AS77: =IF(AND(A77<=Anni,W76>0),W77/W76-1,"") -> -0.0005028843 | AT77: =IF(AND(A77<=Anni,AC76>0),AC77/AC76-1,"") -> -0.0082584549 | AU77: =IF(AND(A77<=Anni,AJ76>0),AJ77/AJ76-1,"") -> 0 | AV77: =IF(AND(A77<=Anni,AO76>0),AO77/AO76-1,"") -> -0.019944205
A78: =A77+1 -> 8 | B78: =Eta_inizio+A78-1 -> 58 | C78: =Anno_inizio+A78-1 -> 2007 | D78: =0 -> 0 | E78: =IF(D78=1,SUMIFS('5 - Dati'!$F$6:$F$186,'5 - Dati'!$A$6:$A$186,Serie,'5 - Dati'!$B$6:$B$186,C78),(1+Rend_c)*(1+Infl_c)-1) -> 0.0506 | F78: =IF(D78=1,SUMIFS('5 - Dati'!$E$6:$E$186,'5 - Dati'!$A$6:$A$186,Serie,'5 - Dati'!$B$6:$B$186,C78),Infl_c) -> 0.02 | G78: =(1+E78)*(1-Bollo_eff) -> 1.0484988 | H78: =H77/G77 -> 0.40603901 | I78: =1-Aliq_eff*MAX(0,1-H78) -> 0.84557014 | J78: =Spesa0 -> 38000 | K78: =J78/I78 -> 44940.092 | L78: =IF(K78>N78+0.000000001,1,0) -> 0 | M78: =MIN(K78,N78)*I78 -> 38000 | N78: =(N77-MIN(K77,N77))*G77/(1+F77) -> 938250.79 | O78: =Tasso0*S78*I78 -> 32874.293 | P78: =O78/I78 -> 38878.257 | Q78: =IF(P78>S78+0.000000001,1,0) -> 0 | R78: =MIN(P78,S78)*I78 -> 32874.293 | S78: =(S77-MIN(P77,S77))*G77/(1+F77) -> 958393.3 | T78: =MAX(Tasso0*X78*I78,Pav_pct*Spesa0) -> 34200 | U78: =T78/I78 -> 40446.083 | V78: =IF(U78>X78+0.000000001,1,0) -> 0 | W78: =MIN(U78,X78)*I78 -> 34200 | X78: =(X77-MIN(U77,X77))*G77/(1+F77) -> 957589.46 | Y78: =IF(Eta_rif_VPW-B78<=1,1,IF(r_VPW=0,1/(Eta_rif_VPW-B78),r_VPW/(1-(1+r_VPW)^(-(Eta_rif_VPW-B78)))/(1+r_VPW))) -> 0.040962789 | Z78: =Y78*AD78*I78 -> 33521.367 | AA78: =Z78/I78 -> 39643.509 | AB78: =IF(AA78>AD78+0.000000001,1,0) -> 0 | AC78: =MIN(AA78,AD78)*I78 -> 33521.367 | AD78: =(AD77-MIN(AA77,AD77))*G77/(1+F77) -> 967793.19 | AE78: =IF(OR(E77>=0,GK_variante=3),AG77,IF(GK_variante=2,AG77/(1+F77),IF(AK78*I78<=0,AG77/(1+F77),IF(AG77/(AK78*I78)>Tasso0,AG77/(1+F77),AG77)))) -> 38000 | AF78: =IF(AK78*I78<=0,9.9,AE78/(AK78*I78)) -> 0.047897739 | AG78: =IF(AND(AF78>Tasso0*(1+GK_banda),A78<=Anni-GK_ultimi),AE78*(1-GK_taglio),IF(AF78<Tasso0*(1-GK_banda),AE78*(1+GK_taglio),AE78)) -> 38000 | AH78: =AG78/I78 -> 44940.092 | AI78: =IF(AH78>AK78+0.000000001,1,0) -> 0 | AJ78: =MIN(AH78,AK78)*I78 -> 38000 | AK78: =(AK77-MIN(AH77,AK77))*G77/(1+F77) -> 938250.79 | AL78: =MIN(MAX(Tasso0*AP78*I78,AL77*(1+VG_pav)),AL77*(1+VG_tetto)) -> 32874.293 | AM78: =AL78/I78 -> 38878.257 | AN78: =IF(AM78>AP78+0.000000001,1,0) -> 0 | AO78: =MIN(AM78,AP78)*I78 -> 32874.293 | AP78: =(AP77-MIN(AM77,AP77))*G77/(1+F77) -> 958393.3 | AQ78: =IF(AND(A78<=Anni,M77>0),M78/M77-1,"") -> 0 | AR78: =IF(AND(A78<=Anni,R77>0),R78/R77-1,"") -> -0.019695352 | AS78: =IF(AND(A78<=Anni,W77>0),W78/W77-1,"") -> 0 | AT78: =IF(AND(A78<=Anni,AC77>0),AC78/AC77-1,"") -> -0.0080066348 | AU78: =IF(AND(A78<=Anni,AJ77>0),AJ78/AJ77-1,"") -> 0 | AV78: =IF(AND(A78<=Anni,AO77>0),AO78/AO77-1,"") -> -0.019695352
A79: =A78+1 -> 9 | B79: =Eta_inizio+A79-1 -> 59 | C79: =Anno_inizio+A79-1 -> 2008 | D79: =0 -> 0 | E79: =IF(D79=1,SUMIFS('5 - Dati'!$F$6:$F$186,'5 - Dati'!$A$6:$A$186,Serie,'5 - Dati'!$B$6:$B$186,C79),(1+Rend_c)*(1+Infl_c)-1) -> 0.0506 | F79: =IF(D79=1,SUMIFS('5 - Dati'!$E$6:$E$186,'5 - Dati'!$A$6:$A$186,Serie,'5 - Dati'!$B$6:$B$186,C79),Infl_c) -> 0.02 | G79: =(1+E79)*(1-Bollo_eff) -> 1.0484988 | H79: =H78/G78 -> 0.38725748 | I79: =1-Aliq_eff*MAX(0,1-H79) -> 0.84068695 | J79: =Spesa0 -> 38000 | K79: =J79/I79 -> 45201.13 | L79: =IF(K79>N79+0.000000001,1,0) -> 0 | M79: =MIN(K79,N79)*I79 -> 38000 | N79: =(N78-MIN(K78,N78))*G78/(1+F78) -> 918269.8 | O79: =Tasso0*S79*I79 -> 32234.722 | P79: =O79/I79 -> 38343.312 | Q79: =IF(P79>S79+0.000000001,1,0) -> 0 | R79: =MIN(P79,S79)*I79 -> 32234.722 | S79: =(S78-MIN(P78,S78))*G78/(1+F78) -> 945206.29 | T79: =MAX(Tasso0*X79*I79,Pav_pct*Spesa0) -> 34200 | U79: =T79/I79 -> 40681.017 | V79: =IF(U79>X79+0.000000001,1,0) -> 0 | W79: =MIN(U79,X79)*I79 -> 34200 | X79: =(X78-MIN(U78,X78))*G78/(1+F78) -> 942768.37 | Y79: =IF(Eta_rif_VPW-B79<=1,1,IF(r_VPW=0,1/(Eta_rif_VPW-B79),r_VPW/(1-(1+r_VPW)^(-(Eta_rif_VPW-B79)))/(1+r_VPW))) -> 0.041468358 | Z79: =Y79*AD79*I79 -> 33261.125 | AA79: =Z79/I79 -> 39564.222 | AB79: =IF(AA79>AD79+0.000000001,1,0) -> 0 | AC79: =MIN(AA79,AD79)*I79 -> 33261.125 | AD79: =(AD78-MIN(AA78,AD78))*G78/(1+F78) -> 954082.18 | AE79: =IF(OR(E78>=0,GK_variante=3),AG78,IF(GK_variante=2,AG78/(1+F78),IF(AK79*I79<=0,AG78/(1+F78),IF(AG78/(AK79*I79)>Tasso0,AG78/(1+F78),AG78)))) -> 38000 | AF79: =IF(AK79*I79<=0,9.9,AE79/(AK79*I79)) -> 0.049224237 | AG79: =IF(AND(AF79>Tasso0*(1+GK_banda),A79<=Anni-GK_ultimi),AE79*(1-GK_taglio),IF(AF79<Tasso0*(1-GK_banda),AE79*(1+GK_taglio),AE79)) -> 34200 | AH79: =AG79/I79 -> 40681.017 | AI79: =IF(AH79>AK79+0.000000001,1,0) -> 0 | AJ79: =MIN(AH79,AK79)*I79 -> 34200 | AK79: =(AK78-MIN(AH78,AK78))*G78/(1+F78) -> 918269.8 | AL79: =MIN(MAX(Tasso0*AP79*I79,AL78*(1+VG_pav)),AL78*(1+VG_tetto)) -> 32234.722 | AM79: =AL79/I79 -> 38343.312 | AN79: =IF(AM79>AP79+0.000000001,1,0) -> 0 | AO79: =MIN(AM79,AP79)*I79 -> 32234.722 | AP79: =(AP78-MIN(AM78,AP78))*G78/(1+F78) -> 945206.29 | AQ79: =IF(AND(A79<=Anni,M78>0),M79/M78-1,"") -> 0 | AR79: =IF(AND(A79<=Anni,R78>0),R79/R78-1,"") -> -0.019455066 | AS79: =IF(AND(A79<=Anni,W78>0),W79/W78-1,"") -> 0 | AT79: =IF(AND(A79<=Anni,AC78>0),AC79/AC78-1,"") -> -0.0077634836 | AU79: =IF(AND(A79<=Anni,AJ78>0),AJ79/AJ78-1,"") -> -0.1 | AV79: =IF(AND(A79<=Anni,AO78>0),AO79/AO78-1,"") -> -0.019455066
A80: =A79+1 -> 10 | B80: =Eta_inizio+A80-1 -> 60 | C80: =Anno_inizio+A80-1 -> 2009 | D80: =0 -> 0 | E80: =IF(D80=1,SUMIFS('5 - Dati'!$F$6:$F$186,'5 - Dati'!$A$6:$A$186,Serie,'5 - Dati'!$B$6:$B$186,C80),(1+Rend_c)*(1+Infl_c)-1) -> 0.0506 | F80: =IF(D80=1,SUMIFS('5 - Dati'!$E$6:$E$186,'5 - Dati'!$A$6:$A$186,Serie,'5 - Dati'!$B$6:$B$186,C80),Infl_c) -> 0.02 | G80: =(1+E80)*(1-Bollo_eff) -> 1.0484988 | H80: =H79/G79 -> 0.36934471 | I80: =1-Aliq_eff*MAX(0,1-H80) -> 0.83602962 | J80: =Spesa0 -> 38000 | K80: =J80/I80 -> 45452.935 | L80: =IF(K80>N80+0.000000001,1,0) -> 0 | M80: =MIN(K80,N80)*I80 -> 38000 | N80: =(N79-MIN(K79,N79))*G79/(1+F79) -> 897462.21 | O80: =Tasso0*S80*I80 -> 31615.068 | P80: =O80/I80 -> 37815.727 | Q80: =IF(P80>S80+0.000000001,1,0) -> 0 | R80: =MIN(P80,S80)*I80 -> 31615.068 | S80: =(S79-MIN(P79,S79))*G79/(1+F79) -> 932200.73 | T80: =MAX(Tasso0*X80*I80,Pav_pct*Spesa0) -> 34200 | U80: =T80/I80 -> 40907.641 | V80: =IF(U80>X80+0.000000001,1,0) -> 0 | W80: =MIN(U80,X80)*I80 -> 34200 | X80: =(X79-MIN(U79,X79))*G79/(1+F79) -> 927291.67 | Y80: =IF(Eta_rif_VPW-B80<=1,1,IF(r_VPW=0,1/(Eta_rif_VPW-B80),r_VPW/(1-(1+r_VPW)^(-(Eta_rif_VPW-B80)))/(1+r_VPW))) -> 0.042002309 | Z80: =Y80*AD80*I80 -> 33010.708 | AA80: =Z80/I80 -> 39485.093 | AB80: =IF(AA80>AD80+0.000000001,1,0) -> 0 | AC80: =MIN(AA80,AD80)*I80 -> 33010.708 | AD80: =(AD79-MIN(AA79,AD79))*G79/(1+F79) -> 940069.59 | AE80: =IF(OR(E79>=0,GK_variante=3),AG79,IF(GK_variante=2,AG79/(1+F79),IF(AK80*I80<=0,AG79/(1+F79),IF(AG79/(AK80*I80)>Tasso0,AG79/(1+F79),AG79)))) -> 34200 | AF80: =IF(AK80*I80<=0,9.9,AE80/(AK80*I80)) -> 0.045346692 | AG80: =IF(AND(AF80>Tasso0*(1+GK_banda),A80<=Anni-GK_ultimi),AE80*(1-GK_taglio),IF(AF80<Tasso0*(1-GK_banda),AE80*(1+GK_taglio),AE80)) -> 34200 | AH80: =AG80/I80 -> 40907.641 | AI80: =IF(AH80>AK80+0.000000001,1,0) -> 0 | AJ80: =MIN(AH80,AK80)*I80 -> 34200 | AK80: =(AK79-MIN(AH79,AK79))*G79/(1+F79) -> 902108.62 | AL80: =MIN(MAX(Tasso0*AP80*I80,AL79*(1+VG_pav)),AL79*(1+VG_tetto)) -> 31615.068 | AM80: =AL80/I80 -> 37815.727 | AN80: =IF(AM80>AP80+0.000000001,1,0) -> 0 | AO80: =MIN(AM80,AP80)*I80 -> 31615.068 | AP80: =(AP79-MIN(AM79,AP79))*G79/(1+F79) -> 932200.73 | AQ80: =IF(AND(A80<=Anni,M79>0),M80/M79-1,"") -> 0 | AR80: =IF(AND(A80<=Anni,R79>0),R80/R79-1,"") -> -0.019223168 | AS80: =IF(AND(A80<=Anni,W79>0),W80/W79-1,"") -> 0 | AT80: =IF(AND(A80<=Anni,AC79>0),AC80/AC79-1,"") -> -0.0075288201 | AU80: =IF(AND(A80<=Anni,AJ79>0),AJ80/AJ79-1,"") -> 0 | AV80: =IF(AND(A80<=Anni,AO79>0),AO80/AO79-1,"") -> -0.019223168
A81: =A80+1 -> 11 | B81: =Eta_inizio+A81-1 -> 61 | C81: =Anno_inizio+A81-1 -> 2010 | D81: =0 -> 0 | E81: =IF(D81=1,SUMIFS('5 - Dati'!$F$6:$F$186,'5 - Dati'!$A$6:$A$186,Serie,'5 - Dati'!$B$6:$B$186,C81),(1+Rend_c)*(1+Infl_c)-1) -> 0.0506 | F81: =IF(D81=1,SUMIFS('5 - Dati'!$E$6:$E$186,'5 - Dati'!$A$6:$A$186,Serie,'5 - Dati'!$B$6:$B$186,C81),Infl_c) -> 0.02 | G81: =(1+E81)*(1-Bollo_eff) -> 1.0484988 | H81: =H80/G80 -> 0.3522605 | I81: =1-Aliq_eff*MAX(0,1-H81) -> 0.83158773 | J81: =Spesa0 -> 38000 | K81: =J81/I81 -> 45695.72 | L81: =IF(K81>N81+0.000000001,1,0) -> 0 | M81: =MIN(K81,N81)*I81 -> 38000 | N81: =(N80-MIN(K80,N80))*G80/(1+F80) -> 875814.41 | O81: =Tasso0*S81*I81 -> 31014.399 | P81: =O81/I81 -> 37295.402 | Q81: =IF(P81>S81+0.000000001,1,0) -> 0 | R81: =MIN(P81,S81)*I81 -> 31014.399 | S81: =(S80-MIN(P80,S80))*G80/(1+F80) -> 919374.12 | T81: =MAX(Tasso0*X81*I81,Pav_pct*Spesa0) -> 34200 | U81: =T81/I81 -> 41126.148 | V81: =IF(U81>X81+0.000000001,1,0) -> 0 | W81: =MIN(U81,X81)*I81 -> 34200 | X81: =(X80-MIN(U80,X80))*G80/(1+F80) -> 911149.6 | Y81: =IF(Eta_rif_VPW-B81<=1,1,IF(r_VPW=0,1/(Eta_rif_VPW-B81),r_VPW/(1-(1+r_VPW)^(-(Eta_rif_VPW-B81)))/(1+r_VPW))) -> 0.042566846 | Z81: =Y81*AD81*I81 -> 32769.648 | AA81: =Z81/I81 -> 39406.123 | AB81: =IF(AA81>AD81+0.000000001,1,0) -> 0 | AC81: =MIN(AA81,AD81)*I81 -> 32769.648 | AD81: =(AD80-MIN(AA80,AD80))*G80/(1+F80) -> 925746.83 | AE81: =IF(OR(E80>=0,GK_variante=3),AG80,IF(GK_variante=2,AG80/(1+F80),IF(AK81*I81<=0,AG80/(1+F80),IF(AG80/(AK81*I81)>Tasso0,AG80/(1+F80),AG80)))) -> 34200 | AF81: =IF(AK81*I81<=0,9.9,AE81/(AK81*I81)) -> 0.046456422 | AG81: =IF(AND(AF81>Tasso0*(1+GK_banda),A81<=Anni-GK_ultimi),AE81*(1-GK_taglio),IF(AF81<Tasso0*(1-GK_banda),AE81*(1+GK_taglio),AE81)) -> 34200 | AH81: =AG81/I81 -> 41126.148 | AI81: =IF(AH81>AK81+0.000000001,1,0) -> 0 | AJ81: =MIN(AH81,AK81)*I81 -> 34200 | AK81: =(AK80-MIN(AH80,AK80))*G80/(1+F80) -> 885262.93 | AL81: =MIN(MAX(Tasso0*AP81*I81,AL80*(1+VG_pav)),AL80*(1+VG_tetto)) -> 31014.399 | AM81: =AL81/I81 -> 37295.402 | AN81: =IF(AM81>AP81+0.000000001,1,0) -> 0 | AO81: =MIN(AM81,AP81)*I81 -> 31014.399 | AP81: =(AP80-MIN(AM80,AP80))*G80/(1+F80) -> 919374.12 | AQ81: =IF(AND(A81<=Anni,M80>0),M81/M80-1,"") -> 0 | AR81: =IF(AND(A81<=Anni,R80>0),R81/R80-1,"") -> -0.018999472 | AS81: =IF(AND(A81<=Anni,W80>0),W81/W80-1,"") -> 0 | AT81: =IF(AND(A81<=Anni,AC80>0),AC81/AC80-1,"") -> -0.007302457 | AU81: =IF(AND(A81<=Anni,AJ80>0),AJ81/AJ80-1,"") -> 0 | AV81: =IF(AND(A81<=Anni,AO80>0),AO81/AO80-1,"") -> -0.018999472
A82: =A81+1 -> 12 | B82: =Eta_inizio+A82-1 -> 62 | C82: =Anno_inizio+A82-1 -> 2011 | D82: =0 -> 0 | E82: =IF(D82=1,SUMIFS('5 - Dati'!$F$6:$F$186,'5 - Dati'!$A$6:$A$186,Serie,'5 - Dati'!$B$6:$B$186,C82),(1+Rend_c)*(1+Infl_c)-1) -> 0.0506 | F82: =IF(D82=1,SUMIFS('5 - Dati'!$E$6:$E$186,'5 - Dati'!$A$6:$A$186,Serie,'5 - Dati'!$B$6:$B$186,C82),Infl_c) -> 0.02 | G82: =(1+E82)*(1-Bollo_eff) -> 1.0484988 | H82: =H81/G81 -> 0.33596652 | I82: =1-Aliq_eff*MAX(0,1-H82) -> 0.8273513 | J82: =Spesa0 -> 38000 | K82: =J82/I82 -> 45929.704 | L82: =IF(K82>N82+0.000000001,1,0) -> 0 | M82: =MIN(K82,N82)*I82 -> 38000 | N82: =(N81-MIN(K81,N81))*G81/(1+F81) -> 853312.21 | O82: =Tasso0*S82*I82 -> 30431.831 | P82: =O82/I82 -> 36782.236 | Q82: =IF(P82>S82+0.000000001,1,0) -> 0 | R82: =MIN(P82,S82)*I82 -> 30431.831 | S82: =(S81-MIN(P81,S81))*G81/(1+F81) -> 906724 | T82: =MAX(Tasso0*X82*I82,Pav_pct*Spesa0) -> 34200 | U82: =T82/I82 -> 41336.733 | V82: =IF(U82>X82+0.000000001,1,0) -> 0 | W82: =MIN(U82,X82)*I82 -> 34200 | X82: =(X81-MIN(U81,X81))*G81/(1+F81) -> 894331.9 | Y82: =IF(Eta_rif_VPW-B82<=1,1,IF(r_VPW=0,1/(Eta_rif_VPW-B82),r_VPW/(1-(1+r_VPW)^(-(Eta_rif_VPW-B82)))/(1+r_VPW))) -> 0.043164408 | Z82: =Y82*AD82*I82 -> 32537.501 | AA82: =Z82/I82 -> 39327.311 | AB82: =IF(AA82>AD82+0.000000001,1,0) -> 0 | AC82: =MIN(AA82,AD82)*I82 -> 32537.501 | AD82: =(AD81-MIN(AA81,AD81))*G81/(1+F81) -> 911105.06 | AE82: =IF(OR(E81>=0,GK_variante=3),AG81,IF(GK_variante=2,AG81/(1+F81),IF(AK82*I82<=0,AG81/(1+F81),IF(AG81/(AK82*I82)>Tasso0,AG81/(1+F81),AG81)))) -> 34200 | AF82: =IF(AK82*I82<=0,9.9,AE82/(AK82*I82)) -> 0.047638224 | AG82: =IF(AND(AF82>Tasso0*(1+GK_banda),A82<=Anni-GK_ultimi),AE82*(1-GK_taglio),IF(AF82<Tasso0*(1-GK_banda),AE82*(1+GK_taglio),AE82)) -> 34200 | AH82: =AG82/I82 -> 41336.733 | AI82: =IF(AH82>AK82+0.000000001,1,0) -> 0 | AJ82: =MIN(AH82,AK82)*I82 -> 34200 | AK82: =(AK81-MIN(AH81,AK81))*G81/(1+F81) -> 867721.96 | AL82: =MIN(MAX(Tasso0*AP82*I82,AL81*(1+VG_pav)),AL81*(1+VG_tetto)) -> 30431.831 | AM82: =AL82/I82 -> 36782.236 | AN82: =IF(AM82>AP82+0.000000001,1,0) -> 0 | AO82: =MIN(AM82,AP82)*I82 -> 30431.831 | AP82: =(AP81-MIN(AM81,AP81))*G81/(1+F81) -> 906724 | AQ82: =IF(AND(A82<=Anni,M81>0),M82/M81-1,"") -> 0 | AR82: =IF(AND(A82<=Anni,R81>0),R82/R81-1,"") -> -0.018783789 | AS82: =IF(AND(A82<=Anni,W81>0),W82/W81-1,"") -> 0 | AT82: =IF(AND(A82<=Anni,AC81>0),AC82/AC81-1,"") -> -0.0070842022 | AU82: =IF(AND(A82<=Anni,AJ81>0),AJ82/AJ81-1,"") -> 0 | AV82: =IF(AND(A82<=Anni,AO81>0),AO82/AO81-1,"") -> -0.018783789
A83: =A82+1 -> 13 | B83: =Eta_inizio+A83-1 -> 63 | C83: =Anno_inizio+A83-1 -> 2012 | D83: =0 -> 0 | E83: =IF(D83=1,SUMIFS('5 - Dati'!$F$6:$F$186,'5 - Dati'!$A$6:$A$186,Serie,'5 - Dati'!$B$6:$B$186,C83),(1+Rend_c)*(1+Infl_c)-1) -> 0.0506 | F83: =IF(D83=1,SUMIFS('5 - Dati'!$E$6:$E$186,'5 - Dati'!$A$6:$A$186,Serie,'5 - Dati'!$B$6:$B$186,C83),Infl_c) -> 0.02 | G83: =(1+E83)*(1-Bollo_eff) -> 1.0484988 | H83: =H82/G82 -> 0.32042624 | I83: =1-Aliq_eff*MAX(0,1-H83) -> 0.82331082 | J83: =Spesa0 -> 38000 | K83: =J83/I83 -> 46155.108 | L83: =IF(K83>N83+0.000000001,1,0) -> 0 | M83: =MIN(K83,N83)*I83 -> 38000 | N83: =(N82-MIN(K82,N82))*G82/(1+F82) -> 829940.77 | O83: =Tasso0*S83*I83 -> 29866.531 | P83: =O83/I83 -> 36276.131 | Q83: =IF(P83>S83+0.000000001,1,0) -> 0 | R83: =MIN(P83,S83)*I83 -> 29866.531 | S83: =(S82-MIN(P82,S82))*G82/(1+F82) -> 894247.93 | T83: =MAX(Tasso0*X83*I83,Pav_pct*Spesa0) -> 34200 | U83: =T83/I83 -> 41539.597 | V83: =IF(U83>X83+0.000000001,1,0) -> 0 | W83: =MIN(U83,X83)*I83 -> 34200 | X83: =(X82-MIN(U82,X82))*G82/(1+F82) -> 876827.86 | Y83: =IF(Eta_rif_VPW-B83<=1,1,IF(r_VPW=0,1/(Eta_rif_VPW-B83),r_VPW/(1-(1+r_VPW)^(-(Eta_rif_VPW-B83)))/(1+r_VPW))) -> 0.043797694 | Z83: =Y83*AD83*I83 -> 32313.843 | AA83: =Z83/I83 -> 39248.656 | AB83: =IF(AA83>AD83+0.000000001,1,0) -> 0 | AC83: =MIN(AA83,AD83)*I83 -> 32313.843 | AD83: =(AD82-MIN(AA82,AD82))*G82/(1+F82) -> 896135.22 | AE83: =IF(OR(E82>=0,GK_variante=3),AG82,IF(GK_variante=2,AG82/(1+F82),IF(AK83*I83<=0,AG82/(1+F82),IF(AG82/(AK83*I83)>Tasso0,AG82/(1+F82),AG82)))) -> 34200 | AF83: =IF(AK83*I83<=0,9.9,AE83/(AK83*I83)) -> 0.04890035 | AG83: =IF(AND(AF83>Tasso0*(1+GK_banda),A83<=Anni-GK_ultimi),AE83*(1-GK_taglio),IF(AF83<Tasso0*(1-GK_banda),AE83*(1+GK_taglio),AE83)) -> 30780 | AH83: =AG83/I83 -> 37385.638 | AI83: =IF(AH83>AK83+0.000000001,1,0) -> 0 | AJ83: =MIN(AH83,AK83)*I83 -> 30780 | AK83: =(AK82-MIN(AH82,AK82))*G82/(1+F82) -> 849474.43 | AL83: =MIN(MAX(Tasso0*AP83*I83,AL82*(1+VG_pav)),AL82*(1+VG_tetto)) -> 29866.531 | AM83: =AL83/I83 -> 36276.131 | AN83: =IF(AM83>AP83+0.000000001,1,0) -> 0 | AO83: =MIN(AM83,AP83)*I83 -> 29866.531 | AP83: =(AP82-MIN(AM82,AP82))*G82/(1+F82) -> 894247.93 | AQ83: =IF(AND(A83<=Anni,M82>0),M83/M82-1,"") -> 0 | AR83: =IF(AND(A83<=Anni,R82>0),R83/R82-1,"") -> -0.018575924 | AS83: =IF(AND(A83<=Anni,W82>0),W83/W82-1,"") -> 0 | AT83: =IF(AND(A83<=Anni,AC82>0),AC83/AC82-1,"") -> -0.0068738594 | AU83: =IF(AND(A83<=Anni,AJ82>0),AJ83/AJ82-1,"") -> -0.1 | AV83: =IF(AND(A83<=Anni,AO82>0),AO83/AO82-1,"") -> -0.018575924
... A130: =A129+1 -> 60 | B130: =Eta_inizio+A130-1 -> 110 | C130: =Anno_inizio+A130-1 -> 2059 | D130: =0 -> 0 | E130: =IF(D130=1,SUMIFS('5 - Dati'!$F$6:$F$186,'5 - Dati'!$A$6:$A$186,Serie,'5 - Dati'!$B$6:$B$186,C130),(1+Rend_c)*(1+Infl_c)-1) -> 0.0506 | F130: =IF(D130=1,SUMIFS('5 - Dati'!$E$6:$E$186,'5 - Dati'!$A$6:$A$186,Serie,'5 - Dati'!$B$6:$B$186,C130),Infl_c) -> 0.02 | G130: =(1+E130)*(1-Bollo_eff) -> 1.0484988 | H130: =H129/G129 -> 0.034596725 | I130: =1-Aliq_eff*MAX(0,1-H130) -> 0.74899515 | J130: =Spesa0 -> 38000 | K130: =J130/I130 -> 50734.641 | L130: =IF(K130>N130+0.000000001,1,0) -> 1 | M130: =MIN(K130,N130)*I130 -> 0 | N130: =(N129-MIN(K129,N129))*G129/(1+F129) -> 0 | O130: =Tasso0*S130*I130 -> 14167.501 | P130: =O130/I130 -> 18915.344 | Q130: =IF(P130>S130+0.000000001,1,0) -> 0 | R130: =MIN(P130,S130)*I130 -> 14167.501 | S130: =(S129-MIN(P129,S129))*G129/(1+F129) -> 466284.76 | T130: =MAX(Tasso0*X130*I130,Pav_pct*Spesa0) -> 34200 | U130: =T130/I130 -> 45661.177 | V130: =IF(U130>X130+0.000000001,1,0) -> 1 | W130: =MIN(U130,X130)*I130 -> 0 | X130: =(X129-MIN(U129,X129))*G129/(1+F129) -> 0 | Y130: =IF(Eta_rif_VPW-B130<=1,1,IF(r_VPW=0,1/(Eta_rif_VPW-B130),r_VPW/(1-(1+r_VPW)^(-(Eta_rif_VPW-B130)))/(1+r_VPW))) -> 1 | Z130: =Y130*AD130*I130 -> 0 | AA130: =Z130/I130 -> 0 | AB130: =IF(AA130>AD130+0.000000001,1,0) -> 0 | AC130: =MIN(AA130,AD130)*I130 -> 0 | AD130: =(AD129-MIN(AA129,AD129))*G129/(1+F129) -> 0 | AE130: =IF(OR(E129>=0,GK_variante=3),AG129,IF(GK_variante=2,AG129/(1+F129),IF(AK130*I130<=0,AG129/(1+F129),IF(AG129/(AK130*I130)>Tasso0,AG129/(1+F129),AG129)))) -> 22438.62 | AF130: =IF(AK130*I130<=0,9.9,AE130/(AK130*I130)) -> 47.751186 | AG130: =IF(AND(AF130>Tasso0*(1+GK_banda),A130<=Anni-GK_ultimi),AE130*(1-GK_taglio),IF(AF130<Tasso0*(1-GK_banda),AE130*(1+GK_taglio),AE130)) -> 22438.62 | AH130: =AG130/I130 -> 29958.298 | AI130: =IF(AH130>AK130+0.000000001,1,0) -> 1 | AJ130: =MIN(AH130,AK130)*I130 -> 469.90708 | AK130: =(AK129-MIN(AH129,AK129))*G129/(1+F129) -> 627.38334 | AL130: =MIN(MAX(Tasso0*AP130*I130,AL129*(1+VG_pav)),AL129*(1+VG_tetto)) -> 14167.501 | AM130: =AL130/I130 -> 18915.344 | AN130: =IF(AM130>AP130+0.000000001,1,0) -> 0 | AO130: =MIN(AM130,AP130)*I130 -> 14167.501 | AP130: =(AP129-MIN(AM129,AP129))*G129/(1+F129) -> 466284.76 | AQ130: =IF(AND(A130<=Anni,M129>0),M130/M129-1,"") | AR130: =IF(AND(A130<=Anni,R129>0),R130/R129-1,"") | AS130: =IF(AND(A130<=Anni,W129>0),W130/W129-1,"") | AT130: =IF(AND(A130<=Anni,AC129>0),AC130/AC129-1,"") | AU130: =IF(AND(A130<=Anni,AJ129>0),AJ130/AJ129-1,"") | AV130: =IF(AND(A130<=Anni,AO129>0),AO130/AO129-1,"")

Sheet 4 - Fisco e pensione
A1: 4 - Fisco e pensione: quanto capitale serve davvero (euro di oggi)
A2: Strumento informativo / divulgativo. NON è consulenza finanziaria. I valori sono indicativi al 2026 e vanno verificati col tuo consulente.
A3: L'ordine dei prelievi fra le sacche del portafoglio NON è in questo file: i numeri del video sull'ordine vengono da uno script. Qui il calcolo è in forma chiusa: ogni anno si vende quanto serve per avere in cassa la spesa netta, pagando il 26% sulla sola plusvalenza latente.
A5: Capitale necessario oggi per spendere la spesa netta fino a fine piano (valore attuale al rendimento reale costante)
A6: Senza pensione | B6: =SUM($I$65:$I$124) -> 1161991.5 | C6: Piano per Anni anni; l'ultimo anno conta solo i mesi indicati.
A7: Con pensione (parametro «Pensione») | B7: =SUM($J$65:$J$124) -> 716353.99
A8: Differenza dovuta alla pensione | B8: =Cap_senza_pens-Cap_con_pens -> 445637.51
A9: Differenza in % del capitale senza pensione | B9: =Cap_diff/Cap_senza_pens -> 0.38351185
A11: Scenario di pensione | B11: Pensione netta annua | C11: Capitale necessario con pensione
A12: Revisione centrale (parametro «Pensione») | B12: =Pensione -> 30711.544 | C12: =Cap_con_pens -> 716353.99
A13: Alternativa 1 (coefficienti di oggi) | B13: 31829 | C13: =SUM($O$65:$O$124) -> 700139.23
A14: Alternativa 2 (revisione accelerata) | B14: 29951 | C14: =SUM($P$65:$P$124) -> 727389.81
A15: Ipotesi di scuola: requisito fermo a 67 anni | B15: 29349 | C15: =SUM($Q$65:$Q$124) -> 736125.08
A17: Il primo anno: quanto esce davvero dal portafoglio
A18: Venduto necessario per la spesa netta | B18: =Spesa_netta/(1-Aliq*Latente0) -> 42837.778
A19: Imposta sulla plusvalenza | B19: =Venduto_anno1-Spesa_netta -> 4837.778
A20: Bollo sul patrimonio | B20: =Bollo*Patrimonio -> 2112
A21: Uscita totale dal portafoglio | B21: =Venduto_anno1+Bollo_anno1 -> 44949.778
A22: Tasso lordo equivalente (venduto / patrimonio) | B22: =Venduto_anno1/Patrimonio -> 0.040566078
A23: Tasso con il bollo (uscita / patrimonio) | B23: =Uscita_anno1/Patrimonio -> 0.042566078
A25: Confronto fra tassi di prelievo lordi (primo anno)
A26: Tasso di prelievo lordo | B26: Venduto | C26: Netto dopo imposta | D26: Netto dopo bollo | E26: % della spesa netta | F26: Capitale per la spesa netta al primo anno (non è un piano)
A27: 0.03 | B27: =A27*Patrimonio -> 31680 | C27: =B27*(1-Aliq*Latente0) -> 28102.298 | D27: =C27-Bollo*Patrimonio -> 25990.298 | E27: =D27/Spesa_netta -> 0.68395521 | F27: =Spesa_netta/(1-Aliq*Latente0)/A27 -> 1427925.9
A28: 0.0231 | B28: =A28*Patrimonio -> 24393.6 | C28: =B28*(1-Aliq*Latente0) -> 21638.769 | D28: =C28-Bollo*Patrimonio -> 19526.769 | E28: =D28/Spesa_netta -> 0.51386235 | F28: =Spesa_netta/(1-Aliq*Latente0)/A28 -> 1854449.3
A29: 0.04 | B29: =A29*Patrimonio -> 42240 | C29: =B29*(1-Aliq*Latente0) -> 37469.731 | D29: =C29-Bollo*Patrimonio -> 35357.731 | E29: =D29/Spesa_netta -> 0.93046659 | F29: =Spesa_netta/(1-Aliq*Latente0)/A29 -> 1070944.4
A31: La plusvalenza latente cresce: l'imposta sul venduto pesa sempre di più
A32: Plusvalenza latente al primo anno | B32: =1-INDEX($E$65:$E$124,1) -> 0.43435582
A33: Plusvalenza latente all'anno della pensione | B33: =IFERROR(1-INDEX($E$65:$E$124,Anno_pens),"n.d.") -> 0.73487156
A34: Plusvalenza latente all'ultimo anno del piano | B34: =1-INDEX($E$65:$E$124,Anni) -> 0.91885573
A35: Imposta sul venduto, primo anno | B35: =Aliq*(1-INDEX($E$65:$E$124,1)) -> 0.11293251
A36: Imposta sul venduto, ultimo anno del piano | B36: =Aliq*(1-INDEX($E$65:$E$124,Anni)) -> 0.23890249
A38: Il ponte: capitale richiesto all'inizio dell'anno della prima rata di pensione
A39: Serve per coprire i fabbisogni residui, già al netto della pensione, con tre ipotesi di plusvalenza latente quel giorno.
A40: Ipotesi di plusvalenza latente | B40: Plusvalenza latente | C40: Capitale richiesto
A41: Latente iniziale (Latente0) | B41: =Latente0 -> 0.43435582 | C41: =SUM($L$65:$L$124) -> 187005.72
A42: Seconda ipotesi (Lat_ponte2) | B42: =Lat_ponte2 -> 0.6 | C42: =SUM($M$65:$M$124) -> 193720.93
A43: Latente effettiva all'anno della pensione | B43: =IFERROR(1-INDEX($E$65:$E$124,Anno_pens),0) -> 0.73487156 | C43: =SUM($N$65:$N$124) -> 199593
A45: Confronto con il capitale delle regole all'anno della pensione (foglio 2)
A46: Il confronto è omogeneo solo in modalità «tassato»: il richiesto è netto di imposte, il capitale delle regole è lordo di imposte latenti.
A47: Regola | B47: Capitale a inizio anno della pensione | C47: Richiesto (latente iniziale) | D47: Differenza
A48: Fisso indicizzato | B48: =IF(Modalita="tassato",IFERROR(INDEX('2 - Sequenza storica'!J$6:J$65,Anno_pens),"n.d."),"confronto non omogeneo: il richiesto è netto di imposte, il capitale è lordo") -> 480860.49 | C48: =C41 -> 187005.72 | D48: =IF(ISNUMBER(B48),B48-C48,"") -> 293854.77
A49: Percentuale costante | B49: =IF(Modalita="tassato",IFERROR(INDEX('2 - Sequenza storica'!K$6:K$65,Anno_pens),"n.d."),"confronto non omogeneo: il richiesto è netto di imposte, il capitale è lordo") -> 792080.29 | C49: =C41 -> 187005.72 | D49: =IF(ISNUMBER(B49),B49-C49,"") -> 605074.57
A50: Percentuale con pavimento | B50: =IF(Modalita="tassato",IFERROR(INDEX('2 - Sequenza storica'!L$6:L$65,Anno_pens),"n.d."),"confronto non omogeneo: il richiesto è netto di imposte, il capitale è lordo") -> 575949.62 | C50: =C41 -> 187005.72 | D50: =IF(ISNUMBER(B50),B50-C50,"") -> 388943.9
A51: Percentuale variabile | B51: =IF(Modalita="tassato",IFERROR(INDEX('2 - Sequenza storica'!M$6:M$65,Anno_pens),"n.d."),"confronto non omogeneo: il richiesto è netto di imposte, il capitale è lordo") -> 779673.17 | C51: =C41 -> 187005.72 | D51: =IF(ISNUMBER(B51),B51-C51,"") -> 592667.45
A52: Guardrail (senza tetto all'inflazione) | B52: =IF(Modalita="tassato",IFERROR(INDEX('2 - Sequenza storica'!N$6:N$65,Anno_pens),"n.d."),"confronto non omogeneo: il richiesto è netto di imposte, il capitale è lordo") -> 747300.8 | C52: =C41 -> 187005.72 | D52: =IF(ISNUMBER(B52),B52-C52,"") -> 560295.08
A53: Tetto e pavimento (+5% / −2,5%) | B53: =IF(Modalita="tassato",IFERROR(INDEX('2 - Sequenza storica'!O$6:O$65,Anno_pens),"n.d."),"confronto non omogeneo: il richiesto è netto di imposte, il capitale è lordo") -> 651979.85 | C53: =C41 -> 187005.72 | D53: =IF(ISNUMBER(B53),B53-C53,"") -> 464974.13
A62: Motore del calcolo, non modificare (forma chiusa, nessuna bisezione)
A64: t | B64: Anno della sequenza | C64: Fabbisogno netto senza pensione | D64: Fabbisogno netto con pensione | E64: k = base di costo / valore | F64: Venduto senza pensione | G64: Venduto con pensione | H64: Fattore di sconto | I64: Valore attuale senza pensione | J64: Valore attuale con pensione | K64: s = anni dalla prima rata | L64: Ponte con latente iniziale | M64: Ponte con seconda ipotesi | N64: Ponte con latente effettiva | O64: Valore attuale alternativa 1 | P64: Valore attuale alternativa 2 | Q64: Valore attuale alternativa 3
A65: 1 | B65: =Anno_inizio+A65-1 -> 2000 | C65: =IF(A65>Anni,0,Spesa_netta*IF(A65=Anni,Mesi_ultimo/12,1)) -> 38000 | D65: =IF(A65>Anni,0,MAX(0,IF(A65<Anno_pens,Spesa_netta,IF(A65=Anno_pens,Spesa_netta-Pensione*(12-Mese_pens+1)/12,Spesa_netta-Pensione))*IF(A65=Anni,Mesi_ultimo/12,1))) -> 38000 | E65: =(1-Latente0)/((1+Rend_c)*(1+Infl_c)*(1-Bollo))^(A65-1) -> 0.56564418 | F65: =C65/(1-Aliq*(1-E65)) -> 42837.778 | G65: =D65/(1-Aliq*(1-E65)) -> 42837.778 | H65: =((1+Rend_c)*(1-Bollo))^(A65-1) -> 1 | I65: =F65/H65 -> 42837.778 | J65: =G65/H65 -> 42837.778 | K65: =IF(AND(A65>=Anno_pens,A65<=Anni),A65-Anno_pens,"") | L65: =IF(K65="","",D65/(1-Aliq*(1-(1-$B$41)/((1+Rend_c)*(1+Infl_c)*(1-Bollo))^K65))/((1+Rend_c)*(1-Bollo))^K65) | M65: =IF(K65="","",D65/(1-Aliq*(1-(1-$B$42)/((1+Rend_c)*(1+Infl_c)*(1-Bollo))^K65))/((1+Rend_c)*(1-Bollo))^K65) | N65: =IF(K65="","",D65/(1-Aliq*(1-(1-$B$43)/((1+Rend_c)*(1+Infl_c)*(1-Bollo))^K65))/((1+Rend_c)*(1-Bollo))^K65) | O65: =(IF(A65>Anni,0,MAX(0,IF(A65<Anno_pens,Spesa_netta,IF(A65=Anno_pens,Spesa_netta-$B$13*(12-Mese_pens+1)/12,Spesa_netta-$B$13))*IF(A65=Anni,Mesi_ultimo/12,1))))/(1-Aliq*(1-E65))/H65 -> 42837.778 | P65: =(IF(A65>Anni,0,MAX(0,IF(A65<Anno_pens,Spesa_netta,IF(A65=Anno_pens,Spesa_netta-$B$14*(12-Mese_pens+1)/12,Spesa_netta-$B$14))*IF(A65=Anni,Mesi_ultimo/12,1))))/(1-Aliq*(1-E65))/H65 -> 42837.778 | Q65: =(IF(A65>Anni,0,MAX(0,IF(A65<Anno_pens,Spesa_netta,IF(A65=Anno_pens,Spesa_netta-$B$15*(12-Mese_pens+1)/12,Spesa_netta-$B$15))*IF(A65=Anni,Mesi_ultimo/12,1))))/(1-Aliq*(1-E65))/H65 -> 42837.778
A66: =A65+1 -> 2 | B66: =Anno_inizio+A66-1 -> 2001 | C66: =IF(A66>Anni,0,Spesa_netta*IF(A66=Anni,Mesi_ultimo/12,1)) -> 38000 | D66: =IF(A66>Anni,0,MAX(0,IF(A66<Anno_pens,Spesa_netta,IF(A66=Anno_pens,Spesa_netta-Pensione*(12-Mese_pens+1)/12,Spesa_netta-Pensione))*IF(A66=Anni,Mesi_ultimo/12,1))) -> 38000 | E66: =(1-Latente0)/((1+Rend_c)*(1+Infl_c)*(1-Bollo))^(A66-1) -> 0.53948004 | F66: =C66/(1-Aliq*(1-E66)) -> 43168.828 | G66: =D66/(1-Aliq*(1-E66)) -> 43168.828 | H66: =((1+Rend_c)*(1-Bollo))^(A66-1) -> 1.02794 | I66: =F66/H66 -> 41995.474 | J66: =G66/H66 -> 41995.474 | K66: =IF(AND(A66>=Anno_pens,A66<=Anni),A66-Anno_pens,"") | L66: =IF(K66="","",D66/(1-Aliq*(1-(1-$B$41)/((1+Rend_c)*(1+Infl_c)*(1-Bollo))^K66))/((1+Rend_c)*(1-Bollo))^K66) | M66: =IF(K66="","",D66/(1-Aliq*(1-(1-$B$42)/((1+Rend_c)*(1+Infl_c)*(1-Bollo))^K66))/((1+Rend_c)*(1-Bollo))^K66) | N66: =IF(K66="","",D66/(1-Aliq*(1-(1-$B$43)/((1+Rend_c)*(1+Infl_c)*(1-Bollo))^K66))/((1+Rend_c)*(1-Bollo))^K66) | O66: =(IF(A66>Anni,0,MAX(0,IF(A66<Anno_pens,Spesa_netta,IF(A66=Anno_pens,Spesa_netta-$B$13*(12-Mese_pens+1)/12,Spesa_netta-$B$13))*IF(A66=Anni,Mesi_ultimo/12,1))))/(1-Aliq*(1-E66))/H66 -> 41995.474 | P66: =(IF(A66>Anni,0,MAX(0,IF(A66<Anno_pens,Spesa_netta,IF(A66=Anno_pens,Spesa_netta-$B$14*(12-Mese_pens+1)/12,Spesa_netta-$B$14))*IF(A66=Anni,Mesi_ultimo/12,1))))/(1-Aliq*(1-E66))/H66 -> 41995.474 | Q66: =(IF(A66>Anni,0,MAX(0,IF(A66<Anno_pens,Spesa_netta,IF(A66=Anno_pens,Spesa_netta-$B$15*(12-Mese_pens+1)/12,Spesa_netta-$B$15))*IF(A66=Anni,Mesi_ultimo/12,1))))/(1-Aliq*(1-E66))/H66 -> 41995.474
A67: =A66+1 -> 3 | B67: =Anno_inizio+A67-1 -> 2002 | C67: =IF(A67>Anni,0,Spesa_netta*IF(A67=Anni,Mesi_ultimo/12,1)) -> 38000 | D67: =IF(A67>Anni,0,MAX(0,IF(A67<Anno_pens,Spesa_netta,IF(A67=Anno_pens,Spesa_netta-Pensione*(12-Mese_pens+1)/12,Spesa_netta-Pensione))*IF(A67=Anni,Mesi_ultimo/12,1))) -> 38000 | E67: =(1-Latente0)/((1+Rend_c)*(1+Infl_c)*(1-Bollo))^(A67-1) -> 0.51452614 | F67: =C67/(1-Aliq*(1-E67)) -> 43489.367 | G67: =D67/(1-Aliq*(1-E67)) -> 43489.367 | H67: =((1+Rend_c)*(1-Bollo))^(A67-1) -> 1.0566606 | I67: =F67/H67 -> 41157.364 | J67: =G67/H67 -> 41157.364 | K67: =IF(AND(A67>=Anno_pens,A67<=Anni),A67-Anno_pens,"") | L67: =IF(K67="","",D67/(1-Aliq*(1-(1-$B$41)/((1+Rend_c)*(1+Infl_c)*(1-Bollo))^K67))/((1+Rend_c)*(1-Bollo))^K67) | M67: =IF(K67="","",D67/(1-Aliq*(1-(1-$B$42)/((1+Rend_c)*(1+Infl_c)*(1-Bollo))^K67))/((1+Rend_c)*(1-Bollo))^K67) | N67: =IF(K67="","",D67/(1-Aliq*(1-(1-$B$43)/((1+Rend_c)*(1+Infl_c)*(1-Bollo))^K67))/((1+Rend_c)*(1-Bollo))^K67) | O67: =(IF(A67>Anni,0,MAX(0,IF(A67<Anno_pens,Spesa_netta,IF(A67=Anno_pens,Spesa_netta-$B$13*(12-Mese_pens+1)/12,Spesa_netta-$B$13))*IF(A67=Anni,Mesi_ultimo/12,1))))/(1-Aliq*(1-E67))/H67 -> 41157.364 | P67: =(IF(A67>Anni,0,MAX(0,IF(A67<Anno_pens,Spesa_netta,IF(A67=Anno_pens,Spesa_netta-$B$14*(12-Mese_pens+1)/12,Spesa_netta-$B$14))*IF(A67=Anni,Mesi_ultimo/12,1))))/(1-Aliq*(1-E67))/H67 -> 41157.364 | Q67: =(IF(A67>Anni,0,MAX(0,IF(A67<Anno_pens,Spesa_netta,IF(A67=Anno_pens,Spesa_netta-$B$15*(12-Mese_pens+1)/12,Spesa_netta-$B$15))*IF(A67=Anni,Mesi_ultimo/12,1))))/(1-Aliq*(1-E67))/H67 -> 41157.364
A68: =A67+1 -> 4 | B68: =Anno_inizio+A68-1 -> 2003 | C68: =IF(A68>Anni,0,Spesa_netta*IF(A68=Anni,Mesi_ultimo/12,1)) -> 38000 | D68: =IF(A68>Anni,0,MAX(0,IF(A68<Anno_pens,Spesa_netta,IF(A68=Anno_pens,Spesa_netta-Pensione*(12-Mese_pens+1)/12,Spesa_netta-Pensione))*IF(A68=Anni,Mesi_ultimo/12,1))) -> 38000 | E68: =(1-Latente0)/((1+Rend_c)*(1+Infl_c)*(1-Bollo))^(A68-1) -> 0.4907265 | F68: =C68/(1-Aliq*(1-E68)) -> 43799.547 | G68: =D68/(1-Aliq*(1-E68)) -> 43799.547 | H68: =((1+Rend_c)*(1-Bollo))^(A68-1) -> 1.0861837 | I68: =F68/H68 -> 40324.252 | J68: =G68/H68 -> 40324.252 | K68: =IF(AND(A68>=Anno_pens,A68<=Anni),A68-Anno_pens,"") | L68: =IF(K68="","",D68/(1-Aliq*(1-(1-$B$41)/((1+Rend_c)*(1+Infl_c)*(1-Bollo))^K68))/((1+Rend_c)*(1-Bollo))^K68) | M68: =IF(K68="","",D68/(1-Aliq*(1-(1-$B$42)/((1+Rend_c)*(1+Infl_c)*(1-Bollo))^K68))/((1+Rend_c)*(1-Bollo))^K68) | N68: =IF(K68="","",D68/(1-Aliq*(1-(1-$B$43)/((1+Rend_c)*(1+Infl_c)*(1-Bollo))^K68))/((1+Rend_c)*(1-Bollo))^K68) | O68: =(IF(A68>Anni,0,MAX(0,IF(A68<Anno_pens,Spesa_netta,IF(A68=Anno_pens,Spesa_netta-$B$13*(12-Mese_pens+1)/12,Spesa_netta-$B$13))*IF(A68=Anni,Mesi_ultimo/12,1))))/(1-Aliq*(1-E68))/H68 -> 40324.252 | P68: =(IF(A68>Anni,0,MAX(0,IF(A68<Anno_pens,Spesa_netta,IF(A68=Anno_pens,Spesa_netta-$B$14*(12-Mese_pens+1)/12,Spesa_netta-$B$14))*IF(A68=Anni,Mesi_ultimo/12,1))))/(1-Aliq*(1-E68))/H68 -> 40324.252 | Q68: =(IF(A68>Anni,0,MAX(0,IF(A68<Anno_pens,Spesa_netta,IF(A68=Anno_pens,Spesa_netta-$B$15*(12-Mese_pens+1)/12,Spesa_netta-$B$15))*IF(A68=Anni,Mesi_ultimo/12,1))))/(1-Aliq*(1-E68))/H68 -> 40324.252
A69: =A68+1 -> 5 | B69: =Anno_inizio+A69-1 -> 2004 | C69: =IF(A69>Anni,0,Spesa_netta*IF(A69=Anni,Mesi_ultimo/12,1)) -> 38000 | D69: =IF(A69>Anni,0,MAX(0,IF(A69<Anno_pens,Spesa_netta,IF(A69=Anno_pens,Spesa_netta-Pensione*(12-Mese_pens+1)/12,Spesa_netta-Pensione))*IF(A69=Anni,Mesi_ultimo/12,1))) -> 38000 | E69: =(1-Latente0)/((1+Rend_c)*(1+Infl_c)*(1-Bollo))^(A69-1) -> 0.46802771 | F69: =C69/(1-Aliq*(1-E69)) -> 44099.529 | G69: =D69/(1-Aliq*(1-E69)) -> 44099.529 | H69: =((1+Rend_c)*(1-Bollo))^(A69-1) -> 1.1165317 | I69: =F69/H69 -> 39496.889 | J69: =G69/H69 -> 39496.889 | K69: =IF(AND(A69>=Anno_pens,A69<=Anni),A69-Anno_pens,"") | L69: =IF(K69="","",D69/(1-Aliq*(1-(1-$B$41)/((1+Rend_c)*(1+Infl_c)*(1-Bollo))^K69))/((1+Rend_c)*(1-Bollo))^K69) | M69: =IF(K69="","",D69/(1-Aliq*(1-(1-$B$42)/((1+Rend_c)*(1+Infl_c)*(1-Bollo))^K69))/((1+Rend_c)*(1-Bollo))^K69) | N69: =IF(K69="","",D69/(1-Aliq*(1-(1-$B$43)/((1+Rend_c)*(1+Infl_c)*(1-Bollo))^K69))/((1+Rend_c)*(1-Bollo))^K69) | O69: =(IF(A69>Anni,0,MAX(0,IF(A69<Anno_pens,Spesa_netta,IF(A69=Anno_pens,Spesa_netta-$B$13*(12-Mese_pens+1)/12,Spesa_netta-$B$13))*IF(A69=Anni,Mesi_ultimo/12,1))))/(1-Aliq*(1-E69))/H69 -> 39496.889 | P69: =(IF(A69>Anni,0,MAX(0,IF(A69<Anno_pens,Spesa_netta,IF(A69=Anno_pens,Spesa_netta-$B$14*(12-Mese_pens+1)/12,Spesa_netta-$B$14))*IF(A69=Anni,Mesi_ultimo/12,1))))/(1-Aliq*(1-E69))/H69 -> 39496.889 | Q69: =(IF(A69>Anni,0,MAX(0,IF(A69<Anno_pens,Spesa_netta,IF(A69=Anno_pens,Spesa_netta-$B$15*(12-Mese_pens+1)/12,Spesa_netta-$B$15))*IF(A69=Anni,Mesi_ultimo/12,1))))/(1-Aliq*(1-E69))/H69 -> 39496.889
A70: =A69+1 -> 6 | B70: =Anno_inizio+A70-1 -> 2005 | C70: =IF(A70>Anni,0,Spesa_netta*IF(A70=Anni,Mesi_ultimo/12,1)) -> 38000 | D70: =IF(A70>Anni,0,MAX(0,IF(A70<Anno_pens,Spesa_netta,IF(A70=Anno_pens,Spesa_netta-Pensione*(12-Mese_pens+1)/12,Spesa_netta-Pensione))*IF(A70=Anni,Mesi_ultimo/12,1))) -> 38000 | E70: =(1-Latente0)/((1+Rend_c)*(1+Infl_c)*(1-Bollo))^(A70-1) -> 0.44637887 | F70: =C70/(1-Aliq*(1-E70)) -> 44389.489 | G70: =D70/(1-Aliq*(1-E70)) -> 44389.489 | H70: =((1+Rend_c)*(1-Bollo))^(A70-1) -> 1.1477276 | I70: =F70/H70 -> 38675.979 | J70: =G70/H70 -> 38675.979 | K70: =IF(AND(A70>=Anno_pens,A70<=Anni),A70-Anno_pens,"") | L70: =IF(K70="","",D70/(1-Aliq*(1-(1-$B$41)/((1+Rend_c)*(1+Infl_c)*(1-Bollo))^K70))/((1+Rend_c)*(1-Bollo))^K70) | M70: =IF(K70="","",D70/(1-Aliq*(1-(1-$B$42)/((1+Rend_c)*(1+Infl_c)*(1-Bollo))^K70))/((1+Rend_c)*(1-Bollo))^K70) | N70: =IF(K70="","",D70/(1-Aliq*(1-(1-$B$43)/((1+Rend_c)*(1+Infl_c)*(1-Bollo))^K70))/((1+Rend_c)*(1-Bollo))^K70) | O70: =(IF(A70>Anni,0,MAX(0,IF(A70<Anno_pens,Spesa_netta,IF(A70=Anno_pens,Spesa_netta-$B$13*(12-Mese_pens+1)/12,Spesa_netta-$B$13))*IF(A70=Anni,Mesi_ultimo/12,1))))/(1-Aliq*(1-E70))/H70 -> 38675.979 | P70: =(IF(A70>Anni,0,MAX(0,IF(A70<Anno_pens,Spesa_netta,IF(A70=Anno_pens,Spesa_netta-$B$14*(12-Mese_pens+1)/12,Spesa_netta-$B$14))*IF(A70=Anni,Mesi_ultimo/12,1))))/(1-Aliq*(1-E70))/H70 -> 38675.979 | Q70: =(IF(A70>Anni,0,MAX(0,IF(A70<Anno_pens,Spesa_netta,IF(A70=Anno_pens,Spesa_netta-$B$15*(12-Mese_pens+1)/12,Spesa_netta-$B$15))*IF(A70=Anni,Mesi_ultimo/12,1))))/(1-Aliq*(1-E70))/H70 -> 38675.979
A71: =A70+1 -> 7 | B71: =Anno_inizio+A71-1 -> 2006 | C71: =IF(A71>Anni,0,Spesa_netta*IF(A71=Anni,Mesi_ultimo/12,1)) -> 38000 | D71: =IF(A71>Anni,0,MAX(0,IF(A71<Anno_pens,Spesa_netta,IF(A71=Anno_pens,Spesa_netta-Pensione*(12-Mese_pens+1)/12,Spesa_netta-Pensione))*IF(A71=Anni,Mesi_ultimo/12,1))) -> 38000 | E71: =(1-Latente0)/((1+Rend_c)*(1+Infl_c)*(1-Bollo))^(A71-1) -> 0.42573141 | F71: =C71/(1-Aliq*(1-E71)) -> 44669.612 | G71: =D71/(1-Aliq*(1-E71)) -> 44669.612 | H71: =((1+Rend_c)*(1-Bollo))^(A71-1) -> 1.1797951 | I71: =F71/H71 -> 37862.178 | J71: =G71/H71 -> 37862.178 | K71: =IF(AND(A71>=Anno_pens,A71<=Anni),A71-Anno_pens,"") | L71: =IF(K71="","",D71/(1-Aliq*(1-(1-$B$41)/((1+Rend_c)*(1+Infl_c)*(1-Bollo))^K71))/((1+Rend_c)*(1-Bollo))^K71) | M71: =IF(K71="","",D71/(1-Aliq*(1-(1-$B$42)/((1+Rend_c)*(1+Infl_c)*(1-Bollo))^K71))/((1+Rend_c)*(1-Bollo))^K71) | N71: =IF(K71="","",D71/(1-Aliq*(1-(1-$B$43)/((1+Rend_c)*(1+Infl_c)*(1-Bollo))^K71))/((1+Rend_c)*(1-Bollo))^K71) | O71: =(IF(A71>Anni,0,MAX(0,IF(A71<Anno_pens,Spesa_netta,IF(A71=Anno_pens,Spesa_netta-$B$13*(12-Mese_pens+1)/12,Spesa_netta-$B$13))*IF(A71=Anni,Mesi_ultimo/12,1))))/(1-Aliq*(1-E71))/H71 -> 37862.178 | P71: =(IF(A71>Anni,0,MAX(0,IF(A71<Anno_pens,Spesa_netta,IF(A71=Anno_pens,Spesa_netta-$B$14*(12-Mese_pens+1)/12,Spesa_netta-$B$14))*IF(A71=Anni,Mesi_ultimo/12,1))))/(1-Aliq*(1-E71))/H71 -> 37862.178 | Q71: =(IF(A71>Anni,0,MAX(0,IF(A71<Anno_pens,Spesa_netta,IF(A71=Anno_pens,Spesa_netta-$B$15*(12-Mese_pens+1)/12,Spesa_netta-$B$15))*IF(A71=Anni,Mesi_ultimo/12,1))))/(1-Aliq*(1-E71))/H71 -> 37862.178
A72: =A71+1 -> 8 | B72: =Anno_inizio+A72-1 -> 2007 | C72: =IF(A72>Anni,0,Spesa_netta*IF(A72=Anni,Mesi_ultimo/12,1)) -> 38000 | D72: =IF(A72>Anni,0,MAX(0,IF(A72<Anno_pens,Spesa_netta,IF(A72=Anno_pens,Spesa_netta-Pensione*(12-Mese_pens+1)/12,Spesa_netta-Pensione))*IF(A72=Anni,Mesi_ultimo/12,1))) -> 38000 | E72: =(1-Latente0)/((1+Rend_c)*(1+Infl_c)*(1-Bollo))^(A72-1) -> 0.40603901 | F72: =C72/(1-Aliq*(1-E72)) -> 44940.092 | G72: =D72/(1-Aliq*(1-E72)) -> 44940.092 | H72: =((1+Rend_c)*(1-Bollo))^(A72-1) -> 1.2127586 | I72: =F72/H72 -> 37056.09 | J72: =G72/H72 -> 37056.09 | K72: =IF(AND(A72>=Anno_pens,A72<=Anni),A72-Anno_pens,"") | L72: =IF(K72="","",D72/(1-Aliq*(1-(1-$B$41)/((1+Rend_c)*(1+Infl_c)*(1-Bollo))^K72))/((1+Rend_c)*(1-Bollo))^K72) | M72: =IF(K72="","",D72/(1-Aliq*(1-(1-$B$42)/((1+Rend_c)*(1+Infl_c)*(1-Bollo))^K72))/((1+Rend_c)*(1-Bollo))^K72) | N72: =IF(K72="","",D72/(1-Aliq*(1-(1-$B$43)/((1+Rend_c)*(1+Infl_c)*(1-Bollo))^K72))/((1+Rend_c)*(1-Bollo))^K72) | O72: =(IF(A72>Anni,0,MAX(0,IF(A72<Anno_pens,Spesa_netta,IF(A72=Anno_pens,Spesa_netta-$B$13*(12-Mese_pens+1)/12,Spesa_netta-$B$13))*IF(A72=Anni,Mesi_ultimo/12,1))))/(1-Aliq*(1-E72))/H72 -> 37056.09 | P72: =(IF(A72>Anni,0,MAX(0,IF(A72<Anno_pens,Spesa_netta,IF(A72=Anno_pens,Spesa_netta-$B$14*(12-Mese_pens+1)/12,Spesa_netta-$B$14))*IF(A72=Anni,Mesi_ultimo/12,1))))/(1-Aliq*(1-E72))/H72 -> 37056.09 | Q72: =(IF(A72>Anni,0,MAX(0,IF(A72<Anno_pens,Spesa_netta,IF(A72=Anno_pens,Spesa_netta-$B$15*(12-Mese_pens+1)/12,Spesa_netta-$B$15))*IF(A72=Anni,Mesi_ultimo/12,1))))/(1-Aliq*(1-E72))/H72 -> 37056.09
A73: =A72+1 -> 9 | B73: =Anno_inizio+A73-1 -> 2008 | C73: =IF(A73>Anni,0,Spesa_netta*IF(A73=Anni,Mesi_ultimo/12,1)) -> 38000 | D73: =IF(A73>Anni,0,MAX(0,IF(A73<Anno_pens,Spesa_netta,IF(A73=Anno_pens,Spesa_netta-Pensione*(12-Mese_pens+1)/12,Spesa_netta-Pensione))*IF(A73=Anni,Mesi_ultimo/12,1))) -> 38000 | E73: =(1-Latente0)/((1+Rend_c)*(1+Infl_c)*(1-Bollo))^(A73-1) -> 0.38725748 | F73: =C73/(1-Aliq*(1-E73)) -> 45201.13 | G73: =D73/(1-Aliq*(1-E73)) -> 45201.13 | H73: =((1+Rend_c)*(1-Bollo))^(A73-1) -> 1.2466431 | I73: =F73/H73 -> 36258.277 | J73: =G73/H73 -> 36258.277 | K73: =IF(AND(A73>=Anno_pens,A73<=Anni),A73-Anno_pens,"") | L73: =IF(K73="","",D73/(1-Aliq*(1-(1-$B$41)/((1+Rend_c)*(1+Infl_c)*(1-Bollo))^K73))/((1+Rend_c)*(1-Bollo))^K73) | M73: =IF(K73="","",D73/(1-Aliq*(1-(1-$B$42)/((1+Rend_c)*(1+Infl_c)*(1-Bollo))^K73))/((1+Rend_c)*(1-Bollo))^K73) | N73: =IF(K73="","",D73/(1-Aliq*(1-(1-$B$43)/((1+Rend_c)*(1+Infl_c)*(1-Bollo))^K73))/((1+Rend_c)*(1-Bollo))^K73) | O73: =(IF(A73>Anni,0,MAX(0,IF(A73<Anno_pens,Spesa_netta,IF(A73=Anno_pens,Spesa_netta-$B$13*(12-Mese_pens+1)/12,Spesa_netta-$B$13))*IF(A73=Anni,Mesi_ultimo/12,1))))/(1-Aliq*(1-E73))/H73 -> 36258.277 | P73: =(IF(A73>Anni,0,MAX(0,IF(A73<Anno_pens,Spesa_netta,IF(A73=Anno_pens,Spesa_netta-$B$14*(12-Mese_pens+1)/12,Spesa_netta-$B$14))*IF(A73=Anni,Mesi_ultimo/12,1))))/(1-Aliq*(1-E73))/H73 -> 36258.277 | Q73: =(IF(A73>Anni,0,MAX(0,IF(A73<Anno_pens,Spesa_netta,IF(A73=Anno_pens,Spesa_netta-$B$15*(12-Mese_pens+1)/12,Spesa_netta-$B$15))*IF(A73=Anni,Mesi_ultimo/12,1))))/(1-Aliq*(1-E73))/H73 -> 36258.277
A74: =A73+1 -> 10 | B74: =Anno_inizio+A74-1 -> 2009 | C74: =IF(A74>Anni,0,Spesa_netta*IF(A74=Anni,Mesi_ultimo/12,1)) -> 38000 | D74: =IF(A74>Anni,0,MAX(0,IF(A74<Anno_pens,Spesa_netta,IF(A74=Anno_pens,Spesa_netta-Pensione*(12-Mese_pens+1)/12,Spesa_netta-Pensione))*IF(A74=Anni,Mesi_ultimo/12,1))) -> 38000 | E74: =(1-Latente0)/((1+Rend_c)*(1+Infl_c)*(1-Bollo))^(A74-1) -> 0.36934471 | F74: =C74/(1-Aliq*(1-E74)) -> 45452.935 | G74: =D74/(1-Aliq*(1-E74)) -> 45452.935 | H74: =((1+Rend_c)*(1-Bollo))^(A74-1) -> 1.2814743 | I74: =F74/H74 -> 35469.253 | J74: =G74/H74 -> 35469.253 | K74: =IF(AND(A74>=Anno_pens,A74<=Anni),A74-Anno_pens,"") | L74: =IF(K74="","",D74/(1-Aliq*(1-(1-$B$41)/((1+Rend_c)*(1+Infl_c)*(1-Bollo))^K74))/((1+Rend_c)*(1-Bollo))^K74) | M74: =IF(K74="","",D74/(1-Aliq*(1-(1-$B$42)/((1+Rend_c)*(1+Infl_c)*(1-Bollo))^K74))/((1+Rend_c)*(1-Bollo))^K74) | N74: =IF(K74="","",D74/(1-Aliq*(1-(1-$B$43)/((1+Rend_c)*(1+Infl_c)*(1-Bollo))^K74))/((1+Rend_c)*(1-Bollo))^K74) | O74: =(IF(A74>Anni,0,MAX(0,IF(A74<Anno_pens,Spesa_netta,IF(A74=Anno_pens,Spesa_netta-$B$13*(12-Mese_pens+1)/12,Spesa_netta-$B$13))*IF(A74=Anni,Mesi_ultimo/12,1))))/(1-Aliq*(1-E74))/H74 -> 35469.253 | P74: =(IF(A74>Anni,0,MAX(0,IF(A74<Anno_pens,Spesa_netta,IF(A74=Anno_pens,Spesa_netta-$B$14*(12-Mese_pens+1)/12,Spesa_netta-$B$14))*IF(A74=Anni,Mesi_ultimo/12,1))))/(1-Aliq*(1-E74))/H74 -> 35469.253 | Q74: =(IF(A74>Anni,0,MAX(0,IF(A74<Anno_pens,Spesa_netta,IF(A74=Anno_pens,Spesa_netta-$B$15*(12-Mese_pens+1)/12,Spesa_netta-$B$15))*IF(A74=Anni,Mesi_ultimo/12,1))))/(1-Aliq*(1-E74))/H74 -> 35469.253
A75: =A74+1 -> 11 | B75: =Anno_inizio+A75-1 -> 2010 | C75: =IF(A75>Anni,0,Spesa_netta*IF(A75=Anni,Mesi_ultimo/12,1)) -> 38000 | D75: =IF(A75>Anni,0,MAX(0,IF(A75<Anno_pens,Spesa_netta,IF(A75=Anno_pens,Spesa_netta-Pensione*(12-Mese_pens+1)/12,Spesa_netta-Pensione))*IF(A75=Anni,Mesi_ultimo/12,1))) -> 38000 | E75: =(1-Latente0)/((1+Rend_c)*(1+Infl_c)*(1-Bollo))^(A75-1) -> 0.3522605 | F75: =C75/(1-Aliq*(1-E75)) -> 45695.72 | G75: =D75/(1-Aliq*(1-E75)) -> 45695.72 | H75: =((1+Rend_c)*(1-Bollo))^(A75-1) -> 1.3172787 | I75: =F75/H75 -> 34689.486 | J75: =G75/H75 -> 34689.486 | K75: =IF(AND(A75>=Anno_pens,A75<=Anni),A75-Anno_pens,"") | L75: =IF(K75="","",D75/(1-Aliq*(1-(1-$B$41)/((1+Rend_c)*(1+Infl_c)*(1-Bollo))^K75))/((1+Rend_c)*(1-Bollo))^K75) | M75: =IF(K75="","",D75/(1-Aliq*(1-(1-$B$42)/((1+Rend_c)*(1+Infl_c)*(1-Bollo))^K75))/((1+Rend_c)*(1-Bollo))^K75) | N75: =IF(K75="","",D75/(1-Aliq*(1-(1-$B$43)/((1+Rend_c)*(1+Infl_c)*(1-Bollo))^K75))/((1+Rend_c)*(1-Bollo))^K75) | O75: =(IF(A75>Anni,0,MAX(0,IF(A75<Anno_pens,Spesa_netta,IF(A75=Anno_pens,Spesa_netta-$B$13*(12-Mese_pens+1)/12,Spesa_netta-$B$13))*IF(A75=Anni,Mesi_ultimo/12,1))))/(1-Aliq*(1-E75))/H75 -> 34689.486 | P75: =(IF(A75>Anni,0,MAX(0,IF(A75<Anno_pens,Spesa_netta,IF(A75=Anno_pens,Spesa_netta-$B$14*(12-Mese_pens+1)/12,Spesa_netta-$B$14))*IF(A75=Anni,Mesi_ultimo/12,1))))/(1-Aliq*(1-E75))/H75 -> 34689.486 | Q75: =(IF(A75>Anni,0,MAX(0,IF(A75<Anno_pens,Spesa_netta,IF(A75=Anno_pens,Spesa_netta-$B$15*(12-Mese_pens+1)/12,Spesa_netta-$B$15))*IF(A75=Anni,Mesi_ultimo/12,1))))/(1-Aliq*(1-E75))/H75 -> 34689.486
A76: =A75+1 -> 12 | B76: =Anno_inizio+A76-1 -> 2011 | C76: =IF(A76>Anni,0,Spesa_netta*IF(A76=Anni,Mesi_ultimo/12,1)) -> 38000 | D76: =IF(A76>Anni,0,MAX(0,IF(A76<Anno_pens,Spesa_netta,IF(A76=Anno_pens,Spesa_netta-Pensione*(12-Mese_pens+1)/12,Spesa_netta-Pensione))*IF(A76=Anni,Mesi_ultimo/12,1))) -> 38000 | E76: =(1-Latente0)/((1+Rend_c)*(1+Infl_c)*(1-Bollo))^(A76-1) -> 0.33596652 | F76: =C76/(1-Aliq*(1-E76)) -> 45929.704 | G76: =D76/(1-Aliq*(1-E76)) -> 45929.704 | H76: =((1+Rend_c)*(1-Bollo))^(A76-1) -> 1.3540834 | I76: =F76/H76 -> 33919.405 | J76: =G76/H76 -> 33919.405 | K76: =IF(AND(A76>=Anno_pens,A76<=Anni),A76-Anno_pens,"") | L76: =IF(K76="","",D76/(1-Aliq*(1-(1-$B$41)/((1+Rend_c)*(1+Infl_c)*(1-Bollo))^K76))/((1+Rend_c)*(1-Bollo))^K76) | M76: =IF(K76="","",D76/(1-Aliq*(1-(1-$B$42)/((1+Rend_c)*(1+Infl_c)*(1-Bollo))^K76))/((1+Rend_c)*(1-Bollo))^K76) | N76: =IF(K76="","",D76/(1-Aliq*(1-(1-$B$43)/((1+Rend_c)*(1+Infl_c)*(1-Bollo))^K76))/((1+Rend_c)*(1-Bollo))^K76) | O76: =(IF(A76>Anni,0,MAX(0,IF(A76<Anno_pens,Spesa_netta,IF(A76=Anno_pens,Spesa_netta-$B$13*(12-Mese_pens+1)/12,Spesa_netta-$B$13))*IF(A76=Anni,Mesi_ultimo/12,1))))/(1-Aliq*(1-E76))/H76 -> 33919.405 | P76: =(IF(A76>Anni,0,MAX(0,IF(A76<Anno_pens,Spesa_netta,IF(A76=Anno_pens,Spesa_netta-$B$14*(12-Mese_pens+1)/12,Spesa_netta-$B$14))*IF(A76=Anni,Mesi_ultimo/12,1))))/(1-Aliq*(1-E76))/H76 -> 33919.405 | Q76: =(IF(A76>Anni,0,MAX(0,IF(A76<Anno_pens,Spesa_netta,IF(A76=Anno_pens,Spesa_netta-$B$15*(12-Mese_pens+1)/12,Spesa_netta-$B$15))*IF(A76=Anni,Mesi_ultimo/12,1))))/(1-Aliq*(1-E76))/H76 -> 33919.405
A77: =A76+1 -> 13 | B77: =Anno_inizio+A77-1 -> 2012 | C77: =IF(A77>Anni,0,Spesa_netta*IF(A77=Anni,Mesi_ultimo/12,1)) -> 38000 | D77: =IF(A77>Anni,0,MAX(0,IF(A77<Anno_pens,Spesa_netta,IF(A77=Anno_pens,Spesa_netta-Pensione*(12-Mese_pens+1)/12,Spesa_netta-Pensione))*IF(A77=Anni,Mesi_ultimo/12,1))) -> 38000 | E77: =(1-Latente0)/((1+Rend_c)*(1+Infl_c)*(1-Bollo))^(A77-1) -> 0.32042624 | F77: =C77/(1-Aliq*(1-E77)) -> 46155.108 | G77: =D77/(1-Aliq*(1-E77)) -> 46155.108 | H77: =((1+Rend_c)*(1-Bollo))^(A77-1) -> 1.3919165 | I77: =F77/H77 -> 33159.394 | J77: =G77/H77 -> 33159.394 | K77: =IF(AND(A77>=Anno_pens,A77<=Anni),A77-Anno_pens,"") | L77: =IF(K77="","",D77/(1-Aliq*(1-(1-$B$41)/((1+Rend_c)*(1+Infl_c)*(1-Bollo))^K77))/((1+Rend_c)*(1-Bollo))^K77) | M77: =IF(K77="","",D77/(1-Aliq*(1-(1-$B$42)/((1+Rend_c)*(1+Infl_c)*(1-Bollo))^K77))/((1+Rend_c)*(1-Bollo))^K77) | N77: =IF(K77="","",D77/(1-Aliq*(1-(1-$B$43)/((1+Rend_c)*(1+Infl_c)*(1-Bollo))^K77))/((1+Rend_c)*(1-Bollo))^K77) | O77: =(IF(A77>Anni,0,MAX(0,IF(A77<Anno_pens,Spesa_netta,IF(A77=Anno_pens,Spesa_netta-$B$13*(12-Mese_pens+1)/12,Spesa_netta-$B$13))*IF(A77=Anni,Mesi_ultimo/12,1))))/(1-Aliq*(1-E77))/H77 -> 33159.394 | P77: =(IF(A77>Anni,0,MAX(0,IF(A77<Anno_pens,Spesa_netta,IF(A77=Anno_pens,Spesa_netta-$B$14*(12-Mese_pens+1)/12,Spesa_netta-$B$14))*IF(A77=Anni,Mesi_ultimo/12,1))))/(1-Aliq*(1-E77))/H77 -> 33159.394 | Q77: =(IF(A77>Anni,0,MAX(0,IF(A77<Anno_pens,Spesa_netta,IF(A77=Anno_pens,Spesa_netta-$B$15*(12-Mese_pens+1)/12,Spesa_netta-$B$15))*IF(A77=Anni,Mesi_ultimo/12,1))))/(1-Aliq*(1-E77))/H77 -> 33159.394
... A124: =A123+1 -> 60 | B124: =Anno_inizio+A124-1 -> 2059 | C124: =IF(A124>Anni,0,Spesa_netta*IF(A124=Anni,Mesi_ultimo/12,1)) -> 0 | D124: =IF(A124>Anni,0,MAX(0,IF(A124<Anno_pens,Spesa_netta,IF(A124=Anno_pens,Spesa_netta-Pensione*(12-Mese_pens+1)/12,Spesa_netta-Pensione))*IF(A124=Anni,Mesi_ultimo/12,1))) -> 0 | E124: =(1-Latente0)/((1+Rend_c)*(1+Infl_c)*(1-Bollo))^(A124-1) -> 0.034596725 | F124: =C124/(1-Aliq*(1-E124)) -> 0 | G124: =D124/(1-Aliq*(1-E124)) -> 0 | H124: =((1+Rend_c)*(1-Bollo))^(A124-1) -> 5.0827435 | I124: =F124/H124 -> 0 | J124: =G124/H124 -> 0 | K124: =IF(AND(A124>=Anno_pens,A124<=Anni),A124-Anno_pens,"") | L124: =IF(K124="","",D124/(1-Aliq*(1-(1-$B$41)/((1+Rend_c)*(1+Infl_c)*(1-Bollo))^K124))/((1+Rend_c)*(1-Bollo))^K124) | M124: =IF(K124="","",D124/(1-Aliq*(1-(1-$B$42)/((1+Rend_c)*(1+Infl_c)*(1-Bollo))^K124))/((1+Rend_c)*(1-Bollo))^K124) | N124: =IF(K124="","",D124/(1-Aliq*(1-(1-$B$43)/((1+Rend_c)*(1+Infl_c)*(1-Bollo))^K124))/((1+Rend_c)*(1-Bollo))^K124) | O124: =(IF(A124>Anni,0,MAX(0,IF(A124<Anno_pens,Spesa_netta,IF(A124=Anno_pens,Spesa_netta-$B$13*(12-Mese_pens+1)/12,Spesa_netta-$B$13))*IF(A124=Anni,Mesi_ultimo/12,1))))/(1-Aliq*(1-E124))/H124 -> 0 | P124: =(IF(A124>Anni,0,MAX(0,IF(A124<Anno_pens,Spesa_netta,IF(A124=Anno_pens,Spesa_netta-$B$14*(12-Mese_pens+1)/12,Spesa_netta-$B$14))*IF(A124=Anni,Mesi_ultimo/12,1))))/(1-Aliq*(1-E124))/H124 -> 0 | Q124: =(IF(A124>Anni,0,MAX(0,IF(A124<Anno_pens,Spesa_netta,IF(A124=Anno_pens,Spesa_netta-$B$15*(12-Mese_pens+1)/12,Spesa_netta-$B$15))*IF(A124=Anni,Mesi_ultimo/12,1))))/(1-Aliq*(1-E124))/H124 -> 0

Sheet 5 - Dati
A1: 5 - Dati: serie annuali e tabella di controllo della percentuale variabile
A2: Strumento informativo / divulgativo. NON è consulenza finanziaria. I valori sono indicativi al 2026 e vanno verificati col tuo consulente.
A3: Serie annuali in euro: la partenza è gennaio, i rendimenti vanno da febbraio a gennaio. EUR = 60% indice azionario mondiale in euro (rendimento netto) + 40% titolo di Stato tedesco a dieci anni (serie sintetica), inflazione armonizzata italiana (HICP), gennaio 2000-gennaio 2026. USA = 60% azioni e 40% titoli di Stato americani dal 1871, inflazione americana (serie storica di Shiller). Colonne C, D, E: dati di fonte. Colonna F: formula (60% azioni + 40% obbligazioni, ribilanciato ogni anno).
A4: Serie annuali (euro nominali, inflazione dell'anno) | H4: Tabella della percentuale variabile di una comunità di investitori americani (controllo)
A5: Serie | B5: Anno di partenza (gennaio) | C5: Rendimento azioni nominale | D5: Rendimento obbligazioni nominale | E5: Inflazione dell'anno | F5: Rendimento 60/40 nominale | H5: Età | I5: Anni residui | J5: 30% azioni | K5: 40% azioni | L5: 50% azioni | M5: 60% azioni | N5: 70% azioni | O5: Ricostruzione 60/40 (%) | P5: Scarto (punti %)
A6: EUR | B6: 2000 | C6: -0.00941299 | D6: 0.12264386 | E6: 0.02459017 | F6: =0.6*C6+0.4*D6 -> 0.04340975 | H6: 40 | I6: 60 | J6: 3.4 | K6: 3.6 | L6: 3.8 | M6: 4.1 | N6: 4.3 | O6: =ROUND($P$70/(1-(1+$P$70)^(-I6))/(1+$P$70)*100,1) -> 4.1 | P6: =O6-M6 -> 0
A7: EUR | B7: 2001 | C7: -0.14529059 | D7: 0.03527092 | E7: 0.02266669 | F7: =0.6*C7+0.4*D7 -> -0.073065986 | H7: 41 | I7: 59 | J7: 3.4 | K7: 3.6 | L7: 3.9 | M7: 4.1 | N7: 4.3 | O7: =ROUND($P$70/(1-(1+$P$70)^(-I7))/(1+$P$70)*100,1) -> 4.1 | P7: =O7-M7 -> 0
A8: EUR | B8: 2002 | C8: -0.35757627 | D8: 0.12325968 | E8: 0.02868319 | F8: =0.6*C8+0.4*D8 -> -0.16524189 | H8: 42 | I8: 58 | J8: 3.4 | K8: 3.7 | L8: 3.9 | M8: 4.1 | N8: 4.3 | O8: =ROUND($P$70/(1-(1+$P$70)^(-I8))/(1+$P$70)*100,1) -> 4.1 | P8: =O8-M8 -> 0
A9: EUR | B9: 2003 | C9: 0.2054035 | D9: 0.02118855 | E9: 0.02154625 | F9: =0.6*C9+0.4*D9 -> 0.13171752 | H9: 43 | I9: 57 | J9: 3.5 | K9: 3.7 | L9: 3.9 | M9: 4.1 | N9: 4.4 | O9: =ROUND($P$70/(1-(1+$P$70)^(-I9))/(1+$P$70)*100,1) -> 4.1 | P9: =O9-M9 -> 0
A10: EUR | B10: 2004 | C10: 0.05180791 | D10: 0.11534314 | E10: 0.01985112 | F10: =0.6*C10+0.4*D10 -> 0.077222002 | H10: 44 | I10: 56 | J10: 3.5 | K10: 3.7 | L10: 3.9 | M10: 4.1 | N10: 4.4 | O10: =ROUND($P$70/(1-(1+$P$70)^(-I10))/(1+$P$70)*100,1) -> 4.1 | P10: =O10-M10 -> 0
A11: EUR | B11: 2005 | C11: 0.25608627 | D11: 0.04145435 | E11: 0.02189781 | F11: =0.6*C11+0.4*D11 -> 0.1702335 | H11: 45 | I11: 55 | J11: 3.5 | K11: 3.7 | L11: 3.9 | M11: 4.2 | N11: 4.4 | O11: =ROUND($P$70/(1-(1+$P$70)^(-I11))/(1+$P$70)*100,1) -> 4.2 | P11: =O11-M11 -> 0
A12: EUR | B12: 2006 | C12: 0.0867097 | D12: -0.00941499 | E12: 0.01904762 | F12: =0.6*C12+0.4*D12 -> 0.048259824 | H12: 46 | I12: 54 | J12: 3.5 | K12: 3.8 | L12: 4 | M12: 4.2 | N12: 4.4 | O12: =ROUND($P$70/(1-(1+$P$70)^(-I12))/(1+$P$70)*100,1) -> 4.2 | P12: =O12-M12 -> 0
A13: EUR | B13: 2007 | C13: -0.12649726 | D13: 0.04770002 | E13: 0.03154206 | F13: =0.6*C13+0.4*D13 -> -0.056818348 | H13: 47 | I13: 53 | J13: 3.6 | K13: 3.8 | L13: 4 | M13: 4.2 | N13: 4.4 | O13: =ROUND($P$70/(1-(1+$P$70)^(-I13))/(1+$P$70)*100,1) -> 4.2 | P13: =O13-M13 -> 0
A14: EUR | B14: 2008 | C14: -0.32330555 | D14: 0.07991652 | E14: 0.01359004 | F14: =0.6*C14+0.4*D14 -> -0.16201672 | H14: 48 | I14: 52 | J14: 3.6 | K14: 3.8 | L14: 4 | M14: 4.2 | N14: 4.5 | O14: =ROUND($P$70/(1-(1+$P$70)^(-I14))/(1+$P$70)*100,1) -> 4.2 | P14: =O14-M14 -> 0
A15: EUR | B15: 2009 | C15: 0.25923938 | D15: 0.0523189 | E15: 0.01340782 | F15: =0.6*C15+0.4*D15 -> 0.17647119 | H15: 49 | I15: 51 | J15: 3.6 | K15: 3.8 | L15: 4.1 | M15: 4.3 | N15: 4.5 | O15: =ROUND($P$70/(1-(1+$P$70)^(-I15))/(1+$P$70)*100,1) -> 4.3 | P15: =O15-M15 -> 0
A16: EUR | B16: 2010 | C16: 0.20863462 | D16: 0.03733263 | E16: 0.01984564 | F16: =0.6*C16+0.4*D16 -> 0.14011382 | H16: 50 | I16: 50 | J16: 3.7 | K16: 3.9 | L16: 4.1 | M16: 4.3 | N16: 4.5 | O16: =ROUND($P$70/(1-(1+$P$70)^(-I16))/(1+$P$70)*100,1) -> 4.3 | P16: =O16-M16 -> 0
A17: EUR | B17: 2011 | C17: 0.01598754 | D17: 0.15584343 | E17: 0.03351352 | F17: =0.6*C17+0.4*D17 -> 0.071929896 | H17: 51 | I17: 49 | J17: 3.7 | K17: 3.9 | L17: 4.1 | M17: 4.3 | N17: 4.6 | O17: =ROUND($P$70/(1-(1+$P$70)^(-I17))/(1+$P$70)*100,1) -> 4.3 | P17: =O17-M17 -> 0
... A65: USA | B65: 1904 | C65: 0.32101747 | D65: 0.02900839 | E65: 0.02298344 | F65: =0.6*C65+0.4*D65 -> 0.20421384 | H65: 99 | I65: 1 | J65: 100 | K65: 100 | L65: 100 | M65: 100 | N65: 100 | O65: =ROUND($P$70/(1-(1+$P$70)^(-I65))/(1+$P$70)*100,1) -> 100 | P65: =O65-M65 -> 0
A66: USA | B66: 1905 | C66: 0.21305461 | D66: 0.03731751 | E66: 0 | F66: =0.6*C66+0.4*D66 -> 0.14275977
A67: USA | B67: 1906 | C67: 0.00698886 | D67: 0.01598292 | E67: 0.04494372 | F67: =0.6*C67+0.4*D67 -> 0.010586484 | O67: Celle con scarto: | P67: =SUMPRODUCT(--(ABS(P6:P65)>0.001)) -> 0
A68: USA | B68: 1907 | C68: -0.24182931 | D68: 0.02365045 | E68: -0.02150076 | F68: =0.6*C68+0.4*D68 -> -0.13563741 | H68: Controllo: la tabella del 60% azioni si ricostruisce con un rendimento reale del 3,76% (5% azioni, 1,9% obbligazioni, annualità anticipata). Con il parametro r_VPW del foglio 1 la regola usa invece il rendimento che scegli tu (default 3%).
A69: USA | B69: 1908 | C69: 0.39423599 | D69: 0.04634416 | E69: 0.03296445 | F69: =0.6*C69+0.4*D69 -> 0.25507926
A70: USA | B70: 1909 | C70: 0.16188182 | D70: 0.02693977 | E70: 0.10638701 | F70: =0.6*C70+0.4*D70 -> 0.107905 | O70: r reale 60/40: | P70: 0.0376
A71: USA | B71: 1910 | C71: -0.03379441 | D71: 0.03455237 | E71: -0.06731328 | F71: =0.6*C71+0.4*D71 -> -0.006455698
A72: USA | B72: 1911 | C72: 0.0352089 | D72: 0.03527748 | E72: -0.01030266 | F72: =0.6*C72+0.4*D72 -> 0.035236332
A73: USA | B73: 1912 | C73: 0.07179273 | D73: 0.011906 | E73: 0.07291382 | F73: =0.6*C73+0.4*D73 -> 0.047838038
A74: USA | B74: 1913 | C74: -0.04737731 | D74: 0.06573667 | E74: 0.02040816 | F74: =0.6*C74+0.4*D74 -> -0.002131718
A75: USA | B75: 1914 | C75: -0.05469913 | D75: 0.038022 | E75: 0.01 | F75: =0.6*C75+0.4*D75 -> -0.017610678
A76: USA | B76: 1915 | C76: 0.31218967 | D76: 0.0556699 | E76: 0.02970297 | F76: =0.6*C76+0.4*D76 -> 0.20958176
A77: USA | B77: 1916 | C77: 0.0823425 | D77: 0.02610128 | E77: 0.12499999 | F77: =0.6*C77+0.4*D77 -> 0.059846012
A78: USA | B78: 1917 | C78: -0.18537996 | D78: 0.01980239 | E78: 0.19658119 | F78: =0.6*C78+0.4*D78 -> -0.10330702
A79: USA | B79: 1918 | C79: 0.18064863 | D79: 0.04834997 | E79: 0.17857142 | F79: =0.6*C79+0.4*D79 -> 0.12772917
A80: USA | B80: 1919 | C80: 0.19628151 | D80: 0.01285436 | E80: 0.16969697 | F80: =0.6*C80+0.4*D80 -> 0.12291065
A81: USA | B81: 1920 | C81: -0.13977176 | D81: 0.04791732 | E81: -0.01554405 | F81: =0.6*C81+0.4*D81 -> -0.064696128
A82: USA | B82: 1921 | C82: 0.10082544 | D82: 0.1087794 | E82: -0.11052633 | F82: =0.6*C82+0.4*D82 -> 0.10400702
... A186: USA | B186: 2025 | C186: 0.17330783 | D186: 0.07043226 | E186: 0.0238643 | F186: =0.6*C186+0.4*D186 -> 0.1321576
