Workbook

Sheet 0 - Indice
A1: Marco FIRE — Riscatto della Laurea 2026
A2: Strumento informativo / divulgativo. NON è consulenza finanziaria. I valori sono indicativi al 2026 e vanno verificati col tuo consulente.
A4: Indice
A5: 1 - COSTO | B5: Costo lordo, risparmio fiscale, costo netto e rata
A6: 2 - PENSIONE | B6: Montante, rivalutazione e pensione attesa in più
A7: 3 - CONFRONTO | B7: Riscatto vs ETF vs anticipo effettivo dell'uscita
A8: 4 - ORDINARIO | B8: Riscatto ordinario col metodo percentuale
A10: Come usare
A11: 1. Le celle GIALLE sono input — modificale coi tuoi numeri.
A12: 2. Le celle VERDI sono output — si aggiornano automaticamente.
A13: 3. Tutti i numeri di default sono al 2026 da fonti pubbliche.
A14: 4. Niente codice nascosto: l'Excel è solo formule modificabili.
A16: Fonti dati
A17: • INPS, circolare n. 14 del 9 febbraio 2026 — minimale artigiani e commercianti 2026: 18.808,00 €
A18: • D.L. 4/2019 art. 20 c. 6 (conv. L. 26/2019) — riscatto agevolato: minimale × aliquota IVS 33%
A19: • D.P.R. 917/1986 (TUIR) art. 10 c. 1 lett. e) — deducibilità integrale dal reddito complessivo
A20: • D.M. 20 novembre 2024 — coefficienti di trasformazione biennio 2025-2026 (67 anni: 5,608%)
A21: • Normativa vigente 2026 — pensione anticipata 42a10m (uomini) / 41a10m (donne); vecchiaia 67 anni con 20 di contributi
A22: • L. 199/2025 (Bilancio 2026) — riscatto agevolato confermato; decreto interministeriale atteso sui periodi ante 1996
A24: Aggiornamenti: github.com/marcofire-it/marco-fire-simulatori

Sheet 1 - COSTO
A1: Quanto costa DAVVERO riscattare la laurea (2026)
A2: Strumento informativo / divulgativo. NON è consulenza finanziaria. I valori sono indicativi al 2026 e vanno verificati col tuo consulente.
A4: INPUT — cambia solo le celle gialle
A5: Anni da riscattare (solo durata legale del corso) | B5: 5
A6: Minimale INPS artigiani/commercianti 2026 (€) | B6: 18808
A7: Aliquota IVS di computo (%) | B7: 0.33
A8: La TUA aliquota marginale IRPEF (23% / 33% / 43%) | B8: 0.33
A9: Addizionali regionali+comunali (%) — opzionale | B9: 0
A10: Numero di rate mensili (max 120, senza interessi) | B10: 120
A11: Scaglioni IRPEF 2026: 23% fino a 28.000 €, 33% da 28.000 a 50.000 €, 43% oltre 50.000 €. Usa l'aliquota dell'ULTIMO euro del tuo reddito. Le addizionali sono lasciate a 0 per prudenza: se le inserisci (tipicamente 1,5-3%) il risparmio fiscale reale sale ancora.
A13: OUTPUT — riscatto AGEVOLATO
A14: Costo per 1 anno riscattato | B14: =B6*B7
A15: Costo LORDO totale | B15: =B14*B5
A16: Risparmio fiscale (deduzione art. 10 TUIR) | B16: =B15*(B8+B9)
A17: COSTO NETTO REALE | B17: =B15-B16
A18: Rata mensile (senza interessi) | B18: =B15/B10
A19: Rata NETTA equivalente dopo deduzione | B19: =B17/B10
A20: Sconto fiscale in percentuale | B20: =B16/B15
A22: CONFRONTO — costo netto per aliquota marginale
A23: Aliquota marginale | B23: Costo netto totale
A24: 23% | B24: =$B$15*(1-(0.23+$B$9))
A25: 33% | B25: =$B$15*(1-(0.33+$B$9))
A26: 43% | B26: =$B$15*(1-(0.43+$B$9))
A28: Puoi riscattare SOLO gli anni di durata legale del corso: gli anni fuori corso non sono riscattabili. Il riscatto agevolato vale per i periodi collocati nel sistema contributivo (dal 1996), o anche prima se la pensione è liquidata interamente col contributivo.

Sheet 2 - PENSIONE
A1: Quanta pensione in più ti dà il riscatto
A2: Strumento informativo / divulgativo. NON è consulenza finanziaria. I valori sono indicativi al 2026 e vanno verificati col tuo consulente.
A4: INPUT
A5: La tua età oggi | B5: 35
A6: Età prevista di pensionamento | B6: 67
A7: Crescita media annua del PIL nominale (%) | B7: 0.02
A8: Coefficiente di trasformazione atteso (%) | B8: 0.05
A9: Il montante contributivo si rivaluta con la media quinquennale del PIL nominale, NON con i mercati. Coefficiente a 67 anni per il biennio 2025-2026: 5,608%. Peggiora nel tempo: per proiezioni lontane usa 5,0% o meno (prudenziale).
A11: OUTPUT
A12: Anni di rivalutazione del montante | B12: =B6-B5
A13: Montante accreditato oggi (= costo lordo) | B13: ='1 - COSTO'!B15
A14: Montante rivalutato al pensionamento | B14: =B13*(1+B7)^B12
A15: Pensione LORDA annua in più | B15: =B14*B8
A16: Pensione lorda mensile in più (13 mensilità) | B16: =B15/13
A17: Anni di pensione per recuperare il costo netto | B17: =IFERROR('1 - COSTO'!B17/B15,NA())
A19: SENSITIVITÀ — pensione mensile lorda in più
A20: PIL nominale | B20: Coeff. 5,608% | C20: Coeff. 5,00% | D20: Coeff. 4,50%
A21: 1,5% | B21: =$B$13*(1+0.015)^$B$12*0.05608/13 | C21: =$B$13*(1+0.015)^$B$12*0.05/13 | D21: =$B$13*(1+0.015)^$B$12*0.045/13
A22: 2,0% | B22: =$B$13*(1+0.02)^$B$12*0.05608/13 | C22: =$B$13*(1+0.02)^$B$12*0.05/13 | D22: =$B$13*(1+0.02)^$B$12*0.045/13
A23: 2,5% | B23: =$B$13*(1+0.025)^$B$12*0.05608/13 | C23: =$B$13*(1+0.025)^$B$12*0.05/13 | D23: =$B$13*(1+0.025)^$B$12*0.045/13
A24: 3,0% | B24: =$B$13*(1+0.03)^$B$12*0.05608/13 | C24: =$B$13*(1+0.03)^$B$12*0.05/13 | D24: =$B$13*(1+0.03)^$B$12*0.045/13
A26: Come PURO investimento il riscatto rende poco. Il suo valore vero è ANTICIPARE la pensione (foglio 3) o sbloccare il requisito minimo dei 20 anni per la vecchiaia.

Sheet 3 - CONFRONTO
A1: Riscatto vs ETF vs anticipo della pensione
A2: Strumento informativo / divulgativo. NON è consulenza finanziaria. I valori sono indicativi al 2026 e vanno verificati col tuo consulente.
A4: INPUT
A5: Rendimento nominale netto ipotizzato per l'ETF (%) | B5: 0.05
A6: Pensione annua lorda attesa (€) | B6: 25000
A7: Anni di anticipo ottenuti col riscatto | B7: 5
A8: Stipendio annuo lordo che rinunci anticipando (€) | B8: 32000
A9: Riduzione % dell'assegno per uscita anticipata | B9: 0.08
A10: L'anticipo è possibile solo se gli anni riscattati ti portano davvero sopra la soglia della pensione anticipata (42 anni e 10 mesi per gli uomini, 41 e 10 per le donne). Se andresti comunque a 67 anni, metti 0.
A12: STRADA A — riscatto, ma vai comunque in pensione a 67
A13: Esborso netto | B13: ='1 - COSTO'!B17
A14: Pensione lorda mensile in più, a vita | B14: ='2 - PENSIONE'!B16
A15: Anni per rientrare del costo netto | B15: =IFERROR('2 - PENSIONE'!B17,NA())
A17: STRADA B — investi la stessa cifra in ETF
A18: Capitale investito (= esborso netto) | B18: =B13
A19: Anni di investimento | B19: ='2 - PENSIONE'!B12
A20: Capitale a scadenza | B20: =B18*(1+B5)^B19
A21: Prelievo sostenibile al 4% annuo | B21: =B20*0.04
A22: Prelievo mensile equivalente | B22: =B21/12
A23: Differenza chiave: con l'ETF il capitale resta tuo (ed è ereditabile), ma non è garantito. Con il riscatto compri una rendita vitalizia rivalutata: è un'assicurazione sulla longevità.
A25: STRADA C — riscatto E anticipi davvero l'uscita
A26: Annualità di pensione incassate in più | B26: =B6*B7
A27: Stipendi lordi a cui rinunci | B27: =-B8*B7
A28: Minore assegno per tutta la vita (25 anni stimati) | B28: =-B6*B9*25
A29: Costo netto del riscatto | B29: =-B13
A30: SALDO NETTO della strada C | B30: =B26+B27+B28+B29
A32: Se il saldo della strada C è positivo, il riscatto conviene MOLTO: è l'unico caso in cui batte nettamente l'ETF. Se è negativo, stai pagando per smettere prima: è una scelta legittima, ma è un costo, non un guadagno.

Sheet 4 - ORDINARIO
A1: Riscatto ORDINARIO (metodo percentuale) — confronto
A2: Strumento informativo / divulgativo. NON è consulenza finanziaria. I valori sono indicativi al 2026 e vanno verificati col tuo consulente.
A4: INPUT
A5: Retribuzione imponibile ultimi 12 mesi (€) | B5: 35000
A6: Aliquota contributiva di computo (%) | B6: 0.33
A7: Anni da riscattare | B7: ='1 - COSTO'!B5
A9: OUTPUT
A10: Costo ORDINARIO per 1 anno | B10: =B5*B6
A11: Costo ORDINARIO totale | B11: =B10*B7
A12: Costo AGEVOLATO totale (foglio 1) | B12: ='1 - COSTO'!B15
A13: Differenza a favore dell'agevolato | B13: =B11-B12
A14: Quante volte costa di più l'ordinario | B14: =IFERROR(B11/B12,NA())
A16: Costo ordinario di 1 anno, per livello di reddito
A17: Reddito imponibile | B17: Costo 1 anno
A18: 20.000 € | B18: =20000*$B$6
A19: 25.000 € | B19: =25000*$B$6
A20: 30.000 € | B20: =30000*$B$6
A21: 35.000 € | B21: =35000*$B$6
A22: 45.000 € | B22: =45000*$B$6
A23: 60.000 € | B23: =60000*$B$6
A25: ATTENZIONE: per i periodi ANTERIORI al 1996 si applica il criterio della riserva matematica, molto più oneroso e non calcolabile con una semplice percentuale. La Legge di Bilancio 2026 ha inoltre delegato a un decreto interministeriale l'aggiornamento di quel calcolo: alla data di questo file il decreto non risulta pubblicato. Usa sempre il simulatore ufficiale INPS prima di presentare domanda.
