Workbook

Sheet 0 - Indice
A1: Marco FIRE — Il tuo tasso vero: SWR, cedole e il ponte (2026)
A2: Strumento informativo / divulgativo. NON è consulenza finanziaria. I valori sono indicativi al 2026 e vanno verificati col tuo consulente.
A4: Indice
A5: 1 - Il tuo tasso vero | B5: I quattro tassi: quello che ti racconti, quello sulla spesa, quello vero, e quello confrontabile col 4% storico
A6: 2 - Quanto costa il canale | B6: Quanto costa ogni canale di incasso, il break-even al 48,08% e il contatore dello zainetto di minusvalenze
A7: 3 - Il ponte | B7: Il motore del ponte anno per anno, i tre scenari a 67 anni e il capitale necessario lordizzato
A8: 4 - Cedole contro total return | B8: L'identita' dei due modi di contare, e quanto costa pagare l'imposta in anticipo a parita' di aliquota
A9: 5 - Sequenza | B9: Lo stesso multiset di rendimenti in due ordini: quanto costa l'ordine
A11: Come usare
A12: 1. Le celle GIALLE sono input — modificale coi tuoi numeri.
A13: 2. Le celle VERDI sono output — si aggiornano automaticamente.
A14: 3. Tutti i numeri di default sono al 2026 da fonti pubbliche.
A15: 4. Niente codice nascosto: l'Excel è solo formule modificabili.
A17: Fonti dati
A18: • MEF - Dipartimento del Tesoro, comunicato del 6 marzo 2026: BTP Valore ISIN IT0005696320, tassi DEFINITIVI 2,60% (anni 1-2), 3,20% (3-4), 3,80% (5-6), cedole trimestrali, premio fedelta' 0,8%, scadenza 10/03/2032. Rendimento vero a scadenza 3,336% lordo e 2,919% netto
A19: • D.L. 66/2014 art. 3 (conv. L. 89/2014): 26% su plusvalenze, dividendi e proventi di fondi; 12,5% su titoli di Stato ed emittenti white list; i redditi diversi da titoli di Stato rilevano nella misura del 48,08%. Da qui il break-even: 0,26 x q = 0,125 da' q = 48,077%
A20: • D.P.R. 600/1973 art. 26-quinquies c. 3: sulle quote di ETF e OICR l'imposta colpisce la sola plusvalenza, col costo medio ponderato
A21: • TUIR art. 67 e art. 68 c. 5, D.Lgs. 461/1997 art. 6 c. 5: le minusvalenze sono redditi diversi, riportabili nell'anno di realizzo e nei quattro successivi, e NON compensano cedole e dividendi, che sono redditi di capitale (art. 44 TUIR)
A22: • Imposta di bollo sui prodotti finanziari: 0,2% annuo, applicata qui al patrimonio di FINE anno (anno 1: 1.862 € su 931.139 €)
A23: • Cooley, Hubbard, Walz, «Retirement Savings: Choosing a Withdrawal Rate That Is Sustainable», AAII Journal, febbraio 1998 (Trinity Study). Testuale nel paper: «The study did not adjust for taxes or transaction costs» — per questo il termine omogeneo col 4% e' il 3,47%, non il 3,67%
... A27: Aggiornamenti: github.com/marcofire-it/marco-fire-simulatori

Sheet 1 - Il tuo tasso vero
A1: Il tuo tasso vero — i quattro numeri, in trenta secondi
A2: Strumento informativo / divulgativo. NON è consulenza finanziaria. I valori sono indicativi al 2026 e vanno verificati col tuo consulente.
A3: Tre numeri in giallo e il foglio ti dice quanto stai prelevando davvero. Il tasso che ti racconti conta solo la parte di spesa che NON e' coperta dalle cedole; il tasso vero conta tutto quello che esce dal portafoglio per farti spendere quella cifra, imposte e bollo compresi. Sono lo stesso portafoglio e la stessa spesa: cambia solo il modo di contarli.
A5: I TUOI NUMERI — cambia solo le celle gialle
A6: Patrimonio totale investito | B6: 920000 | D6: Il caso del video: 450.000 di azionario, 320.000 di BTP Valore, 80.000 di certificati, 70.000 di monetario.
A7: Spesa netta annua che ti serve | B7: 30000 | D7: Quello che ti serve davvero in tasca in un anno, non quello che incassi.
A8: Cedole, dividendi e premi NETTI incassati | B8: 15000 | D8: Il flusso che arriva in conto con la ritenuta gia' pagata.
A9: Plusvalenza latente sulle quote da vendere | B9: 0.2 | D9: Quanta parte del valore delle quote e' guadagno non ancora realizzato. Se hai comprato a 80 e oggi vale 100, e' il 20%.
A10: Aliquota media sulle cedole che incassi | B10: 0.0706522 | D10: Nel caso del video vale 7,07%: le cedole del BTP Valore pagano il 12,5%, ma i premi dei certificati sono azzerati dallo zainetto di minusvalenze finche' dura (1.040 € di imposta su 14.720 € di cedole lorde). Se incassi solo cedole di titoli di Stato scrivi 12,5%; se sono dividendi, 26%.
A11: Aliquota sulle plusvalenze | B11: 0.26 | D11: 26% sulla sola plusvalenza, calcolata col costo medio ponderato (D.P.R. 600/1973 art. 26-quinquies).
A12: Imposta di bollo sui prodotti finanziari | B12: 0.002 | D12: 0,2% annuo del valore. E' un costo, non un prelievo: per questo ha una cella sua e resta fuori dal confronto col 4% storico.
A14: I QUATTRO TASSI
A15: Tasso che ti racconti | B15: =($B$7-$B$8)/$B$6 | D15: (spesa netta meno cedole) diviso patrimonio. E' l'etichetta: conta solo il pezzo di spesa che le cedole non coprono, come se le cedole fossero denaro caduto dal cielo. Nel caso del video: 1,63%.
A16: Tasso sulla spesa | B16: =$B$7/$B$6 | D16: spesa netta diviso patrimonio. E' il conto che torna, ed e' gia' il doppio dell'etichetta. Nel caso del video: 3,26%.
A17: TASSO VERO DI USCITA (imposte e bollo) | B17: =($B$21+$B$24+$B$25)/$B$6 | D17: tutto quello che esce dal portafoglio per farti spendere quella cifra: cedole LORDE, vendita LORDA di quote e imposta di bollo. Nel caso del video: 3,67%. E' il numero-titolo.
A18: Confrontabile con il 4% storico (senza bollo) | B18: =($B$21+$B$24)/$B$6 | D18: Il Trinity Study del 1998 dice testualmente «the study did not adjust for taxes or transaction costs»: il bollo li' non c'e'. Il termine omogeneo col 4% e' questo, 3,47%, non il 3,67%.
A20: DA DOVE VENGONO — la cascata dell'anno 1
A21: Cedole LORDE che il portafoglio stacca | B21: =$B$8/(1-$B$10) | D21: Le cedole nette che incassi, rilordizzate: e' quello che il portafoglio ha davvero pagato, ritenuta compresa.
A22: Fabbisogno da coprire vendendo quote | B22: =$B$7-$B$8
A23: Aliquota effettiva sulla vendita | B23: =$B$11*$B$9 | D23: 26% sulla sola plusvalenza: col 20% latente sono il 5,2% dell'importo venduto. E' il numero che rende la vendita di quote piu' efficiente della cedola sotto il 48,08% di plusvalenza latente (foglio 2).
A24: Vendita LORDA di quote | B24: =$B$22/(1-$B$23)
A25: Imposta di bollo in euro | B25: =$B$12*$B$6
A26: USCITA TOTALE DAL PORTAFOGLIO | B26: =$B$21+$B$24+$B$25 | D26: Il costo pieno di essere investita in Italia.
A27: di cui, senza il bollo | B27: =$B$21+$B$24
A29: Una nota di onesta' sul foglio: qui la cascata usa i 15.000 € netti tondi dichiarati dal caso, mentre il modello del foglio 3 calcola le cedole anno per anno e per l'anno 1 trova 13.680 € netti su 14.720 € lordi. La differenza sull'uscita totale e' di 28 € su 33.800, e non sposta nessuno dei quattro tassi al secondo decimale.
A30: Se il tasso vero e' piu' alto di quello che ti raccontavi, non e' successo niente di grave: e' successo che adesso lo sai, e puoi fare la verifica che con l'etichetta non avresti mai fatto. Il foglio 3 la fa.

Sheet 2 - Quanto costa il canale
A1: Quanto costa il canale — la classifica dei modi di incassare
A2: Strumento informativo / divulgativo. NON è consulenza finanziaria. I valori sono indicativi al 2026 e vanno verificati col tuo consulente.
A3: La domanda di questo foglio e' «quale strumento tengo in portafoglio», non «da dove prelevo». Sono due domande diverse e hanno due risposte diverse: la seconda e' nel riquadro in fondo.
A5: IL TUO CASO
A6: Importo NETTO che ti serve incassare | B6: 15000 | G6: Nel video sono i 15.000 € netti che coprono meta' della spesa di Elena.
A7: Aliquota su dividendi, premi e plusvalenze | B7: 0.26 | G7: D.L. 66/2014 art. 3 c. 1.
A8: Aliquota su titoli di Stato e white list | B8: 0.125 | G8: D.L. 66/2014 art. 3 c. 2: i redditi diversi da titoli di Stato rilevano nella misura del 48,08%, che e' esattamente 12,5 / 26.
A10: LA CLASSIFICA — quanto devi smobilizzare per averne 15.000 netti
A11: Canale di incasso | B11: Plusvalenza latente | C11: Aliquota effettiva | D11: Lordo da smobilizzare | E11: Imposta pagata
A12: Vendita di quote ETF, plusvalenza latente 10% | B12: 0.1 | C12: =$B$7*$B12 | D12: =$B$6/(1-$C12) | E12: =$D12-$B$6
A13: Vendita di quote ETF, plusvalenza latente 20% | B13: 0.2 | C13: =$B$7*$B13 | D13: =$B$6/(1-$C13) | E13: =$D13-$B$6
A14: Vendita di quote ETF, plusvalenza latente 30% | B14: 0.3 | C14: =$B$7*$B14 | D14: =$B$6/(1-$C14) | E14: =$D14-$B$6
A15: CEDOLE BTP e titoli di Stato — il pareggio | B15: =$B$8/$B$7 | C15: =$B$8 | D15: =$B$6/(1-$C15) | E15: =$D15-$B$6
A16: Vendita di quote ETF, plusvalenza latente 80% | B16: 0.8 | C16: =$B$7*$B16 | D16: =$B$6/(1-$C16) | E16: =$D16-$B$6
A17: Dividendi, o premi senza minusvalenze in capienza | B17: — | C17: =$B$7 | D17: =$B$6/(1-$C17) | E17: =$D17-$B$6
A18: La riga gialla e' il pareggio: la cedola di un titolo di Stato costa il 12,5% dell'INTERO flusso, la vendita di quote costa il 26% della sola plusvalenza. Sopra la riga gialla la cedola conviene, sotto conviene vendere quote — e sotto ci stanno quasi tutti.
A20: IL BREAK-EVEN — sopra quanta plusvalenza la cedola conviene
A21: Plusvalenza latente che pareggia la cedola | B21: =$B$8/$B$7 | G21: 0,26 x q = 0,125 da' q = 48,077%. E' la stessa frazione con cui il D.L. 66/2014 abbatte la base imponibile dei titoli di Stato: la stessa divisione, fatta due volte.
A22: Sotto il 48,08% di plusvalenza latente la cedola gia' incassata ti e' costata piu' di quanto ti sarebbe costato vendere quote per lo stesso importo. E' un costo di DETENZIONE: lo paghi ogni anno per il fatto di possedere quello strumento, anche negli anni in cui la cassa non ti serve.
A24: FUORI CLASSIFICA — i premi dei certificati finche' dura la minusvalenza
A25: Questa riga non entra in classifica perche' non e' una proprieta' dello strumento: e' una condizione temporanea, che finisce quando lo zainetto di minusvalenze si esaurisce. Le minusvalenze sono redditi diversi e si riportano nell'anno di realizzo e nei QUATTRO successivi (art. 68 c. 5 TUIR); i premi condizionati dei certificati sono anch'essi redditi diversi, e quindi li assorbono.
A26: Premi dei certificati con minusvalenza in capienza | B26: temporaneo | C26: =0 | D26: =$B$6 | E26: =$D$26-$B$6
A28: Zainetto di minusvalenze da smaltire | B28: 10000 | G28: Dato del caso del video.
A29: Premi lordi dei certificati in un anno | B29: 6400 | G29: 8% su 80.000 €: ipotesi dichiarata, forbice 6-10%.
A30: Risparmio fiscale massimo — IN TUTTO, non all'anno | B30: =$B$7*$B$28 | G30: 26% x 10.000 = 2.600 €, una volta sola: 28 punti base sul patrimonio del caso. Manovra di smaltimento, non pilastro.
A31: Anni per assorbirlo, ai premi dichiarati | B31: =$B$28/$B$29
A32: Se la minusvalenza venisse da titoli di Stato (48,08%) | B32: =$B$7*($B$8/$B$7)*$B$28
A34: Anno | B34: Minusvalenza residua a inizio anno | C34: Premi compensati | D34: Imposta risparmiata | E34: Residua a fine anno
A35: 1 | B35: =$B$28 | C35: =MIN($B35,$B$29) | D35: =$C35*$B$7 | E35: =$B35-$C35
A36: 2 | B36: =$E35 | C36: =MIN($B36,$B$29) | D36: =$C36*$B$7 | E36: =$B36-$C36
A37: 3 | B37: =$E36 | C37: =MIN($B37,$B$29) | D37: =$C37*$B$7 | E37: =$B37-$C37
A38: 4 | B38: =$E37 | C38: =MIN($B38,$B$29) | D38: =$C38*$B$7 | E38: =$B38-$C38
A39: 5 | B39: =$E38 | C39: =MIN($B39,$B$29) | D39: =$C39*$B$7 | E39: =$B39-$C39
A40: Dopo un anno e mezzo il contatore e' a zero e i certificati restano li', con i premi al 26% pieno e il capitale non garantito a scadenza. Il vantaggio fiscale era vero, ed era piccolo e a termine.
A42: DOMANDA B — da dove prelevo, dato il portafoglio che ho
A43: 1. La classifica qui sopra risponde alla domanda «quale strumento tengo». Se la domanda e' invece «da dove prelevo, dato il portafoglio che ho gia'», la risposta si ribalta: la cedola gia' incassata ha costo marginale fiscale ZERO.
A44: 2. La ritenuta e' stata trattenuta comunque e la cedola e' arrivata comunque. Non spenderla e vendere altro al suo posto significa pagare DUE imposte sullo stesso euro di spesa: quella gia' pagata sulla cedola e quella nuova sulla plusvalenza della vendita.
A45: 3. La sintesi che tiene insieme le due domande: il costo fiscale della cedola e' un costo di DETENZIONE, non di prelievo. La domanda giusta non e' «da dove prelevo» — su quella la risposta era gia' corretta — ma «quanto mi costa, ogni anno, avere un portafoglio che mi consegna denaro che non ho chiesto».

Sheet 3 - Il ponte
A1: Il ponte — dieci anni misurati anno per anno
A2: Strumento informativo / divulgativo. NON è consulenza finanziaria. I valori sono indicativi al 2026 e vanno verificati col tuo consulente.
A3: Questo modello tratta il portafoglio come un blocco unico con un unico rendimento. Nella realta' una parte scade e va reinvestita, e strumenti diversi si comportano diversamente nei crolli: il modello serve a misurare i flussi e le imposte, non a premiare un'allocazione. Le uniche eccezioni sono lo schedario cedolare del BTP Valore, il premio fedelta' e il reinvestimento all'anno di rimborso, che sono espliciti.
A5: PARAMETRI DEL MODELLO — cambia solo le celle gialle
A6: Patrimonio iniziale | B6: 920000 | D6: Dato del caso.
A7: Spesa netta dell'anno 1 | B7: 30000 | D7: Indicizzata all'inflazione negli anni successivi.
A8: Inflazione | B8: 0.02 | D8: Ipotesi del modello.
A9: Rendimento reale — scenario centrale | B9: 0.03 | D9: Ipotesi dichiarata, non previsione. Il conto bottom-up sul portafoglio del caso da' 3,02-3,34% reale lordo: il 3% e' il pavimento della forbice.
A10: Rendimento reale — scenario prudente | B10: 0.01 | D10: La banda dichiarata e' 1% / 3%, piu' i due ordinamenti di sequenza del foglio 5. Non esiste uno scenario al 5%.
A11: Durata del ponte (anni) | B11: 10 | D11: Da 57 a 67 anni. Il motore ha dieci righe: per cambiare durata vanno aggiunte o tolte righe.
A12: Plusvalenza latente iniziale | B12: 0.2 | D12: Ipotesi dichiarata.
A13: Aliquota sulle plusvalenze | B13: 0.26 | D13: Sulla sola plusvalenza, a costo medio ponderato.
A14: Aliquota su cedole BTP e premio fedelta' | B14: 0.125
A15: Aliquota sui premi dei certificati | B15: 0.26 | D15: Redditi diversi: compensano le minusvalenze.
A16: Imposta di bollo | B16: 0.002 | D16: 0,2% del patrimonio di FINE anno, applicata a fine anno. Anno 1: 1.862 €.
A17: BTP Valore — capitale nominale | B17: 320000 | D17: ISIN IT0005696320, godimento 10/03/2026, scadenza 10/03/2032.
A18: cedola anni 1-2 | B18: 0.026 | D18: MEF, comunicato del 6 marzo 2026: tassi DEFINITIVI, rivisti al rialzo.
A19: cedola anni 3-4 | B19: 0.032
A20: cedola anni 5-6 | B20: 0.038 | D20: Cedola finale 3,80%, rendimento vero a scadenza 3,336% lordo e 2,919% netto: lo step-up e' marketing di flusso.
A21: premio fedelta' | B21: 0.008 | D21: 0,8% a chi sottoscrive in collocamento e tiene a scadenza. Vale 12 punti base l'anno: sembra grande perche' non e' annualizzato.
A22: anno di rimborso del titolo | B22: 6 | D22: Il rimborso alla pari di 320.000 € dentro l'orizzonte e' 34,8 punti di patrimonio: e' la vera difesa dalla sequenza, e non viene dalle cedole.
A23: tasso di reinvestimento dall'anno successivo | B23: 0.03 | D23: Sensibilita': da 1,5% a 4,0% il capitale finale cambia di 851 € su 817.000, con segno NEGATIVO. Nel modello una cedola piu' alta non aggiunge rendimento: sposta reddito verso un canale piu' tassato.
A24: Certificati — capitale nominale | B24: 80000
A25: premi condizionati | B25: 0.08 | D25: Ipotesi dichiarata, forbice 6-10%. Da questa cella dipende la quota di flusso prodotta dai certificati: fra il 28% e il 49% secondo l'ipotesi e il biennio.
A26: Zainetto di minusvalenze | B26: 10000 | D26: Si consuma sui premi dei certificati, come nel foglio 2.
A28: SCHEDARIO CEDOLARE — i tassi definitivi, anno per anno
A29: Anno | B29: Cedola BTP Valore lorda | C29: Premio fedelta' | D29: Premi dei certificati | E29: CEDOLE LORDE TOTALI
A30: 1 | B30: =IF(1<=2,$B$17*$B$18,IF(1<=4,$B$17*$B$19,IF(1<=$B$22,$B$17*$B$20,$B$17*$B$23))) | C30: =IF(1=$B$22,$B$17*$B$21,0) | D30: =$B$24*$B$25 | E30: =$B30+$C30+$D30
A31: 2 | B31: =IF(2<=2,$B$17*$B$18,IF(2<=4,$B$17*$B$19,IF(2<=$B$22,$B$17*$B$20,$B$17*$B$23))) | C31: =IF(2=$B$22,$B$17*$B$21,0) | D31: =$B$24*$B$25 | E31: =$B31+$C31+$D31
A32: 3 | B32: =IF(3<=2,$B$17*$B$18,IF(3<=4,$B$17*$B$19,IF(3<=$B$22,$B$17*$B$20,$B$17*$B$23))) | C32: =IF(3=$B$22,$B$17*$B$21,0) | D32: =$B$24*$B$25 | E32: =$B32+$C32+$D32
A33: 4 | B33: =IF(4<=2,$B$17*$B$18,IF(4<=4,$B$17*$B$19,IF(4<=$B$22,$B$17*$B$20,$B$17*$B$23))) | C33: =IF(4=$B$22,$B$17*$B$21,0) | D33: =$B$24*$B$25 | E33: =$B33+$C33+$D33
A34: 5 | B34: =IF(5<=2,$B$17*$B$18,IF(5<=4,$B$17*$B$19,IF(5<=$B$22,$B$17*$B$20,$B$17*$B$23))) | C34: =IF(5=$B$22,$B$17*$B$21,0) | D34: =$B$24*$B$25 | E34: =$B34+$C34+$D34
A35: 6 | B35: =IF(6<=2,$B$17*$B$18,IF(6<=4,$B$17*$B$19,IF(6<=$B$22,$B$17*$B$20,$B$17*$B$23))) | C35: =IF(6=$B$22,$B$17*$B$21,0) | D35: =$B$24*$B$25 | E35: =$B35+$C35+$D35
A36: 7 | B36: =IF(7<=2,$B$17*$B$18,IF(7<=4,$B$17*$B$19,IF(7<=$B$22,$B$17*$B$20,$B$17*$B$23))) | C36: =IF(7=$B$22,$B$17*$B$21,0) | D36: =$B$24*$B$25 | E36: =$B36+$C36+$D36
A37: 8 | B37: =IF(8<=2,$B$17*$B$18,IF(8<=4,$B$17*$B$19,IF(8<=$B$22,$B$17*$B$20,$B$17*$B$23))) | C37: =IF(8=$B$22,$B$17*$B$21,0) | D37: =$B$24*$B$25 | E37: =$B37+$C37+$D37
A38: 9 | B38: =IF(9<=2,$B$17*$B$18,IF(9<=4,$B$17*$B$19,IF(9<=$B$22,$B$17*$B$20,$B$17*$B$23))) | C38: =IF(9=$B$22,$B$17*$B$21,0) | D38: =$B$24*$B$25 | E38: =$B38+$C38+$D38
A39: 10 | B39: =IF(10<=2,$B$17*$B$18,IF(10<=4,$B$17*$B$19,IF(10<=$B$22,$B$17*$B$20,$B$17*$B$23))) | C39: =IF(10=$B$22,$B$17*$B$21,0) | D39: =$B$24*$B$25 | E39: =$B39+$C39+$D39
A41: IL PONTE — scenario centrale (rendimento reale della cella B9)
A42: Anno | B42: Spesa netta dell'anno | C42: Cedole lorde | D42: Imposta 12,5% su BTP e premio | E42: Zainetto minus. a inizio anno | F42: Imposta 26% sui premi | G42: Cedole nette | H42: Da coprire vendendo | I42: Plusvalenza latente | J42: Aliquota eff. sulla vendita | K42: Vendita lorda | L42: Uscita lorda (cedole+vendita) | M42: Rendimento reale | N42: Patrimonio prima del bollo | O42: Imposta di bollo | P42: Patrimonio a fine anno | Q42: USCITA TOTALE col bollo | R42: Costo fiscale a fine anno | S42: Patrimonio in euro di oggi
A43: 1 | B43: =$B$7*(1+$B$8)^(1-1) | C43: =$E$30 | D43: =($B$30+$C$30)*$B$14 | E43: =$B$26 | F43: =MAX(0,$D$30-E43)*$B$15 | G43: =C43-D43-F43 | H43: =B43-G43 | I43: =1-($B$6*(1-$B$12))/$B$6 | J43: =$B$13*I43 | K43: =H43/(1-J43) | L43: =C43+K43 | M43: =$B$9 | N43: =($B$6-L43)*(1+M43)*(1+$B$8) | O43: =N43-P43 | P43: =N43/(1+$B$16) | Q43: =L43+O43 | R43: =($B$6*(1-$B$12))-K43*($B$6*(1-$B$12))/$B$6 | S43: =P43/(1+$B$8)^1
A44: 2 | B44: =$B$7*(1+$B$8)^(2-1) | C44: =$E$31 | D44: =($B$31+$C$31)*$B$14 | E44: =MAX(0,E43-$D$30) | F44: =MAX(0,$D$31-E44)*$B$15 | G44: =C44-D44-F44 | H44: =B44-G44 | I44: =1-R43/P43 | J44: =$B$13*I44 | K44: =H44/(1-J44) | L44: =C44+K44 | M44: =$B$9 | N44: =(P43-L44)*(1+M44)*(1+$B$8) | O44: =N44-P44 | P44: =N44/(1+$B$16) | Q44: =L44+O44 | R44: =R43-K44*R43/P43 | S44: =P44/(1+$B$8)^2
A45: 3 | B45: =$B$7*(1+$B$8)^(3-1) | C45: =$E$32 | D45: =($B$32+$C$32)*$B$14 | E45: =MAX(0,E44-$D$31) | F45: =MAX(0,$D$32-E45)*$B$15 | G45: =C45-D45-F45 | H45: =B45-G45 | I45: =1-R44/P44 | J45: =$B$13*I45 | K45: =H45/(1-J45) | L45: =C45+K45 | M45: =$B$9 | N45: =(P44-L45)*(1+M45)*(1+$B$8) | O45: =N45-P45 | P45: =N45/(1+$B$16) | Q45: =L45+O45 | R45: =R44-K45*R44/P44 | S45: =P45/(1+$B$8)^3
A46: 4 | B46: =$B$7*(1+$B$8)^(4-1) | C46: =$E$33 | D46: =($B$33+$C$33)*$B$14 | E46: =MAX(0,E45-$D$32) | F46: =MAX(0,$D$33-E46)*$B$15 | G46: =C46-D46-F46 | H46: =B46-G46 | I46: =1-R45/P45 | J46: =$B$13*I46 | K46: =H46/(1-J46) | L46: =C46+K46 | M46: =$B$9 | N46: =(P45-L46)*(1+M46)*(1+$B$8) | O46: =N46-P46 | P46: =N46/(1+$B$16) | Q46: =L46+O46 | R46: =R45-K46*R45/P45 | S46: =P46/(1+$B$8)^4
A47: 5 | B47: =$B$7*(1+$B$8)^(5-1) | C47: =$E$34 | D47: =($B$34+$C$34)*$B$14 | E47: =MAX(0,E46-$D$33) | F47: =MAX(0,$D$34-E47)*$B$15 | G47: =C47-D47-F47 | H47: =B47-G47 | I47: =1-R46/P46 | J47: =$B$13*I47 | K47: =H47/(1-J47) | L47: =C47+K47 | M47: =$B$9 | N47: =(P46-L47)*(1+M47)*(1+$B$8) | O47: =N47-P47 | P47: =N47/(1+$B$16) | Q47: =L47+O47 | R47: =R46-K47*R46/P46 | S47: =P47/(1+$B$8)^5
A48: 6 | B48: =$B$7*(1+$B$8)^(6-1) | C48: =$E$35 | D48: =($B$35+$C$35)*$B$14 | E48: =MAX(0,E47-$D$34) | F48: =MAX(0,$D$35-E48)*$B$15 | G48: =C48-D48-F48 | H48: =B48-G48 | I48: =1-R47/P47 | J48: =$B$13*I48 | K48: =H48/(1-J48) | L48: =C48+K48 | M48: =$B$9 | N48: =(P47-L48)*(1+M48)*(1+$B$8) | O48: =N48-P48 | P48: =N48/(1+$B$16) | Q48: =L48+O48 | R48: =R47-K48*R47/P47 | S48: =P48/(1+$B$8)^6
A49: 7 | B49: =$B$7*(1+$B$8)^(7-1) | C49: =$E$36 | D49: =($B$36+$C$36)*$B$14 | E49: =MAX(0,E48-$D$35) | F49: =MAX(0,$D$36-E49)*$B$15 | G49: =C49-D49-F49 | H49: =B49-G49 | I49: =1-R48/P48 | J49: =$B$13*I49 | K49: =H49/(1-J49) | L49: =C49+K49 | M49: =$B$9 | N49: =(P48-L49)*(1+M49)*(1+$B$8) | O49: =N49-P49 | P49: =N49/(1+$B$16) | Q49: =L49+O49 | R49: =R48-K49*R48/P48 | S49: =P49/(1+$B$8)^7
A50: 8 | B50: =$B$7*(1+$B$8)^(8-1) | C50: =$E$37 | D50: =($B$37+$C$37)*$B$14 | E50: =MAX(0,E49-$D$36) | F50: =MAX(0,$D$37-E50)*$B$15 | G50: =C50-D50-F50 | H50: =B50-G50 | I50: =1-R49/P49 | J50: =$B$13*I50 | K50: =H50/(1-J50) | L50: =C50+K50 | M50: =$B$9 | N50: =(P49-L50)*(1+M50)*(1+$B$8) | O50: =N50-P50 | P50: =N50/(1+$B$16) | Q50: =L50+O50 | R50: =R49-K50*R49/P49 | S50: =P50/(1+$B$8)^8
A51: 9 | B51: =$B$7*(1+$B$8)^(9-1) | C51: =$E$38 | D51: =($B$38+$C$38)*$B$14 | E51: =MAX(0,E50-$D$37) | F51: =MAX(0,$D$38-E51)*$B$15 | G51: =C51-D51-F51 | H51: =B51-G51 | I51: =1-R50/P50 | J51: =$B$13*I51 | K51: =H51/(1-J51) | L51: =C51+K51 | M51: =$B$9 | N51: =(P50-L51)*(1+M51)*(1+$B$8) | O51: =N51-P51 | P51: =N51/(1+$B$16) | Q51: =L51+O51 | R51: =R50-K51*R50/P50 | S51: =P51/(1+$B$8)^9
A52: 10 | B52: =$B$7*(1+$B$8)^(10-1) | C52: =$E$39 | D52: =($B$39+$C$39)*$B$14 | E52: =MAX(0,E51-$D$38) | F52: =MAX(0,$D$39-E52)*$B$15 | G52: =C52-D52-F52 | H52: =B52-G52 | I52: =1-R51/P51 | J52: =$B$13*I52 | K52: =H52/(1-J52) | L52: =C52+K52 | M52: =$B$9 | N52: =(P51-L52)*(1+M52)*(1+$B$8) | O52: =N52-P52 | P52: =N52/(1+$B$16) | Q52: =L52+O52 | R52: =R51-K52*R51/P51 | S52: =P52/(1+$B$8)^10
A53: Anno 1: escono 14.720 € di cedole lorde e 17.215 € di vendita di quote, piu' 1.862 € di bollo. Uscita totale 33.797 €, che su 920.000 € e' il 3,67%. La spesa e' 30.000 €, cioe' il 3,26%: la differenza sono solo imposte e bollo.
A55: IL PONTE — scenario prudente (rendimento reale della cella B10)
A56: Anno | B56: Spesa netta dell'anno | C56: Cedole lorde | D56: Imposta 12,5% su BTP e premio | E56: Zainetto minus. a inizio anno | F56: Imposta 26% sui premi | G56: Cedole nette | H56: Da coprire vendendo | I56: Plusvalenza latente | J56: Aliquota eff. sulla vendita | K56: Vendita lorda | L56: Uscita lorda (cedole+vendita) | M56: Rendimento reale | N56: Patrimonio prima del bollo | O56: Imposta di bollo | P56: Patrimonio a fine anno | Q56: USCITA TOTALE col bollo | R56: Costo fiscale a fine anno | S56: Patrimonio in euro di oggi
A57: 1 | B57: =$B$7*(1+$B$8)^(1-1) | C57: =$E$30 | D57: =($B$30+$C$30)*$B$14 | E57: =$B$26 | F57: =MAX(0,$D$30-E57)*$B$15 | G57: =C57-D57-F57 | H57: =B57-G57 | I57: =1-($B$6*(1-$B$12))/$B$6 | J57: =$B$13*I57 | K57: =H57/(1-J57) | L57: =C57+K57 | M57: =$B$10 | N57: =($B$6-L57)*(1+M57)*(1+$B$8) | O57: =N57-P57 | P57: =N57/(1+$B$16) | Q57: =L57+O57 | R57: =($B$6*(1-$B$12))-K57*($B$6*(1-$B$12))/$B$6 | S57: =P57/(1+$B$8)^1
A58: 2 | B58: =$B$7*(1+$B$8)^(2-1) | C58: =$E$31 | D58: =($B$31+$C$31)*$B$14 | E58: =MAX(0,E57-$D$30) | F58: =MAX(0,$D$31-E58)*$B$15 | G58: =C58-D58-F58 | H58: =B58-G58 | I58: =1-R57/P57 | J58: =$B$13*I58 | K58: =H58/(1-J58) | L58: =C58+K58 | M58: =$B$10 | N58: =(P57-L58)*(1+M58)*(1+$B$8) | O58: =N58-P58 | P58: =N58/(1+$B$16) | Q58: =L58+O58 | R58: =R57-K58*R57/P57 | S58: =P58/(1+$B$8)^2
A59: 3 | B59: =$B$7*(1+$B$8)^(3-1) | C59: =$E$32 | D59: =($B$32+$C$32)*$B$14 | E59: =MAX(0,E58-$D$31) | F59: =MAX(0,$D$32-E59)*$B$15 | G59: =C59-D59-F59 | H59: =B59-G59 | I59: =1-R58/P58 | J59: =$B$13*I59 | K59: =H59/(1-J59) | L59: =C59+K59 | M59: =$B$10 | N59: =(P58-L59)*(1+M59)*(1+$B$8) | O59: =N59-P59 | P59: =N59/(1+$B$16) | Q59: =L59+O59 | R59: =R58-K59*R58/P58 | S59: =P59/(1+$B$8)^3
A60: 4 | B60: =$B$7*(1+$B$8)^(4-1) | C60: =$E$33 | D60: =($B$33+$C$33)*$B$14 | E60: =MAX(0,E59-$D$32) | F60: =MAX(0,$D$33-E60)*$B$15 | G60: =C60-D60-F60 | H60: =B60-G60 | I60: =1-R59/P59 | J60: =$B$13*I60 | K60: =H60/(1-J60) | L60: =C60+K60 | M60: =$B$10 | N60: =(P59-L60)*(1+M60)*(1+$B$8) | O60: =N60-P60 | P60: =N60/(1+$B$16) | Q60: =L60+O60 | R60: =R59-K60*R59/P59 | S60: =P60/(1+$B$8)^4
A61: 5 | B61: =$B$7*(1+$B$8)^(5-1) | C61: =$E$34 | D61: =($B$34+$C$34)*$B$14 | E61: =MAX(0,E60-$D$33) | F61: =MAX(0,$D$34-E61)*$B$15 | G61: =C61-D61-F61 | H61: =B61-G61 | I61: =1-R60/P60 | J61: =$B$13*I61 | K61: =H61/(1-J61) | L61: =C61+K61 | M61: =$B$10 | N61: =(P60-L61)*(1+M61)*(1+$B$8) | O61: =N61-P61 | P61: =N61/(1+$B$16) | Q61: =L61+O61 | R61: =R60-K61*R60/P60 | S61: =P61/(1+$B$8)^5
A62: 6 | B62: =$B$7*(1+$B$8)^(6-1) | C62: =$E$35 | D62: =($B$35+$C$35)*$B$14 | E62: =MAX(0,E61-$D$34) | F62: =MAX(0,$D$35-E62)*$B$15 | G62: =C62-D62-F62 | H62: =B62-G62 | I62: =1-R61/P61 | J62: =$B$13*I62 | K62: =H62/(1-J62) | L62: =C62+K62 | M62: =$B$10 | N62: =(P61-L62)*(1+M62)*(1+$B$8) | O62: =N62-P62 | P62: =N62/(1+$B$16) | Q62: =L62+O62 | R62: =R61-K62*R61/P61 | S62: =P62/(1+$B$8)^6
A63: 7 | B63: =$B$7*(1+$B$8)^(7-1) | C63: =$E$36 | D63: =($B$36+$C$36)*$B$14 | E63: =MAX(0,E62-$D$35) | F63: =MAX(0,$D$36-E63)*$B$15 | G63: =C63-D63-F63 | H63: =B63-G63 | I63: =1-R62/P62 | J63: =$B$13*I63 | K63: =H63/(1-J63) | L63: =C63+K63 | M63: =$B$10 | N63: =(P62-L63)*(1+M63)*(1+$B$8) | O63: =N63-P63 | P63: =N63/(1+$B$16) | Q63: =L63+O63 | R63: =R62-K63*R62/P62 | S63: =P63/(1+$B$8)^7
A64: 8 | B64: =$B$7*(1+$B$8)^(8-1) | C64: =$E$37 | D64: =($B$37+$C$37)*$B$14 | E64: =MAX(0,E63-$D$36) | F64: =MAX(0,$D$37-E64)*$B$15 | G64: =C64-D64-F64 | H64: =B64-G64 | I64: =1-R63/P63 | J64: =$B$13*I64 | K64: =H64/(1-J64) | L64: =C64+K64 | M64: =$B$10 | N64: =(P63-L64)*(1+M64)*(1+$B$8) | O64: =N64-P64 | P64: =N64/(1+$B$16) | Q64: =L64+O64 | R64: =R63-K64*R63/P63 | S64: =P64/(1+$B$8)^8
A65: 9 | B65: =$B$7*(1+$B$8)^(9-1) | C65: =$E$38 | D65: =($B$38+$C$38)*$B$14 | E65: =MAX(0,E64-$D$37) | F65: =MAX(0,$D$38-E65)*$B$15 | G65: =C65-D65-F65 | H65: =B65-G65 | I65: =1-R64/P64 | J65: =$B$13*I65 | K65: =H65/(1-J65) | L65: =C65+K65 | M65: =$B$10 | N65: =(P64-L65)*(1+M65)*(1+$B$8) | O65: =N65-P65 | P65: =N65/(1+$B$16) | Q65: =L65+O65 | R65: =R64-K65*R64/P64 | S65: =P65/(1+$B$8)^9
A66: 10 | B66: =$B$7*(1+$B$8)^(10-1) | C66: =$E$39 | D66: =($B$39+$C$39)*$B$14 | E66: =MAX(0,E65-$D$38) | F66: =MAX(0,$D$39-E66)*$B$15 | G66: =C66-D66-F66 | H66: =B66-G66 | I66: =1-R65/P65 | J66: =$B$13*I66 | K66: =H66/(1-J66) | L66: =C66+K66 | M66: =$B$10 | N66: =(P65-L66)*(1+M66)*(1+$B$8) | O66: =N66-P66 | P66: =N66/(1+$B$16) | Q66: =L66+O66 | R66: =R65-K66*R65/P65 | S66: =P66/(1+$B$8)^10
A67: Stesso motore, stesso schedario cedolare: cambia solo il rendimento reale del portafoglio.
A69: CAPITALE A 67 ANNI — i tre scenari, in euro di oggi
A70: Scenario centrale (rendimento reale 3%) | B70: =$S$52
A71: Scenario prudente (rendimento reale 1%) | B71: =$S$66
A72: Crolli all'inizio (stessa media, ordine sfavorevole) | B72: ='5 - Sequenza'!$S$31
A73: Il quarto scenario — gli stessi rendimenti in ordine favorevole — sta nel foglio 5, insieme al costo dell'ordine. La banda dichiarata e' 1% / 3% piu' i due ordinamenti: non esiste uno scenario al 5%.
A75: LA CODA — quanto capitale serve a 67 anni per 25 anni di prelievo
A76: Il conto e' lordizzato: il capitale necessario non e' il valore attuale del prelievo NETTO, perche' per avere 5.000 € netti in mano devi smobilizzare di piu' e pagare l'imposta sulla quota di plusvalenza, e ogni anno paghi il bollo. La lordizzazione costa fra l'11% e il 17%.
A77: Perche' basta una tabella e non serve una ricerca del capitale: vendendo a costo medio ponderato il rapporto fra costo fiscale e patrimonio NON cambia con la vendita (base' = phi x (P - vendita)), quindi la quota di plusvalenza di ogni anno e' nota in anticipo e non dipende da quanto capitale hai. Il capitale necessario e' la semplice somma attualizzata dei prelievi lordi.
A78: Anno | B78: Costo fiscale / patrimonio, r=1% | C78: Aliquota effettiva, r=1% | D78: Capitale per 1 € di buco, r=1% | E78: Costo fiscale / patrimonio, r=3% | F78: Aliquota effettiva, r=3% | G78: Capitale per 1 € di buco, r=3%
A79: 1 | B79: =(1-$B$12)/((1+$B$10)/(1+$B$16))^(1-1) | C79: =$B$13*(1-$B79) | D79: =(1/(1-$C79))/((1+$B$10)/(1+$B$16))^(1-1) | E79: =(1-$B$12)/((1+$B$9)/(1+$B$16))^(1-1) | F79: =$B$13*(1-$E79) | G79: =(1/(1-$F79))/((1+$B$9)/(1+$B$16))^(1-1)
A80: 2 | B80: =(1-$B$12)/((1+$B$10)/(1+$B$16))^(2-1) | C80: =$B$13*(1-$B80) | D80: =(1/(1-$C80))/((1+$B$10)/(1+$B$16))^(2-1) | E80: =(1-$B$12)/((1+$B$9)/(1+$B$16))^(2-1) | F80: =$B$13*(1-$E80) | G80: =(1/(1-$F80))/((1+$B$9)/(1+$B$16))^(2-1)
A81: 3 | B81: =(1-$B$12)/((1+$B$10)/(1+$B$16))^(3-1) | C81: =$B$13*(1-$B81) | D81: =(1/(1-$C81))/((1+$B$10)/(1+$B$16))^(3-1) | E81: =(1-$B$12)/((1+$B$9)/(1+$B$16))^(3-1) | F81: =$B$13*(1-$E81) | G81: =(1/(1-$F81))/((1+$B$9)/(1+$B$16))^(3-1)
A82: 4 | B82: =(1-$B$12)/((1+$B$10)/(1+$B$16))^(4-1) | C82: =$B$13*(1-$B82) | D82: =(1/(1-$C82))/((1+$B$10)/(1+$B$16))^(4-1) | E82: =(1-$B$12)/((1+$B$9)/(1+$B$16))^(4-1) | F82: =$B$13*(1-$E82) | G82: =(1/(1-$F82))/((1+$B$9)/(1+$B$16))^(4-1)
A83: 5 | B83: =(1-$B$12)/((1+$B$10)/(1+$B$16))^(5-1) | C83: =$B$13*(1-$B83) | D83: =(1/(1-$C83))/((1+$B$10)/(1+$B$16))^(5-1) | E83: =(1-$B$12)/((1+$B$9)/(1+$B$16))^(5-1) | F83: =$B$13*(1-$E83) | G83: =(1/(1-$F83))/((1+$B$9)/(1+$B$16))^(5-1)
A84: 6 | B84: =(1-$B$12)/((1+$B$10)/(1+$B$16))^(6-1) | C84: =$B$13*(1-$B84) | D84: =(1/(1-$C84))/((1+$B$10)/(1+$B$16))^(6-1) | E84: =(1-$B$12)/((1+$B$9)/(1+$B$16))^(6-1) | F84: =$B$13*(1-$E84) | G84: =(1/(1-$F84))/((1+$B$9)/(1+$B$16))^(6-1)
A85: 7 | B85: =(1-$B$12)/((1+$B$10)/(1+$B$16))^(7-1) | C85: =$B$13*(1-$B85) | D85: =(1/(1-$C85))/((1+$B$10)/(1+$B$16))^(7-1) | E85: =(1-$B$12)/((1+$B$9)/(1+$B$16))^(7-1) | F85: =$B$13*(1-$E85) | G85: =(1/(1-$F85))/((1+$B$9)/(1+$B$16))^(7-1)
A86: 8 | B86: =(1-$B$12)/((1+$B$10)/(1+$B$16))^(8-1) | C86: =$B$13*(1-$B86) | D86: =(1/(1-$C86))/((1+$B$10)/(1+$B$16))^(8-1) | E86: =(1-$B$12)/((1+$B$9)/(1+$B$16))^(8-1) | F86: =$B$13*(1-$E86) | G86: =(1/(1-$F86))/((1+$B$9)/(1+$B$16))^(8-1)
A87: 9 | B87: =(1-$B$12)/((1+$B$10)/(1+$B$16))^(9-1) | C87: =$B$13*(1-$B87) | D87: =(1/(1-$C87))/((1+$B$10)/(1+$B$16))^(9-1) | E87: =(1-$B$12)/((1+$B$9)/(1+$B$16))^(9-1) | F87: =$B$13*(1-$E87) | G87: =(1/(1-$F87))/((1+$B$9)/(1+$B$16))^(9-1)
A88: 10 | B88: =(1-$B$12)/((1+$B$10)/(1+$B$16))^(10-1) | C88: =$B$13*(1-$B88) | D88: =(1/(1-$C88))/((1+$B$10)/(1+$B$16))^(10-1) | E88: =(1-$B$12)/((1+$B$9)/(1+$B$16))^(10-1) | F88: =$B$13*(1-$E88) | G88: =(1/(1-$F88))/((1+$B$9)/(1+$B$16))^(10-1)
A89: 11 | B89: =(1-$B$12)/((1+$B$10)/(1+$B$16))^(11-1) | C89: =$B$13*(1-$B89) | D89: =(1/(1-$C89))/((1+$B$10)/(1+$B$16))^(11-1) | E89: =(1-$B$12)/((1+$B$9)/(1+$B$16))^(11-1) | F89: =$B$13*(1-$E89) | G89: =(1/(1-$F89))/((1+$B$9)/(1+$B$16))^(11-1)
A90: 12 | B90: =(1-$B$12)/((1+$B$10)/(1+$B$16))^(12-1) | C90: =$B$13*(1-$B90) | D90: =(1/(1-$C90))/((1+$B$10)/(1+$B$16))^(12-1) | E90: =(1-$B$12)/((1+$B$9)/(1+$B$16))^(12-1) | F90: =$B$13*(1-$E90) | G90: =(1/(1-$F90))/((1+$B$9)/(1+$B$16))^(12-1)
A91: 13 | B91: =(1-$B$12)/((1+$B$10)/(1+$B$16))^(13-1) | C91: =$B$13*(1-$B91) | D91: =(1/(1-$C91))/((1+$B$10)/(1+$B$16))^(13-1) | E91: =(1-$B$12)/((1+$B$9)/(1+$B$16))^(13-1) | F91: =$B$13*(1-$E91) | G91: =(1/(1-$F91))/((1+$B$9)/(1+$B$16))^(13-1)
A92: 14 | B92: =(1-$B$12)/((1+$B$10)/(1+$B$16))^(14-1) | C92: =$B$13*(1-$B92) | D92: =(1/(1-$C92))/((1+$B$10)/(1+$B$16))^(14-1) | E92: =(1-$B$12)/((1+$B$9)/(1+$B$16))^(14-1) | F92: =$B$13*(1-$E92) | G92: =(1/(1-$F92))/((1+$B$9)/(1+$B$16))^(14-1)
A93: 15 | B93: =(1-$B$12)/((1+$B$10)/(1+$B$16))^(15-1) | C93: =$B$13*(1-$B93) | D93: =(1/(1-$C93))/((1+$B$10)/(1+$B$16))^(15-1) | E93: =(1-$B$12)/((1+$B$9)/(1+$B$16))^(15-1) | F93: =$B$13*(1-$E93) | G93: =(1/(1-$F93))/((1+$B$9)/(1+$B$16))^(15-1)
A94: 16 | B94: =(1-$B$12)/((1+$B$10)/(1+$B$16))^(16-1) | C94: =$B$13*(1-$B94) | D94: =(1/(1-$C94))/((1+$B$10)/(1+$B$16))^(16-1) | E94: =(1-$B$12)/((1+$B$9)/(1+$B$16))^(16-1) | F94: =$B$13*(1-$E94) | G94: =(1/(1-$F94))/((1+$B$9)/(1+$B$16))^(16-1)
A95: 17 | B95: =(1-$B$12)/((1+$B$10)/(1+$B$16))^(17-1) | C95: =$B$13*(1-$B95) | D95: =(1/(1-$C95))/((1+$B$10)/(1+$B$16))^(17-1) | E95: =(1-$B$12)/((1+$B$9)/(1+$B$16))^(17-1) | F95: =$B$13*(1-$E95) | G95: =(1/(1-$F95))/((1+$B$9)/(1+$B$16))^(17-1)
A96: 18 | B96: =(1-$B$12)/((1+$B$10)/(1+$B$16))^(18-1) | C96: =$B$13*(1-$B96) | D96: =(1/(1-$C96))/((1+$B$10)/(1+$B$16))^(18-1) | E96: =(1-$B$12)/((1+$B$9)/(1+$B$16))^(18-1) | F96: =$B$13*(1-$E96) | G96: =(1/(1-$F96))/((1+$B$9)/(1+$B$16))^(18-1)
A97: 19 | B97: =(1-$B$12)/((1+$B$10)/(1+$B$16))^(19-1) | C97: =$B$13*(1-$B97) | D97: =(1/(1-$C97))/((1+$B$10)/(1+$B$16))^(19-1) | E97: =(1-$B$12)/((1+$B$9)/(1+$B$16))^(19-1) | F97: =$B$13*(1-$E97) | G97: =(1/(1-$F97))/((1+$B$9)/(1+$B$16))^(19-1)
A98: 20 | B98: =(1-$B$12)/((1+$B$10)/(1+$B$16))^(20-1) | C98: =$B$13*(1-$B98) | D98: =(1/(1-$C98))/((1+$B$10)/(1+$B$16))^(20-1) | E98: =(1-$B$12)/((1+$B$9)/(1+$B$16))^(20-1) | F98: =$B$13*(1-$E98) | G98: =(1/(1-$F98))/((1+$B$9)/(1+$B$16))^(20-1)
A99: 21 | B99: =(1-$B$12)/((1+$B$10)/(1+$B$16))^(21-1) | C99: =$B$13*(1-$B99) | D99: =(1/(1-$C99))/((1+$B$10)/(1+$B$16))^(21-1) | E99: =(1-$B$12)/((1+$B$9)/(1+$B$16))^(21-1) | F99: =$B$13*(1-$E99) | G99: =(1/(1-$F99))/((1+$B$9)/(1+$B$16))^(21-1)
A100: 22 | B100: =(1-$B$12)/((1+$B$10)/(1+$B$16))^(22-1) | C100: =$B$13*(1-$B100) | D100: =(1/(1-$C100))/((1+$B$10)/(1+$B$16))^(22-1) | E100: =(1-$B$12)/((1+$B$9)/(1+$B$16))^(22-1) | F100: =$B$13*(1-$E100) | G100: =(1/(1-$F100))/((1+$B$9)/(1+$B$16))^(22-1)
A101: 23 | B101: =(1-$B$12)/((1+$B$10)/(1+$B$16))^(23-1) | C101: =$B$13*(1-$B101) | D101: =(1/(1-$C101))/((1+$B$10)/(1+$B$16))^(23-1) | E101: =(1-$B$12)/((1+$B$9)/(1+$B$16))^(23-1) | F101: =$B$13*(1-$E101) | G101: =(1/(1-$F101))/((1+$B$9)/(1+$B$16))^(23-1)
A102: 24 | B102: =(1-$B$12)/((1+$B$10)/(1+$B$16))^(24-1) | C102: =$B$13*(1-$B102) | D102: =(1/(1-$C102))/((1+$B$10)/(1+$B$16))^(24-1) | E102: =(1-$B$12)/((1+$B$9)/(1+$B$16))^(24-1) | F102: =$B$13*(1-$E102) | G102: =(1/(1-$F102))/((1+$B$9)/(1+$B$16))^(24-1)
A103: 25 | B103: =(1-$B$12)/((1+$B$10)/(1+$B$16))^(25-1) | C103: =$B$13*(1-$B103) | D103: =(1/(1-$C103))/((1+$B$10)/(1+$B$16))^(25-1) | E103: =(1-$B$12)/((1+$B$9)/(1+$B$16))^(25-1) | F103: =$B$13*(1-$E103) | G103: =(1/(1-$F103))/((1+$B$9)/(1+$B$16))^(25-1)
A104: CAPITALE NECESSARIO PER 1 € DI BUCO NETTO ANNUO | D104: =SUM($D$79:$D$103) | G104: =SUM($G$79:$G$103)
A106: QUANTO LE SERVE A 67 ANNI — la soglia, lordizzata
A107: Buco netto annuo da coprire | B107: Capitale necessario, r reale 1% | C107: Capitale necessario, r reale 3%
...

Sheet 4 - Cedole contro total return
A1: Contabilita' a cedole contro total return
A2: Strumento informativo / divulgativo. NON è consulenza finanziaria. I valori sono indicativi al 2026 e vanno verificati col tuo consulente.
A3: Le prime due colonne sono IDENTICHE, e non e' un risultato: e' un'identita' del modello. A parita' di portafoglio, il modo di contare non cambia un euro dei flussi. Cambia quello che il framing ti induce a fare: quale portafoglio costruisci, quale domanda ti poni, quanto spendi quando il budget si allarga.
A5: GLI STESSI FLUSSI, DUE MODI DI CONTARLI
A6: Voce | B6: Contabilita' a cedole | C6: Total return | D6: Differenza
A7: Come descrive il prelievo | B7: «prelevo 15.000: il mio SWR e' 1,63%» | C7: «il portafoglio mi consegna 30.000: 3,26%»
A8: Tasso che dichiara | B8: ='1 - Il tuo tasso vero'!$B$15 | C8: ='1 - Il tuo tasso vero'!$B$16 | D8: l'unica cosa che cambia
A9: Spesa netta dell'anno 1 | B9: ='3 - Il ponte'!$B$43 | C9: ='3 - Il ponte'!$B$43 | D9: =$C9-$B9
A10: Uscita lorda dal portafoglio | B10: ='3 - Il ponte'!$L$43 | C10: ='3 - Il ponte'!$L$43 | D10: =$C10-$B10
A11: Uscita totale con il bollo | B11: ='3 - Il ponte'!$Q$43 | C11: ='3 - Il ponte'!$Q$43 | D11: =$C11-$B11
A12: Capitale a 67 anni, 3% reale | B12: ='3 - Il ponte'!$B$70 | C12: ='3 - Il ponte'!$B$70 | D12: =$C12-$B12
A13: Capitale a 67 anni, crolli all'inizio | B13: ='3 - Il ponte'!$B$72 | C13: ='3 - Il ponte'!$B$72 | D13: =$C13-$B13
A14: Tasso vero di uscita sul patrimonio | B14: =$B$11/'3 - Il ponte'!$B$6 | C14: =$C$11/'3 - Il ponte'!$B$6 | D14: =$C$14-$B$14
A16: La colonna «Differenza» e' zero riga per riga, e deve esserlo. Il vantaggio che la contabilita' a cedole sembra avere — vendere meno azionario in un anno storto — e' reale ma e' una proprieta' dell'ALLOCAZIONE, non della contabilita': gli stessi 320.000 € di BTP producono la stessa protezione anche se li chiami «parte del 3,26%». E nel caso del video quella protezione viene dal rimborso alla pari del 2032, non dalle cedole.
A18: L'ATTRITO DELL'IMPOSTA ANTICIPATA — a parita' di aliquota
A19: Convenzione dichiarata: versamenti a INIZIO anno, rendimento nominale, STESSA aliquota sui due rami. Cambia solo il momento in cui l'imposta si paga: subito su ogni cedola incassata, oppure alla fine su tutto il montante. Il confronto e' onesto solo cosi': confrontare il 12,5% della cedola col 26% di un ETF azionario misurerebbe due cose insieme.
A20: Flusso annuo | B20: 16000 | F20: Il flusso cedolare che non ti serve subito.
A21: Rendimento nominale | B21: 0.05
A22: Orizzonte (anni) | B22: 10
A23: Aliquota (selettore) | B23: 0.125 | F23: Scegli 12,50% o 26,00% dal menu. Il 12,5% e' il comparatore onesto della cedola di un titolo di Stato.
A24: Montante lordo del flusso (senza imposte) | B24: =$B$20*(1+$B$21)*((1+$B$21)^$B$22-1)/$B$21
A25: Ramo cedola — tassata subito, netto reinvestito | B25: =$B$24*(1-$B$23)-($B$24*(1-$B$23)-$B$20*(1-$B$23)*$B$22)*$B$23
A26: Ramo accumulo — imposta pagata alla fine | B26: =$B$24*(1-$B$23)
A27: VANTAGGIO DELL'ACCUMULO | B27: =$B$26-$B$25
A28: in percentuale | B28: =$B$27/$B$25
A30: LE DUE ALIQUOTE, UNA ACCANTO ALL'ALTRA
A31: Aliquota | B31: Ramo cedola | C31: Ramo accumulo | D31: Vantaggio dell'accumulo
A32: 0.125 | B32: =$B$24*(1-$A32)-($B$24*(1-$A32)-$B$20*(1-$A32)*$B$22)*$A32 | C32: =$B$24*(1-$A32) | D32: =$C32-$B32
A33: 0.26 | B33: =$B$24*(1-$A33)-($B$24*(1-$A33)-$B$20*(1-$A33)*$B$22)*$A33 | C33: =$B$24*(1-$A33) | D33: =$C33-$B33
A35: Al 12,5% l'accumulo vale 5.612 € in piu' su dieci anni, il 3,1%. Al 26% sono 9.872 €, il 6,7%. Il vantaggio e' esattamente l'imposta che il ramo cedola paga in anticipo sulla crescita del reinvestito: e' piccolo, ed e' vero. Lo stesso meccanismo degli ETF ad accumulazione contro quelli a distribuzione, applicato alle cedole.
A36: Controprova in convenzione posticipata (versamenti a fine anno): il vantaggio scende a 4.511 € e 7.936 €. Il segno non cambia.

Sheet 5 - Sequenza
A1: La sequenza — lo stesso rendimento medio, due ordini diversi
A2: Strumento informativo / divulgativo. NON è consulenza finanziaria. I valori sono indicativi al 2026 e vanno verificati col tuo consulente.
A3: Le due colonne contengono ESATTAMENTE gli stessi dieci rendimenti, in ordine invertito: stessa media geometrica, stessa somma, stesso tutto. L'unica differenza e' quando arrivano i crolli. Questo e' il rischio di sequenza, e non ha niente a che vedere con quanto rende il portafoglio.
A5: IL MULTISET — dieci rendimenti reali, due ordini
A6: Anno | B6: Crolli all'inizio | C6: Crolli alla fine
A7: 1 | B7: -0.1412 | C7: =$B$16
A8: 2 | B8: -0.0912 | C8: =$B$15
A9: 3 | B9: -0.1212 | C9: =$B$14
A10: 4 | B10: 0.1788 | C10: =$B$13
A11: 5 | B11: 0.1188 | C11: =$B$12
A12: 6 | B12: 0.0788 | C12: =$B$11
A13: 7 | B13: 0.1388 | C13: =$B$10
A14: 8 | B14: 0.0588 | C14: =$B$9
A15: 9 | B15: 0.0888 | C15: =$B$8
A16: 10 | B16: 0.0488 | C16: =$B$7
A17: Media geometrica | B17: =EXP(SUMPRODUCT(LN(1+$B$7:$B$16))/10)-1 | C17: =EXP(SUMPRODUCT(LN(1+$C$7:$C$16))/10)-1
A18: 2,998%, che si dichiara come «il 3%» e non come «esattamente il 3,0000%». La colonna di destra e' una formula che rovescia quella di sinistra: cambia un rendimento a sinistra e resta lo stesso multiset.
A20: IL PONTE CON I CROLLI ALL'INIZIO
A21: Anno | B21: Spesa netta dell'anno | C21: Cedole lorde | D21: Imposta 12,5% su BTP e premio | E21: Zainetto minus. a inizio anno | F21: Imposta 26% sui premi | G21: Cedole nette | H21: Da coprire vendendo | I21: Plusvalenza latente | J21: Aliquota eff. sulla vendita | K21: Vendita lorda | L21: Uscita lorda (cedole+vendita) | M21: Rendimento reale | N21: Patrimonio prima del bollo | O21: Imposta di bollo | P21: Patrimonio a fine anno | Q21: USCITA TOTALE col bollo | R21: Costo fiscale a fine anno | S21: Patrimonio in euro di oggi
A22: 1 | B22: ='3 - Il ponte'!$B$7*(1+'3 - Il ponte'!$B$8)^(1-1) | C22: ='3 - Il ponte'!$E$30 | D22: =('3 - Il ponte'!$B$30+'3 - Il ponte'!$C$30)*'3 - Il ponte'!$B$14 | E22: ='3 - Il ponte'!$B$26 | F22: =MAX(0,'3 - Il ponte'!$D$30-E22)*'3 - Il ponte'!$B$15 | G22: =C22-D22-F22 | H22: =B22-G22 | I22: =1-('3 - Il ponte'!$B$6*(1-'3 - Il ponte'!$B$12))/'3 - Il ponte'!$B$6 | J22: ='3 - Il ponte'!$B$13*I22 | K22: =H22/(1-J22) | L22: =C22+K22 | M22: =$B$7 | N22: =('3 - Il ponte'!$B$6-L22)*(1+M22)*(1+'3 - Il ponte'!$B$8) | O22: =N22-P22 | P22: =N22/(1+'3 - Il ponte'!$B$16) | Q22: =L22+O22 | R22: =('3 - Il ponte'!$B$6*(1-'3 - Il ponte'!$B$12))-K22*('3 - Il ponte'!$B$6*(1-'3 - Il ponte'!$B$12))/'3 - Il ponte'!$B$6 | S22: =P22/(1+'3 - Il ponte'!$B$8)^1
A23: 2 | B23: ='3 - Il ponte'!$B$7*(1+'3 - Il ponte'!$B$8)^(2-1) | C23: ='3 - Il ponte'!$E$31 | D23: =('3 - Il ponte'!$B$31+'3 - Il ponte'!$C$31)*'3 - Il ponte'!$B$14 | E23: =MAX(0,E22-'3 - Il ponte'!$D$30) | F23: =MAX(0,'3 - Il ponte'!$D$31-E23)*'3 - Il ponte'!$B$15 | G23: =C23-D23-F23 | H23: =B23-G23 | I23: =1-R22/P22 | J23: ='3 - Il ponte'!$B$13*I23 | K23: =H23/(1-J23) | L23: =C23+K23 | M23: =$B$8 | N23: =(P22-L23)*(1+M23)*(1+'3 - Il ponte'!$B$8) | O23: =N23-P23 | P23: =N23/(1+'3 - Il ponte'!$B$16) | Q23: =L23+O23 | R23: =R22-K23*R22/P22 | S23: =P23/(1+'3 - Il ponte'!$B$8)^2
A24: 3 | B24: ='3 - Il ponte'!$B$7*(1+'3 - Il ponte'!$B$8)^(3-1) | C24: ='3 - Il ponte'!$E$32 | D24: =('3 - Il ponte'!$B$32+'3 - Il ponte'!$C$32)*'3 - Il ponte'!$B$14 | E24: =MAX(0,E23-'3 - Il ponte'!$D$31) | F24: =MAX(0,'3 - Il ponte'!$D$32-E24)*'3 - Il ponte'!$B$15 | G24: =C24-D24-F24 | H24: =B24-G24 | I24: =1-R23/P23 | J24: ='3 - Il ponte'!$B$13*I24 | K24: =H24/(1-J24) | L24: =C24+K24 | M24: =$B$9 | N24: =(P23-L24)*(1+M24)*(1+'3 - Il ponte'!$B$8) | O24: =N24-P24 | P24: =N24/(1+'3 - Il ponte'!$B$16) | Q24: =L24+O24 | R24: =R23-K24*R23/P23 | S24: =P24/(1+'3 - Il ponte'!$B$8)^3
A25: 4 | B25: ='3 - Il ponte'!$B$7*(1+'3 - Il ponte'!$B$8)^(4-1) | C25: ='3 - Il ponte'!$E$33 | D25: =('3 - Il ponte'!$B$33+'3 - Il ponte'!$C$33)*'3 - Il ponte'!$B$14 | E25: =MAX(0,E24-'3 - Il ponte'!$D$32) | F25: =MAX(0,'3 - Il ponte'!$D$33-E25)*'3 - Il ponte'!$B$15 | G25: =C25-D25-F25 | H25: =B25-G25 | I25: =1-R24/P24 | J25: ='3 - Il ponte'!$B$13*I25 | K25: =H25/(1-J25) | L25: =C25+K25 | M25: =$B$10 | N25: =(P24-L25)*(1+M25)*(1+'3 - Il ponte'!$B$8) | O25: =N25-P25 | P25: =N25/(1+'3 - Il ponte'!$B$16) | Q25: =L25+O25 | R25: =R24-K25*R24/P24 | S25: =P25/(1+'3 - Il ponte'!$B$8)^4
A26: 5 | B26: ='3 - Il ponte'!$B$7*(1+'3 - Il ponte'!$B$8)^(5-1) | C26: ='3 - Il ponte'!$E$34 | D26: =('3 - Il ponte'!$B$34+'3 - Il ponte'!$C$34)*'3 - Il ponte'!$B$14 | E26: =MAX(0,E25-'3 - Il ponte'!$D$33) | F26: =MAX(0,'3 - Il ponte'!$D$34-E26)*'3 - Il ponte'!$B$15 | G26: =C26-D26-F26 | H26: =B26-G26 | I26: =1-R25/P25 | J26: ='3 - Il ponte'!$B$13*I26 | K26: =H26/(1-J26) | L26: =C26+K26 | M26: =$B$11 | N26: =(P25-L26)*(1+M26)*(1+'3 - Il ponte'!$B$8) | O26: =N26-P26 | P26: =N26/(1+'3 - Il ponte'!$B$16) | Q26: =L26+O26 | R26: =R25-K26*R25/P25 | S26: =P26/(1+'3 - Il ponte'!$B$8)^5
A27: 6 | B27: ='3 - Il ponte'!$B$7*(1+'3 - Il ponte'!$B$8)^(6-1) | C27: ='3 - Il ponte'!$E$35 | D27: =('3 - Il ponte'!$B$35+'3 - Il ponte'!$C$35)*'3 - Il ponte'!$B$14 | E27: =MAX(0,E26-'3 - Il ponte'!$D$34) | F27: =MAX(0,'3 - Il ponte'!$D$35-E27)*'3 - Il ponte'!$B$15 | G27: =C27-D27-F27 | H27: =B27-G27 | I27: =1-R26/P26 | J27: ='3 - Il ponte'!$B$13*I27 | K27: =H27/(1-J27) | L27: =C27+K27 | M27: =$B$12 | N27: =(P26-L27)*(1+M27)*(1+'3 - Il ponte'!$B$8) | O27: =N27-P27 | P27: =N27/(1+'3 - Il ponte'!$B$16) | Q27: =L27+O27 | R27: =R26-K27*R26/P26 | S27: =P27/(1+'3 - Il ponte'!$B$8)^6
A28: 7 | B28: ='3 - Il ponte'!$B$7*(1+'3 - Il ponte'!$B$8)^(7-1) | C28: ='3 - Il ponte'!$E$36 | D28: =('3 - Il ponte'!$B$36+'3 - Il ponte'!$C$36)*'3 - Il ponte'!$B$14 | E28: =MAX(0,E27-'3 - Il ponte'!$D$35) | F28: =MAX(0,'3 - Il ponte'!$D$36-E28)*'3 - Il ponte'!$B$15 | G28: =C28-D28-F28 | H28: =B28-G28 | I28: =1-R27/P27 | J28: ='3 - Il ponte'!$B$13*I28 | K28: =H28/(1-J28) | L28: =C28+K28 | M28: =$B$13 | N28: =(P27-L28)*(1+M28)*(1+'3 - Il ponte'!$B$8) | O28: =N28-P28 | P28: =N28/(1+'3 - Il ponte'!$B$16) | Q28: =L28+O28 | R28: =R27-K28*R27/P27 | S28: =P28/(1+'3 - Il ponte'!$B$8)^7
A29: 8 | B29: ='3 - Il ponte'!$B$7*(1+'3 - Il ponte'!$B$8)^(8-1) | C29: ='3 - Il ponte'!$E$37 | D29: =('3 - Il ponte'!$B$37+'3 - Il ponte'!$C$37)*'3 - Il ponte'!$B$14 | E29: =MAX(0,E28-'3 - Il ponte'!$D$36) | F29: =MAX(0,'3 - Il ponte'!$D$37-E29)*'3 - Il ponte'!$B$15 | G29: =C29-D29-F29 | H29: =B29-G29 | I29: =1-R28/P28 | J29: ='3 - Il ponte'!$B$13*I29 | K29: =H29/(1-J29) | L29: =C29+K29 | M29: =$B$14 | N29: =(P28-L29)*(1+M29)*(1+'3 - Il ponte'!$B$8) | O29: =N29-P29 | P29: =N29/(1+'3 - Il ponte'!$B$16) | Q29: =L29+O29 | R29: =R28-K29*R28/P28 | S29: =P29/(1+'3 - Il ponte'!$B$8)^8
A30: 9 | B30: ='3 - Il ponte'!$B$7*(1+'3 - Il ponte'!$B$8)^(9-1) | C30: ='3 - Il ponte'!$E$38 | D30: =('3 - Il ponte'!$B$38+'3 - Il ponte'!$C$38)*'3 - Il ponte'!$B$14 | E30: =MAX(0,E29-'3 - Il ponte'!$D$37) | F30: =MAX(0,'3 - Il ponte'!$D$38-E30)*'3 - Il ponte'!$B$15 | G30: =C30-D30-F30 | H30: =B30-G30 | I30: =1-R29/P29 | J30: ='3 - Il ponte'!$B$13*I30 | K30: =H30/(1-J30) | L30: =C30+K30 | M30: =$B$15 | N30: =(P29-L30)*(1+M30)*(1+'3 - Il ponte'!$B$8) | O30: =N30-P30 | P30: =N30/(1+'3 - Il ponte'!$B$16) | Q30: =L30+O30 | R30: =R29-K30*R29/P29 | S30: =P30/(1+'3 - Il ponte'!$B$8)^9
A31: 10 | B31: ='3 - Il ponte'!$B$7*(1+'3 - Il ponte'!$B$8)^(10-1) | C31: ='3 - Il ponte'!$E$39 | D31: =('3 - Il ponte'!$B$39+'3 - Il ponte'!$C$39)*'3 - Il ponte'!$B$14 | E31: =MAX(0,E30-'3 - Il ponte'!$D$38) | F31: =MAX(0,'3 - Il ponte'!$D$39-E31)*'3 - Il ponte'!$B$15 | G31: =C31-D31-F31 | H31: =B31-G31 | I31: =1-R30/P30 | J31: ='3 - Il ponte'!$B$13*I31 | K31: =H31/(1-J31) | L31: =C31+K31 | M31: =$B$16 | N31: =(P30-L31)*(1+M31)*(1+'3 - Il ponte'!$B$8) | O31: =N31-P31 | P31: =N31/(1+'3 - Il ponte'!$B$16) | Q31: =L31+O31 | R31: =R30-K31*R30/P30 | S31: =P31/(1+'3 - Il ponte'!$B$8)^10
A34: IL PONTE CON I CROLLI ALLA FINE
A35: Anno | B35: Spesa netta dell'anno | C35: Cedole lorde | D35: Imposta 12,5% su BTP e premio | E35: Zainetto minus. a inizio anno | F35: Imposta 26% sui premi | G35: Cedole nette | H35: Da coprire vendendo | I35: Plusvalenza latente | J35: Aliquota eff. sulla vendita | K35: Vendita lorda | L35: Uscita lorda (cedole+vendita) | M35: Rendimento reale | N35: Patrimonio prima del bollo | O35: Imposta di bollo | P35: Patrimonio a fine anno | Q35: USCITA TOTALE col bollo | R35: Costo fiscale a fine anno | S35: Patrimonio in euro di oggi
A36: 1 | B36: ='3 - Il ponte'!$B$7*(1+'3 - Il ponte'!$B$8)^(1-1) | C36: ='3 - Il ponte'!$E$30 | D36: =('3 - Il ponte'!$B$30+'3 - Il ponte'!$C$30)*'3 - Il ponte'!$B$14 | E36: ='3 - Il ponte'!$B$26 | F36: =MAX(0,'3 - Il ponte'!$D$30-E36)*'3 - Il ponte'!$B$15 | G36: =C36-D36-F36 | H36: =B36-G36 | I36: =1-('3 - Il ponte'!$B$6*(1-'3 - Il ponte'!$B$12))/'3 - Il ponte'!$B$6 | J36: ='3 - Il ponte'!$B$13*I36 | K36: =H36/(1-J36) | L36: =C36+K36 | M36: =$C$7 | N36: =('3 - Il ponte'!$B$6-L36)*(1+M36)*(1+'3 - Il ponte'!$B$8) | O36: =N36-P36 | P36: =N36/(1+'3 - Il ponte'!$B$16) | Q36: =L36+O36 | R36: =('3 - Il ponte'!$B$6*(1-'3 - Il ponte'!$B$12))-K36*('3 - Il ponte'!$B$6*(1-'3 - Il ponte'!$B$12))/'3 - Il ponte'!$B$6 | S36: =P36/(1+'3 - Il ponte'!$B$8)^1
A37: 2 | B37: ='3 - Il ponte'!$B$7*(1+'3 - Il ponte'!$B$8)^(2-1) | C37: ='3 - Il ponte'!$E$31 | D37: =('3 - Il ponte'!$B$31+'3 - Il ponte'!$C$31)*'3 - Il ponte'!$B$14 | E37: =MAX(0,E36-'3 - Il ponte'!$D$30) | F37: =MAX(0,'3 - Il ponte'!$D$31-E37)*'3 - Il ponte'!$B$15 | G37: =C37-D37-F37 | H37: =B37-G37 | I37: =1-R36/P36 | J37: ='3 - Il ponte'!$B$13*I37 | K37: =H37/(1-J37) | L37: =C37+K37 | M37: =$C$8 | N37: =(P36-L37)*(1+M37)*(1+'3 - Il ponte'!$B$8) | O37: =N37-P37 | P37: =N37/(1+'3 - Il ponte'!$B$16) | Q37: =L37+O37 | R37: =R36-K37*R36/P36 | S37: =P37/(1+'3 - Il ponte'!$B$8)^2
A38: 3 | B38: ='3 - Il ponte'!$B$7*(1+'3 - Il ponte'!$B$8)^(3-1) | C38: ='3 - Il ponte'!$E$32 | D38: =('3 - Il ponte'!$B$32+'3 - Il ponte'!$C$32)*'3 - Il ponte'!$B$14 | E38: =MAX(0,E37-'3 - Il ponte'!$D$31) | F38: =MAX(0,'3 - Il ponte'!$D$32-E38)*'3 - Il ponte'!$B$15 | G38: =C38-D38-F38 | H38: =B38-G38 | I38: =1-R37/P37 | J38: ='3 - Il ponte'!$B$13*I38 | K38: =H38/(1-J38) | L38: =C38+K38 | M38: =$C$9 | N38: =(P37-L38)*(1+M38)*(1+'3 - Il ponte'!$B$8) | O38: =N38-P38 | P38: =N38/(1+'3 - Il ponte'!$B$16) | Q38: =L38+O38 | R38: =R37-K38*R37/P37 | S38: =P38/(1+'3 - Il ponte'!$B$8)^3
A39: 4 | B39: ='3 - Il ponte'!$B$7*(1+'3 - Il ponte'!$B$8)^(4-1) | C39: ='3 - Il ponte'!$E$33 | D39: =('3 - Il ponte'!$B$33+'3 - Il ponte'!$C$33)*'3 - Il ponte'!$B$14 | E39: =MAX(0,E38-'3 - Il ponte'!$D$32) | F39: =MAX(0,'3 - Il ponte'!$D$33-E39)*'3 - Il ponte'!$B$15 | G39: =C39-D39-F39 | H39: =B39-G39 | I39: =1-R38/P38 | J39: ='3 - Il ponte'!$B$13*I39 | K39: =H39/(1-J39) | L39: =C39+K39 | M39: =$C$10 | N39: =(P38-L39)*(1+M39)*(1+'3 - Il ponte'!$B$8) | O39: =N39-P39 | P39: =N39/(1+'3 - Il ponte'!$B$16) | Q39: =L39+O39 | R39: =R38-K39*R38/P38 | S39: =P39/(1+'3 - Il ponte'!$B$8)^4
A40: 5 | B40: ='3 - Il ponte'!$B$7*(1+'3 - Il ponte'!$B$8)^(5-1) | C40: ='3 - Il ponte'!$E$34 | D40: =('3 - Il ponte'!$B$34+'3 - Il ponte'!$C$34)*'3 - Il ponte'!$B$14 | E40: =MAX(0,E39-'3 - Il ponte'!$D$33) | F40: =MAX(0,'3 - Il ponte'!$D$34-E40)*'3 - Il ponte'!$B$15 | G40: =C40-D40-F40 | H40: =B40-G40 | I40: =1-R39/P39 | J40: ='3 - Il ponte'!$B$13*I40 | K40: =H40/(1-J40) | L40: =C40+K40 | M40: =$C$11 | N40: =(P39-L40)*(1+M40)*(1+'3 - Il ponte'!$B$8) | O40: =N40-P40 | P40: =N40/(1+'3 - Il ponte'!$B$16) | Q40: =L40+O40 | R40: =R39-K40*R39/P39 | S40: =P40/(1+'3 - Il ponte'!$B$8)^5
A41: 6 | B41: ='3 - Il ponte'!$B$7*(1+'3 - Il ponte'!$B$8)^(6-1) | C41: ='3 - Il ponte'!$E$35 | D41: =('3 - Il ponte'!$B$35+'3 - Il ponte'!$C$35)*'3 - Il ponte'!$B$14 | E41: =MAX(0,E40-'3 - Il ponte'!$D$34) | F41: =MAX(0,'3 - Il ponte'!$D$35-E41)*'3 - Il ponte'!$B$15 | G41: =C41-D41-F41 | H41: =B41-G41 | I41: =1-R40/P40 | J41: ='3 - Il ponte'!$B$13*I41 | K41: =H41/(1-J41) | L41: =C41+K41 | M41: =$C$12 | N41: =(P40-L41)*(1+M41)*(1+'3 - Il ponte'!$B$8) | O41: =N41-P41 | P41: =N41/(1+'3 - Il ponte'!$B$16) | Q41: =L41+O41 | R41: =R40-K41*R40/P40 | S41: =P41/(1+'3 - Il ponte'!$B$8)^6
A42: 7 | B42: ='3 - Il ponte'!$B$7*(1+'3 - Il ponte'!$B$8)^(7-1) | C42: ='3 - Il ponte'!$E$36 | D42: =('3 - Il ponte'!$B$36+'3 - Il ponte'!$C$36)*'3 - Il ponte'!$B$14 | E42: =MAX(0,E41-'3 - Il ponte'!$D$35) | F42: =MAX(0,'3 - Il ponte'!$D$36-E42)*'3 - Il ponte'!$B$15 | G42: =C42-D42-F42 | H42: =B42-G42 | I42: =1-R41/P41 | J42: ='3 - Il ponte'!$B$13*I42 | K42: =H42/(1-J42) | L42: =C42+K42 | M42: =$C$13 | N42: =(P41-L42)*(1+M42)*(1+'3 - Il ponte'!$B$8) | O42: =N42-P42 | P42: =N42/(1+'3 - Il ponte'!$B$16) | Q42: =L42+O42 | R42: =R41-K42*R41/P41 | S42: =P42/(1+'3 - Il ponte'!$B$8)^7
A43: 8 | B43: ='3 - Il ponte'!$B$7*(1+'3 - Il ponte'!$B$8)^(8-1) | C43: ='3 - Il ponte'!$E$37 | D43: =('3 - Il ponte'!$B$37+'3 - Il ponte'!$C$37)*'3 - Il ponte'!$B$14 | E43: =MAX(0,E42-'3 - Il ponte'!$D$36) | F43: =MAX(0,'3 - Il ponte'!$D$37-E43)*'3 - Il ponte'!$B$15 | G43: =C43-D43-F43 | H43: =B43-G43 | I43: =1-R42/P42 | J43: ='3 - Il ponte'!$B$13*I43 | K43: =H43/(1-J43) | L43: =C43+K43 | M43: =$C$14 | N43: =(P42-L43)*(1+M43)*(1+'3 - Il ponte'!$B$8) | O43: =N43-P43 | P43: =N43/(1+'3 - Il ponte'!$B$16) | Q43: =L43+O43 | R43: =R42-K43*R42/P42 | S43: =P43/(1+'3 - Il ponte'!$B$8)^8
A44: 9 | B44: ='3 - Il ponte'!$B$7*(1+'3 - Il ponte'!$B$8)^(9-1) | C44: ='3 - Il ponte'!$E$38 | D44: =('3 - Il ponte'!$B$38+'3 - Il ponte'!$C$38)*'3 - Il ponte'!$B$14 | E44: =MAX(0,E43-'3 - Il ponte'!$D$37) | F44: =MAX(0,'3 - Il ponte'!$D$38-E44)*'3 - Il ponte'!$B$15 | G44: =C44-D44-F44 | H44: =B44-G44 | I44: =1-R43/P43 | J44: ='3 - Il ponte'!$B$13*I44 | K44: =H44/(1-J44) | L44: =C44+K44 | M44: =$C$15 | N44: =(P43-L44)*(1+M44)*(1+'3 - Il ponte'!$B$8) | O44: =N44-P44 | P44: =N44/(1+'3 - Il ponte'!$B$16) | Q44: =L44+O44 | R44: =R43-K44*R43/P43 | S44: =P44/(1+'3 - Il ponte'!$B$8)^9
A45: 10 | B45: ='3 - Il ponte'!$B$7*(1+'3 - Il ponte'!$B$8)^(10-1) | C45: ='3 - Il ponte'!$E$39 | D45: =('3 - Il ponte'!$B$39+'3 - Il ponte'!$C$39)*'3 - Il ponte'!$B$14 | E45: =MAX(0,E44-'3 - Il ponte'!$D$38) | F45: =MAX(0,'3 - Il ponte'!$D$39-E45)*'3 - Il ponte'!$B$15 | G45: =C45-D45-F45 | H45: =B45-G45 | I45: =1-R44/P44 | J45: ='3 - Il ponte'!$B$13*I45 | K45: =H45/(1-J45) | L45: =C45+K45 | M45: =$C$16 | N45: =(P44-L45)*(1+M45)*(1+'3 - Il ponte'!$B$8) | O45: =N45-P45 | P45: =N45/(1+'3 - Il ponte'!$B$16) | Q45: =L45+O45 | R45: =R44-K45*R44/P44 | S45: =P45/(1+'3 - Il ponte'!$B$8)^10
A48: IL COSTO DELL'ORDINE
A49: Capitale a 67 anni — crolli all'inizio | B49: =$S$31
A50: Capitale a 67 anni — crolli alla fine | B50: =$S$45
A51: QUANTO COSTA L'ORDINE, IN EURO DI OGGI | B51: =$B$50-$B$49
A52: A parita' assoluta di rendimento medio. Non e' una previsione ed e' l'unica cosa che davvero non controlli: e' il motivo per cui la domanda giusta non e' «quanto rende» ma «quanto sto prelevando, e su che orizzonte».
A53: Attenzione a come si legge: le cedole NON proteggono da questo. Quello che protegge e' avere flussi e scadenze certe davanti all'azionario — nel caso del video, 320.000 € che rimborsano alla pari nel 2032 — e il valore di quella protezione, secondo la letteratura sul decumulo, e' comportamentale prima che matematico.
