Workbook

Sheet 0-Indice
A1: Marco FIRE — Il numero vero del ritiro (caso Chiara, 2026)
A2: Strumento informativo / divulgativo. NON è consulenza finanziaria. I valori sono indicativi al 2026 e vanno verificati col tuo consulente.
A4: Indice
A5: 1-Input | B5: I 22 input del caso e i netti di coppia
A6: P-Parametri | B6: Parametri normativi: aliquote, coefficienti, soglie
A7: 2-Composizione | B7: Accumulo 2003-2026, evento 2019, plusvalenza latente
A8: 3-Rendimento | B8: Il 3,25% derivato e la banda 3,00 / 3,25 / 4,15
A9: 4-Montanti | B9: Montanti contributivi al 2026 e al ritiro
A10: 5-Pensioni | B10: Vecchiaia a 68a2m e via contributiva intorno ai 65
A11: 6-TFR | B11: Liquidazione di coppia, tassazione separata, salvaguardia
A12: 7-Fabbisogno | B12: Ponte, coda, waterfall del twist, curva del ×25
A13: 8-Patrimonio | B13: Traiettoria anno per anno e anno dei due milioni
A14: 9-Leve | B14: Le otto leve, ipotesi prudente e scenario centrale
A15: 10-Glide | B15: Glide path, costo atteso, anno peggiore, break-even
A16: 11-Banda | B16: Le quattordici righe della banda del fabbisogno
A17: 12-Verifica | B17: Il controllo annuale: quattro indicatori e semaforo
A19: Come usare
A20: 1. Le celle GIALLE sono input — modificale coi tuoi numeri.
A21: 2. Le celle VERDI sono output — si aggiornano automaticamente.
A22: 3. Tutti i numeri di default sono al 2026 da fonti pubbliche.
A23: 4. Niente codice nascosto: l'Excel è solo formule modificabili.
A25: Fonti dati
A26: • IRPEF 2026 (23% / 33% / 43%) — L. 199/2025; detrazioni art. 13 TUIR c. 3 e c. 3-bis
A27: • Coefficienti di trasformazione — DM 20/11/2024, biennio 2025-2026
A28: • Via contributiva intorno ai 65 anni — art. 24 c. 11 D.L. 201/2011, testo vigente; soglia di 3,2 volte l'assegno sociale in vigore dal 2030
A29: • Requisiti 2027-2028 e proiezione a 68 anni e 2 mesi per il 2039-2040 — L. 199/2025 art. 1 c. 185 e proiezioni RGS per coorte (proiezioni, non norme)
A30: • TFR: quota 1/13,5 e rivalutazione 1,5% + 75% ISTAT — art. 2120 c.c.; tassazione separata art. 19 TUIR
A31: • Clausola di salvaguardia con gli scaglioni 2006 — L. 296/2006, rinumerata nell'art. 21 c. 11 del D.Lgs. 117/2026 (GU n. 152 del 3/7/2026, S.O. 26/L)
... A36: Aggiornamenti: github.com/marcofire-it/marco-fire-simulatori

Sheet 1-Input
A1: I 22 input del caso
A2: Strumento informativo / divulgativo. NON è consulenza finanziaria. I valori sono indicativi al 2026 e vanno verificati col tuo consulente.
A4: INPUT — cambia una cella gialla e tutti i verdi si muovono
A5: (1) Nascita di Chiara — anno / mese | B5: 1972 | C5: 4
A6: (2) Nascita del marito — anno / mese | B6: 1971 | C6: 4
A7: (3) Retribuzione attuale di Chiara (lorda) | B7: 60000
A8: (4) Retribuzione attuale del marito (lorda) | B8: 48000
A9: (5) Media di carriera di Chiara (previdenziale) | B9: 34000
A10: (6) Chiara — anni di carriera al 2026 / densita' contributiva | B10: 30 | C10: 0.85
A11: (7) Media di carriera del marito (previdenziale) | B11: 30000
A12: (8) Marito — anni di carriera al 2026 / densita' contributiva | B12: 30 | C12: 1
A13: (9) Spesa netta di coppia (€/anno) | B13: 52000
A14: (10) Evento del 2019 — netto reinvestito (quota societaria ceduta) | B14: 280000
A15: (11) Anno dell'evento | B15: 2019
A16: (12) Accumulo — primo anno / anno di riferimento (oggi) | B16: 2003 | C16: 2026
A17: (13) Rendimento lordo atteso — menu 3,00% / 3,25% / 4,15% | B17: 0.0325
A18: (14) Bollo titoli | B18: 0.002
A19: (15) Anno di ritiro | B19: 2036
A20: (16) Orizzonte — eta' finale di Chiara: menu 92 / 95 / 97 | B20: 95
A21: (17) Crescita reale del montante — menu 0,0% / 0,6% / 1,2% | B21: 0.006
A22: (18) Requisito anagrafico — anni in piu': 0 / 1 / 2 | B22: 0
A23: (19) Anzianita' TFR al ritiro — Chiara / marito | B23: 18 | C23: 41
A24: (20) TFR lordo maturato al ritiro — Chiara / marito | B24: 80000 | C24: 124000
A25: (21) Retribuzione di riferimento TFR del marito / rivalutazione reale | B25: 34000 | C25: 0.0115
A26: (22) TFR: 1 = in cassa, 0 = conferito al fondo pensione | B26: 1
A27: Le tre grandezze del marito sono DIVERSE e restano distinte: retribuzione attuale 48.000, media di carriera previdenziale 30.000, retribuzione media di riferimento per il TFR 34.000. Sulla terza il foglio 6 mostra la banda del ±15%.
A28: CONVENZIONE 5 — l'input del motore e' il RISPARMIO ARROTONDATO all'euro (riga 40): l'arrotondamento sta all'ingresso del motore, non all'uscita.
A30: I NETTI DI COPPIA — IRPEF 2026, modulo completo
A31: Voce | B31: Chiara | C31: Marito
A32: Retribuzione lorda | B32: =B7 | C32: =B8
A33: Contributi a carico del lavoratore | B33: =B32*'P-Parametri'!$B$17 | C33: =C32*'P-Parametri'!$B$17
A34: Imponibile IRPEF | B34: =B32-B33 | C34: =C32-C33
A35: IRPEF lorda | B35: =IF(B34<='P-Parametri'!$B$6,'P-Parametri'!$C$6*B34,IF(B34<='P-Parametri'!$B$7,'P-Parametri'!$B$9+'P-Parametri'!$C$7*(B34-'P-Parametri'!$B$6),'P-Parametri'!$B$10+'P-Parametri'!$C$8*(B34-'P-Parametri'!$B$7))) | C35: =IF(C34<='P-Parametri'!$B$6,'P-Parametri'!$C$6*C34,IF(C34<='P-Parametri'!$B$7,'P-Parametri'!$B$9+'P-Parametri'!$C$7*(C34-'P-Parametri'!$B$6),'P-Parametri'!$B$10+'P-Parametri'!$C$8*(C34-'P-Parametri'!$B$7)))
A36: Detrazione da lavoro dipendente | B36: =IF(B34<=15000,1955,IF(B34<='P-Parametri'!$B$6,1910+1190*('P-Parametri'!$B$6-B34)/13000,IF(B34<='P-Parametri'!$B$7,'P-Parametri'!$B$16*('P-Parametri'!$B$7-B34)/'P-Parametri'!$C$16,0))) | C36: =IF(C34<=15000,1955,IF(C34<='P-Parametri'!$B$6,1910+1190*('P-Parametri'!$B$6-C34)/13000,IF(C34<='P-Parametri'!$B$7,'P-Parametri'!$B$16*('P-Parametri'!$B$7-C34)/'P-Parametri'!$C$16,0)))
A37: NETTO annuo (imponibile − imposta netta − addizionali) | B37: =B34-MAX(0,B35-B36)-IF(MAX(0,B35-B36)<=0,0,'P-Parametri'!$B$11*B34) | C37: =C34-MAX(0,C35-C36)-IF(MAX(0,C35-C36)<=0,0,'P-Parametri'!$B$11*C34)
A38: NETTO DI COPPIA | B38: =B37+C37
A39: Spesa netta di coppia | B39: =B13
A40: RISPARMIO ANNUO — input del motore, arrotondato (Convenzione 5) | B40: =ROUND(B38-B39,0)
A41: Risparmio in quota del netto | B41: =B40/B38
A42: Spesa contro i consumi ISTAT di coppia | B42: =B13/'P-Parametri'!$B$46
A44: DERIVATI DI CALENDARIO, DI TASSO E DI CARRIERA
A45: Anni di accumulo fino a oggi | B45: =C16-B16+1
A46: Rendimento netto bollo | B46: =B17-B18
A47: Anno di orizzonte (eta' finale di Chiara) | B47: =B5+B20
A48: Contributo annuo futuro — Chiara / marito | B48: =B7*'P-Parametri'!$B$19 | C48: =B8*'P-Parametri'!$B$19
A49: Anni contributivi al 2026 — Chiara / marito | B49: =B10*C10 | C49: =B12*C12
A50: Anni di contribuzione dopo il 2026 (base) | B50: =B19-C16
A51: Vecchiaia, Chiara — anno / mese di decorrenza | B51: =B5+'P-Parametri'!$B$56+INT((C5+'P-Parametri'!$C$56-1)/12) | C51: =MOD(C5+'P-Parametri'!$C$56-1,12)+1
A52: Vecchiaia, marito — anno / mese di decorrenza | B52: =B6+'P-Parametri'!$B$56+INT((C6+'P-Parametri'!$C$56-1)/12) | C52: =MOD(C6+'P-Parametri'!$C$56-1,12)+1
A53: Via contributiva, Chiara — anno / mese di decorrenza | B53: =B5+'P-Parametri'!$B$57+INT((C5+'P-Parametri'!$C$57-1)/12) | C53: =MOD(C5+'P-Parametri'!$C$57-1,12)+1
A54: Via contributiva, marito — anno / mese di decorrenza | B54: =B6+'P-Parametri'!$B$58+INT((C6+'P-Parametri'!$C$58-1)/12) | C54: =MOD(C6+'P-Parametri'!$C$58-1,12)+1
A55: Coefficiente della via contributiva — Chiara / marito (interpolato 65-66) | B55: ='P-Parametri'!$B$22+'P-Parametri'!$C$57/12*('P-Parametri'!$B$23-'P-Parametri'!$B$22) | C55: ='P-Parametri'!$B$22+'P-Parametri'!$C$58/12*('P-Parametri'!$B$23-'P-Parametri'!$B$22)
A56: Eta' di Chiara all'anno di ritiro | B56: =B19-B5

Sheet P-Parametri
A1: Parametri normativi e di fonte
A2: Strumento informativo / divulgativo. NON è consulenza finanziaria. I valori sono indicativi al 2026 e vanno verificati col tuo consulente.
A3: Le uniche costanti del modello, oltre agli input, stanno qui: aliquote, coefficienti, soglie, parametri di fonte. Tutti gli altri fogli le referenziano.
A5: IRPEF 2026 (L. 199/2025) e detrazioni
A6: Primo scaglione — limite / aliquota | B6: 28000 | C6: 0.23
A7: Secondo scaglione — limite / aliquota | B7: 50000 | C7: 0.33
A8: Terzo scaglione — aliquota oltre il secondo limite | C8: 0.43
A9: Imposta cumulata fino al primo scaglione | B9: =B6*C6
A10: Imposta cumulata fino al secondo scaglione | B10: =B9+(B7-B6)*C7
A11: Addizionali regionali e comunali | B11: 0.02
A12: Detrazione da pensione — importo massimo / soglia bassa | B12: 1955 | C12: 8500
A13: Detrazione da pensione 8.500-28.000 — base / incremento / ampiezza | B13: 700 | C13: 1255 | D13: 19500
A14: Detrazione da pensione 28.000-50.000 — base / ampiezza | B14: 700 | C14: 22000
A15: Detrazione art. 13 comma 3-bis — importo / da / a | B15: 50 | C15: 25000 | D15: 29000
A16: Detrazione da lavoro dipendente 28.000-50.000 — base / ampiezza | B16: 1910 | C16: 22000
A17: Contributi a carico del lavoratore | B17: 0.0919
A18: Previdenza obbligatoria
A19: Aliquota di computo (dipendenti) | B19: 0.33
A20: Mensilita' della pensione | B20: 13
A21: Coefficiente di trasformazione — 68 anni e 2 mesi | B21: 0.05844
A22: Coefficiente di trasformazione — 65 anni | B22: 0.0525
A23: Coefficiente di trasformazione — 66 anni | B23: 0.05423
A24: Coefficiente di trasformazione — 70 anni e 2 mesi (controprova) | B24: 0.063
A25: Soglia di 3,2 volte l'assegno sociale (€/mese) | B25: 1747.97
A26: Cap di 5 volte il trattamento minimo (€/mese) | B26: 3059.25
A27: Soglia di importo minima (€/mese) | B27: 546.24
A28: Fattore di rivalutazione cumulata del montante al 2026 | B28: 1.020765
A29: Anni minimi di contribuzione | B29: 20
A30: Fiscalita' finanziaria
A31: Capital gain | B31: 0.26
A32: Titoli di Stato ed equiparati | B32: 0.125
A33: TFR
A34: Quota annua accantonata — divisore | B34: 13.5
A35: Ritenuta sul TFR conferito al fondo — iniziale / a regime | B35: 0.15 | C35: 0.09
A36: Clausola di salvaguardia — scaglioni 2006
A37: Primo scaglione — limite / aliquota | B37: 26000 | C37: 0.23
A38: Secondo scaglione — limite / aliquota | B38: 33500 | C38: 0.33
A39: Terzo scaglione — limite / aliquota | B39: 100000 | C39: 0.39
A40: Oltre — aliquota | C40: 0.43
A41: Rendimenti attesi — le due nature restano dichiarate separatamente
A42: Forward-looking, Yearbook 2023 Fig. 52 — azioni / obbligazioni | B42: 0.04 | C42: 0.015
A43: Reale storico 1900-2024, Yearbook 2025 — azioni / obbligazioni | B43: 0.052 | C43: 0.017
A44: Riferimenti del caso e convenzioni dichiarate
A45: Montante di Chiara, banda O11 — minimo / massimo | B45: 283014 | C45: 299000
A46: Consumi ISTAT di coppia (€/anno) | B46: 34272
A47: Target dichiarato da Chiara | B47: 2000000
A48: Prelievo perpetuo di riferimento | B48: 0.025
A49: Spesa dell'esempio a 35 anni (video numero_fire_personale) | B49: 30000
A50: Esempio a 35 anni — eta' finale / eta' iniziale | B50: 95 | C50: 35
A51: Taglio delle pensioni nello scenario cauto | B51: 0.2
A52: Sequenza sfavorevole — crollo azionario penultimo / ultimo anno | B52: -0.35 | C52: -0.2
A53: Anno peggiore — crollo azionario | B53: -0.4
A54: Quota azionaria attuale del portafoglio | B54: 0.7
A55: Glide path — quota azionaria finale | B55: 0.4
A56: Eta' di decorrenza della vecchiaia — anni / mesi | B56: 68 | C56: 2
A57: Via contributiva, Chiara — anni / mesi alla decorrenza | B57: 65 | C57: 3
A58: Via contributiva, marito — anni / mesi alla decorrenza | B58: 65 | C58: 9
A59: Frazione della prima annualita' (decorrenza non di gennaio) | B59: 0.5
A60: Leva sui costi — riduzione del costo annuo | B60: 0.005
A61: Leva sulla spesa — riduzione | B61: 0.1
A62: Leva sul risparmio — incremento annuo | B62: 3000
A63: Leva sull'allocazione — quota azionaria alternativa | B63: 0.85
A64: Glide — rendimento lordo del portafoglio post-ritiro (40/60) | B64: 0.025
A65: Orizzonte — eta' bassa / eta' alta della banda | B65: 92 | C65: 97
A66: Sensibilita' della spesa nella banda (±) | B66: 5000
A68: REFRESH GENNAIO 2027 — OBBLIGATORIO. I coefficienti di trasformazione di questo foglio sono quelli del DM 20/11/2024, validi per il biennio 2025-2026, e qui vengono applicati a decorrenze del 2037-2042: vanno rifatti alla pubblicazione del decreto successivo.
A69: I 68 anni e 2 mesi della vecchiaia e il requisito della via contributiva intorno ai 65 anni sono PROIEZIONI della Ragioneria generale dello Stato per coorte, non norme in vigore: requisiti e soglie sono quelli di oggi, adeguamenti futuri sono possibili.
A70: La soglia di 3,2 volte l'assegno sociale e' in vigore dal 2030 (penultimo periodo dell'art. 24 c. 11 del D.L. 201/2011: la L. 199/2025 ha soppresso soltanto l'ultimo periodo).
A71: I coefficienti a 65 e 66 anni (5,250% e 5,423%) sono letti su rassegne del DM 20/11/2024, che e' fonte secondaria: convergono con l'estrapolazione della serie e con la somma di controllo sui tre incrementi, ma vanno riconfermati sul testo del decreto prima del go-live.
A72: Il comma 3-bis rinvia al comma 3 nel suo insieme: i 50 € si applicano anche sotto i 28.000 €. Le addizionali NON sono dovute quando l'IRPEF netta e' zero: il modulo lo implementa ovunque.

Sheet 2-Composizione
A1: Composizione del patrimonio e plusvalenza latente
A2: Strumento informativo / divulgativo. NON è consulenza finanziaria. I valori sono indicativi al 2026 e vanno verificati col tuo consulente.
A4: ACCUMULO ANNO PER ANNO — la latente e' DERIVATA, non postulata
A5: Anno | B5: Versamento | C5: Evento | D5: Montante a fine anno | E5: Base di costo cumulata
A6: ='1-Input'!$B$16 | B6: =IF(A6>'1-Input'!$C$16,0,'1-Input'!$B$40) | C6: =IF(A6='1-Input'!$B$15,'1-Input'!$B$14,0) | D6: =(B6)*(1+'1-Input'!$B$46)+C6 | E6: =B6+C6
A7: =A6+1 | B7: =IF(A7>'1-Input'!$C$16,0,'1-Input'!$B$40) | C7: =IF(A7='1-Input'!$B$15,'1-Input'!$B$14,0) | D7: =(D6+B7)*(1+'1-Input'!$B$46)+C7 | E7: =E6+B7+C7
A8: =A7+1 | B8: =IF(A8>'1-Input'!$C$16,0,'1-Input'!$B$40) | C8: =IF(A8='1-Input'!$B$15,'1-Input'!$B$14,0) | D8: =(D7+B8)*(1+'1-Input'!$B$46)+C8 | E8: =E7+B8+C8
A9: =A8+1 | B9: =IF(A9>'1-Input'!$C$16,0,'1-Input'!$B$40) | C9: =IF(A9='1-Input'!$B$15,'1-Input'!$B$14,0) | D9: =(D8+B9)*(1+'1-Input'!$B$46)+C9 | E9: =E8+B9+C9
A10: =A9+1 | B10: =IF(A10>'1-Input'!$C$16,0,'1-Input'!$B$40) | C10: =IF(A10='1-Input'!$B$15,'1-Input'!$B$14,0) | D10: =(D9+B10)*(1+'1-Input'!$B$46)+C10 | E10: =E9+B10+C10
A11: =A10+1 | B11: =IF(A11>'1-Input'!$C$16,0,'1-Input'!$B$40) | C11: =IF(A11='1-Input'!$B$15,'1-Input'!$B$14,0) | D11: =(D10+B11)*(1+'1-Input'!$B$46)+C11 | E11: =E10+B11+C11
A12: =A11+1 | B12: =IF(A12>'1-Input'!$C$16,0,'1-Input'!$B$40) | C12: =IF(A12='1-Input'!$B$15,'1-Input'!$B$14,0) | D12: =(D11+B12)*(1+'1-Input'!$B$46)+C12 | E12: =E11+B12+C12
A13: =A12+1 | B13: =IF(A13>'1-Input'!$C$16,0,'1-Input'!$B$40) | C13: =IF(A13='1-Input'!$B$15,'1-Input'!$B$14,0) | D13: =(D12+B13)*(1+'1-Input'!$B$46)+C13 | E13: =E12+B13+C13
A14: =A13+1 | B14: =IF(A14>'1-Input'!$C$16,0,'1-Input'!$B$40) | C14: =IF(A14='1-Input'!$B$15,'1-Input'!$B$14,0) | D14: =(D13+B14)*(1+'1-Input'!$B$46)+C14 | E14: =E13+B14+C14
A15: =A14+1 | B15: =IF(A15>'1-Input'!$C$16,0,'1-Input'!$B$40) | C15: =IF(A15='1-Input'!$B$15,'1-Input'!$B$14,0) | D15: =(D14+B15)*(1+'1-Input'!$B$46)+C15 | E15: =E14+B15+C15
A16: =A15+1 | B16: =IF(A16>'1-Input'!$C$16,0,'1-Input'!$B$40) | C16: =IF(A16='1-Input'!$B$15,'1-Input'!$B$14,0) | D16: =(D15+B16)*(1+'1-Input'!$B$46)+C16 | E16: =E15+B16+C16
A17: =A16+1 | B17: =IF(A17>'1-Input'!$C$16,0,'1-Input'!$B$40) | C17: =IF(A17='1-Input'!$B$15,'1-Input'!$B$14,0) | D17: =(D16+B17)*(1+'1-Input'!$B$46)+C17 | E17: =E16+B17+C17
A18: =A17+1 | B18: =IF(A18>'1-Input'!$C$16,0,'1-Input'!$B$40) | C18: =IF(A18='1-Input'!$B$15,'1-Input'!$B$14,0) | D18: =(D17+B18)*(1+'1-Input'!$B$46)+C18 | E18: =E17+B18+C18
... A29: =A28+1 | B29: =IF(A29>'1-Input'!$C$16,0,'1-Input'!$B$40) | C29: =IF(A29='1-Input'!$B$15,'1-Input'!$B$14,0) | D29: =(D28+B29)*(1+'1-Input'!$B$46)+C29 | E29: =E28+B29+C29
A31: IL PATRIMONIO DI OGGI
A32: Componente da accumulo (24 versamenti reali costanti) | B32: =D29-B33
A33: Componente dall'evento del 2019, capitalizzata | B33: ='1-Input'!$B$14*(1+'1-Input'!$B$46)^('1-Input'!$C$16-'1-Input'!$B$15)
A34: Base di costo dell'accumulo | B34: ='1-Input'!$B$45*'1-Input'!$B$40
A35: Base di costo dell'evento | B35: ='1-Input'!$B$14
A36: PATRIMONIO FINANZIARIO al 2026 | B36: =D29
A37: Base di costo totale | B37: =E29
A38: PLUSVALENZA LATENTE (con il floor a zero) | B38: =MAX(0,(B36-B37)/B36)
A39: Fattore di lordizzazione G(2026) = 1 / (1 − capital gain × latente) | B39: =1/(1-'P-Parametri'!$B$31*B38)
A41: LA SOGLIA IN CUI IL CAPITALE DIVENTA IL MOTORE
A42: Soglia K* = versamento annuo / rendimento netto | B42: ='1-Input'!$B$40/'1-Input'!$B$46
A43: Multiplo del versamento annuo | B43: =1/'1-Input'!$B$46
A44: Anno in cui la soglia e' stata superata | B44: =INDEX($A$6:$A$29,MATCH(B42,$D$6:$D$29,1)+1)
A45: Capitale a fine dell'anno precedente | B45: =INDEX($D$6:$D$29,MATCH(B42,$D$6:$D$29,1))
A46: Capitale a fine dell'anno di superamento | B46: =INDEX($D$6:$D$29,MATCH(B42,$D$6:$D$29,1)+1)
A47: Crescita attesa del primo anno (patrimonio × rendimento lordo) | B47: =B36*'1-Input'!$B$17
A48: Rapporto fra crescita attesa e versamenti annui | B48: =B47/'1-Input'!$B$40
A50: LA LATENTE E' DERIVATA. Cambiando la spesa cambia il risparmio, quindi l'accumulo, quindi il patrimonio e la base di costo: la plusvalenza latente esce dalla catena e non e' un parametro postulato. Il floor a zero e' dichiarato: una latente negativa non ha significato fiscale qui, e il fattore di lordizzazione non puo' scendere sotto 1.
A51: Convenzione dichiarata: i versamenti entrano a inizio anno e capitalizzano per l'anno intero; l'evento del 2019 entra a fine anno e capitalizza dall'anno successivo. Il rendimento e' quello NETTO BOLLO (rendimento lordo − 0,20%).
A52: Cautela sul caso: 17.457 € reali costanti per ventiquattro anni significa che nei primi anni lo sforzo di risparmio era molto piu' pesante di oggi.

Sheet 3-Rendimento
A1: Il rendimento derivato e la banda
A2: Strumento informativo / divulgativo. NON è consulenza finanziaria. I valori sono indicativi al 2026 e vanno verificati col tuo consulente.
A4: r(w) = rendimento delle azioni × w + rendimento delle obbligazioni × (1 − w)
A5: Quota azionaria del portafoglio | B5: ='P-Parametri'!$B$54
A6: Rendimento atteso delle azioni (forward-looking, Fig. 52) | B6: ='P-Parametri'!$B$42
A7: Rendimento atteso delle obbligazioni (forward-looking, Fig. 52) | B7: ='P-Parametri'!$C$42
A8: RENDIMENTO LORDO DERIVATO sul 70/30 | B8: =B6*B5+B7*(1-B5)
A9: Verifica sul 60/40 del canale (il pavimento della banda) | B9: =B6*0.6+B7*0.4
A10: Bollo titoli | B10: ='1-Input'!$B$18
A11: RENDIMENTO NETTO BOLLO usato dal motore | B11: ='1-Input'!$B$17-'1-Input'!$B$18
A13: LA BANDA — ogni estremo con la sua edizione dichiarata
A14: Estremo | B14: Quota azionaria | C14: Rendimento lordo | D14: Rendimento netto bollo | E14: Edizione dichiarata
A15: Pavimento — 60/40 forward-looking | B15: =0.6 | C15: =B6*0.6+B7*0.4 | D15: =C15-'1-Input'!$B$18 | E15: Yearbook 2023, Fig. 52 — prospettico
A16: Centro — 70/30 forward-looking | B16: =B5 | C16: =B8 | D16: =C16-'1-Input'!$B$18 | E16: Yearbook 2023, Fig. 52 — prospettico
A17: Tetto — 70/30 sul reale storico 1900-2024 | B17: =B5 | C17: ='P-Parametri'!$B$43*B5+'P-Parametri'!$C$43*(1-B5) | D17: =C17-'1-Input'!$B$18 | E17: Yearbook 2025, storico 1900-2024
A19: Centro e pavimento sono FORWARD-LOOKING (Yearbook 2023, cap. 5, Fig. 52 «World in the future»); il tetto e' STORICO (reale 1900-2024, Yearbook 2025). Le due nature sono diverse e metterle nella stessa banda e' una scelta del canale, non della fonte: qui e' dichiarata riga per riga.
A20: Tranello evitato: lo 0,9% del summary 2025 e' la media semplice dei ventuno paesi, non l'indice mondiale, e non entra in questa banda.
A21: Il 3,25% e' una stima prospettica, non una previsione. Il canone del canale resta il 3% reale: questo caso usa il 3,25% derivato dall'allocazione dichiarata, con il 3,00% come pavimento.

Sheet 4-Montanti
A1: Montanti contributivi
A2: Strumento informativo / divulgativo. NON è consulenza finanziaria. I valori sono indicativi al 2026 e vanno verificati col tuo consulente.
A4: IL MONTANTE DI OGGI (2026)
A5: Voce | B5: Chiara | C5: Marito
A6: Anni contributivi al 2026 (anni di carriera × densita') | B6: ='1-Input'!$B$49 | C6: ='1-Input'!$C$49
A7: Contributo annuo medio (aliquota di computo × media di carriera) | B7: ='1-Input'!$B$9*'P-Parametri'!$B$19 | C7: ='1-Input'!$B$11*'P-Parametri'!$B$19
A8: Fattore di rivalutazione cumulata al 2026 | B8: ='P-Parametri'!$B$28 | C8: ='P-Parametri'!$B$28
A9: MONTANTE CONTRIBUTIVO AL 2026 | B9: =B6*B7*B8 | C9: =C6*C7*C8
A10: Banda del montante di Chiara — minimo (buchi all'inizio) / massimo | B10: ='P-Parametri'!$B$45 | C10: ='P-Parametri'!$C$45
A11: Semaforo: almeno 20 anni di contribuzione? | B11: =IF(B6>='P-Parametri'!$B$29,"SI","NO") | C11: =IF(C6>='P-Parametri'!$B$29,"SI","NO")
A13: IL MONTANTE AL RITIRO
A14: Contributo annuo futuro (aliquota × retribuzione attuale) | B14: ='1-Input'!$B$48 | C14: ='1-Input'!$C$48
A15: Anni di contribuzione dopo il 2026 | B15: ='1-Input'!$B$50 | C15: ='1-Input'!$B$50
A16: Fattore di rivalutazione dello stock (1 + g) elevato agli anni | B16: =(1+'1-Input'!$B$21)^B15 | C16: =(1+'1-Input'!$B$21)^C15
A17: Fattore di accumulo dei contributi futuri | B17: =IF('1-Input'!$B$21=0,B15,((1+'1-Input'!$B$21)^B15-1)/'1-Input'!$B$21) | C17: =IF('1-Input'!$B$21=0,C15,((1+'1-Input'!$B$21)^C15-1)/'1-Input'!$B$21)
A18: MONTANTE AL RITIRO (fine dell'anno di ritiro) | B18: =B9*B16+B14*B17 | C18: =C9*C16+C14*C17
A20: CONVENZIONE — ac + ar e' una COSTANTE. La distanza fra oggi e la decorrenza dipende dall'eta', non dalla data in cui si smette di lavorare: lavorare uno o due anni in piu' sposta anni dalla sola rivalutazione alla contribuzione, non li aggiunge. Il motore lo implementa nei fogli 5, 9 e 11.
A21: Il fattore di rivalutazione cumulata al 2026 (1,020765) sintetizza la serie storica del PIL nominale quinquennale. La ricostruzione anno per anno sulla serie INPS 707/2026 e' un refresh dichiarato: la direzione dell'errore e' ignota, l'ampiezza e' misurata (±3% sul montante di Chiara vale circa ±13.000 € sul fabbisogno).
A22: La densita' contributiva di Chiara (85%) e' un'ipotesi centrale con i buchi distribuiti in modo uniforme. La banda della riga 10 mostra gli estremi: buchi all'inizio (montante piu' basso) e buchi alla fine (montante piu' alto).

Sheet 5-Pensioni
A1: Le due pensioni
A2: Strumento informativo / divulgativo. NON è consulenza finanziaria. I valori sono indicativi al 2026 e vanno verificati col tuo consulente.
A4: SCENARIO A — vecchiaia a 68 anni e 2 mesi (proiezione RGS)
A5: Voce | B5: Chiara | C5: Marito
A6: Montante contributivo al 2026 | B6: ='4-Montanti'!$B$9 | C6: ='4-Montanti'!$C$9
A7: Anni di contribuzione dopo il 2026 | B7: ='1-Input'!$B$50 | C7: ='1-Input'!$B$50
A8: Anno di decorrenza (requisito anagrafico incluso) | B8: ='1-Input'!$B$51+'1-Input'!$B$22 | C8: ='1-Input'!$B$52+'1-Input'!$B$22
A9: Mese di decorrenza | B9: ='1-Input'!$C$51 | C9: ='1-Input'!$C$52
A10: Anni di sola rivalutazione fino alla decorrenza (ar) | B10: =B8-('1-Input'!$C$16+1)+(B9-1)/12-B7 | C10: =C8-('1-Input'!$C$16+1)+(C9-1)/12-C7
A11: Montante alla decorrenza | B11: =(B6*(1+'1-Input'!$B$21)^B7+'1-Input'!$B$48*(IF('1-Input'!$B$21=0,B7,((1+'1-Input'!$B$21)^B7-1)/'1-Input'!$B$21)))*(1+'1-Input'!$B$21)^B10 | C11: =(C6*(1+'1-Input'!$B$21)^C7+'1-Input'!$C$48*(IF('1-Input'!$B$21=0,C7,((1+'1-Input'!$B$21)^C7-1)/'1-Input'!$B$21)))*(1+'1-Input'!$B$21)^C10
A12: Coefficiente di trasformazione | B12: ='P-Parametri'!$B$21 | C12: ='P-Parametri'!$B$21
A13: PENSIONE LORDA annua | B13: =B11*B12 | C13: =C11*C12
A14: Pensione lorda mensile | B14: =B13/'P-Parametri'!$B$20 | C14: =C13/'P-Parametri'!$B$20
A15: IRPEF lorda | B15: =IF(B13<='P-Parametri'!$B$6,'P-Parametri'!$C$6*B13,IF(B13<='P-Parametri'!$B$7,'P-Parametri'!$B$9+'P-Parametri'!$C$7*(B13-'P-Parametri'!$B$6),'P-Parametri'!$B$10+'P-Parametri'!$C$8*(B13-'P-Parametri'!$B$7))) | C15: =IF(C13<='P-Parametri'!$B$6,'P-Parametri'!$C$6*C13,IF(C13<='P-Parametri'!$B$7,'P-Parametri'!$B$9+'P-Parametri'!$C$7*(C13-'P-Parametri'!$B$6),'P-Parametri'!$B$10+'P-Parametri'!$C$8*(C13-'P-Parametri'!$B$7)))
A16: Detrazione da pensione (art. 13 c. 3 + comma 3-bis) | B16: =IF(B13<='P-Parametri'!$C$12,'P-Parametri'!$B$12,IF(B13<='P-Parametri'!$B$6,'P-Parametri'!$B$13+'P-Parametri'!$C$13*('P-Parametri'!$B$6-B13)/'P-Parametri'!$D$13,IF(B13<='P-Parametri'!$B$7,'P-Parametri'!$B$14*('P-Parametri'!$B$7-B13)/'P-Parametri'!$C$14,0)))+IF(AND(B13>'P-Parametri'!$C$15,B13<'P-Parametri'!$D$15),'P-Parametri'!$B$15,0) | C16: =IF(C13<='P-Parametri'!$C$12,'P-Parametri'!$B$12,IF(C13<='P-Parametri'!$B$6,'P-Parametri'!$B$13+'P-Parametri'!$C$13*('P-Parametri'!$B$6-C13)/'P-Parametri'!$D$13,IF(C13<='P-Parametri'!$B$7,'P-Parametri'!$B$14*('P-Parametri'!$B$7-C13)/'P-Parametri'!$C$14,0)))+IF(AND(C13>'P-Parametri'!$C$15,C13<'P-Parametri'!$D$15),'P-Parametri'!$B$15,0)
A17: Addizionali (non dovute se l'IRPEF netta e' zero) | B17: =IF(MAX(0,B15-B16)<=0,0,'P-Parametri'!$B$11*B13) | C17: =IF(MAX(0,C15-C16)<=0,0,'P-Parametri'!$B$11*C13)
A18: PENSIONE NETTA annua | B18: =B13-MAX(0,B15-B16)-B17 | C18: =C13-MAX(0,C15-C16)-C17
A19: Frazione della prima annualita' (mezza se la decorrenza non e' di gennaio) | B19: =IF(B9=1,1,'P-Parametri'!$B$59) | C19: =IF(C9=1,1,'P-Parametri'!$B$59)
A20: PENSIONI NETTE DI COPPIA (a regime) | B20: =B18+C18
A21: Copertura della spesa di coppia | B21: =B20/'1-Input'!$B$13
A22: Gap di coda (spesa − pensioni) | B22: ='1-Input'!$B$13-B20
A24: SCENARIO B — la via contributiva intorno ai 65 anni (art. 24 c. 11)
A25: Voce | B25: Chiara | C25: Marito
A26: Anno di decorrenza | B26: ='1-Input'!$B$53 | C26: ='1-Input'!$B$54
A27: Mese di decorrenza | B27: ='1-Input'!$C$53 | C27: ='1-Input'!$C$54
A28: Coefficiente interpolato fra 65 e 66 anni | B28: ='1-Input'!$B$55 | C28: ='1-Input'!$C$55
A29: Anni di sola rivalutazione fino alla decorrenza | B29: =B26-('1-Input'!$C$16+1)+(B27-1)/12-B7 | C29: =C26-('1-Input'!$C$16+1)+(C27-1)/12-C7
A30: Montante alla decorrenza | B30: =(B6*(1+'1-Input'!$B$21)^B7+'1-Input'!$B$48*(IF('1-Input'!$B$21=0,B7,((1+'1-Input'!$B$21)^B7-1)/'1-Input'!$B$21)))*(1+'1-Input'!$B$21)^B29 | C30: =(C6*(1+'1-Input'!$B$21)^C7+'1-Input'!$C$48*(IF('1-Input'!$B$21=0,C7,((1+'1-Input'!$B$21)^C7-1)/'1-Input'!$B$21)))*(1+'1-Input'!$B$21)^C29
A31: PENSIONE LORDA annua | B31: =B30*B28 | C31: =C30*C28
A32: Pensione lorda mensile | B32: =B31/'P-Parametri'!$B$20 | C32: =C31/'P-Parametri'!$B$20
A33: Soglia di 3,2 volte l'assegno sociale (€/mese) | B33: ='P-Parametri'!$B$25 | C33: ='P-Parametri'!$B$25
A34: Verifica di soglia: l'importo e' sopra? | B34: =IF(B32>=B33,"SI","NO") | C34: =IF(C32>=C33,"SI","NO")
A35: Margine sopra la soglia | B35: =B32/B33-1 | C35: =C32/C33-1
A36: Cap di 5 volte il trattamento minimo — l'importo resta sotto? | B36: =IF(B32<='P-Parametri'!$B$26,"SI","NO") | C36: =IF(C32<='P-Parametri'!$B$26,"SI","NO")
A37: IRPEF lorda | B37: =IF(B31<='P-Parametri'!$B$6,'P-Parametri'!$C$6*B31,IF(B31<='P-Parametri'!$B$7,'P-Parametri'!$B$9+'P-Parametri'!$C$7*(B31-'P-Parametri'!$B$6),'P-Parametri'!$B$10+'P-Parametri'!$C$8*(B31-'P-Parametri'!$B$7))) | C37: =IF(C31<='P-Parametri'!$B$6,'P-Parametri'!$C$6*C31,IF(C31<='P-Parametri'!$B$7,'P-Parametri'!$B$9+'P-Parametri'!$C$7*(C31-'P-Parametri'!$B$6),'P-Parametri'!$B$10+'P-Parametri'!$C$8*(C31-'P-Parametri'!$B$7)))
A38: Detrazione da pensione (art. 13 c. 3 + comma 3-bis) | B38: =IF(B31<='P-Parametri'!$C$12,'P-Parametri'!$B$12,IF(B31<='P-Parametri'!$B$6,'P-Parametri'!$B$13+'P-Parametri'!$C$13*('P-Parametri'!$B$6-B31)/'P-Parametri'!$D$13,IF(B31<='P-Parametri'!$B$7,'P-Parametri'!$B$14*('P-Parametri'!$B$7-B31)/'P-Parametri'!$C$14,0)))+IF(AND(B31>'P-Parametri'!$C$15,B31<'P-Parametri'!$D$15),'P-Parametri'!$B$15,0) | C38: =IF(C31<='P-Parametri'!$C$12,'P-Parametri'!$B$12,IF(C31<='P-Parametri'!$B$6,'P-Parametri'!$B$13+'P-Parametri'!$C$13*('P-Parametri'!$B$6-C31)/'P-Parametri'!$D$13,IF(C31<='P-Parametri'!$B$7,'P-Parametri'!$B$14*('P-Parametri'!$B$7-C31)/'P-Parametri'!$C$14,0)))+IF(AND(C31>'P-Parametri'!$C$15,C31<'P-Parametri'!$D$15),'P-Parametri'!$B$15,0)
A39: Addizionali | B39: =IF(MAX(0,B37-B38)<=0,0,'P-Parametri'!$B$11*B31) | C39: =IF(MAX(0,C37-C38)<=0,0,'P-Parametri'!$B$11*C31)
A40: PENSIONE NETTA annua | B40: =B31-MAX(0,B37-B38)-B39 | C40: =C31-MAX(0,C37-C38)-C39
A41: Frazione della prima annualita' | B41: =IF(B27=1,1,'P-Parametri'!$B$59) | C41: =IF(C27=1,1,'P-Parametri'!$B$59)
A42: PENSIONI NETTE DI COPPIA (a regime) | B42: =B40+C40
A43: Copertura della spesa di coppia | B43: =B42/'1-Input'!$B$13
A45: LE PENSIONI FERMANDOSI OGGI — servono alla curva del ×25 e alla leva del tempo
A46: Voce | B46: Chiara | C46: Marito
A47: Montante al 2026, congelato | B47: ='4-Montanti'!$B$9 | C47: ='4-Montanti'!$C$9
A48: Anni di sola rivalutazione fino alla decorrenza | B48: =B8-('1-Input'!$C$16+1)+(B9-1)/12 | C48: =C8-('1-Input'!$C$16+1)+(C9-1)/12
A49: Montante alla decorrenza | B49: =B47*(1+'1-Input'!$B$21)^B48 | C49: =C47*(1+'1-Input'!$B$21)^C48
A50: PENSIONE LORDA annua | B50: =B49*B12 | C50: =C49*C12
A51: IRPEF lorda | B51: =IF(B50<='P-Parametri'!$B$6,'P-Parametri'!$C$6*B50,IF(B50<='P-Parametri'!$B$7,'P-Parametri'!$B$9+'P-Parametri'!$C$7*(B50-'P-Parametri'!$B$6),'P-Parametri'!$B$10+'P-Parametri'!$C$8*(B50-'P-Parametri'!$B$7))) | C51: =IF(C50<='P-Parametri'!$B$6,'P-Parametri'!$C$6*C50,IF(C50<='P-Parametri'!$B$7,'P-Parametri'!$B$9+'P-Parametri'!$C$7*(C50-'P-Parametri'!$B$6),'P-Parametri'!$B$10+'P-Parametri'!$C$8*(C50-'P-Parametri'!$B$7)))
A52: Detrazione da pensione | B52: =IF(B50<='P-Parametri'!$C$12,'P-Parametri'!$B$12,IF(B50<='P-Parametri'!$B$6,'P-Parametri'!$B$13+'P-Parametri'!$C$13*('P-Parametri'!$B$6-B50)/'P-Parametri'!$D$13,IF(B50<='P-Parametri'!$B$7,'P-Parametri'!$B$14*('P-Parametri'!$B$7-B50)/'P-Parametri'!$C$14,0)))+IF(AND(B50>'P-Parametri'!$C$15,B50<'P-Parametri'!$D$15),'P-Parametri'!$B$15,0) | C52: =IF(C50<='P-Parametri'!$C$12,'P-Parametri'!$B$12,IF(C50<='P-Parametri'!$B$6,'P-Parametri'!$B$13+'P-Parametri'!$C$13*('P-Parametri'!$B$6-C50)/'P-Parametri'!$D$13,IF(C50<='P-Parametri'!$B$7,'P-Parametri'!$B$14*('P-Parametri'!$B$7-C50)/'P-Parametri'!$C$14,0)))+IF(AND(C50>'P-Parametri'!$C$15,C50<'P-Parametri'!$D$15),'P-Parametri'!$B$15,0)
A53: Addizionali | B53: =IF(MAX(0,B51-B52)<=0,0,'P-Parametri'!$B$11*B50) | C53: =IF(MAX(0,C51-C52)<=0,0,'P-Parametri'!$B$11*C50)
A54: PENSIONE NETTA annua | B54: =B50-MAX(0,B51-B52)-B53 | C54: =C50-MAX(0,C51-C52)-C53
A55: PENSIONI DI COPPIA fermandosi oggi | B55: =B54+C54
A56: Quanto valgono i dieci anni di lavoro che restano (netti l'anno, a vita) | B56: =B20-B55
A58: REFRESH GENNAIO 2027 — i coefficienti di trasformazione sono quelli del DM 20/11/2024, validi per il biennio 2025-2026, e qui girano su decorrenze del 2037-2042. Vanno rifatti quando esce il decreto successivo. Il foglio 5 deve leggere i coefficienti a 65 e 66 anni sul TESTO del decreto prima del go-live: la fonte e' chiusa su tre controlli convergenti, ma il decreto e' il decreto.
A59: I 68 anni e 2 mesi della vecchiaia e il requisito della via contributiva sono PROIEZIONI della Ragioneria generale dello Stato, non norme: fra i 67 anni e 3 mesi del 2028 e i 68 anni e 2 mesi proiettati per il 2039-2040 corrono undici mesi in undici anni. Requisiti e soglie di oggi, adeguamenti futuri possibili.
A60: La soglia di 3,2 volte l'assegno sociale e' quella in vigore dal 2030 (penultimo periodo dell'art. 24 c. 11: la L. 199/2025 ha soppresso soltanto l'ultimo periodo). La verifica di soglia va rifatta anche al minimo della banda del montante di Chiara.
A61: CONVENZIONE 2 — quando la decorrenza slitta per un adeguamento del requisito, il montante cresce della rivalutazione dello 0,6% reale l'anno ma il COEFFICIENTE resta fermo. E' una convenzione CONSERVATIVA e va dichiarata come tale: col coefficiente vero dell'eta' di decorrenza (70 anni e 2 mesi = 6,3000%) la riga «requisito +2 anni» della banda scenderebbe a circa 163.500 € e il peso del requisito nella banda si ridurrebbe di circa il 60%.
A62: Le addizionali non sono dovute quando l'IRPEF netta e' zero; il comma 3-bis si applica al comma 3 nel suo insieme, quindi anche sotto i 28.000 € di reddito.

Sheet 6-TFR
A1: Il TFR di coppia
A2: Strumento informativo / divulgativo. NON è consulenza finanziaria. I valori sono indicativi al 2026 e vanno verificati col tuo consulente.
A4: IL TFR AL RITIRO E LA TASSAZIONE SEPARATA
A5: Voce | B5: Chiara | C5: Marito | D5: Coppia
A6: Anzianita' TFR al ritiro (anni) | B6: ='1-Input'!$B$23 | C6: ='1-Input'!$C$23
A7: TFR lordo maturato al ritiro | B7: ='1-Input'!$B$24 | C7: ='1-Input'!$C$24 | D7: =B7+C7
A8: Reddito di riferimento (TFR / anzianita' × 12) | B8: =B7/B6*12 | C8: =C7/C6*12
A9: Aliquota della tassazione separata (aliquota media IRPEF 2026) | B9: =(IF(B8<='P-Parametri'!$B$6,'P-Parametri'!$C$6*B8,IF(B8<='P-Parametri'!$B$7,'P-Parametri'!$B$9+'P-Parametri'!$C$7*(B8-'P-Parametri'!$B$6),'P-Parametri'!$B$10+'P-Parametri'!$C$8*(B8-'P-Parametri'!$B$7))))/B8 | C9: =(IF(C8<='P-Parametri'!$B$6,'P-Parametri'!$C$6*C8,IF(C8<='P-Parametri'!$B$7,'P-Parametri'!$B$9+'P-Parametri'!$C$7*(C8-'P-Parametri'!$B$6),'P-Parametri'!$B$10+'P-Parametri'!$C$8*(C8-'P-Parametri'!$B$7))))/C8
A10: TFR NETTO al ritiro | B10: =B7*(1-B9) | C10: =C7*(1-C9) | D10: =B10+C10
A12: Banda del ±15% sul TFR netto — minimo / centrale / massimo | B12: =D10*0.85 | C12: =D10 | D12: =D10*1.15
A14: IL TFR SE SI LAVORA UNO O DUE ANNI IN PIU'
A15: Voce | B15: Al ritiro | C15: +1 anno | D15: +2 anni
A16: Quota annua di Chiara (reddito di riferimento / 13,5) | B16: =B8/'P-Parametri'!$B$34
A17: Quota annua del marito (retribuzione di riferimento / 13,5) | B17: ='1-Input'!$B$25/'P-Parametri'!$B$34
A18: TFR lordo di Chiara | B18: =B7 | C18: =B18*(1+'1-Input'!$C$25)+$B$16 | D18: =C18*(1+'1-Input'!$C$25)+$B$16
A19: TFR lordo del marito | B19: =C7 | C19: =B19*(1+'1-Input'!$C$25)+$B$17 | D19: =C19*(1+'1-Input'!$C$25)+$B$17
A20: Anzianita' di Chiara | B20: =B6 | C20: =B20+1 | D20: =C20+1
A21: Anzianita' del marito | B21: =C6 | C21: =B21+1 | D21: =C21+1
A22: TFR netto di Chiara | B22: =B18*(1-(IF((B18/B20*12)<='P-Parametri'!$B$6,'P-Parametri'!$C$6*(B18/B20*12),IF((B18/B20*12)<='P-Parametri'!$B$7,'P-Parametri'!$B$9+'P-Parametri'!$C$7*((B18/B20*12)-'P-Parametri'!$B$6),'P-Parametri'!$B$10+'P-Parametri'!$C$8*((B18/B20*12)-'P-Parametri'!$B$7))))/(B18/B20*12)) | C22: =C18*(1-(IF((C18/C20*12)<='P-Parametri'!$B$6,'P-Parametri'!$C$6*(C18/C20*12),IF((C18/C20*12)<='P-Parametri'!$B$7,'P-Parametri'!$B$9+'P-Parametri'!$C$7*((C18/C20*12)-'P-Parametri'!$B$6),'P-Parametri'!$B$10+'P-Parametri'!$C$8*((C18/C20*12)-'P-Parametri'!$B$7))))/(C18/C20*12)) | D22: =D18*(1-(IF((D18/D20*12)<='P-Parametri'!$B$6,'P-Parametri'!$C$6*(D18/D20*12),IF((D18/D20*12)<='P-Parametri'!$B$7,'P-Parametri'!$B$9+'P-Parametri'!$C$7*((D18/D20*12)-'P-Parametri'!$B$6),'P-Parametri'!$B$10+'P-Parametri'!$C$8*((D18/D20*12)-'P-Parametri'!$B$7))))/(D18/D20*12))
A23: TFR netto del marito | B23: =B19*(1-(IF((B19/B21*12)<='P-Parametri'!$B$6,'P-Parametri'!$C$6*(B19/B21*12),IF((B19/B21*12)<='P-Parametri'!$B$7,'P-Parametri'!$B$9+'P-Parametri'!$C$7*((B19/B21*12)-'P-Parametri'!$B$6),'P-Parametri'!$B$10+'P-Parametri'!$C$8*((B19/B21*12)-'P-Parametri'!$B$7))))/(B19/B21*12)) | C23: =C19*(1-(IF((C19/C21*12)<='P-Parametri'!$B$6,'P-Parametri'!$C$6*(C19/C21*12),IF((C19/C21*12)<='P-Parametri'!$B$7,'P-Parametri'!$B$9+'P-Parametri'!$C$7*((C19/C21*12)-'P-Parametri'!$B$6),'P-Parametri'!$B$10+'P-Parametri'!$C$8*((C19/C21*12)-'P-Parametri'!$B$7))))/(C19/C21*12)) | D23: =D19*(1-(IF((D19/D21*12)<='P-Parametri'!$B$6,'P-Parametri'!$C$6*(D19/D21*12),IF((D19/D21*12)<='P-Parametri'!$B$7,'P-Parametri'!$B$9+'P-Parametri'!$C$7*((D19/D21*12)-'P-Parametri'!$B$6),'P-Parametri'!$B$10+'P-Parametri'!$C$8*((D19/D21*12)-'P-Parametri'!$B$7))))/(D19/D21*12))
A24: TFR NETTO DI COPPIA — la risorsa che il motore usa | B24: =IF('1-Input'!$B$26=1,B22+B23,(B18+B19)*(1-'P-Parametri'!$C$35)) | C24: =IF('1-Input'!$B$26=1,C22+C23,(C18+C19)*(1-'P-Parametri'!$C$35)) | D24: =IF('1-Input'!$B$26=1,D22+D23,(D18+D19)*(1-'P-Parametri'!$C$35))
A26: IL TFR CONFERITO AL FONDO PENSIONE — vale PIU' della cassa
A27: TFR lordo di coppia al ritiro | B27: =D7
A28: Netto con la ritenuta iniziale del 15% | B28: =B27*(1-'P-Parametri'!$B$35)
A29: Netto con la ritenuta a regime del 9% | B29: =B27*(1-'P-Parametri'!$C$35)
A30: Differenza contro la cassa (ritenuta a regime) | B30: =B29-D10
A32: CLAUSOLA DI SALVAGUARDIA — scaglioni 2006 (art. 21 c. 11 D.Lgs. 117/2026)
A33: Voce | B33: Chiara | C33: Marito
A34: Reddito di riferimento | B34: =B8 | C34: =C8
A35: Aliquota con gli scaglioni 2006 | B35: =(IF(B34<='P-Parametri'!$B$37,'P-Parametri'!$C$37*B34,IF(B34<='P-Parametri'!$B$38,'P-Parametri'!$C$37*'P-Parametri'!$B$37+'P-Parametri'!$C$38*(B34-'P-Parametri'!$B$37),IF(B34<='P-Parametri'!$B$39,'P-Parametri'!$C$37*'P-Parametri'!$B$37+'P-Parametri'!$C$38*('P-Parametri'!$B$38-'P-Parametri'!$B$37)+'P-Parametri'!$C$39*(B34-'P-Parametri'!$B$38),'P-Parametri'!$C$37*'P-Parametri'!$B$37+'P-Parametri'!$C$38*('P-Parametri'!$B$38-'P-Parametri'!$B$37)+'P-Parametri'!$C$39*('P-Parametri'!$B$39-'P-Parametri'!$B$38)+'P-Parametri'!$C$40*(B34-'P-Parametri'!$B$39)))))/B34 | C35: =(IF(C34<='P-Parametri'!$B$37,'P-Parametri'!$C$37*C34,IF(C34<='P-Parametri'!$B$38,'P-Parametri'!$C$37*'P-Parametri'!$B$37+'P-Parametri'!$C$38*(C34-'P-Parametri'!$B$37),IF(C34<='P-Parametri'!$B$39,'P-Parametri'!$C$37*'P-Parametri'!$B$37+'P-Parametri'!$C$38*('P-Parametri'!$B$38-'P-Parametri'!$B$37)+'P-Parametri'!$C$39*(C34-'P-Parametri'!$B$38),'P-Parametri'!$C$37*'P-Parametri'!$B$37+'P-Parametri'!$C$38*('P-Parametri'!$B$38-'P-Parametri'!$B$37)+'P-Parametri'!$C$39*('P-Parametri'!$B$39-'P-Parametri'!$B$38)+'P-Parametri'!$C$40*(C34-'P-Parametri'!$B$39)))))/C34
A36: Aliquota con l'IRPEF 2026 | B36: =B9 | C36: =C9
A37: Margine (punti percentuali) | B37: =(B35-B36)*100 | C37: =(C35-C36)*100
A38: La clausola morde su questo profilo? | B38: =IF(B35<B36,"SI","NO") | C38: =IF(C35<C36,"SI","NO")
A40: IL TFR E' GIA' NETTO E NON SI LORDIZZA. La tassazione separata e' gia' scontata alla liquidazione: per portare in tasca un euro di TFR non si vende nulla, quindi non c'e' imposta sulla plusvalenza. Un euro di TFR risparmia al portafoglio G euro di capitale, non uno: e' per questo che nel waterfall il gradino della liquidazione si scrive in CAPITALE (netto × G) e non in netto.
A41: Il TFR e' STIMATO, non calcolato sulla serie: anzianita', retribuzioni di riferimento e rivalutazione reale sono ipotesi dichiarate, e l'aliquota separata e' applicata all'intero montante invece che alle sole quote. Ampiezza plausibile ±15% (riga 12), su un numero che vale circa meta' del fabbisogno.
A42: La retribuzione media di riferimento del marito per il TFR (34.000) e' una grandezza DIVERSA dalla sua media di carriera previdenziale (30.000) e dalla sua retribuzione attuale (48.000): la prima e' la media dell'ultimo rapporto di lavoro rivalutata, la seconda e' la media di tutta la carriera.
A43: Il margine della clausola di salvaguardia e' di circa un punto sul profilo del marito: «non morde SU QUESTI DUE PROFILI», non «non morde». Le ipotesi su anzianita' e retribuzione di riferimento (±15%) se lo mangerebbero.
A44: Il conferimento al fondo pensione (ritenuta dal 15% scalata al 9%) vale PIU' della cassa: la riga non entra nella banda del fabbisogno, perche' quella banda misura il rischio e questa voce lo abbassa. Rimando a fondo_pensione_guida.

Sheet 7-Fabbisogno
A1: Ponte, coda e fabbisogno al ritiro
A2: Strumento informativo / divulgativo. NON è consulenza finanziaria. I valori sono indicativi al 2026 e vanno verificati col tuo consulente.
A4: IL FLUSSO ANNO PER ANNO — il ponte e la coda
A5: Anno | B5: Eta' di Chiara | C5: Pensione del marito | D5: Pensione di Chiara | E5: Pensioni totali | F5: Spesa | G5: Fabbisogno netto | H5: Fattore di sconto | I5: Valore attuale | K5: Anno | L5: Pensioni (stop oggi) | M5: Fabbisogno netto | N5: Valore attuale
A6: ='1-Input'!$B$19+1 | B6: =$A6-'1-Input'!$B$5 | C6: =IF($A6>'1-Input'!$B$47,0,IF($A6<'5-Pensioni'!$C$8,0,IF($A6='5-Pensioni'!$C$8,'5-Pensioni'!$C$18*'5-Pensioni'!$C$19,'5-Pensioni'!$C$18))) | D6: =IF($A6>'1-Input'!$B$47,0,IF($A6<'5-Pensioni'!$B$8,0,IF($A6='5-Pensioni'!$B$8,'5-Pensioni'!$B$18*'5-Pensioni'!$B$19,'5-Pensioni'!$B$18))) | E6: =C6+D6 | F6: =IF($A6>'1-Input'!$B$47,0,'1-Input'!$B$13) | G6: =F6-E6 | H6: =IF($A6>'1-Input'!$B$47,0,1/(1+'1-Input'!$B$46)^($A6-'1-Input'!$B$19-1)) | I6: =G6*H6 | K6: ='1-Input'!$C$16+1 | L6: =IF($K6>'1-Input'!$B$47,0,IF($K6<'5-Pensioni'!$C$8,0,IF($K6='5-Pensioni'!$C$8,'5-Pensioni'!$C$54*'5-Pensioni'!$C$19,'5-Pensioni'!$C$54))+IF($K6<'5-Pensioni'!$B$8,0,IF($K6='5-Pensioni'!$B$8,'5-Pensioni'!$B$54*'5-Pensioni'!$B$19,'5-Pensioni'!$B$54))) | M6: =IF($K6>'1-Input'!$B$47,0,'1-Input'!$B$13-L6) | N6: =IF($K6>'1-Input'!$B$47,0,M6/(1+'1-Input'!$B$46)^($K6-'1-Input'!$C$16-1))
A7: =A6+1 | B7: =$A7-'1-Input'!$B$5 | C7: =IF($A7>'1-Input'!$B$47,0,IF($A7<'5-Pensioni'!$C$8,0,IF($A7='5-Pensioni'!$C$8,'5-Pensioni'!$C$18*'5-Pensioni'!$C$19,'5-Pensioni'!$C$18))) | D7: =IF($A7>'1-Input'!$B$47,0,IF($A7<'5-Pensioni'!$B$8,0,IF($A7='5-Pensioni'!$B$8,'5-Pensioni'!$B$18*'5-Pensioni'!$B$19,'5-Pensioni'!$B$18))) | E7: =C7+D7 | F7: =IF($A7>'1-Input'!$B$47,0,'1-Input'!$B$13) | G7: =F7-E7 | H7: =IF($A7>'1-Input'!$B$47,0,1/(1+'1-Input'!$B$46)^($A7-'1-Input'!$B$19-1)) | I7: =G7*H7 | K7: =K6+1 | L7: =IF($K7>'1-Input'!$B$47,0,IF($K7<'5-Pensioni'!$C$8,0,IF($K7='5-Pensioni'!$C$8,'5-Pensioni'!$C$54*'5-Pensioni'!$C$19,'5-Pensioni'!$C$54))+IF($K7<'5-Pensioni'!$B$8,0,IF($K7='5-Pensioni'!$B$8,'5-Pensioni'!$B$54*'5-Pensioni'!$B$19,'5-Pensioni'!$B$54))) | M7: =IF($K7>'1-Input'!$B$47,0,'1-Input'!$B$13-L7) | N7: =IF($K7>'1-Input'!$B$47,0,M7/(1+'1-Input'!$B$46)^($K7-'1-Input'!$C$16-1))
A8: =A7+1 | B8: =$A8-'1-Input'!$B$5 | C8: =IF($A8>'1-Input'!$B$47,0,IF($A8<'5-Pensioni'!$C$8,0,IF($A8='5-Pensioni'!$C$8,'5-Pensioni'!$C$18*'5-Pensioni'!$C$19,'5-Pensioni'!$C$18))) | D8: =IF($A8>'1-Input'!$B$47,0,IF($A8<'5-Pensioni'!$B$8,0,IF($A8='5-Pensioni'!$B$8,'5-Pensioni'!$B$18*'5-Pensioni'!$B$19,'5-Pensioni'!$B$18))) | E8: =C8+D8 | F8: =IF($A8>'1-Input'!$B$47,0,'1-Input'!$B$13) | G8: =F8-E8 | H8: =IF($A8>'1-Input'!$B$47,0,1/(1+'1-Input'!$B$46)^($A8-'1-Input'!$B$19-1)) | I8: =G8*H8 | K8: =K7+1 | L8: =IF($K8>'1-Input'!$B$47,0,IF($K8<'5-Pensioni'!$C$8,0,IF($K8='5-Pensioni'!$C$8,'5-Pensioni'!$C$54*'5-Pensioni'!$C$19,'5-Pensioni'!$C$54))+IF($K8<'5-Pensioni'!$B$8,0,IF($K8='5-Pensioni'!$B$8,'5-Pensioni'!$B$54*'5-Pensioni'!$B$19,'5-Pensioni'!$B$54))) | M8: =IF($K8>'1-Input'!$B$47,0,'1-Input'!$B$13-L8) | N8: =IF($K8>'1-Input'!$B$47,0,M8/(1+'1-Input'!$B$46)^($K8-'1-Input'!$C$16-1))
A9: =A8+1 | B9: =$A9-'1-Input'!$B$5 | C9: =IF($A9>'1-Input'!$B$47,0,IF($A9<'5-Pensioni'!$C$8,0,IF($A9='5-Pensioni'!$C$8,'5-Pensioni'!$C$18*'5-Pensioni'!$C$19,'5-Pensioni'!$C$18))) | D9: =IF($A9>'1-Input'!$B$47,0,IF($A9<'5-Pensioni'!$B$8,0,IF($A9='5-Pensioni'!$B$8,'5-Pensioni'!$B$18*'5-Pensioni'!$B$19,'5-Pensioni'!$B$18))) | E9: =C9+D9 | F9: =IF($A9>'1-Input'!$B$47,0,'1-Input'!$B$13) | G9: =F9-E9 | H9: =IF($A9>'1-Input'!$B$47,0,1/(1+'1-Input'!$B$46)^($A9-'1-Input'!$B$19-1)) | I9: =G9*H9 | K9: =K8+1 | L9: =IF($K9>'1-Input'!$B$47,0,IF($K9<'5-Pensioni'!$C$8,0,IF($K9='5-Pensioni'!$C$8,'5-Pensioni'!$C$54*'5-Pensioni'!$C$19,'5-Pensioni'!$C$54))+IF($K9<'5-Pensioni'!$B$8,0,IF($K9='5-Pensioni'!$B$8,'5-Pensioni'!$B$54*'5-Pensioni'!$B$19,'5-Pensioni'!$B$54))) | M9: =IF($K9>'1-Input'!$B$47,0,'1-Input'!$B$13-L9) | N9: =IF($K9>'1-Input'!$B$47,0,M9/(1+'1-Input'!$B$46)^($K9-'1-Input'!$C$16-1))
A10: =A9+1 | B10: =$A10-'1-Input'!$B$5 | C10: =IF($A10>'1-Input'!$B$47,0,IF($A10<'5-Pensioni'!$C$8,0,IF($A10='5-Pensioni'!$C$8,'5-Pensioni'!$C$18*'5-Pensioni'!$C$19,'5-Pensioni'!$C$18))) | D10: =IF($A10>'1-Input'!$B$47,0,IF($A10<'5-Pensioni'!$B$8,0,IF($A10='5-Pensioni'!$B$8,'5-Pensioni'!$B$18*'5-Pensioni'!$B$19,'5-Pensioni'!$B$18))) | E10: =C10+D10 | F10: =IF($A10>'1-Input'!$B$47,0,'1-Input'!$B$13) | G10: =F10-E10 | H10: =IF($A10>'1-Input'!$B$47,0,1/(1+'1-Input'!$B$46)^($A10-'1-Input'!$B$19-1)) | I10: =G10*H10 | K10: =K9+1 | L10: =IF($K10>'1-Input'!$B$47,0,IF($K10<'5-Pensioni'!$C$8,0,IF($K10='5-Pensioni'!$C$8,'5-Pensioni'!$C$54*'5-Pensioni'!$C$19,'5-Pensioni'!$C$54))+IF($K10<'5-Pensioni'!$B$8,0,IF($K10='5-Pensioni'!$B$8,'5-Pensioni'!$B$54*'5-Pensioni'!$B$19,'5-Pensioni'!$B$54))) | M10: =IF($K10>'1-Input'!$B$47,0,'1-Input'!$B$13-L10) | N10: =IF($K10>'1-Input'!$B$47,0,M10/(1+'1-Input'!$B$46)^($K10-'1-Input'!$C$16-1))
A11: =A10+1 | B11: =$A11-'1-Input'!$B$5 | C11: =IF($A11>'1-Input'!$B$47,0,IF($A11<'5-Pensioni'!$C$8,0,IF($A11='5-Pensioni'!$C$8,'5-Pensioni'!$C$18*'5-Pensioni'!$C$19,'5-Pensioni'!$C$18))) | D11: =IF($A11>'1-Input'!$B$47,0,IF($A11<'5-Pensioni'!$B$8,0,IF($A11='5-Pensioni'!$B$8,'5-Pensioni'!$B$18*'5-Pensioni'!$B$19,'5-Pensioni'!$B$18))) | E11: =C11+D11 | F11: =IF($A11>'1-Input'!$B$47,0,'1-Input'!$B$13) | G11: =F11-E11 | H11: =IF($A11>'1-Input'!$B$47,0,1/(1+'1-Input'!$B$46)^($A11-'1-Input'!$B$19-1)) | I11: =G11*H11 | K11: =K10+1 | L11: =IF($K11>'1-Input'!$B$47,0,IF($K11<'5-Pensioni'!$C$8,0,IF($K11='5-Pensioni'!$C$8,'5-Pensioni'!$C$54*'5-Pensioni'!$C$19,'5-Pensioni'!$C$54))+IF($K11<'5-Pensioni'!$B$8,0,IF($K11='5-Pensioni'!$B$8,'5-Pensioni'!$B$54*'5-Pensioni'!$B$19,'5-Pensioni'!$B$54))) | M11: =IF($K11>'1-Input'!$B$47,0,'1-Input'!$B$13-L11) | N11: =IF($K11>'1-Input'!$B$47,0,M11/(1+'1-Input'!$B$46)^($K11-'1-Input'!$C$16-1))
A12: =A11+1 | B12: =$A12-'1-Input'!$B$5 | C12: =IF($A12>'1-Input'!$B$47,0,IF($A12<'5-Pensioni'!$C$8,0,IF($A12='5-Pensioni'!$C$8,'5-Pensioni'!$C$18*'5-Pensioni'!$C$19,'5-Pensioni'!$C$18))) | D12: =IF($A12>'1-Input'!$B$47,0,IF($A12<'5-Pensioni'!$B$8,0,IF($A12='5-Pensioni'!$B$8,'5-Pensioni'!$B$18*'5-Pensioni'!$B$19,'5-Pensioni'!$B$18))) | E12: =C12+D12 | F12: =IF($A12>'1-Input'!$B$47,0,'1-Input'!$B$13) | G12: =F12-E12 | H12: =IF($A12>'1-Input'!$B$47,0,1/(1+'1-Input'!$B$46)^($A12-'1-Input'!$B$19-1)) | I12: =G12*H12 | K12: =K11+1 | L12: =IF($K12>'1-Input'!$B$47,0,IF($K12<'5-Pensioni'!$C$8,0,IF($K12='5-Pensioni'!$C$8,'5-Pensioni'!$C$54*'5-Pensioni'!$C$19,'5-Pensioni'!$C$54))+IF($K12<'5-Pensioni'!$B$8,0,IF($K12='5-Pensioni'!$B$8,'5-Pensioni'!$B$54*'5-Pensioni'!$B$19,'5-Pensioni'!$B$54))) | M12: =IF($K12>'1-Input'!$B$47,0,'1-Input'!$B$13-L12) | N12: =IF($K12>'1-Input'!$B$47,0,M12/(1+'1-Input'!$B$46)^($K12-'1-Input'!$C$16-1))
A13: =A12+1 | B13: =$A13-'1-Input'!$B$5 | C13: =IF($A13>'1-Input'!$B$47,0,IF($A13<'5-Pensioni'!$C$8,0,IF($A13='5-Pensioni'!$C$8,'5-Pensioni'!$C$18*'5-Pensioni'!$C$19,'5-Pensioni'!$C$18))) | D13: =IF($A13>'1-Input'!$B$47,0,IF($A13<'5-Pensioni'!$B$8,0,IF($A13='5-Pensioni'!$B$8,'5-Pensioni'!$B$18*'5-Pensioni'!$B$19,'5-Pensioni'!$B$18))) | E13: =C13+D13 | F13: =IF($A13>'1-Input'!$B$47,0,'1-Input'!$B$13) | G13: =F13-E13 | H13: =IF($A13>'1-Input'!$B$47,0,1/(1+'1-Input'!$B$46)^($A13-'1-Input'!$B$19-1)) | I13: =G13*H13 | K13: =K12+1 | L13: =IF($K13>'1-Input'!$B$47,0,IF($K13<'5-Pensioni'!$C$8,0,IF($K13='5-Pensioni'!$C$8,'5-Pensioni'!$C$54*'5-Pensioni'!$C$19,'5-Pensioni'!$C$54))+IF($K13<'5-Pensioni'!$B$8,0,IF($K13='5-Pensioni'!$B$8,'5-Pensioni'!$B$54*'5-Pensioni'!$B$19,'5-Pensioni'!$B$54))) | M13: =IF($K13>'1-Input'!$B$47,0,'1-Input'!$B$13-L13) | N13: =IF($K13>'1-Input'!$B$47,0,M13/(1+'1-Input'!$B$46)^($K13-'1-Input'!$C$16-1))
A14: =A13+1 | B14: =$A14-'1-Input'!$B$5 | C14: =IF($A14>'1-Input'!$B$47,0,IF($A14<'5-Pensioni'!$C$8,0,IF($A14='5-Pensioni'!$C$8,'5-Pensioni'!$C$18*'5-Pensioni'!$C$19,'5-Pensioni'!$C$18))) | D14: =IF($A14>'1-Input'!$B$47,0,IF($A14<'5-Pensioni'!$B$8,0,IF($A14='5-Pensioni'!$B$8,'5-Pensioni'!$B$18*'5-Pensioni'!$B$19,'5-Pensioni'!$B$18))) | E14: =C14+D14 | F14: =IF($A14>'1-Input'!$B$47,0,'1-Input'!$B$13) | G14: =F14-E14 | H14: =IF($A14>'1-Input'!$B$47,0,1/(1+'1-Input'!$B$46)^($A14-'1-Input'!$B$19-1)) | I14: =G14*H14 | K14: =K13+1 | L14: =IF($K14>'1-Input'!$B$47,0,IF($K14<'5-Pensioni'!$C$8,0,IF($K14='5-Pensioni'!$C$8,'5-Pensioni'!$C$54*'5-Pensioni'!$C$19,'5-Pensioni'!$C$54))+IF($K14<'5-Pensioni'!$B$8,0,IF($K14='5-Pensioni'!$B$8,'5-Pensioni'!$B$54*'5-Pensioni'!$B$19,'5-Pensioni'!$B$54))) | M14: =IF($K14>'1-Input'!$B$47,0,'1-Input'!$B$13-L14) | N14: =IF($K14>'1-Input'!$B$47,0,M14/(1+'1-Input'!$B$46)^($K14-'1-Input'!$C$16-1))
A15: =A14+1 | B15: =$A15-'1-Input'!$B$5 | C15: =IF($A15>'1-Input'!$B$47,0,IF($A15<'5-Pensioni'!$C$8,0,IF($A15='5-Pensioni'!$C$8,'5-Pensioni'!$C$18*'5-Pensioni'!$C$19,'5-Pensioni'!$C$18))) | D15: =IF($A15>'1-Input'!$B$47,0,IF($A15<'5-Pensioni'!$B$8,0,IF($A15='5-Pensioni'!$B$8,'5-Pensioni'!$B$18*'5-Pensioni'!$B$19,'5-Pensioni'!$B$18))) | E15: =C15+D15 | F15: =IF($A15>'1-Input'!$B$47,0,'1-Input'!$B$13) | G15: =F15-E15 | H15: =IF($A15>'1-Input'!$B$47,0,1/(1+'1-Input'!$B$46)^($A15-'1-Input'!$B$19-1)) | I15: =G15*H15 | K15: =K14+1 | L15: =IF($K15>'1-Input'!$B$47,0,IF($K15<'5-Pensioni'!$C$8,0,IF($K15='5-Pensioni'!$C$8,'5-Pensioni'!$C$54*'5-Pensioni'!$C$19,'5-Pensioni'!$C$54))+IF($K15<'5-Pensioni'!$B$8,0,IF($K15='5-Pensioni'!$B$8,'5-Pensioni'!$B$54*'5-Pensioni'!$B$19,'5-Pensioni'!$B$54))) | M15: =IF($K15>'1-Input'!$B$47,0,'1-Input'!$B$13-L15) | N15: =IF($K15>'1-Input'!$B$47,0,M15/(1+'1-Input'!$B$46)^($K15-'1-Input'!$C$16-1))
A16: =A15+1 | B16: =$A16-'1-Input'!$B$5 | C16: =IF($A16>'1-Input'!$B$47,0,IF($A16<'5-Pensioni'!$C$8,0,IF($A16='5-Pensioni'!$C$8,'5-Pensioni'!$C$18*'5-Pensioni'!$C$19,'5-Pensioni'!$C$18))) | D16: =IF($A16>'1-Input'!$B$47,0,IF($A16<'5-Pensioni'!$B$8,0,IF($A16='5-Pensioni'!$B$8,'5-Pensioni'!$B$18*'5-Pensioni'!$B$19,'5-Pensioni'!$B$18))) | E16: =C16+D16 | F16: =IF($A16>'1-Input'!$B$47,0,'1-Input'!$B$13) | G16: =F16-E16 | H16: =IF($A16>'1-Input'!$B$47,0,1/(1+'1-Input'!$B$46)^($A16-'1-Input'!$B$19-1)) | I16: =G16*H16 | K16: =K15+1 | L16: =IF($K16>'1-Input'!$B$47,0,IF($K16<'5-Pensioni'!$C$8,0,IF($K16='5-Pensioni'!$C$8,'5-Pensioni'!$C$54*'5-Pensioni'!$C$19,'5-Pensioni'!$C$54))+IF($K16<'5-Pensioni'!$B$8,0,IF($K16='5-Pensioni'!$B$8,'5-Pensioni'!$B$54*'5-Pensioni'!$B$19,'5-Pensioni'!$B$54))) | M16: =IF($K16>'1-Input'!$B$47,0,'1-Input'!$B$13-L16) | N16: =IF($K16>'1-Input'!$B$47,0,M16/(1+'1-Input'!$B$46)^($K16-'1-Input'!$C$16-1))
A17: =A16+1 | B17: =$A17-'1-Input'!$B$5 | C17: =IF($A17>'1-Input'!$B$47,0,IF($A17<'5-Pensioni'!$C$8,0,IF($A17='5-Pensioni'!$C$8,'5-Pensioni'!$C$18*'5-Pensioni'!$C$19,'5-Pensioni'!$C$18))) | D17: =IF($A17>'1-Input'!$B$47,0,IF($A17<'5-Pensioni'!$B$8,0,IF($A17='5-Pensioni'!$B$8,'5-Pensioni'!$B$18*'5-Pensioni'!$B$19,'5-Pensioni'!$B$18))) | E17: =C17+D17 | F17: =IF($A17>'1-Input'!$B$47,0,'1-Input'!$B$13) | G17: =F17-E17 | H17: =IF($A17>'1-Input'!$B$47,0,1/(1+'1-Input'!$B$46)^($A17-'1-Input'!$B$19-1)) | I17: =G17*H17 | K17: =K16+1 | L17: =IF($K17>'1-Input'!$B$47,0,IF($K17<'5-Pensioni'!$C$8,0,IF($K17='5-Pensioni'!$C$8,'5-Pensioni'!$C$54*'5-Pensioni'!$C$19,'5-Pensioni'!$C$54))+IF($K17<'5-Pensioni'!$B$8,0,IF($K17='5-Pensioni'!$B$8,'5-Pensioni'!$B$54*'5-Pensioni'!$B$19,'5-Pensioni'!$B$54))) | M17: =IF($K17>'1-Input'!$B$47,0,'1-Input'!$B$13-L17) | N17: =IF($K17>'1-Input'!$B$47,0,M17/(1+'1-Input'!$B$46)^($K17-'1-Input'!$C$16-1))
A18: =A17+1 | B18: =$A18-'1-Input'!$B$5 | C18: =IF($A18>'1-Input'!$B$47,0,IF($A18<'5-Pensioni'!$C$8,0,IF($A18='5-Pensioni'!$C$8,'5-Pensioni'!$C$18*'5-Pensioni'!$C$19,'5-Pensioni'!$C$18))) | D18: =IF($A18>'1-Input'!$B$47,0,IF($A18<'5-Pensioni'!$B$8,0,IF($A18='5-Pensioni'!$B$8,'5-Pensioni'!$B$18*'5-Pensioni'!$B$19,'5-Pensioni'!$B$18))) | E18: =C18+D18 | F18: =IF($A18>'1-Input'!$B$47,0,'1-Input'!$B$13) | G18: =F18-E18 | H18: =IF($A18>'1-Input'!$B$47,0,1/(1+'1-Input'!$B$46)^($A18-'1-Input'!$B$19-1)) | I18: =G18*H18 | K18: =K17+1 | L18: =IF($K18>'1-Input'!$B$47,0,IF($K18<'5-Pensioni'!$C$8,0,IF($K18='5-Pensioni'!$C$8,'5-Pensioni'!$C$54*'5-Pensioni'!$C$19,'5-Pensioni'!$C$54))+IF($K18<'5-Pensioni'!$B$8,0,IF($K18='5-Pensioni'!$B$8,'5-Pensioni'!$B$54*'5-Pensioni'!$B$19,'5-Pensioni'!$B$54))) | M18: =IF($K18>'1-Input'!$B$47,0,'1-Input'!$B$13-L18) | N18: =IF($K18>'1-Input'!$B$47,0,M18/(1+'1-Input'!$B$46)^($K18-'1-Input'!$C$16-1))
... A39: =A38+1 | B39: =$A39-'1-Input'!$B$5 | C39: =IF($A39>'1-Input'!$B$47,0,IF($A39<'5-Pensioni'!$C$8,0,IF($A39='5-Pensioni'!$C$8,'5-Pensioni'!$C$18*'5-Pensioni'!$C$19,'5-Pensioni'!$C$18))) | D39: =IF($A39>'1-Input'!$B$47,0,IF($A39<'5-Pensioni'!$B$8,0,IF($A39='5-Pensioni'!$B$8,'5-Pensioni'!$B$18*'5-Pensioni'!$B$19,'5-Pensioni'!$B$18))) | E39: =C39+D39 | F39: =IF($A39>'1-Input'!$B$47,0,'1-Input'!$B$13) | G39: =F39-E39 | H39: =IF($A39>'1-Input'!$B$47,0,1/(1+'1-Input'!$B$46)^($A39-'1-Input'!$B$19-1)) | I39: =G39*H39 | K39: =K38+1 | L39: =IF($K39>'1-Input'!$B$47,0,IF($K39<'5-Pensioni'!$C$8,0,IF($K39='5-Pensioni'!$C$8,'5-Pensioni'!$C$54*'5-Pensioni'!$C$19,'5-Pensioni'!$C$54))+IF($K39<'5-Pensioni'!$B$8,0,IF($K39='5-Pensioni'!$B$8,'5-Pensioni'!$B$54*'5-Pensioni'!$B$19,'5-Pensioni'!$B$54))) | M39: =IF($K39>'1-Input'!$B$47,0,'1-Input'!$B$13-L39) | N39: =IF($K39>'1-Input'!$B$47,0,M39/(1+'1-Input'!$B$46)^($K39-'1-Input'!$C$16-1))
K40: =K39+1 | L40: =IF($K40>'1-Input'!$B$47,0,IF($K40<'5-Pensioni'!$C$8,0,IF($K40='5-Pensioni'!$C$8,'5-Pensioni'!$C$54*'5-Pensioni'!$C$19,'5-Pensioni'!$C$54))+IF($K40<'5-Pensioni'!$B$8,0,IF($K40='5-Pensioni'!$B$8,'5-Pensioni'!$B$54*'5-Pensioni'!$B$19,'5-Pensioni'!$B$54))) | M40: =IF($K40>'1-Input'!$B$47,0,'1-Input'!$B$13-L40) | N40: =IF($K40>'1-Input'!$B$47,0,M40/(1+'1-Input'!$B$46)^($K40-'1-Input'!$C$16-1))
A41: IL FABBISOGNO AL RITIRO — le due letture chiudono allo stesso numero | K41: =K40+1 | L41: =IF($K41>'1-Input'!$B$47,0,IF($K41<'5-Pensioni'!$C$8,0,IF($K41='5-Pensioni'!$C$8,'5-Pensioni'!$C$54*'5-Pensioni'!$C$19,'5-Pensioni'!$C$54))+IF($K41<'5-Pensioni'!$B$8,0,IF($K41='5-Pensioni'!$B$8,'5-Pensioni'!$B$54*'5-Pensioni'!$B$19,'5-Pensioni'!$B$54))) | M41: =IF($K41>'1-Input'!$B$47,0,'1-Input'!$B$13-L41) | N41: =IF($K41>'1-Input'!$B$47,0,M41/(1+'1-Input'!$B$46)^($K41-'1-Input'!$C$16-1))
A42: Capitale al ritiro | B42: ='2-Composizione'!$B$36*(1+'1-Input'!$B$46)^'1-Input'!$B$50+'1-Input'!$B$40*(1+'1-Input'!$B$46)*(((1+'1-Input'!$B$46)^'1-Input'!$B$50-1)/'1-Input'!$B$46) | K42: =K41+1 | L42: =IF($K42>'1-Input'!$B$47,0,IF($K42<'5-Pensioni'!$C$8,0,IF($K42='5-Pensioni'!$C$8,'5-Pensioni'!$C$54*'5-Pensioni'!$C$19,'5-Pensioni'!$C$54))+IF($K42<'5-Pensioni'!$B$8,0,IF($K42='5-Pensioni'!$B$8,'5-Pensioni'!$B$54*'5-Pensioni'!$B$19,'5-Pensioni'!$B$54))) | M42: =IF($K42>'1-Input'!$B$47,0,'1-Input'!$B$13-L42) | N42: =IF($K42>'1-Input'!$B$47,0,M42/(1+'1-Input'!$B$46)^($K42-'1-Input'!$C$16-1))
A43: Base di costo al ritiro | B43: ='2-Composizione'!$B$37+'1-Input'!$B$50*'1-Input'!$B$40 | K43: =K42+1 | L43: =IF($K43>'1-Input'!$B$47,0,IF($K43<'5-Pensioni'!$C$8,0,IF($K43='5-Pensioni'!$C$8,'5-Pensioni'!$C$54*'5-Pensioni'!$C$19,'5-Pensioni'!$C$54))+IF($K43<'5-Pensioni'!$B$8,0,IF($K43='5-Pensioni'!$B$8,'5-Pensioni'!$B$54*'5-Pensioni'!$B$19,'5-Pensioni'!$B$54))) | M43: =IF($K43>'1-Input'!$B$47,0,'1-Input'!$B$13-L43) | N43: =IF($K43>'1-Input'!$B$47,0,M43/(1+'1-Input'!$B$46)^($K43-'1-Input'!$C$16-1))
A44: Plusvalenza latente al ritiro (floor a zero) | B44: =MAX(0,(B42-B43)/B42) | K44: =K43+1 | L44: =IF($K44>'1-Input'!$B$47,0,IF($K44<'5-Pensioni'!$C$8,0,IF($K44='5-Pensioni'!$C$8,'5-Pensioni'!$C$54*'5-Pensioni'!$C$19,'5-Pensioni'!$C$54))+IF($K44<'5-Pensioni'!$B$8,0,IF($K44='5-Pensioni'!$B$8,'5-Pensioni'!$B$54*'5-Pensioni'!$B$19,'5-Pensioni'!$B$54))) | M44: =IF($K44>'1-Input'!$B$47,0,'1-Input'!$B$13-L44) | N44: =IF($K44>'1-Input'!$B$47,0,M44/(1+'1-Input'!$B$46)^($K44-'1-Input'!$C$16-1))
A45: Fattore di lordizzazione G al ritiro | B45: =1/(1-'P-Parametri'!$B$31*B44) | K45: =K44+1 | L45: =IF($K45>'1-Input'!$B$47,0,IF($K45<'5-Pensioni'!$C$8,0,IF($K45='5-Pensioni'!$C$8,'5-Pensioni'!$C$54*'5-Pensioni'!$C$19,'5-Pensioni'!$C$54))+IF($K45<'5-Pensioni'!$B$8,0,IF($K45='5-Pensioni'!$B$8,'5-Pensioni'!$B$54*'5-Pensioni'!$B$19,'5-Pensioni'!$B$54))) | M45: =IF($K45>'1-Input'!$B$47,0,'1-Input'!$B$13-L45) | N45: =IF($K45>'1-Input'!$B$47,0,M45/(1+'1-Input'!$B$46)^($K45-'1-Input'!$C$16-1))
A46: Valore attuale netto del fabbisogno | B46: =SUM(I6:I39) | K46: =K45+1 | L46: =IF($K46>'1-Input'!$B$47,0,IF($K46<'5-Pensioni'!$C$8,0,IF($K46='5-Pensioni'!$C$8,'5-Pensioni'!$C$54*'5-Pensioni'!$C$19,'5-Pensioni'!$C$54))+IF($K46<'5-Pensioni'!$B$8,0,IF($K46='5-Pensioni'!$B$8,'5-Pensioni'!$B$54*'5-Pensioni'!$B$19,'5-Pensioni'!$B$54))) | M46: =IF($K46>'1-Input'!$B$47,0,'1-Input'!$B$13-L46) | N46: =IF($K46>'1-Input'!$B$47,0,M46/(1+'1-Input'!$B$46)^($K46-'1-Input'!$C$16-1))
A47: TFR netto incassato al ritiro | B47: ='6-TFR'!$B$24 | K47: =K46+1 | L47: =IF($K47>'1-Input'!$B$47,0,IF($K47<'5-Pensioni'!$C$8,0,IF($K47='5-Pensioni'!$C$8,'5-Pensioni'!$C$54*'5-Pensioni'!$C$19,'5-Pensioni'!$C$54))+IF($K47<'5-Pensioni'!$B$8,0,IF($K47='5-Pensioni'!$B$8,'5-Pensioni'!$B$54*'5-Pensioni'!$B$19,'5-Pensioni'!$B$54))) | M47: =IF($K47>'1-Input'!$B$47,0,'1-Input'!$B$13-L47) | N47: =IF($K47>'1-Input'!$B$47,0,M47/(1+'1-Input'!$B$46)^($K47-'1-Input'!$C$16-1))
A48: LETTURA IN NETTO — a carico del portafoglio, in netto | B48: =B46-B47 | K48: =K47+1 | L48: =IF($K48>'1-Input'!$B$47,0,IF($K48<'5-Pensioni'!$C$8,0,IF($K48='5-Pensioni'!$C$8,'5-Pensioni'!$C$54*'5-Pensioni'!$C$19,'5-Pensioni'!$C$54))+IF($K48<'5-Pensioni'!$B$8,0,IF($K48='5-Pensioni'!$B$8,'5-Pensioni'!$B$54*'5-Pensioni'!$B$19,'5-Pensioni'!$B$54))) | M48: =IF($K48>'1-Input'!$B$47,0,'1-Input'!$B$13-L48) | N48: =IF($K48>'1-Input'!$B$47,0,M48/(1+'1-Input'!$B$46)^($K48-'1-Input'!$C$16-1))
A49: …portata in capitale (× G) | B49: =MAX(0,B48*B45) | K49: =K48+1 | L49: =IF($K49>'1-Input'!$B$47,0,IF($K49<'5-Pensioni'!$C$8,0,IF($K49='5-Pensioni'!$C$8,'5-Pensioni'!$C$54*'5-Pensioni'!$C$19,'5-Pensioni'!$C$54))+IF($K49<'5-Pensioni'!$B$8,0,IF($K49='5-Pensioni'!$B$8,'5-Pensioni'!$B$54*'5-Pensioni'!$B$19,'5-Pensioni'!$B$54))) | M49: =IF($K49>'1-Input'!$B$47,0,'1-Input'!$B$13-L49) | N49: =IF($K49>'1-Input'!$B$47,0,M49/(1+'1-Input'!$B$46)^($K49-'1-Input'!$C$16-1))
A50: LETTURA IN CAPITALE — fabbisogno lordo (valore attuale × G) | B50: =B46*B45
A51: …meno il capitale che la liquidazione risparmia al portafoglio | B51: =-B47*B45
A52: FABBISOGNO FINANZIARIO (floor a zero) | B52: =MAX(0,B50+B51)
A53: Quota della liquidazione sul fabbisogno lordo | B53: =-B51/B50
A54: Copertura della spesa data dalle pensioni / gap di coda | B54: ='5-Pensioni'!$B$21 | C54: ='5-Pensioni'!$B$22
A56: IL WATERFALL DEL TWIST — cinque gradini, e uno tira nell'altra direzione
A57: Gradino | B57: Valore | C57: Fattore
A58: 0 — Il target dichiarato | B58: ='P-Parametri'!$B$47
A59: 1 — Al tasso vero del portafoglio, bollo incluso, sempre perpetuo | B59: ='1-Input'!$B$13/'1-Input'!$B$46 | C59: =B58/B59
A60: 2 — Orizzonte finito invece dell'infinito (annualita' anticipata) | B60: ='1-Input'!$B$13*((1-(1+'1-Input'!$B$46)^-('1-Input'!$B$47-'1-Input'!$B$19))/'1-Input'!$B$46)*(1+'1-Input'!$B$46) | C60: =B59/B60
A61: 3 — La fiscalita' del prelievo — QUESTO GRADINO SALE | B61: =B60*B45 | C61: =B60/B61
A62: 4 — Contate le due pensioni | B62: =B50 | C62: =B61/B62
A63: 5 — Contata la liquidazione | B63: =B52 | C63: =B62/B63
A64: FATTORE COMPLESSIVO — target / fabbisogno finanziario | B64: =B58/B63 | C64: =C59*C60*C61*C62*C63
A66: IL RIEPILOGO E I RAPPORTI
A67: Il patrimonio di oggi | B67: ='2-Composizione'!$B$36
A68: Il fabbisogno finanziario al ritiro | B68: =B52
A69: Quante volte il target dichiarato vale il fabbisogno | B69: =B64
A70: Il fabbisogno in quota del capitale al ritiro | B70: =B52/B42
A71: Margine: capitale al ritiro diviso fabbisogno | B71: =B42/B52
A72: Il target al prelievo perpetuo di riferimento / di quanto il dichiarato sta sotto | B72: ='1-Input'!$B$13/'P-Parametri'!$B$48 | C72: =1-'P-Parametri'!$B$47/B72
A73: Le due porte: vecchiaia / via dei 65 anni | B73: =B52 | C73: ='11-Banda'!$D$7 | D73: =B73-C73
A74: Scenari di spesa: piu' bassa / centrale / piu' alta | B74: ='11-Banda'!$D$6 | C74: ='11-Banda'!$D$9 | D74: ='11-Banda'!$D$16
A76: LA CURVA DEL ×25 — quattro punti, un metodo solo
A77: Eta' al ritiro | B77: Il ×25 | C77: Il fabbisogno | D77: Rapporto
A78: ='P-Parametri'!$C$50 | B78: ='P-Parametri'!$B$49*25 | C78: ='P-Parametri'!$B$49*((1-(1+'1-Input'!$B$46)^-('P-Parametri'!$B$50-'P-Parametri'!$C$50))/'1-Input'!$B$46)*(1+'1-Input'!$B$46) | D78: =B78/C78
A79: ='1-Input'!$C$16-'1-Input'!$B$5 | B79: ='1-Input'!$B$13*25 | C79: =SUM(N6:N49)*'2-Composizione'!$B$39 | D79: =B79/C79
A80: ='1-Input'!$B$56 | B80: ='1-Input'!$B$13*25 | C80: =B50 | D80: =B80/C80
A81: ='1-Input'!$B$56+2 | B81: ='1-Input'!$B$13*25 | C81: ='9-Leve'!$L$74 | D81: =B81/C81
A83: CONVENZIONI DEL FLUSSO, DICHIARATE. Il prelievo e' a inizio anno; lo sconto e' al rendimento NETTO BOLLO; nell'anno di decorrenza si conta mezza annualita' se la decorrenza non e' di gennaio; l'orizzonte e' l'eta' finale di Chiara.
A84: IL TFR E' GIA' NETTO E NON SI LORDIZZA: la tassazione separata e' gia' scontata alla liquidazione. Il gradino della liquidazione nel waterfall si scrive in CAPITALE (netto × G) e non in netto: sottrarre una risorsa netta da una grandezza in capitale metterebbe due unita' di misura diverse nello stesso gradino. Le due letture, in netto e in capitale, chiudono allo stesso numero.
A85: LA PLUSVALENZA LATENTE HA IL FLOOR A ZERO e il fattore di lordizzazione non scende mai sotto 1. Nel decumulo la latente cresce, quindi un fattore costante sottostima il fabbisogno; negli scenari con i crolli sbaglia nell'altro verso, perche' la latente collassa col mercato.
A86: IL PUNTO A 35 ANNI DELLA CURVA non si lordizza (convenzione dichiarata): chi ha appena raggiunto il suo ×25 partendo da zero ha una latente piccola, e la lordizzazione alzerebbe il fabbisogno, cioe' abbasserebbe ancora il rapporto. La scelta e' conservativa nel verso che protegge il video corretto. Sotto i venti anni di contributi la pensione di vecchiaia non si apre: a quel punto non c'e' nessuna gamba pubblica sotto.
A87: L'identita' coi due milioni e' APPROSSIMATA: al prelievo perpetuo di riferimento farebbero 2.080.000, e il target dichiarato sta sotto di poco. Mai «esattamente».
A88: La coppia e' trattata come un soggetto unico fino all'orizzonte: niente reversibilita', niente calo di spesa alla morte del primo coniuge, niente spesa di non autosufficienza. Tutto il verdetto sta nella coda, e il gap di coda e' la differenza fra due numeri grandi: e' ipersensibile.

Sheet 8-Patrimonio
A1: La traiettoria del patrimonio
A2: Strumento informativo / divulgativo. NON è consulenza finanziaria. I valori sono indicativi al 2026 e vanno verificati col tuo consulente.
A4: ANNO PER ANNO — accumulo, poi decumulo con il TFR consumato per primo
A5: Anno | B5: Eta' | C5: Versamento | D5: Pensioni nette | E5: Fabbisogno netto | F5: TFR usato | G5: TFR residuo | H5: Prelievo lordizzato | I5: Capitale centrale | J5: Capitale al pavimento | K5: Capitale al tetto | L5: Capitale con la sequenza sfavorevole
A6: ='1-Input'!$C$16 | B6: =$A6-'1-Input'!$B$5 | C6: =0 | D6: =0 | E6: =0 | F6: =0 | G6: ='6-TFR'!$B$24 | H6: =0 | I6: ='2-Composizione'!$B$36 | J6: ='2-Composizione'!$B$36 | K6: ='2-Composizione'!$B$36 | L6: ='2-Composizione'!$B$36
A7: =A6+1 | B7: =$A7-'1-Input'!$B$5 | C7: =IF($A7<='1-Input'!$B$19,'1-Input'!$B$40,0) | D7: =IF($A7<='1-Input'!$B$19,0,IF($A7>'1-Input'!$B$47,0,IF($A7<'5-Pensioni'!$C$8,0,IF($A7='5-Pensioni'!$C$8,'5-Pensioni'!$C$18*'5-Pensioni'!$C$19,'5-Pensioni'!$C$18))+IF($A7<'5-Pensioni'!$B$8,0,IF($A7='5-Pensioni'!$B$8,'5-Pensioni'!$B$18*'5-Pensioni'!$B$19,'5-Pensioni'!$B$18)))) | E7: =IF($A7<='1-Input'!$B$19,0,IF($A7>'1-Input'!$B$47,0,MAX(0,'1-Input'!$B$13-D7))) | F7: =MIN(E7,G6) | G7: =G6-F7 | H7: =MAX(0,E7-F7)*$B$51 | I7: =IF($A7<='1-Input'!$B$19,(I6+C7)*(1+'1-Input'!$B$46),(I6-H7)*(1+'1-Input'!$B$46)) | J7: =IF($A7<='1-Input'!$B$19,(J6+C7)*(1+'3-Rendimento'!$D$15),(J6-MAX(0,E7-F7)*$C$51)*(1+'3-Rendimento'!$D$15)) | K7: =IF($A7<='1-Input'!$B$19,(K6+C7)*(1+'3-Rendimento'!$D$17),(K6-MAX(0,E7-F7)*$D$51)*(1+'3-Rendimento'!$D$17)) | L7: =IF($A7>'1-Input'!$B$19,"",(L6+C7)*(1+IF($A7='1-Input'!$B$19-1,'P-Parametri'!$B$54*'P-Parametri'!$B$52+(1-'P-Parametri'!$B$54)*('P-Parametri'!$C$42-'1-Input'!$B$18),IF($A7='1-Input'!$B$19,'P-Parametri'!$B$54*'P-Parametri'!$C$52+(1-'P-Parametri'!$B$54)*('P-Parametri'!$C$42-'1-Input'!$B$18),'1-Input'!$B$46))))
A8: =A7+1 | B8: =$A8-'1-Input'!$B$5 | C8: =IF($A8<='1-Input'!$B$19,'1-Input'!$B$40,0) | D8: =IF($A8<='1-Input'!$B$19,0,IF($A8>'1-Input'!$B$47,0,IF($A8<'5-Pensioni'!$C$8,0,IF($A8='5-Pensioni'!$C$8,'5-Pensioni'!$C$18*'5-Pensioni'!$C$19,'5-Pensioni'!$C$18))+IF($A8<'5-Pensioni'!$B$8,0,IF($A8='5-Pensioni'!$B$8,'5-Pensioni'!$B$18*'5-Pensioni'!$B$19,'5-Pensioni'!$B$18)))) | E8: =IF($A8<='1-Input'!$B$19,0,IF($A8>'1-Input'!$B$47,0,MAX(0,'1-Input'!$B$13-D8))) | F8: =MIN(E8,G7) | G8: =G7-F8 | H8: =MAX(0,E8-F8)*$B$51 | I8: =IF($A8<='1-Input'!$B$19,(I7+C8)*(1+'1-Input'!$B$46),(I7-H8)*(1+'1-Input'!$B$46)) | J8: =IF($A8<='1-Input'!$B$19,(J7+C8)*(1+'3-Rendimento'!$D$15),(J7-MAX(0,E8-F8)*$C$51)*(1+'3-Rendimento'!$D$15)) | K8: =IF($A8<='1-Input'!$B$19,(K7+C8)*(1+'3-Rendimento'!$D$17),(K7-MAX(0,E8-F8)*$D$51)*(1+'3-Rendimento'!$D$17)) | L8: =IF($A8>'1-Input'!$B$19,"",(L7+C8)*(1+IF($A8='1-Input'!$B$19-1,'P-Parametri'!$B$54*'P-Parametri'!$B$52+(1-'P-Parametri'!$B$54)*('P-Parametri'!$C$42-'1-Input'!$B$18),IF($A8='1-Input'!$B$19,'P-Parametri'!$B$54*'P-Parametri'!$C$52+(1-'P-Parametri'!$B$54)*('P-Parametri'!$C$42-'1-Input'!$B$18),'1-Input'!$B$46))))
A9: =A8+1 | B9: =$A9-'1-Input'!$B$5 | C9: =IF($A9<='1-Input'!$B$19,'1-Input'!$B$40,0) | D9: =IF($A9<='1-Input'!$B$19,0,IF($A9>'1-Input'!$B$47,0,IF($A9<'5-Pensioni'!$C$8,0,IF($A9='5-Pensioni'!$C$8,'5-Pensioni'!$C$18*'5-Pensioni'!$C$19,'5-Pensioni'!$C$18))+IF($A9<'5-Pensioni'!$B$8,0,IF($A9='5-Pensioni'!$B$8,'5-Pensioni'!$B$18*'5-Pensioni'!$B$19,'5-Pensioni'!$B$18)))) | E9: =IF($A9<='1-Input'!$B$19,0,IF($A9>'1-Input'!$B$47,0,MAX(0,'1-Input'!$B$13-D9))) | F9: =MIN(E9,G8) | G9: =G8-F9 | H9: =MAX(0,E9-F9)*$B$51 | I9: =IF($A9<='1-Input'!$B$19,(I8+C9)*(1+'1-Input'!$B$46),(I8-H9)*(1+'1-Input'!$B$46)) | J9: =IF($A9<='1-Input'!$B$19,(J8+C9)*(1+'3-Rendimento'!$D$15),(J8-MAX(0,E9-F9)*$C$51)*(1+'3-Rendimento'!$D$15)) | K9: =IF($A9<='1-Input'!$B$19,(K8+C9)*(1+'3-Rendimento'!$D$17),(K8-MAX(0,E9-F9)*$D$51)*(1+'3-Rendimento'!$D$17)) | L9: =IF($A9>'1-Input'!$B$19,"",(L8+C9)*(1+IF($A9='1-Input'!$B$19-1,'P-Parametri'!$B$54*'P-Parametri'!$B$52+(1-'P-Parametri'!$B$54)*('P-Parametri'!$C$42-'1-Input'!$B$18),IF($A9='1-Input'!$B$19,'P-Parametri'!$B$54*'P-Parametri'!$C$52+(1-'P-Parametri'!$B$54)*('P-Parametri'!$C$42-'1-Input'!$B$18),'1-Input'!$B$46))))
A10: =A9+1 | B10: =$A10-'1-Input'!$B$5 | C10: =IF($A10<='1-Input'!$B$19,'1-Input'!$B$40,0) | D10: =IF($A10<='1-Input'!$B$19,0,IF($A10>'1-Input'!$B$47,0,IF($A10<'5-Pensioni'!$C$8,0,IF($A10='5-Pensioni'!$C$8,'5-Pensioni'!$C$18*'5-Pensioni'!$C$19,'5-Pensioni'!$C$18))+IF($A10<'5-Pensioni'!$B$8,0,IF($A10='5-Pensioni'!$B$8,'5-Pensioni'!$B$18*'5-Pensioni'!$B$19,'5-Pensioni'!$B$18)))) | E10: =IF($A10<='1-Input'!$B$19,0,IF($A10>'1-Input'!$B$47,0,MAX(0,'1-Input'!$B$13-D10))) | F10: =MIN(E10,G9) | G10: =G9-F10 | H10: =MAX(0,E10-F10)*$B$51 | I10: =IF($A10<='1-Input'!$B$19,(I9+C10)*(1+'1-Input'!$B$46),(I9-H10)*(1+'1-Input'!$B$46)) | J10: =IF($A10<='1-Input'!$B$19,(J9+C10)*(1+'3-Rendimento'!$D$15),(J9-MAX(0,E10-F10)*$C$51)*(1+'3-Rendimento'!$D$15)) | K10: =IF($A10<='1-Input'!$B$19,(K9+C10)*(1+'3-Rendimento'!$D$17),(K9-MAX(0,E10-F10)*$D$51)*(1+'3-Rendimento'!$D$17)) | L10: =IF($A10>'1-Input'!$B$19,"",(L9+C10)*(1+IF($A10='1-Input'!$B$19-1,'P-Parametri'!$B$54*'P-Parametri'!$B$52+(1-'P-Parametri'!$B$54)*('P-Parametri'!$C$42-'1-Input'!$B$18),IF($A10='1-Input'!$B$19,'P-Parametri'!$B$54*'P-Parametri'!$C$52+(1-'P-Parametri'!$B$54)*('P-Parametri'!$C$42-'1-Input'!$B$18),'1-Input'!$B$46))))
A11: =A10+1 | B11: =$A11-'1-Input'!$B$5 | C11: =IF($A11<='1-Input'!$B$19,'1-Input'!$B$40,0) | D11: =IF($A11<='1-Input'!$B$19,0,IF($A11>'1-Input'!$B$47,0,IF($A11<'5-Pensioni'!$C$8,0,IF($A11='5-Pensioni'!$C$8,'5-Pensioni'!$C$18*'5-Pensioni'!$C$19,'5-Pensioni'!$C$18))+IF($A11<'5-Pensioni'!$B$8,0,IF($A11='5-Pensioni'!$B$8,'5-Pensioni'!$B$18*'5-Pensioni'!$B$19,'5-Pensioni'!$B$18)))) | E11: =IF($A11<='1-Input'!$B$19,0,IF($A11>'1-Input'!$B$47,0,MAX(0,'1-Input'!$B$13-D11))) | F11: =MIN(E11,G10) | G11: =G10-F11 | H11: =MAX(0,E11-F11)*$B$51 | I11: =IF($A11<='1-Input'!$B$19,(I10+C11)*(1+'1-Input'!$B$46),(I10-H11)*(1+'1-Input'!$B$46)) | J11: =IF($A11<='1-Input'!$B$19,(J10+C11)*(1+'3-Rendimento'!$D$15),(J10-MAX(0,E11-F11)*$C$51)*(1+'3-Rendimento'!$D$15)) | K11: =IF($A11<='1-Input'!$B$19,(K10+C11)*(1+'3-Rendimento'!$D$17),(K10-MAX(0,E11-F11)*$D$51)*(1+'3-Rendimento'!$D$17)) | L11: =IF($A11>'1-Input'!$B$19,"",(L10+C11)*(1+IF($A11='1-Input'!$B$19-1,'P-Parametri'!$B$54*'P-Parametri'!$B$52+(1-'P-Parametri'!$B$54)*('P-Parametri'!$C$42-'1-Input'!$B$18),IF($A11='1-Input'!$B$19,'P-Parametri'!$B$54*'P-Parametri'!$C$52+(1-'P-Parametri'!$B$54)*('P-Parametri'!$C$42-'1-Input'!$B$18),'1-Input'!$B$46))))
A12: =A11+1 | B12: =$A12-'1-Input'!$B$5 | C12: =IF($A12<='1-Input'!$B$19,'1-Input'!$B$40,0) | D12: =IF($A12<='1-Input'!$B$19,0,IF($A12>'1-Input'!$B$47,0,IF($A12<'5-Pensioni'!$C$8,0,IF($A12='5-Pensioni'!$C$8,'5-Pensioni'!$C$18*'5-Pensioni'!$C$19,'5-Pensioni'!$C$18))+IF($A12<'5-Pensioni'!$B$8,0,IF($A12='5-Pensioni'!$B$8,'5-Pensioni'!$B$18*'5-Pensioni'!$B$19,'5-Pensioni'!$B$18)))) | E12: =IF($A12<='1-Input'!$B$19,0,IF($A12>'1-Input'!$B$47,0,MAX(0,'1-Input'!$B$13-D12))) | F12: =MIN(E12,G11) | G12: =G11-F12 | H12: =MAX(0,E12-F12)*$B$51 | I12: =IF($A12<='1-Input'!$B$19,(I11+C12)*(1+'1-Input'!$B$46),(I11-H12)*(1+'1-Input'!$B$46)) | J12: =IF($A12<='1-Input'!$B$19,(J11+C12)*(1+'3-Rendimento'!$D$15),(J11-MAX(0,E12-F12)*$C$51)*(1+'3-Rendimento'!$D$15)) | K12: =IF($A12<='1-Input'!$B$19,(K11+C12)*(1+'3-Rendimento'!$D$17),(K11-MAX(0,E12-F12)*$D$51)*(1+'3-Rendimento'!$D$17)) | L12: =IF($A12>'1-Input'!$B$19,"",(L11+C12)*(1+IF($A12='1-Input'!$B$19-1,'P-Parametri'!$B$54*'P-Parametri'!$B$52+(1-'P-Parametri'!$B$54)*('P-Parametri'!$C$42-'1-Input'!$B$18),IF($A12='1-Input'!$B$19,'P-Parametri'!$B$54*'P-Parametri'!$C$52+(1-'P-Parametri'!$B$54)*('P-Parametri'!$C$42-'1-Input'!$B$18),'1-Input'!$B$46))))
A13: =A12+1 | B13: =$A13-'1-Input'!$B$5 | C13: =IF($A13<='1-Input'!$B$19,'1-Input'!$B$40,0) | D13: =IF($A13<='1-Input'!$B$19,0,IF($A13>'1-Input'!$B$47,0,IF($A13<'5-Pensioni'!$C$8,0,IF($A13='5-Pensioni'!$C$8,'5-Pensioni'!$C$18*'5-Pensioni'!$C$19,'5-Pensioni'!$C$18))+IF($A13<'5-Pensioni'!$B$8,0,IF($A13='5-Pensioni'!$B$8,'5-Pensioni'!$B$18*'5-Pensioni'!$B$19,'5-Pensioni'!$B$18)))) | E13: =IF($A13<='1-Input'!$B$19,0,IF($A13>'1-Input'!$B$47,0,MAX(0,'1-Input'!$B$13-D13))) | F13: =MIN(E13,G12) | G13: =G12-F13 | H13: =MAX(0,E13-F13)*$B$51 | I13: =IF($A13<='1-Input'!$B$19,(I12+C13)*(1+'1-Input'!$B$46),(I12-H13)*(1+'1-Input'!$B$46)) | J13: =IF($A13<='1-Input'!$B$19,(J12+C13)*(1+'3-Rendimento'!$D$15),(J12-MAX(0,E13-F13)*$C$51)*(1+'3-Rendimento'!$D$15)) | K13: =IF($A13<='1-Input'!$B$19,(K12+C13)*(1+'3-Rendimento'!$D$17),(K12-MAX(0,E13-F13)*$D$51)*(1+'3-Rendimento'!$D$17)) | L13: =IF($A13>'1-Input'!$B$19,"",(L12+C13)*(1+IF($A13='1-Input'!$B$19-1,'P-Parametri'!$B$54*'P-Parametri'!$B$52+(1-'P-Parametri'!$B$54)*('P-Parametri'!$C$42-'1-Input'!$B$18),IF($A13='1-Input'!$B$19,'P-Parametri'!$B$54*'P-Parametri'!$C$52+(1-'P-Parametri'!$B$54)*('P-Parametri'!$C$42-'1-Input'!$B$18),'1-Input'!$B$46))))
A14: =A13+1 | B14: =$A14-'1-Input'!$B$5 | C14: =IF($A14<='1-Input'!$B$19,'1-Input'!$B$40,0) | D14: =IF($A14<='1-Input'!$B$19,0,IF($A14>'1-Input'!$B$47,0,IF($A14<'5-Pensioni'!$C$8,0,IF($A14='5-Pensioni'!$C$8,'5-Pensioni'!$C$18*'5-Pensioni'!$C$19,'5-Pensioni'!$C$18))+IF($A14<'5-Pensioni'!$B$8,0,IF($A14='5-Pensioni'!$B$8,'5-Pensioni'!$B$18*'5-Pensioni'!$B$19,'5-Pensioni'!$B$18)))) | E14: =IF($A14<='1-Input'!$B$19,0,IF($A14>'1-Input'!$B$47,0,MAX(0,'1-Input'!$B$13-D14))) | F14: =MIN(E14,G13) | G14: =G13-F14 | H14: =MAX(0,E14-F14)*$B$51 | I14: =IF($A14<='1-Input'!$B$19,(I13+C14)*(1+'1-Input'!$B$46),(I13-H14)*(1+'1-Input'!$B$46)) | J14: =IF($A14<='1-Input'!$B$19,(J13+C14)*(1+'3-Rendimento'!$D$15),(J13-MAX(0,E14-F14)*$C$51)*(1+'3-Rendimento'!$D$15)) | K14: =IF($A14<='1-Input'!$B$19,(K13+C14)*(1+'3-Rendimento'!$D$17),(K13-MAX(0,E14-F14)*$D$51)*(1+'3-Rendimento'!$D$17)) | L14: =IF($A14>'1-Input'!$B$19,"",(L13+C14)*(1+IF($A14='1-Input'!$B$19-1,'P-Parametri'!$B$54*'P-Parametri'!$B$52+(1-'P-Parametri'!$B$54)*('P-Parametri'!$C$42-'1-Input'!$B$18),IF($A14='1-Input'!$B$19,'P-Parametri'!$B$54*'P-Parametri'!$C$52+(1-'P-Parametri'!$B$54)*('P-Parametri'!$C$42-'1-Input'!$B$18),'1-Input'!$B$46))))
A15: =A14+1 | B15: =$A15-'1-Input'!$B$5 | C15: =IF($A15<='1-Input'!$B$19,'1-Input'!$B$40,0) | D15: =IF($A15<='1-Input'!$B$19,0,IF($A15>'1-Input'!$B$47,0,IF($A15<'5-Pensioni'!$C$8,0,IF($A15='5-Pensioni'!$C$8,'5-Pensioni'!$C$18*'5-Pensioni'!$C$19,'5-Pensioni'!$C$18))+IF($A15<'5-Pensioni'!$B$8,0,IF($A15='5-Pensioni'!$B$8,'5-Pensioni'!$B$18*'5-Pensioni'!$B$19,'5-Pensioni'!$B$18)))) | E15: =IF($A15<='1-Input'!$B$19,0,IF($A15>'1-Input'!$B$47,0,MAX(0,'1-Input'!$B$13-D15))) | F15: =MIN(E15,G14) | G15: =G14-F15 | H15: =MAX(0,E15-F15)*$B$51 | I15: =IF($A15<='1-Input'!$B$19,(I14+C15)*(1+'1-Input'!$B$46),(I14-H15)*(1+'1-Input'!$B$46)) | J15: =IF($A15<='1-Input'!$B$19,(J14+C15)*(1+'3-Rendimento'!$D$15),(J14-MAX(0,E15-F15)*$C$51)*(1+'3-Rendimento'!$D$15)) | K15: =IF($A15<='1-Input'!$B$19,(K14+C15)*(1+'3-Rendimento'!$D$17),(K14-MAX(0,E15-F15)*$D$51)*(1+'3-Rendimento'!$D$17)) | L15: =IF($A15>'1-Input'!$B$19,"",(L14+C15)*(1+IF($A15='1-Input'!$B$19-1,'P-Parametri'!$B$54*'P-Parametri'!$B$52+(1-'P-Parametri'!$B$54)*('P-Parametri'!$C$42-'1-Input'!$B$18),IF($A15='1-Input'!$B$19,'P-Parametri'!$B$54*'P-Parametri'!$C$52+(1-'P-Parametri'!$B$54)*('P-Parametri'!$C$42-'1-Input'!$B$18),'1-Input'!$B$46))))
A16: =A15+1 | B16: =$A16-'1-Input'!$B$5 | C16: =IF($A16<='1-Input'!$B$19,'1-Input'!$B$40,0) | D16: =IF($A16<='1-Input'!$B$19,0,IF($A16>'1-Input'!$B$47,0,IF($A16<'5-Pensioni'!$C$8,0,IF($A16='5-Pensioni'!$C$8,'5-Pensioni'!$C$18*'5-Pensioni'!$C$19,'5-Pensioni'!$C$18))+IF($A16<'5-Pensioni'!$B$8,0,IF($A16='5-Pensioni'!$B$8,'5-Pensioni'!$B$18*'5-Pensioni'!$B$19,'5-Pensioni'!$B$18)))) | E16: =IF($A16<='1-Input'!$B$19,0,IF($A16>'1-Input'!$B$47,0,MAX(0,'1-Input'!$B$13-D16))) | F16: =MIN(E16,G15) | G16: =G15-F16 | H16: =MAX(0,E16-F16)*$B$51 | I16: =IF($A16<='1-Input'!$B$19,(I15+C16)*(1+'1-Input'!$B$46),(I15-H16)*(1+'1-Input'!$B$46)) | J16: =IF($A16<='1-Input'!$B$19,(J15+C16)*(1+'3-Rendimento'!$D$15),(J15-MAX(0,E16-F16)*$C$51)*(1+'3-Rendimento'!$D$15)) | K16: =IF($A16<='1-Input'!$B$19,(K15+C16)*(1+'3-Rendimento'!$D$17),(K15-MAX(0,E16-F16)*$D$51)*(1+'3-Rendimento'!$D$17)) | L16: =IF($A16>'1-Input'!$B$19,"",(L15+C16)*(1+IF($A16='1-Input'!$B$19-1,'P-Parametri'!$B$54*'P-Parametri'!$B$52+(1-'P-Parametri'!$B$54)*('P-Parametri'!$C$42-'1-Input'!$B$18),IF($A16='1-Input'!$B$19,'P-Parametri'!$B$54*'P-Parametri'!$C$52+(1-'P-Parametri'!$B$54)*('P-Parametri'!$C$42-'1-Input'!$B$18),'1-Input'!$B$46))))
A17: =A16+1 | B17: =$A17-'1-Input'!$B$5 | C17: =IF($A17<='1-Input'!$B$19,'1-Input'!$B$40,0) | D17: =IF($A17<='1-Input'!$B$19,0,IF($A17>'1-Input'!$B$47,0,IF($A17<'5-Pensioni'!$C$8,0,IF($A17='5-Pensioni'!$C$8,'5-Pensioni'!$C$18*'5-Pensioni'!$C$19,'5-Pensioni'!$C$18))+IF($A17<'5-Pensioni'!$B$8,0,IF($A17='5-Pensioni'!$B$8,'5-Pensioni'!$B$18*'5-Pensioni'!$B$19,'5-Pensioni'!$B$18)))) | E17: =IF($A17<='1-Input'!$B$19,0,IF($A17>'1-Input'!$B$47,0,MAX(0,'1-Input'!$B$13-D17))) | F17: =MIN(E17,G16) | G17: =G16-F17 | H17: =MAX(0,E17-F17)*$B$51 | I17: =IF($A17<='1-Input'!$B$19,(I16+C17)*(1+'1-Input'!$B$46),(I16-H17)*(1+'1-Input'!$B$46)) | J17: =IF($A17<='1-Input'!$B$19,(J16+C17)*(1+'3-Rendimento'!$D$15),(J16-MAX(0,E17-F17)*$C$51)*(1+'3-Rendimento'!$D$15)) | K17: =IF($A17<='1-Input'!$B$19,(K16+C17)*(1+'3-Rendimento'!$D$17),(K16-MAX(0,E17-F17)*$D$51)*(1+'3-Rendimento'!$D$17)) | L17: =IF($A17>'1-Input'!$B$19,"",(L16+C17)*(1+IF($A17='1-Input'!$B$19-1,'P-Parametri'!$B$54*'P-Parametri'!$B$52+(1-'P-Parametri'!$B$54)*('P-Parametri'!$C$42-'1-Input'!$B$18),IF($A17='1-Input'!$B$19,'P-Parametri'!$B$54*'P-Parametri'!$C$52+(1-'P-Parametri'!$B$54)*('P-Parametri'!$C$42-'1-Input'!$B$18),'1-Input'!$B$46))))
A18: =A17+1 | B18: =$A18-'1-Input'!$B$5 | C18: =IF($A18<='1-Input'!$B$19,'1-Input'!$B$40,0) | D18: =IF($A18<='1-Input'!$B$19,0,IF($A18>'1-Input'!$B$47,0,IF($A18<'5-Pensioni'!$C$8,0,IF($A18='5-Pensioni'!$C$8,'5-Pensioni'!$C$18*'5-Pensioni'!$C$19,'5-Pensioni'!$C$18))+IF($A18<'5-Pensioni'!$B$8,0,IF($A18='5-Pensioni'!$B$8,'5-Pensioni'!$B$18*'5-Pensioni'!$B$19,'5-Pensioni'!$B$18)))) | E18: =IF($A18<='1-Input'!$B$19,0,IF($A18>'1-Input'!$B$47,0,MAX(0,'1-Input'!$B$13-D18))) | F18: =MIN(E18,G17) | G18: =G17-F18 | H18: =MAX(0,E18-F18)*$B$51 | I18: =IF($A18<='1-Input'!$B$19,(I17+C18)*(1+'1-Input'!$B$46),(I17-H18)*(1+'1-Input'!$B$46)) | J18: =IF($A18<='1-Input'!$B$19,(J17+C18)*(1+'3-Rendimento'!$D$15),(J17-MAX(0,E18-F18)*$C$51)*(1+'3-Rendimento'!$D$15)) | K18: =IF($A18<='1-Input'!$B$19,(K17+C18)*(1+'3-Rendimento'!$D$17),(K17-MAX(0,E18-F18)*$D$51)*(1+'3-Rendimento'!$D$17)) | L18: =IF($A18>'1-Input'!$B$19,"",(L17+C18)*(1+IF($A18='1-Input'!$B$19-1,'P-Parametri'!$B$54*'P-Parametri'!$B$52+(1-'P-Parametri'!$B$54)*('P-Parametri'!$C$42-'1-Input'!$B$18),IF($A18='1-Input'!$B$19,'P-Parametri'!$B$54*'P-Parametri'!$C$52+(1-'P-Parametri'!$B$54)*('P-Parametri'!$C$42-'1-Input'!$B$18),'1-Input'!$B$46))))
... A45: =A44+1 | B45: =$A45-'1-Input'!$B$5 | C45: =IF($A45<='1-Input'!$B$19,'1-Input'!$B$40,0) | D45: =IF($A45<='1-Input'!$B$19,0,IF($A45>'1-Input'!$B$47,0,IF($A45<'5-Pensioni'!$C$8,0,IF($A45='5-Pensioni'!$C$8,'5-Pensioni'!$C$18*'5-Pensioni'!$C$19,'5-Pensioni'!$C$18))+IF($A45<'5-Pensioni'!$B$8,0,IF($A45='5-Pensioni'!$B$8,'5-Pensioni'!$B$18*'5-Pensioni'!$B$19,'5-Pensioni'!$B$18)))) | E45: =IF($A45<='1-Input'!$B$19,0,IF($A45>'1-Input'!$B$47,0,MAX(0,'1-Input'!$B$13-D45))) | F45: =MIN(E45,G44) | G45: =G44-F45 | H45: =MAX(0,E45-F45)*$B$51 | I45: =IF($A45<='1-Input'!$B$19,(I44+C45)*(1+'1-Input'!$B$46),(I44-H45)*(1+'1-Input'!$B$46)) | J45: =IF($A45<='1-Input'!$B$19,(J44+C45)*(1+'3-Rendimento'!$D$15),(J44-MAX(0,E45-F45)*$C$51)*(1+'3-Rendimento'!$D$15)) | K45: =IF($A45<='1-Input'!$B$19,(K44+C45)*(1+'3-Rendimento'!$D$17),(K44-MAX(0,E45-F45)*$D$51)*(1+'3-Rendimento'!$D$17)) | L45: =IF($A45>'1-Input'!$B$19,"",(L44+C45)*(1+IF($A45='1-Input'!$B$19-1,'P-Parametri'!$B$54*'P-Parametri'!$B$52+(1-'P-Parametri'!$B$54)*('P-Parametri'!$C$42-'1-Input'!$B$18),IF($A45='1-Input'!$B$19,'P-Parametri'!$B$54*'P-Parametri'!$C$52+(1-'P-Parametri'!$B$54)*('P-Parametri'!$C$42-'1-Input'!$B$18),'1-Input'!$B$46))))
A47: I FATTORI DI LORDIZZAZIONE PER RENDIMENTO
A48: Voce | B48: Centrale | C48: Pavimento | D48: Tetto
A49: Capitale al ritiro | B49: =INDEX(I6:I45,MATCH('1-Input'!$B$19,A6:A45,0)) | C49: =INDEX(J6:J45,MATCH('1-Input'!$B$19,A6:A45,0)) | D49: =INDEX(K6:K45,MATCH('1-Input'!$B$19,A6:A45,0))
A50: Base di costo al ritiro | B50: ='2-Composizione'!$B$37+'1-Input'!$B$50*'1-Input'!$B$40
A51: Fattore di lordizzazione G (latente col floor a zero) | B51: =1/(1-'P-Parametri'!$B$31*MAX(0,(B49-$B$50)/B49)) | C51: =1/(1-'P-Parametri'!$B$31*MAX(0,(C49-$B$50)/C49)) | D51: =1/(1-'P-Parametri'!$B$31*MAX(0,(D49-$B$50)/D49))
A53: L'ANNO DEI DUE MILIONI
A54: Voce | B54: Centrale | C54: Pavimento | D54: Tetto
A55: Distanza dal target alla fine dell'anno di ritiro | B55: =B49-'P-Parametri'!$B$47 | C55: =C49-'P-Parametri'!$B$47 | D55: =D49-'P-Parametri'!$B$47
A56: Anno in cui il capitale tocca il target | B56: =INDEX($A$6:$A$45,MATCH('P-Parametri'!$B$47,I6:I45,1)+1) | C56: =INDEX($A$6:$A$45,MATCH('P-Parametri'!$B$47,J6:J45,1)+1) | D56: =INDEX($A$6:$A$45,MATCH('P-Parametri'!$B$47,K6:K45,1)+1)
A57: Eta' di Chiara in quell'anno | B57: =B56-'1-Input'!$B$5 | C57: =C56-'1-Input'!$B$5 | D57: =D56-'1-Input'!$B$5
A58: Risparmio annuo che servirebbe per arrivarci entro il ritiro | B58: =('P-Parametri'!$B$47-'2-Composizione'!$B$36*(1+'1-Input'!$B$46)^'1-Input'!$B$50)/((1+'1-Input'!$B$46)*(((1+'1-Input'!$B$46)^'1-Input'!$B$50-1)/'1-Input'!$B$46))
A59: Quanto resterebbe per vivere | B59: ='1-Input'!$B$38-B58
A61: LA SEQUENZA SFAVOREVOLE — scenario illustrativo, non probabilistico
A62: Capitale al ritiro con la sequenza sfavorevole | B62: =INDEX(L6:L45,MATCH('1-Input'!$B$19,A6:A45,0))
A63: Variazione contro il capitale centrale | B63: =B62/B49-1 | C63: =B62-B49
A64: Posizione contro il fabbisogno dello scenario prudente | B64: ='11-Banda'!$D$18 | C64: =B62-B64
A66: CONVENZIONE DEL DECUMULO, DICHIARATA E RIPRODUCIBILE: il TFR in cassa si consuma per primo, i prelievi dal portafoglio sono lordizzati col fattore G del rendimento della colonna, le pensioni entrano alle loro decorrenze con mezza annualita' il primo anno, e i versamenti si fermano alla fine dell'anno di ritiro.
A67: SEQUENZA SFAVOREVOLE — i crolli cadono nei DUE ANNI FINALI dell'accumulo e mordono sulla SOLA gamba azionaria; la gamba obbligazionaria rende il suo atteso. E' uno scenario ILLUSTRATIVO, non probabilistico.
A68: L'anno in cui il capitale tocca il target si raggiunge SENZA PIU' VERSARE: il capitale cresce mentre la coppia ci vive dentro. E' un'ipotesi dichiarata, non una previsione.

Sheet 9-Leve
A1: Le otto leve
A2: Strumento informativo / divulgativo. NON è consulenza finanziaria. I valori sono indicativi al 2026 e vanno verificati col tuo consulente.
A4: LA TABELLA D'IMPATTO — le leve si misurano nell'IPOTESI PRUDENTE
A5: Leva | B5: Fabbisogno (prudente) | C5: Delta posizione netta (prudente) | D5: Fabbisogno (centrale) | E5: Delta posizione netta (centrale)
A6: 1 — Posticipo di 2 anni | B6: =C76 | C6: =C79 | D6: =L76 | E6: =L79
A7: 2 — Spesa meno 10% da oggi e per sempre | B7: =D76 | C7: =D79 | D7: =M76 | E7: =M79
A8: 3 — Spesa obiettivo meno 10% solo dopo il ritiro | B8: =E76 | C8: =E79 | D8: =N76 | E8: =N79
A9: 4 — Posticipo di 1 anno | B9: =F76 | C9: =F79 | D9: =O76 | E9: =O79
A10: 5 — Costi meno 0,5% l'anno | B10: =G76 | C10: =G79 | D10: =P76 | E10: =P79
A11: 6 — Da 70/30 a 85/15 | B11: =H76 | C11: =H79 | D11: =Q76 | E11: =Q79
A12: 7 — Risparmio +3.000 € l'anno | B12: =I76 | C12: =I79 | D12: =R76 | E12: =R79
A13: 8 — Glide path da 70/30 a 40/60 | B13: =J76 | C13: =J79 | D13: =S76 | E13: =S79
A14: BASE — posizione netta di riferimento | B14: =B76 | C14: =B78 | D14: =K76 | E14: =K78
A16: LE DUE LEVE DI TESTA, LE CONVERSIONI E I CONTROLLI
A17: Le due leve di testa nell'ipotesi prudente — maggiore / minore | B17: =MAX(C6,C7) | C17: =MIN(C6,C7)
A18: Distanza fra le due leve di testa | B18: =B17/C17-1
A19: Rapporto delle due di testa con la terza leva vera (i costi) | B19: =B17/C10 | C19: =C17/C10
A20: Rapporto con la riga 3 (cambio dell'obiettivo) e con la riga 4 | B20: =B17/C8 | C20: =B17/C9
A21: Somma delle due di testa / somma delle righe da 3 a 7 | B21: =B17+C17 | C21: =C8+C9+C10+C11+C12
A22: Un anno di posticipo, convertito in risparmio annuo | B22: =C9/((1+'1-Input'!$B$46)*(((1+'1-Input'!$B$46)^'1-Input'!$B$50-1)/'1-Input'!$B$46))
A23: …in quota del risparmio attuale | B23: =B22/'1-Input'!$B$40
A24: Quanto valgono i dieci anni sulla pensione (netti l'anno, a vita) | B24: ='5-Pensioni'!$B$56
A25: IL MOTORE — ipotesi prudente (colonne B:J) e scenario centrale (K:S)
A26: PERCHE' L'IPOTESI PRUDENTE. Nello scenario centrale piu' di una leva porta il fabbisogno a zero: li' la classifica misura il pavimento, non le leve. Nel prudente il floor non viene mai toccato, ed e' li' che le leve si possono confrontare. Il floor a zero e' dichiarato: un fabbisogno negativo significa soltanto che pensioni e liquidazione bastano.
A27: SCENARIO | B27: BASE · prudente | C27: 1 — Posticipo di 2 anni · prudente | D27: 2 — Spesa meno 10% da oggi e per sempre · prudente | E27: 3 — Spesa obiettivo meno 10% solo dopo il ritiro · prudente | F27: 4 — Posticipo di 1 anno · prudente | G27: 5 — Costi meno 0,5% l'anno · prudente | H27: 6 — Da 70/30 a 85/15 · prudente | I27: 7 — Risparmio +3.000 € l'anno · prudente | J27: 8 — Glide path da 70/30 a 40/60 · prudente | K27: BASE · centrale | L27: 1 — Posticipo di 2 anni · centrale | M27: 2 — Spesa meno 10% da oggi e per sempre · centrale | N27: 3 — Spesa obiettivo meno 10% solo dopo il ritiro · centrale | O27: 4 — Posticipo di 1 anno · centrale | P27: 5 — Costi meno 0,5% l'anno · centrale | Q27: 6 — Da 70/30 a 85/15 · centrale | R27: 7 — Risparmio +3.000 € l'anno · centrale | S27: 8 — Glide path da 70/30 a 40/60 · centrale
A28: Spesa prima del ritiro | B28: ='1-Input'!$B$13 | C28: ='1-Input'!$B$13 | D28: ='1-Input'!$B$13*(1-'P-Parametri'!$B$61) | E28: ='1-Input'!$B$13 | F28: ='1-Input'!$B$13 | G28: ='1-Input'!$B$13 | H28: ='1-Input'!$B$13 | I28: ='1-Input'!$B$13 | J28: ='1-Input'!$B$13 | K28: ='1-Input'!$B$13 | L28: ='1-Input'!$B$13 | M28: ='1-Input'!$B$13*(1-'P-Parametri'!$B$61) | N28: ='1-Input'!$B$13 | O28: ='1-Input'!$B$13 | P28: ='1-Input'!$B$13 | Q28: ='1-Input'!$B$13 | R28: ='1-Input'!$B$13 | S28: ='1-Input'!$B$13
A29: Spesa dopo il ritiro | B29: ='1-Input'!$B$13 | C29: ='1-Input'!$B$13 | D29: ='1-Input'!$B$13*(1-'P-Parametri'!$B$61) | E29: ='1-Input'!$B$13*(1-'P-Parametri'!$B$61) | F29: ='1-Input'!$B$13 | G29: ='1-Input'!$B$13 | H29: ='1-Input'!$B$13 | I29: ='1-Input'!$B$13 | J29: ='1-Input'!$B$13 | K29: ='1-Input'!$B$13 | L29: ='1-Input'!$B$13 | M29: ='1-Input'!$B$13*(1-'P-Parametri'!$B$61) | N29: ='1-Input'!$B$13*(1-'P-Parametri'!$B$61) | O29: ='1-Input'!$B$13 | P29: ='1-Input'!$B$13 | Q29: ='1-Input'!$B$13 | R29: ='1-Input'!$B$13 | S29: ='1-Input'!$B$13
A30: Risparmio annuo | B30: ='1-Input'!$B$40 | C30: ='1-Input'!$B$40 | D30: =ROUND('1-Input'!$B$38-'1-Input'!$B$13*(1-'P-Parametri'!$B$61),0) | E30: ='1-Input'!$B$40 | F30: ='1-Input'!$B$40 | G30: ='1-Input'!$B$40 | H30: ='1-Input'!$B$40 | I30: ='1-Input'!$B$40+'P-Parametri'!$B$62 | J30: ='1-Input'!$B$40 | K30: ='1-Input'!$B$40 | L30: ='1-Input'!$B$40 | M30: =ROUND('1-Input'!$B$38-'1-Input'!$B$13*(1-'P-Parametri'!$B$61),0) | N30: ='1-Input'!$B$40 | O30: ='1-Input'!$B$40 | P30: ='1-Input'!$B$40 | Q30: ='1-Input'!$B$40 | R30: ='1-Input'!$B$40+'P-Parametri'!$B$62 | S30: ='1-Input'!$B$40
A31: Anni di lavoro in piu' | B31: =0 | C31: =2 | D31: =0 | E31: =0 | F31: =1 | G31: =0 | H31: =0 | I31: =0 | J31: =0 | K31: =0 | L31: =2 | M31: =0 | N31: =0 | O31: =1 | P31: =0 | Q31: =0 | R31: =0 | S31: =0
A32: Requisito anagrafico: anni in piu' | B32: ='1-Input'!$B$22+2 | C32: ='1-Input'!$B$22+2 | D32: ='1-Input'!$B$22+2 | E32: ='1-Input'!$B$22+2 | F32: ='1-Input'!$B$22+2 | G32: ='1-Input'!$B$22+2 | H32: ='1-Input'!$B$22+2 | I32: ='1-Input'!$B$22+2 | J32: ='1-Input'!$B$22+2 | K32: ='1-Input'!$B$22 | L32: ='1-Input'!$B$22 | M32: ='1-Input'!$B$22 | N32: ='1-Input'!$B$22 | O32: ='1-Input'!$B$22 | P32: ='1-Input'!$B$22 | Q32: ='1-Input'!$B$22 | R32: ='1-Input'!$B$22 | S32: ='1-Input'!$B$22
A33: Fattore sulle pensioni lorde | B33: =1-'P-Parametri'!$B$51 | C33: =1-'P-Parametri'!$B$51 | D33: =1-'P-Parametri'!$B$51 | E33: =1-'P-Parametri'!$B$51 | F33: =1-'P-Parametri'!$B$51 | G33: =1-'P-Parametri'!$B$51 | H33: =1-'P-Parametri'!$B$51 | I33: =1-'P-Parametri'!$B$51 | J33: =1-'P-Parametri'!$B$51 | K33: =1 | L33: =1 | M33: =1 | N33: =1 | O33: =1 | P33: =1 | Q33: =1 | R33: =1 | S33: =1
A34: Anno di orizzonte | B34: ='1-Input'!$B$5+'P-Parametri'!$C$65 | C34: ='1-Input'!$B$5+'P-Parametri'!$C$65 | D34: ='1-Input'!$B$5+'P-Parametri'!$C$65 | E34: ='1-Input'!$B$5+'P-Parametri'!$C$65 | F34: ='1-Input'!$B$5+'P-Parametri'!$C$65 | G34: ='1-Input'!$B$5+'P-Parametri'!$C$65 | H34: ='1-Input'!$B$5+'P-Parametri'!$C$65 | I34: ='1-Input'!$B$5+'P-Parametri'!$C$65 | J34: ='1-Input'!$B$5+'P-Parametri'!$C$65 | K34: ='1-Input'!$B$47 | L34: ='1-Input'!$B$47 | M34: ='1-Input'!$B$47 | N34: ='1-Input'!$B$47 | O34: ='1-Input'!$B$47 | P34: ='1-Input'!$B$47 | Q34: ='1-Input'!$B$47 | R34: ='1-Input'!$B$47 | S34: ='1-Input'!$B$47
A35: Rendimento lordo — accumulo | B35: ='1-Input'!$B$17 | C35: ='1-Input'!$B$17 | D35: ='1-Input'!$B$17 | E35: ='1-Input'!$B$17 | F35: ='1-Input'!$B$17 | G35: ='1-Input'!$B$17+'P-Parametri'!$B$60 | H35: ='P-Parametri'!$B$42*'P-Parametri'!$B$63+'P-Parametri'!$C$42*(1-'P-Parametri'!$B$63) | I35: ='1-Input'!$B$17 | J35: ='1-Input'!$B$17 | K35: ='1-Input'!$B$17 | L35: ='1-Input'!$B$17 | M35: ='1-Input'!$B$17 | N35: ='1-Input'!$B$17 | O35: ='1-Input'!$B$17 | P35: ='1-Input'!$B$17+'P-Parametri'!$B$60 | Q35: ='P-Parametri'!$B$42*'P-Parametri'!$B$63+'P-Parametri'!$C$42*(1-'P-Parametri'!$B$63) | R35: ='1-Input'!$B$17 | S35: ='1-Input'!$B$17
A36: Rendimento lordo — decumulo | B36: ='1-Input'!$B$17 | C36: ='1-Input'!$B$17 | D36: ='1-Input'!$B$17 | E36: ='1-Input'!$B$17 | F36: ='1-Input'!$B$17 | G36: ='1-Input'!$B$17+'P-Parametri'!$B$60 | H36: ='P-Parametri'!$B$42*'P-Parametri'!$B$63+'P-Parametri'!$C$42*(1-'P-Parametri'!$B$63) | I36: ='1-Input'!$B$17 | J36: ='P-Parametri'!$B$64 | K36: ='1-Input'!$B$17 | L36: ='1-Input'!$B$17 | M36: ='1-Input'!$B$17 | N36: ='1-Input'!$B$17 | O36: ='1-Input'!$B$17 | P36: ='1-Input'!$B$17+'P-Parametri'!$B$60 | Q36: ='P-Parametri'!$B$42*'P-Parametri'!$B$63+'P-Parametri'!$C$42*(1-'P-Parametri'!$B$63) | R36: ='1-Input'!$B$17 | S36: ='P-Parametri'!$B$64
A37: Montante di Chiara al 2026 | B37: ='4-Montanti'!$B$9 | C37: ='4-Montanti'!$B$9 | D37: ='4-Montanti'!$B$9 | E37: ='4-Montanti'!$B$9 | F37: ='4-Montanti'!$B$9 | G37: ='4-Montanti'!$B$9 | H37: ='4-Montanti'!$B$9 | I37: ='4-Montanti'!$B$9 | ... S37: ='4-Montanti'!$B$9
A38: Montante del marito al 2026 | B38: ='4-Montanti'!$C$9 | C38: ='4-Montanti'!$C$9 | D38: ='4-Montanti'!$C$9 | E38: ='4-Montanti'!$C$9 | F38: ='4-Montanti'!$C$9 | G38: ='4-Montanti'!$C$9 | H38: ='4-Montanti'!$C$9 | I38: ='4-Montanti'!$C$9 | ... S38: ='4-Montanti'!$C$9
A39: Coefficiente di trasformazione — Chiara | B39: ='P-Parametri'!$B$21 | C39: ='P-Parametri'!$B$21 | D39: ='P-Parametri'!$B$21 | E39: ='P-Parametri'!$B$21 | F39: ='P-Parametri'!$B$21 | G39: ='P-Parametri'!$B$21 | H39: ='P-Parametri'!$B$21 | I39: ='P-Parametri'!$B$21 | ... S39: ='P-Parametri'!$B$21
A40: Coefficiente di trasformazione — marito | B40: ='P-Parametri'!$B$21 | C40: ='P-Parametri'!$B$21 | D40: ='P-Parametri'!$B$21 | E40: ='P-Parametri'!$B$21 | F40: ='P-Parametri'!$B$21 | G40: ='P-Parametri'!$B$21 | H40: ='P-Parametri'!$B$21 | I40: ='P-Parametri'!$B$21 | ... S40: ='P-Parametri'!$B$21
A41: Anno di decorrenza base — Chiara | B41: ='1-Input'!$B$51 | C41: ='1-Input'!$B$51 | D41: ='1-Input'!$B$51 | E41: ='1-Input'!$B$51 | F41: ='1-Input'!$B$51 | G41: ='1-Input'!$B$51 | H41: ='1-Input'!$B$51 | I41: ='1-Input'!$B$51 | ... S41: ='1-Input'!$B$51
A42: Mese di decorrenza — Chiara | B42: ='1-Input'!$C$51 | C42: ='1-Input'!$C$51 | D42: ='1-Input'!$C$51 | E42: ='1-Input'!$C$51 | F42: ='1-Input'!$C$51 | G42: ='1-Input'!$C$51 | H42: ='1-Input'!$C$51 | I42: ='1-Input'!$C$51 | ... S42: ='1-Input'!$C$51
A43: Anno di decorrenza base — marito | B43: ='1-Input'!$B$52 | C43: ='1-Input'!$B$52 | D43: ='1-Input'!$B$52 | E43: ='1-Input'!$B$52 | F43: ='1-Input'!$B$52 | G43: ='1-Input'!$B$52 | H43: ='1-Input'!$B$52 | I43: ='1-Input'!$B$52 | ... S43: ='1-Input'!$B$52
A44: Mese di decorrenza — marito | B44: ='1-Input'!$C$52 | C44: ='1-Input'!$C$52 | D44: ='1-Input'!$C$52 | E44: ='1-Input'!$C$52 | F44: ='1-Input'!$C$52 | G44: ='1-Input'!$C$52 | H44: ='1-Input'!$C$52 | I44: ='1-Input'!$C$52 | ... S44: ='1-Input'!$C$52
A45: Capitale sostitutivo (0 = calcolato dal motore) | B45: =0 | C45: =0 | D45: =0 | E45: =0 | F45: =0 | G45: =0 | H45: =0 | I45: =0 | J45: ='10-Glide'!$B$21 | K45: =0 | L45: =0 | M45: =0 | N45: =0 | O45: =0 | P45: =0 | Q45: =0 | R45: =0 | S45: ='10-Glide'!$B$21
A46: Rendimento netto bollo — accumulo | B46: =B35-'1-Input'!$B$18 | C46: =C35-'1-Input'!$B$18 | D46: =D35-'1-Input'!$B$18 | E46: =E35-'1-Input'!$B$18 | F46: =F35-'1-Input'!$B$18 | G46: =G35-'1-Input'!$B$18 | H46: =H35-'1-Input'!$B$18 | I46: =I35-'1-Input'!$B$18 | ... S46: =S35-'1-Input'!$B$18
A47: Rendimento netto bollo — decumulo | B47: =B36-'1-Input'!$B$18 | C47: =C36-'1-Input'!$B$18 | D47: =D36-'1-Input'!$B$18 | E47: =E36-'1-Input'!$B$18 | F47: =F36-'1-Input'!$B$18 | G47: =G36-'1-Input'!$B$18 | H47: =H36-'1-Input'!$B$18 | I47: =I36-'1-Input'!$B$18 | ... S47: =S36-'1-Input'!$B$18
A48: Anno di valutazione | B48: ='1-Input'!$B$19+B31 | C48: ='1-Input'!$B$19+C31 | D48: ='1-Input'!$B$19+D31 | E48: ='1-Input'!$B$19+E31 | F48: ='1-Input'!$B$19+F31 | G48: ='1-Input'!$B$19+G31 | H48: ='1-Input'!$B$19+H31 | I48: ='1-Input'!$B$19+I31 | ... S48: ='1-Input'!$B$19+S31
A49: Anni di contribuzione dopo il 2026 | B49: ='1-Input'!$B$19-'1-Input'!$C$16+B31 | C49: ='1-Input'!$B$19-'1-Input'!$C$16+C31 | D49: ='1-Input'!$B$19-'1-Input'!$C$16+D31 | E49: ='1-Input'!$B$19-'1-Input'!$C$16+E31 | F49: ='1-Input'!$B$19-'1-Input'!$C$16+F31 | G49: ='1-Input'!$B$19-'1-Input'!$C$16+G31 | H49: ='1-Input'!$B$19-'1-Input'!$C$16+H31 | I49: ='1-Input'!$B$19-'1-Input'!$C$16+I31 | ... S49: ='1-Input'!$B$19-'1-Input'!$C$16+S31
A50: Anno di decorrenza effettivo — Chiara | B50: =B41+B32 | C50: =C41+C32 | D50: =D41+D32 | E50: =E41+E32 | F50: =F41+F32 | G50: =G41+G32 | H50: =H41+H32 | I50: =I41+I32 | ... S50: =S41+S32
A51: Anno di decorrenza effettivo — marito | B51: =B43+B32 | C51: =C43+C32 | D51: =D43+D32 | E51: =E43+E32 | F51: =F43+F32 | G51: =G43+G32 | H51: =H43+H32 | I51: =I43+I32 | ... S51: =S43+S32
A52: Anni di sola rivalutazione — Chiara | B52: =B50-('1-Input'!$C$16+1)+(B42-1)/12-B49 | C52: =C50-('1-Input'!$C$16+1)+(C42-1)/12-C49 | D52: =D50-('1-Input'!$C$16+1)+(D42-1)/12-D49 | E52: =E50-('1-Input'!$C$16+1)+(E42-1)/12-E49 | F52: =F50-('1-Input'!$C$16+1)+(F42-1)/12-F49 | G52: =G50-('1-Input'!$C$16+1)+(G42-1)/12-G49 | H52: =H50-('1-Input'!$C$16+1)+(H42-1)/12-H49 | I52: =I50-('1-Input'!$C$16+1)+(I42-1)/12-I49 | ... S52: =S50-('1-Input'!$C$16+1)+(S42-1)/12-S49
A53: Anni di sola rivalutazione — marito | B53: =B51-('1-Input'!$C$16+1)+(B44-1)/12-B49 | C53: =C51-('1-Input'!$C$16+1)+(C44-1)/12-C49 | D53: =D51-('1-Input'!$C$16+1)+(D44-1)/12-D49 | E53: =E51-('1-Input'!$C$16+1)+(E44-1)/12-E49 | F53: =F51-('1-Input'!$C$16+1)+(F44-1)/12-F49 | G53: =G51-('1-Input'!$C$16+1)+(G44-1)/12-G49 | H53: =H51-('1-Input'!$C$16+1)+(H44-1)/12-H49 | I53: =I51-('1-Input'!$C$16+1)+(I44-1)/12-I49 | ... S53: =S51-('1-Input'!$C$16+1)+(S44-1)/12-S49
A54: Frazione della prima annualita' — Chiara | B54: =IF(B42=1,1,'P-Parametri'!$B$59) | C54: =IF(C42=1,1,'P-Parametri'!$B$59) | D54: =IF(D42=1,1,'P-Parametri'!$B$59) | E54: =IF(E42=1,1,'P-Parametri'!$B$59) | F54: =IF(F42=1,1,'P-Parametri'!$B$59) | G54: =IF(G42=1,1,'P-Parametri'!$B$59) | H54: =IF(H42=1,1,'P-Parametri'!$B$59) | I54: =IF(I42=1,1,'P-Parametri'!$B$59) | ... S54: =IF(S42=1,1,'P-Parametri'!$B$59)
A55: Frazione della prima annualita' — marito | B55: =IF(B44=1,1,'P-Parametri'!$B$59) | C55: =IF(C44=1,1,'P-Parametri'!$B$59) | D55: =IF(D44=1,1,'P-Parametri'!$B$59) | E55: =IF(E44=1,1,'P-Parametri'!$B$59) | F55: =IF(F44=1,1,'P-Parametri'!$B$59) | G55: =IF(G44=1,1,'P-Parametri'!$B$59) | H55: =IF(H44=1,1,'P-Parametri'!$B$59) | I55: =IF(I44=1,1,'P-Parametri'!$B$59) | ... S55: =IF(S44=1,1,'P-Parametri'!$B$59)
A56: Montante alla decorrenza — Chiara | B56: =(B37*(1+'1-Input'!$B$21)^B49+'1-Input'!$B$48*(IF('1-Input'!$B$21=0,B49,((1+'1-Input'!$B$21)^B49-1)/'1-Input'!$B$21)))*(1+'1-Input'!$B$21)^B52 | C56: =(C37*(1+'1-Input'!$B$21)^C49+'1-Input'!$B$48*(IF('1-Input'!$B$21=0,C49,((1+'1-Input'!$B$21)^C49-1)/'1-Input'!$B$21)))*(1+'1-Input'!$B$21)^C52 | D56: =(D37*(1+'1-Input'!$B$21)^D49+'1-Input'!$B$48*(IF('1-Input'!$B$21=0,D49,((1+'1-Input'!$B$21)^D49-1)/'1-Input'!$B$21)))*(1+'1-Input'!$B$21)^D52 | E56: =(E37*(1+'1-Input'!$B$21)^E49+'1-Input'!$B$48*(IF('1-Input'!$B$21=0,E49,((1+'1-Input'!$B$21)^E49-1)/'1-Input'!$B$21)))*(1+'1-Input'!$B$21)^E52 | F56: =(F37*(1+'1-Input'!$B$21)^F49+'1-Input'!$B$48*(IF('1-Input'!$B$21=0,F49,((1+'1-Input'!$B$21)^F49-1)/'1-Input'!$B$21)))*(1+'1-Input'!$B$21)^F52 | G56: =(G37*(1+'1-Input'!$B$21)^G49+'1-Input'!$B$48*(IF('1-Input'!$B$21=0,G49,((1+'1-Input'!$B$21)^G49-1)/'1-Input'!$B$21)))*(1+'1-Input'!$B$21)^G52 | H56: =(H37*(1+'1-Input'!$B$21)^H49+'1-Input'!$B$48*(IF('1-Input'!$B$21=0,H49,((1+'1-Input'!$B$21)^H49-1)/'1-Input'!$B$21)))*(1+'1-Input'!$B$21)^H52 | I56: =(I37*(1+'1-Input'!$B$21)^I49+'1-Input'!$B$48*(IF('1-Input'!$B$21=0,I49,((1+'1-Input'!$B$21)^I49-1)/'1-Input'!$B$21)))*(1+'1-Input'!$B$21)^I52 | ... S56: =(S37*(1+'1-Input'!$B$21)^S49+'1-Input'!$B$48*(IF('1-Input'!$B$21=0,S49,((1+'1-Input'!$B$21)^S49-1)/'1-Input'!$B$21)))*(1+'1-Input'!$B$21)^S52
A57: Montante alla decorrenza — marito | B57: =(B38*(1+'1-Input'!$B$21)^B49+'1-Input'!$C$48*(IF('1-Input'!$B$21=0,B49,((1+'1-Input'!$B$21)^B49-1)/'1-Input'!$B$21)))*(1+'1-Input'!$B$21)^B53 | C57: =(C38*(1+'1-Input'!$B$21)^C49+'1-Input'!$C$48*(IF('1-Input'!$B$21=0,C49,((1+'1-Input'!$B$21)^C49-1)/'1-Input'!$B$21)))*(1+'1-Input'!$B$21)^C53 | D57: =(D38*(1+'1-Input'!$B$21)^D49+'1-Input'!$C$48*(IF('1-Input'!$B$21=0,D49,((1+'1-Input'!$B$21)^D49-1)/'1-Input'!$B$21)))*(1+'1-Input'!$B$21)^D53 | E57: =(E38*(1+'1-Input'!$B$21)^E49+'1-Input'!$C$48*(IF('1-Input'!$B$21=0,E49,((1+'1-Input'!$B$21)^E49-1)/'1-Input'!$B$21)))*(1+'1-Input'!$B$21)^E53 | F57: =(F38*(1+'1-Input'!$B$21)^F49+'1-Input'!$C$48*(IF('1-Input'!$B$21=0,F49,((1+'1-Input'!$B$21)^F49-1)/'1-Input'!$B$21)))*(1+'1-Input'!$B$21)^F53 | G57: =(G38*(1+'1-Input'!$B$21)^G49+'1-Input'!$C$48*(IF('1-Input'!$B$21=0,G49,((1+'1-Input'!$B$21)^G49-1)/'1-Input'!$B$21)))*(1+'1-Input'!$B$21)^G53 | H57: =(H38*(1+'1-Input'!$B$21)^H49+'1-Input'!$C$48*(IF('1-Input'!$B$21=0,H49,((1+'1-Input'!$B$21)^H49-1)/'1-Input'!$B$21)))*(1+'1-Input'!$B$21)^H53 | I57: =(I38*(1+'1-Input'!$B$21)^I49+'1-Input'!$C$48*(IF('1-Input'!$B$21=0,I49,((1+'1-Input'!$B$21)^I49-1)/'1-Input'!$B$21)))*(1+'1-Input'!$B$21)^I53 | ... S57: =(S38*(1+'1-Input'!$B$21)^S49+'1-Input'!$C$48*(IF('1-Input'!$B$21=0,S49,((1+'1-Input'!$B$21)^S49-1)/'1-Input'!$B$21)))*(1+'1-Input'!$B$21)^S53
A58: Pensione lorda — Chiara | B58: =B56*B39*B33 | C58: =C56*C39*C33 | D58: =D56*D39*D33 | E58: =E56*E39*E33 | F58: =F56*F39*F33 | G58: =G56*G39*G33 | H58: =H56*H39*H33 | I58: =I56*I39*I33 | ... S58: =S56*S39*S33
A59: Pensione lorda — marito | B59: =B57*B40*B33 | C59: =C57*C40*C33 | D59: =D57*D40*D33 | E59: =E57*E40*E33 | F59: =F57*F40*F33 | G59: =G57*G40*G33 | H59: =H57*H40*H33 | I59: =I57*I40*I33 | ... S59: =S57*S40*S33
A60: IRPEF lorda — Chiara | B60: =IF(B58<='P-Parametri'!$B$6,'P-Parametri'!$C$6*B58,IF(B58<='P-Parametri'!$B$7,'P-Parametri'!$B$9+'P-Parametri'!$C$7*(B58-'P-Parametri'!$B$6),'P-Parametri'!$B$10+'P-Parametri'!$C$8*(B58-'P-Parametri'!$B$7))) | C60: =IF(C58<='P-Parametri'!$B$6,'P-Parametri'!$C$6*C58,IF(C58<='P-Parametri'!$B$7,'P-Parametri'!$B$9+'P-Parametri'!$C$7*(C58-'P-Parametri'!$B$6),'P-Parametri'!$B$10+'P-Parametri'!$C$8*(C58-'P-Parametri'!$B$7))) | D60: =IF(D58<='P-Parametri'!$B$6,'P-Parametri'!$C$6*D58,IF(D58<='P-Parametri'!$B$7,'P-Parametri'!$B$9+'P-Parametri'!$C$7*(D58-'P-Parametri'!$B$6),'P-Parametri'!$B$10+'P-Parametri'!$C$8*(D58-'P-Parametri'!$B$7))) | E60: =IF(E58<='P-Parametri'!$B$6,'P-Parametri'!$C$6*E58,IF(E58<='P-Parametri'!$B$7,'P-Parametri'!$B$9+'P-Parametri'!$C$7*(E58-'P-Parametri'!$B$6),'P-Parametri'!$B$10+'P-Parametri'!$C$8*(E58-'P-Parametri'!$B$7))) | F60: =IF(F58<='P-Parametri'!$B$6,'P-Parametri'!$C$6*F58,IF(F58<='P-Parametri'!$B$7,'P-Parametri'!$B$9+'P-Parametri'!$C$7*(F58-'P-Parametri'!$B$6),'P-Parametri'!$B$10+'P-Parametri'!$C$8*(F58-'P-Parametri'!$B$7))) | G60: =IF(G58<='P-Parametri'!$B$6,'P-Parametri'!$C$6*G58,IF(G58<='P-Parametri'!$B$7,'P-Parametri'!$B$9+'P-Parametri'!$C$7*(G58-'P-Parametri'!$B$6),'P-Parametri'!$B$10+'P-Parametri'!$C$8*(G58-'P-Parametri'!$B$7))) | H60: =IF(H58<='P-Parametri'!$B$6,'P-Parametri'!$C$6*H58,IF(H58<='P-Parametri'!$B$7,'P-Parametri'!$B$9+'P-Parametri'!$C$7*(H58-'P-Parametri'!$B$6),'P-Parametri'!$B$10+'P-Parametri'!$C$8*(H58-'P-Parametri'!$B$7))) | I60: =IF(I58<='P-Parametri'!$B$6,'P-Parametri'!$C$6*I58,IF(I58<='P-Parametri'!$B$7,'P-Parametri'!$B$9+'P-Parametri'!$C$7*(I58-'P-Parametri'!$B$6),'P-Parametri'!$B$10+'P-Parametri'!$C$8*(I58-'P-Parametri'!$B$7))) | ... S60: =IF(S58<='P-Parametri'!$B$6,'P-Parametri'!$C$6*S58,IF(S58<='P-Parametri'!$B$7,'P-Parametri'!$B$9+'P-Parametri'!$C$7*(S58-'P-Parametri'!$B$6),'P-Parametri'!$B$10+'P-Parametri'!$C$8*(S58-'P-Parametri'!$B$7)))
A61: Detrazione da pensione — Chiara | B61: =IF(B58<='P-Parametri'!$C$12,'P-Parametri'!$B$12,IF(B58<='P-Parametri'!$B$6,'P-Parametri'!$B$13+'P-Parametri'!$C$13*('P-Parametri'!$B$6-B58)/'P-Parametri'!$D$13,IF(B58<='P-Parametri'!$B$7,'P-Parametri'!$B$14*('P-Parametri'!$B$7-B58)/'P-Parametri'!$C$14,0)))+IF(AND(B58>'P-Parametri'!$C$15,B58<'P-Parametri'!$D$15),'P-Parametri'!$B$15,0) | C61: =IF(C58<='P-Parametri'!$C$12,'P-Parametri'!$B$12,IF(C58<='P-Parametri'!$B$6,'P-Parametri'!$B$13+'P-Parametri'!$C$13*('P-Parametri'!$B$6-C58)/'P-Parametri'!$D$13,IF(C58<='P-Parametri'!$B$7,'P-Parametri'!$B$14*('P-Parametri'!$B$7-C58)/'P-Parametri'!$C$14,0)))+IF(AND(C58>'P-Parametri'!$C$15,C58<'P-Parametri'!$D$15),'P-Parametri'!$B$15,0) | D61: =IF(D58<='P-Parametri'!$C$12,'P-Parametri'!$B$12,IF(D58<='P-Parametri'!$B$6,'P-Parametri'!$B$13+'P-Parametri'!$C$13*('P-Parametri'!$B$6-D58)/'P-Parametri'!$D$13,IF(D58<='P-Parametri'!$B$7,'P-Parametri'!$B$14*('P-Parametri'!$B$7-D58)/'P-Parametri'!$C$14,0)))+IF(AND(D58>'P-Parametri'!$C$15,D58<'P-Parametri'!$D$15),'P-Parametri'!$B$15,0) | E61: =IF(E58<='P-Parametri'!$C$12,'P-Parametri'!$B$12,IF(E58<='P-Parametri'!$B$6,'P-Parametri'!$B$13+'P-Parametri'!$C$13*('P-Parametri'!$B$6-E58)/'P-Parametri'!$D$13,IF(E58<='P-Parametri'!$B$7,'P-Parametri'!$B$14*('P-Parametri'!$B$7-E58)/'P-Parametri'!$C$14,0)))+IF(AND(E58>'P-Parametri'!$C$15,E58<'P-Parametri'!$D$15),'P-Parametri'!$B$15,0) | F61: =IF(F58<='P-Parametri'!$C$12,'P-Parametri'!$B$12,IF(F58<='P-Parametri'!$B$6,'P-Parametri'!$B$13+'P-Parametri'!$C$13*('P-Parametri'!$B$6-F58)/'P-Parametri'!$D$13,IF(F58<='P-Parametri'!$B$7,'P-Parametri'!$B$14*('P-Parametri'!$B$7-F58)/'P-Parametri'!$C$14,0)))+IF(AND(F58>'P-Parametri'!$C$15,F58<'P-Parametri'!$D$15),'P-Parametri'!$B$15,0) | G61: =IF(G58<='P-Parametri'!$C$12,'P-Parametri'!$B$12,IF(G58<='P-Parametri'!$B$6,'P-Parametri'!$B$13+'P-Parametri'!$C$13*('P-Parametri'!$B$6-G58)/'P-Parametri'!$D$13,IF(G58<='P-Parametri'!$B$7,'P-Parametri'!$B$14*('P-Parametri'!$B$7-G58)/'P-Parametri'!$C$14,0)))+IF(AND(G58>'P-Parametri'!$C$15,G58<'P-Parametri'!$D$15),'P-Parametri'!$B$15,0) | H61: =IF(H58<='P-Parametri'!$C$12,'P-Parametri'!$B$12,IF(H58<='P-Parametri'!$B$6,'P-Parametri'!$B$13+'P-Parametri'!$C$13*('P-Parametri'!$B$6-H58)/'P-Parametri'!$D$13,IF(H58<='P-Parametri'!$B$7,'P-Parametri'!$B$14*('P-Parametri'!$B$7-H58)/'P-Parametri'!$C$14,0)))+IF(AND(H58>'P-Parametri'!$C$15,H58<'P-Parametri'!$D$15),'P-Parametri'!$B$15,0) | I61: =IF(I58<='P-Parametri'!$C$12,'P-Parametri'!$B$12,IF(I58<='P-Parametri'!$B$6,'P-Parametri'!$B$13+'P-Parametri'!$C$13*('P-Parametri'!$B$6-I58)/'P-Parametri'!$D$13,IF(I58<='P-Parametri'!$B$7,'P-Parametri'!$B$14*('P-Parametri'!$B$7-I58)/'P-Parametri'!$C$14,0)))+IF(AND(I58>'P-Parametri'!$C$15,I58<'P-Parametri'!$D$15),'P-Parametri'!$B$15,0) | ... S61: =IF(S58<='P-Parametri'!$C$12,'P-Parametri'!$B$12,IF(S58<='P-Parametri'!$B$6,'P-Parametri'!$B$13+'P-Parametri'!$C$13*('P-Parametri'!$B$6-S58)/'P-Parametri'!$D$13,IF(S58<='P-Parametri'!$B$7,'P-Parametri'!$B$14*('P-Parametri'!$B$7-S58)/'P-Parametri'!$C$14,0)))+IF(AND(S58>'P-Parametri'!$C$15,S58<'P-Parametri'!$D$15),'P-Parametri'!$B$15,0)
A62: Addizionali — Chiara | B62: =IF(MAX(0,B60-B61)<=0,0,'P-Parametri'!$B$11*B58) | C62: =IF(MAX(0,C60-C61)<=0,0,'P-Parametri'!$B$11*C58) | D62: =IF(MAX(0,D60-D61)<=0,0,'P-Parametri'!$B$11*D58) | E62: =IF(MAX(0,E60-E61)<=0,0,'P-Parametri'!$B$11*E58) | F62: =IF(MAX(0,F60-F61)<=0,0,'P-Parametri'!$B$11*F58) | G62: =IF(MAX(0,G60-G61)<=0,0,'P-Parametri'!$B$11*G58) | H62: =IF(MAX(0,H60-H61)<=0,0,'P-Parametri'!$B$11*H58) | I62: =IF(MAX(0,I60-I61)<=0,0,'P-Parametri'!$B$11*I58) | ... S62: =IF(MAX(0,S60-S61)<=0,0,'P-Parametri'!$B$11*S58)
A63: PENSIONE NETTA — Chiara | B63: =B58-MAX(0,B60-B61)-B62 | C63: =C58-MAX(0,C60-C61)-C62 | D63: =D58-MAX(0,D60-D61)-D62 | E63: =E58-MAX(0,E60-E61)-E62 | F63: =F58-MAX(0,F60-F61)-F62 | G63: =G58-MAX(0,G60-G61)-G62 | H63: =H58-MAX(0,H60-H61)-H62 | I63: =I58-MAX(0,I60-I61)-I62 | ... S63: =S58-MAX(0,S60-S61)-S62
A64: IRPEF lorda — marito | B64: =IF(B59<='P-Parametri'!$B$6,'P-Parametri'!$C$6*B59,IF(B59<='P-Parametri'!$B$7,'P-Parametri'!$B$9+'P-Parametri'!$C$7*(B59-'P-Parametri'!$B$6),'P-Parametri'!$B$10+'P-Parametri'!$C$8*(B59-'P-Parametri'!$B$7))) | C64: =IF(C59<='P-Parametri'!$B$6,'P-Parametri'!$C$6*C59,IF(C59<='P-Parametri'!$B$7,'P-Parametri'!$B$9+'P-Parametri'!$C$7*(C59-'P-Parametri'!$B$6),'P-Parametri'!$B$10+'P-Parametri'!$C$8*(C59-'P-Parametri'!$B$7))) | D64: =IF(D59<='P-Parametri'!$B$6,'P-Parametri'!$C$6*D59,IF(D59<='P-Parametri'!$B$7,'P-Parametri'!$B$9+'P-Parametri'!$C$7*(D59-'P-Parametri'!$B$6),'P-Parametri'!$B$10+'P-Parametri'!$C$8*(D59-'P-Parametri'!$B$7))) | E64: =IF(E59<='P-Parametri'!$B$6,'P-Parametri'!$C$6*E59,IF(E59<='P-Parametri'!$B$7,'P-Parametri'!$B$9+'P-Parametri'!$C$7*(E59-'P-Parametri'!$B$6),'P-Parametri'!$B$10+'P-Parametri'!$C$8*(E59-'P-Parametri'!$B$7))) | F64: =IF(F59<='P-Parametri'!$B$6,'P-Parametri'!$C$6*F59,IF(F59<='P-Parametri'!$B$7,'P-Parametri'!$B$9+'P-Parametri'!$C$7*(F59-'P-Parametri'!$B$6),'P-Parametri'!$B$10+'P-Parametri'!$C$8*(F59-'P-Parametri'!$B$7))) | G64: =IF(G59<='P-Parametri'!$B$6,'P-Parametri'!$C$6*G59,IF(G59<='P-Parametri'!$B$7,'P-Parametri'!$B$9+'P-Parametri'!$C$7*(G59-'P-Parametri'!$B$6),'P-Parametri'!$B$10+'P-Parametri'!$C$8*(G59-'P-Parametri'!$B$7))) | H64: =IF(H59<='P-Parametri'!$B$6,'P-Parametri'!$C$6*H59,IF(H59<='P-Parametri'!$B$7,'P-Parametri'!$B$9+'P-Parametri'!$C$7*(H59-'P-Parametri'!$B$6),'P-Parametri'!$B$10+'P-Parametri'!$C$8*(H59-'P-Parametri'!$B$7))) | I64: =IF(I59<='P-Parametri'!$B$6,'P-Parametri'!$C$6*I59,IF(I59<='P-Parametri'!$B$7,'P-Parametri'!$B$9+'P-Parametri'!$C$7*(I59-'P-Parametri'!$B$6),'P-Parametri'!$B$10+'P-Parametri'!$C$8*(I59-'P-Parametri'!$B$7))) | ... S64: =IF(S59<='P-Parametri'!$B$6,'P-Parametri'!$C$6*S59,IF(S59<='P-Parametri'!$B$7,'P-Parametri'!$B$9+'P-Parametri'!$C$7*(S59-'P-Parametri'!$B$6),'P-Parametri'!$B$10+'P-Parametri'!$C$8*(S59-'P-Parametri'!$B$7)))
A65: Detrazione da pensione — marito | B65: =IF(B59<='P-Parametri'!$C$12,'P-Parametri'!$B$12,IF(B59<='P-Parametri'!$B$6,'P-Parametri'!$B$13+'P-Parametri'!$C$13*('P-Parametri'!$B$6-B59)/'P-Parametri'!$D$13,IF(B59<='P-Parametri'!$B$7,'P-Parametri'!$B$14*('P-Parametri'!$B$7-B59)/'P-Parametri'!$C$14,0)))+IF(AND(B59>'P-Parametri'!$C$15,B59<'P-Parametri'!$D$15),'P-Parametri'!$B$15,0) | C65: =IF(C59<='P-Parametri'!$C$12,'P-Parametri'!$B$12,IF(C59<='P-Parametri'!$B$6,'P-Parametri'!$B$13+'P-Parametri'!$C$13*('P-Parametri'!$B$6-C59)/'P-Parametri'!$D$13,IF(C59<='P-Parametri'!$B$7,'P-Parametri'!$B$14*('P-Parametri'!$B$7-C59)/'P-Parametri'!$C$14,0)))+IF(AND(C59>'P-Parametri'!$C$15,C59<'P-Parametri'!$D$15),'P-Parametri'!$B$15,0) | D65: =IF(D59<='P-Parametri'!$C$12,'P-Parametri'!$B$12,IF(D59<='P-Parametri'!$B$6,'P-Parametri'!$B$13+'P-Parametri'!$C$13*('P-Parametri'!$B$6-D59)/'P-Parametri'!$D$13,IF(D59<='P-Parametri'!$B$7,'P-Parametri'!$B$14*('P-Parametri'!$B$7-D59)/'P-Parametri'!$C$14,0)))+IF(AND(D59>'P-Parametri'!$C$15,D59<'P-Parametri'!$D$15),'P-Parametri'!$B$15,0) | E65: =IF(E59<='P-Parametri'!$C$12,'P-Parametri'!$B$12,IF(E59<='P-Parametri'!$B$6,'P-Parametri'!$B$13+'P-Parametri'!$C$13*('P-Parametri'!$B$6-E59)/'P-Parametri'!$D$13,IF(E59<='P-Parametri'!$B$7,'P-Parametri'!$B$14*('P-Parametri'!$B$7-E59)/'P-Parametri'!$C$14,0)))+IF(AND(E59>'P-Parametri'!$C$15,E59<'P-Parametri'!$D$15),'P-Parametri'!$B$15,0) | F65: =IF(F59<='P-Parametri'!$C$12,'P-Parametri'!$B$12,IF(F59<='P-Parametri'!$B$6,'P-Parametri'!$B$13+'P-Parametri'!$C$13*('P-Parametri'!$B$6-F59)/'P-Parametri'!$D$13,IF(F59<='P-Parametri'!$B$7,'P-Parametri'!$B$14*('P-Parametri'!$B$7-F59)/'P-Parametri'!$C$14,0)))+IF(AND(F59>'P-Parametri'!$C$15,F59<'P-Parametri'!$D$15),'P-Parametri'!$B$15,0) | G65: =IF(G59<='P-Parametri'!$C$12,'P-Parametri'!$B$12,IF(G59<='P-Parametri'!$B$6,'P-Parametri'!$B$13+'P-Parametri'!$C$13*('P-Parametri'!$B$6-G59)/'P-Parametri'!$D$13,IF(G59<='P-Parametri'!$B$7,'P-Parametri'!$B$14*('P-Parametri'!$B$7-G59)/'P-Parametri'!$C$14,0)))+IF(AND(G59>'P-Parametri'!$C$15,G59<'P-Parametri'!$D$15),'P-Parametri'!$B$15,0) | H65: =IF(H59<='P-Parametri'!$C$12,'P-Parametri'!$B$12,IF(H59<='P-Parametri'!$B$6,'P-Parametri'!$B$13+'P-Parametri'!$C$13*('P-Parametri'!$B$6-H59)/'P-Parametri'!$D$13,IF(H59<='P-Parametri'!$B$7,'P-Parametri'!$B$14*('P-Parametri'!$B$7-H59)/'P-Parametri'!$C$14,0)))+IF(AND(H59>'P-Parametri'!$C$15,H59<'P-Parametri'!$D$15),'P-Parametri'!$B$15,0) | I65: =IF(I59<='P-Parametri'!$C$12,'P-Parametri'!$B$12,IF(I59<='P-Parametri'!$B$6,'P-Parametri'!$B$13+'P-Parametri'!$C$13*('P-Parametri'!$B$6-I59)/'P-Parametri'!$D$13,IF(I59<='P-Parametri'!$B$7,'P-Parametri'!$B$14*('P-Parametri'!$B$7-I59)/'P-Parametri'!$C$14,0)))+IF(AND(I59>'P-Parametri'!$C$15,I59<'P-Parametri'!$D$15),'P-Parametri'!$B$15,0) | ... S65: =IF(S59<='P-Parametri'!$C$12,'P-Parametri'!$B$12,IF(S59<='P-Parametri'!$B$6,'P-Parametri'!$B$13+'P-Parametri'!$C$13*('P-Parametri'!$B$6-S59)/'P-Parametri'!$D$13,IF(S59<='P-Parametri'!$B$7,'P-Parametri'!$B$14*('P-Parametri'!$B$7-S59)/'P-Parametri'!$C$14,0)))+IF(AND(S59>'P-Parametri'!$C$15,S59<'P-Parametri'!$D$15),'P-Parametri'!$B$15,0)
A66: Addizionali — marito | B66: =IF(MAX(0,B64-B65)<=0,0,'P-Parametri'!$B$11*B59) | C66: =IF(MAX(0,C64-C65)<=0,0,'P-Parametri'!$B$11*C59) | D66: =IF(MAX(0,D64-D65)<=0,0,'P-Parametri'!$B$11*D59) | E66: =IF(MAX(0,E64-E65)<=0,0,'P-Parametri'!$B$11*E59) | F66: =IF(MAX(0,F64-F65)<=0,0,'P-Parametri'!$B$11*F59) | G66: =IF(MAX(0,G64-G65)<=0,0,'P-Parametri'!$B$11*G59) | H66: =IF(MAX(0,H64-H65)<=0,0,'P-Parametri'!$B$11*H59) | I66: =IF(MAX(0,I64-I65)<=0,0,'P-Parametri'!$B$11*I59) | ... S66: =IF(MAX(0,S64-S65)<=0,0,'P-Parametri'!$B$11*S59)
A67: PENSIONE NETTA — marito | B67: =B59-MAX(0,B64-B65)-B66 | C67: =C59-MAX(0,C64-C65)-C66 | D67: =D59-MAX(0,D64-D65)-D66 | E67: =E59-MAX(0,E64-E65)-E66 | F67: =F59-MAX(0,F64-F65)-F66 | G67: =G59-MAX(0,G64-G65)-G66 | H67: =H59-MAX(0,H64-H65)-H66 | I67: =I59-MAX(0,I64-I65)-I66 | ... S67: =S59-MAX(0,S64-S65)-S66
A68: Pensioni nette di coppia | B68: =B63+B67 | C68: =C63+C67 | D68: =D63+D67 | E68: =E63+E67 | F68: =F63+F67 | G68: =G63+G67 | H68: =H63+H67 | I68: =I63+I67 | ... S68: =S63+S67
A69: Capitale alla valutazione | B69: =IF(B45>0,B45,'2-Composizione'!$B$36*(1+B46)^B49+B30*IF(B46=0,B49,(1+B46)*((1+B46)^B49-1)/B46)) | C69: =IF(C45>0,C45,'2-Composizione'!$B$36*(1+C46)^C49+C30*IF(C46=0,C49,(1+C46)*((1+C46)^C49-1)/C46)) | D69: =IF(D45>0,D45,'2-Composizione'!$B$36*(1+D46)^D49+D30*IF(D46=0,D49,(1+D46)*((1+D46)^D49-1)/D46)) | E69: =IF(E45>0,E45,'2-Composizione'!$B$36*(1+E46)^E49+E30*IF(E46=0,E49,(1+E46)*((1+E46)^E49-1)/E46)) | F69: =IF(F45>0,F45,'2-Composizione'!$B$36*(1+F46)^F49+F30*IF(F46=0,F49,(1+F46)*((1+F46)^F49-1)/F46)) | G69: =IF(G45>0,G45,'2-Composizione'!$B$36*(1+G46)^G49+G30*IF(G46=0,G49,(1+G46)*((1+G46)^G49-1)/G46)) | H69: =IF(H45>0,H45,'2-Composizione'!$B$36*(1+H46)^H49+H30*IF(H46=0,H49,(1+H46)*((1+H46)^H49-1)/H46)) | I69: =IF(I45>0,I45,'2-Composizione'!$B$36*(1+I46)^I49+I30*IF(I46=0,I49,(1+I46)*((1+I46)^I49-1)/I46)) | ... S69: =IF(S45>0,S45,'2-Composizione'!$B$36*(1+S46)^S49+S30*IF(S46=0,S49,(1+S46)*((1+S46)^S49-1)/S46))
A70: Base di costo alla valutazione | B70: ='2-Composizione'!$B$37+B49*B30 | C70: ='2-Composizione'!$B$37+C49*C30 | D70: ='2-Composizione'!$B$37+D49*D30 | E70: ='2-Composizione'!$B$37+E49*E30 | F70: ='2-Composizione'!$B$37+F49*F30 | G70: ='2-Composizione'!$B$37+G49*G30 | H70: ='2-Composizione'!$B$37+H49*H30 | I70: ='2-Composizione'!$B$37+I49*I30 | ... S70: ='2-Composizione'!$B$37+S49*S30
A71: Plusvalenza latente (floor a zero) | B71: =MAX(0,(B69-B70)/B69) | C71: =MAX(0,(C69-C70)/C69) | D71: =MAX(0,(D69-D70)/D69) | E71: =MAX(0,(E69-E70)/E69) | F71: =MAX(0,(F69-F70)/F69) | G71: =MAX(0,(G69-G70)/G69) | H71: =MAX(0,(H69-H70)/H69) | I71: =MAX(0,(I69-I70)/I69) | ... S71: =MAX(0,(S69-S70)/S69)
A72: Fattore di lordizzazione G | B72: =1/(1-'P-Parametri'!$B$31*B71) | C72: =1/(1-'P-Parametri'!$B$31*C71) | D72: =1/(1-'P-Parametri'!$B$31*D71) | E72: =1/(1-'P-Parametri'!$B$31*E71) | F72: =1/(1-'P-Parametri'!$B$31*F71) | G72: =1/(1-'P-Parametri'!$B$31*G71) | H72: =1/(1-'P-Parametri'!$B$31*H71) | I72: =1/(1-'P-Parametri'!$B$31*I71) | ... S72: =1/(1-'P-Parametri'!$B$31*S71)
A73: Valore attuale netto del fabbisogno | B73: =SUM(B82:B115) | C73: =SUM(C82:C115) | D73: =SUM(D82:D115) | E73: =SUM(E82:E115) | F73: =SUM(F82:F115) | G73: =SUM(G82:G115) | H73: =SUM(H82:H115) | I73: =SUM(I82:I115) | ... S73: =SUM(S82:S115)
A74: FABBISOGNO LORDO (in capitale) | B74: =B73*B72 | C74: =C73*C72 | D74: =D73*D72 | E74: =E73*E72 | F74: =F73*F72 | G74: =G73*G72 | H74: =H73*H72 | I74: =I73*I72 | ... S74: =S73*S72
A75: TFR netto alla valutazione | B75: =CHOOSE(B31+1,'6-TFR'!$B$24,'6-TFR'!$C$24,'6-TFR'!$D$24) | C75: =CHOOSE(C31+1,'6-TFR'!$B$24,'6-TFR'!$C$24,'6-TFR'!$D$24) | D75: =CHOOSE(D31+1,'6-TFR'!$B$24,'6-TFR'!$C$24,'6-TFR'!$D$24) | E75: =CHOOSE(E31+1,'6-TFR'!$B$24,'6-TFR'!$C$24,'6-TFR'!$D$24) | F75: =CHOOSE(F31+1,'6-TFR'!$B$24,'6-TFR'!$C$24,'6-TFR'!$D$24) | G75: =CHOOSE(G31+1,'6-TFR'!$B$24,'6-TFR'!$C$24,'6-TFR'!$D$24) | H75: =CHOOSE(H31+1,'6-TFR'!$B$24,'6-TFR'!$C$24,'6-TFR'!$D$24) | I75: =CHOOSE(I31+1,'6-TFR'!$B$24,'6-TFR'!$C$24,'6-TFR'!$D$24) | ... S75: =CHOOSE(S31+1,'6-TFR'!$B$24,'6-TFR'!$C$24,'6-TFR'!$D$24)
A76: FABBISOGNO FINANZIARIO (floor a zero) | B76: =MAX(0,(B73-B75)*B72) | C76: =MAX(0,(C73-C75)*C72) | D76: =MAX(0,(D73-D75)*D72) | E76: =MAX(0,(E73-E75)*E72) | F76: =MAX(0,(F73-F75)*F72) | G76: =MAX(0,(G73-G75)*G72) | H76: =MAX(0,(H73-H75)*H72) | I76: =MAX(0,(I73-I75)*I72) | ... S76: =MAX(0,(S73-S75)*S72)
A77: Posizione netta = capitale meno fabbisogno | B77: =B69-B76 | C77: =C69-C76 | D77: =D69-D76 | E77: =E69-E76 | F77: =F69-F76 | G77: =G69-G76 | H77: =H69-H76 | I77: =I69-I76 | ... S77: =S69-S76
A78: Posizione scontata a fine ritiro | B78: =B77/(1+'1-Input'!$B$46)^B31 | C78: =C77/(1+'1-Input'!$B$46)^C31 | D78: =D77/(1+'1-Input'!$B$46)^D31 | E78: =E77/(1+'1-Input'!$B$46)^E31 | F78: =F77/(1+'1-Input'!$B$46)^F31 | G78: =G77/(1+'1-Input'!$B$46)^G31 | H78: =H77/(1+'1-Input'!$B$46)^H31 | I78: =I77/(1+'1-Input'!$B$46)^I31 | ... S78: =S77/(1+'1-Input'!$B$46)^S31
A79: DELTA contro la base | C79: =C78-B78 | D79: =D78-B78 | E79: =E78-B78 | F79: =F78-B78 | G79: =G78-B78 | H79: =H78-B78 | I79: =I78-B78 | J79: =J78-B78 | L79: =L78-K78 | M79: =M78-K78 | N79: =N78-K78 | O79: =O78-K78 | P79: =P78-K78 | Q79: =Q78-K78 | R79: =R78-K78 | S79: =S78-K78
A81: Anno del flusso — valore attuale del fabbisogno
A82: ='1-Input'!$B$19+1 | B82: =IF(OR($A82<=B48,$A82>B34),0,(B29-IF($A82<B50,0,IF($A82=B50,B63*B54,B63))-IF($A82<B51,0,IF($A82=B51,B67*B55,B67)))/(1+B47)^($A82-B48-1)) | C82: =IF(OR($A82<=C48,$A82>C34),0,(C29-IF($A82<C50,0,IF($A82=C50,C63*C54,C63))-IF($A82<C51,0,IF($A82=C51,C67*C55,C67)))/(1+C47)^($A82-C48-1)) | D82: =IF(OR($A82<=D48,$A82>D34),0,(D29-IF($A82<D50,0,IF($A82=D50,D63*D54,D63))-IF($A82<D51,0,IF($A82=D51,D67*D55,D67)))/(1+D47)^($A82-D48-1)) | E82: =IF(OR($A82<=E48,$A82>E34),0,(E29-IF($A82<E50,0,IF($A82=E50,E63*E54,E63))-IF($A82<E51,0,IF($A82=E51,E67*E55,E67)))/(1+E47)^($A82-E48-1)) | F82: =IF(OR($A82<=F48,$A82>F34),0,(F29-IF($A82<F50,0,IF($A82=F50,F63*F54,F63))-IF($A82<F51,0,IF($A82=F51,F67*F55,F67)))/(1+F47)^($A82-F48-1)) | G82: =IF(OR($A82<=G48,$A82>G34),0,(G29-IF($A82<G50,0,IF($A82=G50,G63*G54,G63))-IF($A82<G51,0,IF($A82=G51,G67*G55,G67)))/(1+G47)^($A82-G48-1)) | H82: =IF(OR($A82<=H48,$A82>H34),0,(H29-IF($A82<H50,0,IF($A82=H50,H63*H54,H63))-IF($A82<H51,0,IF($A82=H51,H67*H55,H67)))/(1+H47)^($A82-H48-1)) | I82: =IF(OR($A82<=I48,$A82>I34),0,(I29-IF($A82<I50,0,IF($A82=I50,I63*I54,I63))-IF($A82<I51,0,IF($A82=I51,I67*I55,I67)))/(1+I47)^($A82-I48-1)) | ... S82: =IF(OR($A82<=S48,$A82>S34),0,(S29-IF($A82<S50,0,IF($A82=S50,S63*S54,S63))-IF($A82<S51,0,IF($A82=S51,S67*S55,S67)))/(1+S47)^($A82-S48-1))
A83: =A82+1 | B83: =IF(OR($A83<=B48,$A83>B34),0,(B29-IF($A83<B50,0,IF($A83=B50,B63*B54,B63))-IF($A83<B51,0,IF($A83=B51,B67*B55,B67)))/(1+B47)^($A83-B48-1)) | C83: =IF(OR($A83<=C48,$A83>C34),0,(C29-IF($A83<C50,0,IF($A83=C50,C63*C54,C63))-IF($A83<C51,0,IF($A83=C51,C67*C55,C67)))/(1+C47)^($A83-C48-1)) | D83: =IF(OR($A83<=D48,$A83>D34),0,(D29-IF($A83<D50,0,IF($A83=D50,D63*D54,D63))-IF($A83<D51,0,IF($A83=D51,D67*D55,D67)))/(1+D47)^($A83-D48-1)) | E83: =IF(OR($A83<=E48,$A83>E34),0,(E29-IF($A83<E50,0,IF($A83=E50,E63*E54,E63))-IF($A83<E51,0,IF($A83=E51,E67*E55,E67)))/(1+E47)^($A83-E48-1)) | F83: =IF(OR($A83<=F48,$A83>F34),0,(F29-IF($A83<F50,0,IF($A83=F50,F63*F54,F63))-IF($A83<F51,0,IF($A83=F51,F67*F55,F67)))/(1+F47)^($A83-F48-1)) | G83: =IF(OR($A83<=G48,$A83>G34),0,(G29-IF($A83<G50,0,IF($A83=G50,G63*G54,G63))-IF($A83<G51,0,IF($A83=G51,G67*G55,G67)))/(1+G47)^($A83-G48-1)) | H83: =IF(OR($A83<=H48,$A83>H34),0,(H29-IF($A83<H50,0,IF($A83=H50,H63*H54,H63))-IF($A83<H51,0,IF($A83=H51,H67*H55,H67)))/(1+H47)^($A83-H48-1)) | I83: =IF(OR($A83<=I48,$A83>I34),0,(I29-IF($A83<I50,0,IF($A83=I50,I63*I54,I63))-IF($A83<I51,0,IF($A83=I51,I67*I55,I67)))/(1+I47)^($A83-I48-1)) | ... S83: =IF(OR($A83<=S48,$A83>S34),0,(S29-IF($A83<S50,0,IF($A83=S50,S63*S54,S63))-IF($A83<S51,0,IF($A83=S51,S67*S55,S67)))/(1+S47)^($A83-S48-1))
A84: =A83+1 | B84: =IF(OR($A84<=B48,$A84>B34),0,(B29-IF($A84<B50,0,IF($A84=B50,B63*B54,B63))-IF($A84<B51,0,IF($A84=B51,B67*B55,B67)))/(1+B47)^($A84-B48-1)) | C84: =IF(OR($A84<=C48,$A84>C34),0,(C29-IF($A84<C50,0,IF($A84=C50,C63*C54,C63))-IF($A84<C51,0,IF($A84=C51,C67*C55,C67)))/(1+C47)^($A84-C48-1)) | D84: =IF(OR($A84<=D48,$A84>D34),0,(D29-IF($A84<D50,0,IF($A84=D50,D63*D54,D63))-IF($A84<D51,0,IF($A84=D51,D67*D55,D67)))/(1+D47)^($A84-D48-1)) | E84: =IF(OR($A84<=E48,$A84>E34),0,(E29-IF($A84<E50,0,IF($A84=E50,E63*E54,E63))-IF($A84<E51,0,IF($A84=E51,E67*E55,E67)))/(1+E47)^($A84-E48-1)) | F84: =IF(OR($A84<=F48,$A84>F34),0,(F29-IF($A84<F50,0,IF($A84=F50,F63*F54,F63))-IF($A84<F51,0,IF($A84=F51,F67*F55,F67)))/(1+F47)^($A84-F48-1)) | G84: =IF(OR($A84<=G48,$A84>G34),0,(G29-IF($A84<G50,0,IF($A84=G50,G63*G54,G63))-IF($A84<G51,0,IF($A84=G51,G67*G55,G67)))/(1+G47)^($A84-G48-1)) | H84: =IF(OR($A84<=H48,$A84>H34),0,(H29-IF($A84<H50,0,IF($A84=H50,H63*H54,H63))-IF($A84<H51,0,IF($A84=H51,H67*H55,H67)))/(1+H47)^($A84-H48-1)) | I84: =IF(OR($A84<=I48,$A84>I34),0,(I29-IF($A84<I50,0,IF($A84=I50,I63*I54,I63))-IF($A84<I51,0,IF($A84=I51,I67*I55,I67)))/(1+I47)^($A84-I48-1)) | ... S84: =IF(OR($A84<=S48,$A84>S34),0,(S29-IF($A84<S50,0,IF($A84=S50,S63*S54,S63))-IF($A84<S51,0,IF($A84=S51,S67*S55,S67)))/(1+S47)^($A84-S48-1))
A85: =A84+1 | B85: =IF(OR($A85<=B48,$A85>B34),0,(B29-IF($A85<B50,0,IF($A85=B50,B63*B54,B63))-IF($A85<B51,0,IF($A85=B51,B67*B55,B67)))/(1+B47)^($A85-B48-1)) | C85: =IF(OR($A85<=C48,$A85>C34),0,(C29-IF($A85<C50,0,IF($A85=C50,C63*C54,C63))-IF($A85<C51,0,IF($A85=C51,C67*C55,C67)))/(1+C47)^($A85-C48-1)) | D85: =IF(OR($A85<=D48,$A85>D34),0,(D29-IF($A85<D50,0,IF($A85=D50,D63*D54,D63))-IF($A85<D51,0,IF($A85=D51,D67*D55,D67)))/(1+D47)^($A85-D48-1)) | E85: =IF(OR($A85<=E48,$A85>E34),0,(E29-IF($A85<E50,0,IF($A85=E50,E63*E54,E63))-IF($A85<E51,0,IF($A85=E51,E67*E55,E67)))/(1+E47)^($A85-E48-1)) | F85: =IF(OR($A85<=F48,$A85>F34),0,(F29-IF($A85<F50,0,IF($A85=F50,F63*F54,F63))-IF($A85<F51,0,IF($A85=F51,F67*F55,F67)))/(1+F47)^($A85-F48-1)) | G85: =IF(OR($A85<=G48,$A85>G34),0,(G29-IF($A85<G50,0,IF($A85=G50,G63*G54,G63))-IF($A85<G51,0,IF($A85=G51,G67*G55,G67)))/(1+G47)^($A85-G48-1)) | H85: =IF(OR($A85<=H48,$A85>H34),0,(H29-IF($A85<H50,0,IF($A85=H50,H63*H54,H63))-IF($A85<H51,0,IF($A85=H51,H67*H55,H67)))/(1+H47)^($A85-H48-1)) | I85: =IF(OR($A85<=I48,$A85>I34),0,(I29-IF($A85<I50,0,IF($A85=I50,I63*I54,I63))-IF($A85<I51,0,IF($A85=I51,I67*I55,I67)))/(1+I47)^($A85-I48-1)) | ... S85: =IF(OR($A85<=S48,$A85>S34),0,(S29-IF($A85<S50,0,IF($A85=S50,S63*S54,S63))-IF($A85<S51,0,IF($A85=S51,S67*S55,S67)))/(1+S47)^($A85-S48-1))
A86: =A85+1 | B86: =IF(OR($A86<=B48,$A86>B34),0,(B29-IF($A86<B50,0,IF($A86=B50,B63*B54,B63))-IF($A86<B51,0,IF($A86=B51,B67*B55,B67)))/(1+B47)^($A86-B48-1)) | C86: =IF(OR($A86<=C48,$A86>C34),0,(C29-IF($A86<C50,0,IF($A86=C50,C63*C54,C63))-IF($A86<C51,0,IF($A86=C51,C67*C55,C67)))/(1+C47)^($A86-C48-1)) | D86: =IF(OR($A86<=D48,$A86>D34),0,(D29-IF($A86<D50,0,IF($A86=D50,D63*D54,D63))-IF($A86<D51,0,IF($A86=D51,D67*D55,D67)))/(1+D47)^($A86-D48-1)) | E86: =IF(OR($A86<=E48,$A86>E34),0,(E29-IF($A86<E50,0,IF($A86=E50,E63*E54,E63))-IF($A86<E51,0,IF($A86=E51,E67*E55,E67)))/(1+E47)^($A86-E48-1)) | F86: =IF(OR($A86<=F48,$A86>F34),0,(F29-IF($A86<F50,0,IF($A86=F50,F63*F54,F63))-IF($A86<F51,0,IF($A86=F51,F67*F55,F67)))/(1+F47)^($A86-F48-1)) | G86: =IF(OR($A86<=G48,$A86>G34),0,(G29-IF($A86<G50,0,IF($A86=G50,G63*G54,G63))-IF($A86<G51,0,IF($A86=G51,G67*G55,G67)))/(1+G47)^($A86-G48-1)) | H86: =IF(OR($A86<=H48,$A86>H34),0,(H29-IF($A86<H50,0,IF($A86=H50,H63*H54,H63))-IF($A86<H51,0,IF($A86=H51,H67*H55,H67)))/(1+H47)^($A86-H48-1)) | I86: =IF(OR($A86<=I48,$A86>I34),0,(I29-IF($A86<I50,0,IF($A86=I50,I63*I54,I63))-IF($A86<I51,0,IF($A86=I51,I67*I55,I67)))/(1+I47)^($A86-I48-1)) | ... S86: =IF(OR($A86<=S48,$A86>S34),0,(S29-IF($A86<S50,0,IF($A86=S50,S63*S54,S63))-IF($A86<S51,0,IF($A86=S51,S67*S55,S67)))/(1+S47)^($A86-S48-1))
A87: =A86+1 | B87: =IF(OR($A87<=B48,$A87>B34),0,(B29-IF($A87<B50,0,IF($A87=B50,B63*B54,B63))-IF($A87<B51,0,IF($A87=B51,B67*B55,B67)))/(1+B47)^($A87-B48-1)) | C87: =IF(OR($A87<=C48,$A87>C34),0,(C29-IF($A87<C50,0,IF($A87=C50,C63*C54,C63))-IF($A87<C51,0,IF($A87=C51,C67*C55,C67)))/(1+C47)^($A87-C48-1)) | D87: =IF(OR($A87<=D48,$A87>D34),0,(D29-IF($A87<D50,0,IF($A87=D50,D63*D54,D63))-IF($A87<D51,0,IF($A87=D51,D67*D55,D67)))/(1+D47)^($A87-D48-1)) | E87: =IF(OR($A87<=E48,$A87>E34),0,(E29-IF($A87<E50,0,IF($A87=E50,E63*E54,E63))-IF($A87<E51,0,IF($A87=E51,E67*E55,E67)))/(1+E47)^($A87-E48-1)) | F87: =IF(OR($A87<=F48,$A87>F34),0,(F29-IF($A87<F50,0,IF($A87=F50,F63*F54,F63))-IF($A87<F51,0,IF($A87=F51,F67*F55,F67)))/(1+F47)^($A87-F48-1)) | G87: =IF(OR($A87<=G48,$A87>G34),0,(G29-IF($A87<G50,0,IF($A87=G50,G63*G54,G63))-IF($A87<G51,0,IF($A87=G51,G67*G55,G67)))/(1+G47)^($A87-G48-1)) | H87: =IF(OR($A87<=H48,$A87>H34),0,(H29-IF($A87<H50,0,IF($A87=H50,H63*H54,H63))-IF($A87<H51,0,IF($A87=H51,H67*H55,H67)))/(1+H47)^($A87-H48-1)) | I87: =IF(OR($A87<=I48,$A87>I34),0,(I29-IF($A87<I50,0,IF($A87=I50,I63*I54,I63))-IF($A87<I51,0,IF($A87=I51,I67*I55,I67)))/(1+I47)^($A87-I48-1)) | ... S87: =IF(OR($A87<=S48,$A87>S34),0,(S29-IF($A87<S50,0,IF($A87=S50,S63*S54,S63))-IF($A87<S51,0,IF($A87=S51,S67*S55,S67)))/(1+S47)^($A87-S48-1))
A88: =A87+1 | B88: =IF(OR($A88<=B48,$A88>B34),0,(B29-IF($A88<B50,0,IF($A88=B50,B63*B54,B63))-IF($A88<B51,0,IF($A88=B51,B67*B55,B67)))/(1+B47)^($A88-B48-1)) | C88: =IF(OR($A88<=C48,$A88>C34),0,(C29-IF($A88<C50,0,IF($A88=C50,C63*C54,C63))-IF($A88<C51,0,IF($A88=C51,C67*C55,C67)))/(1+C47)^($A88-C48-1)) | D88: =IF(OR($A88<=D48,$A88>D34),0,(D29-IF($A88<D50,0,IF($A88=D50,D63*D54,D63))-IF($A88<D51,0,IF($A88=D51,D67*D55,D67)))/(1+D47)^($A88-D48-1)) | E88: =IF(OR($A88<=E48,$A88>E34),0,(E29-IF($A88<E50,0,IF($A88=E50,E63*E54,E63))-IF($A88<E51,0,IF($A88=E51,E67*E55,E67)))/(1+E47)^($A88-E48-1)) | F88: =IF(OR($A88<=F48,$A88>F34),0,(F29-IF($A88<F50,0,IF($A88=F50,F63*F54,F63))-IF($A88<F51,0,IF($A88=F51,F67*F55,F67)))/(1+F47)^($A88-F48-1)) | G88: =IF(OR($A88<=G48,$A88>G34),0,(G29-IF($A88<G50,0,IF($A88=G50,G63*G54,G63))-IF($A88<G51,0,IF($A88=G51,G67*G55,G67)))/(1+G47)^($A88-G48-1)) | H88: =IF(OR($A88<=H48,$A88>H34),0,(H29-IF($A88<H50,0,IF($A88=H50,H63*H54,H63))-IF($A88<H51,0,IF($A88=H51,H67*H55,H67)))/(1+H47)^($A88-H48-1)) | I88: =IF(OR($A88<=I48,$A88>I34),0,(I29-IF($A88<I50,0,IF($A88=I50,I63*I54,I63))-IF($A88<I51,0,IF($A88=I51,I67*I55,I67)))/(1+I47)^($A88-I48-1)) | ... S88: =IF(OR($A88<=S48,$A88>S34),0,(S29-IF($A88<S50,0,IF($A88=S50,S63*S54,S63))-IF($A88<S51,0,IF($A88=S51,S67*S55,S67)))/(1+S47)^($A88-S48-1))
A89: =A88+1 | B89: =IF(OR($A89<=B48,$A89>B34),0,(B29-IF($A89<B50,0,IF($A89=B50,B63*B54,B63))-IF($A89<B51,0,IF($A89=B51,B67*B55,B67)))/(1+B47)^($A89-B48-1)) | C89: =IF(OR($A89<=C48,$A89>C34),0,(C29-IF($A89<C50,0,IF($A89=C50,C63*C54,C63))-IF($A89<C51,0,IF($A89=C51,C67*C55,C67)))/(1+C47)^($A89-C48-1)) | D89: =IF(OR($A89<=D48,$A89>D34),0,(D29-IF($A89<D50,0,IF($A89=D50,D63*D54,D63))-IF($A89<D51,0,IF($A89=D51,D67*D55,D67)))/(1+D47)^($A89-D48-1)) | E89: =IF(OR($A89<=E48,$A89>E34),0,(E29-IF($A89<E50,0,IF($A89=E50,E63*E54,E63))-IF($A89<E51,0,IF($A89=E51,E67*E55,E67)))/(1+E47)^($A89-E48-1)) | F89: =IF(OR($A89<=F48,$A89>F34),0,(F29-IF($A89<F50,0,IF($A89=F50,F63*F54,F63))-IF($A89<F51,0,IF($A89=F51,F67*F55,F67)))/(1+F47)^($A89-F48-1)) | G89: =IF(OR($A89<=G48,$A89>G34),0,(G29-IF($A89<G50,0,IF($A89=G50,G63*G54,G63))-IF($A89<G51,0,IF($A89=G51,G67*G55,G67)))/(1+G47)^($A89-G48-1)) | H89: =IF(OR($A89<=H48,$A89>H34),0,(H29-IF($A89<H50,0,IF($A89=H50,H63*H54,H63))-IF($A89<H51,0,IF($A89=H51,H67*H55,H67)))/(1+H47)^($A89-H48-1)) | I89: =IF(OR($A89<=I48,$A89>I34),0,(I29-IF($A89<I50,0,IF($A89=I50,I63*I54,I63))-IF($A89<I51,0,IF($A89=I51,I67*I55,I67)))/(1+I47)^($A89-I48-1)) | ... S89: =IF(OR($A89<=S48,$A89>S34),0,(S29-IF($A89<S50,0,IF($A89=S50,S63*S54,S63))-IF($A89<S51,0,IF($A89=S51,S67*S55,S67)))/(1+S47)^($A89-S48-1))
A90: =A89+1 | B90: =IF(OR($A90<=B48,$A90>B34),0,(B29-IF($A90<B50,0,IF($A90=B50,B63*B54,B63))-IF($A90<B51,0,IF($A90=B51,B67*B55,B67)))/(1+B47)^($A90-B48-1)) | C90: =IF(OR($A90<=C48,$A90>C34),0,(C29-IF($A90<C50,0,IF($A90=C50,C63*C54,C63))-IF($A90<C51,0,IF($A90=C51,C67*C55,C67)))/(1+C47)^($A90-C48-1)) | D90: =IF(OR($A90<=D48,$A90>D34),0,(D29-IF($A90<D50,0,IF($A90=D50,D63*D54,D63))-IF($A90<D51,0,IF($A90=D51,D67*D55,D67)))/(1+D47)^($A90-D48-1)) | E90: =IF(OR($A90<=E48,$A90>E34),0,(E29-IF($A90<E50,0,IF($A90=E50,E63*E54,E63))-IF($A90<E51,0,IF($A90=E51,E67*E55,E67)))/(1+E47)^($A90-E48-1)) | F90: =IF(OR($A90<=F48,$A90>F34),0,(F29-IF($A90<F50,0,IF($A90=F50,F63*F54,F63))-IF($A90<F51,0,IF($A90=F51,F67*F55,F67)))/(1+F47)^($A90-F48-1)) | G90: =IF(OR($A90<=G48,$A90>G34),0,(G29-IF($A90<G50,0,IF($A90=G50,G63*G54,G63))-IF($A90<G51,0,IF($A90=G51,G67*G55,G67)))/(1+G47)^($A90-G48-1)) | H90: =IF(OR($A90<=H48,$A90>H34),0,(H29-IF($A90<H50,0,IF($A90=H50,H63*H54,H63))-IF($A90<H51,0,IF($A90=H51,H67*H55,H67)))/(1+H47)^($A90-H48-1)) | I90: =IF(OR($A90<=I48,$A90>I34),0,(I29-IF($A90<I50,0,IF($A90=I50,I63*I54,I63))-IF($A90<I51,0,IF($A90=I51,I67*I55,I67)))/(1+I47)^($A90-I48-1)) | ... S90: =IF(OR($A90<=S48,$A90>S34),0,(S29-IF($A90<S50,0,IF($A90=S50,S63*S54,S63))-IF($A90<S51,0,IF($A90=S51,S67*S55,S67)))/(1+S47)^($A90-S48-1))
A91: =A90+1 | B91: =IF(OR($A91<=B48,$A91>B34),0,(B29-IF($A91<B50,0,IF($A91=B50,B63*B54,B63))-IF($A91<B51,0,IF($A91=B51,B67*B55,B67)))/(1+B47)^($A91-B48-1)) | C91: =IF(OR($A91<=C48,$A91>C34),0,(C29-IF($A91<C50,0,IF($A91=C50,C63*C54,C63))-IF($A91<C51,0,IF($A91=C51,C67*C55,C67)))/(1+C47)^($A91-C48-1)) | D91: =IF(OR($A91<=D48,$A91>D34),0,(D29-IF($A91<D50,0,IF($A91=D50,D63*D54,D63))-IF($A91<D51,0,IF($A91=D51,D67*D55,D67)))/(1+D47)^($A91-D48-1)) | E91: =IF(OR($A91<=E48,$A91>E34),0,(E29-IF($A91<E50,0,IF($A91=E50,E63*E54,E63))-IF($A91<E51,0,IF($A91=E51,E67*E55,E67)))/(1+E47)^($A91-E48-1)) | F91: =IF(OR($A91<=F48,$A91>F34),0,(F29-IF($A91<F50,0,IF($A91=F50,F63*F54,F63))-IF($A91<F51,0,IF($A91=F51,F67*F55,F67)))/(1+F47)^($A91-F48-1)) | G91: =IF(OR($A91<=G48,$A91>G34),0,(G29-IF($A91<G50,0,IF($A91=G50,G63*G54,G63))-IF($A91<G51,0,IF($A91=G51,G67*G55,G67)))/(1+G47)^($A91-G48-1)) | H91: =IF(OR($A91<=H48,$A91>H34),0,(H29-IF($A91<H50,0,IF($A91=H50,H63*H54,H63))-IF($A91<H51,0,IF($A91=H51,H67*H55,H67)))/(1+H47)^($A91-H48-1)) | I91: =IF(OR($A91<=I48,$A91>I34),0,(I29-IF($A91<I50,0,IF($A91=I50,I63*I54,I63))-IF($A91<I51,0,IF($A91=I51,I67*I55,I67)))/(1+I47)^($A91-I48-1)) | ... S91: =IF(OR($A91<=S48,$A91>S34),0,(S29-IF($A91<S50,0,IF($A91=S50,S63*S54,S63))-IF($A91<S51,0,IF($A91=S51,S67*S55,S67)))/(1+S47)^($A91-S48-1))
A92: =A91+1 | B92: =IF(OR($A92<=B48,$A92>B34),0,(B29-IF($A92<B50,0,IF($A92=B50,B63*B54,B63))-IF($A92<B51,0,IF($A92=B51,B67*B55,B67)))/(1+B47)^($A92-B48-1)) | C92: =IF(OR($A92<=C48,$A92>C34),0,(C29-IF($A92<C50,0,IF($A92=C50,C63*C54,C63))-IF($A92<C51,0,IF($A92=C51,C67*C55,C67)))/(1+C47)^($A92-C48-1)) | D92: =IF(OR($A92<=D48,$A92>D34),0,(D29-IF($A92<D50,0,IF($A92=D50,D63*D54,D63))-IF($A92<D51,0,IF($A92=D51,D67*D55,D67)))/(1+D47)^($A92-D48-1)) | E92: =IF(OR($A92<=E48,$A92>E34),0,(E29-IF($A92<E50,0,IF($A92=E50,E63*E54,E63))-IF($A92<E51,0,IF($A92=E51,E67*E55,E67)))/(1+E47)^($A92-E48-1)) | F92: =IF(OR($A92<=F48,$A92>F34),0,(F29-IF($A92<F50,0,IF($A92=F50,F63*F54,F63))-IF($A92<F51,0,IF($A92=F51,F67*F55,F67)))/(1+F47)^($A92-F48-1)) | G92: =IF(OR($A92<=G48,$A92>G34),0,(G29-IF($A92<G50,0,IF($A92=G50,G63*G54,G63))-IF($A92<G51,0,IF($A92=G51,G67*G55,G67)))/(1+G47)^($A92-G48-1)) | H92: =IF(OR($A92<=H48,$A92>H34),0,(H29-IF($A92<H50,0,IF($A92=H50,H63*H54,H63))-IF($A92<H51,0,IF($A92=H51,H67*H55,H67)))/(1+H47)^($A92-H48-1)) | I92: =IF(OR($A92<=I48,$A92>I34),0,(I29-IF($A92<I50,0,IF($A92=I50,I63*I54,I63))-IF($A92<I51,0,IF($A92=I51,I67*I55,I67)))/(1+I47)^($A92-I48-1)) | ... S92: =IF(OR($A92<=S48,$A92>S34),0,(S29-IF($A92<S50,0,IF($A92=S50,S63*S54,S63))-IF($A92<S51,0,IF($A92=S51,S67*S55,S67)))/(1+S47)^($A92-S48-1))
A93: =A92+1 | B93: =IF(OR($A93<=B48,$A93>B34),0,(B29-IF($A93<B50,0,IF($A93=B50,B63*B54,B63))-IF($A93<B51,0,IF($A93=B51,B67*B55,B67)))/(1+B47)^($A93-B48-1)) | C93: =IF(OR($A93<=C48,$A93>C34),0,(C29-IF($A93<C50,0,IF($A93=C50,C63*C54,C63))-IF($A93<C51,0,IF($A93=C51,C67*C55,C67)))/(1+C47)^($A93-C48-1)) | D93: =IF(OR($A93<=D48,$A93>D34),0,(D29-IF($A93<D50,0,IF($A93=D50,D63*D54,D63))-IF($A93<D51,0,IF($A93=D51,D67*D55,D67)))/(1+D47)^($A93-D48-1)) | E93: =IF(OR($A93<=E48,$A93>E34),0,(E29-IF($A93<E50,0,IF($A93=E50,E63*E54,E63))-IF($A93<E51,0,IF($A93=E51,E67*E55,E67)))/(1+E47)^($A93-E48-1)) | F93: =IF(OR($A93<=F48,$A93>F34),0,(F29-IF($A93<F50,0,IF($A93=F50,F63*F54,F63))-IF($A93<F51,0,IF($A93=F51,F67*F55,F67)))/(1+F47)^($A93-F48-1)) | G93: =IF(OR($A93<=G48,$A93>G34),0,(G29-IF($A93<G50,0,IF($A93=G50,G63*G54,G63))-IF($A93<G51,0,IF($A93=G51,G67*G55,G67)))/(1+G47)^($A93-G48-1)) | H93: =IF(OR($A93<=H48,$A93>H34),0,(H29-IF($A93<H50,0,IF($A93=H50,H63*H54,H63))-IF($A93<H51,0,IF($A93=H51,H67*H55,H67)))/(1+H47)^($A93-H48-1)) | I93: =IF(OR($A93<=I48,$A93>I34),0,(I29-IF($A93<I50,0,IF($A93=I50,I63*I54,I63))-IF($A93<I51,0,IF($A93=I51,I67*I55,I67)))/(1+I47)^($A93-I48-1)) | ... S93: =IF(OR($A93<=S48,$A93>S34),0,(S29-IF($A93<S50,0,IF($A93=S50,S63*S54,S63))-IF($A93<S51,0,IF($A93=S51,S67*S55,S67)))/(1+S47)^($A93-S48-1))
A94: =A93+1 | B94: =IF(OR($A94<=B48,$A94>B34),0,(B29-IF($A94<B50,0,IF($A94=B50,B63*B54,B63))-IF($A94<B51,0,IF($A94=B51,B67*B55,B67)))/(1+B47)^($A94-B48-1)) | C94: =IF(OR($A94<=C48,$A94>C34),0,(C29-IF($A94<C50,0,IF($A94=C50,C63*C54,C63))-IF($A94<C51,0,IF($A94=C51,C67*C55,C67)))/(1+C47)^($A94-C48-1)) | D94: =IF(OR($A94<=D48,$A94>D34),0,(D29-IF($A94<D50,0,IF($A94=D50,D63*D54,D63))-IF($A94<D51,0,IF($A94=D51,D67*D55,D67)))/(1+D47)^($A94-D48-1)) | E94: =IF(OR($A94<=E48,$A94>E34),0,(E29-IF($A94<E50,0,IF($A94=E50,E63*E54,E63))-IF($A94<E51,0,IF($A94=E51,E67*E55,E67)))/(1+E47)^($A94-E48-1)) | F94: =IF(OR($A94<=F48,$A94>F34),0,(F29-IF($A94<F50,0,IF($A94=F50,F63*F54,F63))-IF($A94<F51,0,IF($A94=F51,F67*F55,F67)))/(1+F47)^($A94-F48-1)) | G94: =IF(OR($A94<=G48,$A94>G34),0,(G29-IF($A94<G50,0,IF($A94=G50,G63*G54,G63))-IF($A94<G51,0,IF($A94=G51,G67*G55,G67)))/(1+G47)^($A94-G48-1)) | H94: =IF(OR($A94<=H48,$A94>H34),0,(H29-IF($A94<H50,0,IF($A94=H50,H63*H54,H63))-IF($A94<H51,0,IF($A94=H51,H67*H55,H67)))/(1+H47)^($A94-H48-1)) | I94: =IF(OR($A94<=I48,$A94>I34),0,(I29-IF($A94<I50,0,IF($A94=I50,I63*I54,I63))-IF($A94<I51,0,IF($A94=I51,I67*I55,I67)))/(1+I47)^($A94-I48-1)) | ... S94: =IF(OR($A94<=S48,$A94>S34),0,(S29-IF($A94<S50,0,IF($A94=S50,S63*S54,S63))-IF($A94<S51,0,IF($A94=S51,S67*S55,S67)))/(1+S47)^($A94-S48-1))
A95: =A94+1 | B95: =IF(OR($A95<=B48,$A95>B34),0,(B29-IF($A95<B50,0,IF($A95=B50,B63*B54,B63))-IF($A95<B51,0,IF($A95=B51,B67*B55,B67)))/(1+B47)^($A95-B48-1)) | C95: =IF(OR($A95<=C48,$A95>C34),0,(C29-IF($A95<C50,0,IF($A95=C50,C63*C54,C63))-IF($A95<C51,0,IF($A95=C51,C67*C55,C67)))/(1+C47)^($A95-C48-1)) | D95: =IF(OR($A95<=D48,$A95>D34),0,(D29-IF($A95<D50,0,IF($A95=D50,D63*D54,D63))-IF($A95<D51,0,IF($A95=D51,D67*D55,D67)))/(1+D47)^($A95-D48-1)) | E95: =IF(OR($A95<=E48,$A95>E34),0,(E29-IF($A95<E50,0,IF($A95=E50,E63*E54,E63))-IF($A95<E51,0,IF($A95=E51,E67*E55,E67)))/(1+E47)^($A95-E48-1)) | F95: =IF(OR($A95<=F48,$A95>F34),0,(F29-IF($A95<F50,0,IF($A95=F50,F63*F54,F63))-IF($A95<F51,0,IF($A95=F51,F67*F55,F67)))/(1+F47)^($A95-F48-1)) | G95: =IF(OR($A95<=G48,$A95>G34),0,(G29-IF($A95<G50,0,IF($A95=G50,G63*G54,G63))-IF($A95<G51,0,IF($A95=G51,G67*G55,G67)))/(1+G47)^($A95-G48-1)) | H95: =IF(OR($A95<=H48,$A95>H34),0,(H29-IF($A95<H50,0,IF($A95=H50,H63*H54,H63))-IF($A95<H51,0,IF($A95=H51,H67*H55,H67)))/(1+H47)^($A95-H48-1)) | I95: =IF(OR($A95<=I48,$A95>I34),0,(I29-IF($A95<I50,0,IF($A95=I50,I63*I54,I63))-IF($A95<I51,0,IF($A95=I51,I67*I55,I67)))/(1+I47)^($A95-I48-1)) | ... S95: =IF(OR($A95<=S48,$A95>S34),0,(S29-IF($A95<S50,0,IF($A95=S50,S63*S54,S63))-IF($A95<S51,0,IF($A95=S51,S67*S55,S67)))/(1+S47)^($A95-S48-1))
A96: =A95+1 | B96: =IF(OR($A96<=B48,$A96>B34),0,(B29-IF($A96<B50,0,IF($A96=B50,B63*B54,B63))-IF($A96<B51,0,IF($A96=B51,B67*B55,B67)))/(1+B47)^($A96-B48-1)) | C96: =IF(OR($A96<=C48,$A96>C34),0,(C29-IF($A96<C50,0,IF($A96=C50,C63*C54,C63))-IF($A96<C51,0,IF($A96=C51,C67*C55,C67)))/(1+C47)^($A96-C48-1)) | D96: =IF(OR($A96<=D48,$A96>D34),0,(D29-IF($A96<D50,0,IF($A96=D50,D63*D54,D63))-IF($A96<D51,0,IF($A96=D51,D67*D55,D67)))/(1+D47)^($A96-D48-1)) | E96: =IF(OR($A96<=E48,$A96>E34),0,(E29-IF($A96<E50,0,IF($A96=E50,E63*E54,E63))-IF($A96<E51,0,IF($A96=E51,E67*E55,E67)))/(1+E47)^($A96-E48-1)) | F96: =IF(OR($A96<=F48,$A96>F34),0,(F29-IF($A96<F50,0,IF($A96=F50,F63*F54,F63))-IF($A96<F51,0,IF($A96=F51,F67*F55,F67)))/(1+F47)^($A96-F48-1)) | G96: =IF(OR($A96<=G48,$A96>G34),0,(G29-IF($A96<G50,0,IF($A96=G50,G63*G54,G63))-IF($A96<G51,0,IF($A96=G51,G67*G55,G67)))/(1+G47)^($A96-G48-1)) | H96: =IF(OR($A96<=H48,$A96>H34),0,(H29-IF($A96<H50,0,IF($A96=H50,H63*H54,H63))-IF($A96<H51,0,IF($A96=H51,H67*H55,H67)))/(1+H47)^($A96-H48-1)) | I96: =IF(OR($A96<=I48,$A96>I34),0,(I29-IF($A96<I50,0,IF($A96=I50,I63*I54,I63))-IF($A96<I51,0,IF($A96=I51,I67*I55,I67)))/(1+I47)^($A96-I48-1)) | ... S96: =IF(OR($A96<=S48,$A96>S34),0,(S29-IF($A96<S50,0,IF($A96=S50,S63*S54,S63))-IF($A96<S51,0,IF($A96=S51,S67*S55,S67)))/(1+S47)^($A96-S48-1))
A97: =A96+1 | B97: =IF(OR($A97<=B48,$A97>B34),0,(B29-IF($A97<B50,0,IF($A97=B50,B63*B54,B63))-IF($A97<B51,0,IF($A97=B51,B67*B55,B67)))/(1+B47)^($A97-B48-1)) | C97: =IF(OR($A97<=C48,$A97>C34),0,(C29-IF($A97<C50,0,IF($A97=C50,C63*C54,C63))-IF($A97<C51,0,IF($A97=C51,C67*C55,C67)))/(1+C47)^($A97-C48-1)) | D97: =IF(OR($A97<=D48,$A97>D34),0,(D29-IF($A97<D50,0,IF($A97=D50,D63*D54,D63))-IF($A97<D51,0,IF($A97=D51,D67*D55,D67)))/(1+D47)^($A97-D48-1)) | E97: =IF(OR($A97<=E48,$A97>E34),0,(E29-IF($A97<E50,0,IF($A97=E50,E63*E54,E63))-IF($A97<E51,0,IF($A97=E51,E67*E55,E67)))/(1+E47)^($A97-E48-1)) | F97: =IF(OR($A97<=F48,$A97>F34),0,(F29-IF($A97<F50,0,IF($A97=F50,F63*F54,F63))-IF($A97<F51,0,IF($A97=F51,F67*F55,F67)))/(1+F47)^($A97-F48-1)) | G97: =IF(OR($A97<=G48,$A97>G34),0,(G29-IF($A97<G50,0,IF($A97=G50,G63*G54,G63))-IF($A97<G51,0,IF($A97=G51,G67*G55,G67)))/(1+G47)^($A97-G48-1)) | H97: =IF(OR($A97<=H48,$A97>H34),0,(H29-IF($A97<H50,0,IF($A97=H50,H63*H54,H63))-IF($A97<H51,0,IF($A97=H51,H67*H55,H67)))/(1+H47)^($A97-H48-1)) | I97: =IF(OR($A97<=I48,$A97>I34),0,(I29-IF($A97<I50,0,IF($A97=I50,I63*I54,I63))-IF($A97<I51,0,IF($A97=I51,I67*I55,I67)))/(1+I47)^($A97-I48-1)) | ... S97: =IF(OR($A97<=S48,$A97>S34),0,(S29-IF($A97<S50,0,IF($A97=S50,S63*S54,S63))-IF($A97<S51,0,IF($A97=S51,S67*S55,S67)))/(1+S47)^($A97-S48-1))
A98: =A97+1 | B98: =IF(OR($A98<=B48,$A98>B34),0,(B29-IF($A98<B50,0,IF($A98=B50,B63*B54,B63))-IF($A98<B51,0,IF($A98=B51,B67*B55,B67)))/(1+B47)^($A98-B48-1)) | C98: =IF(OR($A98<=C48,$A98>C34),0,(C29-IF($A98<C50,0,IF($A98=C50,C63*C54,C63))-IF($A98<C51,0,IF($A98=C51,C67*C55,C67)))/(1+C47)^($A98-C48-1)) | D98: =IF(OR($A98<=D48,$A98>D34),0,(D29-IF($A98<D50,0,IF($A98=D50,D63*D54,D63))-IF($A98<D51,0,IF($A98=D51,D67*D55,D67)))/(1+D47)^($A98-D48-1)) | E98: =IF(OR($A98<=E48,$A98>E34),0,(E29-IF($A98<E50,0,IF($A98=E50,E63*E54,E63))-IF($A98<E51,0,IF($A98=E51,E67*E55,E67)))/(1+E47)^($A98-E48-1)) | F98: =IF(OR($A98<=F48,$A98>F34),0,(F29-IF($A98<F50,0,IF($A98=F50,F63*F54,F63))-IF($A98<F51,0,IF($A98=F51,F67*F55,F67)))/(1+F47)^($A98-F48-1)) | G98: =IF(OR($A98<=G48,$A98>G34),0,(G29-IF($A98<G50,0,IF($A98=G50,G63*G54,G63))-IF($A98<G51,0,IF($A98=G51,G67*G55,G67)))/(1+G47)^($A98-G48-1)) | H98: =IF(OR($A98<=H48,$A98>H34),0,(H29-IF($A98<H50,0,IF($A98=H50,H63*H54,H63))-IF($A98<H51,0,IF($A98=H51,H67*H55,H67)))/(1+H47)^($A98-H48-1)) | I98: =IF(OR($A98<=I48,$A98>I34),0,(I29-IF($A98<I50,0,IF($A98=I50,I63*I54,I63))-IF($A98<I51,0,IF($A98=I51,I67*I55,I67)))/(1+I47)^($A98-I48-1)) | ... S98: =IF(OR($A98<=S48,$A98>S34),0,(S29-IF($A98<S50,0,IF($A98=S50,S63*S54,S63))-IF($A98<S51,0,IF($A98=S51,S67*S55,S67)))/(1+S47)^($A98-S48-1))
A99: =A98+1 | B99: =IF(OR($A99<=B48,$A99>B34),0,(B29-IF($A99<B50,0,IF($A99=B50,B63*B54,B63))-IF($A99<B51,0,IF($A99=B51,B67*B55,B67)))/(1+B47)^($A99-B48-1)) | C99: =IF(OR($A99<=C48,$A99>C34),0,(C29-IF($A99<C50,0,IF($A99=C50,C63*C54,C63))-IF($A99<C51,0,IF($A99=C51,C67*C55,C67)))/(1+C47)^($A99-C48-1)) | D99: =IF(OR($A99<=D48,$A99>D34),0,(D29-IF($A99<D50,0,IF($A99=D50,D63*D54,D63))-IF($A99<D51,0,IF($A99=D51,D67*D55,D67)))/(1+D47)^($A99-D48-1)) | E99: =IF(OR($A99<=E48,$A99>E34),0,(E29-IF($A99<E50,0,IF($A99=E50,E63*E54,E63))-IF($A99<E51,0,IF($A99=E51,E67*E55,E67)))/(1+E47)^($A99-E48-1)) | F99: =IF(OR($A99<=F48,$A99>F34),0,(F29-IF($A99<F50,0,IF($A99=F50,F63*F54,F63))-IF($A99<F51,0,IF($A99=F51,F67*F55,F67)))/(1+F47)^($A99-F48-1)) | G99: =IF(OR($A99<=G48,$A99>G34),0,(G29-IF($A99<G50,0,IF($A99=G50,G63*G54,G63))-IF($A99<G51,0,IF($A99=G51,G67*G55,G67)))/(1+G47)^($A99-G48-1)) | H99: =IF(OR($A99<=H48,$A99>H34),0,(H29-IF($A99<H50,0,IF($A99=H50,H63*H54,H63))-IF($A99<H51,0,IF($A99=H51,H67*H55,H67)))/(1+H47)^($A99-H48-1)) | I99: =IF(OR($A99<=I48,$A99>I34),0,(I29-IF($A99<I50,0,IF($A99=I50,I63*I54,I63))-IF($A99<I51,0,IF($A99=I51,I67*I55,I67)))/(1+I47)^($A99-I48-1)) | ... S99: =IF(OR($A99<=S48,$A99>S34),0,(S29-IF($A99<S50,0,IF($A99=S50,S63*S54,S63))-IF($A99<S51,0,IF($A99=S51,S67*S55,S67)))/(1+S47)^($A99-S48-1))
A100: =A99+1 | B100: =IF(OR($A100<=B48,$A100>B34),0,(B29-IF($A100<B50,0,IF($A100=B50,B63*B54,B63))-IF($A100<B51,0,IF($A100=B51,B67*B55,B67)))/(1+B47)^($A100-B48-1)) | C100: =IF(OR($A100<=C48,$A100>C34),0,(C29-IF($A100<C50,0,IF($A100=C50,C63*C54,C63))-IF($A100<C51,0,IF($A100=C51,C67*C55,C67)))/(1+C47)^($A100-C48-1)) | D100: =IF(OR($A100<=D48,$A100>D34),0,(D29-IF($A100<D50,0,IF($A100=D50,D63*D54,D63))-IF($A100<D51,0,IF($A100=D51,D67*D55,D67)))/(1+D47)^($A100-D48-1)) | E100: =IF(OR($A100<=E48,$A100>E34),0,(E29-IF($A100<E50,0,IF($A100=E50,E63*E54,E63))-IF($A100<E51,0,IF($A100=E51,E67*E55,E67)))/(1+E47)^($A100-E48-1)) | F100: =IF(OR($A100<=F48,$A100>F34),0,(F29-IF($A100<F50,0,IF($A100=F50,F63*F54,F63))-IF($A100<F51,0,IF($A100=F51,F67*F55,F67)))/(1+F47)^($A100-F48-1)) | G100: =IF(OR($A100<=G48,$A100>G34),0,(G29-IF($A100<G50,0,IF($A100=G50,G63*G54,G63))-IF($A100<G51,0,IF($A100=G51,G67*G55,G67)))/(1+G47)^($A100-G48-1)) | H100: =IF(OR($A100<=H48,$A100>H34),0,(H29-IF($A100<H50,0,IF($A100=H50,H63*H54,H63))-IF($A100<H51,0,IF($A100=H51,H67*H55,H67)))/(1+H47)^($A100-H48-1)) | I100: =IF(OR($A100<=I48,$A100>I34),0,(I29-IF($A100<I50,0,IF($A100=I50,I63*I54,I63))-IF($A100<I51,0,IF($A100=I51,I67*I55,I67)))/(1+I47)^($A100-I48-1)) | ... S100: =IF(OR($A100<=S48,$A100>S34),0,(S29-IF($A100<S50,0,IF($A100=S50,S63*S54,S63))-IF($A100<S51,0,IF($A100=S51,S67*S55,S67)))/(1+S47)^($A100-S48-1))
A101: =A100+1 | B101: =IF(OR($A101<=B48,$A101>B34),0,(B29-IF($A101<B50,0,IF($A101=B50,B63*B54,B63))-IF($A101<B51,0,IF($A101=B51,B67*B55,B67)))/(1+B47)^($A101-B48-1)) | C101: =IF(OR($A101<=C48,$A101>C34),0,(C29-IF($A101<C50,0,IF($A101=C50,C63*C54,C63))-IF($A101<C51,0,IF($A101=C51,C67*C55,C67)))/(1+C47)^($A101-C48-1)) | D101: =IF(OR($A101<=D48,$A101>D34),0,(D29-IF($A101<D50,0,IF($A101=D50,D63*D54,D63))-IF($A101<D51,0,IF($A101=D51,D67*D55,D67)))/(1+D47)^($A101-D48-1)) | E101: =IF(OR($A101<=E48,$A101>E34),0,(E29-IF($A101<E50,0,IF($A101=E50,E63*E54,E63))-IF($A101<E51,0,IF($A101=E51,E67*E55,E67)))/(1+E47)^($A101-E48-1)) | F101: =IF(OR($A101<=F48,$A101>F34),0,(F29-IF($A101<F50,0,IF($A101=F50,F63*F54,F63))-IF($A101<F51,0,IF($A101=F51,F67*F55,F67)))/(1+F47)^($A101-F48-1)) | G101: =IF(OR($A101<=G48,$A101>G34),0,(G29-IF($A101<G50,0,IF($A101=G50,G63*G54,G63))-IF($A101<G51,0,IF($A101=G51,G67*G55,G67)))/(1+G47)^($A101-G48-1)) | H101: =IF(OR($A101<=H48,$A101>H34),0,(H29-IF($A101<H50,0,IF($A101=H50,H63*H54,H63))-IF($A101<H51,0,IF($A101=H51,H67*H55,H67)))/(1+H47)^($A101-H48-1)) | I101: =IF(OR($A101<=I48,$A101>I34),0,(I29-IF($A101<I50,0,IF($A101=I50,I63*I54,I63))-IF($A101<I51,0,IF($A101=I51,I67*I55,I67)))/(1+I47)^($A101-I48-1)) | ... S101: =IF(OR($A101<=S48,$A101>S34),0,(S29-IF($A101<S50,0,IF($A101=S50,S63*S54,S63))-IF($A101<S51,0,IF($A101=S51,S67*S55,S67)))/(1+S47)^($A101-S48-1))
A102: =A101+1 | B102: =IF(OR($A102<=B48,$A102>B34),0,(B29-IF($A102<B50,0,IF($A102=B50,B63*B54,B63))-IF($A102<B51,0,IF($A102=B51,B67*B55,B67)))/(1+B47)^($A102-B48-1)) | C102: =IF(OR($A102<=C48,$A102>C34),0,(C29-IF($A102<C50,0,IF($A102=C50,C63*C54,C63))-IF($A102<C51,0,IF($A102=C51,C67*C55,C67)))/(1+C47)^($A102-C48-1)) | D102: =IF(OR($A102<=D48,$A102>D34),0,(D29-IF($A102<D50,0,IF($A102=D50,D63*D54,D63))-IF($A102<D51,0,IF($A102=D51,D67*D55,D67)))/(1+D47)^($A102-D48-1)) | E102: =IF(OR($A102<=E48,$A102>E34),0,(E29-IF($A102<E50,0,IF($A102=E50,E63*E54,E63))-IF($A102<E51,0,IF($A102=E51,E67*E55,E67)))/(1+E47)^($A102-E48-1)) | F102: =IF(OR($A102<=F48,$A102>F34),0,(F29-IF($A102<F50,0,IF($A102=F50,F63*F54,F63))-IF($A102<F51,0,IF($A102=F51,F67*F55,F67)))/(1+F47)^($A102-F48-1)) | G102: =IF(OR($A102<=G48,$A102>G34),0,(G29-IF($A102<G50,0,IF($A102=G50,G63*G54,G63))-IF($A102<G51,0,IF($A102=G51,G67*G55,G67)))/(1+G47)^($A102-G48-1)) | H102: =IF(OR($A102<=H48,$A102>H34),0,(H29-IF($A102<H50,0,IF($A102=H50,H63*H54,H63))-IF($A102<H51,0,IF($A102=H51,H67*H55,H67)))/(1+H47)^($A102-H48-1)) | I102: =IF(OR($A102<=I48,$A102>I34),0,(I29-IF($A102<I50,0,IF($A102=I50,I63*I54,I63))-IF($A102<I51,0,IF($A102=I51,I67*I55,I67)))/(1+I47)^($A102-I48-1)) | ... S102: =IF(OR($A102<=S48,$A102>S34),0,(S29-IF($A102<S50,0,IF($A102=S50,S63*S54,S63))-IF($A102<S51,0,IF($A102=S51,S67*S55,S67)))/(1+S47)^($A102-S48-1))
A103: =A102+1 | B103: =IF(OR($A103<=B48,$A103>B34),0,(B29-IF($A103<B50,0,IF($A103=B50,B63*B54,B63))-IF($A103<B51,0,IF($A103=B51,B67*B55,B67)))/(1+B47)^($A103-B48-1)) | C103: =IF(OR($A103<=C48,$A103>C34),0,(C29-IF($A103<C50,0,IF($A103=C50,C63*C54,C63))-IF($A103<C51,0,IF($A103=C51,C67*C55,C67)))/(1+C47)^($A103-C48-1)) | D103: =IF(OR($A103<=D48,$A103>D34),0,(D29-IF($A103<D50,0,IF($A103=D50,D63*D54,D63))-IF($A103<D51,0,IF($A103=D51,D67*D55,D67)))/(1+D47)^($A103-D48-1)) | E103: =IF(OR($A103<=E48,$A103>E34),0,(E29-IF($A103<E50,0,IF($A103=E50,E63*E54,E63))-IF($A103<E51,0,IF($A103=E51,E67*E55,E67)))/(1+E47)^($A103-E48-1)) | F103: =IF(OR($A103<=F48,$A103>F34),0,(F29-IF($A103<F50,0,IF($A103=F50,F63*F54,F63))-IF($A103<F51,0,IF($A103=F51,F67*F55,F67)))/(1+F47)^($A103-F48-1)) | G103: =IF(OR($A103<=G48,$A103>G34),0,(G29-IF($A103<G50,0,IF($A103=G50,G63*G54,G63))-IF($A103<G51,0,IF($A103=G51,G67*G55,G67)))/(1+G47)^($A103-G48-1)) | H103: =IF(OR($A103<=H48,$A103>H34),0,(H29-IF($A103<H50,0,IF($A103=H50,H63*H54,H63))-IF($A103<H51,0,IF($A103=H51,H67*H55,H67)))/(1+H47)^($A103-H48-1)) | I103: =IF(OR($A103<=I48,$A103>I34),0,(I29-IF($A103<I50,0,IF($A103=I50,I63*I54,I63))-IF($A103<I51,0,IF($A103=I51,I67*I55,I67)))/(1+I47)^($A103-I48-1)) | ... S103: =IF(OR($A103<=S48,$A103>S34),0,(S29-IF($A103<S50,0,IF($A103=S50,S63*S54,S63))-IF($A103<S51,0,IF($A103=S51,S67*S55,S67)))/(1+S47)^($A103-S48-1))
...

Sheet 10-Glide
A1: Il glide path, il costo atteso e il break-even
A2: Strumento informativo / divulgativo. NON è consulenza finanziaria. I valori sono indicativi al 2026 e vanno verificati col tuo consulente.
A4: IL GLIDE ANNO PER ANNO — ribilanciamento a fine anno
A5: Anno | B5: Peso azionario | C5: Rendimento lordo | D5: Rendimento netto bollo | E5: Fattore cumulato | F5: Versamenti capitalizzati
A6: ='1-Input'!$C$16+1 | B6: ='P-Parametri'!$B$54-(('P-Parametri'!$B$54-'P-Parametri'!$B$55)/10)*1 | C6: ='P-Parametri'!$C$42+('P-Parametri'!$B$42-'P-Parametri'!$C$42)*B6 | D6: =C6-'1-Input'!$B$18 | E6: =1+D6 | F6: =('1-Input'!$B$40)*(1+D6)
A7: =A6+1 | B7: ='P-Parametri'!$B$54-(('P-Parametri'!$B$54-'P-Parametri'!$B$55)/10)*2 | C7: ='P-Parametri'!$C$42+('P-Parametri'!$B$42-'P-Parametri'!$C$42)*B7 | D7: =C7-'1-Input'!$B$18 | E7: =E6*(1+D7) | F7: =(F6+'1-Input'!$B$40)*(1+D7)
A8: =A7+1 | B8: ='P-Parametri'!$B$54-(('P-Parametri'!$B$54-'P-Parametri'!$B$55)/10)*3 | C8: ='P-Parametri'!$C$42+('P-Parametri'!$B$42-'P-Parametri'!$C$42)*B8 | D8: =C8-'1-Input'!$B$18 | E8: =E7*(1+D8) | F8: =(F7+'1-Input'!$B$40)*(1+D8)
A9: =A8+1 | B9: ='P-Parametri'!$B$54-(('P-Parametri'!$B$54-'P-Parametri'!$B$55)/10)*4 | C9: ='P-Parametri'!$C$42+('P-Parametri'!$B$42-'P-Parametri'!$C$42)*B9 | D9: =C9-'1-Input'!$B$18 | E9: =E8*(1+D9) | F9: =(F8+'1-Input'!$B$40)*(1+D9)
A10: =A9+1 | B10: ='P-Parametri'!$B$54-(('P-Parametri'!$B$54-'P-Parametri'!$B$55)/10)*5 | C10: ='P-Parametri'!$C$42+('P-Parametri'!$B$42-'P-Parametri'!$C$42)*B10 | D10: =C10-'1-Input'!$B$18 | E10: =E9*(1+D10) | F10: =(F9+'1-Input'!$B$40)*(1+D10)
A11: =A10+1 | B11: ='P-Parametri'!$B$54-(('P-Parametri'!$B$54-'P-Parametri'!$B$55)/10)*6 | C11: ='P-Parametri'!$C$42+('P-Parametri'!$B$42-'P-Parametri'!$C$42)*B11 | D11: =C11-'1-Input'!$B$18 | E11: =E10*(1+D11) | F11: =(F10+'1-Input'!$B$40)*(1+D11)
A12: =A11+1 | B12: ='P-Parametri'!$B$54-(('P-Parametri'!$B$54-'P-Parametri'!$B$55)/10)*7 | C12: ='P-Parametri'!$C$42+('P-Parametri'!$B$42-'P-Parametri'!$C$42)*B12 | D12: =C12-'1-Input'!$B$18 | E12: =E11*(1+D12) | F12: =(F11+'1-Input'!$B$40)*(1+D12)
A13: =A12+1 | B13: ='P-Parametri'!$B$54-(('P-Parametri'!$B$54-'P-Parametri'!$B$55)/10)*8 | C13: ='P-Parametri'!$C$42+('P-Parametri'!$B$42-'P-Parametri'!$C$42)*B13 | D13: =C13-'1-Input'!$B$18 | E13: =E12*(1+D13) | F13: =(F12+'1-Input'!$B$40)*(1+D13)
A14: =A13+1 | B14: ='P-Parametri'!$B$54-(('P-Parametri'!$B$54-'P-Parametri'!$B$55)/10)*9 | C14: ='P-Parametri'!$C$42+('P-Parametri'!$B$42-'P-Parametri'!$C$42)*B14 | D14: =C14-'1-Input'!$B$18 | E14: =E13*(1+D14) | F14: =(F13+'1-Input'!$B$40)*(1+D14)
A15: =A14+1 | B15: ='P-Parametri'!$B$54-(('P-Parametri'!$B$54-'P-Parametri'!$B$55)/10)*10 | C15: ='P-Parametri'!$C$42+('P-Parametri'!$B$42-'P-Parametri'!$C$42)*B15 | D15: =C15-'1-Input'!$B$18 | E15: =E14*(1+D15) | F15: =(F14+'1-Input'!$B$40)*(1+D15)
A17: IL COSTO ATTESO
A18: Fattore cumulato dei dieci anni | B18: =E15
A19: Versamenti capitalizzati | B19: =F15
A20: Capitale al ritiro col portafoglio fisso | B20: ='2-Composizione'!$B$36*(1+'1-Input'!$B$46)^'1-Input'!$B$50+'1-Input'!$B$40*(1+'1-Input'!$B$46)*(((1+'1-Input'!$B$46)^'1-Input'!$B$50-1)/'1-Input'!$B$46)
A21: CAPITALE AL RITIRO COL GLIDE | B21: ='2-Composizione'!$B$36*B18+B19
A22: COSTO ATTESO DEL GLIDE | B22: =B20-B21
A24: L'ANNO PEGGIORE E IL BREAK-EVEN
A25: Capitale residuo col portafoglio fisso | B25: =B20*(1+'P-Parametri'!$B$54*'P-Parametri'!$B$53)
A26: Capitale residuo col glide | B26: =B21*(1+'P-Parametri'!$B$55*'P-Parametri'!$B$53)
A27: Differenza a favore del glide nell'anno peggiore | B27: =B26-B25
A28: BREAK-EVEN sul crollo azionario | B28: =B22/('P-Parametri'!$B$54*B20-'P-Parametri'!$B$55*B21)
A30: IL GLIDE DENTRO IL CONTO DEL FABBISOGNO (ipotesi prudente)
A31: Fabbisogno col glide / con il portafoglio fisso | B31: ='9-Leve'!$J$76 | C31: ='9-Leve'!$B$76
A32: Delta posizione netta | B32: ='9-Leve'!$J$79
A34: CONVENZIONE — il ribilanciamento e' a FINE ANNO, quindi il primo anno il peso azionario e' gia' sceso di tre punti: l'etichetta corretta e' «da 70/30 a 40/60, con i pesi che partono da 67 gia' nel primo anno».
A35: La regola unica che concilia i due video del catalogo: il glide costa rendimento atteso e compra riduzione di dispersione, quindi conviene quando il rendimento a cui rinunci non ti serve piu' per arrivare al traguardo, e non conviene quando ti serve ancora. Nel video sul montante era in DECUMULO con un capitale tirato; qui si ACCUMULA e il capitale avanza.
A36: Scenario ILLUSTRATIVO, non probabilistico: con un crollo azionario sopra il break-even il ribilanciamento lascia piu' capitale in mano, sotto meno. In tutti e due i casi il capitale resta molto sopra il fabbisogno: la scelta sposta il margine, non l'esito.
A37: Il portafoglio post-ritiro del glide (40/60) rende meno, quindi il fabbisogno col glide e' piu' alto: e' il costo dichiarato della riduzione di dispersione, ed e' contato dentro la posizione netta del foglio 9.

Sheet 11-Banda
A1: La banda del fabbisogno — quattordici scenari ricalcolati
A2: Strumento informativo / divulgativo. NON è consulenza finanziaria. I valori sono indicativi al 2026 e vanno verificati col tuo consulente.
A4: LE QUATTORDICI RIGHE, ORDINATE PER FABBISOGNO CRESCENTE
A5: Scenario | B5: Valore attuale netto | C5: Fabbisogno lordo | D5: Fabbisogno finanziario | E5: Scarto contro la base
A6: 1 — Spesa piu' bassa | B6: =B73 | C6: =B74 | D6: =B76 | E6: =B76-$D$9
A7: 2 — Via dei 65 anni (scenario B) | B7: =C73 | C7: =C74 | D7: =C76 | E7: =C76-$D$9
A8: 3 — Orizzonte basso | B8: =D73 | C8: =D74 | D8: =D76 | E8: =D76-$D$9
A9: 4 — BASE (vecchiaia, orizzonte centrale) | B9: =E73 | C9: =E74 | D9: =E76 | E9: =E76-$D$9
A10: 5 — Rendimento al pavimento | B10: =F73 | C10: =F74 | D10: =F76 | E10: =F76-$D$9
A11: 6 — Orizzonte alto | B11: =G73 | C11: =G74 | D11: =G76 | E11: =G76-$D$9
A12: 7 — Montante di Chiara al minimo | B12: =H73 | C12: =H74 | D12: =H76 | E12: =H76-$D$9
A13: 8 — Requisito +1 anno | B13: =I73 | C13: =I74 | D13: =I76 | E13: =I76-$D$9
A14: 9 — Pensioni meno 10% | B14: =J73 | C14: =J74 | D14: =J76 | E14: =J76-$D$9
A15: 10 — Requisito +2 anni | B15: =K73 | C15: =K74 | D15: =K76 | E15: =K76-$D$9
A16: 11 — Spesa piu' alta | B16: =L73 | C16: =L74 | D16: =L76 | E16: =L76-$D$9
A17: 12 — Pensioni meno 20% | B17: =M73 | C17: =M74 | D17: =M76 | E17: =M76-$D$9
A18: 13 — SCENARIO CAUTO (pensioni meno 20% + requisito +2 + orizzonte alto) | B18: =N73 | C18: =N74 | D18: =N76 | E18: =N76-$D$9
A19: 14 — Cauto + rendimento al pavimento | B19: =O73 | C19: =O74 | D19: =O76 | E19: =O76-$D$9
A21: LA FORBICE E LE TRE LEVE DEL RISCHIO
A22: Forbice pubblicata — dal centrale (riga 4) al cauto col pavimento (riga 14) | B22: =D9 | C22: =D19 | D22: =D19/D9
A23: Peso delle tre cautele: pensioni / requisito / orizzonte | B23: =D17-D9 | C23: =D15-D9 | D23: =D11-D9
A24: Le tre cautele una per volta / messe insieme / differenza | B24: =B23+C23+D23 | C24: =D18-D9 | D24: =C24/B24-1
A25: CONVENZIONE 4 — le pensioni degli scenari cauti si tagliano AL LORDO e il netto si ricalcola con il modulo IRPEF completo. La convenzione e' piu' rigorosa (un taglio della prestazione e' un taglio del lordo, e la progressivita' non e' lineare), e la direzione dell'effetto va dichiarata perche' va dalla parte comoda: rende gli scenari cauti MENO severi di quanto sarebbero tagliando il netto.
A27: SCENARIO | B27: 1 — Spesa piu' bassa | C27: 2 — Via dei 65 anni (scenario B) | D27: 3 — Orizzonte basso | E27: 4 — BASE (vecchiaia, orizzonte centrale) | F27: 5 — Rendimento al pavimento | G27: 6 — Orizzonte alto | H27: 7 — Montante di Chiara al minimo | I27: 8 — Requisito +1 anno | J27: 9 — Pensioni meno 10% | K27: 10 — Requisito +2 anni | L27: 11 — Spesa piu' alta | M27: 12 — Pensioni meno 20% | N27: 13 — SCENARIO CAUTO (pensioni meno 20% + requisito +2 + orizzonte alto) | O27: 14 — Cauto + rendimento al pavimento
A28: Spesa prima del ritiro | B28: ='1-Input'!$B$13 | C28: ='1-Input'!$B$13 | D28: ='1-Input'!$B$13 | E28: ='1-Input'!$B$13 | F28: ='1-Input'!$B$13 | G28: ='1-Input'!$B$13 | H28: ='1-Input'!$B$13 | I28: ='1-Input'!$B$13 | ... O28: ='1-Input'!$B$13
A29: Spesa dopo il ritiro | B29: ='1-Input'!$B$13-'P-Parametri'!$B$66 | C29: ='1-Input'!$B$13 | D29: ='1-Input'!$B$13 | E29: ='1-Input'!$B$13 | F29: ='1-Input'!$B$13 | G29: ='1-Input'!$B$13 | H29: ='1-Input'!$B$13 | I29: ='1-Input'!$B$13 | J29: ='1-Input'!$B$13 | K29: ='1-Input'!$B$13 | L29: ='1-Input'!$B$13+'P-Parametri'!$B$66 | M29: ='1-Input'!$B$13 | N29: ='1-Input'!$B$13 | O29: ='1-Input'!$B$13
A30: Risparmio annuo | B30: ='1-Input'!$B$40 | C30: ='1-Input'!$B$40 | D30: ='1-Input'!$B$40 | E30: ='1-Input'!$B$40 | F30: ='1-Input'!$B$40 | G30: ='1-Input'!$B$40 | H30: ='1-Input'!$B$40 | I30: ='1-Input'!$B$40 | ... O30: ='1-Input'!$B$40
A31: Anni di lavoro in piu' | B31: =0 | C31: =0 | D31: =0 | E31: =0 | F31: =0 | G31: =0 | H31: =0 | I31: =0 | ... O31: =0
A32: Requisito anagrafico: anni in piu' | B32: ='1-Input'!$B$22 | C32: ='1-Input'!$B$22 | D32: ='1-Input'!$B$22 | E32: ='1-Input'!$B$22 | F32: ='1-Input'!$B$22 | G32: ='1-Input'!$B$22 | H32: ='1-Input'!$B$22 | I32: ='1-Input'!$B$22+1 | J32: ='1-Input'!$B$22 | K32: ='1-Input'!$B$22+2 | L32: ='1-Input'!$B$22 | M32: ='1-Input'!$B$22 | N32: ='1-Input'!$B$22+2 | O32: ='1-Input'!$B$22+2
A33: Fattore sulle pensioni lorde | B33: =1 | C33: =1 | D33: =1 | E33: =1 | F33: =1 | G33: =1 | H33: =1 | I33: =1 | J33: =1-'P-Parametri'!$B$51/2 | K33: =1 | L33: =1 | M33: =1-'P-Parametri'!$B$51 | N33: =1-'P-Parametri'!$B$51 | O33: =1-'P-Parametri'!$B$51
A34: Anno di orizzonte | B34: ='1-Input'!$B$47 | C34: ='1-Input'!$B$47 | D34: ='1-Input'!$B$5+'P-Parametri'!$B$65 | E34: ='1-Input'!$B$47 | F34: ='1-Input'!$B$47 | G34: ='1-Input'!$B$5+'P-Parametri'!$C$65 | H34: ='1-Input'!$B$47 | I34: ='1-Input'!$B$47 | J34: ='1-Input'!$B$47 | K34: ='1-Input'!$B$47 | L34: ='1-Input'!$B$47 | M34: ='1-Input'!$B$47 | N34: ='1-Input'!$B$5+'P-Parametri'!$C$65 | O34: ='1-Input'!$B$5+'P-Parametri'!$C$65
A35: Rendimento lordo — accumulo | B35: ='1-Input'!$B$17 | C35: ='1-Input'!$B$17 | D35: ='1-Input'!$B$17 | E35: ='1-Input'!$B$17 | F35: ='3-Rendimento'!$C$15 | G35: ='1-Input'!$B$17 | H35: ='1-Input'!$B$17 | I35: ='1-Input'!$B$17 | J35: ='1-Input'!$B$17 | K35: ='1-Input'!$B$17 | L35: ='1-Input'!$B$17 | M35: ='1-Input'!$B$17 | N35: ='1-Input'!$B$17 | O35: ='3-Rendimento'!$C$15
A36: Rendimento lordo — decumulo | B36: ='1-Input'!$B$17 | C36: ='1-Input'!$B$17 | D36: ='1-Input'!$B$17 | E36: ='1-Input'!$B$17 | F36: ='3-Rendimento'!$C$15 | G36: ='1-Input'!$B$17 | H36: ='1-Input'!$B$17 | I36: ='1-Input'!$B$17 | J36: ='1-Input'!$B$17 | K36: ='1-Input'!$B$17 | L36: ='1-Input'!$B$17 | M36: ='1-Input'!$B$17 | N36: ='1-Input'!$B$17 | O36: ='3-Rendimento'!$C$15
A37: Montante di Chiara al 2026 | B37: ='4-Montanti'!$B$9 | C37: ='4-Montanti'!$B$9 | D37: ='4-Montanti'!$B$9 | E37: ='4-Montanti'!$B$9 | F37: ='4-Montanti'!$B$9 | G37: ='4-Montanti'!$B$9 | H37: ='P-Parametri'!$B$45 | I37: ='4-Montanti'!$B$9 | J37: ='4-Montanti'!$B$9 | K37: ='4-Montanti'!$B$9 | L37: ='4-Montanti'!$B$9 | M37: ='4-Montanti'!$B$9 | N37: ='4-Montanti'!$B$9 | O37: ='4-Montanti'!$B$9
A38: Montante del marito al 2026 | B38: ='4-Montanti'!$C$9 | C38: ='4-Montanti'!$C$9 | D38: ='4-Montanti'!$C$9 | E38: ='4-Montanti'!$C$9 | F38: ='4-Montanti'!$C$9 | G38: ='4-Montanti'!$C$9 | H38: ='4-Montanti'!$C$9 | I38: ='4-Montanti'!$C$9 | ... O38: ='4-Montanti'!$C$9
A39: Coefficiente di trasformazione — Chiara | B39: ='P-Parametri'!$B$21 | C39: ='1-Input'!$B$55 | D39: ='P-Parametri'!$B$21 | E39: ='P-Parametri'!$B$21 | F39: ='P-Parametri'!$B$21 | G39: ='P-Parametri'!$B$21 | H39: ='P-Parametri'!$B$21 | I39: ='P-Parametri'!$B$21 | J39: ='P-Parametri'!$B$21 | K39: ='P-Parametri'!$B$21 | ... O39: ='P-Parametri'!$B$21
A40: Coefficiente di trasformazione — marito | B40: ='P-Parametri'!$B$21 | C40: ='1-Input'!$C$55 | D40: ='P-Parametri'!$B$21 | E40: ='P-Parametri'!$B$21 | F40: ='P-Parametri'!$B$21 | G40: ='P-Parametri'!$B$21 | H40: ='P-Parametri'!$B$21 | I40: ='P-Parametri'!$B$21 | J40: ='P-Parametri'!$B$21 | K40: ='P-Parametri'!$B$21 | ... O40: ='P-Parametri'!$B$21
A41: Anno di decorrenza base — Chiara | B41: ='1-Input'!$B$51 | C41: ='1-Input'!$B$53 | D41: ='1-Input'!$B$51 | E41: ='1-Input'!$B$51 | F41: ='1-Input'!$B$51 | G41: ='1-Input'!$B$51 | H41: ='1-Input'!$B$51 | I41: ='1-Input'!$B$51 | J41: ='1-Input'!$B$51 | K41: ='1-Input'!$B$51 | ... O41: ='1-Input'!$B$51
A42: Mese di decorrenza — Chiara | B42: ='1-Input'!$C$51 | C42: ='1-Input'!$C$53 | D42: ='1-Input'!$C$51 | E42: ='1-Input'!$C$51 | F42: ='1-Input'!$C$51 | G42: ='1-Input'!$C$51 | H42: ='1-Input'!$C$51 | I42: ='1-Input'!$C$51 | J42: ='1-Input'!$C$51 | K42: ='1-Input'!$C$51 | ... O42: ='1-Input'!$C$51
A43: Anno di decorrenza base — marito | B43: ='1-Input'!$B$52 | C43: ='1-Input'!$B$54 | D43: ='1-Input'!$B$52 | E43: ='1-Input'!$B$52 | F43: ='1-Input'!$B$52 | G43: ='1-Input'!$B$52 | H43: ='1-Input'!$B$52 | I43: ='1-Input'!$B$52 | J43: ='1-Input'!$B$52 | K43: ='1-Input'!$B$52 | ... O43: ='1-Input'!$B$52
A44: Mese di decorrenza — marito | B44: ='1-Input'!$C$52 | C44: ='1-Input'!$C$54 | D44: ='1-Input'!$C$52 | E44: ='1-Input'!$C$52 | F44: ='1-Input'!$C$52 | G44: ='1-Input'!$C$52 | H44: ='1-Input'!$C$52 | I44: ='1-Input'!$C$52 | J44: ='1-Input'!$C$52 | K44: ='1-Input'!$C$52 | ... O44: ='1-Input'!$C$52
A45: Capitale sostitutivo (0 = calcolato dal motore) | B45: =0 | C45: =0 | D45: =0 | E45: =0 | F45: =0 | G45: =0 | H45: =0 | I45: =0 | ... O45: =0
A46: Rendimento netto bollo — accumulo | B46: =B35-'1-Input'!$B$18 | C46: =C35-'1-Input'!$B$18 | D46: =D35-'1-Input'!$B$18 | E46: =E35-'1-Input'!$B$18 | F46: =F35-'1-Input'!$B$18 | G46: =G35-'1-Input'!$B$18 | H46: =H35-'1-Input'!$B$18 | I46: =I35-'1-Input'!$B$18 | ... O46: =O35-'1-Input'!$B$18
A47: Rendimento netto bollo — decumulo | B47: =B36-'1-Input'!$B$18 | C47: =C36-'1-Input'!$B$18 | D47: =D36-'1-Input'!$B$18 | E47: =E36-'1-Input'!$B$18 | F47: =F36-'1-Input'!$B$18 | G47: =G36-'1-Input'!$B$18 | H47: =H36-'1-Input'!$B$18 | I47: =I36-'1-Input'!$B$18 | ... O47: =O36-'1-Input'!$B$18
A48: Anno di valutazione | B48: ='1-Input'!$B$19+B31 | C48: ='1-Input'!$B$19+C31 | D48: ='1-Input'!$B$19+D31 | E48: ='1-Input'!$B$19+E31 | F48: ='1-Input'!$B$19+F31 | G48: ='1-Input'!$B$19+G31 | H48: ='1-Input'!$B$19+H31 | I48: ='1-Input'!$B$19+I31 | ... O48: ='1-Input'!$B$19+O31
A49: Anni di contribuzione dopo il 2026 | B49: ='1-Input'!$B$19-'1-Input'!$C$16+B31 | C49: ='1-Input'!$B$19-'1-Input'!$C$16+C31 | D49: ='1-Input'!$B$19-'1-Input'!$C$16+D31 | E49: ='1-Input'!$B$19-'1-Input'!$C$16+E31 | F49: ='1-Input'!$B$19-'1-Input'!$C$16+F31 | G49: ='1-Input'!$B$19-'1-Input'!$C$16+G31 | H49: ='1-Input'!$B$19-'1-Input'!$C$16+H31 | I49: ='1-Input'!$B$19-'1-Input'!$C$16+I31 | ... O49: ='1-Input'!$B$19-'1-Input'!$C$16+O31
A50: Anno di decorrenza effettivo — Chiara | B50: =B41+B32 | C50: =C41+C32 | D50: =D41+D32 | E50: =E41+E32 | F50: =F41+F32 | G50: =G41+G32 | H50: =H41+H32 | I50: =I41+I32 | ... O50: =O41+O32
A51: Anno di decorrenza effettivo — marito | B51: =B43+B32 | C51: =C43+C32 | D51: =D43+D32 | E51: =E43+E32 | F51: =F43+F32 | G51: =G43+G32 | H51: =H43+H32 | I51: =I43+I32 | ... O51: =O43+O32
A52: Anni di sola rivalutazione — Chiara | B52: =B50-('1-Input'!$C$16+1)+(B42-1)/12-B49 | C52: =C50-('1-Input'!$C$16+1)+(C42-1)/12-C49 | D52: =D50-('1-Input'!$C$16+1)+(D42-1)/12-D49 | E52: =E50-('1-Input'!$C$16+1)+(E42-1)/12-E49 | F52: =F50-('1-Input'!$C$16+1)+(F42-1)/12-F49 | G52: =G50-('1-Input'!$C$16+1)+(G42-1)/12-G49 | H52: =H50-('1-Input'!$C$16+1)+(H42-1)/12-H49 | I52: =I50-('1-Input'!$C$16+1)+(I42-1)/12-I49 | ... O52: =O50-('1-Input'!$C$16+1)+(O42-1)/12-O49
A53: Anni di sola rivalutazione — marito | B53: =B51-('1-Input'!$C$16+1)+(B44-1)/12-B49 | C53: =C51-('1-Input'!$C$16+1)+(C44-1)/12-C49 | D53: =D51-('1-Input'!$C$16+1)+(D44-1)/12-D49 | E53: =E51-('1-Input'!$C$16+1)+(E44-1)/12-E49 | F53: =F51-('1-Input'!$C$16+1)+(F44-1)/12-F49 | G53: =G51-('1-Input'!$C$16+1)+(G44-1)/12-G49 | H53: =H51-('1-Input'!$C$16+1)+(H44-1)/12-H49 | I53: =I51-('1-Input'!$C$16+1)+(I44-1)/12-I49 | ... O53: =O51-('1-Input'!$C$16+1)+(O44-1)/12-O49
A54: Frazione della prima annualita' — Chiara | B54: =IF(B42=1,1,'P-Parametri'!$B$59) | C54: =IF(C42=1,1,'P-Parametri'!$B$59) | D54: =IF(D42=1,1,'P-Parametri'!$B$59) | E54: =IF(E42=1,1,'P-Parametri'!$B$59) | F54: =IF(F42=1,1,'P-Parametri'!$B$59) | G54: =IF(G42=1,1,'P-Parametri'!$B$59) | H54: =IF(H42=1,1,'P-Parametri'!$B$59) | I54: =IF(I42=1,1,'P-Parametri'!$B$59) | ... O54: =IF(O42=1,1,'P-Parametri'!$B$59)
A55: Frazione della prima annualita' — marito | B55: =IF(B44=1,1,'P-Parametri'!$B$59) | C55: =IF(C44=1,1,'P-Parametri'!$B$59) | D55: =IF(D44=1,1,'P-Parametri'!$B$59) | E55: =IF(E44=1,1,'P-Parametri'!$B$59) | F55: =IF(F44=1,1,'P-Parametri'!$B$59) | G55: =IF(G44=1,1,'P-Parametri'!$B$59) | H55: =IF(H44=1,1,'P-Parametri'!$B$59) | I55: =IF(I44=1,1,'P-Parametri'!$B$59) | ... O55: =IF(O44=1,1,'P-Parametri'!$B$59)
A56: Montante alla decorrenza — Chiara | B56: =(B37*(1+'1-Input'!$B$21)^B49+'1-Input'!$B$48*(IF('1-Input'!$B$21=0,B49,((1+'1-Input'!$B$21)^B49-1)/'1-Input'!$B$21)))*(1+'1-Input'!$B$21)^B52 | C56: =(C37*(1+'1-Input'!$B$21)^C49+'1-Input'!$B$48*(IF('1-Input'!$B$21=0,C49,((1+'1-Input'!$B$21)^C49-1)/'1-Input'!$B$21)))*(1+'1-Input'!$B$21)^C52 | D56: =(D37*(1+'1-Input'!$B$21)^D49+'1-Input'!$B$48*(IF('1-Input'!$B$21=0,D49,((1+'1-Input'!$B$21)^D49-1)/'1-Input'!$B$21)))*(1+'1-Input'!$B$21)^D52 | E56: =(E37*(1+'1-Input'!$B$21)^E49+'1-Input'!$B$48*(IF('1-Input'!$B$21=0,E49,((1+'1-Input'!$B$21)^E49-1)/'1-Input'!$B$21)))*(1+'1-Input'!$B$21)^E52 | F56: =(F37*(1+'1-Input'!$B$21)^F49+'1-Input'!$B$48*(IF('1-Input'!$B$21=0,F49,((1+'1-Input'!$B$21)^F49-1)/'1-Input'!$B$21)))*(1+'1-Input'!$B$21)^F52 | G56: =(G37*(1+'1-Input'!$B$21)^G49+'1-Input'!$B$48*(IF('1-Input'!$B$21=0,G49,((1+'1-Input'!$B$21)^G49-1)/'1-Input'!$B$21)))*(1+'1-Input'!$B$21)^G52 | H56: =(H37*(1+'1-Input'!$B$21)^H49+'1-Input'!$B$48*(IF('1-Input'!$B$21=0,H49,((1+'1-Input'!$B$21)^H49-1)/'1-Input'!$B$21)))*(1+'1-Input'!$B$21)^H52 | I56: =(I37*(1+'1-Input'!$B$21)^I49+'1-Input'!$B$48*(IF('1-Input'!$B$21=0,I49,((1+'1-Input'!$B$21)^I49-1)/'1-Input'!$B$21)))*(1+'1-Input'!$B$21)^I52 | ... O56: =(O37*(1+'1-Input'!$B$21)^O49+'1-Input'!$B$48*(IF('1-Input'!$B$21=0,O49,((1+'1-Input'!$B$21)^O49-1)/'1-Input'!$B$21)))*(1+'1-Input'!$B$21)^O52
A57: Montante alla decorrenza — marito | B57: =(B38*(1+'1-Input'!$B$21)^B49+'1-Input'!$C$48*(IF('1-Input'!$B$21=0,B49,((1+'1-Input'!$B$21)^B49-1)/'1-Input'!$B$21)))*(1+'1-Input'!$B$21)^B53 | C57: =(C38*(1+'1-Input'!$B$21)^C49+'1-Input'!$C$48*(IF('1-Input'!$B$21=0,C49,((1+'1-Input'!$B$21)^C49-1)/'1-Input'!$B$21)))*(1+'1-Input'!$B$21)^C53 | D57: =(D38*(1+'1-Input'!$B$21)^D49+'1-Input'!$C$48*(IF('1-Input'!$B$21=0,D49,((1+'1-Input'!$B$21)^D49-1)/'1-Input'!$B$21)))*(1+'1-Input'!$B$21)^D53 | E57: =(E38*(1+'1-Input'!$B$21)^E49+'1-Input'!$C$48*(IF('1-Input'!$B$21=0,E49,((1+'1-Input'!$B$21)^E49-1)/'1-Input'!$B$21)))*(1+'1-Input'!$B$21)^E53 | F57: =(F38*(1+'1-Input'!$B$21)^F49+'1-Input'!$C$48*(IF('1-Input'!$B$21=0,F49,((1+'1-Input'!$B$21)^F49-1)/'1-Input'!$B$21)))*(1+'1-Input'!$B$21)^F53 | G57: =(G38*(1+'1-Input'!$B$21)^G49+'1-Input'!$C$48*(IF('1-Input'!$B$21=0,G49,((1+'1-Input'!$B$21)^G49-1)/'1-Input'!$B$21)))*(1+'1-Input'!$B$21)^G53 | H57: =(H38*(1+'1-Input'!$B$21)^H49+'1-Input'!$C$48*(IF('1-Input'!$B$21=0,H49,((1+'1-Input'!$B$21)^H49-1)/'1-Input'!$B$21)))*(1+'1-Input'!$B$21)^H53 | I57: =(I38*(1+'1-Input'!$B$21)^I49+'1-Input'!$C$48*(IF('1-Input'!$B$21=0,I49,((1+'1-Input'!$B$21)^I49-1)/'1-Input'!$B$21)))*(1+'1-Input'!$B$21)^I53 | ... O57: =(O38*(1+'1-Input'!$B$21)^O49+'1-Input'!$C$48*(IF('1-Input'!$B$21=0,O49,((1+'1-Input'!$B$21)^O49-1)/'1-Input'!$B$21)))*(1+'1-Input'!$B$21)^O53
A58: Pensione lorda — Chiara | B58: =B56*B39*B33 | C58: =C56*C39*C33 | D58: =D56*D39*D33 | E58: =E56*E39*E33 | F58: =F56*F39*F33 | G58: =G56*G39*G33 | H58: =H56*H39*H33 | I58: =I56*I39*I33 | ... O58: =O56*O39*O33
A59: Pensione lorda — marito | B59: =B57*B40*B33 | C59: =C57*C40*C33 | D59: =D57*D40*D33 | E59: =E57*E40*E33 | F59: =F57*F40*F33 | G59: =G57*G40*G33 | H59: =H57*H40*H33 | I59: =I57*I40*I33 | ... O59: =O57*O40*O33
A60: IRPEF lorda — Chiara | B60: =IF(B58<='P-Parametri'!$B$6,'P-Parametri'!$C$6*B58,IF(B58<='P-Parametri'!$B$7,'P-Parametri'!$B$9+'P-Parametri'!$C$7*(B58-'P-Parametri'!$B$6),'P-Parametri'!$B$10+'P-Parametri'!$C$8*(B58-'P-Parametri'!$B$7))) | C60: =IF(C58<='P-Parametri'!$B$6,'P-Parametri'!$C$6*C58,IF(C58<='P-Parametri'!$B$7,'P-Parametri'!$B$9+'P-Parametri'!$C$7*(C58-'P-Parametri'!$B$6),'P-Parametri'!$B$10+'P-Parametri'!$C$8*(C58-'P-Parametri'!$B$7))) | D60: =IF(D58<='P-Parametri'!$B$6,'P-Parametri'!$C$6*D58,IF(D58<='P-Parametri'!$B$7,'P-Parametri'!$B$9+'P-Parametri'!$C$7*(D58-'P-Parametri'!$B$6),'P-Parametri'!$B$10+'P-Parametri'!$C$8*(D58-'P-Parametri'!$B$7))) | E60: =IF(E58<='P-Parametri'!$B$6,'P-Parametri'!$C$6*E58,IF(E58<='P-Parametri'!$B$7,'P-Parametri'!$B$9+'P-Parametri'!$C$7*(E58-'P-Parametri'!$B$6),'P-Parametri'!$B$10+'P-Parametri'!$C$8*(E58-'P-Parametri'!$B$7))) | F60: =IF(F58<='P-Parametri'!$B$6,'P-Parametri'!$C$6*F58,IF(F58<='P-Parametri'!$B$7,'P-Parametri'!$B$9+'P-Parametri'!$C$7*(F58-'P-Parametri'!$B$6),'P-Parametri'!$B$10+'P-Parametri'!$C$8*(F58-'P-Parametri'!$B$7))) | G60: =IF(G58<='P-Parametri'!$B$6,'P-Parametri'!$C$6*G58,IF(G58<='P-Parametri'!$B$7,'P-Parametri'!$B$9+'P-Parametri'!$C$7*(G58-'P-Parametri'!$B$6),'P-Parametri'!$B$10+'P-Parametri'!$C$8*(G58-'P-Parametri'!$B$7))) | H60: =IF(H58<='P-Parametri'!$B$6,'P-Parametri'!$C$6*H58,IF(H58<='P-Parametri'!$B$7,'P-Parametri'!$B$9+'P-Parametri'!$C$7*(H58-'P-Parametri'!$B$6),'P-Parametri'!$B$10+'P-Parametri'!$C$8*(H58-'P-Parametri'!$B$7))) | I60: =IF(I58<='P-Parametri'!$B$6,'P-Parametri'!$C$6*I58,IF(I58<='P-Parametri'!$B$7,'P-Parametri'!$B$9+'P-Parametri'!$C$7*(I58-'P-Parametri'!$B$6),'P-Parametri'!$B$10+'P-Parametri'!$C$8*(I58-'P-Parametri'!$B$7))) | ... O60: =IF(O58<='P-Parametri'!$B$6,'P-Parametri'!$C$6*O58,IF(O58<='P-Parametri'!$B$7,'P-Parametri'!$B$9+'P-Parametri'!$C$7*(O58-'P-Parametri'!$B$6),'P-Parametri'!$B$10+'P-Parametri'!$C$8*(O58-'P-Parametri'!$B$7)))
A61: Detrazione da pensione — Chiara | B61: =IF(B58<='P-Parametri'!$C$12,'P-Parametri'!$B$12,IF(B58<='P-Parametri'!$B$6,'P-Parametri'!$B$13+'P-Parametri'!$C$13*('P-Parametri'!$B$6-B58)/'P-Parametri'!$D$13,IF(B58<='P-Parametri'!$B$7,'P-Parametri'!$B$14*('P-Parametri'!$B$7-B58)/'P-Parametri'!$C$14,0)))+IF(AND(B58>'P-Parametri'!$C$15,B58<'P-Parametri'!$D$15),'P-Parametri'!$B$15,0) | C61: =IF(C58<='P-Parametri'!$C$12,'P-Parametri'!$B$12,IF(C58<='P-Parametri'!$B$6,'P-Parametri'!$B$13+'P-Parametri'!$C$13*('P-Parametri'!$B$6-C58)/'P-Parametri'!$D$13,IF(C58<='P-Parametri'!$B$7,'P-Parametri'!$B$14*('P-Parametri'!$B$7-C58)/'P-Parametri'!$C$14,0)))+IF(AND(C58>'P-Parametri'!$C$15,C58<'P-Parametri'!$D$15),'P-Parametri'!$B$15,0) | D61: =IF(D58<='P-Parametri'!$C$12,'P-Parametri'!$B$12,IF(D58<='P-Parametri'!$B$6,'P-Parametri'!$B$13+'P-Parametri'!$C$13*('P-Parametri'!$B$6-D58)/'P-Parametri'!$D$13,IF(D58<='P-Parametri'!$B$7,'P-Parametri'!$B$14*('P-Parametri'!$B$7-D58)/'P-Parametri'!$C$14,0)))+IF(AND(D58>'P-Parametri'!$C$15,D58<'P-Parametri'!$D$15),'P-Parametri'!$B$15,0) | E61: =IF(E58<='P-Parametri'!$C$12,'P-Parametri'!$B$12,IF(E58<='P-Parametri'!$B$6,'P-Parametri'!$B$13+'P-Parametri'!$C$13*('P-Parametri'!$B$6-E58)/'P-Parametri'!$D$13,IF(E58<='P-Parametri'!$B$7,'P-Parametri'!$B$14*('P-Parametri'!$B$7-E58)/'P-Parametri'!$C$14,0)))+IF(AND(E58>'P-Parametri'!$C$15,E58<'P-Parametri'!$D$15),'P-Parametri'!$B$15,0) | F61: =IF(F58<='P-Parametri'!$C$12,'P-Parametri'!$B$12,IF(F58<='P-Parametri'!$B$6,'P-Parametri'!$B$13+'P-Parametri'!$C$13*('P-Parametri'!$B$6-F58)/'P-Parametri'!$D$13,IF(F58<='P-Parametri'!$B$7,'P-Parametri'!$B$14*('P-Parametri'!$B$7-F58)/'P-Parametri'!$C$14,0)))+IF(AND(F58>'P-Parametri'!$C$15,F58<'P-Parametri'!$D$15),'P-Parametri'!$B$15,0) | G61: =IF(G58<='P-Parametri'!$C$12,'P-Parametri'!$B$12,IF(G58<='P-Parametri'!$B$6,'P-Parametri'!$B$13+'P-Parametri'!$C$13*('P-Parametri'!$B$6-G58)/'P-Parametri'!$D$13,IF(G58<='P-Parametri'!$B$7,'P-Parametri'!$B$14*('P-Parametri'!$B$7-G58)/'P-Parametri'!$C$14,0)))+IF(AND(G58>'P-Parametri'!$C$15,G58<'P-Parametri'!$D$15),'P-Parametri'!$B$15,0) | H61: =IF(H58<='P-Parametri'!$C$12,'P-Parametri'!$B$12,IF(H58<='P-Parametri'!$B$6,'P-Parametri'!$B$13+'P-Parametri'!$C$13*('P-Parametri'!$B$6-H58)/'P-Parametri'!$D$13,IF(H58<='P-Parametri'!$B$7,'P-Parametri'!$B$14*('P-Parametri'!$B$7-H58)/'P-Parametri'!$C$14,0)))+IF(AND(H58>'P-Parametri'!$C$15,H58<'P-Parametri'!$D$15),'P-Parametri'!$B$15,0) | I61: =IF(I58<='P-Parametri'!$C$12,'P-Parametri'!$B$12,IF(I58<='P-Parametri'!$B$6,'P-Parametri'!$B$13+'P-Parametri'!$C$13*('P-Parametri'!$B$6-I58)/'P-Parametri'!$D$13,IF(I58<='P-Parametri'!$B$7,'P-Parametri'!$B$14*('P-Parametri'!$B$7-I58)/'P-Parametri'!$C$14,0)))+IF(AND(I58>'P-Parametri'!$C$15,I58<'P-Parametri'!$D$15),'P-Parametri'!$B$15,0) | ... O61: =IF(O58<='P-Parametri'!$C$12,'P-Parametri'!$B$12,IF(O58<='P-Parametri'!$B$6,'P-Parametri'!$B$13+'P-Parametri'!$C$13*('P-Parametri'!$B$6-O58)/'P-Parametri'!$D$13,IF(O58<='P-Parametri'!$B$7,'P-Parametri'!$B$14*('P-Parametri'!$B$7-O58)/'P-Parametri'!$C$14,0)))+IF(AND(O58>'P-Parametri'!$C$15,O58<'P-Parametri'!$D$15),'P-Parametri'!$B$15,0)
A62: Addizionali — Chiara | B62: =IF(MAX(0,B60-B61)<=0,0,'P-Parametri'!$B$11*B58) | C62: =IF(MAX(0,C60-C61)<=0,0,'P-Parametri'!$B$11*C58) | D62: =IF(MAX(0,D60-D61)<=0,0,'P-Parametri'!$B$11*D58) | E62: =IF(MAX(0,E60-E61)<=0,0,'P-Parametri'!$B$11*E58) | F62: =IF(MAX(0,F60-F61)<=0,0,'P-Parametri'!$B$11*F58) | G62: =IF(MAX(0,G60-G61)<=0,0,'P-Parametri'!$B$11*G58) | H62: =IF(MAX(0,H60-H61)<=0,0,'P-Parametri'!$B$11*H58) | I62: =IF(MAX(0,I60-I61)<=0,0,'P-Parametri'!$B$11*I58) | ... O62: =IF(MAX(0,O60-O61)<=0,0,'P-Parametri'!$B$11*O58)
A63: PENSIONE NETTA — Chiara | B63: =B58-MAX(0,B60-B61)-B62 | C63: =C58-MAX(0,C60-C61)-C62 | D63: =D58-MAX(0,D60-D61)-D62 | E63: =E58-MAX(0,E60-E61)-E62 | F63: =F58-MAX(0,F60-F61)-F62 | G63: =G58-MAX(0,G60-G61)-G62 | H63: =H58-MAX(0,H60-H61)-H62 | I63: =I58-MAX(0,I60-I61)-I62 | ... O63: =O58-MAX(0,O60-O61)-O62
A64: IRPEF lorda — marito | B64: =IF(B59<='P-Parametri'!$B$6,'P-Parametri'!$C$6*B59,IF(B59<='P-Parametri'!$B$7,'P-Parametri'!$B$9+'P-Parametri'!$C$7*(B59-'P-Parametri'!$B$6),'P-Parametri'!$B$10+'P-Parametri'!$C$8*(B59-'P-Parametri'!$B$7))) | C64: =IF(C59<='P-Parametri'!$B$6,'P-Parametri'!$C$6*C59,IF(C59<='P-Parametri'!$B$7,'P-Parametri'!$B$9+'P-Parametri'!$C$7*(C59-'P-Parametri'!$B$6),'P-Parametri'!$B$10+'P-Parametri'!$C$8*(C59-'P-Parametri'!$B$7))) | D64: =IF(D59<='P-Parametri'!$B$6,'P-Parametri'!$C$6*D59,IF(D59<='P-Parametri'!$B$7,'P-Parametri'!$B$9+'P-Parametri'!$C$7*(D59-'P-Parametri'!$B$6),'P-Parametri'!$B$10+'P-Parametri'!$C$8*(D59-'P-Parametri'!$B$7))) | E64: =IF(E59<='P-Parametri'!$B$6,'P-Parametri'!$C$6*E59,IF(E59<='P-Parametri'!$B$7,'P-Parametri'!$B$9+'P-Parametri'!$C$7*(E59-'P-Parametri'!$B$6),'P-Parametri'!$B$10+'P-Parametri'!$C$8*(E59-'P-Parametri'!$B$7))) | F64: =IF(F59<='P-Parametri'!$B$6,'P-Parametri'!$C$6*F59,IF(F59<='P-Parametri'!$B$7,'P-Parametri'!$B$9+'P-Parametri'!$C$7*(F59-'P-Parametri'!$B$6),'P-Parametri'!$B$10+'P-Parametri'!$C$8*(F59-'P-Parametri'!$B$7))) | G64: =IF(G59<='P-Parametri'!$B$6,'P-Parametri'!$C$6*G59,IF(G59<='P-Parametri'!$B$7,'P-Parametri'!$B$9+'P-Parametri'!$C$7*(G59-'P-Parametri'!$B$6),'P-Parametri'!$B$10+'P-Parametri'!$C$8*(G59-'P-Parametri'!$B$7))) | H64: =IF(H59<='P-Parametri'!$B$6,'P-Parametri'!$C$6*H59,IF(H59<='P-Parametri'!$B$7,'P-Parametri'!$B$9+'P-Parametri'!$C$7*(H59-'P-Parametri'!$B$6),'P-Parametri'!$B$10+'P-Parametri'!$C$8*(H59-'P-Parametri'!$B$7))) | I64: =IF(I59<='P-Parametri'!$B$6,'P-Parametri'!$C$6*I59,IF(I59<='P-Parametri'!$B$7,'P-Parametri'!$B$9+'P-Parametri'!$C$7*(I59-'P-Parametri'!$B$6),'P-Parametri'!$B$10+'P-Parametri'!$C$8*(I59-'P-Parametri'!$B$7))) | ... O64: =IF(O59<='P-Parametri'!$B$6,'P-Parametri'!$C$6*O59,IF(O59<='P-Parametri'!$B$7,'P-Parametri'!$B$9+'P-Parametri'!$C$7*(O59-'P-Parametri'!$B$6),'P-Parametri'!$B$10+'P-Parametri'!$C$8*(O59-'P-Parametri'!$B$7)))
A65: Detrazione da pensione — marito | B65: =IF(B59<='P-Parametri'!$C$12,'P-Parametri'!$B$12,IF(B59<='P-Parametri'!$B$6,'P-Parametri'!$B$13+'P-Parametri'!$C$13*('P-Parametri'!$B$6-B59)/'P-Parametri'!$D$13,IF(B59<='P-Parametri'!$B$7,'P-Parametri'!$B$14*('P-Parametri'!$B$7-B59)/'P-Parametri'!$C$14,0)))+IF(AND(B59>'P-Parametri'!$C$15,B59<'P-Parametri'!$D$15),'P-Parametri'!$B$15,0) | C65: =IF(C59<='P-Parametri'!$C$12,'P-Parametri'!$B$12,IF(C59<='P-Parametri'!$B$6,'P-Parametri'!$B$13+'P-Parametri'!$C$13*('P-Parametri'!$B$6-C59)/'P-Parametri'!$D$13,IF(C59<='P-Parametri'!$B$7,'P-Parametri'!$B$14*('P-Parametri'!$B$7-C59)/'P-Parametri'!$C$14,0)))+IF(AND(C59>'P-Parametri'!$C$15,C59<'P-Parametri'!$D$15),'P-Parametri'!$B$15,0) | D65: =IF(D59<='P-Parametri'!$C$12,'P-Parametri'!$B$12,IF(D59<='P-Parametri'!$B$6,'P-Parametri'!$B$13+'P-Parametri'!$C$13*('P-Parametri'!$B$6-D59)/'P-Parametri'!$D$13,IF(D59<='P-Parametri'!$B$7,'P-Parametri'!$B$14*('P-Parametri'!$B$7-D59)/'P-Parametri'!$C$14,0)))+IF(AND(D59>'P-Parametri'!$C$15,D59<'P-Parametri'!$D$15),'P-Parametri'!$B$15,0) | E65: =IF(E59<='P-Parametri'!$C$12,'P-Parametri'!$B$12,IF(E59<='P-Parametri'!$B$6,'P-Parametri'!$B$13+'P-Parametri'!$C$13*('P-Parametri'!$B$6-E59)/'P-Parametri'!$D$13,IF(E59<='P-Parametri'!$B$7,'P-Parametri'!$B$14*('P-Parametri'!$B$7-E59)/'P-Parametri'!$C$14,0)))+IF(AND(E59>'P-Parametri'!$C$15,E59<'P-Parametri'!$D$15),'P-Parametri'!$B$15,0) | F65: =IF(F59<='P-Parametri'!$C$12,'P-Parametri'!$B$12,IF(F59<='P-Parametri'!$B$6,'P-Parametri'!$B$13+'P-Parametri'!$C$13*('P-Parametri'!$B$6-F59)/'P-Parametri'!$D$13,IF(F59<='P-Parametri'!$B$7,'P-Parametri'!$B$14*('P-Parametri'!$B$7-F59)/'P-Parametri'!$C$14,0)))+IF(AND(F59>'P-Parametri'!$C$15,F59<'P-Parametri'!$D$15),'P-Parametri'!$B$15,0) | G65: =IF(G59<='P-Parametri'!$C$12,'P-Parametri'!$B$12,IF(G59<='P-Parametri'!$B$6,'P-Parametri'!$B$13+'P-Parametri'!$C$13*('P-Parametri'!$B$6-G59)/'P-Parametri'!$D$13,IF(G59<='P-Parametri'!$B$7,'P-Parametri'!$B$14*('P-Parametri'!$B$7-G59)/'P-Parametri'!$C$14,0)))+IF(AND(G59>'P-Parametri'!$C$15,G59<'P-Parametri'!$D$15),'P-Parametri'!$B$15,0) | H65: =IF(H59<='P-Parametri'!$C$12,'P-Parametri'!$B$12,IF(H59<='P-Parametri'!$B$6,'P-Parametri'!$B$13+'P-Parametri'!$C$13*('P-Parametri'!$B$6-H59)/'P-Parametri'!$D$13,IF(H59<='P-Parametri'!$B$7,'P-Parametri'!$B$14*('P-Parametri'!$B$7-H59)/'P-Parametri'!$C$14,0)))+IF(AND(H59>'P-Parametri'!$C$15,H59<'P-Parametri'!$D$15),'P-Parametri'!$B$15,0) | I65: =IF(I59<='P-Parametri'!$C$12,'P-Parametri'!$B$12,IF(I59<='P-Parametri'!$B$6,'P-Parametri'!$B$13+'P-Parametri'!$C$13*('P-Parametri'!$B$6-I59)/'P-Parametri'!$D$13,IF(I59<='P-Parametri'!$B$7,'P-Parametri'!$B$14*('P-Parametri'!$B$7-I59)/'P-Parametri'!$C$14,0)))+IF(AND(I59>'P-Parametri'!$C$15,I59<'P-Parametri'!$D$15),'P-Parametri'!$B$15,0) | ... O65: =IF(O59<='P-Parametri'!$C$12,'P-Parametri'!$B$12,IF(O59<='P-Parametri'!$B$6,'P-Parametri'!$B$13+'P-Parametri'!$C$13*('P-Parametri'!$B$6-O59)/'P-Parametri'!$D$13,IF(O59<='P-Parametri'!$B$7,'P-Parametri'!$B$14*('P-Parametri'!$B$7-O59)/'P-Parametri'!$C$14,0)))+IF(AND(O59>'P-Parametri'!$C$15,O59<'P-Parametri'!$D$15),'P-Parametri'!$B$15,0)
A66: Addizionali — marito | B66: =IF(MAX(0,B64-B65)<=0,0,'P-Parametri'!$B$11*B59) | C66: =IF(MAX(0,C64-C65)<=0,0,'P-Parametri'!$B$11*C59) | D66: =IF(MAX(0,D64-D65)<=0,0,'P-Parametri'!$B$11*D59) | E66: =IF(MAX(0,E64-E65)<=0,0,'P-Parametri'!$B$11*E59) | F66: =IF(MAX(0,F64-F65)<=0,0,'P-Parametri'!$B$11*F59) | G66: =IF(MAX(0,G64-G65)<=0,0,'P-Parametri'!$B$11*G59) | H66: =IF(MAX(0,H64-H65)<=0,0,'P-Parametri'!$B$11*H59) | I66: =IF(MAX(0,I64-I65)<=0,0,'P-Parametri'!$B$11*I59) | ... O66: =IF(MAX(0,O64-O65)<=0,0,'P-Parametri'!$B$11*O59)
A67: PENSIONE NETTA — marito | B67: =B59-MAX(0,B64-B65)-B66 | C67: =C59-MAX(0,C64-C65)-C66 | D67: =D59-MAX(0,D64-D65)-D66 | E67: =E59-MAX(0,E64-E65)-E66 | F67: =F59-MAX(0,F64-F65)-F66 | G67: =G59-MAX(0,G64-G65)-G66 | H67: =H59-MAX(0,H64-H65)-H66 | I67: =I59-MAX(0,I64-I65)-I66 | ... O67: =O59-MAX(0,O64-O65)-O66
A68: Pensioni nette di coppia | B68: =B63+B67 | C68: =C63+C67 | D68: =D63+D67 | E68: =E63+E67 | F68: =F63+F67 | G68: =G63+G67 | H68: =H63+H67 | I68: =I63+I67 | ... O68: =O63+O67
A69: Capitale alla valutazione | B69: =IF(B45>0,B45,'2-Composizione'!$B$36*(1+B46)^B49+B30*IF(B46=0,B49,(1+B46)*((1+B46)^B49-1)/B46)) | C69: =IF(C45>0,C45,'2-Composizione'!$B$36*(1+C46)^C49+C30*IF(C46=0,C49,(1+C46)*((1+C46)^C49-1)/C46)) | D69: =IF(D45>0,D45,'2-Composizione'!$B$36*(1+D46)^D49+D30*IF(D46=0,D49,(1+D46)*((1+D46)^D49-1)/D46)) | E69: =IF(E45>0,E45,'2-Composizione'!$B$36*(1+E46)^E49+E30*IF(E46=0,E49,(1+E46)*((1+E46)^E49-1)/E46)) | F69: =IF(F45>0,F45,'2-Composizione'!$B$36*(1+F46)^F49+F30*IF(F46=0,F49,(1+F46)*((1+F46)^F49-1)/F46)) | G69: =IF(G45>0,G45,'2-Composizione'!$B$36*(1+G46)^G49+G30*IF(G46=0,G49,(1+G46)*((1+G46)^G49-1)/G46)) | H69: =IF(H45>0,H45,'2-Composizione'!$B$36*(1+H46)^H49+H30*IF(H46=0,H49,(1+H46)*((1+H46)^H49-1)/H46)) | I69: =IF(I45>0,I45,'2-Composizione'!$B$36*(1+I46)^I49+I30*IF(I46=0,I49,(1+I46)*((1+I46)^I49-1)/I46)) | ... O69: =IF(O45>0,O45,'2-Composizione'!$B$36*(1+O46)^O49+O30*IF(O46=0,O49,(1+O46)*((1+O46)^O49-1)/O46))
A70: Base di costo alla valutazione | B70: ='2-Composizione'!$B$37+B49*B30 | C70: ='2-Composizione'!$B$37+C49*C30 | D70: ='2-Composizione'!$B$37+D49*D30 | E70: ='2-Composizione'!$B$37+E49*E30 | F70: ='2-Composizione'!$B$37+F49*F30 | G70: ='2-Composizione'!$B$37+G49*G30 | H70: ='2-Composizione'!$B$37+H49*H30 | I70: ='2-Composizione'!$B$37+I49*I30 | ... O70: ='2-Composizione'!$B$37+O49*O30
A71: Plusvalenza latente (floor a zero) | B71: =MAX(0,(B69-B70)/B69) | C71: =MAX(0,(C69-C70)/C69) | D71: =MAX(0,(D69-D70)/D69) | E71: =MAX(0,(E69-E70)/E69) | F71: =MAX(0,(F69-F70)/F69) | G71: =MAX(0,(G69-G70)/G69) | H71: =MAX(0,(H69-H70)/H69) | I71: =MAX(0,(I69-I70)/I69) | ... O71: =MAX(0,(O69-O70)/O69)
A72: Fattore di lordizzazione G | B72: =1/(1-'P-Parametri'!$B$31*B71) | C72: =1/(1-'P-Parametri'!$B$31*C71) | D72: =1/(1-'P-Parametri'!$B$31*D71) | E72: =1/(1-'P-Parametri'!$B$31*E71) | F72: =1/(1-'P-Parametri'!$B$31*F71) | G72: =1/(1-'P-Parametri'!$B$31*G71) | H72: =1/(1-'P-Parametri'!$B$31*H71) | I72: =1/(1-'P-Parametri'!$B$31*I71) | ... O72: =1/(1-'P-Parametri'!$B$31*O71)
A73: Valore attuale netto del fabbisogno | B73: =SUM(B82:B115) | C73: =SUM(C82:C115) | D73: =SUM(D82:D115) | E73: =SUM(E82:E115) | F73: =SUM(F82:F115) | G73: =SUM(G82:G115) | H73: =SUM(H82:H115) | I73: =SUM(I82:I115) | ... O73: =SUM(O82:O115)
A74: FABBISOGNO LORDO (in capitale) | B74: =B73*B72 | C74: =C73*C72 | D74: =D73*D72 | E74: =E73*E72 | F74: =F73*F72 | G74: =G73*G72 | H74: =H73*H72 | I74: =I73*I72 | ... O74: =O73*O72
A75: TFR netto alla valutazione | B75: =CHOOSE(B31+1,'6-TFR'!$B$24,'6-TFR'!$C$24,'6-TFR'!$D$24) | C75: =CHOOSE(C31+1,'6-TFR'!$B$24,'6-TFR'!$C$24,'6-TFR'!$D$24) | D75: =CHOOSE(D31+1,'6-TFR'!$B$24,'6-TFR'!$C$24,'6-TFR'!$D$24) | E75: =CHOOSE(E31+1,'6-TFR'!$B$24,'6-TFR'!$C$24,'6-TFR'!$D$24) | F75: =CHOOSE(F31+1,'6-TFR'!$B$24,'6-TFR'!$C$24,'6-TFR'!$D$24) | G75: =CHOOSE(G31+1,'6-TFR'!$B$24,'6-TFR'!$C$24,'6-TFR'!$D$24) | H75: =CHOOSE(H31+1,'6-TFR'!$B$24,'6-TFR'!$C$24,'6-TFR'!$D$24) | I75: =CHOOSE(I31+1,'6-TFR'!$B$24,'6-TFR'!$C$24,'6-TFR'!$D$24) | ... O75: =CHOOSE(O31+1,'6-TFR'!$B$24,'6-TFR'!$C$24,'6-TFR'!$D$24)
A76: FABBISOGNO FINANZIARIO (floor a zero) | B76: =MAX(0,(B73-B75)*B72) | C76: =MAX(0,(C73-C75)*C72) | D76: =MAX(0,(D73-D75)*D72) | E76: =MAX(0,(E73-E75)*E72) | F76: =MAX(0,(F73-F75)*F72) | G76: =MAX(0,(G73-G75)*G72) | H76: =MAX(0,(H73-H75)*H72) | I76: =MAX(0,(I73-I75)*I72) | ... O76: =MAX(0,(O73-O75)*O72)
A77: Posizione netta = capitale meno fabbisogno | B77: =B69-B76 | C77: =C69-C76 | D77: =D69-D76 | E77: =E69-E76 | F77: =F69-F76 | G77: =G69-G76 | H77: =H69-H76 | I77: =I69-I76 | ... O77: =O69-O76
A78: Posizione scontata a fine ritiro | B78: =B77/(1+'1-Input'!$B$46)^B31 | C78: =C77/(1+'1-Input'!$B$46)^C31 | D78: =D77/(1+'1-Input'!$B$46)^D31 | E78: =E77/(1+'1-Input'!$B$46)^E31 | F78: =F77/(1+'1-Input'!$B$46)^F31 | G78: =G77/(1+'1-Input'!$B$46)^G31 | H78: =H77/(1+'1-Input'!$B$46)^H31 | I78: =I77/(1+'1-Input'!$B$46)^I31 | ... O78: =O77/(1+'1-Input'!$B$46)^O31
A79: DELTA contro la base
A81: Anno del flusso — valore attuale del fabbisogno
A82: ='1-Input'!$B$19+1 | B82: =IF(OR($A82<=B48,$A82>B34),0,(B29-IF($A82<B50,0,IF($A82=B50,B63*B54,B63))-IF($A82<B51,0,IF($A82=B51,B67*B55,B67)))/(1+B47)^($A82-B48-1)) | C82: =IF(OR($A82<=C48,$A82>C34),0,(C29-IF($A82<C50,0,IF($A82=C50,C63*C54,C63))-IF($A82<C51,0,IF($A82=C51,C67*C55,C67)))/(1+C47)^($A82-C48-1)) | D82: =IF(OR($A82<=D48,$A82>D34),0,(D29-IF($A82<D50,0,IF($A82=D50,D63*D54,D63))-IF($A82<D51,0,IF($A82=D51,D67*D55,D67)))/(1+D47)^($A82-D48-1)) | E82: =IF(OR($A82<=E48,$A82>E34),0,(E29-IF($A82<E50,0,IF($A82=E50,E63*E54,E63))-IF($A82<E51,0,IF($A82=E51,E67*E55,E67)))/(1+E47)^($A82-E48-1)) | F82: =IF(OR($A82<=F48,$A82>F34),0,(F29-IF($A82<F50,0,IF($A82=F50,F63*F54,F63))-IF($A82<F51,0,IF($A82=F51,F67*F55,F67)))/(1+F47)^($A82-F48-1)) | G82: =IF(OR($A82<=G48,$A82>G34),0,(G29-IF($A82<G50,0,IF($A82=G50,G63*G54,G63))-IF($A82<G51,0,IF($A82=G51,G67*G55,G67)))/(1+G47)^($A82-G48-1)) | H82: =IF(OR($A82<=H48,$A82>H34),0,(H29-IF($A82<H50,0,IF($A82=H50,H63*H54,H63))-IF($A82<H51,0,IF($A82=H51,H67*H55,H67)))/(1+H47)^($A82-H48-1)) | I82: =IF(OR($A82<=I48,$A82>I34),0,(I29-IF($A82<I50,0,IF($A82=I50,I63*I54,I63))-IF($A82<I51,0,IF($A82=I51,I67*I55,I67)))/(1+I47)^($A82-I48-1)) | ... O82: =IF(OR($A82<=O48,$A82>O34),0,(O29-IF($A82<O50,0,IF($A82=O50,O63*O54,O63))-IF($A82<O51,0,IF($A82=O51,O67*O55,O67)))/(1+O47)^($A82-O48-1))
A83: =A82+1 | B83: =IF(OR($A83<=B48,$A83>B34),0,(B29-IF($A83<B50,0,IF($A83=B50,B63*B54,B63))-IF($A83<B51,0,IF($A83=B51,B67*B55,B67)))/(1+B47)^($A83-B48-1)) | C83: =IF(OR($A83<=C48,$A83>C34),0,(C29-IF($A83<C50,0,IF($A83=C50,C63*C54,C63))-IF($A83<C51,0,IF($A83=C51,C67*C55,C67)))/(1+C47)^($A83-C48-1)) | D83: =IF(OR($A83<=D48,$A83>D34),0,(D29-IF($A83<D50,0,IF($A83=D50,D63*D54,D63))-IF($A83<D51,0,IF($A83=D51,D67*D55,D67)))/(1+D47)^($A83-D48-1)) | E83: =IF(OR($A83<=E48,$A83>E34),0,(E29-IF($A83<E50,0,IF($A83=E50,E63*E54,E63))-IF($A83<E51,0,IF($A83=E51,E67*E55,E67)))/(1+E47)^($A83-E48-1)) | F83: =IF(OR($A83<=F48,$A83>F34),0,(F29-IF($A83<F50,0,IF($A83=F50,F63*F54,F63))-IF($A83<F51,0,IF($A83=F51,F67*F55,F67)))/(1+F47)^($A83-F48-1)) | G83: =IF(OR($A83<=G48,$A83>G34),0,(G29-IF($A83<G50,0,IF($A83=G50,G63*G54,G63))-IF($A83<G51,0,IF($A83=G51,G67*G55,G67)))/(1+G47)^($A83-G48-1)) | H83: =IF(OR($A83<=H48,$A83>H34),0,(H29-IF($A83<H50,0,IF($A83=H50,H63*H54,H63))-IF($A83<H51,0,IF($A83=H51,H67*H55,H67)))/(1+H47)^($A83-H48-1)) | I83: =IF(OR($A83<=I48,$A83>I34),0,(I29-IF($A83<I50,0,IF($A83=I50,I63*I54,I63))-IF($A83<I51,0,IF($A83=I51,I67*I55,I67)))/(1+I47)^($A83-I48-1)) | ... O83: =IF(OR($A83<=O48,$A83>O34),0,(O29-IF($A83<O50,0,IF($A83=O50,O63*O54,O63))-IF($A83<O51,0,IF($A83=O51,O67*O55,O67)))/(1+O47)^($A83-O48-1))
A84: =A83+1 | B84: =IF(OR($A84<=B48,$A84>B34),0,(B29-IF($A84<B50,0,IF($A84=B50,B63*B54,B63))-IF($A84<B51,0,IF($A84=B51,B67*B55,B67)))/(1+B47)^($A84-B48-1)) | C84: =IF(OR($A84<=C48,$A84>C34),0,(C29-IF($A84<C50,0,IF($A84=C50,C63*C54,C63))-IF($A84<C51,0,IF($A84=C51,C67*C55,C67)))/(1+C47)^($A84-C48-1)) | D84: =IF(OR($A84<=D48,$A84>D34),0,(D29-IF($A84<D50,0,IF($A84=D50,D63*D54,D63))-IF($A84<D51,0,IF($A84=D51,D67*D55,D67)))/(1+D47)^($A84-D48-1)) | E84: =IF(OR($A84<=E48,$A84>E34),0,(E29-IF($A84<E50,0,IF($A84=E50,E63*E54,E63))-IF($A84<E51,0,IF($A84=E51,E67*E55,E67)))/(1+E47)^($A84-E48-1)) | F84: =IF(OR($A84<=F48,$A84>F34),0,(F29-IF($A84<F50,0,IF($A84=F50,F63*F54,F63))-IF($A84<F51,0,IF($A84=F51,F67*F55,F67)))/(1+F47)^($A84-F48-1)) | G84: =IF(OR($A84<=G48,$A84>G34),0,(G29-IF($A84<G50,0,IF($A84=G50,G63*G54,G63))-IF($A84<G51,0,IF($A84=G51,G67*G55,G67)))/(1+G47)^($A84-G48-1)) | H84: =IF(OR($A84<=H48,$A84>H34),0,(H29-IF($A84<H50,0,IF($A84=H50,H63*H54,H63))-IF($A84<H51,0,IF($A84=H51,H67*H55,H67)))/(1+H47)^($A84-H48-1)) | I84: =IF(OR($A84<=I48,$A84>I34),0,(I29-IF($A84<I50,0,IF($A84=I50,I63*I54,I63))-IF($A84<I51,0,IF($A84=I51,I67*I55,I67)))/(1+I47)^($A84-I48-1)) | ... O84: =IF(OR($A84<=O48,$A84>O34),0,(O29-IF($A84<O50,0,IF($A84=O50,O63*O54,O63))-IF($A84<O51,0,IF($A84=O51,O67*O55,O67)))/(1+O47)^($A84-O48-1))
A85: =A84+1 | B85: =IF(OR($A85<=B48,$A85>B34),0,(B29-IF($A85<B50,0,IF($A85=B50,B63*B54,B63))-IF($A85<B51,0,IF($A85=B51,B67*B55,B67)))/(1+B47)^($A85-B48-1)) | C85: =IF(OR($A85<=C48,$A85>C34),0,(C29-IF($A85<C50,0,IF($A85=C50,C63*C54,C63))-IF($A85<C51,0,IF($A85=C51,C67*C55,C67)))/(1+C47)^($A85-C48-1)) | D85: =IF(OR($A85<=D48,$A85>D34),0,(D29-IF($A85<D50,0,IF($A85=D50,D63*D54,D63))-IF($A85<D51,0,IF($A85=D51,D67*D55,D67)))/(1+D47)^($A85-D48-1)) | E85: =IF(OR($A85<=E48,$A85>E34),0,(E29-IF($A85<E50,0,IF($A85=E50,E63*E54,E63))-IF($A85<E51,0,IF($A85=E51,E67*E55,E67)))/(1+E47)^($A85-E48-1)) | F85: =IF(OR($A85<=F48,$A85>F34),0,(F29-IF($A85<F50,0,IF($A85=F50,F63*F54,F63))-IF($A85<F51,0,IF($A85=F51,F67*F55,F67)))/(1+F47)^($A85-F48-1)) | G85: =IF(OR($A85<=G48,$A85>G34),0,(G29-IF($A85<G50,0,IF($A85=G50,G63*G54,G63))-IF($A85<G51,0,IF($A85=G51,G67*G55,G67)))/(1+G47)^($A85-G48-1)) | H85: =IF(OR($A85<=H48,$A85>H34),0,(H29-IF($A85<H50,0,IF($A85=H50,H63*H54,H63))-IF($A85<H51,0,IF($A85=H51,H67*H55,H67)))/(1+H47)^($A85-H48-1)) | I85: =IF(OR($A85<=I48,$A85>I34),0,(I29-IF($A85<I50,0,IF($A85=I50,I63*I54,I63))-IF($A85<I51,0,IF($A85=I51,I67*I55,I67)))/(1+I47)^($A85-I48-1)) | ... O85: =IF(OR($A85<=O48,$A85>O34),0,(O29-IF($A85<O50,0,IF($A85=O50,O63*O54,O63))-IF($A85<O51,0,IF($A85=O51,O67*O55,O67)))/(1+O47)^($A85-O48-1))
A86: =A85+1 | B86: =IF(OR($A86<=B48,$A86>B34),0,(B29-IF($A86<B50,0,IF($A86=B50,B63*B54,B63))-IF($A86<B51,0,IF($A86=B51,B67*B55,B67)))/(1+B47)^($A86-B48-1)) | C86: =IF(OR($A86<=C48,$A86>C34),0,(C29-IF($A86<C50,0,IF($A86=C50,C63*C54,C63))-IF($A86<C51,0,IF($A86=C51,C67*C55,C67)))/(1+C47)^($A86-C48-1)) | D86: =IF(OR($A86<=D48,$A86>D34),0,(D29-IF($A86<D50,0,IF($A86=D50,D63*D54,D63))-IF($A86<D51,0,IF($A86=D51,D67*D55,D67)))/(1+D47)^($A86-D48-1)) | E86: =IF(OR($A86<=E48,$A86>E34),0,(E29-IF($A86<E50,0,IF($A86=E50,E63*E54,E63))-IF($A86<E51,0,IF($A86=E51,E67*E55,E67)))/(1+E47)^($A86-E48-1)) | F86: =IF(OR($A86<=F48,$A86>F34),0,(F29-IF($A86<F50,0,IF($A86=F50,F63*F54,F63))-IF($A86<F51,0,IF($A86=F51,F67*F55,F67)))/(1+F47)^($A86-F48-1)) | G86: =IF(OR($A86<=G48,$A86>G34),0,(G29-IF($A86<G50,0,IF($A86=G50,G63*G54,G63))-IF($A86<G51,0,IF($A86=G51,G67*G55,G67)))/(1+G47)^($A86-G48-1)) | H86: =IF(OR($A86<=H48,$A86>H34),0,(H29-IF($A86<H50,0,IF($A86=H50,H63*H54,H63))-IF($A86<H51,0,IF($A86=H51,H67*H55,H67)))/(1+H47)^($A86-H48-1)) | I86: =IF(OR($A86<=I48,$A86>I34),0,(I29-IF($A86<I50,0,IF($A86=I50,I63*I54,I63))-IF($A86<I51,0,IF($A86=I51,I67*I55,I67)))/(1+I47)^($A86-I48-1)) | ... O86: =IF(OR($A86<=O48,$A86>O34),0,(O29-IF($A86<O50,0,IF($A86=O50,O63*O54,O63))-IF($A86<O51,0,IF($A86=O51,O67*O55,O67)))/(1+O47)^($A86-O48-1))
A87: =A86+1 | B87: =IF(OR($A87<=B48,$A87>B34),0,(B29-IF($A87<B50,0,IF($A87=B50,B63*B54,B63))-IF($A87<B51,0,IF($A87=B51,B67*B55,B67)))/(1+B47)^($A87-B48-1)) | C87: =IF(OR($A87<=C48,$A87>C34),0,(C29-IF($A87<C50,0,IF($A87=C50,C63*C54,C63))-IF($A87<C51,0,IF($A87=C51,C67*C55,C67)))/(1+C47)^($A87-C48-1)) | D87: =IF(OR($A87<=D48,$A87>D34),0,(D29-IF($A87<D50,0,IF($A87=D50,D63*D54,D63))-IF($A87<D51,0,IF($A87=D51,D67*D55,D67)))/(1+D47)^($A87-D48-1)) | E87: =IF(OR($A87<=E48,$A87>E34),0,(E29-IF($A87<E50,0,IF($A87=E50,E63*E54,E63))-IF($A87<E51,0,IF($A87=E51,E67*E55,E67)))/(1+E47)^($A87-E48-1)) | F87: =IF(OR($A87<=F48,$A87>F34),0,(F29-IF($A87<F50,0,IF($A87=F50,F63*F54,F63))-IF($A87<F51,0,IF($A87=F51,F67*F55,F67)))/(1+F47)^($A87-F48-1)) | G87: =IF(OR($A87<=G48,$A87>G34),0,(G29-IF($A87<G50,0,IF($A87=G50,G63*G54,G63))-IF($A87<G51,0,IF($A87=G51,G67*G55,G67)))/(1+G47)^($A87-G48-1)) | H87: =IF(OR($A87<=H48,$A87>H34),0,(H29-IF($A87<H50,0,IF($A87=H50,H63*H54,H63))-IF($A87<H51,0,IF($A87=H51,H67*H55,H67)))/(1+H47)^($A87-H48-1)) | I87: =IF(OR($A87<=I48,$A87>I34),0,(I29-IF($A87<I50,0,IF($A87=I50,I63*I54,I63))-IF($A87<I51,0,IF($A87=I51,I67*I55,I67)))/(1+I47)^($A87-I48-1)) | ... O87: =IF(OR($A87<=O48,$A87>O34),0,(O29-IF($A87<O50,0,IF($A87=O50,O63*O54,O63))-IF($A87<O51,0,IF($A87=O51,O67*O55,O67)))/(1+O47)^($A87-O48-1))
A88: =A87+1 | B88: =IF(OR($A88<=B48,$A88>B34),0,(B29-IF($A88<B50,0,IF($A88=B50,B63*B54,B63))-IF($A88<B51,0,IF($A88=B51,B67*B55,B67)))/(1+B47)^($A88-B48-1)) | C88: =IF(OR($A88<=C48,$A88>C34),0,(C29-IF($A88<C50,0,IF($A88=C50,C63*C54,C63))-IF($A88<C51,0,IF($A88=C51,C67*C55,C67)))/(1+C47)^($A88-C48-1)) | D88: =IF(OR($A88<=D48,$A88>D34),0,(D29-IF($A88<D50,0,IF($A88=D50,D63*D54,D63))-IF($A88<D51,0,IF($A88=D51,D67*D55,D67)))/(1+D47)^($A88-D48-1)) | E88: =IF(OR($A88<=E48,$A88>E34),0,(E29-IF($A88<E50,0,IF($A88=E50,E63*E54,E63))-IF($A88<E51,0,IF($A88=E51,E67*E55,E67)))/(1+E47)^($A88-E48-1)) | F88: =IF(OR($A88<=F48,$A88>F34),0,(F29-IF($A88<F50,0,IF($A88=F50,F63*F54,F63))-IF($A88<F51,0,IF($A88=F51,F67*F55,F67)))/(1+F47)^($A88-F48-1)) | G88: =IF(OR($A88<=G48,$A88>G34),0,(G29-IF($A88<G50,0,IF($A88=G50,G63*G54,G63))-IF($A88<G51,0,IF($A88=G51,G67*G55,G67)))/(1+G47)^($A88-G48-1)) | H88: =IF(OR($A88<=H48,$A88>H34),0,(H29-IF($A88<H50,0,IF($A88=H50,H63*H54,H63))-IF($A88<H51,0,IF($A88=H51,H67*H55,H67)))/(1+H47)^($A88-H48-1)) | I88: =IF(OR($A88<=I48,$A88>I34),0,(I29-IF($A88<I50,0,IF($A88=I50,I63*I54,I63))-IF($A88<I51,0,IF($A88=I51,I67*I55,I67)))/(1+I47)^($A88-I48-1)) | ... O88: =IF(OR($A88<=O48,$A88>O34),0,(O29-IF($A88<O50,0,IF($A88=O50,O63*O54,O63))-IF($A88<O51,0,IF($A88=O51,O67*O55,O67)))/(1+O47)^($A88-O48-1))
A89: =A88+1 | B89: =IF(OR($A89<=B48,$A89>B34),0,(B29-IF($A89<B50,0,IF($A89=B50,B63*B54,B63))-IF($A89<B51,0,IF($A89=B51,B67*B55,B67)))/(1+B47)^($A89-B48-1)) | C89: =IF(OR($A89<=C48,$A89>C34),0,(C29-IF($A89<C50,0,IF($A89=C50,C63*C54,C63))-IF($A89<C51,0,IF($A89=C51,C67*C55,C67)))/(1+C47)^($A89-C48-1)) | D89: =IF(OR($A89<=D48,$A89>D34),0,(D29-IF($A89<D50,0,IF($A89=D50,D63*D54,D63))-IF($A89<D51,0,IF($A89=D51,D67*D55,D67)))/(1+D47)^($A89-D48-1)) | E89: =IF(OR($A89<=E48,$A89>E34),0,(E29-IF($A89<E50,0,IF($A89=E50,E63*E54,E63))-IF($A89<E51,0,IF($A89=E51,E67*E55,E67)))/(1+E47)^($A89-E48-1)) | F89: =IF(OR($A89<=F48,$A89>F34),0,(F29-IF($A89<F50,0,IF($A89=F50,F63*F54,F63))-IF($A89<F51,0,IF($A89=F51,F67*F55,F67)))/(1+F47)^($A89-F48-1)) | G89: =IF(OR($A89<=G48,$A89>G34),0,(G29-IF($A89<G50,0,IF($A89=G50,G63*G54,G63))-IF($A89<G51,0,IF($A89=G51,G67*G55,G67)))/(1+G47)^($A89-G48-1)) | H89: =IF(OR($A89<=H48,$A89>H34),0,(H29-IF($A89<H50,0,IF($A89=H50,H63*H54,H63))-IF($A89<H51,0,IF($A89=H51,H67*H55,H67)))/(1+H47)^($A89-H48-1)) | I89: =IF(OR($A89<=I48,$A89>I34),0,(I29-IF($A89<I50,0,IF($A89=I50,I63*I54,I63))-IF($A89<I51,0,IF($A89=I51,I67*I55,I67)))/(1+I47)^($A89-I48-1)) | ... O89: =IF(OR($A89<=O48,$A89>O34),0,(O29-IF($A89<O50,0,IF($A89=O50,O63*O54,O63))-IF($A89<O51,0,IF($A89=O51,O67*O55,O67)))/(1+O47)^($A89-O48-1))
A90: =A89+1 | B90: =IF(OR($A90<=B48,$A90>B34),0,(B29-IF($A90<B50,0,IF($A90=B50,B63*B54,B63))-IF($A90<B51,0,IF($A90=B51,B67*B55,B67)))/(1+B47)^($A90-B48-1)) | C90: =IF(OR($A90<=C48,$A90>C34),0,(C29-IF($A90<C50,0,IF($A90=C50,C63*C54,C63))-IF($A90<C51,0,IF($A90=C51,C67*C55,C67)))/(1+C47)^($A90-C48-1)) | D90: =IF(OR($A90<=D48,$A90>D34),0,(D29-IF($A90<D50,0,IF($A90=D50,D63*D54,D63))-IF($A90<D51,0,IF($A90=D51,D67*D55,D67)))/(1+D47)^($A90-D48-1)) | E90: =IF(OR($A90<=E48,$A90>E34),0,(E29-IF($A90<E50,0,IF($A90=E50,E63*E54,E63))-IF($A90<E51,0,IF($A90=E51,E67*E55,E67)))/(1+E47)^($A90-E48-1)) | F90: =IF(OR($A90<=F48,$A90>F34),0,(F29-IF($A90<F50,0,IF($A90=F50,F63*F54,F63))-IF($A90<F51,0,IF($A90=F51,F67*F55,F67)))/(1+F47)^($A90-F48-1)) | G90: =IF(OR($A90<=G48,$A90>G34),0,(G29-IF($A90<G50,0,IF($A90=G50,G63*G54,G63))-IF($A90<G51,0,IF($A90=G51,G67*G55,G67)))/(1+G47)^($A90-G48-1)) | H90: =IF(OR($A90<=H48,$A90>H34),0,(H29-IF($A90<H50,0,IF($A90=H50,H63*H54,H63))-IF($A90<H51,0,IF($A90=H51,H67*H55,H67)))/(1+H47)^($A90-H48-1)) | I90: =IF(OR($A90<=I48,$A90>I34),0,(I29-IF($A90<I50,0,IF($A90=I50,I63*I54,I63))-IF($A90<I51,0,IF($A90=I51,I67*I55,I67)))/(1+I47)^($A90-I48-1)) | ... O90: =IF(OR($A90<=O48,$A90>O34),0,(O29-IF($A90<O50,0,IF($A90=O50,O63*O54,O63))-IF($A90<O51,0,IF($A90=O51,O67*O55,O67)))/(1+O47)^($A90-O48-1))
A91: =A90+1 | B91: =IF(OR($A91<=B48,$A91>B34),0,(B29-IF($A91<B50,0,IF($A91=B50,B63*B54,B63))-IF($A91<B51,0,IF($A91=B51,B67*B55,B67)))/(1+B47)^($A91-B48-1)) | C91: =IF(OR($A91<=C48,$A91>C34),0,(C29-IF($A91<C50,0,IF($A91=C50,C63*C54,C63))-IF($A91<C51,0,IF($A91=C51,C67*C55,C67)))/(1+C47)^($A91-C48-1)) | D91: =IF(OR($A91<=D48,$A91>D34),0,(D29-IF($A91<D50,0,IF($A91=D50,D63*D54,D63))-IF($A91<D51,0,IF($A91=D51,D67*D55,D67)))/(1+D47)^($A91-D48-1)) | E91: =IF(OR($A91<=E48,$A91>E34),0,(E29-IF($A91<E50,0,IF($A91=E50,E63*E54,E63))-IF($A91<E51,0,IF($A91=E51,E67*E55,E67)))/(1+E47)^($A91-E48-1)) | F91: =IF(OR($A91<=F48,$A91>F34),0,(F29-IF($A91<F50,0,IF($A91=F50,F63*F54,F63))-IF($A91<F51,0,IF($A91=F51,F67*F55,F67)))/(1+F47)^($A91-F48-1)) | G91: =IF(OR($A91<=G48,$A91>G34),0,(G29-IF($A91<G50,0,IF($A91=G50,G63*G54,G63))-IF($A91<G51,0,IF($A91=G51,G67*G55,G67)))/(1+G47)^($A91-G48-1)) | H91: =IF(OR($A91<=H48,$A91>H34),0,(H29-IF($A91<H50,0,IF($A91=H50,H63*H54,H63))-IF($A91<H51,0,IF($A91=H51,H67*H55,H67)))/(1+H47)^($A91-H48-1)) | I91: =IF(OR($A91<=I48,$A91>I34),0,(I29-IF($A91<I50,0,IF($A91=I50,I63*I54,I63))-IF($A91<I51,0,IF($A91=I51,I67*I55,I67)))/(1+I47)^($A91-I48-1)) | ... O91: =IF(OR($A91<=O48,$A91>O34),0,(O29-IF($A91<O50,0,IF($A91=O50,O63*O54,O63))-IF($A91<O51,0,IF($A91=O51,O67*O55,O67)))/(1+O47)^($A91-O48-1))
A92: =A91+1 | B92: =IF(OR($A92<=B48,$A92>B34),0,(B29-IF($A92<B50,0,IF($A92=B50,B63*B54,B63))-IF($A92<B51,0,IF($A92=B51,B67*B55,B67)))/(1+B47)^($A92-B48-1)) | C92: =IF(OR($A92<=C48,$A92>C34),0,(C29-IF($A92<C50,0,IF($A92=C50,C63*C54,C63))-IF($A92<C51,0,IF($A92=C51,C67*C55,C67)))/(1+C47)^($A92-C48-1)) | D92: =IF(OR($A92<=D48,$A92>D34),0,(D29-IF($A92<D50,0,IF($A92=D50,D63*D54,D63))-IF($A92<D51,0,IF($A92=D51,D67*D55,D67)))/(1+D47)^($A92-D48-1)) | E92: =IF(OR($A92<=E48,$A92>E34),0,(E29-IF($A92<E50,0,IF($A92=E50,E63*E54,E63))-IF($A92<E51,0,IF($A92=E51,E67*E55,E67)))/(1+E47)^($A92-E48-1)) | F92: =IF(OR($A92<=F48,$A92>F34),0,(F29-IF($A92<F50,0,IF($A92=F50,F63*F54,F63))-IF($A92<F51,0,IF($A92=F51,F67*F55,F67)))/(1+F47)^($A92-F48-1)) | G92: =IF(OR($A92<=G48,$A92>G34),0,(G29-IF($A92<G50,0,IF($A92=G50,G63*G54,G63))-IF($A92<G51,0,IF($A92=G51,G67*G55,G67)))/(1+G47)^($A92-G48-1)) | H92: =IF(OR($A92<=H48,$A92>H34),0,(H29-IF($A92<H50,0,IF($A92=H50,H63*H54,H63))-IF($A92<H51,0,IF($A92=H51,H67*H55,H67)))/(1+H47)^($A92-H48-1)) | I92: =IF(OR($A92<=I48,$A92>I34),0,(I29-IF($A92<I50,0,IF($A92=I50,I63*I54,I63))-IF($A92<I51,0,IF($A92=I51,I67*I55,I67)))/(1+I47)^($A92-I48-1)) | ... O92: =IF(OR($A92<=O48,$A92>O34),0,(O29-IF($A92<O50,0,IF($A92=O50,O63*O54,O63))-IF($A92<O51,0,IF($A92=O51,O67*O55,O67)))/(1+O47)^($A92-O48-1))
A93: =A92+1 | B93: =IF(OR($A93<=B48,$A93>B34),0,(B29-IF($A93<B50,0,IF($A93=B50,B63*B54,B63))-IF($A93<B51,0,IF($A93=B51,B67*B55,B67)))/(1+B47)^($A93-B48-1)) | C93: =IF(OR($A93<=C48,$A93>C34),0,(C29-IF($A93<C50,0,IF($A93=C50,C63*C54,C63))-IF($A93<C51,0,IF($A93=C51,C67*C55,C67)))/(1+C47)^($A93-C48-1)) | D93: =IF(OR($A93<=D48,$A93>D34),0,(D29-IF($A93<D50,0,IF($A93=D50,D63*D54,D63))-IF($A93<D51,0,IF($A93=D51,D67*D55,D67)))/(1+D47)^($A93-D48-1)) | E93: =IF(OR($A93<=E48,$A93>E34),0,(E29-IF($A93<E50,0,IF($A93=E50,E63*E54,E63))-IF($A93<E51,0,IF($A93=E51,E67*E55,E67)))/(1+E47)^($A93-E48-1)) | F93: =IF(OR($A93<=F48,$A93>F34),0,(F29-IF($A93<F50,0,IF($A93=F50,F63*F54,F63))-IF($A93<F51,0,IF($A93=F51,F67*F55,F67)))/(1+F47)^($A93-F48-1)) | G93: =IF(OR($A93<=G48,$A93>G34),0,(G29-IF($A93<G50,0,IF($A93=G50,G63*G54,G63))-IF($A93<G51,0,IF($A93=G51,G67*G55,G67)))/(1+G47)^($A93-G48-1)) | H93: =IF(OR($A93<=H48,$A93>H34),0,(H29-IF($A93<H50,0,IF($A93=H50,H63*H54,H63))-IF($A93<H51,0,IF($A93=H51,H67*H55,H67)))/(1+H47)^($A93-H48-1)) | I93: =IF(OR($A93<=I48,$A93>I34),0,(I29-IF($A93<I50,0,IF($A93=I50,I63*I54,I63))-IF($A93<I51,0,IF($A93=I51,I67*I55,I67)))/(1+I47)^($A93-I48-1)) | ... O93: =IF(OR($A93<=O48,$A93>O34),0,(O29-IF($A93<O50,0,IF($A93=O50,O63*O54,O63))-IF($A93<O51,0,IF($A93=O51,O67*O55,O67)))/(1+O47)^($A93-O48-1))
A94: =A93+1 | B94: =IF(OR($A94<=B48,$A94>B34),0,(B29-IF($A94<B50,0,IF($A94=B50,B63*B54,B63))-IF($A94<B51,0,IF($A94=B51,B67*B55,B67)))/(1+B47)^($A94-B48-1)) | C94: =IF(OR($A94<=C48,$A94>C34),0,(C29-IF($A94<C50,0,IF($A94=C50,C63*C54,C63))-IF($A94<C51,0,IF($A94=C51,C67*C55,C67)))/(1+C47)^($A94-C48-1)) | D94: =IF(OR($A94<=D48,$A94>D34),0,(D29-IF($A94<D50,0,IF($A94=D50,D63*D54,D63))-IF($A94<D51,0,IF($A94=D51,D67*D55,D67)))/(1+D47)^($A94-D48-1)) | E94: =IF(OR($A94<=E48,$A94>E34),0,(E29-IF($A94<E50,0,IF($A94=E50,E63*E54,E63))-IF($A94<E51,0,IF($A94=E51,E67*E55,E67)))/(1+E47)^($A94-E48-1)) | F94: =IF(OR($A94<=F48,$A94>F34),0,(F29-IF($A94<F50,0,IF($A94=F50,F63*F54,F63))-IF($A94<F51,0,IF($A94=F51,F67*F55,F67)))/(1+F47)^($A94-F48-1)) | G94: =IF(OR($A94<=G48,$A94>G34),0,(G29-IF($A94<G50,0,IF($A94=G50,G63*G54,G63))-IF($A94<G51,0,IF($A94=G51,G67*G55,G67)))/(1+G47)^($A94-G48-1)) | H94: =IF(OR($A94<=H48,$A94>H34),0,(H29-IF($A94<H50,0,IF($A94=H50,H63*H54,H63))-IF($A94<H51,0,IF($A94=H51,H67*H55,H67)))/(1+H47)^($A94-H48-1)) | I94: =IF(OR($A94<=I48,$A94>I34),0,(I29-IF($A94<I50,0,IF($A94=I50,I63*I54,I63))-IF($A94<I51,0,IF($A94=I51,I67*I55,I67)))/(1+I47)^($A94-I48-1)) | ... O94: =IF(OR($A94<=O48,$A94>O34),0,(O29-IF($A94<O50,0,IF($A94=O50,O63*O54,O63))-IF($A94<O51,0,IF($A94=O51,O67*O55,O67)))/(1+O47)^($A94-O48-1))
A95: =A94+1 | B95: =IF(OR($A95<=B48,$A95>B34),0,(B29-IF($A95<B50,0,IF($A95=B50,B63*B54,B63))-IF($A95<B51,0,IF($A95=B51,B67*B55,B67)))/(1+B47)^($A95-B48-1)) | C95: =IF(OR($A95<=C48,$A95>C34),0,(C29-IF($A95<C50,0,IF($A95=C50,C63*C54,C63))-IF($A95<C51,0,IF($A95=C51,C67*C55,C67)))/(1+C47)^($A95-C48-1)) | D95: =IF(OR($A95<=D48,$A95>D34),0,(D29-IF($A95<D50,0,IF($A95=D50,D63*D54,D63))-IF($A95<D51,0,IF($A95=D51,D67*D55,D67)))/(1+D47)^($A95-D48-1)) | E95: =IF(OR($A95<=E48,$A95>E34),0,(E29-IF($A95<E50,0,IF($A95=E50,E63*E54,E63))-IF($A95<E51,0,IF($A95=E51,E67*E55,E67)))/(1+E47)^($A95-E48-1)) | F95: =IF(OR($A95<=F48,$A95>F34),0,(F29-IF($A95<F50,0,IF($A95=F50,F63*F54,F63))-IF($A95<F51,0,IF($A95=F51,F67*F55,F67)))/(1+F47)^($A95-F48-1)) | G95: =IF(OR($A95<=G48,$A95>G34),0,(G29-IF($A95<G50,0,IF($A95=G50,G63*G54,G63))-IF($A95<G51,0,IF($A95=G51,G67*G55,G67)))/(1+G47)^($A95-G48-1)) | H95: =IF(OR($A95<=H48,$A95>H34),0,(H29-IF($A95<H50,0,IF($A95=H50,H63*H54,H63))-IF($A95<H51,0,IF($A95=H51,H67*H55,H67)))/(1+H47)^($A95-H48-1)) | I95: =IF(OR($A95<=I48,$A95>I34),0,(I29-IF($A95<I50,0,IF($A95=I50,I63*I54,I63))-IF($A95<I51,0,IF($A95=I51,I67*I55,I67)))/(1+I47)^($A95-I48-1)) | ... O95: =IF(OR($A95<=O48,$A95>O34),0,(O29-IF($A95<O50,0,IF($A95=O50,O63*O54,O63))-IF($A95<O51,0,IF($A95=O51,O67*O55,O67)))/(1+O47)^($A95-O48-1))
A96: =A95+1 | B96: =IF(OR($A96<=B48,$A96>B34),0,(B29-IF($A96<B50,0,IF($A96=B50,B63*B54,B63))-IF($A96<B51,0,IF($A96=B51,B67*B55,B67)))/(1+B47)^($A96-B48-1)) | C96: =IF(OR($A96<=C48,$A96>C34),0,(C29-IF($A96<C50,0,IF($A96=C50,C63*C54,C63))-IF($A96<C51,0,IF($A96=C51,C67*C55,C67)))/(1+C47)^($A96-C48-1)) | D96: =IF(OR($A96<=D48,$A96>D34),0,(D29-IF($A96<D50,0,IF($A96=D50,D63*D54,D63))-IF($A96<D51,0,IF($A96=D51,D67*D55,D67)))/(1+D47)^($A96-D48-1)) | E96: =IF(OR($A96<=E48,$A96>E34),0,(E29-IF($A96<E50,0,IF($A96=E50,E63*E54,E63))-IF($A96<E51,0,IF($A96=E51,E67*E55,E67)))/(1+E47)^($A96-E48-1)) | F96: =IF(OR($A96<=F48,$A96>F34),0,(F29-IF($A96<F50,0,IF($A96=F50,F63*F54,F63))-IF($A96<F51,0,IF($A96=F51,F67*F55,F67)))/(1+F47)^($A96-F48-1)) | G96: =IF(OR($A96<=G48,$A96>G34),0,(G29-IF($A96<G50,0,IF($A96=G50,G63*G54,G63))-IF($A96<G51,0,IF($A96=G51,G67*G55,G67)))/(1+G47)^($A96-G48-1)) | H96: =IF(OR($A96<=H48,$A96>H34),0,(H29-IF($A96<H50,0,IF($A96=H50,H63*H54,H63))-IF($A96<H51,0,IF($A96=H51,H67*H55,H67)))/(1+H47)^($A96-H48-1)) | I96: =IF(OR($A96<=I48,$A96>I34),0,(I29-IF($A96<I50,0,IF($A96=I50,I63*I54,I63))-IF($A96<I51,0,IF($A96=I51,I67*I55,I67)))/(1+I47)^($A96-I48-1)) | ... O96: =IF(OR($A96<=O48,$A96>O34),0,(O29-IF($A96<O50,0,IF($A96=O50,O63*O54,O63))-IF($A96<O51,0,IF($A96=O51,O67*O55,O67)))/(1+O47)^($A96-O48-1))
