Workbook

Sheet 0-Indice
A1: Marco FIRE — Quanto vale tornare al lavoro (caso Davide, 2026)
A2: Strumento informativo / divulgativo. NON è consulenza finanziaria. I valori sono indicativi al 2026 e vanno verificati col tuo consulente.
A4: Indice
A5: 1-Input | B5: Il caso di Davide: i diciannove input e i derivati
A6: P-Parametri | B6: Parametri normativi 2026, coefficienti, sequenze
A7: 2-Composizione | B7: Da dove vengono i 760.000 e la plusvalenza latente
A8: 3-Simulazione | B8: Il portafoglio anno per anno, quarantadue righe
A9: 4-Griglia | B9: La griglia 3x4: spesa massima, età di esaurimento, capitale
A10: 5-Leve | B10: LE DUE LEVE IN ORDINE: quanto lavoro, quanto taglio di spesa
A11: 6-Fisco | B11: La finestra fiscale riga per riga, la soglia e lo scalino
A12: 7-Rientro | B12: Tabella madre, anni di margine, momento del rientro
A13: 8-Capitale | B13: Capitale equivalente, effetto sequenza, pendenza
A14: 9-Pensione | B14: Montante, contributi riattivati, valore in capitale
A15: 10-Verifica | B15: Cruscotto, semaforo e le note di scadenza
A16: M1 / M2 / M3 | B16: I motori: secanti a sei valutazioni, una simulazione ciascuna
A18: Come usare
A19: 1. Le celle GIALLE sono input — modificale coi tuoi numeri.
A20: 2. Le celle VERDI sono output — si aggiornano automaticamente.
A21: 3. Tutti i numeri di default sono al 2026 da fonti pubbliche.
A22: 4. Niente codice nascosto: l'Excel è solo formule modificabili.
A24: Fonti dati
A25: • IRPEF 2026 (23% / 33% / 43%) — L. 199/2025; detrazioni art. 13 TUIR c. 1 (lavoro) e c. 3 (pensione), che non si cumulano fra loro
A26: • Trattamento integrativo 1.200 € e somma integrativa sul cuneo (7,1% / 5,3% / 4,8%) — L. 207/2024 art. 1 cc. 4-5; ulteriore detrazione 1.000 € fra 20.000 e 40.000 € — L. 207/2024 art. 1 c. 6
A27: • Contributi a carico del lavoratore dipendente 9,19%; aliquota di computo 33% sulla RETRIBUZIONE IMPONIBILE PREVIDENZIALE (il lordo, non il netto)
A28: • Coefficiente di trasformazione a 68 anni e 8 mesi (5,9520%, interpolato) — DM 20/11/2024, biennio 2025-2026: REFRESH GENNAIO 2027
A29: • Decorrenza a 68 anni e 8 mesi nel 2045 per il nato nel 1976: PROIEZIONE della Ragioneria generale dello Stato, non una norma in vigore
A30: • Capital gain 26% — art. 68 TUIR e D.Lgs. 461/1997; imposta di bollo 0,20% sul patrimonio di FINE anno
... A36: Aggiornamenti: github.com/marcofire-it/marco-fire-simulatori

Sheet 1-Input
A1: Il caso di Davide — gli input
A2: Strumento informativo / divulgativo. NON è consulenza finanziaria. I valori sono indicativi al 2026 e vanno verificati col tuo consulente.
A4: INPUT — cambia una cella gialla e tutti i verdi si muovono
A5: (1) Età oggi / anno di nascita | B5: 50 | C5: 1976
A6: (2) Età di decorrenza della pensione — anni / mesi | B6: 68 | C6: 8
A7: (3) Orizzonte di piano (età finale) | B7: 92
A8: (4) Patrimonio investito | B8: 760000
A9: (5) Base di costo | B9: 586000
A10: (6) Spesa netta annua | B10: 29000
A11: (7) Reddito LORDO annuo del rientro | B11: 12000
A12: (8) Anni di rientro — durata A / durata B | B12: 5 | C12: 10
A13: (9) Anno di avvio del rientro (1 = subito) | B13: 1
A14: (10) Pensione attesa — netta / lorda al mese | B14: 1195 | C14: 1462
A15: (11) Rendimento reale del caso base | B15: 0.03
A16: (12) Ordine dei rendimenti del caso base (1=cost. 2=inizio 3=meta 4=fine) | B16: 2
A17: (13) Retribuzione media di carriera (previdenziale) | B17: 35000
A18: (14) Anni di contributi già maturati | B18: 25
A19: (15) Giorni di lavoro nell'anno (365 = contratto per l'anno intero) | B19: 365
A20: Lo stato abitativo fa parte della scheda-caso: Davide è single, ha la CASA DI PROPRIETÀ e il mutuo estinto. Serve perché il video confronta la sua spesa con aggregati ISTAT che includono l'affitto figurativo — una componente non monetaria.
A21: DERIVATI — non si toccano, si ricalcolano
A22: Anni di piano (orizzonte - età oggi) | B22: =B7-B5 -> 42
A23: Pensione netta annua (x 13 mensilità) | B23: =B14*'P-Parametri'!$B$25 -> 15535
A24: Pensione lorda annua (x 13 mensilità) | B24: =C14*'P-Parametri'!$B$25 -> 19006
A25: Decorrenza, in anni dall'inizio del piano | B25: =(B6+C6/12)-B5 -> 18.666667
A26: Anni pieni senza pensione (ponte) | B26: =IF(B25=INT(B25),B25-1,INT(B25)) -> 18
A27: Frazione di pensione nell'anno successivo | B27: =IF(B25=INT(B25),1,1-(B25-INT(B25))) -> 0.33333333
A28: Quota della base di costo sul patrimonio | B28: =B9/B8 -> 0.77105263
A29: Plusvalenza latente iniziale | B29: =(B8-B9)/B8 -> 0.22894737
A30: Netto in busta del reddito del rientro | B30: =((B11*(1-'P-Parametri'!$B$22))+0)-(MAX(0,(IF(((B11*(1-'P-Parametri'!$B$22))+0)<='P-Parametri'!$B$6,'P-Parametri'!$C$6*((B11*(1-'P-Parametri'!$B$22))+0),IF(((B11*(1-'P-Parametri'!$B$22))+0)<='P-Parametri'!$B$7,'P-Parametri'!$B$9+'P-Parametri'!$C$7*(((B11*(1-'P-Parametri'!$B$22))+0)-'P-Parametri'!$B$6),'P-Parametri'!$B$10+'P-Parametri'!$C$8*(((B11*(1-'P-Parametri'!$B$22))+0)-'P-Parametri'!$B$7))))-(IF(((B11*(1-'P-Parametri'!$B$22))+0)<='P-Parametri'!$C$12,'P-Parametri'!$B$12,IF(((B11*(1-'P-Parametri'!$B$22))+0)<='P-Parametri'!$B$6,'P-Parametri'!$B$13+'P-Parametri'!$C$13*('P-Parametri'!$B$6-((B11*(1-'P-Parametri'!$B$22))+0))/'P-Parametri'!$D$13,IF(((B11*(1-'P-Parametri'!$B$22))+0)<='P-Parametri'!$B$7,'P-Parametri'!$B$14*('P-Parametri'!$B$7-((B11*(1-'P-Parametri'!$B$22))+0))/'P-Parametri'!$C$14,0))))-(IF((B11*(1-'P-Parametri'!$B$22))>0,IF(((B11*(1-'P-Parametri'!$B$22))+0)<='P-Parametri'!$C$21,0,IF(((B11*(1-'P-Parametri'!$B$22))+0)<='P-Parametri'!$D$21,'P-Parametri'!$B$21,IF(((B11*(1-'P-Parametri'!$B$22))+0)<'P-Parametri'!$E$21,'P-Parametri'!$B$21*('P-Parametri'!$E$21-((B11*(1-'P-Parametri'!$B$22))+0))/('P-Parametri'!$E$21-'P-Parametri'!$D$21),0))),0))))-(IF(MAX(0,(IF(((B11*(1-'P-Parametri'!$B$22))+0)<='P-Parametri'!$B$6,'P-Parametri'!$C$6*((B11*(1-'P-Parametri'!$B$22))+0),IF(((B11*(1-'P-Parametri'!$B$22))+0)<='P-Parametri'!$B$7,'P-Parametri'!$B$9+'P-Parametri'!$C$7*(((B11*(1-'P-Parametri'!$B$22))+0)-'P-Parametri'!$B$6),'P-Parametri'!$B$10+'P-Parametri'!$C$8*(((B11*(1-'P-Parametri'!$B$22))+0)-'P-Parametri'!$B$7))))-(IF(((B11*(1-'P-Parametri'!$B$22))+0)<='P-Parametri'!$C$12,'P-Parametri'!$B$12,IF(((B11*(1-'P-Parametri'!$B$22))+0)<='P-Parametri'!$B$6,'P-Parametri'!$B$13+'P-Parametri'!$C$13*('P-Parametri'!$B$6-((B11*(1-'P-Parametri'!$B$22))+0))/'P-Parametri'!$D$13,IF(((B11*(1-'P-Parametri'!$B$22))+0)<='P-Parametri'!$B$7,'P-Parametri'!$B$14*('P-Parametri'!$B$7-((B11*(1-'P-Parametri'!$B$22))+0))/'P-Parametri'!$C$14,0))))-(IF((B11*(1-'P-Parametri'!$B$22))>0,IF(((B11*(1-'P-Parametri'!$B$22))+0)<='P-Parametri'!$C$21,0,IF(((B11*(1-'P-Parametri'!$B$22))+0)<='P-Parametri'!$D$21,'P-Parametri'!$B$21,IF(((B11*(1-'P-Parametri'!$B$22))+0)<'P-Parametri'!$E$21,'P-Parametri'!$B$21*('P-Parametri'!$E$21-((B11*(1-'P-Parametri'!$B$22))+0))/('P-Parametri'!$E$21-'P-Parametri'!$D$21),0))),0)))>0,'P-Parametri'!$B$11*((B11*(1-'P-Parametri'!$B$22))+0),0))+(IF(AND(((B11*(1-'P-Parametri'!$B$22))+0)<='P-Parametri'!$C$18,(IF(((B11*(1-'P-Parametri'!$B$22))+0)<='P-Parametri'!$B$6,'P-Parametri'!$C$6*((B11*(1-'P-Parametri'!$B$22))+0),IF(((B11*(1-'P-Parametri'!$B$22))+0)<='P-Parametri'!$B$7,'P-Parametri'!$B$9+'P-Parametri'!$C$7*(((B11*(1-'P-Parametri'!$B$22))+0)-'P-Parametri'!$B$6),'P-Parametri'!$B$10+'P-Parametri'!$C$8*(((B11*(1-'P-Parametri'!$B$22))+0)-'P-Parametri'!$B$7))))>(IF(((B11*(1-'P-Parametri'!$B$22))+0)<='P-Parametri'!$C$12,'P-Parametri'!$B$12,IF(((B11*(1-'P-Parametri'!$B$22))+0)<='P-Parametri'!$B$6,'P-Parametri'!$B$13+'P-Parametri'!$C$13*('P-Parametri'!$B$6-((B11*(1-'P-Parametri'!$B$22))+0))/'P-Parametri'!$D$13,IF(((B11*(1-'P-Parametri'!$B$22))+0)<='P-Parametri'!$B$7,'P-Parametri'!$B$14*('P-Parametri'!$B$7-((B11*(1-'P-Parametri'!$B$22))+0))/'P-Parametri'!$C$14,0))))-'P-Parametri'!$D$18),'P-Parametri'!$B$18,0))+(IF((B11*(1-'P-Parametri'!$B$22))>0,IF(((B11*(1-'P-Parametri'!$B$22))+0)>'P-Parametri'!$D$20,0,IF(((B11*(1-'P-Parametri'!$B$22))+0)<='P-Parametri'!$B$20,'P-Parametri'!$B$19*(B11*(1-'P-Parametri'!$B$22)),IF(((B11*(1-'P-Parametri'!$B$22))+0)<='P-Parametri'!$C$20,'P-Parametri'!$C$19*(B11*(1-'P-Parametri'!$B$22)),'P-Parametri'!$D$19*(B11*(1-'P-Parametri'!$B$22))))),0)) -> 11905.452
A31: Netto / lordo del reddito del rientro | B31: =B30/B11 -> 0.99212097
A32: Pensione in più (netta) dai contributi riattivati | B32: =(('P-Parametri'!$B$24*B11)*(1+'P-Parametri'!$B$26)^(B25-B13-B12+1)*(IF('P-Parametri'!$B$26=0,B12,((1+'P-Parametri'!$B$26)^B12-1)/'P-Parametri'!$B$26)))*'P-Parametri'!$B$27*(1-'P-Parametri'!$B$28) -> 887.4451
A33: Tasso di prelievo di cassa, anno 1 | B33: =B10/B8 -> 0.038157895
A34: Tasso omogeneo (vendita lorda), anno 1 | B34: =(B10/(1-'P-Parametri'!$B$31*B29))/B8 -> 0.040573059
A35: Tasso col bollo (patrimonio di FINE anno), anno 1 | B35: =(B10/(1-'P-Parametri'!$B$31*B29)+'P-Parametri'!$B$32*((B8-B10/(1-'P-Parametri'!$B$31*B29))*(1+B15)))/B8 -> 0.042549479
A37: Il bollo dello 0,20% grava sul patrimonio di FINE anno: è la convenzione del motore ed è la ragione per cui la terza scala del tasso vale 4,255% e non 4,257%. Il 4,257% è lo stesso bollo calcolato sul patrimonio di INIZIO anno.
A38: I 68 anni e 8 mesi e il 2045 sono una PROIEZIONE della Ragioneria generale dello Stato per la coorte del 1976, non una norma in vigore. Vanno dichiarati tali ogni volta che entrano in un conto.
A39: Il montante contributivo si calcola sul 33% della RETRIBUZIONE LORDA, anno per anno, ciascuna annualità rivalutata fino alla decorrenza: non è il 33% del netto in busta, e non si ottiene scalando linearmente il montante di cinque anni.

Sheet P-Parametri
A1: Parametri normativi e di fonte — fotografia del 2026
A2: Strumento informativo / divulgativo. NON è consulenza finanziaria. I valori sono indicativi al 2026 e vanno verificati col tuo consulente.
A3: Le uniche costanti del modello, oltre agli input del foglio 1, stanno qui. Tutti gli altri fogli le referenziano: cambiare un'aliquota qui muove ogni cella verde della cartella.
A5: IRPEF 2026 (L. 199/2025) e detrazioni dell'art. 13 TUIR
A6: Primo scaglione — limite / aliquota | B6: 28000 | C6: 0.23
A7: Secondo scaglione — limite / aliquota | B7: 50000 | C7: 0.33
A8: Terzo scaglione — aliquota oltre il secondo limite | C8: 0.43
A9: Imposta cumulata fino al primo scaglione | B9: =B6*C6 -> 6440
A10: Imposta cumulata fino al secondo scaglione | B10: =B9+(B7-B6)*C7 -> 13700
A11: Addizionali regionale e comunale | B11: 0.02
A12: Detrazione da LAVORO (c. 1) — importo pieno / soglia bassa | B12: 1955 | C12: 15000
A13: Detrazione da lavoro 15.000-28.000 — base / incremento / ampiezza | B13: 1910 | C13: 1190 | D13: 13000
A14: Detrazione da lavoro 28.000-50.000 — base / ampiezza | B14: 1910 | C14: 22000
A15: Detrazione da PENSIONE (c. 3) — importo pieno / soglia bassa | B15: 1955 | C15: 8500
A16: Detrazione da pensione 8.500-28.000 — base / incremento / ampiezza | B16: 700 | C16: 1255 | D16: 19500
A17: Detrazione da pensione 28.000-50.000 — base / ampiezza | B17: 700 | C17: 22000
A18: Trattamento integrativo — importo / soglia / scarto di capienza | B18: 1200 | C18: 15000 | D18: 75
A19: Somma sul cuneo — aliquote (fino a 8.500 / 15.000 / 20.000) | B19: 0.071 | C19: 0.053 | D19: 0.048
A20: Somma sul cuneo — soglie di reddito complessivo | B20: 8500 | C20: 15000 | D20: 20000
A21: Ulteriore detrazione — importo / da / piena fino a / azzerata a | B21: 1000 | C21: 20000 | D21: 32000 | E21: 40000
A22: Contributi a carico del lavoratore dipendente | B22: 0.0919
A23: Previdenza obbligatoria
A24: Aliquota di computo (dipendenti), sulla retribuzione LORDA | B24: 0.33
A25: Mensilità della pensione | B25: 13
A26: Rivalutazione REALE annua del montante (ipotesi RGS) | B26: 0.006
A27: Coefficiente di trasformazione a 68 anni e 8 mesi (interpolato) | B27: 0.05952
A28: Aliquota marginale effettiva sulla pensione | B28: 0.31436
A29: Anni minimi di contribuzione per la vecchiaia | B29: 20
A30: Fiscalità finanziaria
A31: Imposta sulla plusvalenza realizzata | B31: 0.26
A32: Imposta di bollo, sul patrimonio di FINE anno | B32: 0.002
A33: Sequenze dei rendimenti — illustrative, NON probabilistiche
A34: Crolli: primo / secondo | B34: -0.35 | C34: -0.2
A35: Ordine «crolli INIZIO» — anni | B35: 1 | C35: 2
A36: Ordine «crolli METÀ» — anni | B36: 21 | C36: 22
A37: Ordine «crolli FINE» — anni | B37: 41 | C37: 42
A38: Riferimenti del caso
A39: Spesa media ISTAT 2024, persona sola 35-64 (€/anno) | B39: 25164
A40: NASpI — soglia autonomo / subordinato | B40: 5500 | C40: 8500
A41: Maestas — retribuzione pre-ritiro / post (rev. 2004) / post (rev. 2005), in dollari | B41: 42045 | C41: 9592 | D41: 10192
A42: Rendimento reale netto bollo della fase di accumulo | B42: 0.028
A44: LA BANDA E GLI ORDINI — il rendimento anno per anno
A45: Rendimenti della banda | B45: 0.01 | C45: 0.02 | D45: 0.03
A46: Ordine | B46: costante | C46: crolli INIZIO | D46: crolli METÀ | E46: crolli FINE
A47: Anno del primo crollo (0 = nessun crollo) | B47: 0 | C47: =B35 -> 1 | D47: =B36 -> 21 | E47: =B37 -> 41
A48: Anno del secondo crollo | B48: 0 | C48: =C35 -> 2 | D48: =C36 -> 22 | E48: =C37 -> 42
A49: Rendimento degli anni NON di crollo, per (banda x ordine)
A50: r = 1% | B50: =IF(B$47=0,B$45,((1+B$45)^'1-Input'!$B$22/((1+$B$34)*(1+$C$34)))^(1/('1-Input'!$B$22-2))-1) -> 0.01 | C50: =IF(C$47=0,B$45,((1+B$45)^'1-Input'!$B$22/((1+$B$34)*(1+$C$34)))^(1/('1-Input'!$B$22-2))-1) -> 0.02715825 | D50: =IF(D$47=0,B$45,((1+B$45)^'1-Input'!$B$22/((1+$B$34)*(1+$C$34)))^(1/('1-Input'!$B$22-2))-1) -> 0.02715825 | E50: =IF(E$47=0,B$45,((1+B$45)^'1-Input'!$B$22/((1+$B$34)*(1+$C$34)))^(1/('1-Input'!$B$22-2))-1) -> 0.02715825
A51: r = 2% | B51: =IF(B$47=0,C$45,((1+C$45)^'1-Input'!$B$22/((1+$B$34)*(1+$C$34)))^(1/('1-Input'!$B$22-2))-1) -> 0.02 | C51: =IF(C$47=0,C$45,((1+C$45)^'1-Input'!$B$22/((1+$B$34)*(1+$C$34)))^(1/('1-Input'!$B$22-2))-1) -> 0.037839263 | D51: =IF(D$47=0,C$45,((1+C$45)^'1-Input'!$B$22/((1+$B$34)*(1+$C$34)))^(1/('1-Input'!$B$22-2))-1) -> 0.037839263 | E51: =IF(E$47=0,C$45,((1+C$45)^'1-Input'!$B$22/((1+$B$34)*(1+$C$34)))^(1/('1-Input'!$B$22-2))-1) -> 0.037839263
A52: r = 3% | B52: =IF(B$47=0,D$45,((1+D$45)^'1-Input'!$B$22/((1+$B$34)*(1+$C$34)))^(1/('1-Input'!$B$22-2))-1) -> 0.03 | C52: =IF(C$47=0,D$45,((1+D$45)^'1-Input'!$B$22/((1+$B$34)*(1+$C$34)))^(1/('1-Input'!$B$22-2))-1) -> 0.048525513 | D52: =IF(D$47=0,D$45,((1+D$45)^'1-Input'!$B$22/((1+$B$34)*(1+$C$34)))^(1/('1-Input'!$B$22-2))-1) -> 0.048525513 | E52: =IF(E$47=0,D$45,((1+D$45)^'1-Input'!$B$22/((1+$B$34)*(1+$C$34)))^(1/('1-Input'!$B$22-2))-1) -> 0.048525513
A54: I due crolli valgono -35% e -20%; gli altri quaranta anni rendono quanto serve perché la media geometrica sui quarantadue anni resti esattamente il rendimento della banda. Le posizioni sono SCELTE, non stimate: la griglia è illustrativa, non probabilistica.
A55: REFRESH GENNAIO 2027 — OBBLIGATORIO. Il coefficiente di trasformazione è quello del DM 20/11/2024, valido per il biennio 2025-2026, e qui viene applicato a una decorrenza del 2045: va rifatto alla pubblicazione del decreto successivo. Anche detrazioni, trattamento integrativo e somma sul cuneo sono riscritti ogni anno dalla legge di bilancio.
A56: FOTOGRAFIA DEL 2026. Il D.Lgs. 117/2026 (testo unico dei redditi) è entrato in vigore il 4/7/2026 ma i suoi effetti DECORRONO dal 1/1/2027 (art. 377), e l'art. 376 c. 2 dispone la continuità dei rinvii: è RICODIFICAZIONE, non soppressione. Per tutto il 2026 valgono le norme di questo foglio. Chi verificherà nel 2027 su Normattiva leggerà di default la versione già abrogata: bisogna scendere di una versione e leggere quella vigente nell'anno del video.
A57: I requisiti pensionistici oltre il 2026 sono PROIEZIONI della Ragioneria generale dello Stato, non norme in vigore.

Sheet 2-Composizione
A1: Da dove vengono i 760.000 € — e perché la latente è derivata
A2: Strumento informativo / divulgativo. NON è consulenza finanziaria. I valori sono indicativi al 2026 e vanno verificati col tuo consulente.
A3: La plusvalenza latente non si postula: si deriva dalla storia di accumulo. Le tre righe qui sotto sono input gialli; il valore di oggi, la base di costo e la latente sono formule.
A5: LE TRE COMPONENTI DEL PATRIMONIO
A6: Componente | B6: Versamento / importo | C6: Anni | D6: Rendimento reale | E6: Valore oggi | F6: Latente | G6: Conferito totale (base)
A7: Accumulo finanziario — versamento annuo a inizio anno | B7: 11000 | C7: 25 | D7: ='P-Parametri'!$B$42 -> 0.028 | E7: =B7*(((1+D7)^C7-1)/D7)*(1+D7) -> 401624.48 | F7: =E7-G7 -> 126624.48 | G7: =B7*C7 -> 275000
A8: TFR netto alla cessazione (tassazione separata) | B8: 48000 | C8: 0 | D8: ='P-Parametri'!$B$42 -> 0.028 | E8: =B8 -> 48000 | F8: =E8-G8 -> 0 | G8: =B8 -> 48000
A9: Eredità ricevuta a 44 anni e investita | B9: 263000 | C9: 6 | D9: ='P-Parametri'!$B$42 -> 0.028 | E9: =B9*(1+D9)^C9 -> 310394.8 | F9: =E9-G9 -> 47394.8 | G9: =B9 -> 263000
A10: TOTALE — derivato | E10: =SUM(E7:E9) -> 760019.28 | F10: =SUM(F7:F9) -> 174019.28 | G10: =SUM(G7:G9) -> 586000
A11: Plusvalenza latente derivata (latente / valore) | B11: =F10/E10 -> 0.22896693
A12: Patrimonio e base del foglio 1 (arrotondati) — e i due scarti | B12: ='1-Input'!$B$8 -> 760000 | C12: ='1-Input'!$B$9 -> 586000 | E12: =B12-E10 -> -19.276952 | G12: =C12-G10 -> 0
A13: Latente iniziale adottata dal motore ((W − B) / W) | B13: ='1-Input'!$B$29 -> 0.22894737
A14: Peso dell'eredità sul patrimonio | B14: =E9/E10 -> 0.40840385
A15: L'eredità pesa oltre il quaranta per cento del patrimonio, ed è la componente entrata a base piena solo sei anni fa: è la ragione per cui la latente di Davide è più bassa di quella degli altri casi del catalogo. Va dichiarata a schermo.
A17: IL CASO CHIUDE? — tasso di risparmio implicito
A18: Retribuzione lorda media di carriera | B18: ='1-Input'!$B$17 -> 35000
A19: Netto in busta della carriera (modulo fiscale del foglio 6) | B19: =(('1-Input'!$B$17*(1-'P-Parametri'!$B$22))+0)-(MAX(0,(IF((('1-Input'!$B$17*(1-'P-Parametri'!$B$22))+0)<='P-Parametri'!$B$6,'P-Parametri'!$C$6*(('1-Input'!$B$17*(1-'P-Parametri'!$B$22))+0),IF((('1-Input'!$B$17*(1-'P-Parametri'!$B$22))+0)<='P-Parametri'!$B$7,'P-Parametri'!$B$9+'P-Parametri'!$C$7*((('1-Input'!$B$17*(1-'P-Parametri'!$B$22))+0)-'P-Parametri'!$B$6),'P-Parametri'!$B$10+'P-Parametri'!$C$8*((('1-Input'!$B$17*(1-'P-Parametri'!$B$22))+0)-'P-Parametri'!$B$7))))-(IF((('1-Input'!$B$17*(1-'P-Parametri'!$B$22))+0)<='P-Parametri'!$C$12,'P-Parametri'!$B$12,IF((('1-Input'!$B$17*(1-'P-Parametri'!$B$22))+0)<='P-Parametri'!$B$6,'P-Parametri'!$B$13+'P-Parametri'!$C$13*('P-Parametri'!$B$6-(('1-Input'!$B$17*(1-'P-Parametri'!$B$22))+0))/'P-Parametri'!$D$13,IF((('1-Input'!$B$17*(1-'P-Parametri'!$B$22))+0)<='P-Parametri'!$B$7,'P-Parametri'!$B$14*('P-Parametri'!$B$7-(('1-Input'!$B$17*(1-'P-Parametri'!$B$22))+0))/'P-Parametri'!$C$14,0))))-(IF(('1-Input'!$B$17*(1-'P-Parametri'!$B$22))>0,IF((('1-Input'!$B$17*(1-'P-Parametri'!$B$22))+0)<='P-Parametri'!$C$21,0,IF((('1-Input'!$B$17*(1-'P-Parametri'!$B$22))+0)<='P-Parametri'!$D$21,'P-Parametri'!$B$21,IF((('1-Input'!$B$17*(1-'P-Parametri'!$B$22))+0)<'P-Parametri'!$E$21,'P-Parametri'!$B$21*('P-Parametri'!$E$21-(('1-Input'!$B$17*(1-'P-Parametri'!$B$22))+0))/('P-Parametri'!$E$21-'P-Parametri'!$D$21),0))),0))))-(IF(MAX(0,(IF((('1-Input'!$B$17*(1-'P-Parametri'!$B$22))+0)<='P-Parametri'!$B$6,'P-Parametri'!$C$6*(('1-Input'!$B$17*(1-'P-Parametri'!$B$22))+0),IF((('1-Input'!$B$17*(1-'P-Parametri'!$B$22))+0)<='P-Parametri'!$B$7,'P-Parametri'!$B$9+'P-Parametri'!$C$7*((('1-Input'!$B$17*(1-'P-Parametri'!$B$22))+0)-'P-Parametri'!$B$6),'P-Parametri'!$B$10+'P-Parametri'!$C$8*((('1-Input'!$B$17*(1-'P-Parametri'!$B$22))+0)-'P-Parametri'!$B$7))))-(IF((('1-Input'!$B$17*(1-'P-Parametri'!$B$22))+0)<='P-Parametri'!$C$12,'P-Parametri'!$B$12,IF((('1-Input'!$B$17*(1-'P-Parametri'!$B$22))+0)<='P-Parametri'!$B$6,'P-Parametri'!$B$13+'P-Parametri'!$C$13*('P-Parametri'!$B$6-(('1-Input'!$B$17*(1-'P-Parametri'!$B$22))+0))/'P-Parametri'!$D$13,IF((('1-Input'!$B$17*(1-'P-Parametri'!$B$22))+0)<='P-Parametri'!$B$7,'P-Parametri'!$B$14*('P-Parametri'!$B$7-(('1-Input'!$B$17*(1-'P-Parametri'!$B$22))+0))/'P-Parametri'!$C$14,0))))-(IF(('1-Input'!$B$17*(1-'P-Parametri'!$B$22))>0,IF((('1-Input'!$B$17*(1-'P-Parametri'!$B$22))+0)<='P-Parametri'!$C$21,0,IF((('1-Input'!$B$17*(1-'P-Parametri'!$B$22))+0)<='P-Parametri'!$D$21,'P-Parametri'!$B$21,IF((('1-Input'!$B$17*(1-'P-Parametri'!$B$22))+0)<'P-Parametri'!$E$21,'P-Parametri'!$B$21*('P-Parametri'!$E$21-(('1-Input'!$B$17*(1-'P-Parametri'!$B$22))+0))/('P-Parametri'!$E$21-'P-Parametri'!$D$21),0))),0)))>0,'P-Parametri'!$B$11*(('1-Input'!$B$17*(1-'P-Parametri'!$B$22))+0),0))+(IF(AND((('1-Input'!$B$17*(1-'P-Parametri'!$B$22))+0)<='P-Parametri'!$C$18,(IF((('1-Input'!$B$17*(1-'P-Parametri'!$B$22))+0)<='P-Parametri'!$B$6,'P-Parametri'!$C$6*(('1-Input'!$B$17*(1-'P-Parametri'!$B$22))+0),IF((('1-Input'!$B$17*(1-'P-Parametri'!$B$22))+0)<='P-Parametri'!$B$7,'P-Parametri'!$B$9+'P-Parametri'!$C$7*((('1-Input'!$B$17*(1-'P-Parametri'!$B$22))+0)-'P-Parametri'!$B$6),'P-Parametri'!$B$10+'P-Parametri'!$C$8*((('1-Input'!$B$17*(1-'P-Parametri'!$B$22))+0)-'P-Parametri'!$B$7))))>(IF((('1-Input'!$B$17*(1-'P-Parametri'!$B$22))+0)<='P-Parametri'!$C$12,'P-Parametri'!$B$12,IF((('1-Input'!$B$17*(1-'P-Parametri'!$B$22))+0)<='P-Parametri'!$B$6,'P-Parametri'!$B$13+'P-Parametri'!$C$13*('P-Parametri'!$B$6-(('1-Input'!$B$17*(1-'P-Parametri'!$B$22))+0))/'P-Parametri'!$D$13,IF((('1-Input'!$B$17*(1-'P-Parametri'!$B$22))+0)<='P-Parametri'!$B$7,'P-Parametri'!$B$14*('P-Parametri'!$B$7-(('1-Input'!$B$17*(1-'P-Parametri'!$B$22))+0))/'P-Parametri'!$C$14,0))))-'P-Parametri'!$D$18),'P-Parametri'!$B$18,0))+(IF(('1-Input'!$B$17*(1-'P-Parametri'!$B$22))>0,IF((('1-Input'!$B$17*(1-'P-Parametri'!$B$22))+0)>'P-Parametri'!$D$20,0,IF((('1-Input'!$B$17*(1-'P-Parametri'!$B$22))+0)<='P-Parametri'!$B$20,'P-Parametri'!$B$19*('1-Input'!$B$17*(1-'P-Parametri'!$B$22)),IF((('1-Input'!$B$17*(1-'P-Parametri'!$B$22))+0)<='P-Parametri'!$C$20,'P-Parametri'!$C$19*('1-Input'!$B$17*(1-'P-Parametri'!$B$22)),'P-Parametri'!$D$19*('1-Input'!$B$17*(1-'P-Parametri'!$B$22))))),0)) -> 26040.798
A20: Risparmio annuo reale (dalla riga dell'accumulo) | B20: =B7 -> 11000
A21: TASSO DI RISPARMIO IMPLICITO | B21: =B20/B19 -> 0.42241408
A22: Tenore di vita durante l'accumulo (netto − risparmio) | B22: =B19-B20 -> 15040.798
A23: Il salto: spesa di oggi / tenore dell'accumulo | B23: ='1-Input'!$B$10/B22 -> 1.9280891
A25: IL CONFRONTO ISTAT — nelle DUE direzioni
A26: Spesa media ISTAT 2024, persona sola 35-64 (€/anno) | B26: ='P-Parametri'!$B$39 -> 25164
A27: Spesa di oggi / ISTAT | B27: ='1-Input'!$B$10/B26 -> 1.15244
A28: Tenore dell'accumulo / ISTAT | B28: =B22/B26 -> 0.59771095
A29: CLAUSOLA OBBLIGATORIA. L'aggregato ISTAT «spesa media per consumi» INCLUDE l'affitto figurativo, che non è un esborso di cassa. Davide ha la casa di proprietà e il mutuo estinto: il confronto è semmai generoso verso di lui, e va detto in entrambe le direzioni — non solo in quella che conviene.
A31: LA CONVENZIONE DELLA COMPOSIZIONE COSTANTE
A32: Quota della base di costo sul patrimonio, tenuta fissa | B32: ='1-Input'!$B$28 -> 0.77105263
A33: Nella tabella del capitale necessario la composizione del patrimonio è tenuta costante — stessa proporzione fra base di costo e valore — perché altrimenti si confronterebbero due Davide diversi. La latente si deriva dalla storia di accumulo per il caso; per la tabella che dal caso discende, si tiene ferma.

Sheet 3-Simulazione
A1: Il portafoglio anno per anno — il caso base del foglio 1
A2: Strumento informativo / divulgativo. NON è consulenza finanziaria. I valori sono indicativi al 2026 e vanno verificati col tuo consulente.
A4: LA SEQUENZA SCELTA NEL FOGLIO 1
A5: Rendimento della banda / ordine scelto | B5: ='1-Input'!$B$15 -> 0.03 | C5: =CHOOSE('1-Input'!$B$16,"costante","crolli INIZIO","crolli META'","crolli FINE") -> crolli INIZIO
A6: Anno del primo / secondo crollo | B6: =INDEX('P-Parametri'!$B$47:'P-Parametri'!$E$47,'1-Input'!$B$16) -> 1 | C6: =INDEX('P-Parametri'!$B$48:'P-Parametri'!$E$48,'1-Input'!$B$16) -> 2
A7: Rendimento degli anni non di crollo | B7: =IF(B6=0,'1-Input'!$B$15,((1+'1-Input'!$B$15)^'1-Input'!$B$22/((1+'P-Parametri'!$B$34)*(1+'P-Parametri'!$C$34)))^(1/('1-Input'!$B$22-2))-1) -> 0.048525513
A9: SENZA RIENTRO — il piano come sta
A10: anno | B10: rend. | C10: pensione | D10: lavoro | E10: G lordo | F10: patrimonio | G10: base | H10: copre?
A11: =0 -> 0 | E11: =0 -> 0 | F11: ='1-Input'!$B$8 -> 760000 | G11: ='1-Input'!$B$9 -> 586000 | H11: =1 -> 1
A12: =A11+1 -> 1 | B12: =IF($A12='3-Simulazione'!$B$6,'P-Parametri'!$B$34,IF($A12='3-Simulazione'!$C$6,'P-Parametri'!$C$34,'3-Simulazione'!$B$7)) -> -0.35 | C12: =IF($A12<='1-Input'!$B$26,0,IF($A12='1-Input'!$B$26+1,('1-Input'!$B$23+0)*'1-Input'!$B$27,'1-Input'!$B$23+0)) -> 0 | D12: =IF(AND($A12>=1,$A12<1+0),0,0) -> 0 | E12: =MAX(0,('1-Input'!$B$10-C12-D12))/(1-'P-Parametri'!$B$31*MAX(0,IF(F11<=0,0,(F11-G11)/F11))) -> 30835.525 | F12: =((F11-E12+MAX(0,-('1-Input'!$B$10-C12-D12)))*(1+B12))*(1-'P-Parametri'!$B$32) -> 473008.99 | G12: =IF(F11<=0,G11,G11*(1-E12/F11))+MAX(0,-('1-Input'!$B$10-C12-D12)) -> 562224.19 | H12: =IF(OR(F11<=0,F11<E12),0,1) -> 1
A13: =A12+1 -> 2 | B13: =IF($A13='3-Simulazione'!$B$6,'P-Parametri'!$B$34,IF($A13='3-Simulazione'!$C$6,'P-Parametri'!$C$34,'3-Simulazione'!$B$7)) -> -0.2 | C13: =IF($A13<='1-Input'!$B$26,0,IF($A13='1-Input'!$B$26+1,('1-Input'!$B$23+0)*'1-Input'!$B$27,'1-Input'!$B$23+0)) -> 0 | D13: =IF(AND($A13>=1,$A13<1+0),0,0) -> 0 | E13: =MAX(0,('1-Input'!$B$10-C13-D13))/(1-'P-Parametri'!$B$31*MAX(0,IF(F12<=0,0,(F12-G12)/F12))) -> 29000 | F13: =((F12-E13+MAX(0,-('1-Input'!$B$10-C13-D13)))*(1+B13))*(1-'P-Parametri'!$B$32) -> 354496.78 | G13: =IF(F12<=0,G12,G12*(1-E13/F12))+MAX(0,-('1-Input'!$B$10-C13-D13)) -> 527754.44 | H13: =IF(OR(F12<=0,F12<E13),0,1) -> 1
A14: =A13+1 -> 3 | B14: =IF($A14='3-Simulazione'!$B$6,'P-Parametri'!$B$34,IF($A14='3-Simulazione'!$C$6,'P-Parametri'!$C$34,'3-Simulazione'!$B$7)) -> 0.048525513 | C14: =IF($A14<='1-Input'!$B$26,0,IF($A14='1-Input'!$B$26+1,('1-Input'!$B$23+0)*'1-Input'!$B$27,'1-Input'!$B$23+0)) -> 0 | D14: =IF(AND($A14>=1,$A14<1+0),0,0) -> 0 | E14: =MAX(0,('1-Input'!$B$10-C14-D14))/(1-'P-Parametri'!$B$31*MAX(0,IF(F13<=0,0,(F13-G13)/F13))) -> 29000 | F14: =((F13-E14+MAX(0,-('1-Input'!$B$10-C14-D14)))*(1+B14))*(1-'P-Parametri'!$B$32) -> 340609.1 | G14: =IF(F13<=0,G13,G13*(1-E14/F13))+MAX(0,-('1-Input'!$B$10-C14-D14)) -> 484580.9 | H14: =IF(OR(F13<=0,F13<E14),0,1) -> 1
A15: =A14+1 -> 4 | B15: =IF($A15='3-Simulazione'!$B$6,'P-Parametri'!$B$34,IF($A15='3-Simulazione'!$C$6,'P-Parametri'!$C$34,'3-Simulazione'!$B$7)) -> 0.048525513 | C15: =IF($A15<='1-Input'!$B$26,0,IF($A15='1-Input'!$B$26+1,('1-Input'!$B$23+0)*'1-Input'!$B$27,'1-Input'!$B$23+0)) -> 0 | D15: =IF(AND($A15>=1,$A15<1+0),0,0) -> 0 | E15: =MAX(0,('1-Input'!$B$10-C15-D15))/(1-'P-Parametri'!$B$31*MAX(0,IF(F14<=0,0,(F14-G14)/F14))) -> 29000 | F15: =((F14-E15+MAX(0,-('1-Input'!$B$10-C15-D15)))*(1+B15))*(1-'P-Parametri'!$B$32) -> 326076.63 | G15: =IF(F14<=0,G14,G14*(1-E15/F14))+MAX(0,-('1-Input'!$B$10-C15-D15)) -> 443322.92 | H15: =IF(OR(F14<=0,F14<E15),0,1) -> 1
A16: =A15+1 -> 5 | B16: =IF($A16='3-Simulazione'!$B$6,'P-Parametri'!$B$34,IF($A16='3-Simulazione'!$C$6,'P-Parametri'!$C$34,'3-Simulazione'!$B$7)) -> 0.048525513 | C16: =IF($A16<='1-Input'!$B$26,0,IF($A16='1-Input'!$B$26+1,('1-Input'!$B$23+0)*'1-Input'!$B$27,'1-Input'!$B$23+0)) -> 0 | D16: =IF(AND($A16>=1,$A16<1+0),0,0) -> 0 | E16: =MAX(0,('1-Input'!$B$10-C16-D16))/(1-'P-Parametri'!$B$31*MAX(0,IF(F15<=0,0,(F15-G15)/F15))) -> 29000 | F16: =((F15-E16+MAX(0,-('1-Input'!$B$10-C16-D16)))*(1+B16))*(1-'P-Parametri'!$B$32) -> 310869.44 | G16: =IF(F15<=0,G15,G15*(1-E16/F15))+MAX(0,-('1-Input'!$B$10-C16-D16)) -> 403895.48 | H16: =IF(OR(F15<=0,F15<E16),0,1) -> 1
A17: =A16+1 -> 6 | B17: =IF($A17='3-Simulazione'!$B$6,'P-Parametri'!$B$34,IF($A17='3-Simulazione'!$C$6,'P-Parametri'!$C$34,'3-Simulazione'!$B$7)) -> 0.048525513 | C17: =IF($A17<='1-Input'!$B$26,0,IF($A17='1-Input'!$B$26+1,('1-Input'!$B$23+0)*'1-Input'!$B$27,'1-Input'!$B$23+0)) -> 0 | D17: =IF(AND($A17>=1,$A17<1+0),0,0) -> 0 | E17: =MAX(0,('1-Input'!$B$10-C17-D17))/(1-'P-Parametri'!$B$31*MAX(0,IF(F16<=0,0,(F16-G16)/F16))) -> 29000 | F17: =((F16-E17+MAX(0,-('1-Input'!$B$10-C17-D17)))*(1+B17))*(1-'P-Parametri'!$B$32) -> 294956.2 | G17: =IF(F16<=0,G16,G16*(1-E17/F16))+MAX(0,-('1-Input'!$B$10-C17-D17)) -> 366217.38 | H17: =IF(OR(F16<=0,F16<E17),0,1) -> 1
A18: =A17+1 -> 7 | B18: =IF($A18='3-Simulazione'!$B$6,'P-Parametri'!$B$34,IF($A18='3-Simulazione'!$C$6,'P-Parametri'!$C$34,'3-Simulazione'!$B$7)) -> 0.048525513 | C18: =IF($A18<='1-Input'!$B$26,0,IF($A18='1-Input'!$B$26+1,('1-Input'!$B$23+0)*'1-Input'!$B$27,'1-Input'!$B$23+0)) -> 0 | D18: =IF(AND($A18>=1,$A18<1+0),0,0) -> 0 | E18: =MAX(0,('1-Input'!$B$10-C18-D18))/(1-'P-Parametri'!$B$31*MAX(0,IF(F17<=0,0,(F17-G17)/F17))) -> 29000 | F18: =((F17-E18+MAX(0,-('1-Input'!$B$10-C18-D18)))*(1+B18))*(1-'P-Parametri'!$B$32) -> 278304.14 | G18: =IF(F17<=0,G17,G17*(1-E18/F17))+MAX(0,-('1-Input'!$B$10-C18-D18)) -> 330211.01 | H18: =IF(OR(F17<=0,F17<E18),0,1) -> 1
A19: =A18+1 -> 8 | B19: =IF($A19='3-Simulazione'!$B$6,'P-Parametri'!$B$34,IF($A19='3-Simulazione'!$C$6,'P-Parametri'!$C$34,'3-Simulazione'!$B$7)) -> 0.048525513 | C19: =IF($A19<='1-Input'!$B$26,0,IF($A19='1-Input'!$B$26+1,('1-Input'!$B$23+0)*'1-Input'!$B$27,'1-Input'!$B$23+0)) -> 0 | D19: =IF(AND($A19>=1,$A19<1+0),0,0) -> 0 | E19: =MAX(0,('1-Input'!$B$10-C19-D19))/(1-'P-Parametri'!$B$31*MAX(0,IF(F18<=0,0,(F18-G18)/F18))) -> 29000 | F19: =((F18-E19+MAX(0,-('1-Input'!$B$10-C19-D19)))*(1+B19))*(1-'P-Parametri'!$B$32) -> 260878.95 | G19: =IF(F18<=0,G18,G18*(1-E19/F18))+MAX(0,-('1-Input'!$B$10-C19-D19)) -> 295802.18 | H19: =IF(OR(F18<=0,F18<E19),0,1) -> 1
A20: =A19+1 -> 9 | B20: =IF($A20='3-Simulazione'!$B$6,'P-Parametri'!$B$34,IF($A20='3-Simulazione'!$C$6,'P-Parametri'!$C$34,'3-Simulazione'!$B$7)) -> 0.048525513 | C20: =IF($A20<='1-Input'!$B$26,0,IF($A20='1-Input'!$B$26+1,('1-Input'!$B$23+0)*'1-Input'!$B$27,'1-Input'!$B$23+0)) -> 0 | D20: =IF(AND($A20>=1,$A20<1+0),0,0) -> 0 | E20: =MAX(0,('1-Input'!$B$10-C20-D20))/(1-'P-Parametri'!$B$31*MAX(0,IF(F19<=0,0,(F19-G19)/F19))) -> 29000 | F20: =((F19-E20+MAX(0,-('1-Input'!$B$10-C20-D20)))*(1+B20))*(1-'P-Parametri'!$B$32) -> 242644.73 | G20: =IF(F19<=0,G19,G19*(1-E20/F19))+MAX(0,-('1-Input'!$B$10-C20-D20)) -> 262920.02 | H20: =IF(OR(F19<=0,F19<E20),0,1) -> 1
A21: =A20+1 -> 10 | B21: =IF($A21='3-Simulazione'!$B$6,'P-Parametri'!$B$34,IF($A21='3-Simulazione'!$C$6,'P-Parametri'!$C$34,'3-Simulazione'!$B$7)) -> 0.048525513 | C21: =IF($A21<='1-Input'!$B$26,0,IF($A21='1-Input'!$B$26+1,('1-Input'!$B$23+0)*'1-Input'!$B$27,'1-Input'!$B$23+0)) -> 0 | D21: =IF(AND($A21>=1,$A21<1+0),0,0) -> 0 | E21: =MAX(0,('1-Input'!$B$10-C21-D21))/(1-'P-Parametri'!$B$31*MAX(0,IF(F20<=0,0,(F20-G20)/F20))) -> 29000 | F21: =((F20-E21+MAX(0,-('1-Input'!$B$10-C21-D21)))*(1+B21))*(1-'P-Parametri'!$B$32) -> 223563.93 | G21: =IF(F20<=0,G20,G20*(1-E21/F20))+MAX(0,-('1-Input'!$B$10-C21-D21)) -> 231496.79 | H21: =IF(OR(F20<=0,F20<E21),0,1) -> 1
A22: =A21+1 -> 11 | B22: =IF($A22='3-Simulazione'!$B$6,'P-Parametri'!$B$34,IF($A22='3-Simulazione'!$C$6,'P-Parametri'!$C$34,'3-Simulazione'!$B$7)) -> 0.048525513 | C22: =IF($A22<='1-Input'!$B$26,0,IF($A22='1-Input'!$B$26+1,('1-Input'!$B$23+0)*'1-Input'!$B$27,'1-Input'!$B$23+0)) -> 0 | D22: =IF(AND($A22>=1,$A22<1+0),0,0) -> 0 | E22: =MAX(0,('1-Input'!$B$10-C22-D22))/(1-'P-Parametri'!$B$31*MAX(0,IF(F21<=0,0,(F21-G21)/F21))) -> 29000 | F22: =((F21-E22+MAX(0,-('1-Input'!$B$10-C22-D22)))*(1+B22))*(1-'P-Parametri'!$B$32) -> 203597.23 | G22: =IF(F21<=0,G21,G21*(1-E22/F21))+MAX(0,-('1-Input'!$B$10-C22-D22)) -> 201467.77 | H22: =IF(OR(F21<=0,F21<E22),0,1) -> 1
A23: =A22+1 -> 12 | B23: =IF($A23='3-Simulazione'!$B$6,'P-Parametri'!$B$34,IF($A23='3-Simulazione'!$C$6,'P-Parametri'!$C$34,'3-Simulazione'!$B$7)) -> 0.048525513 | C23: =IF($A23<='1-Input'!$B$26,0,IF($A23='1-Input'!$B$26+1,('1-Input'!$B$23+0)*'1-Input'!$B$27,'1-Input'!$B$23+0)) -> 0 | D23: =IF(AND($A23>=1,$A23<1+0),0,0) -> 0 | E23: =MAX(0,('1-Input'!$B$10-C23-D23))/(1-'P-Parametri'!$B$31*MAX(0,IF(F22<=0,0,(F22-G22)/F22))) -> 29079.077 | F23: =((F22-E23+MAX(0,-('1-Input'!$B$10-C23-D23)))*(1+B23))*(1-'P-Parametri'!$B$32) -> 182620.76 | G23: =IF(F22<=0,G22,G22*(1-E23/F22))+MAX(0,-('1-Input'!$B$10-C23-D23)) -> 172692.83 | H23: =IF(OR(F22<=0,F22<E23),0,1) -> 1
... A53: =A52+1 -> 42 | B53: =IF($A53='3-Simulazione'!$B$6,'P-Parametri'!$B$34,IF($A53='3-Simulazione'!$C$6,'P-Parametri'!$C$34,'3-Simulazione'!$B$7)) -> 0.048525513 | C53: =IF($A53<='1-Input'!$B$26,0,IF($A53='1-Input'!$B$26+1,('1-Input'!$B$23+0)*'1-Input'!$B$27,'1-Input'!$B$23+0)) -> 15535 | D53: =IF(AND($A53>=1,$A53<1+0),0,0) -> 0 | E53: =MAX(0,('1-Input'!$B$10-C53-D53))/(1-'P-Parametri'!$B$31*MAX(0,IF(F52<=0,0,(F52-G52)/F52))) -> 13465 | F53: =((F52-E53+MAX(0,-('1-Input'!$B$10-C53-D53)))*(1+B53))*(1-'P-Parametri'!$B$32) -> -558049.32 | G53: =IF(F52<=0,G52,G52*(1-E53/F52))+MAX(0,-('1-Input'!$B$10-C53-D53)) -> -9180.7268 | H53: =IF(OR(F52<=0,F52<E53),0,1) -> 0
A54: ETÀ DI ESAURIMENTO | B54: =IFERROR('1-Input'!$B$5-1+MATCH(0,H11:H53,0)-1,"non si esaurisce") -> 69 | D54: patrimonio finale | E54: =F53 -> -558049.32
A57: CON IL RIENTRO DEL FOGLIO 1 — reddito, durata e avvio degli input
A58: anno | B58: rend. | C58: pensione | D58: lavoro | E58: G lordo | F58: patrimonio | G58: base | H58: copre?
A59: =0 -> 0 | E59: =0 -> 0 | F59: ='1-Input'!$B$8 -> 760000 | G59: ='1-Input'!$B$9 -> 586000 | H59: =1 -> 1
A60: =A59+1 -> 1 | B60: =IF($A60='3-Simulazione'!$B$6,'P-Parametri'!$B$34,IF($A60='3-Simulazione'!$C$6,'P-Parametri'!$C$34,'3-Simulazione'!$B$7)) -> -0.35 | C60: =IF($A60<='1-Input'!$B$26,0,IF($A60='1-Input'!$B$26+1,('1-Input'!$B$23+'1-Input'!$B$32)*'1-Input'!$B$27,'1-Input'!$B$23+'1-Input'!$B$32)) -> 0 | D60: =IF(AND($A60>='1-Input'!$B$13,$A60<'1-Input'!$B$13+'1-Input'!$B$12),'1-Input'!$B$30,0) -> 11905.452 | E60: =MAX(0,('1-Input'!$B$10-C60-D60))/(1-'P-Parametri'!$B$31*MAX(0,IF(F59<=0,0,(F59-G59)/F59))) -> 18176.53 | F60: =((F59-E60+MAX(0,-('1-Input'!$B$10-C60-D60)))*(1+B60))*(1-'P-Parametri'!$B$32) -> 481220.88 | G60: =IF(F59<=0,G59,G59*(1-E60/F59))+MAX(0,-('1-Input'!$B$10-C60-D60)) -> 571984.94 | H60: =IF(OR(F59<=0,F59<E60),0,1) -> 1
A61: =A60+1 -> 2 | B61: =IF($A61='3-Simulazione'!$B$6,'P-Parametri'!$B$34,IF($A61='3-Simulazione'!$C$6,'P-Parametri'!$C$34,'3-Simulazione'!$B$7)) -> -0.2 | C61: =IF($A61<='1-Input'!$B$26,0,IF($A61='1-Input'!$B$26+1,('1-Input'!$B$23+'1-Input'!$B$32)*'1-Input'!$B$27,'1-Input'!$B$23+'1-Input'!$B$32)) -> 0 | D61: =IF(AND($A61>='1-Input'!$B$13,$A61<'1-Input'!$B$13+'1-Input'!$B$12),'1-Input'!$B$30,0) -> 11905.452 | E61: =MAX(0,('1-Input'!$B$10-C61-D61))/(1-'P-Parametri'!$B$31*MAX(0,IF(F60<=0,0,(F60-G60)/F60))) -> 17094.548 | F61: =((F60-E61+MAX(0,-('1-Input'!$B$10-C61-D61)))*(1+B61))*(1-'P-Parametri'!$B$32) -> 370558.47 | G61: =IF(F60<=0,G60,G60*(1-E61/F60))+MAX(0,-('1-Input'!$B$10-C61-D61)) -> 551666.15 | H61: =IF(OR(F60<=0,F60<E61),0,1) -> 1
A62: =A61+1 -> 3 | B62: =IF($A62='3-Simulazione'!$B$6,'P-Parametri'!$B$34,IF($A62='3-Simulazione'!$C$6,'P-Parametri'!$C$34,'3-Simulazione'!$B$7)) -> 0.048525513 | C62: =IF($A62<='1-Input'!$B$26,0,IF($A62='1-Input'!$B$26+1,('1-Input'!$B$23+'1-Input'!$B$32)*'1-Input'!$B$27,'1-Input'!$B$23+'1-Input'!$B$32)) -> 0 | D62: =IF(AND($A62>='1-Input'!$B$13,$A62<'1-Input'!$B$13+'1-Input'!$B$12),'1-Input'!$B$30,0) -> 11905.452 | E62: =MAX(0,('1-Input'!$B$10-C62-D62))/(1-'P-Parametri'!$B$31*MAX(0,IF(F61<=0,0,(F61-G61)/F61))) -> 17094.548 | F62: =((F61-E62+MAX(0,-('1-Input'!$B$10-C62-D62)))*(1+B62))*(1-'P-Parametri'!$B$32) -> 369874.7 | G62: =IF(F61<=0,G61,G61*(1-E62/F61))+MAX(0,-('1-Input'!$B$10-C62-D62)) -> 526216.77 | H62: =IF(OR(F61<=0,F61<E62),0,1) -> 1
A63: =A62+1 -> 4 | B63: =IF($A63='3-Simulazione'!$B$6,'P-Parametri'!$B$34,IF($A63='3-Simulazione'!$C$6,'P-Parametri'!$C$34,'3-Simulazione'!$B$7)) -> 0.048525513 | C63: =IF($A63<='1-Input'!$B$26,0,IF($A63='1-Input'!$B$26+1,('1-Input'!$B$23+'1-Input'!$B$32)*'1-Input'!$B$27,'1-Input'!$B$23+'1-Input'!$B$32)) -> 0 | D63: =IF(AND($A63>='1-Input'!$B$13,$A63<'1-Input'!$B$13+'1-Input'!$B$12),'1-Input'!$B$30,0) -> 11905.452 | E63: =MAX(0,('1-Input'!$B$10-C63-D63))/(1-'P-Parametri'!$B$31*MAX(0,IF(F62<=0,0,(F62-G62)/F62))) -> 17094.548 | F63: =((F62-E63+MAX(0,-('1-Input'!$B$10-C63-D63)))*(1+B63))*(1-'P-Parametri'!$B$32) -> 369159.2 | G63: =IF(F62<=0,G62,G62*(1-E63/F62))+MAX(0,-('1-Input'!$B$10-C63-D63)) -> 501896.54 | H63: =IF(OR(F62<=0,F62<E63),0,1) -> 1
A64: =A63+1 -> 5 | B64: =IF($A64='3-Simulazione'!$B$6,'P-Parametri'!$B$34,IF($A64='3-Simulazione'!$C$6,'P-Parametri'!$C$34,'3-Simulazione'!$B$7)) -> 0.048525513 | C64: =IF($A64<='1-Input'!$B$26,0,IF($A64='1-Input'!$B$26+1,('1-Input'!$B$23+'1-Input'!$B$32)*'1-Input'!$B$27,'1-Input'!$B$23+'1-Input'!$B$32)) -> 0 | D64: =IF(AND($A64>='1-Input'!$B$13,$A64<'1-Input'!$B$13+'1-Input'!$B$12),'1-Input'!$B$30,0) -> 11905.452 | E64: =MAX(0,('1-Input'!$B$10-C64-D64))/(1-'P-Parametri'!$B$31*MAX(0,IF(F63<=0,0,(F63-G63)/F63))) -> 17094.548 | F64: =((F63-E64+MAX(0,-('1-Input'!$B$10-C64-D64)))*(1+B64))*(1-'P-Parametri'!$B$32) -> 368410.47 | G64: =IF(F63<=0,G63,G63*(1-E64/F63))+MAX(0,-('1-Input'!$B$10-C64-D64)) -> 478655.36 | H64: =IF(OR(F63<=0,F63<E64),0,1) -> 1
A65: =A64+1 -> 6 | B65: =IF($A65='3-Simulazione'!$B$6,'P-Parametri'!$B$34,IF($A65='3-Simulazione'!$C$6,'P-Parametri'!$C$34,'3-Simulazione'!$B$7)) -> 0.048525513 | C65: =IF($A65<='1-Input'!$B$26,0,IF($A65='1-Input'!$B$26+1,('1-Input'!$B$23+'1-Input'!$B$32)*'1-Input'!$B$27,'1-Input'!$B$23+'1-Input'!$B$32)) -> 0 | D65: =IF(AND($A65>='1-Input'!$B$13,$A65<'1-Input'!$B$13+'1-Input'!$B$12),'1-Input'!$B$30,0) -> 0 | E65: =MAX(0,('1-Input'!$B$10-C65-D65))/(1-'P-Parametri'!$B$31*MAX(0,IF(F64<=0,0,(F64-G64)/F64))) -> 29000 | F65: =((F64-E65+MAX(0,-('1-Input'!$B$10-C65-D65)))*(1+B65))*(1-'P-Parametri'!$B$32) -> 355168.77 | G65: =IF(F64<=0,G64,G64*(1-E65/F64))+MAX(0,-('1-Input'!$B$10-C65-D65)) -> 440977.26 | H65: =IF(OR(F64<=0,F64<E65),0,1) -> 1
A66: =A65+1 -> 7 | B66: =IF($A66='3-Simulazione'!$B$6,'P-Parametri'!$B$34,IF($A66='3-Simulazione'!$C$6,'P-Parametri'!$C$34,'3-Simulazione'!$B$7)) -> 0.048525513 | C66: =IF($A66<='1-Input'!$B$26,0,IF($A66='1-Input'!$B$26+1,('1-Input'!$B$23+'1-Input'!$B$32)*'1-Input'!$B$27,'1-Input'!$B$23+'1-Input'!$B$32)) -> 0 | D66: =IF(AND($A66>='1-Input'!$B$13,$A66<'1-Input'!$B$13+'1-Input'!$B$12),'1-Input'!$B$30,0) -> 0 | E66: =MAX(0,('1-Input'!$B$10-C66-D66))/(1-'P-Parametri'!$B$31*MAX(0,IF(F65<=0,0,(F65-G65)/F65))) -> 29000 | F66: =((F65-E66+MAX(0,-('1-Input'!$B$10-C66-D66)))*(1+B66))*(1-'P-Parametri'!$B$32) -> 341312.29 | G66: =IF(F65<=0,G65,G65*(1-E66/F65))+MAX(0,-('1-Input'!$B$10-C66-D66)) -> 404970.89 | H66: =IF(OR(F65<=0,F65<E66),0,1) -> 1
A67: =A66+1 -> 8 | B67: =IF($A67='3-Simulazione'!$B$6,'P-Parametri'!$B$34,IF($A67='3-Simulazione'!$C$6,'P-Parametri'!$C$34,'3-Simulazione'!$B$7)) -> 0.048525513 | C67: =IF($A67<='1-Input'!$B$26,0,IF($A67='1-Input'!$B$26+1,('1-Input'!$B$23+'1-Input'!$B$32)*'1-Input'!$B$27,'1-Input'!$B$23+'1-Input'!$B$32)) -> 0 | D67: =IF(AND($A67>='1-Input'!$B$13,$A67<'1-Input'!$B$13+'1-Input'!$B$12),'1-Input'!$B$30,0) -> 0 | E67: =MAX(0,('1-Input'!$B$10-C67-D67))/(1-'P-Parametri'!$B$31*MAX(0,IF(F66<=0,0,(F66-G66)/F66))) -> 29000 | F67: =((F66-E67+MAX(0,-('1-Input'!$B$10-C67-D67)))*(1+B67))*(1-'P-Parametri'!$B$32) -> 326812.47 | G67: =IF(F66<=0,G66,G66*(1-E67/F66))+MAX(0,-('1-Input'!$B$10-C67-D67)) -> 370562.06 | H67: =IF(OR(F66<=0,F66<E67),0,1) -> 1
A68: =A67+1 -> 9 | B68: =IF($A68='3-Simulazione'!$B$6,'P-Parametri'!$B$34,IF($A68='3-Simulazione'!$C$6,'P-Parametri'!$C$34,'3-Simulazione'!$B$7)) -> 0.048525513 | C68: =IF($A68<='1-Input'!$B$26,0,IF($A68='1-Input'!$B$26+1,('1-Input'!$B$23+'1-Input'!$B$32)*'1-Input'!$B$27,'1-Input'!$B$23+'1-Input'!$B$32)) -> 0 | D68: =IF(AND($A68>='1-Input'!$B$13,$A68<'1-Input'!$B$13+'1-Input'!$B$12),'1-Input'!$B$30,0) -> 0 | E68: =MAX(0,('1-Input'!$B$10-C68-D68))/(1-'P-Parametri'!$B$31*MAX(0,IF(F67<=0,0,(F67-G67)/F67))) -> 29000 | F68: =((F67-E68+MAX(0,-('1-Input'!$B$10-C68-D68)))*(1+B68))*(1-'P-Parametri'!$B$32) -> 311639.44 | G68: =IF(F67<=0,G67,G67*(1-E68/F67))+MAX(0,-('1-Input'!$B$10-C68-D68)) -> 337679.9 | H68: =IF(OR(F67<=0,F67<E68),0,1) -> 1
A69: =A68+1 -> 10 | B69: =IF($A69='3-Simulazione'!$B$6,'P-Parametri'!$B$34,IF($A69='3-Simulazione'!$C$6,'P-Parametri'!$C$34,'3-Simulazione'!$B$7)) -> 0.048525513 | C69: =IF($A69<='1-Input'!$B$26,0,IF($A69='1-Input'!$B$26+1,('1-Input'!$B$23+'1-Input'!$B$32)*'1-Input'!$B$27,'1-Input'!$B$23+'1-Input'!$B$32)) -> 0 | D69: =IF(AND($A69>='1-Input'!$B$13,$A69<'1-Input'!$B$13+'1-Input'!$B$12),'1-Input'!$B$30,0) -> 0 | E69: =MAX(0,('1-Input'!$B$10-C69-D69))/(1-'P-Parametri'!$B$31*MAX(0,IF(F68<=0,0,(F68-G68)/F68))) -> 29000 | F69: =((F68-E69+MAX(0,-('1-Input'!$B$10-C69-D69)))*(1+B69))*(1-'P-Parametri'!$B$32) -> 295761.96 | G69: =IF(F68<=0,G68,G68*(1-E69/F68))+MAX(0,-('1-Input'!$B$10-C69-D69)) -> 306256.67 | H69: =IF(OR(F68<=0,F68<E69),0,1) -> 1
A70: =A69+1 -> 11 | B70: =IF($A70='3-Simulazione'!$B$6,'P-Parametri'!$B$34,IF($A70='3-Simulazione'!$C$6,'P-Parametri'!$C$34,'3-Simulazione'!$B$7)) -> 0.048525513 | C70: =IF($A70<='1-Input'!$B$26,0,IF($A70='1-Input'!$B$26+1,('1-Input'!$B$23+'1-Input'!$B$32)*'1-Input'!$B$27,'1-Input'!$B$23+'1-Input'!$B$32)) -> 0 | D70: =IF(AND($A70>='1-Input'!$B$13,$A70<'1-Input'!$B$13+'1-Input'!$B$12),'1-Input'!$B$30,0) -> 0 | E70: =MAX(0,('1-Input'!$B$10-C70-D70))/(1-'P-Parametri'!$B$31*MAX(0,IF(F69<=0,0,(F69-G69)/F69))) -> 29000 | F70: =((F69-E70+MAX(0,-('1-Input'!$B$10-C70-D70)))*(1+B70))*(1-'P-Parametri'!$B$32) -> 279147.31 | G70: =IF(F69<=0,G69,G69*(1-E70/F69))+MAX(0,-('1-Input'!$B$10-C70-D70)) -> 276227.65 | H70: =IF(OR(F69<=0,F69<E70),0,1) -> 1
A71: =A70+1 -> 12 | B71: =IF($A71='3-Simulazione'!$B$6,'P-Parametri'!$B$34,IF($A71='3-Simulazione'!$C$6,'P-Parametri'!$C$34,'3-Simulazione'!$B$7)) -> 0.048525513 | C71: =IF($A71<='1-Input'!$B$26,0,IF($A71='1-Input'!$B$26+1,('1-Input'!$B$23+'1-Input'!$B$32)*'1-Input'!$B$27,'1-Input'!$B$23+'1-Input'!$B$32)) -> 0 | D71: =IF(AND($A71>='1-Input'!$B$13,$A71<'1-Input'!$B$13+'1-Input'!$B$12),'1-Input'!$B$30,0) -> 0 | E71: =MAX(0,('1-Input'!$B$10-C71-D71))/(1-'P-Parametri'!$B$31*MAX(0,IF(F70<=0,0,(F70-G70)/F70))) -> 29079.077 | F71: =((F70-E71+MAX(0,-('1-Input'!$B$10-C71-D71)))*(1+B71))*(1-'P-Parametri'!$B$32) -> 261678.51 | G71: =IF(F70<=0,G70,G70*(1-E71/F70))+MAX(0,-('1-Input'!$B$10-C71-D71)) -> 247452.71 | H71: =IF(OR(F70<=0,F70<E71),0,1) -> 1
... A101: =A100+1 -> 42 | B101: =IF($A101='3-Simulazione'!$B$6,'P-Parametri'!$B$34,IF($A101='3-Simulazione'!$C$6,'P-Parametri'!$C$34,'3-Simulazione'!$B$7)) -> 0.048525513 | C101: =IF($A101<='1-Input'!$B$26,0,IF($A101='1-Input'!$B$26+1,('1-Input'!$B$23+'1-Input'!$B$32)*'1-Input'!$B$27,'1-Input'!$B$23+'1-Input'!$B$32)) -> 16422.445 | D101: =IF(AND($A101>='1-Input'!$B$13,$A101<'1-Input'!$B$13+'1-Input'!$B$12),'1-Input'!$B$30,0) -> 0 | E101: =MAX(0,('1-Input'!$B$10-C101-D101))/(1-'P-Parametri'!$B$31*MAX(0,IF(F100<=0,0,(F100-G100)/F100))) -> 12577.555 | F101: =((F100-E101+MAX(0,-('1-Input'!$B$10-C101-D101)))*(1+B101))*(1-'P-Parametri'!$B$32) -> -245034.25 | G101: =IF(F100<=0,G100,G100*(1-E101/F100))+MAX(0,-('1-Input'!$B$10-C101-D101)) -> -4151.7713 | H101: =IF(OR(F100<=0,F100<E101),0,1) -> 0
A102: ETÀ DI ESAURIMENTO | B102: =IFERROR('1-Input'!$B$5-1+MATCH(0,H59:H101,0)-1,"non si esaurisce") -> 78 | D102: patrimonio finale | E102: =F101 -> -245034.25
A105: ANNI DI MARGINE GUADAGNATI DAL RIENTRO | B105: =IF(ISNUMBER(B54),IF(ISNUMBER(B102),B102-B54,"il piano non si esaurisce più"),"già regge senza rientro") -> 9
A107: Convenzioni del motore, tutte dichiarate: prelievo a INIZIO anno e lordizzato (G = fabbisogno / (1 − 26% × latente)); base di costo ridotta in proporzione (B ← B × (1 − G / W)); bollo dello 0,20% sul patrimonio di FINE anno, che riduce il patrimonio ma NON la base; surplus reinvestito, che aumenta patrimonio e base; orizzonte quarantadue anni; tutto in euro di oggi.
A108: La colonna «copre?» vale 1 finché il patrimonio di inizio anno basta a coprire la vendita lorda dell'anno. L'età di esaurimento è l'età al primo zero.

Sheet 4-Griglia
A1: La griglia 3 × 4 — dodici combinazioni costruite, non estratte
A2: Strumento informativo / divulgativo. NON è consulenza finanziaria. I valori sono indicativi al 2026 e vanno verificati col tuo consulente.
A4: SPESA MASSIMA SOSTENIBILE PER QUARANTADUE ANNI
B5: costante | C5: crolli INIZIO | D5: crolli METÀ | E5: crolli FINE
A6: r = 1% | B6: ='M1-Motore-Griglia'!$B$51 -> 27451.637 | C6: ='M1-Motore-Griglia'!$B$101 -> 21221.533 | D6: ='M1-Motore-Griglia'!$B$151 -> 28180.139 | E6: ='M1-Motore-Griglia'!$B$201 -> 31993.758
A7: r = 2% | B7: ='M1-Motore-Griglia'!$B$251 -> 30039.815 | C7: ='M1-Motore-Griglia'!$B$301 -> 22621.704 | D7: ='M1-Motore-Griglia'!$B$351 -> 30932.171 | E7: ='M1-Motore-Griglia'!$B$401 -> 35415.973
A8: r = 3% | B8: ='M1-Motore-Griglia'!$B$451 -> 32989.828 | C8: ='M1-Motore-Griglia'!$B$501 -> 24119.551 | D8: ='M1-Motore-Griglia'!$B$551 -> 34109.015 | E8: ='M1-Motore-Griglia'!$B$601 -> 39202.863
A10: SCARTO SULLA SPESA DEL CASO
B11: costante | C11: crolli INIZIO | D11: crolli METÀ | E11: crolli FINE
A12: r = 1% | B12: ='M1-Motore-Griglia'!$B$51/'1-Input'!$B$10-1 -> -0.053391811 | C12: ='M1-Motore-Griglia'!$B$101/'1-Input'!$B$10-1 -> -0.26822301 | D12: ='M1-Motore-Griglia'!$B$151/'1-Input'!$B$10-1 -> -0.028271081 | E12: ='M1-Motore-Griglia'!$B$201/'1-Input'!$B$10-1 -> 0.10323304
A13: r = 2% | B13: ='M1-Motore-Griglia'!$B$251/'1-Input'!$B$10-1 -> 0.035855697 | C13: ='M1-Motore-Griglia'!$B$301/'1-Input'!$B$10-1 -> -0.21994123 | D13: ='M1-Motore-Griglia'!$B$351/'1-Input'!$B$10-1 -> 0.066626573 | E13: ='M1-Motore-Griglia'!$B$401/'1-Input'!$B$10-1 -> 0.22124044
A14: r = 3% | B14: ='M1-Motore-Griglia'!$B$451/'1-Input'!$B$10-1 -> 0.13758029 | C14: ='M1-Motore-Griglia'!$B$501/'1-Input'!$B$10-1 -> -0.16829135 | D14: ='M1-Motore-Griglia'!$B$551/'1-Input'!$B$10-1 -> 0.17617293 | E14: ='M1-Motore-Griglia'!$B$601/'1-Input'!$B$10-1 -> 0.35182286
A16: ETÀ A CUI IL CAPITALE NON COPRE PIÙ IL PRELIEVO
B17: costante | C17: crolli INIZIO | D17: crolli METÀ | E17: crolli FINE
A18: r = 1% | B18: ='M1-Motore-Griglia'!$B$1299 -> 86 | C18: ='M1-Motore-Griglia'!$B$1347 -> 66 | D18: ='M1-Motore-Griglia'!$B$1395 -> 89 | E18: ='M1-Motore-Griglia'!$B$1443 -> non si esaurisce
A19: r = 2% | B19: ='M1-Motore-Griglia'!$B$1491 -> non si esaurisce | C19: ='M1-Motore-Griglia'!$B$1539 -> 67 | D19: ='M1-Motore-Griglia'!$B$1587 -> non si esaurisce | E19: ='M1-Motore-Griglia'!$B$1635 -> non si esaurisce
A20: r = 3% | B20: ='M1-Motore-Griglia'!$B$1683 -> non si esaurisce | C20: ='M1-Motore-Griglia'!$B$1731 -> 69 | D20: ='M1-Motore-Griglia'!$B$1779 -> non si esaurisce | E20: ='M1-Motore-Griglia'!$B$1827 -> non si esaurisce
A22: CAPITALE NECESSARIO PER SOSTENERE LA SPESA DEL CASO
B23: costante | C23: crolli INIZIO | D23: crolli METÀ | E23: crolli FINE
A24: r = 1% | B24: ='M1-Motore-Griglia'!$B$651 -> 820838.9 | C24: ='M1-Motore-Griglia'!$B$701 -> 1177197.5 | D24: ='M1-Motore-Griglia'!$B$751 -> 792436.33 | E24: ='M1-Motore-Griglia'!$B$801 -> 669001.43
A25: r = 2% | B25: ='M1-Motore-Griglia'!$B$851 -> 725053.81 | C25: ='M1-Motore-Griglia'!$B$901 -> 1059405.2 | D25: ='M1-Motore-Griglia'!$B$951 -> 695002.54 | E25: ='M1-Motore-Griglia'!$B$1001 -> 592846.01
A26: r = 3% | B26: ='M1-Motore-Griglia'!$B$1051 -> 644533.22 | C26: ='M1-Motore-Griglia'!$B$1101 -> 962349.45 | D26: ='M1-Motore-Griglia'!$B$1151 -> 613108.89 | E26: ='M1-Motore-Griglia'!$B$1201 -> 529788.44
A28: LETTURE DELLA GRIGLIA
A29: Celle in cui il piano regge (su dodici costruite) | B29: =COUNTIF(B6:E8,">="&'1-Input'!$B$10) -> 7
A30: Celle rosse | B30: =12-B29 -> 5
A31: Cella peggiore — spesa massima / età | B31: =MIN(B6:E8) -> 21221.533 | C31: =MIN(B18:E20) -> 66
A32: Capitale necessario nella cella peggiore, e quanto ne manca | B32: =MAX(B24:E26) -> 1177197.5 | C32: =B32-'1-Input'!$B$8 -> 417197.47
A33: Capitale necessario senza alcuna pensione (r = 3%, costante) | B33: ='M1-Motore-Griglia'!$B$1251 -> 839268.36
A34: VALORE IN CAPITALE DELLA PENSIONE PUBBLICA | B34: =B33-'M1-Motore-Griglia'!$B$1051 -> 194735.14
A35: «Sette delle dodici combinazioni che ho costruito» — non «sette su dodici» detto come una frequenza. Le posizioni dei crolli (anni 1-2, 21-22, 41-42) sono SCELTE, non stimate: la griglia è illustrativa, non probabilistica. E una griglia in cui aggiungere reddito non può peggiorare le cose non dimostra che rientrare convenga: dimostra soltanto di quanto.
A36: Il numero grande dell'atto è un'ETA', non un conteggio: sessantasei è una grandezza misurata, «sette su dodici» è un conteggio di scenari scelti a mano e non sopravvive alla perdita della cornice verbale.
A38: LE TRE SCALE DEL TASSO DI PRELIEVO
B39: Cassa | C39: Omogeneo (vendita lorda) | D39: Col bollo
A40: Senza lavoro | B40: ='1-Input'!$B$10/'1-Input'!$B$8 -> 0.038157895 | C40: =('1-Input'!$B$10/(1-'P-Parametri'!$B$31*'1-Input'!$B$29))/'1-Input'!$B$8 -> 0.040573059 | D40: =(('1-Input'!$B$10/(1-'P-Parametri'!$B$31*'1-Input'!$B$29))+'P-Parametri'!$B$32*(('1-Input'!$B$8-'1-Input'!$B$10/(1-'P-Parametri'!$B$31*'1-Input'!$B$29))*(1+'1-Input'!$B$15)))/'1-Input'!$B$8 -> 0.042549479
A41: Col reddito del rientro del foglio 1 | B41: =('1-Input'!$B$10-'1-Input'!$B$30)/'1-Input'!$B$8 -> 0.022492827 | C41: =(('1-Input'!$B$10-'1-Input'!$B$30)/(1-'P-Parametri'!$B$31*'1-Input'!$B$29))/'1-Input'!$B$8 -> 0.023916487 | D41: =((('1-Input'!$B$10-'1-Input'!$B$30)/(1-'P-Parametri'!$B$31*'1-Input'!$B$29))+'P-Parametri'!$B$32*(('1-Input'!$B$8-('1-Input'!$B$10-'1-Input'!$B$30)/(1-'P-Parametri'!$B$31*'1-Input'!$B$29))*(1+'1-Input'!$B$15)))/'1-Input'!$B$8 -> 0.025927219
A42: Il bollo grava sul patrimonio di FINE anno: è la convenzione del motore, ed è la ragione per cui la terza scala vale 4,255% e non 4,257%. Il 4,257% è lo stesso bollo calcolato sul patrimonio di INIZIO anno.
A43: Copertura della spesa dalla pensione pubblica | B43: ='1-Input'!$B$23/'1-Input'!$B$10 -> 0.53568966

Sheet 5-Leve
A1: LE DUE LEVE, IN ORDINE — prima la spesa, poi il lavoro
A2: Strumento informativo / divulgativo. NON è consulenza finanziaria. I valori sono indicativi al 2026 e vanno verificati col tuo consulente.
A3: Questo foglio risponde a una sola domanda: che cosa chiude una cella rossa. La risposta ha due forme — tagliare la spesa, una volta sola e per sempre, oppure lavorare, per un numero di anni dichiarato. Non sono due strade equivalenti: sono una strada e una scorciatoia, e la scorciatoia è la spesa.
A5: CHE COSA CHIUDE OGNI CELLA ROSSA
A6: Cella | B6: Spesa massima | C6: Età | D6: Taglio di spesa | E6: Taglio % | F6: Lavoro — durata A | G6: × carriera | H6: netto in busta | I6: pensione in più | J6: residuo finale | K6: esito | L6: Lavoro — durata B | M6: × carriera | N6: netto in busta | O6: pensione in più | P6: residuo finale | Q6: esito
A7: r = 1% · crolli INIZIO | B7: ='M1-Motore-Griglia'!$B$101 -> 21221.533 | C7: ='M1-Motore-Griglia'!$B$1347 -> 66 | D7: ='1-Input'!$B$10-B7 -> 7778.4674 | E7: =D7/'1-Input'!$B$10 -> 0.26822301 | F7: ='M2-Motore-Chiusura'!$B$53 -> 59803.65 | G7: =F7/'1-Input'!$B$17 -> 1.7086757 | H7: =(($F$7*(1-'P-Parametri'!$B$22))+0)-(MAX(0,(IF((($F$7*(1-'P-Parametri'!$B$22))+0)<='P-Parametri'!$B$6,'P-Parametri'!$C$6*(($F$7*(1-'P-Parametri'!$B$22))+0),IF((($F$7*(1-'P-Parametri'!$B$22))+0)<='P-Parametri'!$B$7,'P-Parametri'!$B$9+'P-Parametri'!$C$7*((($F$7*(1-'P-Parametri'!$B$22))+0)-'P-Parametri'!$B$6),'P-Parametri'!$B$10+'P-Parametri'!$C$8*((($F$7*(1-'P-Parametri'!$B$22))+0)-'P-Parametri'!$B$7))))-(IF((($F$7*(1-'P-Parametri'!$B$22))+0)<='P-Parametri'!$C$12,'P-Parametri'!$B$12,IF((($F$7*(1-'P-Parametri'!$B$22))+0)<='P-Parametri'!$B$6,'P-Parametri'!$B$13+'P-Parametri'!$C$13*('P-Parametri'!$B$6-(($F$7*(1-'P-Parametri'!$B$22))+0))/'P-Parametri'!$D$13,IF((($F$7*(1-'P-Parametri'!$B$22))+0)<='P-Parametri'!$B$7,'P-Parametri'!$B$14*('P-Parametri'!$B$7-(($F$7*(1-'P-Parametri'!$B$22))+0))/'P-Parametri'!$C$14,0))))-(IF(($F$7*(1-'P-Parametri'!$B$22))>0,IF((($F$7*(1-'P-Parametri'!$B$22))+0)<='P-Parametri'!$C$21,0,IF((($F$7*(1-'P-Parametri'!$B$22))+0)<='P-Parametri'!$D$21,'P-Parametri'!$B$21,IF((($F$7*(1-'P-Parametri'!$B$22))+0)<'P-Parametri'!$E$21,'P-Parametri'!$B$21*('P-Parametri'!$E$21-(($F$7*(1-'P-Parametri'!$B$22))+0))/('P-Parametri'!$E$21-'P-Parametri'!$D$21),0))),0))))-(IF(MAX(0,(IF((($F$7*(1-'P-Parametri'!$B$22))+0)<='P-Parametri'!$B$6,'P-Parametri'!$C$6*(($F$7*(1-'P-Parametri'!$B$22))+0),IF((($F$7*(1-'P-Parametri'!$B$22))+0)<='P-Parametri'!$B$7,'P-Parametri'!$B$9+'P-Parametri'!$C$7*((($F$7*(1-'P-Parametri'!$B$22))+0)-'P-Parametri'!$B$6),'P-Parametri'!$B$10+'P-Parametri'!$C$8*((($F$7*(1-'P-Parametri'!$B$22))+0)-'P-Parametri'!$B$7))))-(IF((($F$7*(1-'P-Parametri'!$B$22))+0)<='P-Parametri'!$C$12,'P-Parametri'!$B$12,IF((($F$7*(1-'P-Parametri'!$B$22))+0)<='P-Parametri'!$B$6,'P-Parametri'!$B$13+'P-Parametri'!$C$13*('P-Parametri'!$B$6-(($F$7*(1-'P-Parametri'!$B$22))+0))/'P-Parametri'!$D$13,IF((($F$7*(1-'P-Parametri'!$B$22))+0)<='P-Parametri'!$B$7,'P-Parametri'!$B$14*('P-Parametri'!$B$7-(($F$7*(1-'P-Parametri'!$B$22))+0))/'P-Parametri'!$C$14,0))))-(IF(($F$7*(1-'P-Parametri'!$B$22))>0,IF((($F$7*(1-'P-Parametri'!$B$22))+0)<='P-Parametri'!$C$21,0,IF((($F$7*(1-'P-Parametri'!$B$22))+0)<='P-Parametri'!$D$21,'P-Parametri'!$B$21,IF((($F$7*(1-'P-Parametri'!$B$22))+0)<'P-Parametri'!$E$21,'P-Parametri'!$B$21*('P-Parametri'!$E$21-(($F$7*(1-'P-Parametri'!$B$22))+0))/('P-Parametri'!$E$21-'P-Parametri'!$D$21),0))),0)))>0,'P-Parametri'!$B$11*(($F$7*(1-'P-Parametri'!$B$22))+0),0))+(IF(AND((($F$7*(1-'P-Parametri'!$B$22))+0)<='P-Parametri'!$C$18,(IF((($F$7*(1-'P-Parametri'!$B$22))+0)<='P-Parametri'!$B$6,'P-Parametri'!$C$6*(($F$7*(1-'P-Parametri'!$B$22))+0),IF((($F$7*(1-'P-Parametri'!$B$22))+0)<='P-Parametri'!$B$7,'P-Parametri'!$B$9+'P-Parametri'!$C$7*((($F$7*(1-'P-Parametri'!$B$22))+0)-'P-Parametri'!$B$6),'P-Parametri'!$B$10+'P-Parametri'!$C$8*((($F$7*(1-'P-Parametri'!$B$22))+0)-'P-Parametri'!$B$7))))>(IF((($F$7*(1-'P-Parametri'!$B$22))+0)<='P-Parametri'!$C$12,'P-Parametri'!$B$12,IF((($F$7*(1-'P-Parametri'!$B$22))+0)<='P-Parametri'!$B$6,'P-Parametri'!$B$13+'P-Parametri'!$C$13*('P-Parametri'!$B$6-(($F$7*(1-'P-Parametri'!$B$22))+0))/'P-Parametri'!$D$13,IF((($F$7*(1-'P-Parametri'!$B$22))+0)<='P-Parametri'!$B$7,'P-Parametri'!$B$14*('P-Parametri'!$B$7-(($F$7*(1-'P-Parametri'!$B$22))+0))/'P-Parametri'!$C$14,0))))-'P-Parametri'!$D$18),'P-Parametri'!$B$18,0))+(IF(($F$7*(1-'P-Parametri'!$B$22))>0,IF((($F$7*(1-'P-Parametri'!$B$22))+0)>'P-Parametri'!$D$20,0,IF((($F$7*(1-'P-Parametri'!$B$22))+0)<='P-Parametri'!$B$20,'P-Parametri'!$B$19*($F$7*(1-'P-Parametri'!$B$22)),IF((($F$7*(1-'P-Parametri'!$B$22))+0)<='P-Parametri'!$C$20,'P-Parametri'!$C$19*($F$7*(1-'P-Parametri'!$B$22)),'P-Parametri'!$D$19*($F$7*(1-'P-Parametri'!$B$22))))),0)) -> 37669.232 | I7: =(('P-Parametri'!$B$24*$F$7)*(1+'P-Parametri'!$B$26)^('1-Input'!$B$25-1-'1-Input'!$B$12+1)*(IF('P-Parametri'!$B$26=0,'1-Input'!$B$12,((1+'P-Parametri'!$B$26)^'1-Input'!$B$12-1)/'P-Parametri'!$B$26)))*'P-Parametri'!$B$27*(1-'P-Parametri'!$B$28) -> 4422.7047 | J7: ='M2-Motore-Chiusura'!$E$569 -> 1.9970436e-09 | K7: =IF(ABS(J7)<=1,"radice","GRADINO — la cella si chiude su uno scalino fiscale, non su una radice") -> radice | L7: ='M2-Motore-Chiusura'!$B$105 -> 23941.317 | M7: =L7/'1-Input'!$B$17 -> 0.68403763 | N7: =(($L$7*(1-'P-Parametri'!$B$22))+0)-(MAX(0,(IF((($L$7*(1-'P-Parametri'!$B$22))+0)<='P-Parametri'!$B$6,'P-Parametri'!$C$6*(($L$7*(1-'P-Parametri'!$B$22))+0),IF((($L$7*(1-'P-Parametri'!$B$22))+0)<='P-Parametri'!$B$7,'P-Parametri'!$B$9+'P-Parametri'!$C$7*((($L$7*(1-'P-Parametri'!$B$22))+0)-'P-Parametri'!$B$6),'P-Parametri'!$B$10+'P-Parametri'!$C$8*((($L$7*(1-'P-Parametri'!$B$22))+0)-'P-Parametri'!$B$7))))-(IF((($L$7*(1-'P-Parametri'!$B$22))+0)<='P-Parametri'!$C$12,'P-Parametri'!$B$12,IF((($L$7*(1-'P-Parametri'!$B$22))+0)<='P-Parametri'!$B$6,'P-Parametri'!$B$13+'P-Parametri'!$C$13*('P-Parametri'!$B$6-(($L$7*(1-'P-Parametri'!$B$22))+0))/'P-Parametri'!$D$13,IF((($L$7*(1-'P-Parametri'!$B$22))+0)<='P-Parametri'!$B$7,'P-Parametri'!$B$14*('P-Parametri'!$B$7-(($L$7*(1-'P-Parametri'!$B$22))+0))/'P-Parametri'!$C$14,0))))-(IF(($L$7*(1-'P-Parametri'!$B$22))>0,IF((($L$7*(1-'P-Parametri'!$B$22))+0)<='P-Parametri'!$C$21,0,IF((($L$7*(1-'P-Parametri'!$B$22))+0)<='P-Parametri'!$D$21,'P-Parametri'!$B$21,IF((($L$7*(1-'P-Parametri'!$B$22))+0)<'P-Parametri'!$E$21,'P-Parametri'!$B$21*('P-Parametri'!$E$21-(($L$7*(1-'P-Parametri'!$B$22))+0))/('P-Parametri'!$E$21-'P-Parametri'!$D$21),0))),0))))-(IF(MAX(0,(IF((($L$7*(1-'P-Parametri'!$B$22))+0)<='P-Parametri'!$B$6,'P-Parametri'!$C$6*(($L$7*(1-'P-Parametri'!$B$22))+0),IF((($L$7*(1-'P-Parametri'!$B$22))+0)<='P-Parametri'!$B$7,'P-Parametri'!$B$9+'P-Parametri'!$C$7*((($L$7*(1-'P-Parametri'!$B$22))+0)-'P-Parametri'!$B$6),'P-Parametri'!$B$10+'P-Parametri'!$C$8*((($L$7*(1-'P-Parametri'!$B$22))+0)-'P-Parametri'!$B$7))))-(IF((($L$7*(1-'P-Parametri'!$B$22))+0)<='P-Parametri'!$C$12,'P-Parametri'!$B$12,IF((($L$7*(1-'P-Parametri'!$B$22))+0)<='P-Parametri'!$B$6,'P-Parametri'!$B$13+'P-Parametri'!$C$13*('P-Parametri'!$B$6-(($L$7*(1-'P-Parametri'!$B$22))+0))/'P-Parametri'!$D$13,IF((($L$7*(1-'P-Parametri'!$B$22))+0)<='P-Parametri'!$B$7,'P-Parametri'!$B$14*('P-Parametri'!$B$7-(($L$7*(1-'P-Parametri'!$B$22))+0))/'P-Parametri'!$C$14,0))))-(IF(($L$7*(1-'P-Parametri'!$B$22))>0,IF((($L$7*(1-'P-Parametri'!$B$22))+0)<='P-Parametri'!$C$21,0,IF((($L$7*(1-'P-Parametri'!$B$22))+0)<='P-Parametri'!$D$21,'P-Parametri'!$B$21,IF((($L$7*(1-'P-Parametri'!$B$22))+0)<'P-Parametri'!$E$21,'P-Parametri'!$B$21*('P-Parametri'!$E$21-(($L$7*(1-'P-Parametri'!$B$22))+0))/('P-Parametri'!$E$21-'P-Parametri'!$D$21),0))),0)))>0,'P-Parametri'!$B$11*(($L$7*(1-'P-Parametri'!$B$22))+0),0))+(IF(AND((($L$7*(1-'P-Parametri'!$B$22))+0)<='P-Parametri'!$C$18,(IF((($L$7*(1-'P-Parametri'!$B$22))+0)<='P-Parametri'!$B$6,'P-Parametri'!$C$6*(($L$7*(1-'P-Parametri'!$B$22))+0),IF((($L$7*(1-'P-Parametri'!$B$22))+0)<='P-Parametri'!$B$7,'P-Parametri'!$B$9+'P-Parametri'!$C$7*((($L$7*(1-'P-Parametri'!$B$22))+0)-'P-Parametri'!$B$6),'P-Parametri'!$B$10+'P-Parametri'!$C$8*((($L$7*(1-'P-Parametri'!$B$22))+0)-'P-Parametri'!$B$7))))>(IF((($L$7*(1-'P-Parametri'!$B$22))+0)<='P-Parametri'!$C$12,'P-Parametri'!$B$12,IF((($L$7*(1-'P-Parametri'!$B$22))+0)<='P-Parametri'!$B$6,'P-Parametri'!$B$13+'P-Parametri'!$C$13*('P-Parametri'!$B$6-(($L$7*(1-'P-Parametri'!$B$22))+0))/'P-Parametri'!$D$13,IF((($L$7*(1-'P-Parametri'!$B$22))+0)<='P-Parametri'!$B$7,'P-Parametri'!$B$14*('P-Parametri'!$B$7-(($L$7*(1-'P-Parametri'!$B$22))+0))/'P-Parametri'!$C$14,0))))-'P-Parametri'!$D$18),'P-Parametri'!$B$18,0))+(IF(($L$7*(1-'P-Parametri'!$B$22))>0,IF((($L$7*(1-'P-Parametri'!$B$22))+0)>'P-Parametri'!$D$20,0,IF((($L$7*(1-'P-Parametri'!$B$22))+0)<='P-Parametri'!$B$20,'P-Parametri'!$B$19*($L$7*(1-'P-Parametri'!$B$22)),IF((($L$7*(1-'P-Parametri'!$B$22))+0)<='P-Parametri'!$C$20,'P-Parametri'!$C$19*($L$7*(1-'P-Parametri'!$B$22)),'P-Parametri'!$D$19*($L$7*(1-'P-Parametri'!$B$22))))),0)) -> 19788.762 | O7: =(('P-Parametri'!$B$24*$L$7)*(1+'P-Parametri'!$B$26)^('1-Input'!$B$25-1-'1-Input'!$C$12+1)*(IF('P-Parametri'!$B$26=0,'1-Input'!$C$12,((1+'P-Parametri'!$B$26)^'1-Input'!$C$12-1)/'P-Parametri'!$B$26)))*'P-Parametri'!$B$27*(1-'P-Parametri'!$B$28) -> 3488.9271 | P7: ='M2-Motore-Chiusura'!$E$617 -> -1.564444e-09 | Q7: =IF(ABS(P7)<=1,"radice","GRADINO — la cella si chiude su uno scalino fiscale, non su una radice") -> radice
A8: r = 2% · crolli INIZIO | B8: ='M1-Motore-Griglia'!$B$301 -> 22621.704 | C8: ='M1-Motore-Griglia'!$B$1539 -> 67 | D8: ='1-Input'!$B$10-B8 -> 6378.2955 | E8: =D8/'1-Input'!$B$10 -> 0.21994123 | F8: ='M2-Motore-Chiusura'!$B$157 -> 42527.003 | G8: =F8/'1-Input'!$B$17 -> 1.2150572 | H8: =(($F$8*(1-'P-Parametri'!$B$22))+0)-(MAX(0,(IF((($F$8*(1-'P-Parametri'!$B$22))+0)<='P-Parametri'!$B$6,'P-Parametri'!$C$6*(($F$8*(1-'P-Parametri'!$B$22))+0),IF((($F$8*(1-'P-Parametri'!$B$22))+0)<='P-Parametri'!$B$7,'P-Parametri'!$B$9+'P-Parametri'!$C$7*((($F$8*(1-'P-Parametri'!$B$22))+0)-'P-Parametri'!$B$6),'P-Parametri'!$B$10+'P-Parametri'!$C$8*((($F$8*(1-'P-Parametri'!$B$22))+0)-'P-Parametri'!$B$7))))-(IF((($F$8*(1-'P-Parametri'!$B$22))+0)<='P-Parametri'!$C$12,'P-Parametri'!$B$12,IF((($F$8*(1-'P-Parametri'!$B$22))+0)<='P-Parametri'!$B$6,'P-Parametri'!$B$13+'P-Parametri'!$C$13*('P-Parametri'!$B$6-(($F$8*(1-'P-Parametri'!$B$22))+0))/'P-Parametri'!$D$13,IF((($F$8*(1-'P-Parametri'!$B$22))+0)<='P-Parametri'!$B$7,'P-Parametri'!$B$14*('P-Parametri'!$B$7-(($F$8*(1-'P-Parametri'!$B$22))+0))/'P-Parametri'!$C$14,0))))-(IF(($F$8*(1-'P-Parametri'!$B$22))>0,IF((($F$8*(1-'P-Parametri'!$B$22))+0)<='P-Parametri'!$C$21,0,IF((($F$8*(1-'P-Parametri'!$B$22))+0)<='P-Parametri'!$D$21,'P-Parametri'!$B$21,IF((($F$8*(1-'P-Parametri'!$B$22))+0)<'P-Parametri'!$E$21,'P-Parametri'!$B$21*('P-Parametri'!$E$21-(($F$8*(1-'P-Parametri'!$B$22))+0))/('P-Parametri'!$E$21-'P-Parametri'!$D$21),0))),0))))-(IF(MAX(0,(IF((($F$8*(1-'P-Parametri'!$B$22))+0)<='P-Parametri'!$B$6,'P-Parametri'!$C$6*(($F$8*(1-'P-Parametri'!$B$22))+0),IF((($F$8*(1-'P-Parametri'!$B$22))+0)<='P-Parametri'!$B$7,'P-Parametri'!$B$9+'P-Parametri'!$C$7*((($F$8*(1-'P-Parametri'!$B$22))+0)-'P-Parametri'!$B$6),'P-Parametri'!$B$10+'P-Parametri'!$C$8*((($F$8*(1-'P-Parametri'!$B$22))+0)-'P-Parametri'!$B$7))))-(IF((($F$8*(1-'P-Parametri'!$B$22))+0)<='P-Parametri'!$C$12,'P-Parametri'!$B$12,IF((($F$8*(1-'P-Parametri'!$B$22))+0)<='P-Parametri'!$B$6,'P-Parametri'!$B$13+'P-Parametri'!$C$13*('P-Parametri'!$B$6-(($F$8*(1-'P-Parametri'!$B$22))+0))/'P-Parametri'!$D$13,IF((($F$8*(1-'P-Parametri'!$B$22))+0)<='P-Parametri'!$B$7,'P-Parametri'!$B$14*('P-Parametri'!$B$7-(($F$8*(1-'P-Parametri'!$B$22))+0))/'P-Parametri'!$C$14,0))))-(IF(($F$8*(1-'P-Parametri'!$B$22))>0,IF((($F$8*(1-'P-Parametri'!$B$22))+0)<='P-Parametri'!$C$21,0,IF((($F$8*(1-'P-Parametri'!$B$22))+0)<='P-Parametri'!$D$21,'P-Parametri'!$B$21,IF((($F$8*(1-'P-Parametri'!$B$22))+0)<'P-Parametri'!$E$21,'P-Parametri'!$B$21*('P-Parametri'!$E$21-(($F$8*(1-'P-Parametri'!$B$22))+0))/('P-Parametri'!$E$21-'P-Parametri'!$D$21),0))),0)))>0,'P-Parametri'!$B$11*(($F$8*(1-'P-Parametri'!$B$22))+0),0))+(IF(AND((($F$8*(1-'P-Parametri'!$B$22))+0)<='P-Parametri'!$C$18,(IF((($F$8*(1-'P-Parametri'!$B$22))+0)<='P-Parametri'!$B$6,'P-Parametri'!$C$6*(($F$8*(1-'P-Parametri'!$B$22))+0),IF((($F$8*(1-'P-Parametri'!$B$22))+0)<='P-Parametri'!$B$7,'P-Parametri'!$B$9+'P-Parametri'!$C$7*((($F$8*(1-'P-Parametri'!$B$22))+0)-'P-Parametri'!$B$6),'P-Parametri'!$B$10+'P-Parametri'!$C$8*((($F$8*(1-'P-Parametri'!$B$22))+0)-'P-Parametri'!$B$7))))>(IF((($F$8*(1-'P-Parametri'!$B$22))+0)<='P-Parametri'!$C$12,'P-Parametri'!$B$12,IF((($F$8*(1-'P-Parametri'!$B$22))+0)<='P-Parametri'!$B$6,'P-Parametri'!$B$13+'P-Parametri'!$C$13*('P-Parametri'!$B$6-(($F$8*(1-'P-Parametri'!$B$22))+0))/'P-Parametri'!$D$13,IF((($F$8*(1-'P-Parametri'!$B$22))+0)<='P-Parametri'!$B$7,'P-Parametri'!$B$14*('P-Parametri'!$B$7-(($F$8*(1-'P-Parametri'!$B$22))+0))/'P-Parametri'!$C$14,0))))-'P-Parametri'!$D$18),'P-Parametri'!$B$18,0))+(IF(($F$8*(1-'P-Parametri'!$B$22))>0,IF((($F$8*(1-'P-Parametri'!$B$22))+0)>'P-Parametri'!$D$20,0,IF((($F$8*(1-'P-Parametri'!$B$22))+0)<='P-Parametri'!$B$20,'P-Parametri'!$B$19*($F$8*(1-'P-Parametri'!$B$22)),IF((($F$8*(1-'P-Parametri'!$B$22))+0)<='P-Parametri'!$C$20,'P-Parametri'!$C$19*($F$8*(1-'P-Parametri'!$B$22)),'P-Parametri'!$D$19*($F$8*(1-'P-Parametri'!$B$22))))),0)) -> 29062.952 | I8: =(('P-Parametri'!$B$24*$F$8)*(1+'P-Parametri'!$B$26)^('1-Input'!$B$25-1-'1-Input'!$B$12+1)*(IF('P-Parametri'!$B$26=0,'1-Input'!$B$12,((1+'P-Parametri'!$B$26)^'1-Input'!$B$12-1)/'P-Parametri'!$B$26)))*'P-Parametri'!$B$27*(1-'P-Parametri'!$B$28) -> 3145.0317 | J8: ='M2-Motore-Chiusura'!$E$665 -> 1.2736131e-09 | K8: =IF(ABS(J8)<=1,"radice","GRADINO — la cella si chiude su uno scalino fiscale, non su una radice") -> radice | L8: ='M2-Motore-Chiusura'!$B$209 -> 17034.481 | M8: =L8/'1-Input'!$B$17 -> 0.48669946 | N8: =(($L$8*(1-'P-Parametri'!$B$22))+0)-(MAX(0,(IF((($L$8*(1-'P-Parametri'!$B$22))+0)<='P-Parametri'!$B$6,'P-Parametri'!$C$6*(($L$8*(1-'P-Parametri'!$B$22))+0),IF((($L$8*(1-'P-Parametri'!$B$22))+0)<='P-Parametri'!$B$7,'P-Parametri'!$B$9+'P-Parametri'!$C$7*((($L$8*(1-'P-Parametri'!$B$22))+0)-'P-Parametri'!$B$6),'P-Parametri'!$B$10+'P-Parametri'!$C$8*((($L$8*(1-'P-Parametri'!$B$22))+0)-'P-Parametri'!$B$7))))-(IF((($L$8*(1-'P-Parametri'!$B$22))+0)<='P-Parametri'!$C$12,'P-Parametri'!$B$12,IF((($L$8*(1-'P-Parametri'!$B$22))+0)<='P-Parametri'!$B$6,'P-Parametri'!$B$13+'P-Parametri'!$C$13*('P-Parametri'!$B$6-(($L$8*(1-'P-Parametri'!$B$22))+0))/'P-Parametri'!$D$13,IF((($L$8*(1-'P-Parametri'!$B$22))+0)<='P-Parametri'!$B$7,'P-Parametri'!$B$14*('P-Parametri'!$B$7-(($L$8*(1-'P-Parametri'!$B$22))+0))/'P-Parametri'!$C$14,0))))-(IF(($L$8*(1-'P-Parametri'!$B$22))>0,IF((($L$8*(1-'P-Parametri'!$B$22))+0)<='P-Parametri'!$C$21,0,IF((($L$8*(1-'P-Parametri'!$B$22))+0)<='P-Parametri'!$D$21,'P-Parametri'!$B$21,IF((($L$8*(1-'P-Parametri'!$B$22))+0)<'P-Parametri'!$E$21,'P-Parametri'!$B$21*('P-Parametri'!$E$21-(($L$8*(1-'P-Parametri'!$B$22))+0))/('P-Parametri'!$E$21-'P-Parametri'!$D$21),0))),0))))-(IF(MAX(0,(IF((($L$8*(1-'P-Parametri'!$B$22))+0)<='P-Parametri'!$B$6,'P-Parametri'!$C$6*(($L$8*(1-'P-Parametri'!$B$22))+0),IF((($L$8*(1-'P-Parametri'!$B$22))+0)<='P-Parametri'!$B$7,'P-Parametri'!$B$9+'P-Parametri'!$C$7*((($L$8*(1-'P-Parametri'!$B$22))+0)-'P-Parametri'!$B$6),'P-Parametri'!$B$10+'P-Parametri'!$C$8*((($L$8*(1-'P-Parametri'!$B$22))+0)-'P-Parametri'!$B$7))))-(IF((($L$8*(1-'P-Parametri'!$B$22))+0)<='P-Parametri'!$C$12,'P-Parametri'!$B$12,IF((($L$8*(1-'P-Parametri'!$B$22))+0)<='P-Parametri'!$B$6,'P-Parametri'!$B$13+'P-Parametri'!$C$13*('P-Parametri'!$B$6-(($L$8*(1-'P-Parametri'!$B$22))+0))/'P-Parametri'!$D$13,IF((($L$8*(1-'P-Parametri'!$B$22))+0)<='P-Parametri'!$B$7,'P-Parametri'!$B$14*('P-Parametri'!$B$7-(($L$8*(1-'P-Parametri'!$B$22))+0))/'P-Parametri'!$C$14,0))))-(IF(($L$8*(1-'P-Parametri'!$B$22))>0,IF((($L$8*(1-'P-Parametri'!$B$22))+0)<='P-Parametri'!$C$21,0,IF((($L$8*(1-'P-Parametri'!$B$22))+0)<='P-Parametri'!$D$21,'P-Parametri'!$B$21,IF((($L$8*(1-'P-Parametri'!$B$22))+0)<'P-Parametri'!$E$21,'P-Parametri'!$B$21*('P-Parametri'!$E$21-(($L$8*(1-'P-Parametri'!$B$22))+0))/('P-Parametri'!$E$21-'P-Parametri'!$D$21),0))),0)))>0,'P-Parametri'!$B$11*(($L$8*(1-'P-Parametri'!$B$22))+0),0))+(IF(AND((($L$8*(1-'P-Parametri'!$B$22))+0)<='P-Parametri'!$C$18,(IF((($L$8*(1-'P-Parametri'!$B$22))+0)<='P-Parametri'!$B$6,'P-Parametri'!$C$6*(($L$8*(1-'P-Parametri'!$B$22))+0),IF((($L$8*(1-'P-Parametri'!$B$22))+0)<='P-Parametri'!$B$7,'P-Parametri'!$B$9+'P-Parametri'!$C$7*((($L$8*(1-'P-Parametri'!$B$22))+0)-'P-Parametri'!$B$6),'P-Parametri'!$B$10+'P-Parametri'!$C$8*((($L$8*(1-'P-Parametri'!$B$22))+0)-'P-Parametri'!$B$7))))>(IF((($L$8*(1-'P-Parametri'!$B$22))+0)<='P-Parametri'!$C$12,'P-Parametri'!$B$12,IF((($L$8*(1-'P-Parametri'!$B$22))+0)<='P-Parametri'!$B$6,'P-Parametri'!$B$13+'P-Parametri'!$C$13*('P-Parametri'!$B$6-(($L$8*(1-'P-Parametri'!$B$22))+0))/'P-Parametri'!$D$13,IF((($L$8*(1-'P-Parametri'!$B$22))+0)<='P-Parametri'!$B$7,'P-Parametri'!$B$14*('P-Parametri'!$B$7-(($L$8*(1-'P-Parametri'!$B$22))+0))/'P-Parametri'!$C$14,0))))-'P-Parametri'!$D$18),'P-Parametri'!$B$18,0))+(IF(($L$8*(1-'P-Parametri'!$B$22))>0,IF((($L$8*(1-'P-Parametri'!$B$22))+0)>'P-Parametri'!$D$20,0,IF((($L$8*(1-'P-Parametri'!$B$22))+0)<='P-Parametri'!$B$20,'P-Parametri'!$B$19*($L$8*(1-'P-Parametri'!$B$22)),IF((($L$8*(1-'P-Parametri'!$B$22))+0)<='P-Parametri'!$C$20,'P-Parametri'!$C$19*($L$8*(1-'P-Parametri'!$B$22)),'P-Parametri'!$D$19*($L$8*(1-'P-Parametri'!$B$22))))),0)) -> 15401.339 | O8: =(('P-Parametri'!$B$24*$L$8)*(1+'P-Parametri'!$B$26)^('1-Input'!$B$25-1-'1-Input'!$C$12+1)*(IF('P-Parametri'!$B$26=0,'1-Input'!$C$12,((1+'P-Parametri'!$B$26)^'1-Input'!$C$12-1)/'P-Parametri'!$B$26)))*'P-Parametri'!$B$27*(1-'P-Parametri'!$B$28) -> 2482.4057 | P8: ='M2-Motore-Chiusura'!$E$713 -> 3.0144688e-11 | Q8: =IF(ABS(P8)<=1,"radice","GRADINO — la cella si chiude su uno scalino fiscale, non su una radice") -> radice
A9: r = 3% · crolli INIZIO | B9: ='M1-Motore-Griglia'!$B$501 -> 24119.551 | C9: ='M1-Motore-Griglia'!$B$1731 -> 69 | D9: ='1-Input'!$B$10-B9 -> 4880.4491 | E9: =D9/'1-Input'!$B$10 -> 0.16829135 | F9: ='M2-Motore-Chiusura'!$B$261 -> 26242.12 | G9: =F9/'1-Input'!$B$17 -> 0.74977485 | H9: =(($F$9*(1-'P-Parametri'!$B$22))+0)-(MAX(0,(IF((($F$9*(1-'P-Parametri'!$B$22))+0)<='P-Parametri'!$B$6,'P-Parametri'!$C$6*(($F$9*(1-'P-Parametri'!$B$22))+0),IF((($F$9*(1-'P-Parametri'!$B$22))+0)<='P-Parametri'!$B$7,'P-Parametri'!$B$9+'P-Parametri'!$C$7*((($F$9*(1-'P-Parametri'!$B$22))+0)-'P-Parametri'!$B$6),'P-Parametri'!$B$10+'P-Parametri'!$C$8*((($F$9*(1-'P-Parametri'!$B$22))+0)-'P-Parametri'!$B$7))))-(IF((($F$9*(1-'P-Parametri'!$B$22))+0)<='P-Parametri'!$C$12,'P-Parametri'!$B$12,IF((($F$9*(1-'P-Parametri'!$B$22))+0)<='P-Parametri'!$B$6,'P-Parametri'!$B$13+'P-Parametri'!$C$13*('P-Parametri'!$B$6-(($F$9*(1-'P-Parametri'!$B$22))+0))/'P-Parametri'!$D$13,IF((($F$9*(1-'P-Parametri'!$B$22))+0)<='P-Parametri'!$B$7,'P-Parametri'!$B$14*('P-Parametri'!$B$7-(($F$9*(1-'P-Parametri'!$B$22))+0))/'P-Parametri'!$C$14,0))))-(IF(($F$9*(1-'P-Parametri'!$B$22))>0,IF((($F$9*(1-'P-Parametri'!$B$22))+0)<='P-Parametri'!$C$21,0,IF((($F$9*(1-'P-Parametri'!$B$22))+0)<='P-Parametri'!$D$21,'P-Parametri'!$B$21,IF((($F$9*(1-'P-Parametri'!$B$22))+0)<'P-Parametri'!$E$21,'P-Parametri'!$B$21*('P-Parametri'!$E$21-(($F$9*(1-'P-Parametri'!$B$22))+0))/('P-Parametri'!$E$21-'P-Parametri'!$D$21),0))),0))))-(IF(MAX(0,(IF((($F$9*(1-'P-Parametri'!$B$22))+0)<='P-Parametri'!$B$6,'P-Parametri'!$C$6*(($F$9*(1-'P-Parametri'!$B$22))+0),IF((($F$9*(1-'P-Parametri'!$B$22))+0)<='P-Parametri'!$B$7,'P-Parametri'!$B$9+'P-Parametri'!$C$7*((($F$9*(1-'P-Parametri'!$B$22))+0)-'P-Parametri'!$B$6),'P-Parametri'!$B$10+'P-Parametri'!$C$8*((($F$9*(1-'P-Parametri'!$B$22))+0)-'P-Parametri'!$B$7))))-(IF((($F$9*(1-'P-Parametri'!$B$22))+0)<='P-Parametri'!$C$12,'P-Parametri'!$B$12,IF((($F$9*(1-'P-Parametri'!$B$22))+0)<='P-Parametri'!$B$6,'P-Parametri'!$B$13+'P-Parametri'!$C$13*('P-Parametri'!$B$6-(($F$9*(1-'P-Parametri'!$B$22))+0))/'P-Parametri'!$D$13,IF((($F$9*(1-'P-Parametri'!$B$22))+0)<='P-Parametri'!$B$7,'P-Parametri'!$B$14*('P-Parametri'!$B$7-(($F$9*(1-'P-Parametri'!$B$22))+0))/'P-Parametri'!$C$14,0))))-(IF(($F$9*(1-'P-Parametri'!$B$22))>0,IF((($F$9*(1-'P-Parametri'!$B$22))+0)<='P-Parametri'!$C$21,0,IF((($F$9*(1-'P-Parametri'!$B$22))+0)<='P-Parametri'!$D$21,'P-Parametri'!$B$21,IF((($F$9*(1-'P-Parametri'!$B$22))+0)<'P-Parametri'!$E$21,'P-Parametri'!$B$21*('P-Parametri'!$E$21-(($F$9*(1-'P-Parametri'!$B$22))+0))/('P-Parametri'!$E$21-'P-Parametri'!$D$21),0))),0)))>0,'P-Parametri'!$B$11*(($F$9*(1-'P-Parametri'!$B$22))+0),0))+(IF(AND((($F$9*(1-'P-Parametri'!$B$22))+0)<='P-Parametri'!$C$18,(IF((($F$9*(1-'P-Parametri'!$B$22))+0)<='P-Parametri'!$B$6,'P-Parametri'!$C$6*(($F$9*(1-'P-Parametri'!$B$22))+0),IF((($F$9*(1-'P-Parametri'!$B$22))+0)<='P-Parametri'!$B$7,'P-Parametri'!$B$9+'P-Parametri'!$C$7*((($F$9*(1-'P-Parametri'!$B$22))+0)-'P-Parametri'!$B$6),'P-Parametri'!$B$10+'P-Parametri'!$C$8*((($F$9*(1-'P-Parametri'!$B$22))+0)-'P-Parametri'!$B$7))))>(IF((($F$9*(1-'P-Parametri'!$B$22))+0)<='P-Parametri'!$C$12,'P-Parametri'!$B$12,IF((($F$9*(1-'P-Parametri'!$B$22))+0)<='P-Parametri'!$B$6,'P-Parametri'!$B$13+'P-Parametri'!$C$13*('P-Parametri'!$B$6-(($F$9*(1-'P-Parametri'!$B$22))+0))/'P-Parametri'!$D$13,IF((($F$9*(1-'P-Parametri'!$B$22))+0)<='P-Parametri'!$B$7,'P-Parametri'!$B$14*('P-Parametri'!$B$7-(($F$9*(1-'P-Parametri'!$B$22))+0))/'P-Parametri'!$C$14,0))))-'P-Parametri'!$D$18),'P-Parametri'!$B$18,0))+(IF(($F$9*(1-'P-Parametri'!$B$22))>0,IF((($F$9*(1-'P-Parametri'!$B$22))+0)>'P-Parametri'!$D$20,0,IF((($F$9*(1-'P-Parametri'!$B$22))+0)<='P-Parametri'!$B$20,'P-Parametri'!$B$19*($F$9*(1-'P-Parametri'!$B$22)),IF((($F$9*(1-'P-Parametri'!$B$22))+0)<='P-Parametri'!$C$20,'P-Parametri'!$C$19*($F$9*(1-'P-Parametri'!$B$22)),'P-Parametri'!$D$19*($F$9*(1-'P-Parametri'!$B$22))))),0)) -> 21164.524 | I9: =(('P-Parametri'!$B$24*$F$9)*(1+'P-Parametri'!$B$26)^('1-Input'!$B$25-1-'1-Input'!$B$12+1)*(IF('P-Parametri'!$B$26=0,'1-Input'!$B$12,((1+'P-Parametri'!$B$26)^'1-Input'!$B$12-1)/'P-Parametri'!$B$26)))*'P-Parametri'!$B$27*(1-'P-Parametri'!$B$28) -> 1940.7034 | J9: ='M2-Motore-Chiusura'!$E$761 -> 3.6546092e-10 | K9: =IF(ABS(J9)<=1,"radice","GRADINO — la cella si chiude su uno scalino fiscale, non su una radice") -> radice | L9: ='M2-Motore-Chiusura'!$B$313 -> 11028.517 | M9: =L9/'1-Input'!$B$17 -> 0.3151005 | N9: =(($L$9*(1-'P-Parametri'!$B$22))+0)-(MAX(0,(IF((($L$9*(1-'P-Parametri'!$B$22))+0)<='P-Parametri'!$B$6,'P-Parametri'!$C$6*(($L$9*(1-'P-Parametri'!$B$22))+0),IF((($L$9*(1-'P-Parametri'!$B$22))+0)<='P-Parametri'!$B$7,'P-Parametri'!$B$9+'P-Parametri'!$C$7*((($L$9*(1-'P-Parametri'!$B$22))+0)-'P-Parametri'!$B$6),'P-Parametri'!$B$10+'P-Parametri'!$C$8*((($L$9*(1-'P-Parametri'!$B$22))+0)-'P-Parametri'!$B$7))))-(IF((($L$9*(1-'P-Parametri'!$B$22))+0)<='P-Parametri'!$C$12,'P-Parametri'!$B$12,IF((($L$9*(1-'P-Parametri'!$B$22))+0)<='P-Parametri'!$B$6,'P-Parametri'!$B$13+'P-Parametri'!$C$13*('P-Parametri'!$B$6-(($L$9*(1-'P-Parametri'!$B$22))+0))/'P-Parametri'!$D$13,IF((($L$9*(1-'P-Parametri'!$B$22))+0)<='P-Parametri'!$B$7,'P-Parametri'!$B$14*('P-Parametri'!$B$7-(($L$9*(1-'P-Parametri'!$B$22))+0))/'P-Parametri'!$C$14,0))))-(IF(($L$9*(1-'P-Parametri'!$B$22))>0,IF((($L$9*(1-'P-Parametri'!$B$22))+0)<='P-Parametri'!$C$21,0,IF((($L$9*(1-'P-Parametri'!$B$22))+0)<='P-Parametri'!$D$21,'P-Parametri'!$B$21,IF((($L$9*(1-'P-Parametri'!$B$22))+0)<'P-Parametri'!$E$21,'P-Parametri'!$B$21*('P-Parametri'!$E$21-(($L$9*(1-'P-Parametri'!$B$22))+0))/('P-Parametri'!$E$21-'P-Parametri'!$D$21),0))),0))))-(IF(MAX(0,(IF((($L$9*(1-'P-Parametri'!$B$22))+0)<='P-Parametri'!$B$6,'P-Parametri'!$C$6*(($L$9*(1-'P-Parametri'!$B$22))+0),IF((($L$9*(1-'P-Parametri'!$B$22))+0)<='P-Parametri'!$B$7,'P-Parametri'!$B$9+'P-Parametri'!$C$7*((($L$9*(1-'P-Parametri'!$B$22))+0)-'P-Parametri'!$B$6),'P-Parametri'!$B$10+'P-Parametri'!$C$8*((($L$9*(1-'P-Parametri'!$B$22))+0)-'P-Parametri'!$B$7))))-(IF((($L$9*(1-'P-Parametri'!$B$22))+0)<='P-Parametri'!$C$12,'P-Parametri'!$B$12,IF((($L$9*(1-'P-Parametri'!$B$22))+0)<='P-Parametri'!$B$6,'P-Parametri'!$B$13+'P-Parametri'!$C$13*('P-Parametri'!$B$6-(($L$9*(1-'P-Parametri'!$B$22))+0))/'P-Parametri'!$D$13,IF((($L$9*(1-'P-Parametri'!$B$22))+0)<='P-Parametri'!$B$7,'P-Parametri'!$B$14*('P-Parametri'!$B$7-(($L$9*(1-'P-Parametri'!$B$22))+0))/'P-Parametri'!$C$14,0))))-(IF(($L$9*(1-'P-Parametri'!$B$22))>0,IF((($L$9*(1-'P-Parametri'!$B$22))+0)<='P-Parametri'!$C$21,0,IF((($L$9*(1-'P-Parametri'!$B$22))+0)<='P-Parametri'!$D$21,'P-Parametri'!$B$21,IF((($L$9*(1-'P-Parametri'!$B$22))+0)<'P-Parametri'!$E$21,'P-Parametri'!$B$21*('P-Parametri'!$E$21-(($L$9*(1-'P-Parametri'!$B$22))+0))/('P-Parametri'!$E$21-'P-Parametri'!$D$21),0))),0)))>0,'P-Parametri'!$B$11*(($L$9*(1-'P-Parametri'!$B$22))+0),0))+(IF(AND((($L$9*(1-'P-Parametri'!$B$22))+0)<='P-Parametri'!$C$18,(IF((($L$9*(1-'P-Parametri'!$B$22))+0)<='P-Parametri'!$B$6,'P-Parametri'!$C$6*(($L$9*(1-'P-Parametri'!$B$22))+0),IF((($L$9*(1-'P-Parametri'!$B$22))+0)<='P-Parametri'!$B$7,'P-Parametri'!$B$9+'P-Parametri'!$C$7*((($L$9*(1-'P-Parametri'!$B$22))+0)-'P-Parametri'!$B$6),'P-Parametri'!$B$10+'P-Parametri'!$C$8*((($L$9*(1-'P-Parametri'!$B$22))+0)-'P-Parametri'!$B$7))))>(IF((($L$9*(1-'P-Parametri'!$B$22))+0)<='P-Parametri'!$C$12,'P-Parametri'!$B$12,IF((($L$9*(1-'P-Parametri'!$B$22))+0)<='P-Parametri'!$B$6,'P-Parametri'!$B$13+'P-Parametri'!$C$13*('P-Parametri'!$B$6-(($L$9*(1-'P-Parametri'!$B$22))+0))/'P-Parametri'!$D$13,IF((($L$9*(1-'P-Parametri'!$B$22))+0)<='P-Parametri'!$B$7,'P-Parametri'!$B$14*('P-Parametri'!$B$7-(($L$9*(1-'P-Parametri'!$B$22))+0))/'P-Parametri'!$C$14,0))))-'P-Parametri'!$D$18),'P-Parametri'!$B$18,0))+(IF(($L$9*(1-'P-Parametri'!$B$22))>0,IF((($L$9*(1-'P-Parametri'!$B$22))+0)>'P-Parametri'!$D$20,0,IF((($L$9*(1-'P-Parametri'!$B$22))+0)<='P-Parametri'!$B$20,'P-Parametri'!$B$19*($L$9*(1-'P-Parametri'!$B$22)),IF((($L$9*(1-'P-Parametri'!$B$22))+0)<='P-Parametri'!$C$20,'P-Parametri'!$C$19*($L$9*(1-'P-Parametri'!$B$22)),'P-Parametri'!$D$19*($L$9*(1-'P-Parametri'!$B$22))))),0)) -> 11197.042 | O9: =(('P-Parametri'!$B$24*$L$9)*(1+'P-Parametri'!$B$26)^('1-Input'!$B$25-1-'1-Input'!$C$12+1)*(IF('P-Parametri'!$B$26=0,'1-Input'!$C$12,((1+'P-Parametri'!$B$26)^'1-Input'!$C$12-1)/'P-Parametri'!$B$26)))*'P-Parametri'!$B$27*(1-'P-Parametri'!$B$28) -> 1607.167 | P9: ='M2-Motore-Chiusura'!$E$809 -> -1.0468933e-10 | Q9: =IF(ABS(P9)<=1,"radice","GRADINO — la cella si chiude su uno scalino fiscale, non su una radice") -> radice
A10: r = 1% · costante | B10: ='M1-Motore-Griglia'!$B$51 -> 27451.637 | C10: ='M1-Motore-Griglia'!$B$1299 -> 86 | D10: ='1-Input'!$B$10-B10 -> 1548.3625 | E10: =D10/'1-Input'!$B$10 -> 0.053391811 | F10: ='M2-Motore-Chiusura'!$B$365 -> 9185.5708 | G10: =F10/'1-Input'!$B$17 -> 0.26244488 | H10: =(($F$10*(1-'P-Parametri'!$B$22))+0)-(MAX(0,(IF((($F$10*(1-'P-Parametri'!$B$22))+0)<='P-Parametri'!$B$6,'P-Parametri'!$C$6*(($F$10*(1-'P-Parametri'!$B$22))+0),IF((($F$10*(1-'P-Parametri'!$B$22))+0)<='P-Parametri'!$B$7,'P-Parametri'!$B$9+'P-Parametri'!$C$7*((($F$10*(1-'P-Parametri'!$B$22))+0)-'P-Parametri'!$B$6),'P-Parametri'!$B$10+'P-Parametri'!$C$8*((($F$10*(1-'P-Parametri'!$B$22))+0)-'P-Parametri'!$B$7))))-(IF((($F$10*(1-'P-Parametri'!$B$22))+0)<='P-Parametri'!$C$12,'P-Parametri'!$B$12,IF((($F$10*(1-'P-Parametri'!$B$22))+0)<='P-Parametri'!$B$6,'P-Parametri'!$B$13+'P-Parametri'!$C$13*('P-Parametri'!$B$6-(($F$10*(1-'P-Parametri'!$B$22))+0))/'P-Parametri'!$D$13,IF((($F$10*(1-'P-Parametri'!$B$22))+0)<='P-Parametri'!$B$7,'P-Parametri'!$B$14*('P-Parametri'!$B$7-(($F$10*(1-'P-Parametri'!$B$22))+0))/'P-Parametri'!$C$14,0))))-(IF(($F$10*(1-'P-Parametri'!$B$22))>0,IF((($F$10*(1-'P-Parametri'!$B$22))+0)<='P-Parametri'!$C$21,0,IF((($F$10*(1-'P-Parametri'!$B$22))+0)<='P-Parametri'!$D$21,'P-Parametri'!$B$21,IF((($F$10*(1-'P-Parametri'!$B$22))+0)<'P-Parametri'!$E$21,'P-Parametri'!$B$21*('P-Parametri'!$E$21-(($F$10*(1-'P-Parametri'!$B$22))+0))/('P-Parametri'!$E$21-'P-Parametri'!$D$21),0))),0))))-(IF(MAX(0,(IF((($F$10*(1-'P-Parametri'!$B$22))+0)<='P-Parametri'!$B$6,'P-Parametri'!$C$6*(($F$10*(1-'P-Parametri'!$B$22))+0),IF((($F$10*(1-'P-Parametri'!$B$22))+0)<='P-Parametri'!$B$7,'P-Parametri'!$B$9+'P-Parametri'!$C$7*((($F$10*(1-'P-Parametri'!$B$22))+0)-'P-Parametri'!$B$6),'P-Parametri'!$B$10+'P-Parametri'!$C$8*((($F$10*(1-'P-Parametri'!$B$22))+0)-'P-Parametri'!$B$7))))-(IF((($F$10*(1-'P-Parametri'!$B$22))+0)<='P-Parametri'!$C$12,'P-Parametri'!$B$12,IF((($F$10*(1-'P-Parametri'!$B$22))+0)<='P-Parametri'!$B$6,'P-Parametri'!$B$13+'P-Parametri'!$C$13*('P-Parametri'!$B$6-(($F$10*(1-'P-Parametri'!$B$22))+0))/'P-Parametri'!$D$13,IF((($F$10*(1-'P-Parametri'!$B$22))+0)<='P-Parametri'!$B$7,'P-Parametri'!$B$14*('P-Parametri'!$B$7-(($F$10*(1-'P-Parametri'!$B$22))+0))/'P-Parametri'!$C$14,0))))-(IF(($F$10*(1-'P-Parametri'!$B$22))>0,IF((($F$10*(1-'P-Parametri'!$B$22))+0)<='P-Parametri'!$C$21,0,IF((($F$10*(1-'P-Parametri'!$B$22))+0)<='P-Parametri'!$D$21,'P-Parametri'!$B$21,IF((($F$10*(1-'P-Parametri'!$B$22))+0)<'P-Parametri'!$E$21,'P-Parametri'!$B$21*('P-Parametri'!$E$21-(($F$10*(1-'P-Parametri'!$B$22))+0))/('P-Parametri'!$E$21-'P-Parametri'!$D$21),0))),0)))>0,'P-Parametri'!$B$11*(($F$10*(1-'P-Parametri'!$B$22))+0),0))+(IF(AND((($F$10*(1-'P-Parametri'!$B$22))+0)<='P-Parametri'!$C$18,(IF((($F$10*(1-'P-Parametri'!$B$22))+0)<='P-Parametri'!$B$6,'P-Parametri'!$C$6*(($F$10*(1-'P-Parametri'!$B$22))+0),IF((($F$10*(1-'P-Parametri'!$B$22))+0)<='P-Parametri'!$B$7,'P-Parametri'!$B$9+'P-Parametri'!$C$7*((($F$10*(1-'P-Parametri'!$B$22))+0)-'P-Parametri'!$B$6),'P-Parametri'!$B$10+'P-Parametri'!$C$8*((($F$10*(1-'P-Parametri'!$B$22))+0)-'P-Parametri'!$B$7))))>(IF((($F$10*(1-'P-Parametri'!$B$22))+0)<='P-Parametri'!$C$12,'P-Parametri'!$B$12,IF((($F$10*(1-'P-Parametri'!$B$22))+0)<='P-Parametri'!$B$6,'P-Parametri'!$B$13+'P-Parametri'!$C$13*('P-Parametri'!$B$6-(($F$10*(1-'P-Parametri'!$B$22))+0))/'P-Parametri'!$D$13,IF((($F$10*(1-'P-Parametri'!$B$22))+0)<='P-Parametri'!$B$7,'P-Parametri'!$B$14*('P-Parametri'!$B$7-(($F$10*(1-'P-Parametri'!$B$22))+0))/'P-Parametri'!$C$14,0))))-'P-Parametri'!$D$18),'P-Parametri'!$B$18,0))+(IF(($F$10*(1-'P-Parametri'!$B$22))>0,IF((($F$10*(1-'P-Parametri'!$B$22))+0)>'P-Parametri'!$D$20,0,IF((($F$10*(1-'P-Parametri'!$B$22))+0)<='P-Parametri'!$B$20,'P-Parametri'!$B$19*($F$10*(1-'P-Parametri'!$B$22)),IF((($F$10*(1-'P-Parametri'!$B$22))+0)<='P-Parametri'!$C$20,'P-Parametri'!$C$19*($F$10*(1-'P-Parametri'!$B$22)),'P-Parametri'!$D$19*($F$10*(1-'P-Parametri'!$B$22))))),0)) -> 10133.657 | I10: =(('P-Parametri'!$B$24*$F$10)*(1+'P-Parametri'!$B$26)^('1-Input'!$B$25-1-'1-Input'!$B$12+1)*(IF('P-Parametri'!$B$26=0,'1-Input'!$B$12,((1+'P-Parametri'!$B$26)^'1-Input'!$B$12-1)/'P-Parametri'!$B$26)))*'P-Parametri'!$B$27*(1-'P-Parametri'!$B$28) -> 679.30749 | J10: ='M2-Motore-Chiusura'!$E$857 -> 8797.4379 | K10: =IF(ABS(J10)<=1,"radice","GRADINO — la cella si chiude su uno scalino fiscale, non su una radice") -> GRADINO — la cella si chiude su uno scalino fiscale, non su una radice | L10: ='M2-Motore-Chiusura'!$B$417 -> 4664.2884 | M10: =L10/'1-Input'!$B$17 -> 0.13326538 | N10: =(($L$10*(1-'P-Parametri'!$B$22))+0)-(MAX(0,(IF((($L$10*(1-'P-Parametri'!$B$22))+0)<='P-Parametri'!$B$6,'P-Parametri'!$C$6*(($L$10*(1-'P-Parametri'!$B$22))+0),IF((($L$10*(1-'P-Parametri'!$B$22))+0)<='P-Parametri'!$B$7,'P-Parametri'!$B$9+'P-Parametri'!$C$7*((($L$10*(1-'P-Parametri'!$B$22))+0)-'P-Parametri'!$B$6),'P-Parametri'!$B$10+'P-Parametri'!$C$8*((($L$10*(1-'P-Parametri'!$B$22))+0)-'P-Parametri'!$B$7))))-(IF((($L$10*(1-'P-Parametri'!$B$22))+0)<='P-Parametri'!$C$12,'P-Parametri'!$B$12,IF((($L$10*(1-'P-Parametri'!$B$22))+0)<='P-Parametri'!$B$6,'P-Parametri'!$B$13+'P-Parametri'!$C$13*('P-Parametri'!$B$6-(($L$10*(1-'P-Parametri'!$B$22))+0))/'P-Parametri'!$D$13,IF((($L$10*(1-'P-Parametri'!$B$22))+0)<='P-Parametri'!$B$7,'P-Parametri'!$B$14*('P-Parametri'!$B$7-(($L$10*(1-'P-Parametri'!$B$22))+0))/'P-Parametri'!$C$14,0))))-(IF(($L$10*(1-'P-Parametri'!$B$22))>0,IF((($L$10*(1-'P-Parametri'!$B$22))+0)<='P-Parametri'!$C$21,0,IF((($L$10*(1-'P-Parametri'!$B$22))+0)<='P-Parametri'!$D$21,'P-Parametri'!$B$21,IF((($L$10*(1-'P-Parametri'!$B$22))+0)<'P-Parametri'!$E$21,'P-Parametri'!$B$21*('P-Parametri'!$E$21-(($L$10*(1-'P-Parametri'!$B$22))+0))/('P-Parametri'!$E$21-'P-Parametri'!$D$21),0))),0))))-(IF(MAX(0,(IF((($L$10*(1-'P-Parametri'!$B$22))+0)<='P-Parametri'!$B$6,'P-Parametri'!$C$6*(($L$10*(1-'P-Parametri'!$B$22))+0),IF((($L$10*(1-'P-Parametri'!$B$22))+0)<='P-Parametri'!$B$7,'P-Parametri'!$B$9+'P-Parametri'!$C$7*((($L$10*(1-'P-Parametri'!$B$22))+0)-'P-Parametri'!$B$6),'P-Parametri'!$B$10+'P-Parametri'!$C$8*((($L$10*(1-'P-Parametri'!$B$22))+0)-'P-Parametri'!$B$7))))-(IF((($L$10*(1-'P-Parametri'!$B$22))+0)<='P-Parametri'!$C$12,'P-Parametri'!$B$12,IF((($L$10*(1-'P-Parametri'!$B$22))+0)<='P-Parametri'!$B$6,'P-Parametri'!$B$13+'P-Parametri'!$C$13*('P-Parametri'!$B$6-(($L$10*(1-'P-Parametri'!$B$22))+0))/'P-Parametri'!$D$13,IF((($L$10*(1-'P-Parametri'!$B$22))+0)<='P-Parametri'!$B$7,'P-Parametri'!$B$14*('P-Parametri'!$B$7-(($L$10*(1-'P-Parametri'!$B$22))+0))/'P-Parametri'!$C$14,0))))-(IF(($L$10*(1-'P-Parametri'!$B$22))>0,IF((($L$10*(1-'P-Parametri'!$B$22))+0)<='P-Parametri'!$C$21,0,IF((($L$10*(1-'P-Parametri'!$B$22))+0)<='P-Parametri'!$D$21,'P-Parametri'!$B$21,IF((($L$10*(1-'P-Parametri'!$B$22))+0)<'P-Parametri'!$E$21,'P-Parametri'!$B$21*('P-Parametri'!$E$21-(($L$10*(1-'P-Parametri'!$B$22))+0))/('P-Parametri'!$E$21-'P-Parametri'!$D$21),0))),0)))>0,'P-Parametri'!$B$11*(($L$10*(1-'P-Parametri'!$B$22))+0),0))+(IF(AND((($L$10*(1-'P-Parametri'!$B$22))+0)<='P-Parametri'!$C$18,(IF((($L$10*(1-'P-Parametri'!$B$22))+0)<='P-Parametri'!$B$6,'P-Parametri'!$C$6*(($L$10*(1-'P-Parametri'!$B$22))+0),IF((($L$10*(1-'P-Parametri'!$B$22))+0)<='P-Parametri'!$B$7,'P-Parametri'!$B$9+'P-Parametri'!$C$7*((($L$10*(1-'P-Parametri'!$B$22))+0)-'P-Parametri'!$B$6),'P-Parametri'!$B$10+'P-Parametri'!$C$8*((($L$10*(1-'P-Parametri'!$B$22))+0)-'P-Parametri'!$B$7))))>(IF((($L$10*(1-'P-Parametri'!$B$22))+0)<='P-Parametri'!$C$12,'P-Parametri'!$B$12,IF((($L$10*(1-'P-Parametri'!$B$22))+0)<='P-Parametri'!$B$6,'P-Parametri'!$B$13+'P-Parametri'!$C$13*('P-Parametri'!$B$6-(($L$10*(1-'P-Parametri'!$B$22))+0))/'P-Parametri'!$D$13,IF((($L$10*(1-'P-Parametri'!$B$22))+0)<='P-Parametri'!$B$7,'P-Parametri'!$B$14*('P-Parametri'!$B$7-(($L$10*(1-'P-Parametri'!$B$22))+0))/'P-Parametri'!$C$14,0))))-'P-Parametri'!$D$18),'P-Parametri'!$B$18,0))+(IF(($L$10*(1-'P-Parametri'!$B$22))>0,IF((($L$10*(1-'P-Parametri'!$B$22))+0)>'P-Parametri'!$D$20,0,IF((($L$10*(1-'P-Parametri'!$B$22))+0)<='P-Parametri'!$B$20,'P-Parametri'!$B$19*($L$10*(1-'P-Parametri'!$B$22)),IF((($L$10*(1-'P-Parametri'!$B$22))+0)<='P-Parametri'!$C$20,'P-Parametri'!$C$19*($L$10*(1-'P-Parametri'!$B$22)),'P-Parametri'!$D$19*($L$10*(1-'P-Parametri'!$B$22))))),0)) -> 4536.3707 | O10: =(('P-Parametri'!$B$24*$L$10)*(1+'P-Parametri'!$B$26)^('1-Input'!$B$25-1-'1-Input'!$C$12+1)*(IF('P-Parametri'!$B$26=0,'1-Input'!$C$12,((1+'P-Parametri'!$B$26)^'1-Input'!$C$12-1)/'P-Parametri'!$B$26)))*'P-Parametri'!$B$27*(1-'P-Parametri'!$B$28) -> 679.71875 | P10: ='M2-Motore-Chiusura'!$E$905 -> -7.8840712e-11 | Q10: =IF(ABS(P10)<=1,"radice","GRADINO — la cella si chiude su uno scalino fiscale, non su una radice") -> radice
A11: r = 1% · crolli METÀ | B11: ='M1-Motore-Griglia'!$B$151 -> 28180.139 | C11: ='M1-Motore-Griglia'!$B$1395 -> 89 | D11: ='1-Input'!$B$10-B11 -> 819.86135 | E11: =D11/'1-Input'!$B$10 -> 0.028271081 | F11: ='M2-Motore-Chiusura'!$B$469 -> 4868.3527 | G11: =F11/'1-Input'!$B$17 -> 0.13909579 | H11: =(($F$11*(1-'P-Parametri'!$B$22))+0)-(MAX(0,(IF((($F$11*(1-'P-Parametri'!$B$22))+0)<='P-Parametri'!$B$6,'P-Parametri'!$C$6*(($F$11*(1-'P-Parametri'!$B$22))+0),IF((($F$11*(1-'P-Parametri'!$B$22))+0)<='P-Parametri'!$B$7,'P-Parametri'!$B$9+'P-Parametri'!$C$7*((($F$11*(1-'P-Parametri'!$B$22))+0)-'P-Parametri'!$B$6),'P-Parametri'!$B$10+'P-Parametri'!$C$8*((($F$11*(1-'P-Parametri'!$B$22))+0)-'P-Parametri'!$B$7))))-(IF((($F$11*(1-'P-Parametri'!$B$22))+0)<='P-Parametri'!$C$12,'P-Parametri'!$B$12,IF((($F$11*(1-'P-Parametri'!$B$22))+0)<='P-Parametri'!$B$6,'P-Parametri'!$B$13+'P-Parametri'!$C$13*('P-Parametri'!$B$6-(($F$11*(1-'P-Parametri'!$B$22))+0))/'P-Parametri'!$D$13,IF((($F$11*(1-'P-Parametri'!$B$22))+0)<='P-Parametri'!$B$7,'P-Parametri'!$B$14*('P-Parametri'!$B$7-(($F$11*(1-'P-Parametri'!$B$22))+0))/'P-Parametri'!$C$14,0))))-(IF(($F$11*(1-'P-Parametri'!$B$22))>0,IF((($F$11*(1-'P-Parametri'!$B$22))+0)<='P-Parametri'!$C$21,0,IF((($F$11*(1-'P-Parametri'!$B$22))+0)<='P-Parametri'!$D$21,'P-Parametri'!$B$21,IF((($F$11*(1-'P-Parametri'!$B$22))+0)<'P-Parametri'!$E$21,'P-Parametri'!$B$21*('P-Parametri'!$E$21-(($F$11*(1-'P-Parametri'!$B$22))+0))/('P-Parametri'!$E$21-'P-Parametri'!$D$21),0))),0))))-(IF(MAX(0,(IF((($F$11*(1-'P-Parametri'!$B$22))+0)<='P-Parametri'!$B$6,'P-Parametri'!$C$6*(($F$11*(1-'P-Parametri'!$B$22))+0),IF((($F$11*(1-'P-Parametri'!$B$22))+0)<='P-Parametri'!$B$7,'P-Parametri'!$B$9+'P-Parametri'!$C$7*((($F$11*(1-'P-Parametri'!$B$22))+0)-'P-Parametri'!$B$6),'P-Parametri'!$B$10+'P-Parametri'!$C$8*((($F$11*(1-'P-Parametri'!$B$22))+0)-'P-Parametri'!$B$7))))-(IF((($F$11*(1-'P-Parametri'!$B$22))+0)<='P-Parametri'!$C$12,'P-Parametri'!$B$12,IF((($F$11*(1-'P-Parametri'!$B$22))+0)<='P-Parametri'!$B$6,'P-Parametri'!$B$13+'P-Parametri'!$C$13*('P-Parametri'!$B$6-(($F$11*(1-'P-Parametri'!$B$22))+0))/'P-Parametri'!$D$13,IF((($F$11*(1-'P-Parametri'!$B$22))+0)<='P-Parametri'!$B$7,'P-Parametri'!$B$14*('P-Parametri'!$B$7-(($F$11*(1-'P-Parametri'!$B$22))+0))/'P-Parametri'!$C$14,0))))-(IF(($F$11*(1-'P-Parametri'!$B$22))>0,IF((($F$11*(1-'P-Parametri'!$B$22))+0)<='P-Parametri'!$C$21,0,IF((($F$11*(1-'P-Parametri'!$B$22))+0)<='P-Parametri'!$D$21,'P-Parametri'!$B$21,IF((($F$11*(1-'P-Parametri'!$B$22))+0)<'P-Parametri'!$E$21,'P-Parametri'!$B$21*('P-Parametri'!$E$21-(($F$11*(1-'P-Parametri'!$B$22))+0))/('P-Parametri'!$E$21-'P-Parametri'!$D$21),0))),0)))>0,'P-Parametri'!$B$11*(($F$11*(1-'P-Parametri'!$B$22))+0),0))+(IF(AND((($F$11*(1-'P-Parametri'!$B$22))+0)<='P-Parametri'!$C$18,(IF((($F$11*(1-'P-Parametri'!$B$22))+0)<='P-Parametri'!$B$6,'P-Parametri'!$C$6*(($F$11*(1-'P-Parametri'!$B$22))+0),IF((($F$11*(1-'P-Parametri'!$B$22))+0)<='P-Parametri'!$B$7,'P-Parametri'!$B$9+'P-Parametri'!$C$7*((($F$11*(1-'P-Parametri'!$B$22))+0)-'P-Parametri'!$B$6),'P-Parametri'!$B$10+'P-Parametri'!$C$8*((($F$11*(1-'P-Parametri'!$B$22))+0)-'P-Parametri'!$B$7))))>(IF((($F$11*(1-'P-Parametri'!$B$22))+0)<='P-Parametri'!$C$12,'P-Parametri'!$B$12,IF((($F$11*(1-'P-Parametri'!$B$22))+0)<='P-Parametri'!$B$6,'P-Parametri'!$B$13+'P-Parametri'!$C$13*('P-Parametri'!$B$6-(($F$11*(1-'P-Parametri'!$B$22))+0))/'P-Parametri'!$D$13,IF((($F$11*(1-'P-Parametri'!$B$22))+0)<='P-Parametri'!$B$7,'P-Parametri'!$B$14*('P-Parametri'!$B$7-(($F$11*(1-'P-Parametri'!$B$22))+0))/'P-Parametri'!$C$14,0))))-'P-Parametri'!$D$18),'P-Parametri'!$B$18,0))+(IF(($F$11*(1-'P-Parametri'!$B$22))>0,IF((($F$11*(1-'P-Parametri'!$B$22))+0)>'P-Parametri'!$D$20,0,IF((($F$11*(1-'P-Parametri'!$B$22))+0)<='P-Parametri'!$B$20,'P-Parametri'!$B$19*($F$11*(1-'P-Parametri'!$B$22)),IF((($F$11*(1-'P-Parametri'!$B$22))+0)<='P-Parametri'!$C$20,'P-Parametri'!$C$19*($F$11*(1-'P-Parametri'!$B$22)),'P-Parametri'!$D$19*($F$11*(1-'P-Parametri'!$B$22))))),0)) -> 4734.8386 | I11: =(('P-Parametri'!$B$24*$F$11)*(1+'P-Parametri'!$B$26)^('1-Input'!$B$25-1-'1-Input'!$B$12+1)*(IF('P-Parametri'!$B$26=0,'1-Input'!$B$12,((1+'P-Parametri'!$B$26)^'1-Input'!$B$12-1)/'P-Parametri'!$B$26)))*'P-Parametri'!$B$27*(1-'P-Parametri'!$B$28) -> 360.03298 | J11: ='M2-Motore-Chiusura'!$E$953 -> 2.1070581e-10 | K11: =IF(ABS(J11)<=1,"radice","GRADINO — la cella si chiude su uno scalino fiscale, non su una radice") -> radice | L11: ='M2-Motore-Chiusura'!$B$521 -> 2533.409 | M11: =L11/'1-Input'!$B$17 -> 0.072383115 | N11: =(($L$11*(1-'P-Parametri'!$B$22))+0)-(MAX(0,(IF((($L$11*(1-'P-Parametri'!$B$22))+0)<='P-Parametri'!$B$6,'P-Parametri'!$C$6*(($L$11*(1-'P-Parametri'!$B$22))+0),IF((($L$11*(1-'P-Parametri'!$B$22))+0)<='P-Parametri'!$B$7,'P-Parametri'!$B$9+'P-Parametri'!$C$7*((($L$11*(1-'P-Parametri'!$B$22))+0)-'P-Parametri'!$B$6),'P-Parametri'!$B$10+'P-Parametri'!$C$8*((($L$11*(1-'P-Parametri'!$B$22))+0)-'P-Parametri'!$B$7))))-(IF((($L$11*(1-'P-Parametri'!$B$22))+0)<='P-Parametri'!$C$12,'P-Parametri'!$B$12,IF((($L$11*(1-'P-Parametri'!$B$22))+0)<='P-Parametri'!$B$6,'P-Parametri'!$B$13+'P-Parametri'!$C$13*('P-Parametri'!$B$6-(($L$11*(1-'P-Parametri'!$B$22))+0))/'P-Parametri'!$D$13,IF((($L$11*(1-'P-Parametri'!$B$22))+0)<='P-Parametri'!$B$7,'P-Parametri'!$B$14*('P-Parametri'!$B$7-(($L$11*(1-'P-Parametri'!$B$22))+0))/'P-Parametri'!$C$14,0))))-(IF(($L$11*(1-'P-Parametri'!$B$22))>0,IF((($L$11*(1-'P-Parametri'!$B$22))+0)<='P-Parametri'!$C$21,0,IF((($L$11*(1-'P-Parametri'!$B$22))+0)<='P-Parametri'!$D$21,'P-Parametri'!$B$21,IF((($L$11*(1-'P-Parametri'!$B$22))+0)<'P-Parametri'!$E$21,'P-Parametri'!$B$21*('P-Parametri'!$E$21-(($L$11*(1-'P-Parametri'!$B$22))+0))/('P-Parametri'!$E$21-'P-Parametri'!$D$21),0))),0))))-(IF(MAX(0,(IF((($L$11*(1-'P-Parametri'!$B$22))+0)<='P-Parametri'!$B$6,'P-Parametri'!$C$6*(($L$11*(1-'P-Parametri'!$B$22))+0),IF((($L$11*(1-'P-Parametri'!$B$22))+0)<='P-Parametri'!$B$7,'P-Parametri'!$B$9+'P-Parametri'!$C$7*((($L$11*(1-'P-Parametri'!$B$22))+0)-'P-Parametri'!$B$6),'P-Parametri'!$B$10+'P-Parametri'!$C$8*((($L$11*(1-'P-Parametri'!$B$22))+0)-'P-Parametri'!$B$7))))-(IF((($L$11*(1-'P-Parametri'!$B$22))+0)<='P-Parametri'!$C$12,'P-Parametri'!$B$12,IF((($L$11*(1-'P-Parametri'!$B$22))+0)<='P-Parametri'!$B$6,'P-Parametri'!$B$13+'P-Parametri'!$C$13*('P-Parametri'!$B$6-(($L$11*(1-'P-Parametri'!$B$22))+0))/'P-Parametri'!$D$13,IF((($L$11*(1-'P-Parametri'!$B$22))+0)<='P-Parametri'!$B$7,'P-Parametri'!$B$14*('P-Parametri'!$B$7-(($L$11*(1-'P-Parametri'!$B$22))+0))/'P-Parametri'!$C$14,0))))-(IF(($L$11*(1-'P-Parametri'!$B$22))>0,IF((($L$11*(1-'P-Parametri'!$B$22))+0)<='P-Parametri'!$C$21,0,IF((($L$11*(1-'P-Parametri'!$B$22))+0)<='P-Parametri'!$D$21,'P-Parametri'!$B$21,IF((($L$11*(1-'P-Parametri'!$B$22))+0)<'P-Parametri'!$E$21,'P-Parametri'!$B$21*('P-Parametri'!$E$21-(($L$11*(1-'P-Parametri'!$B$22))+0))/('P-Parametri'!$E$21-'P-Parametri'!$D$21),0))),0)))>0,'P-Parametri'!$B$11*(($L$11*(1-'P-Parametri'!$B$22))+0),0))+(IF(AND((($L$11*(1-'P-Parametri'!$B$22))+0)<='P-Parametri'!$C$18,(IF((($L$11*(1-'P-Parametri'!$B$22))+0)<='P-Parametri'!$B$6,'P-Parametri'!$C$6*(($L$11*(1-'P-Parametri'!$B$22))+0),IF((($L$11*(1-'P-Parametri'!$B$22))+0)<='P-Parametri'!$B$7,'P-Parametri'!$B$9+'P-Parametri'!$C$7*((($L$11*(1-'P-Parametri'!$B$22))+0)-'P-Parametri'!$B$6),'P-Parametri'!$B$10+'P-Parametri'!$C$8*((($L$11*(1-'P-Parametri'!$B$22))+0)-'P-Parametri'!$B$7))))>(IF((($L$11*(1-'P-Parametri'!$B$22))+0)<='P-Parametri'!$C$12,'P-Parametri'!$B$12,IF((($L$11*(1-'P-Parametri'!$B$22))+0)<='P-Parametri'!$B$6,'P-Parametri'!$B$13+'P-Parametri'!$C$13*('P-Parametri'!$B$6-(($L$11*(1-'P-Parametri'!$B$22))+0))/'P-Parametri'!$D$13,IF((($L$11*(1-'P-Parametri'!$B$22))+0)<='P-Parametri'!$B$7,'P-Parametri'!$B$14*('P-Parametri'!$B$7-(($L$11*(1-'P-Parametri'!$B$22))+0))/'P-Parametri'!$C$14,0))))-'P-Parametri'!$D$18),'P-Parametri'!$B$18,0))+(IF(($L$11*(1-'P-Parametri'!$B$22))>0,IF((($L$11*(1-'P-Parametri'!$B$22))+0)>'P-Parametri'!$D$20,0,IF((($L$11*(1-'P-Parametri'!$B$22))+0)<='P-Parametri'!$B$20,'P-Parametri'!$B$19*($L$11*(1-'P-Parametri'!$B$22)),IF((($L$11*(1-'P-Parametri'!$B$22))+0)<='P-Parametri'!$C$20,'P-Parametri'!$C$19*($L$11*(1-'P-Parametri'!$B$22)),'P-Parametri'!$D$19*($L$11*(1-'P-Parametri'!$B$22))))),0)) -> 2463.9305 | O11: =(('P-Parametri'!$B$24*$L$11)*(1+'P-Parametri'!$B$26)^('1-Input'!$B$25-1-'1-Input'!$C$12+1)*(IF('P-Parametri'!$B$26=0,'1-Input'!$C$12,((1+'P-Parametri'!$B$26)^'1-Input'!$C$12-1)/'P-Parametri'!$B$26)))*'P-Parametri'!$B$27*(1-'P-Parametri'!$B$28) -> 369.18936 | P11: ='M2-Motore-Chiusura'!$E$1001 -> 2.4240492e-11 | Q11: =IF(ABS(P11)<=1,"radice","GRADINO — la cella si chiude su uno scalino fiscale, non su una radice") -> radice
A12: La colonna «residuo finale» è il patrimonio all'anno quarantadue simulato al reddito di chiusura: se la secante ha trovato una vera radice vale zero. Dove non vale zero, la funzione non è continua e la cella si chiude su un GRADINO — il trattamento integrativo del foglio 6, che sopra la sua soglia aggiunge di colpo più di milleduecento euro di netto. In quel caso il reddito che chiude la cella è la soglia stessa, e la si legge nel foglio 6.
A14: LA GERARCHIA — la cella peggiore, le due leve affiancate
A15: Cella peggiore | B15: =INDEX(A7:A11,MATCH(MIN(B7:B11),B7:B11,0)) -> r = 1% · crolli INIZIO
A16: PRIMA LEVA — taglio permanente della spesa, in euro e in percentuale | B16: =INDEX(D7:D11,MATCH(MIN(B7:B11),B7:B11,0)) -> 7778.4674 | C16: =INDEX(E7:E11,MATCH(MIN(B7:B11),B7:B11,0)) -> 0.26822301
A17: SECONDA LEVA — reddito lordo per la durata A, e quante carriere vale | B17: =INDEX(F7:F11,MATCH(MIN(B7:B11),B7:B11,0)) -> 59803.65 | C17: =INDEX(G7:G11,MATCH(MIN(B7:B11),B7:B11,0)) -> 1.7086757
A18: SECONDA LEVA — la stessa cella, per la durata B | B18: =INDEX(L7:L11,MATCH(MIN(B7:B11),B7:B11,0)) -> 23941.317 | C18: =INDEX(M7:M11,MATCH(MIN(B7:B11),B7:B11,0)) -> 0.68403763
A19: Quante volte il lavoro chiede più della spesa (per la durata A) | B19: =B17/B16 -> 7.688359
A20: Anni che costa la prima leva / che costa la seconda | B20: ='1-Input'!$B$22 -> 42 | C20: ='1-Input'!$B$12 -> 5
A21: Per chiudere lo stesso scenario, il lavoro chiede un reddito lordo che vale più di una volta e mezza la carriera di Davide, per cinque anni. La spesa ne chiede una frazione, una volta sola e per sempre. Il lavoro è la SECONDA leva: dirlo è ciò che rende onesto tutto il resto.
A23: PERCHÉ COMUNQUE NON SONO LA STESSA COSA — le tre asimmetrie
A24: Asimmetria | B24: Rientrare | C24: Tagliare la spesa
A25: Temporale — anni che costa | B25: ='1-Input'!$B$12 -> 5 | C25: ='1-Input'!$B$22 -> 42
A26: Previdenziale — pensione in più, netta, a vita | B26: ='1-Input'!$B$32 -> 887.4451 | C26: =0 -> 0
A27: Di reversibilità | B27: ="se salta, si torna al piano di prima" -> se salta, si torna al piano di prima | C27: ="un tenore abbassato è difficile da rialzare" -> un tenore abbassato è difficile da rialzare

Sheet 6-Fisco
A1: La finestra fiscale, riga per riga — fotografia del 2026
A2: Strumento informativo / divulgativo. NON è consulenza finanziaria. I valori sono indicativi al 2026 e vanno verificati col tuo consulente.
A3: Chi vive di capitale ha un reddito IRPEF pari a zero: i prelievi pagano l'imposta sostitutiva e non entrano in IRPEF. Il primo scaglione è tutto libero, ed è la ragione per cui un part-time dopo il FIRE rende quanto rende. Con le regole del duemilaventisei.
A5: Pensione lorda annua / netta della sola pensione (baseline) | B5: ='1-Input'!$B$24 -> 19006 | C5: ='1-Input'!$B$24-(MAX(0,(IF('1-Input'!$B$24<='P-Parametri'!$B$6,'P-Parametri'!$C$6*'1-Input'!$B$24,IF('1-Input'!$B$24<='P-Parametri'!$B$7,'P-Parametri'!$B$9+'P-Parametri'!$C$7*('1-Input'!$B$24-'P-Parametri'!$B$6),'P-Parametri'!$B$10+'P-Parametri'!$C$8*('1-Input'!$B$24-'P-Parametri'!$B$7))))-(IF('1-Input'!$B$24<='P-Parametri'!$C$15,'P-Parametri'!$B$15,IF('1-Input'!$B$24<='P-Parametri'!$B$6,'P-Parametri'!$B$16+'P-Parametri'!$C$16*('P-Parametri'!$B$6-'1-Input'!$B$24)/'P-Parametri'!$D$16,IF('1-Input'!$B$24<='P-Parametri'!$B$7,'P-Parametri'!$B$17*('P-Parametri'!$B$7-'1-Input'!$B$24)/'P-Parametri'!$C$17,0))))))-(IF(MAX(0,(IF('1-Input'!$B$24<='P-Parametri'!$B$6,'P-Parametri'!$C$6*'1-Input'!$B$24,IF('1-Input'!$B$24<='P-Parametri'!$B$7,'P-Parametri'!$B$9+'P-Parametri'!$C$7*('1-Input'!$B$24-'P-Parametri'!$B$6),'P-Parametri'!$B$10+'P-Parametri'!$C$8*('1-Input'!$B$24-'P-Parametri'!$B$7))))-(IF('1-Input'!$B$24<='P-Parametri'!$C$15,'P-Parametri'!$B$15,IF('1-Input'!$B$24<='P-Parametri'!$B$6,'P-Parametri'!$B$16+'P-Parametri'!$C$16*('P-Parametri'!$B$6-'1-Input'!$B$24)/'P-Parametri'!$D$16,IF('1-Input'!$B$24<='P-Parametri'!$B$7,'P-Parametri'!$B$17*('P-Parametri'!$B$7-'1-Input'!$B$24)/'P-Parametri'!$C$17,0)))))>0,'P-Parametri'!$B$11*'1-Input'!$B$24,0)) -> 15533.345
A6: LA FINESTRA — netto incrementale prima e dopo la pensione
A7: Lordo | B7: Contributi 9,19% | C7: Reddito complessivo | D7: IRPEF lorda | E7: Detrazione | F7: Ulteriore detr. | G7: Imposta netta | H7: Addizionali | I7: Tratt. integrativo | J7: Somma sul cuneo | K7: NETTO in busta | L7: % del lordo | M7: Netto DOPO la pensione | N7: % del lordo
A8: 6000 | B8: =$A8*'P-Parametri'!$B$22 -> 551.4 | C8: =($A8*(1-'P-Parametri'!$B$22)) -> 5448.6 | D8: =IF($C8<='P-Parametri'!$B$6,'P-Parametri'!$C$6*$C8,IF($C8<='P-Parametri'!$B$7,'P-Parametri'!$B$9+'P-Parametri'!$C$7*($C8-'P-Parametri'!$B$6),'P-Parametri'!$B$10+'P-Parametri'!$C$8*($C8-'P-Parametri'!$B$7))) -> 1253.178 | E8: =IF($C8<='P-Parametri'!$C$12,'P-Parametri'!$B$12,IF($C8<='P-Parametri'!$B$6,'P-Parametri'!$B$13+'P-Parametri'!$C$13*('P-Parametri'!$B$6-$C8)/'P-Parametri'!$D$13,IF($C8<='P-Parametri'!$B$7,'P-Parametri'!$B$14*('P-Parametri'!$B$7-$C8)/'P-Parametri'!$C$14,0))) -> 1955 | F8: =IF($C8<='P-Parametri'!$C$21,0,IF($C8<='P-Parametri'!$D$21,'P-Parametri'!$B$21,IF($C8<'P-Parametri'!$E$21,'P-Parametri'!$B$21*('P-Parametri'!$E$21-$C8)/('P-Parametri'!$E$21-'P-Parametri'!$D$21),0))) -> 0 | G8: =MAX(0,D8-E8-F8) -> 0 | H8: =IF(G8>0,'P-Parametri'!$B$11*C8,0) -> 0 | I8: =IF(AND(C8<='P-Parametri'!$C$18,D8>E8-'P-Parametri'!$D$18),'P-Parametri'!$B$18,0) -> 0 | J8: =IF($C8>'P-Parametri'!$D$20,0,IF($C8<='P-Parametri'!$B$20,'P-Parametri'!$B$19*$C8,IF($C8<='P-Parametri'!$C$20,'P-Parametri'!$C$19*$C8,'P-Parametri'!$D$19*$C8))) -> 386.8506 | K8: =C8-G8-H8+I8+J8 -> 5835.4506 | L8: =K8/A8 -> 0.9725751 | M8: =(($A8*(1-'P-Parametri'!$B$22))+'1-Input'!$B$24)-(MAX(0,(IF((($A8*(1-'P-Parametri'!$B$22))+'1-Input'!$B$24)<='P-Parametri'!$B$6,'P-Parametri'!$C$6*(($A8*(1-'P-Parametri'!$B$22))+'1-Input'!$B$24),IF((($A8*(1-'P-Parametri'!$B$22))+'1-Input'!$B$24)<='P-Parametri'!$B$7,'P-Parametri'!$B$9+'P-Parametri'!$C$7*((($A8*(1-'P-Parametri'!$B$22))+'1-Input'!$B$24)-'P-Parametri'!$B$6),'P-Parametri'!$B$10+'P-Parametri'!$C$8*((($A8*(1-'P-Parametri'!$B$22))+'1-Input'!$B$24)-'P-Parametri'!$B$7))))-(MAX(IF((($A8*(1-'P-Parametri'!$B$22))+'1-Input'!$B$24)<='P-Parametri'!$C$12,'P-Parametri'!$B$12,IF((($A8*(1-'P-Parametri'!$B$22))+'1-Input'!$B$24)<='P-Parametri'!$B$6,'P-Parametri'!$B$13+'P-Parametri'!$C$13*('P-Parametri'!$B$6-(($A8*(1-'P-Parametri'!$B$22))+'1-Input'!$B$24))/'P-Parametri'!$D$13,IF((($A8*(1-'P-Parametri'!$B$22))+'1-Input'!$B$24)<='P-Parametri'!$B$7,'P-Parametri'!$B$14*('P-Parametri'!$B$7-(($A8*(1-'P-Parametri'!$B$22))+'1-Input'!$B$24))/'P-Parametri'!$C$14,0))),IF((($A8*(1-'P-Parametri'!$B$22))+'1-Input'!$B$24)<='P-Parametri'!$C$15,'P-Parametri'!$B$15,IF((($A8*(1-'P-Parametri'!$B$22))+'1-Input'!$B$24)<='P-Parametri'!$B$6,'P-Parametri'!$B$16+'P-Parametri'!$C$16*('P-Parametri'!$B$6-(($A8*(1-'P-Parametri'!$B$22))+'1-Input'!$B$24))/'P-Parametri'!$D$16,IF((($A8*(1-'P-Parametri'!$B$22))+'1-Input'!$B$24)<='P-Parametri'!$B$7,'P-Parametri'!$B$17*('P-Parametri'!$B$7-(($A8*(1-'P-Parametri'!$B$22))+'1-Input'!$B$24))/'P-Parametri'!$C$17,0)))))-(IF(($A8*(1-'P-Parametri'!$B$22))>0,IF((($A8*(1-'P-Parametri'!$B$22))+'1-Input'!$B$24)<='P-Parametri'!$C$21,0,IF((($A8*(1-'P-Parametri'!$B$22))+'1-Input'!$B$24)<='P-Parametri'!$D$21,'P-Parametri'!$B$21,IF((($A8*(1-'P-Parametri'!$B$22))+'1-Input'!$B$24)<'P-Parametri'!$E$21,'P-Parametri'!$B$21*('P-Parametri'!$E$21-(($A8*(1-'P-Parametri'!$B$22))+'1-Input'!$B$24))/('P-Parametri'!$E$21-'P-Parametri'!$D$21),0))),0))))-(IF(MAX(0,(IF((($A8*(1-'P-Parametri'!$B$22))+'1-Input'!$B$24)<='P-Parametri'!$B$6,'P-Parametri'!$C$6*(($A8*(1-'P-Parametri'!$B$22))+'1-Input'!$B$24),IF((($A8*(1-'P-Parametri'!$B$22))+'1-Input'!$B$24)<='P-Parametri'!$B$7,'P-Parametri'!$B$9+'P-Parametri'!$C$7*((($A8*(1-'P-Parametri'!$B$22))+'1-Input'!$B$24)-'P-Parametri'!$B$6),'P-Parametri'!$B$10+'P-Parametri'!$C$8*((($A8*(1-'P-Parametri'!$B$22))+'1-Input'!$B$24)-'P-Parametri'!$B$7))))-(MAX(IF((($A8*(1-'P-Parametri'!$B$22))+'1-Input'!$B$24)<='P-Parametri'!$C$12,'P-Parametri'!$B$12,IF((($A8*(1-'P-Parametri'!$B$22))+'1-Input'!$B$24)<='P-Parametri'!$B$6,'P-Parametri'!$B$13+'P-Parametri'!$C$13*('P-Parametri'!$B$6-(($A8*(1-'P-Parametri'!$B$22))+'1-Input'!$B$24))/'P-Parametri'!$D$13,IF((($A8*(1-'P-Parametri'!$B$22))+'1-Input'!$B$24)<='P-Parametri'!$B$7,'P-Parametri'!$B$14*('P-Parametri'!$B$7-(($A8*(1-'P-Parametri'!$B$22))+'1-Input'!$B$24))/'P-Parametri'!$C$14,0))),IF((($A8*(1-'P-Parametri'!$B$22))+'1-Input'!$B$24)<='P-Parametri'!$C$15,'P-Parametri'!$B$15,IF((($A8*(1-'P-Parametri'!$B$22))+'1-Input'!$B$24)<='P-Parametri'!$B$6,'P-Parametri'!$B$16+'P-Parametri'!$C$16*('P-Parametri'!$B$6-(($A8*(1-'P-Parametri'!$B$22))+'1-Input'!$B$24))/'P-Parametri'!$D$16,IF((($A8*(1-'P-Parametri'!$B$22))+'1-Input'!$B$24)<='P-Parametri'!$B$7,'P-Parametri'!$B$17*('P-Parametri'!$B$7-(($A8*(1-'P-Parametri'!$B$22))+'1-Input'!$B$24))/'P-Parametri'!$C$17,0)))))-(IF(($A8*(1-'P-Parametri'!$B$22))>0,IF((($A8*(1-'P-Parametri'!$B$22))+'1-Input'!$B$24)<='P-Parametri'!$C$21,0,IF((($A8*(1-'P-Parametri'!$B$22))+'1-Input'!$B$24)<='P-Parametri'!$D$21,'P-Parametri'!$B$21,IF((($A8*(1-'P-Parametri'!$B$22))+'1-Input'!$B$24)<'P-Parametri'!$E$21,'P-Parametri'!$B$21*('P-Parametri'!$E$21-(($A8*(1-'P-Parametri'!$B$22))+'1-Input'!$B$24))/('P-Parametri'!$E$21-'P-Parametri'!$D$21),0))),0)))>0,'P-Parametri'!$B$11*(($A8*(1-'P-Parametri'!$B$22))+'1-Input'!$B$24),0))+(IF(AND((($A8*(1-'P-Parametri'!$B$22))+'1-Input'!$B$24)<='P-Parametri'!$C$18,(IF((($A8*(1-'P-Parametri'!$B$22))+'1-Input'!$B$24)<='P-Parametri'!$B$6,'P-Parametri'!$C$6*(($A8*(1-'P-Parametri'!$B$22))+'1-Input'!$B$24),IF((($A8*(1-'P-Parametri'!$B$22))+'1-Input'!$B$24)<='P-Parametri'!$B$7,'P-Parametri'!$B$9+'P-Parametri'!$C$7*((($A8*(1-'P-Parametri'!$B$22))+'1-Input'!$B$24)-'P-Parametri'!$B$6),'P-Parametri'!$B$10+'P-Parametri'!$C$8*((($A8*(1-'P-Parametri'!$B$22))+'1-Input'!$B$24)-'P-Parametri'!$B$7))))>(MAX(IF((($A8*(1-'P-Parametri'!$B$22))+'1-Input'!$B$24)<='P-Parametri'!$C$12,'P-Parametri'!$B$12,IF((($A8*(1-'P-Parametri'!$B$22))+'1-Input'!$B$24)<='P-Parametri'!$B$6,'P-Parametri'!$B$13+'P-Parametri'!$C$13*('P-Parametri'!$B$6-(($A8*(1-'P-Parametri'!$B$22))+'1-Input'!$B$24))/'P-Parametri'!$D$13,IF((($A8*(1-'P-Parametri'!$B$22))+'1-Input'!$B$24)<='P-Parametri'!$B$7,'P-Parametri'!$B$14*('P-Parametri'!$B$7-(($A8*(1-'P-Parametri'!$B$22))+'1-Input'!$B$24))/'P-Parametri'!$C$14,0))),IF((($A8*(1-'P-Parametri'!$B$22))+'1-Input'!$B$24)<='P-Parametri'!$C$15,'P-Parametri'!$B$15,IF((($A8*(1-'P-Parametri'!$B$22))+'1-Input'!$B$24)<='P-Parametri'!$B$6,'P-Parametri'!$B$16+'P-Parametri'!$C$16*('P-Parametri'!$B$6-(($A8*(1-'P-Parametri'!$B$22))+'1-Input'!$B$24))/'P-Parametri'!$D$16,IF((($A8*(1-'P-Parametri'!$B$22))+'1-Input'!$B$24)<='P-Parametri'!$B$7,'P-Parametri'!$B$17*('P-Parametri'!$B$7-(($A8*(1-'P-Parametri'!$B$22))+'1-Input'!$B$24))/'P-Parametri'!$C$17,0)))))-'P-Parametri'!$D$18),'P-Parametri'!$B$18,0))+(IF(($A8*(1-'P-Parametri'!$B$22))>0,IF((($A8*(1-'P-Parametri'!$B$22))+'1-Input'!$B$24)>'P-Parametri'!$D$20,0,IF((($A8*(1-'P-Parametri'!$B$22))+'1-Input'!$B$24)<='P-Parametri'!$B$20,'P-Parametri'!$B$19*($A8*(1-'P-Parametri'!$B$22)),IF((($A8*(1-'P-Parametri'!$B$22))+'1-Input'!$B$24)<='P-Parametri'!$C$20,'P-Parametri'!$C$19*($A8*(1-'P-Parametri'!$B$22)),'P-Parametri'!$D$19*($A8*(1-'P-Parametri'!$B$22))))),0))-'6-Fisco'!$C$5 -> 6042.1458 | N8: =M8/A8 -> 1.0070243
A9: 10000 | B9: =$A9*'P-Parametri'!$B$22 -> 919 | C9: =($A9*(1-'P-Parametri'!$B$22)) -> 9081 | D9: =IF($C9<='P-Parametri'!$B$6,'P-Parametri'!$C$6*$C9,IF($C9<='P-Parametri'!$B$7,'P-Parametri'!$B$9+'P-Parametri'!$C$7*($C9-'P-Parametri'!$B$6),'P-Parametri'!$B$10+'P-Parametri'!$C$8*($C9-'P-Parametri'!$B$7))) -> 2088.63 | E9: =IF($C9<='P-Parametri'!$C$12,'P-Parametri'!$B$12,IF($C9<='P-Parametri'!$B$6,'P-Parametri'!$B$13+'P-Parametri'!$C$13*('P-Parametri'!$B$6-$C9)/'P-Parametri'!$D$13,IF($C9<='P-Parametri'!$B$7,'P-Parametri'!$B$14*('P-Parametri'!$B$7-$C9)/'P-Parametri'!$C$14,0))) -> 1955 | F9: =IF($C9<='P-Parametri'!$C$21,0,IF($C9<='P-Parametri'!$D$21,'P-Parametri'!$B$21,IF($C9<'P-Parametri'!$E$21,'P-Parametri'!$B$21*('P-Parametri'!$E$21-$C9)/('P-Parametri'!$E$21-'P-Parametri'!$D$21),0))) -> 0 | G9: =MAX(0,D9-E9-F9) -> 133.63 | H9: =IF(G9>0,'P-Parametri'!$B$11*C9,0) -> 181.62 | I9: =IF(AND(C9<='P-Parametri'!$C$18,D9>E9-'P-Parametri'!$D$18),'P-Parametri'!$B$18,0) -> 1200 | J9: =IF($C9>'P-Parametri'!$D$20,0,IF($C9<='P-Parametri'!$B$20,'P-Parametri'!$B$19*$C9,IF($C9<='P-Parametri'!$C$20,'P-Parametri'!$C$19*$C9,'P-Parametri'!$D$19*$C9))) -> 481.293 | K9: =C9-G9-H9+I9+J9 -> 10447.043 | L9: =K9/A9 -> 1.0447043 | M9: =(($A9*(1-'P-Parametri'!$B$22))+'1-Input'!$B$24)-(MAX(0,(IF((($A9*(1-'P-Parametri'!$B$22))+'1-Input'!$B$24)<='P-Parametri'!$B$6,'P-Parametri'!$C$6*(($A9*(1-'P-Parametri'!$B$22))+'1-Input'!$B$24),IF((($A9*(1-'P-Parametri'!$B$22))+'1-Input'!$B$24)<='P-Parametri'!$B$7,'P-Parametri'!$B$9+'P-Parametri'!$C$7*((($A9*(1-'P-Parametri'!$B$22))+'1-Input'!$B$24)-'P-Parametri'!$B$6),'P-Parametri'!$B$10+'P-Parametri'!$C$8*((($A9*(1-'P-Parametri'!$B$22))+'1-Input'!$B$24)-'P-Parametri'!$B$7))))-(MAX(IF((($A9*(1-'P-Parametri'!$B$22))+'1-Input'!$B$24)<='P-Parametri'!$C$12,'P-Parametri'!$B$12,IF((($A9*(1-'P-Parametri'!$B$22))+'1-Input'!$B$24)<='P-Parametri'!$B$6,'P-Parametri'!$B$13+'P-Parametri'!$C$13*('P-Parametri'!$B$6-(($A9*(1-'P-Parametri'!$B$22))+'1-Input'!$B$24))/'P-Parametri'!$D$13,IF((($A9*(1-'P-Parametri'!$B$22))+'1-Input'!$B$24)<='P-Parametri'!$B$7,'P-Parametri'!$B$14*('P-Parametri'!$B$7-(($A9*(1-'P-Parametri'!$B$22))+'1-Input'!$B$24))/'P-Parametri'!$C$14,0))),IF((($A9*(1-'P-Parametri'!$B$22))+'1-Input'!$B$24)<='P-Parametri'!$C$15,'P-Parametri'!$B$15,IF((($A9*(1-'P-Parametri'!$B$22))+'1-Input'!$B$24)<='P-Parametri'!$B$6,'P-Parametri'!$B$16+'P-Parametri'!$C$16*('P-Parametri'!$B$6-(($A9*(1-'P-Parametri'!$B$22))+'1-Input'!$B$24))/'P-Parametri'!$D$16,IF((($A9*(1-'P-Parametri'!$B$22))+'1-Input'!$B$24)<='P-Parametri'!$B$7,'P-Parametri'!$B$17*('P-Parametri'!$B$7-(($A9*(1-'P-Parametri'!$B$22))+'1-Input'!$B$24))/'P-Parametri'!$C$17,0)))))-(IF(($A9*(1-'P-Parametri'!$B$22))>0,IF((($A9*(1-'P-Parametri'!$B$22))+'1-Input'!$B$24)<='P-Parametri'!$C$21,0,IF((($A9*(1-'P-Parametri'!$B$22))+'1-Input'!$B$24)<='P-Parametri'!$D$21,'P-Parametri'!$B$21,IF((($A9*(1-'P-Parametri'!$B$22))+'1-Input'!$B$24)<'P-Parametri'!$E$21,'P-Parametri'!$B$21*('P-Parametri'!$E$21-(($A9*(1-'P-Parametri'!$B$22))+'1-Input'!$B$24))/('P-Parametri'!$E$21-'P-Parametri'!$D$21),0))),0))))-(IF(MAX(0,(IF((($A9*(1-'P-Parametri'!$B$22))+'1-Input'!$B$24)<='P-Parametri'!$B$6,'P-Parametri'!$C$6*(($A9*(1-'P-Parametri'!$B$22))+'1-Input'!$B$24),IF((($A9*(1-'P-Parametri'!$B$22))+'1-Input'!$B$24)<='P-Parametri'!$B$7,'P-Parametri'!$B$9+'P-Parametri'!$C$7*((($A9*(1-'P-Parametri'!$B$22))+'1-Input'!$B$24)-'P-Parametri'!$B$6),'P-Parametri'!$B$10+'P-Parametri'!$C$8*((($A9*(1-'P-Parametri'!$B$22))+'1-Input'!$B$24)-'P-Parametri'!$B$7))))-(MAX(IF((($A9*(1-'P-Parametri'!$B$22))+'1-Input'!$B$24)<='P-Parametri'!$C$12,'P-Parametri'!$B$12,IF((($A9*(1-'P-Parametri'!$B$22))+'1-Input'!$B$24)<='P-Parametri'!$B$6,'P-Parametri'!$B$13+'P-Parametri'!$C$13*('P-Parametri'!$B$6-(($A9*(1-'P-Parametri'!$B$22))+'1-Input'!$B$24))/'P-Parametri'!$D$13,IF((($A9*(1-'P-Parametri'!$B$22))+'1-Input'!$B$24)<='P-Parametri'!$B$7,'P-Parametri'!$B$14*('P-Parametri'!$B$7-(($A9*(1-'P-Parametri'!$B$22))+'1-Input'!$B$24))/'P-Parametri'!$C$14,0))),IF((($A9*(1-'P-Parametri'!$B$22))+'1-Input'!$B$24)<='P-Parametri'!$C$15,'P-Parametri'!$B$15,IF((($A9*(1-'P-Parametri'!$B$22))+'1-Input'!$B$24)<='P-Parametri'!$B$6,'P-Parametri'!$B$16+'P-Parametri'!$C$16*('P-Parametri'!$B$6-(($A9*(1-'P-Parametri'!$B$22))+'1-Input'!$B$24))/'P-Parametri'!$D$16,IF((($A9*(1-'P-Parametri'!$B$22))+'1-Input'!$B$24)<='P-Parametri'!$B$7,'P-Parametri'!$B$17*('P-Parametri'!$B$7-(($A9*(1-'P-Parametri'!$B$22))+'1-Input'!$B$24))/'P-Parametri'!$C$17,0)))))-(IF(($A9*(1-'P-Parametri'!$B$22))>0,IF((($A9*(1-'P-Parametri'!$B$22))+'1-Input'!$B$24)<='P-Parametri'!$C$21,0,IF((($A9*(1-'P-Parametri'!$B$22))+'1-Input'!$B$24)<='P-Parametri'!$D$21,'P-Parametri'!$B$21,IF((($A9*(1-'P-Parametri'!$B$22))+'1-Input'!$B$24)<'P-Parametri'!$E$21,'P-Parametri'!$B$21*('P-Parametri'!$E$21-(($A9*(1-'P-Parametri'!$B$22))+'1-Input'!$B$24))/('P-Parametri'!$E$21-'P-Parametri'!$D$21),0))),0)))>0,'P-Parametri'!$B$11*(($A9*(1-'P-Parametri'!$B$22))+'1-Input'!$B$24),0))+(IF(AND((($A9*(1-'P-Parametri'!$B$22))+'1-Input'!$B$24)<='P-Parametri'!$C$18,(IF((($A9*(1-'P-Parametri'!$B$22))+'1-Input'!$B$24)<='P-Parametri'!$B$6,'P-Parametri'!$C$6*(($A9*(1-'P-Parametri'!$B$22))+'1-Input'!$B$24),IF((($A9*(1-'P-Parametri'!$B$22))+'1-Input'!$B$24)<='P-Parametri'!$B$7,'P-Parametri'!$B$9+'P-Parametri'!$C$7*((($A9*(1-'P-Parametri'!$B$22))+'1-Input'!$B$24)-'P-Parametri'!$B$6),'P-Parametri'!$B$10+'P-Parametri'!$C$8*((($A9*(1-'P-Parametri'!$B$22))+'1-Input'!$B$24)-'P-Parametri'!$B$7))))>(MAX(IF((($A9*(1-'P-Parametri'!$B$22))+'1-Input'!$B$24)<='P-Parametri'!$C$12,'P-Parametri'!$B$12,IF((($A9*(1-'P-Parametri'!$B$22))+'1-Input'!$B$24)<='P-Parametri'!$B$6,'P-Parametri'!$B$13+'P-Parametri'!$C$13*('P-Parametri'!$B$6-(($A9*(1-'P-Parametri'!$B$22))+'1-Input'!$B$24))/'P-Parametri'!$D$13,IF((($A9*(1-'P-Parametri'!$B$22))+'1-Input'!$B$24)<='P-Parametri'!$B$7,'P-Parametri'!$B$14*('P-Parametri'!$B$7-(($A9*(1-'P-Parametri'!$B$22))+'1-Input'!$B$24))/'P-Parametri'!$C$14,0))),IF((($A9*(1-'P-Parametri'!$B$22))+'1-Input'!$B$24)<='P-Parametri'!$C$15,'P-Parametri'!$B$15,IF((($A9*(1-'P-Parametri'!$B$22))+'1-Input'!$B$24)<='P-Parametri'!$B$6,'P-Parametri'!$B$16+'P-Parametri'!$C$16*('P-Parametri'!$B$6-(($A9*(1-'P-Parametri'!$B$22))+'1-Input'!$B$24))/'P-Parametri'!$D$16,IF((($A9*(1-'P-Parametri'!$B$22))+'1-Input'!$B$24)<='P-Parametri'!$B$7,'P-Parametri'!$B$17*('P-Parametri'!$B$7-(($A9*(1-'P-Parametri'!$B$22))+'1-Input'!$B$24))/'P-Parametri'!$C$17,0)))))-'P-Parametri'!$D$18),'P-Parametri'!$B$18,0))+(IF(($A9*(1-'P-Parametri'!$B$22))>0,IF((($A9*(1-'P-Parametri'!$B$22))+'1-Input'!$B$24)>'P-Parametri'!$D$20,0,IF((($A9*(1-'P-Parametri'!$B$22))+'1-Input'!$B$24)<='P-Parametri'!$B$20,'P-Parametri'!$B$19*($A9*(1-'P-Parametri'!$B$22)),IF((($A9*(1-'P-Parametri'!$B$22))+'1-Input'!$B$24)<='P-Parametri'!$C$20,'P-Parametri'!$C$19*($A9*(1-'P-Parametri'!$B$22)),'P-Parametri'!$D$19*($A9*(1-'P-Parametri'!$B$22))))),0))-'6-Fisco'!$C$5 -> 8425.6522 | N9: =M9/A9 -> 0.84256522
A10: 12000 | B10: =$A10*'P-Parametri'!$B$22 -> 1102.8 | C10: =($A10*(1-'P-Parametri'!$B$22)) -> 10897.2 | D10: =IF($C10<='P-Parametri'!$B$6,'P-Parametri'!$C$6*$C10,IF($C10<='P-Parametri'!$B$7,'P-Parametri'!$B$9+'P-Parametri'!$C$7*($C10-'P-Parametri'!$B$6),'P-Parametri'!$B$10+'P-Parametri'!$C$8*($C10-'P-Parametri'!$B$7))) -> 2506.356 | E10: =IF($C10<='P-Parametri'!$C$12,'P-Parametri'!$B$12,IF($C10<='P-Parametri'!$B$6,'P-Parametri'!$B$13+'P-Parametri'!$C$13*('P-Parametri'!$B$6-$C10)/'P-Parametri'!$D$13,IF($C10<='P-Parametri'!$B$7,'P-Parametri'!$B$14*('P-Parametri'!$B$7-$C10)/'P-Parametri'!$C$14,0))) -> 1955 | F10: =IF($C10<='P-Parametri'!$C$21,0,IF($C10<='P-Parametri'!$D$21,'P-Parametri'!$B$21,IF($C10<'P-Parametri'!$E$21,'P-Parametri'!$B$21*('P-Parametri'!$E$21-$C10)/('P-Parametri'!$E$21-'P-Parametri'!$D$21),0))) -> 0 | G10: =MAX(0,D10-E10-F10) -> 551.356 | H10: =IF(G10>0,'P-Parametri'!$B$11*C10,0) -> 217.944 | I10: =IF(AND(C10<='P-Parametri'!$C$18,D10>E10-'P-Parametri'!$D$18),'P-Parametri'!$B$18,0) -> 1200 | J10: =IF($C10>'P-Parametri'!$D$20,0,IF($C10<='P-Parametri'!$B$20,'P-Parametri'!$B$19*$C10,IF($C10<='P-Parametri'!$C$20,'P-Parametri'!$C$19*$C10,'P-Parametri'!$D$19*$C10))) -> 577.5516 | K10: =C10-G10-H10+I10+J10 -> 11905.452 | L10: =K10/A10 -> 0.99212097 | M10: =(($A10*(1-'P-Parametri'!$B$22))+'1-Input'!$B$24)-(MAX(0,(IF((($A10*(1-'P-Parametri'!$B$22))+'1-Input'!$B$24)<='P-Parametri'!$B$6,'P-Parametri'!$C$6*(($A10*(1-'P-Parametri'!$B$22))+'1-Input'!$B$24),IF((($A10*(1-'P-Parametri'!$B$22))+'1-Input'!$B$24)<='P-Parametri'!$B$7,'P-Parametri'!$B$9+'P-Parametri'!$C$7*((($A10*(1-'P-Parametri'!$B$22))+'1-Input'!$B$24)-'P-Parametri'!$B$6),'P-Parametri'!$B$10+'P-Parametri'!$C$8*((($A10*(1-'P-Parametri'!$B$22))+'1-Input'!$B$24)-'P-Parametri'!$B$7))))-(MAX(IF((($A10*(1-'P-Parametri'!$B$22))+'1-Input'!$B$24)<='P-Parametri'!$C$12,'P-Parametri'!$B$12,IF((($A10*(1-'P-Parametri'!$B$22))+'1-Input'!$B$24)<='P-Parametri'!$B$6,'P-Parametri'!$B$13+'P-Parametri'!$C$13*('P-Parametri'!$B$6-(($A10*(1-'P-Parametri'!$B$22))+'1-Input'!$B$24))/'P-Parametri'!$D$13,IF((($A10*(1-'P-Parametri'!$B$22))+'1-Input'!$B$24)<='P-Parametri'!$B$7,'P-Parametri'!$B$14*('P-Parametri'!$B$7-(($A10*(1-'P-Parametri'!$B$22))+'1-Input'!$B$24))/'P-Parametri'!$C$14,0))),IF((($A10*(1-'P-Parametri'!$B$22))+'1-Input'!$B$24)<='P-Parametri'!$C$15,'P-Parametri'!$B$15,IF((($A10*(1-'P-Parametri'!$B$22))+'1-Input'!$B$24)<='P-Parametri'!$B$6,'P-Parametri'!$B$16+'P-Parametri'!$C$16*('P-Parametri'!$B$6-(($A10*(1-'P-Parametri'!$B$22))+'1-Input'!$B$24))/'P-Parametri'!$D$16,IF((($A10*(1-'P-Parametri'!$B$22))+'1-Input'!$B$24)<='P-Parametri'!$B$7,'P-Parametri'!$B$17*('P-Parametri'!$B$7-(($A10*(1-'P-Parametri'!$B$22))+'1-Input'!$B$24))/'P-Parametri'!$C$17,0)))))-(IF(($A10*(1-'P-Parametri'!$B$22))>0,IF((($A10*(1-'P-Parametri'!$B$22))+'1-Input'!$B$24)<='P-Parametri'!$C$21,0,IF((($A10*(1-'P-Parametri'!$B$22))+'1-Input'!$B$24)<='P-Parametri'!$D$21,'P-Parametri'!$B$21,IF((($A10*(1-'P-Parametri'!$B$22))+'1-Input'!$B$24)<'P-Parametri'!$E$21,'P-Parametri'!$B$21*('P-Parametri'!$E$21-(($A10*(1-'P-Parametri'!$B$22))+'1-Input'!$B$24))/('P-Parametri'!$E$21-'P-Parametri'!$D$21),0))),0))))-(IF(MAX(0,(IF((($A10*(1-'P-Parametri'!$B$22))+'1-Input'!$B$24)<='P-Parametri'!$B$6,'P-Parametri'!$C$6*(($A10*(1-'P-Parametri'!$B$22))+'1-Input'!$B$24),IF((($A10*(1-'P-Parametri'!$B$22))+'1-Input'!$B$24)<='P-Parametri'!$B$7,'P-Parametri'!$B$9+'P-Parametri'!$C$7*((($A10*(1-'P-Parametri'!$B$22))+'1-Input'!$B$24)-'P-Parametri'!$B$6),'P-Parametri'!$B$10+'P-Parametri'!$C$8*((($A10*(1-'P-Parametri'!$B$22))+'1-Input'!$B$24)-'P-Parametri'!$B$7))))-(MAX(IF((($A10*(1-'P-Parametri'!$B$22))+'1-Input'!$B$24)<='P-Parametri'!$C$12,'P-Parametri'!$B$12,IF((($A10*(1-'P-Parametri'!$B$22))+'1-Input'!$B$24)<='P-Parametri'!$B$6,'P-Parametri'!$B$13+'P-Parametri'!$C$13*('P-Parametri'!$B$6-(($A10*(1-'P-Parametri'!$B$22))+'1-Input'!$B$24))/'P-Parametri'!$D$13,IF((($A10*(1-'P-Parametri'!$B$22))+'1-Input'!$B$24)<='P-Parametri'!$B$7,'P-Parametri'!$B$14*('P-Parametri'!$B$7-(($A10*(1-'P-Parametri'!$B$22))+'1-Input'!$B$24))/'P-Parametri'!$C$14,0))),IF((($A10*(1-'P-Parametri'!$B$22))+'1-Input'!$B$24)<='P-Parametri'!$C$15,'P-Parametri'!$B$15,IF((($A10*(1-'P-Parametri'!$B$22))+'1-Input'!$B$24)<='P-Parametri'!$B$6,'P-Parametri'!$B$16+'P-Parametri'!$C$16*('P-Parametri'!$B$6-(($A10*(1-'P-Parametri'!$B$22))+'1-Input'!$B$24))/'P-Parametri'!$D$16,IF((($A10*(1-'P-Parametri'!$B$22))+'1-Input'!$B$24)<='P-Parametri'!$B$7,'P-Parametri'!$B$17*('P-Parametri'!$B$7-(($A10*(1-'P-Parametri'!$B$22))+'1-Input'!$B$24))/'P-Parametri'!$C$17,0)))))-(IF(($A10*(1-'P-Parametri'!$B$22))>0,IF((($A10*(1-'P-Parametri'!$B$22))+'1-Input'!$B$24)<='P-Parametri'!$C$21,0,IF((($A10*(1-'P-Parametri'!$B$22))+'1-Input'!$B$24)<='P-Parametri'!$D$21,'P-Parametri'!$B$21,IF((($A10*(1-'P-Parametri'!$B$22))+'1-Input'!$B$24)<'P-Parametri'!$E$21,'P-Parametri'!$B$21*('P-Parametri'!$E$21-(($A10*(1-'P-Parametri'!$B$22))+'1-Input'!$B$24))/('P-Parametri'!$E$21-'P-Parametri'!$D$21),0))),0)))>0,'P-Parametri'!$B$11*(($A10*(1-'P-Parametri'!$B$22))+'1-Input'!$B$24),0))+(IF(AND((($A10*(1-'P-Parametri'!$B$22))+'1-Input'!$B$24)<='P-Parametri'!$C$18,(IF((($A10*(1-'P-Parametri'!$B$22))+'1-Input'!$B$24)<='P-Parametri'!$B$6,'P-Parametri'!$C$6*(($A10*(1-'P-Parametri'!$B$22))+'1-Input'!$B$24),IF((($A10*(1-'P-Parametri'!$B$22))+'1-Input'!$B$24)<='P-Parametri'!$B$7,'P-Parametri'!$B$9+'P-Parametri'!$C$7*((($A10*(1-'P-Parametri'!$B$22))+'1-Input'!$B$24)-'P-Parametri'!$B$6),'P-Parametri'!$B$10+'P-Parametri'!$C$8*((($A10*(1-'P-Parametri'!$B$22))+'1-Input'!$B$24)-'P-Parametri'!$B$7))))>(MAX(IF((($A10*(1-'P-Parametri'!$B$22))+'1-Input'!$B$24)<='P-Parametri'!$C$12,'P-Parametri'!$B$12,IF((($A10*(1-'P-Parametri'!$B$22))+'1-Input'!$B$24)<='P-Parametri'!$B$6,'P-Parametri'!$B$13+'P-Parametri'!$C$13*('P-Parametri'!$B$6-(($A10*(1-'P-Parametri'!$B$22))+'1-Input'!$B$24))/'P-Parametri'!$D$13,IF((($A10*(1-'P-Parametri'!$B$22))+'1-Input'!$B$24)<='P-Parametri'!$B$7,'P-Parametri'!$B$14*('P-Parametri'!$B$7-(($A10*(1-'P-Parametri'!$B$22))+'1-Input'!$B$24))/'P-Parametri'!$C$14,0))),IF((($A10*(1-'P-Parametri'!$B$22))+'1-Input'!$B$24)<='P-Parametri'!$C$15,'P-Parametri'!$B$15,IF((($A10*(1-'P-Parametri'!$B$22))+'1-Input'!$B$24)<='P-Parametri'!$B$6,'P-Parametri'!$B$16+'P-Parametri'!$C$16*('P-Parametri'!$B$6-(($A10*(1-'P-Parametri'!$B$22))+'1-Input'!$B$24))/'P-Parametri'!$D$16,IF((($A10*(1-'P-Parametri'!$B$22))+'1-Input'!$B$24)<='P-Parametri'!$B$7,'P-Parametri'!$B$17*('P-Parametri'!$B$7-(($A10*(1-'P-Parametri'!$B$22))+'1-Input'!$B$24))/'P-Parametri'!$C$17,0)))))-'P-Parametri'!$D$18),'P-Parametri'!$B$18,0))+(IF(($A10*(1-'P-Parametri'!$B$22))>0,IF((($A10*(1-'P-Parametri'!$B$22))+'1-Input'!$B$24)>'P-Parametri'!$D$20,0,IF((($A10*(1-'P-Parametri'!$B$22))+'1-Input'!$B$24)<='P-Parametri'!$B$20,'P-Parametri'!$B$19*($A10*(1-'P-Parametri'!$B$22)),IF((($A10*(1-'P-Parametri'!$B$22))+'1-Input'!$B$24)<='P-Parametri'!$C$20,'P-Parametri'!$C$19*($A10*(1-'P-Parametri'!$B$22)),'P-Parametri'!$D$19*($A10*(1-'P-Parametri'!$B$22))))),0))-'6-Fisco'!$C$5 -> 9448.503 | N10: =M10/A10 -> 0.78737525
A11: 15000 | B11: =$A11*'P-Parametri'!$B$22 -> 1378.5 | C11: =($A11*(1-'P-Parametri'!$B$22)) -> 13621.5 | D11: =IF($C11<='P-Parametri'!$B$6,'P-Parametri'!$C$6*$C11,IF($C11<='P-Parametri'!$B$7,'P-Parametri'!$B$9+'P-Parametri'!$C$7*($C11-'P-Parametri'!$B$6),'P-Parametri'!$B$10+'P-Parametri'!$C$8*($C11-'P-Parametri'!$B$7))) -> 3132.945 | E11: =IF($C11<='P-Parametri'!$C$12,'P-Parametri'!$B$12,IF($C11<='P-Parametri'!$B$6,'P-Parametri'!$B$13+'P-Parametri'!$C$13*('P-Parametri'!$B$6-$C11)/'P-Parametri'!$D$13,IF($C11<='P-Parametri'!$B$7,'P-Parametri'!$B$14*('P-Parametri'!$B$7-$C11)/'P-Parametri'!$C$14,0))) -> 1955 | F11: =IF($C11<='P-Parametri'!$C$21,0,IF($C11<='P-Parametri'!$D$21,'P-Parametri'!$B$21,IF($C11<'P-Parametri'!$E$21,'P-Parametri'!$B$21*('P-Parametri'!$E$21-$C11)/('P-Parametri'!$E$21-'P-Parametri'!$D$21),0))) -> 0 | G11: =MAX(0,D11-E11-F11) -> 1177.945 | H11: =IF(G11>0,'P-Parametri'!$B$11*C11,0) -> 272.43 | I11: =IF(AND(C11<='P-Parametri'!$C$18,D11>E11-'P-Parametri'!$D$18),'P-Parametri'!$B$18,0) -> 1200 | J11: =IF($C11>'P-Parametri'!$D$20,0,IF($C11<='P-Parametri'!$B$20,'P-Parametri'!$B$19*$C11,IF($C11<='P-Parametri'!$C$20,'P-Parametri'!$C$19*$C11,'P-Parametri'!$D$19*$C11))) -> 721.9395 | K11: =C11-G11-H11+I11+J11 -> 14093.065 | L11: =K11/A11 -> 0.93953763 | M11: =(($A11*(1-'P-Parametri'!$B$22))+'1-Input'!$B$24)-(MAX(0,(IF((($A11*(1-'P-Parametri'!$B$22))+'1-Input'!$B$24)<='P-Parametri'!$B$6,'P-Parametri'!$C$6*(($A11*(1-'P-Parametri'!$B$22))+'1-Input'!$B$24),IF((($A11*(1-'P-Parametri'!$B$22))+'1-Input'!$B$24)<='P-Parametri'!$B$7,'P-Parametri'!$B$9+'P-Parametri'!$C$7*((($A11*(1-'P-Parametri'!$B$22))+'1-Input'!$B$24)-'P-Parametri'!$B$6),'P-Parametri'!$B$10+'P-Parametri'!$C$8*((($A11*(1-'P-Parametri'!$B$22))+'1-Input'!$B$24)-'P-Parametri'!$B$7))))-(MAX(IF((($A11*(1-'P-Parametri'!$B$22))+'1-Input'!$B$24)<='P-Parametri'!$C$12,'P-Parametri'!$B$12,IF((($A11*(1-'P-Parametri'!$B$22))+'1-Input'!$B$24)<='P-Parametri'!$B$6,'P-Parametri'!$B$13+'P-Parametri'!$C$13*('P-Parametri'!$B$6-(($A11*(1-'P-Parametri'!$B$22))+'1-Input'!$B$24))/'P-Parametri'!$D$13,IF((($A11*(1-'P-Parametri'!$B$22))+'1-Input'!$B$24)<='P-Parametri'!$B$7,'P-Parametri'!$B$14*('P-Parametri'!$B$7-(($A11*(1-'P-Parametri'!$B$22))+'1-Input'!$B$24))/'P-Parametri'!$C$14,0))),IF((($A11*(1-'P-Parametri'!$B$22))+'1-Input'!$B$24)<='P-Parametri'!$C$15,'P-Parametri'!$B$15,IF((($A11*(1-'P-Parametri'!$B$22))+'1-Input'!$B$24)<='P-Parametri'!$B$6,'P-Parametri'!$B$16+'P-Parametri'!$C$16*('P-Parametri'!$B$6-(($A11*(1-'P-Parametri'!$B$22))+'1-Input'!$B$24))/'P-Parametri'!$D$16,IF((($A11*(1-'P-Parametri'!$B$22))+'1-Input'!$B$24)<='P-Parametri'!$B$7,'P-Parametri'!$B$17*('P-Parametri'!$B$7-(($A11*(1-'P-Parametri'!$B$22))+'1-Input'!$B$24))/'P-Parametri'!$C$17,0)))))-(IF(($A11*(1-'P-Parametri'!$B$22))>0,IF((($A11*(1-'P-Parametri'!$B$22))+'1-Input'!$B$24)<='P-Parametri'!$C$21,0,IF((($A11*(1-'P-Parametri'!$B$22))+'1-Input'!$B$24)<='P-Parametri'!$D$21,'P-Parametri'!$B$21,IF((($A11*(1-'P-Parametri'!$B$22))+'1-Input'!$B$24)<'P-Parametri'!$E$21,'P-Parametri'!$B$21*('P-Parametri'!$E$21-(($A11*(1-'P-Parametri'!$B$22))+'1-Input'!$B$24))/('P-Parametri'!$E$21-'P-Parametri'!$D$21),0))),0))))-(IF(MAX(0,(IF((($A11*(1-'P-Parametri'!$B$22))+'1-Input'!$B$24)<='P-Parametri'!$B$6,'P-Parametri'!$C$6*(($A11*(1-'P-Parametri'!$B$22))+'1-Input'!$B$24),IF((($A11*(1-'P-Parametri'!$B$22))+'1-Input'!$B$24)<='P-Parametri'!$B$7,'P-Parametri'!$B$9+'P-Parametri'!$C$7*((($A11*(1-'P-Parametri'!$B$22))+'1-Input'!$B$24)-'P-Parametri'!$B$6),'P-Parametri'!$B$10+'P-Parametri'!$C$8*((($A11*(1-'P-Parametri'!$B$22))+'1-Input'!$B$24)-'P-Parametri'!$B$7))))-(MAX(IF((($A11*(1-'P-Parametri'!$B$22))+'1-Input'!$B$24)<='P-Parametri'!$C$12,'P-Parametri'!$B$12,IF((($A11*(1-'P-Parametri'!$B$22))+'1-Input'!$B$24)<='P-Parametri'!$B$6,'P-Parametri'!$B$13+'P-Parametri'!$C$13*('P-Parametri'!$B$6-(($A11*(1-'P-Parametri'!$B$22))+'1-Input'!$B$24))/'P-Parametri'!$D$13,IF((($A11*(1-'P-Parametri'!$B$22))+'1-Input'!$B$24)<='P-Parametri'!$B$7,'P-Parametri'!$B$14*('P-Parametri'!$B$7-(($A11*(1-'P-Parametri'!$B$22))+'1-Input'!$B$24))/'P-Parametri'!$C$14,0))),IF((($A11*(1-'P-Parametri'!$B$22))+'1-Input'!$B$24)<='P-Parametri'!$C$15,'P-Parametri'!$B$15,IF((($A11*(1-'P-Parametri'!$B$22))+'1-Input'!$B$24)<='P-Parametri'!$B$6,'P-Parametri'!$B$16+'P-Parametri'!$C$16*('P-Parametri'!$B$6-(($A11*(1-'P-Parametri'!$B$22))+'1-Input'!$B$24))/'P-Parametri'!$D$16,IF((($A11*(1-'P-Parametri'!$B$22))+'1-Input'!$B$24)<='P-Parametri'!$B$7,'P-Parametri'!$B$17*('P-Parametri'!$B$7-(($A11*(1-'P-Parametri'!$B$22))+'1-Input'!$B$24))/'P-Parametri'!$C$17,0)))))-(IF(($A11*(1-'P-Parametri'!$B$22))>0,IF((($A11*(1-'P-Parametri'!$B$22))+'1-Input'!$B$24)<='P-Parametri'!$C$21,0,IF((($A11*(1-'P-Parametri'!$B$22))+'1-Input'!$B$24)<='P-Parametri'!$D$21,'P-Parametri'!$B$21,IF((($A11*(1-'P-Parametri'!$B$22))+'1-Input'!$B$24)<'P-Parametri'!$E$21,'P-Parametri'!$B$21*('P-Parametri'!$E$21-(($A11*(1-'P-Parametri'!$B$22))+'1-Input'!$B$24))/('P-Parametri'!$E$21-'P-Parametri'!$D$21),0))),0)))>0,'P-Parametri'!$B$11*(($A11*(1-'P-Parametri'!$B$22))+'1-Input'!$B$24),0))+(IF(AND((($A11*(1-'P-Parametri'!$B$22))+'1-Input'!$B$24)<='P-Parametri'!$C$18,(IF((($A11*(1-'P-Parametri'!$B$22))+'1-Input'!$B$24)<='P-Parametri'!$B$6,'P-Parametri'!$C$6*(($A11*(1-'P-Parametri'!$B$22))+'1-Input'!$B$24),IF((($A11*(1-'P-Parametri'!$B$22))+'1-Input'!$B$24)<='P-Parametri'!$B$7,'P-Parametri'!$B$9+'P-Parametri'!$C$7*((($A11*(1-'P-Parametri'!$B$22))+'1-Input'!$B$24)-'P-Parametri'!$B$6),'P-Parametri'!$B$10+'P-Parametri'!$C$8*((($A11*(1-'P-Parametri'!$B$22))+'1-Input'!$B$24)-'P-Parametri'!$B$7))))>(MAX(IF((($A11*(1-'P-Parametri'!$B$22))+'1-Input'!$B$24)<='P-Parametri'!$C$12,'P-Parametri'!$B$12,IF((($A11*(1-'P-Parametri'!$B$22))+'1-Input'!$B$24)<='P-Parametri'!$B$6,'P-Parametri'!$B$13+'P-Parametri'!$C$13*('P-Parametri'!$B$6-(($A11*(1-'P-Parametri'!$B$22))+'1-Input'!$B$24))/'P-Parametri'!$D$13,IF((($A11*(1-'P-Parametri'!$B$22))+'1-Input'!$B$24)<='P-Parametri'!$B$7,'P-Parametri'!$B$14*('P-Parametri'!$B$7-(($A11*(1-'P-Parametri'!$B$22))+'1-Input'!$B$24))/'P-Parametri'!$C$14,0))),IF((($A11*(1-'P-Parametri'!$B$22))+'1-Input'!$B$24)<='P-Parametri'!$C$15,'P-Parametri'!$B$15,IF((($A11*(1-'P-Parametri'!$B$22))+'1-Input'!$B$24)<='P-Parametri'!$B$6,'P-Parametri'!$B$16+'P-Parametri'!$C$16*('P-Parametri'!$B$6-(($A11*(1-'P-Parametri'!$B$22))+'1-Input'!$B$24))/'P-Parametri'!$D$16,IF((($A11*(1-'P-Parametri'!$B$22))+'1-Input'!$B$24)<='P-Parametri'!$B$7,'P-Parametri'!$B$17*('P-Parametri'!$B$7-(($A11*(1-'P-Parametri'!$B$22))+'1-Input'!$B$24))/'P-Parametri'!$C$17,0)))))-'P-Parametri'!$D$18),'P-Parametri'!$B$18,0))+(IF(($A11*(1-'P-Parametri'!$B$22))>0,IF((($A11*(1-'P-Parametri'!$B$22))+'1-Input'!$B$24)>'P-Parametri'!$D$20,0,IF((($A11*(1-'P-Parametri'!$B$22))+'1-Input'!$B$24)<='P-Parametri'!$B$20,'P-Parametri'!$B$19*($A11*(1-'P-Parametri'!$B$22)),IF((($A11*(1-'P-Parametri'!$B$22))+'1-Input'!$B$24)<='P-Parametri'!$C$20,'P-Parametri'!$C$19*($A11*(1-'P-Parametri'!$B$22)),'P-Parametri'!$D$19*($A11*(1-'P-Parametri'!$B$22))))),0))-'6-Fisco'!$C$5 -> 10904.342 | N11: =M11/A11 -> 0.72695612
A12: 18000 | B12: =$A12*'P-Parametri'!$B$22 -> 1654.2 | C12: =($A12*(1-'P-Parametri'!$B$22)) -> 16345.8 | D12: =IF($C12<='P-Parametri'!$B$6,'P-Parametri'!$C$6*$C12,IF($C12<='P-Parametri'!$B$7,'P-Parametri'!$B$9+'P-Parametri'!$C$7*($C12-'P-Parametri'!$B$6),'P-Parametri'!$B$10+'P-Parametri'!$C$8*($C12-'P-Parametri'!$B$7))) -> 3759.534 | E12: =IF($C12<='P-Parametri'!$C$12,'P-Parametri'!$B$12,IF($C12<='P-Parametri'!$B$6,'P-Parametri'!$B$13+'P-Parametri'!$C$13*('P-Parametri'!$B$6-$C12)/'P-Parametri'!$D$13,IF($C12<='P-Parametri'!$B$7,'P-Parametri'!$B$14*('P-Parametri'!$B$7-$C12)/'P-Parametri'!$C$14,0))) -> 2976.8075 | F12: =IF($C12<='P-Parametri'!$C$21,0,IF($C12<='P-Parametri'!$D$21,'P-Parametri'!$B$21,IF($C12<'P-Parametri'!$E$21,'P-Parametri'!$B$21*('P-Parametri'!$E$21-$C12)/('P-Parametri'!$E$21-'P-Parametri'!$D$21),0))) -> 0 | G12: =MAX(0,D12-E12-F12) -> 782.72646 | H12: =IF(G12>0,'P-Parametri'!$B$11*C12,0) -> 326.916 | I12: =IF(AND(C12<='P-Parametri'!$C$18,D12>E12-'P-Parametri'!$D$18),'P-Parametri'!$B$18,0) -> 0 | J12: =IF($C12>'P-Parametri'!$D$20,0,IF($C12<='P-Parametri'!$B$20,'P-Parametri'!$B$19*$C12,IF($C12<='P-Parametri'!$C$20,'P-Parametri'!$C$19*$C12,'P-Parametri'!$D$19*$C12))) -> 784.5984 | K12: =C12-G12-H12+I12+J12 -> 16020.756 | L12: =K12/A12 -> 0.890042 | M12: =(($A12*(1-'P-Parametri'!$B$22))+'1-Input'!$B$24)-(MAX(0,(IF((($A12*(1-'P-Parametri'!$B$22))+'1-Input'!$B$24)<='P-Parametri'!$B$6,'P-Parametri'!$C$6*(($A12*(1-'P-Parametri'!$B$22))+'1-Input'!$B$24),IF((($A12*(1-'P-Parametri'!$B$22))+'1-Input'!$B$24)<='P-Parametri'!$B$7,'P-Parametri'!$B$9+'P-Parametri'!$C$7*((($A12*(1-'P-Parametri'!$B$22))+'1-Input'!$B$24)-'P-Parametri'!$B$6),'P-Parametri'!$B$10+'P-Parametri'!$C$8*((($A12*(1-'P-Parametri'!$B$22))+'1-Input'!$B$24)-'P-Parametri'!$B$7))))-(MAX(IF((($A12*(1-'P-Parametri'!$B$22))+'1-Input'!$B$24)<='P-Parametri'!$C$12,'P-Parametri'!$B$12,IF((($A12*(1-'P-Parametri'!$B$22))+'1-Input'!$B$24)<='P-Parametri'!$B$6,'P-Parametri'!$B$13+'P-Parametri'!$C$13*('P-Parametri'!$B$6-(($A12*(1-'P-Parametri'!$B$22))+'1-Input'!$B$24))/'P-Parametri'!$D$13,IF((($A12*(1-'P-Parametri'!$B$22))+'1-Input'!$B$24)<='P-Parametri'!$B$7,'P-Parametri'!$B$14*('P-Parametri'!$B$7-(($A12*(1-'P-Parametri'!$B$22))+'1-Input'!$B$24))/'P-Parametri'!$C$14,0))),IF((($A12*(1-'P-Parametri'!$B$22))+'1-Input'!$B$24)<='P-Parametri'!$C$15,'P-Parametri'!$B$15,IF((($A12*(1-'P-Parametri'!$B$22))+'1-Input'!$B$24)<='P-Parametri'!$B$6,'P-Parametri'!$B$16+'P-Parametri'!$C$16*('P-Parametri'!$B$6-(($A12*(1-'P-Parametri'!$B$22))+'1-Input'!$B$24))/'P-Parametri'!$D$16,IF((($A12*(1-'P-Parametri'!$B$22))+'1-Input'!$B$24)<='P-Parametri'!$B$7,'P-Parametri'!$B$17*('P-Parametri'!$B$7-(($A12*(1-'P-Parametri'!$B$22))+'1-Input'!$B$24))/'P-Parametri'!$C$17,0)))))-(IF(($A12*(1-'P-Parametri'!$B$22))>0,IF((($A12*(1-'P-Parametri'!$B$22))+'1-Input'!$B$24)<='P-Parametri'!$C$21,0,IF((($A12*(1-'P-Parametri'!$B$22))+'1-Input'!$B$24)<='P-Parametri'!$D$21,'P-Parametri'!$B$21,IF((($A12*(1-'P-Parametri'!$B$22))+'1-Input'!$B$24)<'P-Parametri'!$E$21,'P-Parametri'!$B$21*('P-Parametri'!$E$21-(($A12*(1-'P-Parametri'!$B$22))+'1-Input'!$B$24))/('P-Parametri'!$E$21-'P-Parametri'!$D$21),0))),0))))-(IF(MAX(0,(IF((($A12*(1-'P-Parametri'!$B$22))+'1-Input'!$B$24)<='P-Parametri'!$B$6,'P-Parametri'!$C$6*(($A12*(1-'P-Parametri'!$B$22))+'1-Input'!$B$24),IF((($A12*(1-'P-Parametri'!$B$22))+'1-Input'!$B$24)<='P-Parametri'!$B$7,'P-Parametri'!$B$9+'P-Parametri'!$C$7*((($A12*(1-'P-Parametri'!$B$22))+'1-Input'!$B$24)-'P-Parametri'!$B$6),'P-Parametri'!$B$10+'P-Parametri'!$C$8*((($A12*(1-'P-Parametri'!$B$22))+'1-Input'!$B$24)-'P-Parametri'!$B$7))))-(MAX(IF((($A12*(1-'P-Parametri'!$B$22))+'1-Input'!$B$24)<='P-Parametri'!$C$12,'P-Parametri'!$B$12,IF((($A12*(1-'P-Parametri'!$B$22))+'1-Input'!$B$24)<='P-Parametri'!$B$6,'P-Parametri'!$B$13+'P-Parametri'!$C$13*('P-Parametri'!$B$6-(($A12*(1-'P-Parametri'!$B$22))+'1-Input'!$B$24))/'P-Parametri'!$D$13,IF((($A12*(1-'P-Parametri'!$B$22))+'1-Input'!$B$24)<='P-Parametri'!$B$7,'P-Parametri'!$B$14*('P-Parametri'!$B$7-(($A12*(1-'P-Parametri'!$B$22))+'1-Input'!$B$24))/'P-Parametri'!$C$14,0))),IF((($A12*(1-'P-Parametri'!$B$22))+'1-Input'!$B$24)<='P-Parametri'!$C$15,'P-Parametri'!$B$15,IF((($A12*(1-'P-Parametri'!$B$22))+'1-Input'!$B$24)<='P-Parametri'!$B$6,'P-Parametri'!$B$16+'P-Parametri'!$C$16*('P-Parametri'!$B$6-(($A12*(1-'P-Parametri'!$B$22))+'1-Input'!$B$24))/'P-Parametri'!$D$16,IF((($A12*(1-'P-Parametri'!$B$22))+'1-Input'!$B$24)<='P-Parametri'!$B$7,'P-Parametri'!$B$17*('P-Parametri'!$B$7-(($A12*(1-'P-Parametri'!$B$22))+'1-Input'!$B$24))/'P-Parametri'!$C$17,0)))))-(IF(($A12*(1-'P-Parametri'!$B$22))>0,IF((($A12*(1-'P-Parametri'!$B$22))+'1-Input'!$B$24)<='P-Parametri'!$C$21,0,IF((($A12*(1-'P-Parametri'!$B$22))+'1-Input'!$B$24)<='P-Parametri'!$D$21,'P-Parametri'!$B$21,IF((($A12*(1-'P-Parametri'!$B$22))+'1-Input'!$B$24)<'P-Parametri'!$E$21,'P-Parametri'!$B$21*('P-Parametri'!$E$21-(($A12*(1-'P-Parametri'!$B$22))+'1-Input'!$B$24))/('P-Parametri'!$E$21-'P-Parametri'!$D$21),0))),0)))>0,'P-Parametri'!$B$11*(($A12*(1-'P-Parametri'!$B$22))+'1-Input'!$B$24),0))+(IF(AND((($A12*(1-'P-Parametri'!$B$22))+'1-Input'!$B$24)<='P-Parametri'!$C$18,(IF((($A12*(1-'P-Parametri'!$B$22))+'1-Input'!$B$24)<='P-Parametri'!$B$6,'P-Parametri'!$C$6*(($A12*(1-'P-Parametri'!$B$22))+'1-Input'!$B$24),IF((($A12*(1-'P-Parametri'!$B$22))+'1-Input'!$B$24)<='P-Parametri'!$B$7,'P-Parametri'!$B$9+'P-Parametri'!$C$7*((($A12*(1-'P-Parametri'!$B$22))+'1-Input'!$B$24)-'P-Parametri'!$B$6),'P-Parametri'!$B$10+'P-Parametri'!$C$8*((($A12*(1-'P-Parametri'!$B$22))+'1-Input'!$B$24)-'P-Parametri'!$B$7))))>(MAX(IF((($A12*(1-'P-Parametri'!$B$22))+'1-Input'!$B$24)<='P-Parametri'!$C$12,'P-Parametri'!$B$12,IF((($A12*(1-'P-Parametri'!$B$22))+'1-Input'!$B$24)<='P-Parametri'!$B$6,'P-Parametri'!$B$13+'P-Parametri'!$C$13*('P-Parametri'!$B$6-(($A12*(1-'P-Parametri'!$B$22))+'1-Input'!$B$24))/'P-Parametri'!$D$13,IF((($A12*(1-'P-Parametri'!$B$22))+'1-Input'!$B$24)<='P-Parametri'!$B$7,'P-Parametri'!$B$14*('P-Parametri'!$B$7-(($A12*(1-'P-Parametri'!$B$22))+'1-Input'!$B$24))/'P-Parametri'!$C$14,0))),IF((($A12*(1-'P-Parametri'!$B$22))+'1-Input'!$B$24)<='P-Parametri'!$C$15,'P-Parametri'!$B$15,IF((($A12*(1-'P-Parametri'!$B$22))+'1-Input'!$B$24)<='P-Parametri'!$B$6,'P-Parametri'!$B$16+'P-Parametri'!$C$16*('P-Parametri'!$B$6-(($A12*(1-'P-Parametri'!$B$22))+'1-Input'!$B$24))/'P-Parametri'!$D$16,IF((($A12*(1-'P-Parametri'!$B$22))+'1-Input'!$B$24)<='P-Parametri'!$B$7,'P-Parametri'!$B$17*('P-Parametri'!$B$7-(($A12*(1-'P-Parametri'!$B$22))+'1-Input'!$B$24))/'P-Parametri'!$C$17,0)))))-'P-Parametri'!$D$18),'P-Parametri'!$B$18,0))+(IF(($A12*(1-'P-Parametri'!$B$22))>0,IF((($A12*(1-'P-Parametri'!$B$22))+'1-Input'!$B$24)>'P-Parametri'!$D$20,0,IF((($A12*(1-'P-Parametri'!$B$22))+'1-Input'!$B$24)<='P-Parametri'!$B$20,'P-Parametri'!$B$19*($A12*(1-'P-Parametri'!$B$22)),IF((($A12*(1-'P-Parametri'!$B$22))+'1-Input'!$B$24)<='P-Parametri'!$C$20,'P-Parametri'!$C$19*($A12*(1-'P-Parametri'!$B$22)),'P-Parametri'!$D$19*($A12*(1-'P-Parametri'!$B$22))))),0))-'6-Fisco'!$C$5 -> 12098.08 | N12: =M12/A12 -> 0.67211558
A13: 20000 | B13: =$A13*'P-Parametri'!$B$22 -> 1838 | C13: =($A13*(1-'P-Parametri'!$B$22)) -> 18162 | D13: =IF($C13<='P-Parametri'!$B$6,'P-Parametri'!$C$6*$C13,IF($C13<='P-Parametri'!$B$7,'P-Parametri'!$B$9+'P-Parametri'!$C$7*($C13-'P-Parametri'!$B$6),'P-Parametri'!$B$10+'P-Parametri'!$C$8*($C13-'P-Parametri'!$B$7))) -> 4177.26 | E13: =IF($C13<='P-Parametri'!$C$12,'P-Parametri'!$B$12,IF($C13<='P-Parametri'!$B$6,'P-Parametri'!$B$13+'P-Parametri'!$C$13*('P-Parametri'!$B$6-$C13)/'P-Parametri'!$D$13,IF($C13<='P-Parametri'!$B$7,'P-Parametri'!$B$14*('P-Parametri'!$B$7-$C13)/'P-Parametri'!$C$14,0))) -> 2810.5554 | F13: =IF($C13<='P-Parametri'!$C$21,0,IF($C13<='P-Parametri'!$D$21,'P-Parametri'!$B$21,IF($C13<'P-Parametri'!$E$21,'P-Parametri'!$B$21*('P-Parametri'!$E$21-$C13)/('P-Parametri'!$E$21-'P-Parametri'!$D$21),0))) -> 0 | G13: =MAX(0,D13-E13-F13) -> 1366.7046 | H13: =IF(G13>0,'P-Parametri'!$B$11*C13,0) -> 363.24 | I13: =IF(AND(C13<='P-Parametri'!$C$18,D13>E13-'P-Parametri'!$D$18),'P-Parametri'!$B$18,0) -> 0 | J13: =IF($C13>'P-Parametri'!$D$20,0,IF($C13<='P-Parametri'!$B$20,'P-Parametri'!$B$19*$C13,IF($C13<='P-Parametri'!$C$20,'P-Parametri'!$C$19*$C13,'P-Parametri'!$D$19*$C13))) -> 871.776 | K13: =C13-G13-H13+I13+J13 -> 17303.831 | L13: =K13/A13 -> 0.86519157 | M13: =(($A13*(1-'P-Parametri'!$B$22))+'1-Input'!$B$24)-(MAX(0,(IF((($A13*(1-'P-Parametri'!$B$22))+'1-Input'!$B$24)<='P-Parametri'!$B$6,'P-Parametri'!$C$6*(($A13*(1-'P-Parametri'!$B$22))+'1-Input'!$B$24),IF((($A13*(1-'P-Parametri'!$B$22))+'1-Input'!$B$24)<='P-Parametri'!$B$7,'P-Parametri'!$B$9+'P-Parametri'!$C$7*((($A13*(1-'P-Parametri'!$B$22))+'1-Input'!$B$24)-'P-Parametri'!$B$6),'P-Parametri'!$B$10+'P-Parametri'!$C$8*((($A13*(1-'P-Parametri'!$B$22))+'1-Input'!$B$24)-'P-Parametri'!$B$7))))-(MAX(IF((($A13*(1-'P-Parametri'!$B$22))+'1-Input'!$B$24)<='P-Parametri'!$C$12,'P-Parametri'!$B$12,IF((($A13*(1-'P-Parametri'!$B$22))+'1-Input'!$B$24)<='P-Parametri'!$B$6,'P-Parametri'!$B$13+'P-Parametri'!$C$13*('P-Parametri'!$B$6-(($A13*(1-'P-Parametri'!$B$22))+'1-Input'!$B$24))/'P-Parametri'!$D$13,IF((($A13*(1-'P-Parametri'!$B$22))+'1-Input'!$B$24)<='P-Parametri'!$B$7,'P-Parametri'!$B$14*('P-Parametri'!$B$7-(($A13*(1-'P-Parametri'!$B$22))+'1-Input'!$B$24))/'P-Parametri'!$C$14,0))),IF((($A13*(1-'P-Parametri'!$B$22))+'1-Input'!$B$24)<='P-Parametri'!$C$15,'P-Parametri'!$B$15,IF((($A13*(1-'P-Parametri'!$B$22))+'1-Input'!$B$24)<='P-Parametri'!$B$6,'P-Parametri'!$B$16+'P-Parametri'!$C$16*('P-Parametri'!$B$6-(($A13*(1-'P-Parametri'!$B$22))+'1-Input'!$B$24))/'P-Parametri'!$D$16,IF((($A13*(1-'P-Parametri'!$B$22))+'1-Input'!$B$24)<='P-Parametri'!$B$7,'P-Parametri'!$B$17*('P-Parametri'!$B$7-(($A13*(1-'P-Parametri'!$B$22))+'1-Input'!$B$24))/'P-Parametri'!$C$17,0)))))-(IF(($A13*(1-'P-Parametri'!$B$22))>0,IF((($A13*(1-'P-Parametri'!$B$22))+'1-Input'!$B$24)<='P-Parametri'!$C$21,0,IF((($A13*(1-'P-Parametri'!$B$22))+'1-Input'!$B$24)<='P-Parametri'!$D$21,'P-Parametri'!$B$21,IF((($A13*(1-'P-Parametri'!$B$22))+'1-Input'!$B$24)<'P-Parametri'!$E$21,'P-Parametri'!$B$21*('P-Parametri'!$E$21-(($A13*(1-'P-Parametri'!$B$22))+'1-Input'!$B$24))/('P-Parametri'!$E$21-'P-Parametri'!$D$21),0))),0))))-(IF(MAX(0,(IF((($A13*(1-'P-Parametri'!$B$22))+'1-Input'!$B$24)<='P-Parametri'!$B$6,'P-Parametri'!$C$6*(($A13*(1-'P-Parametri'!$B$22))+'1-Input'!$B$24),IF((($A13*(1-'P-Parametri'!$B$22))+'1-Input'!$B$24)<='P-Parametri'!$B$7,'P-Parametri'!$B$9+'P-Parametri'!$C$7*((($A13*(1-'P-Parametri'!$B$22))+'1-Input'!$B$24)-'P-Parametri'!$B$6),'P-Parametri'!$B$10+'P-Parametri'!$C$8*((($A13*(1-'P-Parametri'!$B$22))+'1-Input'!$B$24)-'P-Parametri'!$B$7))))-(MAX(IF((($A13*(1-'P-Parametri'!$B$22))+'1-Input'!$B$24)<='P-Parametri'!$C$12,'P-Parametri'!$B$12,IF((($A13*(1-'P-Parametri'!$B$22))+'1-Input'!$B$24)<='P-Parametri'!$B$6,'P-Parametri'!$B$13+'P-Parametri'!$C$13*('P-Parametri'!$B$6-(($A13*(1-'P-Parametri'!$B$22))+'1-Input'!$B$24))/'P-Parametri'!$D$13,IF((($A13*(1-'P-Parametri'!$B$22))+'1-Input'!$B$24)<='P-Parametri'!$B$7,'P-Parametri'!$B$14*('P-Parametri'!$B$7-(($A13*(1-'P-Parametri'!$B$22))+'1-Input'!$B$24))/'P-Parametri'!$C$14,0))),IF((($A13*(1-'P-Parametri'!$B$22))+'1-Input'!$B$24)<='P-Parametri'!$C$15,'P-Parametri'!$B$15,IF((($A13*(1-'P-Parametri'!$B$22))+'1-Input'!$B$24)<='P-Parametri'!$B$6,'P-Parametri'!$B$16+'P-Parametri'!$C$16*('P-Parametri'!$B$6-(($A13*(1-'P-Parametri'!$B$22))+'1-Input'!$B$24))/'P-Parametri'!$D$16,IF((($A13*(1-'P-Parametri'!$B$22))+'1-Input'!$B$24)<='P-Parametri'!$B$7,'P-Parametri'!$B$17*('P-Parametri'!$B$7-(($A13*(1-'P-Parametri'!$B$22))+'1-Input'!$B$24))/'P-Parametri'!$C$17,0)))))-(IF(($A13*(1-'P-Parametri'!$B$22))>0,IF((($A13*(1-'P-Parametri'!$B$22))+'1-Input'!$B$24)<='P-Parametri'!$C$21,0,IF((($A13*(1-'P-Parametri'!$B$22))+'1-Input'!$B$24)<='P-Parametri'!$D$21,'P-Parametri'!$B$21,IF((($A13*(1-'P-Parametri'!$B$22))+'1-Input'!$B$24)<'P-Parametri'!$E$21,'P-Parametri'!$B$21*('P-Parametri'!$E$21-(($A13*(1-'P-Parametri'!$B$22))+'1-Input'!$B$24))/('P-Parametri'!$E$21-'P-Parametri'!$D$21),0))),0)))>0,'P-Parametri'!$B$11*(($A13*(1-'P-Parametri'!$B$22))+'1-Input'!$B$24),0))+(IF(AND((($A13*(1-'P-Parametri'!$B$22))+'1-Input'!$B$24)<='P-Parametri'!$C$18,(IF((($A13*(1-'P-Parametri'!$B$22))+'1-Input'!$B$24)<='P-Parametri'!$B$6,'P-Parametri'!$C$6*(($A13*(1-'P-Parametri'!$B$22))+'1-Input'!$B$24),IF((($A13*(1-'P-Parametri'!$B$22))+'1-Input'!$B$24)<='P-Parametri'!$B$7,'P-Parametri'!$B$9+'P-Parametri'!$C$7*((($A13*(1-'P-Parametri'!$B$22))+'1-Input'!$B$24)-'P-Parametri'!$B$6),'P-Parametri'!$B$10+'P-Parametri'!$C$8*((($A13*(1-'P-Parametri'!$B$22))+'1-Input'!$B$24)-'P-Parametri'!$B$7))))>(MAX(IF((($A13*(1-'P-Parametri'!$B$22))+'1-Input'!$B$24)<='P-Parametri'!$C$12,'P-Parametri'!$B$12,IF((($A13*(1-'P-Parametri'!$B$22))+'1-Input'!$B$24)<='P-Parametri'!$B$6,'P-Parametri'!$B$13+'P-Parametri'!$C$13*('P-Parametri'!$B$6-(($A13*(1-'P-Parametri'!$B$22))+'1-Input'!$B$24))/'P-Parametri'!$D$13,IF((($A13*(1-'P-Parametri'!$B$22))+'1-Input'!$B$24)<='P-Parametri'!$B$7,'P-Parametri'!$B$14*('P-Parametri'!$B$7-(($A13*(1-'P-Parametri'!$B$22))+'1-Input'!$B$24))/'P-Parametri'!$C$14,0))),IF((($A13*(1-'P-Parametri'!$B$22))+'1-Input'!$B$24)<='P-Parametri'!$C$15,'P-Parametri'!$B$15,IF((($A13*(1-'P-Parametri'!$B$22))+'1-Input'!$B$24)<='P-Parametri'!$B$6,'P-Parametri'!$B$16+'P-Parametri'!$C$16*('P-Parametri'!$B$6-(($A13*(1-'P-Parametri'!$B$22))+'1-Input'!$B$24))/'P-Parametri'!$D$16,IF((($A13*(1-'P-Parametri'!$B$22))+'1-Input'!$B$24)<='P-Parametri'!$B$7,'P-Parametri'!$B$17*('P-Parametri'!$B$7-(($A13*(1-'P-Parametri'!$B$22))+'1-Input'!$B$24))/'P-Parametri'!$C$17,0)))))-'P-Parametri'!$D$18),'P-Parametri'!$B$18,0))+(IF(($A13*(1-'P-Parametri'!$B$22))>0,IF((($A13*(1-'P-Parametri'!$B$22))+'1-Input'!$B$24)>'P-Parametri'!$D$20,0,IF((($A13*(1-'P-Parametri'!$B$22))+'1-Input'!$B$24)<='P-Parametri'!$B$20,'P-Parametri'!$B$19*($A13*(1-'P-Parametri'!$B$22)),IF((($A13*(1-'P-Parametri'!$B$22))+'1-Input'!$B$24)<='P-Parametri'!$C$20,'P-Parametri'!$C$19*($A13*(1-'P-Parametri'!$B$22)),'P-Parametri'!$D$19*($A13*(1-'P-Parametri'!$B$22))))),0))-'6-Fisco'!$C$5 -> 12893.906 | N13: =M13/A13 -> 0.64469531
A14: Le colonne da B a K sono il conto della busta paga di chi NON ha altri redditi: il netto incrementale coincide col netto. La colonna M è lo stesso lavoro fatto da pensionato: reddito complessivo più alto, detrazione dell'art. 13 che si sceglie fra quella da lavoro e quella da pensione (non si cumulano), trattamento integrativo perso. La perdita è di un quinto, non di un terzo.
A20: LA SOGLIA SOTTO LA QUALE LA FINESTRA NON SI CHIUDE AFFATTO
A21: Secante a sei valutazioni sul reddito lordo che rende il netto incrementale post-pensione esattamente pari al lordo. Sotto quella cifra il lavoro rende ancora più del lordo anche da pensionato.
A22: candidato → | B22: =5000 -> 5000 | C22: =7000 -> 7000 | D22: =IFERROR(C22-C23*(C22-B22)/(C23-B23),C22) -> 6104.8271 | E22: =IFERROR(D22-D23*(D22-C22)/(D23-C23),D22) -> 6104.8271 | F22: =IFERROR(E22-E23*(E22-D22)/(E23-D23),E22) -> 6104.8271 | G22: =IFERROR(F22-F23*(F22-E22)/(F23-E23),F22) -> 6104.8271
A23: netto incrementale − lordo → | B23: =((B22*(1-'P-Parametri'!$B$22))+'1-Input'!$B$24)-(MAX(0,(IF(((B22*(1-'P-Parametri'!$B$22))+'1-Input'!$B$24)<='P-Parametri'!$B$6,'P-Parametri'!$C$6*((B22*(1-'P-Parametri'!$B$22))+'1-Input'!$B$24),IF(((B22*(1-'P-Parametri'!$B$22))+'1-Input'!$B$24)<='P-Parametri'!$B$7,'P-Parametri'!$B$9+'P-Parametri'!$C$7*(((B22*(1-'P-Parametri'!$B$22))+'1-Input'!$B$24)-'P-Parametri'!$B$6),'P-Parametri'!$B$10+'P-Parametri'!$C$8*(((B22*(1-'P-Parametri'!$B$22))+'1-Input'!$B$24)-'P-Parametri'!$B$7))))-(MAX(IF(((B22*(1-'P-Parametri'!$B$22))+'1-Input'!$B$24)<='P-Parametri'!$C$12,'P-Parametri'!$B$12,IF(((B22*(1-'P-Parametri'!$B$22))+'1-Input'!$B$24)<='P-Parametri'!$B$6,'P-Parametri'!$B$13+'P-Parametri'!$C$13*('P-Parametri'!$B$6-((B22*(1-'P-Parametri'!$B$22))+'1-Input'!$B$24))/'P-Parametri'!$D$13,IF(((B22*(1-'P-Parametri'!$B$22))+'1-Input'!$B$24)<='P-Parametri'!$B$7,'P-Parametri'!$B$14*('P-Parametri'!$B$7-((B22*(1-'P-Parametri'!$B$22))+'1-Input'!$B$24))/'P-Parametri'!$C$14,0))),IF(((B22*(1-'P-Parametri'!$B$22))+'1-Input'!$B$24)<='P-Parametri'!$C$15,'P-Parametri'!$B$15,IF(((B22*(1-'P-Parametri'!$B$22))+'1-Input'!$B$24)<='P-Parametri'!$B$6,'P-Parametri'!$B$16+'P-Parametri'!$C$16*('P-Parametri'!$B$6-((B22*(1-'P-Parametri'!$B$22))+'1-Input'!$B$24))/'P-Parametri'!$D$16,IF(((B22*(1-'P-Parametri'!$B$22))+'1-Input'!$B$24)<='P-Parametri'!$B$7,'P-Parametri'!$B$17*('P-Parametri'!$B$7-((B22*(1-'P-Parametri'!$B$22))+'1-Input'!$B$24))/'P-Parametri'!$C$17,0)))))-(IF((B22*(1-'P-Parametri'!$B$22))>0,IF(((B22*(1-'P-Parametri'!$B$22))+'1-Input'!$B$24)<='P-Parametri'!$C$21,0,IF(((B22*(1-'P-Parametri'!$B$22))+'1-Input'!$B$24)<='P-Parametri'!$D$21,'P-Parametri'!$B$21,IF(((B22*(1-'P-Parametri'!$B$22))+'1-Input'!$B$24)<'P-Parametri'!$E$21,'P-Parametri'!$B$21*('P-Parametri'!$E$21-((B22*(1-'P-Parametri'!$B$22))+'1-Input'!$B$24))/('P-Parametri'!$E$21-'P-Parametri'!$D$21),0))),0))))-(IF(MAX(0,(IF(((B22*(1-'P-Parametri'!$B$22))+'1-Input'!$B$24)<='P-Parametri'!$B$6,'P-Parametri'!$C$6*((B22*(1-'P-Parametri'!$B$22))+'1-Input'!$B$24),IF(((B22*(1-'P-Parametri'!$B$22))+'1-Input'!$B$24)<='P-Parametri'!$B$7,'P-Parametri'!$B$9+'P-Parametri'!$C$7*(((B22*(1-'P-Parametri'!$B$22))+'1-Input'!$B$24)-'P-Parametri'!$B$6),'P-Parametri'!$B$10+'P-Parametri'!$C$8*(((B22*(1-'P-Parametri'!$B$22))+'1-Input'!$B$24)-'P-Parametri'!$B$7))))-(MAX(IF(((B22*(1-'P-Parametri'!$B$22))+'1-Input'!$B$24)<='P-Parametri'!$C$12,'P-Parametri'!$B$12,IF(((B22*(1-'P-Parametri'!$B$22))+'1-Input'!$B$24)<='P-Parametri'!$B$6,'P-Parametri'!$B$13+'P-Parametri'!$C$13*('P-Parametri'!$B$6-((B22*(1-'P-Parametri'!$B$22))+'1-Input'!$B$24))/'P-Parametri'!$D$13,IF(((B22*(1-'P-Parametri'!$B$22))+'1-Input'!$B$24)<='P-Parametri'!$B$7,'P-Parametri'!$B$14*('P-Parametri'!$B$7-((B22*(1-'P-Parametri'!$B$22))+'1-Input'!$B$24))/'P-Parametri'!$C$14,0))),IF(((B22*(1-'P-Parametri'!$B$22))+'1-Input'!$B$24)<='P-Parametri'!$C$15,'P-Parametri'!$B$15,IF(((B22*(1-'P-Parametri'!$B$22))+'1-Input'!$B$24)<='P-Parametri'!$B$6,'P-Parametri'!$B$16+'P-Parametri'!$C$16*('P-Parametri'!$B$6-((B22*(1-'P-Parametri'!$B$22))+'1-Input'!$B$24))/'P-Parametri'!$D$16,IF(((B22*(1-'P-Parametri'!$B$22))+'1-Input'!$B$24)<='P-Parametri'!$B$7,'P-Parametri'!$B$17*('P-Parametri'!$B$7-((B22*(1-'P-Parametri'!$B$22))+'1-Input'!$B$24))/'P-Parametri'!$C$17,0)))))-(IF((B22*(1-'P-Parametri'!$B$22))>0,IF(((B22*(1-'P-Parametri'!$B$22))+'1-Input'!$B$24)<='P-Parametri'!$C$21,0,IF(((B22*(1-'P-Parametri'!$B$22))+'1-Input'!$B$24)<='P-Parametri'!$D$21,'P-Parametri'!$B$21,IF(((B22*(1-'P-Parametri'!$B$22))+'1-Input'!$B$24)<'P-Parametri'!$E$21,'P-Parametri'!$B$21*('P-Parametri'!$E$21-((B22*(1-'P-Parametri'!$B$22))+'1-Input'!$B$24))/('P-Parametri'!$E$21-'P-Parametri'!$D$21),0))),0)))>0,'P-Parametri'!$B$11*((B22*(1-'P-Parametri'!$B$22))+'1-Input'!$B$24),0))+(IF(AND(((B22*(1-'P-Parametri'!$B$22))+'1-Input'!$B$24)<='P-Parametri'!$C$18,(IF(((B22*(1-'P-Parametri'!$B$22))+'1-Input'!$B$24)<='P-Parametri'!$B$6,'P-Parametri'!$C$6*((B22*(1-'P-Parametri'!$B$22))+'1-Input'!$B$24),IF(((B22*(1-'P-Parametri'!$B$22))+'1-Input'!$B$24)<='P-Parametri'!$B$7,'P-Parametri'!$B$9+'P-Parametri'!$C$7*(((B22*(1-'P-Parametri'!$B$22))+'1-Input'!$B$24)-'P-Parametri'!$B$6),'P-Parametri'!$B$10+'P-Parametri'!$C$8*(((B22*(1-'P-Parametri'!$B$22))+'1-Input'!$B$24)-'P-Parametri'!$B$7))))>(MAX(IF(((B22*(1-'P-Parametri'!$B$22))+'1-Input'!$B$24)<='P-Parametri'!$C$12,'P-Parametri'!$B$12,IF(((B22*(1-'P-Parametri'!$B$22))+'1-Input'!$B$24)<='P-Parametri'!$B$6,'P-Parametri'!$B$13+'P-Parametri'!$C$13*('P-Parametri'!$B$6-((B22*(1-'P-Parametri'!$B$22))+'1-Input'!$B$24))/'P-Parametri'!$D$13,IF(((B22*(1-'P-Parametri'!$B$22))+'1-Input'!$B$24)<='P-Parametri'!$B$7,'P-Parametri'!$B$14*('P-Parametri'!$B$7-((B22*(1-'P-Parametri'!$B$22))+'1-Input'!$B$24))/'P-Parametri'!$C$14,0))),IF(((B22*(1-'P-Parametri'!$B$22))+'1-Input'!$B$24)<='P-Parametri'!$C$15,'P-Parametri'!$B$15,IF(((B22*(1-'P-Parametri'!$B$22))+'1-Input'!$B$24)<='P-Parametri'!$B$6,'P-Parametri'!$B$16+'P-Parametri'!$C$16*('P-Parametri'!$B$6-((B22*(1-'P-Parametri'!$B$22))+'1-Input'!$B$24))/'P-Parametri'!$D$16,IF(((B22*(1-'P-Parametri'!$B$22))+'1-Input'!$B$24)<='P-Parametri'!$B$7,'P-Parametri'!$B$17*('P-Parametri'!$B$7-((B22*(1-'P-Parametri'!$B$22))+'1-Input'!$B$24))/'P-Parametri'!$C$17,0)))))-'P-Parametri'!$D$18),'P-Parametri'!$B$18,0))+(IF((B22*(1-'P-Parametri'!$B$22))>0,IF(((B22*(1-'P-Parametri'!$B$22))+'1-Input'!$B$24)>'P-Parametri'!$D$20,0,IF(((B22*(1-'P-Parametri'!$B$22))+'1-Input'!$B$24)<='P-Parametri'!$B$20,'P-Parametri'!$B$19*(B22*(1-'P-Parametri'!$B$22)),IF(((B22*(1-'P-Parametri'!$B$22))+'1-Input'!$B$24)<='P-Parametri'!$C$20,'P-Parametri'!$C$19*(B22*(1-'P-Parametri'!$B$22)),'P-Parametri'!$D$19*(B22*(1-'P-Parametri'!$B$22))))),0))-'6-Fisco'!$C$5-B22 -> 444.19692 | C23: =((C22*(1-'P-Parametri'!$B$22))+'1-Input'!$B$24)-(MAX(0,(IF(((C22*(1-'P-Parametri'!$B$22))+'1-Input'!$B$24)<='P-Parametri'!$B$6,'P-Parametri'!$C$6*((C22*(1-'P-Parametri'!$B$22))+'1-Input'!$B$24),IF(((C22*(1-'P-Parametri'!$B$22))+'1-Input'!$B$24)<='P-Parametri'!$B$7,'P-Parametri'!$B$9+'P-Parametri'!$C$7*(((C22*(1-'P-Parametri'!$B$22))+'1-Input'!$B$24)-'P-Parametri'!$B$6),'P-Parametri'!$B$10+'P-Parametri'!$C$8*(((C22*(1-'P-Parametri'!$B$22))+'1-Input'!$B$24)-'P-Parametri'!$B$7))))-(MAX(IF(((C22*(1-'P-Parametri'!$B$22))+'1-Input'!$B$24)<='P-Parametri'!$C$12,'P-Parametri'!$B$12,IF(((C22*(1-'P-Parametri'!$B$22))+'1-Input'!$B$24)<='P-Parametri'!$B$6,'P-Parametri'!$B$13+'P-Parametri'!$C$13*('P-Parametri'!$B$6-((C22*(1-'P-Parametri'!$B$22))+'1-Input'!$B$24))/'P-Parametri'!$D$13,IF(((C22*(1-'P-Parametri'!$B$22))+'1-Input'!$B$24)<='P-Parametri'!$B$7,'P-Parametri'!$B$14*('P-Parametri'!$B$7-((C22*(1-'P-Parametri'!$B$22))+'1-Input'!$B$24))/'P-Parametri'!$C$14,0))),IF(((C22*(1-'P-Parametri'!$B$22))+'1-Input'!$B$24)<='P-Parametri'!$C$15,'P-Parametri'!$B$15,IF(((C22*(1-'P-Parametri'!$B$22))+'1-Input'!$B$24)<='P-Parametri'!$B$6,'P-Parametri'!$B$16+'P-Parametri'!$C$16*('P-Parametri'!$B$6-((C22*(1-'P-Parametri'!$B$22))+'1-Input'!$B$24))/'P-Parametri'!$D$16,IF(((C22*(1-'P-Parametri'!$B$22))+'1-Input'!$B$24)<='P-Parametri'!$B$7,'P-Parametri'!$B$17*('P-Parametri'!$B$7-((C22*(1-'P-Parametri'!$B$22))+'1-Input'!$B$24))/'P-Parametri'!$C$17,0)))))-(IF((C22*(1-'P-Parametri'!$B$22))>0,IF(((C22*(1-'P-Parametri'!$B$22))+'1-Input'!$B$24)<='P-Parametri'!$C$21,0,IF(((C22*(1-'P-Parametri'!$B$22))+'1-Input'!$B$24)<='P-Parametri'!$D$21,'P-Parametri'!$B$21,IF(((C22*(1-'P-Parametri'!$B$22))+'1-Input'!$B$24)<'P-Parametri'!$E$21,'P-Parametri'!$B$21*('P-Parametri'!$E$21-((C22*(1-'P-Parametri'!$B$22))+'1-Input'!$B$24))/('P-Parametri'!$E$21-'P-Parametri'!$D$21),0))),0))))-(IF(MAX(0,(IF(((C22*(1-'P-Parametri'!$B$22))+'1-Input'!$B$24)<='P-Parametri'!$B$6,'P-Parametri'!$C$6*((C22*(1-'P-Parametri'!$B$22))+'1-Input'!$B$24),IF(((C22*(1-'P-Parametri'!$B$22))+'1-Input'!$B$24)<='P-Parametri'!$B$7,'P-Parametri'!$B$9+'P-Parametri'!$C$7*(((C22*(1-'P-Parametri'!$B$22))+'1-Input'!$B$24)-'P-Parametri'!$B$6),'P-Parametri'!$B$10+'P-Parametri'!$C$8*(((C22*(1-'P-Parametri'!$B$22))+'1-Input'!$B$24)-'P-Parametri'!$B$7))))-(MAX(IF(((C22*(1-'P-Parametri'!$B$22))+'1-Input'!$B$24)<='P-Parametri'!$C$12,'P-Parametri'!$B$12,IF(((C22*(1-'P-Parametri'!$B$22))+'1-Input'!$B$24)<='P-Parametri'!$B$6,'P-Parametri'!$B$13+'P-Parametri'!$C$13*('P-Parametri'!$B$6-((C22*(1-'P-Parametri'!$B$22))+'1-Input'!$B$24))/'P-Parametri'!$D$13,IF(((C22*(1-'P-Parametri'!$B$22))+'1-Input'!$B$24)<='P-Parametri'!$B$7,'P-Parametri'!$B$14*('P-Parametri'!$B$7-((C22*(1-'P-Parametri'!$B$22))+'1-Input'!$B$24))/'P-Parametri'!$C$14,0))),IF(((C22*(1-'P-Parametri'!$B$22))+'1-Input'!$B$24)<='P-Parametri'!$C$15,'P-Parametri'!$B$15,IF(((C22*(1-'P-Parametri'!$B$22))+'1-Input'!$B$24)<='P-Parametri'!$B$6,'P-Parametri'!$B$16+'P-Parametri'!$C$16*('P-Parametri'!$B$6-((C22*(1-'P-Parametri'!$B$22))+'1-Input'!$B$24))/'P-Parametri'!$D$16,IF(((C22*(1-'P-Parametri'!$B$22))+'1-Input'!$B$24)<='P-Parametri'!$B$7,'P-Parametri'!$B$17*('P-Parametri'!$B$7-((C22*(1-'P-Parametri'!$B$22))+'1-Input'!$B$24))/'P-Parametri'!$C$17,0)))))-(IF((C22*(1-'P-Parametri'!$B$22))>0,IF(((C22*(1-'P-Parametri'!$B$22))+'1-Input'!$B$24)<='P-Parametri'!$C$21,0,IF(((C22*(1-'P-Parametri'!$B$22))+'1-Input'!$B$24)<='P-Parametri'!$D$21,'P-Parametri'!$B$21,IF(((C22*(1-'P-Parametri'!$B$22))+'1-Input'!$B$24)<'P-Parametri'!$E$21,'P-Parametri'!$B$21*('P-Parametri'!$E$21-((C22*(1-'P-Parametri'!$B$22))+'1-Input'!$B$24))/('P-Parametri'!$E$21-'P-Parametri'!$D$21),0))),0)))>0,'P-Parametri'!$B$11*((C22*(1-'P-Parametri'!$B$22))+'1-Input'!$B$24),0))+(IF(AND(((C22*(1-'P-Parametri'!$B$22))+'1-Input'!$B$24)<='P-Parametri'!$C$18,(IF(((C22*(1-'P-Parametri'!$B$22))+'1-Input'!$B$24)<='P-Parametri'!$B$6,'P-Parametri'!$C$6*((C22*(1-'P-Parametri'!$B$22))+'1-Input'!$B$24),IF(((C22*(1-'P-Parametri'!$B$22))+'1-Input'!$B$24)<='P-Parametri'!$B$7,'P-Parametri'!$B$9+'P-Parametri'!$C$7*(((C22*(1-'P-Parametri'!$B$22))+'1-Input'!$B$24)-'P-Parametri'!$B$6),'P-Parametri'!$B$10+'P-Parametri'!$C$8*(((C22*(1-'P-Parametri'!$B$22))+'1-Input'!$B$24)-'P-Parametri'!$B$7))))>(MAX(IF(((C22*(1-'P-Parametri'!$B$22))+'1-Input'!$B$24)<='P-Parametri'!$C$12,'P-Parametri'!$B$12,IF(((C22*(1-'P-Parametri'!$B$22))+'1-Input'!$B$24)<='P-Parametri'!$B$6,'P-Parametri'!$B$13+'P-Parametri'!$C$13*('P-Parametri'!$B$6-((C22*(1-'P-Parametri'!$B$22))+'1-Input'!$B$24))/'P-Parametri'!$D$13,IF(((C22*(1-'P-Parametri'!$B$22))+'1-Input'!$B$24)<='P-Parametri'!$B$7,'P-Parametri'!$B$14*('P-Parametri'!$B$7-((C22*(1-'P-Parametri'!$B$22))+'1-Input'!$B$24))/'P-Parametri'!$C$14,0))),IF(((C22*(1-'P-Parametri'!$B$22))+'1-Input'!$B$24)<='P-Parametri'!$C$15,'P-Parametri'!$B$15,IF(((C22*(1-'P-Parametri'!$B$22))+'1-Input'!$B$24)<='P-Parametri'!$B$6,'P-Parametri'!$B$16+'P-Parametri'!$C$16*('P-Parametri'!$B$6-((C22*(1-'P-Parametri'!$B$22))+'1-Input'!$B$24))/'P-Parametri'!$D$16,IF(((C22*(1-'P-Parametri'!$B$22))+'1-Input'!$B$24)<='P-Parametri'!$B$7,'P-Parametri'!$B$17*('P-Parametri'!$B$7-((C22*(1-'P-Parametri'!$B$22))+'1-Input'!$B$24))/'P-Parametri'!$C$17,0)))))-'P-Parametri'!$D$18),'P-Parametri'!$B$18,0))+(IF((C22*(1-'P-Parametri'!$B$22))>0,IF(((C22*(1-'P-Parametri'!$B$22))+'1-Input'!$B$24)>'P-Parametri'!$D$20,0,IF(((C22*(1-'P-Parametri'!$B$22))+'1-Input'!$B$24)<='P-Parametri'!$B$20,'P-Parametri'!$B$19*(C22*(1-'P-Parametri'!$B$22)),IF(((C22*(1-'P-Parametri'!$B$22))+'1-Input'!$B$24)<='P-Parametri'!$C$20,'P-Parametri'!$C$19*(C22*(1-'P-Parametri'!$B$22)),'P-Parametri'!$D$19*(C22*(1-'P-Parametri'!$B$22))))),0))-'6-Fisco'!$C$5-C22 -> -359.90523 | D23: =((D22*(1-'P-Parametri'!$B$22))+'1-Input'!$B$24)-(MAX(0,(IF(((D22*(1-'P-Parametri'!$B$22))+'1-Input'!$B$24)<='P-Parametri'!$B$6,'P-Parametri'!$C$6*((D22*(1-'P-Parametri'!$B$22))+'1-Input'!$B$24),IF(((D22*(1-'P-Parametri'!$B$22))+'1-Input'!$B$24)<='P-Parametri'!$B$7,'P-Parametri'!$B$9+'P-Parametri'!$C$7*(((D22*(1-'P-Parametri'!$B$22))+'1-Input'!$B$24)-'P-Parametri'!$B$6),'P-Parametri'!$B$10+'P-Parametri'!$C$8*(((D22*(1-'P-Parametri'!$B$22))+'1-Input'!$B$24)-'P-Parametri'!$B$7))))-(MAX(IF(((D22*(1-'P-Parametri'!$B$22))+'1-Input'!$B$24)<='P-Parametri'!$C$12,'P-Parametri'!$B$12,IF(((D22*(1-'P-Parametri'!$B$22))+'1-Input'!$B$24)<='P-Parametri'!$B$6,'P-Parametri'!$B$13+'P-Parametri'!$C$13*('P-Parametri'!$B$6-((D22*(1-'P-Parametri'!$B$22))+'1-Input'!$B$24))/'P-Parametri'!$D$13,IF(((D22*(1-'P-Parametri'!$B$22))+'1-Input'!$B$24)<='P-Parametri'!$B$7,'P-Parametri'!$B$14*('P-Parametri'!$B$7-((D22*(1-'P-Parametri'!$B$22))+'1-Input'!$B$24))/'P-Parametri'!$C$14,0))),IF(((D22*(1-'P-Parametri'!$B$22))+'1-Input'!$B$24)<='P-Parametri'!$C$15,'P-Parametri'!$B$15,IF(((D22*(1-'P-Parametri'!$B$22))+'1-Input'!$B$24)<='P-Parametri'!$B$6,'P-Parametri'!$B$16+'P-Parametri'!$C$16*('P-Parametri'!$B$6-((D22*(1-'P-Parametri'!$B$22))+'1-Input'!$B$24))/'P-Parametri'!$D$16,IF(((D22*(1-'P-Parametri'!$B$22))+'1-Input'!$B$24)<='P-Parametri'!$B$7,'P-Parametri'!$B$17*('P-Parametri'!$B$7-((D22*(1-'P-Parametri'!$B$22))+'1-Input'!$B$24))/'P-Parametri'!$C$17,0)))))-(IF((D22*(1-'P-Parametri'!$B$22))>0,IF(((D22*(1-'P-Parametri'!$B$22))+'1-Input'!$B$24)<='P-Parametri'!$C$21,0,IF(((D22*(1-'P-Parametri'!$B$22))+'1-Input'!$B$24)<='P-Parametri'!$D$21,'P-Parametri'!$B$21,IF(((D22*(1-'P-Parametri'!$B$22))+'1-Input'!$B$24)<'P-Parametri'!$E$21,'P-Parametri'!$B$21*('P-Parametri'!$E$21-((D22*(1-'P-Parametri'!$B$22))+'1-Input'!$B$24))/('P-Parametri'!$E$21-'P-Parametri'!$D$21),0))),0))))-(IF(MAX(0,(IF(((D22*(1-'P-Parametri'!$B$22))+'1-Input'!$B$24)<='P-Parametri'!$B$6,'P-Parametri'!$C$6*((D22*(1-'P-Parametri'!$B$22))+'1-Input'!$B$24),IF(((D22*(1-'P-Parametri'!$B$22))+'1-Input'!$B$24)<='P-Parametri'!$B$7,'P-Parametri'!$B$9+'P-Parametri'!$C$7*(((D22*(1-'P-Parametri'!$B$22))+'1-Input'!$B$24)-'P-Parametri'!$B$6),'P-Parametri'!$B$10+'P-Parametri'!$C$8*(((D22*(1-'P-Parametri'!$B$22))+'1-Input'!$B$24)-'P-Parametri'!$B$7))))-(MAX(IF(((D22*(1-'P-Parametri'!$B$22))+'1-Input'!$B$24)<='P-Parametri'!$C$12,'P-Parametri'!$B$12,IF(((D22*(1-'P-Parametri'!$B$22))+'1-Input'!$B$24)<='P-Parametri'!$B$6,'P-Parametri'!$B$13+'P-Parametri'!$C$13*('P-Parametri'!$B$6-((D22*(1-'P-Parametri'!$B$22))+'1-Input'!$B$24))/'P-Parametri'!$D$13,IF(((D22*(1-'P-Parametri'!$B$22))+'1-Input'!$B$24)<='P-Parametri'!$B$7,'P-Parametri'!$B$14*('P-Parametri'!$B$7-((D22*(1-'P-Parametri'!$B$22))+'1-Input'!$B$24))/'P-Parametri'!$C$14,0))),IF(((D22*(1-'P-Parametri'!$B$22))+'1-Input'!$B$24)<='P-Parametri'!$C$15,'P-Parametri'!$B$15,IF(((D22*(1-'P-Parametri'!$B$22))+'1-Input'!$B$24)<='P-Parametri'!$B$6,'P-Parametri'!$B$16+'P-Parametri'!$C$16*('P-Parametri'!$B$6-((D22*(1-'P-Parametri'!$B$22))+'1-Input'!$B$24))/'P-Parametri'!$D$16,IF(((D22*(1-'P-Parametri'!$B$22))+'1-Input'!$B$24)<='P-Parametri'!$B$7,'P-Parametri'!$B$17*('P-Parametri'!$B$7-((D22*(1-'P-Parametri'!$B$22))+'1-Input'!$B$24))/'P-Parametri'!$C$17,0)))))-(IF((D22*(1-'P-Parametri'!$B$22))>0,IF(((D22*(1-'P-Parametri'!$B$22))+'1-Input'!$B$24)<='P-Parametri'!$C$21,0,IF(((D22*(1-'P-Parametri'!$B$22))+'1-Input'!$B$24)<='P-Parametri'!$D$21,'P-Parametri'!$B$21,IF(((D22*(1-'P-Parametri'!$B$22))+'1-Input'!$B$24)<'P-Parametri'!$E$21,'P-Parametri'!$B$21*('P-Parametri'!$E$21-((D22*(1-'P-Parametri'!$B$22))+'1-Input'!$B$24))/('P-Parametri'!$E$21-'P-Parametri'!$D$21),0))),0)))>0,'P-Parametri'!$B$11*((D22*(1-'P-Parametri'!$B$22))+'1-Input'!$B$24),0))+(IF(AND(((D22*(1-'P-Parametri'!$B$22))+'1-Input'!$B$24)<='P-Parametri'!$C$18,(IF(((D22*(1-'P-Parametri'!$B$22))+'1-Input'!$B$24)<='P-Parametri'!$B$6,'P-Parametri'!$C$6*((D22*(1-'P-Parametri'!$B$22))+'1-Input'!$B$24),IF(((D22*(1-'P-Parametri'!$B$22))+'1-Input'!$B$24)<='P-Parametri'!$B$7,'P-Parametri'!$B$9+'P-Parametri'!$C$7*(((D22*(1-'P-Parametri'!$B$22))+'1-Input'!$B$24)-'P-Parametri'!$B$6),'P-Parametri'!$B$10+'P-Parametri'!$C$8*(((D22*(1-'P-Parametri'!$B$22))+'1-Input'!$B$24)-'P-Parametri'!$B$7))))>(MAX(IF(((D22*(1-'P-Parametri'!$B$22))+'1-Input'!$B$24)<='P-Parametri'!$C$12,'P-Parametri'!$B$12,IF(((D22*(1-'P-Parametri'!$B$22))+'1-Input'!$B$24)<='P-Parametri'!$B$6,'P-Parametri'!$B$13+'P-Parametri'!$C$13*('P-Parametri'!$B$6-((D22*(1-'P-Parametri'!$B$22))+'1-Input'!$B$24))/'P-Parametri'!$D$13,IF(((D22*(1-'P-Parametri'!$B$22))+'1-Input'!$B$24)<='P-Parametri'!$B$7,'P-Parametri'!$B$14*('P-Parametri'!$B$7-((D22*(1-'P-Parametri'!$B$22))+'1-Input'!$B$24))/'P-Parametri'!$C$14,0))),IF(((D22*(1-'P-Parametri'!$B$22))+'1-Input'!$B$24)<='P-Parametri'!$C$15,'P-Parametri'!$B$15,IF(((D22*(1-'P-Parametri'!$B$22))+'1-Input'!$B$24)<='P-Parametri'!$B$6,'P-Parametri'!$B$16+'P-Parametri'!$C$16*('P-Parametri'!$B$6-((D22*(1-'P-Parametri'!$B$22))+'1-Input'!$B$24))/'P-Parametri'!$D$16,IF(((D22*(1-'P-Parametri'!$B$22))+'1-Input'!$B$24)<='P-Parametri'!$B$7,'P-Parametri'!$B$17*('P-Parametri'!$B$7-((D22*(1-'P-Parametri'!$B$22))+'1-Input'!$B$24))/'P-Parametri'!$C$17,0)))))-'P-Parametri'!$D$18),'P-Parametri'!$B$18,0))+(IF((D22*(1-'P-Parametri'!$B$22))>0,IF(((D22*(1-'P-Parametri'!$B$22))+'1-Input'!$B$24)>'P-Parametri'!$D$20,0,IF(((D22*(1-'P-Parametri'!$B$22))+'1-Input'!$B$24)<='P-Parametri'!$B$20,'P-Parametri'!$B$19*(D22*(1-'P-Parametri'!$B$22)),IF(((D22*(1-'P-Parametri'!$B$22))+'1-Input'!$B$24)<='P-Parametri'!$C$20,'P-Parametri'!$C$19*(D22*(1-'P-Parametri'!$B$22)),'P-Parametri'!$D$19*(D22*(1-'P-Parametri'!$B$22))))),0))-'6-Fisco'!$C$5-D22 -> 0 | E23: =((E22*(1-'P-Parametri'!$B$22))+'1-Input'!$B$24)-(MAX(0,(IF(((E22*(1-'P-Parametri'!$B$22))+'1-Input'!$B$24)<='P-Parametri'!$B$6,'P-Parametri'!$C$6*((E22*(1-'P-Parametri'!$B$22))+'1-Input'!$B$24),IF(((E22*(1-'P-Parametri'!$B$22))+'1-Input'!$B$24)<='P-Parametri'!$B$7,'P-Parametri'!$B$9+'P-Parametri'!$C$7*(((E22*(1-'P-Parametri'!$B$22))+'1-Input'!$B$24)-'P-Parametri'!$B$6),'P-Parametri'!$B$10+'P-Parametri'!$C$8*(((E22*(1-'P-Parametri'!$B$22))+'1-Input'!$B$24)-'P-Parametri'!$B$7))))-(MAX(IF(((E22*(1-'P-Parametri'!$B$22))+'1-Input'!$B$24)<='P-Parametri'!$C$12,'P-Parametri'!$B$12,IF(((E22*(1-'P-Parametri'!$B$22))+'1-Input'!$B$24)<='P-Parametri'!$B$6,'P-Parametri'!$B$13+'P-Parametri'!$C$13*('P-Parametri'!$B$6-((E22*(1-'P-Parametri'!$B$22))+'1-Input'!$B$24))/'P-Parametri'!$D$13,IF(((E22*(1-'P-Parametri'!$B$22))+'1-Input'!$B$24)<='P-Parametri'!$B$7,'P-Parametri'!$B$14*('P-Parametri'!$B$7-((E22*(1-'P-Parametri'!$B$22))+'1-Input'!$B$24))/'P-Parametri'!$C$14,0))),IF(((E22*(1-'P-Parametri'!$B$22))+'1-Input'!$B$24)<='P-Parametri'!$C$15,'P-Parametri'!$B$15,IF(((E22*(1-'P-Parametri'!$B$22))+'1-Input'!$B$24)<='P-Parametri'!$B$6,'P-Parametri'!$B$16+'P-Parametri'!$C$16*('P-Parametri'!$B$6-((E22*(1-'P-Parametri'!$B$22))+'1-Input'!$B$24))/'P-Parametri'!$D$16,IF(((E22*(1-'P-Parametri'!$B$22))+'1-Input'!$B$24)<='P-Parametri'!$B$7,'P-Parametri'!$B$17*('P-Parametri'!$B$7-((E22*(1-'P-Parametri'!$B$22))+'1-Input'!$B$24))/'P-Parametri'!$C$17,0)))))-(IF((E22*(1-'P-Parametri'!$B$22))>0,IF(((E22*(1-'P-Parametri'!$B$22))+'1-Input'!$B$24)<='P-Parametri'!$C$21,0,IF(((E22*(1-'P-Parametri'!$B$22))+'1-Input'!$B$24)<='P-Parametri'!$D$21,'P-Parametri'!$B$21,IF(((E22*(1-'P-Parametri'!$B$22))+'1-Input'!$B$24)<'P-Parametri'!$E$21,'P-Parametri'!$B$21*('P-Parametri'!$E$21-((E22*(1-'P-Parametri'!$B$22))+'1-Input'!$B$24))/('P-Parametri'!$E$21-'P-Parametri'!$D$21),0))),0))))-(IF(MAX(0,(IF(((E22*(1-'P-Parametri'!$B$22))+'1-Input'!$B$24)<='P-Parametri'!$B$6,'P-Parametri'!$C$6*((E22*(1-'P-Parametri'!$B$22))+'1-Input'!$B$24),IF(((E22*(1-'P-Parametri'!$B$22))+'1-Input'!$B$24)<='P-Parametri'!$B$7,'P-Parametri'!$B$9+'P-Parametri'!$C$7*(((E22*(1-'P-Parametri'!$B$22))+'1-Input'!$B$24)-'P-Parametri'!$B$6),'P-Parametri'!$B$10+'P-Parametri'!$C$8*(((E22*(1-'P-Parametri'!$B$22))+'1-Input'!$B$24)-'P-Parametri'!$B$7))))-(MAX(IF(((E22*(1-'P-Parametri'!$B$22))+'1-Input'!$B$24)<='P-Parametri'!$C$12,'P-Parametri'!$B$12,IF(((E22*(1-'P-Parametri'!$B$22))+'1-Input'!$B$24)<='P-Parametri'!$B$6,'P-Parametri'!$B$13+'P-Parametri'!$C$13*('P-Parametri'!$B$6-((E22*(1-'P-Parametri'!$B$22))+'1-Input'!$B$24))/'P-Parametri'!$D$13,IF(((E22*(1-'P-Parametri'!$B$22))+'1-Input'!$B$24)<='P-Parametri'!$B$7,'P-Parametri'!$B$14*('P-Parametri'!$B$7-((E22*(1-'P-Parametri'!$B$22))+'1-Input'!$B$24))/'P-Parametri'!$C$14,0))),IF(((E22*(1-'P-Parametri'!$B$22))+'1-Input'!$B$24)<='P-Parametri'!$C$15,'P-Parametri'!$B$15,IF(((E22*(1-'P-Parametri'!$B$22))+'1-Input'!$B$24)<='P-Parametri'!$B$6,'P-Parametri'!$B$16+'P-Parametri'!$C$16*('P-Parametri'!$B$6-((E22*(1-'P-Parametri'!$B$22))+'1-Input'!$B$24))/'P-Parametri'!$D$16,IF(((E22*(1-'P-Parametri'!$B$22))+'1-Input'!$B$24)<='P-Parametri'!$B$7,'P-Parametri'!$B$17*('P-Parametri'!$B$7-((E22*(1-'P-Parametri'!$B$22))+'1-Input'!$B$24))/'P-Parametri'!$C$17,0)))))-(IF((E22*(1-'P-Parametri'!$B$22))>0,IF(((E22*(1-'P-Parametri'!$B$22))+'1-Input'!$B$24)<='P-Parametri'!$C$21,0,IF(((E22*(1-'P-Parametri'!$B$22))+'1-Input'!$B$24)<='P-Parametri'!$D$21,'P-Parametri'!$B$21,IF(((E22*(1-'P-Parametri'!$B$22))+'1-Input'!$B$24)<'P-Parametri'!$E$21,'P-Parametri'!$B$21*('P-Parametri'!$E$21-((E22*(1-'P-Parametri'!$B$22))+'1-Input'!$B$24))/('P-Parametri'!$E$21-'P-Parametri'!$D$21),0))),0)))>0,'P-Parametri'!$B$11*((E22*(1-'P-Parametri'!$B$22))+'1-Input'!$B$24),0))+(IF(AND(((E22*(1-'P-Parametri'!$B$22))+'1-Input'!$B$24)<='P-Parametri'!$C$18,(IF(((E22*(1-'P-Parametri'!$B$22))+'1-Input'!$B$24)<='P-Parametri'!$B$6,'P-Parametri'!$C$6*((E22*(1-'P-Parametri'!$B$22))+'1-Input'!$B$24),IF(((E22*(1-'P-Parametri'!$B$22))+'1-Input'!$B$24)<='P-Parametri'!$B$7,'P-Parametri'!$B$9+'P-Parametri'!$C$7*(((E22*(1-'P-Parametri'!$B$22))+'1-Input'!$B$24)-'P-Parametri'!$B$6),'P-Parametri'!$B$10+'P-Parametri'!$C$8*(((E22*(1-'P-Parametri'!$B$22))+'1-Input'!$B$24)-'P-Parametri'!$B$7))))>(MAX(IF(((E22*(1-'P-Parametri'!$B$22))+'1-Input'!$B$24)<='P-Parametri'!$C$12,'P-Parametri'!$B$12,IF(((E22*(1-'P-Parametri'!$B$22))+'1-Input'!$B$24)<='P-Parametri'!$B$6,'P-Parametri'!$B$13+'P-Parametri'!$C$13*('P-Parametri'!$B$6-((E22*(1-'P-Parametri'!$B$22))+'1-Input'!$B$24))/'P-Parametri'!$D$13,IF(((E22*(1-'P-Parametri'!$B$22))+'1-Input'!$B$24)<='P-Parametri'!$B$7,'P-Parametri'!$B$14*('P-Parametri'!$B$7-((E22*(1-'P-Parametri'!$B$22))+'1-Input'!$B$24))/'P-Parametri'!$C$14,0))),IF(((E22*(1-'P-Parametri'!$B$22))+'1-Input'!$B$24)<='P-Parametri'!$C$15,'P-Parametri'!$B$15,IF(((E22*(1-'P-Parametri'!$B$22))+'1-Input'!$B$24)<='P-Parametri'!$B$6,'P-Parametri'!$B$16+'P-Parametri'!$C$16*('P-Parametri'!$B$6-((E22*(1-'P-Parametri'!$B$22))+'1-Input'!$B$24))/'P-Parametri'!$D$16,IF(((E22*(1-'P-Parametri'!$B$22))+'1-Input'!$B$24)<='P-Parametri'!$B$7,'P-Parametri'!$B$17*('P-Parametri'!$B$7-((E22*(1-'P-Parametri'!$B$22))+'1-Input'!$B$24))/'P-Parametri'!$C$17,0)))))-'P-Parametri'!$D$18),'P-Parametri'!$B$18,0))+(IF((E22*(1-'P-Parametri'!$B$22))>0,IF(((E22*(1-'P-Parametri'!$B$22))+'1-Input'!$B$24)>'P-Parametri'!$D$20,0,IF(((E22*(1-'P-Parametri'!$B$22))+'1-Input'!$B$24)<='P-Parametri'!$B$20,'P-Parametri'!$B$19*(E22*(1-'P-Parametri'!$B$22)),IF(((E22*(1-'P-Parametri'!$B$22))+'1-Input'!$B$24)<='P-Parametri'!$C$20,'P-Parametri'!$C$19*(E22*(1-'P-Parametri'!$B$22)),'P-Parametri'!$D$19*(E22*(1-'P-Parametri'!$B$22))))),0))-'6-Fisco'!$C$5-E22 -> 0 | F23: =((F22*(1-'P-Parametri'!$B$22))+'1-Input'!$B$24)-(MAX(0,(IF(((F22*(1-'P-Parametri'!$B$22))+'1-Input'!$B$24)<='P-Parametri'!$B$6,'P-Parametri'!$C$6*((F22*(1-'P-Parametri'!$B$22))+'1-Input'!$B$24),IF(((F22*(1-'P-Parametri'!$B$22))+'1-Input'!$B$24)<='P-Parametri'!$B$7,'P-Parametri'!$B$9+'P-Parametri'!$C$7*(((F22*(1-'P-Parametri'!$B$22))+'1-Input'!$B$24)-'P-Parametri'!$B$6),'P-Parametri'!$B$10+'P-Parametri'!$C$8*(((F22*(1-'P-Parametri'!$B$22))+'1-Input'!$B$24)-'P-Parametri'!$B$7))))-(MAX(IF(((F22*(1-'P-Parametri'!$B$22))+'1-Input'!$B$24)<='P-Parametri'!$C$12,'P-Parametri'!$B$12,IF(((F22*(1-'P-Parametri'!$B$22))+'1-Input'!$B$24)<='P-Parametri'!$B$6,'P-Parametri'!$B$13+'P-Parametri'!$C$13*('P-Parametri'!$B$6-((F22*(1-'P-Parametri'!$B$22))+'1-Input'!$B$24))/'P-Parametri'!$D$13,IF(((F22*(1-'P-Parametri'!$B$22))+'1-Input'!$B$24)<='P-Parametri'!$B$7,'P-Parametri'!$B$14*('P-Parametri'!$B$7-((F22*(1-'P-Parametri'!$B$22))+'1-Input'!$B$24))/'P-Parametri'!$C$14,0))),IF(((F22*(1-'P-Parametri'!$B$22))+'1-Input'!$B$24)<='P-Parametri'!$C$15,'P-Parametri'!$B$15,IF(((F22*(1-'P-Parametri'!$B$22))+'1-Input'!$B$24)<='P-Parametri'!$B$6,'P-Parametri'!$B$16+'P-Parametri'!$C$16*('P-Parametri'!$B$6-((F22*(1-'P-Parametri'!$B$22))+'1-Input'!$B$24))/'P-Parametri'!$D$16,IF(((F22*(1-'P-Parametri'!$B$22))+'1-Input'!$B$24)<='P-Parametri'!$B$7,'P-Parametri'!$B$17*('P-Parametri'!$B$7-((F22*(1-'P-Parametri'!$B$22))+'1-Input'!$B$24))/'P-Parametri'!$C$17,0)))))-(IF((F22*(1-'P-Parametri'!$B$22))>0,IF(((F22*(1-'P-Parametri'!$B$22))+'1-Input'!$B$24)<='P-Parametri'!$C$21,0,IF(((F22*(1-'P-Parametri'!$B$22))+'1-Input'!$B$24)<='P-Parametri'!$D$21,'P-Parametri'!$B$21,IF(((F22*(1-'P-Parametri'!$B$22))+'1-Input'!$B$24)<'P-Parametri'!$E$21,'P-Parametri'!$B$21*('P-Parametri'!$E$21-((F22*(1-'P-Parametri'!$B$22))+'1-Input'!$B$24))/('P-Parametri'!$E$21-'P-Parametri'!$D$21),0))),0))))-(IF(MAX(0,(IF(((F22*(1-'P-Parametri'!$B$22))+'1-Input'!$B$24)<='P-Parametri'!$B$6,'P-Parametri'!$C$6*((F22*(1-'P-Parametri'!$B$22))+'1-Input'!$B$24),IF(((F22*(1-'P-Parametri'!$B$22))+'1-Input'!$B$24)<='P-Parametri'!$B$7,'P-Parametri'!$B$9+'P-Parametri'!$C$7*(((F22*(1-'P-Parametri'!$B$22))+'1-Input'!$B$24)-'P-Parametri'!$B$6),'P-Parametri'!$B$10+'P-Parametri'!$C$8*(((F22*(1-'P-Parametri'!$B$22))+'1-Input'!$B$24)-'P-Parametri'!$B$7))))-(MAX(IF(((F22*(1-'P-Parametri'!$B$22))+'1-Input'!$B$24)<='P-Parametri'!$C$12,'P-Parametri'!$B$12,IF(((F22*(1-'P-Parametri'!$B$22))+'1-Input'!$B$24)<='P-Parametri'!$B$6,'P-Parametri'!$B$13+'P-Parametri'!$C$13*('P-Parametri'!$B$6-((F22*(1-'P-Parametri'!$B$22))+'1-Input'!$B$24))/'P-Parametri'!$D$13,IF(((F22*(1-'P-Parametri'!$B$22))+'1-Input'!$B$24)<='P-Parametri'!$B$7,'P-Parametri'!$B$14*('P-Parametri'!$B$7-((F22*(1-'P-Parametri'!$B$22))+'1-Input'!$B$24))/'P-Parametri'!$C$14,0))),IF(((F22*(1-'P-Parametri'!$B$22))+'1-Input'!$B$24)<='P-Parametri'!$C$15,'P-Parametri'!$B$15,IF(((F22*(1-'P-Parametri'!$B$22))+'1-Input'!$B$24)<='P-Parametri'!$B$6,'P-Parametri'!$B$16+'P-Parametri'!$C$16*('P-Parametri'!$B$6-((F22*(1-'P-Parametri'!$B$22))+'1-Input'!$B$24))/'P-Parametri'!$D$16,IF(((F22*(1-'P-Parametri'!$B$22))+'1-Input'!$B$24)<='P-Parametri'!$B$7,'P-Parametri'!$B$17*('P-Parametri'!$B$7-((F22*(1-'P-Parametri'!$B$22))+'1-Input'!$B$24))/'P-Parametri'!$C$17,0)))))-(IF((F22*(1-'P-Parametri'!$B$22))>0,IF(((F22*(1-'P-Parametri'!$B$22))+'1-Input'!$B$24)<='P-Parametri'!$C$21,0,IF(((F22*(1-'P-Parametri'!$B$22))+'1-Input'!$B$24)<='P-Parametri'!$D$21,'P-Parametri'!$B$21,IF(((F22*(1-'P-Parametri'!$B$22))+'1-Input'!$B$24)<'P-Parametri'!$E$21,'P-Parametri'!$B$21*('P-Parametri'!$E$21-((F22*(1-'P-Parametri'!$B$22))+'1-Input'!$B$24))/('P-Parametri'!$E$21-'P-Parametri'!$D$21),0))),0)))>0,'P-Parametri'!$B$11*((F22*(1-'P-Parametri'!$B$22))+'1-Input'!$B$24),0))+(IF(AND(((F22*(1-'P-Parametri'!$B$22))+'1-Input'!$B$24)<='P-Parametri'!$C$18,(IF(((F22*(1-'P-Parametri'!$B$22))+'1-Input'!$B$24)<='P-Parametri'!$B$6,'P-Parametri'!$C$6*((F22*(1-'P-Parametri'!$B$22))+'1-Input'!$B$24),IF(((F22*(1-'P-Parametri'!$B$22))+'1-Input'!$B$24)<='P-Parametri'!$B$7,'P-Parametri'!$B$9+'P-Parametri'!$C$7*(((F22*(1-'P-Parametri'!$B$22))+'1-Input'!$B$24)-'P-Parametri'!$B$6),'P-Parametri'!$B$10+'P-Parametri'!$C$8*(((F22*(1-'P-Parametri'!$B$22))+'1-Input'!$B$24)-'P-Parametri'!$B$7))))>(MAX(IF(((F22*(1-'P-Parametri'!$B$22))+'1-Input'!$B$24)<='P-Parametri'!$C$12,'P-Parametri'!$B$12,IF(((F22*(1-'P-Parametri'!$B$22))+'1-Input'!$B$24)<='P-Parametri'!$B$6,'P-Parametri'!$B$13+'P-Parametri'!$C$13*('P-Parametri'!$B$6-((F22*(1-'P-Parametri'!$B$22))+'1-Input'!$B$24))/'P-Parametri'!$D$13,IF(((F22*(1-'P-Parametri'!$B$22))+'1-Input'!$B$24)<='P-Parametri'!$B$7,'P-Parametri'!$B$14*('P-Parametri'!$B$7-((F22*(1-'P-Parametri'!$B$22))+'1-Input'!$B$24))/'P-Parametri'!$C$14,0))),IF(((F22*(1-'P-Parametri'!$B$22))+'1-Input'!$B$24)<='P-Parametri'!$C$15,'P-Parametri'!$B$15,IF(((F22*(1-'P-Parametri'!$B$22))+'1-Input'!$B$24)<='P-Parametri'!$B$6,'P-Parametri'!$B$16+'P-Parametri'!$C$16*('P-Parametri'!$B$6-((F22*(1-'P-Parametri'!$B$22))+'1-Input'!$B$24))/'P-Parametri'!$D$16,IF(((F22*(1-'P-Parametri'!$B$22))+'1-Input'!$B$24)<='P-Parametri'!$B$7,'P-Parametri'!$B$17*('P-Parametri'!$B$7-((F22*(1-'P-Parametri'!$B$22))+'1-Input'!$B$24))/'P-Parametri'!$C$17,0)))))-'P-Parametri'!$D$18),'P-Parametri'!$B$18,0))+(IF((F22*(1-'P-Parametri'!$B$22))>0,IF(((F22*(1-'P-Parametri'!$B$22))+'1-Input'!$B$24)>'P-Parametri'!$D$20,0,IF(((F22*(1-'P-Parametri'!$B$22))+'1-Input'!$B$24)<='P-Parametri'!$B$20,'P-Parametri'!$B$19*(F22*(1-'P-Parametri'!$B$22)),IF(((F22*(1-'P-Parametri'!$B$22))+'1-Input'!$B$24)<='P-Parametri'!$C$20,'P-Parametri'!$C$19*(F22*(1-'P-Parametri'!$B$22)),'P-Parametri'!$D$19*(F22*(1-'P-Parametri'!$B$22))))),0))-'6-Fisco'!$C$5-F22 -> 0 | G23: =((G22*(1-'P-Parametri'!$B$22))+'1-Input'!$B$24)-(MAX(0,(IF(((G22*(1-'P-Parametri'!$B$22))+'1-Input'!$B$24)<='P-Parametri'!$B$6,'P-Parametri'!$C$6*((G22*(1-'P-Parametri'!$B$22))+'1-Input'!$B$24),IF(((G22*(1-'P-Parametri'!$B$22))+'1-Input'!$B$24)<='P-Parametri'!$B$7,'P-Parametri'!$B$9+'P-Parametri'!$C$7*(((G22*(1-'P-Parametri'!$B$22))+'1-Input'!$B$24)-'P-Parametri'!$B$6),'P-Parametri'!$B$10+'P-Parametri'!$C$8*(((G22*(1-'P-Parametri'!$B$22))+'1-Input'!$B$24)-'P-Parametri'!$B$7))))-(MAX(IF(((G22*(1-'P-Parametri'!$B$22))+'1-Input'!$B$24)<='P-Parametri'!$C$12,'P-Parametri'!$B$12,IF(((G22*(1-'P-Parametri'!$B$22))+'1-Input'!$B$24)<='P-Parametri'!$B$6,'P-Parametri'!$B$13+'P-Parametri'!$C$13*('P-Parametri'!$B$6-((G22*(1-'P-Parametri'!$B$22))+'1-Input'!$B$24))/'P-Parametri'!$D$13,IF(((G22*(1-'P-Parametri'!$B$22))+'1-Input'!$B$24)<='P-Parametri'!$B$7,'P-Parametri'!$B$14*('P-Parametri'!$B$7-((G22*(1-'P-Parametri'!$B$22))+'1-Input'!$B$24))/'P-Parametri'!$C$14,0))),IF(((G22*(1-'P-Parametri'!$B$22))+'1-Input'!$B$24)<='P-Parametri'!$C$15,'P-Parametri'!$B$15,IF(((G22*(1-'P-Parametri'!$B$22))+'1-Input'!$B$24)<='P-Parametri'!$B$6,'P-Parametri'!$B$16+'P-Parametri'!$C$16*('P-Parametri'!$B$6-((G22*(1-'P-Parametri'!$B$22))+'1-Input'!$B$24))/'P-Parametri'!$D$16,IF(((G22*(1-'P-Parametri'!$B$22))+'1-Input'!$B$24)<='P-Parametri'!$B$7,'P-Parametri'!$B$17*('P-Parametri'!$B$7-((G22*(1-'P-Parametri'!$B$22))+'1-Input'!$B$24))/'P-Parametri'!$C$17,0)))))-(IF((G22*(1-'P-Parametri'!$B$22))>0,IF(((G22*(1-'P-Parametri'!$B$22))+'1-Input'!$B$24)<='P-Parametri'!$C$21,0,IF(((G22*(1-'P-Parametri'!$B$22))+'1-Input'!$B$24)<='P-Parametri'!$D$21,'P-Parametri'!$B$21,IF(((G22*(1-'P-Parametri'!$B$22))+'1-Input'!$B$24)<'P-Parametri'!$E$21,'P-Parametri'!$B$21*('P-Parametri'!$E$21-((G22*(1-'P-Parametri'!$B$22))+'1-Input'!$B$24))/('P-Parametri'!$E$21-'P-Parametri'!$D$21),0))),0))))-(IF(MAX(0,(IF(((G22*(1-'P-Parametri'!$B$22))+'1-Input'!$B$24)<='P-Parametri'!$B$6,'P-Parametri'!$C$6*((G22*(1-'P-Parametri'!$B$22))+'1-Input'!$B$24),IF(((G22*(1-'P-Parametri'!$B$22))+'1-Input'!$B$24)<='P-Parametri'!$B$7,'P-Parametri'!$B$9+'P-Parametri'!$C$7*(((G22*(1-'P-Parametri'!$B$22))+'1-Input'!$B$24)-'P-Parametri'!$B$6),'P-Parametri'!$B$10+'P-Parametri'!$C$8*(((G22*(1-'P-Parametri'!$B$22))+'1-Input'!$B$24)-'P-Parametri'!$B$7))))-(MAX(IF(((G22*(1-'P-Parametri'!$B$22))+'1-Input'!$B$24)<='P-Parametri'!$C$12,'P-Parametri'!$B$12,IF(((G22*(1-'P-Parametri'!$B$22))+'1-Input'!$B$24)<='P-Parametri'!$B$6,'P-Parametri'!$B$13+'P-Parametri'!$C$13*('P-Parametri'!$B$6-((G22*(1-'P-Parametri'!$B$22))+'1-Input'!$B$24))/'P-Parametri'!$D$13,IF(((G22*(1-'P-Parametri'!$B$22))+'1-Input'!$B$24)<='P-Parametri'!$B$7,'P-Parametri'!$B$14*('P-Parametri'!$B$7-((G22*(1-'P-Parametri'!$B$22))+'1-Input'!$B$24))/'P-Parametri'!$C$14,0))),IF(((G22*(1-'P-Parametri'!$B$22))+'1-Input'!$B$24)<='P-Parametri'!$C$15,'P-Parametri'!$B$15,IF(((G22*(1-'P-Parametri'!$B$22))+'1-Input'!$B$24)<='P-Parametri'!$B$6,'P-Parametri'!$B$16+'P-Parametri'!$C$16*('P-Parametri'!$B$6-((G22*(1-'P-Parametri'!$B$22))+'1-Input'!$B$24))/'P-Parametri'!$D$16,IF(((G22*(1-'P-Parametri'!$B$22))+'1-Input'!$B$24)<='P-Parametri'!$B$7,'P-Parametri'!$B$17*('P-Parametri'!$B$7-((G22*(1-'P-Parametri'!$B$22))+'1-Input'!$B$24))/'P-Parametri'!$C$17,0)))))-(IF((G22*(1-'P-Parametri'!$B$22))>0,IF(((G22*(1-'P-Parametri'!$B$22))+'1-Input'!$B$24)<='P-Parametri'!$C$21,0,IF(((G22*(1-'P-Parametri'!$B$22))+'1-Input'!$B$24)<='P-Parametri'!$D$21,'P-Parametri'!$B$21,IF(((G22*(1-'P-Parametri'!$B$22))+'1-Input'!$B$24)<'P-Parametri'!$E$21,'P-Parametri'!$B$21*('P-Parametri'!$E$21-((G22*(1-'P-Parametri'!$B$22))+'1-Input'!$B$24))/('P-Parametri'!$E$21-'P-Parametri'!$D$21),0))),0)))>0,'P-Parametri'!$B$11*((G22*(1-'P-Parametri'!$B$22))+'1-Input'!$B$24),0))+(IF(AND(((G22*(1-'P-Parametri'!$B$22))+'1-Input'!$B$24)<='P-Parametri'!$C$18,(IF(((G22*(1-'P-Parametri'!$B$22))+'1-Input'!$B$24)<='P-Parametri'!$B$6,'P-Parametri'!$C$6*((G22*(1-'P-Parametri'!$B$22))+'1-Input'!$B$24),IF(((G22*(1-'P-Parametri'!$B$22))+'1-Input'!$B$24)<='P-Parametri'!$B$7,'P-Parametri'!$B$9+'P-Parametri'!$C$7*(((G22*(1-'P-Parametri'!$B$22))+'1-Input'!$B$24)-'P-Parametri'!$B$6),'P-Parametri'!$B$10+'P-Parametri'!$C$8*(((G22*(1-'P-Parametri'!$B$22))+'1-Input'!$B$24)-'P-Parametri'!$B$7))))>(MAX(IF(((G22*(1-'P-Parametri'!$B$22))+'1-Input'!$B$24)<='P-Parametri'!$C$12,'P-Parametri'!$B$12,IF(((G22*(1-'P-Parametri'!$B$22))+'1-Input'!$B$24)<='P-Parametri'!$B$6,'P-Parametri'!$B$13+'P-Parametri'!$C$13*('P-Parametri'!$B$6-((G22*(1-'P-Parametri'!$B$22))+'1-Input'!$B$24))/'P-Parametri'!$D$13,IF(((G22*(1-'P-Parametri'!$B$22))+'1-Input'!$B$24)<='P-Parametri'!$B$7,'P-Parametri'!$B$14*('P-Parametri'!$B$7-((G22*(1-'P-Parametri'!$B$22))+'1-Input'!$B$24))/'P-Parametri'!$C$14,0))),IF(((G22*(1-'P-Parametri'!$B$22))+'1-Input'!$B$24)<='P-Parametri'!$C$15,'P-Parametri'!$B$15,IF(((G22*(1-'P-Parametri'!$B$22))+'1-Input'!$B$24)<='P-Parametri'!$B$6,'P-Parametri'!$B$16+'P-Parametri'!$C$16*('P-Parametri'!$B$6-((G22*(1-'P-Parametri'!$B$22))+'1-Input'!$B$24))/'P-Parametri'!$D$16,IF(((G22*(1-'P-Parametri'!$B$22))+'1-Input'!$B$24)<='P-Parametri'!$B$7,'P-Parametri'!$B$17*('P-Parametri'!$B$7-((G22*(1-'P-Parametri'!$B$22))+'1-Input'!$B$24))/'P-Parametri'!$C$17,0)))))-'P-Parametri'!$D$18),'P-Parametri'!$B$18,0))+(IF((G22*(1-'P-Parametri'!$B$22))>0,IF(((G22*(1-'P-Parametri'!$B$22))+'1-Input'!$B$24)>'P-Parametri'!$D$20,0,IF(((G22*(1-'P-Parametri'!$B$22))+'1-Input'!$B$24)<='P-Parametri'!$B$20,'P-Parametri'!$B$19*(G22*(1-'P-Parametri'!$B$22)),IF(((G22*(1-'P-Parametri'!$B$22))+'1-Input'!$B$24)<='P-Parametri'!$C$20,'P-Parametri'!$C$19*(G22*(1-'P-Parametri'!$B$22)),'P-Parametri'!$D$19*(G22*(1-'P-Parametri'!$B$22))))),0))-'6-Fisco'!$C$5-G22 -> 0
A24: SOGLIA — sotto questo lordo non si perde nulla | B24: =IFERROR(G22-G23*(G22-F22)/(G23-F23),G22) -> 6104.8271
A27: LO SCALINO DEL TRATTAMENTO INTEGRATIVO
A28: Condizione di capienza: IRPEF lorda > detrazione − scarto
A29: SOGLIA in reddito LORDO (forma chiusa) | B29: =('P-Parametri'!$B$12-'P-Parametri'!$D$18)/'P-Parametri'!$C$6/(1-'P-Parametri'!$B$22) -> 9001.1156
A30: Netto un centesimo sotto / un centesimo sopra la soglia | B30: =((($B$29-0.01)*(1-'P-Parametri'!$B$22))+0)-(MAX(0,(IF(((($B$29-0.01)*(1-'P-Parametri'!$B$22))+0)<='P-Parametri'!$B$6,'P-Parametri'!$C$6*((($B$29-0.01)*(1-'P-Parametri'!$B$22))+0),IF(((($B$29-0.01)*(1-'P-Parametri'!$B$22))+0)<='P-Parametri'!$B$7,'P-Parametri'!$B$9+'P-Parametri'!$C$7*(((($B$29-0.01)*(1-'P-Parametri'!$B$22))+0)-'P-Parametri'!$B$6),'P-Parametri'!$B$10+'P-Parametri'!$C$8*(((($B$29-0.01)*(1-'P-Parametri'!$B$22))+0)-'P-Parametri'!$B$7))))-(IF(((($B$29-0.01)*(1-'P-Parametri'!$B$22))+0)<='P-Parametri'!$C$12,'P-Parametri'!$B$12,IF(((($B$29-0.01)*(1-'P-Parametri'!$B$22))+0)<='P-Parametri'!$B$6,'P-Parametri'!$B$13+'P-Parametri'!$C$13*('P-Parametri'!$B$6-((($B$29-0.01)*(1-'P-Parametri'!$B$22))+0))/'P-Parametri'!$D$13,IF(((($B$29-0.01)*(1-'P-Parametri'!$B$22))+0)<='P-Parametri'!$B$7,'P-Parametri'!$B$14*('P-Parametri'!$B$7-((($B$29-0.01)*(1-'P-Parametri'!$B$22))+0))/'P-Parametri'!$C$14,0))))-(IF((($B$29-0.01)*(1-'P-Parametri'!$B$22))>0,IF(((($B$29-0.01)*(1-'P-Parametri'!$B$22))+0)<='P-Parametri'!$C$21,0,IF(((($B$29-0.01)*(1-'P-Parametri'!$B$22))+0)<='P-Parametri'!$D$21,'P-Parametri'!$B$21,IF(((($B$29-0.01)*(1-'P-Parametri'!$B$22))+0)<'P-Parametri'!$E$21,'P-Parametri'!$B$21*('P-Parametri'!$E$21-((($B$29-0.01)*(1-'P-Parametri'!$B$22))+0))/('P-Parametri'!$E$21-'P-Parametri'!$D$21),0))),0))))-(IF(MAX(0,(IF(((($B$29-0.01)*(1-'P-Parametri'!$B$22))+0)<='P-Parametri'!$B$6,'P-Parametri'!$C$6*((($B$29-0.01)*(1-'P-Parametri'!$B$22))+0),IF(((($B$29-0.01)*(1-'P-Parametri'!$B$22))+0)<='P-Parametri'!$B$7,'P-Parametri'!$B$9+'P-Parametri'!$C$7*(((($B$29-0.01)*(1-'P-Parametri'!$B$22))+0)-'P-Parametri'!$B$6),'P-Parametri'!$B$10+'P-Parametri'!$C$8*(((($B$29-0.01)*(1-'P-Parametri'!$B$22))+0)-'P-Parametri'!$B$7))))-(IF(((($B$29-0.01)*(1-'P-Parametri'!$B$22))+0)<='P-Parametri'!$C$12,'P-Parametri'!$B$12,IF(((($B$29-0.01)*(1-'P-Parametri'!$B$22))+0)<='P-Parametri'!$B$6,'P-Parametri'!$B$13+'P-Parametri'!$C$13*('P-Parametri'!$B$6-((($B$29-0.01)*(1-'P-Parametri'!$B$22))+0))/'P-Parametri'!$D$13,IF(((($B$29-0.01)*(1-'P-Parametri'!$B$22))+0)<='P-Parametri'!$B$7,'P-Parametri'!$B$14*('P-Parametri'!$B$7-((($B$29-0.01)*(1-'P-Parametri'!$B$22))+0))/'P-Parametri'!$C$14,0))))-(IF((($B$29-0.01)*(1-'P-Parametri'!$B$22))>0,IF(((($B$29-0.01)*(1-'P-Parametri'!$B$22))+0)<='P-Parametri'!$C$21,0,IF(((($B$29-0.01)*(1-'P-Parametri'!$B$22))+0)<='P-Parametri'!$D$21,'P-Parametri'!$B$21,IF(((($B$29-0.01)*(1-'P-Parametri'!$B$22))+0)<'P-Parametri'!$E$21,'P-Parametri'!$B$21*('P-Parametri'!$E$21-((($B$29-0.01)*(1-'P-Parametri'!$B$22))+0))/('P-Parametri'!$E$21-'P-Parametri'!$D$21),0))),0)))>0,'P-Parametri'!$B$11*((($B$29-0.01)*(1-'P-Parametri'!$B$22))+0),0))+(IF(AND(((($B$29-0.01)*(1-'P-Parametri'!$B$22))+0)<='P-Parametri'!$C$18,(IF(((($B$29-0.01)*(1-'P-Parametri'!$B$22))+0)<='P-Parametri'!$B$6,'P-Parametri'!$C$6*((($B$29-0.01)*(1-'P-Parametri'!$B$22))+0),IF(((($B$29-0.01)*(1-'P-Parametri'!$B$22))+0)<='P-Parametri'!$B$7,'P-Parametri'!$B$9+'P-Parametri'!$C$7*(((($B$29-0.01)*(1-'P-Parametri'!$B$22))+0)-'P-Parametri'!$B$6),'P-Parametri'!$B$10+'P-Parametri'!$C$8*(((($B$29-0.01)*(1-'P-Parametri'!$B$22))+0)-'P-Parametri'!$B$7))))>(IF(((($B$29-0.01)*(1-'P-Parametri'!$B$22))+0)<='P-Parametri'!$C$12,'P-Parametri'!$B$12,IF(((($B$29-0.01)*(1-'P-Parametri'!$B$22))+0)<='P-Parametri'!$B$6,'P-Parametri'!$B$13+'P-Parametri'!$C$13*('P-Parametri'!$B$6-((($B$29-0.01)*(1-'P-Parametri'!$B$22))+0))/'P-Parametri'!$D$13,IF(((($B$29-0.01)*(1-'P-Parametri'!$B$22))+0)<='P-Parametri'!$B$7,'P-Parametri'!$B$14*('P-Parametri'!$B$7-((($B$29-0.01)*(1-'P-Parametri'!$B$22))+0))/'P-Parametri'!$C$14,0))))-'P-Parametri'!$D$18),'P-Parametri'!$B$18,0))+(IF((($B$29-0.01)*(1-'P-Parametri'!$B$22))>0,IF(((($B$29-0.01)*(1-'P-Parametri'!$B$22))+0)>'P-Parametri'!$D$20,0,IF(((($B$29-0.01)*(1-'P-Parametri'!$B$22))+0)<='P-Parametri'!$B$20,'P-Parametri'!$B$19*(($B$29-0.01)*(1-'P-Parametri'!$B$22)),IF(((($B$29-0.01)*(1-'P-Parametri'!$B$22))+0)<='P-Parametri'!$C$20,'P-Parametri'!$C$19*(($B$29-0.01)*(1-'P-Parametri'!$B$22)),'P-Parametri'!$D$19*(($B$29-0.01)*(1-'P-Parametri'!$B$22))))),0)) -> 8754.2511 | C30: =((($B$29+0.01)*(1-'P-Parametri'!$B$22))+0)-(MAX(0,(IF(((($B$29+0.01)*(1-'P-Parametri'!$B$22))+0)<='P-Parametri'!$B$6,'P-Parametri'!$C$6*((($B$29+0.01)*(1-'P-Parametri'!$B$22))+0),IF(((($B$29+0.01)*(1-'P-Parametri'!$B$22))+0)<='P-Parametri'!$B$7,'P-Parametri'!$B$9+'P-Parametri'!$C$7*(((($B$29+0.01)*(1-'P-Parametri'!$B$22))+0)-'P-Parametri'!$B$6),'P-Parametri'!$B$10+'P-Parametri'!$C$8*(((($B$29+0.01)*(1-'P-Parametri'!$B$22))+0)-'P-Parametri'!$B$7))))-(IF(((($B$29+0.01)*(1-'P-Parametri'!$B$22))+0)<='P-Parametri'!$C$12,'P-Parametri'!$B$12,IF(((($B$29+0.01)*(1-'P-Parametri'!$B$22))+0)<='P-Parametri'!$B$6,'P-Parametri'!$B$13+'P-Parametri'!$C$13*('P-Parametri'!$B$6-((($B$29+0.01)*(1-'P-Parametri'!$B$22))+0))/'P-Parametri'!$D$13,IF(((($B$29+0.01)*(1-'P-Parametri'!$B$22))+0)<='P-Parametri'!$B$7,'P-Parametri'!$B$14*('P-Parametri'!$B$7-((($B$29+0.01)*(1-'P-Parametri'!$B$22))+0))/'P-Parametri'!$C$14,0))))-(IF((($B$29+0.01)*(1-'P-Parametri'!$B$22))>0,IF(((($B$29+0.01)*(1-'P-Parametri'!$B$22))+0)<='P-Parametri'!$C$21,0,IF(((($B$29+0.01)*(1-'P-Parametri'!$B$22))+0)<='P-Parametri'!$D$21,'P-Parametri'!$B$21,IF(((($B$29+0.01)*(1-'P-Parametri'!$B$22))+0)<'P-Parametri'!$E$21,'P-Parametri'!$B$21*('P-Parametri'!$E$21-((($B$29+0.01)*(1-'P-Parametri'!$B$22))+0))/('P-Parametri'!$E$21-'P-Parametri'!$D$21),0))),0))))-(IF(MAX(0,(IF(((($B$29+0.01)*(1-'P-Parametri'!$B$22))+0)<='P-Parametri'!$B$6,'P-Parametri'!$C$6*((($B$29+0.01)*(1-'P-Parametri'!$B$22))+0),IF(((($B$29+0.01)*(1-'P-Parametri'!$B$22))+0)<='P-Parametri'!$B$7,'P-Parametri'!$B$9+'P-Parametri'!$C$7*(((($B$29+0.01)*(1-'P-Parametri'!$B$22))+0)-'P-Parametri'!$B$6),'P-Parametri'!$B$10+'P-Parametri'!$C$8*(((($B$29+0.01)*(1-'P-Parametri'!$B$22))+0)-'P-Parametri'!$B$7))))-(IF(((($B$29+0.01)*(1-'P-Parametri'!$B$22))+0)<='P-Parametri'!$C$12,'P-Parametri'!$B$12,IF(((($B$29+0.01)*(1-'P-Parametri'!$B$22))+0)<='P-Parametri'!$B$6,'P-Parametri'!$B$13+'P-Parametri'!$C$13*('P-Parametri'!$B$6-((($B$29+0.01)*(1-'P-Parametri'!$B$22))+0))/'P-Parametri'!$D$13,IF(((($B$29+0.01)*(1-'P-Parametri'!$B$22))+0)<='P-Parametri'!$B$7,'P-Parametri'!$B$14*('P-Parametri'!$B$7-((($B$29+0.01)*(1-'P-Parametri'!$B$22))+0))/'P-Parametri'!$C$14,0))))-(IF((($B$29+0.01)*(1-'P-Parametri'!$B$22))>0,IF(((($B$29+0.01)*(1-'P-Parametri'!$B$22))+0)<='P-Parametri'!$C$21,0,IF(((($B$29+0.01)*(1-'P-Parametri'!$B$22))+0)<='P-Parametri'!$D$21,'P-Parametri'!$B$21,IF(((($B$29+0.01)*(1-'P-Parametri'!$B$22))+0)<'P-Parametri'!$E$21,'P-Parametri'!$B$21*('P-Parametri'!$E$21-((($B$29+0.01)*(1-'P-Parametri'!$B$22))+0))/('P-Parametri'!$E$21-'P-Parametri'!$D$21),0))),0)))>0,'P-Parametri'!$B$11*((($B$29+0.01)*(1-'P-Parametri'!$B$22))+0),0))+(IF(AND(((($B$29+0.01)*(1-'P-Parametri'!$B$22))+0)<='P-Parametri'!$C$18,(IF(((($B$29+0.01)*(1-'P-Parametri'!$B$22))+0)<='P-Parametri'!$B$6,'P-Parametri'!$C$6*((($B$29+0.01)*(1-'P-Parametri'!$B$22))+0),IF(((($B$29+0.01)*(1-'P-Parametri'!$B$22))+0)<='P-Parametri'!$B$7,'P-Parametri'!$B$9+'P-Parametri'!$C$7*(((($B$29+0.01)*(1-'P-Parametri'!$B$22))+0)-'P-Parametri'!$B$6),'P-Parametri'!$B$10+'P-Parametri'!$C$8*(((($B$29+0.01)*(1-'P-Parametri'!$B$22))+0)-'P-Parametri'!$B$7))))>(IF(((($B$29+0.01)*(1-'P-Parametri'!$B$22))+0)<='P-Parametri'!$C$12,'P-Parametri'!$B$12,IF(((($B$29+0.01)*(1-'P-Parametri'!$B$22))+0)<='P-Parametri'!$B$6,'P-Parametri'!$B$13+'P-Parametri'!$C$13*('P-Parametri'!$B$6-((($B$29+0.01)*(1-'P-Parametri'!$B$22))+0))/'P-Parametri'!$D$13,IF(((($B$29+0.01)*(1-'P-Parametri'!$B$22))+0)<='P-Parametri'!$B$7,'P-Parametri'!$B$14*('P-Parametri'!$B$7-((($B$29+0.01)*(1-'P-Parametri'!$B$22))+0))/'P-Parametri'!$C$14,0))))-'P-Parametri'!$D$18),'P-Parametri'!$B$18,0))+(IF((($B$29+0.01)*(1-'P-Parametri'!$B$22))>0,IF(((($B$29+0.01)*(1-'P-Parametri'!$B$22))+0)>'P-Parametri'!$D$20,0,IF(((($B$29+0.01)*(1-'P-Parametri'!$B$22))+0)<='P-Parametri'!$B$20,'P-Parametri'!$B$19*(($B$29+0.01)*(1-'P-Parametri'!$B$22)),IF(((($B$29+0.01)*(1-'P-Parametri'!$B$22))+0)<='P-Parametri'!$C$20,'P-Parametri'!$C$19*(($B$29+0.01)*(1-'P-Parametri'!$B$22)),'P-Parametri'!$D$19*(($B$29+0.01)*(1-'P-Parametri'!$B$22))))),0)) -> 9954.2706
A31: IL SALTO — due centesimi di lordo, quanto netto | B31: =C30-B30 -> 1200.0195
A32: Cento euro di lordo in più, a cavallo della soglia | B32: =((($B$29+100)*(1-'P-Parametri'!$B$22))+0)-(MAX(0,(IF(((($B$29+100)*(1-'P-Parametri'!$B$22))+0)<='P-Parametri'!$B$6,'P-Parametri'!$C$6*((($B$29+100)*(1-'P-Parametri'!$B$22))+0),IF(((($B$29+100)*(1-'P-Parametri'!$B$22))+0)<='P-Parametri'!$B$7,'P-Parametri'!$B$9+'P-Parametri'!$C$7*(((($B$29+100)*(1-'P-Parametri'!$B$22))+0)-'P-Parametri'!$B$6),'P-Parametri'!$B$10+'P-Parametri'!$C$8*(((($B$29+100)*(1-'P-Parametri'!$B$22))+0)-'P-Parametri'!$B$7))))-(IF(((($B$29+100)*(1-'P-Parametri'!$B$22))+0)<='P-Parametri'!$C$12,'P-Parametri'!$B$12,IF(((($B$29+100)*(1-'P-Parametri'!$B$22))+0)<='P-Parametri'!$B$6,'P-Parametri'!$B$13+'P-Parametri'!$C$13*('P-Parametri'!$B$6-((($B$29+100)*(1-'P-Parametri'!$B$22))+0))/'P-Parametri'!$D$13,IF(((($B$29+100)*(1-'P-Parametri'!$B$22))+0)<='P-Parametri'!$B$7,'P-Parametri'!$B$14*('P-Parametri'!$B$7-((($B$29+100)*(1-'P-Parametri'!$B$22))+0))/'P-Parametri'!$C$14,0))))-(IF((($B$29+100)*(1-'P-Parametri'!$B$22))>0,IF(((($B$29+100)*(1-'P-Parametri'!$B$22))+0)<='P-Parametri'!$C$21,0,IF(((($B$29+100)*(1-'P-Parametri'!$B$22))+0)<='P-Parametri'!$D$21,'P-Parametri'!$B$21,IF(((($B$29+100)*(1-'P-Parametri'!$B$22))+0)<'P-Parametri'!$E$21,'P-Parametri'!$B$21*('P-Parametri'!$E$21-((($B$29+100)*(1-'P-Parametri'!$B$22))+0))/('P-Parametri'!$E$21-'P-Parametri'!$D$21),0))),0))))-(IF(MAX(0,(IF(((($B$29+100)*(1-'P-Parametri'!$B$22))+0)<='P-Parametri'!$B$6,'P-Parametri'!$C$6*((($B$29+100)*(1-'P-Parametri'!$B$22))+0),IF(((($B$29+100)*(1-'P-Parametri'!$B$22))+0)<='P-Parametri'!$B$7,'P-Parametri'!$B$9+'P-Parametri'!$C$7*(((($B$29+100)*(1-'P-Parametri'!$B$22))+0)-'P-Parametri'!$B$6),'P-Parametri'!$B$10+'P-Parametri'!$C$8*(((($B$29+100)*(1-'P-Parametri'!$B$22))+0)-'P-Parametri'!$B$7))))-(IF(((($B$29+100)*(1-'P-Parametri'!$B$22))+0)<='P-Parametri'!$C$12,'P-Parametri'!$B$12,IF(((($B$29+100)*(1-'P-Parametri'!$B$22))+0)<='P-Parametri'!$B$6,'P-Parametri'!$B$13+'P-Parametri'!$C$13*('P-Parametri'!$B$6-((($B$29+100)*(1-'P-Parametri'!$B$22))+0))/'P-Parametri'!$D$13,IF(((($B$29+100)*(1-'P-Parametri'!$B$22))+0)<='P-Parametri'!$B$7,'P-Parametri'!$B$14*('P-Parametri'!$B$7-((($B$29+100)*(1-'P-Parametri'!$B$22))+0))/'P-Parametri'!$C$14,0))))-(IF((($B$29+100)*(1-'P-Parametri'!$B$22))>0,IF(((($B$29+100)*(1-'P-Parametri'!$B$22))+0)<='P-Parametri'!$C$21,0,IF(((($B$29+100)*(1-'P-Parametri'!$B$22))+0)<='P-Parametri'!$D$21,'P-Parametri'!$B$21,IF(((($B$29+100)*(1-'P-Parametri'!$B$22))+0)<'P-Parametri'!$E$21,'P-Parametri'!$B$21*('P-Parametri'!$E$21-((($B$29+100)*(1-'P-Parametri'!$B$22))+0))/('P-Parametri'!$E$21-'P-Parametri'!$D$21),0))),0)))>0,'P-Parametri'!$B$11*((($B$29+100)*(1-'P-Parametri'!$B$22))+0),0))+(IF(AND(((($B$29+100)*(1-'P-Parametri'!$B$22))+0)<='P-Parametri'!$C$18,(IF(((($B$29+100)*(1-'P-Parametri'!$B$22))+0)<='P-Parametri'!$B$6,'P-Parametri'!$C$6*((($B$29+100)*(1-'P-Parametri'!$B$22))+0),IF(((($B$29+100)*(1-'P-Parametri'!$B$22))+0)<='P-Parametri'!$B$7,'P-Parametri'!$B$9+'P-Parametri'!$C$7*(((($B$29+100)*(1-'P-Parametri'!$B$22))+0)-'P-Parametri'!$B$6),'P-Parametri'!$B$10+'P-Parametri'!$C$8*(((($B$29+100)*(1-'P-Parametri'!$B$22))+0)-'P-Parametri'!$B$7))))>(IF(((($B$29+100)*(1-'P-Parametri'!$B$22))+0)<='P-Parametri'!$C$12,'P-Parametri'!$B$12,IF(((($B$29+100)*(1-'P-Parametri'!$B$22))+0)<='P-Parametri'!$B$6,'P-Parametri'!$B$13+'P-Parametri'!$C$13*('P-Parametri'!$B$6-((($B$29+100)*(1-'P-Parametri'!$B$22))+0))/'P-Parametri'!$D$13,IF(((($B$29+100)*(1-'P-Parametri'!$B$22))+0)<='P-Parametri'!$B$7,'P-Parametri'!$B$14*('P-Parametri'!$B$7-((($B$29+100)*(1-'P-Parametri'!$B$22))+0))/'P-Parametri'!$C$14,0))))-'P-Parametri'!$D$18),'P-Parametri'!$B$18,0))+(IF((($B$29+100)*(1-'P-Parametri'!$B$22))>0,IF(((($B$29+100)*(1-'P-Parametri'!$B$22))+0)>'P-Parametri'!$D$20,0,IF(((($B$29+100)*(1-'P-Parametri'!$B$22))+0)<='P-Parametri'!$B$20,'P-Parametri'!$B$19*(($B$29+100)*(1-'P-Parametri'!$B$22)),IF(((($B$29+100)*(1-'P-Parametri'!$B$22))+0)<='P-Parametri'!$C$20,'P-Parametri'!$C$19*(($B$29+100)*(1-'P-Parametri'!$B$22)),'P-Parametri'!$D$19*(($B$29+100)*(1-'P-Parametri'!$B$22))))),0))-B30 -> 1297.2672
A33: Picco del netto in percentuale del lordo (appena sopra la soglia) | B33: =C30/($B$29+0.01) -> 1.1058918
A34: Il gradino chiude una cella rossa? — due simulazioni di prova
A35: Netto e pensione in più a soglia − 1 € (usati dal motore M3) | C35: =((($B$29-1)*(1-'P-Parametri'!$B$22))+0)-(MAX(0,(IF(((($B$29-1)*(1-'P-Parametri'!$B$22))+0)<='P-Parametri'!$B$6,'P-Parametri'!$C$6*((($B$29-1)*(1-'P-Parametri'!$B$22))+0),IF(((($B$29-1)*(1-'P-Parametri'!$B$22))+0)<='P-Parametri'!$B$7,'P-Parametri'!$B$9+'P-Parametri'!$C$7*(((($B$29-1)*(1-'P-Parametri'!$B$22))+0)-'P-Parametri'!$B$6),'P-Parametri'!$B$10+'P-Parametri'!$C$8*(((($B$29-1)*(1-'P-Parametri'!$B$22))+0)-'P-Parametri'!$B$7))))-(IF(((($B$29-1)*(1-'P-Parametri'!$B$22))+0)<='P-Parametri'!$C$12,'P-Parametri'!$B$12,IF(((($B$29-1)*(1-'P-Parametri'!$B$22))+0)<='P-Parametri'!$B$6,'P-Parametri'!$B$13+'P-Parametri'!$C$13*('P-Parametri'!$B$6-((($B$29-1)*(1-'P-Parametri'!$B$22))+0))/'P-Parametri'!$D$13,IF(((($B$29-1)*(1-'P-Parametri'!$B$22))+0)<='P-Parametri'!$B$7,'P-Parametri'!$B$14*('P-Parametri'!$B$7-((($B$29-1)*(1-'P-Parametri'!$B$22))+0))/'P-Parametri'!$C$14,0))))-(IF((($B$29-1)*(1-'P-Parametri'!$B$22))>0,IF(((($B$29-1)*(1-'P-Parametri'!$B$22))+0)<='P-Parametri'!$C$21,0,IF(((($B$29-1)*(1-'P-Parametri'!$B$22))+0)<='P-Parametri'!$D$21,'P-Parametri'!$B$21,IF(((($B$29-1)*(1-'P-Parametri'!$B$22))+0)<'P-Parametri'!$E$21,'P-Parametri'!$B$21*('P-Parametri'!$E$21-((($B$29-1)*(1-'P-Parametri'!$B$22))+0))/('P-Parametri'!$E$21-'P-Parametri'!$D$21),0))),0))))-(IF(MAX(0,(IF(((($B$29-1)*(1-'P-Parametri'!$B$22))+0)<='P-Parametri'!$B$6,'P-Parametri'!$C$6*((($B$29-1)*(1-'P-Parametri'!$B$22))+0),IF(((($B$29-1)*(1-'P-Parametri'!$B$22))+0)<='P-Parametri'!$B$7,'P-Parametri'!$B$9+'P-Parametri'!$C$7*(((($B$29-1)*(1-'P-Parametri'!$B$22))+0)-'P-Parametri'!$B$6),'P-Parametri'!$B$10+'P-Parametri'!$C$8*(((($B$29-1)*(1-'P-Parametri'!$B$22))+0)-'P-Parametri'!$B$7))))-(IF(((($B$29-1)*(1-'P-Parametri'!$B$22))+0)<='P-Parametri'!$C$12,'P-Parametri'!$B$12,IF(((($B$29-1)*(1-'P-Parametri'!$B$22))+0)<='P-Parametri'!$B$6,'P-Parametri'!$B$13+'P-Parametri'!$C$13*('P-Parametri'!$B$6-((($B$29-1)*(1-'P-Parametri'!$B$22))+0))/'P-Parametri'!$D$13,IF(((($B$29-1)*(1-'P-Parametri'!$B$22))+0)<='P-Parametri'!$B$7,'P-Parametri'!$B$14*('P-Parametri'!$B$7-((($B$29-1)*(1-'P-Parametri'!$B$22))+0))/'P-Parametri'!$C$14,0))))-(IF((($B$29-1)*(1-'P-Parametri'!$B$22))>0,IF(((($B$29-1)*(1-'P-Parametri'!$B$22))+0)<='P-Parametri'!$C$21,0,IF(((($B$29-1)*(1-'P-Parametri'!$B$22))+0)<='P-Parametri'!$D$21,'P-Parametri'!$B$21,IF(((($B$29-1)*(1-'P-Parametri'!$B$22))+0)<'P-Parametri'!$E$21,'P-Parametri'!$B$21*('P-Parametri'!$E$21-((($B$29-1)*(1-'P-Parametri'!$B$22))+0))/('P-Parametri'!$E$21-'P-Parametri'!$D$21),0))),0)))>0,'P-Parametri'!$B$11*((($B$29-1)*(1-'P-Parametri'!$B$22))+0),0))+(IF(AND(((($B$29-1)*(1-'P-Parametri'!$B$22))+0)<='P-Parametri'!$C$18,(IF(((($B$29-1)*(1-'P-Parametri'!$B$22))+0)<='P-Parametri'!$B$6,'P-Parametri'!$C$6*((($B$29-1)*(1-'P-Parametri'!$B$22))+0),IF(((($B$29-1)*(1-'P-Parametri'!$B$22))+0)<='P-Parametri'!$B$7,'P-Parametri'!$B$9+'P-Parametri'!$C$7*(((($B$29-1)*(1-'P-Parametri'!$B$22))+0)-'P-Parametri'!$B$6),'P-Parametri'!$B$10+'P-Parametri'!$C$8*(((($B$29-1)*(1-'P-Parametri'!$B$22))+0)-'P-Parametri'!$B$7))))>(IF(((($B$29-1)*(1-'P-Parametri'!$B$22))+0)<='P-Parametri'!$C$12,'P-Parametri'!$B$12,IF(((($B$29-1)*(1-'P-Parametri'!$B$22))+0)<='P-Parametri'!$B$6,'P-Parametri'!$B$13+'P-Parametri'!$C$13*('P-Parametri'!$B$6-((($B$29-1)*(1-'P-Parametri'!$B$22))+0))/'P-Parametri'!$D$13,IF(((($B$29-1)*(1-'P-Parametri'!$B$22))+0)<='P-Parametri'!$B$7,'P-Parametri'!$B$14*('P-Parametri'!$B$7-((($B$29-1)*(1-'P-Parametri'!$B$22))+0))/'P-Parametri'!$C$14,0))))-'P-Parametri'!$D$18),'P-Parametri'!$B$18,0))+(IF((($B$29-1)*(1-'P-Parametri'!$B$22))>0,IF(((($B$29-1)*(1-'P-Parametri'!$B$22))+0)>'P-Parametri'!$D$20,0,IF(((($B$29-1)*(1-'P-Parametri'!$B$22))+0)<='P-Parametri'!$B$20,'P-Parametri'!$B$19*(($B$29-1)*(1-'P-Parametri'!$B$22)),IF(((($B$29-1)*(1-'P-Parametri'!$B$22))+0)<='P-Parametri'!$C$20,'P-Parametri'!$C$19*(($B$29-1)*(1-'P-Parametri'!$B$22)),'P-Parametri'!$D$19*(($B$29-1)*(1-'P-Parametri'!$B$22))))),0)) -> 8753.2883 | D35: =(('P-Parametri'!$B$24*($B$29-1))*(1+'P-Parametri'!$B$26)^('1-Input'!$B$25-1-'1-Input'!$B$12+1)*(IF('P-Parametri'!$B$26=0,'1-Input'!$B$12,((1+'P-Parametri'!$B$26)^'1-Input'!$B$12-1)/'P-Parametri'!$B$26)))*'P-Parametri'!$B$27*(1-'P-Parametri'!$B$28) -> 665.59238
A36: Netto e pensione in più a soglia + 1 € (usati dal motore M3) | C36: =((($B$29+1)*(1-'P-Parametri'!$B$22))+0)-(MAX(0,(IF(((($B$29+1)*(1-'P-Parametri'!$B$22))+0)<='P-Parametri'!$B$6,'P-Parametri'!$C$6*((($B$29+1)*(1-'P-Parametri'!$B$22))+0),IF(((($B$29+1)*(1-'P-Parametri'!$B$22))+0)<='P-Parametri'!$B$7,'P-Parametri'!$B$9+'P-Parametri'!$C$7*(((($B$29+1)*(1-'P-Parametri'!$B$22))+0)-'P-Parametri'!$B$6),'P-Parametri'!$B$10+'P-Parametri'!$C$8*(((($B$29+1)*(1-'P-Parametri'!$B$22))+0)-'P-Parametri'!$B$7))))-(IF(((($B$29+1)*(1-'P-Parametri'!$B$22))+0)<='P-Parametri'!$C$12,'P-Parametri'!$B$12,IF(((($B$29+1)*(1-'P-Parametri'!$B$22))+0)<='P-Parametri'!$B$6,'P-Parametri'!$B$13+'P-Parametri'!$C$13*('P-Parametri'!$B$6-((($B$29+1)*(1-'P-Parametri'!$B$22))+0))/'P-Parametri'!$D$13,IF(((($B$29+1)*(1-'P-Parametri'!$B$22))+0)<='P-Parametri'!$B$7,'P-Parametri'!$B$14*('P-Parametri'!$B$7-((($B$29+1)*(1-'P-Parametri'!$B$22))+0))/'P-Parametri'!$C$14,0))))-(IF((($B$29+1)*(1-'P-Parametri'!$B$22))>0,IF(((($B$29+1)*(1-'P-Parametri'!$B$22))+0)<='P-Parametri'!$C$21,0,IF(((($B$29+1)*(1-'P-Parametri'!$B$22))+0)<='P-Parametri'!$D$21,'P-Parametri'!$B$21,IF(((($B$29+1)*(1-'P-Parametri'!$B$22))+0)<'P-Parametri'!$E$21,'P-Parametri'!$B$21*('P-Parametri'!$E$21-((($B$29+1)*(1-'P-Parametri'!$B$22))+0))/('P-Parametri'!$E$21-'P-Parametri'!$D$21),0))),0))))-(IF(MAX(0,(IF(((($B$29+1)*(1-'P-Parametri'!$B$22))+0)<='P-Parametri'!$B$6,'P-Parametri'!$C$6*((($B$29+1)*(1-'P-Parametri'!$B$22))+0),IF(((($B$29+1)*(1-'P-Parametri'!$B$22))+0)<='P-Parametri'!$B$7,'P-Parametri'!$B$9+'P-Parametri'!$C$7*(((($B$29+1)*(1-'P-Parametri'!$B$22))+0)-'P-Parametri'!$B$6),'P-Parametri'!$B$10+'P-Parametri'!$C$8*(((($B$29+1)*(1-'P-Parametri'!$B$22))+0)-'P-Parametri'!$B$7))))-(IF(((($B$29+1)*(1-'P-Parametri'!$B$22))+0)<='P-Parametri'!$C$12,'P-Parametri'!$B$12,IF(((($B$29+1)*(1-'P-Parametri'!$B$22))+0)<='P-Parametri'!$B$6,'P-Parametri'!$B$13+'P-Parametri'!$C$13*('P-Parametri'!$B$6-((($B$29+1)*(1-'P-Parametri'!$B$22))+0))/'P-Parametri'!$D$13,IF(((($B$29+1)*(1-'P-Parametri'!$B$22))+0)<='P-Parametri'!$B$7,'P-Parametri'!$B$14*('P-Parametri'!$B$7-((($B$29+1)*(1-'P-Parametri'!$B$22))+0))/'P-Parametri'!$C$14,0))))-(IF((($B$29+1)*(1-'P-Parametri'!$B$22))>0,IF(((($B$29+1)*(1-'P-Parametri'!$B$22))+0)<='P-Parametri'!$C$21,0,IF(((($B$29+1)*(1-'P-Parametri'!$B$22))+0)<='P-Parametri'!$D$21,'P-Parametri'!$B$21,IF(((($B$29+1)*(1-'P-Parametri'!$B$22))+0)<'P-Parametri'!$E$21,'P-Parametri'!$B$21*('P-Parametri'!$E$21-((($B$29+1)*(1-'P-Parametri'!$B$22))+0))/('P-Parametri'!$E$21-'P-Parametri'!$D$21),0))),0)))>0,'P-Parametri'!$B$11*((($B$29+1)*(1-'P-Parametri'!$B$22))+0),0))+(IF(AND(((($B$29+1)*(1-'P-Parametri'!$B$22))+0)<='P-Parametri'!$C$18,(IF(((($B$29+1)*(1-'P-Parametri'!$B$22))+0)<='P-Parametri'!$B$6,'P-Parametri'!$C$6*((($B$29+1)*(1-'P-Parametri'!$B$22))+0),IF(((($B$29+1)*(1-'P-Parametri'!$B$22))+0)<='P-Parametri'!$B$7,'P-Parametri'!$B$9+'P-Parametri'!$C$7*(((($B$29+1)*(1-'P-Parametri'!$B$22))+0)-'P-Parametri'!$B$6),'P-Parametri'!$B$10+'P-Parametri'!$C$8*(((($B$29+1)*(1-'P-Parametri'!$B$22))+0)-'P-Parametri'!$B$7))))>(IF(((($B$29+1)*(1-'P-Parametri'!$B$22))+0)<='P-Parametri'!$C$12,'P-Parametri'!$B$12,IF(((($B$29+1)*(1-'P-Parametri'!$B$22))+0)<='P-Parametri'!$B$6,'P-Parametri'!$B$13+'P-Parametri'!$C$13*('P-Parametri'!$B$6-((($B$29+1)*(1-'P-Parametri'!$B$22))+0))/'P-Parametri'!$D$13,IF(((($B$29+1)*(1-'P-Parametri'!$B$22))+0)<='P-Parametri'!$B$7,'P-Parametri'!$B$14*('P-Parametri'!$B$7-((($B$29+1)*(1-'P-Parametri'!$B$22))+0))/'P-Parametri'!$C$14,0))))-'P-Parametri'!$D$18),'P-Parametri'!$B$18,0))+(IF((($B$29+1)*(1-'P-Parametri'!$B$22))>0,IF(((($B$29+1)*(1-'P-Parametri'!$B$22))+0)>'P-Parametri'!$D$20,0,IF(((($B$29+1)*(1-'P-Parametri'!$B$22))+0)<='P-Parametri'!$B$20,'P-Parametri'!$B$19*(($B$29+1)*(1-'P-Parametri'!$B$22)),IF(((($B$29+1)*(1-'P-Parametri'!$B$22))+0)<='P-Parametri'!$C$20,'P-Parametri'!$C$19*(($B$29+1)*(1-'P-Parametri'!$B$22)),'P-Parametri'!$D$19*(($B$29+1)*(1-'P-Parametri'!$B$22))))),0)) -> 9955.2334 | D36: =(('P-Parametri'!$B$24*($B$29+1))*(1+'P-Parametri'!$B$26)^('1-Input'!$B$25-1-'1-Input'!$B$12+1)*(IF('P-Parametri'!$B$26=0,'1-Input'!$B$12,((1+'P-Parametri'!$B$26)^'1-Input'!$B$12-1)/'P-Parametri'!$B$26)))*'P-Parametri'!$B$27*(1-'P-Parametri'!$B$28) -> 665.74028
A38: LO STESSO CONTRATTO A CHI HA GIÀ UNO STIPENDIO
